Workbook
Name Agriculture: "$'agriculture 2015'.$a$#ref !"
Name Années: '[1]M-2'!$A$4:$AE$4
Name AnnéesR_BI: '[1]Bilan Energie Format SDES AME'!$A$54:$L$54
Name AnnéesResult: '[1]R-5'!$C$6:$H$6
Name AnneesShazam: [1]Outils!$E$104:$V$104
Name blabla: #REF!
Name BY: [1]Outils!$B$19
Name CalageAMEAgriculture: '[1]Calage bilan'!$B$65:$F$71
Name CalageAMEIndustrie: '[1]Calage bilan'!$B$33:$F$39
Name CalageAMERésidentiel: '[1]Calage bilan'!$B$49:$F$55
Name CalageAMETertiaire: '[1]Calage bilan'!$B$57:$F$63
Name CalageAMETransport: '[1]Calage bilan'!$B$41:$F$47
Name CalageAMSAgriculture: '[1]Calage bilan'!$I$65:$M$71
Name CalageAMSIndustrie: '[1]Calage bilan'!$I$33:$M$39
Name CalageAMSRésidentiel: '[1]Calage bilan'!$I$49:$M$55
Name CalageAMSTertiaire: '[1]Calage bilan'!$I$57:$M$63
Name CalageAMSTransport: '[1]Calage bilan'!$I$41:$M$47
Name CalageAnnées: '[1]Calage bilan'!$I$32:$M$32
Name CalageEnergies: '[1]Calage bilan'!$H$33:$H$39
Name Choix_scenario: [2]ReadMe!$H$10
Name CodeInd2: '[1]I-2'!$B$4:$B$353
Name Codeind4: '[1]I-4'!$B$323:$B$670
Name CodeMac: '[1]M-2'!$B$4:$B$123
Name CodeR_BI: '[1]Bilan Energie Format SDES AME'!$A$54:$A$84
Name CodeRes: '[1]R-2'!$B$4:$B$788
Name CodeResbis: '[1]R-2'!$B$828:$B$1291
Name CodeResultAgr: '[1]A-4'!$A$9:$A$14
Name CodeResultInd: '[1]I-5'!$A$10:$A$393
Name CodeResultMac: '[1]M-5'!$A$10:$A$124
Name CodeResultRes: '[1]R-5'!$A$10:$A$311
Name CodeResultTer: '[1]S-5'!$A$10:$A$293
Name CodeResultTra: '[1]T-5'!$A$10:$A$803
Name CodeTer: '[1]S-2'!$B$4:$B$298
Name CodeTra: '[1]T-2'!$B$4:$B$138
Name DataInd: '[1]I-2'!$A$4:$AE$353
Name DataInd4: '[1]I-4'!$A$323:$AE$670
Name DataMac2: '[1]M-2'!$A$4:$AE$141
Name DataRes: '[1]R-2'!$A$4:$AE$788
Name DataResbis: '[1]R-2'!$A$828:$AG$1291
Name DATAShazam: [1]Outils!$E$105:$V$132
Name DataTer: '[1]S-2'!$A$4:$AG$298
Name DataTra: '[1]T-2'!$A$4:$AG$138
Name NRD_CODEShazam: [1]Outils!$C$105:$C$132
Name R_BI2015: '[1]Bilan Energie Format SDES AME'!$A$10:$L$40
Name R_BI2015_2: '[1]Bilan Energie Format SDES AMS'!$A$10:$L$40
Name R_BI2020: '[1]Bilan Energie Format SDES AME'!$A$54:$L$84
Name R_BI2020_2: '[1]Bilan Energie Format SDES AMS'!$A$54:$L$84
Name R_BI2025: '[1]Bilan Energie Format SDES AME'!$A$98:$L$128
Name R_BI2025_2: '[1]Bilan Energie Format SDES AMS'!$A$98:$L$128
Name R_BI2030: '[1]Bilan Energie Format SDES AME'!$A$142:$L$172
Name R_BI2030_2: '[1]Bilan Energie Format SDES AMS'!$A$142:$L$172
Name R_BI2050: '[1]Bilan Energie Format SDES AME'!$A$186:$L$216
Name R_BI2050_2: '[1]Bilan Energie Format SDES AMS'!$A$186:$L$216
Name ResultAgrS1: '[1]A-4'!$C$9:$H$14
Name ResultAgrS2: '[1]A-4'!$K$9:$P$14
Name ResultIndS1: '[1]I-5'!$C$10:$H$393
Name ResultIndS2: '[1]I-5'!$K$10:$P$393
Name ResultMacS1: '[1]M-5'!$C$10:$H$124
Name ResultResS1: '[1]R-5'!$C$10:$H$311
Name ResultResS2: '[1]R-5'!$K$10:$P$311

Sheet ReadMe
A1: Données d'entrée MatMat pour ThreeME
A3: Nom Onglet | B3: Détails | D3: Statut
A4: Delta AMX_2030 | B4: Variation relative 2019-2030 des variables (coefficients techniques (A), vecteurs de demande finale, production et importation), annualisée sur 7 ans (2023-2030 pour coller avec le point de départ 3ME) selon les scénarios AME et AMS | D4: Données d'entrée pour ThreeME
A5: Delta AMX_2050 | B5: Variation relative 2030-2050 des variables (coefficients techniques (A), vecteurs de demande finale, production et importation), annualisée sur 20 ans selon les scénarios AME et AMS | D5: Données d'entrée pour ThreeME
A8: Données
A10: Nom Onglet | B10: Détails | D10: Statut
A11: 2019 | B11: SRIOT Monétaire issue de MatMat, agrégé sur les 37 secteurs de 3ME, pour l'année de calibration (2019) : A (= Matrice des coefficients techniques pour la production domestique selon l'origine France ou RoW - Reste du Monde ), 4 vecteurs de demande finale (Household, Government, GFCF, Exports), production intérieure et importations en volume. Unité EUR | D11: Information | E11: 2019 (Z) correspond à la version du SRIOT avec les consommations intermédiaires Z
A12: AME_20XX | B12: SRIOT pour 2030, 2040 et 2050 pour l'AME. Unité EUR | D12: Information | E12: AME_20XX (Z) correspond à la version du SRIOT avec les consommations intermédiaires Z
A13: AMS_20XX | B13: SRIOT pour 2030, 2040 et 2050 pour l'AMS. Unité EUR | D13: Information | E13: AMS_20XX (Z) correspond à la version du SRIOT avec les consommations intermédiaires Z
A15: Chocs_Run3_250409 | B15: Liste des chocs introduits dans MatMat (Run3 sectoriel DGEC) à date | D15: Information
A16: Bridge | B16: Matrice de passage entre secteurs MatMat et secteurs 3ME | D16: Information
A18: Points d'attention
A19: 1 | B19: Dans MatMat, pas de distinction entre les secteurs 15 et 16 de 3ME (transport de passagers et marchandises par la route), j'ai donc appliqué la même variation aux 2 secteurs
A20: 2 | B20: Compte tenu des différences observées entre les secteurs chimie de MatMat et 3ME, les variations sur les secteurs 07 et 08 ont été agrégés selon méthode décrite dans :
B21: Données 3ME pour informer MatMat.docx
B22: La même variation est appliquée aux 2 secteurs
A23: 3 | B23: Des différences s'observent entre les chocs introduits dans MatMat (Chocs_Run3_250409) et les variations obtenues dans les fichiers Delta (indépendamment de l'annualisation) du fait de l'agrégation de plusieurs secteurs MatMat dans un secteur 3ME
A24: 4 | B24: Des différences de variations peuvent s'observer entre la production française (FR) et les importations (RDM) pour un même vecteur (par exemple C). En effet, dans MatMat, les chocs sont introduits sur les variables A et Y agrégées (FR+RDM), les valeurs FR et RoW sont calculées à partir des M/P (rapport entre importations et production intérieure), ce qui peut induire de légères différences par rapport à la variation totale selon les valeurs du taux M/P (paramétrable). De plus, comme chaque secteur MatMat à un rapport M/P différent, au niveau du secteur agrégé 3ME on peut avoir des divergences FR / RoW plus marquées => comparer les variations sur le TOTAL
A25: 5 | B25: Concernant la variation de l'investissement pour les produits verre, acier, autres métaux non-ferreux, elle peut être ignorée car elle devrait être nulle (le choc portait sur la part de marché entre Matières primaires et secondaires et donc est transparant quand les deux sont agrégées comme dans 3ME). La variation est due aux valeurs nulles pour la FBCF FR ou RDM, qui déforme la projection.
A26: 6 | B26: Au niveau de l’investissement, le choc sur la FBCF de l’agriculture peut avoir du sens pour 3ME (évolution des cheptels suite à l’évolution des régimes alimentaires). Ceux sur les biens d’investissement construction et autres industries sont des résultantes des chocs de demande considérés (baisse des mètres carrés de bureau en AMS, changement des parts de marché dans les modes de traitement des déchets, sobriété sur les équipements électroniques en AMS).
A28: Principaux Chocs considérés par rapport à 2019
A29: RUN 3 20250417 | B29: Valeur des chocs dans onglet Chocs_Run3_250417
B30: AME | C30: AMS | D30: Détails
A31: Agriculture / IAA - Alimentation humaine | B31: Changement Régimes alimentaires | D31: Choc sur DF des Ménages + APU + Exports (hypothèse d'une même évolution des régimes alimentaires dans le RDM qu'en France pour tendre vers cibles de production DGEC)
D32: + choc sur A des Services (hôtels / restaurants, services publics et business services) pour traduire l’évolution des régimes alimentaires dans la restauration, y compris restauration collective dans les entreprises, établissements scolaires, hôpitaux, cliniques, maisons de retraite...
A33: Agriculture | B33: Evolution des cheptels | D33: Choc sur la Matrice d’investissement pour traduire les investissements en cheptels réalisés par les secteurs d’élevage (bovins viande et lait, porcins, ovins et caprins)
A34: Agriculture / IAA - Alimentation animale | B34: Changement Régimes alimentaires des animaux | D34: Choc sur A des activités d'élevage en céréales, fourrages, oléagineux et autres concentrés (orge, son, farines, fécules2)
A35: Agriculture / fertilisants | B35: Baisse de l’usage des engrais chimiques (proxy accroissement part de l'AB) | D35: Choc sur A des activités agricoles en fertilisants chimiques + Choc sur DF des ménages et APU en fertilisants chimiques (en lien avec interdiction de l'utilisation des engrais de synthèse dans les propriétés non agricoles)
A36: Sylviculture | B36: Evolution du stock de bois forêt (investissement productif de la filière), proportionnel à l'accroissement de la récolte | D36: Choc sur la Matrice d’investissement du secteur Forestry en produit Forestry (tout en amont de la chaine de valeur, n'évolue pas sous l'effet du choc de demande adressée à la filière)
A37: Bois énergie | B37: Evolution de la demande en bois énergie | D37: Choc sur DF des ménages (hypothèse que la DF des ménages en produit forestry = bois énergie)
A38: Recyclage | B38: Evolution des taux d'incorporation de MPR (part de marché entre matières vierges et MPR) pour la production française | D38: Choc sur A et tous vecteurs de DF
B39: (les parts de marché matières vierges / MPR sont maintenues constantes pour les matières importées)
A40: Automobile | B40: Allègement de véhicules (masse moyenne) + Nouvelle composition matières | D40: Choc sur A du secteur de la construction automobile
B41: Consommation matières Batteries | D41: Choc sur A du secteur de la construction automobile
A42: Emballage | B42: Fin des emballages plastiques à usage unique (2040) | C42: Fin des emballages plastiques à usage unique (2040) + sobriété | D42: Choc sur DF des ménages et des APU, + A des secteurs Agricoles et IAA, Chimie (pharma, cosmétique), Industrie manufacturière (emballages pour Transport des produits notamment) et Service (commerce notamment) au prorata de la part des emballages dans les consommations de papier, plastiques et verre
A43: Construction | B43: Substitution Acier et Ciment par Bois | D43: Choc sur A de la construction
A44: Services immobiliers | B44: Evolution de la demande des ménages en services immobiliers (hypothèse qu’elle évolue en fonction de l'évolution du parc immobilier en m²) | D44: Choc sur la DF des ménages en services immobiliers
C45: Evolution de la demande en services immobiliers des Administrations publiques et services marchands en fonction des m² de bureaux/employé (sous effet du télétravail notamment) | D45: Choc sur A en Real Estate des APU, services publics (uniquement public administration) et business services (hors commerce)
A46: Industrie | C46: Baisse Taux de Clinker dans Ciment | D46: Choc sur A de la demande en ciment de la filière ciment
A47: Produits Chimiques des ménages | B47: Sobriété sur consommation de produits chimiques (peintures, vernis, détergents, savons, produits pharmaceutiques) + arrêt de la vente de pesticides aux personnes publiques et aux particuliers (loi Labbé3) | D47: Choc sur DF des ménages et APU
A48: Biens d'équipements EEE | C48: Allongement DDV des équipements numériques (on change moins souvent = lutte contre obsolescence marketing + réparation) | D48: Choc sur DF des ménages et APU
A49: Textile | B49: Sobriété (évolution des dépenses textiles) | D49: Choc sur DF Ménages
A50: Déchets | B50: Modification des parts de marchés entre modes de traitement (Baisse enfouissement) | D50: Choc sur A et tous vecteurs de DF (Hypothèse que les parts de marché sur les services importés évoluent comme les parts de marché des services domestiques)

Sheet Delta AME_2030
A1: Variation relative 2019-2030, annualisée sur 7 ans pour coller avec le point de départ 3ME (2023-2030) | D1: category | E1: 01 | F1: 02 | G1: 03 | H1: 04 | I1: 05 | J1: 06 | K1: 07 | L1: 08 | M1: 09 | N1: 10 | O1: 11 | P1: 12 | Q1: 13 | R1: 14 | S1: 15 | T1: 16 | U1: 17 | V1: 18 | W1: 19 | X1: 20 | Y1: 21 | Z1: 22 | AA1: 23 | AB1: 24 | AC1: 25 | AD1: 26 | AE1: 27 | AF1: 28 | AG1: 29 | AH1: 30 | AI1: 31 | AJ1: 32 | AK1: 33 | AL1: 34 | AM1: 35 | AN1: 36 | AO1: 37 | AP1: Household | AQ1: Government | AR1: GFCF | AS1: Exports | AT1: Supply | AU1: Imports
D2: sub_category | E2: 01 | F2: 02 | G2: 03 | H2: 04 | I2: 05 | J2: 06 | K2: 07 | L2: 08 | M2: 09 | N2: 10 | O2: 11 | P2: 12 | Q2: 13 | R2: 14 | S2: 15 | T2: 16 | U2: 17 | V2: 18 | W2: 19 | X2: 20 | Y2: 21 | Z2: 22 | AA2: 23 | AB2: 24 | AC2: 25 | AD2: 26 | AE2: 27 | AF2: 28 | AG2: 29 | AH2: 30 | AI2: 31 | AJ2: 32 | AK2: 33 | AL2: 34 | AM2: 35 | AN2: 36 | AO2: 37 | AP2: C | AQ2: G | AR2: I | AS2: E | AT2: x | AU2: M
D3: sector | E3: Products of agriculture, forestry and fishing | F3: Food products and beverages | G3: Motor vehicles, trailers and semi-trailers | H3: Glass and glass products | I3: Ceramic products and building materials | J3: Articles of paper and paperboard | K3: Inorganic basic chemicals | L3: Organic basic chemicals | M3: Plastics products | N3: Basic iron and steel and of ferro-alloys | O3: Non-ferrous metals | P3: Other industries | Q3: Construction of buildings and Civil engineering | R3: Rail transport (Passenger and Freight) | S3: Passenger transport by road | T3: Freight transport by road and transport via pipeline | U3: Water transport | V3: Air transport | W3: Business services | X3: Public services | Y3: Coal | Z3: Oil | AA3: Biofuel | AB3: Electricity by nuclear | AC3: Electricity by petroleum | AD3: Electricity by gas | AE3: Coal-fired electricity | AF3: Electricity by wind | AG3: Electricity by solar | AH3: Electricity by hydro | AI3: Other electricity | AJ3: Natural gas | AK3: Wood | AL3: Biogas | AM3: Waste incineration | AN3: Geothermal | AO3: Other natural gas and heat
A4: region | B4: category | C4: sub_category | D4: sector | E4: A | F4: A | G4: A | H4: A | I4: A | J4: A | K4: A | L4: A | M4: A | N4: A | O4: A | P4: A | Q4: A | R4: A | S4: A | T4: A | U4: A | V4: A | W4: A | X4: A | Y4: A | Z4: A | AA4: A | AB4: A | AC4: A | AD4: A | AE4: A | AF4: A | AG4: A | AH4: A | AI4: A | AJ4: A | AK4: A | AL4: A | AM4: A | AN4: A | AO4: A
A5: FR | B5: 01 | C5: 01 | D5: Products of agriculture, forestry and fishing | E5: =IF('2019'!E5=0,0,(AME_2030!E5/'2019'!E5)^(1/7)-1) -> 0.0013462924 | F5: =IF('2019'!F5=0,0,(AME_2030!F5/'2019'!F5)^(1/7)-1) -> -0.00013012775 | G5: =IF('2019'!G5=0,0,(AME_2030!G5/'2019'!G5)^(1/7)-1) -> -2.3353149e-09 | H5: =IF('2019'!H5=0,0,(AME_2030!H5/'2019'!H5)^(1/7)-1) -> 0 | I5: =IF('2019'!I5=0,0,(AME_2030!I5/'2019'!I5)^(1/7)-1) -> 0 | J5: =IF('2019'!J5=0,0,(AME_2030!J5/'2019'!J5)^(1/7)-1) -> -0.012228135 | K5: =IF('2019 (Z)'!AW5=0,0,('AME_2030 (Z)'!AW5/'2019 (Z)'!AW5)^(1/7)-1) -> 0.0022948862 | L5: =K5 -> 0.0022948862 | M5: =IF('2019'!M5=0,0,(AME_2030!M5/'2019'!M5)^(1/7)-1) -> -0.0046050638 | N5: =IF('2019'!N5=0,0,(AME_2030!N5/'2019'!N5)^(1/7)-1) -> 0 | O5: =IF('2019'!O5=0,0,(AME_2030!O5/'2019'!O5)^(1/7)-1) -> 0 | P5: =IF('2019'!P5=0,0,(AME_2030!P5/'2019'!P5)^(1/7)-1) -> 0.0092661175 | Q5: =IF('2019'!Q5=0,0,(AME_2030!Q5/'2019'!Q5)^(1/7)-1) -> 0.017204033 | R5: =IF('2019'!R5=0,0,(AME_2030!R5/'2019'!R5)^(1/7)-1) -> -2.0238261e-08 | S5: =T5 -> -1.5204104e-06 | T5: =IF('2019'!T5=0,0,(AME_2030!T5/'2019'!T5)^(1/7)-1) -> -1.5204104e-06 | U5: =IF('2019'!U5=0,0,(AME_2030!U5/'2019'!U5)^(1/7)-1) -> 0 | V5: =IF('2019'!V5=0,0,(AME_2030!V5/'2019'!V5)^(1/7)-1) -> 0 | W5: =IF('2019'!W5=0,0,(AME_2030!W5/'2019'!W5)^(1/7)-1) -> 0.0015931337 | X5: =IF('2019'!X5=0,0,(AME_2030!X5/'2019'!X5)^(1/7)-1) -> 0.0013137303 | Y5: =IF('2019'!Y5=0,0,(AME_2030!Y5/'2019'!Y5)^(1/7)-1) -> 0 | Z5: =IF('2019'!Z5=0,0,(AME_2030!Z5/'2019'!Z5)^(1/7)-1) -> 0.00016178189 | AA5: =IF('2019'!AA5=0,0,(AME_2030!AA5/'2019'!AA5)^(1/7)-1) -> 0.001344016 | ... AU5: =IF('2019'!AU5=0,0,(AME_2030!AU5/'2019'!AU5)^(1/7)-1) -> 0
B6: 02 | C6: 02 | D6: Food products and beverages | E6: =IF('2019'!E6=0,0,(AME_2030!E6/'2019'!E6)^(1/7)-1) -> -0.0017957746 | F6: =IF('2019'!F6=0,0,(AME_2030!F6/'2019'!F6)^(1/7)-1) -> 0.00049671425 | G6: =IF('2019'!G6=0,0,(AME_2030!G6/'2019'!G6)^(1/7)-1) -> -2.3353149e-09 | H6: =IF('2019'!H6=0,0,(AME_2030!H6/'2019'!H6)^(1/7)-1) -> 0.0062533597 | I6: =IF('2019'!I6=0,0,(AME_2030!I6/'2019'!I6)^(1/7)-1) -> -0.001083104 | J6: =IF('2019'!J6=0,0,(AME_2030!J6/'2019'!J6)^(1/7)-1) -> 0.00022818305 | K6: =IF('2019 (Z)'!AW6=0,0,('AME_2030 (Z)'!AW6/'2019 (Z)'!AW6)^(1/7)-1) -> 0.0022937804 | L6: =K6 -> 0.0022937804 | M6: =IF('2019'!M6=0,0,(AME_2030!M6/'2019'!M6)^(1/7)-1) -> 0.00084182489 | N6: =IF('2019'!N6=0,0,(AME_2030!N6/'2019'!N6)^(1/7)-1) -> -0.0016739372 | O6: =IF('2019'!O6=0,0,(AME_2030!O6/'2019'!O6)^(1/7)-1) -> -0.0038404385 | P6: =IF('2019'!P6=0,0,(AME_2030!P6/'2019'!P6)^(1/7)-1) -> 1.5350503e-05 | Q6: =IF('2019'!Q6=0,0,(AME_2030!Q6/'2019'!Q6)^(1/7)-1) -> 1.6442185e-07 | R6: =IF('2019'!R6=0,0,(AME_2030!R6/'2019'!R6)^(1/7)-1) -> -2.0238261e-08 | S6: =T6 -> -1.7908556e-07 | T6: =IF('2019'!T6=0,0,(AME_2030!T6/'2019'!T6)^(1/7)-1) -> -1.7908556e-07 | U6: =IF('2019'!U6=0,0,(AME_2030!U6/'2019'!U6)^(1/7)-1) -> -2.7153555e-06 | V6: =IF('2019'!V6=0,0,(AME_2030!V6/'2019'!V6)^(1/7)-1) -> -2.6346634e-08 | W6: =IF('2019'!W6=0,0,(AME_2030!W6/'2019'!W6)^(1/7)-1) -> 0.00016407789 | X6: =IF('2019'!X6=0,0,(AME_2030!X6/'2019'!X6)^(1/7)-1) -> 0.00049999123 | Y6: =IF('2019'!Y6=0,0,(AME_2030!Y6/'2019'!Y6)^(1/7)-1) -> 0.0024005377 | Z6: =IF('2019'!Z6=0,0,(AME_2030!Z6/'2019'!Z6)^(1/7)-1) -> -0.0011527271 | AA6: =IF('2019'!AA6=0,0,(AME_2030!AA6/'2019'!AA6)^(1/7)-1) -> 0.0013439975 | ... AU6: =IF('2019'!AU6=0,0,(AME_2030!AU6/'2019'!AU6)^(1/7)-1) -> 0
B7: 03 | C7: 03 | D7: Motor vehicles, trailers and semi-trailers | E7: =IF('2019'!E7=0,0,(AME_2030!E7/'2019'!E7)^(1/7)-1) -> -0.00017021846 | F7: =IF('2019'!F7=0,0,(AME_2030!F7/'2019'!F7)^(1/7)-1) -> 0.00023597294 | G7: =IF('2019'!G7=0,0,(AME_2030!G7/'2019'!G7)^(1/7)-1) -> -2.3353149e-09 | H7: =IF('2019'!H7=0,0,(AME_2030!H7/'2019'!H7)^(1/7)-1) -> 0.0039422071 | I7: =IF('2019'!I7=0,0,(AME_2030!I7/'2019'!I7)^(1/7)-1) -> 0.00057751563 | J7: =IF('2019'!J7=0,0,(AME_2030!J7/'2019'!J7)^(1/7)-1) -> 0.00049115518 | K7: =IF('2019 (Z)'!AW7=0,0,('AME_2030 (Z)'!AW7/'2019 (Z)'!AW7)^(1/7)-1) -> 0.0022946097 | L7: =K7 -> 0.0022946097 | M7: =IF('2019'!M7=0,0,(AME_2030!M7/'2019'!M7)^(1/7)-1) -> -0.0061150631 | N7: =IF('2019'!N7=0,0,(AME_2030!N7/'2019'!N7)^(1/7)-1) -> -0.0036935238 | O7: =IF('2019'!O7=0,0,(AME_2030!O7/'2019'!O7)^(1/7)-1) -> 0.0010519187 | P7: =IF('2019'!P7=0,0,(AME_2030!P7/'2019'!P7)^(1/7)-1) -> -0.00062554011 | Q7: =IF('2019'!Q7=0,0,(AME_2030!Q7/'2019'!Q7)^(1/7)-1) -> 1.6442185e-07 | R7: =IF('2019'!R7=0,0,(AME_2030!R7/'2019'!R7)^(1/7)-1) -> -2.0238261e-08 | S7: =T7 -> -2.5259452e-06 | T7: =IF('2019'!T7=0,0,(AME_2030!T7/'2019'!T7)^(1/7)-1) -> -2.5259452e-06 | U7: =IF('2019'!U7=0,0,(AME_2030!U7/'2019'!U7)^(1/7)-1) -> -7.2873332e-06 | V7: =IF('2019'!V7=0,0,(AME_2030!V7/'2019'!V7)^(1/7)-1) -> -2.6346634e-08 | W7: =IF('2019'!W7=0,0,(AME_2030!W7/'2019'!W7)^(1/7)-1) -> -7.9517814e-05 | X7: =IF('2019'!X7=0,0,(AME_2030!X7/'2019'!X7)^(1/7)-1) -> -8.8835412e-06 | Y7: =IF('2019'!Y7=0,0,(AME_2030!Y7/'2019'!Y7)^(1/7)-1) -> 0.0024005377 | Z7: =IF('2019'!Z7=0,0,(AME_2030!Z7/'2019'!Z7)^(1/7)-1) -> -0.0010689398 | AA7: =IF('2019'!AA7=0,0,(AME_2030!AA7/'2019'!AA7)^(1/7)-1) -> 0.0013439412 | ... AU7: =IF('2019'!AU7=0,0,(AME_2030!AU7/'2019'!AU7)^(1/7)-1) -> 0
B8: 04 | C8: 04 | D8: Glass and glass products | E8: =IF('2019'!E8=0,0,(AME_2030!E8/'2019'!E8)^(1/7)-1) -> 0.0097139469 | F8: =IF('2019'!F8=0,0,(AME_2030!F8/'2019'!F8)^(1/7)-1) -> 0.18429546 | G8: =IF('2019'!G8=0,0,(AME_2030!G8/'2019'!G8)^(1/7)-1) -> 0.15472004 | H8: =IF('2019'!H8=0,0,(AME_2030!H8/'2019'!H8)^(1/7)-1) -> -0.10254174 | I8: =IF('2019'!I8=0,0,(AME_2030!I8/'2019'!I8)^(1/7)-1) -> -0.0017907078 | J8: =IF('2019'!J8=0,0,(AME_2030!J8/'2019'!J8)^(1/7)-1) -> -0.02401975 | K8: =IF('2019 (Z)'!AW8=0,0,('AME_2030 (Z)'!AW8/'2019 (Z)'!AW8)^(1/7)-1) -> 0.12539748 | L8: =K8 -> 0.12539748 | M8: =IF('2019'!M8=0,0,(AME_2030!M8/'2019'!M8)^(1/7)-1) -> 0.004625971 | N8: =IF('2019'!N8=0,0,(AME_2030!N8/'2019'!N8)^(1/7)-1) -> -0.0043193728 | O8: =IF('2019'!O8=0,0,(AME_2030!O8/'2019'!O8)^(1/7)-1) -> 0.010489332 | P8: =IF('2019'!P8=0,0,(AME_2030!P8/'2019'!P8)^(1/7)-1) -> -0.024081264 | Q8: =IF('2019'!Q8=0,0,(AME_2030!Q8/'2019'!Q8)^(1/7)-1) -> -0.00060224332 | R8: =IF('2019'!R8=0,0,(AME_2030!R8/'2019'!R8)^(1/7)-1) -> 0.041595517 | S8: =T8 -> -0.0029746563 | T8: =IF('2019'!T8=0,0,(AME_2030!T8/'2019'!T8)^(1/7)-1) -> -0.0029746563 | U8: =IF('2019'!U8=0,0,(AME_2030!U8/'2019'!U8)^(1/7)-1) -> 0.013184157 | V8: =IF('2019'!V8=0,0,(AME_2030!V8/'2019'!V8)^(1/7)-1) -> 0.010740097 | W8: =IF('2019'!W8=0,0,(AME_2030!W8/'2019'!W8)^(1/7)-1) -> -0.0010671182 | X8: =IF('2019'!X8=0,0,(AME_2030!X8/'2019'!X8)^(1/7)-1) -> -0.0011118503 | Y8: =IF('2019'!Y8=0,0,(AME_2030!Y8/'2019'!Y8)^(1/7)-1) -> 0.0036117242 | Z8: =IF('2019'!Z8=0,0,(AME_2030!Z8/'2019'!Z8)^(1/7)-1) -> 0.0028796031 | AA8: =IF('2019'!AA8=0,0,(AME_2030!AA8/'2019'!AA8)^(1/7)-1) -> -0.0014651017 | ... AU8: =IF('2019'!AU8=0,0,(AME_2030!AU8/'2019'!AU8)^(1/7)-1) -> 0
B9: 05 | C9: 05 | D9: Ceramic products and building materials | E9: =IF('2019'!E9=0,0,(AME_2030!E9/'2019'!E9)^(1/7)-1) -> 0.0017572583 | F9: =IF('2019'!F9=0,0,(AME_2030!F9/'2019'!F9)^(1/7)-1) -> -4.4919097e-05 | G9: =IF('2019'!G9=0,0,(AME_2030!G9/'2019'!G9)^(1/7)-1) -> -2.3353151e-09 | H9: =IF('2019'!H9=0,0,(AME_2030!H9/'2019'!H9)^(1/7)-1) -> 0.0089782486 | I9: =IF('2019'!I9=0,0,(AME_2030!I9/'2019'!I9)^(1/7)-1) -> 0.00060127606 | J9: =IF('2019'!J9=0,0,(AME_2030!J9/'2019'!J9)^(1/7)-1) -> 2.6238372e-05 | K9: =IF('2019 (Z)'!AW9=0,0,('AME_2030 (Z)'!AW9/'2019 (Z)'!AW9)^(1/7)-1) -> 0.0022979577 | L9: =K9 -> 0.0022979577 | M9: =IF('2019'!M9=0,0,(AME_2030!M9/'2019'!M9)^(1/7)-1) -> 0.014006948 | N9: =IF('2019'!N9=0,0,(AME_2030!N9/'2019'!N9)^(1/7)-1) -> -0.0011153861 | O9: =IF('2019'!O9=0,0,(AME_2030!O9/'2019'!O9)^(1/7)-1) -> 0.010906863 | P9: =IF('2019'!P9=0,0,(AME_2030!P9/'2019'!P9)^(1/7)-1) -> -0.00033114175 | Q9: =IF('2019'!Q9=0,0,(AME_2030!Q9/'2019'!Q9)^(1/7)-1) -> -0.0014457745 | R9: =IF('2019'!R9=0,0,(AME_2030!R9/'2019'!R9)^(1/7)-1) -> -2.0238261e-08 | S9: =T9 -> 2.7218582e-05 | T9: =IF('2019'!T9=0,0,(AME_2030!T9/'2019'!T9)^(1/7)-1) -> 2.7218582e-05 | U9: =IF('2019'!U9=0,0,(AME_2030!U9/'2019'!U9)^(1/7)-1) -> 1.0886224e-07 | V9: =IF('2019'!V9=0,0,(AME_2030!V9/'2019'!V9)^(1/7)-1) -> -2.6346634e-08 | W9: =IF('2019'!W9=0,0,(AME_2030!W9/'2019'!W9)^(1/7)-1) -> -0.0065455441 | X9: =IF('2019'!X9=0,0,(AME_2030!X9/'2019'!X9)^(1/7)-1) -> -5.3954378e-06 | Y9: =IF('2019'!Y9=0,0,(AME_2030!Y9/'2019'!Y9)^(1/7)-1) -> 0.0024006946 | Z9: =IF('2019'!Z9=0,0,(AME_2030!Z9/'2019'!Z9)^(1/7)-1) -> -0.0007478664 | AA9: =IF('2019'!AA9=0,0,(AME_2030!AA9/'2019'!AA9)^(1/7)-1) -> 0.0013439296 | ... AU9: =IF('2019'!AU9=0,0,(AME_2030!AU9/'2019'!AU9)^(1/7)-1) -> 0
B10: 06 | C10: 06 | D10: Articles of paper and paperboard | E10: =IF('2019'!E10=0,0,(AME_2030!E10/'2019'!E10)^(1/7)-1) -> 0.0062781038 | F10: =IF('2019'!F10=0,0,(AME_2030!F10/'2019'!F10)^(1/7)-1) -> 0.0068410355 | G10: =IF('2019'!G10=0,0,(AME_2030!G10/'2019'!G10)^(1/7)-1) -> -2.3353149e-09 | H10: =IF('2019'!H10=0,0,(AME_2030!H10/'2019'!H10)^(1/7)-1) -> 0.010172025 | I10: =IF('2019'!I10=0,0,(AME_2030!I10/'2019'!I10)^(1/7)-1) -> -0.00051864438 | J10: =IF('2019'!J10=0,0,(AME_2030!J10/'2019'!J10)^(1/7)-1) -> -0.00029435215 | K10: =IF('2019 (Z)'!AW10=0,0,('AME_2030 (Z)'!AW10/'2019 (Z)'!AW10)^(1/7)-1) -> 0.008918326 | L10: =K10 -> 0.008918326 | M10: =IF('2019'!M10=0,0,(AME_2030!M10/'2019'!M10)^(1/7)-1) -> -0.021075676 | N10: =IF('2019'!N10=0,0,(AME_2030!N10/'2019'!N10)^(1/7)-1) -> 0.0035065052 | O10: =IF('2019'!O10=0,0,(AME_2030!O10/'2019'!O10)^(1/7)-1) -> -0.00076565264 | P10: =IF('2019'!P10=0,0,(AME_2030!P10/'2019'!P10)^(1/7)-1) -> 0.0047663682 | Q10: =IF('2019'!Q10=0,0,(AME_2030!Q10/'2019'!Q10)^(1/7)-1) -> 1.492857e-07 | R10: =IF('2019'!R10=0,0,(AME_2030!R10/'2019'!R10)^(1/7)-1) -> -6.9626286e-07 | S10: =T10 -> 0.0012561522 | T10: =IF('2019'!T10=0,0,(AME_2030!T10/'2019'!T10)^(1/7)-1) -> 0.0012561522 | U10: =IF('2019'!U10=0,0,(AME_2030!U10/'2019'!U10)^(1/7)-1) -> -4.6270329e-05 | V10: =IF('2019'!V10=0,0,(AME_2030!V10/'2019'!V10)^(1/7)-1) -> -2.6346634e-08 | W10: =IF('2019'!W10=0,0,(AME_2030!W10/'2019'!W10)^(1/7)-1) -> 0.0066178255 | X10: =IF('2019'!X10=0,0,(AME_2030!X10/'2019'!X10)^(1/7)-1) -> 0.0071120198 | Y10: =IF('2019'!Y10=0,0,(AME_2030!Y10/'2019'!Y10)^(1/7)-1) -> 0.0027175098 | Z10: =IF('2019'!Z10=0,0,(AME_2030!Z10/'2019'!Z10)^(1/7)-1) -> -0.0019560459 | AA10: =IF('2019'!AA10=0,0,(AME_2030!AA10/'2019'!AA10)^(1/7)-1) -> 0.0012614832 | ... AU10: =IF('2019'!AU10=0,0,(AME_2030!AU10/'2019'!AU10)^(1/7)-1) -> 0
B11: 07 | C11: 07 | D11: Inorganic basic chemicals | E11: =IF('2019 (Z)'!E127=0,0,('AME_2030 (Z)'!E127/'2019 (Z)'!E127)^(1/7)-1) -> -0.012232707 | F11: =IF('2019 (Z)'!F127=0,0,('AME_2030 (Z)'!F127/'2019 (Z)'!F127)^(1/7)-1) -> -0.014048726 | G11: =IF('2019 (Z)'!G127=0,0,('AME_2030 (Z)'!G127/'2019 (Z)'!G127)^(1/7)-1) -> -0.014938797 | H11: =IF('2019 (Z)'!H127=0,0,('AME_2030 (Z)'!H127/'2019 (Z)'!H127)^(1/7)-1) -> -0.0050049616 | I11: =IF('2019 (Z)'!I127=0,0,('AME_2030 (Z)'!I127/'2019 (Z)'!I127)^(1/7)-1) -> -0.015499316 | J11: =IF('2019 (Z)'!J127=0,0,('AME_2030 (Z)'!J127/'2019 (Z)'!J127)^(1/7)-1) -> -0.014491784 | K11: =IF('2019 (Z)'!K127=0,0,('AME_2030 (Z)'!K127/'2019 (Z)'!K127)^(1/7)-1) -> -0.012666102 | L11: =IF('2019 (Z)'!L127=0,0,('AME_2030 (Z)'!L127/'2019 (Z)'!L127)^(1/7)-1) -> -0.012666102 | ... R11: =IF('2019 (Z)'!R127=0,0,('AME_2030 (Z)'!R127/'2019 (Z)'!R127)^(1/7)-1) -> -0.014938037 | S11: =T11 -> -0.014142684 | T11: =IF('2019 (Z)'!T127=0,0,('AME_2030 (Z)'!T127/'2019 (Z)'!T127)^(1/7)-1) -> -0.014142684 | U11: =IF('2019 (Z)'!U127=0,0,('AME_2030 (Z)'!U127/'2019 (Z)'!U127)^(1/7)-1) -> -0.014950777 | V11: =IF('2019 (Z)'!V127=0,0,('AME_2030 (Z)'!V127/'2019 (Z)'!V127)^(1/7)-1) -> -0.014938821 | W11: =IF('2019 (Z)'!W127=0,0,('AME_2030 (Z)'!W127/'2019 (Z)'!W127)^(1/7)-1) -> -0.016532777 | X11: =IF('2019 (Z)'!X127=0,0,('AME_2030 (Z)'!X127/'2019 (Z)'!X127)^(1/7)-1) -> -0.014919871 | Y11: =IF('2019 (Z)'!Y127=0,0,('AME_2030 (Z)'!Y127/'2019 (Z)'!Y127)^(1/7)-1) -> -0.012574118 | Z11: =IF('2019 (Z)'!Z127=0,0,('AME_2030 (Z)'!Z127/'2019 (Z)'!Z127)^(1/7)-1) -> -0.015107417 | AA11: =IF('2019 (Z)'!AA127=0,0,('AME_2030 (Z)'!AA127/'2019 (Z)'!AA127)^(1/7)-1) -> -0.01360854 | ... AU11: =IF('2019 (Z)'!AU127=0,0,('AME_2030 (Z)'!AU127/'2019 (Z)'!AU127)^(1/7)-1) -> 0
B12: 08 | C12: 08 | D12: Organic basic chemicals | E12: =E11 -> -0.012232707 | F12: =F11 -> -0.014048726 | G12: =G11 -> -0.014938797 | H12: =H11 -> -0.0050049616 | I12: =I11 -> -0.015499316 | J12: =J11 -> -0.014491784 | K12: =K11 -> -0.012666102 | L12: =L11 -> -0.012666102 | ... R12: =R11 -> -0.014938037 | S12: =T12 -> -0.014142684 | T12: =T11 -> -0.014142684 | U12: =U11 -> -0.014950777 | V12: =V11 -> -0.014938821 | W12: =W11 -> -0.016532777 | X12: =X11 -> -0.014919871 | Y12: =Y11 -> -0.012574118 | Z12: =Z11 -> -0.015107417 | AA12: =AA11 -> -0.01360854 | ... AU12: =AU11 -> 0
B13: 09 | C13: 09 | D13: Plastics products | E13: =IF('2019'!E13=0,0,(AME_2030!E13/'2019'!E13)^(1/7)-1) -> -0.023041319 | F13: =IF('2019'!F13=0,0,(AME_2030!F13/'2019'!F13)^(1/7)-1) -> -0.022615798 | G13: =IF('2019'!G13=0,0,(AME_2030!G13/'2019'!G13)^(1/7)-1) -> 0.11375899 | H13: =IF('2019'!H13=0,0,(AME_2030!H13/'2019'!H13)^(1/7)-1) -> 0.0059118054 | I13: =IF('2019'!I13=0,0,(AME_2030!I13/'2019'!I13)^(1/7)-1) -> -0.00034247169 | J13: =IF('2019'!J13=0,0,(AME_2030!J13/'2019'!J13)^(1/7)-1) -> -5.6445795e-05 | K13: =IF('2019 (Z)'!AW13=0,0,('AME_2030 (Z)'!AW13/'2019 (Z)'!AW13)^(1/7)-1) -> -0.018506549 | L13: =K13 -> -0.018506549 | M13: =IF('2019'!M13=0,0,(AME_2030!M13/'2019'!M13)^(1/7)-1) -> 0.0009201994 | N13: =IF('2019'!N13=0,0,(AME_2030!N13/'2019'!N13)^(1/7)-1) -> 0.0053502517 | O13: =IF('2019'!O13=0,0,(AME_2030!O13/'2019'!O13)^(1/7)-1) -> 0.0023815501 | P13: =IF('2019'!P13=0,0,(AME_2030!P13/'2019'!P13)^(1/7)-1) -> -0.016447839 | Q13: =IF('2019'!Q13=0,0,(AME_2030!Q13/'2019'!Q13)^(1/7)-1) -> 1.6232408e-07 | R13: =IF('2019'!R13=0,0,(AME_2030!R13/'2019'!R13)^(1/7)-1) -> -3.3220551e-08 | S13: =T13 -> -9.3499141e-07 | T13: =IF('2019'!T13=0,0,(AME_2030!T13/'2019'!T13)^(1/7)-1) -> -9.3499141e-07 | U13: =IF('2019'!U13=0,0,(AME_2030!U13/'2019'!U13)^(1/7)-1) -> -3.1512674e-05 | V13: =IF('2019'!V13=0,0,(AME_2030!V13/'2019'!V13)^(1/7)-1) -> 0 | W13: =IF('2019'!W13=0,0,(AME_2030!W13/'2019'!W13)^(1/7)-1) -> -0.023033303 | X13: =IF('2019'!X13=0,0,(AME_2030!X13/'2019'!X13)^(1/7)-1) -> -0.018014984 | Y13: =IF('2019'!Y13=0,0,(AME_2030!Y13/'2019'!Y13)^(1/7)-1) -> 0.0021813868 | Z13: =IF('2019'!Z13=0,0,(AME_2030!Z13/'2019'!Z13)^(1/7)-1) -> -0.0011023493 | AA13: =IF('2019'!AA13=0,0,(AME_2030!AA13/'2019'!AA13)^(1/7)-1) -> 0.0010697181 | ... AU13: =IF('2019'!AU13=0,0,(AME_2030!AU13/'2019'!AU13)^(1/7)-1) -> 0
B14: 10 | C14: 10 | D14: Basic iron and steel and of ferro-alloys | E14: =IF('2019'!E14=0,0,(AME_2030!E14/'2019'!E14)^(1/7)-1) -> 0.0050285925 | F14: =IF('2019'!F14=0,0,(AME_2030!F14/'2019'!F14)^(1/7)-1) -> -0.0023069458 | G14: =IF('2019'!G14=0,0,(AME_2030!G14/'2019'!G14)^(1/7)-1) -> -0.012053245 | H14: =IF('2019'!H14=0,0,(AME_2030!H14/'2019'!H14)^(1/7)-1) -> 0 | I14: =IF('2019'!I14=0,0,(AME_2030!I14/'2019'!I14)^(1/7)-1) -> -0.0019348887 | J14: =IF('2019'!J14=0,0,(AME_2030!J14/'2019'!J14)^(1/7)-1) -> -0.0021898078 | K14: =IF('2019 (Z)'!AW14=0,0,('AME_2030 (Z)'!AW14/'2019 (Z)'!AW14)^(1/7)-1) -> -0.00010507523 | L14: =K14 -> -0.00010507523 | M14: =IF('2019'!M14=0,0,(AME_2030!M14/'2019'!M14)^(1/7)-1) -> -0.002268089 | N14: =IF('2019'!N14=0,0,(AME_2030!N14/'2019'!N14)^(1/7)-1) -> -0.0037918095 | O14: =IF('2019'!O14=0,0,(AME_2030!O14/'2019'!O14)^(1/7)-1) -> -0.0031344206 | P14: =IF('2019'!P14=0,0,(AME_2030!P14/'2019'!P14)^(1/7)-1) -> -0.0019326151 | Q14: =IF('2019'!Q14=0,0,(AME_2030!Q14/'2019'!Q14)^(1/7)-1) -> -0.0025180906 | R14: =IF('2019'!R14=0,0,(AME_2030!R14/'2019'!R14)^(1/7)-1) -> -0.0023932257 | S14: =T14 -> -0.0023611919 | T14: =IF('2019'!T14=0,0,(AME_2030!T14/'2019'!T14)^(1/7)-1) -> -0.0023611919 | U14: =IF('2019'!U14=0,0,(AME_2030!U14/'2019'!U14)^(1/7)-1) -> -0.0019414391 | V14: =IF('2019'!V14=0,0,(AME_2030!V14/'2019'!V14)^(1/7)-1) -> -0.0021169928 | W14: =IF('2019'!W14=0,0,(AME_2030!W14/'2019'!W14)^(1/7)-1) -> -0.0017053511 | X14: =IF('2019'!X14=0,0,(AME_2030!X14/'2019'!X14)^(1/7)-1) -> 0.0017720292 | Y14: =IF('2019'!Y14=0,0,(AME_2030!Y14/'2019'!Y14)^(1/7)-1) -> 1.5081308e-06 | Z14: =IF('2019'!Z14=0,0,(AME_2030!Z14/'2019'!Z14)^(1/7)-1) -> -0.0035080331 | AA14: =IF('2019'!AA14=0,0,(AME_2030!AA14/'2019'!AA14)^(1/7)-1) -> -0.0010524893 | ... AU14: =IF('2019'!AU14=0,0,(AME_2030!AU14/'2019'!AU14)^(1/7)-1) -> 0
B15: 11 | C15: 11 | D15: Non-ferrous metals | E15: =IF('2019'!E15=0,0,(AME_2030!E15/'2019'!E15)^(1/7)-1) -> 0.0073229277 | F15: =IF('2019'!F15=0,0,(AME_2030!F15/'2019'!F15)^(1/7)-1) -> 0.0013368051 | G15: =IF('2019'!G15=0,0,(AME_2030!G15/'2019'!G15)^(1/7)-1) -> 0.13511799 | H15: =IF('2019'!H15=0,0,(AME_2030!H15/'2019'!H15)^(1/7)-1) -> 0.010228447 | I15: =IF('2019'!I15=0,0,(AME_2030!I15/'2019'!I15)^(1/7)-1) -> -0.0010597021 | J15: =IF('2019'!J15=0,0,(AME_2030!J15/'2019'!J15)^(1/7)-1) -> 0.0011637374 | K15: =IF('2019 (Z)'!AW15=0,0,('AME_2030 (Z)'!AW15/'2019 (Z)'!AW15)^(1/7)-1) -> 0.0044523074 | L15: =K15 -> 0.0044523074 | M15: =IF('2019'!M15=0,0,(AME_2030!M15/'2019'!M15)^(1/7)-1) -> 0.0082998513 | N15: =IF('2019'!N15=0,0,(AME_2030!N15/'2019'!N15)^(1/7)-1) -> 0.011354835 | O15: =IF('2019'!O15=0,0,(AME_2030!O15/'2019'!O15)^(1/7)-1) -> -0.0022906053 | P15: =IF('2019'!P15=0,0,(AME_2030!P15/'2019'!P15)^(1/7)-1) -> 0.00073617879 | Q15: =IF('2019'!Q15=0,0,(AME_2030!Q15/'2019'!Q15)^(1/7)-1) -> 0.00012276543 | R15: =IF('2019'!R15=0,0,(AME_2030!R15/'2019'!R15)^(1/7)-1) -> 0.0006301505 | S15: =T15 -> -0.00028029166 | T15: =IF('2019'!T15=0,0,(AME_2030!T15/'2019'!T15)^(1/7)-1) -> -0.00028029166 | U15: =IF('2019'!U15=0,0,(AME_2030!U15/'2019'!U15)^(1/7)-1) -> 6.6664019e-07 | V15: =IF('2019'!V15=0,0,(AME_2030!V15/'2019'!V15)^(1/7)-1) -> -0.00015883153 | W15: =IF('2019'!W15=0,0,(AME_2030!W15/'2019'!W15)^(1/7)-1) -> 0.00075635299 | X15: =IF('2019'!X15=0,0,(AME_2030!X15/'2019'!X15)^(1/7)-1) -> 0.00049973744 | Y15: =IF('2019'!Y15=0,0,(AME_2030!Y15/'2019'!Y15)^(1/7)-1) -> 0.0023470849 | Z15: =IF('2019'!Z15=0,0,(AME_2030!Z15/'2019'!Z15)^(1/7)-1) -> 0.0025729491 | AA15: =IF('2019'!AA15=0,0,(AME_2030!AA15/'2019'!AA15)^(1/7)-1) -> 0.0035005856 | ... AU15: =IF('2019'!AU15=0,0,(AME_2030!AU15/'2019'!AU15)^(1/7)-1) -> 0
B16: 12 | C16: 12 | D16: Other industries | E16: =IF('2019'!E16=0,0,(AME_2030!E16/'2019'!E16)^(1/7)-1) -> 0.00015422655 | F16: =IF('2019'!F16=0,0,(AME_2030!F16/'2019'!F16)^(1/7)-1) -> 5.7738326e-05 | G16: =IF('2019'!G16=0,0,(AME_2030!G16/'2019'!G16)^(1/7)-1) -> 4.899458e-05 | H16: =IF('2019'!H16=0,0,(AME_2030!H16/'2019'!H16)^(1/7)-1) -> -0.032419922 | I16: =IF('2019'!I16=0,0,(AME_2030!I16/'2019'!I16)^(1/7)-1) -> -9.6930831e-05 | J16: =IF('2019'!J16=0,0,(AME_2030!J16/'2019'!J16)^(1/7)-1) -> -0.0016014158 | K16: =IF('2019 (Z)'!AW16=0,0,('AME_2030 (Z)'!AW16/'2019 (Z)'!AW16)^(1/7)-1) -> 0.0022992686 | L16: =K16 -> 0.0022992686 | M16: =IF('2019'!M16=0,0,(AME_2030!M16/'2019'!M16)^(1/7)-1) -> 0.0065322225 | N16: =IF('2019'!N16=0,0,(AME_2030!N16/'2019'!N16)^(1/7)-1) -> -0.00090129465 | O16: =IF('2019'!O16=0,0,(AME_2030!O16/'2019'!O16)^(1/7)-1) -> 0.0031666931 | P16: =IF('2019'!P16=0,0,(AME_2030!P16/'2019'!P16)^(1/7)-1) -> 2.9623938e-05 | Q16: =IF('2019'!Q16=0,0,(AME_2030!Q16/'2019'!Q16)^(1/7)-1) -> 0.0030159972 | R16: =IF('2019'!R16=0,0,(AME_2030!R16/'2019'!R16)^(1/7)-1) -> -2.0238261e-08 | S16: =T16 -> 2.588167e-05 | T16: =IF('2019'!T16=0,0,(AME_2030!T16/'2019'!T16)^(1/7)-1) -> 2.588167e-05 | U16: =IF('2019'!U16=0,0,(AME_2030!U16/'2019'!U16)^(1/7)-1) -> -3.2228987e-05 | V16: =IF('2019'!V16=0,0,(AME_2030!V16/'2019'!V16)^(1/7)-1) -> -2.6346634e-08 | W16: =IF('2019'!W16=0,0,(AME_2030!W16/'2019'!W16)^(1/7)-1) -> -0.00042156542 | X16: =IF('2019'!X16=0,0,(AME_2030!X16/'2019'!X16)^(1/7)-1) -> -1.6294352e-05 | Y16: =IF('2019'!Y16=0,0,(AME_2030!Y16/'2019'!Y16)^(1/7)-1) -> 0.0024005377 | Z16: =IF('2019'!Z16=0,0,(AME_2030!Z16/'2019'!Z16)^(1/7)-1) -> -0.0011357484 | AA16: =IF('2019'!AA16=0,0,(AME_2030!AA16/'2019'!AA16)^(1/7)-1) -> 0.0013440062 | ... AU16: =IF('2019'!AU16=0,0,(AME_2030!AU16/'2019'!AU16)^(1/7)-1) -> 0
B17: 13 | C17: 13 | D17: Construction of buildings and Civil engineering | E17: =IF('2019'!E17=0,0,(AME_2030!E17/'2019'!E17)^(1/7)-1) -> 0.0012955289 | F17: =IF('2019'!F17=0,0,(AME_2030!F17/'2019'!F17)^(1/7)-1) -> 0.00028725348 | G17: =IF('2019'!G17=0,0,(AME_2030!G17/'2019'!G17)^(1/7)-1) -> -2.3353151e-09 | H17: =IF('2019'!H17=0,0,(AME_2030!H17/'2019'!H17)^(1/7)-1) -> 0.014345032 | I17: =IF('2019'!I17=0,0,(AME_2030!I17/'2019'!I17)^(1/7)-1) -> 0.00011444342 | J17: =IF('2019'!J17=0,0,(AME_2030!J17/'2019'!J17)^(1/7)-1) -> 0.0002332246 | K17: =IF('2019 (Z)'!AW17=0,0,('AME_2030 (Z)'!AW17/'2019 (Z)'!AW17)^(1/7)-1) -> 0.0023042647 | L17: =K17 -> 0.0023042647 | M17: =IF('2019'!M17=0,0,(AME_2030!M17/'2019'!M17)^(1/7)-1) -> 0.0097190254 | N17: =IF('2019'!N17=0,0,(AME_2030!N17/'2019'!N17)^(1/7)-1) -> -0.00057882025 | O17: =IF('2019'!O17=0,0,(AME_2030!O17/'2019'!O17)^(1/7)-1) -> 0.0055832409 | P17: =IF('2019'!P17=0,0,(AME_2030!P17/'2019'!P17)^(1/7)-1) -> -0.00026971345 | Q17: =IF('2019'!Q17=0,0,(AME_2030!Q17/'2019'!Q17)^(1/7)-1) -> 1.6442185e-07 | R17: =IF('2019'!R17=0,0,(AME_2030!R17/'2019'!R17)^(1/7)-1) -> -2.0238261e-08 | S17: =T17 -> 1.8950996e-05 | T17: =IF('2019'!T17=0,0,(AME_2030!T17/'2019'!T17)^(1/7)-1) -> 1.8950996e-05 | U17: =IF('2019'!U17=0,0,(AME_2030!U17/'2019'!U17)^(1/7)-1) -> -1.4453742e-05 | V17: =IF('2019'!V17=0,0,(AME_2030!V17/'2019'!V17)^(1/7)-1) -> -2.6346634e-08 | W17: =IF('2019'!W17=0,0,(AME_2030!W17/'2019'!W17)^(1/7)-1) -> -0.00063346482 | X17: =IF('2019'!X17=0,0,(AME_2030!X17/'2019'!X17)^(1/7)-1) -> 1.8122132e-06 | Y17: =IF('2019'!Y17=0,0,(AME_2030!Y17/'2019'!Y17)^(1/7)-1) -> 0.0024005377 | Z17: =IF('2019'!Z17=0,0,(AME_2030!Z17/'2019'!Z17)^(1/7)-1) -> -0.0011430572 | AA17: =IF('2019'!AA17=0,0,(AME_2030!AA17/'2019'!AA17)^(1/7)-1) -> 0.0013439953 | ... AU17: =IF('2019'!AU17=0,0,(AME_2030!AU17/'2019'!AU17)^(1/7)-1) -> 0
B18: 14 | C18: 14 | D18: Rail transport (Passenger and Freight) | E18: =IF('2019'!E18=0,0,(AME_2030!E18/'2019'!E18)^(1/7)-1) -> -0.00038948296 | F18: =IF('2019'!F18=0,0,(AME_2030!F18/'2019'!F18)^(1/7)-1) -> 0.00011100964 | G18: =IF('2019'!G18=0,0,(AME_2030!G18/'2019'!G18)^(1/7)-1) -> -2.3353149e-09 | H18: =IF('2019'!H18=0,0,(AME_2030!H18/'2019'!H18)^(1/7)-1) -> 0.013548732 | I18: =IF('2019'!I18=0,0,(AME_2030!I18/'2019'!I18)^(1/7)-1) -> 6.2856168e-06 | J18: =IF('2019'!J18=0,0,(AME_2030!J18/'2019'!J18)^(1/7)-1) -> -0.0019709509 | K18: =IF('2019 (Z)'!AW18=0,0,('AME_2030 (Z)'!AW18/'2019 (Z)'!AW18)^(1/7)-1) -> 0.0023245323 | L18: =K18 -> 0.0023245323 | M18: =IF('2019'!M18=0,0,(AME_2030!M18/'2019'!M18)^(1/7)-1) -> 0.016341139 | N18: =IF('2019'!N18=0,0,(AME_2030!N18/'2019'!N18)^(1/7)-1) -> -0.01379648 | O18: =IF('2019'!O18=0,0,(AME_2030!O18/'2019'!O18)^(1/7)-1) -> 0.0020462945 | P18: =IF('2019'!P18=0,0,(AME_2030!P18/'2019'!P18)^(1/7)-1) -> 0.00011699906 | Q18: =IF('2019'!Q18=0,0,(AME_2030!Q18/'2019'!Q18)^(1/7)-1) -> 1.6442185e-07 | R18: =IF('2019'!R18=0,0,(AME_2030!R18/'2019'!R18)^(1/7)-1) -> -2.0238261e-08 | S18: =T18 -> -6.8356769e-07 | T18: =IF('2019'!T18=0,0,(AME_2030!T18/'2019'!T18)^(1/7)-1) -> -6.8356769e-07 | U18: =IF('2019'!U18=0,0,(AME_2030!U18/'2019'!U18)^(1/7)-1) -> -2.9816359e-05 | V18: =IF('2019'!V18=0,0,(AME_2030!V18/'2019'!V18)^(1/7)-1) -> -2.6346634e-08 | W18: =IF('2019'!W18=0,0,(AME_2030!W18/'2019'!W18)^(1/7)-1) -> -0.00018015969 | X18: =IF('2019'!X18=0,0,(AME_2030!X18/'2019'!X18)^(1/7)-1) -> 1.5750694e-05 | Y18: =IF('2019'!Y18=0,0,(AME_2030!Y18/'2019'!Y18)^(1/7)-1) -> 0.0024005377 | Z18: =IF('2019'!Z18=0,0,(AME_2030!Z18/'2019'!Z18)^(1/7)-1) -> -0.0011472953 | AA18: =IF('2019'!AA18=0,0,(AME_2030!AA18/'2019'!AA18)^(1/7)-1) -> 0.0013439994 | ... AU18: =IF('2019'!AU18=0,0,(AME_2030!AU18/'2019'!AU18)^(1/7)-1) -> 0
B19: 15 | C19: 15 | D19: Passenger transport by road | E19: =E20 -> -0.00037330182 | F19: =F20 -> 0.00021106379 | G19: =G20 -> -2.3353149e-09 | H19: =H20 -> 0.013591861 | I19: =I20 -> 0.00021342568 | J19: =J20 -> -0.00093420613 | K19: =K20 -> 0.002331404 | L19: =L20 -> 0.002331404 | ... R19: =R20 -> -2.0238261e-08 | S19: =T19 -> 2.220413e-05 | T19: =T20 -> 2.220413e-05 | U19: =U20 -> -2.9484693e-05 | V19: =V20 -> -2.6346634e-08 | W19: =W20 -> 0.00052784111 | X19: =X20 -> 4.2754041e-06 | Y19: =Y20 -> 0.0024005377 | Z19: =Z20 -> -0.0011542043 | AA19: =AA20 -> 0.0013439655 | ... AU19: =AU20 -> 0
B20: 16 | C20: 16 | D20: Freight transport by road and transport via pipeline | E20: =IF('2019'!E20=0,0,(AME_2030!E20/'2019'!E20)^(1/7)-1) -> -0.00037330182 | F20: =IF('2019'!F20=0,0,(AME_2030!F20/'2019'!F20)^(1/7)-1) -> 0.00021106379 | G20: =IF('2019'!G20=0,0,(AME_2030!G20/'2019'!G20)^(1/7)-1) -> -2.3353149e-09 | H20: =IF('2019'!H20=0,0,(AME_2030!H20/'2019'!H20)^(1/7)-1) -> 0.013591861 | I20: =IF('2019'!I20=0,0,(AME_2030!I20/'2019'!I20)^(1/7)-1) -> 0.00021342568 | J20: =IF('2019'!J20=0,0,(AME_2030!J20/'2019'!J20)^(1/7)-1) -> -0.00093420613 | K20: =IF('2019 (Z)'!AW20=0,0,('AME_2030 (Z)'!AW20/'2019 (Z)'!AW20)^(1/7)-1) -> 0.002331404 | L20: =K20 -> 0.002331404 | M20: =IF('2019'!M20=0,0,(AME_2030!M20/'2019'!M20)^(1/7)-1) -> 0.032518991 | N20: =IF('2019'!N20=0,0,(AME_2030!N20/'2019'!N20)^(1/7)-1) -> 0.0012240107 | O20: =IF('2019'!O20=0,0,(AME_2030!O20/'2019'!O20)^(1/7)-1) -> 0.0012463825 | P20: =IF('2019'!P20=0,0,(AME_2030!P20/'2019'!P20)^(1/7)-1) -> 0.00019809474 | Q20: =IF('2019'!Q20=0,0,(AME_2030!Q20/'2019'!Q20)^(1/7)-1) -> 1.6442185e-07 | R20: =IF('2019'!R20=0,0,(AME_2030!R20/'2019'!R20)^(1/7)-1) -> -2.0238261e-08 | S20: =T20 -> 2.220413e-05 | T20: =IF('2019'!T20=0,0,(AME_2030!T20/'2019'!T20)^(1/7)-1) -> 2.220413e-05 | U20: =IF('2019'!U20=0,0,(AME_2030!U20/'2019'!U20)^(1/7)-1) -> -2.9484693e-05 | V20: =IF('2019'!V20=0,0,(AME_2030!V20/'2019'!V20)^(1/7)-1) -> -2.6346634e-08 | W20: =IF('2019'!W20=0,0,(AME_2030!W20/'2019'!W20)^(1/7)-1) -> 0.00052784111 | X20: =IF('2019'!X20=0,0,(AME_2030!X20/'2019'!X20)^(1/7)-1) -> 4.2754041e-06 | Y20: =IF('2019'!Y20=0,0,(AME_2030!Y20/'2019'!Y20)^(1/7)-1) -> 0.0024005377 | Z20: =IF('2019'!Z20=0,0,(AME_2030!Z20/'2019'!Z20)^(1/7)-1) -> -0.0011542043 | AA20: =IF('2019'!AA20=0,0,(AME_2030!AA20/'2019'!AA20)^(1/7)-1) -> 0.0013439655 | ... AU20: =IF('2019'!AU20=0,0,(AME_2030!AU20/'2019'!AU20)^(1/7)-1) -> 0
B21: 17 | C21: 17 | D21: Water transport | E21: =IF('2019'!E21=0,0,(AME_2030!E21/'2019'!E21)^(1/7)-1) -> -0.00055841202 | F21: =IF('2019'!F21=0,0,(AME_2030!F21/'2019'!F21)^(1/7)-1) -> 0.00012750023 | G21: =IF('2019'!G21=0,0,(AME_2030!G21/'2019'!G21)^(1/7)-1) -> -2.3353149e-09 | H21: =IF('2019'!H21=0,0,(AME_2030!H21/'2019'!H21)^(1/7)-1) -> 0.013548732 | I21: =IF('2019'!I21=0,0,(AME_2030!I21/'2019'!I21)^(1/7)-1) -> -0.00021974685 | J21: =IF('2019'!J21=0,0,(AME_2030!J21/'2019'!J21)^(1/7)-1) -> -0.0032097826 | K21: =IF('2019 (Z)'!AW21=0,0,('AME_2030 (Z)'!AW21/'2019 (Z)'!AW21)^(1/7)-1) -> 0.0024052062 | L21: =K21 -> 0.0024052062 | M21: =IF('2019'!M21=0,0,(AME_2030!M21/'2019'!M21)^(1/7)-1) -> 0.047841231 | N21: =IF('2019'!N21=0,0,(AME_2030!N21/'2019'!N21)^(1/7)-1) -> 0.0018555418 | O21: =IF('2019'!O21=0,0,(AME_2030!O21/'2019'!O21)^(1/7)-1) -> 0.0020405095 | P21: =IF('2019'!P21=0,0,(AME_2030!P21/'2019'!P21)^(1/7)-1) -> 0.00057612029 | Q21: =IF('2019'!Q21=0,0,(AME_2030!Q21/'2019'!Q21)^(1/7)-1) -> 1.6442185e-07 | R21: =IF('2019'!R21=0,0,(AME_2030!R21/'2019'!R21)^(1/7)-1) -> -2.0238261e-08 | S21: =T21 -> 1.0622255e-05 | T21: =IF('2019'!T21=0,0,(AME_2030!T21/'2019'!T21)^(1/7)-1) -> 1.0622255e-05 | U21: =IF('2019'!U21=0,0,(AME_2030!U21/'2019'!U21)^(1/7)-1) -> 7.5672153e-06 | V21: =IF('2019'!V21=0,0,(AME_2030!V21/'2019'!V21)^(1/7)-1) -> -2.6346634e-08 | W21: =IF('2019'!W21=0,0,(AME_2030!W21/'2019'!W21)^(1/7)-1) -> -0.00088842062 | X21: =IF('2019'!X21=0,0,(AME_2030!X21/'2019'!X21)^(1/7)-1) -> 1.9605699e-06 | Y21: =IF('2019'!Y21=0,0,(AME_2030!Y21/'2019'!Y21)^(1/7)-1) -> 0.0024005377 | Z21: =IF('2019'!Z21=0,0,(AME_2030!Z21/'2019'!Z21)^(1/7)-1) -> -0.0011257782 | AA21: =IF('2019'!AA21=0,0,(AME_2030!AA21/'2019'!AA21)^(1/7)-1) -> 0.0013440024 | ... AU21: =IF('2019'!AU21=0,0,(AME_2030!AU21/'2019'!AU21)^(1/7)-1) -> 0
B22: 18 | C22: 18 | D22: Air transport | E22: =IF('2019'!E22=0,0,(AME_2030!E22/'2019'!E22)^(1/7)-1) -> -0.00075039922 | F22: =IF('2019'!F22=0,0,(AME_2030!F22/'2019'!F22)^(1/7)-1) -> 9.751166e-05 | G22: =IF('2019'!G22=0,0,(AME_2030!G22/'2019'!G22)^(1/7)-1) -> -2.3353149e-09 | H22: =IF('2019'!H22=0,0,(AME_2030!H22/'2019'!H22)^(1/7)-1) -> 0.014202559 | I22: =IF('2019'!I22=0,0,(AME_2030!I22/'2019'!I22)^(1/7)-1) -> -0.0002433484 | J22: =IF('2019'!J22=0,0,(AME_2030!J22/'2019'!J22)^(1/7)-1) -> -0.00029526049 | K22: =IF('2019 (Z)'!AW22=0,0,('AME_2030 (Z)'!AW22/'2019 (Z)'!AW22)^(1/7)-1) -> 0.0022977829 | L22: =K22 -> 0.0022977829 | M22: =IF('2019'!M22=0,0,(AME_2030!M22/'2019'!M22)^(1/7)-1) -> -0.0114786 | N22: =IF('2019'!N22=0,0,(AME_2030!N22/'2019'!N22)^(1/7)-1) -> -0.015944822 | O22: =IF('2019'!O22=0,0,(AME_2030!O22/'2019'!O22)^(1/7)-1) -> 0.0021432553 | P22: =IF('2019'!P22=0,0,(AME_2030!P22/'2019'!P22)^(1/7)-1) -> 0.00023977016 | Q22: =IF('2019'!Q22=0,0,(AME_2030!Q22/'2019'!Q22)^(1/7)-1) -> 1.6442185e-07 | R22: =IF('2019'!R22=0,0,(AME_2030!R22/'2019'!R22)^(1/7)-1) -> -2.0238261e-08 | S22: =T22 -> 3.8662049e-06 | T22: =IF('2019'!T22=0,0,(AME_2030!T22/'2019'!T22)^(1/7)-1) -> 3.8662049e-06 | U22: =IF('2019'!U22=0,0,(AME_2030!U22/'2019'!U22)^(1/7)-1) -> -1.2235463e-05 | V22: =IF('2019'!V22=0,0,(AME_2030!V22/'2019'!V22)^(1/7)-1) -> -2.6346634e-08 | W22: =IF('2019'!W22=0,0,(AME_2030!W22/'2019'!W22)^(1/7)-1) -> 0.00028336675 | X22: =IF('2019'!X22=0,0,(AME_2030!X22/'2019'!X22)^(1/7)-1) -> 1.0581962e-05 | Y22: =IF('2019'!Y22=0,0,(AME_2030!Y22/'2019'!Y22)^(1/7)-1) -> 0.0024005377 | Z22: =IF('2019'!Z22=0,0,(AME_2030!Z22/'2019'!Z22)^(1/7)-1) -> -0.0011566979 | AA22: =IF('2019'!AA22=0,0,(AME_2030!AA22/'2019'!AA22)^(1/7)-1) -> 0.0013439981 | ... AU22: =IF('2019'!AU22=0,0,(AME_2030!AU22/'2019'!AU22)^(1/7)-1) -> 0
B23: 19 | C23: 19 | D23: Business services | E23: =IF('2019'!E23=0,0,(AME_2030!E23/'2019'!E23)^(1/7)-1) -> -0.0003923783 | F23: =IF('2019'!F23=0,0,(AME_2030!F23/'2019'!F23)^(1/7)-1) -> -0.00021321895 | G23: =IF('2019'!G23=0,0,(AME_2030!G23/'2019'!G23)^(1/7)-1) -> -0.0003334965 | H23: =IF('2019'!H23=0,0,(AME_2030!H23/'2019'!H23)^(1/7)-1) -> 0.0029960267 | I23: =IF('2019'!I23=0,0,(AME_2030!I23/'2019'!I23)^(1/7)-1) -> -0.00085004437 | J23: =IF('2019'!J23=0,0,(AME_2030!J23/'2019'!J23)^(1/7)-1) -> -0.00029399541 | K23: =IF('2019 (Z)'!AW23=0,0,('AME_2030 (Z)'!AW23/'2019 (Z)'!AW23)^(1/7)-1) -> 0.0022735432 | L23: =K23 -> 0.0022735432 | M23: =IF('2019'!M23=0,0,(AME_2030!M23/'2019'!M23)^(1/7)-1) -> 0.0090651885 | N23: =IF('2019'!N23=0,0,(AME_2030!N23/'2019'!N23)^(1/7)-1) -> -0.006734809 | O23: =IF('2019'!O23=0,0,(AME_2030!O23/'2019'!O23)^(1/7)-1) -> 0.00096610984 | P23: =IF('2019'!P23=0,0,(AME_2030!P23/'2019'!P23)^(1/7)-1) -> -0.00040248313 | Q23: =IF('2019'!Q23=0,0,(AME_2030!Q23/'2019'!Q23)^(1/7)-1) -> -0.00022802669 | R23: =IF('2019'!R23=0,0,(AME_2030!R23/'2019'!R23)^(1/7)-1) -> -0.000112276 | S23: =T23 -> -2.1216306e-05 | T23: =IF('2019'!T23=0,0,(AME_2030!T23/'2019'!T23)^(1/7)-1) -> -2.1216306e-05 | U23: =IF('2019'!U23=0,0,(AME_2030!U23/'2019'!U23)^(1/7)-1) -> -0.00019648459 | V23: =IF('2019'!V23=0,0,(AME_2030!V23/'2019'!V23)^(1/7)-1) -> -0.00015338063 | W23: =IF('2019'!W23=0,0,(AME_2030!W23/'2019'!W23)^(1/7)-1) -> -9.0643037e-05 | X23: =IF('2019'!X23=0,0,(AME_2030!X23/'2019'!X23)^(1/7)-1) -> -0.00045293763 | Y23: =IF('2019'!Y23=0,0,(AME_2030!Y23/'2019'!Y23)^(1/7)-1) -> 0.0021769947 | Z23: =IF('2019'!Z23=0,0,(AME_2030!Z23/'2019'!Z23)^(1/7)-1) -> -0.0021494606 | AA23: =IF('2019'!AA23=0,0,(AME_2030!AA23/'2019'!AA23)^(1/7)-1) -> 0.0013104113 | ... AU23: =IF('2019'!AU23=0,0,(AME_2030!AU23/'2019'!AU23)^(1/7)-1) -> 0
B24: 20 | C24: 20 | D24: Public services | E24: =IF('2019'!E24=0,0,(AME_2030!E24/'2019'!E24)^(1/7)-1) -> 0.00059221996 | F24: =IF('2019'!F24=0,0,(AME_2030!F24/'2019'!F24)^(1/7)-1) -> 5.9725089e-05 | G24: =IF('2019'!G24=0,0,(AME_2030!G24/'2019'!G24)^(1/7)-1) -> -2.3353151e-09 | H24: =IF('2019'!H24=0,0,(AME_2030!H24/'2019'!H24)^(1/7)-1) -> 0.033808394 | I24: =IF('2019'!I24=0,0,(AME_2030!I24/'2019'!I24)^(1/7)-1) -> -0.00025619223 | J24: =IF('2019'!J24=0,0,(AME_2030!J24/'2019'!J24)^(1/7)-1) -> -0.0072948281 | K24: =IF('2019 (Z)'!AW24=0,0,('AME_2030 (Z)'!AW24/'2019 (Z)'!AW24)^(1/7)-1) -> 0.0022955051 | L24: =K24 -> 0.0022955051 | M24: =IF('2019'!M24=0,0,(AME_2030!M24/'2019'!M24)^(1/7)-1) -> 0.0035629826 | N24: =IF('2019'!N24=0,0,(AME_2030!N24/'2019'!N24)^(1/7)-1) -> 0.016156425 | O24: =IF('2019'!O24=0,0,(AME_2030!O24/'2019'!O24)^(1/7)-1) -> 0.0028134881 | P24: =IF('2019'!P24=0,0,(AME_2030!P24/'2019'!P24)^(1/7)-1) -> -0.00016399946 | Q24: =IF('2019'!Q24=0,0,(AME_2030!Q24/'2019'!Q24)^(1/7)-1) -> 1.6442185e-07 | R24: =IF('2019'!R24=0,0,(AME_2030!R24/'2019'!R24)^(1/7)-1) -> -2.0238261e-08 | S24: =T24 -> 2.1301747e-06 | T24: =IF('2019'!T24=0,0,(AME_2030!T24/'2019'!T24)^(1/7)-1) -> 2.1301747e-06 | U24: =IF('2019'!U24=0,0,(AME_2030!U24/'2019'!U24)^(1/7)-1) -> -4.0218943e-05 | V24: =IF('2019'!V24=0,0,(AME_2030!V24/'2019'!V24)^(1/7)-1) -> -2.6346634e-08 | W24: =IF('2019'!W24=0,0,(AME_2030!W24/'2019'!W24)^(1/7)-1) -> -0.00030544359 | X24: =IF('2019'!X24=0,0,(AME_2030!X24/'2019'!X24)^(1/7)-1) -> -7.4898273e-06 | Y24: =IF('2019'!Y24=0,0,(AME_2030!Y24/'2019'!Y24)^(1/7)-1) -> 0.0024005377 | Z24: =IF('2019'!Z24=0,0,(AME_2030!Z24/'2019'!Z24)^(1/7)-1) -> -0.0011439708 | AA24: =IF('2019'!AA24=0,0,(AME_2030!AA24/'2019'!AA24)^(1/7)-1) -> 0.0013438777 | ... AU24: =IF('2019'!AU24=0,0,(AME_2030!AU24/'2019'!AU24)^(1/7)-1) -> 0
B25: 21 | C25: 21 | D25: Coal | E25: =IF('2019'!E25=0,0,(AME_2030!E25/'2019'!E25)^(1/7)-1) -> 0 | F25: =IF('2019'!F25=0,0,(AME_2030!F25/'2019'!F25)^(1/7)-1) -> -0.00011650399 | G25: =IF('2019'!G25=0,0,(AME_2030!G25/'2019'!G25)^(1/7)-1) -> -2.3353149e-09 | H25: =IF('2019'!H25=0,0,(AME_2030!H25/'2019'!H25)^(1/7)-1) -> -0.080107715 | I25: =IF('2019'!I25=0,0,(AME_2030!I25/'2019'!I25)^(1/7)-1) -> -0.00040471178 | J25: =IF('2019'!J25=0,0,(AME_2030!J25/'2019'!J25)^(1/7)-1) -> 0 | K25: =IF('2019 (Z)'!AW25=0,0,('AME_2030 (Z)'!AW25/'2019 (Z)'!AW25)^(1/7)-1) -> 0.0023299226 | L25: =K25 -> 0.0023299226 | M25: =IF('2019'!M25=0,0,(AME_2030!M25/'2019'!M25)^(1/7)-1) -> -0.043752193 | N25: =IF('2019'!N25=0,0,(AME_2030!N25/'2019'!N25)^(1/7)-1) -> 0.068221988 | O25: =IF('2019'!O25=0,0,(AME_2030!O25/'2019'!O25)^(1/7)-1) -> -0.010778 | P25: =IF('2019'!P25=0,0,(AME_2030!P25/'2019'!P25)^(1/7)-1) -> 0.00051101568 | Q25: =IF('2019'!Q25=0,0,(AME_2030!Q25/'2019'!Q25)^(1/7)-1) -> 1.6442185e-07 | R25: =IF('2019'!R25=0,0,(AME_2030!R25/'2019'!R25)^(1/7)-1) -> 0 | S25: =T25 -> 0 | T25: =IF('2019'!T25=0,0,(AME_2030!T25/'2019'!T25)^(1/7)-1) -> 0 | U25: =IF('2019'!U25=0,0,(AME_2030!U25/'2019'!U25)^(1/7)-1) -> 0 | V25: =IF('2019'!V25=0,0,(AME_2030!V25/'2019'!V25)^(1/7)-1) -> 0 | W25: =IF('2019'!W25=0,0,(AME_2030!W25/'2019'!W25)^(1/7)-1) -> 0 | X25: =IF('2019'!X25=0,0,(AME_2030!X25/'2019'!X25)^(1/7)-1) -> 0 | Y25: =IF('2019'!Y25=0,0,(AME_2030!Y25/'2019'!Y25)^(1/7)-1) -> 0 | Z25: =IF('2019'!Z25=0,0,(AME_2030!Z25/'2019'!Z25)^(1/7)-1) -> -0.00094348629 | AA25: =IF('2019'!AA25=0,0,(AME_2030!AA25/'2019'!AA25)^(1/7)-1) -> 0.0013440117 | ... AU25: =IF('2019'!AU25=0,0,(AME_2030!AU25/'2019'!AU25)^(1/7)-1) -> 0
B26: 22 | C26: 22 | D26: Oil | E26: =IF('2019'!E26=0,0,(AME_2030!E26/'2019'!E26)^(1/7)-1) -> -0.00018706081 | F26: =IF('2019'!F26=0,0,(AME_2030!F26/'2019'!F26)^(1/7)-1) -> 0.00038140391 | G26: =IF('2019'!G26=0,0,(AME_2030!G26/'2019'!G26)^(1/7)-1) -> -2.3353149e-09 | H26: =IF('2019'!H26=0,0,(AME_2030!H26/'2019'!H26)^(1/7)-1) -> -0.057649093 | I26: =IF('2019'!I26=0,0,(AME_2030!I26/'2019'!I26)^(1/7)-1) -> -0.00074861532 | J26: =IF('2019'!J26=0,0,(AME_2030!J26/'2019'!J26)^(1/7)-1) -> -0.0031385328 | K26: =IF('2019 (Z)'!AW26=0,0,('AME_2030 (Z)'!AW26/'2019 (Z)'!AW26)^(1/7)-1) -> 0.0023451415 | L26: =K26 -> 0.0023451415 | M26: =IF('2019'!M26=0,0,(AME_2030!M26/'2019'!M26)^(1/7)-1) -> 0.0051330029 | N26: =IF('2019'!N26=0,0,(AME_2030!N26/'2019'!N26)^(1/7)-1) -> -0.038887703 | O26: =IF('2019'!O26=0,0,(AME_2030!O26/'2019'!O26)^(1/7)-1) -> -0.010259007 | P26: =IF('2019'!P26=0,0,(AME_2030!P26/'2019'!P26)^(1/7)-1) -> 0.0012818787 | Q26: =IF('2019'!Q26=0,0,(AME_2030!Q26/'2019'!Q26)^(1/7)-1) -> 1.6442185e-07 | R26: =IF('2019'!R26=0,0,(AME_2030!R26/'2019'!R26)^(1/7)-1) -> -2.0238261e-08 | S26: =T26 -> -2.5547003e-06 | T26: =IF('2019'!T26=0,0,(AME_2030!T26/'2019'!T26)^(1/7)-1) -> -2.5547003e-06 | U26: =IF('2019'!U26=0,0,(AME_2030!U26/'2019'!U26)^(1/7)-1) -> -3.8892926e-05 | V26: =IF('2019'!V26=0,0,(AME_2030!V26/'2019'!V26)^(1/7)-1) -> -2.6346634e-08 | W26: =IF('2019'!W26=0,0,(AME_2030!W26/'2019'!W26)^(1/7)-1) -> 2.1101728e-05 | X26: =IF('2019'!X26=0,0,(AME_2030!X26/'2019'!X26)^(1/7)-1) -> -3.416616e-06 | Y26: =IF('2019'!Y26=0,0,(AME_2030!Y26/'2019'!Y26)^(1/7)-1) -> 0.0024005377 | Z26: =IF('2019'!Z26=0,0,(AME_2030!Z26/'2019'!Z26)^(1/7)-1) -> -0.0011564822 | AA26: =IF('2019'!AA26=0,0,(AME_2030!AA26/'2019'!AA26)^(1/7)-1) -> 0.0013438091 | ... AU26: =IF('2019'!AU26=0,0,(AME_2030!AU26/'2019'!AU26)^(1/7)-1) -> 0
B27: 23 | C27: 23 | D27: Biofuel | E27: =IF('2019'!E27=0,0,(AME_2030!E27/'2019'!E27)^(1/7)-1) -> 0.00015631919 | F27: =IF('2019'!F27=0,0,(AME_2030!F27/'2019'!F27)^(1/7)-1) -> 0.00081507841 | G27: =IF('2019'!G27=0,0,(AME_2030!G27/'2019'!G27)^(1/7)-1) -> -2.3353151e-09 | H27: =IF('2019'!H27=0,0,(AME_2030!H27/'2019'!H27)^(1/7)-1) -> 0.11976939 | I27: =IF('2019'!I27=0,0,(AME_2030!I27/'2019'!I27)^(1/7)-1) -> -0.00037575257 | J27: =IF('2019'!J27=0,0,(AME_2030!J27/'2019'!J27)^(1/7)-1) -> 0 | K27: =IF('2019 (Z)'!AW27=0,0,('AME_2030 (Z)'!AW27/'2019 (Z)'!AW27)^(1/7)-1) -> 0.0022936901 | L27: =K27 -> 0.0022936901 | M27: =IF('2019'!M27=0,0,(AME_2030!M27/'2019'!M27)^(1/7)-1) -> -0.001024403 | N27: =IF('2019'!N27=0,0,(AME_2030!N27/'2019'!N27)^(1/7)-1) -> -0.0013528264 | O27: =IF('2019'!O27=0,0,(AME_2030!O27/'2019'!O27)^(1/7)-1) -> -0.020719813 | P27: =IF('2019'!P27=0,0,(AME_2030!P27/'2019'!P27)^(1/7)-1) -> 0.0002651138 | Q27: =IF('2019'!Q27=0,0,(AME_2030!Q27/'2019'!Q27)^(1/7)-1) -> 1.6442185e-07 | R27: =IF('2019'!R27=0,0,(AME_2030!R27/'2019'!R27)^(1/7)-1) -> 0 | S27: =T27 -> 0 | T27: =IF('2019'!T27=0,0,(AME_2030!T27/'2019'!T27)^(1/7)-1) -> 0 | U27: =IF('2019'!U27=0,0,(AME_2030!U27/'2019'!U27)^(1/7)-1) -> 7.6186279e-06 | V27: =IF('2019'!V27=0,0,(AME_2030!V27/'2019'!V27)^(1/7)-1) -> 0 | W27: =IF('2019'!W27=0,0,(AME_2030!W27/'2019'!W27)^(1/7)-1) -> 0 | X27: =IF('2019'!X27=0,0,(AME_2030!X27/'2019'!X27)^(1/7)-1) -> 0 | Y27: =IF('2019'!Y27=0,0,(AME_2030!Y27/'2019'!Y27)^(1/7)-1) -> 0.0024005377 | Z27: =IF('2019'!Z27=0,0,(AME_2030!Z27/'2019'!Z27)^(1/7)-1) -> 0.00028114157 | AA27: =IF('2019'!AA27=0,0,(AME_2030!AA27/'2019'!AA27)^(1/7)-1) -> 0.0013438004 | ... AU27: =IF('2019'!AU27=0,0,(AME_2030!AU27/'2019'!AU27)^(1/7)-1) -> 0
B28: 24 | C28: 24 | D28: Electricity by nuclear | E28: =IF('2019'!E28=0,0,(AME_2030!E28/'2019'!E28)^(1/7)-1) -> -0.00010709151 | F28: =IF('2019'!F28=0,0,(AME_2030!F28/'2019'!F28)^(1/7)-1) -> -1.9086806e-05 | G28: =IF('2019'!G28=0,0,(AME_2030!G28/'2019'!G28)^(1/7)-1) -> -2.3353151e-09 | H28: =IF('2019'!H28=0,0,(AME_2030!H28/'2019'!H28)^(1/7)-1) -> 0.024072717 | I28: =IF('2019'!I28=0,0,(AME_2030!I28/'2019'!I28)^(1/7)-1) -> 9.0622935e-05 | J28: =IF('2019'!J28=0,0,(AME_2030!J28/'2019'!J28)^(1/7)-1) -> -0.011161848 | K28: =IF('2019 (Z)'!AW28=0,0,('AME_2030 (Z)'!AW28/'2019 (Z)'!AW28)^(1/7)-1) -> 0.0022982979 | L28: =K28 -> 0.0022982979 | M28: =IF('2019'!M28=0,0,(AME_2030!M28/'2019'!M28)^(1/7)-1) -> -0.0097233183 | N28: =IF('2019'!N28=0,0,(AME_2030!N28/'2019'!N28)^(1/7)-1) -> 0.035415322 | O28: =IF('2019'!O28=0,0,(AME_2030!O28/'2019'!O28)^(1/7)-1) -> -0.039170238 | P28: =IF('2019'!P28=0,0,(AME_2030!P28/'2019'!P28)^(1/7)-1) -> -4.6226709e-05 | Q28: =IF('2019'!Q28=0,0,(AME_2030!Q28/'2019'!Q28)^(1/7)-1) -> 1.6442185e-07 | R28: =IF('2019'!R28=0,0,(AME_2030!R28/'2019'!R28)^(1/7)-1) -> -2.0238261e-08 | S28: =T28 -> 6.4570597e-07 | T28: =IF('2019'!T28=0,0,(AME_2030!T28/'2019'!T28)^(1/7)-1) -> 6.4570597e-07 | U28: =IF('2019'!U28=0,0,(AME_2030!U28/'2019'!U28)^(1/7)-1) -> 0 | V28: =IF('2019'!V28=0,0,(AME_2030!V28/'2019'!V28)^(1/7)-1) -> -2.6346634e-08 | W28: =IF('2019'!W28=0,0,(AME_2030!W28/'2019'!W28)^(1/7)-1) -> -5.1907287e-05 | X28: =IF('2019'!X28=0,0,(AME_2030!X28/'2019'!X28)^(1/7)-1) -> 5.6582395e-06 | Y28: =IF('2019'!Y28=0,0,(AME_2030!Y28/'2019'!Y28)^(1/7)-1) -> 0.0024005377 | Z28: =IF('2019'!Z28=0,0,(AME_2030!Z28/'2019'!Z28)^(1/7)-1) -> -0.0011572408 | AA28: =IF('2019'!AA28=0,0,(AME_2030!AA28/'2019'!AA28)^(1/7)-1) -> 0.0013440072 | ... AU28: =IF('2019'!AU28=0,0,(AME_2030!AU28/'2019'!AU28)^(1/7)-1) -> 0
B29: 25 | C29: 25 | D29: Electricity by petroleum | E29: =IF('2019'!E29=0,0,(AME_2030!E29/'2019'!E29)^(1/7)-1) -> 0.00028618511 | F29: =IF('2019'!F29=0,0,(AME_2030!F29/'2019'!F29)^(1/7)-1) -> 7.7730447e-05 | G29: =IF('2019'!G29=0,0,(AME_2030!G29/'2019'!G29)^(1/7)-1) -> -2.3353149e-09 | H29: =IF('2019'!H29=0,0,(AME_2030!H29/'2019'!H29)^(1/7)-1) -> 0.023963905 | I29: =IF('2019'!I29=0,0,(AME_2030!I29/'2019'!I29)^(1/7)-1) -> 4.4246249e-05 | J29: =IF('2019'!J29=0,0,(AME_2030!J29/'2019'!J29)^(1/7)-1) -> -0.016824633 | K29: =IF('2019 (Z)'!AW29=0,0,('AME_2030 (Z)'!AW29/'2019 (Z)'!AW29)^(1/7)-1) -> 0.0023015954 | L29: =K29 -> 0.0023015954 | M29: =IF('2019'!M29=0,0,(AME_2030!M29/'2019'!M29)^(1/7)-1) -> -0.0077400527 | N29: =IF('2019'!N29=0,0,(AME_2030!N29/'2019'!N29)^(1/7)-1) -> 0.035993886 | O29: =IF('2019'!O29=0,0,(AME_2030!O29/'2019'!O29)^(1/7)-1) -> -0.035001999 | P29: =IF('2019'!P29=0,0,(AME_2030!P29/'2019'!P29)^(1/7)-1) -> 1.0724485e-05 | Q29: =IF('2019'!Q29=0,0,(AME_2030!Q29/'2019'!Q29)^(1/7)-1) -> 1.6442185e-07 | R29: =IF('2019'!R29=0,0,(AME_2030!R29/'2019'!R29)^(1/7)-1) -> -2.0238261e-08 | S29: =T29 -> 6.1823798e-07 | T29: =IF('2019'!T29=0,0,(AME_2030!T29/'2019'!T29)^(1/7)-1) -> 6.1823798e-07 | U29: =IF('2019'!U29=0,0,(AME_2030!U29/'2019'!U29)^(1/7)-1) -> 0 | V29: =IF('2019'!V29=0,0,(AME_2030!V29/'2019'!V29)^(1/7)-1) -> 0 | W29: =IF('2019'!W29=0,0,(AME_2030!W29/'2019'!W29)^(1/7)-1) -> 0.0001050394 | X29: =IF('2019'!X29=0,0,(AME_2030!X29/'2019'!X29)^(1/7)-1) -> 4.9522659e-06 | Y29: =IF('2019'!Y29=0,0,(AME_2030!Y29/'2019'!Y29)^(1/7)-1) -> 0 | Z29: =IF('2019'!Z29=0,0,(AME_2030!Z29/'2019'!Z29)^(1/7)-1) -> -0.0011567087 | AA29: =IF('2019'!AA29=0,0,(AME_2030!AA29/'2019'!AA29)^(1/7)-1) -> 0.0013440083 | ... AU29: =IF('2019'!AU29=0,0,(AME_2030!AU29/'2019'!AU29)^(1/7)-1) -> 0
B30: 26 | C30: 26 | D30: Electricity by gas | E30: =IF('2019'!E30=0,0,(AME_2030!E30/'2019'!E30)^(1/7)-1) -> -0.00034769384 | F30: =IF('2019'!F30=0,0,(AME_2030!F30/'2019'!F30)^(1/7)-1) -> -4.9613883e-05 | G30: =IF('2019'!G30=0,0,(AME_2030!G30/'2019'!G30)^(1/7)-1) -> -2.3353149e-09 | H30: =IF('2019'!H30=0,0,(AME_2030!H30/'2019'!H30)^(1/7)-1) -> 0.024043467 | I30: =IF('2019'!I30=0,0,(AME_2030!I30/'2019'!I30)^(1/7)-1) -> 4.3750642e-05 | J30: =IF('2019'!J30=0,0,(AME_2030!J30/'2019'!J30)^(1/7)-1) -> -0.016675543 | K30: =IF('2019 (Z)'!AW30=0,0,('AME_2030 (Z)'!AW30/'2019 (Z)'!AW30)^(1/7)-1) -> 0.0022969912 | L30: =K30 -> 0.0022969912 | M30: =IF('2019'!M30=0,0,(AME_2030!M30/'2019'!M30)^(1/7)-1) -> -0.017517297 | N30: =IF('2019'!N30=0,0,(AME_2030!N30/'2019'!N30)^(1/7)-1) -> 0.036012664 | O30: =IF('2019'!O30=0,0,(AME_2030!O30/'2019'!O30)^(1/7)-1) -> -0.034848707 | P30: =IF('2019'!P30=0,0,(AME_2030!P30/'2019'!P30)^(1/7)-1) -> 1.0539391e-05 | Q30: =IF('2019'!Q30=0,0,(AME_2030!Q30/'2019'!Q30)^(1/7)-1) -> 1.6442185e-07 | R30: =IF('2019'!R30=0,0,(AME_2030!R30/'2019'!R30)^(1/7)-1) -> -2.0238261e-08 | S30: =T30 -> 6.1887672e-07 | T30: =IF('2019'!T30=0,0,(AME_2030!T30/'2019'!T30)^(1/7)-1) -> 6.1887672e-07 | U30: =IF('2019'!U30=0,0,(AME_2030!U30/'2019'!U30)^(1/7)-1) -> 0 | V30: =IF('2019'!V30=0,0,(AME_2030!V30/'2019'!V30)^(1/7)-1) -> 0 | W30: =IF('2019'!W30=0,0,(AME_2030!W30/'2019'!W30)^(1/7)-1) -> -0.00014457011 | X30: =IF('2019'!X30=0,0,(AME_2030!X30/'2019'!X30)^(1/7)-1) -> 7.5031978e-06 | Y30: =IF('2019'!Y30=0,0,(AME_2030!Y30/'2019'!Y30)^(1/7)-1) -> 0 | Z30: =IF('2019'!Z30=0,0,(AME_2030!Z30/'2019'!Z30)^(1/7)-1) -> -0.0011548758 | AA30: =IF('2019'!AA30=0,0,(AME_2030!AA30/'2019'!AA30)^(1/7)-1) -> 0.0013440104 | ... AU30: =IF('2019'!AU30=0,0,(AME_2030!AU30/'2019'!AU30)^(1/7)-1) -> 0
B31: 27 | C31: 27 | D31: Coal-fired electricity | E31: =IF('2019'!E31=0,0,(AME_2030!E31/'2019'!E31)^(1/7)-1) -> -0.00035105714 | F31: =IF('2019'!F31=0,0,(AME_2030!F31/'2019'!F31)^(1/7)-1) -> -4.9633278e-05 | G31: =IF('2019'!G31=0,0,(AME_2030!G31/'2019'!G31)^(1/7)-1) -> -2.3353149e-09 | H31: =IF('2019'!H31=0,0,(AME_2030!H31/'2019'!H31)^(1/7)-1) -> 0.023945085 | I31: =IF('2019'!I31=0,0,(AME_2030!I31/'2019'!I31)^(1/7)-1) -> 4.4363113e-05 | J31: =IF('2019'!J31=0,0,(AME_2030!J31/'2019'!J31)^(1/7)-1) -> -0.016785347 | K31: =IF('2019 (Z)'!AW31=0,0,('AME_2030 (Z)'!AW31/'2019 (Z)'!AW31)^(1/7)-1) -> 0.0023015778 | L31: =K31 -> 0.0023015778 | M31: =IF('2019'!M31=0,0,(AME_2030!M31/'2019'!M31)^(1/7)-1) -> -0.0077535753 | N31: =IF('2019'!N31=0,0,(AME_2030!N31/'2019'!N31)^(1/7)-1) -> 0.035989456 | O31: =IF('2019'!O31=0,0,(AME_2030!O31/'2019'!O31)^(1/7)-1) -> -0.034875294 | P31: =IF('2019'!P31=0,0,(AME_2030!P31/'2019'!P31)^(1/7)-1) -> 1.1197482e-05 | Q31: =IF('2019'!Q31=0,0,(AME_2030!Q31/'2019'!Q31)^(1/7)-1) -> 1.6442185e-07 | R31: =IF('2019'!R31=0,0,(AME_2030!R31/'2019'!R31)^(1/7)-1) -> -2.0238261e-08 | S31: =T31 -> 6.174893e-07 | T31: =IF('2019'!T31=0,0,(AME_2030!T31/'2019'!T31)^(1/7)-1) -> 6.174893e-07 | U31: =IF('2019'!U31=0,0,(AME_2030!U31/'2019'!U31)^(1/7)-1) -> 0 | V31: =IF('2019'!V31=0,0,(AME_2030!V31/'2019'!V31)^(1/7)-1) -> 0 | W31: =IF('2019'!W31=0,0,(AME_2030!W31/'2019'!W31)^(1/7)-1) -> -0.00015945868 | X31: =IF('2019'!X31=0,0,(AME_2030!X31/'2019'!X31)^(1/7)-1) -> 4.9720396e-06 | Y31: =IF('2019'!Y31=0,0,(AME_2030!Y31/'2019'!Y31)^(1/7)-1) -> 0 | Z31: =IF('2019'!Z31=0,0,(AME_2030!Z31/'2019'!Z31)^(1/7)-1) -> -0.0011567048 | AA31: =IF('2019'!AA31=0,0,(AME_2030!AA31/'2019'!AA31)^(1/7)-1) -> 0.0013440083 | ... AU31: =IF('2019'!AU31=0,0,(AME_2030!AU31/'2019'!AU31)^(1/7)-1) -> 0
... B41: 37 | C41: 37 | D41: Other natural gas and heat | E41: =IF('2019'!E41=0,0,(AME_2030!E41/'2019'!E41)^(1/7)-1) -> 0.0058175231 | F41: =IF('2019'!F41=0,0,(AME_2030!F41/'2019'!F41)^(1/7)-1) -> 0 | G41: =IF('2019'!G41=0,0,(AME_2030!G41/'2019'!G41)^(1/7)-1) -> 0 | H41: =IF('2019'!H41=0,0,(AME_2030!H41/'2019'!H41)^(1/7)-1) -> 0 | I41: =IF('2019'!I41=0,0,(AME_2030!I41/'2019'!I41)^(1/7)-1) -> 0 | J41: =IF('2019'!J41=0,0,(AME_2030!J41/'2019'!J41)^(1/7)-1) -> 0.00083496361 | K41: =IF('2019 (Z)'!AW41=0,0,('AME_2030 (Z)'!AW41/'2019 (Z)'!AW41)^(1/7)-1) -> 0.002294432 | L41: =K41 -> 0.002294432 | M41: =IF('2019'!M41=0,0,(AME_2030!M41/'2019'!M41)^(1/7)-1) -> -0.044195543 | N41: =IF('2019'!N41=0,0,(AME_2030!N41/'2019'!N41)^(1/7)-1) -> 0 | O41: =IF('2019'!O41=0,0,(AME_2030!O41/'2019'!O41)^(1/7)-1) -> 0 | P41: =IF('2019'!P41=0,0,(AME_2030!P41/'2019'!P41)^(1/7)-1) -> -0.00026056813 | Q41: =IF('2019'!Q41=0,0,(AME_2030!Q41/'2019'!Q41)^(1/7)-1) -> 1.6442185e-07 | R41: =IF('2019'!R41=0,0,(AME_2030!R41/'2019'!R41)^(1/7)-1) -> 0 | S41: =T41 -> -2.5547003e-06 | T41: =IF('2019'!T41=0,0,(AME_2030!T41/'2019'!T41)^(1/7)-1) -> -2.5547003e-06 | U41: =IF('2019'!U41=0,0,(AME_2030!U41/'2019'!U41)^(1/7)-1) -> 0 | V41: =IF('2019'!V41=0,0,(AME_2030!V41/'2019'!V41)^(1/7)-1) -> 0 | W41: =IF('2019'!W41=0,0,(AME_2030!W41/'2019'!W41)^(1/7)-1) -> -0.00011502747 | X41: =IF('2019'!X41=0,0,(AME_2030!X41/'2019'!X41)^(1/7)-1) -> 5.8154676e-06 | Y41: =IF('2019'!Y41=0,0,(AME_2030!Y41/'2019'!Y41)^(1/7)-1) -> 0 | Z41: =IF('2019'!Z41=0,0,(AME_2030!Z41/'2019'!Z41)^(1/7)-1) -> 0.00021145239 | AA41: =IF('2019'!AA41=0,0,(AME_2030!AA41/'2019'!AA41)^(1/7)-1) -> 0.0012866364 | ... AU41: =IF('2019'!AU41=0,0,(AME_2030!AU41/'2019'!AU41)^(1/7)-1) -> 0
A42: RoW | B42: 01 | C42: 01 | D42: Products of agriculture, forestry and fishing | E42: =IF('2019'!E42=0,0,(AME_2030!E42/'2019'!E42)^(1/7)-1) -> -0.00087722449 | F42: =IF('2019'!F42=0,0,(AME_2030!F42/'2019'!F42)^(1/7)-1) -> 0.00085916156 | G42: =IF('2019'!G42=0,0,(AME_2030!G42/'2019'!G42)^(1/7)-1) -> -2.3353149e-09 | H42: =IF('2019'!H42=0,0,(AME_2030!H42/'2019'!H42)^(1/7)-1) -> -0.1011869 | I42: =IF('2019'!I42=0,0,(AME_2030!I42/'2019'!I42)^(1/7)-1) -> -0.0022953161 | J42: =IF('2019'!J42=0,0,(AME_2030!J42/'2019'!J42)^(1/7)-1) -> -0.035012061 | K42: =IF('2019 (Z)'!AW42=0,0,('AME_2030 (Z)'!AW42/'2019 (Z)'!AW42)^(1/7)-1) -> 0.0022948926 | L42: =K42 -> 0.0022948926 | M42: =IF('2019'!M42=0,0,(AME_2030!M42/'2019'!M42)^(1/7)-1) -> -0.0067675096 | N42: =IF('2019'!N42=0,0,(AME_2030!N42/'2019'!N42)^(1/7)-1) -> -0.012995894 | O42: =IF('2019'!O42=0,0,(AME_2030!O42/'2019'!O42)^(1/7)-1) -> -0.012727415 | P42: =IF('2019'!P42=0,0,(AME_2030!P42/'2019'!P42)^(1/7)-1) -> 0.0074647473 | Q42: =IF('2019'!Q42=0,0,(AME_2030!Q42/'2019'!Q42)^(1/7)-1) -> 0.005757743 | R42: =IF('2019'!R42=0,0,(AME_2030!R42/'2019'!R42)^(1/7)-1) -> -2.023826e-08 | S42: =T42 -> -1.5638509e-06 | T42: =IF('2019'!T42=0,0,(AME_2030!T42/'2019'!T42)^(1/7)-1) -> -1.5638509e-06 | U42: =IF('2019'!U42=0,0,(AME_2030!U42/'2019'!U42)^(1/7)-1) -> 2.9174227e-06 | V42: =IF('2019'!V42=0,0,(AME_2030!V42/'2019'!V42)^(1/7)-1) -> -2.6346634e-08 | W42: =IF('2019'!W42=0,0,(AME_2030!W42/'2019'!W42)^(1/7)-1) -> 0.0008072004 | X42: =IF('2019'!X42=0,0,(AME_2030!X42/'2019'!X42)^(1/7)-1) -> 0.00059004235 | Y42: =IF('2019'!Y42=0,0,(AME_2030!Y42/'2019'!Y42)^(1/7)-1) -> 0 | Z42: =IF('2019'!Z42=0,0,(AME_2030!Z42/'2019'!Z42)^(1/7)-1) -> -0.00092876849 | AA42: =IF('2019'!AA42=0,0,(AME_2030!AA42/'2019'!AA42)^(1/7)-1) -> 0.0013441505 | ... AU42: =IF('2019'!AU42=0,0,(AME_2030!AU42/'2019'!AU42)^(1/7)-1) -> 0.0029089933
B43: 02 | C43: 02 | D43: Food products and beverages | E43: =IF('2019'!E43=0,0,(AME_2030!E43/'2019'!E43)^(1/7)-1) -> -0.0018317718 | F43: =IF('2019'!F43=0,0,(AME_2030!F43/'2019'!F43)^(1/7)-1) -> 0.001128743 | G43: =IF('2019'!G43=0,0,(AME_2030!G43/'2019'!G43)^(1/7)-1) -> -2.3353149e-09 | H43: =IF('2019'!H43=0,0,(AME_2030!H43/'2019'!H43)^(1/7)-1) -> 0.0010774424 | I43: =IF('2019'!I43=0,0,(AME_2030!I43/'2019'!I43)^(1/7)-1) -> -0.001108193 | J43: =IF('2019'!J43=0,0,(AME_2030!J43/'2019'!J43)^(1/7)-1) -> 0.00035074739 | K43: =IF('2019 (Z)'!AW43=0,0,('AME_2030 (Z)'!AW43/'2019 (Z)'!AW43)^(1/7)-1) -> 0.0022937388 | L43: =K43 -> 0.0022937388 | M43: =IF('2019'!M43=0,0,(AME_2030!M43/'2019'!M43)^(1/7)-1) -> 0.0058485172 | N43: =IF('2019'!N43=0,0,(AME_2030!N43/'2019'!N43)^(1/7)-1) -> 0.016287863 | O43: =IF('2019'!O43=0,0,(AME_2030!O43/'2019'!O43)^(1/7)-1) -> -0.00019237709 | P43: =IF('2019'!P43=0,0,(AME_2030!P43/'2019'!P43)^(1/7)-1) -> 0.00040386208 | Q43: =IF('2019'!Q43=0,0,(AME_2030!Q43/'2019'!Q43)^(1/7)-1) -> 1.6442185e-07 | R43: =IF('2019'!R43=0,0,(AME_2030!R43/'2019'!R43)^(1/7)-1) -> -2.0238261e-08 | S43: =T43 -> -2.6744146e-07 | T43: =IF('2019'!T43=0,0,(AME_2030!T43/'2019'!T43)^(1/7)-1) -> -2.6744146e-07 | U43: =IF('2019'!U43=0,0,(AME_2030!U43/'2019'!U43)^(1/7)-1) -> 4.5250004e-06 | V43: =IF('2019'!V43=0,0,(AME_2030!V43/'2019'!V43)^(1/7)-1) -> -2.6346634e-08 | W43: =IF('2019'!W43=0,0,(AME_2030!W43/'2019'!W43)^(1/7)-1) -> 0.00032791247 | X43: =IF('2019'!X43=0,0,(AME_2030!X43/'2019'!X43)^(1/7)-1) -> 0.00072924186 | Y43: =IF('2019'!Y43=0,0,(AME_2030!Y43/'2019'!Y43)^(1/7)-1) -> 0.0024005377 | Z43: =IF('2019'!Z43=0,0,(AME_2030!Z43/'2019'!Z43)^(1/7)-1) -> -0.001146874 | AA43: =IF('2019'!AA43=0,0,(AME_2030!AA43/'2019'!AA43)^(1/7)-1) -> 0.0013440012 | ... AU43: =IF('2019'!AU43=0,0,(AME_2030!AU43/'2019'!AU43)^(1/7)-1) -> 0.0010130538
B44: 03 | C44: 03 | D44: Motor vehicles, trailers and semi-trailers | E44: =IF('2019'!E44=0,0,(AME_2030!E44/'2019'!E44)^(1/7)-1) -> -2.1603345e-05 | F44: =IF('2019'!F44=0,0,(AME_2030!F44/'2019'!F44)^(1/7)-1) -> 0.00021537228 | G44: =IF('2019'!G44=0,0,(AME_2030!G44/'2019'!G44)^(1/7)-1) -> -2.3353149e-09 | H44: =IF('2019'!H44=0,0,(AME_2030!H44/'2019'!H44)^(1/7)-1) -> 0.0039422071 | I44: =IF('2019'!I44=0,0,(AME_2030!I44/'2019'!I44)^(1/7)-1) -> 0.00057751563 | J44: =IF('2019'!J44=0,0,(AME_2030!J44/'2019'!J44)^(1/7)-1) -> 0.00052886237 | K44: =IF('2019 (Z)'!AW44=0,0,('AME_2030 (Z)'!AW44/'2019 (Z)'!AW44)^(1/7)-1) -> 0.0022946134 | L44: =K44 -> 0.0022946134 | M44: =IF('2019'!M44=0,0,(AME_2030!M44/'2019'!M44)^(1/7)-1) -> -0.0061169471 | N44: =IF('2019'!N44=0,0,(AME_2030!N44/'2019'!N44)^(1/7)-1) -> -0.0033981669 | O44: =IF('2019'!O44=0,0,(AME_2030!O44/'2019'!O44)^(1/7)-1) -> 0.0011073389 | P44: =IF('2019'!P44=0,0,(AME_2030!P44/'2019'!P44)^(1/7)-1) -> -0.00063867868 | Q44: =IF('2019'!Q44=0,0,(AME_2030!Q44/'2019'!Q44)^(1/7)-1) -> 1.6442185e-07 | R44: =IF('2019'!R44=0,0,(AME_2030!R44/'2019'!R44)^(1/7)-1) -> -2.0238261e-08 | S44: =T44 -> -2.5391862e-06 | T44: =IF('2019'!T44=0,0,(AME_2030!T44/'2019'!T44)^(1/7)-1) -> -2.5391862e-06 | U44: =IF('2019'!U44=0,0,(AME_2030!U44/'2019'!U44)^(1/7)-1) -> -1.3747556e-06 | V44: =IF('2019'!V44=0,0,(AME_2030!V44/'2019'!V44)^(1/7)-1) -> -2.6346634e-08 | W44: =IF('2019'!W44=0,0,(AME_2030!W44/'2019'!W44)^(1/7)-1) -> -4.2671023e-05 | X44: =IF('2019'!X44=0,0,(AME_2030!X44/'2019'!X44)^(1/7)-1) -> -1.5381913e-05 | Y44: =IF('2019'!Y44=0,0,(AME_2030!Y44/'2019'!Y44)^(1/7)-1) -> 0.0024005377 | Z44: =IF('2019'!Z44=0,0,(AME_2030!Z44/'2019'!Z44)^(1/7)-1) -> -0.0011001395 | AA44: =IF('2019'!AA44=0,0,(AME_2030!AA44/'2019'!AA44)^(1/7)-1) -> 0.0013438952 | ... AU44: =IF('2019'!AU44=0,0,(AME_2030!AU44/'2019'!AU44)^(1/7)-1) -> 4.0217545e-05
B45: 04 | C45: 04 | D45: Glass and glass products | E45: =IF('2019'!E45=0,0,(AME_2030!E45/'2019'!E45)^(1/7)-1) -> -0.029522876 | F45: =IF('2019'!F45=0,0,(AME_2030!F45/'2019'!F45)^(1/7)-1) -> -0.082970029 | G45: =IF('2019'!G45=0,0,(AME_2030!G45/'2019'!G45)^(1/7)-1) -> -0.072443685 | H45: =IF('2019'!H45=0,0,(AME_2030!H45/'2019'!H45)^(1/7)-1) -> -0.1062508 | I45: =IF('2019'!I45=0,0,(AME_2030!I45/'2019'!I45)^(1/7)-1) -> -0.0033842839 | J45: =IF('2019'!J45=0,0,(AME_2030!J45/'2019'!J45)^(1/7)-1) -> -0.056959649 | K45: =IF('2019 (Z)'!AW45=0,0,('AME_2030 (Z)'!AW45/'2019 (Z)'!AW45)^(1/7)-1) -> -0.081044005 | L45: =K45 -> -0.081044005 | M45: =IF('2019'!M45=0,0,(AME_2030!M45/'2019'!M45)^(1/7)-1) -> -0.016458398 | N45: =IF('2019'!N45=0,0,(AME_2030!N45/'2019'!N45)^(1/7)-1) -> -0.011467983 | O45: =IF('2019'!O45=0,0,(AME_2030!O45/'2019'!O45)^(1/7)-1) -> -0.012660495 | P45: =IF('2019'!P45=0,0,(AME_2030!P45/'2019'!P45)^(1/7)-1) -> 0.0080957042 | Q45: =IF('2019'!Q45=0,0,(AME_2030!Q45/'2019'!Q45)^(1/7)-1) -> -0.0021320527 | R45: =IF('2019'!R45=0,0,(AME_2030!R45/'2019'!R45)^(1/7)-1) -> -0.032620938 | S45: =T45 -> -0.020560691 | T45: =IF('2019'!T45=0,0,(AME_2030!T45/'2019'!T45)^(1/7)-1) -> -0.020560691 | U45: =IF('2019'!U45=0,0,(AME_2030!U45/'2019'!U45)^(1/7)-1) -> -0.031616485 | V45: =IF('2019'!V45=0,0,(AME_2030!V45/'2019'!V45)^(1/7)-1) -> -0.03109636 | W45: =IF('2019'!W45=0,0,(AME_2030!W45/'2019'!W45)^(1/7)-1) -> -0.017884852 | X45: =IF('2019'!X45=0,0,(AME_2030!X45/'2019'!X45)^(1/7)-1) -> -0.011078176 | Y45: =IF('2019'!Y45=0,0,(AME_2030!Y45/'2019'!Y45)^(1/7)-1) -> 0.0063899592 | Z45: =IF('2019'!Z45=0,0,(AME_2030!Z45/'2019'!Z45)^(1/7)-1) -> 0.010044516 | AA45: =IF('2019'!AA45=0,0,(AME_2030!AA45/'2019'!AA45)^(1/7)-1) -> -0.020088911 | ... AU45: =IF('2019'!AU45=0,0,(AME_2030!AU45/'2019'!AU45)^(1/7)-1) -> -0.02892517
B46: 05 | C46: 05 | D46: Ceramic products and building materials | E46: =IF('2019'!E46=0,0,(AME_2030!E46/'2019'!E46)^(1/7)-1) -> -0.0009737705 | F46: =IF('2019'!F46=0,0,(AME_2030!F46/'2019'!F46)^(1/7)-1) -> -4.514315e-05 | G46: =IF('2019'!G46=0,0,(AME_2030!G46/'2019'!G46)^(1/7)-1) -> -2.3353149e-09 | H46: =IF('2019'!H46=0,0,(AME_2030!H46/'2019'!H46)^(1/7)-1) -> 0.0089781169 | I46: =IF('2019'!I46=0,0,(AME_2030!I46/'2019'!I46)^(1/7)-1) -> 0.00034503333 | J46: =IF('2019'!J46=0,0,(AME_2030!J46/'2019'!J46)^(1/7)-1) -> 2.2900383e-05 | K46: =IF('2019 (Z)'!AW46=0,0,('AME_2030 (Z)'!AW46/'2019 (Z)'!AW46)^(1/7)-1) -> 0.0022979601 | L46: =K46 -> 0.0022979601 | M46: =IF('2019'!M46=0,0,(AME_2030!M46/'2019'!M46)^(1/7)-1) -> -0.0033816475 | N46: =IF('2019'!N46=0,0,(AME_2030!N46/'2019'!N46)^(1/7)-1) -> -0.0011035451 | O46: =IF('2019'!O46=0,0,(AME_2030!O46/'2019'!O46)^(1/7)-1) -> 0.002016216 | P46: =IF('2019'!P46=0,0,(AME_2030!P46/'2019'!P46)^(1/7)-1) -> -0.00035811735 | Q46: =IF('2019'!Q46=0,0,(AME_2030!Q46/'2019'!Q46)^(1/7)-1) -> -0.001118176 | R46: =IF('2019'!R46=0,0,(AME_2030!R46/'2019'!R46)^(1/7)-1) -> -2.0238261e-08 | S46: =T46 -> 2.4583866e-06 | T46: =IF('2019'!T46=0,0,(AME_2030!T46/'2019'!T46)^(1/7)-1) -> 2.4583866e-06 | U46: =IF('2019'!U46=0,0,(AME_2030!U46/'2019'!U46)^(1/7)-1) -> 8.036173e-08 | V46: =IF('2019'!V46=0,0,(AME_2030!V46/'2019'!V46)^(1/7)-1) -> -2.6346634e-08 | W46: =IF('2019'!W46=0,0,(AME_2030!W46/'2019'!W46)^(1/7)-1) -> -0.0033476897 | X46: =IF('2019'!X46=0,0,(AME_2030!X46/'2019'!X46)^(1/7)-1) -> -1.5341007e-06 | Y46: =IF('2019'!Y46=0,0,(AME_2030!Y46/'2019'!Y46)^(1/7)-1) -> 0.0024013584 | Z46: =IF('2019'!Z46=0,0,(AME_2030!Z46/'2019'!Z46)^(1/7)-1) -> -0.0010150442 | AA46: =IF('2019'!AA46=0,0,(AME_2030!AA46/'2019'!AA46)^(1/7)-1) -> 0.0013439507 | ... AU46: =IF('2019'!AU46=0,0,(AME_2030!AU46/'2019'!AU46)^(1/7)-1) -> 0.0028982496
B47: 06 | C47: 06 | D47: Articles of paper and paperboard | E47: =IF('2019'!E47=0,0,(AME_2030!E47/'2019'!E47)^(1/7)-1) -> 0.0063255173 | F47: =IF('2019'!F47=0,0,(AME_2030!F47/'2019'!F47)^(1/7)-1) -> 0.0067291598 | G47: =IF('2019'!G47=0,0,(AME_2030!G47/'2019'!G47)^(1/7)-1) -> -2.3353149e-09 | H47: =IF('2019'!H47=0,0,(AME_2030!H47/'2019'!H47)^(1/7)-1) -> 0.010091756 | I47: =IF('2019'!I47=0,0,(AME_2030!I47/'2019'!I47)^(1/7)-1) -> -0.00079182049 | J47: =IF('2019'!J47=0,0,(AME_2030!J47/'2019'!J47)^(1/7)-1) -> -0.00089750463 | K47: =IF('2019 (Z)'!AW47=0,0,('AME_2030 (Z)'!AW47/'2019 (Z)'!AW47)^(1/7)-1) -> 0.0084408109 | L47: =K47 -> 0.0084408109 | M47: =IF('2019'!M47=0,0,(AME_2030!M47/'2019'!M47)^(1/7)-1) -> 0.0052459547 | N47: =IF('2019'!N47=0,0,(AME_2030!N47/'2019'!N47)^(1/7)-1) -> -0.00086883295 | O47: =IF('2019'!O47=0,0,(AME_2030!O47/'2019'!O47)^(1/7)-1) -> -0.0034460814 | P47: =IF('2019'!P47=0,0,(AME_2030!P47/'2019'!P47)^(1/7)-1) -> 0.0059551679 | Q47: =IF('2019'!Q47=0,0,(AME_2030!Q47/'2019'!Q47)^(1/7)-1) -> 1.0155345e-07 | R47: =IF('2019'!R47=0,0,(AME_2030!R47/'2019'!R47)^(1/7)-1) -> -1.862928e-06 | S47: =T47 -> 2.6061444e-05 | T47: =IF('2019'!T47=0,0,(AME_2030!T47/'2019'!T47)^(1/7)-1) -> 2.6061444e-05 | U47: =IF('2019'!U47=0,0,(AME_2030!U47/'2019'!U47)^(1/7)-1) -> -2.7311267e-05 | V47: =IF('2019'!V47=0,0,(AME_2030!V47/'2019'!V47)^(1/7)-1) -> -2.6346634e-08 | W47: =IF('2019'!W47=0,0,(AME_2030!W47/'2019'!W47)^(1/7)-1) -> 0.0071480388 | X47: =IF('2019'!X47=0,0,(AME_2030!X47/'2019'!X47)^(1/7)-1) -> 0.0070931378 | Y47: =IF('2019'!Y47=0,0,(AME_2030!Y47/'2019'!Y47)^(1/7)-1) -> 0.0024086752 | Z47: =IF('2019'!Z47=0,0,(AME_2030!Z47/'2019'!Z47)^(1/7)-1) -> -0.0046000337 | AA47: =IF('2019'!AA47=0,0,(AME_2030!AA47/'2019'!AA47)^(1/7)-1) -> 0.00070479177 | ... AU47: =IF('2019'!AU47=0,0,(AME_2030!AU47/'2019'!AU47)^(1/7)-1) -> 0.0062593708
B48: 07 | C48: 07 | D48: Inorganic basic chemicals | E48: =IF('2019 (Z)'!E128=0,0,('AME_2030 (Z)'!E128/'2019 (Z)'!E128)^(1/7)-1) -> -0.011731308 | F48: =IF('2019 (Z)'!F128=0,0,('AME_2030 (Z)'!F128/'2019 (Z)'!F128)^(1/7)-1) -> -0.013999783 | G48: =IF('2019 (Z)'!G128=0,0,('AME_2030 (Z)'!G128/'2019 (Z)'!G128)^(1/7)-1) -> -0.014938797 | H48: =IF('2019 (Z)'!H128=0,0,('AME_2030 (Z)'!H128/'2019 (Z)'!H128)^(1/7)-1) -> 0.046868736 | I48: =IF('2019 (Z)'!I128=0,0,('AME_2030 (Z)'!I128/'2019 (Z)'!I128)^(1/7)-1) -> -0.016093478 | J48: =IF('2019 (Z)'!J128=0,0,('AME_2030 (Z)'!J128/'2019 (Z)'!J128)^(1/7)-1) -> -0.014182631 | K48: =IF('2019 (Z)'!K128=0,0,('AME_2030 (Z)'!K128/'2019 (Z)'!K128)^(1/7)-1) -> -0.01263623 | L48: =IF('2019 (Z)'!L128=0,0,('AME_2030 (Z)'!L128/'2019 (Z)'!L128)^(1/7)-1) -> -0.01263623 | ... R48: =IF('2019 (Z)'!R128=0,0,('AME_2030 (Z)'!R128/'2019 (Z)'!R128)^(1/7)-1) -> -0.014938775 | S48: =T48 -> -0.014605515 | T48: =IF('2019 (Z)'!T128=0,0,('AME_2030 (Z)'!T128/'2019 (Z)'!T128)^(1/7)-1) -> -0.014605515 | U48: =IF('2019 (Z)'!U128=0,0,('AME_2030 (Z)'!U128/'2019 (Z)'!U128)^(1/7)-1) -> -0.014966429 | V48: =IF('2019 (Z)'!V128=0,0,('AME_2030 (Z)'!V128/'2019 (Z)'!V128)^(1/7)-1) -> -0.014938821 | W48: =IF('2019 (Z)'!W128=0,0,('AME_2030 (Z)'!W128/'2019 (Z)'!W128)^(1/7)-1) -> -0.015876401 | X48: =IF('2019 (Z)'!X128=0,0,('AME_2030 (Z)'!X128/'2019 (Z)'!X128)^(1/7)-1) -> -0.014939972 | Y48: =IF('2019 (Z)'!Y128=0,0,('AME_2030 (Z)'!Y128/'2019 (Z)'!Y128)^(1/7)-1) -> -0.012552783 | Z48: =IF('2019 (Z)'!Z128=0,0,('AME_2030 (Z)'!Z128/'2019 (Z)'!Z128)^(1/7)-1) -> -0.015578932 | AA48: =IF('2019 (Z)'!AA128=0,0,('AME_2030 (Z)'!AA128/'2019 (Z)'!AA128)^(1/7)-1) -> -0.013581306 | ... AU48: =IF('2019 (Z)'!AU128=0,0,('AME_2030 (Z)'!AU128/'2019 (Z)'!AU128)^(1/7)-1) -> -0.0021774219
B49: 08 | C49: 08 | D49: Organic basic chemicals | E49: =E48 -> -0.011731308 | F49: =F48 -> -0.013999783 | G49: =G48 -> -0.014938797 | H49: =H48 -> 0.046868736 | I49: =I48 -> -0.016093478 | J49: =J48 -> -0.014182631 | K49: =K48 -> -0.01263623 | L49: =L48 -> -0.01263623 | ... R49: =R48 -> -0.014938775 | S49: =T49 -> -0.014605515 | T49: =T48 -> -0.014605515 | U49: =U48 -> -0.014966429 | V49: =V48 -> -0.014938821 | W49: =W48 -> -0.015876401 | X49: =X48 -> -0.014939972 | Y49: =Y48 -> -0.012552783 | Z49: =Z48 -> -0.015578932 | AA49: =AA48 -> -0.013581306 | ... AU49: =AU48 -> -0.0021774219
B50: 09 | C50: 09 | D50: Plastics products | E50: =IF('2019'!E50=0,0,(AME_2030!E50/'2019'!E50)^(1/7)-1) -> -0.022615432 | F50: =IF('2019'!F50=0,0,(AME_2030!F50/'2019'!F50)^(1/7)-1) -> -0.022665533 | G50: =IF('2019'!G50=0,0,(AME_2030!G50/'2019'!G50)^(1/7)-1) -> 0.11375894 | H50: =IF('2019'!H50=0,0,(AME_2030!H50/'2019'!H50)^(1/7)-1) -> 0.0061143098 | I50: =IF('2019'!I50=0,0,(AME_2030!I50/'2019'!I50)^(1/7)-1) -> -0.00026623045 | J50: =IF('2019'!J50=0,0,(AME_2030!J50/'2019'!J50)^(1/7)-1) -> 0.00038334538 | K50: =IF('2019 (Z)'!AW50=0,0,('AME_2030 (Z)'!AW50/'2019 (Z)'!AW50)^(1/7)-1) -> -0.020373608 | L50: =K50 -> -0.020373608 | M50: =IF('2019'!M50=0,0,(AME_2030!M50/'2019'!M50)^(1/7)-1) -> -0.0014313368 | N50: =IF('2019'!N50=0,0,(AME_2030!N50/'2019'!N50)^(1/7)-1) -> -0.0015736627 | O50: =IF('2019'!O50=0,0,(AME_2030!O50/'2019'!O50)^(1/7)-1) -> 0.0023815501 | P50: =IF('2019'!P50=0,0,(AME_2030!P50/'2019'!P50)^(1/7)-1) -> -0.01991505 | Q50: =IF('2019'!Q50=0,0,(AME_2030!Q50/'2019'!Q50)^(1/7)-1) -> 1.644255e-07 | R50: =IF('2019'!R50=0,0,(AME_2030!R50/'2019'!R50)^(1/7)-1) -> -2.0238261e-08 | S50: =T50 -> 2.6895534e-06 | T50: =IF('2019'!T50=0,0,(AME_2030!T50/'2019'!T50)^(1/7)-1) -> 2.6895534e-06 | U50: =IF('2019'!U50=0,0,(AME_2030!U50/'2019'!U50)^(1/7)-1) -> -1.722308e-05 | V50: =IF('2019'!V50=0,0,(AME_2030!V50/'2019'!V50)^(1/7)-1) -> -2.6346634e-08 | W50: =IF('2019'!W50=0,0,(AME_2030!W50/'2019'!W50)^(1/7)-1) -> -0.022716519 | X50: =IF('2019'!X50=0,0,(AME_2030!X50/'2019'!X50)^(1/7)-1) -> -0.022637299 | Y50: =IF('2019'!Y50=0,0,(AME_2030!Y50/'2019'!Y50)^(1/7)-1) -> 0.0024014444 | Z50: =IF('2019'!Z50=0,0,(AME_2030!Z50/'2019'!Z50)^(1/7)-1) -> -0.0011023534 | AA50: =IF('2019'!AA50=0,0,(AME_2030!AA50/'2019'!AA50)^(1/7)-1) -> 0.0013440991 | ... AU50: =IF('2019'!AU50=0,0,(AME_2030!AU50/'2019'!AU50)^(1/7)-1) -> 0.0085889666
B51: 10 | C51: 10 | D51: Basic iron and steel and of ferro-alloys | E51: =IF('2019'!E51=0,0,(AME_2030!E51/'2019'!E51)^(1/7)-1) -> -0.00063972087 | F51: =IF('2019'!F51=0,0,(AME_2030!F51/'2019'!F51)^(1/7)-1) -> -0.0079339065 | G51: =IF('2019'!G51=0,0,(AME_2030!G51/'2019'!G51)^(1/7)-1) -> -0.059648215 | H51: =IF('2019'!H51=0,0,(AME_2030!H51/'2019'!H51)^(1/7)-1) -> 0 | I51: =IF('2019'!I51=0,0,(AME_2030!I51/'2019'!I51)^(1/7)-1) -> -0.0076974963 | J51: =IF('2019'!J51=0,0,(AME_2030!J51/'2019'!J51)^(1/7)-1) -> -0.0078166681 | K51: =IF('2019 (Z)'!AW51=0,0,('AME_2030 (Z)'!AW51/'2019 (Z)'!AW51)^(1/7)-1) -> -0.0057444274 | L51: =K51 -> -0.0057444274 | M51: =IF('2019'!M51=0,0,(AME_2030!M51/'2019'!M51)^(1/7)-1) -> -0.0087538937 | N51: =IF('2019'!N51=0,0,(AME_2030!N51/'2019'!N51)^(1/7)-1) -> -0.0099434126 | O51: =IF('2019'!O51=0,0,(AME_2030!O51/'2019'!O51)^(1/7)-1) -> -0.0087567144 | P51: =IF('2019'!P51=0,0,(AME_2030!P51/'2019'!P51)^(1/7)-1) -> -0.0079333246 | Q51: =IF('2019'!Q51=0,0,(AME_2030!Q51/'2019'!Q51)^(1/7)-1) -> -0.0091877782 | R51: =IF('2019'!R51=0,0,(AME_2030!R51/'2019'!R51)^(1/7)-1) -> -0.008019234 | S51: =T51 -> -0.0078110572 | T51: =IF('2019'!T51=0,0,(AME_2030!T51/'2019'!T51)^(1/7)-1) -> -0.0078110572 | U51: =IF('2019'!U51=0,0,(AME_2030!U51/'2019'!U51)^(1/7)-1) -> -0.0057651213 | V51: =IF('2019'!V51=0,0,(AME_2030!V51/'2019'!V51)^(1/7)-1) -> -0.0065278892 | W51: =IF('2019'!W51=0,0,(AME_2030!W51/'2019'!W51)^(1/7)-1) -> -0.0082120392 | X51: =IF('2019'!X51=0,0,(AME_2030!X51/'2019'!X51)^(1/7)-1) -> 0.002762805 | Y51: =IF('2019'!Y51=0,0,(AME_2030!Y51/'2019'!Y51)^(1/7)-1) -> -0.0056384722 | Z51: =IF('2019'!Z51=0,0,(AME_2030!Z51/'2019'!Z51)^(1/7)-1) -> -0.0091282193 | AA51: =IF('2019'!AA51=0,0,(AME_2030!AA51/'2019'!AA51)^(1/7)-1) -> -0.0066865252 | ... AU51: =IF('2019'!AU51=0,0,(AME_2030!AU51/'2019'!AU51)^(1/7)-1) -> -0.011638371
B52: 11 | C52: 11 | D52: Non-ferrous metals | E52: =IF('2019'!E52=0,0,(AME_2030!E52/'2019'!E52)^(1/7)-1) -> 0.0067345018 | F52: =IF('2019'!F52=0,0,(AME_2030!F52/'2019'!F52)^(1/7)-1) -> -0.009503945 | G52: =IF('2019'!G52=0,0,(AME_2030!G52/'2019'!G52)^(1/7)-1) -> 0.041531586 | H52: =IF('2019'!H52=0,0,(AME_2030!H52/'2019'!H52)^(1/7)-1) -> 0.0048414353 | I52: =IF('2019'!I52=0,0,(AME_2030!I52/'2019'!I52)^(1/7)-1) -> -0.0041048804 | J52: =IF('2019'!J52=0,0,(AME_2030!J52/'2019'!J52)^(1/7)-1) -> -0.0076605082 | K52: =IF('2019 (Z)'!AW52=0,0,('AME_2030 (Z)'!AW52/'2019 (Z)'!AW52)^(1/7)-1) -> -0.0039710316 | L52: =K52 -> -0.0039710316 | M52: =IF('2019'!M52=0,0,(AME_2030!M52/'2019'!M52)^(1/7)-1) -> -0.0077560972 | N52: =IF('2019'!N52=0,0,(AME_2030!N52/'2019'!N52)^(1/7)-1) -> -0.00043013412 | O52: =IF('2019'!O52=0,0,(AME_2030!O52/'2019'!O52)^(1/7)-1) -> -0.00086985508 | P52: =IF('2019'!P52=0,0,(AME_2030!P52/'2019'!P52)^(1/7)-1) -> -0.0053882587 | Q52: =IF('2019'!Q52=0,0,(AME_2030!Q52/'2019'!Q52)^(1/7)-1) -> -0.0015283023 | R52: =IF('2019'!R52=0,0,(AME_2030!R52/'2019'!R52)^(1/7)-1) -> 0.0021367662 | S52: =T52 -> -0.0024649574 | T52: =IF('2019'!T52=0,0,(AME_2030!T52/'2019'!T52)^(1/7)-1) -> -0.0024649574 | U52: =IF('2019'!U52=0,0,(AME_2030!U52/'2019'!U52)^(1/7)-1) -> -1.7000601e-05 | V52: =IF('2019'!V52=0,0,(AME_2030!V52/'2019'!V52)^(1/7)-1) -> -0.00075812041 | W52: =IF('2019'!W52=0,0,(AME_2030!W52/'2019'!W52)^(1/7)-1) -> -0.0048337464 | X52: =IF('2019'!X52=0,0,(AME_2030!X52/'2019'!X52)^(1/7)-1) -> 0.00040921788 | Y52: =IF('2019'!Y52=0,0,(AME_2030!Y52/'2019'!Y52)^(1/7)-1) -> -0.00031584029 | Z52: =IF('2019'!Z52=0,0,(AME_2030!Z52/'2019'!Z52)^(1/7)-1) -> -0.010051881 | AA52: =IF('2019'!AA52=0,0,(AME_2030!AA52/'2019'!AA52)^(1/7)-1) -> -0.0049147749 | ... AU52: =IF('2019'!AU52=0,0,(AME_2030!AU52/'2019'!AU52)^(1/7)-1) -> 0.00071102062
B53: 12 | C53: 12 | D53: Other industries | E53: =IF('2019'!E53=0,0,(AME_2030!E53/'2019'!E53)^(1/7)-1) -> 0.0007189438 | F53: =IF('2019'!F53=0,0,(AME_2030!F53/'2019'!F53)^(1/7)-1) -> 0.00026217583 | G53: =IF('2019'!G53=0,0,(AME_2030!G53/'2019'!G53)^(1/7)-1) -> -2.3353151e-09 | H53: =IF('2019'!H53=0,0,(AME_2030!H53/'2019'!H53)^(1/7)-1) -> 0.010128988 | I53: =IF('2019'!I53=0,0,(AME_2030!I53/'2019'!I53)^(1/7)-1) -> -0.00057463251 | J53: =IF('2019'!J53=0,0,(AME_2030!J53/'2019'!J53)^(1/7)-1) -> -0.0006288572 | K53: =IF('2019 (Z)'!AW53=0,0,('AME_2030 (Z)'!AW53/'2019 (Z)'!AW53)^(1/7)-1) -> 0.0022965788 | L53: =K53 -> 0.0022965788 | M53: =IF('2019'!M53=0,0,(AME_2030!M53/'2019'!M53)^(1/7)-1) -> -0.0025308398 | N53: =IF('2019'!N53=0,0,(AME_2030!N53/'2019'!N53)^(1/7)-1) -> -0.014393918 | O53: =IF('2019'!O53=0,0,(AME_2030!O53/'2019'!O53)^(1/7)-1) -> -0.0037982093 | P53: =IF('2019'!P53=0,0,(AME_2030!P53/'2019'!P53)^(1/7)-1) -> -0.00043035707 | Q53: =IF('2019'!Q53=0,0,(AME_2030!Q53/'2019'!Q53)^(1/7)-1) -> 0.0023035609 | R53: =IF('2019'!R53=0,0,(AME_2030!R53/'2019'!R53)^(1/7)-1) -> -2.0238261e-08 | S53: =T53 -> 3.1026921e-05 | T53: =IF('2019'!T53=0,0,(AME_2030!T53/'2019'!T53)^(1/7)-1) -> 3.1026921e-05 | U53: =IF('2019'!U53=0,0,(AME_2030!U53/'2019'!U53)^(1/7)-1) -> -1.1270134e-05 | V53: =IF('2019'!V53=0,0,(AME_2030!V53/'2019'!V53)^(1/7)-1) -> -2.6346634e-08 | W53: =IF('2019'!W53=0,0,(AME_2030!W53/'2019'!W53)^(1/7)-1) -> -0.00028060883 | X53: =IF('2019'!X53=0,0,(AME_2030!X53/'2019'!X53)^(1/7)-1) -> -1.7266731e-05 | Y53: =IF('2019'!Y53=0,0,(AME_2030!Y53/'2019'!Y53)^(1/7)-1) -> 0.0024005377 | Z53: =IF('2019'!Z53=0,0,(AME_2030!Z53/'2019'!Z53)^(1/7)-1) -> -0.0011360147 | AA53: =IF('2019'!AA53=0,0,(AME_2030!AA53/'2019'!AA53)^(1/7)-1) -> 0.0013439981 | ... AU53: =IF('2019'!AU53=0,0,(AME_2030!AU53/'2019'!AU53)^(1/7)-1) -> 0.0002806414
B54: 13 | C54: 13 | D54: Construction of buildings and Civil engineering | E54: =IF('2019'!E54=0,0,(AME_2030!E54/'2019'!E54)^(1/7)-1) -> 6.9114146e-05 | F54: =IF('2019'!F54=0,0,(AME_2030!F54/'2019'!F54)^(1/7)-1) -> 0.00035058695 | G54: =IF('2019'!G54=0,0,(AME_2030!G54/'2019'!G54)^(1/7)-1) -> -2.3353148e-09 | H54: =IF('2019'!H54=0,0,(AME_2030!H54/'2019'!H54)^(1/7)-1) -> -0.056172338 | I54: =IF('2019'!I54=0,0,(AME_2030!I54/'2019'!I54)^(1/7)-1) -> -0.00065892375 | J54: =IF('2019'!J54=0,0,(AME_2030!J54/'2019'!J54)^(1/7)-1) -> -0.0020628613 | K54: =IF('2019 (Z)'!AW54=0,0,('AME_2030 (Z)'!AW54/'2019 (Z)'!AW54)^(1/7)-1) -> 0.0024068937 | L54: =K54 -> 0.0024068937 | M54: =IF('2019'!M54=0,0,(AME_2030!M54/'2019'!M54)^(1/7)-1) -> -0.00090744132 | N54: =IF('2019'!N54=0,0,(AME_2030!N54/'2019'!N54)^(1/7)-1) -> -0.016135464 | O54: =IF('2019'!O54=0,0,(AME_2030!O54/'2019'!O54)^(1/7)-1) -> -0.014629407 | P54: =IF('2019'!P54=0,0,(AME_2030!P54/'2019'!P54)^(1/7)-1) -> 0.0003484379 | Q54: =IF('2019'!Q54=0,0,(AME_2030!Q54/'2019'!Q54)^(1/7)-1) -> 1.6442185e-07 | R54: =IF('2019'!R54=0,0,(AME_2030!R54/'2019'!R54)^(1/7)-1) -> -2.0238261e-08 | S54: =T54 -> 1.4264148e-05 | T54: =IF('2019'!T54=0,0,(AME_2030!T54/'2019'!T54)^(1/7)-1) -> 1.4264148e-05 | U54: =IF('2019'!U54=0,0,(AME_2030!U54/'2019'!U54)^(1/7)-1) -> -1.7663715e-06 | V54: =IF('2019'!V54=0,0,(AME_2030!V54/'2019'!V54)^(1/7)-1) -> -2.6346634e-08 | W54: =IF('2019'!W54=0,0,(AME_2030!W54/'2019'!W54)^(1/7)-1) -> -0.00097204681 | X54: =IF('2019'!X54=0,0,(AME_2030!X54/'2019'!X54)^(1/7)-1) -> -7.368796e-06 | Y54: =IF('2019'!Y54=0,0,(AME_2030!Y54/'2019'!Y54)^(1/7)-1) -> 0.0024005377 | Z54: =IF('2019'!Z54=0,0,(AME_2030!Z54/'2019'!Z54)^(1/7)-1) -> -0.0011282121 | AA54: =IF('2019'!AA54=0,0,(AME_2030!AA54/'2019'!AA54)^(1/7)-1) -> 0.0013439804 | ... AU54: =IF('2019'!AU54=0,0,(AME_2030!AU54/'2019'!AU54)^(1/7)-1) -> 0.0034993926
B55: 14 | C55: 14 | D55: Rail transport (Passenger and Freight) | E55: =IF('2019'!E55=0,0,(AME_2030!E55/'2019'!E55)^(1/7)-1) -> -0.00051524016 | F55: =IF('2019'!F55=0,0,(AME_2030!F55/'2019'!F55)^(1/7)-1) -> 0.00012686026 | G55: =IF('2019'!G55=0,0,(AME_2030!G55/'2019'!G55)^(1/7)-1) -> -2.3353151e-09 | H55: =IF('2019'!H55=0,0,(AME_2030!H55/'2019'!H55)^(1/7)-1) -> 0.013548732 | I55: =IF('2019'!I55=0,0,(AME_2030!I55/'2019'!I55)^(1/7)-1) -> -0.00023028448 | J55: =IF('2019'!J55=0,0,(AME_2030!J55/'2019'!J55)^(1/7)-1) -> -0.0026457161 | K55: =IF('2019 (Z)'!AW55=0,0,('AME_2030 (Z)'!AW55/'2019 (Z)'!AW55)^(1/7)-1) -> 0.0023806609 | L55: =K55 -> 0.0023806609 | M55: =IF('2019'!M55=0,0,(AME_2030!M55/'2019'!M55)^(1/7)-1) -> 0.040548029 | N55: =IF('2019'!N55=0,0,(AME_2030!N55/'2019'!N55)^(1/7)-1) -> 0.0016562293 | O55: =IF('2019'!O55=0,0,(AME_2030!O55/'2019'!O55)^(1/7)-1) -> 0.0020462945 | P55: =IF('2019'!P55=0,0,(AME_2030!P55/'2019'!P55)^(1/7)-1) -> 0.00056339215 | Q55: =IF('2019'!Q55=0,0,(AME_2030!Q55/'2019'!Q55)^(1/7)-1) -> 1.6442185e-07 | R55: =IF('2019'!R55=0,0,(AME_2030!R55/'2019'!R55)^(1/7)-1) -> -2.0238261e-08 | S55: =T55 -> -4.5426888e-07 | T55: =IF('2019'!T55=0,0,(AME_2030!T55/'2019'!T55)^(1/7)-1) -> -4.5426888e-07 | U55: =IF('2019'!U55=0,0,(AME_2030!U55/'2019'!U55)^(1/7)-1) -> -9.0244093e-06 | V55: =IF('2019'!V55=0,0,(AME_2030!V55/'2019'!V55)^(1/7)-1) -> -2.6346634e-08 | W55: =IF('2019'!W55=0,0,(AME_2030!W55/'2019'!W55)^(1/7)-1) -> 0.00040135339 | X55: =IF('2019'!X55=0,0,(AME_2030!X55/'2019'!X55)^(1/7)-1) -> 1.5389754e-05 | Y55: =IF('2019'!Y55=0,0,(AME_2030!Y55/'2019'!Y55)^(1/7)-1) -> 0.0024005377 | Z55: =IF('2019'!Z55=0,0,(AME_2030!Z55/'2019'!Z55)^(1/7)-1) -> -0.0011328168 | AA55: =IF('2019'!AA55=0,0,(AME_2030!AA55/'2019'!AA55)^(1/7)-1) -> 0.0013439985 | ... AU55: =IF('2019'!AU55=0,0,(AME_2030!AU55/'2019'!AU55)^(1/7)-1) -> 0.00075553118
B56: 15 | C56: 15 | D56: Passenger transport by road | E56: =E57 -> -0.0010771241 | F56: =F57 -> 0.00021374092 | G56: =G57 -> -2.3353149e-09 | H56: =H57 -> 0.013592674 | I56: =I57 -> 0.00052112793 | J56: =J57 -> 7.0087855e-05 | K56: =K57 -> 0.0023040995 | L56: =L57 -> 0.0023040995 | ... R56: =R57 -> -2.0238261e-08 | S56: =T56 -> 1.5259158e-05 | T56: =T57 -> 1.5259158e-05 | U56: =U57 -> -8.9461905e-06 | V56: =V57 -> -2.6346634e-08 | W56: =W57 -> 0.00075538546 | X56: =X57 -> 3.857945e-06 | Y56: =Y57 -> 0.0024005377 | Z56: =Z57 -> -0.0011523828 | AA56: =AA57 -> 0.0013439671 | ... AU56: =AU57 -> 0.00073259674
B57: 16 | C57: 16 | D57: Freight transport by road and transport via pipeline | E57: =IF('2019'!E57=0,0,(AME_2030!E57/'2019'!E57)^(1/7)-1) -> -0.0010771241 | F57: =IF('2019'!F57=0,0,(AME_2030!F57/'2019'!F57)^(1/7)-1) -> 0.00021374092 | G57: =IF('2019'!G57=0,0,(AME_2030!G57/'2019'!G57)^(1/7)-1) -> -2.3353149e-09 | H57: =IF('2019'!H57=0,0,(AME_2030!H57/'2019'!H57)^(1/7)-1) -> 0.013592674 | I57: =IF('2019'!I57=0,0,(AME_2030!I57/'2019'!I57)^(1/7)-1) -> 0.00052112793 | J57: =IF('2019'!J57=0,0,(AME_2030!J57/'2019'!J57)^(1/7)-1) -> 7.0087855e-05 | K57: =IF('2019 (Z)'!AW57=0,0,('AME_2030 (Z)'!AW57/'2019 (Z)'!AW57)^(1/7)-1) -> 0.0023040995 | L57: =K57 -> 0.0023040995 | M57: =IF('2019'!M57=0,0,(AME_2030!M57/'2019'!M57)^(1/7)-1) -> -0.011379303 | N57: =IF('2019'!N57=0,0,(AME_2030!N57/'2019'!N57)^(1/7)-1) -> 0.0017187004 | O57: =IF('2019'!O57=0,0,(AME_2030!O57/'2019'!O57)^(1/7)-1) -> 0.001615764 | P57: =IF('2019'!P57=0,0,(AME_2030!P57/'2019'!P57)^(1/7)-1) -> -0.00045453044 | Q57: =IF('2019'!Q57=0,0,(AME_2030!Q57/'2019'!Q57)^(1/7)-1) -> 1.6442185e-07 | R57: =IF('2019'!R57=0,0,(AME_2030!R57/'2019'!R57)^(1/7)-1) -> -2.0238261e-08 | S57: =T57 -> 1.5259158e-05 | T57: =IF('2019'!T57=0,0,(AME_2030!T57/'2019'!T57)^(1/7)-1) -> 1.5259158e-05 | U57: =IF('2019'!U57=0,0,(AME_2030!U57/'2019'!U57)^(1/7)-1) -> -8.9461905e-06 | V57: =IF('2019'!V57=0,0,(AME_2030!V57/'2019'!V57)^(1/7)-1) -> -2.6346634e-08 | W57: =IF('2019'!W57=0,0,(AME_2030!W57/'2019'!W57)^(1/7)-1) -> 0.00075538546 | X57: =IF('2019'!X57=0,0,(AME_2030!X57/'2019'!X57)^(1/7)-1) -> 3.857945e-06 | Y57: =IF('2019'!Y57=0,0,(AME_2030!Y57/'2019'!Y57)^(1/7)-1) -> 0.0024005377 | Z57: =IF('2019'!Z57=0,0,(AME_2030!Z57/'2019'!Z57)^(1/7)-1) -> -0.0011523828 | AA57: =IF('2019'!AA57=0,0,(AME_2030!AA57/'2019'!AA57)^(1/7)-1) -> 0.0013439671 | ... AU57: =IF('2019'!AU57=0,0,(AME_2030!AU57/'2019'!AU57)^(1/7)-1) -> 0.00073259674
B58: 17 | C58: 17 | D58: Water transport | E58: =IF('2019'!E58=0,0,(AME_2030!E58/'2019'!E58)^(1/7)-1) -> -0.00054163458 | F58: =IF('2019'!F58=0,0,(AME_2030!F58/'2019'!F58)^(1/7)-1) -> 0.00011902572 | G58: =IF('2019'!G58=0,0,(AME_2030!G58/'2019'!G58)^(1/7)-1) -> -2.3353148e-09 | H58: =IF('2019'!H58=0,0,(AME_2030!H58/'2019'!H58)^(1/7)-1) -> 0.013548732 | I58: =IF('2019'!I58=0,0,(AME_2030!I58/'2019'!I58)^(1/7)-1) -> -0.00015678843 | J58: =IF('2019'!J58=0,0,(AME_2030!J58/'2019'!J58)^(1/7)-1) -> -0.0027229689 | K58: =IF('2019 (Z)'!AW58=0,0,('AME_2030 (Z)'!AW58/'2019 (Z)'!AW58)^(1/7)-1) -> 0.0036858866 | L58: =K58 -> 0.0036858866 | M58: =IF('2019'!M58=0,0,(AME_2030!M58/'2019'!M58)^(1/7)-1) -> 0.039629326 | N58: =IF('2019'!N58=0,0,(AME_2030!N58/'2019'!N58)^(1/7)-1) -> -0.0025640181 | O58: =IF('2019'!O58=0,0,(AME_2030!O58/'2019'!O58)^(1/7)-1) -> 0.0020405098 | P58: =IF('2019'!P58=0,0,(AME_2030!P58/'2019'!P58)^(1/7)-1) -> 0.00045695588 | Q58: =IF('2019'!Q58=0,0,(AME_2030!Q58/'2019'!Q58)^(1/7)-1) -> 1.6442185e-07 | R58: =IF('2019'!R58=0,0,(AME_2030!R58/'2019'!R58)^(1/7)-1) -> -2.0238261e-08 | S58: =T58 -> 7.9613318e-06 | T58: =IF('2019'!T58=0,0,(AME_2030!T58/'2019'!T58)^(1/7)-1) -> 7.9613318e-06 | U58: =IF('2019'!U58=0,0,(AME_2030!U58/'2019'!U58)^(1/7)-1) -> 7.6166751e-06 | V58: =IF('2019'!V58=0,0,(AME_2030!V58/'2019'!V58)^(1/7)-1) -> -2.6346634e-08 | W58: =IF('2019'!W58=0,0,(AME_2030!W58/'2019'!W58)^(1/7)-1) -> 0.0019321565 | X58: =IF('2019'!X58=0,0,(AME_2030!X58/'2019'!X58)^(1/7)-1) -> -4.8513034e-07 | Y58: =IF('2019'!Y58=0,0,(AME_2030!Y58/'2019'!Y58)^(1/7)-1) -> 0.0024005377 | Z58: =IF('2019'!Z58=0,0,(AME_2030!Z58/'2019'!Z58)^(1/7)-1) -> -0.00026825763 | AA58: =IF('2019'!AA58=0,0,(AME_2030!AA58/'2019'!AA58)^(1/7)-1) -> 0.0013440027 | ... AU58: =IF('2019'!AU58=0,0,(AME_2030!AU58/'2019'!AU58)^(1/7)-1) -> 0.00011519662
B59: 18 | C59: 18 | D59: Air transport | E59: =IF('2019'!E59=0,0,(AME_2030!E59/'2019'!E59)^(1/7)-1) -> -0.00075011278 | F59: =IF('2019'!F59=0,0,(AME_2030!F59/'2019'!F59)^(1/7)-1) -> 9.751166e-05 | G59: =IF('2019'!G59=0,0,(AME_2030!G59/'2019'!G59)^(1/7)-1) -> -2.3353151e-09 | H59: =IF('2019'!H59=0,0,(AME_2030!H59/'2019'!H59)^(1/7)-1) -> 0.014202559 | I59: =IF('2019'!I59=0,0,(AME_2030!I59/'2019'!I59)^(1/7)-1) -> -0.00023091193 | J59: =IF('2019'!J59=0,0,(AME_2030!J59/'2019'!J59)^(1/7)-1) -> -0.00024229524 | K59: =IF('2019 (Z)'!AW59=0,0,('AME_2030 (Z)'!AW59/'2019 (Z)'!AW59)^(1/7)-1) -> 0.0023066376 | L59: =K59 -> 0.0023066376 | M59: =IF('2019'!M59=0,0,(AME_2030!M59/'2019'!M59)^(1/7)-1) -> 0.0066546862 | N59: =IF('2019'!N59=0,0,(AME_2030!N59/'2019'!N59)^(1/7)-1) -> 0.00076628902 | O59: =IF('2019'!O59=0,0,(AME_2030!O59/'2019'!O59)^(1/7)-1) -> 0.0021432553 | P59: =IF('2019'!P59=0,0,(AME_2030!P59/'2019'!P59)^(1/7)-1) -> 0.00023549949 | Q59: =IF('2019'!Q59=0,0,(AME_2030!Q59/'2019'!Q59)^(1/7)-1) -> 1.6442185e-07 | R59: =IF('2019'!R59=0,0,(AME_2030!R59/'2019'!R59)^(1/7)-1) -> -2.0238261e-08 | S59: =T59 -> 3.8662049e-06 | T59: =IF('2019'!T59=0,0,(AME_2030!T59/'2019'!T59)^(1/7)-1) -> 3.8662049e-06 | U59: =IF('2019'!U59=0,0,(AME_2030!U59/'2019'!U59)^(1/7)-1) -> -9.5471429e-06 | V59: =IF('2019'!V59=0,0,(AME_2030!V59/'2019'!V59)^(1/7)-1) -> -2.6346634e-08 | W59: =IF('2019'!W59=0,0,(AME_2030!W59/'2019'!W59)^(1/7)-1) -> 0.00028405047 | X59: =IF('2019'!X59=0,0,(AME_2030!X59/'2019'!X59)^(1/7)-1) -> -6.2711259e-06 | Y59: =IF('2019'!Y59=0,0,(AME_2030!Y59/'2019'!Y59)^(1/7)-1) -> 0.0024005377 | Z59: =IF('2019'!Z59=0,0,(AME_2030!Z59/'2019'!Z59)^(1/7)-1) -> -0.0011527727 | AA59: =IF('2019'!AA59=0,0,(AME_2030!AA59/'2019'!AA59)^(1/7)-1) -> 0.0013439616 | ... AU59: =IF('2019'!AU59=0,0,(AME_2030!AU59/'2019'!AU59)^(1/7)-1) -> 0.00025859473
B60: 19 | C60: 19 | D60: Business services | E60: =IF('2019'!E60=0,0,(AME_2030!E60/'2019'!E60)^(1/7)-1) -> -0.00040504789 | F60: =IF('2019'!F60=0,0,(AME_2030!F60/'2019'!F60)^(1/7)-1) -> 0.00011741279 | G60: =IF('2019'!G60=0,0,(AME_2030!G60/'2019'!G60)^(1/7)-1) -> -5.9205503e-05 | H60: =IF('2019'!H60=0,0,(AME_2030!H60/'2019'!H60)^(1/7)-1) -> -0.039563172 | I60: =IF('2019'!I60=0,0,(AME_2030!I60/'2019'!I60)^(1/7)-1) -> -0.00059421712 | J60: =IF('2019'!J60=0,0,(AME_2030!J60/'2019'!J60)^(1/7)-1) -> -0.00023768869 | K60: =IF('2019 (Z)'!AW60=0,0,('AME_2030 (Z)'!AW60/'2019 (Z)'!AW60)^(1/7)-1) -> 0.0023005186 | L60: =K60 -> 0.0023005186 | M60: =IF('2019'!M60=0,0,(AME_2030!M60/'2019'!M60)^(1/7)-1) -> -0.0051599305 | N60: =IF('2019'!N60=0,0,(AME_2030!N60/'2019'!N60)^(1/7)-1) -> -0.013009447 | O60: =IF('2019'!O60=0,0,(AME_2030!O60/'2019'!O60)^(1/7)-1) -> -0.0076808382 | P60: =IF('2019'!P60=0,0,(AME_2030!P60/'2019'!P60)^(1/7)-1) -> -0.00025582473 | Q60: =IF('2019'!Q60=0,0,(AME_2030!Q60/'2019'!Q60)^(1/7)-1) -> -3.8642731e-05 | R60: =IF('2019'!R60=0,0,(AME_2030!R60/'2019'!R60)^(1/7)-1) -> -4.9697454e-05 | S60: =T60 -> -5.6687067e-06 | T60: =IF('2019'!T60=0,0,(AME_2030!T60/'2019'!T60)^(1/7)-1) -> -5.6687067e-06 | U60: =IF('2019'!U60=0,0,(AME_2030!U60/'2019'!U60)^(1/7)-1) -> -6.9118553e-05 | V60: =IF('2019'!V60=0,0,(AME_2030!V60/'2019'!V60)^(1/7)-1) -> -2.1137094e-05 | W60: =IF('2019'!W60=0,0,(AME_2030!W60/'2019'!W60)^(1/7)-1) -> -3.1546803e-05 | X60: =IF('2019'!X60=0,0,(AME_2030!X60/'2019'!X60)^(1/7)-1) -> -4.1943941e-05 | Y60: =IF('2019'!Y60=0,0,(AME_2030!Y60/'2019'!Y60)^(1/7)-1) -> 0.0023719627 | Z60: =IF('2019'!Z60=0,0,(AME_2030!Z60/'2019'!Z60)^(1/7)-1) -> -0.0012022348 | AA60: =IF('2019'!AA60=0,0,(AME_2030!AA60/'2019'!AA60)^(1/7)-1) -> 0.0013389486 | ... AU60: =IF('2019'!AU60=0,0,(AME_2030!AU60/'2019'!AU60)^(1/7)-1) -> 0.00067731754
B61: 20 | C61: 20 | D61: Public services | E61: =IF('2019'!E61=0,0,(AME_2030!E61/'2019'!E61)^(1/7)-1) -> 0.0010727372 | F61: =IF('2019'!F61=0,0,(AME_2030!F61/'2019'!F61)^(1/7)-1) -> 3.12215e-05 | G61: =IF('2019'!G61=0,0,(AME_2030!G61/'2019'!G61)^(1/7)-1) -> -2.3353157e-09 | H61: =IF('2019'!H61=0,0,(AME_2030!H61/'2019'!H61)^(1/7)-1) -> 0.014345032 | I61: =IF('2019'!I61=0,0,(AME_2030!I61/'2019'!I61)^(1/7)-1) -> -0.00039804721 | J61: =IF('2019'!J61=0,0,(AME_2030!J61/'2019'!J61)^(1/7)-1) -> -8.2373706e-05 | K61: =IF('2019 (Z)'!AW61=0,0,('AME_2030 (Z)'!AW61/'2019 (Z)'!AW61)^(1/7)-1) -> 0.0022940013 | L61: =K61 -> 0.0022940013 | M61: =IF('2019'!M61=0,0,(AME_2030!M61/'2019'!M61)^(1/7)-1) -> 9.0317342e-05 | N61: =IF('2019'!N61=0,0,(AME_2030!N61/'2019'!N61)^(1/7)-1) -> 0.00040942413 | O61: =IF('2019'!O61=0,0,(AME_2030!O61/'2019'!O61)^(1/7)-1) -> 0.0021642439 | P61: =IF('2019'!P61=0,0,(AME_2030!P61/'2019'!P61)^(1/7)-1) -> -0.00015796305 | Q61: =IF('2019'!Q61=0,0,(AME_2030!Q61/'2019'!Q61)^(1/7)-1) -> 1.6442185e-07 | R61: =IF('2019'!R61=0,0,(AME_2030!R61/'2019'!R61)^(1/7)-1) -> -2.023826e-08 | S61: =T61 -> 7.5953731e-06 | T61: =IF('2019'!T61=0,0,(AME_2030!T61/'2019'!T61)^(1/7)-1) -> 7.5953731e-06 | U61: =IF('2019'!U61=0,0,(AME_2030!U61/'2019'!U61)^(1/7)-1) -> 6.4584204e-06 | V61: =IF('2019'!V61=0,0,(AME_2030!V61/'2019'!V61)^(1/7)-1) -> -2.6346635e-08 | W61: =IF('2019'!W61=0,0,(AME_2030!W61/'2019'!W61)^(1/7)-1) -> -3.7751692e-05 | X61: =IF('2019'!X61=0,0,(AME_2030!X61/'2019'!X61)^(1/7)-1) -> -2.0862488e-06 | Y61: =IF('2019'!Y61=0,0,(AME_2030!Y61/'2019'!Y61)^(1/7)-1) -> 0.0024005377 | Z61: =IF('2019'!Z61=0,0,(AME_2030!Z61/'2019'!Z61)^(1/7)-1) -> -0.0010984169 | AA61: =IF('2019'!AA61=0,0,(AME_2030!AA61/'2019'!AA61)^(1/7)-1) -> 0.0013439214 | ... AU61: =IF('2019'!AU61=0,0,(AME_2030!AU61/'2019'!AU61)^(1/7)-1) -> 3.0381064e-05
B62: 21 | C62: 21 | D62: Coal | E62: =IF('2019'!E62=0,0,(AME_2030!E62/'2019'!E62)^(1/7)-1) -> -0.0013028215 | F62: =IF('2019'!F62=0,0,(AME_2030!F62/'2019'!F62)^(1/7)-1) -> -8.4619531e-05 | G62: =IF('2019'!G62=0,0,(AME_2030!G62/'2019'!G62)^(1/7)-1) -> -2.3353149e-09 | H62: =IF('2019'!H62=0,0,(AME_2030!H62/'2019'!H62)^(1/7)-1) -> -0.079640519 | I62: =IF('2019'!I62=0,0,(AME_2030!I62/'2019'!I62)^(1/7)-1) -> -0.0002904593 | J62: =IF('2019'!J62=0,0,(AME_2030!J62/'2019'!J62)^(1/7)-1) -> -0.01008798 | K62: =IF('2019 (Z)'!AW62=0,0,('AME_2030 (Z)'!AW62/'2019 (Z)'!AW62)^(1/7)-1) -> 0.0023848723 | L62: =K62 -> 0.0023848723 | M62: =IF('2019'!M62=0,0,(AME_2030!M62/'2019'!M62)^(1/7)-1) -> -0.042925259 | N62: =IF('2019'!N62=0,0,(AME_2030!N62/'2019'!N62)^(1/7)-1) -> -0.036709555 | O62: =IF('2019'!O62=0,0,(AME_2030!O62/'2019'!O62)^(1/7)-1) -> -0.0053084686 | P62: =IF('2019'!P62=0,0,(AME_2030!P62/'2019'!P62)^(1/7)-1) -> 0.00059187627 | Q62: =IF('2019'!Q62=0,0,(AME_2030!Q62/'2019'!Q62)^(1/7)-1) -> 1.6442185e-07 | R62: =IF('2019'!R62=0,0,(AME_2030!R62/'2019'!R62)^(1/7)-1) -> 0 | S62: =T62 -> -2.5547003e-06 | T62: =IF('2019'!T62=0,0,(AME_2030!T62/'2019'!T62)^(1/7)-1) -> -2.5547003e-06 | U62: =IF('2019'!U62=0,0,(AME_2030!U62/'2019'!U62)^(1/7)-1) -> 0 | V62: =IF('2019'!V62=0,0,(AME_2030!V62/'2019'!V62)^(1/7)-1) -> 0 | W62: =IF('2019'!W62=0,0,(AME_2030!W62/'2019'!W62)^(1/7)-1) -> -0.0044573577 | X62: =IF('2019'!X62=0,0,(AME_2030!X62/'2019'!X62)^(1/7)-1) -> -1.6339562e-05 | Y62: =IF('2019'!Y62=0,0,(AME_2030!Y62/'2019'!Y62)^(1/7)-1) -> 0.0024005377 | Z62: =IF('2019'!Z62=0,0,(AME_2030!Z62/'2019'!Z62)^(1/7)-1) -> 0.00027632048 | AA62: =IF('2019'!AA62=0,0,(AME_2030!AA62/'2019'!AA62)^(1/7)-1) -> 0.0013440112 | ... AU62: =IF('2019'!AU62=0,0,(AME_2030!AU62/'2019'!AU62)^(1/7)-1) -> -0.01101665
B63: 22 | C63: 22 | D63: Oil | E63: =IF('2019'!E63=0,0,(AME_2030!E63/'2019'!E63)^(1/7)-1) -> -0.00023439323 | F63: =IF('2019'!F63=0,0,(AME_2030!F63/'2019'!F63)^(1/7)-1) -> -6.4128387e-05 | G63: =IF('2019'!G63=0,0,(AME_2030!G63/'2019'!G63)^(1/7)-1) -> -2.3353151e-09 | H63: =IF('2019'!H63=0,0,(AME_2030!H63/'2019'!H63)^(1/7)-1) -> -0.059217334 | I63: =IF('2019'!I63=0,0,(AME_2030!I63/'2019'!I63)^(1/7)-1) -> -0.00052057266 | J63: =IF('2019'!J63=0,0,(AME_2030!J63/'2019'!J63)^(1/7)-1) -> -0.00024800517 | K63: =IF('2019 (Z)'!AW63=0,0,('AME_2030 (Z)'!AW63/'2019 (Z)'!AW63)^(1/7)-1) -> 0.0024041918 | L63: =K63 -> 0.0024041918 | M63: =IF('2019'!M63=0,0,(AME_2030!M63/'2019'!M63)^(1/7)-1) -> -0.043277778 | N63: =IF('2019'!N63=0,0,(AME_2030!N63/'2019'!N63)^(1/7)-1) -> -0.037028989 | O63: =IF('2019'!O63=0,0,(AME_2030!O63/'2019'!O63)^(1/7)-1) -> -0.0075149661 | P63: =IF('2019'!P63=0,0,(AME_2030!P63/'2019'!P63)^(1/7)-1) -> 0.00072477055 | Q63: =IF('2019'!Q63=0,0,(AME_2030!Q63/'2019'!Q63)^(1/7)-1) -> 1.6442185e-07 | R63: =IF('2019'!R63=0,0,(AME_2030!R63/'2019'!R63)^(1/7)-1) -> -2.0238261e-08 | S63: =T63 -> -2.5547003e-06 | T63: =IF('2019'!T63=0,0,(AME_2030!T63/'2019'!T63)^(1/7)-1) -> -2.5547003e-06 | U63: =IF('2019'!U63=0,0,(AME_2030!U63/'2019'!U63)^(1/7)-1) -> 1.2776593e-06 | V63: =IF('2019'!V63=0,0,(AME_2030!V63/'2019'!V63)^(1/7)-1) -> -2.6346634e-08 | W63: =IF('2019'!W63=0,0,(AME_2030!W63/'2019'!W63)^(1/7)-1) -> 0.00032593641 | X63: =IF('2019'!X63=0,0,(AME_2030!X63/'2019'!X63)^(1/7)-1) -> -1.2338391e-05 | Y63: =IF('2019'!Y63=0,0,(AME_2030!Y63/'2019'!Y63)^(1/7)-1) -> 0.0024005377 | Z63: =IF('2019'!Z63=0,0,(AME_2030!Z63/'2019'!Z63)^(1/7)-1) -> -0.0011576017 | AA63: =IF('2019'!AA63=0,0,(AME_2030!AA63/'2019'!AA63)^(1/7)-1) -> 0.001343873 | ... AU63: =IF('2019'!AU63=0,0,(AME_2030!AU63/'2019'!AU63)^(1/7)-1) -> -0.0011976279
B64: 23 | C64: 23 | D64: Biofuel | E64: =IF('2019'!E64=0,0,(AME_2030!E64/'2019'!E64)^(1/7)-1) -> 0 | F64: =IF('2019'!F64=0,0,(AME_2030!F64/'2019'!F64)^(1/7)-1) -> 0 | G64: =IF('2019'!G64=0,0,(AME_2030!G64/'2019'!G64)^(1/7)-1) -> 0 | H64: =IF('2019'!H64=0,0,(AME_2030!H64/'2019'!H64)^(1/7)-1) -> 0 | I64: =IF('2019'!I64=0,0,(AME_2030!I64/'2019'!I64)^(1/7)-1) -> 0 | J64: =IF('2019'!J64=0,0,(AME_2030!J64/'2019'!J64)^(1/7)-1) -> 0 | K64: =IF('2019 (Z)'!AW64=0,0,('AME_2030 (Z)'!AW64/'2019 (Z)'!AW64)^(1/7)-1) -> 0 | L64: =K64 -> 0 | M64: =IF('2019'!M64=0,0,(AME_2030!M64/'2019'!M64)^(1/7)-1) -> 0 | N64: =IF('2019'!N64=0,0,(AME_2030!N64/'2019'!N64)^(1/7)-1) -> 0 | O64: =IF('2019'!O64=0,0,(AME_2030!O64/'2019'!O64)^(1/7)-1) -> 0 | P64: =IF('2019'!P64=0,0,(AME_2030!P64/'2019'!P64)^(1/7)-1) -> 0 | Q64: =IF('2019'!Q64=0,0,(AME_2030!Q64/'2019'!Q64)^(1/7)-1) -> 0 | R64: =IF('2019'!R64=0,0,(AME_2030!R64/'2019'!R64)^(1/7)-1) -> 0 | S64: =T64 -> 0 | T64: =IF('2019'!T64=0,0,(AME_2030!T64/'2019'!T64)^(1/7)-1) -> 0 | U64: =IF('2019'!U64=0,0,(AME_2030!U64/'2019'!U64)^(1/7)-1) -> 0 | V64: =IF('2019'!V64=0,0,(AME_2030!V64/'2019'!V64)^(1/7)-1) -> 0 | W64: =IF('2019'!W64=0,0,(AME_2030!W64/'2019'!W64)^(1/7)-1) -> 0 | X64: =IF('2019'!X64=0,0,(AME_2030!X64/'2019'!X64)^(1/7)-1) -> 0 | Y64: =IF('2019'!Y64=0,0,(AME_2030!Y64/'2019'!Y64)^(1/7)-1) -> 0 | Z64: =IF('2019'!Z64=0,0,(AME_2030!Z64/'2019'!Z64)^(1/7)-1) -> 0 | AA64: =IF('2019'!AA64=0,0,(AME_2030!AA64/'2019'!AA64)^(1/7)-1) -> 0 | ... AU64: =IF('2019'!AU64=0,0,(AME_2030!AU64/'2019'!AU64)^(1/7)-1) -> 0
B65: 24 | C65: 24 | D65: Electricity by nuclear | E65: =IF('2019'!E65=0,0,(AME_2030!E65/'2019'!E65)^(1/7)-1) -> -0.00031342099 | F65: =IF('2019'!F65=0,0,(AME_2030!F65/'2019'!F65)^(1/7)-1) -> -1.2065627e-05 | G65: =IF('2019'!G65=0,0,(AME_2030!G65/'2019'!G65)^(1/7)-1) -> -2.3353123e-09 | H65: =IF('2019'!H65=0,0,(AME_2030!H65/'2019'!H65)^(1/7)-1) -> 0.024059787 | I65: =IF('2019'!I65=0,0,(AME_2030!I65/'2019'!I65)^(1/7)-1) -> 4.3648771e-05 | J65: =IF('2019'!J65=0,0,(AME_2030!J65/'2019'!J65)^(1/7)-1) -> -0.0160483 | K65: =IF('2019 (Z)'!AW65=0,0,('AME_2030 (Z)'!AW65/'2019 (Z)'!AW65)^(1/7)-1) -> 0.0023022627 | L65: =K65 -> 0.0023022627 | M65: =IF('2019'!M65=0,0,(AME_2030!M65/'2019'!M65)^(1/7)-1) -> -0.0065036382 | N65: =IF('2019'!N65=0,0,(AME_2030!N65/'2019'!N65)^(1/7)-1) -> 0.036016647 | O65: =IF('2019'!O65=0,0,(AME_2030!O65/'2019'!O65)^(1/7)-1) -> -0.034847935 | P65: =IF('2019'!P65=0,0,(AME_2030!P65/'2019'!P65)^(1/7)-1) -> -1.6337378e-05 | Q65: =IF('2019'!Q65=0,0,(AME_2030!Q65/'2019'!Q65)^(1/7)-1) -> 1.6442185e-07 | R65: =IF('2019'!R65=0,0,(AME_2030!R65/'2019'!R65)^(1/7)-1) -> -2.0238259e-08 | S65: =T65 -> 6.2189186e-07 | T65: =IF('2019'!T65=0,0,(AME_2030!T65/'2019'!T65)^(1/7)-1) -> 6.2189186e-07 | U65: =IF('2019'!U65=0,0,(AME_2030!U65/'2019'!U65)^(1/7)-1) -> 0 | V65: =IF('2019'!V65=0,0,(AME_2030!V65/'2019'!V65)^(1/7)-1) -> 0 | W65: =IF('2019'!W65=0,0,(AME_2030!W65/'2019'!W65)^(1/7)-1) -> 0.00010884494 | X65: =IF('2019'!X65=0,0,(AME_2030!X65/'2019'!X65)^(1/7)-1) -> 2.9453412e-06 | Y65: =IF('2019'!Y65=0,0,(AME_2030!Y65/'2019'!Y65)^(1/7)-1) -> 0 | Z65: =IF('2019'!Z65=0,0,(AME_2030!Z65/'2019'!Z65)^(1/7)-1) -> -0.0011573596 | AA65: =IF('2019'!AA65=0,0,(AME_2030!AA65/'2019'!AA65)^(1/7)-1) -> 0.0013440084 | ... AU65: =IF('2019'!AU65=0,0,(AME_2030!AU65/'2019'!AU65)^(1/7)-1) -> 0.00089723286
B66: 25 | C66: 25 | D66: Electricity by petroleum | E66: =IF('2019'!E66=0,0,(AME_2030!E66/'2019'!E66)^(1/7)-1) -> -0.00031122067 | F66: =IF('2019'!F66=0,0,(AME_2030!F66/'2019'!F66)^(1/7)-1) -> -1.2304156e-05 | G66: =IF('2019'!G66=0,0,(AME_2030!G66/'2019'!G66)^(1/7)-1) -> -2.3353149e-09 | H66: =IF('2019'!H66=0,0,(AME_2030!H66/'2019'!H66)^(1/7)-1) -> 0.023963905 | I66: =IF('2019'!I66=0,0,(AME_2030!I66/'2019'!I66)^(1/7)-1) -> 4.4246249e-05 | J66: =IF('2019'!J66=0,0,(AME_2030!J66/'2019'!J66)^(1/7)-1) -> -0.016037021 | K66: =IF('2019 (Z)'!AW66=0,0,('AME_2030 (Z)'!AW66/'2019 (Z)'!AW66)^(1/7)-1) -> 0.0023015915 | L66: =K66 -> 0.0023015915 | M66: =IF('2019'!M66=0,0,(AME_2030!M66/'2019'!M66)^(1/7)-1) -> -0.0065384521 | N66: =IF('2019'!N66=0,0,(AME_2030!N66/'2019'!N66)^(1/7)-1) -> 0.036006416 | O66: =IF('2019'!O66=0,0,(AME_2030!O66/'2019'!O66)^(1/7)-1) -> -0.050947051 | P66: =IF('2019'!P66=0,0,(AME_2030!P66/'2019'!P66)^(1/7)-1) -> -9.3164347e-06 | Q66: =IF('2019'!Q66=0,0,(AME_2030!Q66/'2019'!Q66)^(1/7)-1) -> 1.6442185e-07 | R66: =IF('2019'!R66=0,0,(AME_2030!R66/'2019'!R66)^(1/7)-1) -> -2.0238261e-08 | S66: =T66 -> 6.1805371e-07 | T66: =IF('2019'!T66=0,0,(AME_2030!T66/'2019'!T66)^(1/7)-1) -> 6.1805371e-07 | U66: =IF('2019'!U66=0,0,(AME_2030!U66/'2019'!U66)^(1/7)-1) -> 0 | V66: =IF('2019'!V66=0,0,(AME_2030!V66/'2019'!V66)^(1/7)-1) -> 0 | W66: =IF('2019'!W66=0,0,(AME_2030!W66/'2019'!W66)^(1/7)-1) -> 0.00024425622 | X66: =IF('2019'!X66=0,0,(AME_2030!X66/'2019'!X66)^(1/7)-1) -> 5.9516005e-05 | Y66: =IF('2019'!Y66=0,0,(AME_2030!Y66/'2019'!Y66)^(1/7)-1) -> 0 | Z66: =IF('2019'!Z66=0,0,(AME_2030!Z66/'2019'!Z66)^(1/7)-1) -> -0.0011578663 | AA66: =IF('2019'!AA66=0,0,(AME_2030!AA66/'2019'!AA66)^(1/7)-1) -> 0.0013440084 | ... AU66: =IF('2019'!AU66=0,0,(AME_2030!AU66/'2019'!AU66)^(1/7)-1) -> -0.01708125
B67: 26 | C67: 26 | D67: Electricity by gas | E67: =IF('2019'!E67=0,0,(AME_2030!E67/'2019'!E67)^(1/7)-1) -> -0.0003134264 | F67: =IF('2019'!F67=0,0,(AME_2030!F67/'2019'!F67)^(1/7)-1) -> -1.2054199e-05 | G67: =IF('2019'!G67=0,0,(AME_2030!G67/'2019'!G67)^(1/7)-1) -> -2.3353149e-09 | H67: =IF('2019'!H67=0,0,(AME_2030!H67/'2019'!H67)^(1/7)-1) -> 0.024043467 | I67: =IF('2019'!I67=0,0,(AME_2030!I67/'2019'!I67)^(1/7)-1) -> 4.3750642e-05 | J67: =IF('2019'!J67=0,0,(AME_2030!J67/'2019'!J67)^(1/7)-1) -> -0.016046377 | K67: =IF('2019 (Z)'!AW67=0,0,('AME_2030 (Z)'!AW67/'2019 (Z)'!AW67)^(1/7)-1) -> 0.0023016664 | L67: =K67 -> 0.0023016664 | M67: =IF('2019'!M67=0,0,(AME_2030!M67/'2019'!M67)^(1/7)-1) -> -0.0065095779 | N67: =IF('2019'!N67=0,0,(AME_2030!N67/'2019'!N67)^(1/7)-1) -> 0.036012788 | O67: =IF('2019'!O67=0,0,(AME_2030!O67/'2019'!O67)^(1/7)-1) -> 0.0018817144 | P67: =IF('2019'!P67=0,0,(AME_2030!P67/'2019'!P67)^(1/7)-1) -> -9.1675969e-06 | Q67: =IF('2019'!Q67=0,0,(AME_2030!Q67/'2019'!Q67)^(1/7)-1) -> 1.6442185e-07 | R67: =IF('2019'!R67=0,0,(AME_2030!R67/'2019'!R67)^(1/7)-1) -> -2.0238261e-08 | S67: =T67 -> 6.2123709e-07 | T67: =IF('2019'!T67=0,0,(AME_2030!T67/'2019'!T67)^(1/7)-1) -> 6.2123709e-07 | U67: =IF('2019'!U67=0,0,(AME_2030!U67/'2019'!U67)^(1/7)-1) -> 0 | V67: =IF('2019'!V67=0,0,(AME_2030!V67/'2019'!V67)^(1/7)-1) -> 0 | W67: =IF('2019'!W67=0,0,(AME_2030!W67/'2019'!W67)^(1/7)-1) -> 0.00010833178 | X67: =IF('2019'!X67=0,0,(AME_2030!X67/'2019'!X67)^(1/7)-1) -> 2.944293e-06 | Y67: =IF('2019'!Y67=0,0,(AME_2030!Y67/'2019'!Y67)^(1/7)-1) -> 0 | Z67: =IF('2019'!Z67=0,0,(AME_2030!Z67/'2019'!Z67)^(1/7)-1) -> -0.0011573633 | AA67: =IF('2019'!AA67=0,0,(AME_2030!AA67/'2019'!AA67)^(1/7)-1) -> 0.0013440084 | ... AU67: =IF('2019'!AU67=0,0,(AME_2030!AU67/'2019'!AU67)^(1/7)-1) -> 0.00015445291
B68: 27 | C68: 27 | D68: Coal-fired electricity | E68: =IF('2019'!E68=0,0,(AME_2030!E68/'2019'!E68)^(1/7)-1) -> -0.00031345882 | F68: =IF('2019'!F68=0,0,(AME_2030!F68/'2019'!F68)^(1/7)-1) -> -1.2049716e-05 | G68: =IF('2019'!G68=0,0,(AME_2030!G68/'2019'!G68)^(1/7)-1) -> -2.3353149e-09 | H68: =IF('2019'!H68=0,0,(AME_2030!H68/'2019'!H68)^(1/7)-1) -> 0.023945085 | I68: =IF('2019'!I68=0,0,(AME_2030!I68/'2019'!I68)^(1/7)-1) -> 4.4363113e-05 | J68: =IF('2019'!J68=0,0,(AME_2030!J68/'2019'!J68)^(1/7)-1) -> -0.016034814 | K68: =IF('2019 (Z)'!AW68=0,0,('AME_2030 (Z)'!AW68/'2019 (Z)'!AW68)^(1/7)-1) -> 0.0023015738 | L68: =K68 -> 0.0023015738 | M68: =IF('2019'!M68=0,0,(AME_2030!M68/'2019'!M68)^(1/7)-1) -> -0.0065452545 | N68: =IF('2019'!N68=0,0,(AME_2030!N68/'2019'!N68)^(1/7)-1) -> 0.035989577 | O68: =IF('2019'!O68=0,0,(AME_2030!O68/'2019'!O68)^(1/7)-1) -> -0.050880779 | P68: =IF('2019'!P68=0,0,(AME_2030!P68/'2019'!P68)^(1/7)-1) -> -9.0505571e-06 | Q68: =IF('2019'!Q68=0,0,(AME_2030!Q68/'2019'!Q68)^(1/7)-1) -> 1.6442185e-07 | R68: =IF('2019'!R68=0,0,(AME_2030!R68/'2019'!R68)^(1/7)-1) -> -2.0238261e-08 | S68: =T68 -> 6.1730372e-07 | T68: =IF('2019'!T68=0,0,(AME_2030!T68/'2019'!T68)^(1/7)-1) -> 6.1730372e-07 | U68: =IF('2019'!U68=0,0,(AME_2030!U68/'2019'!U68)^(1/7)-1) -> 0 | V68: =IF('2019'!V68=0,0,(AME_2030!V68/'2019'!V68)^(1/7)-1) -> 0 | W68: =IF('2019'!W68=0,0,(AME_2030!W68/'2019'!W68)^(1/7)-1) -> 0.00010737507 | X68: =IF('2019'!X68=0,0,(AME_2030!X68/'2019'!X68)^(1/7)-1) -> 2.9379966e-06 | Y68: =IF('2019'!Y68=0,0,(AME_2030!Y68/'2019'!Y68)^(1/7)-1) -> 0 | Z68: =IF('2019'!Z68=0,0,(AME_2030!Z68/'2019'!Z68)^(1/7)-1) -> -0.0011573725 | AA68: =IF('2019'!AA68=0,0,(AME_2030!AA68/'2019'!AA68)^(1/7)-1) -> 0.0013440084 | ... AU68: =IF('2019'!AU68=0,0,(AME_2030!AU68/'2019'!AU68)^(1/7)-1) -> -0.031687289
... B78: 37 | C78: 37 | D78: Other natural gas and heat | E78: =IF('2019'!E78=0,0,(AME_2030!E78/'2019'!E78)^(1/7)-1) -> 0 | F78: =IF('2019'!F78=0,0,(AME_2030!F78/'2019'!F78)^(1/7)-1) -> 0 | G78: =IF('2019'!G78=0,0,(AME_2030!G78/'2019'!G78)^(1/7)-1) -> 0 | H78: =IF('2019'!H78=0,0,(AME_2030!H78/'2019'!H78)^(1/7)-1) -> 0 | I78: =IF('2019'!I78=0,0,(AME_2030!I78/'2019'!I78)^(1/7)-1) -> 0 | J78: =IF('2019'!J78=0,0,(AME_2030!J78/'2019'!J78)^(1/7)-1) -> 0 | K78: =IF('2019 (Z)'!AW78=0,0,('AME_2030 (Z)'!AW78/'2019 (Z)'!AW78)^(1/7)-1) -> 0 | L78: =K78 -> 0 | M78: =IF('2019'!M78=0,0,(AME_2030!M78/'2019'!M78)^(1/7)-1) -> 0 | N78: =IF('2019'!N78=0,0,(AME_2030!N78/'2019'!N78)^(1/7)-1) -> 0 | O78: =IF('2019'!O78=0,0,(AME_2030!O78/'2019'!O78)^(1/7)-1) -> 0 | P78: =IF('2019'!P78=0,0,(AME_2030!P78/'2019'!P78)^(1/7)-1) -> 0 | Q78: =IF('2019'!Q78=0,0,(AME_2030!Q78/'2019'!Q78)^(1/7)-1) -> 0 | R78: =IF('2019'!R78=0,0,(AME_2030!R78/'2019'!R78)^(1/7)-1) -> 0 | S78: =T78 -> 0 | T78: =IF('2019'!T78=0,0,(AME_2030!T78/'2019'!T78)^(1/7)-1) -> 0 | U78: =IF('2019'!U78=0,0,(AME_2030!U78/'2019'!U78)^(1/7)-1) -> 0 | V78: =IF('2019'!V78=0,0,(AME_2030!V78/'2019'!V78)^(1/7)-1) -> 0 | W78: =IF('2019'!W78=0,0,(AME_2030!W78/'2019'!W78)^(1/7)-1) -> 0 | X78: =IF('2019'!X78=0,0,(AME_2030!X78/'2019'!X78)^(1/7)-1) -> 0 | Y78: =IF('2019'!Y78=0,0,(AME_2030!Y78/'2019'!Y78)^(1/7)-1) -> 0 | Z78: =IF('2019'!Z78=0,0,(AME_2030!Z78/'2019'!Z78)^(1/7)-1) -> 0 | AA78: =IF('2019'!AA78=0,0,(AME_2030!AA78/'2019'!AA78)^(1/7)-1) -> 0 | ... AU78: =IF('2019'!AU78=0,0,(AME_2030!AU78/'2019'!AU78)^(1/7)-1) -> 0
A79: Total | B79: 01 | C79: 01 | D79: Products of agriculture, forestry and fishing | E79: =IF('2019'!E79=0,0,(AME_2030!E79/'2019'!E79)^(1/7)-1) -> 0.00087470775 | F79: =IF('2019'!F79=0,0,(AME_2030!F79/'2019'!F79)^(1/7)-1) -> -4.081706e-05 | G79: =IF('2019'!G79=0,0,(AME_2030!G79/'2019'!G79)^(1/7)-1) -> -2.3353149e-09 | H79: =IF('2019'!H79=0,0,(AME_2030!H79/'2019'!H79)^(1/7)-1) -> -0.1011869 | I79: =IF('2019'!I79=0,0,(AME_2030!I79/'2019'!I79)^(1/7)-1) -> -0.0022953161 | J79: =IF('2019'!J79=0,0,(AME_2030!J79/'2019'!J79)^(1/7)-1) -> -0.0127139 | K79: =IF('2019 (Z)'!AW79=0,0,('AME_2030 (Z)'!AW79/'2019 (Z)'!AW79)^(1/7)-1) -> 0.0022948869 | L79: =K79 -> 0.0022948869 | M79: =IF('2019'!M79=0,0,(AME_2030!M79/'2019'!M79)^(1/7)-1) -> -0.004724569 | N79: =IF('2019'!N79=0,0,(AME_2030!N79/'2019'!N79)^(1/7)-1) -> -0.012995894 | O79: =IF('2019'!O79=0,0,(AME_2030!O79/'2019'!O79)^(1/7)-1) -> -0.012727415 | P79: =IF('2019'!P79=0,0,(AME_2030!P79/'2019'!P79)^(1/7)-1) -> 0.0091877122 | Q79: =IF('2019'!Q79=0,0,(AME_2030!Q79/'2019'!Q79)^(1/7)-1) -> 0.017203845 | R79: =IF('2019'!R79=0,0,(AME_2030!R79/'2019'!R79)^(1/7)-1) -> -2.0238261e-08 | S79: =T79 -> -1.5313969e-06 | T79: =IF('2019'!T79=0,0,(AME_2030!T79/'2019'!T79)^(1/7)-1) -> -1.5313969e-06 | U79: =IF('2019'!U79=0,0,(AME_2030!U79/'2019'!U79)^(1/7)-1) -> 2.9174227e-06 | V79: =IF('2019'!V79=0,0,(AME_2030!V79/'2019'!V79)^(1/7)-1) -> -2.6346634e-08 | W79: =IF('2019'!W79=0,0,(AME_2030!W79/'2019'!W79)^(1/7)-1) -> 0.0015249348 | X79: =IF('2019'!X79=0,0,(AME_2030!X79/'2019'!X79)^(1/7)-1) -> 0.0012749904 | Y79: =IF('2019'!Y79=0,0,(AME_2030!Y79/'2019'!Y79)^(1/7)-1) -> 0 | Z79: =IF('2019'!Z79=0,0,(AME_2030!Z79/'2019'!Z79)^(1/7)-1) -> 0.00014922228 | AA79: =IF('2019'!AA79=0,0,(AME_2030!AA79/'2019'!AA79)^(1/7)-1) -> 0.0013440296 | ... AU79: =IF('2019'!AU79=0,0,(AME_2030!AU79/'2019'!AU79)^(1/7)-1) -> 0.0029089933
B80: 02 | C80: 02 | D80: Food products and beverages | E80: =IF('2019'!E80=0,0,(AME_2030!E80/'2019'!E80)^(1/7)-1) -> -0.0018020316 | F80: =IF('2019'!F80=0,0,(AME_2030!F80/'2019'!F80)^(1/7)-1) -> 0.00073163866 | G80: =IF('2019'!G80=0,0,(AME_2030!G80/'2019'!G80)^(1/7)-1) -> -2.3353149e-09 | H80: =IF('2019'!H80=0,0,(AME_2030!H80/'2019'!H80)^(1/7)-1) -> 0.004450668 | I80: =IF('2019'!I80=0,0,(AME_2030!I80/'2019'!I80)^(1/7)-1) -> -0.001092 | J80: =IF('2019'!J80=0,0,(AME_2030!J80/'2019'!J80)^(1/7)-1) -> 0.00025194 | K80: =IF('2019 (Z)'!AW80=0,0,('AME_2030 (Z)'!AW80/'2019 (Z)'!AW80)^(1/7)-1) -> 0.0022937666 | L80: =K80 -> 0.0022937666 | M80: =IF('2019'!M80=0,0,(AME_2030!M80/'2019'!M80)^(1/7)-1) -> 0.0025107167 | N80: =IF('2019'!N80=0,0,(AME_2030!N80/'2019'!N80)^(1/7)-1) -> 0.0033552643 | O80: =IF('2019'!O80=0,0,(AME_2030!O80/'2019'!O80)^(1/7)-1) -> -0.00031411059 | P80: =IF('2019'!P80=0,0,(AME_2030!P80/'2019'!P80)^(1/7)-1) -> 0.00012075103 | Q80: =IF('2019'!Q80=0,0,(AME_2030!Q80/'2019'!Q80)^(1/7)-1) -> 1.6442185e-07 | R80: =IF('2019'!R80=0,0,(AME_2030!R80/'2019'!R80)^(1/7)-1) -> -2.0238261e-08 | S80: =T80 -> -1.9849599e-07 | T80: =IF('2019'!T80=0,0,(AME_2030!T80/'2019'!T80)^(1/7)-1) -> -1.9849599e-07 | U80: =IF('2019'!U80=0,0,(AME_2030!U80/'2019'!U80)^(1/7)-1) -> -3.4825263e-07 | V80: =IF('2019'!V80=0,0,(AME_2030!V80/'2019'!V80)^(1/7)-1) -> -2.6346634e-08 | W80: =IF('2019'!W80=0,0,(AME_2030!W80/'2019'!W80)^(1/7)-1) -> 0.00021664232 | X80: =IF('2019'!X80=0,0,(AME_2030!X80/'2019'!X80)^(1/7)-1) -> 0.00056408256 | Y80: =IF('2019'!Y80=0,0,(AME_2030!Y80/'2019'!Y80)^(1/7)-1) -> 0.0024005377 | Z80: =IF('2019'!Z80=0,0,(AME_2030!Z80/'2019'!Z80)^(1/7)-1) -> -0.0011515347 | AA80: =IF('2019'!AA80=0,0,(AME_2030!AA80/'2019'!AA80)^(1/7)-1) -> 0.0013439987 | ... AU80: =IF('2019'!AU80=0,0,(AME_2030!AU80/'2019'!AU80)^(1/7)-1) -> 0.0010130538
B81: 03 | C81: 03 | D81: Motor vehicles, trailers and semi-trailers | E81: =IF('2019'!E81=0,0,(AME_2030!E81/'2019'!E81)^(1/7)-1) -> -0.00010558601 | F81: =IF('2019'!F81=0,0,(AME_2030!F81/'2019'!F81)^(1/7)-1) -> 0.00022623442 | G81: =IF('2019'!G81=0,0,(AME_2030!G81/'2019'!G81)^(1/7)-1) -> -2.3353149e-09 | H81: =IF('2019'!H81=0,0,(AME_2030!H81/'2019'!H81)^(1/7)-1) -> 0.0039422071 | I81: =IF('2019'!I81=0,0,(AME_2030!I81/'2019'!I81)^(1/7)-1) -> 0.00057751563 | J81: =IF('2019'!J81=0,0,(AME_2030!J81/'2019'!J81)^(1/7)-1) -> 0.00050938047 | K81: =IF('2019 (Z)'!AW81=0,0,('AME_2030 (Z)'!AW81/'2019 (Z)'!AW81)^(1/7)-1) -> 0.0022946115 | L81: =K81 -> 0.0022946115 | M81: =IF('2019'!M81=0,0,(AME_2030!M81/'2019'!M81)^(1/7)-1) -> -0.0061159655 | N81: =IF('2019'!N81=0,0,(AME_2030!N81/'2019'!N81)^(1/7)-1) -> -0.0035525849 | O81: =IF('2019'!O81=0,0,(AME_2030!O81/'2019'!O81)^(1/7)-1) -> 0.0010783138 | P81: =IF('2019'!P81=0,0,(AME_2030!P81/'2019'!P81)^(1/7)-1) -> -0.00063352195 | Q81: =IF('2019'!Q81=0,0,(AME_2030!Q81/'2019'!Q81)^(1/7)-1) -> 1.6442185e-07 | R81: =IF('2019'!R81=0,0,(AME_2030!R81/'2019'!R81)^(1/7)-1) -> -2.0238261e-08 | S81: =T81 -> -2.5349083e-06 | T81: =IF('2019'!T81=0,0,(AME_2030!T81/'2019'!T81)^(1/7)-1) -> -2.5349083e-06 | U81: =IF('2019'!U81=0,0,(AME_2030!U81/'2019'!U81)^(1/7)-1) -> -3.9294539e-06 | V81: =IF('2019'!V81=0,0,(AME_2030!V81/'2019'!V81)^(1/7)-1) -> -2.6346634e-08 | W81: =IF('2019'!W81=0,0,(AME_2030!W81/'2019'!W81)^(1/7)-1) -> -5.8004209e-05 | X81: =IF('2019'!X81=0,0,(AME_2030!X81/'2019'!X81)^(1/7)-1) -> -1.2606775e-05 | Y81: =IF('2019'!Y81=0,0,(AME_2030!Y81/'2019'!Y81)^(1/7)-1) -> 0.0024005377 | Z81: =IF('2019'!Z81=0,0,(AME_2030!Z81/'2019'!Z81)^(1/7)-1) -> -0.001087457 | AA81: =IF('2019'!AA81=0,0,(AME_2030!AA81/'2019'!AA81)^(1/7)-1) -> 0.0013439192 | ... AU81: =IF('2019'!AU81=0,0,(AME_2030!AU81/'2019'!AU81)^(1/7)-1) -> 4.0217545e-05
B82: 04 | C82: 04 | D82: Glass and glass products | E82: =IF('2019'!E82=0,0,(AME_2030!E82/'2019'!E82)^(1/7)-1) -> -0.019668421 | F82: =IF('2019'!F82=0,0,(AME_2030!F82/'2019'!F82)^(1/7)-1) -> 0.0040748975 | G82: =IF('2019'!G82=0,0,(AME_2030!G82/'2019'!G82)^(1/7)-1) -> 0.016719315 | H82: =IF('2019'!H82=0,0,(AME_2030!H82/'2019'!H82)^(1/7)-1) -> -0.10430252 | I82: =IF('2019'!I82=0,0,(AME_2030!I82/'2019'!I82)^(1/7)-1) -> -0.0024711648 | J82: =IF('2019'!J82=0,0,(AME_2030!J82/'2019'!J82)^(1/7)-1) -> -0.04387476 | K82: =IF('2019 (Z)'!AW82=0,0,('AME_2030 (Z)'!AW82/'2019 (Z)'!AW82)^(1/7)-1) -> 0.0064267546 | L82: =K82 -> 0.0064267546 | M82: =IF('2019'!M82=0,0,(AME_2030!M82/'2019'!M82)^(1/7)-1) -> -0.010340552 | N82: =IF('2019'!N82=0,0,(AME_2030!N82/'2019'!N82)^(1/7)-1) -> -0.0080648081 | O82: =IF('2019'!O82=0,0,(AME_2030!O82/'2019'!O82)^(1/7)-1) -> -0.0021625588 | P82: =IF('2019'!P82=0,0,(AME_2030!P82/'2019'!P82)^(1/7)-1) -> -0.0019050811 | Q82: =IF('2019'!Q82=0,0,(AME_2030!Q82/'2019'!Q82)^(1/7)-1) -> -0.0012641169 | R82: =IF('2019'!R82=0,0,(AME_2030!R82/'2019'!R82)^(1/7)-1) -> -0.031173678 | S82: =T82 -> -0.015103528 | T82: =IF('2019'!T82=0,0,(AME_2030!T82/'2019'!T82)^(1/7)-1) -> -0.015103528 | U82: =IF('2019'!U82=0,0,(AME_2030!U82/'2019'!U82)^(1/7)-1) -> -0.028583196 | V82: =IF('2019'!V82=0,0,(AME_2030!V82/'2019'!V82)^(1/7)-1) -> -0.027137174 | W82: =IF('2019'!W82=0,0,(AME_2030!W82/'2019'!W82)^(1/7)-1) -> -0.011535226 | X82: =IF('2019'!X82=0,0,(AME_2030!X82/'2019'!X82)^(1/7)-1) -> -0.0063697053 | Y82: =IF('2019'!Y82=0,0,(AME_2030!Y82/'2019'!Y82)^(1/7)-1) -> 0.0046252875 | Z82: =IF('2019'!Z82=0,0,(AME_2030!Z82/'2019'!Z82)^(1/7)-1) -> 0.0049334096 | AA82: =IF('2019'!AA82=0,0,(AME_2030!AA82/'2019'!AA82)^(1/7)-1) -> -0.014578986 | ... AU82: =IF('2019'!AU82=0,0,(AME_2030!AU82/'2019'!AU82)^(1/7)-1) -> -0.02892517
B83: 05 | C83: 05 | D83: Ceramic products and building materials | E83: =IF('2019'!E83=0,0,(AME_2030!E83/'2019'!E83)^(1/7)-1) -> 0.00091761681 | F83: =IF('2019'!F83=0,0,(AME_2030!F83/'2019'!F83)^(1/7)-1) -> -4.5024416e-05 | G83: =IF('2019'!G83=0,0,(AME_2030!G83/'2019'!G83)^(1/7)-1) -> -2.3353149e-09 | H83: =IF('2019'!H83=0,0,(AME_2030!H83/'2019'!H83)^(1/7)-1) -> 0.0089782159 | I83: =IF('2019'!I83=0,0,(AME_2030!I83/'2019'!I83)^(1/7)-1) -> 0.00057131009 | J83: =IF('2019'!J83=0,0,(AME_2030!J83/'2019'!J83)^(1/7)-1) -> 2.5080681e-05 | K83: =IF('2019 (Z)'!AW83=0,0,('AME_2030 (Z)'!AW83/'2019 (Z)'!AW83)^(1/7)-1) -> 0.0022979587 | L83: =K83 -> 0.0022979587 | M83: =IF('2019'!M83=0,0,(AME_2030!M83/'2019'!M83)^(1/7)-1) -> 0.005515131 | N83: =IF('2019'!N83=0,0,(AME_2030!N83/'2019'!N83)^(1/7)-1) -> -0.0011127253 | O83: =IF('2019'!O83=0,0,(AME_2030!O83/'2019'!O83)^(1/7)-1) -> 0.0082748564 | P83: =IF('2019'!P83=0,0,(AME_2030!P83/'2019'!P83)^(1/7)-1) -> -0.00033960523 | Q83: =IF('2019'!Q83=0,0,(AME_2030!Q83/'2019'!Q83)^(1/7)-1) -> -0.0014105336 | R83: =IF('2019'!R83=0,0,(AME_2030!R83/'2019'!R83)^(1/7)-1) -> -2.0238261e-08 | S83: =T83 -> 2.0169107e-05 | T83: =IF('2019'!T83=0,0,(AME_2030!T83/'2019'!T83)^(1/7)-1) -> 2.0169107e-05 | U83: =IF('2019'!U83=0,0,(AME_2030!U83/'2019'!U83)^(1/7)-1) -> 9.4697575e-08 | V83: =IF('2019'!V83=0,0,(AME_2030!V83/'2019'!V83)^(1/7)-1) -> -2.6346634e-08 | W83: =IF('2019'!W83=0,0,(AME_2030!W83/'2019'!W83)^(1/7)-1) -> -0.005438231 | X83: =IF('2019'!X83=0,0,(AME_2030!X83/'2019'!X83)^(1/7)-1) -> -4.0235184e-06 | Y83: =IF('2019'!Y83=0,0,(AME_2030!Y83/'2019'!Y83)^(1/7)-1) -> 0.0024008418 | Z83: =IF('2019'!Z83=0,0,(AME_2030!Z83/'2019'!Z83)^(1/7)-1) -> -0.0007940191 | AA83: =IF('2019'!AA83=0,0,(AME_2030!AA83/'2019'!AA83)^(1/7)-1) -> 0.001343938 | ... AU83: =IF('2019'!AU83=0,0,(AME_2030!AU83/'2019'!AU83)^(1/7)-1) -> 0.0028982496
B84: 06 | C84: 06 | D84: Articles of paper and paperboard | E84: =IF('2019'!E84=0,0,(AME_2030!E84/'2019'!E84)^(1/7)-1) -> 0.0062876117 | F84: =IF('2019'!F84=0,0,(AME_2030!F84/'2019'!F84)^(1/7)-1) -> 0.0067898651 | G84: =IF('2019'!G84=0,0,(AME_2030!G84/'2019'!G84)^(1/7)-1) -> -2.3353149e-09 | H84: =IF('2019'!H84=0,0,(AME_2030!H84/'2019'!H84)^(1/7)-1) -> 0.010131519 | I84: =IF('2019'!I84=0,0,(AME_2030!I84/'2019'!I84)^(1/7)-1) -> -0.00065001165 | J84: =IF('2019'!J84=0,0,(AME_2030!J84/'2019'!J84)^(1/7)-1) -> -0.00048247995 | K84: =IF('2019 (Z)'!AW84=0,0,('AME_2030 (Z)'!AW84/'2019 (Z)'!AW84)^(1/7)-1) -> 0.0087353275 | L84: =K84 -> 0.0087353275 | M84: =IF('2019'!M84=0,0,(AME_2030!M84/'2019'!M84)^(1/7)-1) -> -0.016842491 | N84: =IF('2019'!N84=0,0,(AME_2030!N84/'2019'!N84)^(1/7)-1) -> 0.0018508509 | O84: =IF('2019'!O84=0,0,(AME_2030!O84/'2019'!O84)^(1/7)-1) -> -0.0019964607 | P84: =IF('2019'!P84=0,0,(AME_2030!P84/'2019'!P84)^(1/7)-1) -> 0.005250869 | Q84: =IF('2019'!Q84=0,0,(AME_2030!Q84/'2019'!Q84)^(1/7)-1) -> 1.2959797e-07 | R84: =IF('2019'!R84=0,0,(AME_2030!R84/'2019'!R84)^(1/7)-1) -> -1.2985748e-06 | S84: =T84 -> 0.00082706643 | T84: =IF('2019'!T84=0,0,(AME_2030!T84/'2019'!T84)^(1/7)-1) -> 0.00082706643 | U84: =IF('2019'!U84=0,0,(AME_2030!U84/'2019'!U84)^(1/7)-1) -> -3.7089284e-05 | V84: =IF('2019'!V84=0,0,(AME_2030!V84/'2019'!V84)^(1/7)-1) -> -2.6346634e-08 | W84: =IF('2019'!W84=0,0,(AME_2030!W84/'2019'!W84)^(1/7)-1) -> 0.0067395376 | X84: =IF('2019'!X84=0,0,(AME_2030!X84/'2019'!X84)^(1/7)-1) -> 0.0071088255 | Y84: =IF('2019'!Y84=0,0,(AME_2030!Y84/'2019'!Y84)^(1/7)-1) -> 0.0026454663 | Z84: =IF('2019'!Z84=0,0,(AME_2030!Z84/'2019'!Z84)^(1/7)-1) -> -0.0024721747 | AA84: =IF('2019'!AA84=0,0,(AME_2030!AA84/'2019'!AA84)^(1/7)-1) -> 0.0010476841 | ... AU84: =IF('2019'!AU84=0,0,(AME_2030!AU84/'2019'!AU84)^(1/7)-1) -> 0.0062593708
B85: 07 | C85: 07 | D85: Inorganic basic chemicals | E85: =IF('2019 (Z)'!E129=0,0,('AME_2030 (Z)'!E129/'2019 (Z)'!E129)^(1/7)-1) -> -0.011886284 | F85: =IF('2019 (Z)'!F129=0,0,('AME_2030 (Z)'!F129/'2019 (Z)'!F129)^(1/7)-1) -> -0.014014895 | G85: =IF('2019 (Z)'!G129=0,0,('AME_2030 (Z)'!G129/'2019 (Z)'!G129)^(1/7)-1) -> -0.014938797 | H85: =IF('2019 (Z)'!H129=0,0,('AME_2030 (Z)'!H129/'2019 (Z)'!H129)^(1/7)-1) -> 0.035614848 | I85: =IF('2019 (Z)'!I129=0,0,('AME_2030 (Z)'!I129/'2019 (Z)'!I129)^(1/7)-1) -> -0.015871217 | J85: =IF('2019 (Z)'!J129=0,0,('AME_2030 (Z)'!J129/'2019 (Z)'!J129)^(1/7)-1) -> -0.014232088 | K85: =IF('2019 (Z)'!K129=0,0,('AME_2030 (Z)'!K129/'2019 (Z)'!K129)^(1/7)-1) -> -0.012643475 | L85: =IF('2019 (Z)'!L129=0,0,('AME_2030 (Z)'!L129/'2019 (Z)'!L129)^(1/7)-1) -> -0.012643475 | ... R85: =IF('2019 (Z)'!R129=0,0,('AME_2030 (Z)'!R129/'2019 (Z)'!R129)^(1/7)-1) -> -0.014938621 | S85: =T85 -> -0.014499449 | T85: =IF('2019 (Z)'!T129=0,0,('AME_2030 (Z)'!T129/'2019 (Z)'!T129)^(1/7)-1) -> -0.014499449 | U85: =IF('2019 (Z)'!U129=0,0,('AME_2030 (Z)'!U129/'2019 (Z)'!U129)^(1/7)-1) -> -0.014961109 | V85: =IF('2019 (Z)'!V129=0,0,('AME_2030 (Z)'!V129/'2019 (Z)'!V129)^(1/7)-1) -> -0.014938821 | W85: =IF('2019 (Z)'!W129=0,0,('AME_2030 (Z)'!W129/'2019 (Z)'!W129)^(1/7)-1) -> -0.016083615 | X85: =IF('2019 (Z)'!X129=0,0,('AME_2030 (Z)'!X129/'2019 (Z)'!X129)^(1/7)-1) -> -0.014931685 | Y85: =IF('2019 (Z)'!Y129=0,0,('AME_2030 (Z)'!Y129/'2019 (Z)'!Y129)^(1/7)-1) -> -0.01255367 | Z85: =IF('2019 (Z)'!Z129=0,0,('AME_2030 (Z)'!Z129/'2019 (Z)'!Z129)^(1/7)-1) -> -0.015529418 | AA85: =IF('2019 (Z)'!AA129=0,0,('AME_2030 (Z)'!AA129/'2019 (Z)'!AA129)^(1/7)-1) -> -0.013587921 | ... AU85: =IF('2019 (Z)'!AU129=0,0,('AME_2030 (Z)'!AU129/'2019 (Z)'!AU129)^(1/7)-1) -> -0.0021774219
B86: 08 | C86: 08 | D86: Organic basic chemicals | E86: =E85 -> -0.011886284 | F86: =F85 -> -0.014014895 | G86: =G85 -> -0.014938797 | H86: =H85 -> 0.035614848 | I86: =I85 -> -0.015871217 | J86: =J85 -> -0.014232088 | K86: =K85 -> -0.012643475 | L86: =L85 -> -0.012643475 | ... R86: =R85 -> -0.014938621 | S86: =T86 -> -0.014499449 | T86: =T85 -> -0.014499449 | U86: =U85 -> -0.014961109 | V86: =V85 -> -0.014938821 | W86: =W85 -> -0.016083615 | X86: =X85 -> -0.014931685 | Y86: =Y85 -> -0.01255367 | Z86: =Z85 -> -0.015529418 | AA86: =AA85 -> -0.013587921 | ... AU86: =AU85 -> -0.0021774219
B87: 09 | C87: 09 | D87: Plastics products | E87: =IF('2019'!E87=0,0,(AME_2030!E87/'2019'!E87)^(1/7)-1) -> -0.022888934 | F87: =IF('2019'!F87=0,0,(AME_2030!F87/'2019'!F87)^(1/7)-1) -> -0.022637588 | G87: =IF('2019'!G87=0,0,(AME_2030!G87/'2019'!G87)^(1/7)-1) -> 0.11375897 | H87: =IF('2019'!H87=0,0,(AME_2030!H87/'2019'!H87)^(1/7)-1) -> 0.0059763962 | I87: =IF('2019'!I87=0,0,(AME_2030!I87/'2019'!I87)^(1/7)-1) -> -0.00031820328 | J87: =IF('2019'!J87=0,0,(AME_2030!J87/'2019'!J87)^(1/7)-1) -> 0.00012291547 | K87: =IF('2019 (Z)'!AW87=0,0,('AME_2030 (Z)'!AW87/'2019 (Z)'!AW87)^(1/7)-1) -> -0.019302869 | L87: =K87 -> -0.019302869 | M87: =IF('2019'!M87=0,0,(AME_2030!M87/'2019'!M87)^(1/7)-1) -> 0.00050647829 | N87: =IF('2019'!N87=0,0,(AME_2030!N87/'2019'!N87)^(1/7)-1) -> 0.0027363573 | O87: =IF('2019'!O87=0,0,(AME_2030!O87/'2019'!O87)^(1/7)-1) -> 0.0023815501 | P87: =IF('2019'!P87=0,0,(AME_2030!P87/'2019'!P87)^(1/7)-1) -> -0.017838001 | Q87: =IF('2019'!Q87=0,0,(AME_2030!Q87/'2019'!Q87)^(1/7)-1) -> 1.6325152e-07 | R87: =IF('2019'!R87=0,0,(AME_2030!R87/'2019'!R87)^(1/7)-1) -> -2.8255923e-08 | S87: =T87 -> 1.0186614e-06 | T87: =IF('2019'!T87=0,0,(AME_2030!T87/'2019'!T87)^(1/7)-1) -> 1.0186614e-06 | U87: =IF('2019'!U87=0,0,(AME_2030!U87/'2019'!U87)^(1/7)-1) -> -2.5102766e-05 | V87: =IF('2019'!V87=0,0,(AME_2030!V87/'2019'!V87)^(1/7)-1) -> -2.6346634e-08 | W87: =IF('2019'!W87=0,0,(AME_2030!W87/'2019'!W87)^(1/7)-1) -> -0.022888997 | X87: =IF('2019'!X87=0,0,(AME_2030!X87/'2019'!X87)^(1/7)-1) -> -0.019900495 | Y87: =IF('2019'!Y87=0,0,(AME_2030!Y87/'2019'!Y87)^(1/7)-1) -> 0.0022483123 | Z87: =IF('2019'!Z87=0,0,(AME_2030!Z87/'2019'!Z87)^(1/7)-1) -> -0.0011023513 | AA87: =IF('2019'!AA87=0,0,(AME_2030!AA87/'2019'!AA87)^(1/7)-1) -> 0.0011872057 | ... AU87: =IF('2019'!AU87=0,0,(AME_2030!AU87/'2019'!AU87)^(1/7)-1) -> 0.0085889666
B88: 10 | C88: 10 | D88: Basic iron and steel and of ferro-alloys | E88: =IF('2019'!E88=0,0,(AME_2030!E88/'2019'!E88)^(1/7)-1) -> 0.0020629855 | F88: =IF('2019'!F88=0,0,(AME_2030!F88/'2019'!F88)^(1/7)-1) -> -0.0052509213 | G88: =IF('2019'!G88=0,0,(AME_2030!G88/'2019'!G88)^(1/7)-1) -> -0.029260452 | H88: =IF('2019'!H88=0,0,(AME_2030!H88/'2019'!H88)^(1/7)-1) -> 0 | I88: =IF('2019'!I88=0,0,(AME_2030!I88/'2019'!I88)^(1/7)-1) -> -0.0049786291 | J88: =IF('2019'!J88=0,0,(AME_2030!J88/'2019'!J88)^(1/7)-1) -> -0.0051335594 | K88: =IF('2019 (Z)'!AW88=0,0,('AME_2030 (Z)'!AW88/'2019 (Z)'!AW88)^(1/7)-1) -> -0.0030555282 | L88: =K88 -> -0.0030555282 | M88: =IF('2019'!M88=0,0,(AME_2030!M88/'2019'!M88)^(1/7)-1) -> -0.0058690519 | N88: =IF('2019'!N88=0,0,(AME_2030!N88/'2019'!N88)^(1/7)-1) -> -0.0072156362 | O88: =IF('2019'!O88=0,0,(AME_2030!O88/'2019'!O88)^(1/7)-1) -> -0.0060759544 | P88: =IF('2019'!P88=0,0,(AME_2030!P88/'2019'!P88)^(1/7)-1) -> -0.0051408821 | Q88: =IF('2019'!Q88=0,0,(AME_2030!Q88/'2019'!Q88)^(1/7)-1) -> -0.0062554056 | R88: =IF('2019'!R88=0,0,(AME_2030!R88/'2019'!R88)^(1/7)-1) -> -0.0053366076 | S88: =T88 -> -0.005177365 | T88: =IF('2019'!T88=0,0,(AME_2030!T88/'2019'!T88)^(1/7)-1) -> -0.005177365 | U88: =IF('2019'!U88=0,0,(AME_2030!U88/'2019'!U88)^(1/7)-1) -> -0.0036832224 | V88: =IF('2019'!V88=0,0,(AME_2030!V88/'2019'!V88)^(1/7)-1) -> -0.0042253394 | W88: =IF('2019'!W88=0,0,(AME_2030!W88/'2019'!W88)^(1/7)-1) -> -0.0051158955 | X88: =IF('2019'!X88=0,0,(AME_2030!X88/'2019'!X88)^(1/7)-1) -> 0.0019875828 | Y88: =IF('2019'!Y88=0,0,(AME_2030!Y88/'2019'!Y88)^(1/7)-1) -> -0.0029492791 | Z88: =IF('2019'!Z88=0,0,(AME_2030!Z88/'2019'!Z88)^(1/7)-1) -> -0.0064484641 | AA88: =IF('2019'!AA88=0,0,(AME_2030!AA88/'2019'!AA88)^(1/7)-1) -> -0.0040001664 | ... AU88: =IF('2019'!AU88=0,0,(AME_2030!AU88/'2019'!AU88)^(1/7)-1) -> -0.011638371
B89: 11 | C89: 11 | D89: Non-ferrous metals | E89: =IF('2019'!E89=0,0,(AME_2030!E89/'2019'!E89)^(1/7)-1) -> 0.0069608243 | F89: =IF('2019'!F89=0,0,(AME_2030!F89/'2019'!F89)^(1/7)-1) -> -0.0066285752 | G89: =IF('2019'!G89=0,0,(AME_2030!G89/'2019'!G89)^(1/7)-1) -> 0.086803759 | H89: =IF('2019'!H89=0,0,(AME_2030!H89/'2019'!H89)^(1/7)-1) -> 0.0067521141 | I89: =IF('2019'!I89=0,0,(AME_2030!I89/'2019'!I89)^(1/7)-1) -> -0.0035762579 | J89: =IF('2019'!J89=0,0,(AME_2030!J89/'2019'!J89)^(1/7)-1) -> -0.0051157887 | K89: =IF('2019 (Z)'!AW89=0,0,('AME_2030 (Z)'!AW89/'2019 (Z)'!AW89)^(1/7)-1) -> -0.002514792 | L89: =K89 -> -0.002514792 | M89: =IF('2019'!M89=0,0,(AME_2030!M89/'2019'!M89)^(1/7)-1) -> -0.0041625936 | N89: =IF('2019'!N89=0,0,(AME_2030!N89/'2019'!N89)^(1/7)-1) -> 0.0014900897 | O89: =IF('2019'!O89=0,0,(AME_2030!O89/'2019'!O89)^(1/7)-1) -> -0.0014393832 | P89: =IF('2019'!P89=0,0,(AME_2030!P89/'2019'!P89)^(1/7)-1) -> -0.0035223641 | Q89: =IF('2019'!Q89=0,0,(AME_2030!Q89/'2019'!Q89)^(1/7)-1) -> -0.00085636019 | R89: =IF('2019'!R89=0,0,(AME_2030!R89/'2019'!R89)^(1/7)-1) -> 0.0010710499 | S89: =T89 -> -0.0012939084 | T89: =IF('2019'!T89=0,0,(AME_2030!T89/'2019'!T89)^(1/7)-1) -> -0.0012939084 | U89: =IF('2019'!U89=0,0,(AME_2030!U89/'2019'!U89)^(1/7)-1) -> -6.6227942e-06 | V89: =IF('2019'!V89=0,0,(AME_2030!V89/'2019'!V89)^(1/7)-1) -> -0.00047729925 | W89: =IF('2019'!W89=0,0,(AME_2030!W89/'2019'!W89)^(1/7)-1) -> -0.002844683 | X89: =IF('2019'!X89=0,0,(AME_2030!X89/'2019'!X89)^(1/7)-1) -> 0.00046691642 | Y89: =IF('2019'!Y89=0,0,(AME_2030!Y89/'2019'!Y89)^(1/7)-1) -> 0.00033672506 | Z89: =IF('2019'!Z89=0,0,(AME_2030!Z89/'2019'!Z89)^(1/7)-1) -> -0.0080671852 | AA89: =IF('2019'!AA89=0,0,(AME_2030!AA89/'2019'!AA89)^(1/7)-1) -> -0.0034599154 | ... AU89: =IF('2019'!AU89=0,0,(AME_2030!AU89/'2019'!AU89)^(1/7)-1) -> 0.00071102062
B90: 12 | C90: 12 | D90: Other industries | E90: =IF('2019'!E90=0,0,(AME_2030!E90/'2019'!E90)^(1/7)-1) -> 0.00042545358 | F90: =IF('2019'!F90=0,0,(AME_2030!F90/'2019'!F90)^(1/7)-1) -> 0.00014288957 | G90: =IF('2019'!G90=0,0,(AME_2030!G90/'2019'!G90)^(1/7)-1) -> 2.497266e-05 | H90: =IF('2019'!H90=0,0,(AME_2030!H90/'2019'!H90)^(1/7)-1) -> -0.018585312 | I90: =IF('2019'!I90=0,0,(AME_2030!I90/'2019'!I90)^(1/7)-1) -> -0.00016704765 | J90: =IF('2019'!J90=0,0,(AME_2030!J90/'2019'!J90)^(1/7)-1) -> -0.0010817835 | K90: =IF('2019 (Z)'!AW90=0,0,('AME_2030 (Z)'!AW90/'2019 (Z)'!AW90)^(1/7)-1) -> 0.0022982324 | L90: =K90 -> 0.0022982324 | M90: =IF('2019'!M90=0,0,(AME_2030!M90/'2019'!M90)^(1/7)-1) -> 0.002625835 | N90: =IF('2019'!N90=0,0,(AME_2030!N90/'2019'!N90)^(1/7)-1) -> -0.0073097381 | O90: =IF('2019'!O90=0,0,(AME_2030!O90/'2019'!O90)^(1/7)-1) -> -0.00024885628 | P90: =IF('2019'!P90=0,0,(AME_2030!P90/'2019'!P90)^(1/7)-1) -> -0.00018578124 | Q90: =IF('2019'!Q90=0,0,(AME_2030!Q90/'2019'!Q90)^(1/7)-1) -> 0.0027438286 | R90: =IF('2019'!R90=0,0,(AME_2030!R90/'2019'!R90)^(1/7)-1) -> -2.0238261e-08 | S90: =T90 -> 2.83083e-05 | T90: =IF('2019'!T90=0,0,(AME_2030!T90/'2019'!T90)^(1/7)-1) -> 2.83083e-05 | U90: =IF('2019'!U90=0,0,(AME_2030!U90/'2019'!U90)^(1/7)-1) -> -2.3363484e-05 | V90: =IF('2019'!V90=0,0,(AME_2030!V90/'2019'!V90)^(1/7)-1) -> -2.6346634e-08 | W90: =IF('2019'!W90=0,0,(AME_2030!W90/'2019'!W90)^(1/7)-1) -> -0.00034398987 | X90: =IF('2019'!X90=0,0,(AME_2030!X90/'2019'!X90)^(1/7)-1) -> -1.6848219e-05 | Y90: =IF('2019'!Y90=0,0,(AME_2030!Y90/'2019'!Y90)^(1/7)-1) -> 0.0024005377 | Z90: =IF('2019'!Z90=0,0,(AME_2030!Z90/'2019'!Z90)^(1/7)-1) -> -0.0011358949 | AA90: =IF('2019'!AA90=0,0,(AME_2030!AA90/'2019'!AA90)^(1/7)-1) -> 0.0013440031 | ... AU90: =IF('2019'!AU90=0,0,(AME_2030!AU90/'2019'!AU90)^(1/7)-1) -> 0.0002806414
B91: 13 | C91: 13 | D91: Construction of buildings and Civil engineering | E91: =IF('2019'!E91=0,0,(AME_2030!E91/'2019'!E91)^(1/7)-1) -> 0.0011616854 | F91: =IF('2019'!F91=0,0,(AME_2030!F91/'2019'!F91)^(1/7)-1) -> 0.00029711905 | G91: =IF('2019'!G91=0,0,(AME_2030!G91/'2019'!G91)^(1/7)-1) -> -2.3353151e-09 | H91: =IF('2019'!H91=0,0,(AME_2030!H91/'2019'!H91)^(1/7)-1) -> -0.0020336147 | I91: =IF('2019'!I91=0,0,(AME_2030!I91/'2019'!I91)^(1/7)-1) -> -2.6110977e-05 | J91: =IF('2019'!J91=0,0,(AME_2030!J91/'2019'!J91)^(1/7)-1) -> -0.00016544578 | K91: =IF('2019 (Z)'!AW91=0,0,('AME_2030 (Z)'!AW91/'2019 (Z)'!AW91)^(1/7)-1) -> 0.0023150853 | L91: =K91 -> 0.0023150853 | M91: =IF('2019'!M91=0,0,(AME_2030!M91/'2019'!M91)^(1/7)-1) -> 0.0086686151 | N91: =IF('2019'!N91=0,0,(AME_2030!N91/'2019'!N91)^(1/7)-1) -> -0.0023603293 | O91: =IF('2019'!O91=0,0,(AME_2030!O91/'2019'!O91)^(1/7)-1) -> 0.002119531 | P91: =IF('2019'!P91=0,0,(AME_2030!P91/'2019'!P91)^(1/7)-1) -> -0.00024340399 | Q91: =IF('2019'!Q91=0,0,(AME_2030!Q91/'2019'!Q91)^(1/7)-1) -> 1.6442185e-07 | R91: =IF('2019'!R91=0,0,(AME_2030!R91/'2019'!R91)^(1/7)-1) -> -2.0238261e-08 | S91: =T91 -> 1.7625011e-05 | T91: =IF('2019'!T91=0,0,(AME_2030!T91/'2019'!T91)^(1/7)-1) -> 1.7625011e-05 | U91: =IF('2019'!U91=0,0,(AME_2030!U91/'2019'!U91)^(1/7)-1) -> -1.3019822e-05 | V91: =IF('2019'!V91=0,0,(AME_2030!V91/'2019'!V91)^(1/7)-1) -> -2.6346634e-08 | W91: =IF('2019'!W91=0,0,(AME_2030!W91/'2019'!W91)^(1/7)-1) -> -0.00067506985 | X91: =IF('2019'!X91=0,0,(AME_2030!X91/'2019'!X91)^(1/7)-1) -> 6.0744162e-07 | Y91: =IF('2019'!Y91=0,0,(AME_2030!Y91/'2019'!Y91)^(1/7)-1) -> 0.0024005377 | Z91: =IF('2019'!Z91=0,0,(AME_2030!Z91/'2019'!Z91)^(1/7)-1) -> -0.001136741 | AA91: =IF('2019'!AA91=0,0,(AME_2030!AA91/'2019'!AA91)^(1/7)-1) -> 0.0013439938 | ... AU91: =IF('2019'!AU91=0,0,(AME_2030!AU91/'2019'!AU91)^(1/7)-1) -> 0.0034993926
B92: 14 | C92: 14 | D92: Rail transport (Passenger and Freight) | E92: =IF('2019'!E92=0,0,(AME_2030!E92/'2019'!E92)^(1/7)-1) -> -0.00039427463 | F92: =IF('2019'!F92=0,0,(AME_2030!F92/'2019'!F92)^(1/7)-1) -> 0.00011149458 | G92: =IF('2019'!G92=0,0,(AME_2030!G92/'2019'!G92)^(1/7)-1) -> -2.3353149e-09 | H92: =IF('2019'!H92=0,0,(AME_2030!H92/'2019'!H92)^(1/7)-1) -> 0.013548732 | I92: =IF('2019'!I92=0,0,(AME_2030!I92/'2019'!I92)^(1/7)-1) -> -5.0840463e-06 | J92: =IF('2019'!J92=0,0,(AME_2030!J92/'2019'!J92)^(1/7)-1) -> -0.0020029674 | K92: =IF('2019 (Z)'!AW92=0,0,('AME_2030 (Z)'!AW92/'2019 (Z)'!AW92)^(1/7)-1) -> 0.0023258303 | L92: =K92 -> 0.0023258303 | M92: =IF('2019'!M92=0,0,(AME_2030!M92/'2019'!M92)^(1/7)-1) -> 0.017283121 | N92: =IF('2019'!N92=0,0,(AME_2030!N92/'2019'!N92)^(1/7)-1) -> -0.013154506 | O92: =IF('2019'!O92=0,0,(AME_2030!O92/'2019'!O92)^(1/7)-1) -> 0.0020462945 | P92: =IF('2019'!P92=0,0,(AME_2030!P92/'2019'!P92)^(1/7)-1) -> 0.00013072464 | Q92: =IF('2019'!Q92=0,0,(AME_2030!Q92/'2019'!Q92)^(1/7)-1) -> 1.6442185e-07 | R92: =IF('2019'!R92=0,0,(AME_2030!R92/'2019'!R92)^(1/7)-1) -> -2.0238261e-08 | S92: =T92 -> -6.519846e-07 | T92: =IF('2019'!T92=0,0,(AME_2030!T92/'2019'!T92)^(1/7)-1) -> -6.519846e-07 | U92: =IF('2019'!U92=0,0,(AME_2030!U92/'2019'!U92)^(1/7)-1) -> -2.7633139e-05 | V92: =IF('2019'!V92=0,0,(AME_2030!V92/'2019'!V92)^(1/7)-1) -> -2.6346634e-08 | W92: =IF('2019'!W92=0,0,(AME_2030!W92/'2019'!W92)^(1/7)-1) -> -0.0001316556 | X92: =IF('2019'!X92=0,0,(AME_2030!X92/'2019'!X92)^(1/7)-1) -> 1.5722098e-05 | Y92: =IF('2019'!Y92=0,0,(AME_2030!Y92/'2019'!Y92)^(1/7)-1) -> 0.0024005377 | Z92: =IF('2019'!Z92=0,0,(AME_2030!Z92/'2019'!Z92)^(1/7)-1) -> -0.0011471211 | AA92: =IF('2019'!AA92=0,0,(AME_2030!AA92/'2019'!AA92)^(1/7)-1) -> 0.0013439994 | ... AU92: =IF('2019'!AU92=0,0,(AME_2030!AU92/'2019'!AU92)^(1/7)-1) -> 0.00075553118
B93: 15 | C93: 15 | D93: Passenger transport by road | E93: =E94 -> -0.00051456061 | F93: =F94 -> 0.00021168767 | G93: =G94 -> -2.3353149e-09 | H93: =H94 -> 0.013591941 | I93: =I94 -> 0.00027728517 | J93: =J94 -> -0.0006775801 | K93: =K94 -> 0.0023236833 | L93: =L94 -> 0.0023236833 | ... R93: =R94 -> -2.0238261e-08 | S93: =T93 -> 2.0423069e-05 | T93: =T94 -> 2.0423069e-05 | U93: =U94 -> -2.615333e-05 | V93: =V94 -> -2.6346634e-08 | W93: =W94 -> 0.00059027497 | X93: =X94 -> 4.1800561e-06 | Y93: =Y94 -> 0.0024005377 | Z93: =Z94 -> -0.0011538208 | AA93: =AA94 -> 0.0013439659 | ... AU93: =AU94 -> 0.00073259674
B94: 16 | C94: 16 | D94: Freight transport by road and transport via pipeline | E94: =IF('2019'!E94=0,0,(AME_2030!E94/'2019'!E94)^(1/7)-1) -> -0.00051456061 | F94: =IF('2019'!F94=0,0,(AME_2030!F94/'2019'!F94)^(1/7)-1) -> 0.00021168767 | G94: =IF('2019'!G94=0,0,(AME_2030!G94/'2019'!G94)^(1/7)-1) -> -2.3353149e-09 | H94: =IF('2019'!H94=0,0,(AME_2030!H94/'2019'!H94)^(1/7)-1) -> 0.013591941 | I94: =IF('2019'!I94=0,0,(AME_2030!I94/'2019'!I94)^(1/7)-1) -> 0.00027728517 | J94: =IF('2019'!J94=0,0,(AME_2030!J94/'2019'!J94)^(1/7)-1) -> -0.0006775801 | K94: =IF('2019 (Z)'!AW94=0,0,('AME_2030 (Z)'!AW94/'2019 (Z)'!AW94)^(1/7)-1) -> 0.0023236833 | L94: =K94 -> 0.0023236833 | M94: =IF('2019'!M94=0,0,(AME_2030!M94/'2019'!M94)^(1/7)-1) -> 0.021585991 | N94: =IF('2019'!N94=0,0,(AME_2030!N94/'2019'!N94)^(1/7)-1) -> 0.0012514529 | O94: =IF('2019'!O94=0,0,(AME_2030!O94/'2019'!O94)^(1/7)-1) -> 0.0012804025 | P94: =IF('2019'!P94=0,0,(AME_2030!P94/'2019'!P94)^(1/7)-1) -> 3.4803457e-05 | Q94: =IF('2019'!Q94=0,0,(AME_2030!Q94/'2019'!Q94)^(1/7)-1) -> 1.6442185e-07 | R94: =IF('2019'!R94=0,0,(AME_2030!R94/'2019'!R94)^(1/7)-1) -> -2.0238261e-08 | S94: =T94 -> 2.0423069e-05 | T94: =IF('2019'!T94=0,0,(AME_2030!T94/'2019'!T94)^(1/7)-1) -> 2.0423069e-05 | U94: =IF('2019'!U94=0,0,(AME_2030!U94/'2019'!U94)^(1/7)-1) -> -2.615333e-05 | V94: =IF('2019'!V94=0,0,(AME_2030!V94/'2019'!V94)^(1/7)-1) -> -2.6346634e-08 | W94: =IF('2019'!W94=0,0,(AME_2030!W94/'2019'!W94)^(1/7)-1) -> 0.00059027497 | X94: =IF('2019'!X94=0,0,(AME_2030!X94/'2019'!X94)^(1/7)-1) -> 4.1800561e-06 | Y94: =IF('2019'!Y94=0,0,(AME_2030!Y94/'2019'!Y94)^(1/7)-1) -> 0.0024005377 | Z94: =IF('2019'!Z94=0,0,(AME_2030!Z94/'2019'!Z94)^(1/7)-1) -> -0.0011538208 | AA94: =IF('2019'!AA94=0,0,(AME_2030!AA94/'2019'!AA94)^(1/7)-1) -> 0.0013439659 | ... AU94: =IF('2019'!AU94=0,0,(AME_2030!AU94/'2019'!AU94)^(1/7)-1) -> 0.00073259674
B95: 17 | C95: 17 | D95: Water transport | E95: =IF('2019'!E95=0,0,(AME_2030!E95/'2019'!E95)^(1/7)-1) -> -0.00055701301 | F95: =IF('2019'!F95=0,0,(AME_2030!F95/'2019'!F95)^(1/7)-1) -> 0.00012680131 | G95: =IF('2019'!G95=0,0,(AME_2030!G95/'2019'!G95)^(1/7)-1) -> -2.3353149e-09 | H95: =IF('2019'!H95=0,0,(AME_2030!H95/'2019'!H95)^(1/7)-1) -> 0.013548732 | I95: =IF('2019'!I95=0,0,(AME_2030!I95/'2019'!I95)^(1/7)-1) -> -0.00021506253 | J95: =IF('2019'!J95=0,0,(AME_2030!J95/'2019'!J95)^(1/7)-1) -> -0.0031709567 | K95: =IF('2019 (Z)'!AW95=0,0,('AME_2030 (Z)'!AW95/'2019 (Z)'!AW95)^(1/7)-1) -> 0.0028826183 | L95: =K95 -> 0.0028826183 | M95: =IF('2019'!M95=0,0,(AME_2030!M95/'2019'!M95)^(1/7)-1) -> 0.047191983 | N95: =IF('2019'!N95=0,0,(AME_2030!N95/'2019'!N95)^(1/7)-1) -> 0.0015150254 | O95: =IF('2019'!O95=0,0,(AME_2030!O95/'2019'!O95)^(1/7)-1) -> 0.0020405095 | P95: =IF('2019'!P95=0,0,(AME_2030!P95/'2019'!P95)^(1/7)-1) -> 0.00056618929 | Q95: =IF('2019'!Q95=0,0,(AME_2030!Q95/'2019'!Q95)^(1/7)-1) -> 1.6442185e-07 | R95: =IF('2019'!R95=0,0,(AME_2030!R95/'2019'!R95)^(1/7)-1) -> -2.0238261e-08 | S95: =T95 -> 1.0396121e-05 | T95: =IF('2019'!T95=0,0,(AME_2030!T95/'2019'!T95)^(1/7)-1) -> 1.0396121e-05 | U95: =IF('2019'!U95=0,0,(AME_2030!U95/'2019'!U95)^(1/7)-1) -> 7.6037128e-06 | V95: =IF('2019'!V95=0,0,(AME_2030!V95/'2019'!V95)^(1/7)-1) -> -2.6346634e-08 | W95: =IF('2019'!W95=0,0,(AME_2030!W95/'2019'!W95)^(1/7)-1) -> -0.00061137462 | X95: =IF('2019'!X95=0,0,(AME_2030!X95/'2019'!X95)^(1/7)-1) -> 1.7207287e-06 | Y95: =IF('2019'!Y95=0,0,(AME_2030!Y95/'2019'!Y95)^(1/7)-1) -> 0.0024005377 | Z95: =IF('2019'!Z95=0,0,(AME_2030!Z95/'2019'!Z95)^(1/7)-1) -> -0.00112293 | AA95: =IF('2019'!AA95=0,0,(AME_2030!AA95/'2019'!AA95)^(1/7)-1) -> 0.0013440024 | ... AU95: =IF('2019'!AU95=0,0,(AME_2030!AU95/'2019'!AU95)^(1/7)-1) -> 0.00011519662
B96: 18 | C96: 18 | D96: Air transport | E96: =IF('2019'!E96=0,0,(AME_2030!E96/'2019'!E96)^(1/7)-1) -> -0.00075029454 | F96: =IF('2019'!F96=0,0,(AME_2030!F96/'2019'!F96)^(1/7)-1) -> 9.751166e-05 | G96: =IF('2019'!G96=0,0,(AME_2030!G96/'2019'!G96)^(1/7)-1) -> -2.3353149e-09 | H96: =IF('2019'!H96=0,0,(AME_2030!H96/'2019'!H96)^(1/7)-1) -> 0.014202559 | I96: =IF('2019'!I96=0,0,(AME_2030!I96/'2019'!I96)^(1/7)-1) -> -0.00023882023 | J96: =IF('2019'!J96=0,0,(AME_2030!J96/'2019'!J96)^(1/7)-1) -> -0.00027591171 | K96: =IF('2019 (Z)'!AW96=0,0,('AME_2030 (Z)'!AW96/'2019 (Z)'!AW96)^(1/7)-1) -> 0.002299148 | L96: =K96 -> 0.002299148 | M96: =IF('2019'!M96=0,0,(AME_2030!M96/'2019'!M96)^(1/7)-1) -> -0.0065823078 | N96: =IF('2019'!N96=0,0,(AME_2030!N96/'2019'!N96)^(1/7)-1) -> -0.011581432 | O96: =IF('2019'!O96=0,0,(AME_2030!O96/'2019'!O96)^(1/7)-1) -> 0.0021432553 | P96: =IF('2019'!P96=0,0,(AME_2030!P96/'2019'!P96)^(1/7)-1) -> 0.00023820276 | Q96: =IF('2019'!Q96=0,0,(AME_2030!Q96/'2019'!Q96)^(1/7)-1) -> 1.6442185e-07 | R96: =IF('2019'!R96=0,0,(AME_2030!R96/'2019'!R96)^(1/7)-1) -> -2.0238261e-08 | S96: =T96 -> 3.8662049e-06 | T96: =IF('2019'!T96=0,0,(AME_2030!T96/'2019'!T96)^(1/7)-1) -> 3.8662049e-06 | U96: =IF('2019'!U96=0,0,(AME_2030!U96/'2019'!U96)^(1/7)-1) -> -1.1159997e-05 | V96: =IF('2019'!V96=0,0,(AME_2030!V96/'2019'!V96)^(1/7)-1) -> -2.6346634e-08 | W96: =IF('2019'!W96=0,0,(AME_2030!W96/'2019'!W96)^(1/7)-1) -> 0.00028364079 | X96: =IF('2019'!X96=0,0,(AME_2030!X96/'2019'!X96)^(1/7)-1) -> 5.032908e-06 | Y96: =IF('2019'!Y96=0,0,(AME_2030!Y96/'2019'!Y96)^(1/7)-1) -> 0.0024005377 | Z96: =IF('2019'!Z96=0,0,(AME_2030!Z96/'2019'!Z96)^(1/7)-1) -> -0.0011563428 | AA96: =IF('2019'!AA96=0,0,(AME_2030!AA96/'2019'!AA96)^(1/7)-1) -> 0.0013439925 | ... AU96: =IF('2019'!AU96=0,0,(AME_2030!AU96/'2019'!AU96)^(1/7)-1) -> 0.00025859473
B97: 19 | C97: 19 | D97: Business services | E97: =IF('2019'!E97=0,0,(AME_2030!E97/'2019'!E97)^(1/7)-1) -> -0.00039309953 | F97: =IF('2019'!F97=0,0,(AME_2030!F97/'2019'!F97)^(1/7)-1) -> -0.00018663633 | G97: =IF('2019'!G97=0,0,(AME_2030!G97/'2019'!G97)^(1/7)-1) -> -0.00030058252 | H97: =IF('2019'!H97=0,0,(AME_2030!H97/'2019'!H97)^(1/7)-1) -> 0.00041327675 | I97: =IF('2019'!I97=0,0,(AME_2030!I97/'2019'!I97)^(1/7)-1) -> -0.00083209465 | J97: =IF('2019'!J97=0,0,(AME_2030!J97/'2019'!J97)^(1/7)-1) -> -0.00028818907 | K97: =IF('2019 (Z)'!AW97=0,0,('AME_2030 (Z)'!AW97/'2019 (Z)'!AW97)^(1/7)-1) -> 0.0022772821 | L97: =K97 -> 0.0022772821 | M97: =IF('2019'!M97=0,0,(AME_2030!M97/'2019'!M97)^(1/7)-1) -> 0.0079257267 | N97: =IF('2019'!N97=0,0,(AME_2030!N97/'2019'!N97)^(1/7)-1) -> -0.0071750035 | O97: =IF('2019'!O97=0,0,(AME_2030!O97/'2019'!O97)^(1/7)-1) -> 0.00043617996 | P97: =IF('2019'!P97=0,0,(AME_2030!P97/'2019'!P97)^(1/7)-1) -> -0.00038613421 | Q97: =IF('2019'!Q97=0,0,(AME_2030!Q97/'2019'!Q97)^(1/7)-1) -> -0.00020641438 | R97: =IF('2019'!R97=0,0,(AME_2030!R97/'2019'!R97)^(1/7)-1) -> -0.00010903351 | S97: =T97 -> -1.9815574e-05 | T97: =IF('2019'!T97=0,0,(AME_2030!T97/'2019'!T97)^(1/7)-1) -> -1.9815574e-05 | U97: =IF('2019'!U97=0,0,(AME_2030!U97/'2019'!U97)^(1/7)-1) -> -0.00018608109 | V97: =IF('2019'!V97=0,0,(AME_2030!V97/'2019'!V97)^(1/7)-1) -> -0.00013360365 | W97: =IF('2019'!W97=0,0,(AME_2030!W97/'2019'!W97)^(1/7)-1) -> -8.4513061e-05 | X97: =IF('2019'!X97=0,0,(AME_2030!X97/'2019'!X97)^(1/7)-1) -> -0.00037229279 | Y97: =IF('2019'!Y97=0,0,(AME_2030!Y97/'2019'!Y97)^(1/7)-1) -> 0.0022080385 | Z97: =IF('2019'!Z97=0,0,(AME_2030!Z97/'2019'!Z97)^(1/7)-1) -> -0.0020087591 | AA97: =IF('2019'!AA97=0,0,(AME_2030!AA97/'2019'!AA97)^(1/7)-1) -> 0.0013143718 | ... AU97: =IF('2019'!AU97=0,0,(AME_2030!AU97/'2019'!AU97)^(1/7)-1) -> 0.00067731754
B98: 20 | C98: 20 | D98: Public services | E98: =IF('2019'!E98=0,0,(AME_2030!E98/'2019'!E98)^(1/7)-1) -> 0.0005988623 | F98: =IF('2019'!F98=0,0,(AME_2030!F98/'2019'!F98)^(1/7)-1) -> 5.9377138e-05 | G98: =IF('2019'!G98=0,0,(AME_2030!G98/'2019'!G98)^(1/7)-1) -> -2.3353151e-09 | H98: =IF('2019'!H98=0,0,(AME_2030!H98/'2019'!H98)^(1/7)-1) -> 0.033617449 | I98: =IF('2019'!I98=0,0,(AME_2030!I98/'2019'!I98)^(1/7)-1) -> -0.00025793388 | J98: =IF('2019'!J98=0,0,(AME_2030!J98/'2019'!J98)^(1/7)-1) -> -0.0072191187 | K98: =IF('2019 (Z)'!AW98=0,0,('AME_2030 (Z)'!AW98/'2019 (Z)'!AW98)^(1/7)-1) -> 0.0022954898 | L98: =K98 -> 0.0022954898 | M98: =IF('2019'!M98=0,0,(AME_2030!M98/'2019'!M98)^(1/7)-1) -> 0.0035045653 | N98: =IF('2019'!N98=0,0,(AME_2030!N98/'2019'!N98)^(1/7)-1) -> 0.015998369 | O98: =IF('2019'!O98=0,0,(AME_2030!O98/'2019'!O98)^(1/7)-1) -> 0.0028088348 | P98: =IF('2019'!P98=0,0,(AME_2030!P98/'2019'!P98)^(1/7)-1) -> -0.00016392184 | Q98: =IF('2019'!Q98=0,0,(AME_2030!Q98/'2019'!Q98)^(1/7)-1) -> 1.6442185e-07 | R98: =IF('2019'!R98=0,0,(AME_2030!R98/'2019'!R98)^(1/7)-1) -> -2.0238261e-08 | S98: =T98 -> 2.3142738e-06 | T98: =IF('2019'!T98=0,0,(AME_2030!T98/'2019'!T98)^(1/7)-1) -> 2.3142738e-06 | U98: =IF('2019'!U98=0,0,(AME_2030!U98/'2019'!U98)^(1/7)-1) -> -3.8012401e-05 | V98: =IF('2019'!V98=0,0,(AME_2030!V98/'2019'!V98)^(1/7)-1) -> -2.6346634e-08 | W98: =IF('2019'!W98=0,0,(AME_2030!W98/'2019'!W98)^(1/7)-1) -> -0.00030086615 | X98: =IF('2019'!X98=0,0,(AME_2030!X98/'2019'!X98)^(1/7)-1) -> -7.4450834e-06 | Y98: =IF('2019'!Y98=0,0,(AME_2030!Y98/'2019'!Y98)^(1/7)-1) -> 0.0024005377 | Z98: =IF('2019'!Z98=0,0,(AME_2030!Z98/'2019'!Z98)^(1/7)-1) -> -0.0011438272 | AA98: =IF('2019'!AA98=0,0,(AME_2030!AA98/'2019'!AA98)^(1/7)-1) -> 0.0013438782 | ... AU98: =IF('2019'!AU98=0,0,(AME_2030!AU98/'2019'!AU98)^(1/7)-1) -> 3.0381064e-05
B99: 21 | C99: 21 | D99: Coal | E99: =IF('2019'!E99=0,0,(AME_2030!E99/'2019'!E99)^(1/7)-1) -> -0.0013028215 | F99: =IF('2019'!F99=0,0,(AME_2030!F99/'2019'!F99)^(1/7)-1) -> -8.658091e-05 | G99: =IF('2019'!G99=0,0,(AME_2030!G99/'2019'!G99)^(1/7)-1) -> -2.3353149e-09 | H99: =IF('2019'!H99=0,0,(AME_2030!H99/'2019'!H99)^(1/7)-1) -> -0.079670847 | I99: =IF('2019'!I99=0,0,(AME_2030!I99/'2019'!I99)^(1/7)-1) -> -0.00029746392 | J99: =IF('2019'!J99=0,0,(AME_2030!J99/'2019'!J99)^(1/7)-1) -> -0.01008798 | K99: =IF('2019 (Z)'!AW99=0,0,('AME_2030 (Z)'!AW99/'2019 (Z)'!AW99)^(1/7)-1) -> 0.0023845704 | L99: =K99 -> 0.0023845704 | M99: =IF('2019'!M99=0,0,(AME_2030!M99/'2019'!M99)^(1/7)-1) -> -0.042932375 | N99: =IF('2019'!N99=0,0,(AME_2030!N99/'2019'!N99)^(1/7)-1) -> -0.036591807 | O99: =IF('2019'!O99=0,0,(AME_2030!O99/'2019'!O99)^(1/7)-1) -> -0.0081777063 | P99: =IF('2019'!P99=0,0,(AME_2030!P99/'2019'!P99)^(1/7)-1) -> 0.00058666533 | Q99: =IF('2019'!Q99=0,0,(AME_2030!Q99/'2019'!Q99)^(1/7)-1) -> 1.6442185e-07 | R99: =IF('2019'!R99=0,0,(AME_2030!R99/'2019'!R99)^(1/7)-1) -> 0 | S99: =T99 -> -2.5547003e-06 | T99: =IF('2019'!T99=0,0,(AME_2030!T99/'2019'!T99)^(1/7)-1) -> -2.5547003e-06 | U99: =IF('2019'!U99=0,0,(AME_2030!U99/'2019'!U99)^(1/7)-1) -> 0 | V99: =IF('2019'!V99=0,0,(AME_2030!V99/'2019'!V99)^(1/7)-1) -> 0 | W99: =IF('2019'!W99=0,0,(AME_2030!W99/'2019'!W99)^(1/7)-1) -> -0.0044573577 | X99: =IF('2019'!X99=0,0,(AME_2030!X99/'2019'!X99)^(1/7)-1) -> -1.6339562e-05 | Y99: =IF('2019'!Y99=0,0,(AME_2030!Y99/'2019'!Y99)^(1/7)-1) -> 0.0024005377 | Z99: =IF('2019'!Z99=0,0,(AME_2030!Z99/'2019'!Z99)^(1/7)-1) -> 0.00027629387 | AA99: =IF('2019'!AA99=0,0,(AME_2030!AA99/'2019'!AA99)^(1/7)-1) -> 0.0013440112 | ... AU99: =IF('2019'!AU99=0,0,(AME_2030!AU99/'2019'!AU99)^(1/7)-1) -> -0.01101665
B100: 22 | C100: 22 | D100: Oil | E100: =IF('2019'!E100=0,0,(AME_2030!E100/'2019'!E100)^(1/7)-1) -> -0.00019900268 | F100: =IF('2019'!F100=0,0,(AME_2030!F100/'2019'!F100)^(1/7)-1) -> 1.8715191e-05 | G100: =IF('2019'!G100=0,0,(AME_2030!G100/'2019'!G100)^(1/7)-1) -> -2.3353149e-09 | H100: =IF('2019'!H100=0,0,(AME_2030!H100/'2019'!H100)^(1/7)-1) -> -0.058681553 | I100: =IF('2019'!I100=0,0,(AME_2030!I100/'2019'!I100)^(1/7)-1) -> -0.0005659737 | J100: =IF('2019'!J100=0,0,(AME_2030!J100/'2019'!J100)^(1/7)-1) -> -0.00069827398 | K100: =IF('2019 (Z)'!AW100=0,0,('AME_2030 (Z)'!AW100/'2019 (Z)'!AW100)^(1/7)-1) -> 0.0023684354 | L100: =K100 -> 0.0023684354 | M100: =IF('2019'!M100=0,0,(AME_2030!M100/'2019'!M100)^(1/7)-1) -> -0.042585331 | N100: =IF('2019'!N100=0,0,(AME_2030!N100/'2019'!N100)^(1/7)-1) -> -0.03746156 | O100: =IF('2019'!O100=0,0,(AME_2030!O100/'2019'!O100)^(1/7)-1) -> -0.0085792208 | P100: =IF('2019'!P100=0,0,(AME_2030!P100/'2019'!P100)^(1/7)-1) -> 0.0011042474 | Q100: =IF('2019'!Q100=0,0,(AME_2030!Q100/'2019'!Q100)^(1/7)-1) -> 1.6442185e-07 | R100: =IF('2019'!R100=0,0,(AME_2030!R100/'2019'!R100)^(1/7)-1) -> -2.0238261e-08 | S100: =T100 -> -2.5547003e-06 | T100: =IF('2019'!T100=0,0,(AME_2030!T100/'2019'!T100)^(1/7)-1) -> -2.5547003e-06 | U100: =IF('2019'!U100=0,0,(AME_2030!U100/'2019'!U100)^(1/7)-1) -> -3.0157145e-05 | V100: =IF('2019'!V100=0,0,(AME_2030!V100/'2019'!V100)^(1/7)-1) -> -2.6346634e-08 | W100: =IF('2019'!W100=0,0,(AME_2030!W100/'2019'!W100)^(1/7)-1) -> 0.00013832159 | X100: =IF('2019'!X100=0,0,(AME_2030!X100/'2019'!X100)^(1/7)-1) -> -6.3413783e-06 | Y100: =IF('2019'!Y100=0,0,(AME_2030!Y100/'2019'!Y100)^(1/7)-1) -> 0.0024005377 | Z100: =IF('2019'!Z100=0,0,(AME_2030!Z100/'2019'!Z100)^(1/7)-1) -> -0.0011575767 | AA100: =IF('2019'!AA100=0,0,(AME_2030!AA100/'2019'!AA100)^(1/7)-1) -> 0.0013438338 | ... AU100: =IF('2019'!AU100=0,0,(AME_2030!AU100/'2019'!AU100)^(1/7)-1) -> -0.0011976279
B101: 23 | C101: 23 | D101: Biofuel | E101: =IF('2019'!E101=0,0,(AME_2030!E101/'2019'!E101)^(1/7)-1) -> 0.00015631919 | F101: =IF('2019'!F101=0,0,(AME_2030!F101/'2019'!F101)^(1/7)-1) -> 0.00081507841 | G101: =IF('2019'!G101=0,0,(AME_2030!G101/'2019'!G101)^(1/7)-1) -> -2.3353151e-09 | H101: =IF('2019'!H101=0,0,(AME_2030!H101/'2019'!H101)^(1/7)-1) -> 0.11976939 | I101: =IF('2019'!I101=0,0,(AME_2030!I101/'2019'!I101)^(1/7)-1) -> -0.00037575257 | J101: =IF('2019'!J101=0,0,(AME_2030!J101/'2019'!J101)^(1/7)-1) -> 0 | K101: =IF('2019 (Z)'!AW101=0,0,('AME_2030 (Z)'!AW101/'2019 (Z)'!AW101)^(1/7)-1) -> 0.0022936901 | L101: =K101 -> 0.0022936901 | M101: =IF('2019'!M101=0,0,(AME_2030!M101/'2019'!M101)^(1/7)-1) -> -0.001024403 | N101: =IF('2019'!N101=0,0,(AME_2030!N101/'2019'!N101)^(1/7)-1) -> -0.0013528264 | O101: =IF('2019'!O101=0,0,(AME_2030!O101/'2019'!O101)^(1/7)-1) -> -0.020719813 | P101: =IF('2019'!P101=0,0,(AME_2030!P101/'2019'!P101)^(1/7)-1) -> 0.0002651138 | Q101: =IF('2019'!Q101=0,0,(AME_2030!Q101/'2019'!Q101)^(1/7)-1) -> 1.6442185e-07 | R101: =IF('2019'!R101=0,0,(AME_2030!R101/'2019'!R101)^(1/7)-1) -> 0 | S101: =T101 -> 0 | T101: =IF('2019'!T101=0,0,(AME_2030!T101/'2019'!T101)^(1/7)-1) -> 0 | U101: =IF('2019'!U101=0,0,(AME_2030!U101/'2019'!U101)^(1/7)-1) -> 7.6186279e-06 | V101: =IF('2019'!V101=0,0,(AME_2030!V101/'2019'!V101)^(1/7)-1) -> 0 | W101: =IF('2019'!W101=0,0,(AME_2030!W101/'2019'!W101)^(1/7)-1) -> 0 | X101: =IF('2019'!X101=0,0,(AME_2030!X101/'2019'!X101)^(1/7)-1) -> 0 | Y101: =IF('2019'!Y101=0,0,(AME_2030!Y101/'2019'!Y101)^(1/7)-1) -> 0.0024005377 | Z101: =IF('2019'!Z101=0,0,(AME_2030!Z101/'2019'!Z101)^(1/7)-1) -> 0.00028114157 | AA101: =IF('2019'!AA101=0,0,(AME_2030!AA101/'2019'!AA101)^(1/7)-1) -> 0.0013438004 | ... AU101: =IF('2019'!AU101=0,0,(AME_2030!AU101/'2019'!AU101)^(1/7)-1) -> 0
B102: 24 | C102: 24 | D102: Electricity by nuclear | E102: =IF('2019'!E102=0,0,(AME_2030!E102/'2019'!E102)^(1/7)-1) -> -0.00010711571 | F102: =IF('2019'!F102=0,0,(AME_2030!F102/'2019'!F102)^(1/7)-1) -> -1.9086265e-05 | G102: =IF('2019'!G102=0,0,(AME_2030!G102/'2019'!G102)^(1/7)-1) -> -2.3353151e-09 | H102: =IF('2019'!H102=0,0,(AME_2030!H102/'2019'!H102)^(1/7)-1) -> 0.024072716 | I102: =IF('2019'!I102=0,0,(AME_2030!I102/'2019'!I102)^(1/7)-1) -> 9.0619195e-05 | J102: =IF('2019'!J102=0,0,(AME_2030!J102/'2019'!J102)^(1/7)-1) -> -0.011162437 | K102: =IF('2019 (Z)'!AW102=0,0,('AME_2030 (Z)'!AW102/'2019 (Z)'!AW102)^(1/7)-1) -> 0.002298298 | L102: =K102 -> 0.002298298 | M102: =IF('2019'!M102=0,0,(AME_2030!M102/'2019'!M102)^(1/7)-1) -> -0.0097230823 | N102: =IF('2019'!N102=0,0,(AME_2030!N102/'2019'!N102)^(1/7)-1) -> 0.035415382 | O102: =IF('2019'!O102=0,0,(AME_2030!O102/'2019'!O102)^(1/7)-1) -> -0.039169872 | P102: =IF('2019'!P102=0,0,(AME_2030!P102/'2019'!P102)^(1/7)-1) -> -4.6223739e-05 | Q102: =IF('2019'!Q102=0,0,(AME_2030!Q102/'2019'!Q102)^(1/7)-1) -> 1.6442185e-07 | R102: =IF('2019'!R102=0,0,(AME_2030!R102/'2019'!R102)^(1/7)-1) -> -2.0238261e-08 | S102: =T102 -> 6.4570293e-07 | T102: =IF('2019'!T102=0,0,(AME_2030!T102/'2019'!T102)^(1/7)-1) -> 6.4570293e-07 | U102: =IF('2019'!U102=0,0,(AME_2030!U102/'2019'!U102)^(1/7)-1) -> 0 | V102: =IF('2019'!V102=0,0,(AME_2030!V102/'2019'!V102)^(1/7)-1) -> -2.6346634e-08 | W102: =IF('2019'!W102=0,0,(AME_2030!W102/'2019'!W102)^(1/7)-1) -> -5.1894461e-05 | X102: =IF('2019'!X102=0,0,(AME_2030!X102/'2019'!X102)^(1/7)-1) -> 5.6581105e-06 | Y102: =IF('2019'!Y102=0,0,(AME_2030!Y102/'2019'!Y102)^(1/7)-1) -> 0.0024005377 | Z102: =IF('2019'!Z102=0,0,(AME_2030!Z102/'2019'!Z102)^(1/7)-1) -> -0.0011572408 | AA102: =IF('2019'!AA102=0,0,(AME_2030!AA102/'2019'!AA102)^(1/7)-1) -> 0.0013440072 | ... AU102: =IF('2019'!AU102=0,0,(AME_2030!AU102/'2019'!AU102)^(1/7)-1) -> 0.00089723286
B103: 25 | C103: 25 | D103: Electricity by petroleum | E103: =IF('2019'!E103=0,0,(AME_2030!E103/'2019'!E103)^(1/7)-1) -> 0.00028588079 | F103: =IF('2019'!F103=0,0,(AME_2030!F103/'2019'!F103)^(1/7)-1) -> 7.7685987e-05 | G103: =IF('2019'!G103=0,0,(AME_2030!G103/'2019'!G103)^(1/7)-1) -> -2.3353149e-09 | H103: =IF('2019'!H103=0,0,(AME_2030!H103/'2019'!H103)^(1/7)-1) -> 0.023963905 | I103: =IF('2019'!I103=0,0,(AME_2030!I103/'2019'!I103)^(1/7)-1) -> 4.4246249e-05 | J103: =IF('2019'!J103=0,0,(AME_2030!J103/'2019'!J103)^(1/7)-1) -> -0.016824161 | K103: =IF('2019 (Z)'!AW103=0,0,('AME_2030 (Z)'!AW103/'2019 (Z)'!AW103)^(1/7)-1) -> 0.0023015954 | L103: =K103 -> 0.0023015954 | M103: =IF('2019'!M103=0,0,(AME_2030!M103/'2019'!M103)^(1/7)-1) -> -0.0077395121 | N103: =IF('2019'!N103=0,0,(AME_2030!N103/'2019'!N103)^(1/7)-1) -> 0.035993893 | O103: =IF('2019'!O103=0,0,(AME_2030!O103/'2019'!O103)^(1/7)-1) -> -0.045000482 | P103: =IF('2019'!P103=0,0,(AME_2030!P103/'2019'!P103)^(1/7)-1) -> 1.071137e-05 | Q103: =IF('2019'!Q103=0,0,(AME_2030!Q103/'2019'!Q103)^(1/7)-1) -> 1.6442185e-07 | R103: =IF('2019'!R103=0,0,(AME_2030!R103/'2019'!R103)^(1/7)-1) -> -2.0238261e-08 | S103: =T103 -> 6.1823785e-07 | T103: =IF('2019'!T103=0,0,(AME_2030!T103/'2019'!T103)^(1/7)-1) -> 6.1823785e-07 | U103: =IF('2019'!U103=0,0,(AME_2030!U103/'2019'!U103)^(1/7)-1) -> 0 | V103: =IF('2019'!V103=0,0,(AME_2030!V103/'2019'!V103)^(1/7)-1) -> 0 | W103: =IF('2019'!W103=0,0,(AME_2030!W103/'2019'!W103)^(1/7)-1) -> 0.00010518284 | X103: =IF('2019'!X103=0,0,(AME_2030!X103/'2019'!X103)^(1/7)-1) -> 1.0902174e-05 | Y103: =IF('2019'!Y103=0,0,(AME_2030!Y103/'2019'!Y103)^(1/7)-1) -> 0 | Z103: =IF('2019'!Z103=0,0,(AME_2030!Z103/'2019'!Z103)^(1/7)-1) -> -0.0011577024 | AA103: =IF('2019'!AA103=0,0,(AME_2030!AA103/'2019'!AA103)^(1/7)-1) -> 0.0013440083 | ... AU103: =IF('2019'!AU103=0,0,(AME_2030!AU103/'2019'!AU103)^(1/7)-1) -> -0.01708125
B104: 26 | C104: 26 | D104: Electricity by gas | E104: =IF('2019'!E104=0,0,(AME_2030!E104/'2019'!E104)^(1/7)-1) -> -0.0003474257 | F104: =IF('2019'!F104=0,0,(AME_2030!F104/'2019'!F104)^(1/7)-1) -> -4.9403844e-05 | G104: =IF('2019'!G104=0,0,(AME_2030!G104/'2019'!G104)^(1/7)-1) -> -2.3353149e-09 | H104: =IF('2019'!H104=0,0,(AME_2030!H104/'2019'!H104)^(1/7)-1) -> 0.024043467 | I104: =IF('2019'!I104=0,0,(AME_2030!I104/'2019'!I104)^(1/7)-1) -> 4.3750642e-05 | J104: =IF('2019'!J104=0,0,(AME_2030!J104/'2019'!J104)^(1/7)-1) -> -0.016671806 | K104: =IF('2019 (Z)'!AW104=0,0,('AME_2030 (Z)'!AW104/'2019 (Z)'!AW104)^(1/7)-1) -> 0.0022969982 | L104: =K104 -> 0.0022969982 | M104: =IF('2019'!M104=0,0,(AME_2030!M104/'2019'!M104)^(1/7)-1) -> -0.017481139 | N104: =IF('2019'!N104=0,0,(AME_2030!N104/'2019'!N104)^(1/7)-1) -> 0.036012665 | O104: =IF('2019'!O104=0,0,(AME_2030!O104/'2019'!O104)^(1/7)-1) -> -0.034778484 | P104: =IF('2019'!P104=0,0,(AME_2030!P104/'2019'!P104)^(1/7)-1) -> 1.0410686e-05 | Q104: =IF('2019'!Q104=0,0,(AME_2030!Q104/'2019'!Q104)^(1/7)-1) -> 1.6442185e-07 | R104: =IF('2019'!R104=0,0,(AME_2030!R104/'2019'!R104)^(1/7)-1) -> -2.0238261e-08 | S104: =T104 -> 6.1889362e-07 | T104: =IF('2019'!T104=0,0,(AME_2030!T104/'2019'!T104)^(1/7)-1) -> 6.1889362e-07 | U104: =IF('2019'!U104=0,0,(AME_2030!U104/'2019'!U104)^(1/7)-1) -> 0 | V104: =IF('2019'!V104=0,0,(AME_2030!V104/'2019'!V104)^(1/7)-1) -> 0 | W104: =IF('2019'!W104=0,0,(AME_2030!W104/'2019'!W104)^(1/7)-1) -> -0.0001431759 | X104: =IF('2019'!X104=0,0,(AME_2030!X104/'2019'!X104)^(1/7)-1) -> 7.4876917e-06 | Y104: =IF('2019'!Y104=0,0,(AME_2030!Y104/'2019'!Y104)^(1/7)-1) -> 0 | Z104: =IF('2019'!Z104=0,0,(AME_2030!Z104/'2019'!Z104)^(1/7)-1) -> -0.0011548958 | AA104: =IF('2019'!AA104=0,0,(AME_2030!AA104/'2019'!AA104)^(1/7)-1) -> 0.0013440104 | ... AU104: =IF('2019'!AU104=0,0,(AME_2030!AU104/'2019'!AU104)^(1/7)-1) -> 0.00015445291
B105: 27 | C105: 27 | D105: Coal-fired electricity | E105: =IF('2019'!E105=0,0,(AME_2030!E105/'2019'!E105)^(1/7)-1) -> -0.00035072753 | F105: =IF('2019'!F105=0,0,(AME_2030!F105/'2019'!F105)^(1/7)-1) -> -4.9397903e-05 | G105: =IF('2019'!G105=0,0,(AME_2030!G105/'2019'!G105)^(1/7)-1) -> -2.3353149e-09 | H105: =IF('2019'!H105=0,0,(AME_2030!H105/'2019'!H105)^(1/7)-1) -> 0.023945085 | I105: =IF('2019'!I105=0,0,(AME_2030!I105/'2019'!I105)^(1/7)-1) -> 4.4363113e-05 | J105: =IF('2019'!J105=0,0,(AME_2030!J105/'2019'!J105)^(1/7)-1) -> -0.016780319 | K105: =IF('2019 (Z)'!AW105=0,0,('AME_2030 (Z)'!AW105/'2019 (Z)'!AW105)^(1/7)-1) -> 0.0023015777 | L105: =K105 -> 0.0023015777 | M105: =IF('2019'!M105=0,0,(AME_2030!M105/'2019'!M105)^(1/7)-1) -> -0.0077474971 | N105: =IF('2019'!N105=0,0,(AME_2030!N105/'2019'!N105)^(1/7)-1) -> 0.035989457 | O105: =IF('2019'!O105=0,0,(AME_2030!O105/'2019'!O105)^(1/7)-1) -> -0.044659172 | P105: =IF('2019'!P105=0,0,(AME_2030!P105/'2019'!P105)^(1/7)-1) -> 1.1049354e-05 | Q105: =IF('2019'!Q105=0,0,(AME_2030!Q105/'2019'!Q105)^(1/7)-1) -> 1.6442185e-07 | R105: =IF('2019'!R105=0,0,(AME_2030!R105/'2019'!R105)^(1/7)-1) -> -2.0238261e-08 | S105: =T105 -> 6.1748781e-07 | T105: =IF('2019'!T105=0,0,(AME_2030!T105/'2019'!T105)^(1/7)-1) -> 6.1748781e-07 | U105: =IF('2019'!U105=0,0,(AME_2030!U105/'2019'!U105)^(1/7)-1) -> 0 | V105: =IF('2019'!V105=0,0,(AME_2030!V105/'2019'!V105)^(1/7)-1) -> 0 | W105: =IF('2019'!W105=0,0,(AME_2030!W105/'2019'!W105)^(1/7)-1) -> -0.00015834985 | X105: =IF('2019'!X105=0,0,(AME_2030!X105/'2019'!X105)^(1/7)-1) -> 4.9580362e-06 | Y105: =IF('2019'!Y105=0,0,(AME_2030!Y105/'2019'!Y105)^(1/7)-1) -> 0 | Z105: =IF('2019'!Z105=0,0,(AME_2030!Z105/'2019'!Z105)^(1/7)-1) -> -0.0011567109 | AA105: =IF('2019'!AA105=0,0,(AME_2030!AA105/'2019'!AA105)^(1/7)-1) -> 0.0013440083 | ... AU105: =IF('2019'!AU105=0,0,(AME_2030!AU105/'2019'!AU105)^(1/7)-1) -> -0.031687289
... B115: 37 | C115: 37 | D115: Other natural gas and heat | E115: =IF('2019'!E115=0,0,(AME_2030!E115/'2019'!E115)^(1/7)-1) -> 0.0058175231 | F115: =IF('2019'!F115=0,0,(AME_2030!F115/'2019'!F115)^(1/7)-1) -> 0 | G115: =IF('2019'!G115=0,0,(AME_2030!G115/'2019'!G115)^(1/7)-1) -> 0 | H115: =IF('2019'!H115=0,0,(AME_2030!H115/'2019'!H115)^(1/7)-1) -> 0 | I115: =IF('2019'!I115=0,0,(AME_2030!I115/'2019'!I115)^(1/7)-1) -> 0 | J115: =IF('2019'!J115=0,0,(AME_2030!J115/'2019'!J115)^(1/7)-1) -> 0.00083496361 | K115: =IF('2019 (Z)'!AW115=0,0,('AME_2030 (Z)'!AW115/'2019 (Z)'!AW115)^(1/7)-1) -> 0.002294432 | L115: =K115 -> 0.002294432 | M115: =IF('2019'!M115=0,0,(AME_2030!M115/'2019'!M115)^(1/7)-1) -> -0.044195543 | N115: =IF('2019'!N115=0,0,(AME_2030!N115/'2019'!N115)^(1/7)-1) -> 0 | O115: =IF('2019'!O115=0,0,(AME_2030!O115/'2019'!O115)^(1/7)-1) -> 0 | P115: =IF('2019'!P115=0,0,(AME_2030!P115/'2019'!P115)^(1/7)-1) -> -0.00026056813 | Q115: =IF('2019'!Q115=0,0,(AME_2030!Q115/'2019'!Q115)^(1/7)-1) -> 1.6442185e-07 | R115: =IF('2019'!R115=0,0,(AME_2030!R115/'2019'!R115)^(1/7)-1) -> 0 | S115: =T115 -> -2.5547003e-06 | T115: =IF('2019'!T115=0,0,(AME_2030!T115/'2019'!T115)^(1/7)-1) -> -2.5547003e-06 | U115: =IF('2019'!U115=0,0,(AME_2030!U115/'2019'!U115)^(1/7)-1) -> 0 | V115: =IF('2019'!V115=0,0,(AME_2030!V115/'2019'!V115)^(1/7)-1) -> 0 | W115: =IF('2019'!W115=0,0,(AME_2030!W115/'2019'!W115)^(1/7)-1) -> -0.00011502747 | X115: =IF('2019'!X115=0,0,(AME_2030!X115/'2019'!X115)^(1/7)-1) -> 5.8154676e-06 | Y115: =IF('2019'!Y115=0,0,(AME_2030!Y115/'2019'!Y115)^(1/7)-1) -> 0 | Z115: =IF('2019'!Z115=0,0,(AME_2030!Z115/'2019'!Z115)^(1/7)-1) -> 0.00021145239 | AA115: =IF('2019'!AA115=0,0,(AME_2030!AA115/'2019'!AA115)^(1/7)-1) -> 0.0012866364 | ... AU115: =IF('2019'!AU115=0,0,(AME_2030!AU115/'2019'!AU115)^(1/7)-1) -> 0

Sheet Delta AMS_2030
A1: Variation relative 2019-2030, annualisée sur 7 ans pour coller avec le point de départ 3ME (2023-2030) | D1: category | E1: 01 | F1: 02 | G1: 03 | H1: 04 | I1: 05 | J1: 06 | K1: 07 | L1: 08 | M1: 09 | N1: 10 | O1: 11 | P1: 12 | Q1: 13 | R1: 14 | S1: 15 | T1: 16 | U1: 17 | V1: 18 | W1: 19 | X1: 20 | Y1: 21 | Z1: 22 | AA1: 23 | AB1: 24 | AC1: 25 | AD1: 26 | AE1: 27 | AF1: 28 | AG1: 29 | AH1: 30 | AI1: 31 | AJ1: 32 | AK1: 33 | AL1: 34 | AM1: 35 | AN1: 36 | AO1: 37 | AP1: Household | AQ1: Government | AR1: GFCF | AS1: Exports | AT1: Supply | AU1: Imports
D2: sub_category | E2: 01 | F2: 02 | G2: 03 | H2: 04 | I2: 05 | J2: 06 | K2: 07 | L2: 08 | M2: 09 | N2: 10 | O2: 11 | P2: 12 | Q2: 13 | R2: 14 | S2: 15 | T2: 16 | U2: 17 | V2: 18 | W2: 19 | X2: 20 | Y2: 21 | Z2: 22 | AA2: 23 | AB2: 24 | AC2: 25 | AD2: 26 | AE2: 27 | AF2: 28 | AG2: 29 | AH2: 30 | AI2: 31 | AJ2: 32 | AK2: 33 | AL2: 34 | AM2: 35 | AN2: 36 | AO2: 37 | AP2: C | AQ2: G | AR2: I | AS2: E | AT2: x | AU2: M
D3: sector | E3: Products of agriculture, forestry and fishing | F3: Food products and beverages | G3: Motor vehicles, trailers and semi-trailers | H3: Glass and glass products | I3: Ceramic products and building materials | J3: Articles of paper and paperboard | K3: Inorganic basic chemicals | L3: Organic basic chemicals | M3: Plastics products | N3: Basic iron and steel and of ferro-alloys | O3: Non-ferrous metals | P3: Other industries | Q3: Construction of buildings and Civil engineering | R3: Rail transport (Passenger and Freight) | S3: Passenger transport by road | T3: Freight transport by road and transport via pipeline | U3: Water transport | V3: Air transport | W3: Business services | X3: Public services | Y3: Coal | Z3: Oil | AA3: Biofuel | AB3: Electricity by nuclear | AC3: Electricity by petroleum | AD3: Electricity by gas | AE3: Coal-fired electricity | AF3: Electricity by wind | AG3: Electricity by solar | AH3: Electricity by hydro | AI3: Other electricity | AJ3: Natural gas | AK3: Wood | AL3: Biogas | AM3: Waste incineration | AN3: Geothermal | AO3: Other natural gas and heat
A4: region | B4: category | C4: sub_category | D4: sector | E4: A | F4: A | G4: A | H4: A | I4: A | J4: A | K4: A | L4: A | M4: A | N4: A | O4: A | P4: A | Q4: A | R4: A | S4: A | T4: A | U4: A | V4: A | W4: A | X4: A | Y4: A | Z4: A | AA4: A | AB4: A | AC4: A | AD4: A | AE4: A | AF4: A | AG4: A | AH4: A | AI4: A | AJ4: A | AK4: A | AL4: A | AM4: A | AN4: A | AO4: A
A5: FR | B5: 01 | C5: 01 | D5: Products of agriculture, forestry and fishing | E5: =IF('2019'!E5=0,0,(AMS_2030!E5/'2019'!E5)^(1/7)-1) -> -0.005936127 | F5: =IF('2019'!F5=0,0,(AMS_2030!F5/'2019'!F5)^(1/7)-1) -> -0.00037257094 | G5: =IF('2019'!G5=0,0,(AMS_2030!G5/'2019'!G5)^(1/7)-1) -> 6.3933192e-10 | H5: =IF('2019'!H5=0,0,(AMS_2030!H5/'2019'!H5)^(1/7)-1) -> 0 | I5: =IF('2019'!I5=0,0,(AMS_2030!I5/'2019'!I5)^(1/7)-1) -> 0 | J5: =IF('2019'!J5=0,0,(AMS_2030!J5/'2019'!J5)^(1/7)-1) -> -0.013837903 | K5: =IF('2019 (Z)'!AW5=0,0,('AMS_2030 (Z)'!AW5/'2019 (Z)'!AW5)^(1/7)-1) -> 0.0025533199 | L5: =K5 -> 0.0025533199 | M5: =IF('2019'!M5=0,0,(AMS_2030!M5/'2019'!M5)^(1/7)-1) -> -0.0051036727 | N5: =IF('2019'!N5=0,0,(AMS_2030!N5/'2019'!N5)^(1/7)-1) -> 0 | O5: =IF('2019'!O5=0,0,(AMS_2030!O5/'2019'!O5)^(1/7)-1) -> 0 | P5: =IF('2019'!P5=0,0,(AMS_2030!P5/'2019'!P5)^(1/7)-1) -> 0.0056528768 | Q5: =IF('2019'!Q5=0,0,(AMS_2030!Q5/'2019'!Q5)^(1/7)-1) -> 0.015037999 | R5: =IF('2019'!R5=0,0,(AMS_2030!R5/'2019'!R5)^(1/7)-1) -> 1.2248835e-08 | S5: =T5 -> 7.9371765e-06 | T5: =IF('2019'!T5=0,0,(AMS_2030!T5/'2019'!T5)^(1/7)-1) -> 7.9371765e-06 | U5: =IF('2019'!U5=0,0,(AMS_2030!U5/'2019'!U5)^(1/7)-1) -> 0 | V5: =IF('2019'!V5=0,0,(AMS_2030!V5/'2019'!V5)^(1/7)-1) -> 0 | W5: =IF('2019'!W5=0,0,(AMS_2030!W5/'2019'!W5)^(1/7)-1) -> 0.0054949474 | X5: =IF('2019'!X5=0,0,(AMS_2030!X5/'2019'!X5)^(1/7)-1) -> 0.0031515407 | Y5: =IF('2019'!Y5=0,0,(AMS_2030!Y5/'2019'!Y5)^(1/7)-1) -> 0 | Z5: =IF('2019'!Z5=0,0,(AMS_2030!Z5/'2019'!Z5)^(1/7)-1) -> -0.00060110576 | AA5: =IF('2019'!AA5=0,0,(AMS_2030!AA5/'2019'!AA5)^(1/7)-1) -> 0.0037471578 | ... AU5: =IF('2019'!AU5=0,0,(AMS_2030!AU5/'2019'!AU5)^(1/7)-1) -> 0
B6: 02 | C6: 02 | D6: Food products and beverages | E6: =IF('2019'!E6=0,0,(AMS_2030!E6/'2019'!E6)^(1/7)-1) -> -0.014054396 | F6: =IF('2019'!F6=0,0,(AMS_2030!F6/'2019'!F6)^(1/7)-1) -> -0.00072477891 | G6: =IF('2019'!G6=0,0,(AMS_2030!G6/'2019'!G6)^(1/7)-1) -> 6.3933192e-10 | H6: =IF('2019'!H6=0,0,(AMS_2030!H6/'2019'!H6)^(1/7)-1) -> 0.0084034671 | I6: =IF('2019'!I6=0,0,(AMS_2030!I6/'2019'!I6)^(1/7)-1) -> 0.0041708248 | J6: =IF('2019'!J6=0,0,(AMS_2030!J6/'2019'!J6)^(1/7)-1) -> 0.00026801839 | K6: =IF('2019 (Z)'!AW6=0,0,('AMS_2030 (Z)'!AW6/'2019 (Z)'!AW6)^(1/7)-1) -> 0.0025663644 | L6: =K6 -> 0.0025663644 | M6: =IF('2019'!M6=0,0,(AMS_2030!M6/'2019'!M6)^(1/7)-1) -> 0.0019160565 | N6: =IF('2019'!N6=0,0,(AMS_2030!N6/'2019'!N6)^(1/7)-1) -> -0.002355503 | O6: =IF('2019'!O6=0,0,(AMS_2030!O6/'2019'!O6)^(1/7)-1) -> -0.0055615279 | P6: =IF('2019'!P6=0,0,(AMS_2030!P6/'2019'!P6)^(1/7)-1) -> -0.00088030661 | Q6: =IF('2019'!Q6=0,0,(AMS_2030!Q6/'2019'!Q6)^(1/7)-1) -> -8.5851124e-08 | R6: =IF('2019'!R6=0,0,(AMS_2030!R6/'2019'!R6)^(1/7)-1) -> 1.2248834e-08 | S6: =T6 -> 7.6030802e-07 | T6: =IF('2019'!T6=0,0,(AMS_2030!T6/'2019'!T6)^(1/7)-1) -> 7.6030802e-07 | U6: =IF('2019'!U6=0,0,(AMS_2030!U6/'2019'!U6)^(1/7)-1) -> 1.2529201e-07 | V6: =IF('2019'!V6=0,0,(AMS_2030!V6/'2019'!V6)^(1/7)-1) -> 1.2112876e-08 | W6: =IF('2019'!W6=0,0,(AMS_2030!W6/'2019'!W6)^(1/7)-1) -> -0.00084754325 | X6: =IF('2019'!X6=0,0,(AMS_2030!X6/'2019'!X6)^(1/7)-1) -> -0.0018307263 | Y6: =IF('2019'!Y6=0,0,(AMS_2030!Y6/'2019'!Y6)^(1/7)-1) -> -0.0032151038 | Z6: =IF('2019'!Z6=0,0,(AMS_2030!Z6/'2019'!Z6)^(1/7)-1) -> -0.0011551696 | AA6: =IF('2019'!AA6=0,0,(AMS_2030!AA6/'2019'!AA6)^(1/7)-1) -> 0.0037471408 | ... AU6: =IF('2019'!AU6=0,0,(AMS_2030!AU6/'2019'!AU6)^(1/7)-1) -> 0
B7: 03 | C7: 03 | D7: Motor vehicles, trailers and semi-trailers | E7: =IF('2019'!E7=0,0,(AMS_2030!E7/'2019'!E7)^(1/7)-1) -> -0.00091591274 | F7: =IF('2019'!F7=0,0,(AMS_2030!F7/'2019'!F7)^(1/7)-1) -> 0.001468464 | G7: =IF('2019'!G7=0,0,(AMS_2030!G7/'2019'!G7)^(1/7)-1) -> 6.3933192e-10 | H7: =IF('2019'!H7=0,0,(AMS_2030!H7/'2019'!H7)^(1/7)-1) -> 0.0052679287 | I7: =IF('2019'!I7=0,0,(AMS_2030!I7/'2019'!I7)^(1/7)-1) -> -0.0016664124 | J7: =IF('2019'!J7=0,0,(AMS_2030!J7/'2019'!J7)^(1/7)-1) -> 0.00059616421 | K7: =IF('2019 (Z)'!AW7=0,0,('AMS_2030 (Z)'!AW7/'2019 (Z)'!AW7)^(1/7)-1) -> 0.0025565855 | L7: =K7 -> 0.0025565855 | M7: =IF('2019'!M7=0,0,(AMS_2030!M7/'2019'!M7)^(1/7)-1) -> -0.0063782203 | N7: =IF('2019'!N7=0,0,(AMS_2030!N7/'2019'!N7)^(1/7)-1) -> -0.0052104679 | O7: =IF('2019'!O7=0,0,(AMS_2030!O7/'2019'!O7)^(1/7)-1) -> 0.0013100795 | P7: =IF('2019'!P7=0,0,(AMS_2030!P7/'2019'!P7)^(1/7)-1) -> 0.00075537108 | Q7: =IF('2019'!Q7=0,0,(AMS_2030!Q7/'2019'!Q7)^(1/7)-1) -> -8.5851124e-08 | R7: =IF('2019'!R7=0,0,(AMS_2030!R7/'2019'!R7)^(1/7)-1) -> 1.2248835e-08 | S7: =T7 -> 1.3317133e-05 | T7: =IF('2019'!T7=0,0,(AMS_2030!T7/'2019'!T7)^(1/7)-1) -> 1.3317133e-05 | U7: =IF('2019'!U7=0,0,(AMS_2030!U7/'2019'!U7)^(1/7)-1) -> 3.3264061e-07 | V7: =IF('2019'!V7=0,0,(AMS_2030!V7/'2019'!V7)^(1/7)-1) -> 1.2112876e-08 | W7: =IF('2019'!W7=0,0,(AMS_2030!W7/'2019'!W7)^(1/7)-1) -> 0.00043156057 | X7: =IF('2019'!X7=0,0,(AMS_2030!X7/'2019'!X7)^(1/7)-1) -> 1.0166591e-05 | Y7: =IF('2019'!Y7=0,0,(AMS_2030!Y7/'2019'!Y7)^(1/7)-1) -> -0.0032151038 | Z7: =IF('2019'!Z7=0,0,(AMS_2030!Z7/'2019'!Z7)^(1/7)-1) -> -0.0011168865 | AA7: =IF('2019'!AA7=0,0,(AMS_2030!AA7/'2019'!AA7)^(1/7)-1) -> 0.0037470887 | ... AU7: =IF('2019'!AU7=0,0,(AMS_2030!AU7/'2019'!AU7)^(1/7)-1) -> 0
B8: 04 | C8: 04 | D8: Glass and glass products | E8: =IF('2019'!E8=0,0,(AMS_2030!E8/'2019'!E8)^(1/7)-1) -> 0.017781539 | F8: =IF('2019'!F8=0,0,(AMS_2030!F8/'2019'!F8)^(1/7)-1) -> 0.20966177 | G8: =IF('2019'!G8=0,0,(AMS_2030!G8/'2019'!G8)^(1/7)-1) -> 0.17441652 | H8: =IF('2019'!H8=0,0,(AMS_2030!H8/'2019'!H8)^(1/7)-1) -> -0.16814549 | I8: =IF('2019'!I8=0,0,(AMS_2030!I8/'2019'!I8)^(1/7)-1) -> 0.0045368224 | J8: =IF('2019'!J8=0,0,(AMS_2030!J8/'2019'!J8)^(1/7)-1) -> -0.025767008 | K8: =IF('2019 (Z)'!AW8=0,0,('AMS_2030 (Z)'!AW8/'2019 (Z)'!AW8)^(1/7)-1) -> 0.14213615 | L8: =K8 -> 0.14213615 | M8: =IF('2019'!M8=0,0,(AMS_2030!M8/'2019'!M8)^(1/7)-1) -> 0.0092801857 | N8: =IF('2019'!N8=0,0,(AMS_2030!N8/'2019'!N8)^(1/7)-1) -> -0.0044818792 | O8: =IF('2019'!O8=0,0,(AMS_2030!O8/'2019'!O8)^(1/7)-1) -> 0.013899089 | P8: =IF('2019'!P8=0,0,(AMS_2030!P8/'2019'!P8)^(1/7)-1) -> -0.041448041 | Q8: =IF('2019'!Q8=0,0,(AMS_2030!Q8/'2019'!Q8)^(1/7)-1) -> -0.0005183924 | R8: =IF('2019'!R8=0,0,(AMS_2030!R8/'2019'!R8)^(1/7)-1) -> 0.072447169 | S8: =T8 -> -0.00022865337 | T8: =IF('2019'!T8=0,0,(AMS_2030!T8/'2019'!T8)^(1/7)-1) -> -0.00022865337 | U8: =IF('2019'!U8=0,0,(AMS_2030!U8/'2019'!U8)^(1/7)-1) -> 0.027102461 | V8: =IF('2019'!V8=0,0,(AMS_2030!V8/'2019'!V8)^(1/7)-1) -> 0.023013292 | W8: =IF('2019'!W8=0,0,(AMS_2030!W8/'2019'!W8)^(1/7)-1) -> 0.00080952578 | X8: =IF('2019'!X8=0,0,(AMS_2030!X8/'2019'!X8)^(1/7)-1) -> -0.00029762635 | Y8: =IF('2019'!Y8=0,0,(AMS_2030!Y8/'2019'!Y8)^(1/7)-1) -> -0.0020822955 | Z8: =IF('2019'!Z8=0,0,(AMS_2030!Z8/'2019'!Z8)^(1/7)-1) -> 0.0030351268 | AA8: =IF('2019'!AA8=0,0,(AMS_2030!AA8/'2019'!AA8)^(1/7)-1) -> 0.0039512493 | ... AU8: =IF('2019'!AU8=0,0,(AMS_2030!AU8/'2019'!AU8)^(1/7)-1) -> 0
B9: 05 | C9: 05 | D9: Ceramic products and building materials | E9: =IF('2019'!E9=0,0,(AMS_2030!E9/'2019'!E9)^(1/7)-1) -> 0.00093683382 | F9: =IF('2019'!F9=0,0,(AMS_2030!F9/'2019'!F9)^(1/7)-1) -> 0.0020971015 | G9: =IF('2019'!G9=0,0,(AMS_2030!G9/'2019'!G9)^(1/7)-1) -> 6.3933192e-10 | H9: =IF('2019'!H9=0,0,(AMS_2030!H9/'2019'!H9)^(1/7)-1) -> 0.012080944 | I9: =IF('2019'!I9=0,0,(AMS_2030!I9/'2019'!I9)^(1/7)-1) -> -0.013842163 | J9: =IF('2019'!J9=0,0,(AMS_2030!J9/'2019'!J9)^(1/7)-1) -> 0.00013171999 | K9: =IF('2019 (Z)'!AW9=0,0,('AMS_2030 (Z)'!AW9/'2019 (Z)'!AW9)^(1/7)-1) -> 0.0025170985 | L9: =K9 -> 0.0025170985 | M9: =IF('2019'!M9=0,0,(AMS_2030!M9/'2019'!M9)^(1/7)-1) -> 0.017404413 | N9: =IF('2019'!N9=0,0,(AMS_2030!N9/'2019'!N9)^(1/7)-1) -> -0.0015684384 | O9: =IF('2019'!O9=0,0,(AMS_2030!O9/'2019'!O9)^(1/7)-1) -> 0.014288952 | P9: =IF('2019'!P9=0,0,(AMS_2030!P9/'2019'!P9)^(1/7)-1) -> -0.00045113707 | Q9: =IF('2019'!Q9=0,0,(AMS_2030!Q9/'2019'!Q9)^(1/7)-1) -> -0.0012550505 | R9: =IF('2019'!R9=0,0,(AMS_2030!R9/'2019'!R9)^(1/7)-1) -> 1.2248834e-08 | S9: =T9 -> -0.00014591348 | T9: =IF('2019'!T9=0,0,(AMS_2030!T9/'2019'!T9)^(1/7)-1) -> -0.00014591348 | U9: =IF('2019'!U9=0,0,(AMS_2030!U9/'2019'!U9)^(1/7)-1) -> -2.7950418e-09 | V9: =IF('2019'!V9=0,0,(AMS_2030!V9/'2019'!V9)^(1/7)-1) -> 1.2112876e-08 | W9: =IF('2019'!W9=0,0,(AMS_2030!W9/'2019'!W9)^(1/7)-1) -> -0.0065240588 | X9: =IF('2019'!X9=0,0,(AMS_2030!X9/'2019'!X9)^(1/7)-1) -> 3.3782862e-07 | Y9: =IF('2019'!Y9=0,0,(AMS_2030!Y9/'2019'!Y9)^(1/7)-1) -> -0.0032150337 | Z9: =IF('2019'!Z9=0,0,(AMS_2030!Z9/'2019'!Z9)^(1/7)-1) -> -0.00099881464 | AA9: =IF('2019'!AA9=0,0,(AMS_2030!AA9/'2019'!AA9)^(1/7)-1) -> 0.003747078 | ... AU9: =IF('2019'!AU9=0,0,(AMS_2030!AU9/'2019'!AU9)^(1/7)-1) -> 0
B10: 06 | C10: 06 | D10: Articles of paper and paperboard | E10: =IF('2019'!E10=0,0,(AMS_2030!E10/'2019'!E10)^(1/7)-1) -> 0.0023995423 | F10: =IF('2019'!F10=0,0,(AMS_2030!F10/'2019'!F10)^(1/7)-1) -> 0.003778628 | G10: =IF('2019'!G10=0,0,(AMS_2030!G10/'2019'!G10)^(1/7)-1) -> 6.3933192e-10 | H10: =IF('2019'!H10=0,0,(AMS_2030!H10/'2019'!H10)^(1/7)-1) -> 0.013685614 | I10: =IF('2019'!I10=0,0,(AMS_2030!I10/'2019'!I10)^(1/7)-1) -> 0.0015961095 | J10: =IF('2019'!J10=0,0,(AMS_2030!J10/'2019'!J10)^(1/7)-1) -> -0.00028428443 | K10: =IF('2019 (Z)'!AW10=0,0,('AMS_2030 (Z)'!AW10/'2019 (Z)'!AW10)^(1/7)-1) -> 0.0063408798 | L10: =K10 -> 0.0063408798 | M10: =IF('2019'!M10=0,0,(AMS_2030!M10/'2019'!M10)^(1/7)-1) -> -0.025029322 | N10: =IF('2019'!N10=0,0,(AMS_2030!N10/'2019'!N10)^(1/7)-1) -> 0.0049021511 | O10: =IF('2019'!O10=0,0,(AMS_2030!O10/'2019'!O10)^(1/7)-1) -> -0.0013079928 | P10: =IF('2019'!P10=0,0,(AMS_2030!P10/'2019'!P10)^(1/7)-1) -> 0.0029595242 | Q10: =IF('2019'!Q10=0,0,(AMS_2030!Q10/'2019'!Q10)^(1/7)-1) -> -1.0059405e-07 | R10: =IF('2019'!R10=0,0,(AMS_2030!R10/'2019'!R10)^(1/7)-1) -> -6.4639123e-07 | S10: =T10 -> 0.0011642781 | T10: =IF('2019'!T10=0,0,(AMS_2030!T10/'2019'!T10)^(1/7)-1) -> 0.0011642781 | U10: =IF('2019'!U10=0,0,(AMS_2030!U10/'2019'!U10)^(1/7)-1) -> 2.1003582e-06 | V10: =IF('2019'!V10=0,0,(AMS_2030!V10/'2019'!V10)^(1/7)-1) -> 1.2112876e-08 | W10: =IF('2019'!W10=0,0,(AMS_2030!W10/'2019'!W10)^(1/7)-1) -> 0.0043994657 | X10: =IF('2019'!X10=0,0,(AMS_2030!X10/'2019'!X10)^(1/7)-1) -> 0.0041993043 | Y10: =IF('2019'!Y10=0,0,(AMS_2030!Y10/'2019'!Y10)^(1/7)-1) -> -0.002858484 | Z10: =IF('2019'!Z10=0,0,(AMS_2030!Z10/'2019'!Z10)^(1/7)-1) -> -0.0020044743 | AA10: =IF('2019'!AA10=0,0,(AMS_2030!AA10/'2019'!AA10)^(1/7)-1) -> 0.003672419 | ... AU10: =IF('2019'!AU10=0,0,(AMS_2030!AU10/'2019'!AU10)^(1/7)-1) -> 0
B11: 07 | C11: 07 | D11: Inorganic basic chemicals | E11: =IF('2019 (Z)'!E127=0,0,('AMS_2030 (Z)'!E127/'2019 (Z)'!E127)^(1/7)-1) -> -0.020693389 | F11: =IF('2019 (Z)'!F127=0,0,('AMS_2030 (Z)'!F127/'2019 (Z)'!F127)^(1/7)-1) -> -0.020379397 | G11: =IF('2019 (Z)'!G127=0,0,('AMS_2030 (Z)'!G127/'2019 (Z)'!G127)^(1/7)-1) -> -0.014938794 | H11: =IF('2019 (Z)'!H127=0,0,('AMS_2030 (Z)'!H127/'2019 (Z)'!H127)^(1/7)-1) -> -0.001702638 | I11: =IF('2019 (Z)'!I127=0,0,('AMS_2030 (Z)'!I127/'2019 (Z)'!I127)^(1/7)-1) -> -0.013394977 | J11: =IF('2019 (Z)'!J127=0,0,('AMS_2030 (Z)'!J127/'2019 (Z)'!J127)^(1/7)-1) -> -0.014516665 | K11: =IF('2019 (Z)'!K127=0,0,('AMS_2030 (Z)'!K127/'2019 (Z)'!K127)^(1/7)-1) -> -0.012511472 | L11: =IF('2019 (Z)'!L127=0,0,('AMS_2030 (Z)'!L127/'2019 (Z)'!L127)^(1/7)-1) -> -0.012511472 | ... R11: =IF('2019 (Z)'!R127=0,0,('AMS_2030 (Z)'!R127/'2019 (Z)'!R127)^(1/7)-1) -> -0.014941228 | S11: =T11 -> -0.017468903 | T11: =IF('2019 (Z)'!T127=0,0,('AMS_2030 (Z)'!T127/'2019 (Z)'!T127)^(1/7)-1) -> -0.017468903 | U11: =IF('2019 (Z)'!U127=0,0,('AMS_2030 (Z)'!U127/'2019 (Z)'!U127)^(1/7)-1) -> -0.014938249 | V11: =IF('2019 (Z)'!V127=0,0,('AMS_2030 (Z)'!V127/'2019 (Z)'!V127)^(1/7)-1) -> -0.014938783 | W11: =IF('2019 (Z)'!W127=0,0,('AMS_2030 (Z)'!W127/'2019 (Z)'!W127)^(1/7)-1) -> -0.01670075 | X11: =IF('2019 (Z)'!X127=0,0,('AMS_2030 (Z)'!X127/'2019 (Z)'!X127)^(1/7)-1) -> -0.015027753 | Y11: =IF('2019 (Z)'!Y127=0,0,('AMS_2030 (Z)'!Y127/'2019 (Z)'!Y127)^(1/7)-1) -> -0.018105869 | Z11: =IF('2019 (Z)'!Z127=0,0,('AMS_2030 (Z)'!Z127/'2019 (Z)'!Z127)^(1/7)-1) -> -0.015897557 | AA11: =IF('2019 (Z)'!AA127=0,0,('AMS_2030 (Z)'!AA127/'2019 (Z)'!AA127)^(1/7)-1) -> -0.011267628 | ... AU11: =IF('2019 (Z)'!AU127=0,0,('AMS_2030 (Z)'!AU127/'2019 (Z)'!AU127)^(1/7)-1) -> 0
B12: 08 | C12: 08 | D12: Organic basic chemicals | E12: =E11 -> -0.020693389 | F12: =F11 -> -0.020379397 | G12: =G11 -> -0.014938794 | H12: =H11 -> -0.001702638 | I12: =I11 -> -0.013394977 | J12: =J11 -> -0.014516665 | K12: =K11 -> -0.012511472 | L12: =L11 -> -0.012511472 | ... R12: =R11 -> -0.014941228 | S12: =T12 -> -0.017468903 | T12: =T11 -> -0.017468903 | U12: =U11 -> -0.014938249 | V12: =V11 -> -0.014938783 | W12: =W11 -> -0.01670075 | X12: =X11 -> -0.015027753 | Y12: =Y11 -> -0.018105869 | Z12: =Z11 -> -0.015897557 | AA12: =AA11 -> -0.011267628 | ... AU12: =AU11 -> 0
B13: 09 | C13: 09 | D13: Plastics products | E13: =IF('2019'!E13=0,0,(AMS_2030!E13/'2019'!E13)^(1/7)-1) -> -0.024353629 | F13: =IF('2019'!F13=0,0,(AMS_2030!F13/'2019'!F13)^(1/7)-1) -> -0.023602315 | G13: =IF('2019'!G13=0,0,(AMS_2030!G13/'2019'!G13)^(1/7)-1) -> 0.10332665 | H13: =IF('2019'!H13=0,0,(AMS_2030!H13/'2019'!H13)^(1/7)-1) -> 0.0079482089 | I13: =IF('2019'!I13=0,0,(AMS_2030!I13/'2019'!I13)^(1/7)-1) -> 0.00089635513 | J13: =IF('2019'!J13=0,0,(AMS_2030!J13/'2019'!J13)^(1/7)-1) -> -9.692547e-05 | K13: =IF('2019 (Z)'!AW13=0,0,('AMS_2030 (Z)'!AW13/'2019 (Z)'!AW13)^(1/7)-1) -> -0.019155596 | L13: =K13 -> -0.019155596 | M13: =IF('2019'!M13=0,0,(AMS_2030!M13/'2019'!M13)^(1/7)-1) -> -0.00017528904 | N13: =IF('2019'!N13=0,0,(AMS_2030!N13/'2019'!N13)^(1/7)-1) -> 0.0074684524 | O13: =IF('2019'!O13=0,0,(AMS_2030!O13/'2019'!O13)^(1/7)-1) -> 0.0030046101 | P13: =IF('2019'!P13=0,0,(AMS_2030!P13/'2019'!P13)^(1/7)-1) -> -0.016933324 | Q13: =IF('2019'!Q13=0,0,(AMS_2030!Q13/'2019'!Q13)^(1/7)-1) -> -8.8367622e-08 | R13: =IF('2019'!R13=0,0,(AMS_2030!R13/'2019'!R13)^(1/7)-1) -> -3.3088893e-09 | S13: =T13 -> -1.921513e-05 | T13: =IF('2019'!T13=0,0,(AMS_2030!T13/'2019'!T13)^(1/7)-1) -> -1.921513e-05 | U13: =IF('2019'!U13=0,0,(AMS_2030!U13/'2019'!U13)^(1/7)-1) -> 1.4312105e-06 | V13: =IF('2019'!V13=0,0,(AMS_2030!V13/'2019'!V13)^(1/7)-1) -> 0 | W13: =IF('2019'!W13=0,0,(AMS_2030!W13/'2019'!W13)^(1/7)-1) -> -0.023865939 | X13: =IF('2019'!X13=0,0,(AMS_2030!X13/'2019'!X13)^(1/7)-1) -> -0.01885169 | Y13: =IF('2019'!Y13=0,0,(AMS_2030!Y13/'2019'!Y13)^(1/7)-1) -> -0.003476329 | Z13: =IF('2019'!Z13=0,0,(AMS_2030!Z13/'2019'!Z13)^(1/7)-1) -> -0.0011372613 | AA13: =IF('2019'!AA13=0,0,(AMS_2030!AA13/'2019'!AA13)^(1/7)-1) -> 0.0034175442 | ... AU13: =IF('2019'!AU13=0,0,(AMS_2030!AU13/'2019'!AU13)^(1/7)-1) -> 0
B14: 10 | C14: 10 | D14: Basic iron and steel and of ferro-alloys | E14: =IF('2019'!E14=0,0,(AMS_2030!E14/'2019'!E14)^(1/7)-1) -> 0.002870344 | F14: =IF('2019'!F14=0,0,(AMS_2030!F14/'2019'!F14)^(1/7)-1) -> -0.0015144905 | G14: =IF('2019'!G14=0,0,(AMS_2030!G14/'2019'!G14)^(1/7)-1) -> -0.016330788 | H14: =IF('2019'!H14=0,0,(AMS_2030!H14/'2019'!H14)^(1/7)-1) -> 0 | I14: =IF('2019'!I14=0,0,(AMS_2030!I14/'2019'!I14)^(1/7)-1) -> -0.0043201831 | J14: =IF('2019'!J14=0,0,(AMS_2030!J14/'2019'!J14)^(1/7)-1) -> -0.0025540668 | K14: =IF('2019 (Z)'!AW14=0,0,('AMS_2030 (Z)'!AW14/'2019 (Z)'!AW14)^(1/7)-1) -> -0.00023565942 | L14: =K14 -> -0.00023565942 | M14: =IF('2019'!M14=0,0,(AMS_2030!M14/'2019'!M14)^(1/7)-1) -> -0.0037268474 | N14: =IF('2019'!N14=0,0,(AMS_2030!N14/'2019'!N14)^(1/7)-1) -> -0.0046415384 | O14: =IF('2019'!O14=0,0,(AMS_2030!O14/'2019'!O14)^(1/7)-1) -> -0.0039867963 | P14: =IF('2019'!P14=0,0,(AMS_2030!P14/'2019'!P14)^(1/7)-1) -> -0.0026701176 | Q14: =IF('2019'!Q14=0,0,(AMS_2030!Q14/'2019'!Q14)^(1/7)-1) -> -0.0028386318 | R14: =IF('2019'!R14=0,0,(AMS_2030!R14/'2019'!R14)^(1/7)-1) -> -0.002795802 | S14: =T14 -> -0.0027769435 | T14: =IF('2019'!T14=0,0,(AMS_2030!T14/'2019'!T14)^(1/7)-1) -> -0.0027769435 | U14: =IF('2019'!U14=0,0,(AMS_2030!U14/'2019'!U14)^(1/7)-1) -> -0.0023641217 | V14: =IF('2019'!V14=0,0,(AMS_2030!V14/'2019'!V14)^(1/7)-1) -> -0.0025545571 | W14: =IF('2019'!W14=0,0,(AMS_2030!W14/'2019'!W14)^(1/7)-1) -> -0.0017401937 | X14: =IF('2019'!X14=0,0,(AMS_2030!X14/'2019'!X14)^(1/7)-1) -> 0.0024266719 | Y14: =IF('2019'!Y14=0,0,(AMS_2030!Y14/'2019'!Y14)^(1/7)-1) -> -0.006001982 | Z14: =IF('2019'!Z14=0,0,(AMS_2030!Z14/'2019'!Z14)^(1/7)-1) -> -0.0039353171 | AA14: =IF('2019'!AA14=0,0,(AMS_2030!AA14/'2019'!AA14)^(1/7)-1) -> 0.00094081014 | ... AU14: =IF('2019'!AU14=0,0,(AMS_2030!AU14/'2019'!AU14)^(1/7)-1) -> 0
B15: 11 | C15: 11 | D15: Non-ferrous metals | E15: =IF('2019'!E15=0,0,(AMS_2030!E15/'2019'!E15)^(1/7)-1) -> 0.0055812235 | F15: =IF('2019'!F15=0,0,(AMS_2030!F15/'2019'!F15)^(1/7)-1) -> 0.0042815653 | G15: =IF('2019'!G15=0,0,(AMS_2030!G15/'2019'!G15)^(1/7)-1) -> 0.1426363 | H15: =IF('2019'!H15=0,0,(AMS_2030!H15/'2019'!H15)^(1/7)-1) -> 0.014292493 | I15: =IF('2019'!I15=0,0,(AMS_2030!I15/'2019'!I15)^(1/7)-1) -> 0.004988617 | J15: =IF('2019'!J15=0,0,(AMS_2030!J15/'2019'!J15)^(1/7)-1) -> 0.0022232758 | K15: =IF('2019 (Z)'!AW15=0,0,('AMS_2030 (Z)'!AW15/'2019 (Z)'!AW15)^(1/7)-1) -> 0.0063209773 | L15: =K15 -> 0.0063209773 | M15: =IF('2019'!M15=0,0,(AMS_2030!M15/'2019'!M15)^(1/7)-1) -> 0.010935703 | N15: =IF('2019'!N15=0,0,(AMS_2030!N15/'2019'!N15)^(1/7)-1) -> 0.016005981 | O15: =IF('2019'!O15=0,0,(AMS_2030!O15/'2019'!O15)^(1/7)-1) -> -0.0032716735 | P15: =IF('2019'!P15=0,0,(AMS_2030!P15/'2019'!P15)^(1/7)-1) -> 0.0015107666 | Q15: =IF('2019'!Q15=0,0,(AMS_2030!Q15/'2019'!Q15)^(1/7)-1) -> 0.0002407028 | R15: =IF('2019'!R15=0,0,(AMS_2030!R15/'2019'!R15)^(1/7)-1) -> 0.00073877237 | S15: =T15 -> -0.00022440341 | T15: =IF('2019'!T15=0,0,(AMS_2030!T15/'2019'!T15)^(1/7)-1) -> -0.00022440341 | U15: =IF('2019'!U15=0,0,(AMS_2030!U15/'2019'!U15)^(1/7)-1) -> -2.8092275e-08 | V15: =IF('2019'!V15=0,0,(AMS_2030!V15/'2019'!V15)^(1/7)-1) -> -0.00015339236 | W15: =IF('2019'!W15=0,0,(AMS_2030!W15/'2019'!W15)^(1/7)-1) -> 0.0017121168 | X15: =IF('2019'!X15=0,0,(AMS_2030!X15/'2019'!X15)^(1/7)-1) -> 0.00063398743 | Y15: =IF('2019'!Y15=0,0,(AMS_2030!Y15/'2019'!Y15)^(1/7)-1) -> -0.0029028698 | Z15: =IF('2019'!Z15=0,0,(AMS_2030!Z15/'2019'!Z15)^(1/7)-1) -> 0.0049064257 | AA15: =IF('2019'!AA15=0,0,(AMS_2030!AA15/'2019'!AA15)^(1/7)-1) -> 0.007505121 | ... AU15: =IF('2019'!AU15=0,0,(AMS_2030!AU15/'2019'!AU15)^(1/7)-1) -> 0
B16: 12 | C16: 12 | D16: Other industries | E16: =IF('2019'!E16=0,0,(AMS_2030!E16/'2019'!E16)^(1/7)-1) -> 0.0011517939 | F16: =IF('2019'!F16=0,0,(AMS_2030!F16/'2019'!F16)^(1/7)-1) -> 0.0018035848 | G16: =IF('2019'!G16=0,0,(AMS_2030!G16/'2019'!G16)^(1/7)-1) -> 6.4292384e-05 | H16: =IF('2019'!H16=0,0,(AMS_2030!H16/'2019'!H16)^(1/7)-1) -> -0.046459542 | I16: =IF('2019'!I16=0,0,(AMS_2030!I16/'2019'!I16)^(1/7)-1) -> 0.00015887682 | J16: =IF('2019'!J16=0,0,(AMS_2030!J16/'2019'!J16)^(1/7)-1) -> -0.0017721272 | K16: =IF('2019 (Z)'!AW16=0,0,('AMS_2030 (Z)'!AW16/'2019 (Z)'!AW16)^(1/7)-1) -> 0.0025016415 | L16: =K16 -> 0.0025016415 | M16: =IF('2019'!M16=0,0,(AMS_2030!M16/'2019'!M16)^(1/7)-1) -> 0.0077539182 | N16: =IF('2019'!N16=0,0,(AMS_2030!N16/'2019'!N16)^(1/7)-1) -> -0.0012670447 | O16: =IF('2019'!O16=0,0,(AMS_2030!O16/'2019'!O16)^(1/7)-1) -> 0.0041495898 | P16: =IF('2019'!P16=0,0,(AMS_2030!P16/'2019'!P16)^(1/7)-1) -> 0.0002359791 | Q16: =IF('2019'!Q16=0,0,(AMS_2030!Q16/'2019'!Q16)^(1/7)-1) -> 0.0026220244 | R16: =IF('2019'!R16=0,0,(AMS_2030!R16/'2019'!R16)^(1/7)-1) -> 1.2248835e-08 | S16: =T16 -> -0.00013875274 | T16: =IF('2019'!T16=0,0,(AMS_2030!T16/'2019'!T16)^(1/7)-1) -> -0.00013875274 | U16: =IF('2019'!U16=0,0,(AMS_2030!U16/'2019'!U16)^(1/7)-1) -> 1.4636912e-06 | V16: =IF('2019'!V16=0,0,(AMS_2030!V16/'2019'!V16)^(1/7)-1) -> 1.2112876e-08 | W16: =IF('2019'!W16=0,0,(AMS_2030!W16/'2019'!W16)^(1/7)-1) -> -0.00020465695 | X16: =IF('2019'!X16=0,0,(AMS_2030!X16/'2019'!X16)^(1/7)-1) -> 2.3182764e-06 | Y16: =IF('2019'!Y16=0,0,(AMS_2030!Y16/'2019'!Y16)^(1/7)-1) -> -0.0032151038 | Z16: =IF('2019'!Z16=0,0,(AMS_2030!Z16/'2019'!Z16)^(1/7)-1) -> -0.0011454073 | AA16: =IF('2019'!AA16=0,0,(AMS_2030!AA16/'2019'!AA16)^(1/7)-1) -> 0.0037471488 | ... AU16: =IF('2019'!AU16=0,0,(AMS_2030!AU16/'2019'!AU16)^(1/7)-1) -> 0
B17: 13 | C17: 13 | D17: Construction of buildings and Civil engineering | E17: =IF('2019'!E17=0,0,(AMS_2030!E17/'2019'!E17)^(1/7)-1) -> 0.0032704565 | F17: =IF('2019'!F17=0,0,(AMS_2030!F17/'2019'!F17)^(1/7)-1) -> 0.0013249916 | G17: =IF('2019'!G17=0,0,(AMS_2030!G17/'2019'!G17)^(1/7)-1) -> 6.3933192e-10 | H17: =IF('2019'!H17=0,0,(AMS_2030!H17/'2019'!H17)^(1/7)-1) -> 0.019265137 | I17: =IF('2019'!I17=0,0,(AMS_2030!I17/'2019'!I17)^(1/7)-1) -> 8.4407543e-05 | J17: =IF('2019'!J17=0,0,(AMS_2030!J17/'2019'!J17)^(1/7)-1) -> 0.00028716348 | K17: =IF('2019 (Z)'!AW17=0,0,('AMS_2030 (Z)'!AW17/'2019 (Z)'!AW17)^(1/7)-1) -> 0.002442586 | L17: =K17 -> 0.002442586 | M17: =IF('2019'!M17=0,0,(AMS_2030!M17/'2019'!M17)^(1/7)-1) -> 0.011289874 | N17: =IF('2019'!N17=0,0,(AMS_2030!N17/'2019'!N17)^(1/7)-1) -> -0.00081336967 | O17: =IF('2019'!O17=0,0,(AMS_2030!O17/'2019'!O17)^(1/7)-1) -> 0.0073574528 | P17: =IF('2019'!P17=0,0,(AMS_2030!P17/'2019'!P17)^(1/7)-1) -> 0.00026801836 | Q17: =IF('2019'!Q17=0,0,(AMS_2030!Q17/'2019'!Q17)^(1/7)-1) -> -8.5851124e-08 | R17: =IF('2019'!R17=0,0,(AMS_2030!R17/'2019'!R17)^(1/7)-1) -> 1.2248835e-08 | S17: =T17 -> -0.0001016367 | T17: =IF('2019'!T17=0,0,(AMS_2030!T17/'2019'!T17)^(1/7)-1) -> -0.0001016367 | U17: =IF('2019'!U17=0,0,(AMS_2030!U17/'2019'!U17)^(1/7)-1) -> 6.5764001e-07 | V17: =IF('2019'!V17=0,0,(AMS_2030!V17/'2019'!V17)^(1/7)-1) -> 1.2112876e-08 | W17: =IF('2019'!W17=0,0,(AMS_2030!W17/'2019'!W17)^(1/7)-1) -> -0.00060861054 | X17: =IF('2019'!X17=0,0,(AMS_2030!X17/'2019'!X17)^(1/7)-1) -> -3.0342383e-06 | Y17: =IF('2019'!Y17=0,0,(AMS_2030!Y17/'2019'!Y17)^(1/7)-1) -> -0.0032151038 | Z17: =IF('2019'!Z17=0,0,(AMS_2030!Z17/'2019'!Z17)^(1/7)-1) -> -0.0011311883 | AA17: =IF('2019'!AA17=0,0,(AMS_2030!AA17/'2019'!AA17)^(1/7)-1) -> 0.0037471387 | ... AU17: =IF('2019'!AU17=0,0,(AMS_2030!AU17/'2019'!AU17)^(1/7)-1) -> 0
B18: 14 | C18: 14 | D18: Rail transport (Passenger and Freight) | E18: =IF('2019'!E18=0,0,(AMS_2030!E18/'2019'!E18)^(1/7)-1) -> -0.0021704622 | F18: =IF('2019'!F18=0,0,(AMS_2030!F18/'2019'!F18)^(1/7)-1) -> -0.0012023465 | G18: =IF('2019'!G18=0,0,(AMS_2030!G18/'2019'!G18)^(1/7)-1) -> 6.3933192e-10 | H18: =IF('2019'!H18=0,0,(AMS_2030!H18/'2019'!H18)^(1/7)-1) -> 0.018203957 | I18: =IF('2019'!I18=0,0,(AMS_2030!I18/'2019'!I18)^(1/7)-1) -> -1.5478309e-05 | J18: =IF('2019'!J18=0,0,(AMS_2030!J18/'2019'!J18)^(1/7)-1) -> -0.0021900425 | K18: =IF('2019 (Z)'!AW18=0,0,('AMS_2030 (Z)'!AW18/'2019 (Z)'!AW18)^(1/7)-1) -> 0.0022018337 | L18: =K18 -> 0.0022018337 | M18: =IF('2019'!M18=0,0,(AMS_2030!M18/'2019'!M18)^(1/7)-1) -> 0.019508686 | N18: =IF('2019'!N18=0,0,(AMS_2030!N18/'2019'!N18)^(1/7)-1) -> -0.019719968 | O18: =IF('2019'!O18=0,0,(AMS_2030!O18/'2019'!O18)^(1/7)-1) -> 0.0031714821 | P18: =IF('2019'!P18=0,0,(AMS_2030!P18/'2019'!P18)^(1/7)-1) -> -9.8085598e-05 | Q18: =IF('2019'!Q18=0,0,(AMS_2030!Q18/'2019'!Q18)^(1/7)-1) -> -8.5851124e-08 | R18: =IF('2019'!R18=0,0,(AMS_2030!R18/'2019'!R18)^(1/7)-1) -> 1.2248835e-08 | S18: =T18 -> 3.4596241e-06 | T18: =IF('2019'!T18=0,0,(AMS_2030!T18/'2019'!T18)^(1/7)-1) -> 3.4596241e-06 | U18: =IF('2019'!U18=0,0,(AMS_2030!U18/'2019'!U18)^(1/7)-1) -> 1.3542914e-06 | V18: =IF('2019'!V18=0,0,(AMS_2030!V18/'2019'!V18)^(1/7)-1) -> 1.2112876e-08 | W18: =IF('2019'!W18=0,0,(AMS_2030!W18/'2019'!W18)^(1/7)-1) -> 3.8450721e-05 | X18: =IF('2019'!X18=0,0,(AMS_2030!X18/'2019'!X18)^(1/7)-1) -> -1.0237129e-06 | Y18: =IF('2019'!Y18=0,0,(AMS_2030!Y18/'2019'!Y18)^(1/7)-1) -> -0.0032151038 | Z18: =IF('2019'!Z18=0,0,(AMS_2030!Z18/'2019'!Z18)^(1/7)-1) -> -0.0011561281 | AA18: =IF('2019'!AA18=0,0,(AMS_2030!AA18/'2019'!AA18)^(1/7)-1) -> 0.0037471425 | ... AU18: =IF('2019'!AU18=0,0,(AMS_2030!AU18/'2019'!AU18)^(1/7)-1) -> 0
B19: 15 | C19: 15 | D19: Passenger transport by road | E19: =E20 -> -0.001957003 | F19: =F20 -> -0.00061202795 | G19: =G20 -> 6.3933192e-10 | H19: =H20 -> 0.018261474 | I19: =I20 -> -0.00063921256 | J19: =J20 -> -0.0010388269 | K19: =K20 -> 0.0021202949 | L19: =L20 -> 0.0021202949 | ... R19: =R20 -> 1.2248834e-08 | S19: =T19 -> -0.00011905709 | T19: =T20 -> -0.00011905709 | U19: =U20 -> 1.339252e-06 | V19: =V20 -> 1.2112876e-08 | W19: =W20 -> 0.00069291117 | X19: =X20 -> 1.8113142e-06 | Y19: =Y20 -> -0.0032151038 | Z19: =Z20 -> -0.0011596051 | AA19: =AA20 -> 0.0037471111 | ... AU19: =AU20 -> 0
B20: 16 | C20: 16 | D20: Freight transport by road and transport via pipeline | E20: =IF('2019'!E20=0,0,(AMS_2030!E20/'2019'!E20)^(1/7)-1) -> -0.001957003 | F20: =IF('2019'!F20=0,0,(AMS_2030!F20/'2019'!F20)^(1/7)-1) -> -0.00061202795 | G20: =IF('2019'!G20=0,0,(AMS_2030!G20/'2019'!G20)^(1/7)-1) -> 6.3933192e-10 | H20: =IF('2019'!H20=0,0,(AMS_2030!H20/'2019'!H20)^(1/7)-1) -> 0.018261474 | I20: =IF('2019'!I20=0,0,(AMS_2030!I20/'2019'!I20)^(1/7)-1) -> -0.00063921256 | J20: =IF('2019'!J20=0,0,(AMS_2030!J20/'2019'!J20)^(1/7)-1) -> -0.0010388269 | K20: =IF('2019 (Z)'!AW20=0,0,('AMS_2030 (Z)'!AW20/'2019 (Z)'!AW20)^(1/7)-1) -> 0.0021202949 | L20: =K20 -> 0.0021202949 | M20: =IF('2019'!M20=0,0,(AMS_2030!M20/'2019'!M20)^(1/7)-1) -> 0.038511405 | N20: =IF('2019'!N20=0,0,(AMS_2030!N20/'2019'!N20)^(1/7)-1) -> 0.0017164194 | O20: =IF('2019'!O20=0,0,(AMS_2030!O20/'2019'!O20)^(1/7)-1) -> 0.0019705857 | P20: =IF('2019'!P20=0,0,(AMS_2030!P20/'2019'!P20)^(1/7)-1) -> -8.0362705e-05 | Q20: =IF('2019'!Q20=0,0,(AMS_2030!Q20/'2019'!Q20)^(1/7)-1) -> -8.5851124e-08 | R20: =IF('2019'!R20=0,0,(AMS_2030!R20/'2019'!R20)^(1/7)-1) -> 1.2248834e-08 | S20: =T20 -> -0.00011905709 | T20: =IF('2019'!T20=0,0,(AMS_2030!T20/'2019'!T20)^(1/7)-1) -> -0.00011905709 | U20: =IF('2019'!U20=0,0,(AMS_2030!U20/'2019'!U20)^(1/7)-1) -> 1.339252e-06 | V20: =IF('2019'!V20=0,0,(AMS_2030!V20/'2019'!V20)^(1/7)-1) -> 1.2112876e-08 | W20: =IF('2019'!W20=0,0,(AMS_2030!W20/'2019'!W20)^(1/7)-1) -> 0.00069291117 | X20: =IF('2019'!X20=0,0,(AMS_2030!X20/'2019'!X20)^(1/7)-1) -> 1.8113142e-06 | Y20: =IF('2019'!Y20=0,0,(AMS_2030!Y20/'2019'!Y20)^(1/7)-1) -> -0.0032151038 | Z20: =IF('2019'!Z20=0,0,(AMS_2030!Z20/'2019'!Z20)^(1/7)-1) -> -0.0011596051 | AA20: =IF('2019'!AA20=0,0,(AMS_2030!AA20/'2019'!AA20)^(1/7)-1) -> 0.0037471111 | ... AU20: =IF('2019'!AU20=0,0,(AMS_2030!AU20/'2019'!AU20)^(1/7)-1) -> 0
B21: 17 | C21: 17 | D21: Water transport | E21: =IF('2019'!E21=0,0,(AMS_2030!E21/'2019'!E21)^(1/7)-1) -> -0.003200381 | F21: =IF('2019'!F21=0,0,(AMS_2030!F21/'2019'!F21)^(1/7)-1) -> -0.0012556119 | G21: =IF('2019'!G21=0,0,(AMS_2030!G21/'2019'!G21)^(1/7)-1) -> 6.3933192e-10 | H21: =IF('2019'!H21=0,0,(AMS_2030!H21/'2019'!H21)^(1/7)-1) -> 0.018203957 | I21: =IF('2019'!I21=0,0,(AMS_2030!I21/'2019'!I21)^(1/7)-1) -> 0.00064590429 | J21: =IF('2019'!J21=0,0,(AMS_2030!J21/'2019'!J21)^(1/7)-1) -> -0.0035761842 | K21: =IF('2019 (Z)'!AW21=0,0,('AMS_2030 (Z)'!AW21/'2019 (Z)'!AW21)^(1/7)-1) -> 0.001241412 | L21: =K21 -> 0.001241412 | M21: =IF('2019'!M21=0,0,(AMS_2030!M21/'2019'!M21)^(1/7)-1) -> 0.056165892 | N21: =IF('2019'!N21=0,0,(AMS_2030!N21/'2019'!N21)^(1/7)-1) -> 0.0026000135 | O21: =IF('2019'!O21=0,0,(AMS_2030!O21/'2019'!O21)^(1/7)-1) -> 0.0031666184 | P21: =IF('2019'!P21=0,0,(AMS_2030!P21/'2019'!P21)^(1/7)-1) -> 6.7363728e-05 | Q21: =IF('2019'!Q21=0,0,(AMS_2030!Q21/'2019'!Q21)^(1/7)-1) -> -8.5851124e-08 | R21: =IF('2019'!R21=0,0,(AMS_2030!R21/'2019'!R21)^(1/7)-1) -> 1.2248835e-08 | S21: =T21 -> -5.7046525e-05 | T21: =IF('2019'!T21=0,0,(AMS_2030!T21/'2019'!T21)^(1/7)-1) -> -5.7046525e-05 | U21: =IF('2019'!U21=0,0,(AMS_2030!U21/'2019'!U21)^(1/7)-1) -> -3.4106545e-07 | V21: =IF('2019'!V21=0,0,(AMS_2030!V21/'2019'!V21)^(1/7)-1) -> 1.2112876e-08 | W21: =IF('2019'!W21=0,0,(AMS_2030!W21/'2019'!W21)^(1/7)-1) -> -0.00064539507 | X21: =IF('2019'!X21=0,0,(AMS_2030!X21/'2019'!X21)^(1/7)-1) -> 3.2975367e-06 | Y21: =IF('2019'!Y21=0,0,(AMS_2030!Y21/'2019'!Y21)^(1/7)-1) -> -0.0032151038 | Z21: =IF('2019'!Z21=0,0,(AMS_2030!Z21/'2019'!Z21)^(1/7)-1) -> -0.0011458004 | AA21: =IF('2019'!AA21=0,0,(AMS_2030!AA21/'2019'!AA21)^(1/7)-1) -> 0.0037471453 | ... AU21: =IF('2019'!AU21=0,0,(AMS_2030!AU21/'2019'!AU21)^(1/7)-1) -> 0
B22: 18 | C22: 18 | D22: Air transport | E22: =IF('2019'!E22=0,0,(AMS_2030!E22/'2019'!E22)^(1/7)-1) -> -0.0028691762 | F22: =IF('2019'!F22=0,0,(AMS_2030!F22/'2019'!F22)^(1/7)-1) -> 0.00052771922 | G22: =IF('2019'!G22=0,0,(AMS_2030!G22/'2019'!G22)^(1/7)-1) -> 6.3933192e-10 | H22: =IF('2019'!H22=0,0,(AMS_2030!H22/'2019'!H22)^(1/7)-1) -> 0.019075391 | I22: =IF('2019'!I22=0,0,(AMS_2030!I22/'2019'!I22)^(1/7)-1) -> 0.0012000488 | J22: =IF('2019'!J22=0,0,(AMS_2030!J22/'2019'!J22)^(1/7)-1) -> -0.00031819739 | K22: =IF('2019 (Z)'!AW22=0,0,('AMS_2030 (Z)'!AW22/'2019 (Z)'!AW22)^(1/7)-1) -> 0.0025189822 | L22: =K22 -> 0.0025189822 | M22: =IF('2019'!M22=0,0,(AMS_2030!M22/'2019'!M22)^(1/7)-1) -> -0.013154939 | N22: =IF('2019'!N22=0,0,(AMS_2030!N22/'2019'!N22)^(1/7)-1) -> -0.022857581 | O22: =IF('2019'!O22=0,0,(AMS_2030!O22/'2019'!O22)^(1/7)-1) -> 0.0031441001 | P22: =IF('2019'!P22=0,0,(AMS_2030!P22/'2019'!P22)^(1/7)-1) -> -1.2347333e-05 | Q22: =IF('2019'!Q22=0,0,(AMS_2030!Q22/'2019'!Q22)^(1/7)-1) -> -8.5851124e-08 | R22: =IF('2019'!R22=0,0,(AMS_2030!R22/'2019'!R22)^(1/7)-1) -> 1.2248835e-08 | S22: =T22 -> -2.0886572e-05 | T22: =IF('2019'!T22=0,0,(AMS_2030!T22/'2019'!T22)^(1/7)-1) -> -2.0886572e-05 | U22: =IF('2019'!U22=0,0,(AMS_2030!U22/'2019'!U22)^(1/7)-1) -> 5.570418e-07 | V22: =IF('2019'!V22=0,0,(AMS_2030!V22/'2019'!V22)^(1/7)-1) -> 1.2112876e-08 | W22: =IF('2019'!W22=0,0,(AMS_2030!W22/'2019'!W22)^(1/7)-1) -> 0.00038616116 | X22: =IF('2019'!X22=0,0,(AMS_2030!X22/'2019'!X22)^(1/7)-1) -> 2.7121853e-05 | Y22: =IF('2019'!Y22=0,0,(AMS_2030!Y22/'2019'!Y22)^(1/7)-1) -> -0.0032151038 | Z22: =IF('2019'!Z22=0,0,(AMS_2030!Z22/'2019'!Z22)^(1/7)-1) -> -0.0011600656 | AA22: =IF('2019'!AA22=0,0,(AMS_2030!AA22/'2019'!AA22)^(1/7)-1) -> 0.0037471413 | ... AU22: =IF('2019'!AU22=0,0,(AMS_2030!AU22/'2019'!AU22)^(1/7)-1) -> 0
B23: 19 | C23: 19 | D23: Business services | E23: =IF('2019'!E23=0,0,(AMS_2030!E23/'2019'!E23)^(1/7)-1) -> -0.0012515259 | F23: =IF('2019'!F23=0,0,(AMS_2030!F23/'2019'!F23)^(1/7)-1) -> -0.00054451403 | G23: =IF('2019'!G23=0,0,(AMS_2030!G23/'2019'!G23)^(1/7)-1) -> -0.00036065418 | H23: =IF('2019'!H23=0,0,(AMS_2030!H23/'2019'!H23)^(1/7)-1) -> 0.004064883 | I23: =IF('2019'!I23=0,0,(AMS_2030!I23/'2019'!I23)^(1/7)-1) -> -0.0006645639 | J23: =IF('2019'!J23=0,0,(AMS_2030!J23/'2019'!J23)^(1/7)-1) -> -0.00029821622 | K23: =IF('2019 (Z)'!AW23=0,0,('AMS_2030 (Z)'!AW23/'2019 (Z)'!AW23)^(1/7)-1) -> 0.0023426551 | L23: =K23 -> 0.0023426551 | M23: =IF('2019'!M23=0,0,(AMS_2030!M23/'2019'!M23)^(1/7)-1) -> 0.010993282 | N23: =IF('2019'!N23=0,0,(AMS_2030!N23/'2019'!N23)^(1/7)-1) -> -0.0072969015 | O23: =IF('2019'!O23=0,0,(AMS_2030!O23/'2019'!O23)^(1/7)-1) -> 0.001933735 | P23: =IF('2019'!P23=0,0,(AMS_2030!P23/'2019'!P23)^(1/7)-1) -> -0.00051248118 | Q23: =IF('2019'!Q23=0,0,(AMS_2030!Q23/'2019'!Q23)^(1/7)-1) -> -0.00024571569 | R23: =IF('2019'!R23=0,0,(AMS_2030!R23/'2019'!R23)^(1/7)-1) -> -0.00012139038 | S23: =T23 -> -1.916707e-05 | T23: =IF('2019'!T23=0,0,(AMS_2030!T23/'2019'!T23)^(1/7)-1) -> -1.916707e-05 | U23: =IF('2019'!U23=0,0,(AMS_2030!U23/'2019'!U23)^(1/7)-1) -> -0.00019765045 | V23: =IF('2019'!V23=0,0,(AMS_2030!V23/'2019'!V23)^(1/7)-1) -> -0.0001658235 | W23: =IF('2019'!W23=0,0,(AMS_2030!W23/'2019'!W23)^(1/7)-1) -> -0.0010781805 | X23: =IF('2019'!X23=0,0,(AMS_2030!X23/'2019'!X23)^(1/7)-1) -> -0.0006033851 | Y23: =IF('2019'!Y23=0,0,(AMS_2030!Y23/'2019'!Y23)^(1/7)-1) -> -0.0034554867 | Z23: =IF('2019'!Z23=0,0,(AMS_2030!Z23/'2019'!Z23)^(1/7)-1) -> -0.0022283132 | AA23: =IF('2019'!AA23=0,0,(AMS_2030!AA23/'2019'!AA23)^(1/7)-1) -> 0.0037107344 | ... AU23: =IF('2019'!AU23=0,0,(AMS_2030!AU23/'2019'!AU23)^(1/7)-1) -> 0
B24: 20 | C24: 20 | D24: Public services | E24: =IF('2019'!E24=0,0,(AMS_2030!E24/'2019'!E24)^(1/7)-1) -> -0.00031757637 | F24: =IF('2019'!F24=0,0,(AMS_2030!F24/'2019'!F24)^(1/7)-1) -> 0.0015477315 | G24: =IF('2019'!G24=0,0,(AMS_2030!G24/'2019'!G24)^(1/7)-1) -> 6.3933192e-10 | H24: =IF('2019'!H24=0,0,(AMS_2030!H24/'2019'!H24)^(1/7)-1) -> 0.044732871 | I24: =IF('2019'!I24=0,0,(AMS_2030!I24/'2019'!I24)^(1/7)-1) -> 0.00063875541 | J24: =IF('2019'!J24=0,0,(AMS_2030!J24/'2019'!J24)^(1/7)-1) -> -0.0081949567 | K24: =IF('2019 (Z)'!AW24=0,0,('AMS_2030 (Z)'!AW24/'2019 (Z)'!AW24)^(1/7)-1) -> 0.002546009 | L24: =K24 -> 0.002546009 | M24: =IF('2019'!M24=0,0,(AMS_2030!M24/'2019'!M24)^(1/7)-1) -> 0.0041548136 | N24: =IF('2019'!N24=0,0,(AMS_2030!N24/'2019'!N24)^(1/7)-1) -> 0.02227382 | O24: =IF('2019'!O24=0,0,(AMS_2030!O24/'2019'!O24)^(1/7)-1) -> 0.0038543894 | P24: =IF('2019'!P24=0,0,(AMS_2030!P24/'2019'!P24)^(1/7)-1) -> 0.00013425073 | Q24: =IF('2019'!Q24=0,0,(AMS_2030!Q24/'2019'!Q24)^(1/7)-1) -> -8.5851124e-08 | R24: =IF('2019'!R24=0,0,(AMS_2030!R24/'2019'!R24)^(1/7)-1) -> 1.2248835e-08 | S24: =T24 -> -1.1596438e-05 | T24: =IF('2019'!T24=0,0,(AMS_2030!T24/'2019'!T24)^(1/7)-1) -> -1.1596438e-05 | U24: =IF('2019'!U24=0,0,(AMS_2030!U24/'2019'!U24)^(1/7)-1) -> 1.8259812e-06 | V24: =IF('2019'!V24=0,0,(AMS_2030!V24/'2019'!V24)^(1/7)-1) -> 1.2112876e-08 | W24: =IF('2019'!W24=0,0,(AMS_2030!W24/'2019'!W24)^(1/7)-1) -> -7.6439556e-05 | X24: =IF('2019'!X24=0,0,(AMS_2030!X24/'2019'!X24)^(1/7)-1) -> -1.6358778e-06 | Y24: =IF('2019'!Y24=0,0,(AMS_2030!Y24/'2019'!Y24)^(1/7)-1) -> -0.0032151038 | Z24: =IF('2019'!Z24=0,0,(AMS_2030!Z24/'2019'!Z24)^(1/7)-1) -> -0.0011535846 | AA24: =IF('2019'!AA24=0,0,(AMS_2030!AA24/'2019'!AA24)^(1/7)-1) -> 0.00374703 | ... AU24: =IF('2019'!AU24=0,0,(AMS_2030!AU24/'2019'!AU24)^(1/7)-1) -> 0
B25: 21 | C25: 21 | D25: Coal | E25: =IF('2019'!E25=0,0,(AMS_2030!E25/'2019'!E25)^(1/7)-1) -> 0 | F25: =IF('2019'!F25=0,0,(AMS_2030!F25/'2019'!F25)^(1/7)-1) -> 0.0019108432 | G25: =IF('2019'!G25=0,0,(AMS_2030!G25/'2019'!G25)^(1/7)-1) -> 6.3933192e-10 | H25: =IF('2019'!H25=0,0,(AMS_2030!H25/'2019'!H25)^(1/7)-1) -> -0.12508315 | I25: =IF('2019'!I25=0,0,(AMS_2030!I25/'2019'!I25)^(1/7)-1) -> 0.00091312465 | J25: =IF('2019'!J25=0,0,(AMS_2030!J25/'2019'!J25)^(1/7)-1) -> 0 | K25: =IF('2019 (Z)'!AW25=0,0,('AMS_2030 (Z)'!AW25/'2019 (Z)'!AW25)^(1/7)-1) -> 0.0021401382 | L25: =K25 -> 0.0021401382 | M25: =IF('2019'!M25=0,0,(AMS_2030!M25/'2019'!M25)^(1/7)-1) -> -0.05296411 | N25: =IF('2019'!N25=0,0,(AMS_2030!N25/'2019'!N25)^(1/7)-1) -> 0.089707929 | O25: =IF('2019'!O25=0,0,(AMS_2030!O25/'2019'!O25)^(1/7)-1) -> -0.014467167 | P25: =IF('2019'!P25=0,0,(AMS_2030!P25/'2019'!P25)^(1/7)-1) -> -1.5038264e-05 | Q25: =IF('2019'!Q25=0,0,(AMS_2030!Q25/'2019'!Q25)^(1/7)-1) -> -8.5851124e-08 | R25: =IF('2019'!R25=0,0,(AMS_2030!R25/'2019'!R25)^(1/7)-1) -> 0 | S25: =T25 -> 0 | T25: =IF('2019'!T25=0,0,(AMS_2030!T25/'2019'!T25)^(1/7)-1) -> 0 | U25: =IF('2019'!U25=0,0,(AMS_2030!U25/'2019'!U25)^(1/7)-1) -> 0 | V25: =IF('2019'!V25=0,0,(AMS_2030!V25/'2019'!V25)^(1/7)-1) -> 0 | W25: =IF('2019'!W25=0,0,(AMS_2030!W25/'2019'!W25)^(1/7)-1) -> 0 | X25: =IF('2019'!X25=0,0,(AMS_2030!X25/'2019'!X25)^(1/7)-1) -> 0 | Y25: =IF('2019'!Y25=0,0,(AMS_2030!Y25/'2019'!Y25)^(1/7)-1) -> 0 | Z25: =IF('2019'!Z25=0,0,(AMS_2030!Z25/'2019'!Z25)^(1/7)-1) -> -0.00070011607 | AA25: =IF('2019'!AA25=0,0,(AMS_2030!AA25/'2019'!AA25)^(1/7)-1) -> 0.0037471539 | ... AU25: =IF('2019'!AU25=0,0,(AMS_2030!AU25/'2019'!AU25)^(1/7)-1) -> 0
B26: 22 | C26: 22 | D26: Oil | E26: =IF('2019'!E26=0,0,(AMS_2030!E26/'2019'!E26)^(1/7)-1) -> -0.00083969006 | F26: =IF('2019'!F26=0,0,(AMS_2030!F26/'2019'!F26)^(1/7)-1) -> 0.0020893947 | G26: =IF('2019'!G26=0,0,(AMS_2030!G26/'2019'!G26)^(1/7)-1) -> 6.3933192e-10 | H26: =IF('2019'!H26=0,0,(AMS_2030!H26/'2019'!H26)^(1/7)-1) -> -0.085973141 | I26: =IF('2019'!I26=0,0,(AMS_2030!I26/'2019'!I26)^(1/7)-1) -> 0.001403165 | J26: =IF('2019'!J26=0,0,(AMS_2030!J26/'2019'!J26)^(1/7)-1) -> -0.0035621173 | K26: =IF('2019 (Z)'!AW26=0,0,('AMS_2030 (Z)'!AW26/'2019 (Z)'!AW26)^(1/7)-1) -> 0.0019600595 | L26: =K26 -> 0.0019600595 | M26: =IF('2019'!M26=0,0,(AMS_2030!M26/'2019'!M26)^(1/7)-1) -> 0.0060341187 | N26: =IF('2019'!N26=0,0,(AMS_2030!N26/'2019'!N26)^(1/7)-1) -> -0.057725565 | O26: =IF('2019'!O26=0,0,(AMS_2030!O26/'2019'!O26)^(1/7)-1) -> -0.013777208 | P26: =IF('2019'!P26=0,0,(AMS_2030!P26/'2019'!P26)^(1/7)-1) -> 0.00048802822 | Q26: =IF('2019'!Q26=0,0,(AMS_2030!Q26/'2019'!Q26)^(1/7)-1) -> -8.5851124e-08 | R26: =IF('2019'!R26=0,0,(AMS_2030!R26/'2019'!R26)^(1/7)-1) -> 1.2248835e-08 | S26: =T26 -> 1.3470979e-05 | T26: =IF('2019'!T26=0,0,(AMS_2030!T26/'2019'!T26)^(1/7)-1) -> 1.3470979e-05 | U26: =IF('2019'!U26=0,0,(AMS_2030!U26/'2019'!U26)^(1/7)-1) -> 1.7658566e-06 | V26: =IF('2019'!V26=0,0,(AMS_2030!V26/'2019'!V26)^(1/7)-1) -> 1.2112876e-08 | W26: =IF('2019'!W26=0,0,(AMS_2030!W26/'2019'!W26)^(1/7)-1) -> 8.1318807e-05 | X26: =IF('2019'!X26=0,0,(AMS_2030!X26/'2019'!X26)^(1/7)-1) -> 5.1466052e-06 | Y26: =IF('2019'!Y26=0,0,(AMS_2030!Y26/'2019'!Y26)^(1/7)-1) -> -0.0032151038 | Z26: =IF('2019'!Z26=0,0,(AMS_2030!Z26/'2019'!Z26)^(1/7)-1) -> -0.0011607189 | AA26: =IF('2019'!AA26=0,0,(AMS_2030!AA26/'2019'!AA26)^(1/7)-1) -> 0.0037469666 | ... AU26: =IF('2019'!AU26=0,0,(AMS_2030!AU26/'2019'!AU26)^(1/7)-1) -> 0
