Workbook
Name année: [1]Calcul_hypotheses!$D$6
Name anneeAffiche: #REF!
Name anneeAffiche: #REF!
Name anneeAffiche: #REF!
Name anneeDataSet: [2]Dataset!$H$2:$AH$2
Name calIntAnnee: [2]Calculs_intermediaires!$B$328:$AP$328
Name calIntcode: [2]Calculs_intermediaires!$B:$B
Name calIntData: [2]Calculs_intermediaires!$B:$AM
Name convktoeGWh: [2]Intro!$C$40
Name convMtoeGWh: [2]Intro!$C$41
Name dataSet: [2]Dataset!$H:$AH
Name odsAnnee: [2]Odyssee!$A$8:$AMJ$8
Name odsCode: [2]Odyssee!$A:$A
Name odsData: [2]Odyssee!$A:$AMJ
Name Résultats_annuels: [3]RES_annuels!$N$3:$BW$858
Name Résultats_annuels_années: [3]RES_annuels!$N$1:$AX$1
Name Résultats_annuels_choix: [3]RES_annuels!$D$3:$D$858
Name tagOutDataSet: [2]Dataset!$H:$H

Sheet Récap
V1: Combustibles coproduits
V3: 0
B4: Consommation | V4: 0
V5: 0
A7: AMS run 2 | B7: Sorties brutes | V7: 0
A8: Consommation | B8: 2015 | C8: 2019 | D8: 2020 | E8: 2021 | G8: 2025 | H8: 2030 | I8: 2035 | J8: 2040 | K8: 2045 | L8: 2050 | V8: 0
A9: Acier | B9: 12.452717 | C9: 12.240884 | D9: 12.189214 | E9: 12.137543 | G9: 11.930863 | H9: 11.672511 | I9: 11.592389 | J9: 11.512266 | K9: 11.432144 | L9: 11.352021 | V9: 0
A10: Alu | B10: 1.3666521 | C10: 1.4419886 | D10: 1.4608831 | E10: 1.4797776 | G10: 1.5553557 | H10: 1.6498282 | I10: 1.802221 | J10: 1.9546138 | K10: 2.1070066 | L10: 2.2593994
A11: Verre | B11: 4.930894 | C11: 4.8770764 | D11: 4.8560722 | E11: 4.835068 | G11: 4.7510511 | H11: 4.6460301 | I11: 4.3485869 | J11: 4.0511438 | K11: 3.7537006 | L11: 3.4562575 | V11: 0
A12: Clinker | B12: 13.307547 | C12: 12.468566 | D12: 12.251611 | E12: 12.034655 | G12: 11.166834 | H12: 10.082056 | I12: 9.4886314 | J12: 8.8952064 | K12: 8.3017814 | L12: 7.7083564 | V12: 0
A13: NH3 | B13: 2.1547623 | C13: 2.1062658 | D13: 2.0891688 | E13: 2.0720718 | G13: 2.0036836 | H13: 1.9181985 | I13: 1.7642275 | J13: 1.6102564 | K13: 1.4562854 | L13: 1.3023144 | V13: 0
A14: Cl2 | B14: 1.1275838 | C14: 1.1070518 | D14: 1.0992268 | E14: 1.0914018 | G14: 1.0601018 | H14: 1.0209768 | I14: 0.98722775 | J14: 0.95347868 | K14: 0.9197296 | L14: 0.88598053
A15: Ethylène | B15: 3.2018183 | C15: 3.1799101 | D15: 3.0946419 | E15: 3.0093738 | G15: 2.6683013 | H15: 2.2419606 | I15: 2.0976228 | J15: 1.953285 | K15: 1.8089472 | L15: 1.6646095 | V15: 0
A16: Papiers cartons | B16: 8.346785 | C16: 8.7020144 | D16: 8.7503332 | E16: 8.7986521 | G16: 8.9919273 | H16: 9.2335213 | I16: 9.5397952 | J16: 9.8460691 | K16: 10.152343 | L16: 10.458617 | V16: 0
A17: Sucre | B17: 3.7597692 | C17: 3.7715222 | D17: 3.7657544 | E17: 3.7599866 | G17: 3.7369153 | H17: 3.7080761 | I17: 3.6038129 | J17: 3.4995497 | K17: 3.3952865 | L17: 3.2910233 | V17: 0
A18: Total | B18: =SUM(B9:B17) -> 50.648529 | C18: =SUM(C9:C17) -> 49.89528 | D18: =SUM(D9:D17) -> 49.556905 | E18: =SUM(E9:E17) -> 49.218531 | G18: =SUM(G9:G17) -> 47.865032 | H18: =SUM(H9:H17) -> 46.173159 | I18: =SUM(I9:I17) -> 45.224514 | J18: =SUM(J9:J17) -> 44.275869 | K18: =SUM(K9:K17) -> 43.327224 | L18: =SUM(L9:L17) -> 42.378579
V19: 0
V20: 0
V21: 0
B22: Balance commerciale
V23: 0
V24: 0
D25: Nouvelle interpolation de 2025 à 2030 (basée sur 2019) qui donne des valeurs différentes du run 2 avant 2030 (permet de ne pas avoir la BC du clinker qui augente comme dans le run 2 jusqu'à 2030 puis diminue jusqu'à 2050 suite à l'arbitrage) | V25: 0
C26: Observé | D26: Repris de l'observé | G26: Projeté | H26: Projeté | I26: Projeté | J26: Projeté | K26: Projeté | L26: Projeté
B27: Rapport Production / Consommation | C27: 2019 | D27: 2020 | E27: 2021 | G27: 2025 | H27: 2030 | I27: 2035 | J27: 2040 | K27: 2045 | L27: 2050 | V27: 0
B28: Acier | C28: =C42/C9 -> 1.191735 | D28: =D42/D9 -> 0.95085804 | E28: =E42/E9 -> 1.1157222 | G28: =E28+(H28-E28)/9*4 -> 1.193179 | H28: 1.29 | I28: =$H28+($L28-$H28)/20*(I$27-$H$27) -> 1.305 | J28: =$H28+($L28-$H28)/20*(J$27-$H$27) -> 1.32 | K28: =$H28+($L28-$H28)/20*(K$27-$H$27) -> 1.335 | L28: 1.35 | V28: 0
B29: aluminium | C29: =C46/C10 -> 0.61997716 | D29: =D46/D10 -> 0.55993529 | E29: =E46/E10 -> 0.57778952 | G29: =E29+(H29-E29)/9*4 -> 0.6232164 | H29: 0.68 | I29: =$H29+($L29-$H29)/20*(I$27-$H$27) -> 0.7225 | J29: =$H29+($L29-$H29)/20*(J$27-$H$27) -> 0.765 | K29: =$H29+($L29-$H29)/20*(K$27-$H$27) -> 0.8075 | L29: 0.85 | V29: 0
B30: clinker | C30: =C51/C12 -> 1.0374835 | D30: =D51/D12 -> 0.9607754 | E30: =E51/E12 -> 1.0172355 | G30: 1.05 | H30: 1.21 | I30: =$H30+($L30-$H30)/20*(I$27-$H$27) -> 1.1575 | J30: =$H30+($L30-$H30)/20*(J$27-$H$27) -> 1.105 | K30: =$H30+($L30-$H30)/20*(K$27-$H$27) -> 1.0525 | L30: 1
B31: verre | C31: =C52/C11 -> 1.1766629 | D31: =D52/D11 -> 1.0395698 | E31: =E52/E11 -> 1.1730436 | G31: =E31+(H31-E31)/9*4 -> 1.1708664 | H31: 1.168145 | I31: 1.168145 | J31: 1.168145 | K31: 1.168145 | L31: 1.168145 | V31: Combustibles coproduits
B32: ammoniac | C32: =C50/C13 -> 0.5102916 | D32: =D50/D13 -> 0.47861762 | E32: =E50/E13 -> 0.44230767 | G32: =E32+(H32-E32)/9*4 -> 0.53461537 | H32: 0.65 | I32: =$H32+($L32-$H32)/20*(I$27-$H$27) -> 0.6875 | J32: =$H32+($L32-$H32)/20*(J$27-$H$27) -> 0.725 | K32: =$H32+($L32-$H32)/20*(K$27-$H$27) -> 0.7625 | L32: 0.8 | V32: 0
B33: Chlore | C33: =C49/C14 -> 0.26852936 | D33: =D49/D14 -> 0.25325011 | E33: =E49/E14 -> 0.30573709 | G33: =C33 -> 0.26852936 | H33: =G33 -> 0.26852936 | I33: =$H33+($L33-$H33)/20*(I$27-$H$27) -> 0.26852936 | J33: =$H33+($L33-$H33)/20*(J$27-$H$27) -> 0.26852936 | K33: =$H33+($L33-$H33)/20*(K$27-$H$27) -> 0.26852936 | L33: =$C$33 -> 0.26852936 | M33: BC cste comme dans le run 2, mais à un niveau différent du fait du changement de périmètre de la prod historique fournie par le Citepa | V33: 0
B34: Ethylène | C34: =C48/C15 -> 0.73594394 | D34: =D48/D15 -> 0.73441966 | E34: =E48/E15 -> 0.76887807 | G34: =E34 -> 0.76887807 | H34: 0.92 | I34: =$H34+($L34-$H34)/20*(I$27-$H$27) -> 0.94 | J34: =$H34+($L34-$H34)/20*(J$27-$H$27) -> 0.96 | K34: =$H34+($L34-$H34)/20*(K$27-$H$27) -> 0.98 | L34: 1 | V34: 0
B35: Sucre | C35: =C54/C17 -> 1.3175052 | D35: =D54/D17 -> 0.91482334 | E35: =E54/E17 -> 1.2101107 | G35: =E35+(H35-E35)/9*4 -> 1.256781 | H35: 1.3151189 | I35: =$H35+($L35-$H35)/20*(I$27-$H$27) -> 1.3157154 | J35: =$H35+($L35-$H35)/20*(J$27-$H$27) -> 1.316312 | K35: =$H35+($L35-$H35)/20*(K$27-$H$27) -> 1.3169086 | L35: =C35 -> 1.3175052
B36: papier | C36: =C53/C16 -> 0.84152929 | D36: =D53/D16 -> 0.7854558 | E36: =E53/E16 -> 0.8361508 | G36: 0.795 | H36: 0.795 | I36: =$H36+($L36-$H36)/20*(I$27-$H$27) -> 0.77125 | J36: =$H36+($L36-$H36)/20*(J$27-$H$27) -> 0.7475 | K36: =$H36+($L36-$H36)/20*(K$27-$H$27) -> 0.72375 | L36: 0.7 | M36: balance commerciale diminuée pour obtenir une production de pâte à papier stable (suite au retour de Aurélie Lécureuil et de Anne Menez de la DGE), cela ne reflète pas forcément la réalité de la balance commerciale car l'augmentation de la consommation modélisée par Pepito semble ne pas prendre en compte l'effet du recyclage : on pourrait avoir une consommation de pâte à papier primaire stable et une hausse de la consommation de papier recyclé | V36: =#REF!/(#REF!+#REF!) -> #REF!
H37: Valeurs du run 2 | V37: =V36/(V36+H36)*#REF! -> #REF!
B38: Production | V38: =V37/(V37+H37)*#REF! -> #REF!
A39: Attention au périmètre des productions, recyclage inclus ou non
B40: Productions arbitrées AMS run 3 | C40: Observé | D40: Repris de l'observé | H40: Projeté | I40: Projeté | J40: Projeté | K40: Projeté | L40: Projeté | M40: Projeté | N40: Focus acier 2026-2029 | V40: 0
B41: Production (Mt) | C41: 2019 | D41: 2020 | E41: 2021 | F41: 2022 | G41: 2023 | H41: 2025 | I41: 2030 | J41: 2035 | K41: 2040 | L41: 2045 | M41: 2050 | N41: 2026 | O41: 2027 | P41: 2028 | Q41: 2029 | V41: 0
B42: Acier | C42: ='Production historique IGCE'!F3 -> 14.58789 | D42: ='Production historique IGCE'!G3 -> 11.590212 | E42: ='Production historique IGCE'!H3 -> 13.542126 | F42: ='Production historique IGCE'!I3 -> 12.217998 | G42: ='Production historique IGCE'!J3 -> 10.010885 | H42: =G28*G9 -> 14.235654 | I42: =H28*H9 -> 15.05754 | J42: =I28*I9 -> 15.128067 | K42: =J28*J9 -> 15.196191 | L42: =K28*K9 -> 15.261912 | M42: =L28*L9 -> 15.325229 | N42: =$H42+($I42-$H42)/5*(N41-$H$41) -> 14.400031 | O42: =$H42+($I42-$H42)/5*(O41-$H$41) -> 14.564408 | P42: =$H42+($I42-$H42)/5*(P41-$H$41) -> 14.728786 | Q42: =$H42+($I42-$H42)/5*(Q41-$H$41) -> 14.893163 | V42: 0
B43: dont haut fourneaux | C43: ='Production historique IGCE'!F4 -> 10.130063 | D43: ='Production historique IGCE'!G4 -> 7.872834 | E43: ='Production historique IGCE'!H4 -> 8.937677 | F43: ='Production historique IGCE'!I4 -> 8.222646 | G43: ='Production historique IGCE'!J4 -> 6.413039 | H43: =(H42-(H42*'4. Recyclage'!P12))/(1-0.16)-H45 -> 8.8125479 | I43: =(I42-(I42*'4. Recyclage'!Q12))/(1-0.16)-I45 -> 5.2457955 | J43: =(J42-(J42*'4. Recyclage'!R12))/(1-0.16)-J45 -> 3.2441297 | K43: =(K42-(K42*'4. Recyclage'!S12))/(1-0.16)-K45 -> 3.2790028 | L43: 0 | M43: 0 | N43: =H43+(R43-H43)/5*1 -> 8.0991974 | O43: =H43+(R43-H43)/5*2 -> 7.385847 | P43: =H43+(R43-H43)/5*3 -> 6.6724965 | Q43: =H43+(R43-H43)/5*4 -> 5.959146 | R43: =I43 -> 5.2457955
B44: dont procédé électrique | C44: ='Production historique IGCE'!F5 -> 4.4578274 | D44: ='Production historique IGCE'!G5 -> 3.7173779 | E44: ='Production historique IGCE'!H5 -> 4.6044492 | F44: ='Production historique IGCE'!I5 -> 3.9953518 | G44: ='Production historique IGCE'!J5 -> 3.5978462 | H44: =H42-H43-H45 -> 5.4231064 | I44: =I42-I43-I45 -> 6.8117441 | J44: =J42-J43-J45 -> 7.3839377 | K44: =K42-K43-K45 -> 7.4171887 | L44: =L42-L43-L45 -> 9.2619118 | M44: =M42-M43-M45 -> 9.3252285 | N44: =N42-N43-N45 -> 6.300834 | O44: =O42-O43-O45 -> 6.4285615 | ... Q44: =Q42-Q43-Q45 -> 6.6840166 | V44: Combustibles coproduits
B45: dont DRI | C45: ='Production historique IGCE'!F6 -> 0 | D45: ='Production historique IGCE'!G6 -> 0 | E45: ='Production historique IGCE'!H6 -> 0 | F45: ='Production historique IGCE'!I6 -> 0 | G45: ='Production historique IGCE'!J6 -> 0 | H45: 0 | I45: 3 | J45: 4.5 | K45: 4.5 | L45: 6 | M45: 6 | N45: 0 | O45: =N45+($I$45-$N$45)/4 -> 0.75 | P45: =O45+($I$45-$N$45)/4 -> 1.5 | Q45: =P45+($I$45-$N$45)/4 -> 2.25 | V45: 0
B46: Aluminium | C46: ='Production historique IGCE'!F7 -> 0.894 | D46: ='Production historique IGCE'!G7 -> 0.818 | E46: ='Production historique IGCE'!H7 -> 0.855 | F46: ='Production historique IGCE'!I7 -> 0.78249187 | G46: ='Production historique IGCE'!J7 -> 0.74907454 | H46: =G29*G10 -> 0.96932316 | I46: =H29*H10 -> 1.1218832 | J46: =I29*I10 -> 1.3021047 | K46: =J29*J10 -> 1.4952796 | L46: =K29*K10 -> 1.7014078 | M46: =L29*L10 -> 1.9204895 | N46: 3Mt DRI Arcelor Mittal Dunkerque (soutien décarbonation par l'Etat annoncé le 15 janvier lors de visite ministres à Dunkerque); remis en cause en AMS ? | V46: 0
A47: uniquement seconde fusion | B47: dont aluminium recyclé | C47: ='Production historique IGCE'!F8 -> 0.476 | D47: ='Production historique IGCE'!G8 -> 0.401 | E47: ='Production historique IGCE'!H8 -> 0.425 | F47: ='Production historique IGCE'!I8 -> 0.38895795 | G47: ='Production historique IGCE'!J8 -> 0.372347 | H47: =H46*'4. Recyclage'!P13 -> 0.54884942 | I47: =I46*'4. Recyclage'!Q13 -> 0.67312992 | J47: =J46*'4. Recyclage'!R13 -> 0.81381543 | K47: =K46*'4. Recyclage'!S13 -> 0.97193172 | L47: =L46*'4. Recyclage'!T13 -> 1.1484503 | M47: =M46*'4. Recyclage'!U13 -> 1.3443426 | N47: implique d'importer alu primaire, à avoir en tête, nouvelles capacités de recyclage ? | V47: 0
B48: Ethylène | C48: ='Production historique IGCE'!F12 -> 2.3402355 | D48: ='Production historique IGCE'!G12 -> 2.2727659 | E48: ='Production historique IGCE'!H12 -> 2.3138415 | F48: ='Production historique IGCE'!I12 -> 1.626623 | G48: ='Production historique IGCE'!J12 -> 1.8421029 | H48: =G34*G15 -> 2.0515983 | I48: =H34*H15 -> 2.0626038 | J48: =I34*I15 -> 1.9717655 | K48: =J34*J15 -> 1.8751536 | L48: =K34*K15 -> 1.7727683 | M48: =L34*L15 -> 1.6646095
B49: Chlore | C49: ='Production historique IGCE'!F13 -> 0.2972759 | D49: ='Production historique IGCE'!G13 -> 0.2783793 | E49: ='Production historique IGCE'!H13 -> 0.333682 | F49: ='Production historique IGCE'!I13 -> 0.251754 | G49: ='Production historique IGCE'!J13 -> 0.255626 | H49: =G33*G14 -> 0.28466846 | I49: =1.12307450692913/1.22*C49 -> 0.27365818 | J49: =I33*I14 -> 0.26509964 | K49: =J33*J14 -> 0.25603702 | L49: =K33*K14 -> 0.2469744 | M49: =L33*L14 -> 0.23791178 | N49: productions revues à la baisse en historique | V49: 0
B50: Ammoniac | C50: ='Production historique IGCE'!F14 -> 1.0748098 | D50: ='Production historique IGCE'!G14 -> 0.999913 | E50: ='Production historique IGCE'!H14 -> 0.91649323 | F50: ='Production historique IGCE'!I14 -> 0.85601795 | G50: ='Production historique IGCE'!J14 -> 0.69479755 | H50: =G32*G13 -> 1.0712001 | I50: =H32*H13 -> 1.246829 | J50: =I32*I13 -> 1.2129064 | K50: =J32*J13 -> 1.1674359 | L50: =K32*K13 -> 1.1104176 | M50: =L32*L13 -> 1.0418515 | V50: 0
B51: Clinker | C51: ='Production historique IGCE'!F15 -> 12.935931 | D51: ='Production historique IGCE'!G15 -> 11.771046 | E51: ='Production historique IGCE'!H15 -> 12.242079 | F51: ='Production historique IGCE'!I15 -> 12.044779 | G51: ='Production historique IGCE'!J15 -> 10.672455 | H51: =G30*G12 -> 11.725175 | I51: =H30*H12 -> 12.199288 | J51: =I30*I12 -> 10.983091 | K51: =J30*J12 -> 9.8292031 | L51: =K30*K12 -> 8.7376249 | M51: =L30*L12 -> 7.7083564 | V51: 0
B52: Verre | C52: ='Production historique IGCE'!F16 -> 5.7386751 | D52: ='Production historique IGCE'!G16 -> 5.048226 | E52: ='Production historique IGCE'!H16 -> 5.6717456 | F52: ='Production historique IGCE'!I16 -> 5.5682739 | G52: ='Production historique IGCE'!J16 -> 5.0170238 | H52: =G31*G11 -> 5.5628464 | I52: =H31*H11 -> 5.4272367 | J52: =I31*I11 -> 5.07978 | K52: =J31*J11 -> 4.7323233 | L52: =K31*K11 -> 4.3848666 | M52: =L31*L11 -> 4.0374099
B53: Papier | C53: ='Production historique IGCE'!F17 -> 7.323 | D53: ='Production historique IGCE'!G17 -> 6.873 | E53: ='Production historique IGCE'!H17 -> 7.357 | F53: ='Production historique IGCE'!I17 -> 7.0918 | G53: ='Production historique IGCE'!J17 -> 6.1356 | H53: =G36*G16 -> 7.1485822 | I53: =H36*H16 -> 7.3406495 | J53: =I36*I16 -> 7.357567 | K53: =J36*J16 -> 7.3599366 | L53: =K36*K16 -> 7.3477582 | M53: =L36*L16 -> 7.3210317 | N53: commentaire CITEPA pâte à papier dans l'inventaire : nous utilisons des données de production de pâte à papier (kraft et bisulfite) fournies par la profession (Copacel), il semblerait qu’elles n’incluent pas la production de pâte à partir de matières recyclées comme dit dans leur rapport d’activité ; à savoir que, côté CITEPA, aucune émission de CO2 n’est considérée autre que celles liées aux consos énergétiques pour le papier-carton car les carbonates utilisés sont considérés restés soit dans la pâte soit dans les boues ; | V53: 0
B54: Sucre | C54: ='Production historique IGCE'!F19 -> 4.969 | D54: ='Production historique IGCE'!G19 -> 3.445 | E54: ='Production historique IGCE'!H19 -> 4.55 | F54: ='Production historique IGCE'!I19 -> 3.95 | G54: ='Production historique IGCE'!J19 -> 4.225 | H54: =G35*G17 -> 4.6964841 | I54: =H35*H17 -> 4.8765609 | J54: =I35*I17 -> 4.7415923 | K54: =J35*J17 -> 4.6064994 | L54: =K35*K17 -> 4.471282 | M54: =L35*L17 -> 4.3359403 | V54: 0
V55: 0
B56: Diffus
V57: Combustibles coproduits
V58: 0
B59: Evolution des VA de l'industrie (basé sur 3Me du run 1 ou 1bis) | V59: 0
B60: Md€2015 | C60: 2019 | D60: 2020 | E60: 2021 | F60: 2025 | G60: 2030 | H60: 2035 | I60: 2040 | J60: 2045 | K60: 2050 | V60: 0
B61: Métaux primaires | C61: =Diffus!C30 -> 25.805 | D61: =Diffus!D30 -> 22.829 | E61: =Diffus!E30 -> 24.457 | F61: =Diffus!F30 -> 25.771903 | G61: =Diffus!G30 -> 27.082898 | H61: =Diffus!H30 -> 27.438939 | I61: =Diffus!I30 -> 29.218666 | J61: =Diffus!J30 -> 31.687727 | K61: =Diffus!K30 -> 34.388981
B62: Chimie | C62: =Diffus!C31 -> 47.175 | D62: =Diffus!D31 -> 45.889 | E62: =Diffus!E31 -> 46.328 | F62: =Diffus!F31 -> 47.670648 | G62: =Diffus!G31 -> 50.768485 | H62: =Diffus!H31 -> 52.267061 | I62: =Diffus!I31 -> 56.524037 | J62: =Diffus!J31 -> 61.707015 | K62: =Diffus!K31 -> 67.063853 | V62: 0
B63: Minéraux non-métalliques | C63: =Diffus!C32 -> 8.359 | D63: =Diffus!D32 -> 7.464 | E63: =Diffus!E32 -> 8.172 | F63: =Diffus!F32 -> 8.5177449 | G63: =Diffus!G32 -> 8.7279363 | H63: =Diffus!H32 -> 8.9041513 | I63: =Diffus!I32 -> 9.3350748 | J63: =Diffus!J32 -> 9.8976398 | K63: =Diffus!K32 -> 10.585064 | V63: 0
B64: IAA | C64: =Diffus!C33 -> 45.598 | D64: =Diffus!D33 -> 44.089 | E64: =Diffus!E33 -> 44.859 | F64: =Diffus!F33 -> 47.554551 | G64: =Diffus!G33 -> 51.504271 | H64: =Diffus!H33 -> 55.265993 | I64: =Diffus!I33 -> 60.060384 | J64: =Diffus!J33 -> 65.270121 | K64: =Diffus!K33 -> 70.679032 | V64: 0
B65: Equipements | C65: =Diffus!C34 -> 63.615 | D65: =Diffus!D34 -> 49.807 | E65: =Diffus!E34 -> 52.09 | F65: =Diffus!F34 -> 55.555071 | G65: =Diffus!G34 -> 60.438283 | H65: =Diffus!H34 -> 64.996535 | I65: =Diffus!I34 -> 70.538499 | J65: =Diffus!J34 -> 76.917603 | K65: =Diffus!K34 -> 83.983077
B66: Autres (textile, etc.) | C66: =Diffus!C35 -> 23.724 | D66: =Diffus!D35 -> 22.258 | E66: =Diffus!E35 -> 23.781 | F66: =Diffus!F35 -> 25.362932 | G66: =Diffus!G35 -> 27.592298 | H66: =Diffus!H35 -> 29.673308 | I66: =Diffus!I35 -> 32.203418 | J66: =Diffus!J35 -> 35.115713 | K66: =Diffus!K35 -> 38.341362 | V66: 0
B67: Total diffus hors construction | C67: =Diffus!C36 -> 214.276 | D67: =Diffus!D36 -> 192.336 | E67: =Diffus!E36 -> 199.687 | F67: =Diffus!F36 -> 210.43285 | G67: =Diffus!G36 -> 226.11417 | H67: =Diffus!H36 -> 238.54599 | I67: =Diffus!I36 -> 257.88008 | J67: =Diffus!J36 -> 280.59582 | K67: =Diffus!K36 -> 305.04137 | V67: 0
B68: Construction | C68: =Diffus!C37 -> 114.882 | D68: =Diffus!D37 -> 101.443 | E68: =Diffus!E37 -> 108.227 | F68: =Diffus!F37 -> 111.90446 | G68: =Diffus!G37 -> 111.60903 | H68: =Diffus!H37 -> 110.28798 | I68: =Diffus!I37 -> 110.67153 | J68: =Diffus!J37 -> 112.51429 | K68: =Diffus!K37 -> 116.70087 | V68: 0
A70: A maj avec cadrage | B70: Total GVA (progression similaire au PIB) | D70: 2068.8 | E70: 2217.8 | F70: 2245.9711 | G70: 2346.7093 | H70: 2473.2122 | I70: 2642.8254 | J70: 2848.0099 | K70: 3069.6741 | V70: 0
B71: Part VA industrie / Total GVA | D71: =D67/D70 -> 0.092969838 | E71: =E67/E70 -> 0.090038326 | F71: =F67/F70 -> 0.093693482 | G71: =G67/G70 -> 0.096353722 | H71: =H67/H70 -> 0.096451888 | I71: =I67/I70 -> 0.097577417 | J71: =J67/J70 -> 0.098523471 | K71: =K67/K70 -> 0.099372557 | V71: 0
V72: 0
B73: Coefficient de décorrélation VA / production physique
K74: Arbitrages run 3 : AMS + pour hors équipements et autres et -20% sur équipements et autres | V74: Combustibles coproduits
B75: Indice 2019 | C75: 2019 | D75: 2020 | E75: 2021 | F75: 2025 | G75: 2030 | H75: 2035 | I75: 2040 | J75: 2045 | K75: 2050 | V75: 0
B76: Métaux primaires | C76: 1 | D76: 1 | E76: 1 | F76: 0.98 | G76: 0.96 | H76: =G76+($K76-$G76)/20*5 -> 0.94 | I76: =H76+($K76-$G76)/20*5 -> 0.92 | J76: =I76+($K76-$G76)/20*5 -> 0.9 | K76: 0.88 | V76: 0
B77: Chimie | C77: 1 | D77: 1 | E77: 1 | F77: 0.99 | G77: 0.98 | H77: =G77+($K77-$G77)/20*5 -> 0.955 | I77: =H77+($K77-$G77)/20*5 -> 0.93 | J77: =I77+($K77-$G77)/20*5 -> 0.905 | K77: 0.88 | V77: 0
B78: Minéraux non-métalliques | C78: 1 | D78: 1 | E78: 1 | F78: 0.99 | G78: 0.98 | H78: =G78+($K78-$G78)/20*5 -> 0.955 | I78: =H78+($K78-$G78)/20*5 -> 0.93 | J78: =I78+($K78-$G78)/20*5 -> 0.905 | K78: 0.88
B79: IAA | C79: 1 | D79: 1 | E79: 1 | F79: =(E79+G79)/2 -> 0.94 | G79: 0.88 | H79: =G79+($K79-$G79)/20*5 -> 0.82 | I79: =H79+($K79-$G79)/20*5 -> 0.76 | J79: =I79+($K79-$G79)/20*5 -> 0.7 | K79: 0.64 | L79: voir commentaire Production IAA ci-dessous | V79: 0
B80: Equipements | C80: 1 | D80: 1 | E80: 1 | F80: 0.983 | G80: 0.95 | H80: =G80+($K80-$G80)/20*5 -> 0.8825 | I80: =H80+($K80-$G80)/20*5 -> 0.815 | J80: =I80+($K80-$G80)/20*5 -> 0.7475 | K80: =0.85*(1-20%) -> 0.68 | V80: 0
B81: Autres (textile, etc.) | C81: 1 | D81: 1 | E81: 1 | F81: 0.96129032 | G81: 0.92903226 | H81: =G81+($K81-$G81)/20*5 -> 0.85677419 | I81: =H81+($K81-$G81)/20*5 -> 0.78451613 | J81: =I81+($K81-$G81)/20*5 -> 0.71225806 | K81: =0.8*(1-20%) -> 0.64 | V81: 0
B82: Construction | C82: 1 | D82: 1 | E82: 1 | F82: 1 | G82: 1 | H82: =G82+($K82-$G82)/20*5 -> 1 | I82: =H82+($K82-$G82)/20*5 -> 1 | J82: =I82+($K82-$G82)/20*5 -> 1 | K82: 1
V83: 0
C84: Historique | V84: 0
B85: Production "physique" AMS | C85: 2019 | D85: 2020 | E85: 2021 | F85: 2025 | G85: 2030 | H85: 2035 | I85: 2040 | J85: 2045 | K85: 2050 | V85: 0
B86: Métaux primaires | C86: =C61*C76 -> 25.805 | D86: =D61*D76 -> 22.829 | E86: =E61*E76 -> 24.457 | F86: =F61*F76 -> 25.256465 | G86: =G61*G76 -> 25.999582 | H86: =H61*H76 -> 25.792603 | I86: =I61*I76 -> 26.881173 | J86: =J61*J76 -> 28.518954 | K86: =K61*K76 -> 30.262303 | V86: 0
B87: Chimie | C87: =C62*C77 -> 47.175 | D87: =D62*D77 -> 45.889 | E87: =E62*E77 -> 46.328 | F87: =F62*F77 -> 47.193941 | G87: =G62*G77 -> 49.753115 | H87: =H62*H77 -> 49.915043 | I87: =I62*I77 -> 52.567354 | J87: =J62*J77 -> 55.844848 | K87: =K62*K77 -> 59.016191
B88: Minéraux non-métalliques | C88: =C63*C78 -> 8.359 | D88: =D63*D78 -> 7.464 | E88: =E63*E78 -> 8.172 | F88: =F63*F78 -> 8.4325674 | G88: =G63*G78 -> 8.5533775 | H88: =H63*H78 -> 8.5034645 | I88: =I63*I78 -> 8.6816195 | J88: =J63*J78 -> 8.957364 | K88: =K63*K78 -> 9.3148567
B89: IAA | C89: =C64*C79 -> 45.598 | D89: =D64*D79 -> 44.089 | E89: =E64*E79 -> 44.859 | F89: =F64*F79 -> 44.701278 | G89: =G64*G79 -> 45.323759 | H89: =H64*H79 -> 45.318114 | I89: =I64*I79 -> 45.645892 | J89: =J64*J79 -> 45.689085 | K89: =K64*K79 -> 45.23458 | L89: l'augmentation semble trop forte avec les facteurs de décorrélation réhaussés à l'issue du run 2, et les facteurs de décorrélation issus de l'extrapolation des tendances historiques sur les VAA donnent une production légèrement décroissante donc la stabilité est retenue par défaut
B90: Equipements | C90: =C65*C80 -> 63.615 | D90: =D65*D80 -> 49.807 | E90: =E65*E80 -> 52.09 | F90: =F65*F80 -> 54.610634 | G90: =G65*G80 -> 57.416369 | H90: =H65*H80 -> 57.359442 | I90: =I65*I80 -> 57.488877 | J90: =J65*J80 -> 57.495908 | K90: =K65*K80 -> 57.108493
B91: Autres (textile, etc.) | C91: =C66*C81 -> 23.724 | D91: =D66*D81 -> 22.258 | E91: =E66*E81 -> 23.781 | F91: =F66*F81 -> 24.381141 | G91: =G66*G81 -> 25.634135 | H91: =H66*H81 -> 25.423324 | I91: =I66*I81 -> 25.264101 | J91: =J66*J81 -> 25.01145 | K91: =K66*K81 -> 24.538472
B92: Total diffus (hors construction) | C92: =SUM(C86:C91) -> 214.276 | D92: =SUM(D86:D91) -> 192.336 | E92: =SUM(E86:E91) -> 199.687 | F92: =SUM(F86:F91) -> 204.57603 | G92: =SUM(G86:G91) -> 212.68034 | H92: =SUM(H86:H91) -> 212.31199 | I92: =SUM(I86:I91) -> 216.52902 | J92: =SUM(J86:J91) -> 221.51761 | K92: =SUM(K86:K91) -> 225.4749
B93: Construction | C93: =C68*C82 -> 114.882 | D93: =D68*D82 -> 101.443 | E93: =E68*E82 -> 108.227 | F93: =F68*F82 -> 111.90446 | G93: =G68*G82 -> 111.60903 | H93: =H68*H82 -> 110.28798 | I93: =I68*I82 -> 110.67153 | J93: =J68*J82 -> 112.51429 | K93: =K68*K82 -> 116.70087
B96: Leviers
B100: Mix énergétique
B101: Onglet Mix éner % (l'onglet Mix éner % (2) reprend les hypothèses sous un autre format)
B102: AMS run 2 ajusté | T102: Code couleur
B103: Mix énergétique | E103: Charbon | F103: Coke | G103: Produits pétroliers raffinés | H103: Gaz de réseau | I103: Biomasse solide | J103: Déchets | K103: Biocarburants | L103: Gaz renouvelable | M103: Chaleur de l'environnement | N103: Solaire thermique et géothermie | O103: Électricité | P103: Electricité PAC | Q103: Chaleur vendue | R103: Hydrogène (consommation finale) | S103: Total | T103: modifié p/r au run 2 bis | U103: Combustibles coproduits | V103: mise en cohérence avec AMS run 2 en historique
B104: Métaux primaires | T104: modifié au run 2 bis / run 2 | V104: modification AMS run 3
B105: Dont sidérurgie (hauts fourneaux) | C105: 2021 | D105: % | E105: 0.40234553 | F105: 0.59765447 | G105: 0 | H105: 0 | I105: 0 | J105: 0 | K105: 0 | L105: 0 | M105: 0 | N105: 0 | O105: 0 | P105: 0 | Q105: 0 | R105: 0 | S105: =SUM(E105:R105) -> 1 | U105: 0
B106: Dont sidérurgie (hauts fourneaux) | C106: 2030 | D106: % | E106: 0.3655 | F106: 0.5445 | G106: 0 | H106: 0 | I106: 0.03 | J106: 0.06 | K106: 0 | L106: 0 | M106: 0 | N106: 0 | O106: 0 | P106: 0 | Q106: 0 | R106: 0 | S106: =SUM(E106:R106) -> 1 | T106: un peu de CSR à 2030, charbon et coke réduits légèrement | U106: 0
B107: Dont sidérurgie (hauts fourneaux) | C107: 2045 | D107: % | E107: =E106+(E108-E106)/20*15 -> 0.34183509 | F107: =F106+(F108-F106)/20*15 -> 0.50816491 | G107: =G106+(G108-G106)/20*15 -> 0 | H107: =H106+(H108-H106)/20*15 -> 0 | I107: =I106+(I108-I106)/20*15 -> 0.045 | J107: =J106+(J108-J106)/20*15 -> 0.105 | K107: =K106+(K108-K106)/20*15 -> 0 | L107: =L106+(L108-L106)/20*15 -> 0 | ... R107: =R106+(R108-R106)/20*15 -> 0 | S107: =SUM(E107:R107) -> 1
B108: Dont sidérurgie (hauts fourneaux) | C108: 2050 | D108: % | E108: 0.33394679 | F108: 0.49605321 | G108: 0 | H108: 0 | I108: 0.05 | J108: 0.12 | K108: 0 | L108: 0 | M108: 0 | N108: 0 | O108: 0 | P108: 0 | Q108: 0 | R108: 0 | S108: =SUM(E108:R108) -> 1 | T108: ligne ok | U108: 0
...

Sheet Substitutions NE autres chimies
A1: Substitutions NE autres chimies
B2: 2021 | C2: 2030 | D2: 2040 | E2: 2050 | F2: Source
A3: Part du gaz destiné à la production d'H2 en historique | B3: 0.4 | F3: DGE (Tom Gagnebet)
A4: Quantité de gaz non énergétique | B4: =5558.50477255434/1000 -> 5.5585048
A5: Quantité de gaz vaporeformage 2021 (TWh) | B5: =B3*B4 -> 2.2234019 | E5: =E7/0.72 -> 0
A6: Rendement PCI H2/gaz vaporeformage | B6: 0.72 | F6: AFHYPAC | G6: https://s3.production.france-hydrogene.org/uploads/sites/4/2021/11/Fiche_203.1.1_20-_20Production_20_C3_A0_20partir_20de_20fossiles_20-_20rev_20nov2019_20Th_20A.pdf
A7: quantité d'H2 vaporéformé en 2021 | B7: =B5*B6 -> 1.6008494 | E7: 0 | F7: prise en compte de l'augmentation des besoins en H2 proportionnellement à la production
A8: quantité d'H2 électrolysé pré run 3 v1 | B8: 0 | C8: 0 | E8: =3761.05133095219/1000 -> 3.7610513
A9: quantité d'H2 électrolysé pré run 3 v2 | E9: =$B7*Récap!K87/Récap!$E87 -> 2.0392858 | F9: 2,2TWh au final dans Enermed pré run 3 v2
A10: Part H2 pré run 3 v1 | C10: 0 | D10: 0.2 | E10: 0.4
A11: Part H2 pré run 3 v2 | C11: 0 | D11: =AVERAGE(C11,E11) -> 0.10844233 | E11: =E9/E8*E10 -> 0.21688465

Sheet Production historique IGCE
A2: Production (Mt) | B2: 2015 | C2: 2016 | D2: 2017 | E2: 2018 | F2: 2019 | G2: 2020 | H2: 2021 | I2: 2022 | J2: 2023 | K2: source
A3: Acier | B3: =SUM(B4:B6) -> 15.08646 | C3: 14.45 | D3: 15.6 | E3: =SUM(E4:E6) -> 15.449049 | F3: =SUM(F4:F6) -> 14.58789 | G3: =SUM(G4:G6) -> 11.590212 | H3: =SUM(H4:H6) -> 13.542126 | I3: =SUM(I4:I6) -> 12.217998 | J3: =SUM(J4:J6) -> 10.010885 | K3: CITEPA
A4: dont haut fourneaux | B4: =F44/1000 -> 9.985539 | C4: =C3-C5 -> 9.59 | D4: =D3-D5 -> 10.73 | E4: =G44/1000 -> 10.598281 | F4: =H44/1000 -> 10.130063 | G4: =I44/1000 -> 7.872834 | H4: =J44/1000 -> 8.937677 | I4: =K44/1000 -> 8.222646 | J4: =L44/1000 -> 6.413039 | K4: CITEPA
A5: dont procédé électrique | B5: =F45/1000 -> 5.1009214 | C5: 4.86 | D5: 4.87 | E5: =G45/1000 -> 4.8507678 | F5: =H45/1000 -> 4.4578274 | G5: =I45/1000 -> 3.7173779 | H5: =J45/1000 -> 4.6044492 | I5: =K45/1000 -> 3.9953518 | J5: =L45/1000 -> 3.5978462 | K5: CITEPA
A6: dont DRI | B6: 0 | C6: 0 | D6: 0 | E6: 0 | F6: 0 | G6: 0 | H6: 0 | I6: 0 | J6: 0
A7: Aluminium | B7: 0.893 | C7: 0.918 | D7: 0.942 | E7: 0.878 | F7: 0.894 | G7: 0.818 | H7: 0.855 | I7: =H7*I9/H9 -> 0.78249187 | J7: =I7*J9/I9 -> 0.74907454 | K7: BNR 2012-2021, valeur 2022 et 2023 calculée à partir du taux de variation 2021-2022 du CITEPA
A8: dont aluminium recyclé | B8: 0.472 | C8: 0.488 | D8: 0.508 | E8: 0.496 | F8: =0.292+0.184 -> 0.476 | G8: =0.251+0.15 -> 0.401 | H8: =0.282+0.143 -> 0.425 | I8: =H8*I7/H7 -> 0.38895795 | J8: =I8*J7/I7 -> 0.372347 | K8: BNR 2012-2021, valeur 2022 et 2023 à partir du taux de variation 2021-2022 de l'aluminium
A9: Aluminium | B9: =B11+F51/1000000 -> 0.59606631 | C9: 0.62261217 | D9: 0.6369988 | E9: =E11+G51/1000000 -> 0.583051 | F9: =F11+H51/1000000 -> 0.60604568 | G9: =G11+I51/1000000 -> 0.54386673 | H9: =SUM(H10:H11) -> 0.5774852 | I9: =SUM(I10:I11) -> 0.52851166 | J9: =SUM(J10:J11) -> 0.50594089 | K9: CITEPA
A10: dont 1ère fusion | B10: =B9-B11 -> 0.41880998 | C10: =C9-C11 -> 0.42861217 | D10: =D9-D11 -> 0.4319988 | E10: =E9-E11 -> 0.382927 | F10: =F9-F11 -> 0.4219487 | G10: =G9-G11 -> 0.41854734 | H10: =J51/1000000 -> 0.42623765 | I10: =K51/1000000 -> 0.39181055 | J10: =L51/1000000 -> 0.3794109 | K10: CITEPA
A11: dont 2e fusion | B11: =F52/1000000 -> 0.17725633 | C11: 0.194 | D11: 0.205 | E11: =G52/1000000 -> 0.200124 | F11: =H52/1000000 -> 0.18409698 | G11: =I52/1000000 -> 0.12531939 | H11: =J52/1000000 -> 0.15124755 | I11: =K52/1000000 -> 0.13670111 | J11: =L52/1000000 -> 0.12652999 | K11: CITEPA
A12: Ethylène | B12: =F72/1000000 -> 2.5145758 | C12: 2.24 | D12: 2.59 | E12: =G72/1000000 -> 2.158317 | F12: =H72/1000000 -> 2.3402355 | G12: =I72/1000000 -> 2.2727659 | H12: =J72/1000000 -> 2.3138415 | I12: =K72/1000000 -> 1.626623 | J12: =L72/1000000 -> 1.8421029 | K12: CITEPA
A13: Chlore | B13: =F79/1000000 -> 0.613219 | C13: =B13+(E13-B13)/3*1 -> 0.50602933 | D13: =B13+(E13-B13)/3*2 -> 0.39883967 | E13: =G79/1000000 -> 0.29165 | F13: =H79/1000000 -> 0.2972759 | G13: =I79/1000000 -> 0.2783793 | H13: =J79/1000000 -> 0.333682 | I13: =K79/1000000 -> 0.251754 | J13: =L79/1000000 -> 0.255626 | K13: CITEPA | L13: (erreur auparavant, monochlorure de vinyle à la place)
A14: Ammoniac | B14: =F65/1000000 -> 1.068785 | C14: 1.1 | D14: 0.91 | E14: =G65/1000000 -> 1.112167 | F14: =H65/1000000 -> 1.0748098 | G14: =I65/1000000 -> 0.999913 | H14: =J65/1000000 -> 0.91649323 | I14: =K65/1000000 -> 0.85601795 | J14: =L65/1000000 -> 0.69479755 | K14: CITEPA
A15: Clinker | B15: =F30/1000 -> 12.540861 | C15: 12.67 | D15: 12.36 | E15: =G30/1000 -> 12.844855 | F15: =H30/1000 -> 12.935931 | G15: =I30/1000 -> 11.771046 | H15: =J30/1000 -> 12.242079 | I15: =K30/1000 -> 12.044779 | J15: =L30/1000 -> 10.672455 | K15: CITEPA
A16: Verre | B16: =F37/1000000 -> 5.5025794 | C16: 5.168369 | D16: 5.5996366 | E16: =G37/1000000 -> 5.7240104 | F16: =H37/1000000 -> 5.7386751 | G16: =I37/1000000 -> 5.048226 | H16: =J37/1000000 -> 5.6717456 | I16: =K37/1000000 -> 5.5682739 | J16: =L37/1000000 -> 5.0170238 | K16: CITEPA
A17: Papier cartons | B17: 7.986 | C17: 7.984 | D17: 8.021 | E17: 7.87 | F17: 7.323 | G17: 6.873 | H17: 7.357 | I17: =7091800/1000000 -> 7.0918 | J17: =6135600/1000000 -> 6.1356 | K17: BNR 2012-2021 et ADEME pour 2022 et 2023 (venant de rapports statistiques Copacel)
A18: Papier | B18: =F58/1000 -> 1.44732 | C18: 1.423 | D18: 1.406 | E18: =G58/1000 -> 1.284535 | F18: =H58/1000 -> 1.322728 | G18: =I58/1000 -> 1.351074 | H18: =J58/1000 -> 1.309766 | I18: =K58/1000 -> 1.318604 | J18: =L58/1000 -> 1.211874 | K18: CITEPA (pâte à papier) - pas cohérent avec BNR car CITEPA ne prend en compte que la pâte à papier (kraft ou bisulfite)
A19: Sucre | B19: =F86/1000 -> 4.515 | C19: 4.68 | D19: 6.24 | E19: =G86/1000 -> 5.092 | F19: =H86/1000 -> 4.969 | G19: =I86/1000 -> 3.445 | H19: =J86/1000 -> 4.55 | I19: =K86/1000 -> 3.95 | J19: =L86/1000 -> 4.225 | K19: CITEPA
A21: Productions industrielles utilisées dans l'inventaire CITEPA édition 2024 :
A27: Clinker (kt) :
B29: 1990 | C29: 2000 | D29: 2005 | E29: 2010 | F29: 2015 | G29: 2018 | H29: 2019 | I29: 2020 | J29: 2021 | K29: 2022 | L29: 2023
A30: Prod (kt) | B30: 20854 | C30: 16323 | D30: 17328.763 | E30: 14982.373 | F30: 12540.861 | G30: 12844.855 | H30: 12935.931 | I30: 11771.046 | J30: 12242.079 | K30: 12044.779 | L30: 10672.455
A34: Verre (t) :
B36: 1990 | C36: 2000 | D36: 2005 | E36: 2010 | F36: 2015 | G36: 2018 | H36: 2019 | I36: 2020 | J36: 2021 | K36: 2022 | L36: 2023
A37: Prod totale (t) | B37: 5266354 | C37: 6216566 | D37: 6053081.5 | E37: 5267170.2 | F37: 5502579.4 | G37: 5724010.5 | H37: 5738675.1 | I37: 5048226 | J37: 5671745.6 | K37: 5568273.9 | L37: 5017023.8
A38: Verre neuf (t) (hors calcin externe) | B38: 4333354 | C38: 4227566 | D38: 3969081.5 | E38: 2921170.2 | F38: 3161579.4 | G38: 3468010.5 | H38: 3403865.1 | I38: 3012226 | J38: 3512474.6 | K38: 3477611.9 | L38: 2747226.8
A41: Acier (kt) :
B43: 1990 | C43: 2000 | D43: 2005 | E43: 2010 | F43: 2015 | G43: 2018 | H43: 2019 | I43: 2020 | J43: 2021 | K43: 2022 | L43: 2023
A44: Acier O2 (kt) | B44: 13625.295 | C44: 12755.319 | D44: 12349.004 | E44: 10017.557 | F44: 9985.539 | G44: 10598.281 | H44: 10130.063 | I44: 7872.834 | J44: 8937.677 | K44: 8222.646 | L44: 6413.039
A45: Acier élec (kt) | B45: 5448 | C45: 8460 | D45: 7308 | E45: 5728.919 | F45: 5100.9214 | G45: 4850.7678 | H45: 4457.8274 | I45: 3717.3779 | J45: 4604.4492 | K45: 3995.3518 | L45: 3597.8462
A48: Aluminium (t) :
B50: 1990 | C50: 2000 | D50: 2005 | E50: 2010 | F50: 2015 | G50: 2018 | H50: 2019 | I50: 2020 | J50: 2021 | K50: 2022 | L50: 2023
A51: 1ère fusion (t) | B51: 325900 | C51: 437718 | D51: 442588 | E51: 357546 | F51: 418809.98 | G51: 382927 | H51: 421948.7 | I51: 418547.34 | J51: 426237.65 | K51: 391810.55 | L51: 379410.9
A52: 2nde fusion (t) | B52: 224700 | C52: 259788 | D52: 222688 | E52: 199343.16 | F52: 177256.33 | G52: 200124 | H52: 184096.98 | I52: 125319.39 | J52: 151247.55 | K52: 136701.11 | L52: 126529.99
A55: Pâte à papier (kt) :
B57: 1990 | C57: 2000 | D57: 2005 | E57: 2010 | F57: 2015 | G57: 2018 | H57: 2019 | I57: 2020 | J57: 2021 | K57: 2022 | L57: 2023
A58: Prod (kt) | B58: 1644.8 | C58: 1817.4 | D58: 1927.003 | E58: 1369.537 | F58: 1447.32 | G58: 1284.535 | H58: 1322.728 | I58: 1351.074 | J58: 1309.766 | K58: 1318.604 | L58: 1211.874
A62: Ammoniac (t) :
B64: 1990 | C64: 2000 | D64: 2005 | E64: 2010 | F64: 2015 | G64: 2018 | H64: 2019 | I64: 2020 | J64: 2021 | K64: 2022 | L64: 2023
A65: Prod (t) | B65: 1927800 | C65: 1854457.1 | D65: 1474656.9 | E65: 955951 | F65: 1068785 | G65: 1112167 | H65: 1074809.8 | I65: 999913 | J65: 916493.23 | K65: 856017.95 | L65: 694797.55
A69: Ethylène (t) :
B71: 1990 | C71: 2000 | D71: 2005 | E71: 2010 | F71: 2015 | G71: 2018 | H71: 2019 | I71: 2020 | J71: 2021 | K71: 2022 | L71: 2023
A72: Prod (t) | B72: 2347279.5 | C72: 2954840.7 | D72: 2869650.2 | E72: 2323853 | F72: 2514575.8 | G72: 2158317 | H72: 2340235.5 | I72: 2272765.9 | J72: 2313841.5 | K72: 1626623 | L72: 1842102.9
A76: Chlore (t) :
B78: 1990 | C78: 2000 | D78: 2005 | E78: 2010 | F78: 2015 | G78: 2018 | H78: 2019 | I78: 2020 | J78: 2021 | K78: 2022 | L78: 2023
A79: Prod (t) | B79: 873858.92 | C79: 875652.17 | D79: 712263 | E79: 628987 | F79: 613219 | G79: 291650 | H79: 297275.9 | I79: 278379.3 | J79: 333682 | K79: 251754 | L79: 255626
A83: Sucre (kt) :
B85: 1990 | C85: 2000 | D85: 2005 | E85: 2010 | F85: 2015 | G85: 2018 | H85: 2019 | I85: 2020 | J85: 2021 | K85: 2022 | L85: 2023
A86: Prod (kt) | B86: 4250 | C86: 4233 | D86: 4140 | E86: 4225 | F86: 4515 | G86: 5092 | H86: 4969 | I86: 3445 | J86: 4550 | K86: 3950 | L86: 4225

Sheet A renseigner
B1: Balance commerciale
B4: AMS | C4: Observé | D4: Repris de l'observé | F4: Projeté | G4: Projeté | H4: Projeté | I4: Projeté | J4: Projeté | K4: Projeté
B5: Production (Mt) | C5: 2019 | D5: 2020 | E5: 2021 | F5: 2025 | G5: 2030 | H5: 2035 | I5: 2040 | J5: 2045 | K5: 2050
B6: Acier | C6: =Récap!C42 -> 14.58789 | D6: =Récap!D42 -> 11.590212 | E6: =Récap!E42 -> 13.542126 | F6: =Récap!H42 -> 14.235654 | G6: =Récap!I42 -> 15.05754 | H6: =Récap!J42 -> 15.128067 | I6: =Récap!K42 -> 15.196191 | J6: =Récap!L42 -> 15.261912 | K6: =Récap!M42 -> 15.325229
B7: dont haut fourneaux | C7: =Récap!C43 -> 10.130063 | D7: =Récap!D43 -> 7.872834 | E7: =Récap!E43 -> 8.937677 | F7: =Récap!H43 -> 8.8125479 | G7: =Récap!I43 -> 5.2457955 | H7: =Récap!J43 -> 3.2441297 | I7: =Récap!K43 -> 3.2790028 | J7: =Récap!L43 -> 0 | K7: =Récap!M43 -> 0
B8: dont procédé électrique | C8: =Récap!C44 -> 4.4578274 | D8: =Récap!D44 -> 3.7173779 | E8: =Récap!E44 -> 4.6044492 | F8: =Récap!H44 -> 5.4231064 | G8: =Récap!I44 -> 6.8117441 | H8: =Récap!J44 -> 7.3839377 | I8: =Récap!K44 -> 7.4171887 | J8: =Récap!L44 -> 9.2619118 | K8: =Récap!M44 -> 9.3252285
B9: dont DRI | C9: =Récap!C45 -> 0 | D9: =Récap!D45 -> 0 | E9: =Récap!E45 -> 0 | F9: =Récap!H45 -> 0 | G9: =Récap!I45 -> 3 | H9: =Récap!J45 -> 4.5 | I9: =Récap!K45 -> 4.5 | J9: =Récap!L45 -> 6 | K9: =Récap!M45 -> 6
B10: Aluminium | C10: =Récap!C46 -> 0.894 | D10: =Récap!D46 -> 0.818 | E10: =Récap!E46 -> 0.855 | F10: =Récap!H46 -> 0.96932316 | G10: =Récap!I46 -> 1.1218832 | H10: =Récap!J46 -> 1.3021047 | I10: =Récap!K46 -> 1.4952796 | J10: =Récap!L46 -> 1.7014078 | K10: =Récap!M46 -> 1.9204895
B11: dont aluminium recyclé | C11: =Récap!C47 -> 0.476 | D11: =Récap!D47 -> 0.401 | E11: =Récap!E47 -> 0.425 | F11: =Récap!H47 -> 0.54884942 | G11: =Récap!I47 -> 0.67312992 | H11: =Récap!J47 -> 0.81381543 | I11: =Récap!K47 -> 0.97193172 | J11: =Récap!L47 -> 1.1484503 | K11: =Récap!M47 -> 1.3443426
B12: Ethylène | C12: =Récap!C48 -> 2.3402355 | D12: =Récap!D48 -> 2.2727659 | E12: =Récap!E48 -> 2.3138415 | F12: =Récap!H48 -> 2.0515983 | G12: =Récap!I48 -> 2.0626038 | H12: =Récap!J48 -> 1.9717655 | I12: =Récap!K48 -> 1.8751536 | J12: =Récap!L48 -> 1.7727683 | K12: =Récap!M48 -> 1.6646095
B13: Chlore | C13: =Récap!C49 -> 0.2972759 | D13: =Récap!D49 -> 0.2783793 | E13: =Récap!E49 -> 0.333682 | F13: =Récap!H49 -> 0.28466846 | G13: =Récap!I49 -> 0.27365818 | H13: =Récap!J49 -> 0.26509964 | I13: =Récap!K49 -> 0.25603702 | J13: =Récap!L49 -> 0.2469744 | K13: =Récap!M49 -> 0.23791178
B14: Ammoniac | C14: =Récap!C50 -> 1.0748098 | D14: =Récap!D50 -> 0.999913 | E14: =Récap!E50 -> 0.91649323 | F14: =Récap!H50 -> 1.0712001 | G14: =Récap!I50 -> 1.246829 | H14: =Récap!J50 -> 1.2129064 | I14: =Récap!K50 -> 1.1674359 | J14: =Récap!L50 -> 1.1104176 | K14: =Récap!M50 -> 1.0418515
B15: Clinker | C15: =Récap!C51 -> 12.935931 | D15: =Récap!D51 -> 11.771046 | E15: =Récap!E51 -> 12.242079 | F15: =Récap!H51 -> 11.725175 | G15: =Récap!I51 -> 12.199288 | H15: =Récap!J51 -> 10.983091 | I15: =Récap!K51 -> 9.8292031 | J15: =Récap!L51 -> 8.7376249 | K15: =Récap!M51 -> 7.7083564
B16: Verre | C16: =Récap!C52 -> 5.7386751 | D16: =Récap!D52 -> 5.048226 | E16: =Récap!E52 -> 5.6717456 | F16: =Récap!H52 -> 5.5628464 | G16: =Récap!I52 -> 5.4272367 | H16: =Récap!J52 -> 5.07978 | I16: =Récap!K52 -> 4.7323233 | J16: =Récap!L52 -> 4.3848666 | K16: =Récap!M52 -> 4.0374099
B17: Papier | C17: =Récap!C53 -> 7.323 | D17: =Récap!D53 -> 6.873 | E17: =Récap!E53 -> 7.357 | F17: =Récap!H53 -> 7.1485822 | G17: =Récap!I53 -> 7.3406495 | H17: =Récap!J53 -> 7.357567 | I17: =Récap!K53 -> 7.3599366 | J17: =Récap!L53 -> 7.3477582 | K17: =Récap!M53 -> 7.3210317
B18: Sucre | C18: =Récap!C54 -> 4.969 | D18: =Récap!D54 -> 3.445 | E18: =Récap!E54 -> 4.55 | F18: =Récap!H54 -> 4.6964841 | G18: =Récap!I54 -> 4.8765609 | H18: =Récap!J54 -> 4.7415923 | I18: =Récap!K54 -> 4.6064994 | J18: =Récap!L54 -> 4.471282 | K18: =Récap!M54 -> 4.3359403
B20: TOTAL | C20: =SUM(C6,C10,C12:C18) -> 50.160818 | D20: =SUM(D6,D10,D12:D18) -> 43.096543 | E20: =SUM(E6,E10,E12:E18) -> 47.781968 | F20: =SUM(F6,F10,F12:F18) -> 47.745532 | G20: =SUM(G6,G10,G12:G18) -> 49.606249 | H20: =SUM(H6,H10,H12:H18) -> 48.041974 | I20: =SUM(I6,I10,I12:I18) -> 46.51806 | J20: =SUM(J6,J10,J12:J18) -> 45.035012 | K20: =SUM(K6,K10,K12:K18) -> 43.592829
B22: Total run1 | C22: 50.771132 | D22: 43.535749 | E22: 44.535749 | F22: 50.440979 | G22: 49.219427 | H22: 47.038856 | I22: 44.943856 | J22: 42.896681 | K22: 40.85488
B23: Diffus
B27: Coefficient de décorrélation VA / production physique
B29: Indice 2019 | C29: 2019 | D29: 2020 | E29: 2021 | F29: 2025 | G29: 2030 | H29: 2035 | I29: 2040 | J29: 2045 | K29: 2050
B30: Métaux primaires | C30: 1 | D30: 0.99354839 | E30: 1 | F30: 0.98 | G30: 0.96 | H30: 0.94 | I30: 0.93 | J30: 0.92 | K30: 0.92
B31: Chimie | C31: 1 | D31: 0.99354839 | E31: 1 | F31: 0.99 | G31: 0.98 | H31: 0.96 | I31: 0.94 | J31: 0.92 | K31: 0.9
B32: Minéraux non-métalliques | C32: 1 | D32: 0.99354839 | E32: 1 | F32: 0.99 | G32: 0.98 | H32: 0.955 | I32: 0.93 | J32: 0.915 | K32: 0.9
B33: IAA | C33: 1 | D33: 0.99354839 | E33: 1 | F33: 0.983 | G33: 0.95 | H33: 0.925 | I33: 0.9 | J33: 0.9 | K33: 0.9
B34: Equipements | C34: 1 | D34: 0.99354839 | E34: 1 | F34: 0.983 | G34: 0.95 | H34: 0.925 | I34: 0.9 | J34: 0.875 | K34: 0.85
B35: Autres (textile, etc.) | C35: 1 | D35: 0.99354839 | E35: 1 | F35: 0.96129032 | G35: 0.92903226 | H35: 0.89677419 | I35: 0.86451613 | J35: 0.83225806 | K35: 0.8
B36: Total diffus | C36: 1 | D36: 0.99354839 | E36: 1 | F36: 0.9819561 | G36: 0.95680443 | H36: 0.93240837 | I36: 0.90944275 | J36: 0.89277507 | K36: 0.87752987
B37: Construction | C37: 1 | D37: 1 | E37: 1 | F37: 1 | G37: 1 | H37: 1 | I37: 1 | J37: 1 | K37: 1
B39: Production physique | C39: 2019 | D39: 2020 | E39: 2021 | F39: 2025 | G39: 2030 | H39: 2035 | I39: 2040 | J39: 2045 | K39: 2050 | L39: Sortie
B40: Métaux primaires | C40: 25.805 | D40: 22.681716 | E40: 24.457 | F40: 25.256465 | G40: 25.999582 | H40: 25.792603 | I40: 27.173359 | J40: 29.152709 | K40: 31.637862
B41: Chimie | C41: 47.175 | D41: 45.592942 | E41: 46.328 | F41: 47.193941 | G41: 49.753115 | H41: 50.176378 | I41: 53.132595 | J41: 56.770454 | K41: 60.357468
B42: Minéraux non-métalliques | C42: 8.359 | D42: 7.4158452 | E42: 8.172 | F42: 8.4325674 | G42: 8.5533775 | H42: 8.5034645 | I42: 8.6816195 | J42: 9.0563404 | K42: 9.526558
B43: IAA | C43: 45.598 | D43: 43.804555 | E43: 44.859 | F43: 46.746123 | G43: 48.929058 | H43: 51.121043 | I43: 54.054345 | J43: 58.743109 | K43: 63.611128
B44: Equipements | C44: 63.615 | D44: 49.485665 | E44: 52.09 | F44: 54.610634 | G44: 57.416369 | H44: 60.121795 | I44: 63.484649 | J44: 67.302902 | K44: 71.385616
B45: Autres (textile, etc.) | C45: 23.724 | D45: 22.1144 | E45: 23.781 | F45: 24.381141 | G45: 25.634135 | H45: 26.610256 | I45: 27.840374 | J45: 29.225336 | K45: 30.67309
B46: Total diffus | C46: 214.276 | D46: 191.09512 | E46: 199.687 | F46: 206.63582 | G46: 216.34704 | H46: 222.42227 | I46: 234.52717 | J46: 250.50895 | K46: 267.68291
B47: Construction | C47: 114.882 | D47: 101.443 | E47: 108.227 | F47: 111.90446 | G47: 111.60903 | H47: 110.28798 | I47: 110.67153 | J47: 112.51429 | K47: 116.70087
B50: Leviers
B53: Mix énergétique
B54: Onglet Mix éner % (l'onglet Mix éner % (2) reprend les hypothèses sous un autre format)
B56: Mix énergétique | E56: Charbon | F56: Coke | G56: Produits pétroliers raffinés | H56: Gaz de réseau | I56: Biomasse solide | J56: Déchets | K56: Biocarburants | L56: Gaz renouvelable | M56: Chaleur de l'environnement | N56: Solaire thermique et géothermie | O56: Électricité | P56: Electricité PAC | Q56: Chaleur vendue | R56: Hydrogène (consommation finale) | S56: Total
B57: Métaux primaires
B58: Dont sidérurgie (hauts fourneaux) | C58: 2021 | D58: % | E58: =Récap!E105 -> 0.40234553 | F58: =Récap!F105 -> 0.59765447 | G58: =Récap!G105 -> 0 | H58: =Récap!H105 -> 0 | I58: =Récap!I105 -> 0 | J58: =Récap!J105 -> 0 | K58: =Récap!K105 -> 0 | L58: =Récap!L105 -> 0 | ... R58: =Récap!R105 -> 0 | S58: =SUM(E58:R58) -> 1
B59: Dont sidérurgie (hauts fourneaux) | C59: 2030 | D59: % | E59: =Récap!E106 -> 0.3655 | F59: =Récap!F106 -> 0.5445 | G59: =Récap!G106 -> 0 | H59: =Récap!H106 -> 0 | I59: =Récap!I106 -> 0.03 | J59: =Récap!J106 -> 0.06 | K59: =Récap!K106 -> 0 | L59: =Récap!L106 -> 0 | ... R59: =Récap!R106 -> 0 | S59: =SUM(E59:R59) -> 1
B60: Dont sidérurgie (hauts fourneaux) | C60: 2050 | D60: % | E60: =Récap!E108 -> 0.33394679 | F60: =Récap!F108 -> 0.49605321 | G60: =Récap!G108 -> 0 | H60: =Récap!H108 -> 0 | I60: =Récap!I108 -> 0.05 | J60: =Récap!J108 -> 0.12 | K60: =Récap!K108 -> 0 | L60: =Récap!L108 -> 0 | ... R60: =Récap!R108 -> 0 | S60: =SUM(E60:R60) -> 1
B62: Dont sidérurgie (arc électrique) | C62: 2021 | D62: % | E62: =Récap!E110 -> 0.035 | F62: =Récap!F110 -> 0 | G62: =Récap!G110 -> 0.02 | H62: =Récap!H110 -> 0.22 | I62: =Récap!I110 -> 0 | J62: =Récap!J110 -> 0 | K62: =Récap!K110 -> 0 | L62: =Récap!L110 -> 0 | ... R62: =Récap!R110 -> 0 | S62: =SUM(E62:R62) -> 1
B63: Dont sidérurgie (arc électrique) | C63: 2030 | D63: % | E63: =Récap!E111 -> 0.02 | F63: =Récap!F111 -> 0 | G63: =Récap!G111 -> 0.02 | H63: =Récap!H111 -> 0.2 | I63: =Récap!I111 -> 0.01 | J63: =Récap!J111 -> 0 | K63: =Récap!K111 -> 0 | L63: =Récap!L111 -> 0 | ... R63: =Récap!R111 -> 0 | S63: =SUM(E63:R63) -> 1
B64: Dont sidérurgie (arc électrique) | C64: 2050 | D64: % | E64: =Récap!E113 -> 0.010514068 | F64: =Récap!F113 -> 0 | G64: =Récap!G113 -> 0 | H64: =Récap!H113 -> 0.1441397 | I64: =Récap!I113 -> 0.01 | J64: =Récap!J113 -> 0.028080774 | K64: =Récap!K113 -> 0 | L64: =Récap!L113 -> 0 | ... R64: =Récap!R113 -> 0 | S64: =SUM(E64:R64) -> 1
B66: Dont sidérurgie (réduction directe) | C66: 2021 | D66: % | E66: =Récap!E115 -> 0 | F66: =Récap!F115 -> 0 | G66: =Récap!G115 -> 0 | H66: =Récap!H115 -> 0.84803256 | I66: =Récap!I115 -> 0 | J66: =Récap!J115 -> 0 | K66: =Récap!K115 -> 0 | L66: =Récap!L115 -> 0 | ... R66: =Récap!R115 -> 0 | S66: =SUM(E66:R66) -> 1
B67: Dont sidérurgie (réduction directe) | C67: 2030 | D67: % | E67: =Récap!E116 -> 0 | F67: =Récap!F116 -> 0 | G67: =Récap!G116 -> 0 | H67: =Récap!H116 -> 0.54803256 | I67: =Récap!I116 -> 0 | J67: =Récap!J116 -> 0 | K67: =Récap!K116 -> 0 | L67: =Récap!L116 -> 0 | ... R67: =Récap!R116 -> 0.3 | S67: =SUM(E67:R67) -> 1
B68: Dont sidérurgie (réduction directe) | C68: 2050 | D68: % | E68: =Récap!E118 -> 0 | F68: =Récap!F118 -> 0 | G68: =Récap!G118 -> 0 | H68: =Récap!H118 -> 0.15207756 | I68: =Récap!I118 -> 0 | J68: =Récap!J118 -> 0 | K68: =Récap!K118 -> 0 | L68: =Récap!L118 -> 0 | ... R68: =Récap!R118 -> 0.71024931 | S68: =SUM(E68:R68) -> 1
B70: Dont sidérurgie (mise en forme de l'acier) | C70: 2021 | E70: =Récap!E120 -> 0.051378863 | F70: =Récap!F120 -> 0.028814188 | G70: =Récap!G120 -> 0.0084139056 | H70: =Récap!H120 -> 0.43763064 | I70: =Récap!I120 -> 0 | J70: =Récap!J120 -> 0 | K70: =Récap!K120 -> 0 | L70: =Récap!L120 -> 0 | ... R70: =Récap!R120 -> 0 | S70: =SUM(E70:R70) -> 1
B71: Dont sidérurgie (mise en forme de l'acier) | C71: 2030 | E71: =Récap!E121 -> 0.04 | F71: =Récap!F121 -> 0 | G71: =Récap!G121 -> 0.008 | H71: =Récap!H121 -> 0.29 | I71: =Récap!I121 -> 0.032 | J71: =Récap!J121 -> 0.02 | K71: =Récap!K121 -> 0 | L71: =Récap!L121 -> 0 | ... R71: =Récap!R121 -> 0 | S71: =SUM(E71:R71) -> 1
B72: Dont sidérurgie (mise en forme de l'acier) | C72: 2050 | E72: =Récap!E123 -> 0 | F72: =Récap!F123 -> 0 | G72: =Récap!G123 -> 0 | H72: =Récap!H123 -> 0.2 | I72: =Récap!I123 -> 0.062 | J72: =Récap!J123 -> 0.028 | K72: =Récap!K123 -> 0 | L72: =Récap!L123 -> 0 | ... R72: =Récap!R123 -> 0 | S72: =SUM(E72:R72) -> 1
B74: Dont aluminium (primaire) | C74: 2021 | D74: % | E74: =Récap!E125 -> 0 | F74: =Récap!F125 -> 0 | G74: =Récap!G125 -> 0.02811245 | H74: =Récap!H125 -> 0.25100402 | I74: =Récap!I125 -> 0 | J74: =Récap!J125 -> 0 | K74: =Récap!K125 -> 0 | L74: =Récap!L125 -> 0 | ... R74: =Récap!R125 -> 0 | S74: =SUM(E74:R74) -> 1
B75: Dont aluminium (primaire) | C75: 2030 | D75: % | E75: =Récap!E126 -> 0 | F75: =Récap!F126 -> 0 | G75: =Récap!G126 -> 0 | H75: =Récap!H126 -> 0.15 | I75: =Récap!I126 -> 0 | J75: =Récap!J126 -> 0 | K75: =Récap!K126 -> 0 | L75: =Récap!L126 -> 0 | ... R75: =Récap!R126 -> 0 | S75: =SUM(E75:R75) -> 1
B76: Dont aluminium (primaire) | C76: 2050 | D76: % | E76: =Récap!E128 -> 0 | F76: =Récap!F128 -> 0 | G76: =Récap!G128 -> 0 | H76: =Récap!H128 -> 0.11 | I76: =Récap!I128 -> 0 | J76: =Récap!J128 -> 0 | K76: =Récap!K128 -> 0 | L76: =Récap!L128 -> 0 | ... R76: =Récap!R128 -> 0.02 | S76: =SUM(E76:R76) -> 1
B78: Dont aluminium (recyclé) | C78: 2021 | D78: % | E78: =Récap!E130 -> 0 | F78: =Récap!F130 -> 0 | G78: =Récap!G130 -> 0.02461934 | H78: =Récap!H130 -> 0.63990508 | I78: =Récap!I130 -> 0 | J78: =Récap!J130 -> 0 | K78: =Récap!K130 -> 0 | L78: =Récap!L130 -> 0 | ... R78: =Récap!R130 -> 0 | S78: =SUM(E78:R78) -> 1
B79: Dont aluminium (recyclé) | C79: 2030 | D79: % | E79: =Récap!E131 -> 0 | F79: =Récap!F131 -> 0 | G79: =Récap!G131 -> 0 | H79: =Récap!H131 -> 0.55 | I79: =Récap!I131 -> 0 | J79: =Récap!J131 -> 0 | K79: =Récap!K131 -> 0 | L79: =Récap!L131 -> 0 | ... R79: =Récap!R131 -> 0 | S79: =SUM(E79:R79) -> 1
B80: Dont aluminium (recyclé) | C80: 2050 | D80: % | E80: =Récap!E133 -> 0 | F80: =Récap!F133 -> 0 | G80: =Récap!G133 -> 0 | H80: =Récap!H133 -> 0.05 | I80: =Récap!I133 -> 0 | J80: =Récap!J133 -> 0 | K80: =Récap!K133 -> 0 | L80: =Récap!L133 -> 0 | ... R80: =Récap!R133 -> 0 | S80: =SUM(E80:R80) -> 1
B82: Dont autres métaux primaires | C82: 2021 | D82: % | E82: =Récap!E135 -> 0 | F82: =Récap!F135 -> 0 | G82: =Récap!G135 -> 0 | H82: =Récap!H135 -> 0.28501215 | I82: =Récap!I135 -> 0.0025709966 | J82: =Récap!J135 -> 0 | K82: =Récap!K135 -> 0 | L82: =Récap!L135 -> 0 | ... R82: =Récap!R135 -> 0 | S82: =SUM(E82:R82) -> 1
B83: Dont autres métaux primaires | C83: 2030 | D83: % | E83: =Récap!E136 -> 0 | F83: =Récap!F136 -> 0 | G83: =Récap!G136 -> 0 | H83: =Récap!H136 -> 0.219 | I83: =Récap!I136 -> 0.01988383 | J83: =Récap!J136 -> 0 | K83: =Récap!K136 -> 0 | L83: =Récap!L136 -> 0 | ... R83: =Récap!R136 -> 0.03 | S83: =SUM(E83:R83) -> 1
B84: Dont autres métaux primaires | C84: 2050 | D84: % | E84: =Récap!E138 -> 0 | F84: =Récap!F138 -> 0 | G84: =Récap!G138 -> 0 | H84: =Récap!H138 -> 0.08 | I84: =Récap!I138 -> 0.05 | J84: =Récap!J138 -> 0 | K84: =Récap!K138 -> 0 | L84: =Récap!L138 -> 0 | ... R84: =Récap!R138 -> 0.08 | S84: =SUM(E84:R84) -> 1
B86: Chimie | E86: Charbon | F86: Coke | G86: Produits pétroliers raffinés | H86: Gaz naturel | I86: Biomasse solide | J86: Déchets | K86: Biocarburants | L86: Gaz renouvelable | M86: Chaleur de l'environnement | N86: Solaire thermique et géothermie | O86: Électricité | P86: Electricité PAC | Q86: Chaleur vendue | R86: Hydrogène
B87: Dont Ammoniac (vaporeformage) | C87: 2021 | D87: % | E87: =Récap!E141 -> 0 | F87: =Récap!F141 -> 0 | G87: =Récap!G141 -> 0.005 | H87: =Récap!H141 -> 0.93 | I87: =Récap!I141 -> 0.005 | J87: =Récap!J141 -> 0 | K87: =Récap!K141 -> 0 | L87: =Récap!L141 -> 0 | ... R87: =Récap!R141 -> 0 | S87: =SUM(E87:R87) -> 1
B88: Dont Ammoniac (vaporeformage) | C88: 2030 | D88: % | E88: =Récap!E142 -> 0 | F88: =Récap!F142 -> 0 | G88: =Récap!G142 -> 0.005 | H88: =Récap!H142 -> 0.93 | I88: =Récap!I142 -> 0.005 | J88: =Récap!J142 -> 0 | K88: =Récap!K142 -> 0 | L88: =Récap!L142 -> 0 | ... R88: =Récap!R142 -> 0 | S88: =SUM(E88:R88) -> 1
B89: Dont Ammoniac (vaporeformage) | C89: 2050 | D89: % | E89: =Récap!E144 -> 0 | F89: =Récap!F144 -> 0 | G89: =Récap!G144 -> 0 | H89: =Récap!H144 -> 0.9 | I89: =Récap!I144 -> 0 | J89: =Récap!J144 -> 0 | K89: =Récap!K144 -> 0 | L89: =Récap!L144 -> 0 | ... R89: =Récap!R144 -> 0 | S89: =SUM(E89:R89) -> 1
B91: Dont pétrochimie de base | C91: 2021 | D91: % | E91: =Récap!E146 -> 0 | F91: =Récap!F146 -> 0 | G91: =Récap!G146 -> 0 | H91: =Récap!H146 -> 0.10794573 | I91: =Récap!I146 -> 0.012170882 | J91: =Récap!J146 -> 0 | K91: =Récap!K146 -> 0 | L91: =Récap!L146 -> 0 | ... R91: =Récap!R146 -> 0 | S91: =SUM(E91:R91) -> 0.38830754
B92: Dont pétrochimie de base | C92: 2030 | D92: % | E92: =Récap!E147 -> 0 | F92: =Récap!F147 -> 0 | G92: =Récap!G147 -> 0 | H92: =Récap!H147 -> 0.049 | I92: =Récap!I147 -> 0.03 | J92: =Récap!J147 -> 0.0075 | K92: =Récap!K147 -> 0 | L92: =Récap!L147 -> 0 | ... R92: =Récap!R147 -> 0 | S92: =SUM(E92:R92) -> 0.7025
B93: Dont pétrochimie de base | C93: 2050 | D93: % | E93: =Récap!E149 -> 0 | F93: =Récap!F149 -> 0 | G93: =Récap!G149 -> 0 | H93: =Récap!H149 -> 0.0165 | I93: =Récap!I149 -> 0.023 | J93: =Récap!J149 -> 0.0075 | K93: =Récap!K149 -> 0 | L93: =Récap!L149 -> 0 | ... R93: =Récap!R149 -> 0 | S93: =SUM(E93:R93) -> 0.915
B95: Dont autres chimies | C95: 2021 | D95: % | E95: =Récap!E151 -> 0.069144909 | F95: =Récap!F151 -> 0 | G95: =Récap!G151 -> 0.023722328 | H95: =Récap!H151 -> 0.54601876 | I95: =Récap!I151 -> 0.015836627 | J95: =Récap!J151 -> 0 | K95: =Récap!K151 -> 0 | L95: =Récap!L151 -> 0 | ... R95: =Récap!R151 -> 0 | S95: =SUM(E95:R95) -> 1
B96: Dont autres chimies | C96: 2030 | D96: % | E96: =Récap!E152 -> 0 | F96: =Récap!F152 -> 0 | G96: =Récap!G152 -> 0.06 | H96: =Récap!H152 -> 0.24 | I96: =Récap!I152 -> 0.11 | J96: =Récap!J152 -> 0.05 | K96: =Récap!K152 -> 0 | L96: =Récap!L152 -> 0 | ... R96: =Récap!R152 -> 0 | S96: =SUM(E96:R96) -> 1 | T96: Electrification diminuée pour augmentetr la part de biomasse solide et déchets (sans toucher aux autres vecteurs)
B97: Dont autres chimies | C97: 2050 | D97: % | E97: =Récap!E154 -> 0 | F97: =Récap!F154 -> 0 | G97: =Récap!G154 -> 0 | H97: =Récap!H154 -> 0.1 | I97: =Récap!I154 -> 0.09 | J97: =Récap!J154 -> 0.06 | K97: =Récap!K154 -> 0 | L97: =Récap!L154 -> 0 | ... R97: =Récap!R154 -> 0 | S97: =SUM(E97:R97) -> 1
B99: Non-métalliques | E99: Charbon | F99: Coke | G99: Produits pétroliers raffinés | H99: Gaz naturel | I99: Biomasse solide | J99: Déchets | K99: Biocarburants | L99: Gaz renouvelable | M99: Chaleur de l'environnement | N99: Solaire thermique et géothermie | O99: Électricité | P99: Electricité PAC | Q99: Chaleur vendue | R99: Hydrogène
B100: Dont ciment | C100: 2021 | D100: % | E100: =Récap!E157 -> 0.14 | F100: =Récap!F157 -> 0 | G100: =Récap!G157 -> 0.385 | H100: =Récap!H157 -> 0.02 | I100: =Récap!I157 -> 0.17 | J100: =Récap!J157 -> 0.255 | K100: =Récap!K157 -> 0 | L100: =Récap!L157 -> 0 | ... R100: =Récap!R157 -> 0 | S100: =SUM(E100:R100) -> 1
B101: Dont ciment | C101: 2030 | D101: % | E101: =Récap!E158 -> 0.01 | F101: =Récap!F158 -> 0 | G101: =Récap!G158 -> 0.09 | H101: =Récap!H158 -> 0.02 | I101: =Récap!I158 -> 0.3 | J101: =Récap!J158 -> 0.48 | K101: =Récap!K158 -> 0 | L101: =Récap!L158 -> 0 | ... R101: =Récap!R158 -> 0 | S101: =SUM(E101:R101) -> 1 | T101: Augmentation des déchets et biomasse avec forte diminution de l'electrification et de l'utilisation de PPR
B102: Dont ciment | C102: 2050 | D102: % | E102: =Récap!E160 -> 0 | F102: =Récap!F160 -> 0 | G102: =Récap!G160 -> 0 | H102: =Récap!H160 -> 0.01 | I102: =Récap!I160 -> 0.24402641 | J102: =Récap!J160 -> 0.54597359 | K102: =Récap!K160 -> 0 | L102: =Récap!L160 -> 0 | ... R102: =Récap!R160 -> 0 | S102: =SUM(E102:R102) -> 1
B104: Dont verre | C104: 2021 | D104: % | E104: =Récap!E162 -> 0 | F104: =Récap!F162 -> 0 | G104: =Récap!G162 -> 0.09 | H104: =Récap!H162 -> 0.67 | I104: =Récap!I162 -> 0 | J104: =Récap!J162 -> 0 | K104: =Récap!K162 -> 0 | L104: =Récap!L162 -> 0 | ... R104: =Récap!R162 -> 0 | S104: =SUM(E104:R104) -> 1
B105: Dont verre | C105: 2030 | D105: % | E105: =Récap!E163 -> 0 | F105: =Récap!F163 -> 0 | G105: =Récap!G163 -> 0 | H105: =Récap!H163 -> 0.54 | I105: =Récap!I163 -> 0 | J105: =Récap!J163 -> 0 | K105: =Récap!K163 -> 0 | L105: =Récap!L163 -> 0 | ... R105: =Récap!R163 -> 0 | S105: =SUM(E105:R105) -> 1
B106: Dont verre | C106: 2050 | D106: % | E106: =Récap!E165 -> 0 | F106: =Récap!F165 -> 0 | G106: =Récap!G165 -> 0 | H106: =Récap!H165 -> 0.15 | I106: =Récap!I165 -> 0 | J106: =Récap!J165 -> 0 | K106: =Récap!K165 -> 0 | L106: =Récap!L165 -> 0 | ... R106: =Récap!R165 -> 0 | S106: =SUM(E106:R106) -> 1
B108: Dont autres non-métalliques | C108: 2021 | D108: % | E108: =Récap!E167 -> 0.058824428 | F108: =Récap!F167 -> 0.023692804 | G108: =Récap!G167 -> 0.12818758 | H108: =Récap!H167 -> 0.36949937 | I108: =Récap!I167 -> 0.18685926 | J108: =Récap!J167 -> 0 | K108: =Récap!K167 -> 0 | L108: =Récap!L167 -> 0 | ... R108: =Récap!R167 -> 0 | S108: =SUM(E108:R108) -> 1
B109: Dont autres non-métalliques | C109: 2030 | D109: % | E109: =Récap!E168 -> 0 | F109: =Récap!F168 -> 0 | G109: =Récap!G168 -> 0.01 | H109: =Récap!H168 -> 0.245 | I109: =Récap!I168 -> 0.305 | J109: =Récap!J168 -> 0 | K109: =Récap!K168 -> 0 | L109: =Récap!L168 -> 0 | ... R109: =Récap!R168 -> 0 | S109: =SUM(E109:R109) -> 1 | T109: Ajustements pour avoir une évolution plus logique et atteindre les niveaux de consos
B110: Dont autres non-métalliques | C110: 2050 | D110: % | E110: =Récap!E170 -> 0 | F110: =Récap!F170 -> 0 | G110: =Récap!G170 -> 0 | H110: =Récap!H170 -> 0.16 | I110: =Récap!I170 -> 0.27951958 | J110: =Récap!J170 -> 0 | K110: =Récap!K170 -> 0 | L110: =Récap!L170 -> 0 | ... R110: =Récap!R170 -> 0 | S110: =SUM(E110:R110) -> 1
B112: Industries agroalimentaires | E112: Charbon | F112: Coke | G112: Produits pétroliers raffinés | H112: Gaz naturel | I112: Biomasse solide | J112: Déchets | K112: Biocarburants | L112: Gaz renouvelable | M112: Chaleur de l'environnement | N112: Solaire thermique et géothermie | O112: Électricité | P112: Electricité PAC | Q112: Chaleur vendue | R112: Hydrogène
B113: Dont Sucre | C113: 2021 | D113: % | E113: =Récap!E173 -> 0.15 | F113: =Récap!F173 -> 0.04 | G113: =Récap!G173 -> 0.01 | H113: =Récap!H173 -> 0.69950617 | I113: =Récap!I173 -> 0 | J113: =Récap!J173 -> 0 | K113: =Récap!K173 -> 0 | L113: =Récap!L173 -> 0.0004938335 | ... R113: =Récap!R173 -> 0 | S113: =SUM(E113:R113) -> 1
B114: Dont Sucre | C114: 2030 | D114: % | E114: =Récap!E174 -> 0 | F114: =Récap!F174 -> 0.04 | G114: =Récap!G174 -> 0.01 | H114: =Récap!H174 -> 0.65 | I114: =Récap!I174 -> 0.06 | J114: =Récap!J174 -> 0.08 | K114: =Récap!K174 -> 0 | L114: =Récap!L174 -> 0.01 | ... R114: =Récap!R174 -> 0 | S114: =SUM(E114:R114) -> 1
B115: Dont Sucre | C115: 2050 | D115: % | E115: =Récap!E176 -> 0 | F115: =Récap!F176 -> 0 | G115: =Récap!G176 -> 0 | H115: =Récap!H176 -> 0.15 | I115: =Récap!I176 -> 0.23 | J115: =Récap!J176 -> 0.07 | K115: =Récap!K176 -> 0 | L115: =Récap!L176 -> 0.2 | ... R115: =Récap!R176 -> 0 | S115: =SUM(E115:R115) -> 1
B117: Dont autres IAA | C117: 2021 | D117: % | E117: =Récap!E178 -> 0.038197862 | F117: =Récap!F178 -> 0.0023519892 | G117: =Récap!G178 -> 0.062781928 | H117: =Récap!H178 -> 0.37642387 | I117: =Récap!I178 -> 0.018456019 | J117: =Récap!J178 -> 0 | K117: =Récap!K178 -> 0 | L117: =Récap!L178 -> 0 | ... R117: =Récap!R178 -> 0 | S117: =SUM(E117:R117) -> 1
B118: Dont autres IAA | C118: 2030 | D118: % | E118: =Récap!E179 -> 0 | F118: =Récap!F179 -> 0 | G118: =Récap!G179 -> 0 | H118: =Récap!H179 -> 0.12 | I118: =Récap!I179 -> 0.15 | J118: =Récap!J179 -> 0 | K118: =Récap!K179 -> 0 | L118: =Récap!L179 -> 0 | ... R118: =Récap!R179 -> 0 | S118: =SUM(E118:R118) -> 1 | T118: Ajustements pour diminuer légèrement la consommation de biomasse
B119: Dont autres IAA | C119: 2050 | D119: % | E119: =Récap!E181 -> 0 | F119: =Récap!F181 -> 0 | G119: =Récap!G181 -> 0 | H119: =Récap!H181 -> 0.078832364 | I119: =Récap!I181 -> 0.12145701 | J119: =Récap!J181 -> 0 | K119: =Récap!K181 -> 0 | L119: =Récap!L181 -> 0 | ... R119: =Récap!R181 -> 0 | S119: =SUM(E119:R119) -> 1
B121: Equipement | C121: 2021 | E121: =Récap!E183 -> 0.0083013991 | F121: =Récap!F183 -> 0.0083013991 | G121: =Récap!G183 -> 0.040460378 | H121: =Récap!H183 -> 0.340279 | I121: =Récap!I183 -> 0.010248979 | J121: =Récap!J183 -> 0 | K121: =Récap!K183 -> 0 | L121: =Récap!L183 -> 0 | ... R121: =Récap!R183 -> 0 | S121: =SUM(E121:R121) -> 1
B122: Equipement | C122: 2030 | E122: =Récap!E184 -> 0 | F122: =Récap!F184 -> 0 | G122: =Récap!G184 -> 0 | H122: =Récap!H184 -> 0.2 | I122: =Récap!I184 -> 0.05 | J122: =Récap!J184 -> 0.04 | K122: =Récap!K184 -> 0 | L122: =Récap!L184 -> 0 | ... R122: =Récap!R184 -> 0 | S122: =SUM(E122:R122) -> 1 | T122: La conso de biomasse se fait exclusivement sur le biogaz
B123: Equipement | C123: 2050 | E123: =Récap!E186 -> 0 | F123: =Récap!F186 -> 0 | G123: =Récap!G186 -> 0 | H123: =Récap!H186 -> 0.029 | I123: =Récap!I186 -> 0.03 | J123: =Récap!J186 -> 0.08 | K123: =Récap!K186 -> 0 | L123: =Récap!L186 -> 0 | ... R123: =Récap!R186 -> 0 | S123: =SUM(E123:R123) -> 1
B125: Construction | C125: 2021 | E125: =Récap!E188 -> 0 | F125: =Récap!F188 -> 0 | G125: =Récap!G188 -> 0.60033111 | H125: =Récap!H188 -> 0.15234286 | I125: =Récap!I188 -> 0.00096699526 | J125: =Récap!J188 -> 0 | K125: =Récap!K188 -> 0 | L125: =Récap!L188 -> 0 | ... R125: =Récap!R188 -> 0 | S125: =SUM(E125:R125) -> 1
B126: Construction | C126: 2030 | E126: =Récap!E189 -> 0 | F126: =Récap!F189 -> 0 | G126: =Récap!G189 -> 0.43 | H126: =Récap!H189 -> 0.12057348 | I126: =Récap!I189 -> 0.037426519 | J126: =Récap!J189 -> 0.05 | K126: =Récap!K189 -> 0 | L126: =Récap!L189 -> 0 | ... R126: =Récap!R189 -> 0.02 | S126: =SUM(E126:R126) -> 1
B127: Construction | C127: 2050 | E127: =Récap!E191 -> 0 | F127: =Récap!F191 -> 0 | G127: =Récap!G191 -> 0 | H127: =Récap!H191 -> 0.11 | I127: =Récap!I191 -> 0.037426519 | J127: =Récap!J191 -> 0.18657348 | K127: =Récap!K191 -> 0 | L127: =Récap!L191 -> 0 | ... R127: =Récap!R191 -> 0.07 | S127: =SUM(E127:R127) -> 1
B129: Autres | E129: Charbon | F129: Coke | G129: Produits pétroliers raffinés | H129: Gaz naturel | I129: Biomasse solide | J129: Déchets | K129: Biocarburants | L129: Gaz renouvelable | M129: Chaleur de l'environnement | N129: Solaire thermique et géothermie | O129: Électricité | P129: Electricité PAC | Q129: Chaleur vendue | R129: Hydrogène
B130: Dont papier-pâtes | C130: 2021 | D130: % | E130: =Récap!E194 -> 0 | F130: =Récap!F194 -> 0 | G130: =Récap!G194 -> 0.019754512 | H130: =Récap!H194 -> 0.32243632 | I130: =Récap!I194 -> 0.25696781 | J130: =Récap!J194 -> 0 | K130: =Récap!K194 -> 0 | L130: =Récap!L194 -> 0 | ... R130: =Récap!R194 -> 0 | S130: =SUM(E130:R130) -> 1
B131: Dont papier-pâtes | C131: 2030 | D131: % | E131: =Récap!E195 -> 0 | F131: =Récap!F195 -> 0 | G131: =Récap!G195 -> 0 | H131: =Récap!H195 -> 0.12591294 | I131: =Récap!I195 -> 0.42 | J131: =Récap!J195 -> 0.03 | K131: =Récap!K195 -> 0 | L131: =Récap!L195 -> 0 | ... R131: =Récap!R195 -> 0 | S131: =SUM(E131:R131) -> 1
...

Sheet Estimations consommations énerg
B1: Estimation des consommations énergétiques en 2030 à partir des hypothèses (des petites différences peuvent exister avec la modélisation EnerMED) | H1: Hypothèses | Z1: Mix run 2 (ancien mix)
E2: Attention, la variation de production est calculée par rapport à 2019 et pas 2021
B3: Sidérurgie HF | C3: 2021 | D3: 2030 | E3: 2050 | F3: Hausse | I3: Matrice de passage | J3: Charbon | K3: Coke | L3: Produits pétroliers raffinés | M3: Gaz de réseau | N3: Biomasse solide | O3: Déchets | P3: Biocarburants | Q3: Gaz renouvelable | R3: Chaleur de l'environnement | S3: Solaire thermique et géothermie | T3: Électricité | U3: Electricité PAC | V3: Chaleur vendue | W3: Hydrogène (consommation finale)
B4: Electricité | C4: 0 | D4: {=MMULT(J4:W16,TRANSPOSE('A renseigner'!E59:R59))*C17*'A renseigner'!E154*'A renseigner'!G7/'A renseigner'!C7} -> 0 | E4: {=MMULT(J4:W16,TRANSPOSE('A renseigner'!E60:R60))*C17*'A renseigner'!G154*'A renseigner'!K7/'A renseigner'!C7} -> 0 | F4: =D4-C4 -> 0 | I4: Electricité | J4: 0 | K4: 0 | L4: 0 | M4: 0 | N4: 0 | O4: 0 | P4: 0 | Q4: 0 | R4: 0 | S4: 0 | T4: 1 | U4: 0 | V4: 0 | W4: 0 | AA4: Mix énergétique | AD4: Charbon | AE4: Coke | AF4: Produits pétroliers raffinés | AG4: Gaz de réseau | AH4: Biomasse solide | AI4: Déchets | AJ4: Biocarburants | AK4: Gaz renouvelable | AL4: Chaleur de l'environnement | AM4: Solaire thermique et géothermie | AN4: Électricité | AO4: Electricité PAC | AP4: Chaleur vendue | AQ4: Hydrogène (consommation finale) | AR4: Total
B5: Electricité PAC | C5: 0 | D5: 0 | E5: 0 | F5: =D5-C5 -> 0 | I5: Electricité PAC | J5: 0 | K5: 0 | L5: 0 | M5: 0 | N5: 0 | O5: 0 | P5: 0 | Q5: 0 | R5: 0 | S5: 0 | T5: 0 | U5: 1 | V5: 0 | W5: 0 | AA5: Métaux primaires
B6: Produits liquides (fossile, bio, et synthétique) | C6: 0 | D6: 0 | E6: 0 | F6: =D6-C6 -> 0 | I6: Produits liquides (fossile, bio, et synthétique) | J6: 0 | K6: 0 | L6: 1 | M6: 0 | N6: 0 | O6: 0 | P6: 0 | Q6: 0 | R6: 0 | S6: 0 | T6: 0 | U6: 0 | V6: 0 | W6: 0 | AA6: Dont sidérurgie (hauts fourneaux) | AB6: 2021 | AC6: % | AD6: 0.59926162 | AE6: 0.40073838 | AF6: 0 | AG6: 0 | AH6: 0 | AI6: 0 | AJ6: 0 | AK6: 0 | AL6: 0 | AM6: 0 | AN6: 0 | AO6: 0 | AP6: 0 | AQ6: 0 | AR6: 1 | AT6: 0.59926162 | AU6: 0.40073838 | AV6: 0 | AW6: 0 | AX6: 0 | AY6: 0 | AZ6: 0 | BA6: 0 | BB6: 0 | BC6: 0 | BD6: 0 | BE6: 0 | BF6: 0 | BG6: 0 | BI6: =AT6=AD6 -> TRUE | BJ6: =AU6=AE6 -> TRUE | BK6: =AV6=AF6 -> TRUE | BL6: =AW6=AG6 -> TRUE | BM6: =AX6=AH6 -> TRUE | BN6: =AY6=AI6 -> TRUE | BO6: =AZ6=AJ6 -> TRUE | BP6: =BA6=AK6 -> TRUE | ... BV6: =BG6=AQ6 -> TRUE
B7: Gaz de réseau | C7: 0 | D7: 0 | E7: 0 | F7: =D7-C7 -> 0 | I7: Gaz de réseau | J7: 0 | K7: 0 | L7: 0 | M7: =1-M16 -> 0.85 | N7: 0 | O7: 0 | P7: 0 | Q7: 0 | R7: 0 | S7: 0 | T7: 0 | U7: 0 | V7: 0 | W7: 0 | AA7: Dont sidérurgie (hauts fourneaux) | AB7: 2030 | AC7: % | AD7: 0.3782048 | AE7: 0.5617952 | AF7: 0 | AG7: 0 | AH7: 0.03 | AI7: 0.03 | AJ7: 0 | AK7: 0 | AL7: 0 | AM7: 0 | AN7: 0 | AO7: 0 | AP7: 0 | AQ7: 0 | AR7: 1 | AT7: 0.4082048 | AU7: 0.5917952 | AV7: 0 | AW7: 0 | AX7: 0.015 | AY7: 0 | AZ7: 0 | BA7: 0 | BB7: 0 | BC7: 0 | BD7: 0 | BE7: 0 | BF7: 0 | BG7: 0 | BI7: =AT7=AD7 -> FALSE | BJ7: =AU7=AE7 -> FALSE | BK7: =AV7=AF7 -> TRUE | BL7: =AW7=AG7 -> TRUE | BM7: =AX7=AH7 -> FALSE | BN7: =AY7=AI7 -> FALSE | BO7: =AZ7=AJ7 -> TRUE | BP7: =BA7=AK7 -> TRUE | ... BV7: =BG7=AQ7 -> TRUE
B8: Hydrogène | D8: 0 | E8: 0 | F8: =D8-C8 -> 0 | I8: Hydrogène | J8: 0 | K8: 0 | L8: 0 | M8: 0 | N8: 0 | O8: 0 | P8: 0 | Q8: 0 | R8: 0 | S8: 0 | T8: 0 | U8: 0 | V8: 0 | W8: 1 | AA8: Dont sidérurgie (hauts fourneaux) | AB8: 2050 | AC8: % | AD8: 0.33394679 | AE8: 0.49605321 | AF8: 0 | AG8: 0 | AH8: 0.05 | AI8: 0.12 | AJ8: 0 | AK8: 0 | AL8: 0 | AM8: 0 | AN8: 0 | AO8: 0 | AP8: 0 | AQ8: 0 | AR8: 1 | AT8: 0.33394679 | AU8: 0.49605321 | AV8: 0 | AW8: 0 | AX8: 0.05 | AY8: 0.12 | AZ8: 0 | BA8: 0 | BB8: 0 | BC8: 0 | BD8: 0 | BE8: 0 | BF8: 0 | BG8: 0 | BI8: =AT8=AD8 -> TRUE | BJ8: =AU8=AE8 -> TRUE | BK8: =AV8=AF8 -> TRUE | BL8: =AW8=AG8 -> TRUE | BM8: =AX8=AH8 -> TRUE | BN8: =AY8=AI8 -> TRUE | BO8: =AZ8=AJ8 -> TRUE | BP8: =BA8=AK8 -> TRUE | ... BV8: =BG8=AQ8 -> TRUE
B9: Biomasse | C9: 0 | D9: 602.96596 | E9: 0 | F9: =D9-C9 -> 602.96596 | I9: Biomasse | J9: 0 | K9: 0 | L9: 0 | M9: 0 | N9: 1 | O9: 0 | P9: 0 | Q9: 0 | R9: 0 | S9: 0 | T9: 0 | U9: 0 | V9: 0 | W9: 0 | AR9: 0 | BI9: =AT9=AD9 -> TRUE | BJ9: =AU9=AE9 -> TRUE | BK9: =AV9=AF9 -> TRUE | BL9: =AW9=AG9 -> TRUE | BM9: =AX9=AH9 -> TRUE | BN9: =AY9=AI9 -> TRUE | BO9: =AZ9=AJ9 -> TRUE | BP9: =BA9=AK9 -> TRUE | ... BV9: =BG9=AQ9 -> TRUE
B10: Dechets | C10: 0 | D10: 1205.9319 | E10: 0 | F10: =D10-C10 -> 1205.9319 | I10: Dechets | J10: 0 | K10: 0 | L10: 0 | M10: 0 | N10: 0 | O10: 1 | P10: 0 | Q10: 0 | R10: 0 | S10: 0 | T10: 0 | U10: 0 | V10: 0 | W10: 0 | AA10: Dont sidérurgie (arc électrique) | AB10: 2021 | AC10: % | AD10: 0.035 | AE10: 0 | AF10: 0.02 | AG10: 0.22 | AH10: 0 | AI10: 0 | AJ10: 0 | AK10: 0 | AL10: 0 | AM10: 0 | AN10: 0.725 | AO10: 0 | AP10: 0 | AQ10: 0 | AR10: 1 | AT10: 0.035 | AU10: 0 | AV10: 0.02 | AW10: 0.22 | AX10: 0 | AY10: 0 | AZ10: 0 | BA10: 0 | BB10: 0 | BC10: 0 | BD10: 0.725 | BE10: 0 | BF10: 0 | BG10: 0 | BI10: =AT10=AD10 -> TRUE | BJ10: =AU10=AE10 -> TRUE | BK10: =AV10=AF10 -> TRUE | BL10: =AW10=AG10 -> TRUE | BM10: =AX10=AH10 -> TRUE | BN10: =AY10=AI10 -> TRUE | BO10: =AZ10=AJ10 -> TRUE | BP10: =BA10=AK10 -> TRUE | ... BV10: =BG10=AQ10 -> TRUE
B11: Charbon | C11: 17351.18 | D11: 7346.1352 | E11: 0 | F11: =D11-C11 -> -10005.044 | I11: Charbon | J11: 1 | K11: 0 | L11: 0 | M11: 0 | N11: 0 | O11: 0 | P11: 0 | Q11: 0 | R11: 0 | S11: 0 | T11: 0 | U11: 0 | V11: 0 | W11: 0 | AA11: Dont sidérurgie (arc électrique) | AB11: 2030 | AC11: % | AD11: 0.02 | AE11: 0 | AF11: 0.02 | AG11: 0.2 | AH11: 0.01 | AI11: 0 | AJ11: 0 | AK11: 0 | AL11: 0 | AM11: 0 | AN11: 0.75 | AO11: 0 | AP11: 0 | AQ11: 0 | AR11: 1 | AT11: 0.02 | AU11: 0 | AV11: 0.02 | AW11: 0.2 | AX11: 0.01 | AY11: 0 | AZ11: 0 | BA11: 0 | BB11: 0 | BC11: 0 | BD11: 0.75 | BE11: 0 | BF11: 0 | BG11: 0 | BI11: =AT11=AD11 -> TRUE | BJ11: =AU11=AE11 -> TRUE | BK11: =AV11=AF11 -> TRUE | BL11: =AW11=AG11 -> TRUE | BM11: =AX11=AH11 -> TRUE | BN11: =AY11=AI11 -> TRUE | BO11: =AZ11=AJ11 -> TRUE | BP11: =BA11=AK11 -> TRUE | ... BV11: =BG11=AQ11 -> TRUE
B12: Coke | C12: 25773.893 | D12: 10943.832 | E12: 0 | F12: =D12-C12 -> -14830.06 | I12: Coke | J12: 0 | K12: 1 | L12: 0 | M12: 0 | N12: 0 | O12: 0 | P12: 0 | Q12: 0 | R12: 0 | S12: 0 | T12: 0 | U12: 0 | V12: 0 | W12: 0 | AA12: Dont sidérurgie (arc électrique) | AB12: 2050 | AC12: % | AD12: 0.010514068 | AE12: 0 | AF12: 0.016095174 | AG12: 0.1441397 | AH12: 0.0219856 | AI12: 0 | AJ12: 0 | AK12: 0 | AL12: 0 | AM12: 0 | AN12: 0.80726546 | AO12: 0 | AP12: 0 | AQ12: 0 | AR12: 1 | AT12: 0.010514068 | AU12: 0 | AV12: 0.016095174 | AW12: 0.1441397 | AX12: 0.0219856 | AY12: 0 | AZ12: 0 | BA12: 0 | BB12: 0 | BC12: 0 | BD12: 0.80726546 | BE12: 0 | BF12: 0 | BG12: 0 | BI12: =AT12=AD12 -> TRUE | BJ12: =AU12=AE12 -> TRUE | BK12: =AV12=AF12 -> TRUE | BL12: =AW12=AG12 -> TRUE | BM12: =AX12=AH12 -> TRUE | BN12: =AY12=AI12 -> TRUE | BO12: =AZ12=AJ12 -> TRUE | BP12: =BA12=AK12 -> TRUE | ... BV12: =BG12=AQ12 -> TRUE
B13: Chaleur | C13: 0 | D13: 0 | E13: 0 | F13: =D13-C13 -> 0 | I13: Chaleur | J13: 0 | K13: 0 | L13: 0 | M13: 0 | N13: 0 | O13: 0 | P13: 0 | Q13: 0 | R13: 0 | S13: 0 | T13: 0 | U13: 0 | V13: 1 | W13: 0 | AR13: 0 | BI13: =AT13=AD13 -> TRUE | BJ13: =AU13=AE13 -> TRUE | BK13: =AV13=AF13 -> TRUE | BL13: =AW13=AG13 -> TRUE | BM13: =AX13=AH13 -> TRUE | BN13: =AY13=AI13 -> TRUE | BO13: =AZ13=AJ13 -> TRUE | BP13: =BA13=AK13 -> TRUE | ... BV13: =BG13=AQ13 -> TRUE
B14: Solar & Geothermie | C14: 0 | D14: 0 | E14: 0 | F14: =D14-C14 -> 0 | I14: Solar & Geothermie | J14: 0 | K14: 0 | L14: 0 | M14: 0 | N14: 0 | O14: 0 | P14: 0 | Q14: 0 | R14: 0 | S14: 1 | T14: 0 | U14: 0 | V14: 0 | W14: 0 | AA14: Dont sidérurgie (réduction directe) | AB14: 2021 | AC14: % | AD14: 0 | AE14: 0 | AF14: 0 | AG14: 0.84803256 | AH14: 0 | AI14: 0 | AJ14: 0 | AK14: 0 | AL14: 0 | AM14: 0 | AN14: 0.15196744 | AO14: 0 | AP14: 0 | AQ14: 0 | AR14: 1 | AT14: 0 | AU14: 0 | AV14: 0 | AW14: 0.84803256 | AX14: 0 | AY14: 0 | AZ14: 0 | BA14: 0 | BB14: 0 | BC14: 0 | BD14: 0.15196744 | BE14: 0 | BF14: 0 | BG14: 0 | BI14: =AT14=AD14 -> TRUE | BJ14: =AU14=AE14 -> TRUE | BK14: =AV14=AF14 -> TRUE | BL14: =AW14=AG14 -> TRUE | BM14: =AX14=AH14 -> TRUE | BN14: =AY14=AI14 -> TRUE | BO14: =AZ14=AJ14 -> TRUE | BP14: =BA14=AK14 -> TRUE | ... BV14: =BG14=AQ14 -> TRUE
B15: Chaleur Env | C15: 0 | D15: 0 | E15: 0 | F15: =D15-C15 -> 0 | I15: Chaleur Env | J15: 0 | K15: 0 | L15: 0 | M15: 0 | N15: 0 | O15: 0 | P15: 0 | Q15: 0 | R15: 1 | S15: 0 | T15: 0 | U15: 0 | V15: 0 | W15: 0 | AA15: Dont sidérurgie (réduction directe) | AB15: 2030 | AC15: % | AD15: 0 | AE15: 0 | AF15: 0 | AG15: 0.54803256 | AH15: 0 | AI15: 0 | AJ15: 0 | AK15: 0 | AL15: 0 | AM15: 0 | AN15: 0.15196744 | AO15: 0 | AP15: 0 | AQ15: 0.3 | AR15: 1 | AT15: 0 | AU15: 0 | AV15: 0 | AW15: 0.54803256 | AX15: 0 | AY15: 0 | AZ15: 0 | BA15: 0 | BB15: 0 | BC15: 0 | BD15: 0.15196744 | BE15: 0 | BF15: 0 | BG15: 0.3 | BI15: =AT15=AD15 -> TRUE | BJ15: =AU15=AE15 -> TRUE | BK15: =AV15=AF15 -> TRUE | BL15: =AW15=AG15 -> TRUE | BM15: =AX15=AH15 -> TRUE | BN15: =AY15=AI15 -> TRUE | BO15: =AZ15=AJ15 -> TRUE | BP15: =BA15=AK15 -> TRUE | ... BV15: =BG15=AQ15 -> TRUE
B16: Biogaz autoconsommé | C16: 0 | D16: 0 | E16: 0 | F16: =D16-C16 -> 0 | I16: Biogaz autoconsommé | J16: 0 | K16: 0 | L16: 0 | M16: =M22 -> 0.15 | N16: 0 | O16: 0 | P16: 0 | Q16: 1 | R16: 0 | S16: 0 | T16: 0 | U16: 0 | V16: 0 | W16: 0 | AA16: Dont sidérurgie (réduction directe) | AB16: 2050 | AC16: % | AD16: 0 | AE16: 0 | AF16: 0 | AG16: 0.15207756 | AH16: 0 | AI16: 0 | AJ16: 0 | AK16: 0 | AL16: 0 | AM16: 0 | AN16: 0.13767313 | AO16: 0 | AP16: 0 | AQ16: 0.71024931 | AR16: 1 | AT16: 0 | AU16: 0 | AV16: 0 | AW16: 0.15207756 | AX16: 0 | AY16: 0 | AZ16: 0 | BA16: 0 | BB16: 0 | BC16: 0 | BD16: 0.13767313 | BE16: 0 | BF16: 0 | BG16: 0.71024931 | BI16: =AT16=AD16 -> TRUE | BJ16: =AU16=AE16 -> TRUE | BK16: =AV16=AF16 -> TRUE | BL16: =AW16=AG16 -> TRUE | BM16: =AX16=AH16 -> TRUE | BN16: =AY16=AI16 -> TRUE | BO16: =AZ16=AJ16 -> TRUE | BP16: =BA16=AK16 -> TRUE | ... BV16: =BG16=AQ16 -> TRUE
B17: Total | C17: 43125.07 | D17: =SUM(D4:D16) -> 20098.865 | E17: =SUM(E4:E16) -> 0 | F17: =D17-C17 -> -23026.205 | AR17: 0 | BI17: =AT17=AD17 -> TRUE | BJ17: =AU17=AE17 -> TRUE | BK17: =AV17=AF17 -> TRUE | BL17: =AW17=AG17 -> TRUE | BM17: =AX17=AH17 -> TRUE | BN17: =AY17=AI17 -> TRUE | BO17: =AZ17=AJ17 -> TRUE | BP17: =BA17=AK17 -> TRUE | ... BV17: =BG17=AQ17 -> TRUE
AA18: Dont sidérurgie (mise en forme de l'acier) | AB18: 2021 | AD18: 0.051378863 | AE18: 0.028814188 | AF18: 0.0084139056 | AG18: 0.43763064 | AH18: 0 | AI18: 0 | AJ18: 0 | AK18: 0 | AL18: 0 | AM18: 0 | AN18: 0.46695971 | AO18: 0 | AP18: 0.0068027007 | AQ18: 0 | AR18: 1 | AT18: 0.051378863 | AU18: 0.028814188 | AV18: 0.0084139056 | AW18: 0.43763064 | AX18: 0 | AY18: 0 | AZ18: 0 | BA18: 0 | BB18: 0 | BC18: 0 | BD18: 0.46695971 | BE18: 0 | BF18: 0.0068027007 | BG18: 0 | BI18: =AT18=AD18 -> TRUE | BJ18: =AU18=AE18 -> TRUE | BK18: =AV18=AF18 -> TRUE | BL18: =AW18=AG18 -> TRUE | BM18: =AX18=AH18 -> TRUE | BN18: =AY18=AI18 -> TRUE | BO18: =AZ18=AJ18 -> TRUE | BP18: =BA18=AK18 -> TRUE | ... BV18: =BG18=AQ18 -> TRUE
B19: Sidérurgie AC | C19: 2021 | D19: 2030 | E19: 2030 | F19: Hausse | AA19: Dont sidérurgie (mise en forme de l'acier) | AB19: 2030 | AD19: 0.04 | AE19: 0 | AF19: 0.01 | AG19: 0.31 | AH19: 0.03 | AI19: 0 | AJ19: 0 | AK19: 0 | AL19: 0 | AM19: 0 | AN19: 0.6 | AO19: 0 | AP19: 0.01 | AQ19: 0 | AR19: 1 | AT19: 0.04 | AU19: 0 | AV19: 0.01 | AW19: 0.31 | AX19: 0.03 | AY19: 0 | AZ19: 0 | BA19: 0 | BB19: 0 | BC19: 0 | BD19: 0.6 | BE19: 0 | BF19: 0.01 | BG19: 0 | BI19: =AT19=AD19 -> TRUE | BJ19: =AU19=AE19 -> TRUE | BK19: =AV19=AF19 -> TRUE | BL19: =AW19=AG19 -> TRUE | BM19: =AX19=AH19 -> TRUE | BN19: =AY19=AI19 -> TRUE | BO19: =AZ19=AJ19 -> TRUE | BP19: =BA19=AK19 -> TRUE | ... BV19: =BG19=AQ19 -> TRUE
B20: Electricité | C20: 1416.4016 | D20: {=MMULT(J4:W16,TRANSPOSE('A renseigner'!E63:R63))*C33*'A renseigner'!E155*'A renseigner'!G8/'A renseigner'!C8} -> 2127.0042 | E20: {=MMULT(J4:W16,TRANSPOSE('A renseigner'!E64:R64))*C33*'A renseigner'!G155*'A renseigner'!K8/'A renseigner'!C8} -> 2969.2278 | F20: =D20-C20 -> 710.60257 | G20: =E20-C20 -> 1552.8262 | I20: Taux d'incorporation de biogaz | AA20: Dont sidérurgie (mise en forme de l'acier) | AB20: 2050 | AD20: 0.03 | AE20: 0 | AF20: 0.01 | AG20: 0.2 | AH20: 0.05 | AI20: 0 | AJ20: 0 | AK20: 0 | AL20: 0 | AM20: 0 | AN20: 0.7 | AO20: 0 | AP20: 0.01 | AQ20: 0 | AR20: 1 | AT20: 0.03 | AU20: 0 | AV20: 0.01 | AW20: 0.2 | AX20: 0.05 | AY20: 0 | AZ20: 0 | BA20: 0 | BB20: 0 | BC20: 0 | BD20: 0.7 | BE20: 0 | BF20: 0.01 | BG20: 0 | BI20: =AT20=AD20 -> TRUE | BJ20: =AU20=AE20 -> TRUE | BK20: =AV20=AF20 -> TRUE | BL20: =AW20=AG20 -> TRUE | BM20: =AX20=AH20 -> TRUE | BN20: =AY20=AI20 -> TRUE | BO20: =AZ20=AJ20 -> TRUE | BP20: =BA20=AK20 -> TRUE | ... BV20: =BG20=AQ20 -> TRUE
B21: Electricité PAC | C21: 0 | D21: 0 | E21: 0 | F21: =D21-C21 -> 0 | G21: =E21-C21 -> 0 | J21: 2019 | K21: 2020 | L21: 2025 | M21: 2030 | N21: 2035 | O21: 2040 | P21: 2045 | Q21: 2050 | AR21: 0 | BI21: =AT21=AD21 -> TRUE | BJ21: =AU21=AE21 -> TRUE | BK21: =AV21=AF21 -> TRUE | BL21: =AW21=AG21 -> TRUE | BM21: =AX21=AH21 -> TRUE | BN21: =AY21=AI21 -> TRUE | BO21: =AZ21=AJ21 -> TRUE | BP21: =BA21=AK21 -> TRUE | ... BV21: =BG21=AQ21 -> TRUE
B22: Produits liquides (fossile, bio, et synthétique) | C22: 39.073151 | D22: 56.720111 | E22: 0 | F22: =D22-C22 -> 17.646961 | G22: =E22-C22 -> -39.073151 | I22: % gaz non-fossile réseau (conso finale) | J22: 0 | K22: 0.001 | L22: 0.05 | M22: 0.15 | N22: 0.27 | O22: 0.45 | P22: 0.61 | Q22: 1 | AA22: Dont aluminium (primaire) | AB22: 2021 | AC22: % | AD22: 0 | AE22: 0 | AF22: 0.02811245 | AG22: 0.25100402 | AH22: 0 | AI22: 0 | AJ22: 0 | AK22: 0 | AL22: 0 | AM22: 0 | AN22: 0.71285141 | AO22: 0 | AP22: 0.0080321285 | AQ22: 0 | AR22: 1 | AT22: 0 | AU22: 0 | AV22: 0.02811245 | AW22: 0.25100402 | AX22: 0 | AY22: 0 | AZ22: 0 | BA22: 0 | BB22: 0 | BC22: 0 | BD22: 0.71285141 | BE22: 0 | BF22: 0.0080321285 | BG22: 0 | BI22: =AT22=AD22 -> TRUE | BJ22: =AU22=AE22 -> TRUE | BK22: =AV22=AF22 -> TRUE | BL22: =AW22=AG22 -> TRUE | BM22: =AX22=AH22 -> TRUE | BN22: =AY22=AI22 -> TRUE | BO22: =AZ22=AJ22 -> TRUE | BP22: =BA22=AK22 -> TRUE | ... BV22: =BG22=AQ22 -> TRUE
B23: Gaz de réseau | C23: 429.80463 | D23: 482.12095 | E23: 450.63993 | F23: =D23-C23 -> 52.316321 | G23: =E23-C23 -> 20.835302 | I23: dont méthane de synthèse | J23: 0 | K23: 0 | L23: 0 | M23: 0 | N23: 0 | O23: 0 | P23: 0.01 | Q23: 0.05 | AA23: Dont aluminium (primaire) | AB23: 2030 | AC23: % | AD23: 0 | AE23: 0 | AF23: 0 | AG23: 0.15 | AH23: 0 | AI23: 0 | AJ23: 0 | AK23: 0 | AL23: 0 | AM23: 0 | AN23: 0.85 | AO23: 0 | AP23: 0 | AQ23: 0 | AR23: 1 | AT23: 0 | AU23: 0 | AV23: 0 | AW23: 0.15 | AX23: 0 | AY23: 0 | AZ23: 0 | BA23: 0 | BB23: 0 | BC23: 0 | BD23: 0.85 | BE23: 0 | BF23: 0 | BG23: 0 | BI23: =AT23=AD23 -> TRUE | BJ23: =AU23=AE23 -> TRUE | BK23: =AV23=AF23 -> TRUE | BL23: =AW23=AG23 -> TRUE | BM23: =AX23=AH23 -> TRUE | BN23: =AY23=AI23 -> TRUE | BO23: =AZ23=AJ23 -> TRUE | BP23: =BA23=AK23 -> TRUE | ... BV23: =BG23=AQ23 -> TRUE
B24: Hydrogène | D24: 0 | E24: 0 | F24: =D24-C24 -> 0 | G24: =E24-C24 -> 0 | I24: dont biogaz | J24: 0 | K24: 0.001 | L24: 0.05 | M24: 0.15 | N24: 0.27 | O24: 0.45 | P24: 0.6 | Q24: 0.95 | AA24: Dont aluminium (primaire) | AB24: 2050 | AC24: % | AD24: 0 | AE24: 0 | AF24: 0 | AG24: 0.11 | AH24: 0 | AI24: 0 | AJ24: 0 | AK24: 0 | AL24: 0 | AM24: 0 | AN24: 0.87 | AO24: 0 | AP24: 0 | AQ24: 0.02 | AR24: 1 | AT24: 0 | AU24: 0 | AV24: 0 | AW24: 0.11 | AX24: 0 | AY24: 0 | AZ24: 0 | BA24: 0 | BB24: 0 | BC24: 0 | BD24: 0.87 | BE24: 0 | BF24: 0 | BG24: 0.02 | BI24: =AT24=AD24 -> TRUE | BJ24: =AU24=AE24 -> TRUE | BK24: =AV24=AF24 -> TRUE | BL24: =AW24=AG24 -> TRUE | BM24: =AX24=AH24 -> TRUE | BN24: =AY24=AI24 -> TRUE | BO24: =AZ24=AJ24 -> TRUE | BP24: =BA24=AK24 -> TRUE | ... BV24: =BG24=AQ24 -> TRUE
B25: Biomasse | C25: 0 | D25: 28.360056 | E25: 36.781306 | F25: =D25-C25 -> 28.360056 | G25: =E25-C25 -> 36.781306 | I25: % gaz non-fossile pour prod chaleur | J25: 0.1205 | K25: 0.1258 | L25: 0.15 | M25: 0.2 | N25: 0.25 | O25: 0.45 | P25: 0.7 | Q25: 1 | AR25: 0 | BI25: =AT25=AD25 -> TRUE | BJ25: =AU25=AE25 -> TRUE | BK25: =AV25=AF25 -> TRUE | BL25: =AW25=AG25 -> TRUE | BM25: =AX25=AH25 -> TRUE | BN25: =AY25=AI25 -> TRUE | BO25: =AZ25=AJ25 -> TRUE | BP25: =BA25=AK25 -> TRUE | ... BV25: =BG25=AQ25 -> TRUE
B26: Dechets | C26: 0 | D26: 0 | E26: 103.28475 | F26: =D26-C26 -> 0 | G26: =E26-C26 -> 103.28475 | I26: dont méthane de synthèse | J26: 0 | K26: 0 | L26: 0 | M26: 0 | N26: 0 | O26: 0 | P26: 0 | Q26: 0 | AA26: Dont aluminium (recyclé) | AB26: 2021 | AC26: % | AD26: 0 | AE26: 0 | AF26: 0.02461934 | AG26: 0.63990508 | AH26: 0 | AI26: 0 | AJ26: 0 | AK26: 0 | AL26: 0 | AM26: 0 | AN26: 0.33547558 | AO26: 0 | AP26: 0 | AQ26: 0 | AR26: 1 | AT26: 0 | AU26: 0 | AV26: 0.02461934 | AW26: 0.63990508 | AX26: 0 | AY26: 0 | AZ26: 0 | BA26: 0 | BB26: 0 | BC26: 0 | BD26: 0.33547558 | BE26: 0 | BF26: 0 | BG26: 0 | BI26: =AT26=AD26 -> TRUE | BJ26: =AU26=AE26 -> TRUE | BK26: =AV26=AF26 -> TRUE | BL26: =AW26=AG26 -> TRUE | BM26: =AX26=AH26 -> TRUE | BN26: =AY26=AI26 -> TRUE | BO26: =AZ26=AJ26 -> TRUE | BP26: =BA26=AK26 -> TRUE | ... BV26: =BG26=AQ26 -> TRUE
B27: Charbon | C27: 68.378014 | D27: 56.720111 | E27: 38.672114 | F27: =D27-C27 -> -11.657902 | G27: =E27-C27 -> -29.705899 | I27: dont biogaz | J27: 0.1205 | K27: 0.1258 | L27: 0.15 | M27: 0.2 | N27: 0.25 | O27: 0.45 | P27: 0.7 | Q27: 1 | AA27: Dont aluminium (recyclé) | AB27: 2030 | AC27: % | AD27: 0 | AE27: 0 | AF27: 0 | AG27: 0.55 | AH27: 0 | AI27: 0 | AJ27: 0 | AK27: 0 | AL27: 0 | AM27: 0 | AN27: 0.45 | AO27: 0 | AP27: 0 | AQ27: 0 | AR27: 1 | AT27: 0 | AU27: 0 | AV27: 0 | AW27: 0.55 | AX27: 0 | AY27: 0 | AZ27: 0 | BA27: 0 | BB27: 0 | BC27: 0 | BD27: 0.45 | BE27: 0 | BF27: 0 | BG27: 0 | BI27: =AT27=AD27 -> TRUE | BJ27: =AU27=AE27 -> TRUE | BK27: =AV27=AF27 -> TRUE | BL27: =AW27=AG27 -> TRUE | BM27: =AX27=AH27 -> TRUE | BN27: =AY27=AI27 -> TRUE | BO27: =AZ27=AJ27 -> TRUE | BP27: =BA27=AK27 -> TRUE | ... BV27: =BG27=AQ27 -> TRUE
B28: Coke | C28: 0 | D28: 0 | E28: 0 | F28: =D28-C28 -> 0 | G28: =E28-C28 -> 0 | I28: % gaz non-fossile prod élec | J28: 0.0695 | K28: 0.0844 | L28: 0.13 | M28: 0.15 | N28: 0.2 | O28: 0.2 | P28: 0.2 | Q28: 0.2 | AA28: Dont aluminium (recyclé) | AB28: 2050 | AC28: % | AD28: 0 | AE28: 0 | AF28: 0 | AG28: 0.2 | AH28: 0 | AI28: 0 | AJ28: 0 | AK28: 0 | AL28: 0 | AM28: 0 | AN28: 0.8 | AO28: 0 | AP28: 0 | AQ28: 0 | AR28: 1 | AT28: 0 | AU28: 0 | AV28: 0 | AW28: 0.2 | AX28: 0 | AY28: 0 | AZ28: 0 | BA28: 0 | BB28: 0 | BC28: 0 | BD28: 0.8 | BE28: 0 | BF28: 0 | BG28: 0 | BI28: =AT28=AD28 -> TRUE | BJ28: =AU28=AE28 -> TRUE | BK28: =AV28=AF28 -> TRUE | BL28: =AW28=AG28 -> TRUE | BM28: =AX28=AH28 -> TRUE | BN28: =AY28=AI28 -> TRUE | BO28: =AZ28=AJ28 -> TRUE | BP28: =BA28=AK28 -> TRUE | ... BV28: =BG28=AQ28 -> TRUE
B29: Chaleur | C29: 0 | D29: 0 | E29: 0 | F29: =D29-C29 -> 0 | G29: =E29-C29 -> 0 | I29: dont méthane de synthèse | J29: 0 | K29: 0 | L29: 0 | M29: 0 | N29: 0 | O29: 0 | P29: 0 | Q29: 0 | AR29: 0 | BI29: =AT29=AD29 -> TRUE | BJ29: =AU29=AE29 -> TRUE | BK29: =AV29=AF29 -> TRUE | BL29: =AW29=AG29 -> TRUE | BM29: =AX29=AH29 -> TRUE | BN29: =AY29=AI29 -> TRUE | BO29: =AZ29=AJ29 -> TRUE | BP29: =BA29=AK29 -> TRUE | ... BV29: =BG29=AQ29 -> TRUE
B30: Solar & Geothermie | C30: 0 | D30: 0 | E30: 0 | F30: =D30-C30 -> 0 | G30: =E30-C30 -> 0 | I30: dont biogaz | J30: 0.0695 | K30: 0.0844 | L30: 0.13 | M30: 0.15 | N30: 0.2 | O30: 0.2 | P30: 0.2 | Q30: 0.2 | AA30: Dont autres métaux primaires | AB30: 2021 | AC30: % | AD30: 0 | AE30: 0 | AF30: 0 | AG30: 0.28501215 | AH30: 0.0025709966 | AI30: 0 | AJ30: 0 | AK30: 0 | AL30: 0 | AM30: 0 | AN30: 0.67273231 | AO30: 0 | AP30: 0.039684538 | AQ30: 0 | AR30: 1 | AT30: 0 | AU30: 0 | AV30: 0 | AW30: 0.28501215 | AX30: 0.0025709966 | AY30: 0 | AZ30: 0 | BA30: 0 | BB30: 0 | BC30: 0 | BD30: 0.67273231 | BE30: 0 | BF30: 0.039684538 | BG30: 0 | BI30: =AT30=AD30 -> TRUE | BJ30: =AU30=AE30 -> TRUE | BK30: =AV30=AF30 -> TRUE | BL30: =AW30=AG30 -> TRUE | BM30: =AX30=AH30 -> TRUE | BN30: =AY30=AI30 -> TRUE | BO30: =AZ30=AJ30 -> TRUE | BP30: =BA30=AK30 -> TRUE | ... BV30: =BG30=AQ30 -> TRUE
B31: Chaleur Env | C31: 0 | D31: 0 | E31: 0 | F31: =D31-C31 -> 0 | G31: =E31-C31 -> 0 | AA31: Dont autres métaux primaires | AB31: 2030 | AC31: % | AD31: 0 | AE31: 0 | AF31: 0 | AG31: 0.20888383 | AH31: 0.03 | AI31: 0 | AJ31: 0 | AK31: 0 | AL31: 0 | AM31: 0 | AN31: 0.70111617 | AO31: 0 | AP31: 0.03 | AQ31: 0.03 | AR31: 1 | AT31: 0 | AU31: 0 | AV31: 0 | AW31: 0.219 | AX31: 0.02 | AY31: 0 | AZ31: 0 | BA31: 0 | BB31: 0 | BC31: 0 | BD31: 0.70111617 | BE31: 0 | BF31: 0.03 | BG31: 0.03 | BI31: =AT31=AD31 -> TRUE | BJ31: =AU31=AE31 -> TRUE | BK31: =AV31=AF31 -> TRUE | BL31: =AW31=AG31 -> FALSE | BM31: =AX31=AH31 -> FALSE | BN31: =AY31=AI31 -> TRUE | BO31: =AZ31=AJ31 -> TRUE | BP31: =BA31=AK31 -> TRUE | ... BV31: =BG31=AQ31 -> TRUE
B32: Biogaz autoconsommé | C32: 0 | D32: 85.080167 | E32: 79.524693 | F32: =D32-C32 -> 85.080167 | G32: =E32-C32 -> 79.524693 | AA32: Dont autres métaux primaires | AB32: 2050 | AC32: % | AD32: 0 | AE32: 0 | AF32: 0 | AG32: 0.08 | AH32: 0.05 | AI32: 0 | AJ32: 0 | AK32: 0 | AL32: 0 | AM32: 0 | AN32: 0.79 | AO32: 0 | AP32: 0 | AQ32: 0.08 | AR32: 1 | AT32: 0 | AU32: 0 | AV32: 0 | AW32: 0.08 | AX32: 0.05 | AY32: 0 | AZ32: 0 | BA32: 0 | BB32: 0 | BC32: 0 | BD32: 0.79 | BE32: 0 | BF32: 0 | BG32: 0.08 | BI32: =AT32=AD32 -> TRUE | BJ32: =AU32=AE32 -> TRUE | BK32: =AV32=AF32 -> TRUE | BL32: =AW32=AG32 -> TRUE | BM32: =AX32=AH32 -> TRUE | BN32: =AY32=AI32 -> TRUE | BO32: =AZ32=AJ32 -> TRUE | BP32: =BA32=AK32 -> TRUE | ... BV32: =BG32=AQ32 -> TRUE
B33: Total | C33: 1953.6573 | D33: =SUM(D20:D32) -> 2836.0056 | E33: =SUM(E20:E32) -> 3678.1306 | F33: =D33-C33 -> 882.34822 | G33: =E33-C33 -> 1724.4732 | AR33: 0 | BI33: =AT33=AD33 -> TRUE | BJ33: =AU33=AE33 -> TRUE | BK33: =AV33=AF33 -> TRUE | BL33: =AW33=AG33 -> TRUE | BM33: =AX33=AH33 -> TRUE | BN33: =AY33=AI33 -> TRUE | BO33: =AZ33=AJ33 -> TRUE | BP33: =BA33=AK33 -> TRUE | ... BV33: =BG33=AQ33 -> TRUE
H34: Résultats | AA34: Chimie | AD34: Charbon | AE34: Coke | AF34: Produits pétroliers raffinés | AG34: Gaz naturel | AH34: Biomasse solide | AI34: Déchets | AJ34: Biocarburants | AK34: Gaz renouvelable | AL34: Chaleur de l'environnement | AM34: Solaire thermique et géothermie | AN34: Électricité | AO34: Electricité PAC | AP34: Chaleur vendue | AQ34: Hydrogène | AR34: 0 | AT34: Charbon | AU34: Coke | AV34: Produits pétroliers raffinés | AW34: Gaz naturel | AX34: Biomasse solide | AY34: Déchets | AZ34: Biocarburants | BA34: Gaz renouvelable | BB34: Chaleur de l'environnement | BC34: Solaire thermique et géothermie | BD34: Électricité | BE34: Electricité PAC | BF34: Chaleur vendue | BG34: Hydrogène | BI34: =AT34=AD34 -> TRUE | BJ34: =AU34=AE34 -> TRUE | BK34: =AV34=AF34 -> TRUE | BL34: =AW34=AG34 -> TRUE | BM34: =AX34=AH34 -> TRUE | BN34: =AY34=AI34 -> TRUE | BO34: =AZ34=AJ34 -> TRUE | BP34: =BA34=AK34 -> TRUE | ... BV34: =BG34=AQ34 -> TRUE
B35: Sidérurgie RD | C35: 2021 | D35: 2030 | E35: 2030 | F35: Hausse | AA35: Dont Ammoniac (vaporeformage) | AB35: 2021 | AC35: % | AD35: 0 | AE35: 0 | AF35: 0.005 | AG35: 0.93 | AH35: 0.005 | AI35: 0 | AJ35: 0 | AK35: 0 | AL35: 0 | AM35: 0 | AN35: 0.06 | AO35: 0 | AP35: 0 | AQ35: 0 | AR35: 1 | AT35: 0 | AU35: 0 | AV35: 0.005 | AW35: 0.93 | AX35: 0.005 | AY35: 0 | AZ35: 0 | BA35: 0 | BB35: 0 | BC35: 0 | BD35: 0.06 | BE35: 0 | BF35: 0 | BG35: 0 | BI35: =AT35=AD35 -> TRUE | BJ35: =AU35=AE35 -> TRUE | BK35: =AV35=AF35 -> TRUE | BL35: =AW35=AG35 -> TRUE | BM35: =AX35=AH35 -> TRUE | BN35: =AY35=AI35 -> TRUE | BO35: =AZ35=AJ35 -> TRUE | BP35: =BA35=AK35 -> TRUE | ... BV35: =BG35=AQ35 -> TRUE
B36: Electricité | C36: 0.56 | D36: {=MMULT($J$4:$W$16,TRANSPOSE('A renseigner'!$E67:$R67))*$C$49*'A renseigner'!E156*9825/4} -> 1306.725 | E36: {=MMULT($J$4:$W$16,TRANSPOSE('A renseigner'!$E68:$R68))*$C$49*'A renseigner'!G156*18616/4} -> 2124.9835 | F36: =D36-C36 -> 1306.165 | AA36: Dont Ammoniac (vaporeformage) | AB36: 2030 | AC36: % | AD36: 0 | AE36: 0 | AF36: 0.005 | AG36: 0.93 | AH36: 0.005 | AI36: 0 | AJ36: 0 | AK36: 0 | AL36: 0 | AM36: 0 | AN36: 0.06 | AO36: 0 | AP36: 0 | AQ36: 0 | AR36: 1 | AT36: 0 | AU36: 0 | AV36: 0.005 | AW36: 0.93 | AX36: 0.005 | AY36: 0 | AZ36: 0 | BA36: 0 | BB36: 0 | BC36: 0 | BD36: 0.06 | BE36: 0 | BF36: 0 | BG36: 0 | BI36: =AT36=AD36 -> TRUE | BJ36: =AU36=AE36 -> TRUE | BK36: =AV36=AF36 -> TRUE | BL36: =AW36=AG36 -> TRUE | BM36: =AX36=AH36 -> TRUE | BN36: =AY36=AI36 -> TRUE | BO36: =AZ36=AJ36 -> TRUE | BP36: =BA36=AK36 -> TRUE | ... BV36: =BG36=AQ36 -> TRUE
B37: Electricité PAC | C37: 0 | D37: 0 | E37: 0 | F37: =D37-C37 -> 0 | AA37: Dont Ammoniac (vaporeformage) | AB37: 2050 | AC37: % | AD37: 0 | AE37: 0 | AF37: 0.005 | AG37: 0.93 | AH37: 0.005 | AI37: 0 | AJ37: 0 | AK37: 0 | AL37: 0 | AM37: 0 | AN37: 0.06 | AO37: 0 | AP37: 0 | AQ37: 0 | AR37: 1 | AT37: 0 | AU37: 0 | AV37: 0.005 | AW37: 0.93 | AX37: 0.005 | AY37: 0 | AZ37: 0 | BA37: 0 | BB37: 0 | BC37: 0 | BD37: 0.06 | BE37: 0 | BF37: 0 | BG37: 0 | BI37: =AT37=AD37 -> TRUE | BJ37: =AU37=AE37 -> TRUE | BK37: =AV37=AF37 -> TRUE | BL37: =AW37=AG37 -> TRUE | BM37: =AX37=AH37 -> TRUE | BN37: =AY37=AI37 -> TRUE | BO37: =AZ37=AJ37 -> TRUE | BP37: =BA37=AK37 -> TRUE | ... BV37: =BG37=AQ37 -> TRUE
B38: Produits liquides (fossile, bio, et synthétique) | C38: 0 | D38: 0 | E38: 0 | F38: =D38-C38 -> 0 | J38: Où est incluse la consommation de biomasse pour les métaux primaires ? | AR38: 0 | BI38: =AT38=AD38 -> TRUE | BJ38: =AU38=AE38 -> TRUE | BK38: =AV38=AF38 -> TRUE | BL38: =AW38=AG38 -> TRUE | BM38: =AX38=AH38 -> TRUE | BN38: =AY38=AI38 -> TRUE | BO38: =AZ38=AJ38 -> TRUE | BP38: =BA38=AK38 -> TRUE | ... BV38: =BG38=AQ38 -> TRUE
B39: Gaz de réseau | C39: 3.125 | D39: 4005.5204 | E39: 1995.2184 | F39: =D39-C39 -> 4002.3954 | I39: Chiffres FdR DGE | J39: Chimie | K39: Papier-carton | L39: Ciment | M39: Agro-alimentaire | N39: Chaux | O39: Briques et tuiles | P39: Biens d'équipements, matériels de transport | Q39: Autres (détails ?) | R39: Total | AA39: Dont pétrochimie de base | AB39: 2021 | AC39: % | AD39: 0 | AE39: 0 | AF39: 0.022797872 | AG39: 0.64404567 | AH39: 0.014462768 | AI39: 0 | AJ39: 0 | AK39: 0 | AL39: 0 | AM39: 0 | AN39: 0.1746663 | AO39: 0 | AP39: 0.14402739 | AQ39: 0 | AR39: 1 | AT39: 0 | AU39: 0 | AV39: 0.022797872 | AW39: 0.64404567 | AX39: 0.014462768 | AY39: 0 | AZ39: 0 | BA39: 0 | BB39: 0 | BC39: 0 | BD39: 0.1746663 | BE39: 0 | BF39: 0.14402739 | BG39: 0 | BI39: =AT39=AD39 -> TRUE | BJ39: =AU39=AE39 -> TRUE | BK39: =AV39=AF39 -> TRUE | BL39: =AW39=AG39 -> TRUE | BM39: =AX39=AH39 -> TRUE | BN39: =AY39=AI39 -> TRUE | BO39: =AZ39=AJ39 -> TRUE | BP39: =BA39=AK39 -> TRUE | ... BV39: =BG39=AQ39 -> TRUE
B40: Hydrogène | D40: 2579.6151 | E40: 10962.691 | F40: =D40-C40 -> 2579.6151 | I40: Besoins supplémentaires en biomasse en 2030 (TWh) | J40: 7.3913043 | K40: 3.4782609 | L40: 1.7391304 | M40: 6.9565217 | N40: 1.5130435 | O40: 0.54956522 | P40: 1.3043478 | Q40: 1.3 | R40: 24.232174 | AA40: Dont pétrochimie de base | AB40: 2030 | AC40: % | AD40: 0 | AE40: 0 | AF40: 0.02 | AG40: 0.35 | AH40: 0.014 | AI40: 0 | AJ40: 0 | AK40: 0 | AL40: 0 | AM40: 0 | AN40: 0.476 | AO40: 0 | AP40: 0.14 | AQ40: 0 | AR40: 1 | AT40: 0 | AU40: 0 | AV40: 0.02 | AW40: 0.334 | AX40: 0.03 | AY40: 0 | AZ40: 0 | BA40: 0 | BB40: 0 | BC40: 0 | BD40: 0.476 | BE40: 0 | BF40: 0.14 | BG40: 0 | BI40: =AT40=AD40 -> TRUE | BJ40: =AU40=AE40 -> TRUE | BK40: =AV40=AF40 -> TRUE | BL40: =AW40=AG40 -> FALSE | BM40: =AX40=AH40 -> FALSE | BN40: =AY40=AI40 -> TRUE | BO40: =AZ40=AJ40 -> TRUE | BP40: =BA40=AK40 -> TRUE | ... BV40: =BG40=AQ40 -> TRUE
B41: Biomasse | C41: 0 | D41: 0 | E41: 0 | F41: =D41-C41 -> 0 | I41: Besoins supplémentaires en CSR en 2030 (TWh) | J41: 2.173913 | K41: 0.43478261 | L41: 3.0434783 | R41: 5.6521739 | AA41: Dont pétrochimie de base | AB41: 2050 | AC41: % | AD41: 0 | AE41: 0 | AF41: 0.017 | AG41: 0.1 | AH41: 0.015 | AI41: 0 | AJ41: 0 | AK41: 0 | AL41: 0 | AM41: 0 | AN41: 0.718 | AO41: 0 | AP41: 0.15 | AQ41: 0 | AR41: 1 | AT41: 0 | AU41: 0 | AV41: 0.017 | AW41: 0.085 | AX41: 0.03 | AY41: 0 | AZ41: 0 | BA41: 0 | BB41: 0 | BC41: 0 | BD41: 0.718 | BE41: 0 | BF41: 0.15 | BG41: 0 | BI41: =AT41=AD41 -> TRUE | BJ41: =AU41=AE41 -> TRUE | BK41: =AV41=AF41 -> TRUE | BL41: =AW41=AG41 -> FALSE | BM41: =AX41=AH41 -> FALSE | BN41: =AY41=AI41 -> TRUE | BO41: =AZ41=AJ41 -> TRUE | BP41: =BA41=AK41 -> TRUE | ... BV41: =BG41=AQ41 -> TRUE
B42: Dechets | C42: 0 | D42: 0 | E42: 0 | F42: =D42-C42 -> 0 | I42: Besoins supplémentaires totaux biomasse et CSR (TWh) | J42: 9.5652174 | K42: 3.9130435 | L42: 4.7826087 | M42: 6.9565217 | N42: 1.5130435 | O42: 0.54956522 | P42: 1.3043478 | Q42: 1.3 | R42: 29.884348 | S42: Attention, le biogaz n'est pas intégré | AR42: 0 | BI42: =AT42=AD42 -> TRUE | BJ42: =AU42=AE42 -> TRUE | BK42: =AV42=AF42 -> TRUE | BL42: =AW42=AG42 -> TRUE | BM42: =AX42=AH42 -> TRUE | BN42: =AY42=AI42 -> TRUE | BO42: =AZ42=AJ42 -> TRUE | BP42: =BA42=AK42 -> TRUE | ... BV42: =BG42=AQ42 -> TRUE
B43: Charbon | C43: 0 | D43: 0 | E43: 0 | F43: =D43-C43 -> 0 | I43: Besoins supplémentaires en biogaz (TWh) | J43: 1.5 | M43: 1 | O43: 0.4 | Q43: 2.1 | R43: =SUM(J43:Q43) -> 5 | AA43: Dont autres chimies | AB43: 2021 | AC43: % | AD43: 0.069144909 | AE43: 0 | AF43: 0.023722328 | AG43: 0.54601876 | AH43: 0.015836627 | AI43: 0 | AJ43: 0 | AK43: 0 | AL43: 0 | AM43: 0 | AN43: 0.2464913 | AO43: 0 | AP43: 0.098786078 | AQ43: 0 | AR43: 1 | AT43: 0.069144909 | AU43: 0 | AV43: 0.023722328 | AW43: 0.54601876 | AX43: 0.015836627 | AY43: 0 | AZ43: 0 | BA43: 0 | BB43: 0 | BC43: 0 | BD43: 0.2464913 | BE43: 0 | BF43: 0.098786078 | BG43: 0 | BI43: =AT43=AD43 -> TRUE | BJ43: =AU43=AE43 -> TRUE | BK43: =AV43=AF43 -> TRUE | BL43: =AW43=AG43 -> TRUE | BM43: =AX43=AH43 -> TRUE | BN43: =AY43=AI43 -> TRUE | BO43: =AZ43=AJ43 -> TRUE | BP43: =BA43=AK43 -> TRUE | ... BV43: =BG43=AQ43 -> TRUE
B44: Coke | C44: 0 | D44: 0 | E44: 0 | F44: =D44-C44 -> 0 | N44: Autres non métalliques | AA44: Dont autres chimies | AB44: 2030 | AC44: % | AD44: 0 | AE44: 0 | AF44: 0.06 | AG44: 0.35 | AH44: 0.04 | AI44: 0 | AJ44: 0 | AK44: 0 | AL44: 0.04 | AM44: 0 | AN44: 0.38553017 | AO44: 0.02 | AP44: 0.10446983 | AQ44: 0 | AR44: 1 | AT44: 0 | AU44: 0 | AV44: 0.06 | AW44: 0.175 | AX44: 0.17 | AY44: 0.045 | AZ44: 0 | BA44: 0 | BB44: 0.04 | BC44: 0 | BD44: 0.38553017 | BE44: 0.02 | BF44: 0.10446983 | BG44: 0 | BI44: =AT44=AD44 -> TRUE | BJ44: =AU44=AE44 -> TRUE | BK44: =AV44=AF44 -> TRUE | BL44: =AW44=AG44 -> FALSE | BM44: =AX44=AH44 -> FALSE | BN44: =AY44=AI44 -> FALSE | BO44: =AZ44=AJ44 -> TRUE | BP44: =BA44=AK44 -> TRUE | ... BV44: =BG44=AQ44 -> TRUE
B45: Chaleur | C45: 0 | D45: 0 | E45: 0 | F45: =D45-C45 -> 0 | I45: Chiffres run 2 avant changement de mix | J45: Chimie | K45: Papier-carton | L45: Ciment | M45: Agro-alimentaire | N45: Chaux | O45: Briques et tuiles | P45: Biens d'équipements, matériels de transport | Q45: Autres | R45: Total | AA45: Dont autres chimies | AB45: 2050 | AC45: % | AD45: 0 | AE45: 0 | AF45: 0 | AG45: 0.2 | AH45: 0.05 | AI45: 0 | AJ45: 0 | AK45: 0 | AL45: 0.1 | AM45: 0.01 | AN45: 0.52644583 | AO45: 0 | AP45: 0.11355417 | AQ45: 0 | AR45: 1 | AT45: 0 | AU45: 0 | AV45: 0 | AW45: 0.2 | AX45: 0.05 | AY45: 0 | AZ45: 0 | BA45: 0 | BB45: 0.1 | BC45: 0.01 | BD45: 0.52644583 | BE45: 0 | BF45: 0.11355417 | BG45: 0 | BI45: =AT45=AD45 -> TRUE | BJ45: =AU45=AE45 -> TRUE | BK45: =AV45=AF45 -> TRUE | BL45: =AW45=AG45 -> TRUE | BM45: =AX45=AH45 -> TRUE | BN45: =AY45=AI45 -> TRUE | BO45: =AZ45=AJ45 -> TRUE | BP45: =BA45=AK45 -> TRUE | ... BV45: =BG45=AQ45 -> TRUE
B46: Solar & Geothermie | C46: 0 | D46: 0 | E46: 0 | F46: =D46-C46 -> 0 | I46: Besoins supplémentaires en biomasse en 2030 (TWh) | J46: 0.62921585 | K46: 1.1096955 | L46: 0.42722553 | M46: 5.0817571 | N46: -2.6745189 | P46: -0.31207202 | Q46: 2.2137552 | R46: 6.4750583 | S46: Delta run 3 ajusté - run 2 biomasse solide | T46: =R55-R46 -> 13.702836 | AR46: 0 | BI46: =AT46=AD46 -> TRUE | BJ46: =AU46=AE46 -> TRUE | BK46: =AV46=AF46 -> TRUE | BL46: =AW46=AG46 -> TRUE | BM46: =AX46=AH46 -> TRUE | BN46: =AY46=AI46 -> TRUE | BO46: =AZ46=AJ46 -> TRUE | BP46: =BA46=AK46 -> TRUE | ... BV46: =BG46=AQ46 -> TRUE
B47: Chaleur Env | C47: 0 | D47: 0 | E47: 0 | F47: =D47-C47 -> 0 | I47: Besoins supplémentaires en CSR en 2030 (TWh) | J47: 0 | K47: 0.66968487 | L47: 2.0016032 | M47: 0 | N47: 0 | P47: 0 | Q47: 1.011285 | R47: 3.682573 | S47: Delta run 3 ajusté - run 2 CSR | T47: =R56-R47 -> 6.376469 | U47: 7,3TWh run 2 2030 --> 9TWh run 3 : pas loin de la filière (10TWh 2030 et 12,5TWh en 2050) | AA47: Non-métalliques | AD47: Charbon | AE47: Coke | AF47: Produits pétroliers raffinés | AG47: Gaz naturel | AH47: Biomasse solide | AI47: Déchets | AJ47: Biocarburants | AK47: Gaz renouvelable | AL47: Chaleur de l'environnement | AM47: Solaire thermique et géothermie | AN47: Électricité | AO47: Electricité PAC | AP47: Chaleur vendue | AQ47: Hydrogène | AR47: 0 | AT47: Charbon | AU47: Coke | AV47: Produits pétroliers raffinés | AW47: Gaz naturel | AX47: Biomasse solide | AY47: Déchets | AZ47: Biocarburants | BA47: Gaz renouvelable | BB47: Chaleur de l'environnement | BC47: Solaire thermique et géothermie | BD47: Électricité | BE47: Electricité PAC | BF47: Chaleur vendue | BG47: Hydrogène | BI47: =AT47=AD47 -> TRUE | BJ47: =AU47=AE47 -> TRUE | BK47: =AV47=AF47 -> TRUE | BL47: =AW47=AG47 -> TRUE | BM47: =AX47=AH47 -> TRUE | BN47: =AY47=AI47 -> TRUE | BO47: =AZ47=AJ47 -> TRUE | BP47: =BA47=AK47 -> TRUE | ... BV47: =BG47=AQ47 -> TRUE
B48: Biogaz autoconsommé | C48: 0 | D48: 706.85654 | E48: 352.09737 | F48: =D48-C48 -> 706.85654 | G48: sans prendre en compte le NE | I48: Besoins supplémentaires en biogaz en 2030 (TWh) | J48: 3.20348 | K48: 2.1466599 | L48: 0.017749107 | M48: 2.838233 | N48: 1.3099965 | P48: 1.2404737 | Q48: 3.7941906 | R48: 14.550783 | U48: 5,4TWh en 2050 par contre, rehausser ? Malgré quantité de déchets en baisse ? Tous effets pris en compte, on arrierait autour de 7TWh en 2050 pour l'instant | AA48: Dont ciment | AB48: 2021 | AC48: % | AD48: 0.14 | AE48: 0 | AF48: 0.385 | AG48: 0.02 | AH48: 0.17 | AI48: 0.255 | AJ48: 0 | AK48: 0 | AL48: 0 | AM48: 0 | AN48: 0.03 | AO48: 0 | AP48: 0 | AQ48: 0 | AR48: 1 | AT48: 0.147 | AU48: 0 | AV48: 0.323 | AW48: 0.02 | AX48: 0.12 | AY48: 0.26 | AZ48: 0 | BA48: 0 | BB48: 0 | BC48: 0 | BD48: 0.13 | BE48: 0 | BF48: 0 | BG48: 0 | BI48: =AT48=AD48 -> FALSE | BJ48: =AU48=AE48 -> TRUE | BK48: =AV48=AF48 -> FALSE | BL48: =AW48=AG48 -> TRUE | BM48: =AX48=AH48 -> FALSE | BN48: =AY48=AI48 -> FALSE | BO48: =AZ48=AJ48 -> TRUE | BP48: =BA48=AK48 -> TRUE | ... BV48: =BG48=AQ48 -> TRUE
B49: Total | C49: 3.6849999 | D49: =SUM(D37:D48) -> 7291.9921 | E49: =SUM(E37:E48) -> 13310.007 | F49: =D49-C49 -> 7288.3071 | I49: Besoins supplémentaires totaux biomasse et CSR (TWh) | J49: 3.8326959 | K49: 3.9260402 | L49: 2.4465778 | M49: 7.9199901 | N49: -1.3645224 | O49: 0 | P49: 0.92840167 | Q49: 7.0192308 | R49: 24.708414 | U49: augmenter CSR et baisser biomasse ciment autres chimies pour la HT, bien de mettre des CSR là où on capte (car émet du C) | AA49: Dont ciment | AB49: 2030 | AC49: % | AD49: 0.03 | AE49: 0 | AF49: 0.13 | AG49: 0.01 | AH49: 0.23 | AI49: 0.46 | AJ49: 0 | AK49: 0 | AL49: 0 | AM49: 0 | AN49: 0.13 | AO49: 0 | AP49: 0.01 | AQ49: 0 | AR49: 1 | AT49: 0.01 | AU49: 0 | AV49: 0.138 | AW49: 0.02 | AX49: 0.356 | AY49: 0.316 | AZ49: 0 | BA49: 0 | BB49: 0 | BC49: 0 | BD49: 0.16 | BE49: 0 | BF49: 0 | BG49: 0 | BI49: =AT49=AD49 -> FALSE | BJ49: =AU49=AE49 -> TRUE | BK49: =AV49=AF49 -> FALSE | BL49: =AW49=AG49 -> FALSE | BM49: =AX49=AH49 -> FALSE | BN49: =AY49=AI49 -> FALSE | BO49: =AZ49=AJ49 -> TRUE | BP49: =BA49=AK49 -> TRUE | ... BV49: =BG49=AQ49 -> TRUE
I50: Diff DGE | J50: =J49-J42 -> -5.7325215 | K50: =K49-K42 -> 0.012996771 | L50: =L49-L42 -> -2.3360309 | M50: =M49-M42 -> 0.96346833 | N50: =N49-N42 -> -2.8775658 | O50: =O49-O42 -> -0.54956522 | P50: =P49-P42 -> -0.37594615 | Q50: =Q49-Q42 -> 5.7192308 | R50: =R49-R42 -> -5.1759338 | U50: fumées assez impures lorsque beaucoup de CSR, pourrait favoriser la biomasse | AA50: Dont ciment | AB50: 2050 | AC50: % | AD50: 0 | AE50: 0 | AF50: 0.07 | AG50: 0.01 | AH50: 0.29 | AI50: 0.48 | AJ50: 0 | AK50: 0 | AL50: 0 | AM50: 0 | AN50: 0.13 | AO50: 0 | AP50: 0.02 | AQ50: 0 | AR50: 1 | AT50: 0 | AU50: 0 | AV50: 0.097 | AW50: 0.018 | AX50: 0.393 | AY50: 0.262 | AZ50: 0 | BA50: 0 | BB50: 0 | BC50: 0 | BD50: 0.23 | BE50: 0 | BF50: 0 | BG50: 0 | BI50: =AT50=AD50 -> TRUE | BJ50: =AU50=AE50 -> TRUE | BK50: =AV50=AF50 -> FALSE | BL50: =AW50=AG50 -> FALSE | BM50: =AX50=AH50 -> FALSE | BN50: =AY50=AI50 -> FALSE | BO50: =AZ50=AJ50 -> TRUE | BP50: =BA50=AK50 -> TRUE | ... BV50: =BG50=AQ50 -> TRUE
B51: Autres sidérurgies | C51: 2021 | D51: 2030 | E51: 2030 | F51: Hausse | U51: on sait pas trop si on pourrait exporter des CSR | AR51: 0 | BI51: =AT51=AD51 -> TRUE | BJ51: =AU51=AE51 -> TRUE | BK51: =AV51=AF51 -> TRUE | BL51: =AW51=AG51 -> TRUE | BM51: =AX51=AH51 -> TRUE | BN51: =AY51=AI51 -> TRUE | BO51: =AZ51=AJ51 -> TRUE | BP51: =BA51=AK51 -> TRUE | ... BV51: =BG51=AQ51 -> TRUE
B52: Electricité | C52: 11465.761 | D52: {=MMULT(J4:W16,TRANSPOSE('A renseigner'!E71:R71))*C65*'A renseigner'!E157*'A renseigner'!G6/'A renseigner'!C6} -> 14446.407 | E52: {=MMULT(J4:W16,TRANSPOSE('A renseigner'!E72:R72))*C65*'A renseigner'!G157*'A renseigner'!K6/'A renseigner'!C6} -> 16250.94 | F52: =D52-C52 -> 2980.6461 | G52: =E52-C52 -> 4785.1789 | AA52: Dont verre | AB52: 2021 | AC52: % | AD52: 0 | AE52: 0 | AF52: 0.09 | AG52: 0.67 | AH52: 0 | AI52: 0 | AJ52: 0 | AK52: 0 | AL52: 0 | AM52: 0 | AN52: 0.24 | AO52: 0 | AP52: 0 | AQ52: 0 | AR52: 1 | AT52: 0 | AU52: 0 | AV52: 0.09 | AW52: 0.67 | AX52: 0 | AY52: 0 | AZ52: 0 | BA52: 0 | BB52: 0 | BC52: 0 | BD52: 0.24 | BE52: 0 | BF52: 0 | BG52: 0 | BI52: =AT52=AD52 -> TRUE | BJ52: =AU52=AE52 -> TRUE | BK52: =AV52=AF52 -> TRUE | BL52: =AW52=AG52 -> TRUE | BM52: =AX52=AH52 -> TRUE | BN52: =AY52=AI52 -> TRUE | BO52: =AZ52=AJ52 -> TRUE | BP52: =BA52=AK52 -> TRUE | ... BV52: =BG52=AQ52 -> TRUE
B53: Electricité PAC | C53: 0 | D53: 0 | E53: 0 | F53: =D53-C53 -> 0 | G53: =E53-C53 -> 0 | N53: Autres non métalliques | Q53: Autres + autres métalliques + construction + verre + aluminium + sidérurgie | U53: baisser à 0% dans les mix énergétiques les PPR (sortie des fossiles) ? | AA53: Dont verre | AB53: 2030 | AC53: % | AD53: 0 | AE53: 0 | AF53: 0 | AG53: 0.54 | AH53: 0 | AI53: 0 | AJ53: 0 | AK53: 0 | AL53: 0 | AM53: 0 | AN53: 0.45 | AO53: 0 | AP53: 0 | AQ53: 0.01 | AR53: 1 | AT53: 0 | AU53: 0 | AV53: 0 | AW53: 0.54 | AX53: 0 | AY53: 0 | AZ53: 0 | BA53: 0 | BB53: 0 | BC53: 0 | BD53: 0.45 | BE53: 0 | BF53: 0 | BG53: 0.01 | BI53: =AT53=AD53 -> TRUE | BJ53: =AU53=AE53 -> TRUE | BK53: =AV53=AF53 -> TRUE | BL53: =AW53=AG53 -> TRUE | BM53: =AX53=AH53 -> TRUE | BN53: =AY53=AI53 -> TRUE | BO53: =AZ53=AJ53 -> TRUE | BP53: =BA53=AK53 -> TRUE | ... BV53: =BG53=AQ53 -> TRUE
B54: Produits liquides (fossile, bio, et synthétique) | C54: 206.59561 | D54: 192.61876 | E54: 0 | F54: =D54-C54 -> -13.976854 | G54: =E54-C54 -> -206.59561 | I54: Chiffres run 2 estimés après changement de mix | J54: Chimie | K54: Papier-carton | L54: Ciment | M54: Agro-alimentaire | N54: Chaux | O54: Briques et tuiles | P54: Biens d'équipements, matériels de transport | Q54: Autres | R54: Total | U54: aller voir rapports PTS | AA54: Dont verre | AB54: 2050 | AC54: % | AD54: 0 | AE54: 0 | AF54: 0 | AG54: 0.2 | AH54: 0 | AI54: 0 | AJ54: 0 | AK54: 0 | AL54: 0 | AM54: 0 | AN54: 0.65 | AO54: 0 | AP54: 0 | AQ54: 0.15 | AR54: 1 | AT54: 0 | AU54: 0 | AV54: 0 | AW54: 0.2 | AX54: 0 | AY54: 0 | AZ54: 0 | BA54: 0 | BB54: 0 | BC54: 0 | BD54: 0.65 | BE54: 0 | BF54: 0 | BG54: 0.15 | BI54: =AT54=AD54 -> TRUE | BJ54: =AU54=AE54 -> TRUE | BK54: =AV54=AF54 -> TRUE | BL54: =AW54=AG54 -> TRUE | BM54: =AX54=AH54 -> TRUE | BN54: =AY54=AI54 -> TRUE | BO54: =AZ54=AJ54 -> TRUE | BP54: =BA54=AK54 -> TRUE | ... BV54: =BG54=AQ54 -> TRUE
B55: Gaz de réseau | C55: 10745.612 | D55: 5935.0655 | E55: 3946.6568 | F55: =D55-C55 -> -4810.5468 | G55: =E55-C55 -> -6798.9555 | I55: Besoins supplémentaires en biomasse en 2030 (TWh) | J55: =(F106+F123+F140+F262)/1000 -> 4.089042 | K55: =F225/1000 -> 3.4255353 | L55: =F157/1000 -> 1.5009992 | M55: =(F191+F298)/1000 -> 5.9168175 | N55: =F280/1000 -> 1.8744236 | P55: =F316/1000 -> 1.1646824 | Q55: =(F333+F244+F208+F174+F73+F89+F57+F25+F9)/1000 -> 2.2063943 | R55: =SUM(J55:Q55) -> 20.177894 | AR55: 0 | BI55: =AT55=AD55 -> TRUE | BJ55: =AU55=AE55 -> TRUE | BK55: =AV55=AF55 -> TRUE | BL55: =AW55=AG55 -> TRUE | BM55: =AX55=AH55 -> TRUE | BN55: =AY55=AI55 -> TRUE | BO55: =AZ55=AJ55 -> TRUE | BP55: =BA55=AK55 -> TRUE | ... BV55: =BG55=AQ55 -> TRUE
B56: Hydrogène | D56: 0 | E56: 0 | F56: =D56-C56 -> 0 | G56: =E56-C56 -> 0 | I56: Besoins supplémentaires en CSR en 2030 (TWh) | J56: =(F107+F124+F141+F263)/1000 -> 2.3670534 | K56: =F226/1000 -> 0.73943273 | L56: =F158/1000 -> 2.6310292 | M56: =(F192+F299)/1000 -> 0.65919806 | N56: =F281/1000 -> 0 | P56: =F317/1000 -> 1.1814035 | Q56: =(F334+F245+F209+F175+F74+F90+F58+F26+F10)/1000 -> 2.4809252 | R56: =SUM(J56:Q56) -> 10.059042 | AA56: Dont autres non-métalliques | AB56: 2021 | AC56: % | AD56: 0.058824428 | AE56: 0.023692804 | AF56: 0.12818758 | AG56: 0.36949937 | AH56: 0.18685926 | AI56: 0 | AJ56: 0 | AK56: 0 | AL56: 0 | AM56: 0 | AN56: 0.22296449 | AO56: 0 | AP56: 0.0099720701 | AQ56: 0 | AR56: 1 | AT56: 0.058824428 | AU56: 0.023692804 | AV56: 0.12818758 | AW56: 0.36949937 | AX56: 0.18685926 | AY56: 0 | AZ56: 0 | BA56: 0 | BB56: 0 | BC56: 0 | BD56: 0.22296449 | BE56: 0 | BF56: 0.0099720701 | BG56: 0 | BI56: =AT56=AD56 -> TRUE | BJ56: =AU56=AE56 -> TRUE | BK56: =AV56=AF56 -> TRUE | BL56: =AW56=AG56 -> TRUE | BM56: =AX56=AH56 -> TRUE | BN56: =AY56=AI56 -> TRUE | BO56: =AZ56=AJ56 -> TRUE | BP56: =BA56=AK56 -> TRUE | ... BV56: =BG56=AQ56 -> TRUE
B57: Biomasse | C57: 0 | D57: 770.47503 | E57: 1439.3689 | F57: =D57-C57 -> 770.47503 | G57: =E57-C57 -> 1439.3689 | I57: Besoins supplémentaires en biogaz en 2030 (TWh) | J57: =(F113+F130+F147+F269)/1000 -> 2.465185 | K57: =F232/1000 -> 0.46552074 | L57: =F164/1000 -> 0.037953035 | M57: =(F198+F305)/1000 -> 1.7639798 | N57: =F287/1000 -> 0.63064301 | P57: =F323/1000 -> 0.88605264 | Q57: =(F340+F251+F215+F181+F80+F96+F64+F48+F32+F16)/1000 -> 4.3599053 | R57: =SUM(J57:Q57) -> 10.609239 | S57: dur de réduire plus le biogaz autres | AA57: Dont autres non-métalliques | AB57: 2030 | AC57: % | AD57: 0 | AE57: 0 | AF57: 0.01 | AG57: 0.51 | AH57: 0.04 | AI57: 0 | AJ57: 0 | AK57: 0 | AL57: 0 | AM57: 0 | AN57: 0.44 | AO57: 0 | AP57: 0 | AQ57: 0 | AR57: 1 | AT57: 0 | AU57: 0 | AV57: 0.01 | AW57: 0.245 | AX57: 0.305 | AY57: 0 | AZ57: 0 | BA57: 0 | BB57: 0 | BC57: 0 | BD57: 0.44 | BE57: 0 | BF57: 0 | BG57: 0 | BI57: =AT57=AD57 -> TRUE | BJ57: =AU57=AE57 -> TRUE | BK57: =AV57=AF57 -> TRUE | BL57: =AW57=AG57 -> FALSE | BM57: =AX57=AH57 -> FALSE | BN57: =AY57=AI57 -> TRUE | BO57: =AZ57=AJ57 -> TRUE | BP57: =BA57=AK57 -> TRUE | ... BV57: =BG57=AQ57 -> TRUE
B58: Dechets | C58: 0 | D58: 481.54689 | E58: 650.03759 | F58: =D58-C58 -> 481.54689 | G58: =E58-C58 -> 650.03759 | I58: Besoins supplémentaires totaux biomasse et CSR (TWh) | J58: =J55+J56+J57 -> 8.9212804 | K58: =K55+K56+K57 -> 4.6304888 | L58: =L55+L56+L57 -> 4.1699815 | M58: =M55+M56+M57 -> 8.3399953 | N58: =N55+N56+N57 -> 2.5050666 | P58: =P55+P56+P57 -> 3.2321385 | Q58: =Q55+Q56+Q57 -> 9.0472248 | R58: =R55+R56+R57 -> 40.846176 | AA58: Dont autres non-métalliques | AB58: 2050 | AC58: % | AD58: 0 | AE58: 0 | AF58: 0 | AG58: 0.38951958 | AH58: 0.05 | AI58: 0 | AJ58: 0 | AK58: 0 | AL58: 0 | AM58: 0 | AN58: 0.56048042 | AO58: 0 | AP58: 0 | AQ58: 0 | AR58: 1 | AT58: 0 | AU58: 0 | AV58: 0 | AW58: 0.16 | AX58: 0.28 | AY58: 0 | AZ58: 0 | BA58: 0 | BB58: 0 | BC58: 0 | BD58: 0.56048042 | BE58: 0 | BF58: 0 | BG58: 0 | BI58: =AT58=AD58 -> TRUE | BJ58: =AU58=AE58 -> TRUE | BK58: =AV58=AF58 -> TRUE | BL58: =AW58=AG58 -> FALSE | BM58: =AX58=AH58 -> FALSE | BN58: =AY58=AI58 -> TRUE | BO58: =AZ58=AJ58 -> TRUE | BP58: =BA58=AK58 -> TRUE | ... BV58: =BG58=AQ58 -> TRUE
B59: Charbon | C59: 1261.5602 | D59: 963.09379 | E59: 0 | F59: =D59-C59 -> -298.46639 | G59: =E59-C59 -> -1261.5602 | I59: Diff DGE | J59: =J58-(J42+J43) -> -2.143937 | K59: =K58-(K42+K43) -> 0.71744529 | L59: =L58-(L42+L43) -> -0.6126272 | M59: =M58-(M42+M43) -> 0.38347361 | N59: =N58-(N42+N43) -> 0.99202315 | O59: =O58-(O42+O43) -> -0.94956522 | P59: =P58-(P42+P43) -> 1.9277907 | Q59: =Q58-(Q42+Q43) -> 5.6472248 | R59: =R58-(R42+R43) -> 5.9618281 | AR59: 0 | BI59: =AT59=AD59 -> TRUE | BJ59: =AU59=AE59 -> TRUE | BK59: =AV59=AF59 -> TRUE | BL59: =AW59=AG59 -> TRUE | BM59: =AX59=AH59 -> TRUE | BN59: =AY59=AI59 -> TRUE | BO59: =AZ59=AJ59 -> TRUE | BP59: =BA59=AK59 -> TRUE | ... BV59: =BG59=AQ59 -> TRUE
B60: Coke | C60: 707.50555 | D60: 0 | E60: 0 | F60: =D60-C60 -> -707.50555 | G60: =E60-C60 -> -707.50555 | I60: Cohérent avec le 30TWh + 5TWh DGE | AA60: Industries agroalimentaires | AD60: Charbon | AE60: Coke | AF60: Produits pétroliers raffinés | AG60: Gaz naturel | AH60: Biomasse solide | AI60: Déchets | AJ60: Biocarburants | AK60: Gaz renouvelable | AL60: Chaleur de l'environnement | AM60: Solaire thermique et géothermie | AN60: Électricité | AO60: Electricité PAC | AP60: Chaleur vendue | AQ60: Hydrogène | AR60: 0 | AT60: Charbon | AU60: Coke | AV60: Produits pétroliers raffinés | AW60: Gaz naturel | AX60: Biomasse solide | AY60: Déchets | AZ60: Biocarburants | BA60: Gaz renouvelable | BB60: Chaleur de l'environnement | BC60: Solaire thermique et géothermie | BD60: Électricité | BE60: Electricité PAC | BF60: Chaleur vendue | BG60: Hydrogène | BI60: =AT60=AD60 -> TRUE | BJ60: =AU60=AE60 -> TRUE | BK60: =AV60=AF60 -> TRUE | BL60: =AW60=AG60 -> TRUE | BM60: =AX60=AH60 -> TRUE | BN60: =AY60=AI60 -> TRUE | BO60: =AZ60=AJ60 -> TRUE | BP60: =BA60=AK60 -> TRUE | ... BV60: =BG60=AQ60 -> TRUE
B61: Chaleur | C61: 167.03398 | D61: 240.77345 | E61: 232.15628 | F61: =D61-C61 -> 73.739466 | G61: =E61-C61 -> 65.1223 | J61: 2021 | K61: 2030 | L61: 2050 | AA61: Dont Sucre | AB61: 2021 | AC61: % | AD61: 0.1 | AE61: 0 | AF61: 0 | AG61: 0.7 | AH61: 0.1 | AI61: 0 | AJ61: 0 | AK61: 0 | AL61: 0 | AM61: 0 | AN61: 0.1 | AO61: 0 | AP61: 0 | AQ61: 0 | AR61: 1 | AT61: 0.1 | AU61: 0 | AV61: 0 | AW61: 0.7 | AX61: 0.1 | AY61: 0 | AZ61: 0 | BA61: 0 | BB61: 0 | BC61: 0 | BD61: 0.1 | BE61: 0 | BF61: 0 | BG61: 0 | BI61: =AT61=AD61 -> TRUE | BJ61: =AU61=AE61 -> TRUE | BK61: =AV61=AF61 -> TRUE | BL61: =AW61=AG61 -> TRUE | BM61: =AX61=AH61 -> TRUE | BN61: =AY61=AI61 -> TRUE | BO61: =AZ61=AJ61 -> TRUE | BP61: =BA61=AK61 -> TRUE | ... BV61: =BG61=AQ61 -> TRUE
B62: Solar & Geothermie | C62: 0 | D62: 0 | E62: 0 | F62: =D62-C62 -> 0 | G62: =E62-C62 -> 0 | I62: CSR run 2 industrie hors cimenteries | J62: 0 | K62: =1696.87158203125/1000 -> 1.6968716 | L62: =1129.830078125/1000 -> 1.1298301 | AA62: Dont Sucre | AB62: 2030 | AC62: % | AD62: 0.01 | AE62: 0 | AF62: 0 | AG62: 0.35 | AH62: 0.39 | AI62: 0 | AJ62: 0 | AK62: 0 | AL62: 0 | AM62: 0 | AN62: 0.25 | AO62: 0 | AP62: 0 | AQ62: 0 | AR62: 1 | AT62: 0.01 | AU62: 0 | AV62: 0 | AW62: 0.35 | AX62: 0.39 | AY62: 0 | AZ62: 0 | BA62: 0 | BB62: 0 | BC62: 0 | BD62: 0.25 | BE62: 0 | BF62: 0 | BG62: 0 | BI62: =AT62=AD62 -> TRUE | BJ62: =AU62=AE62 -> TRUE | BK62: =AV62=AF62 -> TRUE | BL62: =AW62=AG62 -> TRUE | BM62: =AX62=AH62 -> TRUE | BN62: =AY62=AI62 -> TRUE | BO62: =AZ62=AJ62 -> TRUE | BP62: =BA62=AK62 -> TRUE | ... BV62: =BG62=AQ62 -> TRUE
B63: Chaleur Env | C63: 0 | D63: 0 | E63: 0 | F63: =D63-C63 -> 0 | G63: =E63-C63 -> 0 | I63: CSR run 3 industrie hors cimenteries | J63: 0 | K63: =J63+(F334+F317+F245+F209+F192+F175+F141+F74+F90+F58+F26+F10+F226+F263)/1000 -> 7.4280129 | L63: =J63+(G334+G317+G245+G209+G192+G175+G141+G74+G90+G58+G26+G10+G226+G263)/1000 -> 10.67017 | M63: Le delta vient en 2030 surtout de la construction via autres chimies et en 2050 le delta supplémentaire vient de la baisse des PPR au profit des CSR | AA63: Dont Sucre | AB63: 2050 | AC63: % | AD63: 0 | AE63: 0 | AF63: 0 | AG63: 0.29 | AH63: 0.4 | AI63: 0 | AJ63: 0 | AK63: 0 | AL63: 0 | AM63: 0 | AN63: 0.31 | AO63: 0 | AP63: 0 | AQ63: 0 | AR63: 1 | AT63: 0 | AU63: 0 | AV63: 0 | AW63: 0.29 | AX63: 0.4 | AY63: 0 | AZ63: 0 | BA63: 0 | BB63: 0 | BC63: 0 | BD63: 0.31 | BE63: 0 | BF63: 0 | BG63: 0 | BI63: =AT63=AD63 -> TRUE | BJ63: =AU63=AE63 -> TRUE | BK63: =AV63=AF63 -> TRUE | BL63: =AW63=AG63 -> TRUE | BM63: =AX63=AH63 -> TRUE | BN63: =AY63=AI63 -> TRUE | BO63: =AZ63=AJ63 -> TRUE | BP63: =BA63=AK63 -> TRUE | ... BV63: =BG63=AQ63 -> TRUE
B64: Biogaz autoconsommé | C64: 0 | D64: 1047.3645 | E64: 696.46884 | F64: =D64-C64 -> 1047.3645 | G64: =E64-C64 -> 696.46884 | I64: CSR run 3 déchets hors cimenteries (hors RCU) | J64: 0.2537502 | K64: 7.6125061 | L64: 10.150008 | AR64: 0 | BI64: =AT64=AD64 -> TRUE | BJ64: =AU64=AE64 -> TRUE | BK64: =AV64=AF64 -> TRUE | BL64: =AW64=AG64 -> TRUE | BM64: =AX64=AH64 -> TRUE | BN64: =AY64=AI64 -> TRUE | BO64: =AZ64=AJ64 -> TRUE | BP64: =BA64=AK64 -> TRUE | ... BV64: =BG64=AQ64 -> TRUE
B65: Total | C65: 24554.068 | D65: =SUM(D52:D64) -> 24077.345 | E65: =SUM(E52:E64) -> 23215.628 | F65: =D65-C65 -> -476.72366 | G65: =E65-C65 -> -1338.4402 | I65: CSR run 2 industrie cimenteries | J65: =3441.45629882812/1000 -> 3.4414563 | K65: =5592.17333984375/1000 -> 5.5921733 | L65: =4227.93701171875/1000 -> 4.227937 | AA65: Dont autres IAA | AB65: 2021 | AC65: % | AD65: 0.038197862 | AE65: 0.0023519892 | AF65: 0.062781928 | AG65: 0.37642387 | AH65: 0.018456019 | AI65: 0 | AJ65: 0 | AK65: 0 | AL65: 0 | AM65: 0 | AN65: 0.4236174 | AO65: 0 | AP65: 0.078170936 | AQ65: 0 | AR65: 1 | AT65: 0.038197862 | AU65: 0.0023519892 | AV65: 0.062781928 | AW65: 0.37642387 | AX65: 0.018456019 | AY65: 0 | AZ65: 0 | BA65: 0 | BB65: 0 | BC65: 0 | BD65: 0.4236174 | BE65: 0 | BF65: 0.078170936 | BG65: 0 | BI65: =AT65=AD65 -> TRUE | BJ65: =AU65=AE65 -> TRUE | BK65: =AV65=AF65 -> TRUE | BL65: =AW65=AG65 -> TRUE | BM65: =AX65=AH65 -> TRUE | BN65: =AY65=AI65 -> TRUE | BO65: =AZ65=AJ65 -> TRUE | BP65: =BA65=AK65 -> TRUE | ... BV65: =BG65=AQ65 -> TRUE
I66: CSR run 3 industrie cimenteries | J66: =3441.45629882812/1000 -> 3.4414563 | K66: =K65+L56-L47 -> 6.2215994 | L66: =J66+(E158-C158)/1000 -> 4.0219186 | M66: la différence pourrait venir du fait que les cimentiers bruûlent des déchets qui ne sont pas des CSR, on pourrait être bon en 2050 si ces déchets là ne sont plus brûlés et qu'il n'y a que des CSR | AA66: Dont autres IAA | AB66: 2030 | AC66: % | AD66: 0 | AE66: 0 | AF66: 0 | AG66: 0.33540341 | AH66: 0.08 | AI66: 0 | AJ66: 0 | AK66: 0 | AL66: 0.04 | AM66: 0 | AN66: 0.456 | AO66: 0.02 | AP66: 0.068139581 | AQ66: 0 | AR66: 0.99954299 | AT66: 0 | AU66: 0 | AV66: 0 | AW66: 0.275 | AX66: 0.12 | AY66: 0 | AZ66: 0 | BA66: 0 | BB66: 0.04 | BC66: 0 | BD66: 0.465 | BE66: 0.02 | BF66: 0.08 | BG66: 0 | BI66: =AT66=AD66 -> TRUE | BJ66: =AU66=AE66 -> TRUE | BK66: =AV66=AF66 -> TRUE | BL66: =AW66=AG66 -> FALSE | BM66: =AX66=AH66 -> FALSE | BN66: =AY66=AI66 -> TRUE | BO66: =AZ66=AJ66 -> TRUE | BP66: =BA66=AK66 -> TRUE | ... BV66: =BG66=AQ66 -> TRUE
B67: Aluminium primaire | C67: 2021 | D67: 2030 | E67: 2030 | F67: Hausse | I67: CSR run 3 déchets cimenteries | J67: 1.212501 | K67: 4.0416699 | L67: 4.0416699 | AA67: Dont autres IAA | AB67: 2050 | AC67: % | AD67: 0 | AE67: 0 | AF67: 0 | AG67: 0.078832364 | AH67: 0.15 | AI67: 0 | AJ67: 0 | AK67: 0 | AL67: 0.1 | AM67: 0 | AN67: 0.506 | AO67: 0.085 | AP67: 0.079710631 | AQ67: 0 | AR67: 0.99954299 | AT67: 0 | AU67: 0 | AV67: 0 | AW67: 0.078832364 | AX67: 0.15 | AY67: 0 | AZ67: 0 | BA67: 0 | BB67: 0.1 | BC67: 0 | BD67: 0.506 | BE67: 0.085 | BF67: 0.079710631 | BG67: 0 | BI67: =AT67=AD67 -> TRUE | BJ67: =AU67=AE67 -> TRUE | BK67: =AV67=AF67 -> TRUE | BL67: =AW67=AG67 -> TRUE | BM67: =AX67=AH67 -> TRUE | BN67: =AY67=AI67 -> TRUE | BO67: =AZ67=AJ67 -> TRUE | BP67: =BA67=AK67 -> TRUE | ... BV67: =BG67=AQ67 -> TRUE
B68: Electricité | C68: 3805.9824 | D68: {=MMULT(J4:W16,TRANSPOSE('A renseigner'!E75:R75))*C81*'A renseigner'!E158*'A renseigner'!G10/'A renseigner'!C10} -> 5125.5367 | E68: {=MMULT(J4:W16,TRANSPOSE('A renseigner'!E75:R75))*C81*'A renseigner'!G158*'A renseigner'!K10/'A renseigner'!C10} -> 7799.2189 | F68: =D68-C68 -> 1319.5543 | AR68: 0 | BI68: =AT68=AD68 -> TRUE | BJ68: =AU68=AE68 -> TRUE | BK68: =AV68=AF68 -> TRUE | BL68: =AW68=AG68 -> TRUE | BM68: =AX68=AH68 -> TRUE | BN68: =AY68=AI68 -> TRUE | BO68: =AZ68=AJ68 -> TRUE | BP68: =BA68=AK68 -> TRUE | ... BV68: =BG68=AQ68 -> TRUE
B69: Electricité PAC | C69: 0 | D69: 0 | E69: 0 | F69: =D69-C69 -> 0 | AA69: Equipement | AB69: 2021 | AD69: 0.0083013991 | AE69: 0.0083013991 | AF69: 0.040460378 | AG69: 0.340279 | AH69: 0.010248979 | AI69: 0 | AJ69: 0 | AK69: 0 | AL69: 0 | AM69: 0 | AN69: 0.58049486 | AO69: 0 | AP69: 0.011913982 | AQ69: 0 | AR69: 1 | AT69: 0.0083013991 | AU69: 0.0083013991 | AV69: 0.040460378 | AW69: 0.340279 | AX69: 0.010248979 | AY69: 0 | AZ69: 0 | BA69: 0 | BB69: 0 | BC69: 0 | BD69: 0.58049486 | BE69: 0 | BF69: 0.011913982 | BG69: 0 | BI69: =AT69=AD69 -> TRUE | BJ69: =AU69=AE69 -> TRUE | BK69: =AV69=AF69 -> TRUE | BL69: =AW69=AG69 -> TRUE | BM69: =AX69=AH69 -> TRUE | BN69: =AY69=AI69 -> TRUE | BO69: =AZ69=AJ69 -> TRUE | BP69: =BA69=AK69 -> TRUE | ... BV69: =BG69=AQ69 -> TRUE
B70: Produits liquides (fossile, bio, et synthétique) | C70: 150.09508 | D70: 0 | E70: 0 | F70: =D70-C70 -> -150.09508 | AA70: Equipement | AB70: 2030 | AD70: 0 | AE70: 0 | AF70: 0 | AG70: 0.28 | AH70: 0 | AI70: 0 | AJ70: 0 | AK70: 0 | AL70: 0.02 | AM70: 0 | AN70: 0.68 | AO70: 0.01 | AP70: 0.01 | AQ70: 0 | AR70: 1 | AT70: 0 | AU70: 0 | AV70: 0 | AW70: 0.24 | AX70: 0.05 | AY70: 0 | AZ70: 0 | BA70: 0 | BB70: 0.02 | BC70: 0 | BD70: 0.67 | BE70: 0.01 | BF70: 0.01 | BG70: 0 | BI70: =AT70=AD70 -> TRUE | BJ70: =AU70=AE70 -> TRUE | BK70: =AV70=AF70 -> TRUE | BL70: =AW70=AG70 -> FALSE | BM70: =AX70=AH70 -> FALSE | BN70: =AY70=AI70 -> TRUE | BO70: =AZ70=AJ70 -> TRUE | BP70: =BA70=AK70 -> TRUE | ... BV70: =BG70=AQ70 -> TRUE
B71: Gaz de réseau | C71: 1340.1346 | D71: 768.8305 | E71: 1169.8828 | F71: =D71-C71 -> -571.30414 | AA71: Equipement | AB71: 2050 | AD71: 0 | AE71: 0 | AF71: 0 | AG71: 0.13918942 | AH71: 0 | AI71: 0 | AJ71: 0 | AK71: 0 | AL71: 0.09 | AM71: 0 | AN71: 0.70581058 | AO71: 0.045 | AP71: 0.02 | AQ71: 0 | AR71: 1 | AT71: 0 | AU71: 0 | AV71: 0 | AW71: 0.099 | AX71: 0.05 | AY71: 0 | AZ71: 0 | BA71: 0 | BB71: 0.09 | BC71: 0 | BD71: 0.696 | BE71: 0.045 | BF71: 0.02 | BG71: 0 | BI71: =AT71=AD71 -> TRUE | BJ71: =AU71=AE71 -> TRUE | BK71: =AV71=AF71 -> TRUE | BL71: =AW71=AG71 -> FALSE | BM71: =AX71=AH71 -> FALSE | BN71: =AY71=AI71 -> TRUE | BO71: =AZ71=AJ71 -> TRUE | BP71: =BA71=AK71 -> TRUE | ... BV71: =BG71=AQ71 -> TRUE
B72: Hydrogène | D72: 0 | E72: 0 | F72: =D72-C72 -> 0 | AR72: 0 | BI72: =AT72=AD72 -> TRUE | BJ72: =AU72=AE72 -> TRUE | BK72: =AV72=AF72 -> TRUE | BL72: =AW72=AG72 -> TRUE | BM72: =AX72=AH72 -> TRUE | BN72: =AY72=AI72 -> TRUE | BO72: =AZ72=AJ72 -> TRUE | BP72: =BA72=AK72 -> TRUE | ... BV72: =BG72=AQ72 -> TRUE
B73: Biomasse | C73: 0 | D73: 0 | E73: 0 | F73: =D73-C73 -> 0 | I73: Chiffres run 2 estimés après changement de mix | J73: Chimie | K73: Papier-carton | L73: Ciment | M73: Agro-alimentaire | N73: Chaux + briques et tuiles | P73: Biens d'équipements, matériels de transport | Q73: Autres | R73: Total | AA73: Construction | AB73: 2021 | AD73: 0 | AE73: 0 | AF73: 0.60033111 | AG73: 0.15234286 | AH73: 0.00096699526 | AI73: 0 | AJ73: 0 | AK73: 0 | AL73: 0 | AM73: 0 | AN73: 0.24635904 | AO73: 0 | AP73: 0 | AQ73: 0 | AR73: 1 | AT73: 0 | AU73: 0 | AV73: 0.60033111 | AW73: 0.15234286 | AX73: 0.00096699526 | AY73: 0 | AZ73: 0 | BA73: 0 | BB73: 0 | BC73: 0 | BD73: 0.24635904 | BE73: 0 | BF73: 0 | BG73: 0 | BI73: =AT73=AD73 -> TRUE | BJ73: =AU73=AE73 -> TRUE | BK73: =AV73=AF73 -> TRUE | BL73: =AW73=AG73 -> TRUE | BM73: =AX73=AH73 -> TRUE | BN73: =AY73=AI73 -> TRUE | BO73: =AZ73=AJ73 -> TRUE | BP73: =BA73=AK73 -> TRUE | ... BV73: =BG73=AQ73 -> TRUE
B74: Dechets | C74: 0 | D74: 0 | E74: 0 | F74: =D74-C74 -> 0 | H74: Run 2 ajusté | I74: Besoins supplémentaires en biomasse en 2030 (TWh) | J74: 7.3286315 | K74: 3.4224648 | L74: 2.9480603 | M74: 7.2728507 | N74: 1.9989892 | P74: 1.1646824 | Q74: 1.2803735 | R74: 25.416052 | AA74: Construction | AB74: 2030 | AD74: 0 | AE74: 0 | AF74: 0.45 | AG74: 0.12495101 | AH74: 0.037426519 | AI74: 0.025959042 | AJ74: 0 | AK74: 0 | AL74: 0 | AM74: 0 | AN74: 0.342 | AO74: 0 | AP74: 0 | AQ74: 0.02 | AR74: 1.0003366 | AT74: 0 | AU74: 0 | AV74: 0.45 | AW74: 0.12495101 | AX74: 0.037426519 | AY74: 0.025959042 | AZ74: 0 | BA74: 0 | BB74: 0 | BC74: 0 | BD74: 0.342 | BE74: 0 | BF74: 0 | BG74: 0.02 | BI74: =AT74=AD74 -> TRUE | BJ74: =AU74=AE74 -> TRUE | BK74: =AV74=AF74 -> TRUE | BL74: =AW74=AG74 -> TRUE | BM74: =AX74=AH74 -> TRUE | BN74: =AY74=AI74 -> TRUE | BO74: =AZ74=AJ74 -> TRUE | BP74: =BA74=AK74 -> TRUE | ... BV74: =BG74=AQ74 -> TRUE
B75: Charbon | C75: 0 | D75: 0 | E75: 0 | F75: =D75-C75 -> 0 | I75: Besoins supplémentaires en CSR en 2030 (TWh) | J75: 2.1691488 | K75: 0.41395951 | L75: 0.54542328 | M75: 0 | N75: 0 | P75: 0 | Q75: 0 | R75: 3.1285316 | AA75: Construction | AB75: 2050 | AD75: 0 | AE75: 0 | AF75: 0.1 | AG75: 0.11 | AH75: 0.037426519 | AI75: 0.086676573 | AJ75: 0 | AK75: 0 | AL75: 0 | AM75: 0 | AN75: 0.596 | AO75: 0 | AP75: 0 | AQ75: 0.07 | AR75: 1.0001031 | AT75: 0 | AU75: 0 | AV75: 0.1 | AW75: 0.11 | AX75: 0.037426519 | AY75: 0.086676573 | AZ75: 0 | BA75: 0 | BB75: 0 | BC75: 0 | BD75: 0.596 | BE75: 0 | BF75: 0 | BG75: 0.07 | BI75: =AT75=AD75 -> TRUE | BJ75: =AU75=AE75 -> TRUE | BK75: =AV75=AF75 -> TRUE | BL75: =AW75=AG75 -> TRUE | BM75: =AX75=AH75 -> TRUE | BN75: =AY75=AI75 -> TRUE | BO75: =AZ75=AJ75 -> TRUE | BP75: =BA75=AK75 -> TRUE | ... BV75: =BG75=AQ75 -> TRUE
B76: Coke | C76: 0 | D76: 0 | E76: 0 | F76: =D76-C76 -> 0 | I76: Besoins supplémentaires en biogaz en 2030 (TWh) | J76: 2.545141 | K76: 1.94285 | L76: 0.038490751 | M76: 2.4959577 | N76: 0.64565214 | P76: 1.0632632 | Q76: 3.5085123 | R76: 12.239867 | AR76: 0 | BI76: =AT76=AD76 -> TRUE | BJ76: =AU76=AE76 -> TRUE | BK76: =AV76=AF76 -> TRUE | BL76: =AW76=AG76 -> TRUE | BM76: =AX76=AH76 -> TRUE | BN76: =AY76=AI76 -> TRUE | BO76: =AZ76=AJ76 -> TRUE | BP76: =BA76=AK76 -> TRUE | ... BV76: =BG76=AQ76 -> TRUE
B77: Chaleur | C77: 42.884308 | D77: 0 | E77: 0 | F77: =D77-C77 -> -42.884308 | I77: Besoins supplémentaires totaux biomasse et CSR (TWh) | J77: 12.042921 | K77: 5.7792743 | L77: 3.5319743 | M77: 9.7688084 | N77: 2.6446413 | O77: 0 | P77: 2.2279455 | Q77: 4.7888858 | R77: 40.784451 | AA77: Autres | AR77: 0 | BI77: =AT77=AD77 -> TRUE | BJ77: =AU77=AE77 -> TRUE | BK77: =AV77=AF77 -> TRUE | BL77: =AW77=AG77 -> TRUE | BM77: =AX77=AH77 -> TRUE | BN77: =AY77=AI77 -> TRUE | BO77: =AZ77=AJ77 -> TRUE | BP77: =BA77=AK77 -> TRUE | ... BV77: =BG77=AQ77 -> TRUE
B78: Solar & Geothermie | C78: 0 | D78: 0 | E78: 0 | F78: =D78-C78 -> 0 | H78: Chiffres FdR | I78: Besoins supplémentaires en biomasse en 2030 (TWh) | J78: 7.3913043 | K78: 3.4782609 | L78: 1.7391304 | M78: 6.9565217 | N78: 1.5130435 | O78: 0.54956522 | P78: 1.3043478 | Q78: 1.3 | R78: 24.232174 | AA78: Dont papier-pâtes | AB78: 2021 | AC78: % | AD78: 0 | AE78: 0 | AF78: 0.019754512 | AG78: 0.32243632 | AH78: 0.25696781 | AI78: 0 | AJ78: 0 | AK78: 0 | AL78: 0 | AM78: 0 | AN78: 0.25840134 | AO78: 0 | AP78: 0.14244002 | AQ78: 0 | AR78: 1 | AT78: 0 | AU78: 0 | AV78: 0.019754512 | AW78: 0.32243632 | AX78: 0.25696781 | AY78: 0 | AZ78: 0 | BA78: 0 | BB78: 0 | BC78: 0 | BD78: 0.25840134 | BE78: 0 | BF78: 0.14244002 | BG78: 0 | BI78: =AT78=AD78 -> TRUE | BJ78: =AU78=AE78 -> TRUE | BK78: =AV78=AF78 -> TRUE | BL78: =AW78=AG78 -> TRUE | BM78: =AX78=AH78 -> TRUE | BN78: =AY78=AI78 -> TRUE | BO78: =AZ78=AJ78 -> TRUE | BP78: =BA78=AK78 -> TRUE | ... BV78: =BG78=AQ78 -> TRUE
B79: Chaleur Env | C79: 0 | D79: 0 | E79: 0 | F79: =D79-C79 -> 0 | I79: Besoins supplémentaires en CSR en 2030 (TWh) | J79: 2.173913 | K79: 0.43478261 | L79: 3.0434783 | R79: 5.6521739 | AA79: Dont papier-pâtes | AB79: 2030 | AC79: % | AD79: 0 | AE79: 0 | AF79: 0 | AG79: 0.20091294 | AH79: 0.3 | AI79: 0.025 | AJ79: 0 | AK79: 0.05 | AL79: 0 | AM79: 0 | AN79: 0.28 | AO79: 0 | AP79: 0.14408706 | AQ79: 0 | AR79: 1 | AT79: 0 | AU79: 0 | AV79: 0 | AW79: 0.136 | AX79: 0.375 | AY79: 0.015 | AZ79: 0 | BA79: 0.05 | BB79: 0 | BC79: 0 | BD79: 0.28 | BE79: 0 | BF79: 0.14408706 | BG79: 0 | BI79: =AT79=AD79 -> TRUE | BJ79: =AU79=AE79 -> TRUE | BK79: =AV79=AF79 -> TRUE | BL79: =AW79=AG79 -> FALSE | BM79: =AX79=AH79 -> FALSE | BN79: =AY79=AI79 -> FALSE | BO79: =AZ79=AJ79 -> TRUE | BP79: =BA79=AK79 -> TRUE | ... BV79: =BG79=AQ79 -> TRUE
B80: Biogaz autoconsommé | C80: 0 | D80: 135.67597 | E80: 206.44991 | F80: =D80-C80 -> 135.67597 | I80: Besoins supplémentaires en biogaz en 2030 (TWh) | J80: 1.5 | M80: 1 | O80: 0.4 | Q80: 2.1 | R80: =SUM(J80:Q80) -> 5 | AA80: Dont papier-pâtes | AB80: 2050 | AC80: % | AD80: 0 | AE80: 0 | AF80: 0 | AG80: 0.04 | AH80: 0.24 | AI80: 0 | AJ80: 0 | AK80: 0 | AL80: 0.18 | AM80: 0 | AN80: 0.25 | AO80: 0.09 | AP80: 0.2 | AQ80: 0 | AR80: 1 | AT80: 0 | AU80: 0 | AV80: 0 | AW80: 0.04 | AX80: 0.24 | AY80: 0 | AZ80: 0 | BA80: 0 | BB80: 0.18 | BC80: 0 | BD80: 0.25 | BE80: 0.09 | BF80: 0.2 | BG80: 0 | BI80: =AT80=AD80 -> TRUE | BJ80: =AU80=AE80 -> TRUE | BK80: =AV80=AF80 -> TRUE | BL80: =AW80=AG80 -> TRUE | BM80: =AX80=AH80 -> TRUE | BN80: =AY80=AI80 -> TRUE | BO80: =AZ80=AJ80 -> TRUE | BP80: =BA80=AK80 -> TRUE | ... BV80: =BG80=AQ80 -> TRUE
B81: Total | C81: 5339.0967 | D81: =SUM(D68:D80) -> 6030.0431 | E81: =SUM(E68:E80) -> 9175.5517 | F81: =D81-C81 -> 690.94646 | I81: Besoins supplémentaires totaux biomasse et CSR (TWh) | J81: =J78+J79+J80 -> 11.065217 | K81: =K78+K79+K80 -> 3.9130435 | L81: =L78+L79+L80 -> 4.7826087 | M81: =M78+M79+M80 -> 7.9565217 | N81: =N78+N79+N80 -> 1.5130435 | O81: =O78+O79+O80 -> 0.94956522 | P81: =P78+P79+P80 -> 1.3043478 | Q81: =Q78+Q79+Q80 -> 3.4 | R81: =R78+R79+R80 -> 34.884348 | AR81: 0 | BI81: =AT81=AD81 -> TRUE | BJ81: =AU81=AE81 -> TRUE | BK81: =AV81=AF81 -> TRUE | BL81: =AW81=AG81 -> TRUE | BM81: =AX81=AH81 -> TRUE | BN81: =AY81=AI81 -> TRUE | BO81: =AZ81=AJ81 -> TRUE | BP81: =BA81=AK81 -> TRUE | ... BV81: =BG81=AQ81 -> TRUE
AA82: Dont autres | AB82: 2021 | AC82: % | AD82: 0 | AE82: 0 | AF82: 0.14647137 | AG82: 0.33207215 | AH82: 0.013333321 | AI82: 0 | AJ82: 0 | AK82: 0 | AL82: 0 | AM82: 0 | AN82: 0.48260816 | AO82: 0 | AP82: 0.025515003 | AQ82: 0 | AR82: 1 | AT82: 0 | AU82: 0 | AV82: 0.14647137 | AW82: 0.33207215 | AX82: 0.013333321 | AY82: 0 | AZ82: 0 | BA82: 0 | BB82: 0 | BC82: 0 | BD82: 0.48260816 | BE82: 0 | BF82: 0.025515003 | BG82: 0 | BI82: =AT82=AD82 -> TRUE | BJ82: =AU82=AE82 -> TRUE | BK82: =AV82=AF82 -> TRUE | BL82: =AW82=AG82 -> TRUE | BM82: =AX82=AH82 -> TRUE | BN82: =AY82=AI82 -> TRUE | BO82: =AZ82=AJ82 -> TRUE | BP82: =BA82=AK82 -> TRUE | ... BV82: =BG82=AQ82 -> TRUE
B83: Aluminium recyclé | C83: 2021 | D83: 2030 | E83: 2030 | F83: Hausse | AA83: Dont autres | AB83: 2030 | AC83: % | AD83: 0 | AE83: 0 | AF83: 0.04 | AG83: 0.31 | AH83: 0.02 | AI83: 0 | AJ83: 0 | AK83: 0 | AL83: 0.06 | AM83: 0 | AN83: 0.52 | AO83: 0.03 | AP83: 0.02 | AQ83: 0 | AR83: 1 | AT83: 0 | AU83: 0 | AV83: 0.04 | AW83: 0.31 | AX83: 0.02 | AY83: 0 | AZ83: 0 | BA83: 0 | BB83: 0.06 | BC83: 0 | BD83: 0.52 | BE83: 0.03 | BF83: 0.02 | BG83: 0 | BI83: =AT83=AD83 -> TRUE | BJ83: =AU83=AE83 -> TRUE | BK83: =AV83=AF83 -> TRUE | BL83: =AW83=AG83 -> TRUE | BM83: =AX83=AH83 -> TRUE | BN83: =AY83=AI83 -> TRUE | BO83: =AZ83=AJ83 -> TRUE | BP83: =BA83=AK83 -> TRUE | ... BV83: =BG83=AQ83 -> TRUE
B84: Electricité | C84: 448.63 | D84: {=MMULT($J$4:$W$16,TRANSPOSE('A renseigner'!$E$79:$R$79))*C97*'A renseigner'!E159*'A renseigner'!G11/'A renseigner'!$E11} -> 714.84377 | E84: {=MMULT($J$4:$W$16,TRANSPOSE('A renseigner'!$E$79:$R$79))*C97*'A renseigner'!G159*'A renseigner'!K11/'A renseigner'!$E11} -> 1427.6515 | F84: =D84-C84 -> 266.21376 | AA84: Dont autres | AB84: 2050 | AC84: % | AD84: 0 | AE84: 0 | AF84: 0 | AG84: 0.083851481 | AH84: 0.02 | AI84: 0 | AJ84: 0 | AK84: 0 | AL84: 0.22 | AM84: 0 | AN84: 0.54 | AO84: 0.11 | AP84: 0.026148519 | AQ84: 0 | AR84: 1 | AT84: 0 | AU84: 0 | AV84: 0 | AW84: 0.083851481 | AX84: 0.02 | AY84: 0 | AZ84: 0 | BA84: 0 | BB84: 0.22 | BC84: 0 | BD84: 0.54 | BE84: 0.11 | BF84: 0.026148519 | BG84: 0 | BI84: =AT84=AD84 -> TRUE | BJ84: =AU84=AE84 -> TRUE | BK84: =AV84=AF84 -> TRUE | BL84: =AW84=AG84 -> TRUE | BM84: =AX84=AH84 -> TRUE | BN84: =AY84=AI84 -> TRUE | BO84: =AZ84=AJ84 -> TRUE | BP84: =BA84=AK84 -> TRUE | ... BV84: =BG84=AQ84 -> TRUE
B85: Electricité PAC | C85: 0 | D85: 0 | E85: 0 | F85: =D85-C85 -> 0 | AR85: 0 | BI85: =AT85=AD85 -> TRUE | BJ85: =AU85=AE85 -> TRUE | BK85: =AV85=AF85 -> TRUE | BL85: =AW85=AG85 -> TRUE | BM85: =AX85=AH85 -> TRUE | BN85: =AY85=AI85 -> TRUE | BO85: =AZ85=AJ85 -> TRUE | BP85: =BA85=AK85 -> TRUE | ... BV85: =BG85=AQ85 -> TRUE
B86: Produits liquides (fossile, bio, et synthétique) | C86: 32.923332 | D86: 0 | E86: 0 | F86: =D86-C86 -> -32.923332 | AA86: Ammoniac hydrogene | AD86: Charbon | AE86: Coke | AF86: Produits pétroliers raffinés | AG86: Gaz naturel | AH86: Biomasse solide | AI86: Déchets | AJ86: Biocarburants | AK86: Gaz renouvelable | AL86: Chaleur de l'environnement | AM86: Solaire thermique et géothermie | AN86: Électricité | AO86: Electricité PAC | AP86: Chaleur vendue | AQ86: Hydrogène | AR86: 0 | AT86: Charbon | AU86: Coke | AV86: Produits pétroliers raffinés | AW86: Gaz naturel | AX86: Biomasse solide | AY86: Déchets | AZ86: Biocarburants | BA86: Gaz renouvelable | BB86: Chaleur de l'environnement | BC86: Solaire thermique et géothermie | BD86: Électricité | BE86: Electricité PAC | BF86: Chaleur vendue | BG86: Hydrogène | BI86: =AT86=AD86 -> TRUE | BJ86: =AU86=AE86 -> TRUE | BK86: =AV86=AF86 -> TRUE | BL86: =AW86=AG86 -> TRUE | BM86: =AX86=AH86 -> TRUE | BN86: =AY86=AI86 -> TRUE | BO86: =AZ86=AJ86 -> TRUE | BP86: =BA86=AK86 -> TRUE | ... BV86: =BG86=AQ86 -> TRUE
B87: Gaz de réseau | C87: 855.74225 | D87: 742.64325 | E87: 1483.1713 | F87: =D87-C87 -> -113.099 | AA87: Ammoniac hydrogene | AB87: 2021 | AC87: % | AD87: 0 | AE87: 0 | AF87: 0 | AG87: 0 | AH87: 0 | AI87: 0 | AJ87: 0 | AK87: 0 | AL87: 0 | AM87: 0 | AN87: 1 | AO87: 0 | AP87: 0 | AQ87: 0 | AR87: 1 | AT87: 0 | AU87: 0 | AV87: 0 | AW87: 0 | AX87: 0 | AY87: 0 | AZ87: 0 | BA87: 0 | BB87: 0 | BC87: 0 | BD87: 1 | BE87: 0 | BF87: 0 | BG87: 0 | BI87: =AT87=AD87 -> TRUE | BJ87: =AU87=AE87 -> TRUE | BK87: =AV87=AF87 -> TRUE | BL87: =AW87=AG87 -> TRUE | BM87: =AX87=AH87 -> TRUE | BN87: =AY87=AI87 -> TRUE | BO87: =AZ87=AJ87 -> TRUE | BP87: =BA87=AK87 -> TRUE | ... BV87: =BG87=AQ87 -> TRUE
B88: Hydrogène | D88: 0 | E88: 0 | F88: =D88-C88 -> 0 | J88: run 2 - ajusté | K88: run 2 - central | AA88: Ammoniac hydrogene | AB88: 2030 | AC88: % | AD88: 0 | AE88: 0 | AF88: 0 | AG88: 0 | AH88: 0 | AI88: 0 | AJ88: 0 | AK88: 0 | AL88: 0 | AM88: 0 | AN88: 1 | AO88: 0 | AP88: 0 | AQ88: 0 | AR88: 1 | AT88: 0 | AU88: 0 | AV88: 0 | AW88: 0 | AX88: 0 | AY88: 0 | AZ88: 0 | BA88: 0 | BB88: 0 | BC88: 0 | BD88: 1 | BE88: 0 | BF88: 0 | BG88: 0 | BI88: =AT88=AD88 -> TRUE | BJ88: =AU88=AE88 -> TRUE | BK88: =AV88=AF88 -> TRUE | BL88: =AW88=AG88 -> TRUE | BM88: =AX88=AH88 -> TRUE | BN88: =AY88=AI88 -> TRUE | BO88: =AZ88=AJ88 -> TRUE | BP88: =BA88=AK88 -> TRUE | ... BV88: =BG88=AQ88 -> TRUE
B89: Biomasse | C89: 0 | D89: 0 | E89: 0 | F89: =D89-C89 -> 0 | I89: Consommation gaz naturel | J89: =D55+D23+D71+D138+D155+D172+D189+D206+D223+D242+D260+D278+D296+D314+D331 -> 50778.693 | K89: 75924 | AA89: Ammoniac hydrogene | AB89: 2050 | AC89: % | AD89: 0 | AE89: 0 | AF89: 0 | AG89: 0 | AH89: 0 | AI89: 0 | AJ89: 0 | AK89: 0 | AL89: 0 | AM89: 0 | AN89: 1 | AO89: 0 | AP89: 0 | AQ89: 0 | AR89: 1 | AT89: 0 | AU89: 0 | AV89: 0 | AW89: 0 | AX89: 0 | AY89: 0 | AZ89: 0 | BA89: 0 | BB89: 0 | BC89: 0 | BD89: 1 | BE89: 0 | BF89: 0 | BG89: 0 | BI89: =AT89=AD89 -> TRUE | BJ89: =AU89=AE89 -> TRUE | BK89: =AV89=AF89 -> TRUE | BL89: =AW89=AG89 -> TRUE | BM89: =AX89=AH89 -> TRUE | BN89: =AY89=AI89 -> TRUE | BO89: =AZ89=AJ89 -> TRUE | BP89: =BA89=AK89 -> TRUE | ... BV89: =BG89=AQ89 -> TRUE
B90: Dechets | C90: 0 | D90: 0 | E90: 0 | F90: =D90-C90 -> 0 | I90: Différence | J90: =J89-K89 -> -25145.307
B91: Charbon | C91: 0 | D91: 0 | E91: 0 | F91: =D91-C91 -> 0 | I91: FE | J91: 0.205 | K91: =J90*J91/1000 -> -5.154788 | L91: MtCO2eq
B92: Coke | C92: 0 | D92: 0 | E92: 0 | F92: =D92-C92 -> 0 | Z92: Mix run 2 ajusté
B93: Chaleur | C93: 0 | D93: 0 | E93: 0 | F93: =D93-C93 -> 0
B94: Solar & Geothermie | C94: 0 | D94: 0 | E94: 0 | F94: =D94-C94 -> 0
B95: Chaleur Env | C95: 0 | D95: 0 | E95: 0 | F95: =D95-C95 -> 0
B96: Biogaz autoconsommé | C96: 0 | D96: 131.05469 | E96: 261.73611 | F96: =D96-C96 -> 131.05469 | G96: l'impact de l'EE semble trop fort | AA96: Mix énergétique | AD96: Charbon | AE96: Coke | AF96: Produits pétroliers raffinés | AG96: Gaz de réseau | AH96: Biomasse solide | AI96: Déchets | AJ96: Biocarburants | AK96: Gaz renouvelable | AL96: Chaleur de l'environnement | AM96: Solaire thermique et géothermie | AN96: Électricité | AO96: Electricité PAC | AP96: Chaleur vendue | AQ96: Hydrogène (consommation finale) | AR96: Total
B97: Total | C97: 1337.2955 | D97: =SUM(D85:D96) -> 873.69794 | E97: =SUM(E85:E96) -> 1744.9074 | F97: =D97-C97 -> -463.59759 | AA97: Métaux primaires
AA98: Dont sidérurgie (hauts fourneaux) | AB98: 2021 | AC98: % | AD98: 0.59926162 | AE98: 0.40073838 | AF98: 0 | AG98: 0 | AH98: 0 | AI98: 0 | AJ98: 0 | AK98: 0 | AL98: 0 | AM98: 0 | AN98: 0 | AO98: 0 | AP98: 0 | AQ98: 0 | AR98: 1 | AT98: 0.59926162 | AU98: 0.40073838 | AV98: 0 | AW98: 0 | AX98: 0 | AY98: 0 | AZ98: 0 | BA98: 0 | BB98: 0 | BC98: 0 | BD98: 0 | BE98: 0 | BF98: 0 | BG98: 0 | BI98: =AT98=AD98 -> TRUE | BJ98: =AU98=AE98 -> TRUE | BK98: =AV98=AF98 -> TRUE | BL98: =AW98=AG98 -> TRUE | BM98: =AX98=AH98 -> TRUE | BN98: =AY98=AI98 -> TRUE | BO98: =AZ98=AJ98 -> TRUE | BP98: =BA98=AK98 -> TRUE | ... BV98: =BG98=AQ98 -> TRUE
AA99: Dont sidérurgie (hauts fourneaux) | AB99: 2030 | AC99: % | AD99: 0.4082048 | AE99: 0.5917952 | AF99: 0 | AG99: 0 | AH99: 0.015 | AI99: 0 | AJ99: 0 | AK99: 0 | AL99: 0 | AM99: 0 | AN99: 0 | AO99: 0 | AP99: 0 | AQ99: 0 | AR99: 1 | AT99: 0.4082048 | AU99: 0.5917952 | AV99: 0 | AW99: 0 | AX99: 0.015 | AY99: 0 | AZ99: 0 | BA99: 0 | BB99: 0 | BC99: 0 | BD99: 0 | BE99: 0 | BF99: 0 | BG99: 0 | BI99: =AT99=AD99 -> TRUE | BJ99: =AU99=AE99 -> TRUE | BK99: =AV99=AF99 -> TRUE | BL99: =AW99=AG99 -> TRUE | BM99: =AX99=AH99 -> TRUE | BN99: =AY99=AI99 -> TRUE | BO99: =AZ99=AJ99 -> TRUE | BP99: =BA99=AK99 -> TRUE | ... BV99: =BG99=AQ99 -> TRUE
B100: Ammoniac gas | C100: 2021 | D100: 2030 | E100: 2030 | F100: Hausse | AA100: Dont sidérurgie (hauts fourneaux) | AB100: 2050 | AC100: % | AD100: 0.33394679 | AE100: 0.49605321 | AF100: 0 | AG100: 0 | AH100: 0.05 | AI100: 0.12 | AJ100: 0 | AK100: 0 | AL100: 0 | AM100: 0 | AN100: 0 | AO100: 0 | AP100: 0 | AQ100: 0 | AR100: 1 | AT100: 0.33394679 | AU100: 0.49605321 | AV100: 0 | AW100: 0 | AX100: 0.05 | AY100: 0.12 | AZ100: 0 | BA100: 0 | BB100: 0 | BC100: 0 | BD100: 0 | BE100: 0 | BF100: 0 | BG100: 0 | BI100: =AT100=AD100 -> TRUE | BJ100: =AU100=AE100 -> TRUE | BK100: =AV100=AF100 -> TRUE | BL100: =AW100=AG100 -> TRUE | BM100: =AX100=AH100 -> TRUE | BN100: =AY100=AI100 -> TRUE | BO100: =AZ100=AJ100 -> TRUE | BP100: =BA100=AK100 -> TRUE | ... BV100: =BG100=AQ100 -> TRUE
...

Sheet Diffus
B1: Cadrage AMS run 2 | C1: 2019 | D1: 2020 | E1: 2021 | F1: 2025 | G1: 2030 | H1: 2035 | I1: 2040 | J1: 2045 | K1: 2050
B2: industrie (hors correction) | C2: 260.68485 | D2: 235.28544 | E2: 244.90887 | F2: 247.64108 | G2: 260.18351 | H2: 275.00144 | I2: 294.71462 | J2: 319.32509 | K2: 345.78526
B3: dont sidérurgie | C3: 3.4365522 | D3: 2.7321756 | E3: 5.2177233 | F3: 5.2481932 | G3: 5.3741724 | H3: 5.441197 | I3: 5.7309247 | J3: 6.1596607 | K3: 6.6449343
B4: dont métaux non-ferreux | C4: 2.2910348 | D4: 1.8214504 | E4: 3.4784822 | F4: 3.750326 | G4: 4.0122333 | H4: 3.9761485 | I4: 4.1714048 | J4: 4.464064 | K4: 4.7914431
B5: dont chimie | C5: 52.462654 | D5: 51.129802 | E5: 53.025615 | F5: 53.554882 | G5: 56.623341 | H5: 57.755283 | I5: 61.726253 | J5: 66.70407 | K5: 71.933909
B6: dont minéraux non-métalliques | C6: 10.005872 | D6: 9.476369 | E6: 9.6003547 | F6: 9.8241243 | G6: 9.9846511 | H6: 10.086062 | I6: 10.429099 | J6: 10.917187 | K6: 11.561558
B7: dont papier pâtes | C7: 5.2611182 | D7: 5.1356951 | E7: 5.1306308 | F7: 5.1887157 | G7: 5.3781099 | H7: 5.5670169 | I7: 5.9113743 | J7: 6.3435855 | K7: 6.8323863
B8: dont IAA | C8: 53.627666 | D8: 54.703848 | E8: 51.664645 | F8: 53.787515 | G8: 57.871473 | H8: 61.635582 | I8: 66.27904 | J8: 71.349193 | K8: 76.7004
B9: dont autres (hors correction) | C9: 173.5554 | D9: 151.84077 | E9: 158.2249 | F9: 155.74388 | G9: 159.15276 | H9: 166.25811 | I9: 175.40217 | J9: 186.93083 | K9: 200.7026
B11: dont construction | C11: 124.11577 | D11: 112.21961 | E11: 123.89472 | F11: 128.10456 | G11: 127.76635 | H11: 126.25407 | I11: 126.69314 | J11: 128.80267 | K11: 133.59533
B14: dont autres correction run 2 | C14: 0 | D14: 0 | E14: 0 | F14: 10 | G14: 20 | H14: 25 | I14: 30 | J14: 35 | K14: 40
B15: autres cadrage | C15: =C9 -> 173.5554 | D15: =D9 -> 151.84077 | E15: =E9 -> 158.2249 | F15: =F9 -> 155.74388 | G15: =G9 -> 159.15276 | H15: =H9 -> 166.25811 | I15: =I9 -> 175.40217 | J15: =J9 -> 186.93083 | K15: =K9 -> 200.7026
B16: autres run 2 | C16: =C15+C14 -> 173.5554 | D16: =D15+D14 -> 151.84077 | E16: =E15+E14 -> 158.2249 | F16: =F15+F14 -> 165.74388 | G16: =G15+G14 -> 179.15276 | H16: =H15+H14 -> 191.25811 | I16: =I15+I14 -> 205.40217 | J16: =J15+J14 -> 221.93083 | K16: =K15+K14 -> 240.7026
D18: Valeur ajoutée brute (Md€) - cf Cadrage | L18: Evolution / 2021 brute | R18: Evolution / 2021 corrigée
C19: Md€2015 | D19: 2020 | E19: 2021 | F19: 2025 | G19: 2030 | H19: 2035 | I19: 2040 | J19: 2045 | K19: 2050 | L19: 2025 | M19: 2030 | N19: 2035 | O19: 2040 | P19: 2045 | Q19: 2050 | R19: 2025 | S19: 2030 | T19: 2035 | U19: 2040 | V19: 2045 | W19: 2050
B20: Métaux primaires | D20: =D4+D3 -> 4.553626 | E20: =E4+E3 -> 8.6962056 | F20: =F4+F3 -> 8.9985192 | G20: =G4+G3 -> 9.3864057 | H20: =H4+H3 -> 9.4173455 | I20: =I4+I3 -> 9.9023295 | J20: =J4+J3 -> 10.623725 | K20: =K4+K3 -> 11.436377 | L20: =F20/$E20 -> 1.0347639 | M20: =G20/$E20 -> 1.079368 | N20: =H20/$E20 -> 1.0829258 | O20: =I20/$E20 -> 1.1386954 | P20: =J20/$E20 -> 1.2216506 | Q20: =K20/$E20 -> 1.3150997 | R20: =L20+0.019 -> 1.0537639 | S20: =M20+0.028 -> 1.107368 | T20: =N20+0.039 -> 1.1219258 | U20: =O20+0.056 -> 1.1946954 | V20: =P20+0.074 -> 1.2956506 | W20: =Q20+0.091 -> 1.4060997
B21: Chimie | D21: =D5 -> 51.129802 | E21: =E5 -> 53.025615 | F21: =F5 -> 53.554882 | G21: =G5 -> 56.623341 | H21: =H5 -> 57.755283 | I21: =I5 -> 61.726253 | J21: =J5 -> 66.70407 | K21: =K5 -> 71.933909 | L21: =F21/$E21 -> 1.0099813 | M21: =G21/$E21 -> 1.0678488 | N21: =H21/$E21 -> 1.0891959 | O21: =I21/$E21 -> 1.1640837 | P21: =J21/$E21 -> 1.2579594 | Q21: =K21/$E21 -> 1.3565879 | R21: =L21+0.019 -> 1.0289813 | S21: =M21+0.028 -> 1.0958488 | T21: =N21+0.039 -> 1.1281959 | U21: =O21+0.056 -> 1.2200837 | V21: =P21+0.074 -> 1.3319594 | W21: =Q21+0.091 -> 1.4475879
B22: Minéraux non-métalliques | D22: =D6 -> 9.476369 | E22: =E6 -> 9.6003547 | F22: =F6 -> 9.8241243 | G22: =G6 -> 9.9846511 | H22: =H6 -> 10.086062 | I22: =I6 -> 10.429099 | J22: =J6 -> 10.917187 | K22: =K6 -> 11.561558 | L22: =F22/$E22 -> 1.0233085 | M22: =G22/$E22 -> 1.0400294 | N22: =H22/$E22 -> 1.0505927 | O22: =I22/$E22 -> 1.0863244 | P22: =J22/$E22 -> 1.1371649 | Q22: =K22/$E22 -> 1.2042844 | R22: =L22+0.019 -> 1.0423085 | S22: =M22+0.028 -> 1.0680294 | T22: =N22+0.039 -> 1.0895927 | U22: =O22+0.056 -> 1.1423244 | V22: =P22+0.074 -> 1.2111649 | W22: =Q22+0.091 -> 1.2952844
B23: IAA | D23: =D8 -> 54.703848 | E23: =E8 -> 51.664645 | F23: =F8 -> 53.787515 | G23: =G8 -> 57.871473 | H23: =H8 -> 61.635582 | I23: =I8 -> 66.27904 | J23: =J8 -> 71.349193 | K23: =K8 -> 76.7004 | L23: =F23/$E23 -> 1.0410894 | M23: =G23/$E23 -> 1.1201369 | N23: =H23/$E23 -> 1.1929934 | O23: =I23/$E23 -> 1.2828703 | P23: =J23/$E23 -> 1.3810062 | Q23: =K23/$E23 -> 1.484582 | R23: =L23+0.019 -> 1.0600894 | S23: =M23+0.028 -> 1.1481369 | T23: =N23+0.039 -> 1.2319934 | U23: =O23+0.056 -> 1.3388703 | V23: =P23+0.074 -> 1.4550062 | W23: =Q23+0.091 -> 1.575582
B24: Autres | D24: =D16 -> 151.84077 | E24: =E16 -> 158.2249 | F24: =F16 -> 165.74388 | G24: =G16 -> 179.15276 | H24: =H16 -> 191.25811 | I24: =I16 -> 205.40217 | J24: =J16 -> 221.93083 | K24: =K16 -> 240.7026 | L24: =F24/$E24 -> 1.0475208 | M24: =G24/$E24 -> 1.1322665 | N24: =H24/$E24 -> 1.2087738 | O24: =I24/$E24 -> 1.2981659 | P24: =J24/$E24 -> 1.402629 | Q24: =K24/$E24 -> 1.5212687 | R24: =L24+0.019 -> 1.0665208 | S24: =M24+0.028 -> 1.1602665 | T24: =N24+0.039 -> 1.2477738 | U24: =O24+0.056 -> 1.3541659 | V24: =P24+0.074 -> 1.476629 | W24: =Q24+0.091 -> 1.6122687
B25: Total industrie | D25: =SUM(D20:D24) -> 271.70442 | E25: =SUM(E20:E24) -> 281.21172 | F25: =SUM(F20:F24) -> 291.90892 | G25: =SUM(G20:G24) -> 313.01863 | H25: =SUM(H20:H24) -> 330.15238 | I25: =SUM(I20:I24) -> 353.73889 | J25: =SUM(J20:J24) -> 381.52501 | K25: =SUM(K20:K24) -> 412.33484
B26: Construction | D26: =D11 -> 112.21961 | E26: =E11 -> 123.89472 | F26: =F11 -> 128.10456 | G26: =G11 -> 127.76635 | H26: =H11 -> 126.25407 | I26: =I11 -> 126.69314 | J26: =J11 -> 128.80267 | K26: =K11 -> 133.59533 | L26: =F26/$E26 -> 1.0339792 | M26: =G26/$E26 -> 1.0312494 | N26: =H26/$E26 -> 1.0190432 | O26: =I26/$E26 -> 1.0225871 | P26: =J26/$E26 -> 1.0396139 | Q26: =K26/$E26 -> 1.0782972
B29: Md€2015 | C29: 2019 | D29: 2020 | E29: 2021 | F29: 2025 | G29: 2030 | H29: 2035 | I29: 2040 | J29: 2045 | K29: 2050
B30: Métaux primaires | C30: 25.805 | D30: 22.829 | E30: 24.457 | F30: =$E30*R20 -> 25.771903 | G30: =$E30*S20 -> 27.082898 | H30: =$E30*T20 -> 27.438939 | I30: =$E30*U20 -> 29.218666 | J30: =$E30*V20 -> 31.687727 | K30: =$E30*W20 -> 34.388981
B31: Chimie | C31: 47.175 | D31: 45.889 | E31: 46.328 | F31: =$E31*R21 -> 47.670648 | G31: =$E31*S21 -> 50.768485 | H31: =$E31*T21 -> 52.267061 | I31: =$E31*U21 -> 56.524037 | J31: =$E31*V21 -> 61.707015 | K31: =$E31*W21 -> 67.063853
B32: Minéraux non-métalliques | C32: 8.359 | D32: 7.464 | E32: 8.172 | F32: =$E32*R22 -> 8.5177449 | G32: =$E32*S22 -> 8.7279363 | H32: =$E32*T22 -> 8.9041513 | I32: =$E32*U22 -> 9.3350748 | J32: =$E32*V22 -> 9.8976398 | K32: =$E32*W22 -> 10.585064
B33: IAA | C33: 45.598 | D33: 44.089 | E33: 44.859 | F33: =$E33*R23 -> 47.554551 | G33: =$E33*S23 -> 51.504271 | H33: =$E33*T23 -> 55.265993 | I33: =$E33*U23 -> 60.060384 | J33: =$E33*V23 -> 65.270121 | K33: =$E33*W23 -> 70.679032
B34: Equipements | C34: 63.615 | D34: 49.807 | E34: 52.09 | F34: =$E34*R24 -> 55.555071 | G34: =$E34*S24 -> 60.438283 | H34: =$E34*T24 -> 64.996535 | I34: =$E34*U24 -> 70.538499 | J34: =$E34*V24 -> 76.917603 | K34: =$E34*W24 -> 83.983077
B35: Autres (textile, etc.) | C35: 23.724 | D35: 22.258 | E35: 23.781 | F35: =$E35*R24 -> 25.362932 | G35: =$E35*S24 -> 27.592298 | H35: =$E35*T24 -> 29.673308 | I35: =$E35*U24 -> 32.203418 | J35: =$E35*V24 -> 35.115713 | K35: =$E35*W24 -> 38.341362
B36: Total diffus hors construction | C36: 214.276 | D36: 192.336 | E36: 199.687 | F36: =SUM(F30:F35) -> 210.43285 | G36: =SUM(G30:G35) -> 226.11417 | H36: =SUM(H30:H35) -> 238.54599 | I36: =SUM(I30:I35) -> 257.88008 | J36: =SUM(J30:J35) -> 280.59582 | K36: =SUM(K30:K35) -> 305.04137
B37: Construction | C37: 114.882 | D37: 101.443 | E37: 108.227 | F37: =$E37*L26 -> 111.90446 | G37: =$E37*M26 -> 111.60903 | H37: =$E37*N26 -> 110.28798 | I37: =$E37*O26 -> 110.67153 | J37: =$E37*P26 -> 112.51429 | K37: =$E37*Q26 -> 116.70087

Sheet EE AMS run 2
L1: Calcul à partir du ratio énergie/production
C2: AMS run 2
B3: %/2021 | D3: AME 23 | N3: S2 Ademe | P3: S3 Ademe
D4: 2025 | E4: 2030 | F4: 2040 | G4: 2050 | N4: 2030 | O4: 2050 | P4: 2030 | Q4: 2050
B5: Métaux primaires | L5: Secteur ADEME
B6: Dont sidérurgie (hauts fourneaux) | D6: 0.98 | E6: 0.9 | F6: 0 | G6: 0.7 | H6: ADEME S3 | I6: ~Cohérent 50sites (76% pour toute la sidérurgie en 2050, 82% en 2030 | L6: dont hauts fourneaux * | N6: / | O6: / | P6: 0.91332715 | Q6: 0.6883209
B7: Dont sidérurgie (arc électrique) | D7: 0.98 | E7: 0.95 | F7: 0 | G7: 0.9 | H7: ADEME S2/S3 | L7: dont aciérie électrique (EAF) * | N7: 0.94483144 | O7: 0.90539175 | P7: 0.95666387 | Q7: 0.93693348
B8: Dont sidérurgie (réduction directe) | D8: 1 | E8: 0.95 | F8: 0 | G8: 0.9 | H8: Identique EAF | L8: dont DRI-EAF *
B9: Autre sidérurgie | D9: 1 | E9: 0.95 | F9: 0 | G9: 0.9 | H9: Identique EAF
B10: Dont aluminium primaire | D10: 0.98 | E10: 0.95 | F10: 0 | G10: 0.8 | H10: Tentative d’alignement avec l’ADEME | I10: Ajustement 50sites | L10: dont aluminium * | N10: 0.78469454 | O10: 0.44811455 | P10: 0.92518971 | Q10: 0.85869097
B11: Dont aluminium recyclé | D11: 0.95 | E11: 0.75 | F11: 0 | G11: 0.75 | H11: Tentative d’alignement avec l’ADEME | I11: Ajustement 50sites
B12: Dont autres métaux primaires | D12: 0.98 | E12: 0.95 | F12: 0 | G12: 0.9 | H12: Reprise acier/alu primaire | L12: Métaux non ferreux | N12: 1.0021292 | O12: 0.64012062 | P12: 1.0960055 | Q12: 1.0758914
B13: Chimie | D13: 0 | E13: 0 | F13: 0 | G13: 0
B14: Dont Ammoniac | D14: 0.95 | E14: 0.92 | F14: 0 | G14: 1 | H14: ADEME S2/S3 | I14: Ajustement 50sites (perte EE du fait du passage à l'H2) | L14: dont ammoniac * | N14: 0.73576299 | O14: 0.71200386 | P14: 0.73832803 | Q14: 0.71794869
B15: Dont pétrochimie de base | D15: 0.98 | E15: 0.95 | F15: 0 | G15: 0.87 | H15: ADEME S2/S3 | I15: Ajustement 50sites | L15: Chimie organique | N15: 0.9583518 | O15: 0.90754207 | P15: 0.88775029 | Q15: 0.70941642
B16: Dont autres chimies | D16: 0.95 | E16: 0.91 | F16: 0 | G16: 0.81 | H16: ADEME S3 | L16: Chimie minérale | N16: 0.93182592 | O16: 0.86133876 | P16: 0.91063309 | Q16: 0.80554219
B17: Non-métalliques | D17: 0 | E17: 0 | F17: 0 | G17: 0
B18: Dont clinker | D18: 0.97 | E18: 0.93 | F18: 0 | G18: 0.86 | H18: ADEME S2/S3 | L18: Ciment, chaux * | N18: 0.92646664 | O18: 0.83507565 | P18: 0.93921393 | Q18: 0.89399409
B19: Dont verre | D19: 0.93 | E19: 0.86 | F19: 0 | G19: 0.75 | H19: ADEME S2/S3 (prend en compte les gains du recyclage) | L19: Verre * | N19: 0.88605352 | O19: 0.72794278 | P19: 0.83604427 | Q19: 0.64009664
B20: Dont autres non-métalliques | D20: 0.955 | E20: 0.91 | F20: 0 | G20: 0.8 | H20: ADEME S3 | L20: Matériaux de construction | N20: 0.96532754 | O20: 0.95644669 | P20: 0.90467101 | Q20: 0.79108186
B21: Industrie agroalimentaire | D21: 0 | E21: 0 | F21: 0 | G21: 0
B22: Dont sucre | D22: 0.94 | E22: 0.86 | F22: 0 | G22: 0.64 | H22: ADEME S3 | L22: Sucre * | N22: 0.93477128 | O22: 0.87881339 | P22: 0.86532322 | Q22: 0.70728093
B23: Dont autres Industries alimentaires et agricoles | D23: 0.93 | E23: 0.86 | F23: 0 | G23: 0.73 | H23: ADEME S2/S3 | L23: Autres agro alimentaire | N23: 0.90009674 | O23: 0.76845064 | P23: 0.87339443 | Q23: 0.71363019
B24: Equipement | D24: 0.94 | E24: 0.88 | F24: 0 | G24: 0.74 | H24: ADEME S2/S3 | L24: Transports terrestres | N24: 0.87734261 | O24: 0.72604683 | P24: 0.88569269 | Q24: 0.74927517
B25: Construction | D25: 0.95 | E25: 0.87 | F25: 0 | G25: 0.71 | H25: Gains calculées via FdR301 (en reprenant les gains PL), divisé par deux par conservatisme | L25: Matériaux de construction | N25: 0.96532754 | O25: 0.95644669 | P25: 0.90467101 | Q25: 0.79108186
B26: Autres | D26: 0 | E26: 0 | F26: 0 | G26: 0
B27: Dont papier-pâtes | D27: 0.94 | E27: 0.88 | F27: 0 | G27: 0.74 | H27: ADEME, en prenant en compte le recyclage | L27: Papiers-cartons (blanchiment) * | N27: 0.87734261 | O27: 0.72604683 | P27: 0.88569269 | Q27: 0.74927517
B28: Dont autres | D28: 0.925 | E28: 0.88 | F28: 0 | G28: 0.74 | H28: Reprise équipements

Sheet 4. Recyclage
P4: =700*0.45 -> 315
B7: Taux d'incorporation matières premières recyclées
B9: Taux d'incorporation | C9: Historique (BNR ADEME 2019) | J9: AME 2023 | P9: AMS run 3 | Z9: AME 2021 | AB9: AMS 2018 | AE9: ADEME | AL9: RTE
C10: 2010 | D10: 2015 | E10: 2016 | F10: 2017 | G10: 2018 | H10: 2019 | I10: 2021 | J10: 2025 | K10: 2030 | L10: 2035 | M10: 2040 | N10: 2045 | O10: 2050 | P10: 2025 | Q10: 2030 | R10: 2035 | S10: 2040 | T10: 2045 | U10: 2050 | V10: commentaire historique | W10: commentaire AME | X10: commentaire AMS | Z10: 2030 | AA10: 2050 | AB10: 2030 | AC10: 2050 | AF10: TEND | AG10: S1 | AH10: S2 | AI10: S3 | AJ10: S4 | AM10: REF
B11: Métaux primaires | C11: 0 | W11: Impact prix du C : +0,5pt tous les 5 ans | AE11: Acier | AF11: 0.43 | AG11: 0.51 | AH11: 0.7 | AI11: 0.44 | AJ11: 0.4 | AL11: Acier | AM11: 0.8
A12: MàJ 50sites | B12: Dont sidérurgie | D12: 0.44389662 | E12: 0.44251903 | F12: 0.42223077 | G12: 0.42368932 | H12: =Récap!D258 -> 0.41677862 | I12: =Récap!E258 -> 0.43 | J12: 0.44338931 | K12: 0.47 | L12: 0.475 | M12: 0.48 | N12: 0.485 | O12: 0.49 | P12: =Récap!F258 -> 0.48 | Q12: =Récap!G258 -> 0.54 | R12: =Récap!H258 -> 0.57 | S12: =Récap!I258 -> 0.57 | T12: =Récap!J258 -> 0.6 | U12: =Récap!K258 -> 0.6 | V12: Repris du CITEPA | W12: hausse à 2030 puis constant | X12: Niveau 2050 AMS18 revu à la baisse / AMS18 (ADEMe autour de 45 % sauf S2 à 70%), niveau 2030 revu en accord avec les données Arcelor-Mittal/FR relance | Z12: 0.36 | AA12: 0.36 | AB12: 0.48 | AC12: 0.8 | AE12: Aluminium | AF12: 0.55 | AG12: 0.75 | AH12: 0.85 | AI12: 0.55 | AJ12: 0.45 | AL12: Aluminium | AM12: 0.7
A13: MàJ 50sites | B13: Dont aluminium | C13: 0.55944846 | D13: 0.52855543 | E13: 0.53159041 | F13: 0.53927813 | G13: 0.56492027 | H13: =Récap!D259 -> 0.50638298 | I13: =Récap!E259 -> 0.5 | J13: 0.53743848 | K13: 0.54243848 | L13: 0.54993848 | M13: 0.55743848 | N13: 0.56493848 | O13: 0.57243848 | P13: =Récap!F259 -> 0.56621924 | Q13: =Récap!G259 -> 0.6 | R13: =Récap!H259 -> 0.625 | S13: =Récap!I259 -> 0.65 | T13: =Récap!J259 -> 0.675 | U13: =Récap!K259 -> 0.7 | V13: taux de l’aluminium issu de l’affinage et du recyclage direct | W13: stable | X13: reprise AMS/ ademe S1/S2 | Z13: 0.46571429 | AA13: 0.62 | AB13: 0.55 | AC13: 0.8 | AE13: Verre | AF13: 0.52 | AG13: 0.85 | AH13: 0.85 | AI13: 0.65 | AJ13: 0.52 | AL13: Verre | AM13: 0.8
B14: Dont autres métaux primaires | H14: =Récap!D260 -> 0 | I14: =Récap!E260 -> 0 | P14: =Récap!F260 -> 0 | Q14: =Récap!G260 -> 0 | R14: =Récap!H260 -> 0 | S14: =Récap!I260 -> 0 | T14: =Récap!J260 -> 0 | U14: =Récap!K260 -> 0 | Z14: 0 | AA14: 0 | AB14: 0 | AC14: 0 | AE14: Papier | AF14: 0.73 | AG14: 0.85 | AH14: 0.95 | AI14: 0.85 | AJ14: 0.73 | AL14: Papier | AM14: 0.87
B15: Chimie | C15: 0 | H15: =Récap!D261 -> 0 | I15: =Récap!E261 -> 0 | Z15: 0 | AA15: 0 | AB15: 0 | AC15: 0 | AE15: Plastiques | AF15: 0.058693594 | AG15: 0.8 | AH15: 0.8 | AI15: 0.4 | AJ15: 0.058693594 | AL15: Plastiques | AM15: 0.35
B16: Dont Ammoniac | H16: =Récap!D262 -> 0 | I16: =Récap!E262 -> 0 | P16: =Récap!F262 -> 0 | Q16: =Récap!G262 -> 0 | R16: =Récap!H262 -> 0 | S16: =Récap!I262 -> 0 | T16: =Récap!J262 -> 0 | U16: =Récap!K262 -> 0 | Z16: 0 | AA16: 0 | AB16: 0 | AC16: 0
A17: MàJ 50sites | B17: Dont pétrochimie de base | C17: N.R | D17: N.R | E17: N.R | F17: N.R | G17: N.R | H17: =Récap!D263 -> 0.145 | I17: =Récap!E263 -> 0.14 | J17: 0.2225 | K17: 0.3 | L17: 0.3075 | M17: 0.315 | N17: 0.3225 | O17: 0.33 | P17: =Récap!F263 -> 0.2475 | Q17: =Récap!G263 -> 0.35 | R17: =Récap!H263 -> 0.35 | S17: =Récap!I263 -> 0.35 | T17: =Récap!J263 -> 0.35 | U17: =Récap!K263 -> 0.35 | V17: emballages uniquement – volume incorporé 2018 / volume de résines consommées 2019 – attention donnée peu fiable | W17: Effet plan de relance : +700kt de plastique recyclé incorporé dont 45 % sont des emballages | X17: reprise AMS/ ademe S1/S2 | Z17: 0 | AA17: 0 | AB17: 0.3 | AC17: 0.8
B18: Dont autres chimies | H18: =Récap!D264 -> 0 | I18: =Récap!E264 -> 0 | P18: =Récap!F264 -> 0 | Q18: =Récap!G264 -> 0 | R18: =Récap!H264 -> 0 | S18: =Récap!I264 -> 0 | T18: =Récap!J264 -> 0 | U18: =Récap!K264 -> 0 | Z18: 0 | AA18: 0 | AB18: 0 | AC18: 0 | AE18: NW
B19: Non-métalliques | C19: 0 | H19: =Récap!D265 -> 0 | I19: =Récap!E265 -> 0 | Z19: 0 | AA19: 0 | AB19: 0 | AC19: 0 | AE19: TAUX MPR BAU AME | AF19: 2015 | AG19: 2020 | AH19: 2025 | AI19: 2030 | AJ19: 2035 | AK19: 2040 | AL19: 2045 | AM19: 2050
B20: Dont ciment | H20: =Récap!D266 -> 0 | I20: =Récap!E266 -> 0 | P20: =Récap!F266 -> 0 | Q20: =Récap!G266 -> 0 | R20: =Récap!H266 -> 0 | S20: =Récap!I266 -> 0 | T20: =Récap!J266 -> 0 | U20: =Récap!K266 -> 0 | Z20: 0 | AA20: 0 | AB20: 0 | AC20: 0 | AE20: Acier (%EAF/(EAF+BOF) | AF20: 0.33270114 | AG20: 0.33270114 | AH20: 0.33270114 | AI20: 0.33270114 | AJ20: 0.33270114 | AK20: 0.33270114 | AL20: 0.33270114 | AM20: 0.33270114
B21: Dont verre | C21: 0.58040244 | D21: 0.6096732 | E21: 0.64116379 | F21: 0.60014764 | G21: 0.59520958 | H21: =Récap!D267 -> 0.60669056 | I21: =Récap!E267 -> 0.63 | J21: 0.61169056 | K21: 0.61669056 | L21: 0.62419056 | M21: 0.63169056 | N21: 0.63919056 | O21: 0.64669056 | P21: =Récap!F267 -> 0.68834528 | Q21: =Récap!G267 -> 0.77 | R21: =Récap!H267 -> 0.79 | S21: =Récap!I267 -> 0.81 | T21: =Récap!J267 -> 0.83 | U21: =Récap!K267 -> 0.85 | V21: taux d’incorporation de calcin par les verriers | W21: stable | X21: reprise AMS/ ademe S1/S2 | Z21: 0.65 | AA21: 0.65 | AB21: 0.77 | AC21: 0.85 | AE21: Aluminium | AF21: 0.55146126 | AG21: 0.55146126 | AH21: 0.55146126 | AI21: 0.55146126 | AJ21: 0.55146126 | AK21: 0.55146126 | AL21: 0.55146126 | AM21: 0.55146126
B22: Dont autres non-métalliques | H22: =Récap!D268 -> 0 | I22: =Récap!E268 -> 0 | P22: =Récap!F268 -> 0 | Q22: =Récap!G268 -> 0 | R22: =Récap!H268 -> 0 | S22: =Récap!I268 -> 0 | T22: =Récap!J268 -> 0 | U22: =Récap!K268 -> 0 | Z22: 0 | AA22: 0 | AB22: 0 | AC22: 0 | AE22: Plastiques | AF22: 0.057066664 | AG22: 0.058536353 | AH22: 0.058798904 | AI22: 0.0585728 | AJ22: 0.058933694 | AK22: 0.059581339 | AL22: 0.059854466 | AM22: 0.059739647
B23: Industrie agroalimentaire | C23: 0 | H23: =Récap!D269 -> 0 | I23: =Récap!E269 -> 0 | Z23: 0 | AA23: 0 | AB23: 0 | AC23: 0 | AE23: Verre | AF23: 0.52685211 | AG23: 0.53259415 | AH23: 0.53320913 | AI23: 0.53259546 | AJ23: 0.53316252 | AK23: 0.53425086 | AL23: 0.53598297 | AM23: 0.53663799
B24: Dont sucre | H24: =Récap!D270 -> 0 | I24: =Récap!E270 -> 0 | P24: =Récap!F270 -> 0 | Q24: =Récap!G270 -> 0 | R24: =Récap!H270 -> 0 | S24: =Récap!I270 -> 0 | T24: =Récap!J270 -> 0 | U24: =Récap!K270 -> 0 | Z24: 0 | AA24: 0 | AB24: 0 | AC24: 0 | AE24: Papier | AF24: 0.72548371 | AG24: 0.72548371 | AH24: 0.72548371 | AI24: 0.72548371 | AJ24: 0.72548371 | AK24: 0.72548371 | AL24: 0.72548371 | AM24: 0.72548371
B25: Dont autres Industries agro-alimentaires | H25: =Récap!D271 -> 0 | I25: =Récap!E271 -> 0 | P25: =Récap!F271 -> 0 | Q25: =Récap!G271 -> 0 | R25: =Récap!H271 -> 0 | S25: =Récap!I271 -> 0 | T25: =Récap!J271 -> 0 | U25: =Récap!K271 -> 0 | Z25: 0 | AA25: 0 | AB25: 0 | AC25: 0
B26: Equipement | H26: =Récap!D272 -> 0 | I26: =Récap!E272 -> 0 | P26: =Récap!F272 -> 0 | Q26: =Récap!G272 -> 0 | R26: =Récap!H272 -> 0 | S26: =Récap!I272 -> 0 | T26: =Récap!J272 -> 0 | U26: =Récap!K272 -> 0 | Z26: 0 | AA26: 0 | AB26: 0 | AC26: 0 | AE26: TAUX MPR nW AMS | AF26: 2015 | AG26: 2020 | AH26: 2025 | AI26: 2030 | AJ26: 2035 | AK26: 2040 | AL26: 2045 | AM26: 2050
B27: Construction | H27: =Récap!D273 -> 0 | I27: =Récap!E273 -> 0 | P27: =Récap!F273 -> 0 | Q27: =Récap!G273 -> 0 | R27: =Récap!H273 -> 0 | S27: =Récap!I273 -> 0 | T27: =Récap!J273 -> 0 | U27: =Récap!K273 -> 0 | AE27: Acier (%EAF/(EAF+BOF) | AF27: 0.33270114 | AG27: 0.33270114 | AH27: 0.47564119 | AI27: 0.60127171 | AJ27: 0.58305097 | AK27: 0.60000914 | AL27: 0.61703162 | AM27: 0.636375
B28: Autres | C28: 0 | H28: =Récap!D274 -> 0 | I28: =Récap!E274 -> 0 | Z28: 0 | AA28: 0 | AE28: Aluminium | AF28: 0.55146126 | AG28: 0.55146126 | AH28: 0.65073063 | AI28: 0.73222254 | AJ28: 0.775 | AK28: 0.78406324 | AL28: 0.825 | AM28: 0.85
B29: Dont papier-pâtes | C29: 0.59752203 | D29: 0.66287522 | E29: 0.67060224 | F29: 0.67109968 | G29: 0.68641753 | H29: =Récap!D275 -> 0.71244213 | I29: =Récap!E275 -> 0.71 | J29: 0.73622107 | K29: 0.76 | L29: 0.765 | M29: 0.77 | N29: 0.775 | O29: 0.78 | P29: =Récap!F275 -> 0.74622107 | Q29: =Récap!G275 -> 0.78 | R29: =Récap!H275 -> 0.8025 | S29: =Récap!I275 -> 0.825 | T29: =Récap!J275 -> 0.8475 | U29: =Récap!K275 -> 0.87 | V29: taux d’incorporation de PCR | W29: poursuite de la hausse à 2030 puis constant | X29: Poursuite de la hausse 2015-2019. Reprise ADEME S1/S2/S3 | Z29: 0.66428571 | AA29: 0.75 | AB29: 0.75 | AC29: 0.85 | AD29: Papier - pâtes | AE29: Plastiques | AF29: 0.057060846 | AG29: 0.05833885 | AH29: 0.10607291 | AI29: 0.16787362 | AJ29: 0.2179487 | AK29: 0.27113888 | AL29: 0.34396394 | AM29: 0.44322455
B30: Dont autres | H30: =Récap!D276 -> 0 | I30: =Récap!E276 -> 0 | P30: =Récap!F276 -> 0 | Q30: =Récap!G276 -> 0 | R30: =Récap!H276 -> 0 | S30: =Récap!I276 -> 0 | T30: =Récap!J276 -> 0 | U30: =Récap!K276 -> 0 | Z30: 0 | AA30: 0 | AB30: 0 | AC30: 0 | AE30: Verre | AF30: 0.52683488 | AG30: 0.5324758 | AH30: 0.51774814 | AI30: 0.50320799 | AJ30: 0.49111047 | AK30: 0.48509279 | AL30: 0.50931796 | AM30: 0.51666237
AE31: Papier | AF31: 0.72548371 | AG31: 0.72548371 | AH31: 0.72548371 | AI31: 0.72548371 | AJ31: 0.74411278 | AK31: 0.76274186 | AL31: 0.78137093 | AM31: 0.8

Sheet CCUS FdR 50 sites et CSF
A1: FdR 50 sites | B1: Scénario Bas - CCS tonnes captées (MtCO2) - Projets A | I1: FdR - CSF (filières) | L1: CO2 capté anticipé par la filière en MtCO2/an
B2: 2030 | C2: 2035 | D2: 2040 | E2: 2045 | F2: 2050 | G2: Nombre de projets | K2: MtCO2 | L2: 2025 | M2: 2030 | N2: 2035 | O2: 2040 | P2: 2045 | Q2: 2050
A3: Raffinage | B3: 0 | C3: 0 | D3: 0 | E3: 0 | F3: 0 | G3: 0 | J3: Ciment - Ambitieux | Q3: 6.85
A4: Chimie | B4: 0.709265 | C4: 1.23069 | D4: 1.91269 | E4: 2.21269 | F4: 2.21269 | G4: 8 | J4: Ciment - Central | M4: 2.401 | Q4: 5.816
A5: Chimie et raffinage | B5: 0.1 | C5: 0.3 | D5: 0.3 | E5: 0.39999 | F5: 0.39999 | G5: 3 | J5: Ciment - Bas | Q5: 1.965
A6: Acier et fonte | B6: 0 | C6: 0 | D6: 0 | E6: 0 | F6: 0.335 | G6: 1
A7: Aluminium | B7: 0 | C7: 0 | D7: 0 | E7: 0 | F7: 0 | G7: 0 | J7: Chaux | L7: - | M7: - | N7: - | O7: - | P7: - | Q7: -
A8: Ciment | B8: 0 | C8: 0.87 | D8: 0.87 | E8: 0.87 | F8: 0.87 | G8: 1
A9: Chaux | B9: 0 | C9: 0 | D9: 0 | E9: 0 | F9: 0 | G9: 0
A10: Agroalimentaire | B10: 0 | C10: 0 | D10: 0 | E10: 0 | F10: 0 | G10: 0 | J10: Chimie - Ambitieux | M10: 2.5 | Q10: 4.7
J11: Chimie - Central | M11: 1.1 | Q11: 2.8 | S11: CCS évoqué mais pas chiffré spécifiquement
J12: Chimie - Bas | L12: - | M12: - | N12: - | O12: - | P12: - | Q12: -
L14: 2025 | M14: 2030 | N14: 2035 | O14: 2040 | P14: 2045 | Q14: 2050 | S14: Que du CCS, pas de CCU évoqué
J15: Agroalimentaire (ANIA) | L15: - | M15: - | N15: - | O15: - | P15: - | Q15: -
S19: CCS : Potentiel de 500 à 600 kt de CO2 biogénique pour le seul secteur sucre ; également du CO2 biogénique isu de la méthanisation et de la combustion de la biomasse.
J20: Amidon | L20: - | M20: - | N20: - | O20: - | P20: - | Q20: - | S20: CCU : besoin de CO2 biogénique dans l'agroalimentaire, pour un marché estimé de 150 à 200 kt/an.
J21: Lait | L21: - | M21: - | N21: - | O21: - | P21: - | Q21: - | S21: Aucun chiffrage précis, mais potentiel global du secteur estimé > 1MtCO2/an
J22: Sucre | L22: - | M22: - | N22: - | O22: - | P22: - | Q22: - | S22: Les 3 secteurs les plus émetteurs étant l'amidon, le sucre et le lait.
S24: CCS pas évoqué
J25: Papier carton | L25: - | M25: - | N25: - | O25: - | P25: - | Q25: - | S25: CCS pas évoqué
S26: Estimation du potentiel à 700 kt/an, pilotes possibles avant 2030
L27: 2025 | M27: 2030 | N27: 2035 | O27: 2040 | P27: 2045 | Q27: 2050
J28: Tuiles et Briques - Ambitieux | L28: - | M28: - | N28: - | O28: - | P28: - | Q28: 0.3
J29: Tuiles et Briques - Central | L29: - | M29: - | N29: - | O29: - | P29: - | Q29: 0.3 | S29: CCS pas évoqué
J30: Tuiles et Briques - Tendanciel | L30: - | M30: 0.126121 | N30: - | O30: - | P30: - | Q30: -
S32: Potentiel pas chiffré explicitement mais la filière compte sur le CCU et le CCS pour se décarboner.
J33: Verre | L33: - | M33: - | N33: - | O33: - | P33: - | Q33: - | S33: Spécificité : fumées très chargées et polluées. Jusqu'à 300kt/an captées en 2050.
S37: La fiche de décarbonation filière évoque surtout le levier de l'hydrogène ; seule mention est faite à une future étude sur le potentiel du CCS pour cette industrie.
