Workbook

Sheet TER_RENO
A1: Sources | B1: Intro | C1: Rénovation des bâtiments tertiaires | H1: 2015 | I1: 2016 | J1: 2017 | K1: 2018 | L1: 2019 | M1: 2020 | N1: 2021 | O1: 2022 | P1: 2023 | Q1: 2024 | S1: 2015 | T1: 2016 | U1: 2017 | V1: 2018 | W1: 2019 | X1: 2020 | Y1: 2021 | Z1: 2022 | AA1: 2023 | AB1: 2024 | AC1: 2025 | AD1: 2026 | AE1: 2027 | AF1: 2028 | AG1: 2029 | AH1: 2030 | AI1: 2031 | AJ1: 2032 | AK1: 2033 | AL1: 2034 | AM1: 2035 | AN1: 2036 | AO1: 2037 | AP1: 2038 | AQ1: 2039 | AR1: 2040 | AS1: 2041 | AT1: 2042 | AU1: 2043 | AV1: 2044 | AW1: 2045 | AX1: 2046 | AY1: 2047 | AZ1: 2048 | BA1: 2049 | BB1: 2050 | BD1: 2015 | BE1: 2016 | BF1: 2017 | BG1: 2018 | BH1: 2019 | BI1: 2020 | BJ1: 2021 | BK1: 2022 | BL1: 2023 | BM1: 2024 | BN1: 2025 | BO1: 2026 | BP1: 2027 | BQ1: 2028 | BR1: 2029 | BS1: 2030 | BT1: 2031 | BU1: 2032 | BV1: 2033 | BW1: 2034 | BX1: 2035 | BY1: 2036 | BZ1: 2037 | CA1: 2038 | CB1: 2039 | CC1: 2040 | CD1: 2041 | CE1: 2042 | CF1: 2043 | CG1: 2044 | CH1: 2045 | CI1: 2046 | CJ1: 2047 | CK1: 2048 | CL1: 2049 | CM1: 2050 | CO1: 2015 | CP1: 2016 | CQ1: 2017 | CR1: 2018 | CS1: 2019 | CT1: 2020 | CU1: 2021 | CV1: 2022 | CW1: 2023 | CX1: 2024 | CY1: 2025 | CZ1: 2026 | DA1: 2027 | DB1: 2028 | DC1: 2029 | DD1: 2030 | DE1: 2031 | DF1: 2032 | DG1: 2033 | DH1: 2034 | DI1: 2035 | DJ1: 2036 | DK1: 2037 | DL1: 2038 | DM1: 2039 | DN1: 2040 | DO1: 2041 | DP1: 2042 | DQ1: 2043 | DR1: 2044 | DS1: 2045 | DT1: 2046 | DU1: 2047 | DV1: 2048 | DW1: 2049 | DX1: 2050 | DZ1: 2015 | EA1: 2016 | EB1: 2017 | EC1: 2018 | ED1: 2019 | EE1: 2020 | EF1: 2021 | EG1: 2022 | EH1: 2023 | EI1: 2024 | EJ1: 2025 | EK1: 2026 | EL1: 2027 | EM1: 2028 | EN1: 2029 | EO1: 2030 | EP1: 2031 | EQ1: 2032 | ER1: 2033 | ES1: 2034 | ET1: 2035 | EU1: 2036 | EV1: 2037 | EW1: 2038 | EX1: 2039 | EY1: 2040 | EZ1: 2041 | FA1: 2042 | FB1: 2043 | FC1: 2044 | FD1: 2045 | FE1: 2046 | FF1: 2047 | FG1: 2048 | FH1: 2049 | FI1: 2050 | FK1: 2015 | FL1: 2016 | FM1: 2017 | FN1: 2018 | FO1: 2019 | FP1: 2020 | FQ1: 2021 | FR1: 2022 | FS1: 2023 | FT1: 2024 | FU1: 2025 | FV1: 2026 | FW1: 2027 | FX1: 2028 | FY1: 2029 | FZ1: 2030 | GA1: 2031 | GB1: 2032 | GC1: 2033 | GD1: 2034 | GE1: 2035 | GF1: 2036 | GG1: 2037 | GH1: 2038 | GI1: 2039 | GJ1: 2040 | GK1: 2041 | GL1: 2042 | GM1: 2043 | GN1: 2044 | GO1: 2045 | GP1: 2046 | GQ1: 2047 | GR1: 2048 | GS1: 2049 | GT1: 2050 | GV1: 2015 | GW1: 2016 | GX1: 2017 | GY1: 2018 | GZ1: 2019 | HA1: 2020 | HB1: 2021 | HC1: 2022 | HD1: 2023 | HE1: 2024 | HF1: 2025 | HG1: 2026 | HH1: 2027 | HI1: 2028 | HJ1: 2029 | HK1: 2030 | HL1: 2031 | HM1: 2032 | HN1: 2033 | HO1: 2034 | HP1: 2035 | HQ1: 2036 | HR1: 2037 | HS1: 2038 | HT1: 2039 | HU1: 2040 | HV1: 2041 | HW1: 2042 | HX1: 2043 | HY1: 2044 | HZ1: 2045 | IA1: 2046 | IB1: 2047 | IC1: 2048 | ID1: 2049 | IE1: 2050 | IG1: 2015 | IH1: 2016 | II1: 2017 | IJ1: 2018 | IK1: 2019 | IL1: 2020 | IM1: 2021 | IN1: 2022 | IO1: 2023 | IP1: 2024 | IQ1: 2025 | IR1: 2026 | IS1: 2027 | IT1: 2028 | IU1: 2029 | IV1: 2030 | IW1: 2031 | IX1: 2032 | IY1: 2033 | IZ1: 2034 | JA1: 2035 | JB1: 2036 | JC1: 2037 | JD1: 2038 | JE1: 2039 | JF1: 2040 | JG1: 2041 | JH1: 2042 | JI1: 2043 | JJ1: 2044 | JK1: 2045 | JL1: 2046 | JM1: 2047 | JN1: 2048 | JO1: 2049 | JP1: 2050 | JR1: 2015 | JS1: 2016 | JT1: 2017 | JU1: 2018 | JV1: 2019 | JW1: 2020 | JX1: 2021 | JY1: 2022 | JZ1: 2023 | KA1: 2024 | KB1: 2025 | KC1: 2026 | KD1: 2027 | KE1: 2028 | KF1: 2029 | KG1: 2030 | KH1: 2031 | KI1: 2032 | KJ1: 2033 | KK1: 2034 | KL1: 2035 | KM1: 2036 | KN1: 2037 | KO1: 2038 | KP1: 2039 | KQ1: 2040 | KR1: 2041 | KS1: 2042 | KT1: 2043 | KU1: 2044 | KV1: 2045 | KW1: 2046 | KX1: 2047 | KY1: 2048 | KZ1: 2049 | LA1: 2050 | LC1: 2015 | LD1: 2016 | LE1: 2017 | LF1: 2018 | LG1: 2019 | LH1: 2020 | LI1: 2021 | LJ1: 2022 | LK1: 2023 | LL1: 2024 | LM1: 2025 | LN1: 2026 | LO1: 2027 | LP1: 2028 | LQ1: 2029 | LR1: 2030 | LS1: 2031 | LT1: 2032 | LU1: 2033 | LV1: 2034 | LW1: 2035 | LX1: 2036 | LY1: 2037 | LZ1: 2038 | MA1: 2039 | MB1: 2040 | MC1: 2041 | MD1: 2042 | ME1: 2043 | MF1: 2044 | MG1: 2045 | MH1: 2046 | MI1: 2047 | MJ1: 2048 | MK1: 2049 | ML1: 2050
H2: Historique | S2: AMS 2018 | BD2: ADEME Tend. | CO2: ADEME S1 | DZ2: ADEME S2 | FK2: ADEME S3 | GV2: ADEME S4 | IG2: AME 2023 | JR2: AMS run 2 2023 | LC2: AMS run 3 2025
C4: Dernière modif. | D4: 44816 | H4: Historique | I4: Historique | J4: Historique | K4: Historique | L4: Historique | M4: Historique | N4: Historique | O4: Historique | P4: Historique | Q4: Historique | S4: SNBC | T4: SNBC | U4: SNBC | V4: SNBC | W4: SNBC | X4: SNBC | Y4: SNBC | Z4: SNBC | AA4: SNBC | AB4: SNBC | AC4: SNBC | AD4: SNBC | AE4: SNBC | AF4: SNBC | AG4: SNBC | AH4: SNBC | AI4: SNBC | AJ4: SNBC | AK4: SNBC | AL4: SNBC | AM4: SNBC | AN4: SNBC | AO4: SNBC | AP4: SNBC | AQ4: SNBC | AR4: SNBC | AS4: SNBC | AT4: SNBC | AU4: SNBC | AV4: SNBC | AW4: SNBC | AX4: SNBC | AY4: SNBC | AZ4: SNBC | BA4: SNBC | BB4: SNBC | BD4: S0 | BE4: S0 | BF4: S0 | BG4: S0 | BH4: S0 | BI4: S0 | BJ4: S0 | BK4: S0 | BL4: S0 | BM4: S0 | BN4: S0 | BO4: S0 | BP4: S0 | BQ4: S0 | BR4: S0 | BS4: S0 | BT4: S0 | BU4: S0 | BV4: S0 | BW4: S0 | BX4: S0 | BY4: S0 | BZ4: S0 | CA4: S0 | CB4: S0 | CC4: S0 | CD4: S0 | CE4: S0 | CF4: S0 | CG4: S0 | CH4: S0 | CI4: S0 | CJ4: S0 | CK4: S0 | CL4: S0 | CM4: S0 | CO4: S1 | CP4: S1 | CQ4: S1 | CR4: S1 | CS4: S1 | CT4: S1 | CU4: S1 | CV4: S1 | CW4: S1 | CX4: S1 | CY4: S1 | CZ4: S1 | DA4: S1 | DB4: S1 | DC4: S1 | DD4: S1 | DE4: S1 | DF4: S1 | DG4: S1 | DH4: S1 | DI4: S1 | DJ4: S1 | DK4: S1 | DL4: S1 | DM4: S1 | DN4: S1 | DO4: S1 | DP4: S1 | DQ4: S1 | DR4: S1 | DS4: S1 | DT4: S1 | DU4: S1 | DV4: S1 | DW4: S1 | DX4: S1 | DZ4: S2 | EA4: S2 | EB4: S2 | EC4: S2 | ED4: S2 | EE4: S2 | EF4: S2 | EG4: S2 | EH4: S2 | EI4: S2 | EJ4: S2 | EK4: S2 | EL4: S2 | EM4: S2 | EN4: S2 | EO4: S2 | EP4: S2 | EQ4: S2 | ER4: S2 | ES4: S2 | ET4: S2 | EU4: S2 | EV4: S2 | EW4: S2 | EX4: S2 | EY4: S2 | EZ4: S2 | FA4: S2 | FB4: S2 | FC4: S2 | FD4: S2 | FE4: S2 | FF4: S2 | FG4: S2 | FH4: S2 | FI4: S2 | FK4: S3 | FL4: S3 | FM4: S3 | FN4: S3 | FO4: S3 | FP4: S3 | FQ4: S3 | FR4: S3 | FS4: S3 | FT4: S3 | FU4: S3 | FV4: S3 | FW4: S3 | FX4: S3 | FY4: S3 | FZ4: S3 | GA4: S3 | GB4: S3 | GC4: S3 | GD4: S3 | GE4: S3 | GF4: S3 | GG4: S3 | GH4: S3 | GI4: S3 | GJ4: S3 | GK4: S3 | GL4: S3 | GM4: S3 | GN4: S3 | GO4: S3 | GP4: S3 | GQ4: S3 | GR4: S3 | GS4: S3 | GT4: S3 | GV4: S4 | GW4: S4 | GX4: S4 | GY4: S4 | GZ4: S4 | HA4: S4 | HB4: S4 | HC4: S4 | HD4: S4 | HE4: S4 | HF4: S4 | HG4: S4 | HH4: S4 | HI4: S4 | HJ4: S4 | HK4: S4 | HL4: S4 | HM4: S4 | HN4: S4 | HO4: S4 | HP4: S4 | HQ4: S4 | HR4: S4 | HS4: S4 | HT4: S4 | HU4: S4 | HV4: S4 | HW4: S4 | HX4: S4 | HY4: S4 | HZ4: S4 | IA4: S4 | IB4: S4 | IC4: S4 | ID4: S4 | IE4: S4 | IG4: AME 2023 | IH4: AME 2023 | II4: AME 2023 | IJ4: AME 2023 | IK4: AME 2023 | IL4: AME 2023 | IM4: AME 2023 | IN4: AME 2023 | IO4: AME 2023 | IP4: AME 2023 | IQ4: AME 2023 | IR4: AME 2023 | IS4: AME 2023 | IT4: AME 2023 | IU4: AME 2023 | IV4: AME 2023 | IW4: AME 2023 | IX4: AME 2023 | IY4: AME 2023 | IZ4: AME 2023 | JA4: AME 2023 | JB4: AME 2023 | JC4: AME 2023 | JD4: AME 2023 | JE4: AME 2023 | JF4: AME 2023 | JG4: AME 2023 | JH4: AME 2023 | JI4: AME 2023 | JJ4: AME 2023 | JK4: AME 2023 | JL4: AME 2023 | JM4: AME 2023 | JN4: AME 2023 | JO4: AME 2023 | JP4: AME 2023 | JR4: AMS2 2023 | JS4: AMS2 2023 | JT4: AMS2 2023 | JU4: AMS2 2023 | JV4: AMS2 2023 | JW4: AMS2 2023 | JX4: AMS2 2023 | JY4: AMS2 2023 | JZ4: AMS2 2023 | KA4: AMS2 2023 | KB4: AMS2 2023 | KC4: AMS2 2023 | KD4: AMS2 2023 | KE4: AMS2 2023 | KF4: AMS2 2023 | KG4: AMS2 2023 | KH4: AMS2 2023 | KI4: AMS2 2023 | KJ4: AMS2 2023 | KK4: AMS2 2023 | KL4: AMS2 2023 | KM4: AMS2 2023 | KN4: AMS2 2023 | KO4: AMS2 2023 | KP4: AMS2 2023 | KQ4: AMS2 2023 | KR4: AMS2 2023 | KS4: AMS2 2023 | KT4: AMS2 2023 | KU4: AMS2 2023 | KV4: AMS2 2023 | KW4: AMS2 2023 | KX4: AMS2 2023 | KY4: AMS2 2023 | KZ4: AMS2 2023 | LA4: AMS2 2023 | LC4: AMS3 2025 | LD4: AMS3 2025 | LE4: AMS3 2025 | LF4: AMS3 2025 | LG4: AMS3 2025 | LH4: AMS3 2025 | LI4: AMS3 2025 | LJ4: AMS3 2025 | LK4: AMS3 2025 | LL4: AMS3 2025 | LM4: AMS3 2025 | LN4: AMS3 2025 | LO4: AMS3 2025 | LP4: AMS3 2025 | LQ4: AMS3 2025 | LR4: AMS3 2025 | LS4: AMS3 2025 | LT4: AMS3 2025 | LU4: AMS3 2025 | LV4: AMS3 2025 | LW4: AMS3 2025 | LX4: AMS3 2025 | LY4: AMS3 2025 | LZ4: AMS3 2025 | MA4: AMS3 2025 | MB4: AMS3 2025 | MC4: AMS3 2025 | MD4: AMS3 2025 | ME4: AMS3 2025 | MF4: AMS3 2025 | MG4: AMS3 2025 | MH4: AMS3 2025 | MI4: AMS3 2025 | MJ4: AMS3 2025 | MK4: AMS3 2025 | ML4: AMS3 2025
C6: Contenu | D6: Les travaux d'entretien-amélioration et de rénovation des bâtiments tertiaires.
C8: Sommaire
C10: Définitions
C11: Parc de bâtiments
C12: Consommation d'énergie
C13: Nombre de rénovations
C14: Le dispositif éco-énergie tertiaire (DEET) et les rénovations basse consommation (BBC)
C15: Les autres rénovations
C16: Coûts
C17: Investissements
B20: retour | C20: Définitions
C22: Parc tertiaire
C24: Les bâtiments tertiaires font partie des bâtiments non-résidentiels et hébergent les activités économiques du secteur tertiaire (par opposition aux locaux agricoles et industriels).
C25: Les surfaces chauffées de ces bâtiments sont recensées par le CEREN qui les regroupe en huit branches.
C26: Les consommations énergétiques du tertiaire comprennent non seulement les consommations des bâtiments, mais aussi de l'éclairage public, des armées, des grands centres de recherche, des télécommunications, du secteur de l'eau ou encore des data centers.
C27: Toutes ces consommations "hors bâtiment" ne sont pas étudiées ici.
C29: Travaux de rénovation énergétique
C31: Différentes études retiennent des périmètres légèrement différents pour caractériser les coûts de rénovation énergétique
C33: Ministère de la Transition Ecologique et Solidaire et Ministère de la Cohésion des Territoires, « Calcul des niveaux optimaux en fonction des coûts des exigences minimales en matière de performance énergétique », pp.26-27
C34: Les coûts d’investissement initiaux recouvrent tous les coûts supportés jusqu’à la livraison (...) de l’élément de bâtiment, prêt à l’emploi. (...) tous les coûts des éléments qui n’ont pas d’incidence sur [la performance énergétique] ont été omis (…).
C35: rénovation il a cependant été choisi d’intégrer les coûts suivants : échafaudages, ensemble des déposes (systèmes ou isolation préexistante, le cas échéant) finitions « minimales » (par exemple : (…) enduit sur ITE)
C37: Observatoire BBC, « Guide méthodologique : comment analyser les coûts associés à la rénovation énergétique ? »
C38: Les travaux de rénovation énergétique regroupent les lots « Enveloppe – Rénovation Energétique » et « Equipements – Rénovation Energétique »
... C63: European Commission, « Guidelines Accompanying Commission Delegated Regulation (EU) No 244/2012 ».
B64: [LIEN] | C64: Dans ses recommandations accompagnant la directive de 2012 sur la performance énergétique des bâtiments, la Commission Européenne fournit (p.6)une liste indicative d'équipements liés à la performance énergétique.
C65: Les dépenses listées peuvent concerner la structure (ou enveloppe) du bâtiment (isolation des murs, des toitures…), ou les systèmes (chauffage, eau chaude sanitaire, ventilateurs, calorifugeage des conduites, etc.)
C66: Cependant, nous ne sommes pas en mesure de déterminer si toutes les sources exploitées dans ce document se réfèrent au même périmètre de travaux.
C68: Rénovation énergétique et investissements favorables au climat
C70: Au sein des investissements historiques du secteur, les dépenses d'installation de systèmes de chauffage gaz et fioul, qui sont classés comme investissements fossiles.
C71: Faute d'une représentation aussi détaillée des travaux, dans cet onglet prospectif, tous les travaux anticipés sont considérés favorables au climat. On considère que les ventes de chaudières gaz et fioul sont négligeables dans les totaux simulés.
C73: Les autres travaux de rénovation et le coût des opérations
C75: Les données de référence de l'Observatoire BBC font apparaitre une distinciton importante entre le coût des rénovations énergétiques, le coût des autres travaux de rénovation et le coût total des opérations.
C76: Le coût des travaux énergétiques est décrit ci-dessus, le champ exact varie peu d'une étude à l'autre
C77: Les autres travaux de rénovation comprennent la démolition, le nettoyage, les échafaudages, le gros œuvre, l'étanchéité, la plomberie, la peinture, les ascenseurs… liste non exhautive (voir source Observatoire BBC op. cit., pp.56)
C78: Le coût complet des opérations comprend, outre les travaux de rénovation ci-dessus, le coût du foncier, de la MOE et de l'assistance à MOA, l'ingénierie, les labels et frais de concours, l'instrumentation, l'aménagement et le poste VRD, les frais et taxes, ainsi que les frais pour imprévus
C81: Input ADEME
B83: Zone input
BD84: Secteurs CEREN - Surface chauffée [thousand sq m] | CO84: Secteurs CEREN - Surface chauffée [thousand sq m] | DZ84: Secteurs CEREN - Surface chauffée [thousand sq m] | FK84: Secteurs CEREN - Surface chauffée [thousand sq m] | GV84: Secteurs CEREN - Surface chauffée [thousand sq m]
C85: Secteur | BD85: 2006 | BE85: 2015 | BF85: 2020 | BG85: 2030 | BH85: 2040 | BI85: 2050 | CO85: 2006 | CP85: 2015 | CQ85: 2020 | CR85: 2030 | CS85: 2040 | CT85: 2050 | DZ85: 2006 | EA85: 2015 | EB85: 2020 | EC85: 2030 | ED85: 2040 | EE85: 2050 | FK85: 2006 | FL85: 2015 | FM85: 2020 | FN85: 2030 | FO85: 2040 | FP85: 2050 | GV85: 2006 | GW85: 2015 | GX85: 2020 | GY85: 2030 | GZ85: 2040 | HA85: 2050
C86: Bureaux | BD86: 191050 | BE86: 220833 | BF86: 239113.67 | BG86: 216780.99 | BH86: 200390.5 | BI86: 183339.68 | CO86: 191050 | CP86: 220833 | CQ86: 239113.67 | CR86: 206077.96 | CS86: 181091.4 | CT86: 157502.53 | DZ86: 191050 | EA86: 220833 | EB86: 239113.67 | EC86: 206077.96 | ED86: 181091.4 | EE86: 157502.53 | FK86: 191050 | FL86: 220833 | FM86: 239113.67 | FN86: 216780.99 | FO86: 200390.5 | FP86: 183339.68 | GV86: 191050 | GW86: 220833 | GX86: 239113.67 | GY86: 216780.99 | GZ86: 200390.5 | HA86: 183339.68
C87: Cafés-hôtels-restaurants | BD87: 58716 | BE87: 64402 | BF87: 67389.902 | BG87: 74487.718 | BH87: 82026.333 | BI87: 89401.61 | CO87: 58716 | CP87: 64402 | CQ87: 67389.902 | CR87: 64124.675 | CS87: 60790.304 | CT87: 57038.339 | DZ87: 58716 | EA87: 64402 | EB87: 67389.902 | EC87: 64124.675 | ED87: 60790.304 | EE87: 57038.339 | FK87: 58716 | FL87: 64402 | FM87: 67389.902 | FN87: 69138.511 | FO87: 70668.197 | FP87: 71491.005 | GV87: 58716 | GW87: 64402 | GX87: 67389.902 | GY87: 74487.718 | GZ87: 82026.333 | HA87: 89401.61
C88: Commerce | BD88: 198857 | BE88: 210718 | BF88: 215959 | BG88: 222663.01 | BH88: 227589.42 | BI88: 230239.3 | CO88: 198857 | CP88: 210718 | CQ88: 215959 | CR88: 211777.04 | CS88: 205879.77 | CT88: 198094.26 | DZ88: 198857 | EA88: 210718 | EB88: 215959 | EC88: 211777.04 | ED88: 205879.77 | EE88: 198094.26 | FK88: 198857 | FL88: 210718 | FM88: 215959 | FN88: 222663.01 | FO88: 227589.42 | FP88: 230239.3 | GV88: 198857 | GW88: 210718 | GX88: 215959 | GY88: 222663.01 | GZ88: 227589.42 | HA88: 230239.3
C89: Enseignement-recherche | BD89: 176652 | BE89: 186911 | BF89: 190850 | BG89: 192214.2 | BH89: 202191.29 | BI89: 214970.75 | CO89: 176652 | CP89: 186911 | CQ89: 190850 | CR89: 158255.86 | CS89: 137060.12 | CT89: 119978.21 | DZ89: 176652 | EA89: 186911 | EB89: 190850 | EC89: 158255.86 | ED89: 137060.12 | EE89: 119978.21 | FK89: 176652 | FL89: 186911 | FM89: 190850 | FN89: 177661.39 | FO89: 172733.92 | FP89: 169747.02 | GV89: 176652 | GW89: 186911 | GX89: 190850 | GY89: 192214.2 | GZ89: 202191.29 | HA89: 214970.75
C90: Habitat communautaire | BD90: 58694 | BE90: 69798 | BF90: 72592 | BG90: 84879.099 | BH90: 97268.707 | BI90: 110323.73 | CO90: 58694 | CP90: 69798 | CQ90: 72592 | CR90: 84879.099 | CS90: 97268.707 | CT90: 110323.73 | DZ90: 58694 | EA90: 69798 | EB90: 72592 | EC90: 84879.099 | ED90: 97268.707 | EE90: 110323.73 | FK90: 58694 | FL90: 69798 | FM90: 72592 | FN90: 84879.099 | FO90: 97268.707 | FP90: 110323.73 | GV90: 58694 | GW90: 69798 | GX90: 72592 | GY90: 84879.099 | GZ90: 97268.707 | HA90: 110323.73
C91: Santé | BD91: 100191 | BE91: 114188 | BF91: 118445.14 | BG91: 133413.05 | BH91: 148223.78 | BI91: 162989.97 | CO91: 100191 | CP91: 114188 | CQ91: 118445.14 | CR91: 114760.18 | CS91: 109674 | CT91: 103738.41 | DZ91: 100191 | EA91: 114188 | EB91: 118445.14 | EC91: 115244.83 | ED91: 110602.3 | EE91: 105058.28 | FK91: 100191 | FL91: 114188 | FM91: 118445.14 | FN91: 122739.04 | FO91: 125454.63 | FP91: 126915.33 | GV91: 100191 | GW91: 114188 | GX91: 118445.14 | GY91: 133413.05 | GZ91: 148223.78 | HA91: 162989.97
C92: Sport, Loisirs, Culture | BD92: 64974 | BE92: 71426 | BF92: 74481 | BG92: 87630.941 | BH92: 100991.4 | BI92: 115195.28 | CO92: 64974 | CP92: 71426 | CQ92: 74481 | CR92: 70288.861 | CS92: 64974.424 | CT92: 59445.883 | DZ92: 64974 | EA92: 71426 | EB92: 74481 | EC92: 70288.861 | ED92: 64974.424 | EE92: 59445.883 | FK92: 64974 | FL92: 71426 | FM92: 74481 | FN92: 77720.316 | FO92: 79439.874 | FP92: 80364.814 | GV92: 64974 | GW92: 71426 | GX92: 74481 | GY92: 87630.941 | GZ92: 100991.4 | HA92: 115195.28
C93: Transport | BD93: 24887 | BE93: 25399 | BF93: 25839.303 | BG93: 25942.268 | BH93: 26018.782 | BI93: 26093.323 | CO93: 24887 | CP93: 25399 | CQ93: 25839.303 | CR93: 25942.268 | CS93: 26018.782 | CT93: 26093.323 | DZ93: 24887 | EA93: 25399 | EB93: 25839.303 | EC93: 25942.268 | ED93: 26018.782 | EE93: 26093.323 | FK93: 24887 | FL93: 25399 | FM93: 25839.303 | FN93: 25942.268 | FO93: 26018.782 | FP93: 26093.323 | GV93: 24887 | GW93: 25399 | GX93: 25839.303 | GY93: 25942.268 | GZ93: 26018.782 | HA93: 26093.323
C94: TOTAL | BD94: 874021 | BE94: 963675 | BF94: 1004670 | BG94: 1038011.3 | BH94: 1084700.2 | BI94: 1132553.6 | CO94: 874021 | CP94: 963675 | CQ94: 1004670 | CR94: 936105.94 | CS94: 882757.51 | CT94: 832214.68 | DZ94: 874021 | EA94: 963675 | EB94: 1004670 | EC94: 936590.59 | ED94: 883685.81 | EE94: 833534.54 | FK94: 874021 | FL94: 963675 | FM94: 1004670 | FN94: 997524.62 | FO94: 999564.02 | FP94: 998514.2 | GV94: 874021 | GW94: 963675 | GX94: 1004670 | GY94: 1038011.3 | GZ94: 1084700.2 | HA94: 1132553.6
BD97: Secteurs CEREN - Surface chauffée construites après 2015 [thousand sq m] | CO97: Secteurs CEREN - Surface chauffée construites après 2015 [thousand sq m] | DZ97: Secteurs CEREN - Surface chauffée construites après 2015 [thousand sq m] | FK97: Secteurs CEREN - Surface chauffée construites après 2015 [thousand sq m] | GV97: Secteurs CEREN - Surface chauffée construites après 2015 [thousand sq m]
C98: Secteur | BD98: 2006 | BE98: 2015 | BF98: 2020 | BG98: 2030 | BH98: 2040 | BI98: 2050 | CO98: 2006 | CP98: 2015 | CQ98: 2020 | CR98: 2030 | CS98: 2040 | CT98: 2050 | DZ98: 2006 | EA98: 2015 | EB98: 2020 | EC98: 2030 | ED98: 2040 | EE98: 2050 | FK98: 2006 | FL98: 2015 | FM98: 2020 | FN98: 2030 | FO98: 2040 | FP98: 2050 | GV98: 2006 | GW98: 2015 | GX98: 2020 | GY98: 2030 | GZ98: 2040 | HA98: 2050
C99: Bureaux | BF99: 14324 | BG99: 29597.985 | BH99: 32207.495 | BI99: 34156.677 | CQ99: 14324 | CR99: 24894.959 | CS99: 24908.404 | CT99: 26319.531 | EB99: 14324 | EC99: 24894.959 | ED99: 24908.404 | EE99: 26319.531 | FM99: 14324 | FN99: 29597.985 | FO99: 32207.495 | FP99: 34156.677 | GX99: 14324 | GY99: 29597.985 | GZ99: 32207.495 | HA99: 34156.677
C100: Cafés-hôtels-restaurants | BF100: 2344.9017 | BG100: 11419.468 | BH100: 18589.932 | BI100: 25597.057 | CQ100: 2344.9017 | CR100: 5224.5765 | CS100: 5690.206 | CT100: 5738.2404 | EB100: 2344.9017 | EC100: 5224.5765 | ED100: 5690.206 | EE100: 5738.2404 | FM100: 2344.9017 | FN100: 6070.2611 | FO100: 7231.7953 | FP100: 7686.4526 | GX100: 2344.9017 | GY100: 11419.468 | GZ100: 18589.932 | HA100: 25597.057
C101: Commerce | BF101: 4877 | BG101: 18828.616 | BH101: 26125.629 | BI101: 31146.12 | CQ101: 4877 | CR101: 13572.045 | CS101: 15674.772 | CT101: 15889.256 | EB101: 4877 | EC101: 13572.045 | ED101: 15674.772 | EE101: 15889.256 | FM101: 4877 | FN101: 18828.616 | FO101: 26125.629 | FP101: 31146.12 | GX101: 4877 | GY101: 18828.616 | GZ101: 26125.629 | HA101: 31146.12
C102: Enseignement-recherche | BF102: 3053 | BG102: 5458.9881 | BH102: 13424.865 | BI102: 24193.118 | CQ102: 3053 | CR102: 3511.8587 | CS102: 12316.117 | CT102: 25234.206 | EB102: 3053 | EC102: 3511.8587 | ED102: 12316.117 | EE102: 25234.206 | FM102: 3053 | FN102: 3917.3919 | FO102: 9989.9182 | FP102: 18003.018 | GX102: 3053 | GY102: 5458.9881 | GZ102: 13424.865 | HA102: 24193.118
C103: Habitat communautaire | BF103: 2800 | BG103: 15425.887 | BH103: 25354.283 | BI103: 35948.092 | CQ103: 2800 | CR103: 15425.887 | CS103: 25354.283 | CT103: 35948.092 | EB103: 2800 | EC103: 15425.887 | ED103: 25354.283 | EE103: 35948.092 | FM103: 2800 | FN103: 15425.887 | FO103: 25354.283 | FP103: 35948.092 | GX103: 2800 | GY103: 15425.887 | GZ103: 25354.283 | HA103: 35948.092
C104: Santé | BF104: 4380.1391 | BG104: 25234.439 | BH104: 41551.424 | BI104: 57823.864 | CQ104: 4380.1391 | CR104: 11075.317 | CS104: 11989.142 | CT104: 12053.55 | EB104: 4380.1391 | EC104: 11559.966 | ED104: 12917.438 | EE104: 13373.416 | FM104: 4380.1391 | FN104: 14560.427 | FO104: 18782.271 | FP104: 21749.223 | GX104: 4380.1391 | GY104: 25234.439 | GZ104: 41551.424 | HA104: 57823.864
C105: Sport, Loisirs, Culture | BF105: 2784 | BG105: 20624.638 | BH105: 35891.79 | BI105: 52002.371 | CQ105: 2784 | CR105: 7375.8608 | CS105: 8061.4239 | CT105: 8532.8827 | EB105: 2784 | EC105: 7375.8608 | ED105: 8061.4239 | EE105: 8532.8827 | FM105: 2784 | FN105: 10714.013 | FO105: 14340.268 | FP105: 17171.905 | GX105: 2784 | GY105: 20624.638 | GZ105: 35891.79 | HA105: 52002.371
C106: Transport | BF106: 282.3032 | BG106: 385.26849 | BH106: 461.78156 | BI106: 536.32264 | CQ106: 282.3032 | CR106: 385.26849 | CS106: 461.78156 | CT106: 536.32264 | EB106: 282.3032 | EC106: 385.26849 | ED106: 461.78156 | EE106: 536.32264 | FM106: 282.3032 | FN106: 385.26849 | FO106: 461.78156 | FP106: 536.32264 | GX106: 282.3032 | GY106: 385.26849 | GZ106: 461.78156 | HA106: 536.32264
C107: TOTAL | BF107: 34845.344 | BG107: 126975.29 | BH107: 193607.2 | BI107: 261403.62 | CQ107: 34845.344 | CR107: 81465.772 | CS107: 104456.13 | CT107: 130252.08 | EB107: 34845.344 | EC107: 81950.421 | ED107: 105384.42 | EE107: 131571.95 | FM107: 34845.344 | FN107: 99499.85 | FO107: 134493.44 | FP107: 166397.81 | GX107: 34845.344 | GY107: 126975.29 | GZ107: 193607.2 | HA107: 261403.62
C110: Secteur | BD110: Proportion du parc suivant la trajectoire "Décret tertiaire" | CO110: Proportion du parc suivant la trajectoire "Décret tertiaire" | DZ110: Proportion du parc suivant la trajectoire "Décret tertiaire" | FK110: Proportion du parc suivant la trajectoire "Décret tertiaire" | GV110: Proportion du parc suivant la trajectoire "Décret tertiaire"
C111: Bureaux | BD111: 0.45 | CO111: 0.75 | DZ111: 0.65 | FK111: 0.65 | GV111: 0.55
C112: Cafés-hôtels-restaurants | BD112: 0.46 | CO112: 0.76 | DZ112: 0.66 | FK112: 0.66 | GV112: 0.55
C113: Commerce | BD113: 0.32 | CO113: 0.62 | DZ113: 0.52 | FK113: 0.52 | GV113: 0.42
C114: Enseignement-recherche | BD114: 0.65 | CO114: 0.96 | DZ114: 0.85 | FK114: 0.85 | GV114: 0.75
C115: Habitat communautaire | BD115: 0.58 | CO115: 0.89 | DZ115: 0.78 | FK115: 0.78 | GV115: 0.68
C116: Santé | BD116: 0.79 | CO116: 0.99 | DZ116: 0.99 | FK116: 0.99 | GV116: 0.89
C117: Sport, Loisirs, Culture | BD117: 0.39 | CO117: 0.69 | DZ117: 0.59 | FK117: 0.59 | GV117: 0.49
C118: Transport | BD118: 0.58 | CO118: 0.88 | DZ118: 0.78 | FK118: 0.58 | GV118: 0.58
BD120: Secteurs CEREN - Consommation d'énergie [GWh LHV] | CO120: Secteurs CEREN - Consommation d'énergie [GWh LHV] | DZ120: Secteurs CEREN - Consommation d'énergie [GWh LHV] | FK120: Secteurs CEREN - Consommation d'énergie [GWh LHV] | GV120: Secteurs CEREN - Consommation d'énergie [GWh LHV]
C121: Secteur | BD121: 2006 | BE121: 2015 | BF121: 2020 | BG121: 2030 | BH121: 2040 | BI121: 2050 | CO121: 2006 | CP121: 2015 | CQ121: 2020 | CR121: 2030 | CS121: 2040 | CT121: 2050 | DZ121: < | EA121: 2015 | EB121: 2020 | EC121: 2030 | ED121: 2040 | EE121: 2050 | FK121: 2006 | FL121: 2015 | FM121: 2020 | FN121: 2030 | FO121: 2040 | FP121: 2050 | GV121: 2006 | GW121: 2015 | GX121: 2020 | GY121: 2030 | GZ121: 2040 | HA121: 2050
C122: Bureaux | BD122: 54330 | BE122: 57423.943 | BF122: 56420.57 | BG122: 47064.614 | BH122: 40222.397 | BI122: 34537.915 | CO122: 54330 | CP122: 57423.943 | CQ122: 56423.035 | CR122: 37765.2 | CS122: 28241 | CT122: 21421.497 | DZ122: 54330 | EA122: 57423.943 | EB122: 56429.199 | EC122: 39524.484 | ED122: 30151.98 | EE122: 23529.314 | FK122: 54330 | FL122: 57423.943 | FM122: 56429.199 | FN122: 43798.74 | FO122: 36051.401 | FP122: 29602.647 | GV122: 54330 | GW122: 57423.943 | GX122: 56420.981 | GY122: 45910.949 | GZ122: 38972.474 | HA122: 32565.804
C123: Cafés-hôtels-restaurants | BD123: 22320 | BE123: 22757.806 | BF123: 22294.565 | BG123: 20678.447 | BH123: 19966.513 | BI123: 19317.178 | CO123: 22320 | CP123: 22757.806 | CQ123: 22294.565 | CR123: 15782.035 | CS123: 12565.197 | CT123: 9900.3675 | DZ123: 22320 | EA123: 22757.806 | EB123: 22294.565 | EC123: 16621.393 | ED123: 13401.26 | EE123: 10884.449 | FK123: 22320 | FL123: 22757.806 | FM123: 22294.565 | FN123: 18351.272 | FO123: 16470.484 | FP123: 14574.879 | GV123: 22320 | GW123: 22757.806 | GX123: 22294.565 | GY123: 20432.889 | GZ123: 19991.399 | HA123: 19552.119
C124: Commerce | BD124: 51116 | BE124: 50450.378 | BF124: 47186.975 | BG124: 43240.44 | BH124: 41399.153 | BI124: 39840.601 | CO124: 51116 | CP124: 50450.378 | CQ124: 47186.975 | CR124: 34221.524 | CS124: 27974.318 | CT124: 23897.367 | DZ124: 51116 | EA124: 50450.378 | EB124: 47186.975 | EC124: 35999.305 | ED124: 30717.464 | EE124: 26644.99 | FK124: 51116 | FL124: 50450.378 | FM124: 47186.975 | FN124: 39723.907 | FO124: 37050.756 | FP124: 34772.409 | GV124: 51116 | GW124: 50450.378 | GX124: 47186.975 | GY124: 42625.664 | GZ124: 40546.893 | HA124: 38820.31
C125: Enseignement-recherche | BD125: 26275.6 | BE125: 26147.969 | BF125: 25283.356 | BG125: 21007.965 | BH125: 21070.652 | BI125: 23468.619 | CO125: 26275.6 | CP125: 26147.969 | CQ125: 25283.356 | CR125: 13921.497 | CS125: 10331.376 | CT125: 8206.4642 | DZ125: 26275.6 | EA125: 26147.969 | EB125: 25283.356 | EC125: 15908.456 | ED125: 12018.41 | EE125: 9931.519 | FK125: 26275.6 | FL125: 26147.969 | FM125: 25283.356 | FN125: 16970.228 | FO125: 15771.742 | FP125: 16100.391 | GV125: 26275.6 | GW125: 26147.969 | GX125: 25283.356 | GY125: 20817.141 | GZ125: 20802.704 | HA125: 22188.95
C126: Habitat communautaire | BD126: 12687 | BE126: 13446.692 | BF126: 13194.896 | BG126: 12599 | BH126: 13203.014 | BI126: 14469.083 | CO126: 12687 | CP126: 13446.692 | CQ126: 13194.896 | CR126: 10621.006 | CS126: 10129.354 | CT126: 9844.8248 | DZ126: 12687 | EA126: 13446.692 | EB126: 13194.896 | EC126: 11332.436 | ED126: 10652.037 | EE126: 10523.631 | FK126: 12687 | FL126: 13446.692 | FM126: 13194.896 | FN126: 11222.381 | FO126: 11373.212 | FP126: 11677.377 | GV126: 12687 | GW126: 13446.692 | GX126: 13194.896 | GY126: 12678.562 | GZ126: 13002.746 | HA126: 13521.647
C127: Santé | BD127: 26154.86 | BE127: 27145.342 | BF127: 26529.488 | BG127: 22796.37 | BH127: 22538.393 | BI127: 22656.558 | CO127: 26154.86 | CP127: 27145.342 | CQ127: 26529.488 | CR127: 16858.684 | CS127: 13764.763 | CT127: 11172.282 | DZ127: 26154.86 | EA127: 27145.342 | EB127: 26529.488 | EC127: 18341.392 | ED127: 15162.11 | EE127: 12805.794 | FK127: 26154.86 | FL127: 27145.342 | FM127: 26529.488 | FN127: 19059.563 | FO127: 17276.152 | FP127: 15476.207 | GV127: 26154.86 | GW127: 27145.342 | GX127: 26529.488 | GY127: 22450.912 | GZ127: 21957.03 | HA127: 21489.441
C128: Sport, Loisirs, Culture | BD128: 17353 | BE128: 17626.243 | BF128: 17429.316 | BG128: 17542.521 | BH128: 18752.422 | BI128: 21085.38 | CO128: 17353 | CP128: 17626.243 | CQ128: 17429.316 | CR128: 11612.096 | CS128: 8723.8668 | CT128: 6563.6996 | DZ128: 17353 | EA128: 17626.243 | EB128: 17429.316 | EC128: 12435.85 | ED128: 9508.427 | EE128: 7404.2841 | FK128: 17353 | FL128: 17626.243 | FM128: 17429.316 | FN128: 14493.751 | FO128: 13594.776 | FP128: 13005.284 | GV128: 17353 | GW128: 17626.243 | GX128: 17429.316 | GY128: 17521.721 | GZ128: 18747.378 | HA128: 20689.815
C129: Transport | BD129: 8655 | BE129: 8041.1339 | BF129: 7777.9672 | BG129: 7240.791 | BH129: 6730.9186 | BI129: 6353.9935 | CO129: 8655 | CP129: 8041.1339 | CQ129: 7777.9672 | CR129: 6435.615 | CS129: 5807.2088 | CT129: 5173.643 | DZ129: 8655 | EA129: 8041.1339 | EB129: 7777.9672 | EC129: 6902.114 | ED129: 6073.2451 | EE129: 5531.421 | FK129: 8655 | FL129: 8041.1339 | FM129: 7777.9672 | FN129: 6670.1447 | FO129: 6248.8982 | FP129: 5840.539 | GV129: 8655 | GW129: 8041.1339 | GX129: 7777.9672 | GY129: 7257.6894 | GZ129: 6748.6398 | HA129: 6289.9983
C130: TOTAL | BD130: 218891.46 | BE130: 223039.51 | BF130: 216117.13 | BG130: 192170.15 | BH130: 183883.46 | BI130: 181729.33 | CO130: 218891.46 | CP130: 223039.51 | CQ130: 216119.6 | CR130: 147217.66 | CS130: 117537.08 | CT130: 96180.144 | DZ130: 218891.46 | EA130: 223039.51 | EB130: 216125.76 | EC130: 157065.43 | ED130: 127684.93 | EE130: 107255.4 | FK130: 218891.46 | FL130: 223039.51 | FM130: 216125.76 | FN130: 170289.99 | FO130: 153837.42 | FP130: 141049.73 | GV130: 218891.46 | GW130: 223039.51 | GX130: 216117.54 | GY130: 189695.53 | GZ130: 180769.26 | HA130: 175118.08
BD133: Secteurs CEREN - Consommation par usage [GWh LHV] | CO133: Secteurs CEREN - Consommation par usage [GWh LHV] | DZ133: Secteurs CEREN - Consommation par usage [GWh LHV] | FK133: Secteurs CEREN - Consommation par usage [GWh LHV] | GV133: Secteurs CEREN - Consommation par usage [GWh LHV]
C134: Usage | BD134: 2006 | BE134: 2015 | BF134: 2020 | BG134: 2030 | BH134: 2040 | BI134: 2050 | CO134: 2006 | CP134: 2015 | CQ134: 2020 | CR134: 2030 | CS134: 2040 | CT134: 2050 | DZ134: 2006 | EA134: 2015 | EB134: 2020 | EC134: 2030 | ED134: 2040 | EE134: 2050 | FK134: 2006 | FL134: 2015 | FM134: 2020 | FN134: 2030 | FO134: 2040 | FP134: 2050 | GV134: 2006 | GW134: 2015 | GX134: 2020 | GY134: 2030 | GZ134: 2040 | HA134: 2050
C135: Chauffage | BD135: 110624.86 | BE135: 102098.56 | BF135: 98507.793 | BG135: 78487.596 | BH135: 69169.7 | BI135: 62200.751 | CO135: 110624.86 | CP135: 102098.56 | CQ135: 98510.258 | CR135: 57014.586 | CS135: 41623.078 | CT135: 31499.692 | DZ135: 110624.86 | EA135: 102098.56 | EB135: 98516.422 | EC135: 64122.822 | ED135: 48877.488 | EE135: 39658.56 | FK135: 110624.86 | FL135: 102098.56 | FM135: 98516.422 | FN135: 63748.009 | FO135: 53175.87 | FP135: 45452.111 | GV135: 110624.86 | GW135: 102098.56 | GX135: 98508.204 | GY135: 76135.044 | GZ135: 66275.327 | HA135: 58772.908
C136: Autres usages thermiques | BD136: 11060 | BE136: 11060 | BF136: 10975.476 | BG136: 10519.965 | BH136: 9998.4237 | BI136: 9424.538 | CO136: 11060 | CP136: 11060 | CQ136: 10975.476 | CR136: 8076.0347 | CS136: 7245.2792 | CT136: 6460.5664 | DZ136: 11060 | EA136: 11060 | EB136: 10975.476 | EC136: 9901.1354 | ED136: 8866.0958 | EE136: 7884.8227 | FK136: 11060 | FL136: 11060 | FM136: 10975.476 | FN136: 10333.824 | FO136: 9644.6592 | FP136: 8925.1788 | GV136: 11060 | GW136: 11060 | GX136: 10975.476 | GY136: 10519.965 | GZ136: 9998.4237 | HA136: 9424.538
C137: Eau chaude | BD137: 20329 | BE137: 21492.943 | BF137: 21932.633 | BG137: 22342.813 | BH137: 22907.939 | BI137: 23543.62 | CO137: 20329 | CP137: 21492.943 | CQ137: 21932.633 | CR137: 17237.85 | CS137: 13579.571 | CT137: 10682.278 | DZ137: 20329 | EA137: 21492.943 | EB137: 21932.633 | EC137: 17968.348 | ED137: 14762.401 | EE137: 12119.839 | FK137: 20329 | FL137: 21492.943 | FM137: 21932.633 | FN137: 20215.303 | FO137: 18715.05 | FP137: 17331.425 | GV137: 20329 | GW137: 21492.943 | GX137: 21932.633 | GY137: 22561.422 | GZ137: 23327.36 | HA137: 24141.216
C138: Cuisson | BD138: 11257 | BE138: 10687 | BF138: 10864.14 | BG138: 10317.64 | BH138: 9942.355 | BI138: 9471.6096 | CO138: 11257 | CP138: 10687 | CQ138: 10864.14 | CR138: 9257.9734 | CS138: 8059.2029 | CT138: 7025.407 | DZ138: 11257 | EA138: 10687 | EB138: 10864.14 | EC138: 9315.389 | ED138: 8089.1456 | EE138: 7036.4558 | FK138: 11257 | FL138: 10687 | FM138: 10864.14 | FN138: 9834.1116 | FO138: 9026.0459 | FP138: 8244.8011 | GV138: 11257 | GW138: 10687 | GX138: 10864.14 | GY138: 10318.512 | GZ138: 9928.6525 | HA138: 9471.6096
C139: Spécifique | BD139: 52238 | BE139: 59069 | BF139: 60437.713 | BG139: 55997.502 | BH139: 53302.501 | BI139: 50419.563 | CO139: 52238 | CP139: 59069 | CQ139: 60437.713 | CR139: 49398.798 | CS139: 42067.844 | CT139: 35871.13 | DZ139: 52238 | EA139: 59069 | EB139: 60437.713 | EC139: 49412.539 | ED139: 42093.386 | EE139: 35906.344 | FK139: 52238 | FL139: 59069 | FM139: 60437.713 | FN139: 54472.279 | FO139: 50285.704 | FP139: 46002.871 | GV139: 52238 | GW139: 59069 | GX139: 60437.713 | GY139: 56906.917 | GZ139: 56020.284 | HA139: 54999.887
C140: Climatisation | BD140: 13382.6 | BE140: 18632 | BF140: 13399.377 | BG140: 14504.633 | BH140: 18562.544 | BI140: 26669.246 | CO140: 13382.6 | CP140: 18632 | CQ140: 13399.377 | CR140: 6232.4141 | CS140: 4962.1089 | CT140: 4641.0709 | DZ140: 13382.6 | EA140: 18632 | EB140: 13399.377 | EC140: 6345.1961 | ED140: 4996.4158 | EE140: 4649.3807 | FK140: 13382.6 | FL140: 18632 | FM140: 13399.377 | FN140: 11686.461 | FO140: 12990.093 | FP140: 15093.346 | GV140: 13382.6 | GW140: 18632 | GX140: 13399.377 | GY140: 13253.669 | GZ140: 15219.214 | HA140: 18307.925
C141: Total | BD141: 218891.46 | BE141: 223039.51 | BF141: 216117.13 | BG141: 192170.15 | BH141: 183883.46 | BI141: 181729.33 | CO141: 218891.46 | CP141: 223039.51 | CQ141: 216119.6 | CR141: 147217.66 | CS141: 117537.08 | CT141: 96180.144 | DZ141: 218891.46 | EA141: 223039.51 | EB141: 216125.76 | EC141: 157065.43 | ED141: 127684.93 | EE141: 107255.4 | FK141: 218891.46 | FL141: 223039.51 | FM141: 216125.76 | FN141: 170289.99 | FO141: 153837.42 | FP141: 141049.73 | GV141: 218891.46 | GW141: 223039.51 | GX141: 216117.54 | GY141: 189695.53 | GZ141: 180769.26 | HA141: 175118.08
C143: Source: tableur SB_VIVALDI _Run5
B147: retour | C147: Parc de bâtiments
C149: Surfaces chauffées | H149: HISTO | S149: SNBC | BD149: S0 | CO149: S1 | DZ149: S2 | FK149: S3 | GV149: S4 | IG149: AME 2023 | JR149: =JR$4 -> AMS2 2023 | LC149: =LC$4 -> AMS3 2025
E150: (unité) | F150: (détail) | H150: =H$1 -> 2015 | I150: =I$1 -> 2016 | J150: =J$1 -> 2017 | K150: =K$1 -> 2018 | L150: =L$1 -> 2019 | M150: =M$1 -> 2020 | N150: =N$1 -> 2021 | O150: =O$1 -> 2022 | ... Q150: =Q$1 -> 2024 | S150: =S$1 -> 2015 | T150: =T$1 -> 2016 | U150: =U$1 -> 2017 | V150: =V$1 -> 2018 | W150: =W$1 -> 2019 | X150: =X$1 -> 2020 | Y150: =Y$1 -> 2021 | Z150: =Z$1 -> 2022 | ... BB150: =BB$1 -> 2050 | BD150: =BD$1 -> 2015 | BE150: =BE$1 -> 2016 | BF150: =BF$1 -> 2017 | BG150: =BG$1 -> 2018 | BH150: =BH$1 -> 2019 | BI150: =BI$1 -> 2020 | BJ150: =BJ$1 -> 2021 | BK150: =BK$1 -> 2022 | ... CM150: =CM$1 -> 2050 | CO150: =CO$1 -> 2015 | CP150: =CP$1 -> 2016 | CQ150: =CQ$1 -> 2017 | CR150: =CR$1 -> 2018 | CS150: =CS$1 -> 2019 | CT150: =CT$1 -> 2020 | CU150: =CU$1 -> 2021 | CV150: =CV$1 -> 2022 | ... DX150: =DX$1 -> 2050 | DZ150: =DZ$1 -> 2015 | EA150: =EA$1 -> 2016 | EB150: =EB$1 -> 2017 | EC150: =EC$1 -> 2018 | ED150: =ED$1 -> 2019 | EE150: =EE$1 -> 2020 | EF150: =EF$1 -> 2021 | EG150: =EG$1 -> 2022 | ... FI150: =FI$1 -> 2050 | FK150: =FK$1 -> 2015 | FL150: =FL$1 -> 2016 | FM150: =FM$1 -> 2017 | FN150: =FN$1 -> 2018 | FO150: =FO$1 -> 2019 | FP150: =FP$1 -> 2020 | FQ150: =FQ$1 -> 2021 | FR150: =FR$1 -> 2022 | ... GT150: =GT$1 -> 2050 | GV150: =GV$1 -> 2015 | GW150: =GW$1 -> 2016 | GX150: =GX$1 -> 2017 | GY150: =GY$1 -> 2018 | GZ150: =GZ$1 -> 2019 | HA150: =HA$1 -> 2020 | HB150: =HB$1 -> 2021 | HC150: =HC$1 -> 2022 | ... IE150: =IE$1 -> 2050 | IG150: =IG$1 -> 2015 | IH150: =IH$1 -> 2016 | II150: =II$1 -> 2017 | IJ150: =IJ$1 -> 2018 | IK150: =IK$1 -> 2019 | IL150: =IL$1 -> 2020 | IM150: =IM$1 -> 2021 | IN150: =IN$1 -> 2022 | ... JP150: =JP$1 -> 2050 | JR150: =JR$1 -> 2015 | JS150: =JS$1 -> 2016 | JT150: =JT$1 -> 2017 | JU150: =JU$1 -> 2018 | JV150: =JV$1 -> 2019 | JW150: =JW$1 -> 2020 | JX150: =JX$1 -> 2021 | JY150: =JY$1 -> 2022 | ... LA150: =LA$1 -> 2050 | LC150: =LC$1 -> 2015 | LD150: =LD$1 -> 2016 | LE150: =LE$1 -> 2017 | LF150: =LF$1 -> 2018 | LG150: =LG$1 -> 2019 | LH150: =LH$1 -> 2020 | LI150: =LI$1 -> 2021 | LJ150: =LJ$1 -> 2022 | ... ML150: =ML$1 -> 2050
C151: Bureaux | E151: (milliers m²) | F151: A | BD151: =BE86 -> 220833 | BE151: =BD151+(BI151-BD151)*(BE1-BD1)/(BI1-BD1) -> 224489.13 | BF151: =BD151+(BI151-BD151)*(BF1-BD1)/(BI1-BD1) -> 228145.27 | BG151: =BD151+(BI151-BD151)*(BG1-BD1)/(BI1-BD1) -> 231801.4 | BH151: =BD151+(BI151-BD151)*(BH1-BD1)/(BI1-BD1) -> 235457.54 | BI151: =BF86 -> 239113.67 | BJ151: =BI151+(BS151-BI151)*(BJ1-BI1)/(BS1-BI1) -> 236880.4 | BK151: =BI151+(BS151-BI151)*(BK1-BI1)/(BS1-BI1) -> 234647.14 | BL151: =BI151+(BS151-BI151)*(BL1-BI1)/(BS1-BI1) -> 232413.87 | BM151: =BI151+(BS151-BI151)*(BM1-BI1)/(BS1-BI1) -> 230180.6 | BN151: =BI151+(BS151-BI151)*(BN1-BI1)/(BS1-BI1) -> 227947.33 | BO151: =BI151+(BS151-BI151)*(BO1-BI1)/(BS1-BI1) -> 225714.06 | BP151: =BI151+(BS151-BI151)*(BP1-BI1)/(BS1-BI1) -> 223480.79 | BQ151: =BI151+(BS151-BI151)*(BQ1-BI1)/(BS1-BI1) -> 221247.52 | BR151: =BI151+(BS151-BI151)*(BR1-BI1)/(BS1-BI1) -> 219014.25 | BS151: =BG86 -> 216780.99 | BT151: =BS151+(CC151-BS151)*(BT1-BS1)/(CC1-BS1) -> 215141.94 | BU151: =BS151+(CC151-BS151)*(BU1-BS1)/(CC1-BS1) -> 213502.89 | BV151: =BS151+(CC151-BS151)*(BV1-BS1)/(CC1-BS1) -> 211863.84 | BW151: =BS151+(CC151-BS151)*(BW1-BS1)/(CC1-BS1) -> 210224.79 | BX151: =BS151+(CC151-BS151)*(BX1-BS1)/(CC1-BS1) -> 208585.74 | BY151: =BS151+(CC151-BS151)*(BY1-BS1)/(CC1-BS1) -> 206946.69 | BZ151: =BS151+(CC151-BS151)*(BZ1-BS1)/(CC1-BS1) -> 205307.64 | CA151: =BS151+(CC151-BS151)*(CA1-BS1)/(CC1-BS1) -> 203668.59 | CB151: =BS151+(CC151-BS151)*(CB1-BS1)/(CC1-BS1) -> 202029.54 | CC151: =BH86 -> 200390.5 | CD151: =CC151+(CM151-CC151)*(CD1-CC1)/(CM1-CC1) -> 198685.41 | CE151: =CC151+(CM151-CC151)*(CE1-CC1)/(CM1-CC1) -> 196980.33 | CF151: =CC151+(CM151-CC151)*(CF1-CC1)/(CM1-CC1) -> 195275.25 | CG151: =CC151+(CM151-CC151)*(CG1-CC1)/(CM1-CC1) -> 193570.17 | CH151: =CC151+(CM151-CC151)*(CH1-CC1)/(CM1-CC1) -> 191865.09 | CI151: =CC151+(CM151-CC151)*(CI1-CC1)/(CM1-CC1) -> 190160 | CJ151: =CC151+(CM151-CC151)*(CJ1-CC1)/(CM1-CC1) -> 188454.92 | CK151: =CC151+(CM151-CC151)*(CK1-CC1)/(CM1-CC1) -> 186749.84 | CL151: =CC151+(CM151-CC151)*(CL1-CC1)/(CM1-CC1) -> 185044.76 | CM151: =BI86 -> 183339.68 | CO151: =CP86 -> 220833 | CP151: =CO151+(CT151-CO151)*(CP1-CO1)/(CT1-CO1) -> 224489.13 | CQ151: =CO151+(CT151-CO151)*(CQ1-CO1)/(CT1-CO1) -> 228145.27 | CR151: =CO151+(CT151-CO151)*(CR1-CO1)/(CT1-CO1) -> 231801.4 | CS151: =CO151+(CT151-CO151)*(CS1-CO1)/(CT1-CO1) -> 235457.54 | CT151: =CQ86 -> 239113.67 | CU151: =CT151+(DD151-CT151)*(CU1-CT1)/(DD1-CT1) -> 235810.1 | CV151: =CT151+(DD151-CT151)*(CV1-CT1)/(DD1-CT1) -> 232506.53 | CW151: =CT151+(DD151-CT151)*(CW1-CT1)/(DD1-CT1) -> 229202.96 | CX151: =CT151+(DD151-CT151)*(CX1-CT1)/(DD1-CT1) -> 225899.39 | CY151: =CT151+(DD151-CT151)*(CY1-CT1)/(DD1-CT1) -> 222595.82 | CZ151: =CT151+(DD151-CT151)*(CZ1-CT1)/(DD1-CT1) -> 219292.24 | DA151: =CT151+(DD151-CT151)*(DA1-CT1)/(DD1-CT1) -> 215988.67 | DB151: =CT151+(DD151-CT151)*(DB1-CT1)/(DD1-CT1) -> 212685.1 | DC151: =CT151+(DD151-CT151)*(DC1-CT1)/(DD1-CT1) -> 209381.53 | DD151: =CR86 -> 206077.96 | DE151: =DD151+(DN151-DD151)*(DE1-DD1)/(DN1-DD1) -> 203579.3 | DF151: =DD151+(DN151-DD151)*(DF1-DD1)/(DN1-DD1) -> 201080.65 | DG151: =DD151+(DN151-DD151)*(DG1-DD1)/(DN1-DD1) -> 198581.99 | DH151: =DD151+(DN151-DD151)*(DH1-DD1)/(DN1-DD1) -> 196083.34 | DI151: =DD151+(DN151-DD151)*(DI1-DD1)/(DN1-DD1) -> 193584.68 | DJ151: =DD151+(DN151-DD151)*(DJ1-DD1)/(DN1-DD1) -> 191086.03 | DK151: =DD151+(DN151-DD151)*(DK1-DD1)/(DN1-DD1) -> 188587.37 | DL151: =DD151+(DN151-DD151)*(DL1-DD1)/(DN1-DD1) -> 186088.72 | DM151: =DD151+(DN151-DD151)*(DM1-DD1)/(DN1-DD1) -> 183590.06 | DN151: =CS86 -> 181091.4 | DO151: =DN151+(DX151-DN151)*(DO1-DN1)/(DX1-DN1) -> 178732.52 | DP151: =DN151+(DX151-DN151)*(DP1-DN1)/(DX1-DN1) -> 176373.63 | DQ151: =DN151+(DX151-DN151)*(DQ1-DN1)/(DX1-DN1) -> 174014.74 | DR151: =DN151+(DX151-DN151)*(DR1-DN1)/(DX1-DN1) -> 171655.86 | DS151: =DN151+(DX151-DN151)*(DS1-DN1)/(DX1-DN1) -> 169296.97 | DT151: =DN151+(DX151-DN151)*(DT1-DN1)/(DX1-DN1) -> 166938.08 | DU151: =DN151+(DX151-DN151)*(DU1-DN1)/(DX1-DN1) -> 164579.19 | DV151: =DN151+(DX151-DN151)*(DV1-DN1)/(DX1-DN1) -> 162220.31 | DW151: =DN151+(DX151-DN151)*(DW1-DN1)/(DX1-DN1) -> 159861.42 | DX151: =CT86 -> 157502.53 | DZ151: =EA86 -> 220833 | EA151: =DZ151+(EE151-DZ151)*(EA1-DZ1)/(EE1-DZ1) -> 224489.13 | EB151: =DZ151+(EE151-DZ151)*(EB1-DZ1)/(EE1-DZ1) -> 228145.27 | EC151: =DZ151+(EE151-DZ151)*(EC1-DZ1)/(EE1-DZ1) -> 231801.4 | ED151: =DZ151+(EE151-DZ151)*(ED1-DZ1)/(EE1-DZ1) -> 235457.54 | EE151: =EB86 -> 239113.67 | EF151: =EE151+(EO151-EE151)*(EF1-EE1)/(EO1-EE1) -> 235810.1 | EG151: =EE151+(EO151-EE151)*(EG1-EE1)/(EO1-EE1) -> 232506.53 | EH151: =EE151+(EO151-EE151)*(EH1-EE1)/(EO1-EE1) -> 229202.96 | EI151: =EE151+(EO151-EE151)*(EI1-EE1)/(EO1-EE1) -> 225899.39 | EJ151: =EE151+(EO151-EE151)*(EJ1-EE1)/(EO1-EE1) -> 222595.82 | EK151: =EE151+(EO151-EE151)*(EK1-EE1)/(EO1-EE1) -> 219292.24 | EL151: =EE151+(EO151-EE151)*(EL1-EE1)/(EO1-EE1) -> 215988.67 | EM151: =EE151+(EO151-EE151)*(EM1-EE1)/(EO1-EE1) -> 212685.1 | EN151: =EE151+(EO151-EE151)*(EN1-EE1)/(EO1-EE1) -> 209381.53 | EO151: =EC86 -> 206077.96 | EP151: =EO151+(EY151-EO151)*(EP1-EO1)/(EY1-EO1) -> 203579.3 | EQ151: =EO151+(EY151-EO151)*(EQ1-EO1)/(EY1-EO1) -> 201080.65 | ER151: =EO151+(EY151-EO151)*(ER1-EO1)/(EY1-EO1) -> 198581.99 | ES151: =EO151+(EY151-EO151)*(ES1-EO1)/(EY1-EO1) -> 196083.34 | ET151: =EO151+(EY151-EO151)*(ET1-EO1)/(EY1-EO1) -> 193584.68 | EU151: =EO151+(EY151-EO151)*(EU1-EO1)/(EY1-EO1) -> 191086.03 | EV151: =EO151+(EY151-EO151)*(EV1-EO1)/(EY1-EO1) -> 188587.37 | EW151: =EO151+(EY151-EO151)*(EW1-EO1)/(EY1-EO1) -> 186088.72 | EX151: =EO151+(EY151-EO151)*(EX1-EO1)/(EY1-EO1) -> 183590.06 | EY151: =ED86 -> 181091.4 | EZ151: =EY151+(FI151-EY151)*(EZ1-EY1)/(FI1-EY1) -> 178732.52 | FA151: =EY151+(FI151-EY151)*(FA1-EY1)/(FI1-EY1) -> 176373.63 | FB151: =EY151+(FI151-EY151)*(FB1-EY1)/(FI1-EY1) -> 174014.74 | FC151: =EY151+(FI151-EY151)*(FC1-EY1)/(FI1-EY1) -> 171655.86 | FD151: =EY151+(FI151-EY151)*(FD1-EY1)/(FI1-EY1) -> 169296.97 | FE151: =EY151+(FI151-EY151)*(FE1-EY1)/(FI1-EY1) -> 166938.08 | FF151: =EY151+(FI151-EY151)*(FF1-EY1)/(FI1-EY1) -> 164579.19 | FG151: =EY151+(FI151-EY151)*(FG1-EY1)/(FI1-EY1) -> 162220.31 | FH151: =EY151+(FI151-EY151)*(FH1-EY1)/(FI1-EY1) -> 159861.42 | FI151: =EE86 -> 157502.53 | FK151: =FL86 -> 220833 | FL151: =FK151+(FP151-FK151)*(FL1-FK1)/(FP1-FK1) -> 224489.13 | FM151: =FK151+(FP151-FK151)*(FM1-FK1)/(FP1-FK1) -> 228145.27 | FN151: =FK151+(FP151-FK151)*(FN1-FK1)/(FP1-FK1) -> 231801.4 | FO151: =FK151+(FP151-FK151)*(FO1-FK1)/(FP1-FK1) -> 235457.54 | FP151: =FM86 -> 239113.67 | FQ151: =FP151+(FZ151-FP151)*(FQ1-FP1)/(FZ1-FP1) -> 236880.4 | FR151: =FP151+(FZ151-FP151)*(FR1-FP1)/(FZ1-FP1) -> 234647.14 | FS151: =FP151+(FZ151-FP151)*(FS1-FP1)/(FZ1-FP1) -> 232413.87 | FT151: =FP151+(FZ151-FP151)*(FT1-FP1)/(FZ1-FP1) -> 230180.6 | FU151: =FP151+(FZ151-FP151)*(FU1-FP1)/(FZ1-FP1) -> 227947.33 | FV151: =FP151+(FZ151-FP151)*(FV1-FP1)/(FZ1-FP1) -> 225714.06 | FW151: =FP151+(FZ151-FP151)*(FW1-FP1)/(FZ1-FP1) -> 223480.79 | FX151: =FP151+(FZ151-FP151)*(FX1-FP1)/(FZ1-FP1) -> 221247.52 | FY151: =FP151+(FZ151-FP151)*(FY1-FP1)/(FZ1-FP1) -> 219014.25 | FZ151: =FN86 -> 216780.99 | GA151: =FZ151+(GJ151-FZ151)*(GA1-FZ1)/(GJ1-FZ1) -> 215141.94 | GB151: =FZ151+(GJ151-FZ151)*(GB1-FZ1)/(GJ1-FZ1) -> 213502.89 | GC151: =FZ151+(GJ151-FZ151)*(GC1-FZ1)/(GJ1-FZ1) -> 211863.84 | GD151: =FZ151+(GJ151-FZ151)*(GD1-FZ1)/(GJ1-FZ1) -> 210224.79 | GE151: =FZ151+(GJ151-FZ151)*(GE1-FZ1)/(GJ1-FZ1) -> 208585.74 | GF151: =FZ151+(GJ151-FZ151)*(GF1-FZ1)/(GJ1-FZ1) -> 206946.69 | GG151: =FZ151+(GJ151-FZ151)*(GG1-FZ1)/(GJ1-FZ1) -> 205307.64 | GH151: =FZ151+(GJ151-FZ151)*(GH1-FZ1)/(GJ1-FZ1) -> 203668.59 | GI151: =FZ151+(GJ151-FZ151)*(GI1-FZ1)/(GJ1-FZ1) -> 202029.54 | GJ151: =FO86 -> 200390.5 | GK151: =GJ151+(GT151-GJ151)*(GK1-GJ1)/(GT1-GJ1) -> 198685.41 | GL151: =GJ151+(GT151-GJ151)*(GL1-GJ1)/(GT1-GJ1) -> 196980.33 | GM151: =GJ151+(GT151-GJ151)*(GM1-GJ1)/(GT1-GJ1) -> 195275.25 | GN151: =GJ151+(GT151-GJ151)*(GN1-GJ1)/(GT1-GJ1) -> 193570.17 | GO151: =GJ151+(GT151-GJ151)*(GO1-GJ1)/(GT1-GJ1) -> 191865.09 | GP151: =GJ151+(GT151-GJ151)*(GP1-GJ1)/(GT1-GJ1) -> 190160 | GQ151: =GJ151+(GT151-GJ151)*(GQ1-GJ1)/(GT1-GJ1) -> 188454.92 | GR151: =GJ151+(GT151-GJ151)*(GR1-GJ1)/(GT1-GJ1) -> 186749.84 | GS151: =GJ151+(GT151-GJ151)*(GS1-GJ1)/(GT1-GJ1) -> 185044.76 | GT151: =FP86 -> 183339.68 | GV151: =GW86 -> 220833 | GW151: =GV151+(HA151-GV151)*(GW1-GV1)/(HA1-GV1) -> 224489.13 | GX151: =GV151+(HA151-GV151)*(GX1-GV1)/(HA1-GV1) -> 228145.27 | GY151: =GV151+(HA151-GV151)*(GY1-GV1)/(HA1-GV1) -> 231801.4 | GZ151: =GV151+(HA151-GV151)*(GZ1-GV1)/(HA1-GV1) -> 235457.54 | HA151: =GX86 -> 239113.67 | HB151: =HA151+(HK151-HA151)*(HB1-HA1)/(HK1-HA1) -> 236880.4 | HC151: =HA151+(HK151-HA151)*(HC1-HA1)/(HK1-HA1) -> 234647.14 | HD151: =HA151+(HK151-HA151)*(HD1-HA1)/(HK1-HA1) -> 232413.87 | HE151: =HA151+(HK151-HA151)*(HE1-HA1)/(HK1-HA1) -> 230180.6 | HF151: =HA151+(HK151-HA151)*(HF1-HA1)/(HK1-HA1) -> 227947.33 | HG151: =HA151+(HK151-HA151)*(HG1-HA1)/(HK1-HA1) -> 225714.06 | HH151: =HA151+(HK151-HA151)*(HH1-HA1)/(HK1-HA1) -> 223480.79 | HI151: =HA151+(HK151-HA151)*(HI1-HA1)/(HK1-HA1) -> 221247.52 | HJ151: =HA151+(HK151-HA151)*(HJ1-HA1)/(HK1-HA1) -> 219014.25 | HK151: =GY86 -> 216780.99 | HL151: =HK151+(HU151-HK151)*(HL1-HK1)/(HU1-HK1) -> 215141.94 | HM151: =HK151+(HU151-HK151)*(HM1-HK1)/(HU1-HK1) -> 213502.89 | HN151: =HK151+(HU151-HK151)*(HN1-HK1)/(HU1-HK1) -> 211863.84 | HO151: =HK151+(HU151-HK151)*(HO1-HK1)/(HU1-HK1) -> 210224.79 | HP151: =HK151+(HU151-HK151)*(HP1-HK1)/(HU1-HK1) -> 208585.74 | HQ151: =HK151+(HU151-HK151)*(HQ1-HK1)/(HU1-HK1) -> 206946.69 | HR151: =HK151+(HU151-HK151)*(HR1-HK1)/(HU1-HK1) -> 205307.64 | HS151: =HK151+(HU151-HK151)*(HS1-HK1)/(HU1-HK1) -> 203668.59 | HT151: =HK151+(HU151-HK151)*(HT1-HK1)/(HU1-HK1) -> 202029.54 | HU151: =GZ86 -> 200390.5 | HV151: =HU151+(IE151-HU151)*(HV1-HU1)/(IE1-HU1) -> 198685.41 | HW151: =HU151+(IE151-HU151)*(HW1-HU1)/(IE1-HU1) -> 196980.33 | HX151: =HU151+(IE151-HU151)*(HX1-HU1)/(IE1-HU1) -> 195275.25 | HY151: =HU151+(IE151-HU151)*(HY1-HU1)/(IE1-HU1) -> 193570.17 | HZ151: =HU151+(IE151-HU151)*(HZ1-HU1)/(IE1-HU1) -> 191865.09 | IA151: =HU151+(IE151-HU151)*(IA1-HU1)/(IE1-HU1) -> 190160 | IB151: =HU151+(IE151-HU151)*(IB1-HU1)/(IE1-HU1) -> 188454.92 | IC151: =HU151+(IE151-HU151)*(IC1-HU1)/(IE1-HU1) -> 186749.84 | ID151: =HU151+(IE151-HU151)*(ID1-HU1)/(IE1-HU1) -> 185044.76 | IE151: =HA86 -> 183339.68 | IL151: 234167.92 | IV151: 238650.56 | JF151: 236777.1 | JP151: 229656.87 | JW151: 234167.92 | JX151: =$JW151+($KG151-$JW151)*(JX$1-$JW$1)/($KG$1-$JW$1) -> 234282.98 | JY151: =$JW151+($KG151-$JW151)*(JY$1-$JW$1)/($KG$1-$JW$1) -> 234398.05 | JZ151: =$JW151+($KG151-$JW151)*(JZ$1-$JW$1)/($KG$1-$JW$1) -> 234513.11 | KA151: =$JW151+($KG151-$JW151)*(KA$1-$JW$1)/($KG$1-$JW$1) -> 234628.17 | KB151: =$JW151+($KG151-$JW151)*(KB$1-$JW$1)/($KG$1-$JW$1) -> 234743.24 | KC151: =$JW151+($KG151-$JW151)*(KC$1-$JW$1)/($KG$1-$JW$1) -> 234858.3 | KD151: =$JW151+($KG151-$JW151)*(KD$1-$JW$1)/($KG$1-$JW$1) -> 234973.36 | KE151: =$JW151+($KG151-$JW151)*(KE$1-$JW$1)/($KG$1-$JW$1) -> 235088.43 | KF151: =$JW151+($KG151-$JW151)*(KF$1-$JW$1)/($KG$1-$JW$1) -> 235203.49 | KG151: 235318.55 | KH151: =$KG151+($KQ151-$KG151)*(KH$1-$KG$1)/($KQ$1-$KG$1) -> 234561.14 | KI151: =$KG151+($KQ151-$KG151)*(KI$1-$KG$1)/($KQ$1-$KG$1) -> 233803.72 | KJ151: =$KG151+($KQ151-$KG151)*(KJ$1-$KG$1)/($KQ$1-$KG$1) -> 233046.3 | KK151: =$KG151+($KQ151-$KG151)*(KK$1-$KG$1)/($KQ$1-$KG$1) -> 232288.89 | KL151: =$KG151+($KQ151-$KG151)*(KL$1-$KG$1)/($KQ$1-$KG$1) -> 231531.47 | KM151: =$KG151+($KQ151-$KG151)*(KM$1-$KG$1)/($KQ$1-$KG$1) -> 230774.06 | KN151: =$KG151+($KQ151-$KG151)*(KN$1-$KG$1)/($KQ$1-$KG$1) -> 230016.64 | KO151: =$KG151+($KQ151-$KG151)*(KO$1-$KG$1)/($KQ$1-$KG$1) -> 229259.22 | KP151: =$KG151+($KQ151-$KG151)*(KP$1-$KG$1)/($KQ$1-$KG$1) -> 228501.81 | KQ151: 227744.39 | KR151: =$KQ151+($LA151-$KQ151)*(KR$1-$KQ$1)/($LA$1-$KQ$1) -> 226539.85 | KS151: =$KQ151+($LA151-$KQ151)*(KS$1-$KQ$1)/($LA$1-$KQ$1) -> 225335.3 | KT151: =$KQ151+($LA151-$KQ151)*(KT$1-$KQ$1)/($LA$1-$KQ$1) -> 224130.76 | KU151: =$KQ151+($LA151-$KQ151)*(KU$1-$KQ$1)/($LA$1-$KQ$1) -> 222926.22 | KV151: =$KQ151+($LA151-$KQ151)*(KV$1-$KQ$1)/($LA$1-$KQ$1) -> 221721.67 | KW151: =$KQ151+($LA151-$KQ151)*(KW$1-$KQ$1)/($LA$1-$KQ$1) -> 220517.13 | KX151: =$KQ151+($LA151-$KQ151)*(KX$1-$KQ$1)/($LA$1-$KQ$1) -> 219312.59 | KY151: =$KQ151+($LA151-$KQ151)*(KY$1-$KQ$1)/($LA$1-$KQ$1) -> 218108.04 | KZ151: =$KQ151+($LA151-$KQ151)*(KZ$1-$KQ$1)/($LA$1-$KQ$1) -> 216903.5 | LA151: 215698.95
C152: Cafés-hôtels-restaurants | E152: " | F152: " | BD152: =BE87 -> 64402 | BE152: =BD152+(BI152-BD152)*(BE1-BD1)/(BI1-BD1) -> 64999.58 | BF152: =BD152+(BI152-BD152)*(BF1-BD1)/(BI1-BD1) -> 65597.161 | BG152: =BD152+(BI152-BD152)*(BG1-BD1)/(BI1-BD1) -> 66194.741 | BH152: =BD152+(BI152-BD152)*(BH1-BD1)/(BI1-BD1) -> 66792.321 | BI152: =BF87 -> 67389.902 | BJ152: =BI152+(BS152-BI152)*(BJ1-BI1)/(BS1-BI1) -> 68099.683 | BK152: =BI152+(BS152-BI152)*(BK1-BI1)/(BS1-BI1) -> 68809.465 | BL152: =BI152+(BS152-BI152)*(BL1-BI1)/(BS1-BI1) -> 69519.246 | BM152: =BI152+(BS152-BI152)*(BM1-BI1)/(BS1-BI1) -> 70229.028 | BN152: =BI152+(BS152-BI152)*(BN1-BI1)/(BS1-BI1) -> 70938.81 | BO152: =BI152+(BS152-BI152)*(BO1-BI1)/(BS1-BI1) -> 71648.591 | BP152: =BI152+(BS152-BI152)*(BP1-BI1)/(BS1-BI1) -> 72358.373 | BQ152: =BI152+(BS152-BI152)*(BQ1-BI1)/(BS1-BI1) -> 73068.154 | BR152: =BI152+(BS152-BI152)*(BR1-BI1)/(BS1-BI1) -> 73777.936 | BS152: =BG87 -> 74487.718 | BT152: =BS152+(CC152-BS152)*(BT1-BS1)/(CC1-BS1) -> 75241.579 | BU152: =BS152+(CC152-BS152)*(BU1-BS1)/(CC1-BS1) -> 75995.441 | BV152: =BS152+(CC152-BS152)*(BV1-BS1)/(CC1-BS1) -> 76749.302 | BW152: =BS152+(CC152-BS152)*(BW1-BS1)/(CC1-BS1) -> 77503.164 | BX152: =BS152+(CC152-BS152)*(BX1-BS1)/(CC1-BS1) -> 78257.025 | BY152: =BS152+(CC152-BS152)*(BY1-BS1)/(CC1-BS1) -> 79010.887 | BZ152: =BS152+(CC152-BS152)*(BZ1-BS1)/(CC1-BS1) -> 79764.749 | CA152: =BS152+(CC152-BS152)*(CA1-BS1)/(CC1-BS1) -> 80518.61 | CB152: =BS152+(CC152-BS152)*(CB1-BS1)/(CC1-BS1) -> 81272.472 | CC152: =BH87 -> 82026.333 | CD152: =CC152+(CM152-CC152)*(CD1-CC1)/(CM1-CC1) -> 82763.861 | CE152: =CC152+(CM152-CC152)*(CE1-CC1)/(CM1-CC1) -> 83501.389 | CF152: =CC152+(CM152-CC152)*(CF1-CC1)/(CM1-CC1) -> 84238.916 | CG152: =CC152+(CM152-CC152)*(CG1-CC1)/(CM1-CC1) -> 84976.444 | CH152: =CC152+(CM152-CC152)*(CH1-CC1)/(CM1-CC1) -> 85713.972 | CI152: =CC152+(CM152-CC152)*(CI1-CC1)/(CM1-CC1) -> 86451.499 | CJ152: =CC152+(CM152-CC152)*(CJ1-CC1)/(CM1-CC1) -> 87189.027 | CK152: =CC152+(CM152-CC152)*(CK1-CC1)/(CM1-CC1) -> 87926.555 | CL152: =CC152+(CM152-CC152)*(CL1-CC1)/(CM1-CC1) -> 88664.083 | CM152: =BI87 -> 89401.61 | CO152: =CP87 -> 64402 | CP152: =CO152+(CT152-CO152)*(CP1-CO1)/(CT1-CO1) -> 64999.58 | CQ152: =CO152+(CT152-CO152)*(CQ1-CO1)/(CT1-CO1) -> 65597.161 | CR152: =CO152+(CT152-CO152)*(CR1-CO1)/(CT1-CO1) -> 66194.741 | CS152: =CO152+(CT152-CO152)*(CS1-CO1)/(CT1-CO1) -> 66792.321 | CT152: =CQ87 -> 67389.902 | CU152: =CT152+(DD152-CT152)*(CU1-CT1)/(DD1-CT1) -> 67063.379 | CV152: =CT152+(DD152-CT152)*(CV1-CT1)/(DD1-CT1) -> 66736.856 | CW152: =CT152+(DD152-CT152)*(CW1-CT1)/(DD1-CT1) -> 66410.334 | CX152: =CT152+(DD152-CT152)*(CX1-CT1)/(DD1-CT1) -> 66083.811 | CY152: =CT152+(DD152-CT152)*(CY1-CT1)/(DD1-CT1) -> 65757.288 | CZ152: =CT152+(DD152-CT152)*(CZ1-CT1)/(DD1-CT1) -> 65430.766 | DA152: =CT152+(DD152-CT152)*(DA1-CT1)/(DD1-CT1) -> 65104.243 | DB152: =CT152+(DD152-CT152)*(DB1-CT1)/(DD1-CT1) -> 64777.72 | DC152: =CT152+(DD152-CT152)*(DC1-CT1)/(DD1-CT1) -> 64451.197 | DD152: =CR87 -> 64124.675 | DE152: =DD152+(DN152-DD152)*(DE1-DD1)/(DN1-DD1) -> 63791.238 | DF152: =DD152+(DN152-DD152)*(DF1-DD1)/(DN1-DD1) -> 63457.801 | DG152: =DD152+(DN152-DD152)*(DG1-DD1)/(DN1-DD1) -> 63124.364 | DH152: =DD152+(DN152-DD152)*(DH1-DD1)/(DN1-DD1) -> 62790.927 | DI152: =DD152+(DN152-DD152)*(DI1-DD1)/(DN1-DD1) -> 62457.49 | DJ152: =DD152+(DN152-DD152)*(DJ1-DD1)/(DN1-DD1) -> 62124.052 | DK152: =DD152+(DN152-DD152)*(DK1-DD1)/(DN1-DD1) -> 61790.615 | DL152: =DD152+(DN152-DD152)*(DL1-DD1)/(DN1-DD1) -> 61457.178 | DM152: =DD152+(DN152-DD152)*(DM1-DD1)/(DN1-DD1) -> 61123.741 | DN152: =CS87 -> 60790.304 | DO152: =DN152+(DX152-DN152)*(DO1-DN1)/(DX1-DN1) -> 60415.108 | DP152: =DN152+(DX152-DN152)*(DP1-DN1)/(DX1-DN1) -> 60039.911 | DQ152: =DN152+(DX152-DN152)*(DQ1-DN1)/(DX1-DN1) -> 59664.715 | DR152: =DN152+(DX152-DN152)*(DR1-DN1)/(DX1-DN1) -> 59289.518 | DS152: =DN152+(DX152-DN152)*(DS1-DN1)/(DX1-DN1) -> 58914.321 | DT152: =DN152+(DX152-DN152)*(DT1-DN1)/(DX1-DN1) -> 58539.125 | DU152: =DN152+(DX152-DN152)*(DU1-DN1)/(DX1-DN1) -> 58163.928 | DV152: =DN152+(DX152-DN152)*(DV1-DN1)/(DX1-DN1) -> 57788.732 | DW152: =DN152+(DX152-DN152)*(DW1-DN1)/(DX1-DN1) -> 57413.535 | DX152: =CT87 -> 57038.339 | DZ152: =EA87 -> 64402 | EA152: =DZ152+(EE152-DZ152)*(EA1-DZ1)/(EE1-DZ1) -> 64999.58 | EB152: =DZ152+(EE152-DZ152)*(EB1-DZ1)/(EE1-DZ1) -> 65597.161 | EC152: =DZ152+(EE152-DZ152)*(EC1-DZ1)/(EE1-DZ1) -> 66194.741 | ED152: =DZ152+(EE152-DZ152)*(ED1-DZ1)/(EE1-DZ1) -> 66792.321 | EE152: =EB87 -> 67389.902 | EF152: =EE152+(EO152-EE152)*(EF1-EE1)/(EO1-EE1) -> 67063.379 | EG152: =EE152+(EO152-EE152)*(EG1-EE1)/(EO1-EE1) -> 66736.856 | EH152: =EE152+(EO152-EE152)*(EH1-EE1)/(EO1-EE1) -> 66410.334 | EI152: =EE152+(EO152-EE152)*(EI1-EE1)/(EO1-EE1) -> 66083.811 | EJ152: =EE152+(EO152-EE152)*(EJ1-EE1)/(EO1-EE1) -> 65757.288 | EK152: =EE152+(EO152-EE152)*(EK1-EE1)/(EO1-EE1) -> 65430.766 | EL152: =EE152+(EO152-EE152)*(EL1-EE1)/(EO1-EE1) -> 65104.243 | EM152: =EE152+(EO152-EE152)*(EM1-EE1)/(EO1-EE1) -> 64777.72 | EN152: =EE152+(EO152-EE152)*(EN1-EE1)/(EO1-EE1) -> 64451.197 | EO152: =EC87 -> 64124.675 | EP152: =EO152+(EY152-EO152)*(EP1-EO1)/(EY1-EO1) -> 63791.238 | EQ152: =EO152+(EY152-EO152)*(EQ1-EO1)/(EY1-EO1) -> 63457.801 | ER152: =EO152+(EY152-EO152)*(ER1-EO1)/(EY1-EO1) -> 63124.364 | ES152: =EO152+(EY152-EO152)*(ES1-EO1)/(EY1-EO1) -> 62790.927 | ET152: =EO152+(EY152-EO152)*(ET1-EO1)/(EY1-EO1) -> 62457.49 | EU152: =EO152+(EY152-EO152)*(EU1-EO1)/(EY1-EO1) -> 62124.052 | EV152: =EO152+(EY152-EO152)*(EV1-EO1)/(EY1-EO1) -> 61790.615 | EW152: =EO152+(EY152-EO152)*(EW1-EO1)/(EY1-EO1) -> 61457.178 | EX152: =EO152+(EY152-EO152)*(EX1-EO1)/(EY1-EO1) -> 61123.741 | EY152: =ED87 -> 60790.304 | EZ152: =EY152+(FI152-EY152)*(EZ1-EY1)/(FI1-EY1) -> 60415.108 | FA152: =EY152+(FI152-EY152)*(FA1-EY1)/(FI1-EY1) -> 60039.911 | FB152: =EY152+(FI152-EY152)*(FB1-EY1)/(FI1-EY1) -> 59664.715 | FC152: =EY152+(FI152-EY152)*(FC1-EY1)/(FI1-EY1) -> 59289.518 | FD152: =EY152+(FI152-EY152)*(FD1-EY1)/(FI1-EY1) -> 58914.321 | FE152: =EY152+(FI152-EY152)*(FE1-EY1)/(FI1-EY1) -> 58539.125 | FF152: =EY152+(FI152-EY152)*(FF1-EY1)/(FI1-EY1) -> 58163.928 | FG152: =EY152+(FI152-EY152)*(FG1-EY1)/(FI1-EY1) -> 57788.732 | FH152: =EY152+(FI152-EY152)*(FH1-EY1)/(FI1-EY1) -> 57413.535 | FI152: =EE87 -> 57038.339 | FK152: =FL87 -> 64402 | FL152: =FK152+(FP152-FK152)*(FL1-FK1)/(FP1-FK1) -> 64999.58 | FM152: =FK152+(FP152-FK152)*(FM1-FK1)/(FP1-FK1) -> 65597.161 | FN152: =FK152+(FP152-FK152)*(FN1-FK1)/(FP1-FK1) -> 66194.741 | FO152: =FK152+(FP152-FK152)*(FO1-FK1)/(FP1-FK1) -> 66792.321 | FP152: =FM87 -> 67389.902 | FQ152: =FP152+(FZ152-FP152)*(FQ1-FP1)/(FZ1-FP1) -> 67564.763 | FR152: =FP152+(FZ152-FP152)*(FR1-FP1)/(FZ1-FP1) -> 67739.624 | FS152: =FP152+(FZ152-FP152)*(FS1-FP1)/(FZ1-FP1) -> 67914.484 | FT152: =FP152+(FZ152-FP152)*(FT1-FP1)/(FZ1-FP1) -> 68089.345 | FU152: =FP152+(FZ152-FP152)*(FU1-FP1)/(FZ1-FP1) -> 68264.206 | FV152: =FP152+(FZ152-FP152)*(FV1-FP1)/(FZ1-FP1) -> 68439.067 | FW152: =FP152+(FZ152-FP152)*(FW1-FP1)/(FZ1-FP1) -> 68613.928 | FX152: =FP152+(FZ152-FP152)*(FX1-FP1)/(FZ1-FP1) -> 68788.789 | FY152: =FP152+(FZ152-FP152)*(FY1-FP1)/(FZ1-FP1) -> 68963.65 | FZ152: =FN87 -> 69138.511 | GA152: =FZ152+(GJ152-FZ152)*(GA1-FZ1)/(GJ1-FZ1) -> 69291.479 | GB152: =FZ152+(GJ152-FZ152)*(GB1-FZ1)/(GJ1-FZ1) -> 69444.448 | GC152: =FZ152+(GJ152-FZ152)*(GC1-FZ1)/(GJ1-FZ1) -> 69597.417 | GD152: =FZ152+(GJ152-FZ152)*(GD1-FZ1)/(GJ1-FZ1) -> 69750.385 | GE152: =FZ152+(GJ152-FZ152)*(GE1-FZ1)/(GJ1-FZ1) -> 69903.354 | GF152: =FZ152+(GJ152-FZ152)*(GF1-FZ1)/(GJ1-FZ1) -> 70056.322 | GG152: =FZ152+(GJ152-FZ152)*(GG1-FZ1)/(GJ1-FZ1) -> 70209.291 | GH152: =FZ152+(GJ152-FZ152)*(GH1-FZ1)/(GJ1-FZ1) -> 70362.259 | GI152: =FZ152+(GJ152-FZ152)*(GI1-FZ1)/(GJ1-FZ1) -> 70515.228 | GJ152: =FO87 -> 70668.197 | GK152: =GJ152+(GT152-GJ152)*(GK1-GJ1)/(GT1-GJ1) -> 70750.477 | GL152: =GJ152+(GT152-GJ152)*(GL1-GJ1)/(GT1-GJ1) -> 70832.758 | GM152: =GJ152+(GT152-GJ152)*(GM1-GJ1)/(GT1-GJ1) -> 70915.039 | GN152: =GJ152+(GT152-GJ152)*(GN1-GJ1)/(GT1-GJ1) -> 70997.32 | GO152: =GJ152+(GT152-GJ152)*(GO1-GJ1)/(GT1-GJ1) -> 71079.601 | GP152: =GJ152+(GT152-GJ152)*(GP1-GJ1)/(GT1-GJ1) -> 71161.882 | GQ152: =GJ152+(GT152-GJ152)*(GQ1-GJ1)/(GT1-GJ1) -> 71244.163 | GR152: =GJ152+(GT152-GJ152)*(GR1-GJ1)/(GT1-GJ1) -> 71326.444 | GS152: =GJ152+(GT152-GJ152)*(GS1-GJ1)/(GT1-GJ1) -> 71408.724 | GT152: =FP87 -> 71491.005 | GV152: =GW87 -> 64402 | GW152: =GV152+(HA152-GV152)*(GW1-GV1)/(HA1-GV1) -> 64999.58 | GX152: =GV152+(HA152-GV152)*(GX1-GV1)/(HA1-GV1) -> 65597.161 | GY152: =GV152+(HA152-GV152)*(GY1-GV1)/(HA1-GV1) -> 66194.741 | GZ152: =GV152+(HA152-GV152)*(GZ1-GV1)/(HA1-GV1) -> 66792.321 | HA152: =GX87 -> 67389.902 | HB152: =HA152+(HK152-HA152)*(HB1-HA1)/(HK1-HA1) -> 68099.683 | HC152: =HA152+(HK152-HA152)*(HC1-HA1)/(HK1-HA1) -> 68809.465 | HD152: =HA152+(HK152-HA152)*(HD1-HA1)/(HK1-HA1) -> 69519.246 | HE152: =HA152+(HK152-HA152)*(HE1-HA1)/(HK1-HA1) -> 70229.028 | HF152: =HA152+(HK152-HA152)*(HF1-HA1)/(HK1-HA1) -> 70938.81 | HG152: =HA152+(HK152-HA152)*(HG1-HA1)/(HK1-HA1) -> 71648.591 | HH152: =HA152+(HK152-HA152)*(HH1-HA1)/(HK1-HA1) -> 72358.373 | HI152: =HA152+(HK152-HA152)*(HI1-HA1)/(HK1-HA1) -> 73068.154 | HJ152: =HA152+(HK152-HA152)*(HJ1-HA1)/(HK1-HA1) -> 73777.936 | HK152: =GY87 -> 74487.718 | HL152: =HK152+(HU152-HK152)*(HL1-HK1)/(HU1-HK1) -> 75241.579 | HM152: =HK152+(HU152-HK152)*(HM1-HK1)/(HU1-HK1) -> 75995.441 | HN152: =HK152+(HU152-HK152)*(HN1-HK1)/(HU1-HK1) -> 76749.302 | HO152: =HK152+(HU152-HK152)*(HO1-HK1)/(HU1-HK1) -> 77503.164 | HP152: =HK152+(HU152-HK152)*(HP1-HK1)/(HU1-HK1) -> 78257.025 | HQ152: =HK152+(HU152-HK152)*(HQ1-HK1)/(HU1-HK1) -> 79010.887 | HR152: =HK152+(HU152-HK152)*(HR1-HK1)/(HU1-HK1) -> 79764.749 | HS152: =HK152+(HU152-HK152)*(HS1-HK1)/(HU1-HK1) -> 80518.61 | HT152: =HK152+(HU152-HK152)*(HT1-HK1)/(HU1-HK1) -> 81272.472 | HU152: =GZ87 -> 82026.333 | HV152: =HU152+(IE152-HU152)*(HV1-HU1)/(IE1-HU1) -> 82763.861 | HW152: =HU152+(IE152-HU152)*(HW1-HU1)/(IE1-HU1) -> 83501.389 | HX152: =HU152+(IE152-HU152)*(HX1-HU1)/(IE1-HU1) -> 84238.916 | HY152: =HU152+(IE152-HU152)*(HY1-HU1)/(IE1-HU1) -> 84976.444 | HZ152: =HU152+(IE152-HU152)*(HZ1-HU1)/(IE1-HU1) -> 85713.972 | IA152: =HU152+(IE152-HU152)*(IA1-HU1)/(IE1-HU1) -> 86451.499 | IB152: =HU152+(IE152-HU152)*(IB1-HU1)/(IE1-HU1) -> 87189.027 | IC152: =HU152+(IE152-HU152)*(IC1-HU1)/(IE1-HU1) -> 87926.555 | ID152: =HU152+(IE152-HU152)*(ID1-HU1)/(IE1-HU1) -> 88664.083 | IE152: =HA87 -> 89401.61 | IL152: 58010.28 | IV152: 59239.239 | JF152: 59962.716 | JP152: 59335.641 | JW152: 58010.28 | JX152: =$JW152+($KG152-$JW152)*(JX$1-$JW$1)/($KG$1-$JW$1) -> 58062.196 | JY152: =$JW152+($KG152-$JW152)*(JY$1-$JW$1)/($KG$1-$JW$1) -> 58114.112 | JZ152: =$JW152+($KG152-$JW152)*(JZ$1-$JW$1)/($KG$1-$JW$1) -> 58166.029 | KA152: =$JW152+($KG152-$JW152)*(KA$1-$JW$1)/($KG$1-$JW$1) -> 58217.945 | KB152: =$JW152+($KG152-$JW152)*(KB$1-$JW$1)/($KG$1-$JW$1) -> 58269.861 | KC152: =$JW152+($KG152-$JW152)*(KC$1-$JW$1)/($KG$1-$JW$1) -> 58321.778 | KD152: =$JW152+($KG152-$JW152)*(KD$1-$JW$1)/($KG$1-$JW$1) -> 58373.694 | KE152: =$JW152+($KG152-$JW152)*(KE$1-$JW$1)/($KG$1-$JW$1) -> 58425.61 | KF152: =$JW152+($KG152-$JW152)*(KF$1-$JW$1)/($KG$1-$JW$1) -> 58477.526 | KG152: 58529.443 | KH152: =$KG152+($KQ152-$KG152)*(KH$1-$KG$1)/($KQ$1-$KG$1) -> 58572.703 | KI152: =$KG152+($KQ152-$KG152)*(KI$1-$KG$1)/($KQ$1-$KG$1) -> 58615.963 | KJ152: =$KG152+($KQ152-$KG152)*(KJ$1-$KG$1)/($KQ$1-$KG$1) -> 58659.223 | KK152: =$KG152+($KQ152-$KG152)*(KK$1-$KG$1)/($KQ$1-$KG$1) -> 58702.483 | KL152: =$KG152+($KQ152-$KG152)*(KL$1-$KG$1)/($KQ$1-$KG$1) -> 58745.743 | KM152: =$KG152+($KQ152-$KG152)*(KM$1-$KG$1)/($KQ$1-$KG$1) -> 58789.003 | KN152: =$KG152+($KQ152-$KG152)*(KN$1-$KG$1)/($KQ$1-$KG$1) -> 58832.264 | KO152: =$KG152+($KQ152-$KG152)*(KO$1-$KG$1)/($KQ$1-$KG$1) -> 58875.524 | KP152: =$KG152+($KQ152-$KG152)*(KP$1-$KG$1)/($KQ$1-$KG$1) -> 58918.784 | KQ152: 58962.044 | KR152: =$KQ152+($LA152-$KQ152)*(KR$1-$KQ$1)/($LA$1-$KQ$1) -> 58878.561 | KS152: =$KQ152+($LA152-$KQ152)*(KS$1-$KQ$1)/($LA$1-$KQ$1) -> 58795.078 | KT152: =$KQ152+($LA152-$KQ152)*(KT$1-$KQ$1)/($LA$1-$KQ$1) -> 58711.594 | KU152: =$KQ152+($LA152-$KQ152)*(KU$1-$KQ$1)/($LA$1-$KQ$1) -> 58628.111 | KV152: =$KQ152+($LA152-$KQ152)*(KV$1-$KQ$1)/($LA$1-$KQ$1) -> 58544.628 | KW152: =$KQ152+($LA152-$KQ152)*(KW$1-$KQ$1)/($LA$1-$KQ$1) -> 58461.145 | KX152: =$KQ152+($LA152-$KQ152)*(KX$1-$KQ$1)/($LA$1-$KQ$1) -> 58377.662 | KY152: =$KQ152+($LA152-$KQ152)*(KY$1-$KQ$1)/($LA$1-$KQ$1) -> 58294.178 | KZ152: =$KQ152+($LA152-$KQ152)*(KZ$1-$KQ$1)/($LA$1-$KQ$1) -> 58210.695 | LA152: 58127.212
C153: Commerce | E153: " | F153: " | BD153: =BE88 -> 210718 | BE153: =BD153+(BI153-BD153)*(BE1-BD1)/(BI1-BD1) -> 211766.2 | BF153: =BD153+(BI153-BD153)*(BF1-BD1)/(BI1-BD1) -> 212814.4 | BG153: =BD153+(BI153-BD153)*(BG1-BD1)/(BI1-BD1) -> 213862.6 | BH153: =BD153+(BI153-BD153)*(BH1-BD1)/(BI1-BD1) -> 214910.8 | BI153: =BF88 -> 215959 | BJ153: =BI153+(BS153-BI153)*(BJ1-BI1)/(BS1-BI1) -> 216629.4 | BK153: =BI153+(BS153-BI153)*(BK1-BI1)/(BS1-BI1) -> 217299.8 | BL153: =BI153+(BS153-BI153)*(BL1-BI1)/(BS1-BI1) -> 217970.2 | BM153: =BI153+(BS153-BI153)*(BM1-BI1)/(BS1-BI1) -> 218640.6 | BN153: =BI153+(BS153-BI153)*(BN1-BI1)/(BS1-BI1) -> 219311.01 | BO153: =BI153+(BS153-BI153)*(BO1-BI1)/(BS1-BI1) -> 219981.41 | BP153: =BI153+(BS153-BI153)*(BP1-BI1)/(BS1-BI1) -> 220651.81 | BQ153: =BI153+(BS153-BI153)*(BQ1-BI1)/(BS1-BI1) -> 221322.21 | BR153: =BI153+(BS153-BI153)*(BR1-BI1)/(BS1-BI1) -> 221992.61 | BS153: =BG88 -> 222663.01 | BT153: =BS153+(CC153-BS153)*(BT1-BS1)/(CC1-BS1) -> 223155.65 | BU153: =BS153+(CC153-BS153)*(BU1-BS1)/(CC1-BS1) -> 223648.29 | BV153: =BS153+(CC153-BS153)*(BV1-BS1)/(CC1-BS1) -> 224140.93 | BW153: =BS153+(CC153-BS153)*(BW1-BS1)/(CC1-BS1) -> 224633.57 | BX153: =BS153+(CC153-BS153)*(BX1-BS1)/(CC1-BS1) -> 225126.21 | BY153: =BS153+(CC153-BS153)*(BY1-BS1)/(CC1-BS1) -> 225618.85 | BZ153: =BS153+(CC153-BS153)*(BZ1-BS1)/(CC1-BS1) -> 226111.49 | CA153: =BS153+(CC153-BS153)*(CA1-BS1)/(CC1-BS1) -> 226604.14 | CB153: =BS153+(CC153-BS153)*(CB1-BS1)/(CC1-BS1) -> 227096.78 | CC153: =BH88 -> 227589.42 | CD153: =CC153+(CM153-CC153)*(CD1-CC1)/(CM1-CC1) -> 227854.41 | CE153: =CC153+(CM153-CC153)*(CE1-CC1)/(CM1-CC1) -> 228119.39 | CF153: =CC153+(CM153-CC153)*(CF1-CC1)/(CM1-CC1) -> 228384.38 | CG153: =CC153+(CM153-CC153)*(CG1-CC1)/(CM1-CC1) -> 228649.37 | CH153: =CC153+(CM153-CC153)*(CH1-CC1)/(CM1-CC1) -> 228914.36 | CI153: =CC153+(CM153-CC153)*(CI1-CC1)/(CM1-CC1) -> 229179.35 | CJ153: =CC153+(CM153-CC153)*(CJ1-CC1)/(CM1-CC1) -> 229444.34 | CK153: =CC153+(CM153-CC153)*(CK1-CC1)/(CM1-CC1) -> 229709.32 | CL153: =CC153+(CM153-CC153)*(CL1-CC1)/(CM1-CC1) -> 229974.31 | CM153: =BI88 -> 230239.3 | CO153: =CP88 -> 210718 | CP153: =CO153+(CT153-CO153)*(CP1-CO1)/(CT1-CO1) -> 211766.2 | CQ153: =CO153+(CT153-CO153)*(CQ1-CO1)/(CT1-CO1) -> 212814.4 | CR153: =CO153+(CT153-CO153)*(CR1-CO1)/(CT1-CO1) -> 213862.6 | CS153: =CO153+(CT153-CO153)*(CS1-CO1)/(CT1-CO1) -> 214910.8 | CT153: =CQ88 -> 215959 | CU153: =CT153+(DD153-CT153)*(CU1-CT1)/(DD1-CT1) -> 215540.8 | CV153: =CT153+(DD153-CT153)*(CV1-CT1)/(DD1-CT1) -> 215122.61 | CW153: =CT153+(DD153-CT153)*(CW1-CT1)/(DD1-CT1) -> 214704.41 | CX153: =CT153+(DD153-CT153)*(CX1-CT1)/(DD1-CT1) -> 214286.22 | CY153: =CT153+(DD153-CT153)*(CY1-CT1)/(DD1-CT1) -> 213868.02 | CZ153: =CT153+(DD153-CT153)*(CZ1-CT1)/(DD1-CT1) -> 213449.83 | DA153: =CT153+(DD153-CT153)*(DA1-CT1)/(DD1-CT1) -> 213031.63 | DB153: =CT153+(DD153-CT153)*(DB1-CT1)/(DD1-CT1) -> 212613.44 | DC153: =CT153+(DD153-CT153)*(DC1-CT1)/(DD1-CT1) -> 212195.24 | DD153: =CR88 -> 211777.04 | DE153: =DD153+(DN153-DD153)*(DE1-DD1)/(DN1-DD1) -> 211187.32 | DF153: =DD153+(DN153-DD153)*(DF1-DD1)/(DN1-DD1) -> 210597.59 | DG153: =DD153+(DN153-DD153)*(DG1-DD1)/(DN1-DD1) -> 210007.86 | DH153: =DD153+(DN153-DD153)*(DH1-DD1)/(DN1-DD1) -> 209418.14 | DI153: =DD153+(DN153-DD153)*(DI1-DD1)/(DN1-DD1) -> 208828.41 | DJ153: =DD153+(DN153-DD153)*(DJ1-DD1)/(DN1-DD1) -> 208238.68 | DK153: =DD153+(DN153-DD153)*(DK1-DD1)/(DN1-DD1) -> 207648.95 | DL153: =DD153+(DN153-DD153)*(DL1-DD1)/(DN1-DD1) -> 207059.23 | DM153: =DD153+(DN153-DD153)*(DM1-DD1)/(DN1-DD1) -> 206469.5 | DN153: =CS88 -> 205879.77 | DO153: =DN153+(DX153-DN153)*(DO1-DN1)/(DX1-DN1) -> 205101.22 | DP153: =DN153+(DX153-DN153)*(DP1-DN1)/(DX1-DN1) -> 204322.67 | DQ153: =DN153+(DX153-DN153)*(DQ1-DN1)/(DX1-DN1) -> 203544.12 | DR153: =DN153+(DX153-DN153)*(DR1-DN1)/(DX1-DN1) -> 202765.57 | DS153: =DN153+(DX153-DN153)*(DS1-DN1)/(DX1-DN1) -> 201987.01 | DT153: =DN153+(DX153-DN153)*(DT1-DN1)/(DX1-DN1) -> 201208.46 | DU153: =DN153+(DX153-DN153)*(DU1-DN1)/(DX1-DN1) -> 200429.91 | DV153: =DN153+(DX153-DN153)*(DV1-DN1)/(DX1-DN1) -> 199651.36 | DW153: =DN153+(DX153-DN153)*(DW1-DN1)/(DX1-DN1) -> 198872.81 | DX153: =CT88 -> 198094.26 | DZ153: =EA88 -> 210718 | EA153: =DZ153+(EE153-DZ153)*(EA1-DZ1)/(EE1-DZ1) -> 211766.2 | EB153: =DZ153+(EE153-DZ153)*(EB1-DZ1)/(EE1-DZ1) -> 212814.4 | EC153: =DZ153+(EE153-DZ153)*(EC1-DZ1)/(EE1-DZ1) -> 213862.6 | ED153: =DZ153+(EE153-DZ153)*(ED1-DZ1)/(EE1-DZ1) -> 214910.8 | EE153: =EB88 -> 215959 | EF153: =EE153+(EO153-EE153)*(EF1-EE1)/(EO1-EE1) -> 215540.8 | EG153: =EE153+(EO153-EE153)*(EG1-EE1)/(EO1-EE1) -> 215122.61 | EH153: =EE153+(EO153-EE153)*(EH1-EE1)/(EO1-EE1) -> 214704.41 | EI153: =EE153+(EO153-EE153)*(EI1-EE1)/(EO1-EE1) -> 214286.22 | EJ153: =EE153+(EO153-EE153)*(EJ1-EE1)/(EO1-EE1) -> 213868.02 | EK153: =EE153+(EO153-EE153)*(EK1-EE1)/(EO1-EE1) -> 213449.83 | EL153: =EE153+(EO153-EE153)*(EL1-EE1)/(EO1-EE1) -> 213031.63 | EM153: =EE153+(EO153-EE153)*(EM1-EE1)/(EO1-EE1) -> 212613.44 | EN153: =EE153+(EO153-EE153)*(EN1-EE1)/(EO1-EE1) -> 212195.24 | EO153: =EC88 -> 211777.04 | EP153: =EO153+(EY153-EO153)*(EP1-EO1)/(EY1-EO1) -> 211187.32 | EQ153: =EO153+(EY153-EO153)*(EQ1-EO1)/(EY1-EO1) -> 210597.59 | ER153: =EO153+(EY153-EO153)*(ER1-EO1)/(EY1-EO1) -> 210007.86 | ES153: =EO153+(EY153-EO153)*(ES1-EO1)/(EY1-EO1) -> 209418.14 | ET153: =EO153+(EY153-EO153)*(ET1-EO1)/(EY1-EO1) -> 208828.41 | EU153: =EO153+(EY153-EO153)*(EU1-EO1)/(EY1-EO1) -> 208238.68 | EV153: =EO153+(EY153-EO153)*(EV1-EO1)/(EY1-EO1) -> 207648.95 | EW153: =EO153+(EY153-EO153)*(EW1-EO1)/(EY1-EO1) -> 207059.23 | EX153: =EO153+(EY153-EO153)*(EX1-EO1)/(EY1-EO1) -> 206469.5 | EY153: =ED88 -> 205879.77 | EZ153: =EY153+(FI153-EY153)*(EZ1-EY1)/(FI1-EY1) -> 205101.22 | FA153: =EY153+(FI153-EY153)*(FA1-EY1)/(FI1-EY1) -> 204322.67 | FB153: =EY153+(FI153-EY153)*(FB1-EY1)/(FI1-EY1) -> 203544.12 | FC153: =EY153+(FI153-EY153)*(FC1-EY1)/(FI1-EY1) -> 202765.57 | FD153: =EY153+(FI153-EY153)*(FD1-EY1)/(FI1-EY1) -> 201987.01 | FE153: =EY153+(FI153-EY153)*(FE1-EY1)/(FI1-EY1) -> 201208.46 | FF153: =EY153+(FI153-EY153)*(FF1-EY1)/(FI1-EY1) -> 200429.91 | FG153: =EY153+(FI153-EY153)*(FG1-EY1)/(FI1-EY1) -> 199651.36 | FH153: =EY153+(FI153-EY153)*(FH1-EY1)/(FI1-EY1) -> 198872.81 | FI153: =EE88 -> 198094.26 | FK153: =FL88 -> 210718 | FL153: =FK153+(FP153-FK153)*(FL1-FK1)/(FP1-FK1) -> 211766.2 | FM153: =FK153+(FP153-FK153)*(FM1-FK1)/(FP1-FK1) -> 212814.4 | FN153: =FK153+(FP153-FK153)*(FN1-FK1)/(FP1-FK1) -> 213862.6 | FO153: =FK153+(FP153-FK153)*(FO1-FK1)/(FP1-FK1) -> 214910.8 | FP153: =FM88 -> 215959 | FQ153: =FP153+(FZ153-FP153)*(FQ1-FP1)/(FZ1-FP1) -> 216629.4 | FR153: =FP153+(FZ153-FP153)*(FR1-FP1)/(FZ1-FP1) -> 217299.8 | FS153: =FP153+(FZ153-FP153)*(FS1-FP1)/(FZ1-FP1) -> 217970.2 | FT153: =FP153+(FZ153-FP153)*(FT1-FP1)/(FZ1-FP1) -> 218640.6 | FU153: =FP153+(FZ153-FP153)*(FU1-FP1)/(FZ1-FP1) -> 219311.01 | FV153: =FP153+(FZ153-FP153)*(FV1-FP1)/(FZ1-FP1) -> 219981.41 | FW153: =FP153+(FZ153-FP153)*(FW1-FP1)/(FZ1-FP1) -> 220651.81 | FX153: =FP153+(FZ153-FP153)*(FX1-FP1)/(FZ1-FP1) -> 221322.21 | FY153: =FP153+(FZ153-FP153)*(FY1-FP1)/(FZ1-FP1) -> 221992.61 | FZ153: =FN88 -> 222663.01 | GA153: =FZ153+(GJ153-FZ153)*(GA1-FZ1)/(GJ1-FZ1) -> 223155.65 | GB153: =FZ153+(GJ153-FZ153)*(GB1-FZ1)/(GJ1-FZ1) -> 223648.29 | GC153: =FZ153+(GJ153-FZ153)*(GC1-FZ1)/(GJ1-FZ1) -> 224140.93 | GD153: =FZ153+(GJ153-FZ153)*(GD1-FZ1)/(GJ1-FZ1) -> 224633.57 | GE153: =FZ153+(GJ153-FZ153)*(GE1-FZ1)/(GJ1-FZ1) -> 225126.21 | GF153: =FZ153+(GJ153-FZ153)*(GF1-FZ1)/(GJ1-FZ1) -> 225618.85 | GG153: =FZ153+(GJ153-FZ153)*(GG1-FZ1)/(GJ1-FZ1) -> 226111.49 | GH153: =FZ153+(GJ153-FZ153)*(GH1-FZ1)/(GJ1-FZ1) -> 226604.14 | GI153: =FZ153+(GJ153-FZ153)*(GI1-FZ1)/(GJ1-FZ1) -> 227096.78 | GJ153: =FO88 -> 227589.42 | GK153: =GJ153+(GT153-GJ153)*(GK1-GJ1)/(GT1-GJ1) -> 227854.41 | GL153: =GJ153+(GT153-GJ153)*(GL1-GJ1)/(GT1-GJ1) -> 228119.39 | GM153: =GJ153+(GT153-GJ153)*(GM1-GJ1)/(GT1-GJ1) -> 228384.38 | GN153: =GJ153+(GT153-GJ153)*(GN1-GJ1)/(GT1-GJ1) -> 228649.37 | GO153: =GJ153+(GT153-GJ153)*(GO1-GJ1)/(GT1-GJ1) -> 228914.36 | GP153: =GJ153+(GT153-GJ153)*(GP1-GJ1)/(GT1-GJ1) -> 229179.35 | GQ153: =GJ153+(GT153-GJ153)*(GQ1-GJ1)/(GT1-GJ1) -> 229444.34 | GR153: =GJ153+(GT153-GJ153)*(GR1-GJ1)/(GT1-GJ1) -> 229709.32 | GS153: =GJ153+(GT153-GJ153)*(GS1-GJ1)/(GT1-GJ1) -> 229974.31 | GT153: =FP88 -> 230239.3 | GV153: =GW88 -> 210718 | GW153: =GV153+(HA153-GV153)*(GW1-GV1)/(HA1-GV1) -> 211766.2 | GX153: =GV153+(HA153-GV153)*(GX1-GV1)/(HA1-GV1) -> 212814.4 | GY153: =GV153+(HA153-GV153)*(GY1-GV1)/(HA1-GV1) -> 213862.6 | GZ153: =GV153+(HA153-GV153)*(GZ1-GV1)/(HA1-GV1) -> 214910.8 | HA153: =GX88 -> 215959 | HB153: =HA153+(HK153-HA153)*(HB1-HA1)/(HK1-HA1) -> 216629.4 | HC153: =HA153+(HK153-HA153)*(HC1-HA1)/(HK1-HA1) -> 217299.8 | HD153: =HA153+(HK153-HA153)*(HD1-HA1)/(HK1-HA1) -> 217970.2 | HE153: =HA153+(HK153-HA153)*(HE1-HA1)/(HK1-HA1) -> 218640.6 | HF153: =HA153+(HK153-HA153)*(HF1-HA1)/(HK1-HA1) -> 219311.01 | HG153: =HA153+(HK153-HA153)*(HG1-HA1)/(HK1-HA1) -> 219981.41 | HH153: =HA153+(HK153-HA153)*(HH1-HA1)/(HK1-HA1) -> 220651.81 | HI153: =HA153+(HK153-HA153)*(HI1-HA1)/(HK1-HA1) -> 221322.21 | HJ153: =HA153+(HK153-HA153)*(HJ1-HA1)/(HK1-HA1) -> 221992.61 | HK153: =GY88 -> 222663.01 | HL153: =HK153+(HU153-HK153)*(HL1-HK1)/(HU1-HK1) -> 223155.65 | HM153: =HK153+(HU153-HK153)*(HM1-HK1)/(HU1-HK1) -> 223648.29 | HN153: =HK153+(HU153-HK153)*(HN1-HK1)/(HU1-HK1) -> 224140.93 | HO153: =HK153+(HU153-HK153)*(HO1-HK1)/(HU1-HK1) -> 224633.57 | HP153: =HK153+(HU153-HK153)*(HP1-HK1)/(HU1-HK1) -> 225126.21 | HQ153: =HK153+(HU153-HK153)*(HQ1-HK1)/(HU1-HK1) -> 225618.85 | HR153: =HK153+(HU153-HK153)*(HR1-HK1)/(HU1-HK1) -> 226111.49 | HS153: =HK153+(HU153-HK153)*(HS1-HK1)/(HU1-HK1) -> 226604.14 | HT153: =HK153+(HU153-HK153)*(HT1-HK1)/(HU1-HK1) -> 227096.78 | HU153: =GZ88 -> 227589.42 | HV153: =HU153+(IE153-HU153)*(HV1-HU1)/(IE1-HU1) -> 227854.41 | HW153: =HU153+(IE153-HU153)*(HW1-HU1)/(IE1-HU1) -> 228119.39 | HX153: =HU153+(IE153-HU153)*(HX1-HU1)/(IE1-HU1) -> 228384.38 | HY153: =HU153+(IE153-HU153)*(HY1-HU1)/(IE1-HU1) -> 228649.37 | HZ153: =HU153+(IE153-HU153)*(HZ1-HU1)/(IE1-HU1) -> 228914.36 | IA153: =HU153+(IE153-HU153)*(IA1-HU1)/(IE1-HU1) -> 229179.35 | IB153: =HU153+(IE153-HU153)*(IB1-HU1)/(IE1-HU1) -> 229444.34 | IC153: =HU153+(IE153-HU153)*(IC1-HU1)/(IE1-HU1) -> 229709.32 | ID153: =HU153+(IE153-HU153)*(ID1-HU1)/(IE1-HU1) -> 229974.31 | IE153: =HA88 -> 230239.3 | IL153: 196121.59 | IV153: 200877.3 | JF153: 203940.56 | JP153: 202413.23 | JW153: 196121.59 | JX153: =$JW153+($KG153-$JW153)*(JX$1-$JW$1)/($KG$1-$JW$1) -> 196297.11 | JY153: =$JW153+($KG153-$JW153)*(JY$1-$JW$1)/($KG$1-$JW$1) -> 196472.63 | JZ153: =$JW153+($KG153-$JW153)*(JZ$1-$JW$1)/($KG$1-$JW$1) -> 196648.15 | KA153: =$JW153+($KG153-$JW153)*(KA$1-$JW$1)/($KG$1-$JW$1) -> 196823.67 | KB153: =$JW153+($KG153-$JW153)*(KB$1-$JW$1)/($KG$1-$JW$1) -> 196999.19 | KC153: =$JW153+($KG153-$JW153)*(KC$1-$JW$1)/($KG$1-$JW$1) -> 197174.7 | KD153: =$JW153+($KG153-$JW153)*(KD$1-$JW$1)/($KG$1-$JW$1) -> 197350.22 | KE153: =$JW153+($KG153-$JW153)*(KE$1-$JW$1)/($KG$1-$JW$1) -> 197525.74 | KF153: =$JW153+($KG153-$JW153)*(KF$1-$JW$1)/($KG$1-$JW$1) -> 197701.26 | KG153: 197876.78 | KH153: =$KG153+($KQ153-$KG153)*(KH$1-$KG$1)/($KQ$1-$KG$1) -> 198023.04 | KI153: =$KG153+($KQ153-$KG153)*(KI$1-$KG$1)/($KQ$1-$KG$1) -> 198169.29 | KJ153: =$KG153+($KQ153-$KG153)*(KJ$1-$KG$1)/($KQ$1-$KG$1) -> 198315.54 | KK153: =$KG153+($KQ153-$KG153)*(KK$1-$KG$1)/($KQ$1-$KG$1) -> 198461.8 | KL153: =$KG153+($KQ153-$KG153)*(KL$1-$KG$1)/($KQ$1-$KG$1) -> 198608.05 | KM153: =$KG153+($KQ153-$KG153)*(KM$1-$KG$1)/($KQ$1-$KG$1) -> 198754.31 | KN153: =$KG153+($KQ153-$KG153)*(KN$1-$KG$1)/($KQ$1-$KG$1) -> 198900.56 | KO153: =$KG153+($KQ153-$KG153)*(KO$1-$KG$1)/($KQ$1-$KG$1) -> 199046.81 | KP153: =$KG153+($KQ153-$KG153)*(KP$1-$KG$1)/($KQ$1-$KG$1) -> 199193.07 | KQ153: 199339.32 | KR153: =$KQ153+($LA153-$KQ153)*(KR$1-$KQ$1)/($LA$1-$KQ$1) -> 199057.08 | KS153: =$KQ153+($LA153-$KQ153)*(KS$1-$KQ$1)/($LA$1-$KQ$1) -> 198774.84 | KT153: =$KQ153+($LA153-$KQ153)*(KT$1-$KQ$1)/($LA$1-$KQ$1) -> 198492.6 | KU153: =$KQ153+($LA153-$KQ153)*(KU$1-$KQ$1)/($LA$1-$KQ$1) -> 198210.36 | KV153: =$KQ153+($LA153-$KQ153)*(KV$1-$KQ$1)/($LA$1-$KQ$1) -> 197928.12 | KW153: =$KQ153+($LA153-$KQ153)*(KW$1-$KQ$1)/($LA$1-$KQ$1) -> 197645.88 | KX153: =$KQ153+($LA153-$KQ153)*(KX$1-$KQ$1)/($LA$1-$KQ$1) -> 197363.64 | KY153: =$KQ153+($LA153-$KQ153)*(KY$1-$KQ$1)/($LA$1-$KQ$1) -> 197081.4 | KZ153: =$KQ153+($LA153-$KQ153)*(KZ$1-$KQ$1)/($LA$1-$KQ$1) -> 196799.16 | LA153: 196516.92
C154: Enseignement-recherche | E154: " | F154: " | BD154: =BE89 -> 186911 | BE154: =BD154+(BI154-BD154)*(BE1-BD1)/(BI1-BD1) -> 187698.8 | BF154: =BD154+(BI154-BD154)*(BF1-BD1)/(BI1-BD1) -> 188486.6 | BG154: =BD154+(BI154-BD154)*(BG1-BD1)/(BI1-BD1) -> 189274.4 | BH154: =BD154+(BI154-BD154)*(BH1-BD1)/(BI1-BD1) -> 190062.2 | BI154: =BF89 -> 190850 | BJ154: =BI154+(BS154-BI154)*(BJ1-BI1)/(BS1-BI1) -> 190986.42 | BK154: =BI154+(BS154-BI154)*(BK1-BI1)/(BS1-BI1) -> 191122.84 | BL154: =BI154+(BS154-BI154)*(BL1-BI1)/(BS1-BI1) -> 191259.26 | BM154: =BI154+(BS154-BI154)*(BM1-BI1)/(BS1-BI1) -> 191395.68 | BN154: =BI154+(BS154-BI154)*(BN1-BI1)/(BS1-BI1) -> 191532.1 | BO154: =BI154+(BS154-BI154)*(BO1-BI1)/(BS1-BI1) -> 191668.52 | BP154: =BI154+(BS154-BI154)*(BP1-BI1)/(BS1-BI1) -> 191804.94 | BQ154: =BI154+(BS154-BI154)*(BQ1-BI1)/(BS1-BI1) -> 191941.36 | BR154: =BI154+(BS154-BI154)*(BR1-BI1)/(BS1-BI1) -> 192077.78 | BS154: =BG89 -> 192214.2 | BT154: =BS154+(CC154-BS154)*(BT1-BS1)/(CC1-BS1) -> 193211.91 | BU154: =BS154+(CC154-BS154)*(BU1-BS1)/(CC1-BS1) -> 194209.62 | BV154: =BS154+(CC154-BS154)*(BV1-BS1)/(CC1-BS1) -> 195207.33 | BW154: =BS154+(CC154-BS154)*(BW1-BS1)/(CC1-BS1) -> 196205.04 | BX154: =BS154+(CC154-BS154)*(BX1-BS1)/(CC1-BS1) -> 197202.74 | BY154: =BS154+(CC154-BS154)*(BY1-BS1)/(CC1-BS1) -> 198200.45 | BZ154: =BS154+(CC154-BS154)*(BZ1-BS1)/(CC1-BS1) -> 199198.16 | CA154: =BS154+(CC154-BS154)*(CA1-BS1)/(CC1-BS1) -> 200195.87 | CB154: =BS154+(CC154-BS154)*(CB1-BS1)/(CC1-BS1) -> 201193.58 | CC154: =BH89 -> 202191.29 | CD154: =CC154+(CM154-CC154)*(CD1-CC1)/(CM1-CC1) -> 203469.24 | CE154: =CC154+(CM154-CC154)*(CE1-CC1)/(CM1-CC1) -> 204747.18 | CF154: =CC154+(CM154-CC154)*(CF1-CC1)/(CM1-CC1) -> 206025.13 | CG154: =CC154+(CM154-CC154)*(CG1-CC1)/(CM1-CC1) -> 207303.08 | CH154: =CC154+(CM154-CC154)*(CH1-CC1)/(CM1-CC1) -> 208581.02 | CI154: =CC154+(CM154-CC154)*(CI1-CC1)/(CM1-CC1) -> 209858.97 | CJ154: =CC154+(CM154-CC154)*(CJ1-CC1)/(CM1-CC1) -> 211136.91 | CK154: =CC154+(CM154-CC154)*(CK1-CC1)/(CM1-CC1) -> 212414.86 | CL154: =CC154+(CM154-CC154)*(CL1-CC1)/(CM1-CC1) -> 213692.81 | CM154: =BI89 -> 214970.75 | CO154: =CP89 -> 186911 | CP154: =CO154+(CT154-CO154)*(CP1-CO1)/(CT1-CO1) -> 187698.8 | CQ154: =CO154+(CT154-CO154)*(CQ1-CO1)/(CT1-CO1) -> 188486.6 | CR154: =CO154+(CT154-CO154)*(CR1-CO1)/(CT1-CO1) -> 189274.4 | CS154: =CO154+(CT154-CO154)*(CS1-CO1)/(CT1-CO1) -> 190062.2 | CT154: =CQ89 -> 190850 | CU154: =CT154+(DD154-CT154)*(CU1-CT1)/(DD1-CT1) -> 187590.59 | CV154: =CT154+(DD154-CT154)*(CV1-CT1)/(DD1-CT1) -> 184331.17 | CW154: =CT154+(DD154-CT154)*(CW1-CT1)/(DD1-CT1) -> 181071.76 | CX154: =CT154+(DD154-CT154)*(CX1-CT1)/(DD1-CT1) -> 177812.34 | CY154: =CT154+(DD154-CT154)*(CY1-CT1)/(DD1-CT1) -> 174552.93 | CZ154: =CT154+(DD154-CT154)*(CZ1-CT1)/(DD1-CT1) -> 171293.52 | DA154: =CT154+(DD154-CT154)*(DA1-CT1)/(DD1-CT1) -> 168034.1 | DB154: =CT154+(DD154-CT154)*(DB1-CT1)/(DD1-CT1) -> 164774.69 | DC154: =CT154+(DD154-CT154)*(DC1-CT1)/(DD1-CT1) -> 161515.27 | DD154: =CR89 -> 158255.86 | DE154: =DD154+(DN154-DD154)*(DE1-DD1)/(DN1-DD1) -> 156136.28 | DF154: =DD154+(DN154-DD154)*(DF1-DD1)/(DN1-DD1) -> 154016.71 | DG154: =DD154+(DN154-DD154)*(DG1-DD1)/(DN1-DD1) -> 151897.14 | DH154: =DD154+(DN154-DD154)*(DH1-DD1)/(DN1-DD1) -> 149777.56 | DI154: =DD154+(DN154-DD154)*(DI1-DD1)/(DN1-DD1) -> 147657.99 | DJ154: =DD154+(DN154-DD154)*(DJ1-DD1)/(DN1-DD1) -> 145538.41 | DK154: =DD154+(DN154-DD154)*(DK1-DD1)/(DN1-DD1) -> 143418.84 | DL154: =DD154+(DN154-DD154)*(DL1-DD1)/(DN1-DD1) -> 141299.27 | DM154: =DD154+(DN154-DD154)*(DM1-DD1)/(DN1-DD1) -> 139179.69 | DN154: =CS89 -> 137060.12 | DO154: =DN154+(DX154-DN154)*(DO1-DN1)/(DX1-DN1) -> 135351.93 | DP154: =DN154+(DX154-DN154)*(DP1-DN1)/(DX1-DN1) -> 133643.73 | DQ154: =DN154+(DX154-DN154)*(DQ1-DN1)/(DX1-DN1) -> 131935.54 | DR154: =DN154+(DX154-DN154)*(DR1-DN1)/(DX1-DN1) -> 130227.35 | DS154: =DN154+(DX154-DN154)*(DS1-DN1)/(DX1-DN1) -> 128519.16 | DT154: =DN154+(DX154-DN154)*(DT1-DN1)/(DX1-DN1) -> 126810.97 | DU154: =DN154+(DX154-DN154)*(DU1-DN1)/(DX1-DN1) -> 125102.78 | DV154: =DN154+(DX154-DN154)*(DV1-DN1)/(DX1-DN1) -> 123394.59 | DW154: =DN154+(DX154-DN154)*(DW1-DN1)/(DX1-DN1) -> 121686.4 | DX154: =CT89 -> 119978.21 | DZ154: =EA89 -> 186911 | EA154: =DZ154+(EE154-DZ154)*(EA1-DZ1)/(EE1-DZ1) -> 187698.8 | EB154: =DZ154+(EE154-DZ154)*(EB1-DZ1)/(EE1-DZ1) -> 188486.6 | EC154: =DZ154+(EE154-DZ154)*(EC1-DZ1)/(EE1-DZ1) -> 189274.4 | ED154: =DZ154+(EE154-DZ154)*(ED1-DZ1)/(EE1-DZ1) -> 190062.2 | EE154: =EB89 -> 190850 | EF154: =EE154+(EO154-EE154)*(EF1-EE1)/(EO1-EE1) -> 187590.59 | EG154: =EE154+(EO154-EE154)*(EG1-EE1)/(EO1-EE1) -> 184331.17 | EH154: =EE154+(EO154-EE154)*(EH1-EE1)/(EO1-EE1) -> 181071.76 | EI154: =EE154+(EO154-EE154)*(EI1-EE1)/(EO1-EE1) -> 177812.34 | EJ154: =EE154+(EO154-EE154)*(EJ1-EE1)/(EO1-EE1) -> 174552.93 | EK154: =EE154+(EO154-EE154)*(EK1-EE1)/(EO1-EE1) -> 171293.52 | EL154: =EE154+(EO154-EE154)*(EL1-EE1)/(EO1-EE1) -> 168034.1 | EM154: =EE154+(EO154-EE154)*(EM1-EE1)/(EO1-EE1) -> 164774.69 | EN154: =EE154+(EO154-EE154)*(EN1-EE1)/(EO1-EE1) -> 161515.27 | EO154: =EC89 -> 158255.86 | EP154: =EO154+(EY154-EO154)*(EP1-EO1)/(EY1-EO1) -> 156136.28 | EQ154: =EO154+(EY154-EO154)*(EQ1-EO1)/(EY1-EO1) -> 154016.71 | ER154: =EO154+(EY154-EO154)*(ER1-EO1)/(EY1-EO1) -> 151897.14 | ES154: =EO154+(EY154-EO154)*(ES1-EO1)/(EY1-EO1) -> 149777.56 | ET154: =EO154+(EY154-EO154)*(ET1-EO1)/(EY1-EO1) -> 147657.99 | EU154: =EO154+(EY154-EO154)*(EU1-EO1)/(EY1-EO1) -> 145538.41 | EV154: =EO154+(EY154-EO154)*(EV1-EO1)/(EY1-EO1) -> 143418.84 | EW154: =EO154+(EY154-EO154)*(EW1-EO1)/(EY1-EO1) -> 141299.27 | EX154: =EO154+(EY154-EO154)*(EX1-EO1)/(EY1-EO1) -> 139179.69 | EY154: =ED89 -> 137060.12 | EZ154: =EY154+(FI154-EY154)*(EZ1-EY1)/(FI1-EY1) -> 135351.93 | FA154: =EY154+(FI154-EY154)*(FA1-EY1)/(FI1-EY1) -> 133643.73 | FB154: =EY154+(FI154-EY154)*(FB1-EY1)/(FI1-EY1) -> 131935.54 | FC154: =EY154+(FI154-EY154)*(FC1-EY1)/(FI1-EY1) -> 130227.35 | FD154: =EY154+(FI154-EY154)*(FD1-EY1)/(FI1-EY1) -> 128519.16 | FE154: =EY154+(FI154-EY154)*(FE1-EY1)/(FI1-EY1) -> 126810.97 | FF154: =EY154+(FI154-EY154)*(FF1-EY1)/(FI1-EY1) -> 125102.78 | FG154: =EY154+(FI154-EY154)*(FG1-EY1)/(FI1-EY1) -> 123394.59 | FH154: =EY154+(FI154-EY154)*(FH1-EY1)/(FI1-EY1) -> 121686.4 | FI154: =EE89 -> 119978.21 | FK154: =FL89 -> 186911 | FL154: =FK154+(FP154-FK154)*(FL1-FK1)/(FP1-FK1) -> 187698.8 | FM154: =FK154+(FP154-FK154)*(FM1-FK1)/(FP1-FK1) -> 188486.6 | FN154: =FK154+(FP154-FK154)*(FN1-FK1)/(FP1-FK1) -> 189274.4 | FO154: =FK154+(FP154-FK154)*(FO1-FK1)/(FP1-FK1) -> 190062.2 | FP154: =FM89 -> 190850 | FQ154: =FP154+(FZ154-FP154)*(FQ1-FP1)/(FZ1-FP1) -> 189531.14 | FR154: =FP154+(FZ154-FP154)*(FR1-FP1)/(FZ1-FP1) -> 188212.28 | FS154: =FP154+(FZ154-FP154)*(FS1-FP1)/(FZ1-FP1) -> 186893.42 | FT154: =FP154+(FZ154-FP154)*(FT1-FP1)/(FZ1-FP1) -> 185574.56 | FU154: =FP154+(FZ154-FP154)*(FU1-FP1)/(FZ1-FP1) -> 184255.7 | FV154: =FP154+(FZ154-FP154)*(FV1-FP1)/(FZ1-FP1) -> 182936.84 | FW154: =FP154+(FZ154-FP154)*(FW1-FP1)/(FZ1-FP1) -> 181617.97 | FX154: =FP154+(FZ154-FP154)*(FX1-FP1)/(FZ1-FP1) -> 180299.11 | FY154: =FP154+(FZ154-FP154)*(FY1-FP1)/(FZ1-FP1) -> 178980.25 | FZ154: =FN89 -> 177661.39 | GA154: =FZ154+(GJ154-FZ154)*(GA1-FZ1)/(GJ1-FZ1) -> 177168.64 | GB154: =FZ154+(GJ154-FZ154)*(GB1-FZ1)/(GJ1-FZ1) -> 176675.9 | GC154: =FZ154+(GJ154-FZ154)*(GC1-FZ1)/(GJ1-FZ1) -> 176183.15 | GD154: =FZ154+(GJ154-FZ154)*(GD1-FZ1)/(GJ1-FZ1) -> 175690.4 | GE154: =FZ154+(GJ154-FZ154)*(GE1-FZ1)/(GJ1-FZ1) -> 175197.66 | GF154: =FZ154+(GJ154-FZ154)*(GF1-FZ1)/(GJ1-FZ1) -> 174704.91 | GG154: =FZ154+(GJ154-FZ154)*(GG1-FZ1)/(GJ1-FZ1) -> 174212.16 | GH154: =FZ154+(GJ154-FZ154)*(GH1-FZ1)/(GJ1-FZ1) -> 173719.41 | GI154: =FZ154+(GJ154-FZ154)*(GI1-FZ1)/(GJ1-FZ1) -> 173226.67 | GJ154: =FO89 -> 172733.92 | GK154: =GJ154+(GT154-GJ154)*(GK1-GJ1)/(GT1-GJ1) -> 172435.23 | GL154: =GJ154+(GT154-GJ154)*(GL1-GJ1)/(GT1-GJ1) -> 172136.54 | GM154: =GJ154+(GT154-GJ154)*(GM1-GJ1)/(GT1-GJ1) -> 171837.85 | GN154: =GJ154+(GT154-GJ154)*(GN1-GJ1)/(GT1-GJ1) -> 171539.16 | GO154: =GJ154+(GT154-GJ154)*(GO1-GJ1)/(GT1-GJ1) -> 171240.47 | GP154: =GJ154+(GT154-GJ154)*(GP1-GJ1)/(GT1-GJ1) -> 170941.78 | GQ154: =GJ154+(GT154-GJ154)*(GQ1-GJ1)/(GT1-GJ1) -> 170643.09 | GR154: =GJ154+(GT154-GJ154)*(GR1-GJ1)/(GT1-GJ1) -> 170344.4 | GS154: =GJ154+(GT154-GJ154)*(GS1-GJ1)/(GT1-GJ1) -> 170045.71 | GT154: =FP89 -> 169747.02 | GV154: =GW89 -> 186911 | GW154: =GV154+(HA154-GV154)*(GW1-GV1)/(HA1-GV1) -> 187698.8 | GX154: =GV154+(HA154-GV154)*(GX1-GV1)/(HA1-GV1) -> 188486.6 | GY154: =GV154+(HA154-GV154)*(GY1-GV1)/(HA1-GV1) -> 189274.4 | GZ154: =GV154+(HA154-GV154)*(GZ1-GV1)/(HA1-GV1) -> 190062.2 | HA154: =GX89 -> 190850 | HB154: =HA154+(HK154-HA154)*(HB1-HA1)/(HK1-HA1) -> 190986.42 | HC154: =HA154+(HK154-HA154)*(HC1-HA1)/(HK1-HA1) -> 191122.84 | HD154: =HA154+(HK154-HA154)*(HD1-HA1)/(HK1-HA1) -> 191259.26 | HE154: =HA154+(HK154-HA154)*(HE1-HA1)/(HK1-HA1) -> 191395.68 | HF154: =HA154+(HK154-HA154)*(HF1-HA1)/(HK1-HA1) -> 191532.1 | HG154: =HA154+(HK154-HA154)*(HG1-HA1)/(HK1-HA1) -> 191668.52 | HH154: =HA154+(HK154-HA154)*(HH1-HA1)/(HK1-HA1) -> 191804.94 | HI154: =HA154+(HK154-HA154)*(HI1-HA1)/(HK1-HA1) -> 191941.36 | HJ154: =HA154+(HK154-HA154)*(HJ1-HA1)/(HK1-HA1) -> 192077.78 | HK154: =GY89 -> 192214.2 | HL154: =HK154+(HU154-HK154)*(HL1-HK1)/(HU1-HK1) -> 193211.91 | HM154: =HK154+(HU154-HK154)*(HM1-HK1)/(HU1-HK1) -> 194209.62 | HN154: =HK154+(HU154-HK154)*(HN1-HK1)/(HU1-HK1) -> 195207.33 | HO154: =HK154+(HU154-HK154)*(HO1-HK1)/(HU1-HK1) -> 196205.04 | HP154: =HK154+(HU154-HK154)*(HP1-HK1)/(HU1-HK1) -> 197202.74 | HQ154: =HK154+(HU154-HK154)*(HQ1-HK1)/(HU1-HK1) -> 198200.45 | HR154: =HK154+(HU154-HK154)*(HR1-HK1)/(HU1-HK1) -> 199198.16 | HS154: =HK154+(HU154-HK154)*(HS1-HK1)/(HU1-HK1) -> 200195.87 | HT154: =HK154+(HU154-HK154)*(HT1-HK1)/(HU1-HK1) -> 201193.58 | HU154: =GZ89 -> 202191.29 | HV154: =HU154+(IE154-HU154)*(HV1-HU1)/(IE1-HU1) -> 203469.24 | HW154: =HU154+(IE154-HU154)*(HW1-HU1)/(IE1-HU1) -> 204747.18 | HX154: =HU154+(IE154-HU154)*(HX1-HU1)/(IE1-HU1) -> 206025.13 | HY154: =HU154+(IE154-HU154)*(HY1-HU1)/(IE1-HU1) -> 207303.08 | HZ154: =HU154+(IE154-HU154)*(HZ1-HU1)/(IE1-HU1) -> 208581.02 | IA154: =HU154+(IE154-HU154)*(IA1-HU1)/(IE1-HU1) -> 209858.97 | IB154: =HU154+(IE154-HU154)*(IB1-HU1)/(IE1-HU1) -> 211136.91 | IC154: =HU154+(IE154-HU154)*(IC1-HU1)/(IE1-HU1) -> 212414.86 | ID154: =HU154+(IE154-HU154)*(ID1-HU1)/(IE1-HU1) -> 213692.81 | IE154: =HA89 -> 214970.75 | IL154: 234402.67 | IV154: 239368.54 | JF154: 242291.9 | JP154: 239758.07 | JW154: 234402.67 | JX154: =$JW154+($KG154-$JW154)*(JX$1-$JW$1)/($KG$1-$JW$1) -> 234612.45 | JY154: =$JW154+($KG154-$JW154)*(JY$1-$JW$1)/($KG$1-$JW$1) -> 234822.23 | JZ154: =$JW154+($KG154-$JW154)*(JZ$1-$JW$1)/($KG$1-$JW$1) -> 235032.01 | KA154: =$JW154+($KG154-$JW154)*(KA$1-$JW$1)/($KG$1-$JW$1) -> 235241.79 | KB154: =$JW154+($KG154-$JW154)*(KB$1-$JW$1)/($KG$1-$JW$1) -> 235451.56 | KC154: =$JW154+($KG154-$JW154)*(KC$1-$JW$1)/($KG$1-$JW$1) -> 235661.34 | KD154: =$JW154+($KG154-$JW154)*(KD$1-$JW$1)/($KG$1-$JW$1) -> 235871.12 | KE154: =$JW154+($KG154-$JW154)*(KE$1-$JW$1)/($KG$1-$JW$1) -> 236080.9 | KF154: =$JW154+($KG154-$JW154)*(KF$1-$JW$1)/($KG$1-$JW$1) -> 236290.68 | KG154: 236500.46 | KH154: =$KG154+($KQ154-$KG154)*(KH$1-$KG$1)/($KQ$1-$KG$1) -> 236675.26 | KI154: =$KG154+($KQ154-$KG154)*(KI$1-$KG$1)/($KQ$1-$KG$1) -> 236850.06 | KJ154: =$KG154+($KQ154-$KG154)*(KJ$1-$KG$1)/($KQ$1-$KG$1) -> 237024.86 | KK154: =$KG154+($KQ154-$KG154)*(KK$1-$KG$1)/($KQ$1-$KG$1) -> 237199.66 | KL154: =$KG154+($KQ154-$KG154)*(KL$1-$KG$1)/($KQ$1-$KG$1) -> 237374.46 | KM154: =$KG154+($KQ154-$KG154)*(KM$1-$KG$1)/($KQ$1-$KG$1) -> 237549.27 | KN154: =$KG154+($KQ154-$KG154)*(KN$1-$KG$1)/($KQ$1-$KG$1) -> 237724.07 | KO154: =$KG154+($KQ154-$KG154)*(KO$1-$KG$1)/($KQ$1-$KG$1) -> 237898.87 | KP154: =$KG154+($KQ154-$KG154)*(KP$1-$KG$1)/($KQ$1-$KG$1) -> 238073.67 | KQ154: 238248.47 | KR154: =$KQ154+($LA154-$KQ154)*(KR$1-$KQ$1)/($LA$1-$KQ$1) -> 237911.14 | KS154: =$KQ154+($LA154-$KQ154)*(KS$1-$KQ$1)/($LA$1-$KQ$1) -> 237573.81 | KT154: =$KQ154+($LA154-$KQ154)*(KT$1-$KQ$1)/($LA$1-$KQ$1) -> 237236.48 | KU154: =$KQ154+($LA154-$KQ154)*(KU$1-$KQ$1)/($LA$1-$KQ$1) -> 236899.15 | KV154: =$KQ154+($LA154-$KQ154)*(KV$1-$KQ$1)/($LA$1-$KQ$1) -> 236561.82 | KW154: =$KQ154+($LA154-$KQ154)*(KW$1-$KQ$1)/($LA$1-$KQ$1) -> 236224.48 | KX154: =$KQ154+($LA154-$KQ154)*(KX$1-$KQ$1)/($LA$1-$KQ$1) -> 235887.15 | KY154: =$KQ154+($LA154-$KQ154)*(KY$1-$KQ$1)/($LA$1-$KQ$1) -> 235549.82 | KZ154: =$KQ154+($LA154-$KQ154)*(KZ$1-$KQ$1)/($LA$1-$KQ$1) -> 235212.49 | LA154: 234875.16
C155: Habitat communautaire | E155: " | F155: " | BD155: =BE90 -> 69798 | BE155: =BD155+(BI155-BD155)*(BE1-BD1)/(BI1-BD1) -> 70356.8 | BF155: =BD155+(BI155-BD155)*(BF1-BD1)/(BI1-BD1) -> 70915.6 | BG155: =BD155+(BI155-BD155)*(BG1-BD1)/(BI1-BD1) -> 71474.4 | BH155: =BD155+(BI155-BD155)*(BH1-BD1)/(BI1-BD1) -> 72033.2 | BI155: =BF90 -> 72592 | BJ155: =BI155+(BS155-BI155)*(BJ1-BI1)/(BS1-BI1) -> 73820.71 | BK155: =BI155+(BS155-BI155)*(BK1-BI1)/(BS1-BI1) -> 75049.42 | BL155: =BI155+(BS155-BI155)*(BL1-BI1)/(BS1-BI1) -> 76278.13 | BM155: =BI155+(BS155-BI155)*(BM1-BI1)/(BS1-BI1) -> 77506.84 | BN155: =BI155+(BS155-BI155)*(BN1-BI1)/(BS1-BI1) -> 78735.55 | BO155: =BI155+(BS155-BI155)*(BO1-BI1)/(BS1-BI1) -> 79964.26 | BP155: =BI155+(BS155-BI155)*(BP1-BI1)/(BS1-BI1) -> 81192.969 | BQ155: =BI155+(BS155-BI155)*(BQ1-BI1)/(BS1-BI1) -> 82421.679 | BR155: =BI155+(BS155-BI155)*(BR1-BI1)/(BS1-BI1) -> 83650.389 | BS155: =BG90 -> 84879.099 | BT155: =BS155+(CC155-BS155)*(BT1-BS1)/(CC1-BS1) -> 86118.06 | BU155: =BS155+(CC155-BS155)*(BU1-BS1)/(CC1-BS1) -> 87357.021 | BV155: =BS155+(CC155-BS155)*(BV1-BS1)/(CC1-BS1) -> 88595.982 | BW155: =BS155+(CC155-BS155)*(BW1-BS1)/(CC1-BS1) -> 89834.942 | BX155: =BS155+(CC155-BS155)*(BX1-BS1)/(CC1-BS1) -> 91073.903 | BY155: =BS155+(CC155-BS155)*(BY1-BS1)/(CC1-BS1) -> 92312.864 | BZ155: =BS155+(CC155-BS155)*(BZ1-BS1)/(CC1-BS1) -> 93551.825 | CA155: =BS155+(CC155-BS155)*(CA1-BS1)/(CC1-BS1) -> 94790.785 | CB155: =BS155+(CC155-BS155)*(CB1-BS1)/(CC1-BS1) -> 96029.746 | CC155: =BH90 -> 97268.707 | CD155: =CC155+(CM155-CC155)*(CD1-CC1)/(CM1-CC1) -> 98574.209 | CE155: =CC155+(CM155-CC155)*(CE1-CC1)/(CM1-CC1) -> 99879.711 | CF155: =CC155+(CM155-CC155)*(CF1-CC1)/(CM1-CC1) -> 101185.21 | CG155: =CC155+(CM155-CC155)*(CG1-CC1)/(CM1-CC1) -> 102490.72 | CH155: =CC155+(CM155-CC155)*(CH1-CC1)/(CM1-CC1) -> 103796.22 | CI155: =CC155+(CM155-CC155)*(CI1-CC1)/(CM1-CC1) -> 105101.72 | CJ155: =CC155+(CM155-CC155)*(CJ1-CC1)/(CM1-CC1) -> 106407.22 | CK155: =CC155+(CM155-CC155)*(CK1-CC1)/(CM1-CC1) -> 107712.72 | CL155: =CC155+(CM155-CC155)*(CL1-CC1)/(CM1-CC1) -> 109018.23 | CM155: =BI90 -> 110323.73 | CO155: =CP90 -> 69798 | CP155: =CO155+(CT155-CO155)*(CP1-CO1)/(CT1-CO1) -> 70356.8 | CQ155: =CO155+(CT155-CO155)*(CQ1-CO1)/(CT1-CO1) -> 70915.6 | CR155: =CO155+(CT155-CO155)*(CR1-CO1)/(CT1-CO1) -> 71474.4 | CS155: =CO155+(CT155-CO155)*(CS1-CO1)/(CT1-CO1) -> 72033.2 | CT155: =CQ90 -> 72592 | CU155: =CT155+(DD155-CT155)*(CU1-CT1)/(DD1-CT1) -> 73820.71 | CV155: =CT155+(DD155-CT155)*(CV1-CT1)/(DD1-CT1) -> 75049.42 | CW155: =CT155+(DD155-CT155)*(CW1-CT1)/(DD1-CT1) -> 76278.13 | CX155: =CT155+(DD155-CT155)*(CX1-CT1)/(DD1-CT1) -> 77506.84 | CY155: =CT155+(DD155-CT155)*(CY1-CT1)/(DD1-CT1) -> 78735.55 | CZ155: =CT155+(DD155-CT155)*(CZ1-CT1)/(DD1-CT1) -> 79964.26 | DA155: =CT155+(DD155-CT155)*(DA1-CT1)/(DD1-CT1) -> 81192.969 | DB155: =CT155+(DD155-CT155)*(DB1-CT1)/(DD1-CT1) -> 82421.679 | DC155: =CT155+(DD155-CT155)*(DC1-CT1)/(DD1-CT1) -> 83650.389 | DD155: =CR90 -> 84879.099 | DE155: =DD155+(DN155-DD155)*(DE1-DD1)/(DN1-DD1) -> 86118.06 | DF155: =DD155+(DN155-DD155)*(DF1-DD1)/(DN1-DD1) -> 87357.021 | DG155: =DD155+(DN155-DD155)*(DG1-DD1)/(DN1-DD1) -> 88595.982 | DH155: =DD155+(DN155-DD155)*(DH1-DD1)/(DN1-DD1) -> 89834.942 | DI155: =DD155+(DN155-DD155)*(DI1-DD1)/(DN1-DD1) -> 91073.903 | DJ155: =DD155+(DN155-DD155)*(DJ1-DD1)/(DN1-DD1) -> 92312.864 | DK155: =DD155+(DN155-DD155)*(DK1-DD1)/(DN1-DD1) -> 93551.825 | DL155: =DD155+(DN155-DD155)*(DL1-DD1)/(DN1-DD1) -> 94790.785 | DM155: =DD155+(DN155-DD155)*(DM1-DD1)/(DN1-DD1) -> 96029.746 | DN155: =CS90 -> 97268.707 | DO155: =DN155+(DX155-DN155)*(DO1-DN1)/(DX1-DN1) -> 98574.209 | DP155: =DN155+(DX155-DN155)*(DP1-DN1)/(DX1-DN1) -> 99879.711 | DQ155: =DN155+(DX155-DN155)*(DQ1-DN1)/(DX1-DN1) -> 101185.21 | DR155: =DN155+(DX155-DN155)*(DR1-DN1)/(DX1-DN1) -> 102490.72 | DS155: =DN155+(DX155-DN155)*(DS1-DN1)/(DX1-DN1) -> 103796.22 | DT155: =DN155+(DX155-DN155)*(DT1-DN1)/(DX1-DN1) -> 105101.72 | DU155: =DN155+(DX155-DN155)*(DU1-DN1)/(DX1-DN1) -> 106407.22 | DV155: =DN155+(DX155-DN155)*(DV1-DN1)/(DX1-DN1) -> 107712.72 | DW155: =DN155+(DX155-DN155)*(DW1-DN1)/(DX1-DN1) -> 109018.23 | DX155: =CT90 -> 110323.73 | DZ155: =EA90 -> 69798 | EA155: =DZ155+(EE155-DZ155)*(EA1-DZ1)/(EE1-DZ1) -> 70356.8 | EB155: =DZ155+(EE155-DZ155)*(EB1-DZ1)/(EE1-DZ1) -> 70915.6 | EC155: =DZ155+(EE155-DZ155)*(EC1-DZ1)/(EE1-DZ1) -> 71474.4 | ED155: =DZ155+(EE155-DZ155)*(ED1-DZ1)/(EE1-DZ1) -> 72033.2 | EE155: =EB90 -> 72592 | EF155: =EE155+(EO155-EE155)*(EF1-EE1)/(EO1-EE1) -> 73820.71 | EG155: =EE155+(EO155-EE155)*(EG1-EE1)/(EO1-EE1) -> 75049.42 | EH155: =EE155+(EO155-EE155)*(EH1-EE1)/(EO1-EE1) -> 76278.13 | EI155: =EE155+(EO155-EE155)*(EI1-EE1)/(EO1-EE1) -> 77506.84 | EJ155: =EE155+(EO155-EE155)*(EJ1-EE1)/(EO1-EE1) -> 78735.55 | EK155: =EE155+(EO155-EE155)*(EK1-EE1)/(EO1-EE1) -> 79964.26 | EL155: =EE155+(EO155-EE155)*(EL1-EE1)/(EO1-EE1) -> 81192.969 | EM155: =EE155+(EO155-EE155)*(EM1-EE1)/(EO1-EE1) -> 82421.679 | EN155: =EE155+(EO155-EE155)*(EN1-EE1)/(EO1-EE1) -> 83650.389 | EO155: =EC90 -> 84879.099 | EP155: =EO155+(EY155-EO155)*(EP1-EO1)/(EY1-EO1) -> 86118.06 | EQ155: =EO155+(EY155-EO155)*(EQ1-EO1)/(EY1-EO1) -> 87357.021 | ER155: =EO155+(EY155-EO155)*(ER1-EO1)/(EY1-EO1) -> 88595.982 | ES155: =EO155+(EY155-EO155)*(ES1-EO1)/(EY1-EO1) -> 89834.942 | ET155: =EO155+(EY155-EO155)*(ET1-EO1)/(EY1-EO1) -> 91073.903 | EU155: =EO155+(EY155-EO155)*(EU1-EO1)/(EY1-EO1) -> 92312.864 | EV155: =EO155+(EY155-EO155)*(EV1-EO1)/(EY1-EO1) -> 93551.825 | EW155: =EO155+(EY155-EO155)*(EW1-EO1)/(EY1-EO1) -> 94790.785 | EX155: =EO155+(EY155-EO155)*(EX1-EO1)/(EY1-EO1) -> 96029.746 | EY155: =ED90 -> 97268.707 | EZ155: =EY155+(FI155-EY155)*(EZ1-EY1)/(FI1-EY1) -> 98574.209 | FA155: =EY155+(FI155-EY155)*(FA1-EY1)/(FI1-EY1) -> 99879.711 | FB155: =EY155+(FI155-EY155)*(FB1-EY1)/(FI1-EY1) -> 101185.21 | FC155: =EY155+(FI155-EY155)*(FC1-EY1)/(FI1-EY1) -> 102490.72 | FD155: =EY155+(FI155-EY155)*(FD1-EY1)/(FI1-EY1) -> 103796.22 | FE155: =EY155+(FI155-EY155)*(FE1-EY1)/(FI1-EY1) -> 105101.72 | FF155: =EY155+(FI155-EY155)*(FF1-EY1)/(FI1-EY1) -> 106407.22 | FG155: =EY155+(FI155-EY155)*(FG1-EY1)/(FI1-EY1) -> 107712.72 | FH155: =EY155+(FI155-EY155)*(FH1-EY1)/(FI1-EY1) -> 109018.23 | FI155: =EE90 -> 110323.73 | FK155: =FL90 -> 69798 | FL155: =FK155+(FP155-FK155)*(FL1-FK1)/(FP1-FK1) -> 70356.8 | FM155: =FK155+(FP155-FK155)*(FM1-FK1)/(FP1-FK1) -> 70915.6 | FN155: =FK155+(FP155-FK155)*(FN1-FK1)/(FP1-FK1) -> 71474.4 | FO155: =FK155+(FP155-FK155)*(FO1-FK1)/(FP1-FK1) -> 72033.2 | FP155: =FM90 -> 72592 | FQ155: =FP155+(FZ155-FP155)*(FQ1-FP1)/(FZ1-FP1) -> 73820.71 | FR155: =FP155+(FZ155-FP155)*(FR1-FP1)/(FZ1-FP1) -> 75049.42 | FS155: =FP155+(FZ155-FP155)*(FS1-FP1)/(FZ1-FP1) -> 76278.13 | FT155: =FP155+(FZ155-FP155)*(FT1-FP1)/(FZ1-FP1) -> 77506.84 | FU155: =FP155+(FZ155-FP155)*(FU1-FP1)/(FZ1-FP1) -> 78735.55 | FV155: =FP155+(FZ155-FP155)*(FV1-FP1)/(FZ1-FP1) -> 79964.26 | FW155: =FP155+(FZ155-FP155)*(FW1-FP1)/(FZ1-FP1) -> 81192.969 | FX155: =FP155+(FZ155-FP155)*(FX1-FP1)/(FZ1-FP1) -> 82421.679 | FY155: =FP155+(FZ155-FP155)*(FY1-FP1)/(FZ1-FP1) -> 83650.389 | FZ155: =FN90 -> 84879.099 | GA155: =FZ155+(GJ155-FZ155)*(GA1-FZ1)/(GJ1-FZ1) -> 86118.06 | GB155: =FZ155+(GJ155-FZ155)*(GB1-FZ1)/(GJ1-FZ1) -> 87357.021 | GC155: =FZ155+(GJ155-FZ155)*(GC1-FZ1)/(GJ1-FZ1) -> 88595.982 | GD155: =FZ155+(GJ155-FZ155)*(GD1-FZ1)/(GJ1-FZ1) -> 89834.942 | GE155: =FZ155+(GJ155-FZ155)*(GE1-FZ1)/(GJ1-FZ1) -> 91073.903 | GF155: =FZ155+(GJ155-FZ155)*(GF1-FZ1)/(GJ1-FZ1) -> 92312.864 | GG155: =FZ155+(GJ155-FZ155)*(GG1-FZ1)/(GJ1-FZ1) -> 93551.825 | GH155: =FZ155+(GJ155-FZ155)*(GH1-FZ1)/(GJ1-FZ1) -> 94790.785 | GI155: =FZ155+(GJ155-FZ155)*(GI1-FZ1)/(GJ1-FZ1) -> 96029.746 | GJ155: =FO90 -> 97268.707 | GK155: =GJ155+(GT155-GJ155)*(GK1-GJ1)/(GT1-GJ1) -> 98574.209 | GL155: =GJ155+(GT155-GJ155)*(GL1-GJ1)/(GT1-GJ1) -> 99879.711 | GM155: =GJ155+(GT155-GJ155)*(GM1-GJ1)/(GT1-GJ1) -> 101185.21 | GN155: =GJ155+(GT155-GJ155)*(GN1-GJ1)/(GT1-GJ1) -> 102490.72 | GO155: =GJ155+(GT155-GJ155)*(GO1-GJ1)/(GT1-GJ1) -> 103796.22 | GP155: =GJ155+(GT155-GJ155)*(GP1-GJ1)/(GT1-GJ1) -> 105101.72 | GQ155: =GJ155+(GT155-GJ155)*(GQ1-GJ1)/(GT1-GJ1) -> 106407.22 | GR155: =GJ155+(GT155-GJ155)*(GR1-GJ1)/(GT1-GJ1) -> 107712.72 | GS155: =GJ155+(GT155-GJ155)*(GS1-GJ1)/(GT1-GJ1) -> 109018.23 | GT155: =FP90 -> 110323.73 | GV155: =GW90 -> 69798 | GW155: =GV155+(HA155-GV155)*(GW1-GV1)/(HA1-GV1) -> 70356.8 | GX155: =GV155+(HA155-GV155)*(GX1-GV1)/(HA1-GV1) -> 70915.6 | GY155: =GV155+(HA155-GV155)*(GY1-GV1)/(HA1-GV1) -> 71474.4 | GZ155: =GV155+(HA155-GV155)*(GZ1-GV1)/(HA1-GV1) -> 72033.2 | HA155: =GX90 -> 72592 | HB155: =HA155+(HK155-HA155)*(HB1-HA1)/(HK1-HA1) -> 73820.71 | HC155: =HA155+(HK155-HA155)*(HC1-HA1)/(HK1-HA1) -> 75049.42 | HD155: =HA155+(HK155-HA155)*(HD1-HA1)/(HK1-HA1) -> 76278.13 | HE155: =HA155+(HK155-HA155)*(HE1-HA1)/(HK1-HA1) -> 77506.84 | HF155: =HA155+(HK155-HA155)*(HF1-HA1)/(HK1-HA1) -> 78735.55 | HG155: =HA155+(HK155-HA155)*(HG1-HA1)/(HK1-HA1) -> 79964.26 | HH155: =HA155+(HK155-HA155)*(HH1-HA1)/(HK1-HA1) -> 81192.969 | HI155: =HA155+(HK155-HA155)*(HI1-HA1)/(HK1-HA1) -> 82421.679 | HJ155: =HA155+(HK155-HA155)*(HJ1-HA1)/(HK1-HA1) -> 83650.389 | HK155: =GY90 -> 84879.099 | HL155: =HK155+(HU155-HK155)*(HL1-HK1)/(HU1-HK1) -> 86118.06 | HM155: =HK155+(HU155-HK155)*(HM1-HK1)/(HU1-HK1) -> 87357.021 | HN155: =HK155+(HU155-HK155)*(HN1-HK1)/(HU1-HK1) -> 88595.982 | HO155: =HK155+(HU155-HK155)*(HO1-HK1)/(HU1-HK1) -> 89834.942 | HP155: =HK155+(HU155-HK155)*(HP1-HK1)/(HU1-HK1) -> 91073.903 | HQ155: =HK155+(HU155-HK155)*(HQ1-HK1)/(HU1-HK1) -> 92312.864 | HR155: =HK155+(HU155-HK155)*(HR1-HK1)/(HU1-HK1) -> 93551.825 | HS155: =HK155+(HU155-HK155)*(HS1-HK1)/(HU1-HK1) -> 94790.785 | HT155: =HK155+(HU155-HK155)*(HT1-HK1)/(HU1-HK1) -> 96029.746 | HU155: =GZ90 -> 97268.707 | HV155: =HU155+(IE155-HU155)*(HV1-HU1)/(IE1-HU1) -> 98574.209 | HW155: =HU155+(IE155-HU155)*(HW1-HU1)/(IE1-HU1) -> 99879.711 | HX155: =HU155+(IE155-HU155)*(HX1-HU1)/(IE1-HU1) -> 101185.21 | HY155: =HU155+(IE155-HU155)*(HY1-HU1)/(IE1-HU1) -> 102490.72 | HZ155: =HU155+(IE155-HU155)*(HZ1-HU1)/(IE1-HU1) -> 103796.22 | IA155: =HU155+(IE155-HU155)*(IA1-HU1)/(IE1-HU1) -> 105101.72 | IB155: =HU155+(IE155-HU155)*(IB1-HU1)/(IE1-HU1) -> 106407.22 | IC155: =HU155+(IE155-HU155)*(IC1-HU1)/(IE1-HU1) -> 107712.72 | ID155: =HU155+(IE155-HU155)*(ID1-HU1)/(IE1-HU1) -> 109018.23 | IE155: =HA90 -> 110323.73 | IL155: 71786.848 | IV155: 73527.59 | JF155: 74648.845 | JP155: 74089.791 | JW155: 71786.848 | JX155: =$JW155+($KG155-$JW155)*(JX$1-$JW$1)/($KG$1-$JW$1) -> 71858.337 | JY155: =$JW155+($KG155-$JW155)*(JY$1-$JW$1)/($KG$1-$JW$1) -> 71929.826 | JZ155: =$JW155+($KG155-$JW155)*(JZ$1-$JW$1)/($KG$1-$JW$1) -> 72001.314 | KA155: =$JW155+($KG155-$JW155)*(KA$1-$JW$1)/($KG$1-$JW$1) -> 72072.803 | KB155: =$JW155+($KG155-$JW155)*(KB$1-$JW$1)/($KG$1-$JW$1) -> 72144.291 | KC155: =$JW155+($KG155-$JW155)*(KC$1-$JW$1)/($KG$1-$JW$1) -> 72215.78 | KD155: =$JW155+($KG155-$JW155)*(KD$1-$JW$1)/($KG$1-$JW$1) -> 72287.268 | KE155: =$JW155+($KG155-$JW155)*(KE$1-$JW$1)/($KG$1-$JW$1) -> 72358.757 | KF155: =$JW155+($KG155-$JW155)*(KF$1-$JW$1)/($KG$1-$JW$1) -> 72430.245 | KG155: 72501.734 | KH155: =$KG155+($KQ155-$KG155)*(KH$1-$KG$1)/($KQ$1-$KG$1) -> 72562.625 | KI155: =$KG155+($KQ155-$KG155)*(KI$1-$KG$1)/($KQ$1-$KG$1) -> 72623.516 | KJ155: =$KG155+($KQ155-$KG155)*(KJ$1-$KG$1)/($KQ$1-$KG$1) -> 72684.407 | KK155: =$KG155+($KQ155-$KG155)*(KK$1-$KG$1)/($KQ$1-$KG$1) -> 72745.298 | KL155: =$KG155+($KQ155-$KG155)*(KL$1-$KG$1)/($KQ$1-$KG$1) -> 72806.189 | KM155: =$KG155+($KQ155-$KG155)*(KM$1-$KG$1)/($KQ$1-$KG$1) -> 72867.08 | KN155: =$KG155+($KQ155-$KG155)*(KN$1-$KG$1)/($KQ$1-$KG$1) -> 72927.971 | KO155: =$KG155+($KQ155-$KG155)*(KO$1-$KG$1)/($KQ$1-$KG$1) -> 72988.862 | KP155: =$KG155+($KQ155-$KG155)*(KP$1-$KG$1)/($KQ$1-$KG$1) -> 73049.753 | KQ155: 73110.644 | KR155: =$KQ155+($LA155-$KQ155)*(KR$1-$KQ$1)/($LA$1-$KQ$1) -> 73014.336 | KS155: =$KQ155+($LA155-$KQ155)*(KS$1-$KQ$1)/($LA$1-$KQ$1) -> 72918.028 | KT155: =$KQ155+($LA155-$KQ155)*(KT$1-$KQ$1)/($LA$1-$KQ$1) -> 72821.719 | KU155: =$KQ155+($LA155-$KQ155)*(KU$1-$KQ$1)/($LA$1-$KQ$1) -> 72725.411 | KV155: =$KQ155+($LA155-$KQ155)*(KV$1-$KQ$1)/($LA$1-$KQ$1) -> 72629.103 | KW155: =$KQ155+($LA155-$KQ155)*(KW$1-$KQ$1)/($LA$1-$KQ$1) -> 72532.794 | KX155: =$KQ155+($LA155-$KQ155)*(KX$1-$KQ$1)/($LA$1-$KQ$1) -> 72436.486 | KY155: =$KQ155+($LA155-$KQ155)*(KY$1-$KQ$1)/($LA$1-$KQ$1) -> 72340.177 | KZ155: =$KQ155+($LA155-$KQ155)*(KZ$1-$KQ$1)/($LA$1-$KQ$1) -> 72243.869 | LA155: 72147.561
...

Sheet axTER
C1: Scénarios de rénovation tertiaire
C3: Commissariat Général au Développement Durable et al., « Scénarios de rénovation énergétique des bâtiments tertiaires - Quelles solutions pour quels coûts à l’horizon 2050 ? »
C5: Aperçu des résultats
C6: Nom | G6: P0 | H6: P0 | I6: P0 | J6: REF | K6: AME | L6: AMSDec0
C7: Couverture | G7: parc existant | H7: parc existant | I7: parc total | J7: parc total | K7: parc total | L7: parc total
C8: Année | G8: 2019 | H8: 2050 | I8: 2050 | J8: 2050 | K8: 2050 | L8: 2050
B9: p.71 | C9: Conso. unitaire moy. (kWhEF/m² par an) | G9: 109 | H9: 74 | I9: 59 | J9: 52 | K9: 41 | L9: 28
B10: idem | C10: Besoin unitaire moy. (kWhEF/m² par an) | G10: 97 | H10: 82 | I10: 68 | J10: 64 | K10: 55 | L10: 46
C11: gain sur besoin moyen (% 2019) | H11: =(H10-$G$10)/$G$10 -> -0.15463918 | I11: =(I10-$G$10)/$G$10 -> -0.29896907 | J11: =(J10-$G$10)/$G$10 -> -0.34020619 | K11: =(K10-$G$10)/$G$10 -> -0.43298969 | L11: =(L10-$G$10)/$G$10 -> -0.5257732
B12: idem | C12: Rendement moyen | G12: 0.9 | H12: 1.1 | I12: 1.2 | J12: 1.2 | K12: 1.3 | L12: 1.6
B13: p.69 | C13: Consommations en énergie primaire (kWhEP/m² par an) | G13: 284 | H13: 194 | I13: n.d. | J13: 187 | K13: 176 | L13: 130
C15: Corrections pour séparer les effets de la construction neuve et des rénovations.
C18: Dynamiques de construction
C19: Surfaces construites (en mm²) | G19: en 2010 | H19: en 2020 | I19: en 2030 | J19: en 2040 | K19: en 2050
C20: Scénarios REF & AME | G20: 10 | H20: 112 | I20: 152 | J20: 194 | K20: 345
C21: Scénarios AMS | G21: 10 | H21: 112 | I21: 148 | J21: 186 | K21: 319
C22: source: op. cit. pp.54-55, tableaux 13 et 14
C24: Dynamiques de construction, par période
C25: Surfaces construites (en mm²) | G25: 2010-2020 | H25: 2021-2030 | I25: 2031-2040 | J25: 2041-2050 | K25: Ensemble
C26: Scénarios REF & AME | G26: =H20 -> 112 | H26: =I20-H20 -> 40 | I26: =J20-I20 -> 42 | J26: =K20-J20 -> 151 | K26: =SUM(G26:J26) -> 345
C27: Scénarios AMS | G27: =H21 -> 112 | H27: =I21-H21 -> 36 | I27: =J21-I21 -> 38 | J27: =K21-J21 -> 133 | K27: =SUM(G27:J27) -> 319
C28: Ancien : 818 millions de m²
C31: Besoins unitaires des bâtiments neufs pour le chauffage, scénarios REF et AME
G32: Parc existant | H32: Parc total | I32: Parc neuf
C33: Besoin unitaire moy. (kWhEF/m² par an) | G33: 82 | H33: 68 | I33: =(H33*H34-G33*G34)/I34 -> 34.724638
C34: Nombre de logements | G34: 820 | H34: =820+345 -> 1165 | I34: 345
C36: Besoins unitaires des bâtiments neufs pour le chauffage
C37: (en kWhEF/m² par an) | G37: 2010-2020 | H37: 2021-2030 | I37: 2031-2040 | J37: 2041-2050 | K37: Ensemble
C38: Scénarios REF & AME | G38: 35 | H38: 35 | I38: 35 | J38: 35
C39: Scénarios AMS | G39: 35 | H39: =$G$38*(1-5%) -> 33.25 | I39: =$G$38*(1-15%) -> 29.75 | J39: =$G$38*(1-30%) -> 24.5 | K39: =SUMPRODUCT(G39:J39,G27:J27)/K27 -> 29.799373
C40: source: op. cit. p.55, Pour les scénarios AMS, (…), l’hypothèse retenue est de faire baisser les besoins unitaires des bâtiments entrants progressivement entre 2020 et 2050.
C43: Besoins unitaires des bâtiments neufs pour le chauffage, scénarios AMS
G44: Parc existant | H44: Parc total | I44: Parc neuf
C45: Besoin unitaire moy. (kWhEF/m² par an) | G45: =(H45*H46-I45*I46)/G46 -> 52.239609 | H45: 46 | I45: 30
C46: Nombre de logements | G46: 818 | H46: =818+319 -> 1137 | I46: 319
C49: Coûts unitaires rénovations tertiaires
C51: Agence de l’Environnement et de la Maîtrise de l’Energie, « Retours d’expérience : 12 projets de rénovation énergétique de bâtiments tertiaires en Auvergne Rhône-Alpes ».
C52: Région Auvergne-Rhône-Alpes, « Fiches projet rénovation énergétique », 2017
G54: Consommation (GWh) | J54: Surface | K54: Coût des travaux
G55: Avant travaux | H55: Après travaux | I55: Gain | K55: Total | L55: dont conception - réalisation | M55: dont EE | N55: total / m² | O55: EE / m²
C56: École des Vennes à Bourg-en-Bresse | G56: 350 | H56: 140 | I56: =ROUND((H56-G56)/G56,2) -> -0.6 | J56: 2357 | K56: 1390962 | L56: 1309506 | M56: 0.93 | N56: =K56/J56 -> 590.14086 | O56: =ROUND(K56*M56/J56,1) -> 548.8
C57: Groupe scolaire Baudin à Bourg-en-Bresse (01) | G57: 372 | H57: 167 | I57: =ROUND((H57-G57)/G57,2) -> -0.55 | J57: 1581 | K57: 1858823 | L57: 1792377 | M57: 0.35 | N57: =K57/J57 -> 1175.7261 | O57: =ROUND(K57*M57/J57,1) -> 411.5
C59: (…)
C61: Paramétrage panel 100
C63: Besoins de chauffage enveloppe kWh/m² par an
C65: BUREAUX | D65: ANCIEN | E65: 144
C66: BUREAUX | D66: RECENT | E66: 72
C67: BUREAUX | D67: SIMPLE | E67: 120
C68: BUREAUX | D68: MOYENNE | E68: 80
C69: BUREAUX | D69: COMPLETE | E69: 50
C70: CAHOR | D70: ANCIEN | E70: 136
C71: CAHOR | D71: RECENT | E71: 72
C72: CAHOR | D72: SIMPLE | E72: 120
C73: CAHOR | D73: MOYENNE | E73: 80
C74: CAHOR | D74: COMPLETE | E74: 50
C75: COMMERCE | D75: ANCIEN | E75: 96
C76: COMMERCE | D76: RECENT | E76: 64
... C104: TRANSPORT | D104: COMPLETE | E104: 40
C106: Rendements
C108: GAZ | E108: 0.95
C109: FIOUL | E109: 0.9
C110: ELEC-J | E110: 0.9
C111: ELEC-PAC | E111: 3
C112: URBAIN | E112: 1
C113: BOIS | E113: 1
C117: Coût des travaux énergétiques
C119: Enveloppe initiale | D119: Enveloppe finale | E119: Coût €/m²
C121: ANCIEN | D121: SIMPLE | E121: 100
C122: ANCIEN | D122: MOYENNE | E122: 200
C123: ANCIEN | D123: COMPLETE | E123: 450
C125: RECENT | D125: SIMPLE | E125: 60
C126: RECENT | D126: MOYENNE | E126: 150
C127: RECENT | D127: COMPLETE | E127: 400
C130: Travaux d'entretien
C132: Enveloppe finale | E132: Coût €/m²/an
C133: ANCIEN | E133: 4
C134: RECENT | E134: 1.5
C135: SIMPLE | E135: 1.5
C136: MOYENNE | E136: 1.5
C137: COMPLETE | E137: 1.5
C139: Systèmes de chauffage
E141: Coût €/m²
C142: GAZ | E142: 18
C143: FIOUL | E143: 24
C144: ELEC-J | E144: 10
C145: ELEC-PAC | E145: 80
C146: URBAIN | E146: 31
C147: BOIS | E147: 31
E150: Coût €/m²/an
C151: GAZ | E151: =E142*0.035 -> 0.63
C152: FIOUL | E152: =E143*0.035 -> 0.84
C153: ELEC-J | E153: =E144*0.035 -> 0.35
C154: ELEC-PAC | E154: =E145*0.035 -> 2.8
C155: URBAIN | E155: =E146*0.035 -> 1.085
C156: BOIS | E156: =E147*0.035 -> 1.085
