Workbook
Name GES.élec: 'total biocarb'!$C$16
Name GES.fossile: 'total biocarb'!$C$15
Name NRJ.kWh: 'total biocarb'!$C$12

Sheet Bilan énergie
B1: Taux de bio (taux d'incorporation en énergie)
C2: 2018 | D2: 2019 | E2: 2020 | F2: 2021 | G2: 2022 | H2: 2023 | I2: 2025 | J2: 2030 | K2: 2035 | L2: 2040 | M2: 2045 | N2: 2050
B3: essence | C3: =FE_et_bio!B46 -> 0.073 | D3: =FE_et_bio!C46 -> 0.082039105 | E3: =FE_et_bio!D46 -> 0.076978498 | F3: =FE_et_bio!E46 -> 0.077583337 | G3: =FE_et_bio!F46 -> 0.080734559 | H3: =FE_et_bio!G46 -> 0.086852684 | I3: =FE_et_bio!H46 -> 0.105 | J3: =FE_et_bio!I46 -> 0.137 | ... N3: =FE_et_bio!M46 -> 1
B4: gazole | C4: =FE_et_bio!B47 -> 0.0697 | D4: =FE_et_bio!C47 -> 0.075808287 | E4: =FE_et_bio!D47 -> 0.075100974 | F4: =FE_et_bio!E47 -> 0.072170546 | G4: =FE_et_bio!F47 -> 0.073714163 | H4: =FE_et_bio!G47 -> 0.078624535 | I4: =FE_et_bio!H47 -> 0.094 | J4: =FE_et_bio!I47 -> 0.137 | ... N4: =FE_et_bio!M47 -> 1
B5: GNV | C5: =FE_et_bio!B48 -> 0.001 | D5: =FE_et_bio!C48 -> 0.074333333 | E5: =FE_et_bio!D48 -> 0.001 | F5: =FE_et_bio!E48 -> 0 | G5: =FE_et_bio!F48 -> 0 | H5: =FE_et_bio!G48 -> 0.01 | I5: =FE_et_bio!H48 -> 0.05 | J5: =FE_et_bio!I48 -> 0.15 | ... N5: =FE_et_bio!M48 -> 1
B7: FE avec taux de bio (taux d'incorporation en énergie) | I7: reprise de la feuille FE et bio
C8: 2018 | D8: 2019 | E8: 2020 | F8: 2021 | G8: 2022 | H8: 2023 | I8: 2025 | J8: 2030 | K8: 2035 | L8: 2040 | M8: 2045 | N8: 2050
B9: Taux d’incorporation des biocarburants dans l’essence (routier) | C9: =FE_et_bio!B67 -> 2.8407961 | D9: =FE_et_bio!C67 -> 2.8130958 | E9: =FE_et_bio!D67 -> 2.828604 | F9: =FE_et_bio!E67 -> 2.8267505 | G9: =FE_et_bio!F67 -> 2.8170935 | H9: =FE_et_bio!G67 -> 2.7983445 | I9: =FE_et_bio!H67 -> 2.742732 | J9: =FE_et_bio!I67 -> 2.6446678 | ... N9: =FE_et_bio!M67 -> 0
B10: Taux d’incorporation des biocarburants dans le diesel (routier) | C10: =FE_et_bio!B68 -> 2.9320544 | D10: =FE_et_bio!C68 -> 2.9128027 | E10: =FE_et_bio!D68 -> 2.915032 | F10: =FE_et_bio!E68 -> 2.9242679 | G10: =FE_et_bio!F68 -> 2.9194029 | H10: =FE_et_bio!G68 -> 2.9039267 | I10: =FE_et_bio!H68 -> 2.8554674 | J10: =FE_et_bio!I68 -> 2.719943 | ... N10: =FE_et_bio!M68 -> 0
B11: Taux d’incorporation du gaz renouvelable dans le gaz (GNV routier) | C11: =FE_et_bio!B69 -> 2.3606669 | D11: =FE_et_bio!C69 -> 2.187378 | E11: =FE_et_bio!D69 -> 2.3606669 | F11: =FE_et_bio!E69 -> 2.3630299 | G11: =FE_et_bio!F69 -> 2.3630299 | H11: =FE_et_bio!G69 -> 2.3393996 | I11: =FE_et_bio!H69 -> 2.2448784 | J11: =FE_et_bio!I69 -> 2.0085754 | ... N11: =FE_et_bio!M69 -> 0
B16: 4 - Demande d'énergie finale des transports | M16: Mtep | P16: 4 - Demande d'énergie finale des transports | AA16: TWh | AD16: 4 - GES | AO16: MtCO2e
C17: 2018 | D17: 2019 | E17: 2020 | F17: 2021 | G17: 2022 | H17: 2023 | I17: 2025 | J17: 2030 | K17: 2035 | L17: 2040 | M17: 2045 | N17: 2050 | Q17: 2018 | R17: 2019 | S17: 2020 | T17: 2021 | U17: 2022 | V17: 2023 | W17: 2025 | X17: 2030 | Y17: 2035 | Z17: 2040 | AA17: 2045 | AB17: 2050 | AE17: 2018 | AF17: 2019 | AG17: 2020 | AH17: 2021 | AI17: 2022 | AJ17: 2023 | AK17: 2025 | AL17: 2030 | AM17: 2035 | AN17: 2040 | AO17: 2045 | AP17: 2050
B19: 4.1 Trafics
C20: 2018 | D20: 2019 | E20: 2020 | F20: 2021 | G20: 2022 | H20: 2023 | I20: 2025 | J20: 2030 | K20: 2035 | L20: 2040 | M20: 2045 | N20: 2050
B21: Passagers (Gpkm)
B22: Voitures | C22: =Trafic!C34 -> 827.91488 | D22: =Trafic!D34 -> 834.04487 | E22: =Trafic!E34 -> 669.08139 | F22: =Trafic!F34 -> 725.93652 | G22: =Trafic!G34 -> 809.40368 | H22: =Trafic!H34 -> 796.49623 | I22: =Trafic!I34 -> 807.28652 | J22: =Trafic!J34 -> 803.06063 | ... N22: =Trafic!N34 -> 792.41584
B23: Bus et autocars | C23: =Trafic!C37 -> 59.355012 | D23: =Trafic!D37 -> 60.956931 | E23: =Trafic!E37 -> 37.910503 | F23: =Trafic!F37 -> 41.749797 | G23: =Trafic!G37 -> 47.908934 | H23: =Trafic!H37 -> 53.67602 | I23: =Trafic!I37 -> 53.413542 | J23: =Trafic!J37 -> 63 | ... N23: =Trafic!N37 -> 69.193386
B24: Ferroviaire | C24: =Trafic!C36 -> 107.87256 | D24: =Trafic!D36 -> 112.30932 | E24: =Trafic!E36 -> 64.816306 | F24: =Trafic!F36 -> 86.419111 | G24: =Trafic!G36 -> 117.85172 | H24: =Trafic!H36 -> 123.74975 | I24: =Trafic!I36 -> 130.56 | J24: =Trafic!J36 -> 152.67788 | ... N24: =Trafic!N36 -> 199.23288
B25: Aérien domestique | C25: =Aérien!C6 -> 16.012112 | D25: =Aérien!D6 -> 16.265166 | E25: =Aérien!E6 -> 7.2496757 | F25: =Aérien!F6 -> 10.086837 | G25: =Aérien!G6 -> 13.52361 | H25: =Aérien!H6 -> 13.233747 | I25: =Aérien!I6 -> 12.510166 | J25: =Aérien!J6 -> 12.344811 | ... N25: =Aérien!N6 -> 5.4891365
B28: Marchandises Gtkm)
B29: Poids lourds | C29: =Trafic!C69 -> 286.16291 | D29: =Trafic!D69 -> 296.78758 | E29: =Trafic!E69 -> 286.97453 | F29: =Trafic!F69 -> 296.16941 | G29: =Trafic!G69 -> 296.17082 | H29: =Trafic!H69 -> 289.12141 | I29: =Trafic!I69 -> 301.49401 | J29: =Trafic!J69 -> 276.66456 | ... N29: =Trafic!N69 -> 267.64517
B30: VUL | C30: =Trafic!C73 -> - | D30: =Trafic!D73 -> - | E30: =Trafic!E73 -> - | F30: =Trafic!F73 -> - | G30: =Trafic!G73 -> - | H30: =Trafic!H73 -> - | I30: =Trafic!I73 -> - | J30: =Trafic!J73 -> - | ... N30: =Trafic!N73 -> -
B31: Ferroviaire | C31: =Trafic!C70 -> 33.849726 | D31: =Trafic!D70 -> 33.90871 | E31: =Trafic!E70 -> 31.29656 | F31: =Trafic!F70 -> 35.769721 | G31: =Trafic!G70 -> 35.281856 | H31: =Trafic!H70 -> 29.398991 | I31: =Trafic!I70 -> 34.260683 | J31: =Trafic!J70 -> 63.037494 | ... N31: =Trafic!N70 -> 94.241257
B32: Fluvial | C32: =Trafic!C71 -> 7.255286 | D32: =Trafic!D71 -> 7.9964556 | E32: =Trafic!E71 -> 6.987717 | F32: =Trafic!F71 -> 7.2654698 | G32: =Trafic!G71 -> 6.5932717 | H32: =Trafic!H71 -> 5.9066986 | I32: =Trafic!I71 -> 6.8521366 | J32: =Trafic!J71 -> 10.506249 | ... N32: =Trafic!N71 -> 15.078601
B34: Voitures Gvkm | C34: =Trafic!C111 -> 501 | D34: =Trafic!D111 -> 504.5 | E34: =Trafic!E111 -> 406.6 | F34: =Trafic!F111 -> 441.1 | G34: =Trafic!G111 -> 489.7 | H34: =Trafic!H111 -> 481.8648 | I34: =Trafic!I111 -> 480.62862 | J34: =Trafic!J111 -> 465.73168 | ... N34: =Trafic!N111 -> 435.74481
K37: y compris vols vers DROM | Y37: y compris vols vers DROM | AN37: y compris vols vers DROM
B38: 4.2 Demande d'énergie finale par énergie | P38: 4.2 Demande d'énergie finale par énergie | AD38: 4.2 Demande de ges
B39: Mtep | C39: 2018 | D39: 2019 | E39: 2020 | F39: 2021 | G39: 2022 | H39: 2023 | I39: 2025 | J39: 2030 | K39: 2035 | L39: 2040 | M39: 2045 | N39: 2050 | P39: TWh | Q39: 2018 | R39: 2019 | S39: 2020 | T39: 2021 | U39: 2022 | V39: 2023 | W39: 2025 | X39: 2030 | Y39: 2035 | Z39: 2040 | AA39: 2045 | AB39: 2050 | AD39: Mt CO2eq | AE39: 2018 | AF39: 2019 | AG39: 2020 | AH39: 2021 | AI39: 2022 | AJ39: 2023 | AK39: 2025 | AL39: 2030 | AM39: 2035 | AN39: 2040 | AO39: 2045 | AP39: 2050
B40: Essence (yc carb subst) | C40: =C112+C143 -> 7.9780722 | D40: =D112+D143 -> 8.4834587 | E40: =E112+E143 -> 7.3040589 | F40: =F112+F143 -> 8.3465132 | G40: =G112+G143 -> 9.4562389 | H40: =H112+H143 -> 9.808148 | I40: =I112+I143 -> 10.28291 | J40: =J112+J143 -> 12.401463 | ... N40: =N112+N143 -> 0.24934978 | P40: Essence (yc carb subst) | Q40: =C40*11.63 -> 92.784979 | R40: =D40*11.63 -> 98.662625 | S40: =E40*11.63 -> 84.946205 | T40: =F40*11.63 -> 97.069949 | U40: =G40*11.63 -> 109.97606 | V40: =H40*11.63 -> 114.06876 | W40: =I40*11.63 -> 119.59024 | X40: =J40*11.63 -> 144.22902 | ... AB40: =N40*11.63 -> 2.899938 | AD40: Essence (yc carb subst) | AE40: =C40*C9 -> 22.664077 | AF40: =D40*D9 -> 23.864782 | AG40: =E40*E9 -> 20.66029 | AH40: =F40*F9 -> 23.59351 | AI40: =G40*G9 -> 26.63911 | AJ40: =H40*H9 -> 27.446577 | AK40: =I40*I9 -> 28.203265 | AL40: =J40*J9 -> 32.79775 | ... AP40: =N40*N9 -> 0
B41: dont essence fossile | C41: =C40*(1-FE_et_bio!B46) -> 7.3956729 | D41: =D40*(1-FE_et_bio!C46) -> 7.7874834 | E41: =E40*(1-FE_et_bio!D46) -> 6.7418034 | F41: =F40*(1-FE_et_bio!E46) -> 7.6989629 | G41: =G40*(1-FE_et_bio!F46) -> 8.6927936 | H41: =H40*(1-FE_et_bio!G46) -> 8.956284 | I41: =I40*(1-FE_et_bio!H46) -> 9.2032041 | J41: =J40*(1-FE_et_bio!I46) -> 10.702463 | ... N41: =N40*(1-FE_et_bio!M46) -> 0 | P41: dont essence fossile | Q41: =C41*11.63 -> 86.011676 | R41: =D41*11.63 -> 90.568432 | S41: =E41*11.63 -> 78.407174 | T41: =F41*11.63 -> 89.538938 | U41: =G41*11.63 -> 101.09719 | V41: =H41*11.63 -> 104.16158 | W41: =I41*11.63 -> 107.03326 | X41: =J41*11.63 -> 124.46964 | ... AB41: =N41*11.63 -> 0 | AD41: dont essence fossile | AE41: =C41*FE_et_bio!$B$17 -> 22.664077 | AF41: =D41*FE_et_bio!$B$17 -> 23.864782 | AG41: =E41*FE_et_bio!$B$17 -> 20.66029 | AH41: =F41*FE_et_bio!$B$17 -> 23.59351 | AI41: =G41*FE_et_bio!$B$17 -> 26.63911 | AJ41: =H41*FE_et_bio!$B$17 -> 27.446577 | AK41: =I41*FE_et_bio!$B$17 -> 28.203265 | AL41: =J41*FE_et_bio!$B$17 -> 32.79775 | ... AP41: =N41*FE_et_bio!$B$17 -> 0
B42: dont bio-essence | C42: =C40-C41 -> 0.58239927 | D42: =D40-D41 -> 0.69597536 | E42: =E40-E41 -> 0.56225548 | F42: =F40-F41 -> 0.64755035 | G42: =G40-G41 -> 0.76344528 | H42: =H40-H41 -> 0.85186397 | I42: =I40-I41 -> 1.0797055 | J42: =J40-J41 -> 1.6990004 | ... N42: =N40-N41 -> 0.24934978 | P42: dont bio-essence | Q42: =C42*11.63 -> 6.7733035 | R42: =D42*11.63 -> 8.0941934 | S42: =E42*11.63 -> 6.5390313 | T42: =F42*11.63 -> 7.5310106 | U42: =G42*11.63 -> 8.8788686 | V42: =H42*11.63 -> 9.907178 | W42: =I42*11.63 -> 12.556975 | X42: =J42*11.63 -> 19.759375 | ... AB42: =N42*11.63 -> 2.899938 | AD42: dont bio-essence | AE42: =0 -> 0 | AF42: =0 -> 0 | AG42: =0 -> 0 | AH42: =0 -> 0 | AI42: =0 -> 0 | AJ42: =0 -> 0 | AK42: =0 -> 0 | AL42: =0 -> 0 | ... AP42: =0 -> 0
B43: Gazole (yc carb subst) | C43: =C113+C124+C141 -> 35.903297 | D43: =D113+D124+D141 -> 35.889475 | E43: =E113+E124+E141 -> 29.655065 | F43: =F113+F124+F141 -> 31.610134 | G43: =G113+G124+G141 -> 32.89847 | H43: =H113+H124+H141 -> 31.401752 | I43: =I113+I124+I141 -> 28.988553 | J43: =J113+J124+J141 -> 18.298499 | ... N43: =N113+N124+N141 -> 1.3575248 | P43: Gazole (yc carb subst) | Q43: =C43*11.63 -> 417.55534 | R43: =D43*11.63 -> 417.3946 | S43: =E43*11.63 -> 344.8884 | T43: =F43*11.63 -> 367.62586 | U43: =G43*11.63 -> 382.60921 | V43: =H43*11.63 -> 365.20238 | W43: =I43*11.63 -> 337.13688 | X43: =J43*11.63 -> 212.81155 | ... AB43: =N43*11.63 -> 15.788013 | AD43: Gazole (yc carb subst) | AE43: =C43*C10 -> 105.27042 | AF43: =D43*D10 -> 104.53896 | AG43: =E43*E10 -> 86.445463 | AH43: =F43*F10 -> 92.436501 | AI43: =G43*G10 -> 96.043887 | AJ43: =H43*H10 -> 91.188387 | AK43: =I43*I10 -> 82.775869 | AL43: =J43*J10 -> 49.770875 | ... AP43: =N43*N10 -> 0
B44: dont gazole fossile | C44: =C43*(1-FE_et_bio!B47) -> 33.400837 | D44: =D43*(1-FE_et_bio!C47) -> 33.168756 | E44: =E43*(1-FE_et_bio!D47) -> 27.427941 | F44: =F43*(1-FE_et_bio!E47) -> 29.328813 | G44: =G43*(1-FE_et_bio!F47) -> 30.473387 | H44: =H43*(1-FE_et_bio!G47) -> 28.932804 | I44: =I43*(1-FE_et_bio!H47) -> 26.263629 | J44: =J43*(1-FE_et_bio!I47) -> 15.791605 | ... N44: =N43*(1-FE_et_bio!M47) -> 0 | P44: dont gazole fossile | Q44: =C44*11.63 -> 388.45174 | R44: =D44*11.63 -> 385.75263 | S44: =E44*11.63 -> 318.98695 | T44: =F44*11.63 -> 341.0941 | U44: =G44*11.63 -> 354.40549 | V44: =H44*11.63 -> 336.48851 | W44: =I44*11.63 -> 305.44601 | X44: =J44*11.63 -> 183.65636 | ... AB44: =N44*11.63 -> 0 | AD44: dont gazole fossile | AE44: =C44*FE_et_bio!$B$18 -> 105.27042 | AF44: =D44*FE_et_bio!$B$18 -> 104.53896 | AG44: =E44*FE_et_bio!$B$18 -> 86.445463 | AH44: =F44*FE_et_bio!$B$18 -> 92.436501 | AI44: =G44*FE_et_bio!$B$18 -> 96.043887 | AJ44: =H44*FE_et_bio!$B$18 -> 91.188387 | AK44: =I44*FE_et_bio!$B$18 -> 82.775869 | AL44: =J44*FE_et_bio!$B$18 -> 49.770875 | ... AP44: =N44*FE_et_bio!$B$18 -> 0
B45: dont bio-gazole | C45: =C43-C44 -> 2.5024598 | D45: =D43-D44 -> 2.7207196 | E45: =E43-E44 -> 2.2271242 | F45: =F43-F44 -> 2.2813207 | G45: =G43-G44 -> 2.4250832 | H45: =H43-H44 -> 2.4689482 | I45: =I43-I44 -> 2.724924 | J45: =J43-J44 -> 2.5068944 | ... N45: =N43-N44 -> 1.3575248 | P45: dont bio-gazole | Q45: =C45*11.63 -> 29.103607 | R45: =D45*11.63 -> 31.641969 | S45: =E45*11.63 -> 25.901455 | T45: =F45*11.63 -> 26.531759 | U45: =G45*11.63 -> 28.203717 | V45: =H45*11.63 -> 28.713867 | W45: =I45*11.63 -> 31.690866 | X45: =J45*11.63 -> 29.155182 | ... AB45: =N45*11.63 -> 15.788013 | AD45: dont bio-gazole | AE45: =0 -> 0 | AF45: =0 -> 0 | AG45: =0 -> 0 | AH45: =0 -> 0 | AI45: =0 -> 0 | AJ45: =0 -> 0 | AK45: =0 -> 0 | AL45: =0 -> 0 | ... AP45: =0 -> 0
B46: Carburéacteurs autres que H2 (yc vols vers DROM) | C46: =C128+C134-C131-C137 -> 1.6167023 | D46: =D128+D134-D131-D137 -> 1.6501915 | E46: =E128+E134-E131-E137 -> 1.0163051 | F46: =F128+F134-F131-F137 -> 1.2527221 | G46: =G128+G134-G131-G137 -> 1.5262755 | H46: =H128+H134-H131-H137 -> 1.4636046 | I46: =I128+I134-I131-I137 -> 1.4574536 | J46: =J128+J134-J131-J137 -> 1.4204002 | ... N46: =N128+N134-N131-N137 -> 0.86172722 | P46: Carburéacteurs autres que H2 (yc vols vers DROM) | Q46: =Q47+Q48+Q49 -> 18.802248 | R46: =R47+R48+R49 -> 19.191728 | S46: =S47+S48+S49 -> 11.819628 | T46: =T47+T48+T49 -> 14.569159 | U46: =U47+U48+U49 -> 17.750584 | V46: =V47+V48+V49 -> 17.021721 | W46: =W47+W48+W49 -> 16.950185 | X46: =X47+X48+X49 -> 16.519254 | ... AB46: =AB47+AB48+AB49 -> 10.021888 | AD46: Carburéacteurs autres que H2 | AE46: =AE47+AE48+AE49 -> 4.8942251 | AF46: =AF47+AF48+AF49 -> 4.9956067 | AG46: =AG47+AG48+AG49 -> 3.0766492 | AH46: =AH47+AH48+AH49 -> 3.7771826 | AI46: =AI47+AI48+AI49 -> 4.5835133 | AJ46: =AJ47+AJ48+AJ49 -> 4.377585 | AK46: =AK47+AK48+AK49 -> 4.3238905 | AL46: =AL47+AL48+AL49 -> 4.0600239 | ... AP46: =AP47+AP48+AP49 -> 1.6502231
B47: dont kérosène fossile | C47: =C132+C138 -> 1.6167023 | D47: =D132+D138 -> 1.6501915 | E47: =E132+E138 -> 1.0163051 | F47: =F132+F138 -> 1.2477113 | G47: =G132+G138 -> 1.5140653 | H47: =H132+H138 -> 1.4460413 | I47: =I132+I138 -> 1.4283045 | J47: =J132+J138 -> 1.3351762 | ... N47: =N132+N138 -> 0.1356906 | P47: dont kérosène fossile | Q47: =Q132+Q138 -> 18.802248 | R47: =R132+R138 -> 19.191728 | S47: =S132+S138 -> 11.819628 | T47: =T132+T138 -> 14.510882 | U47: =U132+U138 -> 17.60858 | V47: =V132+V138 -> 16.817461 | W47: =W132+W138 -> 16.611181 | X47: =X132+X138 -> 15.528099 | ... AB47: =AB132+AB138 -> 1.5780817 | AD47: dont kérosène fossile | AE47: =C47*FE_et_bio!$B$19 -> 4.8942251 | AF47: =D47*FE_et_bio!$B$19 -> 4.9956067 | AG47: =E47*FE_et_bio!$B$19 -> 3.0766492 | AH47: =F47*FE_et_bio!$B$19 -> 3.7771826 | AI47: =G47*FE_et_bio!$B$19 -> 4.5835133 | AJ47: =H47*FE_et_bio!$B$19 -> 4.377585 | AK47: =I47*FE_et_bio!$B$19 -> 4.3238905 | AL47: =J47*FE_et_bio!$B$19 -> 4.0419641 | ... AP47: =N47*FE_et_bio!$B$19 -> 0.41077467
B48: dont biocarburants durables pour l'aéronautique | C48: =C129+C135 -> 0 | D48: =D129+D135 -> 0 | E48: =E129+E135 -> 0 | F48: =F129+F135 -> 0.0050108886 | G48: =G129+G135 -> 0.012210204 | H48: =H129+H135 -> 0.017563255 | I48: =I129+I135 -> 0.029149072 | J48: =J129+J135 -> 0.079258329 | ... N48: =N129+N135 -> 0.31661141 | P48: dont biocarburants durables pour l'aéronautique | Q48: =Q129+Q135 -> 0 | R48: =R129+R135 -> 0 | S48: =S129+S135 -> 0 | T48: =T129+T135 -> 0.058276634 | U48: =U129+U135 -> 0.14200468 | V48: =V129+V135 -> 0.20426066 | W48: =W129+W135 -> 0.3390037 | X48: =X129+X135 -> 0.92177437 | ... AB48: =AB129+AB135 -> 3.6821907 | AD48: dont biocarburants durables pour l'aéronautique | AE48: =0 -> 0 | AF48: =0 -> 0 | AG48: =0 -> 0 | AH48: =0 -> 0 | AI48: =0 -> 0 | AJ48: =0 -> 0 | AK48: =0 -> 0 | AL48: =0 -> 0 | ... AP48: =0 -> 0
B49: dont PtL pour l'aéronautique | C49: =C130+C136 -> 0 | D49: =D130+D136 -> 0 | E49: =E130+E136 -> 0 | F49: =F130+F136 -> 0 | G49: =G130+G136 -> 0 | H49: =H130+H136 -> 0 | I49: =I130+I136 -> 0 | J49: =J130+J136 -> 0.0059656807 | ... N49: =N130+N136 -> 0.40942521 | P49: dont PtL pour l'aéronautique | Q49: =Q130+Q136 -> 0 | R49: =R130+R136 -> 0 | S49: =S130+S136 -> 0 | T49: =T130+T136 -> 0 | U49: =U130+U136 -> 0 | V49: =V130+V136 -> 0 | W49: =W130+W136 -> 0 | X49: =X130+X136 -> 0.069380867 | ... AB49: =AB130+AB136 -> 4.7616152 | AD49: dont PtL pour l'aéronautique | AE49: =C49*FE_et_bio!$B$19 -> 0 | AF49: =D49*FE_et_bio!$B$19 -> 0 | AG49: =E49*FE_et_bio!$B$19 -> 0 | AH49: =F49*FE_et_bio!$B$19 -> 0 | AI49: =G49*FE_et_bio!$B$19 -> 0 | AJ49: =H49*FE_et_bio!$B$19 -> 0 | AK49: =I49*FE_et_bio!$B$19 -> 0 | AL49: =J49*FE_et_bio!$B$19 -> 0.01805984 | ... AP49: =N49*FE_et_bio!$B$19 -> 1.2394484
B50: GPL | C50: =C114 -> 0 | D50: =D114 -> 0 | E50: =E114 -> 0 | F50: =F114 -> 0 | G50: =G114 -> 0 | H50: =H114 -> 0 | I50: =I114 -> 0 | J50: =J114 -> 0 | ... N50: =N114 -> 0 | P50: GPL | Q50: =C50*11.63 -> 0 | R50: =D50*11.63 -> 0 | S50: =E50*11.63 -> 0 | T50: =F50*11.63 -> 0 | U50: =G50*11.63 -> 0 | V50: =H50*11.63 -> 0 | W50: =I50*11.63 -> 0 | X50: =J50*11.63 -> 0 | ... AB50: =N50*11.63 -> 0 | AD50: GPL | AE50: =C50 -> 0 | AF50: =D50 -> 0 | AG50: =E50 -> 0 | AH50: =F50 -> 0 | AI50: =G50 -> 0 | AJ50: =H50 -> 0 | AK50: =I50 -> 0 | AL50: =J50 -> 0 | ... AP50: =N50 -> 0
B51: GNV (dont bio-GNV) | C51: =C115+C142 -> 0.091650184 | D51: =D115+D142 -> 0.11204792 | E51: =E115+E142 -> 0.13537863 | F51: =F115+F142 -> 0.20167722 | G51: =G115+G142 -> 0.25879115 | H51: =H115+H142 -> 0.26124573 | I51: =I115+I142 -> 0.35432371 | J51: =J115+J142 -> 0.4263092 | ... N51: =N115+N142 -> 0.044497549 | P51: GNV (dont bio-GNV) | Q51: =C51*11.63 -> 1.0658916 | R51: =D51*11.63 -> 1.3031174 | S51: =E51*11.63 -> 1.5744535 | T51: =F51*11.63 -> 2.3455061 | U51: =G51*11.63 -> 3.009741 | V51: =H51*11.63 -> 3.0382879 | W51: =I51*11.63 -> 4.1207847 | X51: =J51*11.63 -> 4.957976 | ... AB51: =N51*11.63 -> 0.51750649 | AD51: GNV (dont bio-GNV) | AE51: =C51*C11 -> 0.21635555 | AF51: =D51*D11 -> 0.24509117 | AG51: =E51*E11 -> 0.31958385 | AH51: =F51*F11 -> 0.4765693 | AI51: =G51*G11 -> 0.61153122 | AJ51: =H51*H11 -> 0.61115817 | AK51: =I51*I11 -> 0.79541364 | AL51: =J51*J11 -> 0.85627419 | ... AP51: =N51*N11 -> 0
B52: dont GNV fossile | C52: =C$51*(1-FE_et_bio!B48) -> 0.091558534 | D52: =D$51*(1-FE_et_bio!C48) -> 0.10371903 | E52: =E$51*(1-FE_et_bio!D48) -> 0.13524325 | F52: =F$51*(1-FE_et_bio!E48) -> 0.20167722 | G52: =G$51*(1-FE_et_bio!F48) -> 0.25879115 | H52: =H$51*(1-FE_et_bio!G48) -> 0.25863328 | I52: =I$51*(1-FE_et_bio!H48) -> 0.33660752 | J52: =J$51*(1-FE_et_bio!I48) -> 0.36236282 | ... N52: =N$51*(1-FE_et_bio!M48) -> 0 | P52: dont GNV fossile | Q52: =C52*11.63 -> 1.0648257 | R52: =D52*11.63 -> 1.2062523 | S52: =E52*11.63 -> 1.572879 | T52: =F52*11.63 -> 2.3455061 | U52: =G52*11.63 -> 3.009741 | V52: =H52*11.63 -> 3.007905 | W52: =I52*11.63 -> 3.9147455 | X52: =J52*11.63 -> 4.2142796 | ... AB52: =N52*11.63 -> 0 | AD52: dont GNV fossile | AE52: =C52*FE_et_bio!$B$20 -> 0.21635555 | AF52: =D52*FE_et_bio!$B$20 -> 0.24509117 | AG52: =E52*FE_et_bio!$B$20 -> 0.31958385 | AH52: =F52*FE_et_bio!$B$20 -> 0.4765693 | AI52: =G52*FE_et_bio!$B$20 -> 0.61153122 | AJ52: =H52*FE_et_bio!$B$20 -> 0.61115817 | AK52: =I52*FE_et_bio!$B$20 -> 0.79541364 | AL52: =J52*FE_et_bio!$B$20 -> 0.85627419 | ... AP52: =N52*FE_et_bio!$B$20 -> 0
B53: dont bio-GNV | C53: =C$51*(1*FE_et_bio!B50) -> 0 | D53: =D$51*(1*FE_et_bio!C50) -> 0 | E53: =E$51*(1*FE_et_bio!D50) -> 0.00013537863 | F53: =F$51*(1*FE_et_bio!E50) -> 0 | G53: =G$51*(1*FE_et_bio!F50) -> 0 | H53: =H$51*(1*FE_et_bio!G50) -> 0 | I53: =I$51*(1*FE_et_bio!H50) -> 0.017716185 | J53: =J$51*(1*FE_et_bio!I50) -> 0.063946381 | ... N53: =N$51*(1*FE_et_bio!M50) -> 0.044497549 | P53: dont bio-GNV | Q53: =C53*11.63 -> 0 | R53: =D53*11.63 -> 0 | S53: =E53*11.63 -> 0.0015744535 | T53: =F53*11.63 -> 0 | U53: =G53*11.63 -> 0 | V53: =H53*11.63 -> 0 | W53: =I53*11.63 -> 0.20603923 | X53: =J53*11.63 -> 0.74369641 | ... AB53: =N53*11.63 -> 0.51750649 | AD53: dont bio-GNV | AE53: =0 -> 0 | AF53: =0 -> 0 | AG53: =0 -> 0 | AH53: =0 -> 0 | AI53: =0 -> 0 | AJ53: =0 -> 0 | AK53: =0 -> 0 | AL53: =0 -> 0 | ... AP53: =0 -> 0
B54: dont e-GNV | C54: =C$51*(1*FE_et_bio!B49) -> 0 | D54: =D$51*(1*FE_et_bio!C49) -> 0 | E54: =E$51*(1*FE_et_bio!D49) -> 0 | F54: =F$51*(1*FE_et_bio!E49) -> 0 | G54: =G$51*(1*FE_et_bio!F49) -> 0 | H54: =H$51*(1*FE_et_bio!G49) -> 0 | I54: =I$51*(1*FE_et_bio!H49) -> 0 | J54: =J$51*(1*FE_et_bio!I49) -> 0 | ... N54: =N$51*(1*FE_et_bio!M49) -> 0 | P54: dont e-GNV | Q54: =C54*11.63 -> 0 | R54: =D54*11.63 -> 0 | S54: =E54*11.63 -> 0 | T54: =F54*11.63 -> 0 | U54: =G54*11.63 -> 0 | V54: =H54*11.63 -> 0 | W54: =I54*11.63 -> 0 | X54: =J54*11.63 -> 0 | ... AB54: =N54*11.63 -> 0 | AD54: dont e-GNV | AE54: =C54*FE_et_bio!$B$20 -> 0 | AF54: =D54*FE_et_bio!$B$20 -> 0 | AG54: =E54*FE_et_bio!$B$20 -> 0 | AH54: =F54*FE_et_bio!$B$20 -> 0 | AI54: =G54*FE_et_bio!$B$20 -> 0 | AJ54: =H54*FE_et_bio!$B$20 -> 0 | AK54: =I54*FE_et_bio!$B$20 -> 0 | AL54: =J54*FE_et_bio!$B$20 -> 0 | ... AP54: =N54*FE_et_bio!$B$20 -> 0
B55: Electricité | C55: =C117+C125+C144 -> 0.77981625 | D55: =D117+D125+D144 -> 0.7787078 | E55: =E117+E125+E144 -> 0.65268276 | F55: =F117+F125+F144 -> 0.79456154 | G55: =G117+G125+G144 -> 0.93779349 | H55: =H117+H125+H144 -> 0.98565722 | I55: =I117+I125+I144 -> 1.1772053 | J55: =J117+J125+J144 -> 2.6268277 | ... N55: =N117+N125+N144 -> 10.956344 | P55: Electricité | Q55: =C55*11.63 -> 9.069263 | R55: =D55*11.63 -> 9.0563717 | S55: =E55*11.63 -> 7.5907005 | T55: =F55*11.63 -> 9.2407507 | U55: =G55*11.63 -> 10.906538 | V55: =H55*11.63 -> 11.463193 | W55: =I55*11.63 -> 13.690898 | X55: =J55*11.63 -> 30.550007 | ... AB55: =N55*11.63 -> 127.42228 | AD55: Electricité | AE55: =0 -> 0 | AF55: =0 -> 0 | AG55: =0 -> 0 | AH55: =0 -> 0 | AI55: =0 -> 0 | AJ55: =0 -> 0 | AK55: =0 -> 0 | AL55: =0 -> 0 | ... AP55: =0 -> 0
B56: H2 | C56: =C116+C126+C131+C137 -> 0 | D56: =D116+D126+D131+D137 -> 0 | E56: =E116+E126+E131+E137 -> 0 | F56: =F116+F126+F131+F137 -> 0 | G56: =G116+G126+G131+G137 -> 0 | H56: =H116+H126+H131+H137 -> 0 | I56: =I116+I126+I131+I137 -> 0.0048722932 | J56: =J116+J126+J131+J137 -> 0.0080975193 | ... N56: =N116+N126+N131+N137 -> 0.24442936 | P56: H2 | Q56: =Q116+Q126+Q131+Q137 -> 0 | R56: =R116+R126+R131+R137 -> 0 | S56: =S116+S126+S131+S137 -> 0 | T56: =T116+T126+T131+T137 -> 0 | U56: =U116+U126+U131+U137 -> 0 | V56: =V116+V126+V131+V137 -> 0 | W56: =W116+W126+W131+W137 -> 0.05666477 | X56: =X116+X126+X131+X137 -> 0.094174149 | ... AB56: =AB116+AB126+AB131+AB137 -> 2.8427134 | AD56: H2 | AE56: =AE116+AE126 -> 0 | AF56: =AF116+AF126 -> 0 | AG56: =AG116+AG126 -> 0 | AH56: =AH116+AH126 -> 0 | AI56: =AI116+AI126 -> 0 | AJ56: =AJ116+AJ126 -> 0 | AK56: =AK116+AK126 -> 0 | AL56: =AL116+AL126 -> 0 | ... AP56: =AP116+AP126 -> 0
B58: Total | C58: =C40+C43+C46+C50+C51+C55+C56 -> 46.369538 | D58: =D40+D43+D46+D50+D51+D55+D56 -> 46.913881 | E58: =E40+E43+E46+E50+E51+E55+E56 -> 38.76349 | F58: =F40+F43+F46+F50+F51+F55+F56 -> 42.205608 | G58: =G40+G43+G46+G50+G51+G55+G56 -> 45.077569 | H58: =H40+H43+H46+H50+H51+H55+H56 -> 43.920408 | I58: =I40+I43+I46+I50+I51+I55+I56 -> 42.265318 | J58: =J40+J43+J46+J50+J51+J55+J56 -> 35.181597 | ... N58: =N40+N43+N46+N50+N51+N55+N56 -> 13.713873 | P58: Total | Q58: =Q40+Q43+Q46+Q50+Q51+Q55+Q56 -> 539.27772 | R58: =R40+R43+R46+R50+R51+R55+R56 -> 545.60844 | S58: =S40+S43+S46+S50+S51+S55+S56 -> 450.81939 | T58: =T40+T43+T46+T50+T51+T55+T56 -> 490.85122 | U58: =U40+U43+U46+U50+U51+U55+U56 -> 524.25213 | V58: =V40+V43+V46+V50+V51+V55+V56 -> 510.79434 | W58: =W40+W43+W46+W50+W51+W55+W56 -> 491.54565 | X58: =X40+X43+X46+X50+X51+X55+X56 -> 409.16197 | ... AB58: =AB40+AB43+AB46+AB50+AB51+AB55+AB56 -> 159.49234 | AD58: Total | AE58: =AE40+AE43+AE46+AE50+AE51+AE55+AE56 -> 133.04508 | AF58: =AF40+AF43+AF46+AF50+AF51+AF55+AF56 -> 133.64444 | AG58: =AG40+AG43+AG46+AG50+AG51+AG55+AG56 -> 110.50199 | AH58: =AH40+AH43+AH46+AH50+AH51+AH55+AH56 -> 120.28376 | AI58: =AI40+AI43+AI46+AI50+AI51+AI55+AI56 -> 127.87804 | AJ58: =AJ40+AJ43+AJ46+AJ50+AJ51+AJ55+AJ56 -> 123.62371 | AK58: =AK40+AK43+AK46+AK50+AK51+AK55+AK56 -> 116.09844 | AL58: =AL40+AL43+AL46+AL50+AL51+AL55+AL56 -> 87.484923 | ... AP58: =AP40+AP43+AP46+AP50+AP51+AP55+AP56 -> 1.6502231
B59: Réduction / 2018 | C59: =C58/$C58-1 -> 0 | D59: =D58/$C58-1 -> 0.011739247 | E59: =E58/$C58-1 -> -0.16403113 | F59: =F58/$C58-1 -> -0.089798815 | G59: =G58/$C58-1 -> -0.027862445 | H59: =H58/$C58-1 -> -0.05281765 | I59: =I58/$C58-1 -> -0.088511122 | J59: =J58/$C58-1 -> -0.24127782 | ... N59: =N58/$C58-1 -> -0.70424823 | P59: Réduction / 2018 | AD59: Réduction / 2018 | AE59: =AE58/$AE58-1 -> 0 | AF59: =AF58/$AE58-1 -> 0.0045049715 | AG59: =AG58/$AE58-1 -> -0.1694395 | AH59: =AH58/$AE58-1 -> -0.095917222 | AI59: =AI58/$AE58-1 -> -0.038836731 | AJ59: =AJ58/$AE58-1 -> -0.070813373 | AK59: =AK58/$AE58-1 -> -0.12737517 | AL59: =AL58/$AE58-1 -> -0.34244149 | ... AP59: =AP58/$AE58-1 -> -0.98759651
B60: Total hors élec et H2 | C60: =C40+C43+C46+C50+C51 -> 45.589722 | D60: =D40+D43+D46+D50+D51 -> 46.135173 | E60: =E40+E43+E46+E50+E51 -> 38.110807 | F60: =F40+F43+F46+F50+F51 -> 41.411047 | G60: =G40+G43+G46+G50+G51 -> 44.139776 | H60: =H40+H43+H46+H50+H51 -> 42.934751 | I60: =I40+I43+I46+I50+I51 -> 41.08324 | J60: =J40+J43+J46+J50+J51 -> 32.546672 | ... N60: =N40+N43+N46+N50+N51 -> 2.5130993 | P60: Total hors élec et H2 | Q60: =Q40+Q43+Q46+Q50+Q51 -> 530.20846 | R60: =R40+R43+R46+R50+R51 -> 536.55207 | S60: =S40+S43+S46+S50+S51 -> 443.22869 | T60: =T40+T43+T46+T50+T51 -> 481.61047 | U60: =U40+U43+U46+U50+U51 -> 513.34559 | V60: =V40+V43+V46+V50+V51 -> 499.33115 | W60: =W40+W43+W46+W50+W51 -> 477.79809 | X60: =X40+X43+X46+X50+X51 -> 378.51779 | ... AB60: =AB40+AB43+AB46+AB50+AB51 -> 29.227345 | AD60: Total hors élec et H2 | AE60: =AE40+AE43+AE46+AE50+AE51 -> 133.04508 | AF60: =AF40+AF43+AF46+AF50+AF51 -> 133.64444 | AG60: =AG40+AG43+AG46+AG50+AG51 -> 110.50199 | AH60: =AH40+AH43+AH46+AH50+AH51 -> 120.28376 | AI60: =AI40+AI43+AI46+AI50+AI51 -> 127.87804 | AJ60: =AJ40+AJ43+AJ46+AJ50+AJ51 -> 123.62371 | AK60: =AK40+AK43+AK46+AK50+AK51 -> 116.09844 | AL60: =AL40+AL43+AL46+AL50+AL51 -> 87.484923 | ... AP60: =AP40+AP43+AP46+AP50+AP51 -> 1.6502231
B61: Réduction / 2018 | C61: =C60/$C60-1 -> 0 | D61: =D60/$C60-1 -> 0.011964362 | E61: =E60/$C60-1 -> -0.16404825 | F61: =F60/$C60-1 -> -0.091658266 | G61: =G60/$C60-1 -> -0.031804229 | H61: =H60/$C60-1 -> -0.058236175 | I61: =I60/$C60-1 -> -0.098848622 | J61: =J60/$C60-1 -> -0.28609628 | ... N61: =N60/$C60-1 -> -0.94487575 | P61: Réduction / 2018 | AD61: Réduction / 2020 | AE61: =AE60/$AE60-1 -> 0 | AF61: =AF60/$AE60-1 -> 0.0045049715 | AG61: =AG60/$AE60-1 -> -0.1694395 | AH61: =AH60/$AE60-1 -> -0.095917222 | AI61: =AI60/$AE60-1 -> -0.038836731 | AJ61: =AJ60/$AE60-1 -> -0.070813373 | AK61: =AK60/$AE60-1 -> -0.12737517 | AL61: =AL60/$AE60-1 -> -0.34244149 | ... AP61: =AP60/$AE60-1 -> -0.98759651
B63: 4.3 Demande d'énergie finale par infrastructure | P63: 4.3 Demande d'énergie finale par infrastructure
B64: Mtep | C64: 2018 | D64: 2019 | E64: 2020 | F64: 2021 | G64: 2022 | H64: 2023 | I64: 2025 | J64: 2030 | K64: 2035 | L64: 2040 | M64: 2045 | N64: 2050 | P64: TWh | Q64: 2018 | R64: 2019 | S64: 2020 | T64: 2021 | U64: 2022 | V64: 2023 | W64: 2025 | X64: 2030 | Y64: 2035 | Z64: 2040 | AA64: 2045 | AB64: 2050 | AD64: Mt CO2eq | AE64: 2018 | AF64: 2019 | AG64: 2020 | AH64: 2021 | AI64: 2022 | AJ64: 2023 | AK64: 2025 | AL64: 2030 | AM64: 2035 | AN64: 2040 | AO64: 2045 | AP64: 2050
B65: Routier | C65: =C111 -> 43.439204 | D65: =D111 -> 43.954337 | E65: =E111 -> 36.602589 | F65: =F111 -> 39.712257 | G65: =G111 -> 42.254475 | H65: =H111 -> 41.223941 | I65: =I111 -> 39.587128 | J65: =J111 -> 32.477097 | ... N65: =N111 -> 11.417643 | P65: Routier | Q65: =C65*11.63 -> 505.19794 | R65: =D65*11.63 -> 511.18894 | S65: =E65*11.63 -> 425.68811 | T65: =F65*11.63 -> 461.85355 | U65: =G65*11.63 -> 491.41954 | V65: =H65*11.63 -> 479.43444 | W65: =I65*11.63 -> 460.39829 | X65: =J65*11.63 -> 377.70864 | ... AB65: =N65*11.63 -> 132.78719 | AD65: Routier | AE65: =AE111 -> 126.50474 | AF65: =AF111 -> 126.99217 | AG65: =AG111 -> 105.85614 | AH65: =AH111 -> 114.88253 | AI65: =AI111 -> 121.68735 | AJ65: =AJ111 -> 117.69249 | AK65: =AK111 -> 110.30568 | AL65: =AL111 -> 81.965732 | ... AP65: =AP111 -> 0
B66: Ferroviaire | C66: =C123 -> 0.86592862 | D66: =D123 -> 0.85343014 | E66: =E123 -> 0.69986012 | F66: =F123 -> 0.79281313 | G66: =G123 -> 0.85645714 | H66: =H123 -> 0.80011439 | I66: =I123 -> 0.79966615 | J66: =J123 -> 0.84871882 | ... N66: =N123 -> 0.99077696 | P66: Ferroviaire | Q66: =C66*11.63 -> 10.07075 | R66: =D66*11.63 -> 9.9253925 | S66: =E66*11.63 -> 8.1393732 | T66: =F66*11.63 -> 9.2204167 | U66: =G66*11.63 -> 9.9605965 | V66: =H66*11.63 -> 9.3053303 | W66: =I66*11.63 -> 9.3001173 | X66: =J66*11.63 -> 9.8705999 | ... AB66: =N66*11.63 -> 11.522736 | AD66: Ferroviaire | AE66: =AE123 -> 0.36693278 | AF66: =AF123 -> 0.36527108 | AG66: =AG123 -> 0.30451963 | AH66: =AH123 -> 0.35032659 | AI66: =AI123 -> 0.35916049 | AJ66: =AJ123 -> 0.3357402 | AK66: =AK123 -> 0.31585376 | AL66: =AL123 -> 0.31880939 | ... AP66: =AP123 -> 0
B67: Fluvial et plaisance | C67: =C140 -> 0.44770327 | D67: =D140 -> 0.45592293 | E67: =E140 -> 0.44473589 | F67: =F140 -> 0.44781621 | G67: =G140 -> 0.44036145 | H67: =H140 -> 0.43274726 | I67: =I140 -> 0.42107067 | J67: =J140 -> 0.43538117 | ... N67: =N140 -> 0.40084862 | P67: Fluvial et plaisance | Q67: =C67*11.63 -> 5.206789 | R67: =D67*11.63 -> 5.3023837 | S67: =E67*11.63 -> 5.1722784 | T67: =F67*11.63 -> 5.2081025 | U67: =G67*11.63 -> 5.1214036 | V67: =H67*11.63 -> 5.0328507 | W67: =I67*11.63 -> 4.8970519 | X67: =J67*11.63 -> 5.063483 | ... AB67: =N67*11.63 -> 4.6618694 | AD67: Fluvial et plaisance | AE67: =AE140 -> 1.2791765 | AF67: =AF140 -> 1.2913971 | AG67: =AG140 -> 1.2646794 | AH67: =AH140 -> 1.2737221 | AI67: =AI140 -> 1.2480203 | AJ67: =AJ140 -> 1.2178922 | AK67: =AK140 -> 1.1530129 | AL67: =AL140 -> 1.1403581 | ... AP67: =AP140 -> 0
B68: Aérien domestique | C68: =C128+C134 -> 1.6167023 | D68: =D128+D134 -> 1.6501915 | E68: =E128+E134 -> 1.0163051 | F68: =F128+F134 -> 1.2527221 | G68: =G128+G134 -> 1.5262755 | H68: =H128+H134 -> 1.4636046 | I68: =I128+I134 -> 1.4574536 | J68: =J128+J134 -> 1.4204002 | ... N68: =N128+N134 -> 0.90460403 | P68: Aérien domestique | Q68: =Q128+Q134 -> 18.802248 | R68: =R128+R134 -> 19.191728 | S68: =S128+S134 -> 11.819628 | T68: =T128+T134 -> 14.569159 | U68: =U128+U134 -> 17.750584 | V68: =V128+V134 -> 17.021721 | W68: =W128+W134 -> 16.950185 | X68: =X128+X134 -> 16.519254 | ... AB68: =AB128+AB134 -> 10.520545 | AD68: Aérien domestique | AE68: =AE128+AE134 -> 4.8942251 | AF68: =AF128+AF134 -> 4.9956067 | AG68: =AG128+AG134 -> 3.0766492 | AH68: =AH128+AH134 -> 3.7771826 | AI68: =AI128+AI134 -> 4.5835133 | AJ68: =AJ128+AJ134 -> 4.377585 | AK68: =AK128+AK134 -> 4.3238905 | AL68: =AL128+AL134 -> 4.0600239 | ... AP68: =AP128+AP134 -> 1.6502231
B70: Total | C70: =SUM(C65:C68) -> 46.369538 | D70: =SUM(D65:D68) -> 46.913881 | E70: =SUM(E65:E68) -> 38.76349 | F70: =SUM(F65:F68) -> 42.205608 | G70: =SUM(G65:G68) -> 45.077569 | H70: =SUM(H65:H68) -> 43.920408 | I70: =SUM(I65:I68) -> 42.265318 | J70: =SUM(J65:J68) -> 35.181597 | ... N70: =SUM(N65:N68) -> 13.713873 | P70: Total | Q70: =SUM(Q65:Q68) -> 539.27772 | R70: =SUM(R65:R68) -> 545.60844 | S70: =SUM(S65:S68) -> 450.81939 | T70: =SUM(T65:T68) -> 490.85122 | U70: =SUM(U65:U68) -> 524.25213 | V70: =SUM(V65:V68) -> 510.79434 | W70: =SUM(W65:W68) -> 491.54565 | X70: =SUM(X65:X68) -> 409.16197 | ... AB70: =SUM(AB65:AB68) -> 159.49234 | AD70: Total | AE70: =SUM(AE65:AE68) -> 133.04508 | AF70: =SUM(AF65:AF68) -> 133.64444 | AG70: =SUM(AG65:AG68) -> 110.50199 | AH70: =SUM(AH65:AH68) -> 120.28376 | AI70: =SUM(AI65:AI68) -> 127.87804 | AJ70: =SUM(AJ65:AJ68) -> 123.62371 | AK70: =SUM(AK65:AK68) -> 116.09844 | AL70: =SUM(AL65:AL68) -> 87.484923 | ... AP70: =SUM(AP65:AP68) -> 1.6502231
B71: Réduction / 2018 | C71: =C70/$C70-1 -> 0 | D71: =D70/$C70-1 -> 0.011739247 | E71: =E70/$C70-1 -> -0.16403113 | F71: =F70/$C70-1 -> -0.089798815 | G71: =G70/$C70-1 -> -0.027862445 | H71: =H70/$C70-1 -> -0.05281765 | I71: =I70/$C70-1 -> -0.088511122 | J71: =J70/$C70-1 -> -0.24127782 | ... N71: =N70/$C70-1 -> -0.70424823 | P71: Réduction / 2018 | AD71: Réduction / 2018 | AE71: =AE70/$C70-1 -> 1.8692345 | AF71: =AF70/$C70-1 -> 1.8821603 | AG71: =AG70/$C70-1 -> 1.3830729 | AH71: =AH70/$C70-1 -> 1.5940255 | AI71: =AI70/$C70-1 -> 1.7578028 | AJ71: =AJ70/$C70-1 -> 1.6660543 | AK71: =AK70/$C70-1 -> 1.5037653 | AL71: =AL70/$C70-1 -> 0.88668957 | ... AP71: =AP70/$C70-1 -> -0.96441148
AF72: =(AF76*7.9%+7.3%*AF77)/(20.6+50.7) -> 0.078797919 | AG72: =(AG76*8.7%+12.1%*AG77)/(29+16.6) -> 0.14429358 | AH72: =(AH76*8.7%+12.1%*AH77)/(29+16.6) -> 0.15483326 | AI72: =(AI76*8.7%+12.1%*AI77)/(29+16.6) -> 0.16919016 | AJ72: =(AJ76*8.7%+12.1%*AJ77)/(29+16.6) -> 0.16210184 | AK72: =(AK76*8.7%+12.1%*AK77)/(29+16.6) -> 0.14761783 | AL72: =(AL76*8.7%+12.1%*AL77)/(29+16.6) -> 0.10302156
B73: 4.4 Transports routiers | P73: 4.4 Transports routiers | AD73: 4.4 Transports routiers
B74: Mtep | C74: 2018 | D74: 2019 | E74: 2020 | F74: 2021 | G74: 2022 | H74: 2023 | I74: 2025 | J74: 2030 | K74: 2035 | L74: 2040 | M74: 2045 | N74: 2050 | P74: TWh | Q74: 2018 | R74: 2019 | S74: 2020 | T74: 2021 | U74: 2022 | V74: 2023 | W74: 2025 | X74: 2030 | Y74: 2035 | Z74: 2040 | AA74: 2045 | AB74: 2050 | AD74: Mt CO2eq | AE74: 2018 | AF74: 2019 | AG74: 2020 | AH74: 2021 | AI74: 2022 | AJ74: 2023 | AK74: 2025 | AL74: 2030 | AM74: 2035 | AN74: 2040 | AO74: 2045 | AP74: 2050
B75: Voitures particulières | C75: =SUM(C76:C81) -> 25.724778 | D75: =SUM(D76:D81) -> 26.111329 | E75: =SUM(E76:E81) -> 20.682151 | F75: =SUM(F76:F81) -> 22.347284 | G75: =SUM(G76:G81) -> 24.660604 | H75: =SUM(H76:H81) -> 24.060911 | I75: =SUM(I76:I81) -> 22.85167 | J75: =SUM(J76:J81) -> 19.06125 | ... N75: =SUM(N76:N81) -> 5.9249892 | P75: Voitures particulières | Q75: =C75*11.63 -> 299.17917 | R75: =D75*11.63 -> 303.67476 | S75: =E75*11.63 -> 240.53342 | T75: =F75*11.63 -> 259.89891 | U75: =G75*11.63 -> 286.80282 | V75: =H75*11.63 -> 279.8284 | W75: =I75*11.63 -> 265.76492 | X75: =J75*11.63 -> 221.68234 | ... AB75: =N75*11.63 -> 68.907624 | AD75: Voitures particulières | AE75: =SUM(AE76:AE81) -> 74.69577 | AF75: =SUM(AF76:AF81) -> 75.187827 | AG75: =SUM(AG76:AG81) -> 59.597036 | AH75: =SUM(AH76:AH81) -> 64.352049 | AI75: =SUM(AI76:AI81) -> 70.631912 | AJ75: =SUM(AJ76:AJ81) -> 68.191593 | AK75: =SUM(AK76:AK81) -> 63.005808 | AL75: =SUM(AL76:AL81) -> 47.599784 | ... AP75: =SUM(AP76:AP81) -> 0
B76: Essence (yc carb. subst.) | C76: =VP!C183 -> 7.1717285 | D76: =VP!D183 -> 7.6772015 | E76: =VP!E183 -> 6.5658491 | F76: =VP!F183 -> 7.5559749 | G76: =VP!G183 -> 8.6800985 | H76: =VP!H183 -> 9.0320075 | I76: =VP!I183 -> 9.5689228 | J76: =VP!J183 -> 11.808338 | ... N76: =VP!N183 -> 0.014736221 | P76: Essence (yc carb. subst.) | Q76: =C76*11.63 -> 83.407202 | R76: =D76*11.63 -> 89.285853 | S76: =E76*11.63 -> 76.360826 | T76: =F76*11.63 -> 87.875988 | U76: =G76*11.63 -> 100.94955 | V76: =H76*11.63 -> 105.04225 | W76: =I76*11.63 -> 111.28657 | X76: =J76*11.63 -> 137.33097 | ... AB76: =N76*11.63 -> 0.17138225 | AD76: Essence (yc carb. subst.) | AE76: =C76*C$9 -> 20.373419 | AF76: =D76*D$9 -> 21.596703 | AG76: =E76*E$9 -> 18.572187 | AH76: =F76*F$9 -> 21.358856 | AI76: =G76*G$9 -> 24.452649 | AJ76: =H76*H$9 -> 25.274669 | AK76: =I76*I$9 -> 26.244991 | AL76: =J76*J$9 -> 31.229131 | ... AP76: =N76*N$9 -> 0
B77: Gazole (yc carb. subs) | C77: =VP!C184 -> 18.527061 | D77: =VP!D184 -> 18.398474 | E77: =VP!E184 -> 14.07355 | F77: =VP!F184 -> 14.702207 | G77: =VP!G184 -> 15.818051 | H77: =VP!H184 -> 14.778928 | I77: =VP!I184 -> 12.873836 | J77: =VP!J184 -> 6.0187482 | ... N77: =VP!N184 -> 3.9158724e-17 | P77: Gazole (yc carb. subs) | Q77: =C77*11.63 -> 215.46972 | R77: =D77*11.63 -> 213.97425 | S77: =E77*11.63 -> 163.67539 | T77: =F77*11.63 -> 170.98667 | U77: =G77*11.63 -> 183.96393 | V77: =H77*11.63 -> 171.87894 | W77: =I77*11.63 -> 149.72271 | X77: =J77*11.63 -> 69.998042 | ... AB77: =N77*11.63 -> 4.5541596e-16 | AD77: Gazole (yc carb. subs) | AE77: =C77*C$10 -> 54.322351 | AF77: =D77*D$10 -> 53.591125 | AG77: =E77*E$10 -> 41.024849 | AH77: =F77*F$10 -> 42.993193 | AI77: =G77*G$10 -> 46.179263 | AJ77: =H77*H$10 -> 42.916925 | AK77: =I77*I$10 -> 36.760818 | AL77: =J77*J$10 -> 16.370652 | ... AP77: =N77*N$10 -> 0
B78: GPL | C78: =0 -> 0 | D78: =0 -> 0 | E78: =0 -> 0 | F78: =0 -> 0 | G78: =0 -> 0 | H78: =0 -> 0 | I78: =0 -> 0 | J78: =0 -> 0 | ... N78: =0 -> 0 | P78: GPL | Q78: =C78*11.63 -> 0 | R78: =D78*11.63 -> 0 | S78: =E78*11.63 -> 0 | T78: =F78*11.63 -> 0 | U78: =G78*11.63 -> 0 | V78: =H78*11.63 -> 0 | W78: =I78*11.63 -> 0 | X78: =J78*11.63 -> 0 | ... AB78: =N78*11.63 -> 0 | AD78: GPL | AE78: =C78*C$9 -> 0 | AF78: =D78*D$9 -> 0 | AG78: =E78*E$9 -> 0 | AH78: =F78*F$9 -> 0 | AI78: =G78*G$9 -> 0 | AJ78: =H78*H$9 -> 0 | AK78: =I78*I$9 -> 0 | AL78: =J78*J$9 -> 0 | ... AP78: =N78*N$9 -> 0
B79: GNV | C79: =0 -> 0 | D79: =0 -> 0 | E79: =0 -> 0 | F79: =0 -> 0 | G79: =0 -> 0 | H79: =0 -> 0 | I79: =0 -> 0 | J79: =0 -> 0 | ... N79: =0 -> 0 | P79: GNV | Q79: =C79*11.63 -> 0 | R79: =D79*11.63 -> 0 | S79: =E79*11.63 -> 0 | T79: =F79*11.63 -> 0 | U79: =G79*11.63 -> 0 | V79: =H79*11.63 -> 0 | W79: =I79*11.63 -> 0 | X79: =J79*11.63 -> 0 | ... AB79: =N79*11.63 -> 0 | AD79: GNV | AE79: =C79*C$11 -> 0 | AF79: =D79*D$11 -> 0 | AG79: =E79*E$11 -> 0 | AH79: =F79*F$11 -> 0 | AI79: =G79*G$11 -> 0 | AJ79: =H79*H$11 -> 0 | AK79: =I79*I$11 -> 0 | AL79: =J79*J$11 -> 0 | ... AP79: =N79*N$11 -> 0
B80: H2 | C80: =VP!C186 -> 0 | D80: =VP!D186 -> 0 | E80: =VP!E186 -> 0 | F80: =VP!F186 -> 0 | G80: =VP!G186 -> 0 | H80: =VP!H186 -> 0 | I80: =VP!I186 -> 0 | J80: =VP!J186 -> 0 | ... N80: =VP!N186 -> 0 | P80: H2 | Q80: =C80*11.63 -> 0 | R80: =D80*11.63 -> 0 | S80: =E80*11.63 -> 0 | T80: =F80*11.63 -> 0 | U80: =G80*11.63 -> 0 | V80: =H80*11.63 -> 0 | W80: =I80*11.63 -> 0 | X80: =J80*11.63 -> 0 | ... AB80: =N80*11.63 -> 0 | AD80: H2 | AE80: =C80*0 -> 0 | AF80: =D80*0 -> 0 | AG80: =E80*0 -> 0 | AH80: =F80*0 -> 0 | AI80: =G80*0 -> 0 | AJ80: =H80*0 -> 0 | AK80: =I80*0 -> 0 | AL80: =J80*0 -> 0 | ... AP80: =N80*0 -> 0
B81: Electricité | C81: =VP!C185 -> 0.025988669 | D81: =VP!D185 -> 0.035653802 | E81: =VP!E185 -> 0.042751913 | F81: =VP!F185 -> 0.08910182 | G81: =VP!G185 -> 0.16245443 | H81: =VP!H185 -> 0.24997558 | I81: =VP!I185 -> 0.40891106 | J81: =VP!J185 -> 1.2341642 | ... N81: =VP!N185 -> 5.910253 | P81: Electricité | Q81: =C81*11.63 -> 0.30224822 | R81: =D81*11.63 -> 0.41465372 | S81: =E81*11.63 -> 0.49720475 | T81: =F81*11.63 -> 1.0362542 | U81: =G81*11.63 -> 1.889345 | V81: =H81*11.63 -> 2.907216 | W81: =I81*11.63 -> 4.7556356 | X81: =J81*11.63 -> 14.35333 | ... AB81: =N81*11.63 -> 68.736242 | AD81: Electricité | AE81: =C81*0 -> 0 | AF81: =D81*0 -> 0 | AG81: =E81*0 -> 0 | AH81: =F81*0 -> 0 | AI81: =G81*0 -> 0 | AJ81: =H81*0 -> 0 | AK81: =I81*0 -> 0 | AL81: =J81*0 -> 0 | ... AP81: =N81*0 -> 0
B83: VUL | C83: =SUM(C84:C89) -> 5.8617288 | D83: =SUM(D84:D89) -> 5.9170924 | E83: =SUM(E84:E89) -> 5.1422961 | F83: =SUM(F84:F89) -> 5.7078693 | G83: =SUM(G84:G89) -> 5.8080336 | H83: =SUM(H84:H89) -> 5.7011768 | I83: =SUM(I84:I89) -> 5.5627541 | J83: =SUM(J84:J89) -> 4.9317986 | ... N83: =SUM(N84:N89) -> 1.6828361 | P83: VUL | Q83: =C83*11.63 -> 68.171906 | R83: =D83*11.63 -> 68.815784 | S83: =E83*11.63 -> 59.804903 | T83: =F83*11.63 -> 66.38252 | U83: =G83*11.63 -> 67.547431 | V83: =H83*11.63 -> 66.304687 | W83: =I83*11.63 -> 64.69483 | X83: =J83*11.63 -> 57.356817 | ... AB83: =N83*11.63 -> 19.571384 | AD83: VUL | AE83: =SUM(AE84:AE89) -> 17.157625 | AF83: =SUM(AF84:AF89) -> 17.20054 | AG83: =SUM(AG84:AG89) -> 14.954123 | AH83: =SUM(AH84:AH89) -> 16.645378 | AI83: =SUM(AI84:AI89) -> 16.900328 | AJ83: =SUM(AJ84:AJ89) -> 16.483689 | AK83: =SUM(AK84:AK89) -> 15.768974 | AL83: =SUM(AL84:AL89) -> 12.80551 | ... AP83: =SUM(AP84:AP89) -> 0
B84: Essence (yc carb. subst.) | C84: =0 -> 0 | D84: =0 -> 0 | E84: =0 -> 0 | F84: =0 -> 0 | G84: =0 -> 0 | H84: =0 -> 0 | I84: =0 -> 0 | J84: =0 -> 0 | ... N84: =0 -> 0 | P84: Essence (yc carb. subst.) | Q84: =C84*11.63 -> 0 | R84: =D84*11.63 -> 0 | S84: =E84*11.63 -> 0 | T84: =F84*11.63 -> 0 | U84: =G84*11.63 -> 0 | V84: =H84*11.63 -> 0 | W84: =I84*11.63 -> 0 | X84: =J84*11.63 -> 0 | ... AB84: =N84*11.63 -> 0 | AD84: Essence (yc carb. subst.) | AE84: =C84*C$9 -> 0 | AF84: =D84*D$9 -> 0 | AG84: =E84*E$9 -> 0 | AH84: =F84*F$9 -> 0 | AI84: =G84*G$9 -> 0 | AJ84: =H84*H$9 -> 0 | AK84: =I84*I$9 -> 0 | AL84: =J84*J$9 -> 0 | ... AP84: =N84*N$9 -> 0
B85: Gazole (yc carb. subs) | C85: =VUL!C127 -> 5.8517417 | D85: =VUL!D127 -> 5.9051508 | E85: =VUL!E127 -> 5.1300031 | F85: =VUL!F127 -> 5.6921522 | G85: =VUL!G127 -> 5.7889674 | H85: =VUL!H127 -> 5.6763446 | I85: =VUL!I127 -> 5.5137097 | J85: =VUL!J127 -> 4.6956528 | ... N85: =VUL!N127 -> 0 | P85: Gazole (yc carb. subs) | Q85: =C85*11.63 -> 68.055757 | R85: =D85*11.63 -> 68.676904 | S85: =E85*11.63 -> 59.661936 | T85: =F85*11.63 -> 66.199731 | U85: =G85*11.63 -> 67.325691 | V85: =H85*11.63 -> 66.015888 | W85: =I85*11.63 -> 64.124444 | X85: =J85*11.63 -> 54.610442 | ... AB85: =N85*11.63 -> 0 | AD85: Gazole (yc carb. subs) | AE85: =C85*C$10 -> 17.157625 | AF85: =D85*D$10 -> 17.20054 | AG85: =E85*E$10 -> 14.954123 | AH85: =F85*F$10 -> 16.645378 | AI85: =G85*G$10 -> 16.900328 | AJ85: =H85*H$10 -> 16.483689 | AK85: =I85*I$10 -> 15.744218 | AL85: =J85*J$10 -> 12.771908 | ... AP85: =N85*N$10 -> 0
B86: GPL | C86: =0 -> 0 | D86: =0 -> 0 | E86: =0 -> 0 | F86: =0 -> 0 | G86: =0 -> 0 | H86: =0 -> 0 | I86: =0 -> 0 | J86: =0 -> 0 | ... N86: =0 -> 0 | P86: GPL | Q86: =C86*11.63 -> 0 | R86: =D86*11.63 -> 0 | S86: =E86*11.63 -> 0 | T86: =F86*11.63 -> 0 | U86: =G86*11.63 -> 0 | V86: =H86*11.63 -> 0 | W86: =I86*11.63 -> 0 | X86: =J86*11.63 -> 0 | ... AB86: =N86*11.63 -> 0 | AD86: GPL | AE86: =C86*C$9 -> 0 | AF86: =D86*D$9 -> 0 | AG86: =E86*E$9 -> 0 | AH86: =F86*F$9 -> 0 | AI86: =G86*G$9 -> 0 | AJ86: =H86*H$9 -> 0 | AK86: =I86*I$9 -> 0 | AL86: =J86*J$9 -> 0 | ... AP86: =N86*N$9 -> 0
B87: GNV | C87: =VUL!C128 -> 0 | D87: =VUL!D128 -> 0 | E87: =VUL!E128 -> 0 | F87: =VUL!F128 -> 0 | G87: =VUL!G128 -> 0 | H87: =VUL!H128 -> 0 | I87: =VUL!I128 -> 0.011027636 | J87: =VUL!J128 -> 0.01672943 | ... N87: =VUL!N128 -> 0.00011103938 | P87: GNV | Q87: =C87*11.63 -> 0 | R87: =D87*11.63 -> 0 | S87: =E87*11.63 -> 0 | T87: =F87*11.63 -> 0 | U87: =G87*11.63 -> 0 | V87: =H87*11.63 -> 0 | W87: =I87*11.63 -> 0.12825141 | X87: =J87*11.63 -> 0.19456328 | ... AB87: =N87*11.63 -> 0.001291388 | AD87: GNV | AE87: =C87*C$11 -> 0 | AF87: =D87*D$11 -> 0 | AG87: =E87*E$11 -> 0 | AH87: =F87*F$11 -> 0 | AI87: =G87*G$11 -> 0 | AJ87: =H87*H$11 -> 0 | AK87: =I87*I$11 -> 0.024755703 | AL87: =J87*J$11 -> 0.033602323 | ... AP87: =N87*N$11 -> 0
B88: H2 | C88: =VUL!C130 -> 0 | D88: =VUL!D130 -> 0 | E88: =VUL!E130 -> 0 | F88: =VUL!F130 -> 0 | G88: =VUL!G130 -> 0 | H88: =VUL!H130 -> 0 | I88: =VUL!I130 -> 0 | J88: =VUL!J130 -> 0 | ... N88: =VUL!N130 -> 0 | P88: H2 | Q88: =C88*11.63 -> 0 | R88: =D88*11.63 -> 0 | S88: =E88*11.63 -> 0 | T88: =F88*11.63 -> 0 | U88: =G88*11.63 -> 0 | V88: =H88*11.63 -> 0 | W88: =I88*11.63 -> 0 | X88: =J88*11.63 -> 0 | ... AB88: =N88*11.63 -> 0 | AD88: H2 | AE88: =C88*0 -> 0 | AF88: =D88*0 -> 0 | AG88: =E88*0 -> 0 | AH88: =F88*0 -> 0 | AI88: =G88*0 -> 0 | AJ88: =H88*0 -> 0 | AK88: =I88*0 -> 0 | AL88: =J88*0 -> 0 | ... AP88: =N88*0 -> 0
B89: Electricité | C89: =VUL!C129 -> 0.0099870179 | D89: =VUL!D129 -> 0.011941561 | E89: =VUL!E129 -> 0.012292928 | F89: =VUL!F129 -> 0.015717099 | G89: =VUL!G129 -> 0.019066166 | H89: =VUL!H129 -> 0.024832259 | I89: =VUL!I129 -> 0.038016774 | J89: =VUL!J129 -> 0.21941632 | ... N89: =VUL!N129 -> 1.6827251 | P89: Electricité | Q89: =C89*11.63 -> 0.11614902 | R89: =D89*11.63 -> 0.13888036 | S89: =E89*11.63 -> 0.14296675 | T89: =F89*11.63 -> 0.18278986 | U89: =G89*11.63 -> 0.22173951 | V89: =H89*11.63 -> 0.28879917 | W89: =I89*11.63 -> 0.44213508 | X89: =J89*11.63 -> 2.5518119 | ... AB89: =N89*11.63 -> 19.570092 | AD89: Electricité | AE89: =C89*0 -> 0 | AF89: =D89*0 -> 0 | AG89: =E89*0 -> 0 | AH89: =F89*0 -> 0 | AI89: =G89*0 -> 0 | AJ89: =H89*0 -> 0 | AK89: =I89*0 -> 0 | AL89: =J89*0 -> 0 | ... AP89: =N89*0 -> 0
B91: Poids lourds | C91: =SUM(C92:C97) -> 10.672696 | D91: =SUM(D92:D97) -> 10.73186 | E91: =SUM(E92:E97) -> 9.8629807 | F91: =SUM(F92:F97) -> 10.593258 | G91: =SUM(G92:G97) -> 10.670923 | H91: =SUM(H92:H97) -> 10.314554 | I91: =SUM(I92:I97) -> 10.051301 | J91: =SUM(J92:J97) -> 7.4726261 | ... N91: =SUM(N92:N97) -> 3.2938313 | P91: Poids lourds | Q91: =C91*11.63 -> 124.12345 | R91: =D91*11.63 -> 124.81153 | S91: =E91*11.63 -> 114.70647 | T91: =F91*11.63 -> 123.19959 | U91: =G91*11.63 -> 124.10283 | V91: =H91*11.63 -> 119.95827 | W91: =I91*11.63 -> 116.89664 | X91: =J91*11.63 -> 86.906641 | ... AB91: =N91*11.63 -> 38.307258 | AD91: Poids lourds | AE91: =SUM(AE92:AE97) -> 31.25713 | AF91: =SUM(AF92:AF97) -> 31.199484 | AG91: =SUM(AG92:AG97) -> 28.687407 | AH91: =SUM(AH92:AH97) -> 30.86727 | AI91: =SUM(AI92:AI97) -> 31.021156 | AJ91: =SUM(AJ92:AJ97) -> 29.822558 | AK91: =SUM(AK92:AK97) -> 28.505453 | AL91: =SUM(AL92:AL97) -> 19.165726 | ... AP91: =SUM(AP92:AP97) -> 0
B92: Essence (yc carb. subst.) | C92: =0 -> 0 | D92: =0 -> 0 | E92: =0 -> 0 | F92: =0 -> 0 | G92: =0 -> 0 | H92: =0 -> 0 | I92: =0 -> 0 | J92: =0 -> 0 | ... N92: =0 -> 0 | P92: Essence (yc carb. subst.) | Q92: =C92*11.63 -> 0 | R92: =D92*11.63 -> 0 | S92: =E92*11.63 -> 0 | T92: =F92*11.63 -> 0 | U92: =G92*11.63 -> 0 | V92: =H92*11.63 -> 0 | W92: =I92*11.63 -> 0 | X92: =J92*11.63 -> 0 | ... AB92: =N92*11.63 -> 0 | AD92: Essence (yc carb. subst.) | AE92: =C92*C$9 -> 0 | AF92: =D92*D$9 -> 0 | AG92: =E92*E$9 -> 0 | AH92: =F92*F$9 -> 0 | AI92: =G92*G$9 -> 0 | AJ92: =H92*H$9 -> 0 | AK92: =I92*I$9 -> 0 | AL92: =J92*J$9 -> 0 | ... AP92: =N92*N$9 -> 0
B93: Gazole (yc carb. subs) | C93: =PL!C195 -> 10.61005 | D93: =PL!D195 -> 10.648726 | E93: =PL!E195 -> 9.7484406 | F93: =PL!F195 -> 10.424463 | G93: =PL!G195 -> 10.462474 | H93: =PL!H195 -> 10.117427 | I93: =PL!I195 -> 9.7800599 | J93: =PL!J195 -> 6.8361944 | ... N93: =PL!N195 -> 1.1075788 | P93: Gazole (yc carb. subs) | Q93: =C93*11.63 -> 123.39488 | R93: =D93*11.63 -> 123.84468 | S93: =E93*11.63 -> 113.37436 | T93: =F93*11.63 -> 121.2365 | U93: =G93*11.63 -> 121.67858 | V93: =H93*11.63 -> 117.66568 | W93: =I93*11.63 -> 113.7421 | X93: =J93*11.63 -> 79.50494 | ... AB93: =N93*11.63 -> 12.881141 | AD93: Gazole (yc carb. subs) | AE93: =C93*C$10 -> 31.109245 | AF93: =D93*D$10 -> 31.017637 | AG93: =E93*E$10 -> 28.417016 | AH93: =F93*F$10 -> 30.483922 | AI93: =G93*G$10 -> 30.544178 | AJ93: =H93*H$10 -> 29.380266 | AK93: =I93*I$10 -> 27.926642 | AL93: =J93*J$10 -> 18.594059 | ... AP93: =N93*N$10 -> 0
B94: GPL | C94: =0 -> 0 | D94: =0 -> 0 | E94: =0 -> 0 | F94: =0 -> 0 | G94: =0 -> 0 | H94: =0 -> 0 | I94: =0 -> 0 | J94: =0 -> 0 | ... N94: =0 -> 0 | P94: GPL | Q94: =C94*11.63 -> 0 | R94: =D94*11.63 -> 0 | S94: =E94*11.63 -> 0 | T94: =F94*11.63 -> 0 | U94: =G94*11.63 -> 0 | V94: =H94*11.63 -> 0 | W94: =I94*11.63 -> 0 | X94: =J94*11.63 -> 0 | ... AB94: =N94*11.63 -> 0 | AD94: GPL | AE94: =C94*C$9 -> 0 | AF94: =D94*D$9 -> 0 | AG94: =E94*E$9 -> 0 | AH94: =F94*F$9 -> 0 | AI94: =G94*G$9 -> 0 | AJ94: =H94*H$9 -> 0 | AK94: =I94*I$9 -> 0 | AL94: =J94*J$9 -> 0 | ... AP94: =N94*N$9 -> 0
B95: GNV | C95: =PL!C196 -> 0.062645582 | D95: =PL!D196 -> 0.083134476 | E95: =PL!E196 -> 0.11454011 | F95: =PL!F196 -> 0.16222746 | G95: =PL!G196 -> 0.20185004 | H95: =PL!H196 -> 0.18906188 | I95: =PL!I196 -> 0.25783621 | J95: =PL!J196 -> 0.28461344 | ... N95: =PL!N196 -> 0.004486742 | P95: GNV | Q95: =C95*11.63 -> 0.72856812 | R95: =D95*11.63 -> 0.96685396 | S95: =E95*11.63 -> 1.3321015 | T95: =F95*11.63 -> 1.8867053 | U95: =G95*11.63 -> 2.347516 | V95: =H95*11.63 -> 2.1987897 | W95: =I95*11.63 -> 2.9986352 | X95: =J95*11.63 -> 3.3100543 | ... AB95: =N95*11.63 -> 0.05218081 | AD95: GNV | AE95: =C95*C$11 -> 0.14788535 | AF95: =D95*D$11 -> 0.18184653 | AG95: =E95*E$11 -> 0.27039104 | AH95: =F95*F$11 -> 0.38334834 | AI95: =G95*G$11 -> 0.47697769 | AJ95: =H95*H$11 -> 0.4422913 | AK95: =I95*I$11 -> 0.57881095 | AL95: =J95*J$11 -> 0.57166756 | ... AP95: =N95*N$11 -> 0
B96: H2 | C96: =PL!C198 -> 0 | D96: =PL!D198 -> 0 | E96: =PL!E198 -> 0 | F96: =PL!F198 -> 0 | G96: =PL!G198 -> 0 | H96: =PL!H198 -> 0 | I96: =PL!I198 -> 0.0041661213 | J96: =PL!J198 -> 0.006916372 | ... N96: =PL!N198 -> 0.15472536 | P96: H2 | Q96: =C96*11.63 -> 0 | R96: =D96*11.63 -> 0 | S96: =E96*11.63 -> 0 | T96: =F96*11.63 -> 0 | U96: =G96*11.63 -> 0 | V96: =H96*11.63 -> 0 | W96: =I96*11.63 -> 0.048451991 | X96: =J96*11.63 -> 0.080437407 | ... AB96: =N96*11.63 -> 1.7994559 | AD96: H2 | AE96: =C96*0 -> 0 | AF96: =D96*0 -> 0 | AG96: =E96*0 -> 0 | AH96: =F96*0 -> 0 | AI96: =G96*0 -> 0 | AJ96: =H96*0 -> 0 | AK96: =I96*0 -> 0 | AL96: =J96*0 -> 0 | ... AP96: =N96*0 -> 0
B97: Electricité | C97: =PL!C197 -> 0 | D97: =PL!D197 -> 0 | E97: =PL!E197 -> 0 | F97: =PL!F197 -> 0.0065682622 | G97: =PL!G197 -> 0.0065981661 | H97: =PL!H197 -> 0.0080655451 | I97: =PL!I197 -> 0.0092392329 | J97: =PL!J197 -> 0.34490189 | ... N97: =PL!N197 -> 2.0270404 | P97: Electricité | Q97: =C97*11.63 -> 0 | R97: =D97*11.63 -> 0 | S97: =E97*11.63 -> 0 | T97: =F97*11.63 -> 0.076388889 | U97: =G97*11.63 -> 0.076736672 | V97: =H97*11.63 -> 0.09380229 | W97: =I97*11.63 -> 0.10745228 | X97: =J97*11.63 -> 4.011209 | ... AB97: =N97*11.63 -> 23.57448 | AD97: Electricité | AE97: =C97*0 -> 0 | AF97: =D97*0 -> 0 | AG97: =E97*0 -> 0 | AH97: =F97*0 -> 0 | AI97: =G97*0 -> 0 | AJ97: =H97*0 -> 0 | AK97: =I97*0 -> 0 | AL97: =J97*0 -> 0 | ... AP97: =N97*0 -> 0
B99: Bus et autocars | C99: =SUM(C100:C105) -> 0.74089836 | D99: =SUM(D100:D105) -> 0.75503928 | E99: =SUM(E100:E105) -> 0.54419267 | F99: =SUM(F100:F105) -> 0.63384549 | G99: =SUM(G100:G105) -> 0.69506149 | H99: =SUM(H100:H105) -> 0.72744523 | I99: =SUM(I100:I105) -> 0.7383282 | J99: =SUM(J100:J105) -> 0.70143621 | ... N99: =SUM(N100:N105) -> 0.37621935 | P99: Bus et autocars | Q99: =C99*11.63 -> 8.616648 | R99: =D99*11.63 -> 8.7811069 | S99: =E99*11.63 -> 6.3289607 | T99: =F99*11.63 -> 7.371623 | U99: =G99*11.63 -> 8.0835651 | V99: =H99*11.63 -> 8.460188 | W99: =I99*11.63 -> 8.586757 | X99: =J99*11.63 -> 8.1577031 | ... AB99: =N99*11.63 -> 4.3754311 | AD99: Bus et autocars | AE99: =SUM(AE100:AE105) -> 2.1468175 | AF99: =SUM(AF100:AF105) -> 2.1693222 | AG99: =SUM(AG100:AG105) -> 1.5682483 | AH99: =SUM(AH100:AH105) -> 1.8212797 | AI99: =SUM(AI100:AI105) -> 1.9820443 | AJ99: =SUM(AJ100:AJ105) -> 2.0504089 | AK99: =SUM(AK100:AK105) -> 2.0144842 | AL99: =SUM(AL100:AL105) -> 1.6827184 | ... AP99: =SUM(AP100:AP105) -> 0
B100: Essence (yc carb. subst.) | C100: =0 -> 0 | D100: =0 -> 0 | E100: =0 -> 0 | F100: =0 -> 0 | G100: =0 -> 0 | H100: =0 -> 0 | I100: =0 -> 0 | J100: =0 -> 0 | ... N100: =0 -> 0 | P100: Essence (yc carb. subst.) | Q100: =C100*11.63 -> 0 | R100: =D100*11.63 -> 0 | S100: =E100*11.63 -> 0 | T100: =F100*11.63 -> 0 | U100: =G100*11.63 -> 0 | V100: =H100*11.63 -> 0 | W100: =I100*11.63 -> 0 | X100: =J100*11.63 -> 0 | ... AB100: =N100*11.63 -> 0 | AD100: Essence (yc carb. subst.) | AE100: =C100*C$9 -> 0 | AF100: =D100*D$9 -> 0 | AG100: =E100*E$9 -> 0 | AH100: =F100*F$9 -> 0 | AI100: =G100*G$9 -> 0 | AJ100: =H100*H$9 -> 0 | AK100: =I100*I$9 -> 0 | AL100: =J100*J$9 -> 0 | ... AP100: =N100*N$9 -> 0
B101: Gazole (yc carb. subs) | C101: ='B&C'!C105 -> 0.70883653 | D101: ='B&C'!D105 -> 0.72304161 | E101: ='B&C'!E105 -> 0.52111107 | F101: ='B&C'!F105 -> 0.59093721 | G101: ='B&C'!G105 -> 0.63283173 | H101: ='B&C'!H105 -> 0.64793026 | I101: ='B&C'!I105 -> 0.63886488 | J101: ='B&C'!J105 -> 0.52792528 | ... N101: ='B&C'!N105 -> 0.12819127 | P101: Gazole (yc carb. subs) | Q101: =C101*11.63 -> 8.2437689 | R101: =D101*11.63 -> 8.4089739 | S101: =E101*11.63 -> 6.0605217 | T101: =F101*11.63 -> 6.8725997 | U101: =G101*11.63 -> 7.359833 | V101: =H101*11.63 -> 7.535429 | W101: =I101*11.63 -> 7.4299985 | X101: =J101*11.63 -> 6.139771 | ... AB101: =N101*11.63 -> 1.4908644 | AD101: Gazole (yc carb. subs) | AE101: =C101*C$10 -> 2.0783473 | AF101: =D101*D$10 -> 2.1060776 | AG101: =E101*E$10 -> 1.5190554 | AH101: =F101*F$10 -> 1.7280587 | AI101: =G101*G$10 -> 1.8474908 | AJ101: =H101*H$10 -> 1.881542 | AK101: =I101*I$10 -> 1.8242578 | AL101: =J101*J$10 -> 1.4359267 | ... AP101: =N101*N$10 -> 0
B102: GPL | C102: =0 -> 0 | D102: =0 -> 0 | E102: =0 -> 0 | F102: =0 -> 0 | G102: =0 -> 0 | H102: =0 -> 0 | I102: =0 -> 0 | J102: =0 -> 0 | ... N102: =0 -> 0 | P102: GPL | Q102: =C102*11.63 -> 0 | R102: =D102*11.63 -> 0 | S102: =E102*11.63 -> 0 | T102: =F102*11.63 -> 0 | U102: =G102*11.63 -> 0 | V102: =H102*11.63 -> 0 | W102: =I102*11.63 -> 0 | X102: =J102*11.63 -> 0 | ... AB102: =N102*11.63 -> 0 | AD102: GPL | AE102: =C102*C$9 -> 0 | AF102: =D102*D$9 -> 0 | AG102: =E102*E$9 -> 0 | AH102: =F102*F$9 -> 0 | AI102: =G102*G$9 -> 0 | AJ102: =H102*H$9 -> 0 | AK102: =I102*I$9 -> 0 | AL102: =J102*J$9 -> 0 | ... AP102: =N102*N$9 -> 0
B103: GNV | C103: ='B&C'!C106 -> 0.029004602 | D103: ='B&C'!D106 -> 0.028913448 | E103: ='B&C'!E106 -> 0.020838521 | F103: ='B&C'!F106 -> 0.039449761 | G103: ='B&C'!G106 -> 0.056941103 | H103: ='B&C'!H106 -> 0.072183852 | I103: ='B&C'!I106 -> 0.084737941 | J103: ='B&C'!J106 -> 0.12286905 | ... N103: ='B&C'!N106 -> 0.0022744589 | P103: GNV | Q103: =C103*11.63 -> 0.33732352 | R103: =D103*11.63 -> 0.3362634 | S103: =E103*11.63 -> 0.242352 | T103: =F103*11.63 -> 0.45880072 | U103: =G103*11.63 -> 0.66222503 | V103: =H103*11.63 -> 0.8394982 | W103: =I103*11.63 -> 0.98550225 | X103: =J103*11.63 -> 1.4289671 | ... AB103: =N103*11.63 -> 0.026451957 | AD103: GNV | AE103: =C103*C$11 -> 0.068470203 | AF103: =D103*D$11 -> 0.063244641 | AG103: =E103*E$11 -> 0.049192807 | AH103: =F103*F$11 -> 0.093220965 | AI103: =G103*G$11 -> 0.13455353 | AJ103: =H103*H$11 -> 0.16886688 | AK103: =I103*I$11 -> 0.19022638 | AL103: =J103*J$11 -> 0.24679176 | ... AP103: =N103*N$11 -> 0
B104: H2 | C104: ='B&C'!C108 -> 0 | D104: ='B&C'!D108 -> 0 | E104: ='B&C'!E108 -> 0 | F104: ='B&C'!F108 -> 0 | G104: ='B&C'!G108 -> 0 | H104: ='B&C'!H108 -> 0 | I104: ='B&C'!I108 -> 0.00070617192 | J104: ='B&C'!J108 -> 0.0011811472 | ... N104: ='B&C'!N108 -> 0.012864877 | P104: H2 | Q104: =C104*11.63 -> 0 | R104: =D104*11.63 -> 0 | S104: =E104*11.63 -> 0 | T104: =F104*11.63 -> 0 | U104: =G104*11.63 -> 0 | V104: =H104*11.63 -> 0 | W104: =I104*11.63 -> 0.0082127794 | X104: =J104*11.63 -> 0.013736742 | ... AB104: =N104*11.63 -> 0.14961852 | AD104: H2 | AE104: =C104*0 -> 0 | AF104: =D104*0 -> 0 | AG104: =E104*0 -> 0 | AH104: =F104*0 -> 0 | AI104: =G104*0 -> 0 | AJ104: =H104*0 -> 0 | AK104: =I104*0 -> 0 | AL104: =J104*0 -> 0 | ... AP104: =N104*0 -> 0
B105: Electricité | C105: ='B&C'!C107 -> 0.0030572275 | D105: ='B&C'!D107 -> 0.0030842274 | E105: ='B&C'!E107 -> 0.0022430745 | F105: ='B&C'!F107 -> 0.0034585185 | G105: ='B&C'!G107 -> 0.0052886493 | H105: ='B&C'!H107 -> 0.0073311129 | I105: ='B&C'!I107 -> 0.014019212 | J105: ='B&C'!J107 -> 0.049460731 | ... N105: ='B&C'!N107 -> 0.23288875 | P105: Electricité | Q105: =C105*11.63 -> 0.035555556 | R105: =D105*11.63 -> 0.035869565 | S105: =E105*11.63 -> 0.026086957 | T105: =F105*11.63 -> 0.04022257 | U105: =G105*11.63 -> 0.061506991 | V105: =H105*11.63 -> 0.085260843 | W105: =I105*11.63 -> 0.16304343 | X105: =J105*11.63 -> 0.57522831 | ... AB105: =N105*11.63 -> 2.7084962 | AD105: Electricité | AE105: =C105*0 -> 0 | AF105: =D105*0 -> 0 | AG105: =E105*0 -> 0 | AH105: =F105*0 -> 0 | AI105: =G105*0 -> 0 | AJ105: =H105*0 -> 0 | AK105: =I105*0 -> 0 | AL105: =J105*0 -> 0 | ... AP105: =N105*0 -> 0
B107: 2 roues | C107: =C108+C109 -> 0.43910244 | D107: =D108+D109 -> 0.43901604 | E107: =E108+E109 -> 0.37096855 | F107: =F108+F109 -> 0.42999961 | G107: =G108+G109 -> 0.41985348 | H107: =H108+H109 -> 0.41985348 | I107: =I108+I109 -> 0.38307421 | J107: =J108+J109 -> 0.30998554 | ... N107: =N108+N109 -> 0.13976737 | P107: 2 roues | Q107: =C107*11.63 -> 5.1067613 | R107: =D107*11.63 -> 5.1057565 | S107: =E107*11.63 -> 4.3143643 | T107: =F107*11.63 -> 5.0008954 | U107: =G107*11.63 -> 4.882896 | V107: =H107*11.63 -> 4.882896 | W107: =I107*11.63 -> 4.4551531 | X107: =J107*11.63 -> 3.6051318 | ... AB107: =N107*11.63 -> 1.6254945 | AD107: 2 roues | AE107: =AE108+AE109 -> 1.2474005 | AF107: =AF108+AF109 -> 1.2349942 | AG107: =AG108+AG109 -> 1.0493231 | AH107: =AH108+AH109 -> 1.1965554 | AI107: =AI108+AI109 -> 1.1519073 | AJ107: =AJ108+AJ109 -> 1.1442409 | AK107: =AK108+AK109 -> 1.0109612 | AL107: =AL108+AL109 -> 0.71199303 | ... AP107: =AP108+AP109 -> 0
B108: Essence (yc carb. subst.) | C108: ='2RM'!E36 -> 0.43910244 | D108: ='2RM'!F36 -> 0.43901604 | E108: ='2RM'!G36 -> 0.37096855 | F108: ='2RM'!H36 -> 0.42329714 | G108: ='2RM'!I36 -> 0.40889922 | H108: ='2RM'!J36 -> 0.40889922 | I108: ='2RM'!K36 -> 0.36859644 | J108: ='2RM'!L36 -> 0.26921832 | ... N108: ='2RM'!P36 -> 0.041811917 | P108: Essence (yc carb. subst.) | Q108: =C108*11.63 -> 5.1067613 | R108: =D108*11.63 -> 5.1057565 | S108: =E108*11.63 -> 4.3143643 | T108: =F108*11.63 -> 4.9229458 | U108: =G108*11.63 -> 4.7554979 | V108: =H108*11.63 -> 4.7554979 | W108: =I108*11.63 -> 4.2867766 | X108: =J108*11.63 -> 3.1310091 | ... AB108: =N108*11.63 -> 0.4862726 | AD108: Essence (yc carb. subst.) | AE108: =C108*C$9 -> 1.2474005 | AF108: =D108*D$9 -> 1.2349942 | AG108: =E108*E$9 -> 1.0493231 | AH108: =F108*F$9 -> 1.1965554 | AI108: =G108*G$9 -> 1.1519073 | AJ108: =H108*H$9 -> 1.1442409 | AK108: =I108*I$9 -> 1.0109612 | AL108: =J108*J$9 -> 0.71199303 | ... AP108: =N108*N$9 -> 0
B109: Electricité | C109: ='2RM'!E37 -> 0 | D109: ='2RM'!F37 -> 0 | E109: ='2RM'!G37 -> 0 | F109: ='2RM'!H37 -> 0.0067024631 | G109: ='2RM'!I37 -> 0.010954263 | H109: ='2RM'!J37 -> 0.010954263 | I109: ='2RM'!K37 -> 0.014477769 | J109: ='2RM'!L37 -> 0.040767217 | ... N109: ='2RM'!P37 -> 0.097955454 | P109: Electricité | Q109: =C109*11.63 -> 0 | R109: =D109*11.63 -> 0 | S109: =E109*11.63 -> 0 | T109: =F109*11.63 -> 0.077949646 | U109: =G109*11.63 -> 0.12739808 | V109: =H109*11.63 -> 0.12739808 | W109: =I109*11.63 -> 0.16837646 | X109: =J109*11.63 -> 0.47412273 | ... AB109: =N109*11.63 -> 1.1392219 | AD109: Electricité | AE109: =C109*0 -> 0 | AF109: =D109*0 -> 0 | AG109: =E109*0 -> 0 | AH109: =F109*0 -> 0 | AI109: =G109*0 -> 0 | AJ109: =H109*0 -> 0 | AK109: =I109*0 -> 0 | AL109: =J109*0 -> 0 | ... AP109: =N109*0 -> 0
B111: Total modes routiers | C111: =C75+C83+C91+C99+C107 -> 43.439204 | D111: =D75+D83+D91+D99+D107 -> 43.954337 | E111: =E75+E83+E91+E99+E107 -> 36.602589 | F111: =F75+F83+F91+F99+F107 -> 39.712257 | G111: =G75+G83+G91+G99+G107 -> 42.254475 | H111: =H75+H83+H91+H99+H107 -> 41.223941 | I111: =I75+I83+I91+I99+I107 -> 39.587128 | J111: =J75+J83+J91+J99+J107 -> 32.477097 | ... N111: =N75+N83+N91+N99+N107 -> 11.417643 | P111: Total modes routiers | Q111: =C111*11.63 -> 505.19794 | R111: =D111*11.63 -> 511.18894 | S111: =E111*11.63 -> 425.68811 | T111: =F111*11.63 -> 461.85355 | U111: =G111*11.63 -> 491.41954 | V111: =H111*11.63 -> 479.43444 | W111: =I111*11.63 -> 460.39829 | X111: =J111*11.63 -> 377.70864 | ... AB111: =N111*11.63 -> 132.78719 | AD111: Total modes routiers | AE111: =AE75+AE83+AE91+AE99+AE107 -> 126.50474 | AF111: =AF75+AF83+AF91+AF99+AF107 -> 126.99217 | AG111: =AG75+AG83+AG91+AG99+AG107 -> 105.85614 | AH111: =AH75+AH83+AH91+AH99+AH107 -> 114.88253 | AI111: =AI75+AI83+AI91+AI99+AI107 -> 121.68735 | AJ111: =AJ75+AJ83+AJ91+AJ99+AJ107 -> 117.69249 | AK111: =AK75+AK83+AK91+AK99+AK107 -> 110.30568 | AL111: =AL75+AL83+AL91+AL99+AL107 -> 81.965732 | ... AP111: =AP75+AP83+AP91+AP99+AP107 -> 0
B112: Essence (yc carb. subst.) | C112: =C76+C84+C92+C100+C108 -> 7.6108309 | D112: =D76+D84+D92+D100+D108 -> 8.1162175 | E112: =E76+E84+E92+E100+E108 -> 6.9368177 | F112: =F76+F84+F92+F100+F108 -> 7.979272 | G112: =G76+G84+G92+G100+G108 -> 9.0889977 | H112: =H76+H84+H92+H100+H108 -> 9.4409067 | I112: =I76+I84+I92+I100+I108 -> 9.9375193 | J112: =J76+J84+J92+J100+J108 -> 12.077556 | ... N112: =N76+N84+N92+N100+N108 -> 0.056548138 | P112: Essence (yc carb. subst.) | Q112: =C112*11.63 -> 88.513964 | R112: =D112*11.63 -> 94.391609 | S112: =E112*11.63 -> 80.67519 | T112: =F112*11.63 -> 92.798933 | U112: =G112*11.63 -> 105.70504 | V112: =H112*11.63 -> 109.79775 | W112: =I112*11.63 -> 115.57335 | X112: =J112*11.63 -> 140.46198 | ... AB112: =N112*11.63 -> 0.65765485 | AD112: Essence (yc carb. subst.) | AE112: =AE76+AE84+AE92+AE100+AE108 -> 21.620819 | AF112: =AF76+AF84+AF92+AF100+AF108 -> 22.831697 | AG112: =AG76+AG84+AG92+AG100+AG108 -> 19.62151 | AH112: =AH76+AH84+AH92+AH100+AH108 -> 22.555411 | AI112: =AI76+AI84+AI92+AI100+AI108 -> 25.604557 | AJ112: =AJ76+AJ84+AJ92+AJ100+AJ108 -> 26.41891 | AK112: =AK76+AK84+AK92+AK100+AK108 -> 27.255952 | AL112: =AL76+AL84+AL92+AL100+AL108 -> 31.941124 | ... AP112: =AP76+AP84+AP92+AP100+AP108 -> 0
B113: Gazole (yc carb. subs) | C113: =C77+C85+C93+C101 -> 35.69769 | D113: =D77+D85+D93+D101 -> 35.675392 | E113: =E77+E85+E93+E101 -> 29.473105 | F113: =F77+F85+F93+F101 -> 31.409759 | G113: =G77+G85+G93+G101 -> 32.702324 | H113: =H77+H85+H93+H101 -> 31.22063 | I113: =I77+I85+I93+I101 -> 28.80647 | J113: =J77+J85+J93+J101 -> 18.078521 | ... N113: =N77+N85+N93+N101 -> 1.2357701 | P113: Gazole (yc carb. subs) | Q113: =C113*11.63 -> 415.16413 | R113: =D113*11.63 -> 414.9048 | S113: =E113*11.63 -> 342.77221 | T113: =F113*11.63 -> 365.2955 | U113: =G113*11.63 -> 380.32803 | V113: =H113*11.63 -> 363.09593 | W113: =I113*11.63 -> 335.01925 | X113: =J113*11.63 -> 210.2532 | ... AB113: =N113*11.63 -> 14.372006 | AD113: Gazole (yc carb. subs) | AE113: =AE77+AE85+AE93+AE101 -> 104.66757 | AF113: =AF77+AF85+AF93+AF101 -> 103.91538 | AG113: =AG77+AG85+AG93+AG101 -> 85.915044 | AH113: =AH77+AH85+AH93+AH101 -> 91.850552 | AI113: =AI77+AI85+AI93+AI101 -> 95.47126 | AJ113: =AJ77+AJ85+AJ93+AJ101 -> 90.662422 | AK113: =AK77+AK85+AK93+AK101 -> 82.255936 | AL113: =AL77+AL85+AL93+AL101 -> 49.172546 | ... AP113: =AP77+AP85+AP93+AP101 -> 0
B114: GPL | C114: =C78+C86+C94+C102 -> 0 | D114: =D78+D86+D94+D102 -> 0 | E114: =E78+E86+E94+E102 -> 0 | F114: =F78+F86+F94+F102 -> 0 | G114: =G78+G86+G94+G102 -> 0 | H114: =H78+H86+H94+H102 -> 0 | I114: =I78+I86+I94+I102 -> 0 | J114: =J78+J86+J94+J102 -> 0 | ... N114: =N78+N86+N94+N102 -> 0 | P114: GPL | Q114: =C114*11.63 -> 0 | R114: =D114*11.63 -> 0 | S114: =E114*11.63 -> 0 | T114: =F114*11.63 -> 0 | U114: =G114*11.63 -> 0 | V114: =H114*11.63 -> 0 | W114: =I114*11.63 -> 0 | X114: =J114*11.63 -> 0 | ... AB114: =N114*11.63 -> 0 | AD114: GPL | AE114: =AE78+AE86+AE94+AE102 -> 0 | AF114: =AF78+AF86+AF94+AF102 -> 0 | AG114: =AG78+AG86+AG94+AG102 -> 0 | AH114: =AH78+AH86+AH94+AH102 -> 0 | AI114: =AI78+AI86+AI94+AI102 -> 0 | AJ114: =AJ78+AJ86+AJ94+AJ102 -> 0 | AK114: =AK78+AK86+AK94+AK102 -> 0 | AL114: =AL78+AL86+AL94+AL102 -> 0 | ... AP114: =AP78+AP86+AP94+AP102 -> 0
B115: GNV | C115: =C79+C87+C95+C103 -> 0.091650184 | D115: =D79+D87+D95+D103 -> 0.11204792 | E115: =E79+E87+E95+E103 -> 0.13537863 | F115: =F79+F87+F95+F103 -> 0.20167722 | G115: =G79+G87+G95+G103 -> 0.25879115 | H115: =H79+H87+H95+H103 -> 0.26124573 | I115: =I79+I87+I95+I103 -> 0.35360179 | J115: =J79+J87+J95+J103 -> 0.42421192 | ... N115: =N79+N87+N95+N103 -> 0.0068722403 | P115: GNV | Q115: =C115*11.63 -> 1.0658916 | R115: =D115*11.63 -> 1.3031174 | S115: =E115*11.63 -> 1.5744535 | T115: =F115*11.63 -> 2.3455061 | U115: =G115*11.63 -> 3.009741 | V115: =H115*11.63 -> 3.0382879 | W115: =I115*11.63 -> 4.1123888 | X115: =J115*11.63 -> 4.9335847 | ... AB115: =N115*11.63 -> 0.079924155 | AD115: GNV | AE115: =AE79+AE87+AE95+AE103 -> 0.21635555 | AF115: =AF79+AF87+AF95+AF103 -> 0.24509117 | AG115: =AG79+AG87+AG95+AG103 -> 0.31958385 | AH115: =AH79+AH87+AH95+AH103 -> 0.4765693 | AI115: =AI79+AI87+AI95+AI103 -> 0.61153122 | AJ115: =AJ79+AJ87+AJ95+AJ103 -> 0.61115817 | AK115: =AK79+AK87+AK95+AK103 -> 0.79379303 | AL115: =AL79+AL87+AL95+AL103 -> 0.85206164 | ... AP115: =AP79+AP87+AP95+AP103 -> 0
B116: H2 | C116: =C80+C88+C96+C104 -> 0 | D116: =D80+D88+D96+D104 -> 0 | E116: =E80+E88+E96+E104 -> 0 | F116: =F80+F88+F96+F104 -> 0 | G116: =G80+G88+G96+G104 -> 0 | H116: =H80+H88+H96+H104 -> 0 | I116: =I80+I88+I96+I104 -> 0.0048722932 | J116: =J80+J88+J96+J104 -> 0.0080975193 | ... N116: =N80+N88+N96+N104 -> 0.16759024 | P116: H2 | Q116: =C116*11.63 -> 0 | R116: =D116*11.63 -> 0 | S116: =E116*11.63 -> 0 | T116: =F116*11.63 -> 0 | U116: =G116*11.63 -> 0 | V116: =H116*11.63 -> 0 | W116: =I116*11.63 -> 0.05666477 | X116: =J116*11.63 -> 0.094174149 | ... AB116: =N116*11.63 -> 1.9490745 | AD116: H2 | AE116: =AE80+AE88+AE96+AE104 -> 0 | AF116: =AF80+AF88+AF96+AF104 -> 0 | AG116: =AG80+AG88+AG96+AG104 -> 0 | AH116: =AH80+AH88+AH96+AH104 -> 0 | AI116: =AI80+AI88+AI96+AI104 -> 0 | AJ116: =AJ80+AJ88+AJ96+AJ104 -> 0 | AK116: =AK80+AK88+AK96+AK104 -> 0 | AL116: =AL80+AL88+AL96+AL104 -> 0 | ... AP116: =AP80+AP88+AP96+AP104 -> 0
B117: Electricité | C117: =C81+C89+C97+C105+C109 -> 0.039032914 | D117: =D81+D89+D97+D105+D109 -> 0.050679591 | E117: =E81+E89+E97+E105+E109 -> 0.057287916 | F117: =F81+F89+F97+F105+F109 -> 0.12154816 | G117: =G81+G89+G97+G105+G109 -> 0.20436167 | H117: =H81+H89+H97+H105+H109 -> 0.30115876 | I117: =I81+I89+I97+I105+I109 -> 0.48466405 | J117: =J81+J89+J97+J105+J109 -> 1.8887104 | ... N117: =N81+N89+N97+N105+N109 -> 9.9508626 | P117: Electricité | Q117: =C117*11.63 -> 0.45395279 | R117: =D117*11.63 -> 0.58940364 | S117: =E117*11.63 -> 0.66625846 | T117: =F117*11.63 -> 1.4136051 | U117: =G117*11.63 -> 2.3767262 | V117: =H117*11.63 -> 3.5024764 | W117: =I117*11.63 -> 5.6366428 | X117: =J117*11.63 -> 21.965702 | ... AB117: =N117*11.63 -> 115.72853 | AD117: Electricité | AE117: =AE81+AE89+AE97+AE105+AE109 -> 0 | AF117: =AF81+AF89+AF97+AF105+AF109 -> 0 | AG117: =AG81+AG89+AG97+AG105+AG109 -> 0 | AH117: =AH81+AH89+AH97+AH105+AH109 -> 0 | AI117: =AI81+AI89+AI97+AI105+AI109 -> 0 | AJ117: =AJ81+AJ89+AJ97+AJ105+AJ109 -> 0 | AK117: =AK81+AK89+AK97+AK105+AK109 -> 0 | AL117: =AL81+AL89+AL97+AL105+AL109 -> 0 | ... AP117: =AP81+AP89+AP97+AP105+AP109 -> 0
B119: Réduction / 2018 | C119: =C111/$C111-1 -> 0 | D119: =D111/$C111-1 -> 0.011858713 | E119: =E111/$C111-1 -> -0.15738351 | F119: =F111/$C111-1 -> -0.08579685 | G119: =G111/$C111-1 -> -0.027273258 | H119: =H111/$C111-1 -> -0.050996839 | I119: =I111/$C111-1 -> -0.088677409 | J119: =J111/$C111-1 -> -0.25235515 | ... N119: =N111/$C111-1 -> -0.73715809 | P119: Réduction / 2022 | AA119: =AA113+AA112 -> 51.550876 | AD119: Réduction / 2018 | AE119: =AE111/$AE111-1 -> 0 | AF119: =AF111/$AE111-1 -> 0.0038530089 | AG119: =AG111/$AE111-1 -> -0.16322396 | AH119: =AH111/$AE111-1 -> -0.091871741 | AI119: =AI111/$AE111-1 -> -0.03808075 | AJ119: =AJ111/$AE111-1 -> -0.069659472 | AK119: =AK111/$AE111-1 -> -0.12805103 | AL119: =AL111/$AE111-1 -> -0.35207385 | ... AP119: =AP111/$AE111-1 -> -1
B121: 4.5 Autres modes | P121: 4.5 Autres modes | AD121: 4.5 Autres modes | AL121: (métropole + 50% des vols vers outre-mer)
...

Sheet FE_et_bio
A1: 1 tep | B1: 41.868 | C1: GJ | D1: =B1/3.6 -> 11.63 | E1: MWh
A3: 1/ Sur produits fossiles
B4: MJ/L | C4: MJ/kg | D4: kWh/L | E4: kgCO2/L | F4: kgCO2/kWh | G4: avec maj 1% | I4: 1kWh/L vaut 1TWh/m3
A5: H2 | C5: 120
A6: Gazole | B6: 36 | C6: 42.6 | D6: 10 | E6: 2.68272 | F6: 0.268272 | G6: 0.27095472
A7: Essence | B7: 32 | C7: 44 | D7: 8.8888889 | E7: 2.31936 | F7: 0.260928 | G7: 0.26353728
A8: carburéacteur | B8: 34 | C8: 44 | D8: 9.4444444 | E8: 2.43406 | F8: 0.257724 | G8: 0.26030124
C10: MJ/kg | D10: kWh/kg | E10: kgCO2/kg | F10: kgCO2/kWh | G10: avec maj 1%
A11: GNV/gaz | C11: =D11*3.6 -> 49.6 | D11: 13.777778 | E11: 2.799424 | F11: 0.203184 | G11: 0.20521584
A12: GPL | C12: =D12*3.6 -> 46 | D12: 12.777778 | E12: 2.9026 | F12: 0.22716 | G12: 0.2294316
A14: FE sur produits fossile
B15: FE (tCO2/tep) | C15: FE (kgCO2/kWh)
B16: 2015 | C16: 2015
A17: Essence | B17: =C17*11.63 -> 3.064505 | C17: 0.2635 | E17: 0.26096303 | F17: =C17/E17 -> 1.0097216
A18: Diesel | B18: =C18*11.63 -> 3.15173 | C18: 0.271 | E18: 0.27343078 | F18: =C18/E18 -> 0.99111006
A19: Kérosène | B19: =C19*11.63 -> 3.027289 | C19: 0.2603 | E19: 0.25984523 | F19: =C19/E19 -> 1.0017502
A20: GNV | B20: =C20*11.63 -> 2.3630299 | C20: =F11 -> 0.203184 | E20: 0.20309544 | F20: =C20/E20 -> 1.000436
A23: FE du fossile | B23: FE par udp (avec maj 1%) | D23: Energie par udp
A24: Essence | B24: =E7*1.01 -> 2.3425536 | C24: kgCO2/L | D24: =32/3.6 -> 8.8888889 | E24: kWh/L
A25: Gazole | B25: =E6*1.01 -> 2.7095472 | C25: kgCO2/L | D25: 10 | E25: kWh/L
A26: Kérosène | B26: =E8*1.01 -> 2.4584006 | C26: kgCO2/L | D26: =34/3.6 -> 9.4444444 | E26: kWh/L
A27: GNV | B27: =E11 -> 2.799424 | C27: kgCO2/kg | D27: =D11 -> 13.777778 | E27: kWh/kg
A29: 2/ Part de bio-énergies
C30: 2019 | D30: 2020 | E30: 2021 | F30: 2022 | G30: 2023 | H30: 2025
A31: tx observé fer | C31: 0.06756197 | D31: 0.066866998 | E31: 0.094685302 | F31: 0.095325097 | G31: 0.097510637
A32: Taux observés
A33: tx observé biocarb routier moy | C33: 0.077192913 | D33: 0.075518201 | E33: 0.073373389 | F33: 0.075274251 | G33: 0.080453012
A34: tx bio théorique | C34: =C39/4.5+3.5/4.5*C40 -> 0.074333333 | D34: =D39/4.5+3.5/4.5*D40 -> 0.080444444 | E34: =E39/4.5+3.5/4.5*E40 -> 0.081333333 | F34: =F39/4.5+3.5/4.5*F40 -> 0.085777778 | G34: =G39/4.5+3.5/4.5*G40 -> 0.088
A35: correctif | C35: =C33/C34 -> 1.0384697 | D35: =D33/D34 -> 0.93876217 | E35: =E33/E34 -> 0.90213183 | F35: =F33/F34 -> 0.87754956 | G35: =G33/G34 -> 0.91423878 | H35: 1
A37: Taux théoriques plafonds
B38: 2018 | C38: 2019 | D38: 2020 | E38: 2021 | F38: 2022 | G38: 2023 | H38: 2025
A39: Taux d’incorporation des biocarburants dans l’essence | B39: 0.073 | C39: 0.079 | D39: 0.082 | E39: 0.086 | F39: 0.092 | G39: 0.095 | H39: 0.105
A40: Taux d’incorporation des biocarburants dans le diesel | B40: 0.0697 | C40: 0.073 | D40: 0.08 | E40: 0.08 | F40: 0.084 | G40: 0.086 | H40: 0.094
A41: Taux d’incorporation du gaz renouvelable dans le gaz | B41: =0.1% -> 0.001 | C41: =0.1% -> 0.001 | D41: =0.1% -> 0.001 | E41: =D41 -> 0.001 | F41: =E41 -> 0.001 | G41: 0.01 | H41: =2% -> 0.02
A43: Taux appliqués
A44: Taux de bio dans les carburants terrestres (taux d'incorporation en énergie)
B45: 2018 | C45: 2019 | D45: 2020 | E45: 2021 | F45: 2022 | G45: 2023 | H45: 2025 | I45: 2030 | J45: 2035 | K45: 2040 | L45: 2045 | M45: 2050 | P45: 2022 | Q45: 2023 | R45: 2024 | S45: 2025
A46: Taux d’incorporation des biocarburants dans l’essence | B46: =B39 -> 0.073 | C46: =C39*C$35 -> 0.082039105 | D46: =D39*D$35 -> 0.076978498 | E46: =E39*E$35 -> 0.077583337 | F46: =F39*F$35 -> 0.080734559 | G46: =G39*G$35 -> 0.086852684 | H46: =H39*H$35 -> 0.105 | I46: 0.137 | J46: 0.19 | K46: 0.3 | L46: 0.6 | M46: 1 | O46: essence | Q46: 0.095 | R46: 0.099 | S46: 0.105
A47: Taux d’incorporation des biocarburants dans le diesel | B47: =B40 -> 0.0697 | C47: =C40*C$35 -> 0.075808287 | D47: =D40*D$35 -> 0.075100974 | E47: =E40*E$35 -> 0.072170546 | F47: =F40*F$35 -> 0.073714163 | G47: =G40*G$35 -> 0.078624535 | H47: =H40*H$35 -> 0.094 | I47: =I46 -> 0.137 | J47: 0.19 | K47: =K46 -> 0.3 | L47: =L46 -> 0.6 | M47: =M46 -> 1 | O47: gazole | Q47: 0.086 | R47: 0.092 | S47: 0.094
A48: Taux d’incorporation du gaz renouvelable dans le gaz | B48: =0.1% -> 0.001 | C48: =C34 -> 0.074333333 | D48: =0.1% -> 0.001 | G48: 0.01 | H48: 0.05 | I48: 0.15 | J48: 0.2 | K48: 0.4 | L48: 0.5 | M48: 1 | O48: carbu | Q48: 0.01 | R48: 0.015 | S48: 0.02
A49: dont méthane de synthèse | D49: =0 -> 0 | E49: =0 -> 0 | F49: =0 -> 0 | H49: =0 -> 0 | I49: =0 -> 0 | J49: =0 -> 0 | K49: =0 -> 0 | L49: =0 -> 0 | M49: =0 -> 0
A50: dont biogaz | D50: =D48-D49 -> 0.001 | E50: =E48-E49 -> 0 | F50: =F48-F49 -> 0 | H50: =H48-H49 -> 0.05 | I50: =I48-I49 -> 0.15 | J50: =J48-J49 -> 0.2 | K50: =K48-K49 -> 0.4 | L50: =L48-L49 -> 0.5 | M50: =M48-M49 -> 1
B51: 2018 | C51: 2019 | D51: 2020 | E51: 2021 | F51: 2022 | G51: 2023 | H51: 2025 | I51: 2030 | J51: 2035 | K51: 2040 | L51: 2045 | M51: 2050
A52: carburéacteurs | F52: 0.01 | G52: 0.01 | H52: 0.02
A55: Taux de biocarburants, PtL, H2 dans les carburants aériens et maritimes : cf onglets afférents
A57: 4/ FE par udp en intégrant les bioénergies
B59: 2018 | C59: 2019 | D59: 2020 | E59: 2021 | F59: 2022 | G59: 2023 | H59: 2025 | I59: 2030 | J59: 2035 | K59: 2040 | L59: 2045 | M59: 2050
A60: Essence (kgCO2/L) | B60: =$B24*(1-B46) -> 2.1715472 | C60: =$B24*(1-C46) -> 2.1503726 | D60: =$B24*(1-D46) -> 2.1622273 | E60: =$B24*(1-E46) -> 2.1608105 | F60: =$B24*(1-F46) -> 2.1534286 | G60: =$B24*(1-G46) -> 2.1390965 | H60: =$B24*(1-H46) -> 2.0965855 | I60: =$B24*(1-I46) -> 2.0216238 | ... M60: =$B24*(1-M46) -> 0
A61: Gazole (kg CO2/L) | B61: =$B25*(1-B47) -> 2.5206918 | C61: =$B25*(1-C47) -> 2.5041411 | D61: =$B25*(1-D47) -> 2.5060576 | E61: =$B25*(1-E47) -> 2.5139977 | F61: =$B25*(1-F47) -> 2.5098152 | G61: =$B25*(1-G47) -> 2.4965103 | H61: =$B25*(1-H47) -> 2.4548498 | I61: =$B25*(1-I47) -> 2.3383392 | ... M61: =$B25*(1-M47) -> 0
A62: GNV (kg CO2/kg) | B62: =$B27*(1-B48) -> 2.7966246 | C62: =$B27*(1-C48) -> 2.5913335 | D62: =$B27*(1-D48) -> 2.7966246 | E62: =$B27*(1-E48) -> 2.799424 | F62: =$B27*(1-F48) -> 2.799424 | G62: =$B27*(1-G48) -> 2.7714298 | H62: =$B27*(1-H48) -> 2.6594528 | I62: =$B27*(1-I48) -> 2.3795104 | ... M62: =$B27*(1-M48) -> 0
A64: 3/ FE par Mtep en intégrant les bioénergies
B66: 2018 | C66: 2019 | D66: 2020 | E66: 2021 | F66: 2022 | G66: 2023 | H66: 2025 | I66: 2030 | J66: 2035 | K66: 2040 | L66: 2045 | M66: 2050
A67: Essence (kgCO2/L) | B67: =$B17*(1-B46) -> 2.8407961 | C67: =$B17*(1-C46) -> 2.8130958 | D67: =$B17*(1-D46) -> 2.828604 | E67: =$B17*(1-E46) -> 2.8267505 | F67: =$B17*(1-F46) -> 2.8170935 | G67: =$B17*(1-G46) -> 2.7983445 | H67: =$B17*(1-H46) -> 2.742732 | I67: =$B17*(1-I46) -> 2.6446678 | ... M67: =$B17*(1-M46) -> 0
A68: Gazole (kg CO2/L) | B68: =$B18*(1-B47) -> 2.9320544 | C68: =$B18*(1-C47) -> 2.9128027 | D68: =$B18*(1-D47) -> 2.915032 | E68: =$B18*(1-E47) -> 2.9242679 | F68: =$B18*(1-F47) -> 2.9194029 | G68: =$B18*(1-G47) -> 2.9039267 | H68: =$B18*(1-H47) -> 2.8554674 | I68: =$B18*(1-I47) -> 2.719943 | ... M68: =$B18*(1-M47) -> 0
A69: GNV (kg CO2/kg) | B69: =$B20*(1-B48) -> 2.3606669 | C69: =$B20*(1-C48) -> 2.187378 | D69: =$B20*(1-D48) -> 2.3606669 | E69: =$B20*(1-E48) -> 2.3630299 | F69: =$B20*(1-F48) -> 2.3630299 | G69: =$B20*(1-G48) -> 2.3393996 | H69: =$B20*(1-H48) -> 2.2448784 | I69: =$B20*(1-I48) -> 2.0085754 | ... M69: =$B20*(1-M48) -> 0
A72: % CO2 biogénique
A73: % CO2 biogénique dans CO2 des efuels | B73: 2018 | C73: 2019 | D73: 2020 | E73: 2021 | F73: 2022 | G73: 2023 | H73: 2025 | I73: 2030 | J73: 2035 | K73: 2040 | L73: 2045 | M73: 2050
A74: de l'aviation | B74: =100% -> 1 | C74: =100% -> 1 | D74: =100% -> 1 | E74: =100% -> 1 | F74: =100% -> 1 | G74: =100% -> 1 | H74: =100% -> 1 | I74: =100% -> 1 | ... M74: =100% -> 1
A75: du maritime | B75: =100% -> 1 | C75: =100% -> 1 | D75: =100% -> 1 | E75: =100% -> 1 | F75: =100% -> 1 | G75: =100% -> 1 | H75: =100% -> 1 | I75: =100% -> 1 | ... M75: =100% -> 1

Sheet VP
B2: 1 tep | C2: 41.868 | D2: GJ | E2: =C2/3.6 -> 11.63 | K2: MWh
B4: FE du fossile sans intégration des parts de bio et avec contenu élec à 0 (pour calcul de l'évolution des émissions des véh neufs)
B5: FE du fossile | C5: FE par udp | E5: Energie par udp
B6: Essence | C6: 2.3422222 | D6: kgCO2/L | E6: 8.8888889 | F6: kWh/L | G6: =C6/E6 -> 0.2635
B7: Gazole | C7: 2.71 | D7: kgCO2/L | E7: 10 | F7: kWh/L | G7: =C7/E7 -> 0.271
B8: Kérosène | C8: 2.4583889 | D8: kgCO2/L | E8: 9.4444444 | F8: kWh/L | G8: =C8/E8 -> 0.2603
B9: GNV | C9: 2.8027171 | D9: kgCO2/kg | E9: 13.8 | F9: kWh/kg | G9: =C9/E9 -> 0.20309544
B10: Electricité | C10: 0
B12: FE des carburants avec intégration des parts de bio et avec facteur émissions de l'élec nul (pour calcul roulant)
B13: FE du fossile | C13: 2018 | D13: 2019 | E13: 2020 | F13: 2021 | G13: 2022 | H13: 2023 | I13: 2025 | J13: 2030 | K13: 2035 | L13: 2040 | M13: 2045 | N13: 2050
B14: Essence | C14: =FE_et_bio!B60 -> 2.1715472 | D14: =FE_et_bio!C60 -> 2.1503726 | E14: =FE_et_bio!D60 -> 2.1622273 | F14: =FE_et_bio!E60 -> 2.1608105 | G14: =FE_et_bio!F60 -> 2.1534286 | H14: =FE_et_bio!G60 -> 2.1390965 | I14: =FE_et_bio!H60 -> 2.0965855 | J14: =FE_et_bio!I60 -> 2.0216238 | ... N14: =FE_et_bio!M60 -> 0
B15: Gazole | C15: =FE_et_bio!B61 -> 2.5206918 | D15: =FE_et_bio!C61 -> 2.5041411 | E15: =FE_et_bio!D61 -> 2.5060576 | F15: =FE_et_bio!E61 -> 2.5139977 | G15: =FE_et_bio!F61 -> 2.5098152 | H15: =FE_et_bio!G61 -> 2.4965103 | I15: =FE_et_bio!H61 -> 2.4548498 | J15: =FE_et_bio!I61 -> 2.3383392 | ... N15: =FE_et_bio!M61 -> 0
B16: GNV | C16: =FE_et_bio!B62 -> 2.7966246 | D16: =FE_et_bio!C62 -> 2.5913335 | E16: =FE_et_bio!D62 -> 2.7966246 | F16: =FE_et_bio!E62 -> 2.799424 | G16: =FE_et_bio!F62 -> 2.799424 | H16: =FE_et_bio!G62 -> 2.7714298 | I16: =FE_et_bio!H62 -> 2.6594528 | J16: =FE_et_bio!I62 -> 2.3795104 | ... N16: =FE_et_bio!M62 -> 0
B17: Electricité | C17: 0 | D17: 0 | E17: =0 -> 0 | F17: =0 -> 0 | G17: =0 -> 0 | H17: =0 -> 0 | I17: =0 -> 0 | J17: =0 -> 0 | K17: =0 -> 0 | L17: =0 -> 0 | ... N17: =0 -> 0
B19: Pop
B20: en millions hab | C20: 2018 | D20: 2019 | E20: 2020 | I20: 2025 | J20: 2030 | K20: 2035 | L20: 2040 | M20: 2045 | N20: 2050
B21: France entière | C21: 66.992 | D21: 67.146 | E21: 67.3 | I21: 68 | J21: 68.6 | K21: 69 | L21: 69.2 | M21: 69.3 | N21: 69.2
B22: Métropole | C22: 64.880941 | D22: 65.031872 | E22: 65.182804 | I22: 65.867327 | J22: 66.45135 | K22: 66.835909 | L22: 67.022388 | M22: 67.109411 | N22: 66.999161
B23: évol pop métropole / 2019 | D23: =D22/$D22 -> 1 | E23: =E22/$D22 -> 1.0023209 | I23: =I22/$D22 -> 1.0128468 | J23: =J22/$D22 -> 1.0218274 | K23: =K22/$D22 -> 1.0277408 | L23: =L22/$D22 -> 1.0306083 | M23: =M22/$D22 -> 1.0319465 | N23: =N22/$D22 -> 1.0302511
B26: I) Hypothèses sur les parts des énergies et consos des véh neufs
B28: A) Parcs roulants et immatriculations des VP
B30: Parcs et immatriculations VP | C30: observé | D30: observé | E30: observé | F30: observé | G30: observé
B31: VP | C31: 2018 | D31: 2019 | E31: 2020 | F31: 2021 | G31: 2022 | H31: 2023 | I31: 2025 | J31: 2030 | K31: 2035 | L31: 2040 | M31: 2045 | N31: 2050
B32: Ensemble VP | C32: 37.988 | D32: 38.095 | E32: 38.046 | F32: 38.461 | G32: 38.682 | H32: 37.992 | I32: =I33/$G33*$G32 -> 36.837684 | J32: =J33/$G33*$G32 -> 35.315862 | K32: =K33/$G33*$G32 -> 33.842371 | L32: =L33/$G33*$G32 -> 32.36888 | M32: =M33/$G33*$G32 -> 30.895389 | N32: =N33/$G33*$G32 -> 29.421897
B33: Parc VP (*) | C33: 37.321089 | D33: 37.548734 | E33: 37.63588 | F33: =F32*$D$33/$D$32 -> 37.909486 | G33: =G32*$D$33/$D$32 -> 38.127317 | H33: =H32*$D$33/$D$32 -> 37.447211 | I33: 36.309448 | J33: 34.809448 | K33: =J33*0.75+0.25*N33 -> 33.357086 | L33: =0.5*J33+0.5*N33 -> 31.904724 | M33: =0.25*J33+0.75*N33 -> 30.452362 | N33: 29
B34: Immatriculations VP | C34: 2.223581 | D34: 2.258277 | E34: 1.69353 | F34: 1.708675 | G34: 1.57695 | H34: 1.817346 | I34: 1.9 | J34: 1.8 | K34: 1.8 | L34: 2 | M34: 2 | N34: 1.9
B35: ratio | C35: =C33/C34 -> 16.784227 | D35: =D33/D34 -> 16.62716 | E35: =E33/E34 -> 22.223332 | F35: =F33/F34 -> 22.186481 | G35: =G33/G34 -> 24.177886 | H35: =H33/H34 -> 20.605438 | I35: =I33/I34 -> 19.110236 | J35: =J33/J34 -> 19.338582 | ... N35: =N33/N34 -> 15.263158
B36: (*) parc effectif recalé
B38: Kilométrage moyen des véhicules immatriculés en France
C39: 2018 | D39: 2019 | E39: 2020 | F39: 2021 | G39: 2022
B40: Voitures pavillon français | C40: 12518 | D40: 12511 | E40: 10205 | F40: 10945 | G40: 11957 | H40: 11693.496
B41: Diesel (y compris hybrides) | C41: 14807 | D41: 14762 | E41: 11940 | F41: 12730 | G41: 13975 | H41: 13424.866
B42: Essence | C42: 8840 | D42: 9148 | E42: 7776 | F42: 8625 | G42: 9535 | H42: 9780.6297
B43: Electricité | C43: 10317 | D43: 10939 | E43: 9165 | F43: 10166 | G43: 11353 | H43: 12791.995
B45: B) Part de marché des énergies au sein des immatriculations
B47: Evolutions des parts de marché des énergies dans les immatriculations annuelles de véhicules particuliers
C48: observé | D48: observé | E48: observé | F48: observé | G48: observé | H48: observé | I48: projeté | J48: projeté | K48: projeté | L48: projeté | M48: projeté | N48: projeté
B49: % | C49: 2018 | D49: 2019 | E49: 2020 | F49: 2021 | G49: 2022 | H49: 2023 | I49: 2025 | J49: 2030 | K49: 2035 | L49: 2040 | M49: 2045 | N49: 2050 | P49: Part de marché des véhicules particuliers neufs (%)
B50: Thermiques | C50: =C51+C52 -> 0.97909858 | D50: =D51+D52 -> 0.97236123 | E50: =E51+E52 -> 0.88918354 | F50: =F51+F52 -> 0.82040528 | G50: =G51+G52 -> 0.78769143 | H50: 0.74318044 | I50: =1-I53-I54-I55 -> 0.69 | J50: =1-J53-J54-J55 -> 0.29 | K50: =1-K53-K54-K55 -> 0 | L50: =1-L53-L54-L55 -> 0 | M50: =1-M53-M54-M55 -> 0 | N50: =1-N53-N54-N55 -> 0 | P50: % | Q50: 2022 | R50: 2025 | S50: 2030 | T50: 2035 | U50: 2040 | V50: 2045 | W50: 2050
B51: dont Essence | C51: 0.59261525 | D51: 0.63022782 | E51: 0.57224437 | F51: 0.59102989 | G51: 0.61816798 | H51: 0.63596916 | I51: =I50-I52 -> 0.64 | J51: =J50-J52 -> 0.28 | K51: 0 | L51: 0 | M51: 0 | N51: 0 | P51: Essence | Q51: 0.63596916 | R51: 0.64 | S51: 0.28 | T51: 0 | U51: 0 | V51: 0 | W51: 0
B52: dont Diesel | C52: 0.38648333 | D52: 0.34213341 | E52: 0.31693917 | F52: 0.22937539 | G52: 0.16952345 | H52: 0.10721129 | I52: 0.05 | J52: 0.01 | K52: 0 | L52: 0 | M52: 0 | N52: 0 | P52: Diesel | Q52: 0.10721129 | R52: 0.05 | S52: 0.01 | T52: 0 | U52: 0 | V52: 0 | W52: 0
B53: Electrique | C53: 0.014266627 | D53: 0.019318711 | E53: 0.066553294 | F53: 0.096933004 | G53: 0.13149688 | H53: 0.16721912 | I53: 0.26 | J53: 0.66 | K53: 1 | L53: 1 | M53: 1 | N53: 1 | P53: Electrique | Q53: 0.16721912 | R53: 0.26 | S53: 0.66 | T53: 1 | U53: 1 | V53: 1 | W53: 1
B54: Hybride rechargeable | C54: 0.0066347932 | D54: 0.0083200599 | E54: 0.044263166 | F54: 0.082661712 | G54: 0.080811693 | H54: 0.089600439 | I54: 0.05 | J54: 0.05 | K54: 0 | L54: 0 | M54: 0 | N54: 0 | P54: Hybride rechargeable | Q54: 0.089600439 | R54: 0.05 | S54: 0.05 | T54: 0 | U54: 0 | V54: 0 | W54: 0
B55: H2 | C55: 0 | D55: 0 | E55: =0 -> 0 | F55: =0 -> 0 | G55: =0 -> 0 | H55: 0 | I55: 0 | J55: 0 | K55: 0 | L55: 0 | M55: 0 | N55: 0 | P55: Hydrogène | Q55: 0 | R55: 0 | S55: 0 | T55: 0 | U55: 0 | V55: 0 | W55: 0
B56: % diesel au sein des thermiques | C56: =C52/C50 -> 0.39473383 | D56: =D52/D50 -> 0.35185834 | E56: =E52/E50 -> 0.35643842 | F56: =F52/F50 -> 0.2795879 | G56: =G52/G50 -> 0.21521555 | H56: =H52/H50 -> 0.1442601 | I56: =I52/I50 -> 0.072463768 | J56: =J52/J50 -> 0.034482759 | P56: Périmètre hexagone
B57: total VE+VHR | C57: =C53+C54 -> 0.02090142 | D57: =D53+D54 -> 0.027638771 | E57: =E53+E54 -> 0.11081646 | F57: =F53+F54 -> 0.17959472 | G57: =G53+G54 -> 0.21230857 | H57: =H53+H54 -> 0.25681956 | I57: =I53+I54 -> 0.31 | J57: =J53+J54 -> 0.71 | ... N57: =N53+N54 -> 1
B58: check | C58: =SUM(C51:C55) -> 1 | D58: =SUM(D51:D55) -> 1 | E58: =SUM(E51:E55) -> 1 | F58: =SUM(F51:F55) -> 1 | G58: =SUM(G51:G55) -> 1 | H58: =SUM(H51:H55) -> 1 | I58: =SUM(I51:I55) -> 1 | J58: =SUM(J51:J55) -> 1 | ... N58: =SUM(N51:N55) -> 1
B60: nb véh électriques | C60: =C$34*C53*1000 -> 31.723 | D60: =D$34*D53*1000 -> 43.627 | E60: =E$34*E53*1000 -> 112.71 | F60: =F$34*F53*1000 -> 165.627 | G60: =G$34*G53*1000 -> 207.364 | H60: =H$34*H53*1000 -> 303.895 | I60: =I$34*I53*1000 -> 494 | J60: =J$34*J53*1000 -> 1188 | ... N60: =N$34*N53*1000 -> 1900
B61: nb VHR | C61: =C$34*C54*1000 -> 14.753 | D61: =D$34*D54*1000 -> 18.789 | E61: =E$34*E54*1000 -> 74.961 | F61: =F$34*F54*1000 -> 141.242 | G61: =G$34*G54*1000 -> 127.436 | H61: =H$34*H54*1000 -> 162.835 | I61: =I$34*I54*1000 -> 95 | J61: =J$34*J54*1000 -> 90 | ... N61: =N$34*N54*1000 -> 0
B62: nb véh élec et VHR | C62: =C60+C61 -> 46.476 | D62: =D60+D61 -> 62.416 | E62: =E60+E61 -> 187.671 | F62: =F60+F61 -> 306.869 | G62: =G60+G61 -> 334.8 | H62: =H60+H61 -> 466.73 | I62: =I60+I61 -> 589 | J62: =J60+J61 -> 1278 | ... N62: =N60+N61 -> 1900
B64: C) Consommations des VP (véhicules neufs)
B66: Evolution des consommations unitaires des véhicules particuliers neufs
C67: estimations | D67: estimations | E67: estimations | F67: estimations | G67: estimations | H67: estimations | P67: Consommation moyenne réelle des véhicules particuliers neufs
C68: 2018 | D68: 2019 | E68: 2020 | F68: 2021 | G68: 2022 | H68: 2023 | I68: 2025 | J68: 2030 | K68: 2035 | L68: 2040 | M68: 2045 | N68: 2050 | O68: 2030/2019 | Q68: 2023 | R68: 2025 | S68: 2030 | T68: 2035 | U68: 2040 | V68: 2045 | W68: 2050
B69: Essence (l/100 km) | C69: 6.22 | D69: 6.22 | E69: 6 | F69: 5.8 | G69: 5.8 | H69: 5.7 | I69: 5.6 | J69: 5.2 | K69: - | L69: - | M69: - | N69: - | O69: =J69/H69-1 -> -0.087719298 | P69: Essence (L / 100 km) | Q69: 5.7 | R69: 5.6 | S69: 5.2 | T69: - | U69: - | V69: - | W69: -
B70: Diesel (l/100 km) | C70: 5.35 | D70: 5.35 | E70: 5.35 | F70: 5.35 | G70: 5.3 | H70: 5.2 | I70: 5.2 | J70: 5.2 | K70: - | L70: - | M70: - | N70: - | O70: =J70/H70-1 -> 0 | P70: Diesel (L / 100 km) | Q70: 5.2 | R70: 5.2 | S70: 5.2 | T70: - | U70: - | V70: - | W70: -
B71: VE (kWh/100 km) | C71: 17.8 | D71: 17.8 | E71: 17.4 | F71: =E71 -> 17.4 | G71: =F71 -> 17.4 | H71: =G71 -> 17.4 | I71: 17.2 | J71: 17 | K71: 16.5 | L71: 16 | M71: 15.5 | N71: 15 | P71: Véhicules électriques (kWh / 100 km) | Q71: 17.4 | R71: 17.2 | S71: 17 | T71: 16.5 | U71: 16 | V71: 15.5 | W71: 15
B72: gCO2 moy | C72: =(C69*2.342*C51+2.71*C70*C52+2.342*C54*(1-C80))*10 -> 142.47074 | D72: =(D69*2.342*D51+2.71*D70*D52+2.342*D54*(1-D80))*10 -> 141.60587 | E72: =(E69*2.342*E51+2.71*E70*E52+2.342*E54*(1-E80))*10 -> 127.39985 | F72: =(F69*2.342*F51+2.71*F70*F52+2.342*F54*(1-F80))*10 -> 115.47507 | G72: =(G69*2.342*G51+2.71*G70*G52+2.342*G54*(1-G80))*10 -> 110.21073 | H72: =(H69*2.342*H51+2.71*H70*H52+2.342*H54*(1-H80))*10 -> 102.10472 | I72: =(I69*2.342*I51+2.71*I70*I52+2.342*I54*(1-I80))*10 -> 92.15428 | J72: =(J69*2.342*J51+2.71*J70*J52+2.342*J54*(1-J80))*10 -> 36.67972
B73: objectif | I73: =I72/123-1 -> -0.25077821 | J73: =J72/123-1 -> -0.70179089
B75: effi moy | C75: =(C69*C51+C52*C70)/(C51+C52) -> 5.8765816 | D75: =(D69*D51+D52*D70)/(D51+D52) -> 5.9138832 | E75: =(E69*E51+E52*E70)/(E51+E52) -> 5.768315 | F75: =(F69*F51+F52*F70)/(F51+F52) -> 5.6741854 | G75: =(G69*G51+G52*G70)/(G51+G52) -> 5.6923922 | H75: =(H69*H51+H52*H70)/(H51+H52) -> 5.6278699 | I75: =(I69*I51+I52*I70)/(I51+I52) -> 5.5710145 | J75: =(J69*J51+J52*J70)/(J51+J52) -> 5.2
B76: gco2 | C76: =(C51*C69*FE_et_bio!$E$7+VP!C70*FE_et_bio!$E$6*C52)/(C51+C52)*10 -> 143.97261 | D76: =(D51*D69*FE_et_bio!$E$7+VP!D70*FE_et_bio!$E$6*D52)/(D51+D52)*10 -> 144.00428 | E76: =(E51*E69*FE_et_bio!$E$7+VP!E70*FE_et_bio!$E$6*E52)/(E51+E52)*10 -> 140.71707 | F76: =(F51*F69*FE_et_bio!$E$7+VP!F70*FE_et_bio!$E$6*F52)/(F51+F52)*10 -> 137.03991 | G76: =(G51*G69*FE_et_bio!$E$7+VP!G70*FE_et_bio!$E$6*G52)/(G51+G52)*10 -> 136.17171 | H76: =(H51*H69*FE_et_bio!$E$7+VP!H70*FE_et_bio!$E$6*H52)/(H51+H52)*10 -> 133.25632 | I76: =(I51*I69*FE_et_bio!$E$7+VP!I70*FE_et_bio!$E$6*I52)/(I51+I52)*10 -> 130.58106 | J76: =(J51*J69*FE_et_bio!$E$7+VP!J70*FE_et_bio!$E$6*J52)/(J51+J52)*10 -> 121.25826
B77: gco2 theo | C77: =C76/$C$82 -> 137.11677 | D77: =D76/$C$82 -> 137.14694 | E77: =E76/$C$82 -> 134.01626 | F77: =F76/$C$82 -> 130.5142 | G77: =G76/$C$82 -> 129.68734 | H77: =H76/$C$82 -> 126.91078 | I77: =I76/$C$82 -> 124.36292 | J77: =J76/$C$82 -> 115.48406
B79: hypothèse | C79: Tous les VHR sont des essences rechargeables
B80: % de circulation en mode électrique | C80: 0.3
B82: ratio wltp | C82: 1.05
C83: 2018 | D83: 2019 | E83: 2020 | F83: 2021 | G83: 2022 | H83: 2023 | I83: 2025 | J83: 2030 | K83: 2035 | L83: 2040 | M83: 2045 | N83: 2050
B84: gCO2 théorique WLTP | C84: =C72/$C$82 -> 135.68642 | D84: =D72/$C$82 -> 134.86273 | E84: =E72/$C$82 -> 121.33319 | F84: =F72/$C$82 -> 109.97625 | G84: =G72/$C$82 -> 104.9626 | H84: =H72/$C$82 -> 97.242593 | I84: =I72/$C$82 -> 87.765981 | J84: =J72/$C$82 -> 34.933067 | ... N84: =N72/$C$82 -> 0
I85: =I84/$F84-1 -> -0.20195516 | J85: =J84/$F84-1 -> -0.68235809
C87: 2018 | D87: 2019 | E87: 2020 | F87: 2021 | G87: 2022 | H87: 2023 | I87: 2025 | J87: 2030 | K87: 2035 | L87: 2040 | M87: 2045 | N87: 2050
B88: gCO2 théorique NEDC | C88: 111.8
B91: gCO2 théorique WLTP | C91: 2018 | D91: 2019 | E91: 2020 | F91: 2021 | G91: 2022 | H91: 2023 | I91: 2025 | J91: 2030 | K91: 2035 | L91: 2040 | M91: 2045 | N91: 2050
A92: observé | B92: moyenne | C92: 138.71467 | D92: 138.39433 | E92: 120.70833 | F92: 108.51667 | G92: 102.94167 | H92: 96.2
B93: moyenne hors élec | C93: =C92/(1-C53) -> 140.7223 | D93: =D92/(1-D53) -> 141.1206 | E93: =E92/(1-E53) -> 129.31465 | F93: =F92/(1-F53) -> 120.16458 | G93: =G92/(1-G53) -> 118.52769 | H93: =H92/(1-H53) -> 115.51658
B94: moyennehors elec et vhr | C94: =C93/(C51+C52+C54*0.3)*(C51+C52+C54) -> 141.38846 | D94: =D93/(D51+D52+D54*0.3)*(D51+D52+D54) -> 141.96369 | E94: =E93/(E51+E52+E54*0.3)*(E51+E52+E54) -> 133.75441 | F94: =F93/(F51+F52+F54*0.3)*(F51+F52+F54) -> 128.39113 | G94: =G93/(G51+G52+G54*0.3)*(G51+G52+G54) -> 126.78561 | H94: =H93/(H51+H52+H54*0.3)*(H51+H52+H54) -> 124.92524
B95: passage au réel | C95: =C94*$C$82 -> 148.45788 | D95: =D94*$C$82 -> 149.06188 | E95: =E94*$C$82 -> 140.44213 | F95: =F94*$C$82 -> 134.81068 | G95: =G94*$C$82 -> 133.12489 | H95: =H94*$C$82 -> 131.1715
B96: passage au réel ES | C96: =C95/$C$6/10 -> 6.3383347 | D96: =D95/$C$6/10 -> 6.3641218 | E96: =E95/$C$6/10 -> 5.9961059 | F96: =F95/$C$6/10 -> 5.7556743 | G96: =G95/$C$6/10 -> 5.6837003 | H96: =H95/$C$6/10 -> 5.6003012
A97: observé | B97: essence yc vhnr | G97: 125.8
A98: observé | B98: essence vhr | G98: 34.6
A99: observé | B99: go | G99: 130.3
A100: observé | B100: moy | G100: =G97*G51+G52*G99+G98*G54 -> 102.65052
B102: II) Parts des énergies et consommations du parc roulant
B104: Les chiffrages du parc roulant se déduisent des hypothèses qui précèdent
B106: B1) Parts de marché des énergies sur le parc roulant (sur nbr de véh du parc roulant puis sur les km parcourus par le parc roulant)
B108: Parts de marché des énergies au sein du parc roulant (en nb de véh)
C109: 2018 | D109: 2019 | E109: 2020 | F109: 2021 | G109: 2022 | H109: 2023 | I109: 2025 | J109: 2030 | K109: 2035 | L109: 2040 | M109: 2045 | N109: 2050 | P109: var 2030 | Q109: Parc roulant des véhicules particuliers (%)
B110: Thermiques | C110: 0.94464872 | D110: 0.94464872 | E110: 0.94464872 | F110: 0.94464872 | G110: 0.94464872 | H110: 0.9687224 | I110: =I111+I112 -> 0.94362992 | J110: =J111+J112 -> 0.81609112 | K110: =K111+K112 -> 0.59062219 | L110: =L111+L112 -> 0.32904078 | M110: =M111+M112 -> 0.10958978 | N110: =N111+N112 -> 5.8286863e-17 | Q110: % | R110: 2023 | S110: 2025 | T110: 2030 | U110: 2035 | V110: 2040 | W110: 2045 | X110: 2050
B111: Essence | C111: 0.37956723 | D111: 0.39572122 | E111: 0.40908374 | F111: 0.4211019 | G111: 0.43294039 | H111: 0.44430437 | I111: 0.47621951 | J111: 0.56513921 | K111: 0.50087312 | L111: 0.31025145 | M111: 0.10581082 | N111: 5.6276971e-17 | P111: =J111-D111 -> 0.16941799 | Q111: Essence | R111: 0.44430437 | S111: 0.47471338 | T111: 0.56011176 | U111: 0.49568266 | V111: 0.30659317 | W111: 0.10581082 | X111: 5.255618e-17
B112: Diesel | C112: 0.61632621 | D112: 0.59902874 | E112: 0.5831362 | F112: 0.56496191 | G112: 0.54513727 | H112: 0.52441804 | I112: 0.46741041 | J112: 0.25095191 | K112: 0.089749074 | L112: 0.018789335 | M112: 0.0037789578 | N112: 2.0098918e-18 | P112: =J112-D112 -> -0.34807683 | Q112: Diesel | R112: 0.52441804 | S112: 0.46758184 | T112: 0.25135815 | U112: 0.090110211 | V112: 0.018914074 | W112: 0.0037789578 | X112: 1.8770064e-18
B113: Electrique | C113: 0.0025271138 | D113: 0.0032812705 | E113: 0.0049151028 | F113: 0.0081121136 | G113: 0.012693242 | H113: 0.018439427 | I113: 0.038450534 | J113: 0.15185871 | K113: 0.36955229 | L113: 0.64528401 | M113: 0.87880612 | N113: 0.99716364 | P113: =J113-D113 -> 0.14857744 | Q113: Electrique | R113: 0.018439427 | S113: 0.038450534 | T113: 0.15185871 | U113: 0.36955229 | V113: 0.64528401 | W113: 0.87880612 | X113: 0.99716364
B114: Hybride rechargeable | C114: 0.0015794461 | D114: 0.0019687623 | E114: 0.002864953 | F114: 0.0058240815 | G114: 0.0092290988 | H114: 0.012838168 | I114: 0.017919549 | J114: 0.032050176 | K114: 0.039825515 | L114: 0.025675202 | M114: 0.011604105 | N114: 0.0028363612 | P114: =J114-D114 -> 0.030081414 | Q114: Hybride rechargeable | R114: 0.012838168 | S114: 0.019254241 | T114: 0.036671391 | U114: 0.044654834 | V114: 0.029208744 | W114: 0.011604105 | X114: 0.0028363612
B115: H2 | C115: =0 -> 0 | D115: =0 -> 0 | E115: =0 -> 0 | F115: =0 -> 0 | G115: =0 -> 0 | H115: =0 -> 0 | I115: 0 | J115: 0 | K115: 0 | L115: 0 | M115: 0 | N115: 0 | Q115: Hydrogène | R115: 0 | S115: 0 | T115: 0 | U115: 0 | V115: 0 | W115: 0 | X115: 0
B116: Ensemble | C116: =SUM(C111:C115) -> 1 | D116: =SUM(D111:D115) -> 1 | E116: =SUM(E111:E115) -> 1 | F116: =SUM(F111:F115) -> 1 | G116: =SUM(G111:G115) -> 1 | H116: 1 | I116: 1 | J116: 1 | K116: 1 | L116: 1 | M116: 1 | N116: 1 | R116: =SUM(R111:R115) -> 1 | S116: =SUM(S111:S115) -> 1 | T116: =SUM(T111:T115) -> 1 | U116: =SUM(U111:U115) -> 1 | V116: =SUM(V111:V115) -> 1 | W116: =SUM(W111:W115) -> 1 | X116: =SUM(X111:X115) -> 1
I117: =SUM(I111:I114) -> 1 | J117: =SUM(J111:J114) -> 1 | K117: =SUM(K111:K114) -> 1 | L117: =SUM(L111:L114) -> 1 | M117: =SUM(M111:M114) -> 1 | N117: =SUM(N111:N114) -> 1 | R117: 1
B118: % de circulation en mode électrique | C118: 0.7
B121: Parts de marché des énergies au sein des VP-km
C122: 2018 | D122: 2019 | E122: 2020 | F122: 2021 | G122: 2022 | H122: 2023 | I122: 2025 | J122: 2030 | K122: 2035 | L122: 2040 | M122: 2045 | N122: 2050 | P122: var 2030
B123: Thermique | C123: =C124+C125 -> 0.99592886 | D123: =D124+D125 -> 0.99467065 | E123: =E124+E125 -> 0.99188694 | F123: =F124+F125 -> 0.98406951 | G123: =G124+G125 -> 0.97342412 | H123: 0.95911083 | I123: =I124+I125 -> 0.93522181 | J123: =J124+J125 -> 0.80930411 | K123: =K124+K125 -> 0.59062219 | L123: =L124+L125 -> 0.32904078 | M123: =M124+M125 -> 0.10958978 | N123: =N124+N125 -> 5.8286863e-17
B124: Essence | C124: 0.26698093 | D124: 0.28778512 | E124: 0.30960482 | F124: 0.32705769 | G124: 0.33670108 | H124: 0.3575345 | I124: 0.39969658 | J124: 0.54533085 | K124: 0.50087312 | L124: 0.31025145 | M124: 0.10581082 | N124: 5.6276971e-17 | P124: =J124-D124 -> 0.25754573
B125: Diesel | C125: 0.72894793 | D125: 0.70688553 | E125: 0.68228213 | F125: 0.65701183 | G125: 0.63672304 | H125: 0.60157633 | I125: 0.53552524 | J125: 0.26397326 | K125: 0.089749074 | L125: 0.018789335 | M125: 0.0037789578 | N125: 2.0098918e-18 | P125: =J125-D125 -> -0.44291227
B126: Electrique | C126: 0.0020393653 | D126: 0.0028268103 | E126: 0.0043813812 | F126: 0.0075106964 | G126: 0.012026225 | H126: 0.020171646 | I126: 0.039399232 | J126: 0.15452252 | K126: 0.36955229 | L126: 0.64528401 | M126: 0.87880612 | N126: 0.99716364 | P126: =J126-D126 -> 0.15169571
...

Sheet VUL
B1: 1 tep | C1: 41.868 | F1: GJ | G1: =C1/3.6 -> 11.63 | I1: MWh
B3: FE du fossile sans intégration des parts de bio et avec contenu élec à 0 (pour calcul de l'évolution des émissions théoriques des véh neufs)
B4: FE du fossile | C4: FE par udp | E4: Energie par udp
B5: Essence | C5: 2.3422222 | D5: kgCO2/L | E5: 8.8888889 | F5: kWh/L
B6: Gazole | C6: 2.71 | D6: kgCO2/L | E6: 10 | F6: kWh/L
B7: Kérosène | C7: 2.4583889 | D7: kgCO2/L | E7: 9.4444444 | F7: kWh/L
B8: GNV | C8: 2.8027171 | D8: kgCO2/kg | E8: 13.8 | F8: kWh/kg
B9: Electricité | C9: 0
B11: FE des carburants avec intégration des parts de bio et avec facteur émissions de l'élec nul (pour calcul roulant)
B12: FE du fossile | C12: 2018 | D12: 2019 | E12: 2020 | F12: 2021 | G12: 2022 | H12: 2023 | I12: 2025 | J12: 2030 | K12: 2035 | L12: 2040 | M12: 2045 | N12: 2050
B13: Essence | C13: =FE_et_bio!B60 -> 2.1715472 | D13: =FE_et_bio!C60 -> 2.1503726 | E13: =FE_et_bio!D60 -> 2.1622273 | F13: =FE_et_bio!E60 -> 2.1608105 | G13: =FE_et_bio!F60 -> 2.1534286 | H13: =FE_et_bio!G60 -> 2.1390965 | I13: =FE_et_bio!H60 -> 2.0965855 | J13: =FE_et_bio!I60 -> 2.0216238 | ... N13: =FE_et_bio!M60 -> 0
B14: Gazole | C14: =FE_et_bio!B61 -> 2.5206918 | D14: =FE_et_bio!C61 -> 2.5041411 | E14: =FE_et_bio!D61 -> 2.5060576 | F14: =FE_et_bio!E61 -> 2.5139977 | G14: =FE_et_bio!F61 -> 2.5098152 | H14: =FE_et_bio!G61 -> 2.4965103 | I14: =FE_et_bio!H61 -> 2.4548498 | J14: =FE_et_bio!I61 -> 2.3383392 | ... N14: =FE_et_bio!M61 -> 0
B15: GNV | C15: =FE_et_bio!B62 -> 2.7966246 | D15: =FE_et_bio!C62 -> 2.5913335 | E15: =FE_et_bio!D62 -> 2.7966246 | F15: =FE_et_bio!E62 -> 2.799424 | G15: =FE_et_bio!F62 -> 2.799424 | H15: =FE_et_bio!G62 -> 2.7714298 | I15: =FE_et_bio!H62 -> 2.6594528 | J15: =FE_et_bio!I62 -> 2.3795104 | ... N15: =FE_et_bio!M62 -> 0
B16: Electricité | C16: 0 | D16: 0 | E16: 0 | F16: 1 | G16: 2 | H16: 3 | I16: 0 | J16: 0 | K16: 0 | L16: 0 | M16: 0 | N16: 0
B18: VUL-AME 2021
B20: I) Données sur les parts des énergies et consos des véh neufs
B22: A) Circulations, parcs roulants et immatriculations des VUL | P22: Immatriculations de véhicules (millions)
P23: Millions de véhicules | Q23: 2022 | R23: 2025 | S23: 2030 | T23: 2035 | U23: 2040 | V23: 2045 | W23: 2050
B24: Parc et immatriculations | P24: Véhicules particuliers | Q24: 1.58 | R24: 1.9 | S24: 1.8 | T24: 1.8 | U24: 2 | V24: 2 | W24: 1.9
P25: Véhicules utilitaires légers | Q25: 0.36 | R25: 0.36 | S25: 0.36 | T25: 0.36 | U25: 0.36 | V25: 0.36 | W25: 0.36
C26: 2018 | D26: 2019 | E26: 2020 | F26: 2021 | G26: 2022 | H26: 2023 | I26: 2025 | J26: 2030 | K26: 2035 | L26: 2040 | M26: 2045 | N26: 2050 | P26: Poids lourds | Q26: 0.05 | R26: 0.04 | S26: 0.04 | T26: 0.04 | U26: 0.04 | V26: 0.04 | W26: 0.04
B27: Parc VUL | C27: 6100.0734 | D27: 6091.1969 | E27: 6039.2158 | F27: 6161.463 | G27: 6222.0553 | H27: 6264.0927 | I27: 6200 | J27: 6138.2475 | K27: 6077.1101 | L27: 6016.5816 | M27: 5956.6559 | N27: 5897.3272 | P27: Bus et car | Q27: 0.01 | R27: 0.01 | S27: 0.01 | T27: 0.01 | U27: 0.01 | V27: 0.01 | W27: 0.01
B28: Immatriculations VUL | C28: 471.132 | D28: 490.256 | E28: 411.763 | F28: 444.99 | G28: 358.893 | H28: 390.471 | I28: 390 | J28: 410 | K28: 420 | L28: 420 | M28: 420 | N28: 420 | P28: Périmètre hexagone
C29: =C27/C28 -> 12.947695 | D29: =D27/D28 -> 12.424523 | E29: =E27/E28 -> 14.666728 | F29: =F27/F28 -> 13.846295 | G29: =G27/G28 -> 17.336798 | H29: =H27/H28 -> 16.042402 | I29: =I27/I28 -> 15.897436 | J29: =J27/J28 -> 14.971335 | ... N29: =N27/N28 -> 14.041255
P30: Parc de véhicules (millions)
B31: Kilométrage moyen des véhicules immatriculés en France | P31: Millions de véhicules | Q31: 2022 | R31: 2025 | S31: 2030 | T31: 2035 | U31: 2040 | V31: 2045 | W31: 2050
C32: 2018 | D32: 2019 | E32: 2020 | F32: 2021 | G32: 2022 | P32: Véhicules particuliers | Q32: 38.1 | R32: 36.3 | S32: 34.8 | T32: 33.4 | U32: 31.9 | V32: 30.5 | W32: 29
B33: Véhicules utilitaires légers pavillon français | C33: 13942 | D33: 14173 | E33: 12691 | F33: 13596 | G33: 13793 | P33: Véhicules utilitaires légers | Q33: 6.4 | R33: 6.4 | S33: 6.4 | T33: 6.4 | U33: 6.4 | V33: 6.4 | W33: 6.4
B34: Diesel (y compris hybrides) | C34: 14321 | D34: 14529 | E34: 12987 | F34: 13900 | G34: 14103 | P34: Poids lourds | Q34: 0.6 | R34: 0.6 | S34: 0.6 | T34: 0.6 | U34: 0.6 | V34: 0.6 | W34: 0.6
B35: Essence et autres énergies | C35: 7709 | D35: 7766 | E35: 6977 | F35: 7517 | G35: 7447 | P35: Bus et car | Q35: 0.1 | R35: 0.1 | S35: 0.1 | T35: 0.1 | U35: 0.1 | V35: 0.1 | W35: 0.1
P36: Périmètre hexagone
Q37: =Q32/Q24 -> 24.113924 | R37: =R32/R24 -> 19.105263 | S37: =S32/S24 -> 19.333333 | T37: =T32/T24 -> 18.555556 | U37: =U32/U24 -> 15.95 | V37: =V32/V24 -> 15.25 | W37: =W32/W24 -> 15.263158
B38: B) Parts de marchés des énergies | C38: véhicules neufs | Q38: =Q33/Q25 -> 17.777778 | R38: =R33/R25 -> 17.777778 | S38: =S33/S25 -> 17.777778 | T38: =T33/T25 -> 17.777778 | U38: =U33/U25 -> 17.777778 | V38: =V33/V25 -> 17.777778 | W38: =W33/W25 -> 17.777778
Q39: =Q34/Q26 -> 12 | R39: =R34/R26 -> 15 | S39: =S34/S26 -> 15 | T39: =T34/T26 -> 15 | U39: =U34/U26 -> 15 | V39: =V34/V26 -> 15 | W39: =W34/W26 -> 15
B40: Evolutions des parts de marché des énergies dans les immatriculations annuelles
C41: observé | D41: observé | E41: observé | P41: Part de marché des véhicules utilitaires légers neufs (%)
C42: 2018 | D42: 2019 | E42: 2020 | F42: 2021 | G42: 2022 | H42: 2023 | I42: 2025 | J42: 2030 | K42: 2035 | L42: 2040 | M42: 2045 | N42: 2050 | P42: % | Q42: 2023 | R42: 2025 | S42: 2030 | T42: 2035 | U42: 2040 | V42: 2045 | W42: 2050
B43: Thermique | C43: 0.98047005 | D43: 0.98069605 | E43: 0.97294705 | F43: 0.96439759 | G43: 0.94759254 | H43: 0.91697207 | I43: 0.83 | J43: 0.477 | K43: 0 | L43: 2.7755576e-17 | M43: 2.7755576e-17 | N43: 2.7755576e-17 | P43: Thermiques | Q43: 0.91697207 | R43: 0.83 | S43: 0.477 | T43: 0 | U43: 2.7755576e-17 | V43: 2.7755576e-17 | W43: 2.7755576e-17
B44: Gaz | C44: 0.0019873547 | D44: 0.0026571989 | E44: 0.0041453671 | F44: 0.0058292397 | G44: 0.0039996998 | H44: 0.0045304261 | I44: 0.003 | J44: 0.003 | K44: 0 | L44: 0 | M44: 0 | N44: 0 | P44: GNV | Q44: 0.0045304261 | R44: 0.003 | S44: 0.003 | T44: 0 | U44: 0 | V44: 0 | W44: 0
B45: Electrique | C45: 0.017542595 | D45: 0.01664675 | E45: 0.022907585 | F45: 0.029773168 | G45: 0.048407764 | H45: 0.078497507 | I45: 0.167 | J45: 0.51 | K45: 0.99 | L45: 0.99 | M45: 0.99 | N45: 0.99 | P45: Electrique | Q45: 0.078497507 | R45: 0.167 | S45: 0.51 | T45: =1-T46 -> 0.99 | U45: =1-U46 -> 0.99 | V45: =1-V46 -> 0.99 | W45: =1-W46 -> 0.99
B46: H2 | I46: 0 | J46: 0.01 | K46: 0.01 | L46: 0.01 | M46: 0.01 | N46: 0.01 | P46: H2 | R46: 0 | S46: =1% -> 0.01 | T46: =1% -> 0.01 | U46: =1% -> 0.01 | V46: =1% -> 0.01 | W46: =1% -> 0.01
C47: =SUM(C43:C46) -> 1 | D47: =SUM(D43:D46) -> 1 | E47: =SUM(E43:E46) -> 1 | F47: =SUM(F43:F46) -> 1 | G47: =SUM(G43:G46) -> 1 | H47: =SUM(H43:H46) -> 1 | I47: =SUM(I43:I46) -> 1 | J47: =SUM(J43:J46) -> 1 | ... N47: =SUM(N43:N46) -> 1
B50: C) Consommations des VUL | C50: véhicules neufs
P51: Consommation moyenne réelle des véhicules utilitaires légers neufs
C52: 2018 | D52: 2019 | E52: 2020 | F52: 2021 | G52: 2022 | H52: 2023 | I52: 2025 | J52: 2030 | K52: 2035 | L52: 2040 | M52: 2045 | N52: 2050 | Q52: 2023 | R52: 2025 | S52: 2030 | T52: 2035 | U52: 2040 | V52: 2045 | W52: 2050
B53: Thermique (l/100km) | C53: =C66 -> 7.295745 | D53: =D66 -> 7.2840785 | E53: 7.2 | F53: 7.1 | G53: 7 | H53: 7 | I53: 6.6165032 | J53: 6.2682662 | K53: 6.0941477 | L53: - | M53: - | N53: - | O53: =J53/H53-1 -> -0.1045334 | P53: Thermique (l/100km) | Q53: 7 | R53: 6.6165032 | S53: 6.2682662 | T53: 6.0941477 | U53: - | V53: - | W53: -
B54: GNV (kg/100km) | C54: 6.1842598 | D54: 6.1800007 | E54: 5.9200292 | F54: =E54 -> 5.9200292 | G54: =F54 -> 5.9200292 | H54: 5.9200292 | I54: 5.6240277 | J54: 5.3280263 | K54: 5.1800255 | L54: - | M54: - | N54: - | O54: =J54/H54-1 -> -0.1 | P54: GNV (kg/100km) | Q54: 5.9200292 | R54: 5.6240277 | S54: 5.3280263 | T54: 5.1800255 | U54: - | V54: - | W54: -
B55: Electrique (kWh/100km) | C55: 24.5 | D55: 24.5 | E55: 24.5 | F55: 24.5 | G55: 24.5 | H55: 24.5 | I55: 24.08 | J55: 23.8 | K55: 23.1 | L55: 22.4 | M55: 21.7 | N55: 21 | O55: =J55/H55-1 -> -0.028571429 | P55: Electrique (kWh/100km) | Q55: 24.5 | R55: 24.08 | S55: 23.8 | T55: 23.1 | U55: 22.4 | V55: 21.7 | W55: 21
B56: H2 | C56: 1.55 | D56: 1.55 | E56: 1.55 | F56: =E56 -> 1.55 | G56: =F56 -> 1.55 | H56: =G56 -> 1.55 | I56: 1.39 | J56: 1.23 | K56: =1.2 -> 1.2 | L56: =1.2 -> 1.2 | M56: =1.2 -> 1.2 | N56: =1.2 -> 1.2 | O56: =J56/H56-1 -> -0.20645161 | P56: H2 (kg/100km) | Q56: 1.55 | R56: 1.39 | S56: 1.23 | T56: 1.15 | U56: 1.07 | V56: 1.035 | W56: 1
B57: baisse H2 / 2023 | H57: =H56/$H$56-1 -> 0 | I57: =I56/$H$56-1 -> -0.10322581 | J57: =J56/$H$56-1 -> -0.20645161 | K57: =K56/$H$56-1 -> -0.22580645 | L57: =L56/$H$56-1 -> -0.22580645 | M57: =M56/$H$56-1 -> -0.22580645 | N57: =N56/$H$56-1 -> -0.22580645
B59: coeft passage | C59: 1.04
B60: Emissions théoriques observées pour le neuf
B61: gCO2/véh-km | C61: 2018 | D61: 2019 | E61: 2020 | F61: 2021 | G61: 2022 | H61: 2023 | I61: 2025 | J61: 2030 | K61: 2035 | L61: 2040 | M61: 2045 | N61: 2050
B62: NEDC | C62: 145.2 | D62: 145.1 | E62: 139
B63: WLTP | C63: =C62*$E63/$E62 -> 186.77525 | D63: =D62*$E63/$E62 -> 186.64662 | E63: 178.8 | F63: 179.7 | G63: 177 | H63: 171.1
B64: WLTP hors élec | C64: =C63/(C43+C44) -> 190.11028 | D64: =D63/(D43+D44) -> 189.80628 | E64: =E63/(E43+E44) -> 182.9919 | F64: =F63/(F43+F44) -> 185.21442 | G64: =G63/(G43+G44) -> 186.00404 | H64: =H63/(H43+H44) -> 185.67503
B65: réel hors élec | C65: =C64*$C$59 -> 197.71469 | D65: =D64*$C$59 -> 197.39853 | E65: =E64*$C$59 -> 190.31158 | F65: =F64*$C$59 -> 192.623 | G65: =G64*$C$59 -> 193.4442 | H65: =H64*$C$59 -> 193.10203
B66: réel hors élec | C66: =C65/$C$6/10 -> 7.295745 | D66: =D65/$C$6/10 -> 7.2840785 | E66: =E65/$C$6/10 -> 7.0225675 | F66: =F64/$C$6/10*$C$59 -> 7.1078597 | G66: =G64/$C$6/10*$C$59 -> 7.1381624 | H66: =H64/$C$6/10*$C$59 -> 7.1255361
B68: Calcul émissions GES immat à partir des consos
B69: gCO2/véh-km | C69: 2018 | D69: 2019 | E69: 2020 | F69: 2021 | G69: 2022 | H69: 2023 | I69: 2025 | J69: 2030 | K69: 2035 | L69: 2040 | M69: 2045 | N69: 2050
B70: Diesel | C70: =C53*$C6*10 -> 197.71469 | D70: =D53*$C6*10 -> 197.39853 | E70: =E53*$C6*10 -> 195.12 | F70: =F53*$C6*10 -> 192.41 | G70: =G53*$C6*10 -> 189.7 | H70: =H53*$C6*10 -> 189.7 | I70: =I53*$C6*10 -> 179.30724 | J70: =J53*$C6*10 -> 169.87001 | ... N70: =N53*$C6*10 -> #VALUE!
B71: Electrique | C71: 0 | D71: 0 | E71: =0 -> 0 | F71: =0 -> 0 | G71: =0 -> 0 | H71: =0 -> 0 | I71: 0 | J71: 0 | K71: 0 | L71: 0 | M71: 0 | N71: 0
B72: VUL moyen | C72: =(C70*C43) -> 193.85333 | D72: =(D70*D43) -> 193.58796 | E72: =(E70*E43) -> 189.84143 | F72: =(F70*F43) -> 185.55974 | G72: =(G70*G43) -> 179.7583 | H72: =(H70*H43) -> 173.9496 | I72: =(I70*I43) -> 148.82501 | J72: =(J70*J43) -> 81.027997 | ... N72: =(N70*N43) -> #VALUE!
B73: Baisse par rapport à 2020 | I73: =I72/$F72-1 -> -0.19796716 | J73: =J72/$F72-1 -> -0.56333202
B78: Traduction dans le parc roulant
B80: B) Parts de marché des énergies sur le parc roulant
B82: Evolution des parts de marché des énergie parc roulant | P82: Parc roulant des véhicules utilitaires légers (%)
C83: 2018 | D83: 2019 | E83: 2020 | F83: 2021 | G83: 2022 | H83: 2023 | I83: 2025 | J83: 2030 | K83: 2035 | L83: 2040 | M83: 2045 | N83: 2050 | P83: % | Q83: 2023 | R83: 2025 | S83: 2030 | T83: 2035 | U83: 2040 | V83: 2045 | W83: 2050
B84: Thermiques | C84: 0.99472928 | D84: 0.993762 | E84: 0.99241446 | F84: 0.99129747 | G84: 0.98961611 | H84: 0.98622217 | I84: 0.9776797 | J84: 0.87610505 | K84: 0.63779827 | L84: 0.31184442 | M84: 0.081682368 | N84: 0 | P84: Thermiques | Q84: 0.98622217 | R84: 0.97747303 | S84: 0.87336138 | T84: 0.63181725 | U84: 0.30629875 | V84: 0.079285721 | W84: 0.002080433
B85: GNV | H85: 0 | I85: 0.0017960977 | J85: 0.0027867572 | K85: 0.0025570214 | L85: 0.0014344369 | M85: 0.00043655478 | N85: 1.9738874e-05 | P85: GNV | Q85: 0 | R85: 0.0018068811 | S85: 0.0028220861 | T85: 0.0026035661 | U85: 0.0014653515 | V85: 0.00044259844 | W85: 1.9738874e-05
B86: Electrique | C86: 0.0054304424 | D86: 0.0063979527 | E86: 0.0074241446 | F86: 0.0087025316 | G86: 0.010383889 | H86: 0.013777828 | I86: 0.020524205 | J86: 0.11979837 | K86: 0.35491548 | L86: 0.67845399 | M86: 0.90804334 | N86: 0.99002938 | P86: Electrique | Q86: 0.013777828 | R86: 0.020720088 | S86: 0.12247413 | T86: 0.36076769 | U86: 0.68388564 | V86: 0.91040037 | W86: 0.98792921
B87: H2 | H87: 0 | I87: 0 | J87: 0.0013098201 | K87: 0.0047292216 | L87: 0.0082671529 | M87: 0.0098377346 | N87: 0.0099706186 | P87: Hydrogène | Q87: 0 | R87: 0 | S87: 0.0013424027 | T87: 0.0048114975 | U87: 0.0083502566 | V87: 0.0098713105 | W87: 0.0099706186
C88: =C86+C87 -> 0.0054304424 | D88: =D86+D87 -> 0.0063979527 | E88: =E86+E87 -> 0.0074241446 | F88: =F86+F87 -> 0.0087025316 | G88: =G86+G87 -> 0.010383889 | H88: =H86+H87 -> 0.013777828 | I88: =I86+I87 -> 0.020524205 | J88: =J86+J87 -> 0.12110819 | ... N88: =N86+N87 -> 1 | P88: Périmètre hexagone
I89: =I84+I85+I86+I87 -> 1 | J89: =J84+J85+J86+J87 -> 1 | K89: =K84+K85+K86+K87 -> 1 | L89: =L84+L85+L86+L87 -> 1 | M89: =M84+M85+M86+M87 -> 1 | N89: =N84+N85+N86+N87 -> 1.0000197
B90: C) Consommations du roulant
C92: observé | P92: Consommation moyenne réelle du parc roulant des véhicules utilitaires légers
C93: 2018 | D93: 2019 | E93: 2020 | F93: 2021 | G93: 2022 | H93: 2023 | I93: 2025 | J93: 2030 | K93: 2035 | L93: 2040 | M93: 2045 | N93: 2050 | P93: L / 100 km | Q93: 2023 | R93: 2025 | S93: 2030 | T93: 2035 | U93: 2040 | V93: 2045 | W93: 2050
B94: Thermique (l/100km) | C94: 7.8369256 | D94: 7.8 | E94: 7.6485959 | F94: 7.77426 | G94: 7.7573694 | H94: 7.7488612 | I94: 7.3608993 | J94: 7.0081352 | K94: 6.7997838 | L94: 6.4091386 | M94: 6.221572 | N94: 6.0941477 | P94: Thermique (l/100km) | Q94: 7.7488612 | R94: 7.3608094 | S94: 7.0048803 | T94: 6.7974184 | U94: 6.4096505 | V94: 6.2218346 | W94: 6.0941477
B95: Gaz (kg/100km) | C95: 6.069529 | D95: 6.033534 | E95: 5.9976352 | F95: 5.9459614 | G95: 5.889123 | H95: 5.8515878 | I95: 5.8070688 | J95: 5.6880789 | K95: 5.5528462 | L95: 5.4215583 | M95: 5.2883362 | N95: 5.2883362 | P95: Gaz (kg/100km) | Q95: 5.8515878 | R95: 5.8057328 | S95: 5.6858568 | T95: 5.5518252 | U95: 5.4220291 | V95: 5.2885594 | W95: 5.2885594
B96: Electrique (kWh/100km) | C96: 24.5 | D96: 24.5 | E96: 24.5 | F96: 24.45194 | G96: 24.34913 | H96: 24.264948 | I96: 24.176447 | J96: 23.948631 | K96: 23.553022 | L96: 23.142168 | M96: 22.660756 | N96: 22.05 | P96: Electrique (kWh/100km) | Q96: 24.264948 | R96: 24.175083 | S96: 23.947931 | T96: 23.555742 | U96: 23.146647 | V96: 22.663667 | W96: 22.05
B97: H2 (kg/100km) | C97: 1.6 | D97: =C97 -> 1.6 | E97: =D97 -> 1.6 | F97: 1.6 | G97: 1.6 | H97: 1.6 | I97: 0 | J97: 1.2721746 | K97: 1.2341409 | L97: 1.2208491 | M97: 1.2055516 | N97: 1.2 | P97: H2 (kg/100km) | Q97: 1.6 | R97: 1.39 | S97: 1.2721865 | T97: 1.23439 | U97: 1.2211242 | V97: 1.205625 | W97: 1.2
B100: A) Evolution des intensités énergétiques et des intensités d'émissions de gaz à effet de serre
B103: A) Evolution des intensités énergétiques et des intensités d'émissions de gaz à effet de serre
B105: Intensité énergétique
B106: kWh/100km | C106: 2018 | D106: 2019 | E106: 2020 | F106: 2021 | G106: 2022 | H106: 2023 | I106: 2025 | J106: 2030 | K106: 2035 | L106: 2040 | M106: 2045 | N106: 2050
B107: Diesel | C107: =C94*$E$6 -> 78.369256 | D107: =D94*$E$6 -> 78 | E107: =E94*$E$6 -> 76.485959 | F107: =F94*$E$6 -> 77.7426 | G107: =G94*$E$6 -> 77.573694 | H107: =H94*$E$6 -> 77.488612 | I107: =I94*$E$6 -> 73.608993 | J107: =J94*$E$6 -> 70.081352 | ... N107: =N94*$E$6 -> 60.941477
B108: Gaz | C108: =C95*$E$8 -> 83.7595 | D108: =D95*$E$8 -> 83.262769 | E108: =E95*$E$8 -> 82.767366 | F108: =F95*$E$8 -> 82.054268 | G108: =G95*$E$8 -> 81.269898 | H108: =H95*$E$8 -> 80.751912 | I108: =I95*$E$8 -> 80.137549 | J108: =J95*$E$8 -> 78.495489 | ... N108: =N95*$E$8 -> 72.97904
B109: Electrique | C109: =C96 -> 24.5 | D109: =D96 -> 24.5 | E109: =E96 -> 24.5 | F109: =F96 -> 24.45194 | G109: =G96 -> 24.34913 | H109: =H96 -> 24.264948 | I109: =I96 -> 24.176447 | J109: =J96 -> 23.948631 | ... N109: =N96 -> 22.05
B110: H2 | C110: =C97*33.3 -> 53.28 | D110: =D97*33.3 -> 53.28 | E110: =E97*33.3 -> 53.28 | F110: =F97*33.3 -> 53.28 | G110: =G97*33.3 -> 53.28 | H110: =H97*33.3 -> 53.28 | I110: =I97*33.3 -> 0 | J110: =J97*33.3 -> 42.363415 | ... N110: =N97*33.3 -> 39.96
B111: Moyenne (kWh/100km) | C111: =(C107*C84+C108*C85+C109*C86+C110*C87)/(C84+C85+C86+C87) -> 78.076769 | D111: =(D107*D84+D108*D85+D109*D86+D110*D87)/(D84+D85+D86+D87) -> 77.657764 | E111: =(E107*E84+E108*E85+E109*E86+E110*E87)/(E84+E85+E86+E87) -> 76.099945 | F111: =(F107*F84+F108*F85+F109*F86+F110*F87)/(F84+F85+F86+F87) -> 77.278836 | G111: =(G107*G84+G108*G85+G109*G86+G110*G87)/(G84+G85+G86+G87) -> 77.021016 | H111: =(H107*H84+H108*H85+H109*H86+H110*H87)/(H84+H85+H86+H87) -> 76.755305 | I111: =(I107*I84+I108*I85+I109*I86+I110*I87)/(I84+I85+I86+I87) -> 72.606155 | J111: =(J107*J84+J108*J85+J109*J86+J110*J87)/(J84+J85+J86+J87) -> 64.54187 | ... N111: =(N107*N84+N108*N85+N109*N86+N110*N87)/(N84+N85+N86+N87) -> 22.229576
B113: Intensité carbone
B114: gCO2/km | C114: 2018 | D114: 2019 | E114: 2020 | F114: 2021 | G114: 2022 | H114: 2023 | I114: 2025 | J114: 2030 | K114: 2035 | L114: 2040 | M114: 2045 | N114: 2050
B115: Diesel | C115: =C94*C14*10 -> 197.54474 | D115: =D94*D14*10 -> 195.323 | E115: =E94*E14*10 -> 191.67822 | F115: =F94*F14*10 -> 195.44472 | G115: =G94*G14*10 -> 194.69564 | H115: =H94*H14*10 -> 193.45112 | I115: =I94*I14*10 -> 180.69902 | J115: =J94*J14*10 -> 163.87398 | ... N115: =N94*N14*10 -> 0
B116: Gaz | C116: =C95*C15*10 -> 169.74194 | D116: =D95*D15*10 -> 156.34899 | E116: =E95*E15*10 -> 167.73134 | F116: =F95*F15*10 -> 166.45267 | G116: =G95*G15*10 -> 164.86152 | H116: =H95*H15*10 -> 162.17265 | I116: =I95*I15*10 -> 154.43625 | J116: =J95*J15*10 -> 135.34843 | ... N116: =N95*N15*10 -> 0
B117: Electrique | C117: =0 -> 0 | D117: =0 -> 0 | E117: =0 -> 0 | F117: =0 -> 0 | G117: =0 -> 0 | H117: =0 -> 0 | I117: =0 -> 0 | J117: =0 -> 0 | ... N117: =0 -> 0
B118: H2 | C118: =0 -> 0 | D118: =0 -> 0 | E118: =0 -> 0 | F118: =0 -> 0 | G118: =0 -> 0 | H118: =0 -> 0 | I118: =0 -> 0 | J118: =0 -> 0 | ... N118: =0 -> 0
B119: Moyenne (gCO2/km) | C119: =(C115*C84+C116*C85+C117*C86+C118*C87)/(C84+C85+C86+C87) -> 196.47215 | D119: =(D115*D84+D116*D85+D117*D86+D118*D87)/(D84+D85+D86+D87) -> 194.07354 | E119: =(E115*E84+E116*E85+E117*E86+E118*E87)/(E84+E85+E86+E87) -> 190.25494 | F119: =(F115*F84+F116*F85+F117*F86+F118*F87)/(F84+F85+F86+F87) -> 193.74385 | G119: =(G115*G84+G116*G85+G117*G86+G118*G87)/(G84+G85+G86+G87) -> 192.67394 | H119: =(H115*H84+H116*H85+H117*H86+H118*H87)/(H84+H85+H86+H87) -> 190.78578 | I119: =(I115*I84+I116*I85+I117*I86+I118*I87)/(I84+I85+I86+I87) -> 176.94314 | J119: =(J115*J84+J116*J85+J117*J86+J118*J87)/(J84+J85+J86+J87) -> 143.948 | ... N119: =(N115*N84+N116*N85+N117*N86+N118*N87)/(N84+N85+N86+N87) -> 0
B121: B) Evolution des consommations énergétiques en volume (en Mtep) par type d'énergie
B123: Trafic | C123: 2018 | D123: 2019 | E123: 2020 | F123: 2021 | G123: 2022 | H123: 2023 | I123: 2025 | J123: 2030 | K123: 2035 | L123: 2040 | M123: 2045 | N123: 2050
B124: VUL | C124: =Trafic!C113 -> 87.3 | D124: =Trafic!D113 -> 88.6 | E124: =Trafic!E113 -> 78.6 | F124: =Trafic!F113 -> 85.9 | G124: =Trafic!G113 -> 87.7 | H124: =Trafic!H113 -> 86.3845 | I124: =Trafic!I113 -> 89.103782 | J124: =Trafic!J113 -> 88.944078 | ... N124: =Trafic!N113 -> 89.647091
...

Sheet PL
B1: 1 tep | C1: 41.868 | D1: GJ | E1: =C1/3.6 -> 11.63 | F1: MWh
B3: FE du fossile sans intégration des parts de bio et avec contenu élec à 0 (pour calcul de l'évolution des émissions théoriques des véh neufs)
B4: FE du fossile | C4: FE par udp | E4: Energie par udp
B5: Essence | C5: 2.3422222 | D5: kgCO2/L | E5: 8.8888889 | F5: kWh/L
B6: Gazole | C6: 2.71 | D6: kgCO2/L | E6: 10 | F6: kWh/L
B7: Kérosène | C7: 2.4583889 | D7: kgCO2/L | E7: 9.4444444 | F7: kWh/L
B8: GNV | C8: 2.8027171 | D8: kgCO2/kg | E8: 13.8 | F8: kWh/kg
B9: Electricité | C9: 0
B11: FE des carburants avec intégration des parts de bio et avec un contenu de l'élec nul
B12: FE du fossile | C12: 2018 | D12: 2019 | E12: 2020 | F12: 2021 | G12: 2022 | H12: 2023 | I12: 2025 | J12: 2030 | K12: 2035 | L12: 2040 | M12: 2045 | N12: 2050
B13: Essence | C13: =FE_et_bio!B60 -> 2.1715472 | D13: =FE_et_bio!C60 -> 2.1503726 | E13: =FE_et_bio!D60 -> 2.1622273 | F13: =FE_et_bio!E60 -> 2.1608105 | G13: =FE_et_bio!F60 -> 2.1534286 | H13: =FE_et_bio!G60 -> 2.1390965 | I13: =FE_et_bio!H60 -> 2.0965855 | J13: =FE_et_bio!I60 -> 2.0216238 | ... N13: =FE_et_bio!M60 -> 0
B14: Gazole | C14: =FE_et_bio!B61 -> 2.5206918 | D14: =FE_et_bio!C61 -> 2.5041411 | E14: =FE_et_bio!D61 -> 2.5060576 | F14: =FE_et_bio!E61 -> 2.5139977 | G14: =FE_et_bio!F61 -> 2.5098152 | H14: =FE_et_bio!G61 -> 2.4965103 | I14: =FE_et_bio!H61 -> 2.4548498 | J14: =FE_et_bio!I61 -> 2.3383392 | ... N14: =FE_et_bio!M61 -> 0
B15: GNV | C15: =FE_et_bio!B62 -> 2.7966246 | D15: =FE_et_bio!C62 -> 2.5913335 | E15: =FE_et_bio!D62 -> 2.7966246 | F15: =FE_et_bio!E62 -> 2.799424 | G15: =FE_et_bio!F62 -> 2.799424 | H15: =FE_et_bio!G62 -> 2.7714298 | I15: =FE_et_bio!H62 -> 2.6594528 | J15: =FE_et_bio!I62 -> 2.3795104 | ... N15: =FE_et_bio!M62 -> 0
B16: Electricité | C16: 0 | D16: 0 | E16: 0 | F16: 1 | G16: 2 | H16: 3 | I16: 0 | J16: 0 | K16: 0 | L16: 0 | M16: 0 | N16: 0
B19: PL | C19: AMS
B21: I) Données sur les parts des énergies et consos des véh neufs
B23: A) Circulations, parcs roulants et immatriculations des PL
P24: Immatriculations de véhicules (millions)
B25: Parc et immatriculation des PL immatriculés en France (camions + tracteurs routiers) | P25: Millions de véhicules | Q25: 2022 | R25: 2025 | S25: 2030 | T25: 2035 | U25: 2040 | V25: 2045 | W25: 2050
C26: 2018 | D26: 2019 | E26: 2020 | F26: 2021 | G26: 2022 | H26: 2023 | I26: 2025 | J26: 2030 | K26: 2035 | L26: 2040 | M26: 2045 | N26: 2050 | P26: Véhicules particuliers | Q26: 1.57695 | R26: 1.9 | S26: 1.8 | T26: 1.8 | U26: 2 | V26: 2 | W26: 1.9
B27: Parc de camions (milliers) | C27: 599 | D27: 606 | E27: 605 | F27: 612 | G27: 619 | H27: 611.55771 | I27: =E27 -> 605 | J27: =I27 -> 605 | K27: =J27 -> 605 | L27: =K27 -> 605 | M27: =L27 -> 605 | N27: =M27 -> 605 | P27: Véhicules utilitaires légers | Q27: 0.358893 | R27: 0.358893 | S27: 0.358893 | T27: 0.358893 | U27: 0.358893 | V27: 0.358893 | W27: 0.358893
B28: Immatriculations (milliers par an) | C28: 56.792 | D28: 57.278 | E28: 43.466 | F28: 45.944 | G28: 46.163 | H28: 50.48 | I28: =44.3 -> 44.3 | J28: =44.3 -> 44.3 | K28: =44.3 -> 44.3 | L28: =44.3 -> 44.3 | M28: =44.3 -> 44.3 | N28: =44.3 -> 44.3 | P28: Poids lourds | Q28: 0.046163 | R28: 0.0443 | S28: 0.0443 | T28: 0.0443 | U28: 0.0443 | V28: 0.0443 | W28: 0.0443
C29: =C27/C28 -> 10.54726 | D29: =D27/D28 -> 10.579978 | E29: =E27/E28 -> 13.918925 | F29: =F27/F28 -> 13.320564 | G29: =G27/G28 -> 13.409007 | H29: =H27/H28 -> 12.114852 | I29: =I27/I28 -> 13.656885 | J29: =J27/J28 -> 13.656885 | ... N29: =N27/N28 -> 13.656885 | P29: Bus et car | Q29: 0.006192 | R29: 0.0062 | S29: 0.0062 | T29: 0.0062 | U29: 0.0062 | V29: 0.0062 | W29: 0.0062
P30: Périmètre hexagone
B31: Kilométrage moyen des véhicules immatriculés en France
C32: 2018 | D32: 2019 | E32: 2020 | F32: 2021 | G32: 2022 | P32: Parc de véhicules (millions)
B33: Poids lourds pavillon français | C33: 44050 | D33: 44202 | E33: 41087 | F33: 43893 | G33: 44031 | P33: Millions de véhicules | Q33: 2022 | R33: 2025 | S33: 2030 | T33: 2035 | U33: 2040 | V33: 2045 | W33: 2050
B34: Diesel | C34: 44070 | D34: 44196 | E34: 41024 | F34: 43798 | G34: 43972 | P34: Véhicules particuliers | Q34: 38.127317 | R34: 36.309448 | S34: 34.809448 | T34: 33.357086 | U34: 31.904724 | V34: 30.452362 | W34: 29
B35: GNV | C35: 44677 | D35: 48206 | E35: 49942 | F35: 53137 | G35: 49770 | P35: Véhicules utilitaires légers | Q35: 6.356 | R35: 6.356 | S35: 6.356 | T35: 6.356 | U35: 6.356 | V35: 6.356 | W35: 6.356
B36: Electrique | C36: 11540 | D36: 15069 | E36: 16056 | F36: 18911 | G36: 16067 | P36: Poids lourds | Q36: 0.619 | R36: 0.605 | S36: 0.605 | T36: 0.605 | U36: 0.605 | V36: 0.605 | W36: 0.605
P37: Bus et car | Q37: 0.094 | R37: 0.094 | S37: 0.094 | T37: 0.094 | U37: 0.094 | V37: 0.094 | W37: 0.094
P38: Périmètre hexagone
B39: B) Part de marchés des énergies | E39: véhicules neufs
P40: Part de marché des poids lourds neufs (%)
C41: 2018 | D41: 2019 | E41: 2020 | F41: 2021 | G41: 2022 | H41: 2023 | I41: 2025 | J41: 2030 | K41: 2035 | L41: 2040 | M41: 2045 | N41: 2050 | P41: % | Q41: 2023 | R41: 2025 | S41: 2030 | T41: 2035 | U41: 2040 | V41: 2045 | W41: 2050
B42: Thermiques | C42: 0.97777856 | D42: 0.97045986 | E42: 0.96266047 | F42: 0.96077834 | G42: 0.93891212 | H42: 0.95186212 | I42: 0.89 | J42: 0.49 | K42: 0.33 | L42: 0.17 | M42: 0.11 | N42: 0.1 | P42: Thermiques | Q42: 0.93891212 | R42: 0.89 | S42: 0.49 | T42: 0.33 | U42: 0.17 | V42: 0.11 | W42: 0.1
B43: GNV | C43: 0.020566277 | D43: 0.026729285 | E43: 0.035360972 | F43: 0.036849208 | G43: 0.049563503 | H43: 0.035003962 | I43: 0.03 | J43: 0.01 | K43: 0 | L43: 0 | M43: 0 | N43: 0 | P43: GNV | Q43: 0.049563503 | R43: 0.03 | S43: 0.01 | T43: 0 | U43: 0 | V43: 0 | W43: 0
B44: Electrique | C44: 0.00015847302 | D44: 0.00094277035 | E44: 0.001035292 | F44: 0.001697719 | G44: 0.011199445 | H44: 0.013034865 | I44: 0.08 | J44: 0.496 | K44: 0.65 | L44: 0.8 | M44: 0.85 | N44: 0.85 | P44: Electrique | Q44: 0.011199445 | R44: 0.08 | S44: 0.496 | T44: 0.65 | U44: 0.8 | V44: 0.85 | W44: 0.85
B45: H2 | C45: 0.0014966897 | D45: 0.001868082 | E45: 0.000943266 | F45: 0.00067473446 | G45: 0.00032493555 | H45: 0 | I45: 0 | J45: 0.004 | K45: 0.02 | L45: 0.03 | M45: 0.04 | N45: 0.05 | P45: H2 | Q45: 0.00032493555 | R45: 0 | S45: 0.004 | T45: 0.02 | U45: 0.03 | V45: 0.04 | W45: 0.05
B46: baisse émissions parc à comparer avec règlement UE CO2 PL : | E46: =E103/$E103-1 -> 0 | F46: =F103/$E103-1 -> -0.0106042 | G46: =G103/$E103-1 -> -0.030089353 | H46: =H103/$E103-1 -> -0.041091971 | I46: =I103/$E103-1 -> -0.13126028 | J46: =J103/$E103-1 -> -0.55928379 | K46: =K103/$E103-1 -> -0.71990328 | L46: =L103/$E103-1 -> -0.8609916 | ... N46: =N103/$E103-1 -> -0.91823035
C47: =SUM(C42:C45) -> 1 | D47: =SUM(D42:D45) -> 1 | E47: =SUM(E42:E45) -> 1 | F47: =SUM(F42:F45) -> 1 | G47: =SUM(G42:G45) -> 1 | H47: =SUM(H42:H45) -> 0.99990095 | I47: =SUM(I42:I45) -> 1 | J47: =SUM(J42:J45) -> 1 | ... N47: =SUM(N42:N45) -> 1
B48: total élec+H2 | C48: =C44+C45 -> 0.0016551627 | D48: =D44+D45 -> 0.0028108523 | E48: =E44+E45 -> 0.001978558 | F48: =F44+F45 -> 0.0023724534 | G48: =G44+G45 -> 0.011524381 | H48: =H44+H45 -> 0.013034865 | I48: =I44+I45 -> 0.08 | J48: =J44+J45 -> 0.5 | ... N48: =N44+N45 -> 0.9
B51: C) Consommations des PL neufs | E51: véhicules neufs
B53: GLOBAL
B54: Evolution des consommations unitaires des PL neufs | O54: =N57/H57-1 -> -0.15966818
C55: estimation | D55: estimation | E55: estimation | F55: estimation | G55: estimation | H55: estimation | P55: Consommation moyenne réelle des poids lourds neufs
C56: 2018 | D56: 2019 | E56: 2020 | F56: 2021 | G56: 2022 | H56: 2023 | I56: 2025 | J56: 2030 | K56: 2035 | L56: 2040 | M56: 2045 | N56: 2050 | Q56: 2023 | R56: 2025 | S56: 2030 | T56: 2035 | U56: 2040 | V56: 2045 | W56: 2050
A57: 30 | B57: Diesel (L/100km) | C57: =D57*1.01 -> 29.40902 | D57: =E57*1.01 -> 29.117842 | E57: =F57*1.01 -> 28.829546 | F57: =G57*1.01 -> 28.544105 | G57: =H57*1.01 -> 28.261491 | H57: 27.981674 | I57: 27.198344 | J57: 25.336317 | K57: 24.407677 | L57: 23.513891 | M57: 23.513891 | N57: 23.513891 | O57: =J57/H57-1 -> -0.094538891 | P57: Diesel (L/100km) | Q57: 27.981674 | R57: 27.198344 | S57: 25.336317 | T57: 24.407677 | U57: 23.513891 | V57: 23.513891 | W57: 23.513891
A58: 27.5 | B58: Gaz (kg/100km) | C58: 27.932053 | D58: 27.680665 | E58: 27.431539 | F58: =E58*0.8+0.2*I58 -> 26.942116 | G58: =E58*0.6+I58*0.4 -> 26.452693 | H58: 25.963271 | I58: 24.984426 | J58: 25 | K58: 25 | L58: 25 | M58: 25 | N58: 25 | P58: Gaz (kg/100km) | Q58: 25.963271 | R58: 24.984426 | S58: 25 | T58: 25 | U58: 25 | V58: 25 | W58: 25
A59: 120 | B59: Electrique (kWh/100km) | C59: =D59*1.01 -> 131.52923 | D59: =E59*1.01 -> 130.22696 | E59: =F59*1.01 -> 128.93759 | F59: =G59*1.01 -> 127.66098 | G59: =H59*1.01 -> 126.39701 | H59: 125.14555 | I59: 124.69928 | J59: 116.14576 | K59: 108.18918 | L59: 100.78736 | M59: 100 | N59: 100 | P59: Electrique (kWh/100km) | Q59: 125.14555 | R59: 124.69928 | S59: 116.14576 | T59: 108.18918 | U59: 100.78736 | V59: 100 | W59: 100
A60: 7.1 | B60: H2 (kg/100km) | C60: =7.1 -> 7.1 | D60: =7.1 -> 7.1 | E60: =7.1 -> 7.1 | F60: =E60*0.8+0.2*I60 -> 6.973 | G60: =E60*0.6+I60*0.4 -> 6.846 | H60: 6.719 | I60: 6.465 | J60: 5.973 | K60: 5.555 | L60: 5.1 | M60: 5.1 | N60: 5.1 | P60: H2 (kg/100km) | Q60: 6.719 | R60: 6.465 | S60: 5.973 | T60: 5.555 | U60: 5.1 | V60: 5.1 | W60: 5.1
B61: baisse / 2020 diesel | F61: =F57/$E57-1 -> -0.0099009901 | G61: =G57/$E57-1 -> -0.019703951 | H61: =H57/$E57-1 -> -0.029409852 | I61: =I57/$E57-1 -> -0.056580917 | J61: =J57/$E57-1 -> -0.12116837 | K61: =K57/$E57-1 -> -0.15337979 | L61: =L57/$E57-1 -> -0.18438222 | M61: =M57/$E57-1 -> -0.18438222 | N61: =N57/$E57-1 -> -0.18438222
B62: baisse / 2020 gaz | F62: =F58/$E58-1 -> -0.017841603 | G62: =G58/$E58-1 -> -0.035683205 | H62: =H58/$E58-1 -> -0.053524808 | I62: =I58/$E58-1 -> -0.089208013 | J62: =J58/$E58-1 -> -0.08864026 | K62: =K58/$E58-1 -> -0.08864026 | L62: =L58/$E58-1 -> -0.08864026 | M62: =M58/$E58-1 -> -0.08864026 | N62: =N58/$E58-1 -> -0.08864026
B63: baisse / 2020 élec | F63: =F59/$E59-1 -> -0.0099009901 | G63: =G59/$E59-1 -> -0.019703951 | H63: =H59/$E59-1 -> -0.029409852 | I63: =I59/$E59-1 -> -0.032870972 | J63: =J59/$E59-1 -> -0.099209459 | K63: =K59/$E59-1 -> -0.16091821 | L63: =L59/$E59-1 -> -0.21832447 | M63: =M59/$E59-1 -> -0.22443096 | N63: =N59/$E59-1 -> -0.22443096
B64: ratio GNV/diesel | C64: =C58/C57 -> 0.94977843 | D64: =D58/D57 -> 0.95064273 | E64: =E58/E57 -> 0.95150781 | F64: =F58/F57 -> 0.9438767 | G64: =G58/G57 -> 0.93599782 | H64: =H58/H57 -> 0.92786697 | I64: =I58/I57 -> 0.91860098 | J64: =J58/J57 -> 0.98672588 | ... N64: =N58/N57 -> 1.0632013
B66: kWh/véh-km | C66: 2018 | D66: 2019 | E66: 2020 | F66: 2021 | G66: 2022 | H66: 2023 | I66: 2025 | J66: 2030 | K66: 2035 | L66: 2040 | M66: 2045 | N66: 2050
B67: Diesel | C67: =C57*$E$6 -> 294.0902 | D67: =D57*$E$6 -> 291.17842 | E67: =E57*$E$6 -> 288.29546 | F67: =F57*$E$6 -> 285.44105 | G67: =G57*$E$6 -> 282.61491 | H67: =H57*$E$6 -> 279.81674 | I67: =I57*$E$6 -> 271.98344 | J67: =J57*$E$6 -> 253.36317 | ... N67: =N57*$E$6 -> 235.13891
B68: Gaz | C68: =C58*$E$8 -> 385.46233 | D68: =D58*$E$8 -> 381.99317 | E68: =E58*$E$8 -> 378.55523 | F68: =F58*$E$8 -> 371.8012 | G68: =G58*$E$8 -> 365.04717 | H68: =H58*$E$8 -> 358.29314 | I68: =I58*$E$8 -> 344.78507 | J68: =J58*$E$8 -> 345 | ... N68: =N58*$E$8 -> 345
B69: Electrique | C69: =C59 -> 131.52923 | D69: =D59 -> 130.22696 | E69: =E59 -> 128.93759 | F69: =F59 -> 127.66098 | G69: =G59 -> 126.39701 | H69: =H59 -> 125.14555 | I69: =I59 -> 124.69928 | J69: =J59 -> 116.14576 | ... N69: =N59 -> 100
B70: H2 | C70: =C60*33.3 -> 236.43 | D70: =D60*33.3 -> 236.43 | E70: =E60*33.3 -> 236.43 | F70: =F60*33.3 -> 232.2009 | G70: =G60*33.3 -> 227.9718 | H70: =H60*33.3 -> 223.7427 | I70: =I60*33.3 -> 215.2845 | J70: =J60*33.3 -> 198.9009 | ... N70: =N60*33.3 -> 169.83
B71: En moyenne | C71: =(C67*C42+C68*C43+C69*C44+C70*C45) -> 295.85733 | D71: =(D67*D42+D68*D43+D69*D44+D70*D45) -> 293.35182 | E71: =(E67*E42+E68*E43+E69*E44+E70*E45) -> 291.27323 | F71: =(F67*F42+F68*F43+F69*F44+F70*F45) -> 288.31957 | G71: =(G67*G42+G68*G43+G69*G44+G70*G45) -> 284.93323 | H71: =(H67*H42+H68*H43+H69*H44+H70*H45) -> 280.51989 | I71: =(I67*I42+I68*I43+I69*I44+I70*I45) -> 262.38476 | J71: =(J67*J42+J68*J43+J69*J44+J70*J45) -> 186.00185 | ... N71: =(N67*N42+N68*N43+N69*N44+N70*N45) -> 117.00539
B74: PAR PTAC
B75: Evolution des consommations unitaires des PL neufs GNV (kg/100km) | Q75: Repris du paramétrage du modèle TCO de la DGITM, adapté aux chiffres AMS
C76: 2018 | D76: 2019 | E76: 2020 | I76: 2025 | J76: 2030 | K76: 2035 | L76: 2040 | M76: 2045 | N76: 2050
B77: Porteurs < 7,5t | D77: 16.570297 | E77: 16.409702 | I77: 14.440538 | J77: 12.799568 | K77: 11.574263 | L77: 10.348958 | M77: 9.9601244 | N77: 9.5712907
B78: Porteurs [7,5t ; 12t] | D78: 16.570297 | E78: 16.409702 | I78: 14.440538 | J78: 12.799568 | K78: 11.574263 | L78: 10.348958 | M78: 9.9601244 | N78: 9.5712907
B79: Porteurs [12t ; 16t] | D79: 23.145812 | E79: 22.921489 | I79: 20.17091 | J79: 17.878761 | K79: 16.167224 | L79: 14.455688 | M79: 13.912555 | N79: 13.369422
B80: Porteurs [16t ; 19t] | D80: 26.039038 | E80: 25.786675 | I80: 22.692274 | J80: 20.113606 | K80: 18.188127 | L80: 16.262648 | M80: 15.651624 | N80: 15.0406
B81: Porteurs [19t ; 26t] | D81: 29.616118 | E81: 29.329086 | I81: 25.809596 | J81: 22.876687 | K81: 20.686698 | L81: 18.496709 | M81: 17.801746 | N81: 17.106783
B82: Porteurs [26t ; 32t] | D82: 29.616118 | E82: 29.329086 | I82: 25.809596 | J82: 22.876687 | K82: 20.686698 | L82: 18.496709 | M82: 17.801746 | N82: 17.106783
B83: Tracteurs routiers | D83: 28.406224 | E83: 28.130918 | I83: 24.755208 | J83: 21.942116 | K83: 19.841593 | L83: 17.741071 | M83: 17.074499 | N83: 16.407927
B85: Evolution des consommations unitaires des PL neufs diesel (L/100km) | Q85: Repris du paramétrage du modèle TCO de la DGITM, adapté aux chiffres AMS
C86: 2018 | D86: 2019 | E86: 2020 | I86: 2025 | J86: 2030 | K86: 2035 | L86: 2040 | M86: 2045 | N86: 2050
B87: Porteurs < 7,5t | D87: 19.221512 | E87: 19.040177 | I87: 16.777425 | J87: 14.8709 | K87: 13.781462 | L87: 12.693451 | M87: 12.391226 | N87: 12.089001
B88: Porteurs [7,5t ; 12t] | D88: 19.221512 | E88: 19.040177 | I88: 16.777425 | J88: 14.8709 | K88: 13.781462 | L88: 12.693451 | M88: 12.391226 | N88: 12.089001
B89: Porteurs [12t ; 16t] | D89: 24.164187 | E89: 23.936223 | I89: 21.09162 | J89: 18.694845 | K89: 17.325266 | L89: 15.957482 | M89: 15.577542 | N89: 15.197602
B90: Porteurs [16t ; 19t] | D90: 30.205233 | E90: 29.920278 | I90: 26.364526 | J90: 23.368557 | K90: 21.656582 | L90: 19.946852 | M90: 19.471927 | N90: 18.997002
B91: Porteurs [19t ; 26t] | D91: 33.50035 | E91: 33.184309 | I91: 29.240656 | J91: 25.917854 | K91: 24.019119 | L91: 22.122873 | M91: 21.596137 | N91: 21.069402
B92: Porteurs [26t ; 32t] | D92: 33.50035 | E92: 33.184309 | I92: 29.240656 | J92: 25.917854 | K92: 24.019119 | L92: 22.122873 | M92: 21.596137 | N92: 21.069402
B93: Tracteurs routiers | D93: 32.951164 | E93: 32.640304 | I93: 28.761301 | J93: 25.492971 | K93: 23.625363 | L93: 21.760202 | M93: 21.242102 | N93: 20.724002
B95: C) Emissions de GES des PL neufs | E95: véhicules neufs
B97: GLOBAL
B98: gCO2/véh-km | C98: 2018 | D98: 2019 | E98: 2020 | F98: 2021 | G98: 2022 | H98: 2023 | I98: 2025 | J98: 2030 | K98: 2035 | L98: 2040 | M98: 2045 | N98: 2050
B99: Diesel | C99: =C57*$C$6*10 -> 796.98445 | D99: =D57*$C$6*10 -> 789.09352 | E99: =E57*$C$6*10 -> 781.28071 | F99: =F57*$C$6*10 -> 773.54526 | G99: =G57*$C$6*10 -> 765.88639 | H99: =H57*$C$6*10 -> 758.30336 | I99: =I57*$C$6*10 -> 737.07513 | J99: =J57*$C$6*10 -> 686.6142 | ... N99: =N57*$C$6*10 -> 637.22644
B100: Gaz | C100: =C58*$C$8*10 -> 782.85643 | D100: =D58*$C$8*10 -> 775.81073 | E100: =E58*$C$8*10 -> 768.82843 | F100: =F58*$C$8*10 -> 755.1113 | G100: =G58*$C$8*10 -> 741.39417 | H100: =H58*$C$8*10 -> 727.67704 | I100: =I58*$C$8*10 -> 700.24277 | J100: =J58*$C$8*10 -> 700.67928 | ... N100: =N58*$C$8*10 -> 700.67928
B101: Electrique | C101: 0 | D101: 0 | E101: 0 | F101: 0 | G101: 0 | H101: 0 | I101: 0 | J101: 0 | K101: 0 | L101: 0 | M101: 0 | N101: 0
B102: H2 | C102: 0 | D102: 0 | E102: 0 | F102: 0 | G102: 0 | H102: 0 | I102: 0 | J102: 0 | K102: 0 | L102: 0 | M102: 0 | N102: 0
B103: En moyenne | C103: =(C99*C42+C100*C43+C101*C44+C102*C45) -> 795.37475 | D103: =(D99*D42+D100*D43+D101*D44+D102*D45) -> 786.52045 | E103: =(E99*E42+E100*E43+E101*E44+E102*E45) -> 779.29458 | F103: =(F99*F42+F100*F43+F101*F44+F102*F45) -> 771.03078 | G103: =(G99*G42+G100*G43+G101*G44+G102*G45) -> 755.84611 | H103: =(H99*H42+H100*H43+H101*H44+H102*H45) -> 747.27183 | I103: =(I99*I42+I100*I43+I101*I44+I102*I45) -> 677.00415 | J103: =(J99*J42+J100*J43+J101*J44+J102*J45) -> 343.44775 | ... N103: =(N99*N42+N100*N43+N101*N44+N102*N45) -> 63.722644
E104: =E103/$E103-1 -> 0 | F104: =F103/$E103-1 -> -0.0106042 | G104: =G103/$E103-1 -> -0.030089353 | H104: =H103/$E103-1 -> -0.041091971 | I104: =I103/$E103-1 -> -0.13126028 | J104: =J103/$E103-1 -> -0.55928379 | K104: =K103/$E103-1 -> -0.71990328 | L104: =L103/$E103-1 -> -0.8609916 | ... N104: =N103/$E103-1 -> -0.91823035
C105: =C100/C99 -> 0.98227316 | D105: =D100/D99 -> 0.98316703 | E105: =E100/E99 -> 0.98406171 | F105: =F100/F99 -> 0.97616951 | G105: =G100/G99 -> 0.96802107 | H105: =H100/H99 -> 0.95961204 | I105: =I100/I99 -> 0.95002903 | J105: =J100/J99 -> 1.0204847 | ... N105: =N100/N99 -> 1.0995766
B107: PAR PTAC
B108: Emissions unitaires des PL neufs GNV (gCO2/km)
C109: 2018 | D109: 2019 | E109: 2020 | I109: 2025 | J109: 2030 | K109: 2035 | L109: 2040 | M109: 2045 | N109: 2050
B110: Porteurs < 7,5t | D110: =(D77/100)*($C$8*1000) -> 464.41855 | E110: =(E77/100)*($C$8*1000) -> 459.91753 | I110: =(I77/100)*($C$8*1000) -> 404.72742 | J110: =(J77/100)*($C$8*1000) -> 358.73567 | K110: =(K77/100)*($C$8*1000) -> 324.39385 | L110: =(L77/100)*($C$8*1000) -> 290.05202 | M110: =(M77/100)*($C$8*1000) -> 279.15411 | N110: =(N77/100)*($C$8*1000) -> 268.2562
B111: Porteurs [7,5t ; 12t] | D111: =(D78/100)*($C$8*1000) -> 464.41855 | E111: =(E78/100)*($C$8*1000) -> 459.91753 | I111: =(I78/100)*($C$8*1000) -> 404.72742 | J111: =(J78/100)*($C$8*1000) -> 358.73567 | K111: =(K78/100)*($C$8*1000) -> 324.39385 | L111: =(L78/100)*($C$8*1000) -> 290.05202 | M111: =(M78/100)*($C$8*1000) -> 279.15411 | N111: =(N78/100)*($C$8*1000) -> 268.2562
B112: Porteurs [12t ; 16t] | D112: =(D79/100)*($C$8*1000) -> 648.71163 | E112: =(E79/100)*($C$8*1000) -> 642.42448 | I112: =(I79/100)*($C$8*1000) -> 565.33354 | J112: =(J79/100)*($C$8*1000) -> 501.0911 | K112: =(K79/100)*($C$8*1000) -> 453.12156 | L112: =(L79/100)*($C$8*1000) -> 405.15203 | M112: =(M79/100)*($C$8*1000) -> 389.92955 | N112: =(N79/100)*($C$8*1000) -> 374.70708
B113: Porteurs [16t ; 19t] | D113: =(D80/100)*($C$8*1000) -> 729.80058 | E113: =(E80/100)*($C$8*1000) -> 722.72754 | I113: =(I80/100)*($C$8*1000) -> 636.00024 | J113: =(J80/100)*($C$8*1000) -> 563.72748 | K113: =(K80/100)*($C$8*1000) -> 509.76176 | L113: =(L80/100)*($C$8*1000) -> 455.79603 | M113: =(M80/100)*($C$8*1000) -> 438.67075 | N113: =(N80/100)*($C$8*1000) -> 421.54546
B114: Porteurs [19t ; 26t] | D114: =(D81/100)*($C$8*1000) -> 830.05601 | E114: =(E81/100)*($C$8*1000) -> 822.01133 | I114: =(I81/100)*($C$8*1000) -> 723.36997 | J114: =(J81/100)*($C$8*1000) -> 641.16883 | K114: =(K81/100)*($C$8*1000) -> 579.78963 | L114: =(L81/100)*($C$8*1000) -> 518.41044 | M114: =(M81/100)*($C$8*1000) -> 498.93259 | N114: =(N81/100)*($C$8*1000) -> 479.45474
B115: Porteurs [26t ; 32t] | D115: =(D82/100)*($C$8*1000) -> 830.05601 | E115: =(E82/100)*($C$8*1000) -> 822.01133 | I115: =(I82/100)*($C$8*1000) -> 723.36997 | J115: =(J82/100)*($C$8*1000) -> 641.16883 | K115: =(K82/100)*($C$8*1000) -> 579.78963 | L115: =(L82/100)*($C$8*1000) -> 518.41044 | M115: =(M82/100)*($C$8*1000) -> 498.93259 | N115: =(N82/100)*($C$8*1000) -> 479.45474
B116: Tracteurs routiers | D116: =(D83/100)*($C$8*1000) -> 796.14609 | E116: =(E83/100)*($C$8*1000) -> 788.43005 | I116: =(I83/100)*($C$8*1000) -> 693.81844 | J116: =(J83/100)*($C$8*1000) -> 614.97544 | K116: =(K83/100)*($C$8*1000) -> 556.10373 | L116: =(L83/100)*($C$8*1000) -> 497.23203 | M116: =(M83/100)*($C$8*1000) -> 478.54991 | N116: =(N83/100)*($C$8*1000) -> 459.86778
...

Sheet donnees parc
B3: Extrait du SDES 2019. Base : RSVERO (remontée des contrôles techniques).
B4: Traitement novembre 2022.
C6: inf à 7,5t | D6: ]7,5t-12t] | E6: ]12t-16t] | F6: ]16t-19t] | G6: ]19t-26t] | H6: sup à > 26t | J6: Tracteurs routiers
B7: Taille du parc | C7: moins de 7,5T | D7: 7.5 à moins de 12T | E7: 12 à moins de 16T | F7: 16 à moins de 19T | G7: 19 à moins de 26T | H7: 26T et plus | I7: Ensemble camions | J7: Tracteurs routiers | K7: Ensemble camion + tracteur
B8: Ensemble du parc | C8: 19700 | D8: 47300 | E8: 32900 | F8: 66400 | G8: 65100 | H8: 74000 | I8: 305600 | J8: 215600 | K8: 521200 | L8: =K8*K12/10^6 -> 25330.32
B9: 0 à 8 ans | C9: 9100 | D9: 19600 | E9: 13700 | F9: 25100 | G9: 30000 | H9: 50600 | I9: 148100 | J9: 181400 | K9: 329500 | L9: =K9*K13/10^6 -> 22175.35
B11: Parcours annuel moyen 2019 (km) | C11: moins de 7,5T | D11: 7.5 à moins de 12T | E11: 12 à moins de 16T | F11: 16 à moins de 19T | G11: 19 à moins de 26T | H11: 26T et plus | I11: Ensemble camions | J11: Tracteurs routiers | K11: Ensemble camion + tracteur
B12: Ensemble du parc | C12: 13800 | D12: 19400 | E12: 20000 | F12: 26300 | G12: 32900 | H12: 34700 | I12: 27200 | J12: 78900 | K12: 48600
B13: 0 à 8 ans | C13: 20400 | D13: 31100 | E13: 31400 | F13: 44300 | G13: 51300 | H13: 41000 | I13: 40200 | J13: 89500 | K13: 67300 | L13: camions | M13: tracteurs | N13: ensemble
A14: km | B14: Ensemble du parc | C14: =C8*C12/10^6 -> 271.86 | D14: =D8*D12/10^6 -> 917.62 | E14: =E8*E12/10^6 -> 658 | F14: =F8*F12/10^6 -> 1746.32 | G14: =G8*G12/10^6 -> 2141.79 | H14: =H8*H12/10^6 -> 2567.8 | I14: =I8*I12/10^6 -> 8312.32 | J14: =J8*J12/10^6 -> 17010.84 | K14: =K8*K12/10^6 -> 25330.32 | L14: =SUM(C14:H14) -> 8303.39 | M14: =J14 -> 17010.84 | N14: =L14+M14 -> 25314.23
A15: km | B15: 0-8 ans | C15: =C9*C13/10^6 -> 185.64 | D15: =D9*D13/10^6 -> 609.56 | E15: =E9*E13/10^6 -> 430.18 | F15: =F9*F13/10^6 -> 1111.93 | G15: =G9*G13/10^6 -> 1539 | H15: =H9*H13/10^6 -> 2074.6 | I15: =I9*I13/10^6 -> 5953.62 | J15: =J9*J13/10^6 -> 16235.3 | K15: =K9*K13/10^6 -> 22175.35 | L15: =SUM(C15:H15) -> 5950.91 | M15: =J15 -> 16235.3 | N15: =L15+M15 -> 22186.21
B16: % <8 ans | C16: =C15/C14 -> 0.68285147 | D16: =D15/D14 -> 0.66428369 | E16: =E15/E14 -> 0.653769 | F16: =F15/F14 -> 0.63672752 | G16: =G15/G14 -> 0.71855784 | H16: =H15/H14 -> 0.80792897 | I16: =I15/I14 -> 0.71624047 | J16: =J15/J14 -> 0.95440907 | K16: =K15/K14 -> 0.8754469
B17: % km tot | C17: =C14/$N14 -> 0.010739414 | D17: =D14/$N14 -> 0.036249177 | E17: =E14/$N14 -> 0.025993285 | F17: =F14/$N14 -> 0.068985705 | G17: =G14/$N14 -> 0.084608143 | H17: =H14/$N14 -> 0.10143702 | I17: =I14/$N14 -> 0.32836551 | J17: =J14/$N14 -> 0.67198726 | K17: =K14/$N14 -> 1.0006356
B19: Pour compte d'autrui | C19: Compte d’autrui : approche sectorielle des entreprises en considérant que les secteurs des transports (et location de camions) opérent essentiellement pour compte d'autrui.
B21: Taille du parc | C21: moins de 7,5T | D21: 7.5 à moins de 12T | E21: 12 à moins de 16T | F21: 16 à moins de 19T | G21: 19 à moins de 26T | H21: 26T et plus | I21: Ensemble camions | J21: Tracteurs routiers | K21: Ensemble camion + tracteur
B22: Tout âge | C22: 3200 | D22: 12800 | E22: 8000 | F22: 20000 | G22: 20600 | H22: 28500 | I22: 93100 | J22: 147400 | K22: 240500
B23: 0 à 8 ans | C23: 2200 | D23: 8500 | E23: 5000 | F23: 12000 | G23: 14500 | H23: 22700 | I23: 64900 | J23: 134100 | K23: 199000
B26: Ratio Pour Autrui / Ensemble | C26: moins de 7,5T | D26: 7.5 à moins de 12T | E26: 12 à moins de 16T | F26: 16 à moins de 19T | G26: 19 à moins de 26T | H26: 26T et plus | I26: Ensemble camions | J26: Tracteurs routiers | K26: Ensemble camion + tracteur
B27: Tout âge | C27: 0.16243655 | D27: 0.27061311 | E27: 0.24316109 | F27: 0.30120482 | G27: 0.31643625 | H27: 0.38513514 | I27: 0.3046466 | J27: 0.68367347 | K27: 0.46143515
B28: 0 à 8 ans | C28: 0.24175824 | D28: 0.43367347 | E28: 0.3649635 | F28: 0.47808765 | G28: 0.48333333 | H28: 0.4486166 | I28: 0.43821742 | J28: 0.73925028 | K28: 0.60394537
B30: Parcours annuel moyen 2019 (km) | C30: moins de 7,5T | D30: 7.5 à moins de 12T | E30: 12 à moins de 16T | F30: 16 à moins de 19T | G30: 19 à moins de 26T | H30: 26T et plus | I30: Ensemble camions | J30: Tracteurs routiers | K30: Ensemble camion + tracteur
B31: Tout âge | C31: 23100 | D31: 31200 | E31: 32900 | F31: 44700 | G31: 52900 | H31: 43000 | I31: 42400 | J31: 88900 | K31: 70900 | L31: =K22*K31/10^6 -> 17051.45
B32: 0 à 8 ans | C32: 27100 | D32: 36200 | E32: 38600 | F32: 56200 | G32: 64700 | H32: 47400 | I32: 50100 | J32: 94600 | K32: 80100 | L32: =K23*K32/10^6 -> 15939.9
B34: Ratio Pour Autrui / Ensemble | C34: moins de 7,5T | D34: 7.5 à moins de 12T | E34: 12 à moins de 16T | F34: 16 à moins de 19T | G34: 19 à moins de 26T | H34: 26T et plus | I34: Ensemble camions | J34: Tracteurs routiers | K34: Ensemble camion + tracteur
B35: Tout âge | C35: 1.673913 | D35: 1.6082474 | E35: 1.645 | F35: 1.6996198 | G35: 1.6079027 | H35: 1.2391931 | I35: 1.5588235 | J35: 1.1267427 | K35: 1.4588477
B36: 0 à 8 ans | C36: 1.3284314 | D36: 1.1639871 | E36: 1.2292994 | F36: 1.268623 | G36: 1.2612086 | H36: 1.1560976 | I36: 1.2462687 | J36: 1.0569832 | K36: 1.1901932

Sheet B&C
B3: Bus et cars
B5: I) Données sur les parts des énergies et consos des véh neufs
B7: A) Parcs roulants et immatriculations des autobus et autocars
B9: Evolution du parc et des immatriculations d’autobus et de cars
C11: 2018 | D11: 2019 | E11: 2020 | F11: 2021 | G11: 2022 | H11: 2023 | I11: 2025 | J11: 2030 | K11: 2035 | L11: 2040 | M11: 2045 | N11: 2050
B12: Parc (milliers) | C12: 90 | D12: 92 | E12: 92 | F12: 94 | G12: 94 | H12: =G12 -> 94 | I12: =94 -> 94 | J12: =94 -> 94 | K12: =94 -> 94 | L12: =94 -> 94 | M12: =94 -> 94 | N12: =94 -> 94
B13: Immatriculations (milliers) | C13: =C14+C15 -> 6.471 | D13: =D14+D15 -> 7.045 | E13: =E14+E15 -> 6.399 | F13: =F14+F15 -> 7.207 | G13: =G14+G15 -> 6.192 | H13: =H14+H15 -> 6.142 | I13: 6.2 | J13: 6.2 | K13: 6.2 | L13: 6.2 | M13: 6.2 | N13: 6.2
B14: dont autobus | C14: 1.691 | D14: 1.888 | E14: 1.849 | F14: 2.211 | G14: 1.911 | H14: 1.789 | I14: 1.9 | J14: 1.9 | K14: 1.9 | L14: 1.9 | M14: 1.9 | N14: 1.9
B15: dont autocars | C15: 4.78 | D15: 5.157 | E15: 4.55 | F15: 4.996 | G15: 4.281 | H15: 4.353 | I15: 4.3 | J15: 4.3 | K15: 4.3 | L15: 4.3 | M15: 4.3 | N15: 4.3
B17: durée de vie | C17: =C12/C13 -> 13.908206 | D17: =D12/D13 -> 13.058907 | E17: =E12/E13 -> 14.377246 | F17: =F12/F13 -> 13.042875 | G17: =G12/G13 -> 15.180879 | H17: =H12/H13 -> 15.304461 | I17: =I12/I13 -> 15.16129 | J17: =J12/J13 -> 15.16129 | ... N17: =N12/N13 -> 15.16129
B19: % bus dans les immat
B21: Evolution du kilométrage moyen
C22: 2018 | D22: 2019 | E22: 2020 | F22: 2021 | G22: 2022
B23: Autobus et autocars pavillon français | C23: 34109.517 | D23: 33528.401 | E23: 25856.157 | F23: 25856.157 | G23: 25856.157
B26: A1) Evolution des parts de marché des immatriculations
B28: dont autobus
B29: Parts de marché des énergies dans les immatriculations annuelles d'autobus
Q30: Part de marché des bus neufs (%)
B31: Bus | C31: 2018 | D31: 2019 | E31: 2020 | F31: 2021 | G31: 2022 | H31: 2023 | I31: 2025 | J31: 2030 | K31: 2035 | L31: 2040 | M31: 2045 | N31: 2050 | Q31: % | R31: 2023 | S31: 2025 | T31: 2030 | U31: 2035 | V31: 2040 | W31: 2045 | X31: 2050
B32: Gazole | C32: 0.80603193 | D32: 0.61493644 | E32: 0.53758789 | F32: 0.24242424 | G32: 0.12192569 | H32: 0.19333996 | I32: 0.2 | J32: 0.05 | K32: 0 | L32: 0 | M32: 0 | N32: 0 | Q32: Thermiques | R32: 0.19333996 | S32: 0.2 | T32: 0.05 | U32: 0 | V32: 0 | W32: 0 | X32: 0
B33: GNV | C33: 0.15198108 | D33: 0.24417373 | E33: 0.35911303 | F33: 0.48032564 | G33: 0.49659864 | H33: 0.43737575 | I33: 0.3 | J33: 0.05 | K33: 0 | L33: 0 | M33: 0 | N33: 0 | Q33: GNV | R33: 0.43737575 | S33: 0.3 | T33: 0.05 | U33: 0 | V33: 0 | W33: 0 | X33: 0
B34: Electrique | C34: 0.039621526 | D34: 0.13983051 | E34: 0.094645754 | F34: 0.27725011 | G34: 0.38147567 | H34: 0.36928429 | I34: 0.5 | J34: 0.89 | K34: 0.99 | L34: 0.99 | M34: 0.99 | N34: 0.99 | Q34: Electrique | R34: 0.36928429 | S34: 0.5 | T34: 0.89 | U34: 0.99 | V34: 0.99 | W34: 0.99 | X34: 0.99
B35: H2 | C35: 0.0023654642 | D35: 0.001059322 | E35: 0.0086533261 | F35: 0 | G35: 0 | H35: 0 | I35: 0 | J35: 0.01 | K35: 0.01 | L35: 0.01 | M35: 0.01 | N35: 0.01 | Q35: H2 | R35: 0 | S35: 0 | T35: 0.01 | U35: 0.01 | V35: 0.01 | W35: 0.01 | X35: 0.01
B36: check | C36: =SUM(C32:C35) -> 1 | D36: =SUM(D32:D35) -> 1 | E36: =SUM(E32:E35) -> 1 | F36: =SUM(F32:F35) -> 1 | G36: =SUM(G32:G35) -> 1 | H36: =SUM(H32:H35) -> 1 | I36: =SUM(I32:I35) -> 1 | J36: =SUM(J32:J35) -> 1 | ... N36: =SUM(N32:N35) -> 1
B39: Parts de marché des énergies dans les immatriculations annuelles d’autocars
Q40: Part de marché des autocars neufs (%)
B41: Cars | C41: 2018 | D41: 2019 | E41: 2020 | F41: 2021 | G41: 2022 | H41: 2023 | I41: 2025 | J41: 2030 | K41: 2035 | L41: 2040 | M41: 2045 | N41: 2050 | Q41: % | R41: 2023 | S41: 2025 | T41: 2030 | U41: 2035 | V41: 2040 | W41: 2045 | X41: 2050
B42: Gazole et cars B100 | C42: 0.98284519 | D42: 0.96800465 | E42: 0.91450549 | F42: 0.86289031 | G42: 0.83578603 | H42: =1-H43-H44-H45 -> 0.87680085 | I42: 0.9 | J42: 0.67 | K42: 0.48 | L42: 0.12 | M42: 0.11 | N42: 0.1 | Q42: Thermiques | R42: 0.87680085 | S42: 0.9 | T42: =1-T43-T44-T45 -> 0.67 | U42: =1-U43-U44-U45 -> 0.48 | V42: =1-V43-V44-V45 -> 0.12 | W42: =1-W43-W44-W45 -> 0.11 | X42: =1-X43-X44-X45 -> 0.1
B43: GNV | C43: 0.011924686 | D43: 0.025208455 | E43: 0.08 | F43: 0.13230584 | G43: 0.14552675 | H43: 0.11348495 | I43: 0.08 | J43: 0.03 | K43: 0 | L43: 0 | M43: 0 | N43: 0 | Q43: GNV | R43: 0.11348495 | S43: 0.08 | T43: 0.03 | U43: 0 | V43: 0 | W43: 0 | X43: 0
B44: Electrique | C44: 0.0052301255 | D44: 0.0032964902 | E44: 0.0010989011 | F44: 0.0018014412 | G44: 0.014716188 | H44: 0.0057431656 | I44: 0.02 | J44: 0.296 | K44: 0.5 | L44: 0.85 | M44: 0.85 | N44: 0.85 | Q44: Electrique | R44: 0.0057431656 | S44: 0.02 | T44: 0.296 | U44: 0.5 | V44: 0.85 | W44: 0.85 | X44: 0.85
B45: H2 | C45: 0 | D45: 0.0034904014 | E45: 0.0043956044 | F45: 0.0030024019 | G45: 0.0039710348 | H45: 0.0039710348 | I45: 0 | J45: 0.004 | K45: 0.02 | L45: 0.03 | M45: 0.04 | N45: 0.05 | Q45: H2 | R45: 0.0039710348 | S45: 0 | T45: 0.004 | U45: 0.02 | V45: 0.03 | W45: 0.04 | X45: 0.05
B46: dont gazole B100 | C46: 0 | D46: 0.0034904014 | E46: 0.0043956044 | F46: 0.0030024019 | G46: 0.0039710348 | H46: 0.08
B47: check | C47: =SUM(C42:C45) -> 1 | D47: =SUM(D42:D45) -> 1 | E47: =SUM(E42:E45) -> 1 | F47: =SUM(F42:F45) -> 1 | G47: =SUM(G42:G45) -> 1 | H47: =SUM(H42:H45) -> 1 | I47: =SUM(I42:I45) -> 1 | J47: =SUM(J42:J45) -> 1 | ... N47: =SUM(N42:N45) -> 1
B49: autobus et autocars
B50: Parts de marché des énergies dans les immatriculations annuelles d'autobus et d’autocars
B52: Bus et cars | C52: 2018 | D52: 2019 | E52: 2020 | F52: 2021 | G52: 2022 | H52: 2023 | I52: 2025 | J52: 2030 | K52: 2035 | L52: 2040 | M52: 2045 | N52: 2050
B53: Gazole | C53: =(C$14*C32+C$15*C42)/(C$13) -> 0.9366404 | D53: =(D$14*D32+D$15*D42)/(D$13) -> 0.87338538 | E53: =(E$14*E32+E$15*E42)/(E$13) -> 0.80559462 | F53: =(F$14*F32+F$15*F42)/(F$13) -> 0.67254059 | G53: =(G$14*G32+G$15*G42)/(G$13) -> 0.61547158 | H53: =(H$14*H32+H$15*H42)/(H$13) -> 0.67772701 | I53: =(I$14*I32+I$15*I42)/(I$13) -> 0.68548387 | J53: =(J$14*J32+J$15*J42)/(J$13) -> 0.48 | ... N53: =(N$14*N32+N$15*N42)/(N$13) -> 0.069354839 | O53: gazole
B54: GNV | C54: =(C$14*C33+C$15*C43)/(C$13) -> 0.048524185 | D54: =(D$14*D33+D$15*D43)/(D$13) -> 0.083889283 | E54: =(E$14*E33+E$15*E43)/(E$13) -> 0.1606501 | F54: =(F$14*F33+F$15*F43)/(F$13) -> 0.23907312 | G54: =(G$14*G33+G$15*G43)/(G$13) -> 0.25387597 | H54: =(H$14*H33+H$15*H43)/(H$13) -> 0.20782566 | I54: =(I$14*I33+I$15*I43)/(I$13) -> 0.14741935 | J54: =(J$14*J33+J$15*J43)/(J$13) -> 0.036129032 | ... N54: =(N$14*N33+N$15*N43)/(N$13) -> 0 | O54: gnv
B55: Electrique | C55: =(C$14*C34+C$15*C44)/(C$13) -> 0.014217277 | D55: =(D$14*D34+D$15*D44)/(D$13) -> 0.039886444 | E55: =(E$14*E34+E$15*E44)/(E$13) -> 0.028129395 | F55: =(F$14*F34+F$15*F44)/(F$13) -> 0.086304981 | G55: =(G$14*G34+G$15*G44)/(G$13) -> 0.12790698 | H55: =(H$14*H34+H$15*H44)/(H$13) -> 0.11163295 | I55: =(I$14*I34+I$15*I44)/(I$13) -> 0.16709677 | J55: =(J$14*J34+J$15*J44)/(J$13) -> 0.47803226 | ... N55: =(N$14*N34+N$15*N44)/(N$13) -> 0.89290323 | O55: élec
B56: H2 | C56: =(C$14*C35+C$15*C45)/(C$13) -> 0.00061814248 | D56: =(D$14*D35+D$15*D45)/(D$13) -> 0.0028388928 | E56: =(E$14*E35+E$15*E45)/(E$13) -> 0.005625879 | F56: =(F$14*F35+F$15*F45)/(F$13) -> 0.0020813098 | G56: =(G$14*G35+G$15*G45)/(G$13) -> 0.002745478 | H56: =(H$14*H35+H$15*H45)/(H$13) -> 0.0028143788 | I56: =(I$14*I35+I$15*I45)/(I$13) -> 0 | J56: =(J$14*J35+J$15*J45)/(J$13) -> 0.0058387097 | ... N56: =(N$14*N35+N$15*N45)/(N$13) -> 0.037741935 | O56: h2
B57: check | C57: =SUM(C53:C56) -> 1 | D57: =SUM(D53:D56) -> 1 | E57: =SUM(E53:E56) -> 1 | F57: =SUM(F53:F56) -> 1 | G57: =SUM(G53:G56) -> 1 | H57: =SUM(H53:H56) -> 1 | I57: =SUM(I53:I56) -> 1 | J57: =SUM(J53:J56) -> 1 | ... N57: =SUM(N53:N56) -> 1
B58: (*) : on suppose que les autobus hybrides sont des hybrides électriques-diesel non rechargeables
B61: II) Parts de marché des énergies et consommations sur le parc roulant
B63: A2) Evolution des parts de marché des énergies du parc roulant
B66: Parts de marché des énergies dans les parcs roulants d'autobus et d’autocars
Q67: Parc roulant (en %)
B68: Bus et cars | C68: 2018 | D68: 2019 | E68: 2020 | F68: 2021 | G68: 2022 | H68: 2023 | I68: 2025 | J68: 2030 | K68: 2035 | L68: 2040 | M68: 2045 | N68: 2050 | R68: 2015 | S68: 2020 | T68: 2025 | U68: 2030 | V68: 2035 | W68: 2040 | X68: 2045 | Y68: 2050
B69: Gazole | C69: =1-C70-C71-C72 -> 0.95555556 | D69: =1-D70-D71-D72 -> 0.95652174 | E69: =1-E70-E71-E72 -> 0.95652174 | F69: 0.93256075 | G69: 0.91032964 | H69: 0.88965499 | I69: 0.85598673 | J69: 0.71617886 | K69: 0.58229819 | L69: 0.4279255 | M69: 0.27654869 | N69: 0.18455178 | Q69: Gazole | R69: 1 | S69: 0.97523906 | T69: 0.85598673 | U69: 0.71617886 | V69: 0.58229819 | W69: 0.4279255 | X69: 0.27654869 | Y69: 0.18455178
B70: GNV | C70: 0.033333333 | D70: 0.032608696 | E70: 0.032608696 | F70: 0.053074042 | G70: 0.069829398 | H70: 0.084495853 | I70: 0.096518055 | J70: 0.12896563 | K70: 0.078504147 | L70: 0.020658888 | M70: 0.0038483185 | N70: 0.0022340426 | Q70: GNV | R70: 0 | S70: 0.01796208 | T70: 0.096518055 | U70: 0.12896563 | V70: 0.078504147 | W70: 0.020658888 | X70: 0.0038483185 | Y70: 0.0022340426
B71: Electrique | C71: 0.011111111 | D71: 0.010869565 | E71: 0.010869565 | F71: 0.014365204 | G71: 0.019840965 | H71: 0.025849152 | I71: 0.046232215 | J71: 0.15272292 | K71: 0.3342742 | L71: 0.53964149 | M71: 0.70031671 | N71: 0.78754431 | Q71: Electrique | R71: 0 | S71: 0.0065414191 | T71: 0.046232215 | U71: 0.15272292 | V71: 0.3342742 | W71: 0.53964149 | X71: 0.70031671 | Y71: 0.78754431
B72: H2 | C72: =0 -> 0 | D72: =0 -> 0 | E72: =0 -> 0 | F72: =0 -> 0 | G72: =0 -> 0 | H72: =0 -> 0 | I72: 0.0012629961 | J72: 0.0021325912 | K72: 0.004923461 | L72: 0.011774125 | M72: 0.019286273 | N72: 0.02566987 | Q72: H2 | R72: 0 | S72: 0.0002574388 | T72: 0.0012629961 | U72: 0.0021325912 | V72: 0.004923461 | W72: 0.011774125 | X72: 0.019286273 | Y72: 0.02566987
B73: check | C73: =SUM(C69:C72) -> 1 | D73: =SUM(D69:D72) -> 1 | E73: =SUM(E69:E72) -> 1 | F73: =SUM(F69:F72) -> 1 | G73: =SUM(G69:G72) -> 1 | H73: =SUM(H69:H72) -> 1 | I73: 1 | J73: 1 | K73: 1 | L73: 1 | M73: 1 | N73: 1 | Q73: Ensemble | R73: 1 | S73: 1 | T73: 1 | U73: 1 | V73: 1 | W73: 1 | X73: 1 | Y73: 1
B75: B) Consommations des bus et cars
C77: 2018 | D77: 2019 | E77: 2020 | G77: Ratio B&C / PL | I77: 1
B78: Gazole | C78: =PL!C154 -> 33.7 | D78: =PL!D154 -> 33.3 | E78: =PL!E154 -> 33
B79: GNV | C79: =PL!C155 -> 28.645 | D79: =PL!D155 -> 28.305 | E79: =PL!E155 -> 28.05
B80: Electrique | C80: =PL!C156 -> 125 | D80: =PL!D156 -> 125 | E80: =PL!E156 -> 125
B81: H2 | C81: =PL!C157 -> 6.9147936 | D81: =PL!D157 -> 6.9147936 | E81: =PL!E157 -> 6.9147936
C84: 2018 | D84: 2019 | E84: 2020 | F84: 2021 | G84: 2022 | H84: 2023 | I84: 2025 | J84: 2030 | K84: 2035 | L84: 2040 | M84: 2045 | N84: 2050
B85: Gazole | C85: =PL!C154*$I$77 -> 33.7 | D85: =PL!D154*$I$77 -> 33.3 | E85: =PL!E154*$I$77 -> 33 | F85: =PL!F154*$I$77 -> 32.9 | G85: =PL!G154*$I$77 -> 32.6 | H85: =PL!H154*$I$77 -> 32.099114 | I85: =PL!I154*$I$77 -> 30.736683 | J85: =PL!J154*$I$77 -> 27.061103 | ... N85: =PL!N154*$I$77 -> 23.538166
B86: GNV | C86: =PL!C155*$I$77 -> 28.645 | D86: =PL!D155*$I$77 -> 28.305 | E86: =PL!E155*$I$77 -> 28.05 | F86: =PL!F155*$I$77 -> 27.965 | G86: =PL!G155*$I$77 -> 27.71 | H86: =PL!H155*$I$77 -> 27.284247 | I86: =PL!I155*$I$77 -> 26.200241 | J86: =PL!J155*$I$77 -> 25.344515 | ... N86: =PL!N155*$I$77 -> 25
B87: Electrique | C87: =PL!C156*$I$77 -> 125 | D87: =PL!D156*$I$77 -> 125 | E87: =PL!E156*$I$77 -> 125 | F87: =PL!F156*$I$77 -> 125 | G87: =PL!G156*$I$77 -> 125 | H87: =PL!H156*$I$77 -> 125 | I87: =PL!I156*$I$77 -> 124.8803 | J87: =PL!J156*$I$77 -> 118.89151 | ... N87: =PL!N156*$I$77 -> 100.20882
B88: H2 | C88: =PL!C157*$I$77 -> 6.9147936 | D88: =PL!D157*$I$77 -> 6.9147936 | E88: =PL!E157*$I$77 -> 6.9147936 | F88: =PL!F157*$I$77 -> 6.9147936 | G88: =PL!G157*$I$77 -> 6.9147936 | H88: =PL!H157*$I$77 -> 6.9147936 | I88: =PL!I157*$I$77 -> 6.9147936 | J88: =PL!J157*$I$77 -> 6.1058586 | ... N88: =PL!N157*$I$77 -> 5.1
B91: Intensité énergétique
B92: kWh/100 km | C92: 2018 | D92: 2019 | E92: 2020 | F92: 2021 | G92: 2022 | H92: 2023 | I92: 2025 | J92: 2030 | K92: 2035 | L92: 2040 | M92: 2045 | N92: 2050
B93: Gazole (kWh/100km) | C93: =PL!C172*0.8 -> 269.6 | D93: =PL!D172*0.8 -> 266.4 | E93: =PL!E172*0.8 -> 264 | F93: =PL!F172*0.8 -> 263.2 | G93: =PL!G172*0.8 -> 260.8 | H93: =PL!H172*0.8 -> 256.79291 | I93: =PL!I172*0.8 -> 245.89347 | J93: =PL!J172*0.8 -> 216.48883 | ... N93: =PL!N172*0.8 -> 188.30533
B94: GNV (kWh/100km) | C94: =PL!C173*0.8 -> 316.2408 | D94: =PL!D173*0.8 -> 312.4872 | E94: =PL!E173*0.8 -> 309.672 | F94: =PL!F173*0.8 -> 308.7336 | G94: =PL!G173*0.8 -> 305.9184 | H94: =PL!H173*0.8 -> 301.21809 | I94: =PL!I173*0.8 -> 289.25066 | J94: =PL!J173*0.8 -> 279.80345 | ... N94: =PL!N173*0.8 -> 276
B95: Electrique (kWh/100km) | C95: =PL!C174*0.8 -> 100 | D95: =PL!D174*0.8 -> 100 | E95: =PL!E174*0.8 -> 100 | F95: =PL!F174*0.8 -> 100 | G95: =PL!G174*0.8 -> 100 | H95: =PL!H174*0.8 -> 100 | I95: =PL!I174*0.8 -> 99.904238 | J95: =PL!J174*0.8 -> 95.113211 | ... N95: =PL!N174*0.8 -> 80.167056
B96: H2 (kWh/100km) | C96: =PL!C175*0.8 -> 184.2101 | D96: =PL!D175*0.8 -> 184.2101 | E96: =PL!E175*0.8 -> 184.2101 | F96: =PL!F175*0.8 -> 184.2101 | G96: =PL!G175*0.8 -> 184.2101 | H96: =PL!H175*0.8 -> 184.2101 | I96: =PL!I175*0.8 -> 184.2101 | J96: =PL!J175*0.8 -> 162.66007 | ... N96: =PL!N175*0.8 -> 135.864
B99: III) Parts de marché des énergies et consommations sur le parc roulant
C101: 2018 | D101: 2019 | E101: 2020 | F101: 2021 | G101: 2022 | H101: 2023 | I101: 2025 | J101: 2030 | K101: 2035 | L101: 2040 | M101: 2045 | N101: 2050
B102: Bus et cars | C102: =Trafic!C114 -> 3.2 | D102: =Trafic!D114 -> 3.3 | E102: =Trafic!E114 -> 2.4 | F102: =Trafic!F114 -> 2.8 | G102: =Trafic!G114 -> 3.1 | H102: =Trafic!H114 -> 3.2984 | I102: =Trafic!I114 -> 3.53 | J102: =Trafic!J114 -> 3.96 | ... N102: =Trafic!N114 -> 4.29
B104: Mtep VP | C104: 2018 | D104: 2019 | E104: 2020 | F104: 2021 | G104: 2022 | H104: 2023 | I104: 2025 | J104: 2030 | K104: 2035 | L104: 2040 | M104: 2045 | N104: 2050
B105: Gazole | C105: =(C69)*C93/100*C$102/11.63 -> 0.70883653 | D105: =(D69)*D93/100*D$102/11.63 -> 0.72304161 | E105: =(E69)*E93/100*E$102/11.63 -> 0.52111107 | F105: =(F69)*F93/100*F$102/11.63 -> 0.59093721 | G105: =(G69)*G93/100*G$102/11.63 -> 0.63283173 | H105: =(H69)*H93/100*H$102/11.63 -> 0.64793026 | I105: =(I69)*I93/100*I$102/11.63 -> 0.63886488 | J105: =(J69)*J93/100*J$102/11.63 -> 0.52792528 | ... N105: =(N69)*N93/100*N$102/11.63 -> 0.12819127
B106: GNV | C106: =(C70)*C94/100*C$102/11.63 -> 0.029004602 | D106: =(D70)*D94/100*D$102/11.63 -> 0.028913448 | E106: =(E70)*E94/100*E$102/11.63 -> 0.020838521 | F106: =(F70)*F94/100*F$102/11.63 -> 0.039449761 | G106: =(G70)*G94/100*G$102/11.63 -> 0.056941103 | H106: =(H70)*H94/100*H$102/11.63 -> 0.072183852 | I106: =(I70)*I94/100*I$102/11.63 -> 0.084737941 | J106: =(J70)*J94/100*J$102/11.63 -> 0.12286905 | ... N106: =(N70)*N94/100*N$102/11.63 -> 0.0022744589
B107: Electrique | C107: =(C71)*C95/100*C$102/11.63 -> 0.0030572275 | D107: =(D71)*D95/100*D$102/11.63 -> 0.0030842274 | E107: =(E71)*E95/100*E$102/11.63 -> 0.0022430745 | F107: =(F71)*F95/100*F$102/11.63 -> 0.0034585185 | G107: =(G71)*G95/100*G$102/11.63 -> 0.0052886493 | H107: =(H71)*H95/100*H$102/11.63 -> 0.0073311129 | I107: =(I71)*I95/100*I$102/11.63 -> 0.014019212 | J107: =(J71)*J95/100*J$102/11.63 -> 0.049460731 | ... N107: =(N71)*N95/100*N$102/11.63 -> 0.23288875
B108: Hydrogène | C108: =(C72)*C96/100*C$102/11.63 -> 0 | D108: =(D72)*D96/100*D$102/11.63 -> 0 | E108: =(E72)*E96/100*E$102/11.63 -> 0 | F108: =(F72)*F96/100*F$102/11.63 -> 0 | G108: =(G72)*G96/100*G$102/11.63 -> 0 | H108: =(H72)*H96/100*H$102/11.63 -> 0 | I108: =(I72)*I96/100*I$102/11.63 -> 0.00070617192 | J108: =(J72)*J96/100*J$102/11.63 -> 0.0011811472 | ... N108: =(N72)*N96/100*N$102/11.63 -> 0.012864877
B109: Ensemble | C109: =SUM(C105:C108) -> 0.74089836 | D109: =SUM(D105:D108) -> 0.75503928 | E109: =SUM(E105:E108) -> 0.54419267 | F109: =SUM(F105:F108) -> 0.63384549 | G109: =SUM(G105:G108) -> 0.69506149 | H109: =SUM(H105:H108) -> 0.72744523 | I109: =SUM(I105:I108) -> 0.7383282 | J109: =SUM(J105:J108) -> 0.70143621 | ... N109: =SUM(N105:N108) -> 0.37621935
B112: B&C - Twh | C112: 2018 | D112: 2019 | E112: 2020 | F112: 2021 | G112: 2022 | H112: 2023 | I112: 2025 | J112: 2030 | K112: 2035 | L112: 2040 | M112: 2045 | N112: 2050
B113: Gazole | C113: =C105*11.63 -> 8.2437689 | D113: =D105*11.63 -> 8.4089739 | E113: =E105*11.63 -> 6.0605217 | F113: =F105*11.63 -> 6.8725997 | G113: =G105*11.63 -> 7.359833 | H113: =H105*11.63 -> 7.535429 | I113: =I105*11.63 -> 7.4299985 | J113: =J105*11.63 -> 6.139771 | ... N113: =N105*11.63 -> 1.4908644
B114: GNV | C114: =C106*11.63 -> 0.33732352 | D114: =D106*11.63 -> 0.3362634 | E114: =E106*11.63 -> 0.242352 | F114: =F106*11.63 -> 0.45880072 | G114: =G106*11.63 -> 0.66222503 | H114: =H106*11.63 -> 0.8394982 | I114: =I106*11.63 -> 0.98550225 | J114: =J106*11.63 -> 1.4289671 | ... N114: =N106*11.63 -> 0.026451957
B115: Electrique | C115: =C107*11.63 -> 0.035555556 | D115: =D107*11.63 -> 0.035869565 | E115: =E107*11.63 -> 0.026086957 | F115: =F107*11.63 -> 0.04022257 | G115: =G107*11.63 -> 0.061506991 | H115: =H107*11.63 -> 0.085260843 | I115: =I107*11.63 -> 0.16304343 | J115: =J107*11.63 -> 0.57522831 | ... N115: =N107*11.63 -> 2.7084962
B116: Hydrogène | C116: =C108*11.63 -> 0 | D116: =D108*11.63 -> 0 | E116: =E108*11.63 -> 0 | F116: =F108*11.63 -> 0 | G116: =G108*11.63 -> 0 | H116: =H108*11.63 -> 0 | I116: =I108*11.63 -> 0.0082127794 | J116: =J108*11.63 -> 0.013736742 | ... N116: =N108*11.63 -> 0.14961852
B117: Ensemble | C117: =C109*11.63 -> 8.616648 | D117: =D109*11.63 -> 8.7811069 | E117: =E109*11.63 -> 6.3289607 | F117: =F109*11.63 -> 7.371623 | G117: =G109*11.63 -> 8.0835651 | H117: =H109*11.63 -> 8.460188 | I117: =I109*11.63 -> 8.586757 | J117: =J109*11.63 -> 8.1577031 | ... N117: =N109*11.63 -> 4.3754311

Sheet 2RM
A2: 1) Deux roues motorisés
A5: Mix énergétique | B5: (moyennes motos, motocyclettes)
A6: % des immatriculations | B6: observé | C6: observé | D6: observé | E6: observé | F6: observé
B7: 2015 | C7: 2016 | D7: 2017 | E7: 2018 | F7: 2019 | G7: 2020 | H7: 2021 | I7: 2022 | J7: 2023 | K7: 2025 | L7: 2030 | M7: 2035 | N7: 2040 | O7: 2045 | P7: 2050
A8: % essence | B8: 0.98843692 | C8: 0.97516497 | D8: 0.9672865 | E8: 0.95262318 | F8: 0.94323566 | G8: 0.94141541 | H8: =1-H9 -> 0.85208187 | I8: =1-I9 -> 0.76004125 | J8: =I8 -> 0.76004125 | K8: 0.6707077 | L8: 0.4 | M8: 0.325 | N8: 0.25 | O8: 0.125 | P8: 0
A9: % électricité | B9: 0.011563079 | C9: 0.02483503 | D9: 0.032713502 | E9: 0.047376824 | F9: 0.05676434 | G9: 0.058584593 | H9: =0.67*G9+0.33*K9 -> 0.14791813 | I9: =0.33*G9+0.67*K9 -> 0.23995875 | J9: =I9 -> 0.23995875 | K9: 0.3292923 | L9: 0.6 | M9: 0.675 | N9: 0.75 | O9: 0.875 | P9: 1
A10: passage roulant - essence | G10: =1-G11 -> 0.98044326 | H10: =1-H11 -> 0.94910996 | I10: =1-I11 -> 0.91682716 | K10: =1-K11 -> 0.88549386 | L10: =1-L11 -> 0.6707077 | M10: =1-M11 -> 0.44892693 | N10: =1-N11 -> 0.325 | O10: =1-O11 -> 0.2375 | P10: =1-P11 -> 0.125
A11: passage roulant - élec | G11: =0.83*B9+0.17*G9 -> 0.019556737 | H11: =0.67*G11+0.33*K11 -> 0.05089004 | I11: =0.33*G11+0.67*K11 -> 0.083172837 | K11: =0.25*B9+0.5*G9+0.25*K9 -> 0.11450614 | L11: =0.25*G9+0.5*K9+0.25*L9 -> 0.3292923 | M11: =0.25*K9+0.5*L9+0.25*M9 -> 0.55107307 | N11: =0.25*L9+0.5*M9+0.25*N9 -> 0.675 | O11: =0.25*M9+0.5*N9+0.25*O9 -> 0.7625 | P11: =0.25*N9+0.5*O9+0.25*P9 -> 0.875
A13: % du parc roulant | B13: observé
B14: 2015 | C14: 2016 | D14: 2017 | E14: 2018 | F14: 2019 | G14: 2020 | H14: 2021 | I14: 2022 | J14: 2023 | K14: 2025 | L14: 2030 | M14: 2035 | N14: 2040 | O14: 2045 | P14: 2050
A15: % essence | B15: =1-B16 -> 1 | C15: =1-C16 -> 1 | D15: =1-D16 -> 0.99217731 | E15: =1-E16 -> 0.98826596 | F15: =1-F16 -> 0.98435461 | G15: =G10 -> 0.98044326 | H15: =H10 -> 0.94910996 | I15: =I10 -> 0.91682716 | J15: =I15 -> 0.91682716 | K15: =K10 -> 0.88549386 | L15: =L10 -> 0.6707077 | M15: =M10 -> 0.44892693 | N15: =N10 -> 0.325 | O15: =O10 -> 0.2375 | P15: =P10 -> 0.125
A16: % électricité | B16: =0% -> 0 | C16: =0.8*B16*0.2*G16 -> 0 | D16: =B16*0.6+G16*0.4 -> 0.0078226946 | E16: =0.4*B16+0.6*G16 -> 0.011734042 | F16: =B16*0.2+G16*0.8 -> 0.015645389 | G16: =G11 -> 0.019556737 | H16: =0.67*G16+0.33*K16 -> 0.05089004 | I16: =0.33*G16+0.67*K16 -> 0.083172837 | J16: =I16 -> 0.083172837 | K16: =K11 -> 0.11450614 | L16: =L11 -> 0.3292923 | M16: =M11 -> 0.55107307 | N16: =N11 -> 0.675 | O16: =O11 -> 0.7625 | P16: =P11 -> 0.875
A19: efficacité énergétique essence | E19: 1
A20: efficacité énergétique électricité | E20: 0.3
A22: Gains d'efficacité énergétique
B23: 2015 | C23: 2016 | D23: 2017 | E23: 2018 | F23: 2019 | G23: 2020 | H23: 2021 | I23: 2022 | J23: 2023 | K23: 2025 | L23: 2030 | M23: 2035 | N23: 2040 | O23: 2045 | P23: 2050
A24: Efficacité essence | B24: =0 -> 0 | C24: =0% -> 0 | D24: =0% -> 0 | E24: =0% -> 0 | F24: =E24 -> 0 | G24: =F24 -> 0 | H24: =G24 -> 0 | I24: =H24 -> 0 | J24: =I24 -> 0 | K24: 0.066666667 | L24: 0.1 | M24: 0.1375 | N24: 0.175 | O24: 0.2125 | P24: 0.25
A25: Efficacité électricité | B25: =0 -> 0 | C25: =0% -> 0 | D25: =0% -> 0 | E25: =0% -> 0 | F25: =E25 -> 0 | G25: =F25 -> 0 | H25: =G25 -> 0 | I25: =H25 -> 0 | J25: =I25 -> 0 | K25: 0.04 | L25: 0.06 | M25: 0.0825 | N25: 0.105 | O25: 0.1275 | P25: 0.15
B29: 2015 | C29: 2016 | D29: 2017 | E29: 2018 | F29: 2019 | G29: 2020 | H29: 2021 | I29: 2022 | J29: 2023 | K29: 2025 | L29: 2030 | M29: 2035 | N29: 2040 | O29: 2045 | P29: 2050
A30: Trafics 2RM | E30: =Trafic!C39 -> 11.340238 | F30: =Trafic!D39 -> 11.340238 | G30: =Trafic!E39 -> 9.5825009 | H30: =Trafic!F39 -> 9.8220635 | I30: =Trafic!G39 -> 11.069466 | J30: =I30 -> 11.069466 | K30: =Trafic!I39 -> 11.088283 | L30: =Trafic!J39 -> 11.1 | M30: =Trafic!K39 -> 11.10217 | N30: =Trafic!L39 -> 11.099269 | O30: =Trafic!M39 -> 11.091298 | P30: =Trafic!N39 -> 11.078257
A34: Mtep
A35: Mtep VP | B35: 2015 | C35: 2016 | D35: 2017 | E35: 2018 | F35: 2019 | G35: 2020 | H35: 2021 | I35: 2022 | J35: 2023 | K35: 2025 | L35: 2030 | M35: 2035 | N35: 2040 | O35: 2045 | P35: 2050
A36: Essence | B36: 0.43109493 | C36: 0.43407389 | D36: 0.43650341 | E36: 0.43910244 | F36: 0.43901604 | G36: 0.37096855 | H36: =$F36*(1-H24)*H15/$F15 -> 0.42329714 | I36: =$F36*(1-I24)*I15/$F15 -> 0.40889922 | J36: =$F36*(1-J24)*J15/$F15 -> 0.40889922 | K36: =$F36*(1-K24)*K15/$F15 -> 0.36859644 | L36: =$F36*(1-L24)*L15/$F15 -> 0.26921832 | M36: =$F36*(1-M24)*M15/$F15 -> 0.17268856 | N36: =$F36*(1-N24)*N15/$F15 -> 0.11958208 | O36: =$F36*(1-O24)*O15/$F15 -> 0.083414775 | P36: =$F36*(1-P24)*P15/$F15 -> 0.041811917
A37: Electricité | B37: =0 -> 0 | C37: =0 -> 0 | D37: =0 -> 0 | E37: =0 -> 0 | F37: =0 -> 0 | G37: =0 -> 0 | H37: =$F36*$E$20*(1-H25)*H16 -> 0.0067024631 | I37: =$F36*$E$20*(1-I25)*I16 -> 0.010954263 | J37: =$F36*$E$20*(1-J25)*J16 -> 0.010954263 | K37: =$F36*$E$20*(1-K25)*K16 -> 0.014477769 | L37: =$F36*$E$20*(1-L25)*L16 -> 0.040767217 | M37: =$F36*$E$20*(1-M25)*M16 -> 0.06659121 | N37: =$F36*$E$20*(1-N25)*N16 -> 0.079566169 | O37: =$F36*$E$20*(1-O25)*O16 -> 0.087620742 | P37: =$F36*$E$20*(1-P25)*P16 -> 0.097955454
A38: Somme | B38: =B36+B37 -> 0.43109493 | C38: =C36+C37 -> 0.43407389 | D38: =D36+D37 -> 0.43650341 | E38: =E36+E37 -> 0.43910244 | F38: =F36+F37 -> 0.43901604 | G38: =G36+G37 -> 0.37096855 | H38: =H36+H37 -> 0.42999961 | I38: =I36+I37 -> 0.41985348 | ... P38: =P36+P37 -> 0.13976737
E39: =E38/$E38-1 -> 0 | F39: =F38/$E38-1 -> -0.00019676122 | G39: =G38/$E38-1 -> -0.15516626 | H39: =H38/$E38-1 -> -0.020730539 | I39: =I38/$E38-1 -> -0.043837055 | J39: =J38/$E38-1 -> -0.043837055 | K39: =K38/$E38-1 -> -0.12759717 | L39: =L38/$E38-1 -> -0.29404733 | ... P39: =P38/$E38-1 -> -0.68169757

Sheet Autres_modes
B2: Le ferroviaire
B5: Mix fer
B7: Fer-observé (TWh) | C7: 2018 | D7: 2019 | E7: 2020 | F7: 2021 | G7: 2022 | H7: 2023
B8: Thermiques fer | C8: 1.4554397 | D8: 1.4584244 | E8: 1.2149312 | F8: 1.3932712 | G8: 1.4307845 | H8: 1.3446133
B9: Electricité ferroviaire | C9: 7.2754 | D9: 7.1854 | E9: 5.710499 | F9: 6.4794505 | G9: 6.9610792 | H9: 6.7008315
B10: Total fer | C10: =C8+C9 -> 8.7308397 | D10: =D8+D9 -> 8.6438244 | E10: =E8+E9 -> 6.9254302 | F10: =F8+F9 -> 7.8727217 | G10: =G8+G9 -> 8.3918637 | H10: =H8+H9 -> 8.0454449
B11: % gazole | C11: =C8/C10 -> 0.16670099 | D11: =D8/D10 -> 0.16872444 | E11: =E8/E10 -> 0.17543043 | F11: =F8/F10 -> 0.17697452 | G11: =G8/G10 -> 0.17049664 | H11: =H8/H10 -> 0.16712728
B12: %biogazole | C12: 0.063259045 | D12: 0.063286228 | E12: 0.062676039 | F12: 0.086495454 | G12: 0.087029045 | H12: 0.0888471
B14: TCU élec observé (TWh) | C14: 2018 | D14: 2019 | E14: 2020 | F14: 2021 | G14: 2022 | H14: 2023
B15: Electricité | C15: 1.3399102 | D15: 1.2815681 | E15: 1.213943 | F15: 1.347695 | G15: 1.5687328 | H15: 1.2598855
B17: Fer + TCU observé | C17: 2018 | D17: 2019 | E17: 2020 | F17: 2021 | G17: 2022 | H17: 2023
B18: Fer + TCU | C18: =C10+C15 -> 10.07075 | D18: =D10+D15 -> 9.9253925 | E18: =E10+E15 -> 8.1393732 | F18: =F10+F15 -> 9.2204167 | G18: =G10+G15 -> 9.9605965 | H18: =H10+H15 -> 9.3053303
B20: hypothèse gains d'efficacité énergétique | C20: 0.01
C21: 2018 | D21: 2019 | E21: 2020 | F21: 2021 | G21: 2022 | H21: 2023 | I21: 2025 | J21: 2030 | K21: 2035 | L21: 2040 | M21: 2045 | N21: 2050
B22: Hausse liée au trafic | H22: =Trafic!H23/Trafic!$H23 -> 1 | I22: =Trafic!I23/Trafic!$H23 -> 1.019643 | J22: =Trafic!J23/Trafic!$H23 -> 1.1361472 | K22: =Trafic!K23/Trafic!$H23 -> 1.2502245 | L22: =Trafic!L23/Trafic!$H23 -> 1.36722 | M22: =Trafic!M23/Trafic!$H23 -> 1.4871338 | N22: =Trafic!N23/Trafic!$H23 -> 1.6099659
B23: Hausse liée à gains d'efficacité énergétque | H23: =(1-$C$20)^(H21-$H21) -> 1 | I23: =(1-$C$20)^(I21-$H21) -> 0.9801 | J23: =(1-$C$20)^(J21-$H21) -> 0.93206535 | K23: =(1-$C$20)^(K21-$H21) -> 0.88638487 | L23: =(1-$C$20)^(L21-$H21) -> 0.84294319 | M23: =(1-$C$20)^(M21-$H21) -> 0.80163059 | N23: =(1-$C$20)^(N21-$H21) -> 0.76234271
B24: Hausse combinée | H24: =H22*H23 -> 1 | I24: =I22*I23 -> 0.99935206 | J24: =J22*J23 -> 1.0589635 | K24: =K22*K23 -> 1.1081801 | L24: =L22*L23 -> 1.1524888 | M24: =M22*M23 -> 1.1921319 | N24: =N22*N23 -> 1.2273458
C26: 2018 | D26: 2019 | E26: 2020 | F26: 2021 | G26: 2022 | H26: 2023 | I26: 2025 | J26: 2030 | K26: 2035 | L26: 2040 | M26: 2045 | N26: 2050
B27: Consommation du ferroviaire | C27: =C10 -> 8.7308397 | D27: =D10 -> 8.6438244 | E27: =E10 -> 6.9254302 | F27: =F10 -> 7.8727217 | G27: =G10 -> 8.3918637 | H27: =H10 -> 8.0454449 | I27: =$H27*I24 -> 8.0402319 | J27: =$H27*J24 -> 8.5198321 | K27: =$H27*K24 -> 8.9158016 | L27: =$H27*L24 -> 9.272285 | M27: =$H27*M24 -> 9.5912318 | N27: =$H27*N24 -> 9.8745426 | O27: =N27/H27 -> 1.2273458
C29: 2018 | D29: 2019 | E29: 2020 | F29: 2021 | G29: 2022 | H29: 2023 | I29: 2025 | J29: 2030 | K29: 2035 | L29: 2040 | M29: 2045 | N29: 2050
B30: % énergie trains au gazole ou biocarb | C30: =C8/C10 -> 0.16670099 | D30: =D8/D10 -> 0.16872444 | E30: =E8/E10 -> 0.17543043 | F30: =F8/F10 -> 0.17697452 | G30: =G8/G10 -> 0.17049664 | H30: =H8/H10 -> 0.16712728 | I30: 0.16 | J30: 0.16 | K30: 0.14 | L30: 0.12 | M30: 0.06 | N30: 0.04
B31: % énergie électricité | C31: =1-C30 -> 0.83329901 | D31: =1-D30 -> 0.83127556 | E31: =1-E30 -> 0.82456957 | F31: =1-F30 -> 0.82302548 | G31: =1-G30 -> 0.82950336 | H31: =1-H30 -> 0.83287272 | I31: =1-I30-I32 -> 0.84 | J31: =1-J30-J32 -> 0.84 | K31: =1-K30-K32 -> 0.85 | L31: =1-L30-L32 -> 0.86 | M31: =1-M30-M32 -> 0.91 | N31: =1-N30-N32 -> 0.92
B32: % énergie H2 | C32: =0 -> 0 | D32: =0 -> 0 | E32: =0 -> 0 | F32: =0 -> 0 | G32: =0 -> 0 | H32: =0 -> 0 | I32: 0 | J32: 0 | K32: 0.01 | L32: 0.02 | M32: 0.03 | N32: 0.04
I33: =I30+I31+I32 -> 1 | J33: =J30+J31+J32 -> 1 | K33: =K30+K31+K32 -> 1 | L33: =L30+L31+L32 -> 1 | M33: =M30+M31+M32 -> 1 | N33: =N30+N31+N32 -> 1
B34: Consommation d'énergie des transports ferrés (ferroviaire et transports urbains électriques) (Mtep)
B35: hyp croissance tcu | C35: 0.01 | E35: sur 25 ans | F35: =(1+C35)^25 -> 1.282432
C36: observé | D36: observé | E36: observé | F36: observé | G36: observé | H36: observé
C37: 2018 | D37: 2019 | E37: 2020 | F37: 2021 | G37: 2022 | H37: 2023 | I37: 2025 | J37: 2030 | K37: 2035 | L37: 2040 | M37: 2045 | N37: 2050
B38: Transports ferroviaires SNCF | C38: =SUM(C39:C41) -> 8.7308397 | D38: =SUM(D39:D41) -> 8.6438244 | E38: =SUM(E39:E41) -> 6.9254302 | F38: =SUM(F39:F41) -> 7.8727217 | G38: =SUM(G39:G41) -> 8.3918637 | H38: =SUM(H39:H41) -> 8.0454449 | I38: =I27 -> 8.0402319 | J38: =J27 -> 8.5198321 | K38: =K27 -> 8.9158016 | L38: =L27 -> 9.272285 | M38: =M27 -> 9.5912318 | N38: =N27 -> 9.8745426
B39: Gazole | C39: =C8 -> 1.4554397 | D39: =D8 -> 1.4584244 | E39: =E8 -> 1.2149312 | F39: =F8 -> 1.3932712 | G39: =G8 -> 1.4307845 | H39: =H8 -> 1.3446133 | I39: =I38*I30 -> 1.2864371 | J39: =J38*J30 -> 1.3631731 | K39: =K38*K30 -> 1.2482122 | L39: =L38*L30 -> 1.1126742 | M39: =M38*M30 -> 0.57547391 | N39: =N38*N30 -> 0.39498171
B40: Electricité | C40: =C9 -> 7.2754 | D40: =D9 -> 7.1854 | E40: =E9 -> 5.710499 | F40: =F9 -> 6.4794505 | G40: =G9 -> 6.9610792 | H40: =H9 -> 6.7008315 | I40: =I38*I31 -> 6.7537948 | J40: =J38*J31 -> 7.156659 | K40: =K38*K31 -> 7.5784313 | L40: =L38*L31 -> 7.9741651 | M40: =M38*M31 -> 8.728021 | N40: =N38*N31 -> 9.0845792
B41: H2 | C41: =0 -> 0 | D41: =0 -> 0 | E41: =0 -> 0 | F41: =0 -> 0 | G41: =0 -> 0 | H41: =0 -> 0 | I41: =I38*I32 -> 0 | J41: =J38*J32 -> 0 | K41: =K38*K32 -> 0.089158016 | L41: =L38*L32 -> 0.1854457 | M41: =M38*M32 -> 0.28773696 | N41: =N38*N32 -> 0.39498171
B42: Transports urbains de voyageurs fonctionnant à l'électricité | C42: =C15 -> 1.3399102 | D42: =D15 -> 1.2815681 | E42: =E15 -> 1.213943 | F42: =F15 -> 1.347695 | G42: =G15 -> 1.5687328 | H42: =H15 -> 1.2598855 | I42: =H42 -> 1.2598855 | J42: =$H$42*(1+$C$35)^(J37-$H37) -> 1.3507677 | K42: =$H$42*(1+$C$35)^(K37-$H37) -> 1.4196705 | L42: =$H$42*(1+$C$35)^(L37-$H37) -> 1.4920879 | M42: =$H$42*(1+$C$35)^(M37-$H37) -> 1.5681994 | N42: =$H$42*(1+$C$35)^(N37-$H37) -> 1.6481933
B43: Ensemble | C43: =C38+C42 -> 10.07075 | D43: =D38+D42 -> 9.9253925 | E43: =E38+E42 -> 8.1393732 | F43: =F38+F42 -> 9.2204167 | G43: =G38+G42 -> 9.9605965 | H43: =H38+H42 -> 9.3053303 | I43: =I38+I42 -> 9.3001173 | J43: =J38+J42 -> 9.8705999 | ... N43: =N38+N42 -> 11.522736
B44: Gazole | C44: =C39 -> 1.4554397 | D44: =D39 -> 1.4584244 | E44: =E39 -> 1.2149312 | F44: =F39 -> 1.3932712 | G44: =G39 -> 1.4307845 | H44: =H39 -> 1.3446133 | I44: =I39 -> 1.2864371 | J44: =J39 -> 1.3631731 | ... N44: =N39 -> 0.39498171
B45: Electricité | C45: =C40+C42 -> 8.6153102 | D45: =D40+D42 -> 8.4669681 | E45: =E40+E42 -> 6.924442 | F45: =F40+F42 -> 7.8271455 | G45: =G40+G42 -> 8.529812 | H45: =H40+H42 -> 7.960717 | I45: =I40+I42 -> 8.0136802 | J45: =J40+J42 -> 8.5074267 | ... N45: =N40+N42 -> 10.732773
B46: H2 | C46: =C41 -> 0 | D46: =D41 -> 0 | E46: =E41 -> 0 | F46: =F41 -> 0 | G46: =G41 -> 0 | H46: =H41 -> 0 | I46: =I41 -> 0 | J46: =J41 -> 0 | ... N46: =N41 -> 0.39498171
B48: Consommation d'énergie des transports ferrés (ferroviaire et transports urbains électriques) (Mtep)
C49: observé | D49: observé
C50: 2018 | D50: 2019 | E50: 2020 | F50: 2021 | G50: 2022 | H50: 2023 | I50: 2025 | J50: 2030 | K50: 2035 | L50: 2040 | M50: 2045 | N50: 2050
B51: Transports ferroviaires SNCF | C51: =C38/11.63 -> 0.75071708 | D51: =D38/11.63 -> 0.74323512 | E51: =E38/11.63 -> 0.59547981 | F51: =F38/11.63 -> 0.67693222 | G51: =G38/11.63 -> 0.7215704 | H51: =H38/11.63 -> 0.69178374 | I51: =I38/11.63 -> 0.6913355 | J51: =J38/11.63 -> 0.7325737 | ... N51: =N38/11.63 -> 0.84905784
B52: Gazole | C52: =C39/11.63 -> 0.12514528 | D52: =D39/11.63 -> 0.12540193 | E52: =E39/11.63 -> 0.10446528 | F52: =F39/11.63 -> 0.11979976 | G52: =G39/11.63 -> 0.12302533 | H52: =H39/11.63 -> 0.11561594 | I52: =I39/11.63 -> 0.11061368 | J52: =J39/11.63 -> 0.11721179 | ... N52: =N39/11.63 -> 0.033962313
B53: Electricité | C53: =C40/11.63 -> 0.6255718 | D53: =D40/11.63 -> 0.61783319 | E53: =E40/11.63 -> 0.49101453 | F53: =F40/11.63 -> 0.55713246 | G53: =G40/11.63 -> 0.59854507 | H53: =H40/11.63 -> 0.5761678 | I53: =I40/11.63 -> 0.58072182 | J53: =J40/11.63 -> 0.61536191 | ... N53: =N40/11.63 -> 0.78113321
B54: H2 | C54: =C41/11.63 -> 0 | D54: =D41/11.63 -> 0 | E54: =E41/11.63 -> 0 | F54: =F41/11.63 -> 0 | G54: =G41/11.63 -> 0 | H54: =H41/11.63 -> 0 | I54: =I41/11.63 -> 0 | J54: =J41/11.63 -> 0 | ... N54: =N41/11.63 -> 0.033962313
B55: Transports urbains de voyageurs fonctionnant à l'électricité | C55: =C42/11.63 -> 0.11521154 | D55: =D42/11.63 -> 0.11019502 | E55: =E42/11.63 -> 0.10438031 | F55: =F42/11.63 -> 0.11588091 | G55: =G42/11.63 -> 0.13488674 | H55: =H42/11.63 -> 0.10833065 | I55: =I42/11.63 -> 0.10833065 | J55: =J42/11.63 -> 0.11614512 | ... N55: =N42/11.63 -> 0.14171912
B56: Ensemble | C56: =C43/11.63 -> 0.86592862 | D56: =D43/11.63 -> 0.85343014 | E56: =E43/11.63 -> 0.69986012 | F56: =F43/11.63 -> 0.79281313 | G56: =G43/11.63 -> 0.85645714 | H56: =H43/11.63 -> 0.80011439 | I56: =I43/11.63 -> 0.79966615 | J56: =J43/11.63 -> 0.84871882 | ... N56: =N43/11.63 -> 0.99077696
B57: Gazole | C57: =C44/11.63 -> 0.12514528 | D57: =D44/11.63 -> 0.12540193 | E57: =E44/11.63 -> 0.10446528 | F57: =F44/11.63 -> 0.11979976 | G57: =G44/11.63 -> 0.12302533 | H57: =H44/11.63 -> 0.11561594 | I57: =I44/11.63 -> 0.11061368 | J57: =J44/11.63 -> 0.11721179 | ... N57: =N44/11.63 -> 0.033962313
B58: Electricité | C58: =C45/11.63 -> 0.74078334 | D58: =D45/11.63 -> 0.72802821 | E58: =E45/11.63 -> 0.59539484 | F58: =F45/11.63 -> 0.67301337 | G58: =G45/11.63 -> 0.73343181 | H58: =H45/11.63 -> 0.68449845 | I58: =I45/11.63 -> 0.68905247 | J58: =J45/11.63 -> 0.73150703 | ... N58: =N45/11.63 -> 0.92285233
B59: H2 | C59: =C46/11.63 -> 0 | D59: =D46/11.63 -> 0 | E59: =E46/11.63 -> 0 | F59: =F46/11.63 -> 0 | G59: =G46/11.63 -> 0 | H59: =H46/11.63 -> 0 | I59: =I46/11.63 -> 0 | J59: =J46/11.63 -> 0 | ... N59: =N46/11.63 -> 0.033962313
B62: 3) Le fluvial et maritime domestique
O63: 1.A.3.d. Domestic Navigation (12) | P63: 21168.62 | Q63: =SUM(Q64:Q72) -> 5.9825742 | R63: 1.A.4.c.iii. Fishing | S63: 13121.313 | T63: =SUM(T64:T72) -> 3.6503053
E64: Mtep | O64: Residual fuel oil | P64: 1796.5988 | Q64: =P64/3.6/1000 -> 0.49905521 | R64: Residual fuel oil | S64: NO
C65: 2018 | D65: 2019 | E65: 2020 | F65: 2021 | G65: 2022 | H65: 2023 | O65: Gas/diesel oil | P65: 7179.1203 | Q65: =P65/3.6/1000 -> 1.9942001 | R65: Gas/diesel oil | S65: 12347.53 | T65: =S65/3.6/1000 -> 3.4298694
B66: Fluvial | C66: =C70/11.63 -> 0.08046204 | D66: =D70/11.63 -> 0.081835179 | E66: =E70/11.63 -> 0.015530822 | F66: =F70/11.63 -> 0.073770846 | G66: =G70/11.63 -> 0.12006914 | H66: =H70/11.63 -> 0.12430694 | O66: Gasoline | P66: 10548.843 | Q66: =P66/3.6/1000 -> 2.9302342 | R66: Gasoline | S66: 720.39414 | T66: =S66/3.6/1000 -> 0.20010948
B67: Plaisance, autres navigations | C67: =C71/11.63 -> 0.36724123 | D67: =D71/11.63 -> 0.37118712 | E67: =E71/11.63 -> 0.37316006 | F67: =F71/11.63 -> 0.37639166 | G67: =G71/11.63 -> 0.37528854 | H67: =H71/11.63 -> 0.37528854 | O67: Other liquid fuels (please specify) | P67: 152.78567 | Q67: =P67/3.6/1000 -> 0.042440463 | R67: Other liquid fuels (please specify) | S67: 6.0545068 | T67: =S67/3.6/1000 -> 0.0016818074
O68: Other liquid fuels [IPCC Software 1.A.3.d.ii] | P68: 152.78567 | Q68: =P68/3.6/1000 -> 0.042440463 | R68: Other liquid fuels [IPCC Software 1.A.4.c.iii] | S68: 6.0545068 | T68: =S68/3.6/1000 -> 0.0016818074
B69: observé | C69: 2018 | D69: 2019 | E69: 2020 | F69: 2021 | G69: 2022 | H69: 2023 | O69: Gaseous fuels (6) | P69: NO | R69: Gaseous fuels (6) | S69: NO
B70: Fluvial | C70: 0.93577352 | D70: 0.95174313 | E70: 0.18062346 | F70: 0.85795494 | G70: 1.3964041 | H70: 1.4456897 | O70: Biomass (3) | P70: 1275.4109 | Q70: =P70/3.6/1000 -> 0.35428081 | R70: Biomass(3) | S70: 33.603472 | T70: =S70/3.6/1000 -> 0.0093342977
B71: Plaisance | C71: 4.2710155 | D71: 4.3169062 | E71: 4.3398515 | F71: 4.377435 | G71: 4.3646057 | H71: 4.3646057 | I71: =H71+H70 -> 5.8102954 | O71: Other fossil fuels (please specify)(7) | P71: 215.86125 | Q71: =P71/3.6/1000 -> 0.059961457 | R71: Other fossil fuels (please specify)(7) | S71: 13.731343 | T71: =S71/3.6/1000 -> 0.0038142619
B72: Maritime (international principalement) | C72: 22.615435 | D72: 19.898071 | E72: 11.423715 | F72: 12.140691 | G72: 13.539184 | H72: 11.77111 | O72: Other fossil fuels [IPCC Software 1.A.3.d.ii] | P72: 215.86125 | Q72: =P72/3.6/1000 -> 0.059961457 | R72: Other fossil fuels [IPCC Software 1.A.4.c.iii] | S72: 13.731343 | T72: =S72/3.6/1000 -> 0.0038142619
B75: Trafic fluvial
B77: Evolution trafic fluvial
C78: 2018 | D78: 2019 | E78: 2020 | F78: 2021 | G78: 2022 | H78: 2023 | I78: 2025 | J78: 2030 | K78: 2035 | L78: 2040 | M78: 2045 | N78: 2050
B79: Trafic fluvial | C79: =Trafic!C71 -> 7.255286 | D79: =Trafic!D71 -> 7.9964556 | E79: =Trafic!E71 -> 6.987717 | F79: =Trafic!F71 -> 7.2654698 | G79: =Trafic!G71 -> 6.5932717 | H79: =Trafic!H71 -> 5.9066986 | I79: =Trafic!I71 -> 6.8521366 | J79: =Trafic!J71 -> 10.506249 | ... N79: =Trafic!N71 -> 15.078601
B80: Indice trafic fluvial | C80: =C79/$C79 -> 1 | D80: =D79/$C79 -> 1.1021558 | E80: =E79/$C79 -> 0.96312082 | F80: =F79/$C79 -> 1.0014036 | G80: =G79/$C79 -> 0.90875421 | H80: =H79/$C79 -> 0.81412347 | I80: =I79/$C79 -> 0.94443369 | J80: =J79/$C79 -> 1.448082 | ... N80: =N79/$C79 -> 2.0782918
C82: 2018 | D82: 2019 | E82: 2020 | F82: 2021 | G82: 2022 | H82: 2023 | I82: 2025 | J82: 2030 | K82: 2035 | L82: 2040 | M82: 2045 | N82: 2050
B83: Fluvial | C83: =1 -> 1 | D83: =1 -> 1 | E83: 1 | F83: 1 | G83: 1 | H83: 1 | I83: 0.95 | J83: 0.9 | K83: 0.85 | L83: 0.8 | M83: 0.75 | N83: 0.75
B84: Plaisance | C84: =1 -> 1 | D84: =1 -> 1 | E84: 1 | F84: 1 | G84: 1 | H84: 1 | I84: 0.95 | J84: 0.9 | K84: 0.85 | L84: 0.8 | M84: 0.75 | N84: 0.75
B86: Mix énergétique | C86: observé | D86: observé
C87: 2018 | D87: 2019 | E87: 2020 | F87: 2021 | G87: 2022 | H87: 2023 | I87: 2025 | J87: 2030 | K87: 2035 | L87: 2040 | M87: 2045 | N87: 2050
B88: GNR fluvial | C88: 1 | D88: 1 | E88: 1 | F88: 1 | G88: 1 | H88: 1 | I88: 0.99 | J88: 0.98 | K88: 0.91 | L88: 0.84 | M88: 0.77 | N88: 0.7
B89: GNV fluvial | C89: 0 | D89: 0 | E89: 0 | F89: 0 | G89: 0 | H89: 0 | I89: 0.01 | J89: 0.02 | K89: 0.09 | L89: 0.16 | M89: 0.23 | N89: 0.3
B90: Essence maritime plaisance | C90: 1 | D90: 1 | E90: 1 | F90: 1 | G90: 1 | H90: 1 | I90: 0.99 | J90: 0.98 | K90: 0.91 | L90: 0.84 | M90: 0.77 | N90: 0.7
B91: Electricité maritime plaisance | C91: 0 | D91: 0 | E91: 0 | F91: 0 | G91: 0 | H91: 0 | I91: 0.01 | J91: 0.02 | K91: 0.09 | L91: 0.16 | M91: 0.23 | N91: 0.3
B94: Consommation d'énergie dans le transport fluvial et la plaisance (Mtep)
C95: observé | D95: observé
C96: 2018 | D96: 2019 | E96: 2020 | F96: 2021 | G96: 2022 | H96: 2023 | I96: 2025 | J96: 2030 | K96: 2035 | L96: 2040 | M96: 2045 | N96: 2050
B97: GNR fluvial | C97: =$C$66*C$80*C$83*C88 -> 0.08046204 | D97: =$C$66*D$80*D$83*D88 -> 0.088681704 | E97: =$C$66*E$80*E$83*E88 -> 0.077494666 | F97: =$C$66*F$80*F$83*F88 -> 0.080574979 | G97: =$C$66*G$80*G$83*G88 -> 0.073120217 | H97: =$C$66*H$80*H$83*H88 -> 0.065506035 | I97: =$C$66*I$80*I$83*I88 -> 0.071469593 | J97: =$C$66*J$80*J$83*J88 -> 0.10276679 | ... N97: =$C$66*N$80*N$83*N88 -> 0.087792387
B98: GNV fluvial | C98: =$C$66*C$80*C$83*C89 -> 0 | D98: =$C$66*D$80*D$83*D89 -> 0 | E98: =$C$66*E$80*E$83*E89 -> 0 | F98: =$C$66*F$80*F$83*F89 -> 0 | G98: =$C$66*G$80*G$83*G89 -> 0 | H98: =$C$66*H$80*H$83*H89 -> 0 | I98: =$C$66*I$80*I$83*I89 -> 0.00072191508 | J98: =$C$66*J$80*J$83*J89 -> 0.0020972813 | ... N98: =$C$66*N$80*N$83*N89 -> 0.037625309
B99: Essence maritime plaisance | C99: =$C$67*C$84*C90 -> 0.36724123 | D99: =$C$67*D$84*D90 -> 0.36724123 | E99: =$C$67*E$84*E90 -> 0.36724123 | F99: =$C$67*F$84*F90 -> 0.36724123 | G99: =$C$67*G$84*G90 -> 0.36724123 | H99: =$C$67*H$84*H90 -> 0.36724123 | I99: =$C$67*I$84*I90 -> 0.34539038 | J99: =$C$67*J$84*J90 -> 0.32390676 | ... N99: =$C$67*N$84*N90 -> 0.19280164
B100: Electricité maritime plaisance | C100: =$C$67*C$84*C91 -> 0 | D100: =$C$67*D$84*D91 -> 0 | E100: =$C$67*E$84*E91 -> 0 | F100: =$C$67*F$84*F91 -> 0 | G100: =$C$67*G$84*G91 -> 0 | H100: =$C$67*H$84*H91 -> 0 | I100: =$C$67*I$84*I91 -> 0.0034887917 | J100: =$C$67*J$84*J91 -> 0.0066103421 | ... N100: =$C$67*N$84*N91 -> 0.082629276
B102: Consommation d'énergie dans le transport fluvial et la plaisance (TWh)
C103: observé | D103: observé
C104: 2018 | D104: 2019 | E104: 2020 | F104: 2021 | G104: 2022 | H104: 2023 | I104: 2025 | J104: 2030 | K104: 2035 | L104: 2040 | M104: 2045 | N104: 2050
B105: GNR fluvial | C105: =C97*11.63 -> 0.93577352 | D105: =D97*11.63 -> 1.0313682 | E105: =E97*11.63 -> 0.90126296 | F105: =F97*11.63 -> 0.937087 | G105: =G97*11.63 -> 0.85038813 | H105: =H97*11.63 -> 0.76183518 | I105: =I97*11.63 -> 0.83119137 | J105: =J97*11.63 -> 1.1951777 | ... N105: =N97*11.63 -> 1.0210255
B106: GNV fluvial | C106: =C98*11.63 -> 0 | D106: =D98*11.63 -> 0 | E106: =E98*11.63 -> 0 | F106: =F98*11.63 -> 0 | G106: =G98*11.63 -> 0 | H106: =H98*11.63 -> 0 | I106: =I98*11.63 -> 0.0083958724 | J106: =J98*11.63 -> 0.024391382 | ... N106: =N98*11.63 -> 0.43758234
B107: Essence maritime plaisance | C107: =C99*11.63 -> 4.2710155 | D107: =D99*11.63 -> 4.2710155 | E107: =E99*11.63 -> 4.2710155 | F107: =F99*11.63 -> 4.2710155 | G107: =G99*11.63 -> 4.2710155 | H107: =H99*11.63 -> 4.2710155 | I107: =I99*11.63 -> 4.0168901 | J107: =J99*11.63 -> 3.7670357 | ... N107: =N99*11.63 -> 2.2422831
B108: Electricité maritime plaisance | C108: =C100*11.63 -> 0 | D108: =D100*11.63 -> 0 | E108: =E100*11.63 -> 0 | F108: =F100*11.63 -> 0 | G108: =G100*11.63 -> 0 | H108: =H100*11.63 -> 0 | I108: =I100*11.63 -> 0.040574647 | J108: =J100*11.63 -> 0.076878279 | ... N108: =N100*11.63 -> 0.96097848
B110: transport fluvial : évolution comme le trafic fluvial
B111: plaisance essence : stabilité des consommations (même trend de stabilité que sur la période récente)
B113: 4) Maritime (soutes internationales uniquement)
B114: Gain annuel efficacité énergétique 2025-2030 | C114: =0.8^0.2 -> 0.9563525 | F114: =1+C114 -> 1.9563525 | G114: =F114^2 -> 3.8273151
B115: Gain annuel efficacité énergétique 2023-2031
B116: new | C116: observé | D116: observé
C117: 2018 | D117: 2019 | E117: 2020 | F117: 2021 | G117: 2022 | H117: 2023 | I117: 2025 | J117: 2030 | K117: 2035 | L117: 2040 | M117: 2045 | N117: 2050 | P117: 2023 | Q117: 2025 | R117: 2030 | S117: 2035 | T117: 2040 | U117: 2045 | V117: 2050
B118: Croissance du trafic en tkm base 2023 | H118: 1 | I118: =1.015^2 -> 1.030225 | J118: =1.015^7 -> 1.1098449 | K118: =1.015^12 -> 1.1956182 | L118: =K118 -> 1.1956182 | M118: =L118 -> 1.1956182 | N118: =M118 -> 1.1956182 | P118: 1 | Q118: 1.030225 | R118: 1.1098449 | S118: 1.1956182 | T118: 1.1956182 | U118: 1.1956182 | V118: 1.1956182
B119: Efficacité énergétique totale | D119: 1 | H119: 1 | I119: 0.99 | J119: 0.8 | K119: 0.78 | L119: 0.76 | M119: 0.74 | N119: 0.73 | P119: 1 | Q119: 0.99 | R119: 0.8 | S119: 0.73 | T119: 0.73 | U119: 0.73 | V119: 0.73
B120: Evolution des consommations base 2023 | H120: =H118*H119 -> 1 | I120: =I118*I119 -> 1.0199227 | J120: =J118*J119 -> 0.88787593 | K120: =K118*K119 -> 0.93258217 | L120: =L118*L119 -> 0.90866981 | M120: =M118*M119 -> 0.88475745 | N120: =N118*N119 -> 0.87280127 | P120: 1 | Q120: 1.0199227 | R120: 0.88787593 | S120: 0.87280127 | T120: 0.87280127 | U120: 0.87280127 | V120: 0.87280127
H121: =11.8*H118 -> 11.8 | I121: =11.8*I118 -> 12.156655 | J121: =11.8*J118 -> 13.09617 | K121: =11.8*K118 -> 14.108294 | L121: =11.8*L118 -> 14.108294 | M121: =11.8*M118 -> 14.108294 | N121: =11.8*N118 -> 14.108294
B122: Consommation d'énergie dans les soutes maritimes (Mtep) | I122: =T126/I121 -> 0.98420312 | J122: =U126/J121 -> 0.79936021 | K122: =V126/K121 -> 0.72985063 | L122: =W126/L121 -> 0.72985063 | M122: =X126/M121 -> 0.72985063 | N122: =Y126/N121 -> 0.72985063
...

Sheet Aérien
B1: Trafics
B4: Trafics intérieur métropole post modifs (Mds PKT)
C5: 2018 | D5: 2019 | E5: 2020 | F5: 2021 | G5: 2022 | H5: 2023 | I5: 2025 | J5: 2030 | K5: 2035 | L5: 2040 | M5: 2045 | N5: 2050 | P5: Evolution du trafic aérien (Mds passagers.km)
B6: Intérieur métropole (*) | C6: 16.012112 | D6: 16.265166 | E6: 7.2496757 | F6: 10.086837 | G6: 13.52361 | H6: 13.233747 | I6: 12.510166 | J6: 12.344811 | K6: 5.9958234 | L6: 5.4439514 | M6: 5.3006867 | N6: 5.4891365 | P6: Mds passagers kilomètres | Q6: 2019 | R6: 2025 | S6: 2030 | T6: 2035 | U6: 2040 | V6: 2045 | W6: 2050
B7: Métropole-OM & intra OM | C7: 35.823383 | D7: 36.898087 | E7: 19.784458 | F7: 23.293341 | G7: 36.327985 | H7: 36.724806 | I7: 39.554503 | J7: 42.674209 | K7: 39.325503 | L7: 39.108496 | M7: 41.582061 | N7: 44.887793 | P7: Intérieur hexagone | Q7: 16.267953 | R7: 14.206156 | S7: 14.375611 | T7: 6.950162 | U7: 5.9425745 | V7: 5.766804 | W7: 6.5252741 | X7: =W7/Q7-1 -> -0.59888781
B8: International France (1 sens) | C8: 174.6339 | D8: 183.66098 | E8: 47.119074 | F8: 56.064445 | G8: 136.81601 | H8: 172.05729 | I8: 201.3078 | J8: 215.20032 | K8: 213.95261 | L8: 216.75856 | M8: 229.91178 | N8: 245.92045 | P8: Hexagone-OM & intra OM | Q8: 36.8981 | R8: 40.075178 | S8: 45.18138 | T8: 43.732926 | U8: 44.870035 | V8: 45.650066 | W8: 44.142508 | X8: =W8/Q8-1 -> 0.19633552
B9: Total_France (2 sens intérieur + 1 sens international) | C9: 226.4694 | D9: 236.82423 | E9: 74.153208 | F9: 89.444623 | G9: 186.6676 | H9: 222.01584 | I9: 253.37246 | J9: 270.21934 | K9: 259.27393 | L9: 261.31101 | M9: 276.79453 | N9: 296.29738 | P9: International France (1 sens) | Q9: 183.63153 | R9: 195.05427 | S9: 217.12249 | T9: 218.92954 | U9: 217.95837 | V9: 222.12413 | W9: 215.75507 | X9: =W9/Q9-1 -> 0.17493478
B10: Format : tous les départs France (dans les 2 sens pour l'intérieur France et dans un seul sens pour l'international) | P10: Total France (2 sens intérieur + 1 sens international) | Q10: 236.79758 | R10: 249.33561 | S10: 276.67948 | T10: 269.61263 | U10: 268.77097 | V10: 273.541 | W10: 266.42285 | X10: =W10/Q10-1 -> 0.12510799
B11: (*) dont Corse | C11: 2.6762608 | D11: 2.6732301 | E11: 1.633418 | F11: 2.5225151 | G11: 2.8247045 | H11: 2.702913 | I11: 2.6156481 | J11: 2.5810755 | K11: 2.3044368 | L11: 2.0923301 | M11: 2.1246634 | N11: 2.2001993
B12: dont Europe | C12: 42.606879 | D12: 44.253954 | E12: 11.959998 | F12: 17.506052 | G12: 38.449859 | H12: 44.763378 | I12: 46.546971 | J12: 49.05714 | K12: 48.382726 | L12: 47.207843 | M12: 49.511174 | N12: 52.115867
B13: dont international hors Europe | C13: 132.02703 | D13: 139.40703 | E13: 35.159076 | F13: 38.558393 | G13: 98.366149 | H13: 127.29391 | I13: 154.76082 | J13: 166.14318 | K13: 165.56988 | L13: 169.55072 | M13: 180.40061 | N13: 193.80459
B15: domestique | C15: =C6+C7 -> 51.835495 | D15: =D6+D7 -> 53.163252 | E15: =E6+E7 -> 27.034134 | F15: =F6+F7 -> 33.380178 | G15: =G6+G7 -> 49.851596 | H15: =H6+H7 -> 49.958554 | I15: =I6+I7 -> 52.064669 | J15: =J6+J7 -> 55.01902 | ... N15: =N6+N7 -> 50.376929
B17: Evolution des trafics en base 100 en 2019
C18: 2018 | D18: 2019 | E18: 2020 | F18: 2021 | G18: 2022 | H18: 2023 | I18: 2025 | J18: 2030 | K18: 2035 | L18: 2040 | M18: 2045 | N18: 2050
B19: Trafics métropole | D19: =D6/$D6 -> 1 | E19: =E6/$D6 -> 0.44571792 | F19: =F6/$D6 -> 0.6201497 | G19: =G6/$D6 -> 0.83144622 | H19: =H6/$D6 -> 0.81362514 | I19: =I6/$D6 -> 0.76913855 | J19: =J6/$D6 -> 0.75897238 | K19: =K6/$D6 -> 0.36862972 | ... N19: =N6/$D6 -> 0.33747806
B20: Trafics Dom-Com | D20: =D7/$D7 -> 1 | E20: =E7/$D7 -> 0.53619198 | F20: =F7/$D7 -> 0.63128858 | G20: =G7/$D7 -> 0.98454929 | H20: =H7/$D7 -> 0.99530381 | I20: =I7/$D7 -> 1.0719933 | J20: =J7/$D7 -> 1.1565426 | K20: =K7/$D7 -> 1.0657871 | ... N20: =N7/$D7 -> 1.2165344
B21: Trafics international | D21: =D8/$D8 -> 1 | E21: =E8/$D8 -> 0.25655462 | F21: =F8/$D8 -> 0.30526051 | G21: =G8/$D8 -> 0.74493781 | H21: =H8/$D8 -> 0.93682006 | I21: =I8/$D8 -> 1.0960836 | J21: =J8/$D8 -> 1.1717259 | K21: =K8/$D8 -> 1.1649323 | ... N21: =N8/$D8 -> 1.3389913
B22: Moyenne | D22: =D9/$D9 -> 1 | E22: =E9/$D9 -> 0.31311495 | F22: =F9/$D9 -> 0.37768358 | G22: =G9/$D9 -> 0.78821158 | H22: =H9/$D9 -> 0.93747097 | I22: =I9/$D9 -> 1.0698756 | J22: =J9/$D9 -> 1.1410122 | K22: =K9/$D9 -> 1.0947948 | ... N22: =N9/$D9 -> 1.2511278
B25: Consommations unitaires | D25: (pour mémoire)
B27: Evolution des consos unitaires en base 100
C28: 2018 | D28: 2019 | E28: 2020 | F28: 2021 | G28: 2022 | H28: 2023 | I28: 2025 | J28: 2030 | K28: 2035 | L28: 2040 | M28: 2045 | N28: 2050
B29: Intérieur métropole | C29: 1 | D29: =D41/D6 -> 0.53834634 | E29: =E41/E6 -> 0.64733907 | F29: =F41/F6 -> 0.59723756 | G29: =G41/G6 -> 0.53264663 | H29: =H41/H6 -> 0.51870055 | I29: =I41/I6 -> 0.50447634 | J29: =J41/J6 -> 0.47059903 | K29: =K41/K6 -> 0.4389967 | ... N29: =N41/N6 -> 0.35636244 | P29: =J29/H29-1 -> -0.09273467 | Q29: =N29/H29-1 -> -0.31297077 | S29: =N29^(1/31)-1 -> -0.032736275 | U29: =N29/D29 -> 0.66195758
B30: Métropole-OM & intra OM | D30: =D48/D7 -> 0.28281778 | E30: =E48/E7 -> 0.36021353 | F30: =F48/F7 -> 0.36683963 | G30: =G48/G7 -> 0.29033482 | H30: =H48/H7 -> 0.27658061 | I30: =I48/I7 -> 0.26897323 | J30: =J48/J7 -> 0.25096652 | K30: =K48/K7 -> 0.23467282 | ... N30: =N48/N7 -> 0.19079626 | P30: =J30/H30-1 -> -0.092609841 | Q30: =N30/H30-1 -> -0.3101604 | S30: =N30^(1/31)-1 -> -0.052034405 | U30: =N30/D30 -> 0.67462609
B31: International France (1 sens) | D31: =D55/D8 -> 0.39440002 | E31: =E55/E8 -> 0.63131861 | F31: =F55/F8 -> 0.61933579 | G31: =G55/G8 -> 0.41073515 | H31: =H55/H8 -> 0.38129514 | I31: =I55/I8 -> 0.37134798 | J31: =J55/J8 -> 0.3480965 | K31: =K55/K8 -> 0.32631262 | ... N31: =N55/N8 -> 0.26874917 | P31: =J31/H31-1 -> -0.087068094 | Q31: =N31/H31-1 -> -0.29516758 | S31: =N31^(1/31)-1 -> -0.041500605 | U31: =N31/D31 -> 0.68141268
B32: En moyenne | D32: =D62/D9 -> 0.38690137 | E32: =E62/E9 -> 0.56055263 | F32: =F62/F9 -> 0.5510882 | G32: =G62/G9 -> 0.39613584 | H32: =H62/H9 -> 0.37216411 | I32: =I62/I9 -> 0.36193921 | J32: =J62/J9 -> 0.33835377 | K32: =K62/K9 -> 0.31501898 | ... N32: =N62/N9 -> 0.25856274 | P32: =J32/H32-1 -> -0.090847948 | Q32: =N32/H32-1 -> -0.30524537 | S32: =N32^(1/31)-1 -> -0.042694588 | U32: =N32/D32 -> 0.66829109
B34: Consos en volume | C34: TWh en données d'entrée DGAC
B36: Intérieur métropole | C36: 2018 | D36: 2019 | E36: 2020 | F36: 2021 | G36: 2022 | H36: 2023 | I36: 2025 | J36: 2030 | K36: 2035 | L36: 2040 | M36: 2045 | N36: 2050
B37: Biocarburants | C37: 0 | D37: 0 | E37: 0 | F37: 0.024096953 | G37: 0.057626445 | H37: 0.082372226 | I37: 0.12622165 | J37: 0.32416766 | K37: 0.394822 | L37: 0.53505319 | M37: 0.54673592 | N37: 0.68464273
B38: PtL | C38: 0 | D38: 0 | E38: 0 | F38: 0 | G38: 0 | H38: 0 | I38: 0 | J38: 0.024399716 | K38: 0.12083393 | L38: 0.22952521 | M38: 0.34001958 | N38: 0.4794038
B39: H2 | C39: 0 | D39: 0 | E39: 0 | F39: 0 | G39: 0 | H39: 0 | I39: 0 | J39: 0 | K39: 0.0107734 | L39: 0.060295263 | M39: 0.20671633 | N39: 0.49865725
B40: kérosène fossile | C40: 8.5964198 | D40: 8.7562924 | E40: 4.6929983 | F40: 6.0001412 | G40: 7.1456791 | H40: 6.7819799 | I40: 6.184861 | J40: 5.4608888 | K40: 2.1057173 | L40: 1.4045146 | M40: 0.931476 | N40: 0.29341831
B41: Consommation totale | C41: 8.5964198 | D41: 8.7562924 | E41: 4.6929983 | F41: 6.0242381 | G41: 7.2033056 | H41: 6.8643521 | I41: 6.3110826 | J41: 5.8094562 | K41: 2.6321467 | L41: 2.2293883 | M41: 2.0249478 | N41: 1.9561221
B43: Métropole-DROM & intra DROM | C43: 2018 | D43: 2019 | E43: 2020 | F43: 2021 | G43: 2022 | H43: 2023 | I43: 2025 | J43: 2030 | K43: 2035 | L43: 2040 | M43: 2045 | N43: 2050
B44: Biocarburants | C44: 0 | D44: 0 | E44: 0 | F44: 0.034179682 | G44: 0.084378231 | H44: 0.12188843 | I44: 0.21278205 | J44: 0.59760671 | K44: 1.384294 | L44: 2.0573193 | M44: 2.2970094 | N44: 2.997548
B45: PtL | C45: 0 | D45: 0 | E45: 0 | F45: 0 | G45: 0 | H45: 0 | I45: 0 | J45: 0.04498115 | K45: 0.46143135 | L45: 1.1143813 | M45: 2.2970094 | N45: 4.2822114
B46: H2 | C46: 0 | D46: 0 | E46: 0 | F46: 0 | G46: 0 | H46: 0 | I46: 0 | J46: 0 | K46: 0 | L46: 0 | M46: 0 | N46: 0
B47: kérosène fossile | C47: 10.205828 | D47: 10.435435 | E47: 7.1266296 | F47: 8.5107407 | G47: 10.462901 | H47: 10.035481 | I47: 10.42632 | J47: 10.06721 | K47: 7.3829015 | L47: 5.4004631 | M47: 3.9134234 | N47: 1.2846634
B48: Consommation totale | C48: 10.205828 | D48: 10.435435 | E48: 7.1266296 | F48: 8.5449204 | G48: 10.547279 | H48: 10.157369 | I48: 10.639102 | J48: 10.709798 | K48: 9.2286269 | L48: 8.5721637 | M48: 8.5074422 | N48: 8.5644228
... B74: Besoin en émlectricité primaire | C74: 0 | D74: 0 | E74: 0 | F74: 0 | G74: 0 | H74: 0 | I74: 0 | J74: 0.73847092 | K74: 7.8156129 | L74: 19.047458 | M74: 38.861853 | N74: 71.619679
B77: Consommations en TWH énergie finale
B79: Intérieur métropole | C79: 2018 | D79: 2019 | E79: 2020 | F79: 2021 | G79: 2022 | H79: 2023 | I79: 2025 | J79: 2030 | K79: 2035 | L79: 2040 | M79: 2045 | N79: 2050
B80: Biocarburants | C80: 0 | D80: 0 | E80: 0 | F80: 0.024096953 | G80: 0.057626445 | H80: 0.082372226 | I80: 0.12622165 | J80: 0.32416766 | K80: 0.394822 | L80: 0.53505319 | M80: 0.54673592 | N80: 0.68464273
B81: PtL | C81: 0 | D81: 0 | E81: 0 | F81: 0 | G81: 0 | H81: 0 | I81: 0 | J81: 0.024399716 | K81: 0.12083393 | L81: 0.22952521 | M81: 0.34001958 | N81: 0.4794038
B82: H2 | C82: 0 | D82: 0 | E82: 0 | F82: 0 | G82: 0 | H82: 0 | I82: 0 | J82: 0 | K82: 0.0107734 | L82: 0.060295263 | M82: 0.20671633 | N82: 0.49865725
B83: kérosène fossile | C83: 8.5964198 | D83: 8.7562924 | E83: 4.6929983 | F83: 6.0001412 | G83: 7.1456791 | H83: 6.7819799 | I83: 6.184861 | J83: 5.4608888 | K83: 2.1057173 | L83: 1.4045146 | M83: 0.931476 | N83: 0.29341831
B84: Consommation totale | C84: 8.5964198 | D84: 8.7562924 | E84: 4.6929983 | F84: 6.0242381 | G84: 7.2033056 | H84: 6.8643521 | I84: 6.3110826 | J84: 5.8094562 | K84: 2.6321467 | L84: 2.2293883 | M84: 2.0249478 | N84: 1.9561221
C85: 0 | D85: 0 | E85: 0 | F85: 4.510281e-16 | G85: 0 | I85: 0 | J85: -1.7515145e-10 | K85: 0 | L85: 0 | M85: 0 | N85: 0
B86: Métropole-DROM & intra DROM | C86: 2018 | D86: 2019 | E86: 2020 | F86: 2021 | G86: 2022 | H86: 2023 | I86: 2025 | J86: 2030 | K86: 2035 | L86: 2040 | M86: 2045 | N86: 2050
B87: Biocarburants | C87: 0 | D87: 0 | E87: 0 | F87: 0.034179682 | G87: 0.084378231 | H87: 0.12188843 | I87: 0.21278205 | J87: 0.59760671 | K87: 1.384294 | L87: 2.0573193 | M87: 2.2970094 | N87: 2.997548
B88: PtL | C88: 0 | D88: 0 | E88: 0 | F88: 0 | G88: 0 | H88: 0 | I88: 0 | J88: 0.04498115 | K88: 0.46143135 | L88: 1.1143813 | M88: 2.2970094 | N88: 4.2822114
B89: H2 | C89: 0 | D89: 0 | E89: 0 | F89: 0 | G89: 0 | H89: 0 | I89: 0 | J89: 0 | K89: 0 | L89: 0 | M89: 0 | N89: 0
B90: kérosène fossile | C90: 10.205828 | D90: 10.435435 | E90: 7.1266296 | F90: 8.5107407 | G90: 10.462901 | H90: 10.035481 | I90: 10.42632 | J90: 10.06721 | K90: 7.3829015 | L90: 5.4004631 | M90: 3.9134234 | N90: 1.2846634
B91: Consommation totale | C91: 10.205828 | D91: 10.435435 | E91: 7.1266296 | F91: 8.5449204 | G91: 10.547279 | H91: 10.157369 | I91: 10.639102 | J91: 10.709798 | K91: 9.2286269 | L91: 8.5721637 | M91: 8.5074422 | N91: 8.5644228
C92: 0 | D92: 0 | E92: 0 | F92: -1.8665625e-15 | G92: 3.1086245e-15 | I92: 0 | J92: -2.9143621e-10 | K92: 0 | L92: 0 | M92: 0 | N92: 0
B93: International France | C93: 2018 | D93: 2019 | E93: 2020 | F93: 2021 | G93: 2022 | H93: 2023 | I93: 2025 | J93: 2030 | K93: 2035 | L93: 2040 | M93: 2045 | N93: 2050
B94: Biocarburants | C94: 0 | D94: 0 | E94: 0 | F94: 0.13889087 | G94: 0.44956115 | H94: 0.7872553 | I94: 1.4951049 | J94: 4.1800047 | K94: 10.472315 | L94: 15.910626 | M94: 17.194298 | N94: 20.294399
B95: PtL | C95: 0 | D95: 0 | E95: 0 | F95: 0 | G95: 0 | H95: 0 | I95: 0 | J95: 0.31462401 | K95: 3.4249662 | L95: 8.2205206 | M95: 15.768252 | N95: 25.800974
B96: H2 | C96: 0 | D96: 0 | E96: 0 | F96: 0 | G96: 0 | H96: 0 | I96: 0 | J96: 0 | K96: 0.065805528 | L96: 0.39773496 | M96: 1.4260462 | N96: 3.1910247
B97: kérosène fossile | C97: 70.509055 | D97: 72.435894 | E97: 29.747148 | F97: 34.583827 | G97: 55.745583 | H97: 64.817353 | I97: 73.260139 | J97: 70.41585 | K97: 55.852348 | L97: 41.765392 | M97: 29.293989 | N97: 8.6975995
B98: Consommation totale | C98: 70.509055 | D98: 72.435894 | E98: 29.747148 | F98: 34.722718 | G98: 56.195144 | H98: 65.604608 | I98: 74.755244 | J98: 74.910479 | K98: 69.815435 | L98: 66.294274 | M98: 63.682584 | N98: 57.983997
B100: Ensemble | C100: 2018 | D100: 2019 | E100: 2020 | F100: 2021 | G100: 2022 | H100: 2023 | I100: 2025 | J100: 2030 | K100: 2035 | L100: 2040 | M100: 2045 | N100: 2050
B101: Biocarburants | C101: 0 | D101: 0 | E101: 0 | F101: 0.1971675 | G101: 0.59156583 | H101: 0.99151595 | I101: 1.8341086 | J101: 5.1017791 | K101: 12.251431 | L101: 18.502998 | M101: 20.038043 | N101: 23.97659
B102: PtL | C102: 0 | D102: 0 | E102: 0 | F102: 0 | G102: 0 | H102: 0 | I102: 0 | J102: 0.38400488 | K102: 4.0072315 | L102: 9.5644271 | M102: 18.405281 | N102: 30.562589
B103: H2 | C103: 0 | D103: 0 | E103: 0 | F103: 0 | G103: 0 | H103: 0 | I103: 0 | J103: 0 | K103: 0.076578928 | L103: 0.45803022 | M103: 1.6327625 | N103: 3.6896819
B104: kérosène fossile | C104: 89.311303 | D104: 91.627621 | E104: 41.566776 | F104: 49.094709 | G104: 73.354163 | H104: 81.634814 | I104: 89.87132 | J104: 85.943949 | K104: 65.340967 | L104: 48.57037 | M104: 34.138888 | N104: 10.275681
B105: Consommation totale | C105: 89.311303 | D105: 91.627621 | E105: 41.566776 | F105: 49.291876 | G105: 73.945729 | H105: 82.62633 | I105: 91.705429 | J105: 91.429733 | K105: 81.676209 | L105: 77.095825 | M105: 74.214974 | N105: 68.504542
C106: 0 | D106: 0 | E106: 0 | F106: -4.096723e-14 | G106: 4.7295501e-14 | I106: 0 | J106: -2.442448e-09 | K106: 0 | L106: 0 | M106: 0 | N106: 0
B108: Mix | C108: 2018 | D108: 2019 | E108: 2020 | F108: 2021 | G108: 2022 | H108: 2023 | I108: 2025 | J108: 2030 | K108: 2035 | L108: 2040 | M108: 2045 | N108: 2050
B109: Biocarburants | C109: 0 | D109: 0 | E109: 0 | F109: 0.004 | G109: 0.008 | H109: 0.012 | I109: 0.02 | J109: 0.0558 | K109: 0.15 | L109: 0.24 | M109: 0.27 | N109: 0.35
B110: PtL | C110: 0 | D110: 0 | E110: 0 | F110: 0 | G110: 0 | H110: 0 | I110: 0 | J110: 0.0042 | K110: 0.049062408 | L110: 0.12405895 | M110: 0.24799955 | N110: 0.4461396
B111: H2 | C111: 0 | D111: 0 | E111: 0 | F111: 0 | G111: 0 | H111: 0 | I111: 0 | J111: 0 | K111: 0.00093759161 | L111: 0.0059410508 | M111: 0.022000445 | N111: 0.053860398
B112: kérosène fossile | C112: 1 | D112: 1 | E112: 1 | F112: 0.996 | G112: 0.992 | H112: 0.988 | I112: 0.98 | J112: 0.94 | K112: 0.8 | L112: 0.63 | M112: 0.46 | N112: 0.15
B113: Consommation totale | C113: 1 | D113: 1 | E113: 1 | F113: 1 | G113: 1 | H113: 1 | I113: 1 | J113: 1 | K113: 1 | L113: 1 | M113: 1 | N113: 1
C114: 0 | D114: 0 | E114: 0 | F114: -8.8470897e-16 | G114: 6.7307271e-16 | I114: 0 | J114: -2.442448e-09 | K114: 0 | L114: 0 | M114: 0 | N114: 0
B116: Ensemble | C116: 2018 | D116: 2019 | E116: 2020 | F116: 2021 | G116: 2022 | H116: 2023 | I116: 2025 | J116: 2030 | K116: 2035 | L116: 2040 | M116: 2045 | N116: 2050
B117: Besoin en émlectricité primaire | C117: 0 | D117: 0 | E117: 0 | F117: 0 | G117: 0 | H117: 0 | I117: 0 | J117: 0.73847092 | K117: 7.8156129 | L117: 19.047458 | M117: 37.727288 | N117: 64.045184
B121: Mix | C121: 2019 | D121: 2020 | E121: 2021 | F121: 2022 | G121: 2023 | H121: 2025 | I121: 2030 | J121: 2035 | K121: 2040 | L121: 2045 | M121: 2050
B122: Biocarburants | C122: =D109 -> 0 | D122: =E109 -> 0 | E122: =F109 -> 0.004 | F122: =G109 -> 0.008 | G122: =H109 -> 0.012 | H122: =I109 -> 0.02 | I122: =J109 -> 0.0558 | J122: =K109 -> 0.15 | ... M122: =N109 -> 0.35
B123: PtL | C123: =D110 -> 0 | D123: =E110 -> 0 | E123: =F110 -> 0 | F123: =G110 -> 0 | G123: =H110 -> 0 | H123: =I110 -> 0 | I123: =J110 -> 0.0042 | J123: =K110 -> 0.049062408 | ... M123: =N110 -> 0.4461396
