Workbook

Sheet Feuil4
B1: TAX_0 | C1: TAX_01_0 | D1: TAX_02_0 | E1: TAX_03_0 | F1: TAX_04_0 | G1: TAX_05_0 | H1: TAX_06_0 | I1: TAX_07_0 | J1: TAX_08_0 | K1: TAX_09_0 | L1: TAX_10_0 | M1: TAX_11_0 | N1: TAX_12_0 | O1: TAX_13_0 | P1: TAX_14_0 | Q1: TAX_15_0 | R1: TAX_16_0 | S1: TAX_17_0 | T1: TAX_18_0 | U1: TAX_19_0 | V1: TAX_21_0 | W1: TAX_22_0 | X1: TAX_23_0 | Y1: TAX_24_0 | Z1: TAX_CR_19_0
A2: 2004 | B2: 198321.64 | C2: 1826.8672 | D2: 23732.807 | E2: 10811.354 | F2: 318.68468 | G2: 249.91078 | H2: 834.97324 | I2: 52.306908 | J2: 120.11216 | K2: 803.97655 | L2: 7.7491716 | M2: 11.623757 | N2: 31876.895 | O2: 21060.311 | P2: 282.13879 | Q2: 743.92047 | R2: 235.78891 | S2: 12.873246 | T2: 525.99233 | U2: 63127.657 | V2: 32.933979 | W2: 33245.165 | X2: 6431.8124 | Y2: 1975.7881 | Z2: 0
A3: 2005 | B3: 201505.76 | C3: 1856.1981 | D3: 24113.844 | E3: 10984.933 | F3: 323.80127 | G3: 253.92318 | H3: 848.379 | I3: 53.146712 | J3: 122.0406 | K3: 816.88465 | L3: 7.873587 | M3: 11.810381 | N3: 32388.689 | O3: 21398.441 | P3: 286.66862 | Q3: 755.86435 | R3: 239.57458 | S3: 13.07993 | T3: 534.4373 | U3: 64141.192 | V3: 33.462745 | W3: 33778.927 | X3: 6535.0772 | Y3: 2007.5101 | Z3: 0
A4: 2006 | B4: 204740.96 | C4: 1886 | D4: 24501 | E4: 11161.3 | F4: 329 | G4: 258 | H4: 862 | I4: 54 | J4: 124 | K4: 830 | L4: 8 | M4: 12 | N4: 32908.699 | O4: 21741.995 | P4: 291.27117 | Q4: 768 | R4: 243.42103 | S4: 13.289932 | T4: 543.01787 | U4: 65171 | V4: 33.999985 | W4: 34321.219 | X4: 6640.0087 | Y4: 2039.7396 | Z4: 0
A5: 2007 | B5: 209991.48 | C5: 1905.3784 | D5: 25023.326 | E5: 11567.724 | F5: 338.8825 | G5: 265.75246 | H5: 882.3168 | I5: 56.439168 | J5: 128.57922 | K5: 863.56227 | L5: 8.206801 | M5: 12.266661 | N5: 34428.957 | O5: 22680.404 | P5: 297.65121 | Q5: 784.87869 | R5: 250.27937 | S5: 13.746692 | T5: 570.48784 | U5: 66788.126 | V5: 33.509741 | W5: 34363.047 | X5: 6704.8705 | Y5: 2023.0879 | Z5: 0
A6: 2008 | B6: 209240.76 | C6: 1896.549 | D6: 24894.248 | E6: 11196.434 | F6: 331.8491 | G6: 260.37759 | H6: 863.61728 | I6: 57.082176 | J6: 128.94595 | K6: 856.90965 | L6: 7.5151293 | M6: 11.236936 | N6: 34437.717 | O6: 22926.553 | P6: 313.61209 | Q6: 821.52287 | R6: 250.80888 | S6: 13.822104 | T6: 578.00804 | U6: 67101.751 | V6: 30.068643 | W6: 33456.791 | X6: 6844.7814 | Y6: 1960.5571 | Z6: 0
A7: 2009 | B7: 204626.3 | C7: 1947.3629 | D7: 24730.051 | E7: 11129.926 | F7: 305.08907 | G7: 239.18113 | H7: 838.55167 | I7: 54.581015 | J7: 119.55474 | K7: 847.062 | L7: 6.0322074 | M7: 8.5210077 | N7: 33709.029 | O7: 21800.771 | P7: 312.4621 | Q7: 814.74771 | R7: 240.58612 | S7: 13.671677 | T7: 507.46659 | U7: 65807.79 | V7: 27.572189 | W7: 32730.937 | X7: 6499.3414 | Y7: 1936.0172 | Z7: 0
A8: 2010 | B8: 207310.26 | C8: 1951.0907 | D8: 25085.223 | E8: 11057.388 | F8: 308.93554 | G8: 242.73377 | H8: 844.34921 | I8: 58.083519 | J8: 127.76504 | K8: 892.9076 | L8: 6.5552107 | M8: 9.6328423 | N8: 34473.266 | O8: 22074.181 | P8: 319.45385 | Q8: 833.39603 | R8: 252.27214 | S8: 14.176641 | T8: 535.11449 | U8: 67121.995 | V8: 27.171899 | W8: 32504.314 | X8: 6639.6542 | Y8: 1930.6015 | Z8: 0
A9: 2011 | B9: 209299.36 | C9: 1932.5557 | D9: 25689.117 | E9: 11180.927 | F9: 316.98661 | G9: 248.96462 | H9: 842.9682 | I9: 60.323065 | J9: 131.71102 | K9: 916.06177 | L9: 6.6628278 | M9: 10.189248 | N9: 35058.739 | O9: 22342.25 | P9: 323.89321 | Q9: 844.07264 | R9: 255.7418 | S9: 13.960516 | T9: 571.38808 | U9: 67990.382 | V9: 25.836487 | W9: 31824.112 | X9: 6829.5699 | Y9: 1882.943 | Z9: 0
A10: 2012 | B10: 207603.31 | C10: 1935.2784 | D10: 25530.945 | E10: 10384.846 | F10: 311.92784 | G10: 244.72036 | H10: 837.21273 | I10: 60.999181 | J10: 131.36426 | K10: 899.37692 | L10: 6.3662693 | M10: 9.5946222 | N10: 34855.862 | O10: 22242.91 | P10: 325.51307 | Q10: 846.95563 | R10: 253.85742 | S10: 13.64376 | T10: 574.6161 | U10: 68506.187 | V10: 24.980025 | W10: 30852.697 | X10: 6948.9828 | Y10: 1804.4711 | Z10: 0
A11: 2013 | B11: 207229.4 | C11: 1969.8312 | D11: 25554.739 | E11: 9974.3644 | F11: 307.53944 | G11: 241.4469 | H11: 833.40556 | I11: 60.827276 | J11: 128.80102 | K11: 884.60346 | L11: 6.3358361 | M11: 9.7084025 | N11: 35011.17 | O11: 22079.734 | P11: 324.94148 | Q11: 845.9058 | R11: 255.20131 | S11: 14.042138 | T11: 575.97145 | U11: 69243.975 | V11: 25.086553 | W11: 30190.983 | X11: 6928.1032 | Y11: 1762.6834 | Z11: 0
A12: 2014 | B12: 209134.95 | C12: 2040.6589 | D12: 25862.833 | E12: 9941.7861 | F12: 306.48311 | G12: 240.81379 | H12: 837.12414 | I12: 62.771682 | J12: 131.52531 | K12: 901.38293 | L12: 6.364072 | M12: 9.7492743 | N12: 35883.383 | O12: 22005.91 | P12: 322.3745 | Q12: 839.73136 | R12: 255.81424 | S12: 14.510243 | T12: 581.1474 | U12: 70352.641 | V12: 24.938725 | W12: 29881.596 | X12: 6892.6535 | Y12: 1738.7546 | Z12: 0
A13: 2015 | B13: 212002.04 | C13: 2031.8 | D13: 26297.76 | E13: 10415.97 | F13: 303.26803 | G13: 238.39571 | H13: 840.76786 | I13: 64.551057 | J13: 135.09932 | K13: 907.42527 | L13: 6.1862031 | M13: 9.8302362 | N13: 36853.612 | O13: 22000.406 | P13: 320.64201 | Q13: 831.31365 | R13: 249.80779 | S13: 14.932055 | T13: 580.20501 | U13: 71533.502 | V13: 24.415355 | W13: 29853.086 | X13: 6763.2855 | Y13: 1725.7792 | Z13: 0
... A48: 2050 | B48: 295197.15 | C48: 2028.0217 | D48: 34402.122 | E48: 27423.6 | F48: 735.11041 | G48: 590.12363 | H48: 1649.007 | I48: 60.182294 | J48: 139.91303 | K48: 1880.3915 | L48: 6.4014144 | M48: 13.225613 | N48: 26529.842 | O48: 26170.295 | P48: 357.00295 | Q48: 912.78049 | R48: 447.31213 | S48: 36.035839 | T48: 930.14481 | U48: 146926.03 | V48: 7.6950037 | W48: 13675.934 | X48: 9363.4383 | Y48: 912.54259 | Z48: 34.343913
B49: =(B48/B18)^(1/30)-1 -> 0.0080421095 | C49: =(C48/C18)^(1/30)-1 -> 0.00023422648 | D49: =(D48/D18)^(1/30)-1 -> 0.0048957139 | E49: =(E48/E18)^(1/30)-1 -> 0.025664407 | F49: =(F48/F18)^(1/30)-1 -> 0.023337781 | G49: =(G48/G18)^(1/30)-1 -> 0.023585564 | H49: =(H48/H18)^(1/30)-1 -> 0.018861881 | I49: =(I48/I18)^(1/30)-1 -> -0.0042132468 | ... Z49: =(Z48/Z18)^(1/30)-1 -> #DIV/0!

Sheet résultats
D1: 2004 | E1: 2005 | F1: 2006 | G1: 2007 | H1: 2008 | I1: 2009 | J1: 2010 | K1: 2011 | L1: 2012 | M1: 2013 | N1: 2014 | O1: 2015 | P1: 2016 | Q1: 2017 | R1: 2018 | S1: 2019 | T1: 2020 | U1: 2021 | V1: 2022 | W1: 2023 | X1: 2024 | Y1: 2025 | Z1: 2026 | AA1: 2027 | AB1: 2028 | AC1: 2029 | AD1: 2030 | AE1: 2031 | AF1: 2032 | AG1: 2033 | AH1: 2034 | AI1: 2035 | AJ1: 2036 | AK1: 2037 | AL1: 2038 | AM1: 2039 | AN1: 2040 | AO1: 2041 | AP1: 2042 | AQ1: 2043 | AR1: 2044 | AS1: 2045 | AT1: 2046 | AU1: 2047 | AV1: 2048 | AW1: 2049 | AX1: 2050
B2: Déficit public Tend | C2: DEP_VAL_1-REC_VAL_1 | F2: 46046.848 | G2: 41515.083 | H2: 39594.513 | I2: 69718.51 | J2: 87488.349 | K2: 77038.755 | L2: 81118.732 | M2: 92939.121 | N2: 101137.91 | O2: 107539.25 | P2: 112002.03 | Q2: 106420.95 | R2: 102279.62 | S2: 108345.1 | T2: 123607.72 | U2: 139142.73 | V2: 148016.42 | W2: 160126.87 | X2: 168814.27 | Y2: 180400.69 | Z2: 194747.04 | AA2: 210868.31 | AB2: 225696.61 | AC2: 240632.17 | AD2: 254458.85 | AE2: 269491.64 | AF2: 285171.44 | AG2: 300672.08 | AH2: 317224.11 | AI2: 335142.05 | AJ2: 353508.56 | AK2: 374408.8 | AL2: 396617.8 | AM2: 419707.55 | AN2: 444154.1 | AO2: 470379.62 | AP2: 498706.87 | AQ2: 528110.03 | AR2: 558501.84 | AS2: 590076.11 | AT2: 623118.38 | AU2: 657464.49 | AV2: 693614.92 | AW2: 731588.92 | AX2: 769566.07
A3: TEND | B3: Déficit public en % PIB | C3: (DEP_VAL_1-REC_VAL_1)/(PGDP_1*GDP_1) | F3: 0.026124716 | G3: 0.02274442 | H3: 0.021522202 | I3: 0.038636076 | J3: 0.047502793 | K3: 0.041135131 | L3: 0.043197439 | M3: 0.049103405 | N3: 0.05244689 | O3: 0.054724876 | P3: 0.055834333 | Q3: 0.051298635 | R3: 0.047620238 | S3: 0.048286177 | T3: 0.053494859 | U3: 0.058288537 | V3: 0.060211743 | W3: 0.062828808 | X3: 0.064223792 | Y3: 0.066833525 | Z3: 0.070364834 | AA3: 0.074166454 | AB3: 0.07721077 | AC3: 0.080065451 | AD3: 0.08232817 | AE3: 0.084731084 | AF3: 0.087058824 | AG3: 0.089077886 | AH3: 0.091156791 | AI3: 0.09330227 | AJ3: 0.095276489 | AK3: 0.097641455 | AL3: 0.10002783 | AM3: 0.10233191 | AN3: 0.10468288 | AO3: 0.1072081 | AP3: 0.10987339 | AQ3: 0.11249255 | AR3: 0.11501937 | AS3: 0.11753069 | AT3: 0.1200381 | AU3: 0.12251456 | AV3: 0.12503402 | AW3: 0.12758576 | AX3: 0.12974965
B4: Dépenses publiques | C4: DEP_VAL_1 | E4: 912128.34 | F4: 937425.07 | G4: 961862 | H4: 986659.9 | I4: 1008523.5 | J4: 1032902.3 | K4: 1047851.8 | L4: 1070612.1 | M4: 1095908.2 | N4: 1121771.6 | O4: 1148883 | P4: 1175814.4 | Q4: 1206902.8 | R4: 1245996.2 | S4: 1296419.4 | T4: 1350708.4 | U4: 1402975.7 | V4: 1451638.6 | W4: 1509929.7 | X4: 1562894.7 | Y4: 1614378 | Z4: 1666703.6 | AA4: 1720982.7 | AB4: 1777230.8 | AC4: 1834921.4 | AD4: 1894585.3 | AE4: 1956462 | AF4: 2020712.3 | AG4: 2087899.9 | AH4: 2158999.1 | AI4: 2234346.9 | AJ4: 2314702.1 | AK4: 2400777.3 | AL4: 2490977.1 | AM4: 2585434.4 | AN4: 2683857.6 | AO4: 2787150.9 | AP4: 2895092.8 | AQ4: 3006721 | AR4: 3121990.2 | AS4: 3240852.9 | AT4: 3363392.3 | AU4: 3490293 | AV4: 3621928 | AW4: 3758278.4 | AX4: 3899770.5
B5: Cotisations sociales | C5: CL_S_20_1*L_S_20_1*PROG_L_20_1 | D5: 225891.81 | E5: 234108.95 | F5: 242473.94 | G5: 250402.08 | H5: 256846.06 | I5: 262566.58 | J5: 263167.14 | K5: 263676.15 | L5: 266631.64 | M5: 271219.5 | N5: 274530.54 | O5: 277636.51 | P5: 281316.62 | Q5: 286630.63 | R5: 294477.82 | S5: 304804.23 | T5: 315357.14 | U5: 325800.82 | V5: 336494.3 | W5: 349298.7 | X5: 361057.5 | Y5: 371493.17 | Z5: 382345.68 | AA5: 393507.52 | AB5: 404975.84 | AC5: 416650.51 | AD5: 428687.48 | AE5: 441273.82 | AF5: 454423.9 | AG5: 468306.16 | AH5: 483094.09 | AI5: 498892.45 | AJ5: 515802.52 | AK5: 533927.48 | AL5: 552830.23 | AM5: 572566.72 | AN5: 593050.89 | AO5: 614387.83 | AP5: 636528.74 | AQ5: 659213.31 | AR5: 682440.05 | AS5: 706213.51 | AT5: 730634.24 | AU5: 755794.01 | AV5: 781789.86 | AW5: 808601.89 | AX5: 836360.22
B6: Intérêts de la dette | C6: R_G_1(-1)*DEBT_G_VAL_1(-1) | E6: 41668.561 | F6: 43184.314 | G6: 43187.915 | H6: 42585.465 | I6: 43691.245 | J6: 43903.569 | K6: 45997.25 | L6: 47736.632 | M6: 49746.374 | N6: 51750.62 | O6: 54600.366 | P6: 57036.086 | Q6: 59608.47 | R6: 63917.696 | S6: 69712.845 | T6: 75012.737 | U6: 81112.827 | V6: 87706.558 | W6: 94734.86 | X6: 102253.86 | Y6: 110015.36 | Z6: 118114.17 | AA6: 126559.44 | AB6: 135469.42 | AC6: 144844.8 | AD6: 154706.49 | AE6: 165029.94 | AF6: 175911.67 | AG6: 187245.57 | AH6: 199257.16 | AI6: 211998.08 | AJ6: 225322.65 | AK6: 239682.38 | AL6: 254834.68 | AM6: 270844.39 | AN6: 287736.18 | AO6: 305568.31 | AP6: 324501.1 | AQ6: 344518.61 | AR6: 365670.45 | AS6: 387995.51 | AT6: 411526.55 | AU6: 436361.98 | AV6: 462557.85 | AW6: 490171.08 | AX6: 519229.76
B7: Facture énergétique | C7: PE_20_1*E_20_1 | D7: 5997.7128 | E7: 6215.8882 | F7: 6313.0449 | G7: 6408.2141 | H7: 6729.4513 | I7: 6554.4748 | J7: 6722.3094 | K7: 7044.4625 | L7: 7352.392 | M7: 7418.0233 | N7: 7378.7942 | O7: 7231.5171 | P7: 6831.6071 | Q7: 6866.0636 | R7: 7125.6747 | S7: 7046.934 | T7: 6890.9903 | U7: 7036.1768 | V7: 7189.8606 | W7: 7336.3779 | X7: 7446.8042 | Y7: 7522.2589 | Z7: 7589.8646 | AA7: 7659.7754 | AB7: 7730.1456 | AC7: 7801.9572 | AD7: 7873.2494 | AE7: 7942.2767 | AF7: 8011.5302 | AG7: 8074.5251 | AH7: 8143.0708 | AI7: 8206.4834 | AJ7: 8272.9158 | AK7: 8340.7582 | AL7: 8409.995 | AM7: 8479.8915 | AN7: 8551.2528 | AO7: 8625.0632 | AP7: 8699.6065 | AQ7: 8776.0369 | AR7: 8853.3439 | AS7: 8931.4201 | AT7: 9012.6121 | AU7: 9095.167 | AV7: 9181.8398 | AW7: 9264.0289 | AX7: 9346.0282
B8: Consommations intermédiaires | C8: PMAT_20_1*MAT_20_1 | D8: 79234.609 | E8: 82116.881 | F8: 84010.915 | G8: 86823.459 | H8: 87308.063 | I8: 81976.69 | J8: 85097.05 | K8: 86655.463 | L8: 86623.655 | M8: 87570.65 | N8: 89540.406 | O8: 92873.071 | P8: 94878.687 | Q8: 99511.806 | R8: 103270.42 | S8: 108144.72 | T8: 111864.5 | U8: 115659.22 | V8: 119505.11 | W8: 123828.11 | X8: 128117.41 | Y8: 132149.39 | Z8: 136112.48 | AA8: 140161.46 | AB8: 144340.62 | AC8: 148639.92 | AD8: 153085.93 | AE8: 157629.17 | AF8: 162375.38 | AG8: 167332.19 | AH8: 172539.58 | AI8: 178063.66 | AJ8: 183907.28 | AK8: 190122.88 | AL8: 196667.26 | AM8: 203529.43 | AN8: 210686.97 | AO8: 218143.41 | AP8: 225911.21 | AQ8: 233937 | AR8: 242204.91 | AS8: 250699.34 | AT8: 259435.99 | AU8: 268429.47 | AV8: 277708.56 | AW8: 287278.94 | AX8: 297181.5
B9: Taxe à la production | C9: PIY_20_1*IY_20_1 | D9: 7105.6417 | E9: 7364.1196 | F9: 7461.7212 | G9: 7630.9433 | H9: 7780.8693 | I9: 7889.7548 | J9: 7984.8462 | K9: 8073.1776 | L9: 8165.7128 | M9: 8284.1869 | N9: 8396.2133 | O9: 8558.7543 | P9: 8722.3275 | Q9: 8949.8236 | R9: 9200.5088 | S9: 9520.9596 | T9: 9847.0824 | U9: 10181.936 | V9: 10520.846 | W9: 10900.939 | X9: 11277.729 | Y9: 11632.571 | Z9: 11981.497 | AA9: 12338.106 | AB9: 12705.916 | AC9: 13083.907 | AD9: 13474.151 | AE9: 13876.57 | AF9: 14295.903 | AG9: 14733.023 | AH9: 15191.22 | AI9: 15676.152 | AJ9: 16188.91 | AK9: 16734.184 | AL9: 17308.494 | AM9: 17910.952 | AN9: 18539.625 | AO9: 19195.57 | AP9: 19879.596 | AQ9: 20586.832 | AR9: 21315.739 | AS9: 22064.798 | AT9: 22835.249 | AU9: 23628.229 | AV9: 24446.08 | AW9: 25289.462 | AX9: 26160.313
B10: Investissements | C10: PIA_20_1*IA_20_1 | D10: 56421.514 | E10: 58473.927 | F10: 60071.544 | G10: 61013.011 | H10: 60073.363 | I10: 62700.448 | J10: 63450.005 | K10: 60935.431 | L10: 63272.986 | M10: 62819.218 | N10: 61054.072 | O10: 60796.705 | P10: 62812.171 | Q10: 62624.632 | R10: 65020.912 | S10: 71426.599 | T10: 73890.333 | U10: 76328.741 | V10: 78845.266 | W10: 81858.997 | X10: 84617.555 | Y10: 87074.422 | Z10: 89603.334 | AA10: 92225.244 | AB10: 94957.072 | AC10: 97759.157 | AD10: 100661.3 | AE10: 103706.65 | AF10: 106891.85 | AG10: 110226.9 | AH10: 113746.5 | AI10: 117503.55 | AJ10: 121482.67 | AK10: 125733.94 | AL10: 130174.36 | AM10: 134814.48 | AN10: 139636.21 | AO10: 144656.39 | AP10: 149879.63 | AQ10: 155246.28 | AR10: 160754.08 | AS10: 166399.79 | AT10: 172204.94 | AU10: 178189.24 | AV10: 184372.63 | AW10: 190750.39 | AX10: 197376.14
B11: Consommation finale | C11: PG_1*G_1-PG_20_1*G_20_1 | D11: 107619 | E11: 111533.8 | F11: 113942.67 | G11: 117442.67 | H11: 123159.05 | I11: 127288.16 | J11: 132353 | K11: 134411.74 | L11: 138386.77 | M11: 143777.02 | N11: 148459.89 | O11: 153311.54 | P11: 158002.3 | Q11: 162015.26 | R11: 164253.74 | S11: 169990.65 | T11: 175872.75 | U11: 181812.26 | V11: 187877.36 | W11: 194596.61 | X11: 201343.37 | Y11: 207721.1 | Z11: 214027.09 | AA11: 220408.29 | AB11: 226947.75 | AC11: 233645.1 | AD11: 240538.92 | AE11: 247695.01 | AF11: 255140.26 | AG11: 262913.14 | AH11: 271084.11 | AI11: 279726.78 | AJ11: 288892.31 | AK11: 298654.92 | AL11: 308942.59 | AM11: 319733.36 | AN11: 330995.35 | AO11: 342738.18 | AP11: 354964.91 | AQ11: 367608.05 | AR11: 380632.29 | AS11: 394016.81 | AT11: 407774.1 | AU11: 421934.41 | AV11: 436539.05 | AW11: 451599.39 | AX11: 467162.18
B12: Subventions | C12: 0-(PSUB_1*SUB_1-PSUB_01_1*SUB_01_1) | D12: 8435.1565 | E12: 8741.9973 | F12: 9052.0676 | G12: 9514.5739 | H12: 9579.7848 | I12: 9185.7675 | J12: 9668.5068 | K12: 9958.4654 | L12: 10138.964 | M12: 10380.176 | N12: 10657.159 | O12: 10910.06 | P12: 11189.514 | Q12: 11835.116 | R12: 12147.105 | S12: 12663.046 | T12: 12921.232 | U12: 13199.942 | V12: 13543.215 | W12: 13963.058 | X12: 14418.093 | Y12: 14859.872 | Z12: 15285.356 | AA12: 15712.974 | AB12: 16159 | AC12: 16613.691 | AD12: 17083.717 | AE12: 17529.075 | AF12: 17968.217 | AG12: 18436.308 | AH12: 18926.688 | AI12: 19417.465 | AJ12: 19972.814 | AK12: 20543.634 | AL12: 21133.195 | AM12: 21743.865 | AN12: 22372.435 | AO12: 23015.883 | AP12: 23685.677 | AQ12: 24374.318 | AR12: 25083.314 | AS12: 25809.649 | AT12: 26565.526 | AU12: 27343.676 | AV12: 28145.897 | AW12: 28970.224 | AX12: 29826.427
B13: Subventions à la production | C13: 0-(PSY_1*SY_1-PSY_01_1*SY_01_1) | D13: 14588.352 | E13: 15119.024 | F13: 15344.916 | G13: 15983.264 | H13: 16301.289 | I13: 15772.841 | J13: 16234.242 | K13: 16522.807 | L13: 16716.689 | M13: 16911.088 | N13: 17281.824 | O13: 17695.966 | P13: 18040.865 | Q13: 18786.288 | R13: 19467.161 | S13: 20347.074 | T13: 20953.956 | U13: 21678.036 | V13: 22367.955 | W13: 23211.139 | X13: 23986.274 | Y13: 24694.152 | Z13: 25348.433 | AA13: 26064.881 | AB13: 26824.271 | AC13: 27614.382 | AD13: 28442.663 | AE13: 29254.24 | AF13: 30113.901 | AG13: 31016.293 | AH13: 31962.766 | AI13: 32973.91 | AJ13: 34043.808 | AK13: 35169.082 | AL13: 36349.705 | AM13: 37583.41 | AN13: 38864.022 | AO13: 40182.702 | AP13: 41562.588 | AQ13: 42981.666 | AR13: 44445.954 | AS13: 45946.449 | AT13: 47496.024 | AU13: 49089.058 | AV13: 50733.476 | AW13: 52430.076 | AX13: 54203.878
B14: Prestations sociales | C14: PRESOC_VAL_1 | D14: 334613.16 | E14: 346785.19 | F14: 355569.94 | G14: 362474.15 | H14: 375166.89 | I14: 389779.76 | J14: 402784.48 | K14: 413040.95 | L14: 424174.08 | M14: 435846.94 | N14: 448624.69 | O14: 460339.77 | P14: 470567.91 | Q14: 482243.94 | R14: 497227.39 | S14: 511861.13 | T14: 538863.16 | U14: 556795.2 | V14: 575163.65 | W14: 596984.81 | X14: 617015.79 | Y14: 634827.7 | Z14: 653737.58 | AA14: 673445 | AB14: 693811.23 | AC14: 714508.93 | AD14: 735794.43 | AE14: 757932.65 | AF14: 780689.81 | AG14: 804428.23 | AH14: 829568.36 | AI14: 856185.29 | AJ14: 884744.01 | AK14: 915443.48 | AL14: 947558.99 | AM14: 981117.9 | AN14: 1015976 | AO14: 1052363.7 | AP14: 1090311.4 | AQ14: 1129341.4 | AR14: 1169398.3 | AS14: 1210442.2 | AT14: 1252620.9 | AU14: 1296081 | AV14: 1340968.7 | AW14: 1387225.8 | AX14: 1434916.2
B15: Subventions à la rénovation énergétique | C15: SUB_RENOV_VAL_1 | D15: 0 | E15: 0 | F15: 0 | G15: 981.71741 | H15: 1275.7646 | I15: 1256.1846 | J15: 962.83367 | K15: 907.83579 | L15: 730.04444 | M15: 1046.0339 | N15: 1478.0556 | O15: 2067.9391 | P15: 1560.2962 | Q15: 1611.5249 | R15: 1227.2902 | S15: 1845.6156 | T15: 1829.233 | U15: 3502.7992 | V15: 2632.5168 | W15: 2779.9116 | X15: 0 | Y15: 0 | Z15: 0 | AA15: 0 | AB15: 0 | AC15: 0 | AD15: 0 | AE15: 0 | AF15: 0 | AG15: 0 | AH15: 0 | AI15: 0 | AJ15: 0 | AK15: 0 | AL15: 0 | AM15: 0 | AN15: 0 | AO15: 0 | AP15: 0 | AQ15: 0 | AR15: 0 | AS15: 0 | AT15: 0 | AU15: 0 | AV15: 0 | AW15: 0 | AX15: 0
B16: Subventions aux automobiles | C16: SUB_AUTO_VAL_1 | D16: 0 | E16: 0 | F16: 0 | G16: 0 | H16: -146.15689 | I16: -138.40401 | J16: -122.17213 | K16: -60.537774 | L16: 30.851943 | M16: 248.66455 | N16: 291.27213 | O16: -1159.0664 | P16: -1100.1117 | Q16: -1744.0667 | R16: -2367.1233 | S16: -1949.7674 | T16: -3557.2983 | U16: -1245.6668 | V16: -1567.8608 | W16: -1318.5097 | X16: -1088.306 | Y16: -832.82382 | Z16: -651.75153 | AA16: -384.02915 | AB16: -86.374331 | AC16: 220.77697 | AD16: 523.75277 | AE16: 816.18698 | AF16: 1044.671 | AG16: 1266.8012 | AH16: 1479.0389 | AI16: 1600.2116 | AJ16: 1826.6695 | AK16: 2022.7327 | AL16: 2195.0392 | AM16: 2351.0038 | AN16: 2491.7308 | AO16: 2609.1341 | AP16: 2728.5225 | AQ16: 2846.2287 | AR16: 2959.1383 | AS16: 3066.5467 | AT16: 3154.3593 | AU16: 3244.5288 | AV16: 3332.8367 | AW16: 3416.9084 | AX16: 3500.0569
B17: Redistribution des recettes de taxe carbone aux ménages | C17: REDIS_VAL_TCO_H_1 | D17: 0 | E17: 0 | F17: 0 | G17: 0 | H17: 0 | I17: 0 | J17: 0 | K17: 0 | L17: 0 | M17: 0 | N17: 882.28486 | O17: 1736.9373 | P17: 2713.0584 | Q17: 3719.5187 | R17: 5332.1552 | S17: 5271.6672 | T17: 5175.6218 | U17: 5019.5414 | V17: 4854.2733 | W17: 4679.7854 | X17: 4603.5513 | Y17: 4523.5657 | Z17: 4426.1807 | AA17: 4336.4638 | AB17: 4250.8516 | AC17: 4167.1391 | AD17: 4084.0852 | AE17: 4002.8592 | AF17: 3918.1668 | AG17: 3832.3533 | AH17: 3745.957 | AI17: 3657.2084 | AJ17: 3575.9356 | AK17: 3497.2599 | AL17: 3420.5984 | AM17: 3345.7049 | AN17: 3272.7044 | AO17: 3195.9268 | AP17: 3119.8798 | AQ17: 3044.4722 | AR17: 2969.7843 | AS17: 2895.8531 | AT17: 2821.7121 | AU17: 2748.4372 | AV17: 2675.3321 | AW17: 2603.4753 | AX17: 2533.0899
B18: Redistribution des recettes de l'ETS aux secteurs | C18: REDIS_VAL_SEC_TCO_1 | D18: 0 | E18: 0 | F18: 0 | G18: 0 | H18: 0 | I18: 0 | J18: 0 | K18: 0 | L18: 0 | M18: 0 | N18: 804.87323 | O18: 1636.4205 | P18: 2517.5888 | Q18: 3417.9982 | R18: 4753.4041 | S18: 4618.4269 | T18: 4516.8533 | U18: 4481.9143 | V18: 4453.284 | W18: 4449.0536 | X18: 4524.5909 | Y18: 4574.287 | Z18: 4565.3748 | AA18: 4566.5347 | AB18: 4571.7816 | AC18: 4578.5093 | AD18: 4588.2624 | AE18: 4579.8662 | AF18: 4574.083 | AG18: 4570.3513 | AH18: 4566.7284 | AI18: 4566.477 | AJ18: 4582.2889 | AK18: 4600.5013 | AL18: 4620.2469 | AM18: 4641.3396 | AN18: 4663.0128 | AO18: 4695.203 | AP18: 4730.587 | AQ18: 4765.6237 | AR18: 4801.0399 | AS18: 4835.9385 | AT18: 4880.9187 | AU18: 4926.0795 | AV18: 4971.1071 | AW18: 5017.2263 | AX18: 5065.3508
... B21: Redistribution des recettes de l'ETS aux secteurs | C21: REDIS_VAL_SEC_ETS2_1 | D21: 0 | E21: 0 | F21: 0 | G21: 0 | H21: 0 | I21: 0 | J21: 0 | K21: 0 | L21: 0 | M21: 0 | N21: 0 | O21: 0 | P21: 0 | Q21: 0 | R21: 0 | S21: 0 | T21: 0 | U21: 0 | V21: 0 | W21: 0 | X21: 0 | Y21: 0 | Z21: 0 | AA21: 0 | AB21: 0 | AC21: 0 | AD21: 0 | AE21: 0 | AF21: 0 | AG21: 0 | AH21: 0 | AI21: 0 | AJ21: 0 | AK21: 0 | AL21: 0 | AM21: 0 | AN21: 0 | AO21: 0 | AP21: 0 | AQ21: 0 | AR21: 0 | AS21: 0 | AT21: 0 | AU21: 0 | AV21: 0 | AW21: 0 | AX21: 0
B22: Recettes publiques | C22: REC_VAL_1 | F22: 891378.22 | G22: 920346.92 | H22: 947065.38 | I22: 938804.99 | J22: 945413.99 | K22: 970813.09 | L22: 989493.32 | M22: 1002969.1 | N22: 1020633.7 | O22: 1041343.8 | P22: 1063812.4 | Q22: 1100481.8 | R22: 1143716.6 | S22: 1188074.3 | T22: 1227100.7 | U22: 1263833 | V22: 1303622.2 | W22: 1349802.8 | X22: 1394080.5 | Y22: 1433977.3 | Z22: 1471956.5 | AA22: 1510114.4 | AB22: 1551534.1 | AC22: 1594289.2 | AD22: 1640126.4 | AE22: 1686970.3 | AF22: 1735540.8 | AG22: 1787227.8 | AH22: 1841775 | AI22: 1899204.8 | AJ22: 1961193.5 | AK22: 2026368.5 | AL22: 2094359.3 | AM22: 2165726.9 | AN22: 2239703.5 | AO22: 2316771.3 | AP22: 2396386 | AQ22: 2478610.9 | AR22: 2563488.4 | AS22: 2650776.8 | AT22: 2740273.9 | AU22: 2832828.5 | AV22: 2928313.1 | AW22: 3026689.5 | AX22: 3130204.5
B23: Dividendes | C23: DIV_GOV_VAL_1 | D23: 6736.0217 | E23: 6981.0542 | F23: 7184.2108 | G23: 6897.7147 | H23: 6995.8402 | I23: 6577.538 | J23: 6110.018 | K23: 6724.3593 | L23: 7115.3042 | M23: 7000.438 | N23: 6942.4202 | O23: 7144.7234 | P23: 7346.8706 | Q23: 7554.5856 | R23: 7841.8697 | S23: 8018.0041 | T23: 8358.3008 | U23: 8434.0763 | V23: 8682.2554 | W23: 8877.5713 | X23: 9099.16 | Y23: 9277.953 | Z23: 9377.266 | AA23: 9415.522 | AB23: 9589.7261 | AC23: 9837.5845 | AD23: 10083.097 | AE23: 10344.902 | AF23: 10646.632 | AG23: 10995.089 | AH23: 11350.762 | AI23: 11714.508 | AJ23: 12117.548 | AK23: 12529.16 | AL23: 12936.479 | AM23: 13376.175 | AN23: 13834.35 | AO23: 14306.499 | AP23: 14760.816 | AQ23: 15248.234 | AR23: 15757.142 | AS23: 16292.795 | AT23: 16839.839 | AU23: 17412.563 | AV23: 17999.446 | AW23: 18602.692 | AX23: 19220.508
B24: Impôts sur les revenus et le patrimoine | C24: IR_VAL_1 | D24: 130354.82 | E24: 135096.67 | F24: 138640.55 | G24: 147517.58 | H24: 157566.63 | I24: 161161.36 | J24: 165854.42 | K24: 175705.73 | L24: 185407.9 | M24: 192921.2 | N24: 195697.58 | O24: 199466.42 | P24: 203516.6 | Q24: 209936.36 | R24: 218159.57 | S24: 226261.65 | T24: 235671.71 | U24: 242524.46 | V24: 250415.56 | W24: 259367.27 | X24: 267742.4 | Y24: 275093.45 | Z24: 282301.99 | AA24: 289415.28 | AB24: 297377.86 | AC24: 305840.31 | AD24: 314549.97 | AE24: 323724.82 | AF24: 333418.18 | AG24: 343829.33 | AH24: 354819.97 | AI24: 366425.28 | AJ24: 378974.5 | AK24: 392235.73 | AL24: 405973.11 | AM24: 420388.96 | AN24: 435376.92 | AO24: 450956.27 | AP24: 466947.53 | AQ24: 483452.09 | AR24: 500424.44 | AS24: 517887.79 | AT24: 535838.68 | AU24: 554394.3 | AV24: 573555.55 | AW24: 593313.15 | AX24: 613882.41
B25: Taxes sur les revenus financiers | C25: AIC_VAL_1 | D25: 16317.279 | E25: 16910.844 | F25: 17354.453 | G25: 17686.606 | H25: 18234.342 | I25: 18023.439 | J25: 17945.089 | K25: 18412.209 | L25: 18835.65 | M25: 19018.22 | N25: 19291.916 | O25: 19663.45 | P25: 20062.718 | Q25: 20695.579 | R25: 21506.225 | S25: 22304.93 | T25: 23232.577 | U25: 23908.122 | V25: 24686.029 | W25: 25568.491 | X25: 26394.112 | Y25: 27118.781 | Z25: 27829.401 | AA25: 28530.63 | AB25: 29315.584 | AC25: 30149.814 | AD25: 31008.415 | AE25: 31912.874 | AF25: 32868.447 | AG25: 33894.781 | AH25: 34978.242 | AI25: 36122.295 | AJ25: 37359.401 | AK25: 38666.697 | AL25: 40020.931 | AM25: 41442.049 | AN25: 42919.565 | AO25: 44455.381 | AP25: 46031.805 | AQ25: 47658.828 | AR25: 49331.966 | AS25: 51053.508 | AT25: 52823.111 | AU25: 54652.329 | AV25: 56541.25 | AW25: 58488.959 | AX25: 60516.682
B26: Versement européens | C26: INC_GOV_OTH_NET | D26: 13404.851 | E26: 13892.471 | F26: 14397.83 | G26: 14944.719 | H26: 15512.381 | I26: 16101.606 | J26: 16713.211 | K26: 17348.048 | L26: 18006.999 | M26: 18690.979 | N26: 19400.94 | O26: 20137.868 | P26: 20846.405 | Q26: 21579.871 | R26: 22339.144 | S26: 23111.678 | T26: 23907.252 | U26: 24697.605 | V26: 25509.093 | W26: 26478.863 | X26: 27368.02 | Y26: 28157.266 | Z26: 28980.126 | AA26: 29835.301 | AB26: 30727.385 | AC26: 31643.97 | AD26: 32594.03 | AE26: 33587.271 | AF26: 34619.5 | AG26: 35699.35 | AH26: 36837.936 | AI26: 38045.151 | AJ26: 39329.348 | AK26: 40701.058 | AL26: 42133.61 | AM26: 43631.043 | AN26: 45187.199 | AO26: 46813.04 | AP26: 48507.035 | AQ26: 50249.529 | AR26: 52040.109 | AS26: 53877.777 | AT26: 55768.666 | AU26: 57719.138 | AV26: 59735.578 | AW26: 61816.323 | AX26: 63964.189
B27: Taxes à la consommation | C27: PTAX_1*TAX_1 | D27: 190620.57 | E27: 197554.67 | F27: 201147.45 | G27: 206937.78 | H27: 209327.17 | I27: 205566.88 | J27: 210304.23 | K27: 214070.8 | L27: 214158.71 | M27: 215210.81 | N27: 221745.64 | O27: 225341.83 | P27: 228654.9 | Q27: 236281.66 | R27: 243367.73 | S27: 251221.58 | T27: 256087.16 | U27: 262341.11 | V27: 269169.91 | W27: 278849.91 | X27: 286714.01 | Y27: 293569.3 | Z27: 300400.64 | AA27: 307295.61 | AB27: 314686.83 | AC27: 322299.68 | AD27: 330207.75 | AE27: 338463.05 | AF27: 346663.58 | AG27: 355563.6 | AH27: 364970.75 | AI27: 374655.37 | AJ27: 385637.78 | AK27: 396940.88 | AL27: 408791.54 | AM27: 421112.69 | AN27: 433823.27 | AO27: 446797.1 | AP27: 460299.8 | AQ27: 474185.32 | AR27: 488647.39 | AS27: 503408.9 | AT27: 518614.92 | AU27: 534392.16 | AV27: 550649.67 | AW27: 567404.96 | AX27: 585574.01
B28: Taxes à la production | C28: PIY_1*IY_1 | D28: 70157.971 | E28: 72710.067 | F28: 73838.983 | G28: 76385.248 | H28: 77177.742 | I28: 73793.167 | J28: 76150.993 | K28: 77725.644 | L28: 78078.96 | M28: 78660.372 | N28: 80171.835 | O28: 82000.075 | P28: 83462.603 | Q28: 87053.346 | R28: 90348.384 | S28: 94366.063 | T28: 97076.558 | U28: 100479.77 | V28: 103649.76 | W28: 107579.43 | X28: 111271.61 | Y28: 114639.81 | Z28: 117668.47 | AA28: 121063 | AB28: 124700.71 | AC28: 128510.98 | AD28: 132539.43 | AE28: 136297.45 | AF28: 140310.18 | AG28: 144509.55 | AH28: 148910.79 | AI28: 153641.1 | AJ28: 158606.57 | AK28: 163826.06 | AL28: 169305.97 | AM28: 175029.8 | AN28: 180966.35 | AO28: 187059.96 | AP28: 193437.87 | AQ28: 199989.16 | AR28: 206755.11 | AS28: 213684.59 | AT28: 220861.8 | AU28: 228239.84 | AV28: 235855.63 | AW28: 243709.41 | AX28: 251945
B29: Impôts sur les bénéfices | C29: PIS_1*IS_1 | F29: 41720 | G29: 39457.604 | H29: 40747.154 | I29: 37985.352 | J29: 35239.253 | K29: 39462.881 | L29: 41536.949 | M29: 40347.046 | N29: 40273.369 | O29: 41738.573 | P29: 42656.482 | Q29: 43783.153 | R29: 45752.284 | S29: 46287.534 | T29: 48729.568 | U29: 49719.348 | V29: 51548.731 | W29: 51967.247 | X29: 53691.619 | Y29: 55095.203 | Z29: 56197.89 | AA29: 56866.112 | AB29: 58321.593 | AC29: 59445.246 | AD29: 62057.103 | AE29: 64165.635 | AF29: 66016.768 | AG29: 68051.159 | AH29: 70321.819 | AI29: 72540.278 | AJ29: 75096.344 | AK29: 77685.893 | AL29: 80271.597 | AM29: 83194.414 | AN29: 86033.258 | AO29: 89059.829 | AP29: 91929.397 | AQ29: 95062.383 | AR29: 98299.989 | AS29: 101731.56 | AT29: 105123.35 | AU29: 108721.56 | AV29: 112353.96 | AW29: 115945.19 | AX29: 119794.69
B30: Cotisations sociales | C30: PCSE_TOT_1*CSE_TOT_1+PCSS_TOT_1*CSS_TOT_1 | D30: 344617.11 | E30: 357153.05 | F30: 369017.92 | G30: 385094.53 | H30: 396077.86 | I30: 389117.47 | J30: 385211.89 | K30: 387603.98 | L30: 391386.7 | M30: 396035.84 | N30: 400161.67 | O30: 405640.99 | P30: 412494.56 | Q30: 425797.97 | R30: 443279.15 | S30: 465026.74 | T30: 480948.52 | U30: 496677.55 | V30: 512965.64 | W30: 532615.3 | X30: 550542.5 | Y30: 566378.02 | Z30: 582572.16 | AA30: 599024.02 | AB30: 615963 | AC30: 633332.61 | AD30: 651363.4 | AE30: 670424.17 | AF30: 690563.72 | AG30: 711936.96 | AH30: 734654.86 | AI30: 758967.49 | AJ30: 784857.36 | AK30: 812449.14 | AL30: 841162.16 | AM30: 871132.98 | AN30: 902254.23 | AO30: 934450.46 | AP30: 967725.19 | AQ30: 1001749.9 | AR30: 1036594.8 | AS30: 1072287.1 | AT30: 1108962.8 | AU30: 1146769.9 | AV30: 1185853.8 | AW30: 1226187.3 | AX30: 1268483.4
B31: Revenus des services publics | C31: PY_20_1*Y_20_1-(PE_20_1*E_20_1+PMAT_20_1*MAT_20_1+PIY_20_1*IY_20_1) | D31: 258421.17 | E31: 267821.61 | F31: 270550.76 | G31: 275827.22 | H31: 282272.32 | I31: 293044.75 | J31: 294355.51 | K31: 296746.96 | L31: 300946.15 | M31: 305663.35 | N31: 309150.81 | O31: 313826.46 | P31: 320131.73 | Q31: 326466.65 | R31: 334572.43 | S31: 345274.99 | T31: 357483.58 | U31: 369738.33 | V31: 382129.66 | W31: 396042.74 | X31: 409865.87 | Y31: 422919.86 | Z31: 435764.44 | AA31: 448892.4 | AB31: 462431.44 | AC31: 476341.27 | AD31: 490697.51 | AE31: 505547.61 | AF31: 521012.55 | AG31: 537133.39 | AH31: 554017.44 | AI31: 571882.97 | AJ31: 590771.68 | AK31: 610859.54 | AL31: 632021.58 | AM31: 654226.46 | AN31: 677402.36 | AO31: 701595.89 | AP31: 726835.43 | AQ31: 752937.57 | AR31: 779844.85 | AS31: 807499.43 | AT31: 835943.26 | AU31: 865218.47 | AV31: 895406.85 | AW31: 926543.16 | AX31: 958675.95
B32: moins les cotisations salariales des salariés du public | C32: (-1)*CL_S_20_1*L_S_20_1*PROG_L_20_1 | D32: -225891.81 | E32: -234108.95 | F32: -242473.94 | G32: -250402.08 | H32: -256846.06 | I32: -262566.58 | J32: -263167.14 | K32: -263676.15 | L32: -266631.64 | M32: -271219.5 | N32: -274530.54 | O32: -277636.51 | P32: -281316.62 | Q32: -286630.63 | R32: -294477.82 | S32: -304804.23 | T32: -315357.14 | U32: -325800.82 | V32: -336494.3 | W32: -349298.7 | X32: -361057.5 | Y32: -371493.17 | Z32: -382345.68 | AA32: -393507.52 | AB32: -404975.84 | AC32: -416650.51 | AD32: -428687.48 | AE32: -441273.82 | AF32: -454423.9 | AG32: -468306.16 | AH32: -483094.09 | AI32: -498892.45 | AJ32: -515802.52 | AK32: -533927.48 | AL32: -552830.23 | AM32: -572566.72 | AN32: -593050.89 | AO32: -614387.83 | AP32: -636528.74 | AQ32: -659213.31 | AR32: -682440.05 | AS32: -706213.51 | AT32: -730634.24 | AU32: -755794.01 | AV32: -781789.86 | AW32: -808601.89 | AX32: -836360.22
B33: recettes de l'ETS aux secteurs | C33: REC_VAL_SEC_ETS_1 | D33: 0 | E33: 0 | F33: 0 | G33: 0 | H33: 0 | I33: 0 | J33: 696.51547 | K33: 688.64066 | L33: 651.64154 | M33: 640.32182 | N33: 640.94018 | O33: 646.54145 | P33: 725.47396 | Q33: 825.77768 | R33: 942.08791 | S33: 1115.2353 | T33: 1270.1604 | U33: 1611.9912 | V33: 2052.2536 | W33: 2625.8302 | X33: 3320.5108 | Y33: 4122.9858 | Z33: 4218.283 | AA33: 4381.0472 | AB33: 4573.2224 | AC33: 4792.5871 | AD33: 5040.8345 | AE33: 5193.6462 | AF33: 5352.9102 | AG33: 5518.0531 | AH33: 5693.791 | AI33: 5879.1492 | AJ33: 6087.3201 | AK33: 6304.056 | AL33: 6531.6808 | AM33: 6771.9781 | AN33: 7021.1339 | AO33: 7773.5589 | AP33: 8589.3526 | AQ33: 9481.12 | AR33: 10461.881 | AS33: 11535.065 | AT33: 12429.099 | AU33: 13427.672 | AV33: 14504.834 | AW33: 15659.5 | AX33: 16909.441
B34: recettes de l'ETS aux secteurs | C34: REC_VAL_SEC_ETS2_1 | D34: 0 | E34: 0 | F34: 0 | G34: 0 | H34: 0 | I34: 0 | J34: 0 | K34: 0 | L34: 0 | M34: 0 | N34: 0 | O34: 0 | P34: 0 | Q34: 0 | R34: 0 | S34: 0 | T34: 0 | U34: 0 | V34: 0 | W34: 0 | X34: 0 | Y34: 0 | Z34: 0 | AA34: 0 | AB34: 0 | AC34: 0 | AD34: 0 | AE34: 0 | AF34: 0 | AG34: 0 | AH34: 0 | AI34: 0 | AJ34: 0 | AK34: 0 | AL34: 0 | AM34: 0 | AN34: 0 | AO34: 0 | AP34: 0 | AQ34: 0 | AR34: 0 | AS34: 0 | AT34: 0 | AU34: 0 | AV34: 0 | AW34: 0 | AX34: 0
B35: recettes de l'ETS aux ménages | C35: REC_VAL_ETS2_HH_1 | D35: 0 | E35: 0 | F35: 0 | G35: 0 | H35: 0 | I35: 0 | J35: 0 | K35: 0 | L35: 0 | M35: 0 | N35: 0 | O35: 0 | P35: 0 | Q35: 0 | R35: 0 | S35: 0 | T35: 0 | U35: 0 | V35: 0 | W35: 0 | X35: 0 | Y35: 0 | Z35: 0 | AA35: 0 | AB35: 0 | AC35: 0 | AD35: 0 | AE35: 0 | AF35: 0 | AG35: 0 | AH35: 0 | AI35: 0 | AJ35: 0 | AK35: 0 | AL35: 0 | AM35: 0 | AN35: 0 | AO35: 0 | AP35: 0 | AQ35: 0 | AR35: 0 | AS35: 0 | AT35: 0 | AU35: 0 | AV35: 0 | AW35: 0 | AX35: 0
B36: recettes de taxe carbone aux ménages | C36: REC_VAL_TCO_HH_1 | D36: 0 | E36: 0 | F36: 0 | G36: 0 | H36: 0 | I36: 0 | J36: 0 | K36: 0 | L36: 0 | M36: 0 | N36: 882.28486 | O36: 1736.9373 | P36: 2713.0584 | Q36: 3719.5187 | R36: 5332.1552 | S36: 5271.6672 | T36: 5175.6218 | U36: 5019.5414 | V36: 4854.2733 | W36: 4679.7854 | X36: 4603.5513 | Y36: 4523.5657 | Z36: 4426.1807 | AA36: 4336.4638 | AB36: 4250.8516 | AC36: 4167.1391 | AD36: 4084.0852 | AE36: 4002.8592 | AF36: 3918.1668 | AG36: 3832.3533 | AH36: 3745.957 | AI36: 3657.2084 | AJ36: 3575.9356 | AK36: 3497.2599 | AL36: 3420.5984 | AM36: 3345.7049 | AN36: 3272.7044 | AO36: 3195.9268 | AP36: 3119.8798 | AQ36: 3044.4722 | AR36: 2969.7843 | AS36: 2895.8531 | AT36: 2821.7121 | AU36: 2748.4372 | AV36: 2675.3321 | AW36: 2603.4753 | AX36: 2533.0899
B37: recettes de taxe carbone aux secteurs | C37: REC_VAL_SEC_TCO_1 | D37: 0 | E37: 0 | F37: 0 | G37: 0 | H37: 0 | I37: 0 | J37: 0 | K37: 0 | L37: 0 | M37: 0 | N37: 804.87323 | O37: 1636.4205 | P37: 2517.5888 | Q37: 3417.9982 | R37: 4753.4041 | S37: 4618.4269 | T37: 4516.8533 | U37: 4481.9143 | V37: 4453.284 | W37: 4449.0536 | X37: 4524.5909 | Y37: 4574.287 | Z37: 4565.3748 | AA37: 4566.5347 | AB37: 4571.7816 | AC37: 4578.5093 | AD37: 4588.2624 | AE37: 4579.8662 | AF37: 4574.083 | AG37: 4570.3513 | AH37: 4566.7284 | AI37: 4566.477 | AJ37: 4582.2889 | AK37: 4600.5013 | AL37: 4620.2469 | AM37: 4641.3396 | AN37: 4663.0128 | AO37: 4695.203 | AP37: 4730.587 | AQ37: 4765.6237 | AR37: 4801.0399 | AS37: 4835.9385 | AT37: 4880.9187 | AU37: 4926.0795 | AV37: 4971.1071 | AW37: 5017.2263 | AX37: 5065.3508
B38: Déficit public choc | C38: DEP_VAL_2-REC_VAL_2 | F38: 46046.848 | G38: 41515.083 | H38: 39594.513 | I38: 69718.51 | J38: 87488.349 | K38: 77038.755 | L38: 81118.732 | M38: 92939.121 | N38: 101137.91 | O38: 107539.25 | P38: 112002.03 | Q38: 106420.95 | R38: 102279.62 | S38: 108345.1 | T38: 123607.72 | U38: 139142.73 | V38: 148016.42 | W38: 160126.87 | X38: 169040.22 | Y38: 180349.64 | Z38: 194109.44 | AA38: 209638.35 | AB38: 224034.74 | AC38: 238668.32 | AD38: 252209.17 | AE38: 266381.91 | AF38: 282234.76 | AG38: 298025 | AH38: 314918.26 | AI38: 333068.07 | AJ38: 351738.04 | AK38: 372926.84 | AL38: 395367.14 | AM38: 418698.03 | AN38: 443370.68 | AO38: 469817.95 | AP38: 498305.43 | AQ38: 527843.59 | AR38: 558361.53 | AS38: 590045.18 | AT38: 623173.87 | AU38: 657605.48 | AV38: 693820.2 | AW38: 731741.26 | AX38: 769923.52
B39: Déficit public en % PIB | C39: (DEP_VAL_2-REC_VAL_2)/(PGDP_2*GDP_2) | F39: 0.026124716 | G39: 0.02274442 | H39: 0.021522202 | I39: 0.038636076 | J39: 0.047502793 | K39: 0.041135131 | L39: 0.043197439 | M39: 0.049103405 | N39: 0.05244689 | O39: 0.054724876 | P39: 0.055834333 | Q39: 0.051298635 | R39: 0.047620238 | S39: 0.048286177 | T39: 0.053494859 | U39: 0.058288537 | V39: 0.060211743 | W39: 0.062828808 | X39: 0.064302091 | Y39: 0.066781026 | Z39: 0.070064054 | AA39: 0.073621488 | AB39: 0.076485172 | AC39: 0.079207143 | AD39: 0.081346987 | AE39: 0.083453501 | AF39: 0.085825794 | AG39: 0.087923864 | AH39: 0.090093614 | AI39: 0.092296793 | AJ39: 0.094347299 | AK39: 0.096778738 | AL39: 0.099214242 | AM39: 0.10156782 | AN39: 0.10396142 | AO39: 0.10652453 | AP39: 0.1092103 | AQ39: 0.11184305 | AR39: 0.11438128 | AS39: 0.11689909 | AT39: 0.11940568 | AU39: 0.12187955 | AV39: 0.12439091 | AW39: 0.12691387 | AX39: 0.12909372 | AY39: =AX39-AX3 -> -0.00065593353
B40: Dépenses publiques | C40: DEP_VAL_2 | E40: 912128.34 | F40: 937425.07 | G40: 961862 | H40: 986659.9 | I40: 1008523.5 | J40: 1032902.3 | K40: 1047851.8 | L40: 1070612.1 | M40: 1095908.2 | N40: 1121771.6 | O40: 1148883 | P40: 1175814.4 | Q40: 1206902.8 | R40: 1245996.2 | S40: 1296419.4 | T40: 1350708.4 | U40: 1402975.7 | V40: 1451638.6 | W40: 1509929.7 | X40: 1562504.7 | Y40: 1613383.2 | Z40: 1665297.1 | AA40: 1719346.4 | AB40: 1775567.5 | AC40: 1833395.2 | AD40: 1893323.5 | AE40: 1955899.8 | AF40: 2021046.4 | AG40: 2089099.4 | AH40: 2161002.8 | AI40: 2237105.5 | AJ40: 2318176.5 | AK40: 2404909 | AL40: 2495727.7 | AM40: 2590785.2 | AN40: 2689784.3 | AO40: 2793482.5 | AP40: 2901786.6 | AQ40: 3013748.4 | AR40: 3129322.3 | AS40: 3248464.5 | AT40: 3371392 | AU40: 3498694.6 | AV40: 3630730.5 | AW40: 3767498.9 | AX40: 3909429.1
B41: Cotisations sociales | C41: CL_S_20_2*L_S_20_2*PROG_L_20_2 | D41: 225891.81 | E41: 234108.95 | F41: 242473.94 | G41: 250402.08 | H41: 256846.06 | I41: 262566.58 | J41: 263167.14 | K41: 263676.15 | L41: 266631.64 | M41: 271219.5 | N41: 274530.54 | O41: 277636.51 | P41: 281316.62 | Q41: 286630.63 | R41: 294477.82 | S41: 304804.23 | T41: 315357.14 | U41: 325800.82 | V41: 336494.3 | W41: 349298.7 | X41: 361045.38 | Y41: 371489.97 | Z41: 382419.34 | AA41: 393734.59 | AB41: 405428.38 | AC41: 417383.43 | AD41: 429740.74 | AE41: 442689.58 | AF41: 456216.82 | AG41: 470447.92 | AH41: 485554.74 | AI41: 501638.98 | AJ41: 518806.15 | AK41: 537162.07 | AL41: 556274.12 | AM41: 576201.73 | AN41: 596859.65 | AO41: 618353.07 | AP41: 640638.93 | AQ41: 663460.04 | AR41: 686817.27 | AS41: 710717.43 | AT41: 735266.54 | AU41: 760558.02 | AV41: 786689.63 | AW41: 813644.51 | AX41: 841552.82
A42: choc | B42: Intérêts de la dette | C42: R_G_2(-1)*DEBT_G_VAL_2(-1) | E42: 41668.561 | F42: 43184.314 | G42: 43187.915 | H42: 42585.465 | I42: 43691.245 | J42: 43903.569 | K42: 45997.25 | L42: 47736.632 | M42: 49746.374 | N42: 51750.62 | O42: 54600.366 | P42: 57036.086 | Q42: 59608.47 | R42: 63917.696 | S42: 69712.845 | T42: 75012.737 | U42: 81112.827 | V42: 87706.558 | W42: 94734.86 | X42: 102253.86 | Y42: 109977.53 | Z42: 118027.46 | AA42: 126421.96 | AB42: 135296.84 | AC42: 144651.94 | AD42: 154507.21 | AE42: 164837.07 | AF42: 175802.14 | AG42: 187201.93 | AH42: 199276.28 | AI42: 212064.45 | AJ42: 225445.01 | AK42: 239844.99 | AL42: 255027.83 | AM42: 271071.26 | AN42: 287995.5 | AO42: 305858.14 | AP42: 324801.81 | AQ42: 344825.45 | AR42: 365979.92 | AS42: 388302.85 | AT42: 411828.13 | AU42: 436674.65 | AV42: 462881.7 | AW42: 490504.24 | AX42: 519590.95
B43: Facture énergétique | C43: PE_20_2*E_20_2 | D43: 5997.7128 | E43: 6215.8882 | F43: 6313.0449 | G43: 6408.2141 | H43: 6729.4513 | I43: 6554.4748 | J43: 6722.3094 | K43: 7044.4625 | L43: 7352.392 | M43: 7418.0233 | N43: 7378.7942 | O43: 7231.5171 | P43: 6831.6071 | Q43: 6866.0636 | R43: 7125.6747 | S43: 7046.934 | T43: 6890.9903 | U43: 7036.1768 | V43: 7189.8606 | W43: 7336.3779 | X43: 7448.1304 | Y43: 7526.3313 | Z43: 7587.5725 | AA43: 7656.6257 | AB43: 7726.9634 | AC43: 7799.3385 | AD43: 7871.6266 | AE43: 7942.2859 | AF43: 8014.1673 | AG43: 8082.0013 | AH43: 8150.1291 | AI43: 8218.1524 | AJ43: 8286.3015 | AK43: 8353.6826 | AL43: 8424.3078 | AM43: 8495.5241 | AN43: 8568.0833 | AO43: 8642.9975 | AP43: 8718.3685 | AQ43: 8795.6426 | AR43: 8873.7413 | AS43: 8952.6039 | AT43: 9034.6114 | AU43: 9117.7578 | AV43: 9204.8883 | AW43: 9287.5807 | AX43: 9370.0128
B44: Consommations intermédiaires | C44: PMAT_20_2*MAT_20_2 | D44: 79234.609 | E44: 82116.881 | F44: 84010.915 | G44: 86823.459 | H44: 87308.063 | I44: 81976.69 | J44: 85097.05 | K44: 86655.463 | L44: 86623.655 | M44: 87570.65 | N44: 89540.406 | O44: 92873.071 | P44: 94878.687 | Q44: 99511.806 | R44: 103270.42 | S44: 108144.72 | T44: 111864.5 | U44: 115659.22 | V44: 119505.11 | W44: 123828.11 | X44: 128108.56 | Y44: 132135.53 | Z44: 136104.16 | AA44: 140166.34 | AB44: 144366.94 | AC44: 148694.88 | AD44: 153177.28 | AE44: 157778.95 | AF44: 162579.73 | AG44: 167590.31 | AH44: 172849.22 | AI44: 178423.07 | AJ44: 184315.29 | AK44: 190578.77 | AL44: 197169.97 | AM44: 204078.35 | AN44: 211281.68 | AO44: 218780.95 | AP44: 226591.12 | AQ44: 234658.82 | AR44: 242968.14 | AS44: 251503.73 | AT44: 260282.98 | AU44: 269319.95 | AV44: 278643.19 | AW44: 288259.83 | AX44: 298209.74
B45: Taxe à la production | C45: PIY_20_2*IY_20_2 | D45: 7105.6417 | E45: 7364.1196 | F45: 7461.7212 | G45: 7630.9433 | H45: 7780.8693 | I45: 7889.7548 | J45: 7984.8462 | K45: 8073.1776 | L45: 8165.7128 | M45: 8284.1869 | N45: 8396.2133 | O45: 8558.7543 | P45: 8722.3275 | Q45: 8949.8236 | R45: 9200.5088 | S45: 9520.9596 | T45: 9847.0824 | U45: 10181.936 | V45: 10520.846 | W45: 10900.939 | X45: 11277.801 | Y45: 11633.142 | Z45: 11982.998 | AA45: 12340.914 | AB45: 12710.49 | AC45: 13090.776 | AD45: 13483.859 | AE45: 13889.458 | AF45: 14312.527 | AG45: 14753.849 | AH45: 15216.604 | AI45: 15706.333 | AJ45: 16224.115 | AK45: 16774.622 | AL45: 17354.278 | AM45: 17962.174 | AN45: 18596.361 | AO45: 19257.864 | AP45: 19947.497 | AQ45: 20660.353 | AR45: 21394.876 | AS45: 22149.544 | AT45: 22925.601 | AU45: 23724.218 | AV45: 24547.754 | AW45: 25396.823 | AX45: 26273.509
B46: Investissements | C46: PIA_20_2*IA_20_2 | D46: 56421.514 | E46: 58473.927 | F46: 60071.544 | G46: 61013.011 | H46: 60073.363 | I46: 62700.448 | J46: 63450.005 | K46: 60935.431 | L46: 63272.986 | M46: 62819.218 | N46: 61054.072 | O46: 60796.705 | P46: 62812.171 | Q46: 62624.632 | R46: 65020.912 | S46: 71426.599 | T46: 73890.333 | U46: 76328.741 | V46: 78845.266 | W46: 81858.997 | X46: 84615.757 | Y46: 87076.979 | Z46: 89619.649 | AA46: 92261.63 | AB46: 95019.302 | AC46: 97852.041 | AD46: 100789.36 | AE46: 103875.22 | AF46: 107102.6 | AG46: 110477.9 | AH46: 114036.2 | AI46: 117830.33 | AJ46: 121846.02 | AK46: 126133.11 | AL46: 130607.92 | AM46: 135281.8 | AN46: 140136.69 | AO46: 145188.41 | AP46: 150442.65 | AQ46: 155839.82 | AR46: 161377.53 | AS46: 167052.72 | AT46: 172887.67 | AU46: 178902.56 | AV46: 185117.06 | AW46: 191526.09 | AX46: 198185.2
B47: Consommation finale | C47: PG_2*G_2-PG_20_2*G_20_2 | D47: 107619 | E47: 111533.8 | F47: 113942.67 | G47: 117442.67 | H47: 123159.05 | I47: 127288.16 | J47: 132353 | K47: 134411.74 | L47: 138386.77 | M47: 143777.02 | N47: 148459.89 | O47: 153311.54 | P47: 158002.3 | Q47: 162015.26 | R47: 164253.74 | S47: 169990.65 | T47: 175872.75 | U47: 181812.26 | V47: 187877.36 | W47: 194596.61 | X47: 201329.86 | Y47: 207695.45 | Z47: 214003.31 | AA47: 220401.91 | AB47: 226974.47 | AC47: 233718.56 | AD47: 240671.69 | AE47: 247927.6 | AF47: 255469.02 | AG47: 263335.83 | AH47: 271596.42 | AI47: 280326.92 | AJ47: 289578.82 | AK47: 299426.11 | AL47: 309797.31 | AM47: 320671.02 | AN47: 332015.3 | AO47: 343837.33 | AP47: 356142.11 | AQ47: 368862.87 | AR47: 381964.27 | AS47: 395425.69 | AT47: 409261.2 | AU47: 423501.21 | AV47: 438186.52 | AW47: 453330.44 | AX47: 468978.62
B48: Subventions sur les produits | C48: 0-(PSUB_2*SUB_2-PSUB_01_2*SUB_01_2) | D48: 8435.1565 | E48: 8741.9973 | F48: 9052.0676 | G48: 9514.5739 | H48: 9579.7848 | I48: 9185.7675 | J48: 9668.5068 | K48: 9958.4654 | L48: 10138.964 | M48: 10380.176 | N48: 10657.159 | O48: 10910.06 | P48: 11189.514 | Q48: 11835.116 | R48: 12147.105 | S48: 12663.046 | T48: 12921.232 | U48: 13199.942 | V48: 13543.215 | W48: 13963.058 | X48: 14460.81 | Y48: 14942.922 | Z48: 15402.337 | AA48: 15857.563 | AB48: 16326.757 | AC48: 16801.698 | AD48: 17290.196 | AE48: 17741.198 | AF48: 18183.932 | AG48: 18655.284 | AH48: 19148.355 | AI48: 19641.271 | AJ48: 20199.121 | AK48: 20773.19 | AL48: 21365.671 | AM48: 21979.216 | AN48: 22610.678 | AO48: 23255.134 | AP48: 23925.691 | AQ48: 24614.769 | AR48: 25323.916 | AS48: 26050.125 | AT48: 26807.467 | AU48: 27587.479 | AV48: 28391.46 | AW48: 29217.116 | AX48: 30075.307
B49: Subventions à la production | C49: 0-(PSY_2*SY_2-PSY_01_2*SY_01_2) | D49: 14588.352 | E49: 15119.024 | F49: 15344.916 | G49: 15983.264 | H49: 16301.289 | I49: 15772.841 | J49: 16234.242 | K49: 16522.807 | L49: 16716.689 | M49: 16911.088 | N49: 17281.824 | O49: 17695.966 | P49: 18040.865 | Q49: 18786.288 | R49: 19467.161 | S49: 20347.074 | T49: 20953.956 | U49: 21678.036 | V49: 22367.955 | W49: 23211.139 | X49: 23986.601 | Y49: 24700.197 | Z49: 25363.868 | AA49: 26090.909 | AB49: 26862.052 | AC49: 27665.075 | AD49: 28507.087 | AE49: 29331.805 | AF49: 30203.119 | AG49: 31116.714 | AH49: 32073.708 | AI49: 33094.243 | AJ49: 34172.951 | AK49: 35306.86 | AL49: 36495.481 | AM49: 37736.772 | AN49: 39024.759 | AO49: 40350.293 | AP49: 41737.103 | AQ49: 43163.025 | AR49: 44634.003 | AS49: 46141.256 | AT49: 47697.835 | AU49: 49298.296 | AV49: 50950.514 | AW49: 52654.901 | AX49: 54437.531
B50: Prestations sociales | C50: PRESOC_VAL_2 | D50: 334613.16 | E50: 346785.19 | F50: 355569.94 | G50: 362474.15 | H50: 375166.89 | I50: 389779.76 | J50: 402784.48 | K50: 413040.95 | L50: 424174.08 | M50: 435846.94 | N50: 448624.69 | O50: 460339.77 | P50: 470567.91 | Q50: 482243.94 | R50: 497227.39 | S50: 511861.13 | T50: 538863.16 | U50: 556795.2 | V50: 575163.65 | W50: 596984.81 | X50: 616974.23 | Y50: 634679.93 | Z50: 653454.95 | AA50: 673062.18 | AB50: 693389.23 | AC50: 714103.46 | AD50: 735453.21 | AE50: 757778.38 | AF50: 780812.15 | AG50: 804843.18 | AH50: 830262.72 | AI50: 857164.69 | AJ50: 886008.84 | AK50: 916985.62 | AL50: 949377.62 | AM50: 983215.05 | AN50: 1018350.6 | AO50: 1055003.9 | AP50: 1093209.6 | AQ50: 1132492.3 | AR50: 1172796.6 | AS50: 1214082.9 | AT50: 1256510.7 | AU50: 1300223.4 | AV50: 1345362.9 | AW50: 1391885.5 | AX50: 1439838
B51: Subventions à la rénovation énergétique | C51: SUB_RENOV_VAL_2 | D51: 0 | E51: 0 | F51: 0 | G51: 981.71741 | H51: 1275.7646 | I51: 1256.1846 | J51: 962.83367 | K51: 907.83579 | L51: 730.04444 | M51: 1046.0339 | N51: 1478.0556 | O51: 2067.9391 | P51: 1560.2962 | Q51: 1611.5249 | R51: 1227.2902 | S51: 1845.6156 | T51: 1829.233 | U51: 3502.7992 | V51: 2632.5168 | W51: 2779.9116 | X51: 0 | Y51: 0 | Z51: 0 | AA51: 0 | AB51: 0 | AC51: 0 | AD51: 0 | AE51: 0 | AF51: 0 | AG51: 0 | AH51: 0 | AI51: 0 | AJ51: 0 | AK51: 0 | AL51: 0 | AM51: 0 | AN51: 0 | AO51: 0 | AP51: 0 | AQ51: 0 | AR51: 0 | AS51: 0 | AT51: 0 | AU51: 0 | AV51: 0 | AW51: 0 | AX51: 0
B52: Subventions aux automobiles | C52: SUB_AUTO_VAL_2 | D52: 0 | E52: 0 | F52: 0 | G52: 0 | H52: -146.15689 | I52: -138.40401 | J52: -122.17213 | K52: -60.537774 | L52: 30.851943 | M52: 248.66455 | N52: 291.27213 | O52: -1159.0664 | P52: -1100.1117 | Q52: -1744.0667 | R52: -2367.1233 | S52: -1949.7674 | T52: -3557.2983 | U52: -1245.6668 | V52: -1567.8608 | W52: -1318.5097 | X52: -1089.0966 | Y52: -834.97631 | Z52: -654.10896 | AA52: -385.80999 | AB52: -87.322382 | AC52: 220.5095 | AD52: 523.9818 | AE52: 816.38039 | AF52: 1045.0485 | AG52: 1266.7581 | AH52: 1478.8549 | AI52: 1599.7516 | AJ52: 1825.8887 | AK52: 2021.7437 | AL52: 2193.8385 | AM52: 2349.5788 | AN52: 2490.1318 | AO52: 2607.5033 | AP52: 2726.8899 | AQ52: 2844.5778 | AR52: 2957.4706 | AS52: 3064.8722 | AT52: 3152.5613 | AU52: 3242.721 | AV52: 3331.0838 | AW52: 3414.7952 | AX52: 3498.0362
B53: Redistribution des recettes de taxe carbone aux ménages | C53: REDIS_VAL_TCO_H_2 | D53: 0 | E53: 0 | F53: 0 | G53: 0 | H53: 0 | I53: 0 | J53: 0 | K53: 0 | L53: 0 | M53: 0 | N53: 882.28486 | O53: 1736.9373 | P53: 2713.0584 | Q53: 3719.5187 | R53: 5332.1552 | S53: 5271.6672 | T53: 5175.6218 | U53: 5019.5414 | V53: 4854.2733 | W53: 4679.7854 | X53: 4603.3607 | Y53: 4525.4827 | Z53: 4429.608 | AA53: 4341.196 | AB53: 4256.9397 | AC53: 4174.6278 | AD53: 4092.9683 | AE53: 4012.7042 | AF53: 3928.7012 | AG53: 3843.1537 | AH53: 3757.501 | AI53: 3669.4228 | AJ53: 3588.3585 | AK53: 3509.5732 | AL53: 3433.0007 | AM53: 3358.1491 | AN53: 3285.1668 | AO53: 3208.6387 | AP53: 3132.8811 | AQ53: 3057.8115 | AR53: 2983.5163 | AS53: 2910.0351 | AT53: 2835.9773 | AU53: 2762.7545 | AV53: 2689.652 | AW53: 2617.7494 | AX53: 2547.2809
B54: Redistribution des recettes de l'ETS aux secteurs | C54: REDIS_VAL_SEC_TCO_2 | D54: 0 | E54: 0 | F54: 0 | G54: 0 | H54: 0 | I54: 0 | J54: 0 | K54: 0 | L54: 0 | M54: 0 | N54: 804.87323 | O54: 1636.4205 | P54: 2517.5888 | Q54: 3417.9982 | R54: 4753.4041 | S54: 4618.4269 | T54: 4516.8533 | U54: 4481.9143 | V54: 4453.284 | W54: 4449.0536 | X54: 4386.6833 | Y54: 4306.4511 | Z54: 4203.6019 | AA54: 4130.5998 | AB54: 4075.8064 | AC54: 4032.7039 | AD54: 3999.554 | AE54: 3981.6347 | AF54: 3971.1692 | AG54: 3963.1552 | AH54: 3956.1216 | AI54: 3951.3817 | AJ54: 3960.1532 | AK54: 3970.5747 | AL54: 3982.3031 | AM54: 3995.0796 | AN54: 4008.2906 | AO54: 4032.8874 | AP54: 4060.1498 | AQ54: 4087.2607 | AR54: 4114.7768 | AS54: 4141.9416 | AT54: 4179.0798 | AU54: 4216.5172 | AV54: 4254.1054 | AW54: 4292.5363 | AX54: 4332.8468
... B57: Redistribution des recettes de l'ETS aux secteurs | C57: REDIS_VAL_SEC_ETS2_2 | D57: 0 | E57: 0 | F57: 0 | G57: 0 | H57: 0 | I57: 0 | J57: 0 | K57: 0 | L57: 0 | M57: 0 | N57: 0 | O57: 0 | P57: 0 | Q57: 0 | R57: 0 | S57: 0 | T57: 0 | U57: 0 | V57: 0 | W57: 0 | X57: 0 | Y57: 0 | Z57: 0 | AA57: 0 | AB57: 0 | AC57: 0 | AD57: 0 | AE57: 0 | AF57: 0 | AG57: 0 | AH57: 0 | AI57: 0 | AJ57: 0 | AK57: 0 | AL57: 0 | AM57: 0 | AN57: 0 | AO57: 0 | AP57: 0 | AQ57: 0 | AR57: 0 | AS57: 0 | AT57: 0 | AU57: 0 | AV57: 0 | AW57: 0 | AX57: 0
B58: Recettes publiques | C58: REC_VAL_2 | F58: 891378.22 | G58: 920346.92 | H58: 947065.38 | I58: 938804.99 | J58: 945413.99 | K58: 970813.09 | L58: 989493.32 | M58: 1002969.1 | N58: 1020633.7 | O58: 1041343.8 | P58: 1063812.4 | Q58: 1100481.8 | R58: 1143716.6 | S58: 1188074.3 | T58: 1227100.7 | U58: 1263833 | V58: 1303622.2 | W58: 1349802.8 | X58: 1393464.5 | Y58: 1433033.5 | Z58: 1471187.7 | AA58: 1509708.1 | AB58: 1551532.7 | AC58: 1594726.9 | AD58: 1641114.3 | AE58: 1689517.9 | AF58: 1738811.7 | AG58: 1791074.4 | AH58: 1846084.5 | AI58: 1904037.4 | AJ58: 1966438.5 | AK58: 2031982.1 | AL58: 2100360.5 | AM58: 2172087.1 | AN58: 2246413.6 | AO58: 2323664.6 | AP58: 2403481.2 | AQ58: 2485904.8 | AR58: 2570960.8 | AS58: 2658419.3 | AT58: 2748218.2 | AU58: 2841089.1 | AV58: 2936910.3 | AW58: 3035757.6 | AX58: 3139505.5
B59: Dividendes | C59: DIV_GOV_VAL_2 | D59: 6736.0217 | E59: 6981.0542 | F59: 7184.2108 | G59: 6897.7147 | H59: 6995.8402 | I59: 6577.538 | J59: 6110.018 | K59: 6724.3593 | L59: 7115.3042 | M59: 7000.438 | N59: 6942.4202 | O59: 7144.7234 | P59: 7346.8706 | Q59: 7554.5856 | R59: 7841.8697 | S59: 8018.0041 | T59: 8358.3008 | U59: 8434.0763 | V59: 8682.2554 | W59: 8877.5713 | X59: 9104.1914 | Y59: 9294.3854 | Z59: 9409.6639 | AA59: 9458.2844 | AB59: 9637.375 | AC59: 9886.5267 | AD59: 10129.205 | AE59: 10367.778 | AF59: 10654.852 | AG59: 10987.051 | AH59: 11330.675 | AI59: 11681.294 | AJ59: 12072.779 | AK59: 12474.411 | AL59: 12872.357 | AM59: 13303.557 | AN59: 13754.134 | AO59: 14219.818 | AP59: 14668.8 | AQ59: 15152.102 | AR59: 15657.393 | AS59: 16189.605 | AT59: 16733.493 | AU59: 17304.452 | AV59: 17890.046 | AW59: 18489.019 | AX59: 19107.941
B60: Impôts sur les revenus et le patrimoine | C60: IR_VAL_2 | D60: 130354.82 | E60: 135096.67 | F60: 138640.55 | G60: 147517.58 | H60: 157566.63 | I60: 161161.36 | J60: 165854.42 | K60: 175705.73 | L60: 185407.9 | M60: 192921.2 | N60: 195697.58 | O60: 199466.42 | P60: 203516.6 | Q60: 209936.36 | R60: 218159.57 | S60: 226261.65 | T60: 235671.71 | U60: 242524.46 | V60: 250415.56 | W60: 259367.27 | X60: 267747.26 | Y60: 275174.56 | Z60: 282533.52 | AA60: 289814.56 | AB60: 297948.54 | AC60: 306587.29 | AD60: 315472.29 | AE60: 324771.91 | AF60: 334598.66 | AG60: 345117.48 | AH60: 356215.99 | AI60: 367916.05 | AJ60: 380549.57 | AK60: 393891 | AL60: 407703.86 | AM60: 422190.31 | AN60: 437245.57 | AO60: 452884.48 | AP60: 468938.36 | AQ60: 485508.1 | AR60: 502544.85 | AS60: 520072.14 | AT60: 538095.05 | AU60: 556729.95 | AV60: 575975.88 | AW60: 595813.72 | AX60: 616484.22
C61: AIC_VAL_2 | D61: 16317.279 | E61: 16910.844 | F61: 17354.453 | G61: 17686.606 | H61: 18234.342 | I61: 18023.439 | J61: 17945.089 | K61: 18412.209 | L61: 18835.65 | M61: 19018.22 | N61: 19291.916 | O61: 19663.45 | P61: 20062.718 | Q61: 20695.579 | R61: 21506.225 | S61: 22304.93 | T61: 23232.577 | U61: 23908.122 | V61: 24686.029 | W61: 25568.491 | X61: 26394.592 | Y61: 27126.777 | Z61: 27852.225 | AA61: 28569.992 | AB61: 29371.842 | AC61: 30223.451 | AD61: 31099.337 | AE61: 32016.097 | AF61: 32984.819 | AG61: 34021.768 | AH61: 35115.862 | AI61: 36269.256 | AJ61: 37514.672 | AK61: 38829.873 | AL61: 40191.549 | AM61: 41619.626 | AN61: 43103.777 | AO61: 44645.465 | AP61: 46228.06 | AQ61: 47861.51 | AR61: 49540.997 | AS61: 51268.842 | AT61: 53045.544 | AU61: 54882.578 | AV61: 56779.846 | AW61: 58735.465 | AX61: 60773.169
B62: Versement européens | C62: INC_GOV_OTH_NET | D62: 13404.851 | E62: 13892.471 | F62: 14397.83 | G62: 14944.719 | H62: 15512.381 | I62: 16101.606 | J62: 16713.211 | K62: 17348.048 | L62: 18006.999 | M62: 18690.979 | N62: 19400.94 | O62: 20137.868 | P62: 20846.405 | Q62: 21579.871 | R62: 22339.144 | S62: 23111.678 | T62: 23907.252 | U62: 24697.605 | V62: 25509.093 | W62: 26478.863 | X62: 27368.02 | Y62: 28157.266 | Z62: 28980.126 | AA62: 29835.301 | AB62: 30727.385 | AC62: 31643.97 | AD62: 32594.03 | AE62: 33587.271 | AF62: 34619.5 | AG62: 35699.35 | AH62: 36837.936 | AI62: 38045.151 | AJ62: 39329.348 | AK62: 40701.058 | AL62: 42133.61 | AM62: 43631.043 | AN62: 45187.199 | AO62: 46813.04 | AP62: 48507.035 | AQ62: 50249.529 | AR62: 52040.109 | AS62: 53877.777 | AT62: 55768.666 | AU62: 57719.138 | AV62: 59735.578 | AW62: 61816.323 | AX62: 63964.189
B63: Taxes à la consommation | C63: PTAX_2*TAX_2 | D63: 190620.57 | E63: 197554.67 | F63: 201147.45 | G63: 206937.78 | H63: 209327.17 | I63: 205566.88 | J63: 210304.23 | K63: 214070.8 | L63: 214158.71 | M63: 215210.81 | N63: 221745.64 | O63: 225341.83 | P63: 228654.9 | Q63: 236281.66 | R63: 243367.73 | S63: 251221.58 | T63: 256087.16 | U63: 262341.11 | V63: 269169.91 | W63: 278849.91 | X63: 286630.85 | Y63: 293443.18 | Z63: 300284.69 | AA63: 307207.9 | AB63: 314641.42 | AC63: 322314.56 | AD63: 330294.55 | AE63: 338669.35 | AF63: 346968.45 | AG63: 355974.58 | AH63: 365483.02 | AI63: 375258.15 | AJ63: 386314.22 | AK63: 397684.19 | AL63: 409593.39 | AM63: 421965.17 | AN63: 434723.22 | AO63: 447732.94 | AP63: 461272.38 | AQ63: 475192.2 | AR63: 489682.34 | AS63: 504472.8 | AT63: 519716.84 | AU63: 535539.99 | AV63: 551849.23 | AW63: 568650.34 | AX63: 586886.22
B64: Taxes à la production | C64: PIY_2*IY_2 | D64: 70157.971 | E64: 72710.067 | F64: 73838.983 | G64: 76385.248 | H64: 77177.742 | I64: 73793.167 | J64: 76150.993 | K64: 77725.644 | L64: 78078.96 | M64: 78660.372 | N64: 80171.835 | O64: 82000.075 | P64: 83462.603 | Q64: 87053.346 | R64: 90348.384 | S64: 94366.063 | T64: 97076.558 | U64: 100479.77 | V64: 103649.76 | W64: 107579.43 | X64: 111302.56 | Y64: 114726.42 | Z64: 117820.2 | AA64: 121281.55 | AB64: 124988.25 | AC64: 128870.62 | AD64: 132974.5 | AE64: 136801.7 | AF64: 140871.77 | AG64: 145125.7 | AH64: 149576.07 | AI64: 154351.77 | AJ64: 159357.18 | AK64: 164614.38 | AL64: 170129.93 | AM64: 175887.1 | AN64: 181855.83 | AO64: 187975.7 | AP64: 194379.74 | AQ64: 200956.3 | AR64: 207746.06 | AS64: 214699.44 | AT64: 221904.18 | AU64: 229312.05 | AV64: 236958.93 | AW64: 244843.27 | AX64: 253114.86
B65: Impôts sur les bénéfices | C65: PIS_2*IS_2 | F65: 41720 | G65: 39457.604 | H65: 40747.154 | I65: 37985.352 | J65: 35239.253 | K65: 39462.881 | L65: 41536.949 | M65: 40347.046 | N65: 40273.369 | O65: 41738.573 | P65: 42656.482 | Q65: 43783.153 | R65: 45752.284 | S65: 46287.534 | T65: 48729.568 | U65: 49719.348 | V65: 51548.731 | W65: 51967.247 | X65: 53446.766 | Y65: 54726.117 | Z65: 55753.303 | AA65: 56399.605 | AB65: 57811.636 | AC65: 58869.73 | AD65: 61492.031 | AE65: 64472.551 | AF65: 66398.801 | AG65: 68426.982 | AH65: 70587.855 | AI65: 72807.798 | AJ65: 75306.908 | AK65: 77816.611 | AL65: 80375.084 | AM65: 83270.27 | AN65: 86089.487 | AO65: 89095.441 | AP65: 91962.034 | AQ65: 95098.361 | AR65: 98342.428 | AS65: 101781.88 | AT65: 105187.64 | AU65: 108797.76 | AV65: 112443.34 | AW65: 116200.29 | AX65: 119911.23
B66: Cotisations sociales | C66: PCSE_TOT_2*CSE_TOT_2+PCSS_TOT_2*CSS_TOT_2 | D66: 344617.11 | E66: 357153.05 | F66: 369017.92 | G66: 385094.53 | H66: 396077.86 | I66: 389117.47 | J66: 385211.89 | K66: 387603.98 | L66: 391386.7 | M66: 396035.84 | N66: 400161.67 | O66: 405640.99 | P66: 412494.56 | Q66: 425797.97 | R66: 443279.15 | S66: 465026.74 | T66: 480948.52 | U66: 496677.55 | V66: 512965.64 | W66: 532615.3 | X66: 550545.93 | Y66: 566557.38 | Z66: 583140.1 | AA66: 600111.39 | AB66: 617651.78 | AC66: 635679.57 | AD66: 654414.62 | AE66: 674207.77 | AF66: 695016.94 | AG66: 716966.7 | AH66: 740203.85 | AI66: 764978.07 | AJ66: 791279.02 | AK66: 819238.04 | AL66: 848276.75 | AM66: 878539.89 | AN66: 909924.42 | AO66: 942350.63 | AP66: 975838.16 | AQ66: 1010064.1 | AR66: 1045100.7 | AS66: 1080981 | AT66: 1117852.5 | AU66: 1155869.1 | AV66: 1195176.8 | AW66: 1235745.6 | AX66: 1278298.8
B67: Revenus des services publics | C67: PY_20_2*Y_20_2-(PE_20_2*E_20_2+PMAT_20_2*MAT_20_2+PIY_20_2*IY_20_2) | D67: 258421.17 | E67: 267821.61 | F67: 270550.76 | G67: 275827.22 | H67: 282272.32 | I67: 293044.75 | J67: 294355.51 | K67: 296746.96 | L67: 300946.15 | M67: 305663.35 | N67: 309150.81 | O67: 313826.46 | P67: 320131.73 | Q67: 326466.65 | R67: 334572.43 | S67: 345274.99 | T67: 357483.58 | U67: 369738.33 | V67: 382129.66 | W67: 396042.74 | X67: 409876.88 | Y67: 422957.23 | Z67: 435847.61 | AA67: 449026.46 | AB67: 462629.5 | AC67: 476621.12 | AD67: 491077.27 | AE67: 506021.14 | AF67: 521609.55 | AG67: 537875 | AH67: 554928.44 | AI67: 572971.56 | AJ67: 592052.91 | AK67: 612346.45 | AL67: 633718.8 | AM67: 656139.19 | AN67: 679534.79 | AO67: 703953.18 | AP67: 729420.69 | AQ67: 755751.9 | AR67: 782888.58 | AS67: 810772.47 | AT67: 839444 | AU67: 868947.77 | AV67: 899366.47 | AW67: 930731.05 | AX67: 963098.32
B68: moins les cotisations salariales des salariés du public | C68: (-1)*CL_S_20_2*L_S_20_2*PROG_L_20_2 | D68: -225891.81 | E68: -234108.95 | F68: -242473.94 | G68: -250402.08 | H68: -256846.06 | I68: -262566.58 | J68: -263167.14 | K68: -263676.15 | L68: -266631.64 | M68: -271219.5 | N68: -274530.54 | O68: -277636.51 | P68: -281316.62 | Q68: -286630.63 | R68: -294477.82 | S68: -304804.23 | T68: -315357.14 | U68: -325800.82 | V68: -336494.3 | W68: -349298.7 | X68: -361045.38 | Y68: -371489.97 | Z68: -382419.34 | AA68: -393734.59 | AB68: -405428.38 | AC68: -417383.43 | AD68: -429740.74 | AE68: -442689.58 | AF68: -456216.82 | AG68: -470447.92 | AH68: -485554.74 | AI68: -501638.98 | AJ68: -518806.15 | AK68: -537162.07 | AL68: -556274.12 | AM68: -576201.73 | AN68: -596859.65 | AO68: -618353.07 | AP68: -640638.93 | AQ68: -663460.04 | AR68: -686817.27 | AS68: -710717.43 | AT68: -735266.54 | AU68: -760558.02 | AV68: -786689.63 | AW68: -813644.51 | AX68: -841552.82
B69: recettes de l'ETS aux secteurs | C69: REC_VAL_SEC_ETS_2 | D69: 0 | E69: 0 | F69: 0 | G69: 0 | H69: 0 | I69: 0 | J69: 696.51547 | K69: 688.64066 | L69: 651.64154 | M69: 640.32182 | N69: 640.94018 | O69: 646.54145 | P69: 725.47396 | Q69: 825.77768 | R69: 942.08791 | S69: 1115.2353 | T69: 1270.1604 | U69: 1611.9912 | V69: 2052.2536 | W69: 2625.8302 | X69: 3102.7794 | Y69: 3528.2521 | Z69: 3352.4026 | AA69: 3265.8285 | AB69: 3220.6225 | AC69: 3206.193 | AD69: 3214.6726 | AE69: 3297.5287 | AF69: 3405.3179 | AG69: 3521.3924 | AH69: 3645.9166 | AI69: 3776.5226 | AJ69: 3919.473 | AK69: 4068.0417 | AL69: 4224.0147 | AM69: 4389.4571 | AN69: 4561.3454 | AO69: 5105.4455 | AP69: 5711.8091 | AQ69: 6385.668 | AR69: 7136.2977 | AS69: 7968.7507 | AT69: 8721.7232 | AU69: 9565.0968 | AV69: 10480.018 | AW69: 11466.832 | AX69: 12539.253
B70: recettes de l'ETS aux secteurs | C70: REC_VAL_SEC_ETS2_2 | D70: 0 | E70: 0 | F70: 0 | G70: 0 | H70: 0 | I70: 0 | J70: 0 | K70: 0 | L70: 0 | M70: 0 | N70: 0 | O70: 0 | P70: 0 | Q70: 0 | R70: 0 | S70: 0 | T70: 0 | U70: 0 | V70: 0 | W70: 0 | X70: 0 | Y70: 0 | Z70: 0 | AA70: 0 | AB70: 0 | AC70: 0 | AD70: 0 | AE70: 0 | AF70: 0 | AG70: 0 | AH70: 0 | AI70: 0 | AJ70: 0 | AK70: 0 | AL70: 0 | AM70: 0 | AN70: 0 | AO70: 0 | AP70: 0 | AQ70: 0 | AR70: 0 | AS70: 0 | AT70: 0 | AU70: 0 | AV70: 0 | AW70: 0 | AX70: 0
B71: recettes de l'ETS aux ménages | C71: REC_VAL_ETS2_HH_2 | D71: 0 | E71: 0 | F71: 0 | G71: 0 | H71: 0 | I71: 0 | J71: 0 | K71: 0 | L71: 0 | M71: 0 | N71: 0 | O71: 0 | P71: 0 | Q71: 0 | R71: 0 | S71: 0 | T71: 0 | U71: 0 | V71: 0 | W71: 0 | X71: 0 | Y71: 0 | Z71: 0 | AA71: 0 | AB71: 0 | AC71: 0 | AD71: 0 | AE71: 0 | AF71: 0 | AG71: 0 | AH71: 0 | AI71: 0 | AJ71: 0 | AK71: 0 | AL71: 0 | AM71: 0 | AN71: 0 | AO71: 0 | AP71: 0 | AQ71: 0 | AR71: 0 | AS71: 0 | AT71: 0 | AU71: 0 | AV71: 0 | AW71: 0 | AX71: 0
B72: recettes de taxe carbone aux ménages | C72: REC_VAL_TCO_HH_2 | D72: 0 | E72: 0 | F72: 0 | G72: 0 | H72: 0 | I72: 0 | J72: 0 | K72: 0 | L72: 0 | M72: 0 | N72: 882.28486 | O72: 1736.9373 | P72: 2713.0584 | Q72: 3719.5187 | R72: 5332.1552 | S72: 5271.6672 | T72: 5175.6218 | U72: 5019.5414 | V72: 4854.2733 | W72: 4679.7854 | X72: 4603.3607 | Y72: 4525.4827 | Z72: 4429.608 | AA72: 4341.196 | AB72: 4256.9397 | AC72: 4174.6278 | AD72: 4092.9683 | AE72: 4012.7042 | AF72: 3928.7012 | AG72: 3843.1537 | AH72: 3757.501 | AI72: 3669.4228 | AJ72: 3588.3585 | AK72: 3509.5732 | AL72: 3433.0007 | AM72: 3358.1491 | AN72: 3285.1668 | AO72: 3208.6387 | AP72: 3132.8811 | AQ72: 3057.8115 | AR72: 2983.5163 | AS72: 2910.0351 | AT72: 2835.9773 | AU72: 2762.7545 | AV72: 2689.652 | AW72: 2617.7494 | AX72: 2547.2809
B73: recettes de taxe carbone aux secteurs | C73: REC_VAL_SEC_TCO_2 | D73: 0 | E73: 0 | F73: 0 | G73: 0 | H73: 0 | I73: 0 | J73: 0 | K73: 0 | L73: 0 | M73: 0 | N73: 804.87323 | O73: 1636.4205 | P73: 2517.5888 | Q73: 3417.9982 | R73: 4753.4041 | S73: 4618.4269 | T73: 4516.8533 | U73: 4481.9143 | V73: 4453.284 | W73: 4449.0536 | X73: 4386.6833 | Y73: 4306.4511 | Z73: 4203.6019 | AA73: 4130.5998 | AB73: 4075.8064 | AC73: 4032.7039 | AD73: 3999.554 | AE73: 3981.6347 | AF73: 3971.1692 | AG73: 3963.1552 | AH73: 3956.1216 | AI73: 3951.3817 | AJ73: 3960.1532 | AK73: 3970.5747 | AL73: 3982.3031 | AM73: 3995.0796 | AN73: 4008.2906 | AO73: 4032.8874 | AP73: 4060.1498 | AQ73: 4087.2607 | AR73: 4114.7768 | AS73: 4141.9416 | AT73: 4179.0798 | AU73: 4216.5172 | AV73: 4254.1054 | AW73: 4292.5363 | AX73: 4332.8468
C74: DEP_VAL_1 | E74: 912128.34 | F74: 937425.07 | G74: 961862 | H74: 986659.9 | I74: 1008523.5 | J74: 1032902.3 | K74: 1047851.8 | L74: 1070612.1 | M74: 1095908.2 | N74: 1121771.6 | O74: 1148883 | P74: 1175814.4 | Q74: 1206902.8 | R74: 1245996.2 | S74: 1296419.4 | T74: 1350708.4 | U74: 1402975.7 | V74: 1451638.6 | W74: 1509929.7 | X74: 1562894.7 | Y74: 1614378 | Z74: 1666703.6 | AA74: 1720982.7 | AB74: 1777230.8 | AC74: 1834921.4 | AD74: 1894585.3 | AE74: 1956462 | AF74: 2020712.3 | AG74: 2087899.9 | AH74: 2158999.1 | AI74: 2234346.9 | AJ74: 2314702.1 | AK74: 2400777.3 | AL74: 2490977.1 | AM74: 2585434.4 | AN74: 2683857.6 | AO74: 2787150.9 | AP74: 2895092.8 | AQ74: 3006721 | AR74: 3121990.2 | AS74: 3240852.9 | AT74: 3363392.3 | AU74: 3490293 | AV74: 3621928 | AW74: 3758278.4 | AX74: 3899770.5
C75: CL_S_20_1 | D75: 39.375695 | E75: 40.163209 | F75: 40.965571 | G75: 41.668772 | H75: 42.351366 | I75: 42.869102 | J75: 42.448832 | K75: 41.869215 | L75: 41.56026 | M75: 41.492424 | N75: 41.418085 | O75: 41.39552 | P75: 41.429784 | Q75: 41.566799 | R75: 42.090112 | S75: 43.023861 | T75: 43.89101 | U75: 44.769849 | V75: 45.663181 | W75: 46.58119 | X75: 47.518729 | Y75: 48.466807 | Z75: 49.435265 | AA75: 50.406458 | AB75: 51.363369 | AC75: 52.328472 | AD75: 53.311581 | AE75: 54.318673 | AF75: 55.353833 | AG75: 56.426116 | AH75: 57.542234 | AI75: 58.688799 | AJ75: 59.870694 | AK75: 61.085951 | AL75: 62.314691 | AM75: 63.563252 | AN75: 64.835653 | AO75: 66.124674 | AP75: 67.42712 | AQ75: 68.746892 | AR75: 70.08628 | AS75: 71.447888 | AT75: 72.834136 | AU75: 74.245494 | AV75: 75.684431 | AW75: 77.151176 | AX75: 78.660524
C76: L_S_20_1 | D76: 5875.3439 | E76: 5898.8878 | F76: 5918.9688 | G76: 5938.0893 | H76: 5921.6735 | I76: 5909.5378 | J76: 5910.7674 | K76: 5932.988 | L76: 5972.4201 | M76: 6012.9628 | N76: 6024.9931 | O76: 6024.1893 | P76: 6026.6725 | Q76: 6047.7019 | R76: 6063.2623 | S76: 6066.8736 | T76: 6079.9488 | U76: 6090.9946 | V76: 6100.7335 | W76: 6113.4238 | X76: 6127.0749 | Y76: 6140.6731 | Z76: 6152.9189 | AA76: 6164.554 | AB76: 6177.1064 | AC76: 6188.6466 | AD76: 6198.5979 | AE76: 6207.687 | AF76: 6216.2185 | AG76: 6223.86 | AH76: 6230.2554 | AI76: 6237.0773 | AJ76: 6243.0474 | AK76: 6247.6851 | AL76: 6252.566 | AM76: 6257.0209 | AN76: 6260.4684 | AO76: 6263.6275 | AP76: 6266.2168 | AQ76: 6267.9315 | AR76: 6269.2332 | AS76: 6269.7754 | AT76: 6269.6906 | AU76: 6269.347 | AV76: 6268.5243 | AW76: 6267.2739 | AX76: 6265.1661
C77: PROG_L_20_1 | D77: 0.97642519 | E77: 0.98814229 | F77: 1 | G77: 1.012 | H77: 1.024144 | I77: 1.0364337 | J77: 1.0488709 | K77: 1.0614574 | L77: 1.0741949 | M77: 1.0870852 | N77: 1.1001302 | O77: 1.1133318 | P77: 1.1266918 | Q77: 1.1402121 | R77: 1.1538946 | S77: 1.1677414 | T77: 1.1817543 | U77: 1.1947536 | V77: 1.2078958 | W77: 1.2265969 | X77: 1.2401047 | Y77: 1.248218 | Z77: 1.2570082 | AA77: 1.2663834 | AB77: 1.276411 | AC77: 1.2865841 | AD77: 1.2972562 | AE77: 1.3086672 | AF77: 1.3206484 | AG77: 1.3334904 | AH77: 1.3475322 | AI77: 1.3629207 | AJ77: 1.3799792 | AK77: 1.3990132 | AL77: 1.4188715 | AM77: 1.439635 | AN77: 1.4610707 | AO77: 1.4833825 | AP77: 1.5065307 | AQ77: 1.5298493 | AR77: 1.5531631 | AS77: 1.5765024 | AT77: 1.5999962 | AU77: 1.6237196 | AV77: 1.6478519 | AW77: 1.6722975 | AX77: 1.6970864
C78: R_G_1(-1) | E78: 0.040034451 | F78: 0.040034451 | G78: 0.038398621 | H78: 0.036515158 | I78: 0.036233179 | J78: 0.034419222 | K78: 0.033746023 | L78: 0.033148577 | M78: 0.032702069 | N78: 0.032060826 | O78: 0.031831814 | P78: 0.031290097 | Q78: 0.03080831 | R78: 0.031313188 | S78: 0.032522624 | T78: 0.033311404 | U78: 0.034145993 | V78: 0.034878736 | W78: 0.035579425 | X78: 0.036224814 | Y78: 0.036775105 | Z78: 0.037236822 | AA78: 0.037591326 | AB78: 0.037866137 | AC78: 0.038084136 | AD78: 0.038256598 | AE78: 0.038393562 | AF78: 0.038510681 | AG78: 0.038583162 | AH78: 0.038662855 | AI78: 0.038749884 | AJ78: 0.038808074 | AK78: 0.038912098 | AL78: 0.039001365 | AM78: 0.039079435 | AN78: 0.039146079 | AO78: 0.039203201 | AP78: 0.039262779 | AQ78: 0.039312632 | AR78: 0.039354654 | AS78: 0.03938972 | AT78: 0.039417316 | AU78: 0.039442062 | AV78: 0.039464596 | AW78: 0.039483928 | AX78: 0.039497063
C79: DEBT_G_VAL_1(-1) | E79: 1040817.6 | F79: 1078678.8 | G79: 1124725.7 | H79: 1166240.7 | I79: 1205835.3 | J79: 1275553.8 | K79: 1363042.1 | L79: 1440080.9 | M79: 1521199.6 | N79: 1614138.7 | O79: 1715276.6 | P79: 1822815.9 | Q79: 1934817.9 | R79: 2041238.9 | S79: 2143518.5 | T79: 2251863.6 | U79: 2375471.3 | V79: 2514614 | W79: 2662630.5 | X79: 2822757.3 | Y79: 2991571.6 | Z79: 3171972.3 | AA79: 3366719.3 | AB79: 3577587.6 | AC79: 3803284.3 | AD79: 4043916.4 | AE79: 4298375.3 | AF79: 4567866.9 | AG79: 4853038.4 | AH79: 5153710.4 | AI79: 5470934.6 | AJ79: 5806076.6 | AK79: 6159585.2 | AL79: 6533994 | AM79: 6930611.8 | AN79: 7350319.3 | AO79: 7794473.4 | AP79: 8264853 | AQ79: 8763559.9 | AR79: 9291669.9 | AS79: 9850171.8 | AT79: 10440248 | AU79: 11063366 | AV79: 11720831 | AW79: 12414446 | AX79: 13146035
C80: PRESOC_VAL_1 | D80: 334613.16 | E80: 346785.19 | F80: 355569.94 | G80: 362474.15 | H80: 375166.89 | I80: 389779.76 | J80: 402784.48 | K80: 413040.95 | L80: 424174.08 | M80: 435846.94 | N80: 448624.69 | O80: 460339.77 | P80: 470567.91 | Q80: 482243.94 | R80: 497227.39 | S80: 511861.13 | T80: 538863.16 | U80: 556795.2 | V80: 575163.65 | W80: 596984.81 | X80: 617015.79 | Y80: 634827.7 | Z80: 653737.58 | AA80: 673445 | AB80: 693811.23 | AC80: 714508.93 | AD80: 735794.43 | AE80: 757932.65 | AF80: 780689.81 | AG80: 804428.23 | AH80: 829568.36 | AI80: 856185.29 | AJ80: 884744.01 | AK80: 915443.48 | AL80: 947558.99 | AM80: 981117.9 | AN80: 1015976 | AO80: 1052363.7 | AP80: 1090311.4 | AQ80: 1129341.4 | AR80: 1169398.3 | AS80: 1210442.2 | AT80: 1252620.9 | AU80: 1296081 | AV80: 1340968.7 | AW80: 1387225.8 | AX80: 1434916.2
C81: SUB_REHAB_VAL_1-CEE | D81: 0 | E81: 0 | F81: 0 | G81: 981.71741 | H81: 1275.7646 | I81: 1256.1846 | J81: 962.83367 | K81: 907.83579 | L81: 730.04444 | M81: 1046.0339 | N81: 1478.0556 | O81: 2067.9391 | P81: 1560.2962 | Q81: 1611.5249 | R81: 1227.2902 | S81: 1845.6156 | T81: 1829.233 | U81: 3502.7992 | V81: 2632.5168 | W81: 2779.9116 | X81: 1.497483e-09 | Y81: -3.3847255e-07 | Z81: 0 | AA81: 0 | AB81: 0 | AC81: 0 | AD81: 0 | AE81: 0 | AF81: 0 | AG81: 0 | AH81: 0 | AI81: 0 | AJ81: 0 | AK81: 0 | AL81: 0 | AM81: 0 | AN81: 0 | AO81: 0 | AP81: 0 | AQ81: 0 | AR81: 0 | AS81: 0 | AT81: 0 | AU81: 0 | AV81: 0 | AW81: 0 | AX81: 0
C82: SUB_AUTO_VAL_1 | D82: 0 | E82: 0 | F82: 0 | G82: 0 | H82: -146.15689 | I82: -138.40401 | J82: -122.17213 | K82: -60.537774 | L82: 30.851943 | M82: 248.66455 | N82: 291.27213 | O82: -1159.0664 | P82: -1100.1117 | Q82: -1744.0667 | R82: -2367.1233 | S82: -1949.7674 | T82: -3557.2983 | U82: -1245.6668 | V82: -1567.8608 | W82: -1318.5097 | X82: -1088.306 | Y82: -832.82382 | Z82: -651.75153 | AA82: -384.02915 | AB82: -86.374331 | AC82: 220.77697 | AD82: 523.75277 | AE82: 816.18698 | AF82: 1044.671 | AG82: 1266.8012 | AH82: 1479.0389 | AI82: 1600.2116 | AJ82: 1826.6695 | AK82: 2022.7327 | AL82: 2195.0392 | AM82: 2351.0038 | AN82: 2491.7308 | AO82: 2609.1341 | AP82: 2728.5225 | AQ82: 2846.2287 | AR82: 2959.1383 | AS82: 3066.5467 | AT82: 3154.3593 | AU82: 3244.5288 | AV82: 3332.8367 | AW82: 3416.9084 | AX82: 3500.0569
C83: PE_20_1 | D83: 0.96116878 | E83: 0.98039216 | F83: 0.97579872 | G83: 0.96922967 | H83: 1.0167957 | I83: 0.96537062 | J83: 0.98679907 | K83: 1.0369927 | L83: 1.083025 | M83: 1.0835507 | N83: 1.0703968 | O83: 1.033906 | P83: 1.0142658 | Q83: 1.060122 | R83: 1.1460074 | S83: 1.182574 | T83: 1.2089175 | U83: 1.2343882 | V83: 1.2613496 | W83: 1.2870538 | X83: 1.3164113 | Y83: 1.3399912 | Z83: 1.3625281 | AA83: 1.3858347 | AB83: 1.4095925 | AC83: 1.4339928 | AD83: 1.4586878 | AE83: 1.4833587 | AF83: 1.5084737 | AG83: 1.532813 | AH83: 1.5586175 | AI83: 1.583862 | AJ83: 1.610119 | AK83: 1.6370985 | AL83: 1.6648158 | AM83: 1.6931433 | AN83: 1.7222592 | AO83: 1.7523842 | AP83: 1.7831934 | AQ83: 1.8149438 | AR83: 1.8474501 | AS83: 1.8807101 | AT83: 1.9152435 | AU83: 1.9507096 | AV83: 1.9877312 | AW83: 2.0244724 | AX83: 2.0618727
C84: E_20_1 | D84: 6240.0204 | E84: 6340.2059 | F84: 6469.6179 | G84: 6611.657 | H84: 6618.2922 | I84: 6789.5942 | J84: 6812.2373 | K84: 6793.1647 | L84: 6788.7558 | M84: 6846.0327 | N84: 6893.513 | O84: 6994.366 | P84: 6735.5194 | Q84: 6476.6728 | R84: 6217.8262 | S84: 5958.9796 | T84: 5700.133 | U84: 5700.133 | V84: 5700.133 | W84: 5700.133 | X84: 5656.8979 | Y84: 5613.6628 | Z84: 5570.4278 | AA84: 5527.1927 | AB84: 5483.9576 | AC84: 5440.7226 | AD84: 5397.4875 | AE84: 5354.2525 | AF84: 5311.0174 | AG84: 5267.7823 | AH84: 5224.5473 | AI84: 5181.3122 | AJ84: 5138.0771 | AK84: 5094.8421 | AL84: 5051.607 | AM84: 5008.3719 | AN84: 4965.1369 | AO84: 4921.9018 | AP84: 4878.6667 | AQ84: 4835.4317 | AR84: 4792.1966 | AS84: 4748.9615 | AT84: 4705.7265 | AU84: 4662.4914 | AV84: 4619.2564 | AW84: 4576.0213 | AX84: 4532.7862
C85: PMAT_20_1 | D85: 0.96116878 | E85: 0.98039216 | F85: 0.98715589 | G85: 0.98997305 | H85: 0.99954962 | I85: 1.0094079 | J85: 1.0168193 | K85: 1.0208958 | L85: 1.026659 | M85: 1.0357766 | N85: 1.0466175 | O85: 1.0611779 | P85: 1.0715186 | Q85: 1.082961 | R85: 1.0992965 | S85: 1.1184687 | T85: 1.1410035 | U85: 1.1638849 | V85: 1.1873095 | W85: 1.211297 | X85: 1.2357172 | Y85: 1.2604904 | Z85: 1.2856919 | AA85: 1.3112988 | AB85: 1.3372978 | AC85: 1.3636945 | AD85: 1.3905236 | AE85: 1.4178159 | AF85: 1.445693 | AG85: 1.4741753 | AH85: 1.5033382 | AI85: 1.5332181 | AJ85: 1.5637618 | AK85: 1.5949871 | AL85: 1.6268506 | AM85: 1.6593477 | AN85: 1.6924855 | AO85: 1.7261907 | AP85: 1.760483 | AQ85: 1.7953803 | AR85: 1.8309005 | AS85: 1.8670659 | AT85: 1.9039011 | AU85: 1.9414314 | AV85: 1.979689 | AW85: 2.0186749 | AX85: 2.058565
C86: MAT_20_1 | D86: 82435.687 | E86: 83759.219 | F86: 85104 | G86: 87702.851 | H86: 87347.402 | I86: 81212.652 | J86: 83689.452 | K86: 84881.789 | L86: 84374.318 | M86: 84545.888 | N86: 85552.175 | O86: 87518.849 | P86: 88546.005 | Q86: 91888.63 | R86: 93942.282 | S86: 96689.981 | T86: 98040.456 | U86: 99373.416 | V86: 100652.02 | W86: 102227.7 | X86: 103678.59 | Y86: 104839.67 | Z86: 105867.11 | AA86: 106887.5 | AB86: 107934.54 | AC86: 108997.96 | AD86: 110092.29 | AE86: 111177.47 | AF86: 112316.64 | AG86: 113509.01 | AH86: 114770.97 | AI86: 116137.2 | AJ86: 117605.69 | AK86: 119200.26 | AL86: 120888.34 | AM86: 122656.29 | AN86: 124483.77 | AO86: 126372.72 | AP86: 128323.42 | AQ86: 130299.41 | AR86: 132287.31 | AS86: 134274.5 | AT86: 136265.47 | AU86: 138263.69 | AV86: 140278.88 | AW86: 142310.65 | AX86: 144363.43
C87: PIY_20_1 | D87: 0.96116878 | E87: 0.98039216 | F87: 0.97820825 | G87: 0.98496723 | H87: 0.99826356 | I87: 0.99968759 | J87: 0.99995771 | K87: 0.99685741 | L87: 0.99217621 | M87: 0.99125018 | N87: 0.99556701 | O87: 1.0040731 | P87: 1.0108111 | Q87: 1.0213068 | R87: 1.0377083 | S87: 1.0617254 | T87: 1.0831781 | U87: 1.1050455 | V87: 1.1273357 | W87: 1.150068 | X87: 1.1732576 | Y87: 1.1968888 | Z87: 1.2209781 | AA87: 1.2455055 | AB87: 1.2704249 | AC87: 1.2957347 | AD87: 1.3214492 | AE87: 1.347592 | AF87: 1.374193 | AG87: 1.4012931 | AH87: 1.4289444 | AI87: 1.4571697 | AJ87: 1.4859996 | AK87: 1.5154588 | AL87: 1.5455362 | AM87: 1.5762338 | AN87: 1.6075614 | AO87: 1.6395122 | AP87: 1.672077 | AQ87: 1.7052553 | AR87: 1.739051 | AS87: 1.773472 | AT87: 1.8085299 | AU87: 1.8442369 | AV87: 1.8806093 | AW87: 1.9176609 | AX87: 1.9554352
C88: IY_20_1 | D88: 7392.7097 | E88: 7511.402 | F88: 7627.9475 | G88: 7747.4083 | H88: 7794.4038 | I88: 7892.2204 | J88: 7985.1839 | K88: 8098.6283 | L88: 8230.1034 | M88: 8357.3119 | N88: 8433.5993 | O88: 8524.0346 | P88: 8629.038 | Q88: 8763.1097 | R88: 8866.1804 | S88: 8967.4405 | T88: 9090.9174 | U88: 9214.0422 | V88: 9332.4877 | W88: 9478.5167 | X88: 9612.3213 | Y88: 9719.0074 | Z88: 9813.0322 | AA88: 9906.1034 | AB88: 10001.313 | AC88: 10097.675 | AD88: 10196.496 | AE88: 10297.308 | AF88: 10403.126 | AG88: 10513.877 | AH88: 10631.078 | AI88: 10757.945 | AJ88: 10894.29 | AK88: 11042.321 | AL88: 11199.022 | AM88: 11363.131 | AN88: 11532.763 | AO88: 11708.098 | AP88: 11889.163 | AQ88: 12072.58 | AR88: 12257.11 | AS88: 12441.583 | AT88: 12626.415 | AU88: 12811.927 | AV88: 12999.021 | AW88: 13187.661 | AX88: 13378.256
C89: PIA_20_1 | D89: 0.96116878 | E89: 0.98039216 | F89: 0.99126324 | G89: 0.99095385 | H89: 0.99273778 | I89: 1.00472 | J89: 1.0226154 | K89: 1.0358484 | L89: 1.0466218 | M89: 1.057368 | N89: 1.0755293 | O89: 1.1059944 | P89: 1.1267068 | Q89: 1.1398264 | R89: 1.1500563 | S89: 1.1599531 | T89: 1.1833178 | U89: 1.2071106 | V89: 1.231469 | W89: 1.25631 | X89: 1.2815425 | Y89: 1.3072874 | Z89: 1.3334931 | AA89: 1.3602163 | AB89: 1.3874232 | AC89: 1.4150789 | AD89: 1.4431961 | AE89: 1.4719005 | AF89: 1.501115 | AG89: 1.5308476 | AH89: 1.5611733 | AI89: 1.5921635 | AJ89: 1.623773 | AK89: 1.6560451 | AL89: 1.6889908 | AM89: 1.722603 | AN89: 1.7568887 | AO89: 1.7917245 | AP89: 1.8272831 | AQ89: 1.8635639 | AR89: 1.9005353 | AS89: 1.9381919 | AT89: 1.9765576 | AU89: 2.0156534 | AV89: 2.0554932 | AW89: 2.0960857 | AX89: 2.1377605
C90: IA_20_1 | D90: 58700.943 | E90: 59643.406 | F90: 60601 | G90: 61569.982 | H90: 60512.82 | I90: 62405.892 | J90: 62046.794 | K90: 58826.594 | L90: 60454.487 | M90: 59410.934 | N90: 56766.535 | O90: 54970.176 | P90: 55748.464 | Q90: 54942.252 | R90: 56537.158 | S90: 61577.144 | T90: 62443.353 | U90: 63232.6 | V90: 64025.374 | W90: 65158.28 | X90: 66027.898 | Y90: 66606.948 | Z90: 67194.448 | AA90: 67801.895 | AB90: 68441.32 | AC90: 69083.893 | AD90: 69748.871 | AE90: 70457.652 | AF90: 71208.302 | AG90: 72003.833 | AH90: 72859.624 | AI90: 73801.187 | AJ90: 74815.058 | AK90: 75924.225 | AL90: 77072.274 | AM90: 78262.073 | AN90: 79479.257 | AO90: 80735.843 | AP90: 82023.215 | AQ90: 83306.123 | AR90: 84583.582 | AS90: 85853.104 | AT90: 87123.663 | AU90: 88402.721 | AV90: 89697.515 | AW90: 91003.143 | AX90: 92328.46
C91: PG_1 | D91: 0.96116878 | E91: 0.98039216 | F91: 0.98015895 | G91: 0.98578193 | H91: 0.99781249 | I91: 1.000915 | J91: 1.0025584 | K91: 1.000713 | L91: 0.99826621 | M91: 0.99956909 | N91: 1.0051401 | O91: 1.0146342 | P91: 1.0218053 | Q91: 1.0324124 | R91: 1.0484613 | S91: 1.0711914 | T91: 1.0928093 | U91: 1.1148277 | V91: 1.1372972 | W91: 1.1602348 | X91: 1.1836233 | Y91: 1.2074313 | Z91: 1.231676 | AA91: 1.2563471 | AB91: 1.2814005 | AC91: 1.3068368 | AD91: 1.3326784 | AE91: 1.3589669 | AF91: 1.3857517 | AG91: 1.4130659 | AH91: 1.4409659 | AI91: 1.4694806 | AJ91: 1.4986131 | AK91: 1.5283877 | AL91: 1.5587837 | AM91: 1.5897978 | AN91: 1.6214394 | AO91: 1.6536864 | AP91: 1.6865321 | AQ91: 1.7199826 | AR91: 1.754047 | AS91: 1.7887379 | AT91: 1.8240702 | AU91: 1.8600592 | AV91: 1.8967253 | AW91: 1.9340806 | AX91: 1.9721979
... C105: CL_S_20_1*L_S_20_1*PROG_L_20_1 | D105: 225891.81 | E105: 234108.95 | F105: 242473.94 | G105: 250402.08 | H105: 256846.06 | I105: 262566.58 | J105: 263167.14 | K105: 263676.15 | L105: 266631.64 | M105: 271219.5 | N105: 274530.54 | O105: 277636.51 | P105: 281316.62 | Q105: 286630.63 | R105: 294477.82 | S105: 304804.23 | T105: 315357.14 | U105: 325800.82 | V105: 336494.3 | W105: 349298.7 | X105: 361057.5 | Y105: 371493.17 | Z105: 382345.68 | AA105: 393507.52 | AB105: 404975.84 | AC105: 416650.51 | AD105: 428687.48 | AE105: 441273.82 | AF105: 454423.9 | AG105: 468306.16 | AH105: 483094.09 | AI105: 498892.45 | AJ105: 515802.52 | AK105: 533927.48 | AL105: 552830.23 | AM105: 572566.72 | AN105: 593050.89 | AO105: 614387.83 | AP105: 636528.74 | AQ105: 659213.31 | AR105: 682440.05 | AS105: 706213.51 | AT105: 730634.24 | AU105: 755794.01 | AV105: 781789.86 | AW105: 808601.89 | AX105: 836360.22
C106: R_G_1(-1)*DEBT_G_VAL_1(-1) | E106: 41668.561 | F106: 43184.314 | G106: 43187.915 | H106: 42585.465 | I106: 43691.245 | J106: 43903.569 | K106: 45997.25 | L106: 47736.632 | M106: 49746.374 | N106: 51750.62 | O106: 54600.366 | P106: 57036.086 | Q106: 59608.47 | R106: 63917.696 | S106: 69712.845 | T106: 75012.737 | U106: 81112.827 | V106: 87706.558 | W106: 94734.86 | X106: 102253.86 | Y106: 110015.36 | Z106: 118114.17 | AA106: 126559.44 | AB106: 135469.42 | AC106: 144844.8 | AD106: 154706.49 | AE106: 165029.94 | AF106: 175911.67 | AG106: 187245.57 | AH106: 199257.16 | AI106: 211998.08 | AJ106: 225322.65 | AK106: 239682.38 | AL106: 254834.68 | AM106: 270844.39 | AN106: 287736.18 | AO106: 305568.31 | AP106: 324501.1 | AQ106: 344518.61 | AR106: 365670.45 | AS106: 387995.51 | AT106: 411526.55 | AU106: 436361.98 | AV106: 462557.85 | AW106: 490171.08 | AX106: 519229.76
C107: PE_20_1*E_20_1 | D107: 5997.7128 | E107: 6215.8882 | F107: 6313.0449 | G107: 6408.2141 | H107: 6729.4513 | I107: 6554.4748 | J107: 6722.3094 | K107: 7044.4625 | L107: 7352.392 | M107: 7418.0233 | N107: 7378.7942 | O107: 7231.5171 | P107: 6831.6071 | Q107: 6866.0636 | R107: 7125.6747 | S107: 7046.934 | T107: 6890.9903 | U107: 7036.1768 | V107: 7189.8606 | W107: 7336.3779 | X107: 7446.8042 | Y107: 7522.2589 | Z107: 7589.8646 | AA107: 7659.7754 | AB107: 7730.1456 | AC107: 7801.9572 | AD107: 7873.2494 | AE107: 7942.2767 | AF107: 8011.5302 | AG107: 8074.5251 | AH107: 8143.0708 | AI107: 8206.4834 | AJ107: 8272.9158 | AK107: 8340.7582 | AL107: 8409.995 | AM107: 8479.8915 | AN107: 8551.2528 | AO107: 8625.0632 | AP107: 8699.6065 | AQ107: 8776.0369 | AR107: 8853.3439 | AS107: 8931.4201 | AT107: 9012.6121 | AU107: 9095.167 | AV107: 9181.8398 | AW107: 9264.0289 | AX107: 9346.0282
C108: PMAT_20_1*MAT_20_1 | D108: 79234.609 | E108: 82116.881 | F108: 84010.915 | G108: 86823.459 | H108: 87308.063 | I108: 81976.69 | J108: 85097.05 | K108: 86655.463 | L108: 86623.655 | M108: 87570.65 | N108: 89540.406 | O108: 92873.071 | P108: 94878.687 | Q108: 99511.806 | R108: 103270.42 | S108: 108144.72 | T108: 111864.5 | U108: 115659.22 | V108: 119505.11 | W108: 123828.11 | X108: 128117.41 | Y108: 132149.39 | Z108: 136112.48 | AA108: 140161.46 | AB108: 144340.62 | AC108: 148639.92 | AD108: 153085.93 | AE108: 157629.17 | AF108: 162375.38 | AG108: 167332.19 | AH108: 172539.58 | AI108: 178063.66 | AJ108: 183907.28 | AK108: 190122.88 | AL108: 196667.26 | AM108: 203529.43 | AN108: 210686.97 | AO108: 218143.41 | AP108: 225911.21 | AQ108: 233937 | AR108: 242204.91 | AS108: 250699.34 | AT108: 259435.99 | AU108: 268429.47 | AV108: 277708.56 | AW108: 287278.94 | AX108: 297181.5
C109: PIY_20_1*IY_20_1 | D109: 7105.6417 | E109: 7364.1196 | F109: 7461.7212 | G109: 7630.9433 | H109: 7780.8693 | I109: 7889.7548 | J109: 7984.8462 | K109: 8073.1776 | L109: 8165.7128 | M109: 8284.1869 | N109: 8396.2133 | O109: 8558.7543 | P109: 8722.3275 | Q109: 8949.8236 | R109: 9200.5088 | S109: 9520.9596 | T109: 9847.0824 | U109: 10181.936 | V109: 10520.846 | W109: 10900.939 | X109: 11277.729 | Y109: 11632.571 | Z109: 11981.497 | AA109: 12338.106 | AB109: 12705.916 | AC109: 13083.907 | AD109: 13474.151 | AE109: 13876.57 | AF109: 14295.903 | AG109: 14733.023 | AH109: 15191.22 | AI109: 15676.152 | AJ109: 16188.91 | AK109: 16734.184 | AL109: 17308.494 | AM109: 17910.952 | AN109: 18539.625 | AO109: 19195.57 | AP109: 19879.596 | AQ109: 20586.832 | AR109: 21315.739 | AS109: 22064.798 | AT109: 22835.249 | AU109: 23628.229 | AV109: 24446.08 | AW109: 25289.462 | AX109: 26160.313
C110: PIA_20_1*IA_20_1 | D110: 56421.514 | E110: 58473.927 | F110: 60071.544 | G110: 61013.011 | H110: 60073.363 | I110: 62700.448 | J110: 63450.005 | K110: 60935.431 | L110: 63272.986 | M110: 62819.218 | N110: 61054.072 | O110: 60796.705 | P110: 62812.171 | Q110: 62624.632 | R110: 65020.912 | S110: 71426.599 | T110: 73890.333 | U110: 76328.741 | V110: 78845.266 | W110: 81858.997 | X110: 84617.555 | Y110: 87074.422 | Z110: 89603.334 | AA110: 92225.244 | AB110: 94957.072 | AC110: 97759.157 | AD110: 100661.3 | AE110: 103706.65 | AF110: 106891.85 | AG110: 110226.9 | AH110: 113746.5 | AI110: 117503.55 | AJ110: 121482.67 | AK110: 125733.94 | AL110: 130174.36 | AM110: 134814.48 | AN110: 139636.21 | AO110: 144656.39 | AP110: 149879.63 | AQ110: 155246.28 | AR110: 160754.08 | AS110: 166399.79 | AT110: 172204.94 | AU110: 178189.24 | AV110: 184372.63 | AW110: 190750.39 | AX110: 197376.14
C111: PG_1*G_1-PG_20_1*G_20_1 | D111: 107619 | E111: 111533.8 | F111: 113942.67 | G111: 117442.67 | H111: 123159.05 | I111: 127288.16 | J111: 132353 | K111: 134411.74 | L111: 138386.77 | M111: 143777.02 | N111: 148459.89 | O111: 153311.54 | P111: 158002.3 | Q111: 162015.26 | R111: 164253.74 | S111: 169990.65 | T111: 175872.75 | U111: 181812.26 | V111: 187877.36 | W111: 194596.61 | X111: 201343.37 | Y111: 207721.1 | Z111: 214027.09 | AA111: 220408.29 | AB111: 226947.75 | AC111: 233645.1 | AD111: 240538.92 | AE111: 247695.01 | AF111: 255140.26 | AG111: 262913.14 | AH111: 271084.11 | AI111: 279726.78 | AJ111: 288892.31 | AK111: 298654.92 | AL111: 308942.59 | AM111: 319733.36 | AN111: 330995.35 | AO111: 342738.18 | AP111: 354964.91 | AQ111: 367608.05 | AR111: 380632.29 | AS111: 394016.81 | AT111: 407774.1 | AU111: 421934.41 | AV111: 436539.05 | AW111: 451599.39 | AX111: 467162.18
C112: 0-(PSUB_1*SUB_1-PSUB_01_1*SUB_01_1) | D112: 8435.1565 | E112: 8741.9973 | F112: 9052.0676 | G112: 9514.5739 | H112: 9579.7848 | I112: 9185.7675 | J112: 9668.5068 | K112: 9958.4654 | L112: 10138.964 | M112: 10380.176 | N112: 10657.159 | O112: 10910.06 | P112: 11189.514 | Q112: 11835.116 | R112: 12147.105 | S112: 12663.046 | T112: 12921.232 | U112: 13199.942 | V112: 13543.215 | W112: 13963.058 | X112: 14418.093 | Y112: 14859.872 | Z112: 15285.356 | AA112: 15712.974 | AB112: 16159 | AC112: 16613.691 | AD112: 17083.717 | AE112: 17529.075 | AF112: 17968.217 | AG112: 18436.308 | AH112: 18926.688 | AI112: 19417.465 | AJ112: 19972.814 | AK112: 20543.634 | AL112: 21133.195 | AM112: 21743.865 | AN112: 22372.435 | AO112: 23015.883 | AP112: 23685.677 | AQ112: 24374.318 | AR112: 25083.314 | AS112: 25809.649 | AT112: 26565.526 | AU112: 27343.676 | AV112: 28145.897 | AW112: 28970.224 | AX112: 29826.427
C113: 0-(PSY_1*SY_1-PSY_01_1*SY_01_1) | D113: 14588.352 | E113: 15119.024 | F113: 15344.916 | G113: 15983.264 | H113: 16301.289 | I113: 15772.841 | J113: 16234.242 | K113: 16522.807 | L113: 16716.689 | M113: 16911.088 | N113: 17281.824 | O113: 17695.966 | P113: 18040.865 | Q113: 18786.288 | R113: 19467.161 | S113: 20347.074 | T113: 20953.956 | U113: 21678.036 | V113: 22367.955 | W113: 23211.139 | X113: 23986.274 | Y113: 24694.152 | Z113: 25348.433 | AA113: 26064.881 | AB113: 26824.271 | AC113: 27614.382 | AD113: 28442.663 | AE113: 29254.24 | AF113: 30113.901 | AG113: 31016.293 | AH113: 31962.766 | AI113: 32973.91 | AJ113: 34043.808 | AK113: 35169.082 | AL113: 36349.705 | AM113: 37583.41 | AN113: 38864.022 | AO113: 40182.702 | AP113: 41562.588 | AQ113: 42981.666 | AR113: 44445.954 | AS113: 45946.449 | AT113: 47496.024 | AU113: 49089.058 | AV113: 50733.476 | AW113: 52430.076 | AX113: 54203.878
C114: REC_VAL_1 | F114: 891378.22 | G114: 920346.92 | H114: 947065.38 | I114: 938804.99 | J114: 945413.99 | K114: 970813.09 | L114: 989493.32 | M114: 1002969.1 | N114: 1020633.7 | O114: 1041343.8 | P114: 1063812.4 | Q114: 1100481.8 | R114: 1143716.6 | S114: 1188074.3 | T114: 1227100.7 | U114: 1263833 | V114: 1303622.2 | W114: 1349802.8 | X114: 1394080.5 | Y114: 1433977.3 | Z114: 1471956.5 | AA114: 1510114.4 | AB114: 1551534.1 | AC114: 1594289.2 | AD114: 1640126.4 | AE114: 1686970.3 | AF114: 1735540.8 | AG114: 1787227.8 | AH114: 1841775 | AI114: 1899204.8 | AJ114: 1961193.5 | AK114: 2026368.5 | AL114: 2094359.3 | AM114: 2165726.9 | AN114: 2239703.5 | AO114: 2316771.3 | AP114: 2396386 | AQ114: 2478610.9 | AR114: 2563488.4 | AS114: 2650776.8 | AT114: 2740273.9 | AU114: 2832828.5 | AV114: 2928313.1 | AW114: 3026689.5 | AX114: 3130204.5
C115: DIV_GOV_VAL_1 | D115: 6736.0217 | E115: 6981.0542 | F115: 7184.2108 | G115: 6897.7147 | H115: 6995.8402 | I115: 6577.538 | J115: 6110.018 | K115: 6724.3593 | L115: 7115.3042 | M115: 7000.438 | N115: 6942.4202 | O115: 7144.7234 | P115: 7346.8706 | Q115: 7554.5856 | R115: 7841.8697 | S115: 8018.0041 | T115: 8358.3008 | U115: 8434.0763 | V115: 8682.2554 | W115: 8877.5713 | X115: 9099.16 | Y115: 9277.953 | Z115: 9377.266 | AA115: 9415.522 | AB115: 9589.7261 | AC115: 9837.5845 | AD115: 10083.097 | AE115: 10344.902 | AF115: 10646.632 | AG115: 10995.089 | AH115: 11350.762 | AI115: 11714.508 | AJ115: 12117.548 | AK115: 12529.16 | AL115: 12936.479 | AM115: 13376.175 | AN115: 13834.35 | AO115: 14306.499 | AP115: 14760.816 | AQ115: 15248.234 | AR115: 15757.142 | AS115: 16292.795 | AT115: 16839.839 | AU115: 17412.563 | AV115: 17999.446 | AW115: 18602.692 | AX115: 19220.508
C116: IR_VAL_1 | D116: 130354.82 | E116: 135096.67 | F116: 138640.55 | G116: 147517.58 | H116: 157566.63 | I116: 161161.36 | J116: 165854.42 | K116: 175705.73 | L116: 185407.9 | M116: 192921.2 | N116: 195697.58 | O116: 199466.42 | P116: 203516.6 | Q116: 209936.36 | R116: 218159.57 | S116: 226261.65 | T116: 235671.71 | U116: 242524.46 | V116: 250415.56 | W116: 259367.27 | X116: 267742.4 | Y116: 275093.45 | Z116: 282301.99 | AA116: 289415.28 | AB116: 297377.86 | AC116: 305840.31 | AD116: 314549.97 | AE116: 323724.82 | AF116: 333418.18 | AG116: 343829.33 | AH116: 354819.97 | AI116: 366425.28 | AJ116: 378974.5 | AK116: 392235.73 | AL116: 405973.11 | AM116: 420388.96 | AN116: 435376.92 | AO116: 450956.27 | AP116: 466947.53 | AQ116: 483452.09 | AR116: 500424.44 | AS116: 517887.79 | AT116: 535838.68 | AU116: 554394.3 | AV116: 573555.55 | AW116: 593313.15 | AX116: 613882.41
C117: AIC_VAL_1 | D117: 16317.279 | E117: 16910.844 | F117: 17354.453 | G117: 17686.606 | H117: 18234.342 | I117: 18023.439 | J117: 17945.089 | K117: 18412.209 | L117: 18835.65 | M117: 19018.22 | N117: 19291.916 | O117: 19663.45 | P117: 20062.718 | Q117: 20695.579 | R117: 21506.225 | S117: 22304.93 | T117: 23232.577 | U117: 23908.122 | V117: 24686.029 | W117: 25568.491 | X117: 26394.112 | Y117: 27118.781 | Z117: 27829.401 | AA117: 28530.63 | AB117: 29315.584 | AC117: 30149.814 | AD117: 31008.415 | AE117: 31912.874 | AF117: 32868.447 | AG117: 33894.781 | AH117: 34978.242 | AI117: 36122.295 | AJ117: 37359.401 | AK117: 38666.697 | AL117: 40020.931 | AM117: 41442.049 | AN117: 42919.565 | AO117: 44455.381 | AP117: 46031.805 | AQ117: 47658.828 | AR117: 49331.966 | AS117: 51053.508 | AT117: 52823.111 | AU117: 54652.329 | AV117: 56541.25 | AW117: 58488.959 | AX117: 60516.682
...

Sheet T graph
B1: en écart au Tend | C1: 2020 | D1: 2021 | E1: 2022 | F1: 2023 | G1: 2024 | H1: 2025 | I1: 2026 | J1: 2027 | K1: 2028 | L1: 2029 | M1: 2030 | N1: 2031 | O1: 2032 | P1: 2033 | Q1: 2034 | R1: 2035 | S1: 2036 | T1: 2037 | U1: 2038 | V1: 2039 | W1: 2040 | X1: 2041 | Y1: 2042 | Z1: 2043 | AA1: 2044 | AB1: 2045 | AC1: 2046 | AD1: 2047 | AE1: 2048 | AF1: 2049 | AG1: 2050
B2: Solde public | C2: =-(résultats!T58-résultats!T40)+(résultats!T22-résultats!T4) -> 0 | D2: =-(résultats!U58-résultats!U40)+(résultats!U22-résultats!U4) -> 0 | E2: =+(résultats!V58-résultats!V40)-(résultats!V22-résultats!V4) -> 0 | F2: =+(résultats!W58-résultats!W40)-(résultats!W22-résultats!W4) -> 0 | G2: =+(résultats!X58-résultats!X40)-(résultats!X22-résultats!X4) -> -225.945 | H2: =+(résultats!Y58-résultats!Y40)-(résultats!Y22-résultats!Y4) -> 51.045 | I2: =+(résultats!Z58-résultats!Z40)-(résultats!Z22-résultats!Z4) -> 637.593 | J2: =+(résultats!AA58-résultats!AA40)-(résultats!AA22-résultats!AA4) -> 1229.961 | K2: =+(résultats!AB58-résultats!AB40)-(résultats!AB22-résultats!AB4) -> 1661.868 | L2: =+(résultats!AC58-résultats!AC40)-(résultats!AC22-résultats!AC4) -> 1963.849 | ... AG2: =+(résultats!AX58-résultats!AX40)-(résultats!AX22-résultats!AX4) -> -357.449 | AH2: =E4+E14-E2 -> 0 | AI2: =AG2+(résultats!AX237-résultats!AX236) -> 0.00049999997
B3: Déficit public en % PIB | C3: =résultats!T39-résultats!T3 -> 0 | D3: =résultats!U39-résultats!U3 -> 0 | E3: =résultats!V39-résultats!V3 -> 0 | F3: =(résultats!W39-résultats!W3) -> 0 | G3: =(résultats!X39-résultats!X3) -> 7.8299091e-05 | H3: =(résultats!Y39-résultats!Y3) -> -5.2499338e-05 | I3: =(résultats!Z39-résultats!Z3) -> -0.00030078031 | J3: =(résultats!AA39-résultats!AA3) -> -0.00054496604 | K3: =(résultats!AB39-résultats!AB3) -> -0.00072559803 | L3: =(résultats!AC39-résultats!AC3) -> -0.00085830747 | M3: =(résultats!AD39-résultats!AD3) -> -0.00098118281 | ... AG3: =(résultats!AX39-résultats!AX3) -> -0.00065593353
B4: Dépenses publiques (-) en M€ courants | C4: =-(résultats!T40-résultats!T4) -> 0 | D4: =-(résultats!U40-résultats!U4) -> 0 | E4: =-(résultats!V40-résultats!V4) -> 0 | F4: =-(résultats!W40-résultats!W4) -> 0 | G4: =-(résultats!X40-résultats!X4) -> 390.016 | H4: =-(résultats!Y40-résultats!Y4) -> 994.833 | I4: =-(résultats!Z40-résultats!Z4) -> 1406.427 | J4: =-(résultats!AA40-résultats!AA4) -> 1636.272 | ... AG4: =-(résultats!AX40-résultats!AX4) -> -9658.523 | AH4: =SUM(E5:E13)-E4 -> 0
B5: Intérêts de la dette | C5: =-(résultats!T42-résultats!T6) -> 0 | D5: =-(résultats!U42-résultats!U6) -> 0 | E5: =-(résultats!V42-résultats!V6) -> 0 | F5: =-(résultats!W42-résultats!W6) -> 0 | G5: =-(résultats!X42-résultats!X6) -> 0 | H5: =-(résultats!Y42-résultats!Y6) -> 37.83308 | I5: =-(résultats!Z42-résultats!Z6) -> 86.710528 | J5: =-(résultats!AA42-résultats!AA6) -> 137.48254 | ... AG5: =-(résultats!AX42-résultats!AX6) -> -361.19708
B6: Facture énergétique | C6: =-(résultats!T43-résultats!T7) -> 0 | D6: =-(résultats!U43-résultats!U7) -> 0 | E6: =-(résultats!V43-résultats!V7) -> 0 | F6: =-(résultats!W43-résultats!W7) -> 0 | G6: =-(résultats!X43-résultats!X7) -> -1.3262088 | H6: =-(résultats!Y43-résultats!Y7) -> -4.0723924 | I6: =-(résultats!Z43-résultats!Z7) -> 2.2920361 | J6: =-(résultats!AA43-résultats!AA7) -> 3.1497813 | ... AG6: =-(résultats!AX43-résultats!AX7) -> -23.984572
B7: Charges courantes | C7: =-(résultats!T44-résultats!T8+(résultats!T41-résultats!T5)+(résultats!T45-résultats!T9)+(résultats!T47-résultats!T11)) -> 0 | D7: =-(résultats!U44-résultats!U8+(résultats!U41-résultats!U5)+(résultats!U45-résultats!U9)+(résultats!U47-résultats!U11)) -> 0 | E7: =-(résultats!V44-résultats!V8+(résultats!V41-résultats!V5)+(résultats!V45-résultats!V9)+(résultats!V47-résultats!V11)) -> 0 | F7: =-(résultats!W44-résultats!W8+(résultats!W41-résultats!W5)+(résultats!W45-résultats!W9)+(résultats!W47-résultats!W11)) -> 0 | G7: =-(résultats!X44-résultats!X8+(résultats!X41-résultats!X5)+(résultats!X45-résultats!X9)+(résultats!X47-résultats!X11)) -> 34.414416 | H7: =-(résultats!Y44-résultats!Y8+(résultats!Y41-résultats!Y5)+(résultats!Y45-résultats!Y9)+(résultats!Y47-résultats!Y11)) -> 42.151774 | I7: =-(résultats!Z44-résultats!Z8+(résultats!Z41-résultats!Z5)+(résultats!Z45-résultats!Z9)+(résultats!Z47-résultats!Z11)) -> -43.051542 | J7: =-(résultats!AA44-résultats!AA8+(résultats!AA41-résultats!AA5)+(résultats!AA45-résultats!AA9)+(résultats!AA47-résultats!AA11)) -> -228.37756 | ... AG7: =-(résultats!AX44-résultats!AX8+(résultats!AX41-résultats!AX5)+(résultats!AX45-résultats!AX9)+(résultats!AX47-résultats!AX11)) -> -8150.466
B8: Investissements | C8: =-(résultats!T46-résultats!T10) -> 0 | D8: =-(résultats!U46-résultats!U10) -> 0 | E8: =-(résultats!V46-résultats!V10) -> 0 | F8: =-(résultats!W46-résultats!W10) -> 0 | G8: =-(résultats!X46-résultats!X10) -> 1.7984423 | H8: =-(résultats!Y46-résultats!Y10) -> -2.5573333 | I8: =-(résultats!Z46-résultats!Z10) -> -16.315256 | J8: =-(résultats!AA46-résultats!AA10) -> -36.38554 | ... AG8: =-(résultats!AX46-résultats!AX10) -> -809.05966
B9: Prestations sociales | C9: =-(résultats!T50-résultats!T14) -> 0 | D9: =-(résultats!U50-résultats!U14) -> 0 | E9: =-(résultats!V50-résultats!V14) -> 0 | F9: =-(résultats!W50-résultats!W14) -> 0 | G9: =-(résultats!X50-résultats!X14) -> 41.554 | H9: =-(résultats!Y50-résultats!Y14) -> 147.7702 | I9: =-(résultats!Z50-résultats!Z14) -> 282.6237 | J9: =-(résultats!AA50-résultats!AA14) -> 382.8192 | ... AG9: =-(résultats!AX50-résultats!AX14) -> -4921.805
B10: Subventions | C10: =-((résultats!T49-résultats!T13)+(résultats!T48-résultats!T12)) -> 0 | D10: =-((résultats!U49-résultats!U13)+(résultats!U48-résultats!U12)) -> 0 | E10: =-((résultats!V49-résultats!V13)+(résultats!V48-résultats!V12)) -> 0 | F10: =-((résultats!W49-résultats!W13)+(résultats!W48-résultats!W12)) -> 0 | G10: =-((résultats!X49-résultats!X13)+(résultats!X48-résultats!X12)) -> -43.044196 | H10: =-((résultats!Y49-résultats!Y13)+(résultats!Y48-résultats!Y12)) -> -89.096296 | I10: =-((résultats!Z49-résultats!Z13)+(résultats!Z48-résultats!Z12)) -> -132.41675 | J10: =-((résultats!AA49-résultats!AA13)+(résultats!AA48-résultats!AA12)) -> -170.61828 | ... AG10: =-((résultats!AX49-résultats!AX13)+(résultats!AX48-résultats!AX12)) -> -482.5337
B11: Subventions à la rénovation énergétique | C11: =-(résultats!T51-résultats!T15) -> 0 | D11: =-(résultats!U51-résultats!U15) -> 0 | E11: =-(résultats!V51-résultats!V15) -> 0 | F11: =-(résultats!W51-résultats!W15) -> 0 | G11: =-(résultats!X51-résultats!X15) -> 0 | H11: =-(résultats!Y51-résultats!Y15) -> 0 | I11: =-(résultats!Z51-résultats!Z15) -> 0 | J11: =-(résultats!AA51-résultats!AA15) -> 0 | ... AG11: =-(résultats!AX51-résultats!AX15) -> 0
B12: Solde bonus malus automobile | C12: =-(résultats!T52-résultats!T16) -> 0 | D12: =-(résultats!U52-résultats!U16) -> 0 | E12: =-(résultats!V52-résultats!V16) -> 0 | F12: =-(résultats!W52-résultats!W16) -> 0 | G12: =-(résultats!X52-résultats!X16) -> 0.790545 | H12: =-(résultats!Y52-résultats!Y16) -> 2.1524958 | I12: =-(résultats!Z52-résultats!Z16) -> 2.357425 | J12: =-(résultats!AA52-résultats!AA16) -> 1.7808381 | ... AG12: =-(résultats!AX52-résultats!AX16) -> 2.020689
B13: Redistribution aux agents | C13: =SUM(résultats!T53:T57)-SUM(résultats!T17:T21) -> 0 | D13: =SUM(résultats!U53:U57)-SUM(résultats!U17:U21) -> 0 | E13: =SUM(résultats!V53:V57)-SUM(résultats!V17:V21) -> 0 | F13: =-(SUM(résultats!W53:W57)-SUM(résultats!W17:W21)) -> 0 | G13: =-(SUM(résultats!X53:X57)-SUM(résultats!X17:X21)) -> 355.82958 | H13: =-(SUM(résultats!Y53:Y57)-SUM(résultats!Y17:Y21)) -> 860.65254 | I13: =-(SUM(résultats!Z53:Z57)-SUM(résultats!Z17:Z21)) -> 1224.2261 | J13: =-(SUM(résultats!AA53:AA57)-SUM(résultats!AA17:AA21)) -> 1546.4214 | K13: =-(SUM(résultats!AB53:AB57)-SUM(résultats!AB17:AB21)) -> 1842.4871 | L13: =-(SUM(résultats!AC53:AC57)-SUM(résultats!AC17:AC21)) -> 2124.7109 | M13: =-(SUM(résultats!AD53:AD57)-SUM(résultats!AD17:AD21)) -> 2405.9872 | ... AG13: =-(SUM(résultats!AX53:AX57)-SUM(résultats!AX17:AX21)) -> 5088.5008
B14: Recettes publiques en M€ courants | C14: =(résultats!T58-résultats!T22) -> 0 | D14: =(résultats!U58-résultats!U22) -> 0 | E14: =(résultats!V58-résultats!V22) -> 0 | F14: =(résultats!W58-résultats!W22) -> 0 | G14: =(résultats!X58-résultats!X22) -> -615.961 | H14: =(résultats!Y58-résultats!Y22) -> -943.788 | I14: =(résultats!Z58-résultats!Z22) -> -768.834 | J14: =(résultats!AA58-résultats!AA22) -> -406.311 | ... AG14: =(résultats!AX58-résultats!AX22) -> 9301.074
B15: Impôts sur les revenus et le patrimoine | C15: =(résultats!T59-résultats!T23+(résultats!T60-résultats!T24)+(résultats!T61-résultats!T25)) -> 0 | D15: =(résultats!U59-résultats!U23+(résultats!U60-résultats!U24)+(résultats!U61-résultats!U25)) -> 0 | E15: =(résultats!V59-résultats!V23+(résultats!V60-résultats!V24)+(résultats!V61-résultats!V25)) -> 0 | F15: =(résultats!W59-résultats!W23+(résultats!W60-résultats!W24)+(résultats!W61-résultats!W25)) -> 0 | G15: =(résultats!X59-résultats!X23+(résultats!X60-résultats!X24)+(résultats!X61-résultats!X25)) -> 10.375427 | H15: =(résultats!Y59-résultats!Y23+(résultats!Y60-résultats!Y24)+(résultats!Y61-résultats!Y25)) -> 105.54581 | I15: =(résultats!Z59-résultats!Z23+(résultats!Z60-résultats!Z24)+(résultats!Z61-résultats!Z25)) -> 286.7507 | J15: =(résultats!AA59-résultats!AA23+(résultats!AA60-résultats!AA24)+(résultats!AA61-résultats!AA25)) -> 481.40512 | ... AG15: =(résultats!AX59-résultats!AX23+(résultats!AX60-résultats!AX24)+(résultats!AX61-résultats!AX25)) -> 2745.7343
B16: Taxes à la consommation | C16: =(résultats!T63-résultats!T27) -> 0 | D16: =(résultats!U63-résultats!U27) -> 0 | E16: =(résultats!V63-résultats!V27) -> 0 | F16: =(résultats!W63-résultats!W27) -> 0 | G16: =(résultats!X63-résultats!X27) -> -83.161 | H16: =(résultats!Y63-résultats!Y27) -> -126.12893 | I16: =(résultats!Z63-résultats!Z27) -> -115.9511 | J16: =(résultats!AA63-résultats!AA27) -> -87.714401 | ... AG16: =(résultats!AX63-résultats!AX27) -> 1312.2078
B17: Taxes énergétiques | C17: =SUM(résultats!T69:T73)-SUM(résultats!T33:T37) -> 0 | D17: =SUM(résultats!U69:U73)-SUM(résultats!U33:U37) -> 0 | E17: =SUM(résultats!V69:V73)-SUM(résultats!V33:V37) -> 0 | F17: =SUM(résultats!W69:W73)-SUM(résultats!W33:W37) -> 0 | G17: =SUM(résultats!X69:X73)-SUM(résultats!X33:X37) -> -355.82958 | H17: =SUM(résultats!Y69:Y73)-SUM(résultats!Y33:Y37) -> -860.65254 | I17: =SUM(résultats!Z69:Z73)-SUM(résultats!Z33:Z37) -> -1224.2261 | J17: =SUM(résultats!AA69:AA73)-SUM(résultats!AA33:AA37) -> -1546.4214 | ... AG17: =SUM(résultats!AX69:AX73)-SUM(résultats!AX33:AX37) -> -5088.5008
B18: Taxes à la production | C18: =(résultats!T64-résultats!T28) -> 0 | D18: =(résultats!U64-résultats!U28) -> 0 | E18: =(résultats!V64-résultats!V28) -> 0 | F18: =(résultats!W64-résultats!W28) -> 0 | G18: =(résultats!X64-résultats!X28) -> 30.948442 | H18: =(résultats!Y64-résultats!Y28) -> 86.606698 | I18: =(résultats!Z64-résultats!Z28) -> 151.73404 | J18: =(résultats!AA64-résultats!AA28) -> 218.55817 | ... AG18: =(résultats!AX64-résultats!AX28) -> 1169.859
B19: Impôts sur les bénéfices | C19: =(résultats!T65-résultats!T29) -> 0 | D19: =(résultats!U65-résultats!U29) -> 0 | E19: =(résultats!V65-résultats!V29) -> 0 | F19: =(résultats!W65-résultats!W29) -> 0 | G19: =(résultats!X65-résultats!X29) -> -244.85271 | H19: =(résultats!Y65-résultats!Y29) -> -369.08619 | I19: =(résultats!Z65-résultats!Z29) -> -444.58739 | J19: =(résultats!AA65-résultats!AA29) -> -466.50743 | ... AG19: =(résultats!AX65-résultats!AX29) -> 116.53325
B20: Cotisations sociales | C20: =(résultats!T66-résultats!T30) -> 0 | D20: =(résultats!U66-résultats!U30) -> 0 | E20: =(résultats!V66-résultats!V30) -> 0 | F20: =(résultats!W66-résultats!W30) -> 0 | G20: =(résultats!X66-résultats!X30) -> 3.430913 | H20: =(résultats!Y66-résultats!Y30) -> 179.35576 | I20: =(résultats!Z66-résultats!Z30) -> 567.93861 | J20: =(résultats!AA66-résultats!AA30) -> 1087.373 | ... AG20: =(résultats!AX66-résultats!AX30) -> 9815.476
B21: Revenus des services publics | C21: =(résultats!T67-résultats!T31+(résultats!T68-résultats!T32)) -> 0 | D21: =(résultats!U67-résultats!U31+(résultats!U68-résultats!U32)) -> 0 | E21: =(résultats!V67-résultats!V31+(résultats!V68-résultats!V32)) -> 0 | F21: =(résultats!W67-résultats!W31+(résultats!W68-résultats!W32)) -> 0 | G21: =(résultats!X67-résultats!X31+(résultats!X68-résultats!X32)) -> 23.126647 | H21: =(résultats!Y67-résultats!Y31+(résultats!Y68-résultats!Y32)) -> 40.571841 | I21: =(résultats!Z67-résultats!Z31+(résultats!Z68-résultats!Z32)) -> 9.506593 | J21: =(résultats!AA67-résultats!AA31+(résultats!AA68-résultats!AA32)) -> -93.004129 | ... AG21: =(résultats!AX67-résultats!AX31+(résultats!AX68-résultats!AX32)) -> -770.23556
E22: =SUM(E15:E21,E5:E12) -> 0 | F22: =SUM(F15:F21,F5:F13)-F2 -> 0 | G22: =SUM(G15:G21,G5:G13)-G2 -> -0.00028227786 | H22: =SUM(H15:H21,H5:H13)-H2 -> 0.0015186248 | I22: =SUM(I15:I21,I5:I13)-I2 -> -0.0014006859 | J22: =SUM(J15:J21,J5:J13)-J2 -> 0.00028350736 | K22: =SUM(K15:K21,K5:K13)-K2 -> -0.00045556735 | L22: =SUM(L15:L21,L5:L13)-L2 -> -0.0010033515 | M22: =SUM(M15:M21,M5:M13)-M2 -> -0.0011196327 | ... AG22: =SUM(AG15:AG21,AG5:AG13)-AG2 -> -0.0015740375
E25: =E2+E4+E14 -> 0 | F25: =SUM(F15:F21)-F14 -> 0 | G25: =SUM(G15:G21)-G14 -> -0.00086438217 | H25: =SUM(H15:H21)-H14 -> 0.00045414684 | I25: =SUM(I15:I21)-I14 -> -0.00066624862 | J25: =SUM(J15:J21)-J14 -> -9.3744935e-05 | K25: =SUM(K15:K21)-K14 -> -0.00034063562 | L25: =SUM(L15:L21)-L14 -> -0.00027033425 | M25: =SUM(M15:M21)-M14 -> -0.0008759891 | ... AG25: =SUM(AG15:AG21)-AG14 -> -7.1769067e-05
F26: =SUM(F5:F13)-F4 -> 0 | G26: =SUM(G5:G13)-G4 -> 0.00058210431 | H26: =SUM(H5:H13)-H4 -> 0.0010644779 | I26: =SUM(I5:I13)-I4 -> -0.00073443733 | J26: =SUM(J5:J13)-J4 -> 0.00037725229 | K26: =SUM(K5:K13)-K4 -> -0.00011493173 | L26: =SUM(L5:L13)-L4 -> -0.00073301726 | M26: =SUM(M5:M13)-M4 -> -0.00024364362 | ... AG26: =SUM(AG5:AG13)-AG4 -> -0.0015022684
