Workbook

Sheet Produits et secteurs 3ME

Sheet Sorties des modèles
A2: En valeur
A4: Ménages
A5: 1 | B5: Consommation TTC des ménages totale
A6: 2 | B6: Investissements des ménages
A8: 3 | B8: Revenu des ménages
A9: 4 | B9: RDB des ménages
A11: 5 | B11: Flux nets d'endettement des ménages hors 'co-financeurs'
A12: 6 | B12: Flux nets d'endettement des ménages y compris auprès des 'co-financeurs'
A14: 7 | B14: Flux de remboursement des ménages (hors remboursement aux 'co-financeurs')
A15: 8 | B15: Flux de remboursement des ménages (yc remboursement aux 'co-financeurs')
A18: Entreprises
A19: 9 | B19: Valeur ajoutée
A21: 10 | B21: Masse salariale
A23: 11 | B23: Investissement des entreprises
A25: 12 | B25: Flux net (des remboursements) d'endettement des entreprises
A28: Etat
A29: 13 | B29: recettes
A30: 14 | B30: dont | C30: toutes taxes sur l'énergie
A31: 15 | C31: taxe carbone
A32: 16 | C32: (taux de la taxe carbone)
A33: 17 | B33: dépenses
A34: 18 | B34: dont | C34: investisements
A35: 19 | B35: déficit public courant
A37: 20 | B37: Dette publique
A40: Extérieur
A41: 21 | B41: Exportations
A42: 22 | B42: Importations
A43: 23 | B43: dont | C43: importations d'énergie | E43: (ventilées pr secteur ?)
A44: 24 | B44: Solde du compte courant
A46: Déclinaison sectorielles (en valeur)
B48: Consommation TTC des ménages
A49: 1 | B49: en | C49: biens manufacturés
A50: 2 | C50: services de transports
A51: 3 | C51: services (hors service de transports)
A52: 4 | C52: énergie
A53: 5 | C53: autre
B55: Valeur ajoutée
A56: 6 | B56: secteur | C56: énergie
A57: 7 | C57: manuf
A58: 8 | C58: bâtiment
A59: 9 | C59: services de transports
A60: 10 | C60: autres
B62: Masse salariale
A63: 11 | B63: secteur | C63: énergie
A64: 12 | C64: manuf
A65: 13 | C65: bâtiment
A66: 14 | C66: services de transports
A67: 15 | C67: autres
B69: CI d'énergie
A70: 16 | B70: secteur | C70: énergie
A71: 17 | C71: manuf
A72: 18 | C72: bâtiment
A73: 19 | C73: services de transports
A74: 20 | C74: autres
A76: Indices de prix
A78: 1 | B78: IPC
B80: Prix (TTC) relatifs de la conso des ménages
A81: 2 | C81: biens / IPC
A82: 3 | C82: Services / IPC
A83: 4 | C83: Energie / IPC
A85: 5 | B85: Prix des investissement
A86: 6 | B86: Prix du PIB
A88: 7 | B88: prix exports / prix imports
A90: 8 | B90: taux d'intérêt nominal
A91: 9 | B91: taux d'intérêt réel
A93: 10 | B93: taux de change / USD
A94: 11 | B94: taux de change réel / USD
A95: 12 | B95: taux de change réel
A99: en volume
A101: 1 | B101: PIB
A102: 2 | B102: Consommation
A103: 3 | B103: dont | C103: ménages
A104: 4 | C104: Etat
A105: 5 | B105: Investissement
A106: 6 | B106: dont | C106: ménages
A107: 7 | C107: entreprises
A108: 8 | C108: Etat
A109: 9 | B109: Exportations
A110: 10 | B110: Importations
A111: 11 | B111: Variation de stocks
A114: 12 | B114: Heures travaillées
A115: 13 | B115: Emploi
A116: 14 | B116: taux de chômage
A117: 15 | B117: Productivité apparente du travail
A119: 16 | B119: émissions de CO2

Sheet résultats
C1: 2004 | D1: 2005 | E1: 2006 | F1: 2007 | G1: 2008 | H1: 2009 | I1: 2010 | J1: 2011 | K1: 2012 | L1: 2013 | M1: 2014 | N1: 2015 | O1: 2016 | P1: 2017 | Q1: 2018 | R1: 2019 | S1: 2020 | T1: 2021 | U1: 2022 | V1: 2023 | W1: 2024 | X1: 2025 | Y1: 2026 | Z1: 2027 | AA1: 2028 | AB1: 2029 | AC1: 2030 | AD1: 2031 | AE1: 2032 | AF1: 2033 | AG1: 2034 | AH1: 2035 | AI1: 2036 | AJ1: 2037 | AK1: 2038 | AL1: 2039 | AM1: 2040 | AN1: 2041 | AO1: 2042 | AP1: 2043 | AQ1: 2044 | AR1: 2045 | AS1: 2046 | AT1: 2047 | AU1: 2048 | AV1: 2049 | AW1: 2050
A2: Rénovation (M€ courants) | B2: REHAB_VAL_1 | C2: 4655.932 | D2: 4825.2982 | E2: 4958.9472 | F2: 4601.6258 | G2: 5944.0779 | H2: 6462.5149 | I2: 5653.6409 | J2: 5784.6682 | K2: 7209.2996 | L2: 8182.7283 | M2: 8166.9262 | N2: 7060.4379 | O2: 6430.2519 | P2: 5813.7251 | Q2: 7353.7641 | R2: 9159.3655 | S2: 11855.356 | T2: 11651.666 | U2: 13714.466 | V2: 14527.82 | W2: 16838.812 | X2: 16165.677 | Y2: 18324.099 | Z2: 16897.383 | AA2: 16509.013 | AB2: 16393.135 | AC2: 16443.474 | AD2: 16582.41 | AE2: 16767.135 | AF2: 17001.913 | AG2: 17272.97 | AH2: 17556.6 | AI2: 17867.131 | AJ2: 18200.34 | AK2: 18555.372 | AL2: 18940.04 | AM2: 19348.699 | AN2: 19809.074 | AO2: 20384.705 | AP2: 21016.29 | AQ2: 21676.068 | AR2: 22355.738 | AS2: 23048.951 | AT2: 23772.974 | AU2: 24515.987 | AV2: 25254.508 | AW2: 25982.98
A3: Taux de financement des rénovations par emprunt | B3: R_LOAN_REHAB_H01_CG_1 | C3: 0.3 | D3: 0.3 | E3: 0.3 | F3: 0.3 | G3: 0.3 | H3: 0.3 | I3: 0.3 | J3: 0.3 | K3: 0.3 | L3: 0.3 | M3: 0.3 | N3: 0.3 | O3: 0.3 | P3: 0.3 | Q3: 0.3 | R3: 0.3 | S3: 0.3 | T3: 0.3 | U3: 0.3 | V3: 0.3 | W3: 0.3 | X3: 0.3 | Y3: 0.3 | Z3: 0.3 | AA3: 0.3 | AB3: 0.3 | AC3: 0.3 | AD3: 0.3 | AE3: 0.3 | AF3: 0.3 | AG3: 0.3 | AH3: 0.3 | AI3: 0.3 | AJ3: 0.3 | AK3: 0.3 | AL3: 0.3 | AM3: 0.3 | AN3: 0.3 | AO3: 0.3 | AP3: 0.3 | AQ3: 0.3 | AR3: 0.3 | AS3: 0.3 | AT3: 0.3 | AU3: 0.3 | AV3: 0.3 | AW3: 0.3
A4: Taux d'intérêt | B4: R_1 | C4: 0.02637643 | D4: 0.02637643 | E4: 0.013276695 | F4: 0.0096219735 | G4: 0.020462196 | H4: 0.0078342748 | I4: 0.015112648 | J4: 0.014958585 | K4: 0.01552575 | L4: 0.013503432 | M4: 0.016129302 | N4: 0.013312163 | O4: 0.013202983 | P4: 0.020584777 | Q4: 0.026723349 | R4: 0.024559854 | S4: 0.026213344 | T4: 0.026268186 | U4: 0.026752761 | V4: 0.026908462 | W4: 0.026980911 | X4: 0.026954565 | Y4: 0.026389747 | Z4: 0.026029573 | AA4: 0.025826511 | AB4: 0.025647215 | AC4: 0.025510008 | AD4: 0.025473788 | AE4: 0.025202476 | AF4: 0.025395825 | AG4: 0.025497706 | AH4: 0.025355401 | AI4: 0.025799573 | AJ4: 0.025775958 | AK4: 0.025785726 | AL4: 0.02577651 | AM4: 0.025769324 | AN4: 0.025822692 | AO4: 0.02581647 | AP4: 0.025807983 | AQ4: 0.025798682 | AR4: 0.025778892 | AS4: 0.025783489 | AT4: 0.025798547 | AU4: 0.025788078 | AV4: 0.025783999 | AW4: 0.025899267
A5: Durée de vie (an) | B5: LD_REHAB_H01_CG | C5: 25 | D5: 25 | E5: 25 | F5: 25 | G5: 25 | H5: 25 | I5: 25 | J5: 25 | K5: 25 | L5: 25 | M5: 25 | N5: 25 | O5: 25 | P5: 25 | Q5: 25 | R5: 25 | S5: 25 | T5: 25 | U5: 25 | V5: 10 | W5: 10 | X5: 10 | Y5: 10 | Z5: 10 | AA5: 10 | AB5: 10 | AC5: 10 | AD5: 10 | AE5: 10 | AF5: 10 | AG5: 10 | AH5: 10 | AI5: 10 | AJ5: 10 | AK5: 10 | AL5: 10 | AM5: 10 | AN5: 10 | AO5: 10 | AP5: 10 | AQ5: 10 | AR5: 10 | AS5: 10 | AT5: 10 | AU5: 10 | AV5: 10 | AW5: 10
A6: Revenu (M€ courants) | B6: DISPINC_AI_VAL_1 | C6: 1226094.8 | D6: 1270695.8 | E6: 1304023.8 | F6: 1328960 | G6: 1369991.9 | H6: 1353956.9 | I6: 1347772.3 | J6: 1381927.6 | K6: 1413118.6 | L6: 1426218.4 | M6: 1446051.5 | N6: 1472687 | O6: 1500976.7 | P6: 1546623.6 | Q6: 1605310.6 | R6: 1662475.8 | S6: 1730997.1 | T6: 1778158.3 | U6: 1847853.8 | V6: 1909512.6 | W6: 1969195.8 | X6: 2021255.6 | Y6: 2074851 | Z6: 2124425 | AA6: 2182092.3 | AB6: 2243899 | AC6: 2307698 | AD6: 2375217.5 | AE6: 2443514.9 | AF6: 2517975.1 | AG6: 2597145.4 | AH6: 2681060.4 | AI6: 2772204.3 | AJ6: 2868949.7 | AK6: 2969073.5 | AL6: 3074302.9 | AM6: 3183629.9 | AN6: 3296919 | AO6: 3412780 | AP6: 3532910.1 | AQ6: 3656420 | AR6: 3783615.1 | AS6: 3914023.4 | AT6: 4049042.9 | AU6: 4188199.6 | AV6: 4331599 | AW6: 4480933.7
A7: Rénovation (M€ courants) | B7: REHAB_VAL_2 | C7: 4655.932 | D7: 4825.2982 | E7: 4958.9472 | F7: 4601.6258 | G7: 5944.0779 | H7: 6462.5149 | I7: 5653.6409 | J7: 5784.6682 | K7: 7209.2996 | L7: 8182.7283 | M7: 8166.9262 | N7: 7060.4379 | O7: 6430.2519 | P7: 5813.7251 | Q7: 7353.7641 | R7: 9159.3655 | S7: 11855.356 | T7: 11651.666 | U7: 13714.466 | V7: 14461.436 | W7: 14900.55 | X7: 14360.468 | Y7: 16540.241 | Z7: 17963.955 | AA7: 18402.456 | AB7: 19020.008 | AC7: 19298.321 | AD7: 19272.862 | AE7: 19827.051 | AF7: 19846.019 | AG7: 19653.632 | AH7: 19757.599 | AI7: 19668.47 | AJ7: 19358.769 | AK7: 19293.234 | AL7: 19276.444 | AM7: 19157.138 | AN7: 19752.526 | AO7: 19907.195 | AP7: 19953.81 | AQ7: 19932.211 | AR7: 19877.753 | AS7: 19899.083 | AT7: 20228.442 | AU7: 20637.406 | AV7: 21054.949 | AW7: 21454.89
A8: Taux de financement des rénovations par emprunt | B8: R_LOAN_REHAB_H01_CG_2 | C8: 0.3 | D8: 0.3 | E8: 0.3 | F8: 0.3 | G8: 0.3 | H8: 0.3 | I8: 0.3 | J8: 0.3 | K8: 0.3 | L8: 0.3 | M8: 0.3 | N8: 0.3 | O8: 0.3 | P8: 0.3 | Q8: 0.3 | R8: 0.3 | S8: 0.3 | T8: 0.3 | U8: 0.3 | V8: 0.3 | W8: 0.3 | X8: 0.3 | Y8: 0.3 | Z8: 0.3 | AA8: 0.3 | AB8: 0.3 | AC8: 0.3 | AD8: 0.3 | AE8: 0.3 | AF8: 0.3 | AG8: 0.3 | AH8: 0.3 | AI8: 0.3 | AJ8: 0.3 | AK8: 0.3 | AL8: 0.3 | AM8: 0.3 | AN8: 0.3 | AO8: 0.3 | AP8: 0.3 | AQ8: 0.3 | AR8: 0.3 | AS8: 0.3 | AT8: 0.3 | AU8: 0.3 | AV8: 0.3 | AW8: 0.3
A9: Taux d'intérêt | B9: R_2 | C9: 0.02637643 | D9: 0.02637643 | E9: 0.013276695 | F9: 0.0096219735 | G9: 0.020462196 | H9: 0.0078342748 | I9: 0.015112648 | J9: 0.014958585 | K9: 0.01552575 | L9: 0.013503432 | M9: 0.016129302 | N9: 0.013312163 | O9: 0.013202983 | P9: 0.020584777 | Q9: 0.026723349 | R9: 0.024559854 | S9: 0.026213344 | T9: 0.026268186 | U9: 0.026752761 | V9: 0.026713653 | W9: 0.027659423 | X9: 0.027662767 | Y9: 0.026055448 | Z9: 0.02602458 | AA9: 0.026311389 | AB9: 0.027418035 | AC9: 0.027664483 | AD9: 0.027130643 | AE9: 0.026762764 | AF9: 0.0267073 | AG9: 0.026804054 | AH9: 0.026672382 | AI9: 0.026643006 | AJ9: 0.026652602 | AK9: 0.026921291 | AL9: 0.026874944 | AM9: 0.027136271 | AN9: 0.02701082 | AO9: 0.027155187 | AP9: 0.027251786 | AQ9: 0.027215843 | AR9: 0.027219554 | AS9: 0.027309751 | AT9: 0.027270024 | AU9: 0.027184411 | AV9: 0.027097897 | AW9: 0.027128778
A10: Durée de vie (an) | B10: LD_REHAB_H01_CG | C10: 25 | D10: 25 | E10: 25 | F10: 25 | G10: 25 | H10: 25 | I10: 25 | J10: 25 | K10: 25 | L10: 25 | M10: 25 | N10: 25 | O10: 25 | P10: 25 | Q10: 25 | R10: 25 | S10: 25 | T10: 25 | U10: 25 | V10: 10 | W10: 10 | X10: 10 | Y10: 10 | Z10: 10 | AA10: 10 | AB10: 10 | AC10: 10 | AD10: 10 | AE10: 10 | AF10: 10 | AG10: 10 | AH10: 10 | AI10: 10 | AJ10: 10 | AK10: 10 | AL10: 10 | AM10: 10 | AN10: 10 | AO10: 10 | AP10: 10 | AQ10: 10 | AR10: 10 | AS10: 10 | AT10: 10 | AU10: 10 | AV10: 10 | AW10: 10
A11: Revenu (M€ courants) | B11: DISPINC_AI_VAL_2 | C11: 1226094.8 | D11: 1270695.8 | E11: 1304023.8 | F11: 1328960 | G11: 1369991.9 | H11: 1353956.9 | I11: 1347772.3 | J11: 1381927.6 | K11: 1413118.6 | L11: 1426218.4 | M11: 1446051.5 | N11: 1472687 | O11: 1500976.7 | P11: 1546623.6 | Q11: 1605310.6 | R11: 1662475.8 | S11: 1730997.1 | T11: 1778158.3 | U11: 1847853.8 | V11: 1910081.8 | W11: 1972574.8 | X11: 2026244.5 | Y11: 2083491.2 | Z11: 2144130.6 | AA11: 2211944.2 | AB11: 2282059 | AC11: 2349925.2 | AD11: 2422079.2 | AE11: 2500526.2 | AF11: 2582089.8 | AG11: 2666812.1 | AH11: 2753800.6 | AI11: 2847335.5 | AJ11: 2950395.3 | AK11: 3055102.5 | AL11: 3168320.2 | AM11: 3281520.8 | AN11: 3404298 | AO11: 3530623.6 | AP11: 3662069.7 | AQ11: 3797312.3 | AR11: 3936247 | AS11: 4075436.7 | AT11: 4217175 | AU11: 4365692.1 | AV11: 4520122 | AW11: 4680122.5
A12: Prix d'achat des automobiles net de subvention | B12: PNEWAUTO_H01_1*NEWAUTO_H01_1*(1-R_SUB_AUTO_H01_1) | C12: 49901.347 | D12: 51716.58 | E12: 53220.249 | F12: 55902.555 | G12: 55392.29 | H12: 62075.577 | I12: 61001.942 | J12: 59921.041 | K12: 52167.917 | L12: 49897.42 | M12: 51255.567 | N12: 50283.355 | O12: 53942.513 | P12: 58730.11 | Q12: 61674.524 | R12: 63471.097 | S12: 56843.074 | T12: 49792.871 | U12: 51465.625 | V12: 53671.433 | W12: 54592.047 | X12: 55058.827 | Y12: 63123.964 | Z12: 67558.932 | AA12: 71218.997 | AB12: 74185.567 | AC12: 76676.994 | AD12: 79047.075 | AE12: 77395.468 | AF12: 77753.893 | AG12: 78851.369 | AH12: 76538.484 | AI12: 80196.787 | AJ12: 82872.33 | AK12: 85054.069 | AL12: 87049.468 | AM12: 88881.345 | AN12: 89956.757 | AO12: 91450.319 | AP12: 93249.35 | AQ12: 95150.687 | AR12: 97122.094 | AS12: 98657.737 | AT12: 100494.94 | AU12: 102463.37 | AV12: 104521.48 | AW12: 106712.05
A13: Taux de financement des auto par emprunt | B13: R_LOAN_AUTO_H01_CA | C13: 0.2 | D13: 0.2 | E13: 0.2 | F13: 0.2 | G13: 0.2 | H13: 0.2 | I13: 0.2 | J13: 0.2 | K13: 0.2 | L13: 0.2 | M13: 0.2 | N13: 0.2 | O13: 0.2 | P13: 0.2 | Q13: 0.2 | R13: 0.2 | S13: 0.2 | T13: 0.2 | U13: 0.2 | V13: 0.2 | W13: 0.2 | X13: 0.2 | Y13: 0.2 | Z13: 0.2 | AA13: 0.2 | AB13: 0.2 | AC13: 0.2 | AD13: 0.2 | AE13: 0.2 | AF13: 0.2 | AG13: 0.2 | AH13: 0.2 | AI13: 0.2 | AJ13: 0.2 | AK13: 0.2 | AL13: 0.2 | AM13: 0.2 | AN13: 0.2 | AO13: 0.2 | AP13: 0.2 | AQ13: 0.2 | AR13: 0.2 | AS13: 0.2 | AT13: 0.2 | AU13: 0.2 | AV13: 0.2 | AW13: 0.2
... A233: Réhabilitation | B233: REHAB_VAL_2 | C233: 4655.932 | D233: 4825.2982 | E233: 4958.9472 | F233: 4601.6258 | G233: 5944.0779 | H233: 6462.5149 | I233: 5653.6409 | J233: 5784.6682 | K233: 7209.2996 | L233: 8182.7283 | M233: 8166.9262 | N233: 7060.4379 | O233: 6430.2519 | P233: 5813.7251 | Q233: 7353.7641 | R233: 9159.3655 | S233: 11855.356 | T233: 11651.666 | U233: 13714.466 | V233: 14461.436 | W233: 14900.55 | X233: 14360.468 | Y233: 16540.241 | Z233: 17963.955 | AA233: 18402.456 | AB233: 19020.008 | AC233: 19298.321 | AD233: 19272.862 | AE233: 19827.051 | AF233: 19846.019 | AG233: 19653.632 | AH233: 19757.599 | AI233: 19668.47 | AJ233: 19358.769 | AK233: 19293.234 | AL233: 19276.444 | AM233: 19157.138 | AN233: 19752.526 | AO233: 19907.195 | AP233: 19953.81 | AQ233: 19932.211 | AR233: 19877.753 | AS233: 19899.083 | AT233: 20228.442 | AU233: 20637.406 | AV233: 21054.949 | AW233: 21454.89
A234: Coût unitaire du capital CB | B234: UC_K_REHAB_H01_CB_1 | D234: 8.3580815e-06 | E234: 8.4538508e-06 | F234: 6.5740456e-06 | G234: 6.46202e-06 | H234: 6.9722041e-06 | I234: 6.9108297e-06 | J234: 7.0538631e-06 | K234: 7.5241695e-06 | L234: 7.4850678e-06 | M234: 7.2609709e-06 | N234: 7.0409358e-06 | O234: 7.102457e-06 | P234: 6.4998734e-06 | Q234: 7.1133829e-06 | R234: 6.4998605e-06 | S234: 7.2709093e-06 | T234: 6.5084439e-06 | U234: 7.3231407e-06 | V234: 6.8913137e-06 | W234: 8.3357107e-06 | X234: 8.4174628e-06 | Y234: 1.0376323e-05 | Z234: 1.057335e-05 | AA234: 1.077744e-05 | AB234: 1.0987707e-05 | AC234: 1.1201823e-05 | AD234: 1.14212e-05 | AE234: 1.1646025e-05 | AF234: 1.1869862e-05 | AG234: 1.2107457e-05 | AH234: 1.2347951e-05 | AI234: 1.2587989e-05 | AJ234: 1.2845751e-05 | AK234: 1.3098475e-05 | AL234: 1.3356985e-05 | AM234: 1.3620172e-05 | AN234: 1.3887095e-05 | AO234: 1.4161603e-05 | AP234: 1.4440334e-05 | AQ234: 1.472422e-05 | AR234: 1.5013246e-05 | AS234: 1.5307433e-05 | AT234: 1.5607828e-05 | AU234: 1.5914172e-05 | AV234: 1.6225567e-05 | AW234: 1.6545947e-05
A235: Coût unitaire du capital CC | B235: UC_K_REHAB_H01_CC_1 | D235: 5.8631016e-06 | E235: 5.9302827e-06 | F235: 4.6116202e-06 | G235: 4.5330355e-06 | H235: 4.890924e-06 | I235: 4.8478706e-06 | J235: 4.9482069e-06 | K235: 5.2781216e-06 | L235: 5.2506922e-06 | M235: 5.0934907e-06 | N235: 4.9391385e-06 | O235: 4.9822949e-06 | P235: 4.5595892e-06 | Q235: 4.9899593e-06 | R235: 4.5595802e-06 | S235: 5.1004624e-06 | T235: 4.5656013e-06 | U235: 5.1371021e-06 | V235: 4.8341803e-06 | W235: 5.8474088e-06 | X235: 5.9047569e-06 | Y235: 7.2788753e-06 | Z235: 7.417088e-06 | AA235: 7.5602551e-06 | AB235: 7.7077547e-06 | AC235: 7.857955e-06 | AD235: 8.0118451e-06 | AE235: 8.1695577e-06 | AF235: 8.3265765e-06 | AG235: 8.4932469e-06 | AH235: 8.6619512e-06 | AI235: 8.8303346e-06 | AJ235: 9.0111518e-06 | AK235: 9.1884352e-06 | AL235: 9.3697772e-06 | AM235: 9.5544001e-06 | AN235: 9.7416435e-06 | AO235: 9.9342079e-06 | AP235: 1.0129734e-05 | AQ235: 1.0328877e-05 | AR235: 1.0531626e-05 | AS235: 1.0737995e-05 | AT235: 1.0948719e-05 | AU235: 1.1163616e-05 | AV235: 1.1382056e-05 | AW235: 1.1606798e-05
A236: Coût unitaire du capital CD | B236: UC_K_REHAB_H01_CD_1 | D236: 3.4620548e-06 | E236: 3.501724e-06 | F236: 2.7230778e-06 | G236: 2.676675e-06 | H236: 2.8880016e-06 | I236: 2.8625793e-06 | J236: 2.9218261e-06 | K236: 3.1166347e-06 | L236: 3.1004382e-06 | M236: 3.0076136e-06 | N236: 2.9164714e-06 | O236: 2.9419545e-06 | P236: 2.6923544e-06 | Q236: 2.9464802e-06 | R236: 2.6923491e-06 | S236: 3.0117302e-06 | T236: 2.6959045e-06 | U236: 3.0333653e-06 | V236: 2.8544955e-06 | W236: 3.4527885e-06 | X236: 3.4866515e-06 | Y236: 4.2980434e-06 | Z236: 4.3796555e-06 | AA236: 4.4641931e-06 | AB236: 4.5512889e-06 | AC236: 4.6399794e-06 | AD236: 4.7308487e-06 | AE236: 4.8239751e-06 | AF236: 4.9166919e-06 | AG236: 5.0151078e-06 | AH236: 5.1147245e-06 | AI236: 5.2141519e-06 | AJ236: 5.3209212e-06 | AK236: 5.4256037e-06 | AL236: 5.5326829e-06 | AM236: 5.6416994e-06 | AN236: 5.7522632e-06 | AO236: 5.865969e-06 | AP236: 5.9814237e-06 | AQ236: 6.099014e-06 | AR236: 6.2187335e-06 | AS236: 6.3405906e-06 | AT236: 6.4650192e-06 | AU236: 6.5919119e-06 | AV236: 6.7208969e-06 | AW236: 6.8536032e-06
A237: Coût unitaire du capital CE | B237: UC_K_REHAB_H01_CE_1 | D237: 7.3182617e-06 | E237: 7.4021164e-06 | F237: 5.7561758e-06 | G237: 5.6580872e-06 | H237: 6.1047998e-06 | I237: 6.051061e-06 | J237: 6.1762997e-06 | K237: 6.5880958e-06 | L237: 6.5538588e-06 | M237: 6.3576415e-06 | N237: 6.1649807e-06 | O237: 6.2188481e-06 | P237: 5.6912312e-06 | Q237: 6.2284147e-06 | R237: 5.69122e-06 | S237: 6.3663435e-06 | T237: 5.6987355e-06 | U237: 6.4120768e-06 | V237: 6.0339729e-06 | W237: 7.2986741e-06 | X237: 7.3702554e-06 | Y237: 9.0854156e-06 | Z237: 9.2579312e-06 | AA237: 9.4366309e-06 | AB237: 9.6207383e-06 | AC237: 9.8082167e-06 | AD237: 1.0000301e-05 | AE237: 1.0197156e-05 | AF237: 1.0393145e-05 | AG237: 1.0601181e-05 | AH237: 1.0811756e-05 | AI237: 1.1021931e-05 | AJ237: 1.1247625e-05 | AK237: 1.1468908e-05 | AL237: 1.1695257e-05 | AM237: 1.1925702e-05 | AN237: 1.2159417e-05 | AO237: 1.2399774e-05 | AP237: 1.2643828e-05 | AQ237: 1.2892396e-05 | AR237: 1.3145465e-05 | AS237: 1.3403052e-05 | AT237: 1.3666076e-05 | AU237: 1.3934308e-05 | AV237: 1.4206962e-05 | AW237: 1.4487483e-05
A238: Coût unitaire du capital CF | B238: UC_K_REHAB_H01_CF_1 | D238: 1.1158829e-05 | E238: 1.128669e-05 | F238: 8.7769727e-06 | G238: 8.6274079e-06 | H238: 9.308552e-06 | I238: 9.2266114e-06 | J238: 9.4175744e-06 | K238: 1.0045478e-05 | L238: 9.9932736e-06 | M238: 9.6940829e-06 | N238: 9.4003152e-06 | O238: 9.4824519e-06 | P238: 8.6779458e-06 | Q238: 9.497039e-06 | R238: 8.6779285e-06 | S238: 9.7073517e-06 | T238: 8.6893882e-06 | U238: 9.7770855e-06 | V238: 9.2005557e-06 | W238: 1.1128962e-05 | X238: 1.1238109e-05 | Y238: 1.3853372e-05 | Z238: 1.4116422e-05 | AA238: 1.4388902e-05 | AB238: 1.4669628e-05 | AC238: 1.4955494e-05 | AD238: 1.5248382e-05 | AE238: 1.5548545e-05 | AF238: 1.5847388e-05 | AG238: 1.61646e-05 | AH238: 1.6485683e-05 | AI238: 1.6806155e-05 | AJ238: 1.7150292e-05 | AK238: 1.7487703e-05 | AL238: 1.7832838e-05 | AM238: 1.8184218e-05 | AN238: 1.8540586e-05 | AO238: 1.890708e-05 | AP238: 1.9279211e-05 | AQ238: 1.9658226e-05 | AR238: 2.0044104e-05 | AS238: 2.0436871e-05 | AT238: 2.0837927e-05 | AU238: 2.1246925e-05 | AV238: 2.1662667e-05 | AW238: 2.2090404e-05
A239: Coût unitaire du capital CG | B239: UC_K_REHAB_H01_CG_1 | D239: 1.1136217e-05 | E239: 1.1263819e-05 | F239: 8.7591871e-06 | G239: 8.6099253e-06 | H239: 9.2896891e-06 | I239: 9.2079146e-06 | J239: 9.3984906e-06 | K239: 1.0025122e-05 | L239: 9.9730232e-06 | M239: 9.6744388e-06 | N239: 9.3812664e-06 | O239: 9.4632366e-06 | P239: 8.6603608e-06 | Q239: 9.4777942e-06 | R239: 8.6603436e-06 | S239: 9.6876807e-06 | T239: 8.67178e-06 | U239: 9.7572732e-06 | V239: 9.1819116e-06 | W239: 1.110641e-05 | X239: 1.1215336e-05 | Y239: 1.3825299e-05 | Z239: 1.4087817e-05 | AA239: 1.4359745e-05 | AB239: 1.4639901e-05 | AC239: 1.4925188e-05 | AD239: 1.5217482e-05 | AE239: 1.5517037e-05 | AF239: 1.5815275e-05 | AG239: 1.6131844e-05 | AH239: 1.6452277e-05 | AI239: 1.6772099e-05 | AJ239: 1.7115539e-05 | AK239: 1.7452266e-05 | AL239: 1.7796702e-05 | AM239: 1.814737e-05 | AN239: 1.8503015e-05 | AO239: 1.8868766e-05 | AP239: 1.9240144e-05 | AQ239: 1.961839e-05 | AR239: 2.0003486e-05 | AS239: 2.0395458e-05 | AT239: 2.0795701e-05 | AU239: 2.120387e-05 | AV239: 2.161877e-05 | AW239: 2.204564e-05
A240: Coût unitaire du capital CB (choc) | B240: UC_K_REHAB_H01_CB_2 | D240: 8.3580815e-06 | E240: 8.4538508e-06 | F240: 6.5740456e-06 | G240: 6.46202e-06 | H240: 6.9722041e-06 | I240: 6.9108297e-06 | J240: 7.0538631e-06 | K240: 7.5241695e-06 | L240: 7.4850678e-06 | M240: 7.2609709e-06 | N240: 7.0409358e-06 | O240: 7.102457e-06 | P240: 6.4998734e-06 | Q240: 7.1133829e-06 | R240: 6.4998605e-06 | S240: 7.2709093e-06 | T240: 6.5084439e-06 | U240: 7.3231407e-06 | V240: 6.8858641e-06 | W240: 6.8670117e-06 | X240: 5.9492137e-06 | Y240: 6.1434672e-06 | Z240: 6.4763982e-06 | AA240: 6.6788078e-06 | AB240: 7.0377393e-06 | AC240: 7.2243134e-06 | AD240: 7.1513819e-06 | AE240: 7.3867808e-06 | AF240: 7.5828682e-06 | AG240: 7.6973588e-06 | AH240: 7.9226484e-06 | AI240: 8.1291361e-06 | AJ240: 8.2496314e-06 | AK240: 8.4596477e-06 | AL240: 8.6860886e-06 | AM240: 8.6810352e-06 | AN240: 8.9755841e-06 | AO240: 9.2315944e-06 | AP240: 9.4862078e-06 | AQ240: 9.7380879e-06 | AR240: 9.9872097e-06 | AS240: 1.0244214e-05 | AT240: 1.0527386e-05 | AU240: 1.0814348e-05 | AV240: 1.1101841e-05 | AW240: 1.1391777e-05
A241: Coût unitaire du capital CC | B241: UC_K_REHAB_H01_CC_2 | D241: 5.8631016e-06 | E241: 5.9302827e-06 | F241: 4.6116202e-06 | G241: 4.5330355e-06 | H241: 4.890924e-06 | I241: 4.8478706e-06 | J241: 4.9482069e-06 | K241: 5.2781216e-06 | L241: 5.2506922e-06 | M241: 5.0934907e-06 | N241: 4.9391385e-06 | O241: 4.9822949e-06 | P241: 4.5595892e-06 | Q241: 4.9899593e-06 | R241: 4.5595802e-06 | S241: 5.1004624e-06 | T241: 4.5656013e-06 | U241: 5.1371021e-06 | V241: 4.8303574e-06 | W241: 4.8171327e-06 | X241: 4.1733075e-06 | Y241: 4.3095742e-06 | Z241: 4.5431216e-06 | AA241: 4.6851097e-06 | AB241: 4.9368962e-06 | AC241: 5.0677759e-06 | AD241: 5.0166152e-06 | AE241: 5.1817449e-06 | AF241: 5.3192981e-06 | AG241: 5.399612e-06 | AH241: 5.5576502e-06 | AI241: 5.702499e-06 | AJ241: 5.7870251e-06 | AK241: 5.9343492e-06 | AL241: 6.093195e-06 | AM241: 6.0896501e-06 | AN241: 6.2962729e-06 | AO241: 6.4758613e-06 | AP241: 6.6544697e-06 | AQ241: 6.8311608e-06 | AR241: 7.0059171e-06 | AS241: 7.186203e-06 | AT241: 7.3848444e-06 | AU241: 7.5861454e-06 | AV241: 7.7878187e-06 | AW241: 7.9912053e-06
A242: Coût unitaire du capital CD | B242: UC_K_REHAB_H01_CD_2 | D242: 3.4620548e-06 | E242: 3.501724e-06 | F242: 2.7230778e-06 | G242: 2.676675e-06 | H242: 2.8880016e-06 | I242: 2.8625793e-06 | J242: 2.9218261e-06 | K242: 3.1166347e-06 | L242: 3.1004382e-06 | M242: 3.0076136e-06 | N242: 2.9164714e-06 | O242: 2.9419545e-06 | P242: 2.6923544e-06 | Q242: 2.9464802e-06 | R242: 2.6923491e-06 | S242: 3.0117302e-06 | T242: 2.6959045e-06 | U242: 3.0333653e-06 | V242: 2.8522382e-06 | W242: 2.8444292e-06 | X242: 2.4642622e-06 | Y242: 2.5447252e-06 | Z242: 2.6826306e-06 | AA242: 2.766472e-06 | AB242: 2.9151474e-06 | AC242: 2.9924294e-06 | AD242: 2.96222e-06 | AE242: 3.0597261e-06 | AF242: 3.1409487e-06 | AG242: 3.1883726e-06 | AH242: 3.2816913e-06 | AI242: 3.3672219e-06 | AJ242: 3.417133e-06 | AK242: 3.5041252e-06 | AL242: 3.5979207e-06 | AM242: 3.5958276e-06 | AN242: 3.7178346e-06 | AO242: 3.8238782e-06 | AP242: 3.9293433e-06 | AQ242: 4.0336762e-06 | AR242: 4.1368665e-06 | AS242: 4.2433221e-06 | AT242: 4.3606162e-06 | AU242: 4.4794808e-06 | AV242: 4.5985652e-06 | AW242: 4.7186613e-06
A243: Coût unitaire du capital CE | B243: UC_K_REHAB_H01_CE_2 | D243: 7.3182617e-06 | E243: 7.4021164e-06 | F243: 5.7561758e-06 | G243: 5.6580872e-06 | H243: 6.1047998e-06 | I243: 6.051061e-06 | J243: 6.1762997e-06 | K243: 6.5880958e-06 | L243: 6.5538588e-06 | M243: 6.3576415e-06 | N243: 6.1649807e-06 | O243: 6.2188481e-06 | P243: 5.6912312e-06 | Q243: 6.2284147e-06 | R243: 5.69122e-06 | S243: 6.3663435e-06 | T243: 5.6987355e-06 | U243: 6.4120768e-06 | V243: 6.0292013e-06 | W243: 6.0126943e-06 | X243: 5.2090785e-06 | Y243: 5.3791652e-06 | Z243: 5.6706766e-06 | AA243: 5.8479046e-06 | AB243: 6.1621819e-06 | AC243: 6.3255445e-06 | AD243: 6.2616863e-06 | AE243: 6.4677995e-06 | AF243: 6.6394919e-06 | AG243: 6.7397388e-06 | AH243: 6.9370004e-06 | AI243: 7.1177992e-06 | AJ243: 7.2233038e-06 | AK243: 7.4071922e-06 | AL243: 7.6054618e-06 | AM243: 7.6010371e-06 | AN243: 7.8589415e-06 | AO243: 8.0831019e-06 | AP243: 8.306039e-06 | AQ243: 8.526583e-06 | AR243: 8.7447119e-06 | AS243: 8.9697429e-06 | AT243: 9.217685e-06 | AU243: 9.4689468e-06 | AV243: 9.7206733e-06 | AW243: 9.9745384e-06
A244: Coût unitaire du capital CF | B244: UC_K_REHAB_H01_CF_2 | D244: 1.1158829e-05 | E244: 1.128669e-05 | F244: 8.7769727e-06 | G244: 8.6274079e-06 | H244: 9.308552e-06 | I244: 9.2266114e-06 | J244: 9.4175744e-06 | K244: 1.0045478e-05 | L244: 9.9932736e-06 | M244: 9.6940829e-06 | N244: 9.4003152e-06 | O244: 9.4824519e-06 | P244: 8.6779458e-06 | Q244: 9.497039e-06 | R244: 8.6779285e-06 | S244: 9.7073517e-06 | T244: 8.6893882e-06 | U244: 9.7770855e-06 | V244: 9.1932799e-06 | W244: 9.1681102e-06 | X244: 7.942763e-06 | Y244: 8.2021098e-06 | Z244: 8.6466042e-06 | AA244: 8.9168401e-06 | AB244: 9.3960476e-06 | AC244: 9.6451417e-06 | AD244: 9.5477713e-06 | AE244: 9.8620511e-06 | AF244: 1.0123846e-05 | AG244: 1.0276702e-05 | AH244: 1.0577485e-05 | AI244: 1.0853166e-05 | AJ244: 1.1014038e-05 | AK244: 1.129443e-05 | AL244: 1.159675e-05 | AM244: 1.1590003e-05 | AN244: 1.1983254e-05 | AO244: 1.2325052e-05 | AP244: 1.2664985e-05 | AQ244: 1.3001268e-05 | AR244: 1.333387e-05 | AS244: 1.3676995e-05 | AT244: 1.4055055e-05 | AU244: 1.4438178e-05 | AV244: 1.4822008e-05 | AW244: 1.52091e-05
A245: Coût unitaire du capital CG | B245: UC_K_REHAB_H01_CG_2 | D245: 1.1136217e-05 | E245: 1.1263819e-05 | F245: 8.7591871e-06 | G245: 8.6099253e-06 | H245: 9.2896891e-06 | I245: 9.2079146e-06 | J245: 9.3984906e-06 | K245: 1.0025122e-05 | L245: 9.9730232e-06 | M245: 9.6744388e-06 | N245: 9.3812664e-06 | O245: 9.4632366e-06 | P245: 8.6603608e-06 | Q245: 9.4777942e-06 | R245: 8.6603436e-06 | S245: 9.6876807e-06 | T245: 8.67178e-06 | U245: 9.7572732e-06 | V245: 9.1746506e-06 | W245: 9.1495319e-06 | X245: 7.9266678e-06 | Y245: 8.1854891e-06 | Z245: 8.6290827e-06 | AA245: 8.898771e-06 | AB245: 9.3770075e-06 | AC245: 9.6255968e-06 | AD245: 9.5284237e-06 | AE245: 9.8420666e-06 | AF245: 1.0103331e-05 | AG245: 1.0255877e-05 | AH245: 1.0556051e-05 | AI245: 1.0831173e-05 | AJ245: 1.0991719e-05 | AK245: 1.1271543e-05 | AL245: 1.157325e-05 | AM245: 1.1566517e-05 | AN245: 1.1958971e-05 | AO245: 1.2300076e-05 | AP245: 1.263932e-05 | AQ245: 1.2974923e-05 | AR245: 1.330685e-05 | AS245: 1.364928e-05 | AT245: 1.4026574e-05 | AU245: 1.440892e-05 | AV245: 1.4791973e-05 | AW245: 1.517828e-05
A246: Subvention à la rénovation CA (M€ constants) | B246: SUB_REHAB_VAL_H01_CA_1 | C246: 0 | D246: 0 | E246: 0 | F246: 0 | G246: 0 | H246: 0 | I246: 0 | J246: 0 | K246: 0 | L246: 0 | M246: 0 | N246: 0 | O246: 0 | P246: 0 | Q246: 0 | R246: 0 | S246: 0 | T246: 0 | U246: 0 | V246: 0 | W246: 0 | X246: 0 | Y246: 0 | Z246: 0 | AA246: 0 | AB246: 0 | AC246: 0 | AD246: 0 | AE246: 0 | AF246: 0 | AG246: 0 | AH246: 0 | AI246: 0 | AJ246: 0 | AK246: 0 | AL246: 0 | AM246: 0 | AN246: 0 | AO246: 0 | AP246: 0 | AQ246: 0 | AR246: 0 | AS246: 0 | AT246: 0 | AU246: 0 | AV246: 0 | AW246: 0
A247: Subvention à la rénovation CB (M€ constants) | B247: SUB_REHAB_VAL_H01_CB_1 | C247: 0 | D247: 0 | E247: 0 | F247: 0.00013503238 | G247: 152.98778 | H247: 216.03471 | I247: 218.29437 | J247: 259.75154 | K247: 190.8707 | L247: 228.87427 | M247: 320.55608 | N247: 481.00491 | O247: 514.52687 | P247: 735.28336 | Q247: 698.84213 | R247: 1039.8408 | S247: 973.97649 | T247: 1508.9163 | U247: 1402.1665 | V247: 1510.6607 | W247: 910.41561 | X247: 1002.8794 | Y247: 0 | Z247: 0 | AA247: 0 | AB247: 0 | AC247: 0 | AD247: 0 | AE247: 0 | AF247: 0 | AG247: 0 | AH247: 0 | AI247: 0 | AJ247: 0 | AK247: 0 | AL247: 0 | AM247: 0 | AN247: 0 | AO247: 0 | AP247: 0 | AQ247: 0 | AR247: 0 | AS247: 0 | AT247: 0 | AU247: 0 | AV247: 0 | AW247: 0
A248: Subvention à la rénovation CC (M€ constants) | B248: SUB_REHAB_VAL_H01_CC_1 | C248: 0 | D248: 0 | E248: 0 | F248: 0.00067244915 | G248: 16.859833 | H248: 36.506958 | I248: 61.94118 | J248: 114.5842 | K248: 108.41514 | L248: 146.45529 | M248: 209.66858 | N248: 302.19969 | O248: 294.32749 | P248: 428.48347 | Q248: 412.70738 | R248: 683.5767 | S248: 600.60743 | T248: 902.80566 | U248: 779.90457 | V248: 839.94526 | W248: 459.56035 | X248: 492.85905 | Y248: 0 | Z248: 0 | AA248: 0 | AB248: 0 | AC248: 0 | AD248: 0 | AE248: 0 | AF248: 0 | AG248: 0 | AH248: 0 | AI248: 0 | AJ248: 0 | AK248: 0 | AL248: 0 | AM248: 0 | AN248: 0 | AO248: 0 | AP248: 0 | AQ248: 0 | AR248: 0 | AS248: 0 | AT248: 0 | AU248: 0 | AV248: 0 | AW248: 0
A249: Subvention à la rénovation CD (M€ constants) | B249: SUB_REHAB_VAL_H01_CD_1 | C249: 0 | D249: 0 | E249: 0 | F249: 78.288711 | G249: 90.988067 | H249: 78.762245 | I249: 56.112706 | J249: 72.456152 | K249: 65.097583 | L249: 90.953034 | M249: 133.21418 | N249: 188.35731 | O249: 158.3237 | P249: 228.7214 | Q249: 254.17437 | R249: 530.68777 | S249: 526.00171 | T249: 821.68192 | U249: 751.16489 | V249: 782.10284 | W249: 409.88359 | X249: 390.14522 | Y249: 0 | Z249: 0 | AA249: 0 | AB249: 0 | AC249: 0 | AD249: 0 | AE249: 0 | AF249: 0 | AG249: 0 | AH249: 0 | AI249: 0 | AJ249: 0 | AK249: 0 | AL249: 0 | AM249: 0 | AN249: 0 | AO249: 0 | AP249: 0 | AQ249: 0 | AR249: 0 | AS249: 0 | AT249: 0 | AU249: 0 | AV249: 0 | AW249: 0
A250: Subvention à la rénovation CE (M€ constants) | B250: SUB_REHAB_VAL_H01_CE_1 | C250: 0 | D250: 0 | E250: 0 | F250: 297.15475 | G250: 331.79758 | H250: 290.38186 | I250: 166.69439 | J250: 189.0671 | K250: 174.70294 | L250: 247.09012 | M250: 317.01085 | N250: 335.84459 | O250: 283.34712 | P250: 348.51186 | Q250: 438.51122 | R250: 1035.816 | S250: 981.23654 | T250: 1492.993 | U250: 1274.314 | V250: 1282.8503 | W250: 660.73376 | X250: 647.44927 | Y250: 0 | Z250: 0 | AA250: 0 | AB250: 0 | AC250: 0 | AD250: 0 | AE250: 0 | AF250: 0 | AG250: 0 | AH250: 0 | AI250: 0 | AJ250: 0 | AK250: 0 | AL250: 0 | AM250: 0 | AN250: 0 | AO250: 0 | AP250: 0 | AQ250: 0 | AR250: 0 | AS250: 0 | AT250: 0 | AU250: 0 | AV250: 0 | AW250: 0
A251: Subvention à la rénovation CF (M€ constants) | B251: SUB_REHAB_VAL_H01_CF_1 | C251: 0 | D251: 0 | E251: 0 | F251: 268.22371 | G251: 312.32736 | H251: 289.01243 | I251: 179.08071 | J251: 212.17465 | K251: 194.93855 | L251: 271.23808 | M251: 347.84121 | N251: 381.54141 | O251: 329.40342 | P251: 402.52954 | Q251: 460.54204 | R251: 997.72536 | S251: 914.5752 | T251: 1386.5086 | U251: 1168.9478 | V251: 1185.7883 | W251: 620.22038 | X251: 607.74827 | Y251: 0 | Z251: 0 | AA251: 0 | AB251: 0 | AC251: 0 | AD251: 0 | AE251: 0 | AF251: 0 | AG251: 0 | AH251: 0 | AI251: 0 | AJ251: 0 | AK251: 0 | AL251: 0 | AM251: 0 | AN251: 0 | AO251: 0 | AP251: 0 | AQ251: 0 | AR251: 0 | AS251: 0 | AT251: 0 | AU251: 0 | AV251: 0 | AW251: 0
A252: Subvention à la rénovation CG (M€ constants) | B252: SUB_REHAB_VAL_H01_CG_1 | C252: 0 | D252: 0 | E252: 0 | F252: 336.56001 | G252: 361.23348 | H252: 320.25701 | I252: 238.23679 | J252: 258.71242 | K252: 194.54666 | L252: 228.30981 | M252: 283.63452 | N252: 342.37766 | O252: 264.27333 | P252: 289.29728 | Q252: 271.05429 | R252: 469.44721 | S252: 421.48574 | T252: 590.36133 | U252: 499.00247 | V252: 477.74723 | W252: 245.49103 | X252: 231.34957 | Y252: 0 | Z252: 0 | AA252: 0 | AB252: 0 | AC252: 0 | AD252: 0 | AE252: 0 | AF252: 0 | AG252: 0 | AH252: 0 | AI252: 0 | AJ252: 0 | AK252: 0 | AL252: 0 | AM252: 0 | AN252: 0 | AO252: 0 | AP252: 0 | AQ252: 0 | AR252: 0 | AS252: 0 | AT252: 0 | AU252: 0 | AV252: 0 | AW252: 0
A253: Subvention à la rénovation CA (M€ constants) choc | B253: SUB_REHAB_VAL_H01_CA_2 | C253: 0 | D253: 0 | E253: 0 | F253: 0 | G253: 0 | H253: 0 | I253: 0 | J253: 0 | K253: 0 | L253: 0 | M253: 0 | N253: 0 | O253: 0 | P253: 0 | Q253: 0 | R253: 0 | S253: 0 | T253: 0 | U253: 0 | V253: 0 | W253: 0 | X253: 0 | Y253: 0 | Z253: 0 | AA253: 0 | AB253: 0 | AC253: 0 | AD253: 0 | AE253: 0 | AF253: 0 | AG253: 0 | AH253: 0 | AI253: 0 | AJ253: 0 | AK253: 0 | AL253: 0 | AM253: 0 | AN253: 0 | AO253: 0 | AP253: 0 | AQ253: 0 | AR253: 0 | AS253: 0 | AT253: 0 | AU253: 0 | AV253: 0 | AW253: 0
A254: Subvention à la rénovation CB (M€ constants) | B254: SUB_REHAB_VAL_H01_CB_2 | C254: 0 | D254: 0 | E254: 0 | F254: 0.00013503238 | G254: 152.98778 | H254: 216.03471 | I254: 218.29437 | J254: 259.75154 | K254: 190.8707 | L254: 228.87427 | M254: 320.55608 | N254: 481.00491 | O254: 514.52687 | P254: 735.28336 | Q254: 698.84213 | R254: 1039.8408 | S254: 973.97649 | T254: 1508.9163 | U254: 1402.1665 | V254: 1513.3814 | W254: 1744.5877 | X254: 2583.4226 | Y254: 2908.9114 | Z254: 3149.0737 | AA254: 3440.0106 | AB254: 3517.5056 | AC254: 3688.4624 | AD254: 4088.0479 | AE254: 4200.6743 | AF254: 4329.1027 | AG254: 4523.4725 | AH254: 4598.391 | AI254: 4675.3336 | AJ254: 4823.4376 | AK254: 4871.1233 | AL254: 4904.0546 | AM254: 5184.5207 | AN254: 5199.9082 | AO254: 5251.26 | AP254: 5296.1899 | AQ254: 5328.4593 | AR254: 5350.547 | AS254: 5357.2737 | AT254: 5346.962 | AU254: 5345.7876 | AV254: 5356.0865 | AW254: 5376.1027
A255: Subvention à la rénovation CC (M€ constants) | B255: SUB_REHAB_VAL_H01_CC_2 | C255: 0 | D255: 0 | E255: 0 | F255: 0.00067244915 | G255: 16.859833 | H255: 36.506958 | I255: 61.94118 | J255: 114.5842 | K255: 108.41514 | L255: 146.45529 | M255: 209.66858 | N255: 302.19969 | O255: 294.32749 | P255: 428.48347 | Q255: 412.70738 | R255: 683.5767 | S255: 600.60743 | T255: 902.80566 | U255: 779.90457 | V255: 839.58911 | W255: 983.59525 | X255: 1629.0263 | Y255: 1932.14 | Z255: 2010.6501 | AA255: 2084.2714 | AB255: 2048.9128 | AC255: 2117.9787 | AD255: 2385.3209 | AE255: 2447.0878 | AF255: 2476.6594 | AG255: 2564.4335 | AH255: 2588.2818 | AI255: 2587.5929 | AJ255: 2637.7091 | AK255: 2649.1643 | AL255: 2651.6207 | AM255: 2837.9746 | AN255: 2863.5044 | AO255: 2835.2522 | AP255: 2799.9463 | AQ255: 2763.4282 | AR255: 2726.9108 | AS255: 2707.5708 | AT255: 2720.5605 | AU255: 2737.6491 | AV255: 2757.7768 | AW255: 2778.1704
A256: Subvention à la rénovation CD (M€ constants) | B256: SUB_REHAB_VAL_H01_CD_2 | C256: 0 | D256: 0 | E256: 0 | F256: 78.288711 | G256: 90.988067 | H256: 78.762245 | I256: 56.112706 | J256: 72.456152 | K256: 65.097583 | L256: 90.953034 | M256: 133.21418 | N256: 188.35731 | O256: 158.3237 | P256: 228.7214 | Q256: 254.17437 | R256: 530.68777 | S256: 526.00171 | T256: 821.68192 | U256: 751.16489 | V256: 781.02711 | W256: 895.76914 | X256: 1485.8399 | Y256: 1839.0477 | Z256: 1852.1284 | AA256: 1812.9359 | AB256: 1674.2122 | AC256: 1614.3209 | AD256: 1720.3057 | AE256: 1687.475 | AF256: 1605.9963 | AG256: 1572.1938 | AH256: 1511.3394 | AI256: 1434.1142 | AJ256: 1391.5568 | AK256: 1338.7482 | AL256: 1282.2719 | AM256: 1327.07 | AN256: 1311.1782 | AO256: 1249.0987 | AP256: 1187.686 | AQ256: 1132.2423 | AR256: 1090.336 | AS256: 1053.6552 | AT256: 1032.5302 | AU256: 1015.0735 | AV256: 999.13124 | AW256: 983.17381
A257: Subvention à la rénovation CE (M€ constants) | B257: SUB_REHAB_VAL_H01_CE_2 | C257: 0 | D257: 0 | E257: 0 | F257: 297.15475 | G257: 331.79758 | H257: 290.38186 | I257: 166.69439 | J257: 189.0671 | K257: 174.70294 | L257: 247.09012 | M257: 317.01085 | N257: 335.84459 | O257: 283.34712 | P257: 348.51186 | Q257: 438.51122 | R257: 1035.816 | S257: 981.23654 | T257: 1492.993 | U257: 1274.314 | V257: 1277.2082 | W257: 1360.7707 | X257: 2016.3721 | Y257: 2156.003 | Z257: 1978.1596 | AA257: 1807.3402 | AB257: 1584.4254 | AC257: 1522.7135 | AD257: 1609.3769 | AE257: 1515.1364 | AF257: 1391.9361 | AG257: 1305.3704 | AH257: 1200.4554 | AI257: 1103.3317 | AJ257: 1033.3757 | AK257: 950.0233 | AL257: 884.12163 | AM257: 924.64158 | AN257: 909.89965 | AO257: 862.77345 | AP257: 812.04866 | AQ257: 760.24701 | AR257: 707.94853 | AS257: 671.79831 | AT257: 682.01945 | AU257: 703.58663 | AV257: 723.04758 | AW257: 736.84006
... A469: Taux d'intérêt directeur | B469: R_DIR_2 | C469: 0.02637643 | D469: 0.02637643 | E469: 0.013276695 | F469: 0.0096219735 | G469: 0.020462196 | H469: 0.0078342748 | I469: 0.015112648 | J469: 0.014958585 | K469: 0.01552575 | L469: 0.013503432 | M469: 0.016129302 | N469: 0.013312163 | O469: 0.013202983 | P469: 0.020584777 | Q469: 0.026723349 | R469: 0.024559854 | S469: 0.026213344 | T469: 0.026268186 | U469: 0.026752761 | V469: 0.026713653 | W469: 0.027659423 | X469: 0.027662767 | Y469: 0.026055448 | Z469: 0.02602458 | AA469: 0.026311389 | AB469: 0.027418035 | AC469: 0.027664483 | AD469: 0.027130643 | AE469: 0.026762764 | AF469: 0.0267073 | AG469: 0.026804054 | AH469: 0.026672382 | AI469: 0.026643006 | AJ469: 0.026652602 | AK469: 0.026921291 | AL469: 0.026874944 | AM469: 0.027136271 | AN469: 0.02701082 | AO469: 0.027155187 | AP469: 0.027251786 | AQ469: 0.027215843 | AR469: 0.027219554 | AS469: 0.027309751 | AT469: 0.027270024 | AU469: 0.027184411 | AV469: 0.027097897 | AW469: 0.027128778
B470: TS_2 | C470: 0.043327542 | D470: 0.043327542 | E470: 0.059872177 | F470: 0.071907338 | G470: 0.080391001 | H470: 0.061875943 | I470: 0.034763886 | J470: 0.039273311 | K470: 0.051220228 | L470: 0.044855211 | M470: 0.039804271 | N470: 0.043244748 | O470: 0.041207826 | P470: 0.037947118 | Q470: 0.040783076 | R470: 0.041889179 | S470: 0.055257917 | T470: 0.060711416 | U470: 0.06692993 | V470: 0.062430978 | W470: 0.059547477 | X470: 0.061772863 | Y470: 0.066182449 | Z470: 0.067406879 | AA470: 0.069921674 | AB470: 0.073316566 | AC470: 0.076456752 | AD470: 0.077955901 | AE470: 0.078594258 | AF470: 0.080116707 | AG470: 0.082108762 | AH470: 0.083887697 | AI470: 0.085907874 | AJ470: 0.088796714 | AK470: 0.091233513 | AL470: 0.094347995 | AM470: 0.097158824 | AN470: 0.099261099 | AO470: 0.10086867 | AP470: 0.10280785 | AQ470: 0.10447431 | AR470: 0.10595161 | AS470: 0.10748534 | AT470: 0.10890689 | AU470: 0.11037683 | AV470: 0.11183009 | AW470: 0.11299548
B471: TS_H01_2 | C471: 0.043327542 | D471: 0.043327542 | E471: 0.059872177 | F471: 0.071907338 | G471: 0.080391001 | H471: 0.061875943 | I471: 0.034763886 | J471: 0.039273311 | K471: 0.051220228 | L471: 0.044855211 | M471: 0.039804271 | N471: 0.043244748 | O471: 0.041207826 | P471: 0.037947118 | Q471: 0.040783076 | R471: 0.041889179 | S471: 0.055257917 | T471: 0.060711416 | U471: 0.06692993 | V471: 0.062430978 | W471: 0.059547477 | X471: 0.061772863 | Y471: 0.066182449 | Z471: 0.067406879 | AA471: 0.069921674 | AB471: 0.073316566 | AC471: 0.076456752 | AD471: 0.077955901 | AE471: 0.078594258 | AF471: 0.080116707 | AG471: 0.082108762 | AH471: 0.083887697 | AI471: 0.085907874 | AJ471: 0.088796714 | AK471: 0.091233513 | AL471: 0.094347995 | AM471: 0.097158824 | AN471: 0.099261099 | AO471: 0.10086867 | AP471: 0.10280785 | AQ471: 0.10447431 | AR471: 0.10595161 | AS471: 0.10748534 | AT471: 0.10890689 | AU471: 0.11037683 | AV471: 0.11183009 | AW471: 0.11299548
B472: DISPINC_VAL_H01_2 | C472: 1079422.7 | D472: 1118688.3 | E472: 1148029.4 | F472: 1164739.4 | G472: 1195330.4 | H472: 1175909.3 | I472: 1164857.4 | J472: 1188821.6 | K472: 1209901.7 | L472: 1215912.5 | M472: 1233227.4 | N472: 1254943.4 | O472: 1278775.5 | P472: 1317136.4 | Q472: 1366128.4 | R472: 1415860.2 | S472: 1472585.8 | T472: 1516787.5 | U472: 1574903.2 | V472: 1628302 | W472: 1682098.4 | X472: 1728742.5 | Y472: 1779806.2 | Z472: 1832153.2 | AA472: 1890382 | AB472: 1950485.4 | AC472: 2008700.5 | AD472: 2071736.2 | AE472: 2139014.9 | AF472: 2208667.1 | AG472: 2280925.5 | AH472: 2355061.3 | AI472: 2434732.1 | AJ472: 2522477 | AK472: 2611609.5 | AL472: 2707994.9 | AM472: 2804510.2 | AN472: 2909207.5 | AO472: 3016781 | AP472: 3128682.5 | AQ472: 3243796.7 | AR472: 3362110 | AS472: 3480630.2 | AT472: 3601416 | AU472: 3728001.8 | AV472: 3859624.3 | AW472: 3995963.3
B473: DISPINC_AI_VAL_H01_2 | C473: 1226094.8 | D473: 1270695.8 | E473: 1304023.8 | F473: 1328960 | G473: 1369991.9 | H473: 1353956.9 | I473: 1347772.3 | J473: 1381927.6 | K473: 1413118.6 | L473: 1426218.4 | M473: 1446051.5 | N473: 1472687 | O473: 1500976.7 | P473: 1546623.6 | Q473: 1605310.6 | R473: 1662475.8 | S473: 1730997.1 | T473: 1778158.3 | U473: 1847853.8 | V473: 1910081.8 | W473: 1972574.8 | X473: 2026244.5 | Y473: 2083491.2 | Z473: 2144130.6 | AA473: 2211944.2 | AB473: 2282059 | AC473: 2349925.2 | AD473: 2422079.2 | AE473: 2500526.2 | AF473: 2582089.8 | AG473: 2666812.1 | AH473: 2753800.6 | AI473: 2847335.5 | AJ473: 2950395.3 | AK473: 3055102.5 | AL473: 3168320.2 | AM473: 3281520.8 | AN473: 3404298 | AO473: 3530623.6 | AP473: 3662069.7 | AQ473: 3797312.3 | AR473: 3936247 | AS473: 4075436.7 | AT473: 4217175 | AU473: 4365692.1 | AV473: 4520122 | AW473: 4680122.5
B474: IR_VAL_H01_2 | C474: 130354.82 | D474: 135096.67 | E474: 138640 | F474: 147514.56 | G474: 157549.07 | H474: 161120.87 | I474: 165776 | J474: 175504.8 | K474: 185118.54 | L474: 192539.49 | M474: 195216.95 | N474: 198812.74 | O474: 202631.86 | P474: 208794.18 | Q474: 216716.93 | R474: 224434.23 | S474: 233684.61 | T474: 240051.37 | U474: 249460.26 | V474: 257861.05 | W474: 266297.6 | X474: 273543.01 | Y474: 281271.31 | Z474: 289457.63 | AA474: 298612.47 | AB474: 308077.97 | AC474: 317239.9 | AD474: 326980.69 | AE474: 337571.04 | AF474: 348582.12 | AG474: 360019.63 | AH474: 371763.08 | AI474: 384390.29 | AJ474: 398303.36 | AK474: 412438.84 | AL474: 427723.23 | AM474: 443005.31 | AN474: 459580.23 | AO474: 476634.19 | AP474: 494379.41 | AQ474: 512637.16 | AR474: 531393.35 | AS474: 550183.95 | AT474: 569318.63 | AU474: 589368.43 | AV474: 610216.47 | AW474: 631816.53
B475: AIC_VAL_H01_2 | C475: 16317.279 | D475: 16910.844 | E475: 17354.384 | F475: 17686.243 | G475: 18232.309 | H475: 18018.91 | I475: 17936.604 | J475: 18391.154 | K475: 18806.255 | L475: 18980.591 | M475: 19244.536 | N475: 19599.01 | O475: 19975.499 | P475: 20582.983 | Q475: 21364.009 | R475: 22124.783 | S475: 23036.687 | T475: 23664.325 | U475: 24591.855 | V475: 25420.007 | W475: 26251.684 | X475: 26965.938 | Y475: 27727.796 | Z475: 28534.805 | AA475: 29437.292 | AB475: 30370.403 | AC475: 31273.589 | AD475: 32233.838 | AE475: 33277.838 | AF475: 34363.312 | AG475: 35490.825 | AH475: 36648.498 | AI475: 37893.291 | AJ475: 39264.845 | AK475: 40658.324 | AL475: 42165.063 | AM475: 43671.574 | AN475: 45305.534 | AO475: 46986.718 | AP475: 48736.046 | AQ475: 50535.899 | AR475: 52384.889 | AS475: 54237.271 | AT475: 56123.573 | AU475: 58100.087 | AV475: 60155.292 | AW475: 62284.632
B476: SUB_AUTO_VAL_2 | C476: 0 | D476: 0 | E476: 0 | F476: 0 | G476: -146.2765 | H476: -138.78175 | I476: -122.74094 | J476: -61.286666 | K476: 29.918918 | L476: 247.37512 | M476: 289.78912 | N476: -1160.0307 | O476: -1101.4157 | P476: -1745.7829 | Q476: -2369.1178 | R476: -1952.2962 | S476: -3562.523 | T476: -1242.8345 | U476: -1596.0485 | V476: -1325.7562 | W476: -1351.1928 | X476: -1418.2835 | Y476: -841.469 | Z476: -435.98528 | AA476: -48.588723 | AB476: 331.4578 | AC476: 676.5563 | AD476: 1128.8782 | AE476: 1475.5475 | AF476: 1705.0609 | AG476: 1840.9775 | AH476: 1912.0682 | AI476: 1996.3501 | AJ476: 2043.6874 | AK476: 2058.3936 | AL476: 2064.1997 | AM476: 2054.5938 | AN476: 2041.082 | AO476: 2023.5557 | AP476: 2004.3111 | AQ476: 1982.743 | AR476: 2022.6276 | AS476: 2024.0659 | AT476: 2015.0342 | AU476: 2003.1116 | AV476: 1986.4273 | AW476: 1946.0858
B477: SUB_RENOV_VAL_2 | C477: 0 | D477: 0 | E477: 0 | F477: 980.22799 | G477: 1266.1941 | H477: 1230.9552 | I477: 920.36014 | J477: 851.25212 | K477: 677.9779 | L477: 966.80417 | M477: 1347.561 | N477: 1828.2302 | O477: 1507.5111 | P477: 1635.7929 | Q477: 1267.8746 | R477: 1895.6705 | S477: 1872.4976 | T477: 3587.662 | U477: 2697.5833 | V477: 2827.0184 | W477: 3424.0927 | X477: 4425.2491 | Y477: 6155.5552 | Z477: 6451.0643 | AA477: 6536.103 | AB477: 6543.3099 | AC477: 6612.2186 | AD477: 7742.6207 | AE477: 7862.0172 | AF477: 7817.6729 | AG477: 7782.8774 | AH477: 7760.1995 | AI477: 7683.8235 | AJ477: 7606.2563 | AK477: 7545.7447 | AL477: 7498.8148 | AM477: 7611.7128 | AN477: 7754.1754 | AO477: 7754.7318 | AP477: 7723.9366 | AQ477: 7674.7371 | AR477: 7618.5843 | AS477: 7590.6945 | AT477: 7668.1474 | AU477: 7775.1354 | AV477: 7887.6496 | AW477: 7995.9634
B478: EXP_H01_2 | C478: 1074373.2 | D478: 1091622.6 | E478: 1093371.1 | F478: 1120073.4 | G478: 1121282.5 | H478: 1118384.9 | I478: 1132035.4 | J478: 1139627 | K478: 1132388.3 | L478: 1134062.9 | M478: 1143982.9 | N478: 1152299.8 | O478: 1163945.3 | P478: 1185651.3 | Q478: 1198999.1 | R478: 1219785.2 | S478: 1225569 | T478: 1232918.5 | U478: 1245011.5 | V478: 1268265.4 | W478: 1287655.9 | X478: 1296475.5 | Y478: 1303790.8 | Z478: 1314930.3 | AA478: 1326825.6 | AB478: 1335406.8 | AC478: 1342182.1 | AD478: 1354591.6 | AE478: 1369190.1 | AF478: 1382902.5 | AG478: 1396274.3 | AH478: 1409725.3 | AI478: 1424790.2 | AJ478: 1441821.5 | AK478: 1458239 | AL478: 1476109.6 | AM478: 1493143.9 | AN478: 1513597.4 | AO478: 1534385.5 | AP478: 1554849.5 | AQ478: 1575629.8 | AR478: 1596514.1 | AS478: 1615584.2 | AT478: 1634445.2 | AU478: 1654332.1 | AV478: 1674901.1 | AW478: 1696198.5
B479: EXP_11_H01_2 | C479: 158.85802 | D479: 161.40853 | E479: 160.90834 | F479: 153.09755 | G479: 144.51275 | H479: 149.96616 | I479: 145.83813 | J479: 141.7114 | K479: 131.01543 | L479: 132.28842 | M479: 133.58498 | N479: 132.27532 | O479: 132.27532 | P479: 133.61117 | Q479: 128.37123 | R479: 119.56248 | S479: 121.1351 | T479: 122.61805 | U479: 124.17858 | V479: 126.52186 | W479: 127.68283 | X479: 128.31288 | Y479: 130.44736 | Z479: 132.65466 | AA479: 134.77143 | AB479: 136.54409 | AC479: 138.02966 | AD479: 139.88835 | AE479: 142.11494 | AF479: 144.32756 | AG479: 146.53077 | AH479: 148.72842 | AI479: 151.04854 | AJ479: 153.68712 | AK479: 156.26984 | AL479: 159.03003 | AM479: 161.6801 | AN479: 164.61889 | AO479: 167.68081 | AP479: 170.71735 | AQ479: 173.75457 | AR479: 176.69306 | AS479: 179.47495 | AT479: 182.19394 | AU479: 185.05038 | AV479: 188.00078 | AW479: 191.00438
B480: EXP_12_H01_2 | C480: 173659.52 | D480: 176447.68 | E480: 175900.88 | F480: 183029.1 | G480: 182209.1 | H480: 179009.91 | I480: 181991.78 | J480: 184068.31 | K480: 182440.83 | L480: 182677.99 | M480: 186584.3 | N480: 191757.35 | O480: 194068.08 | P480: 197772.58 | Q480: 197761.43 | R480: 202652.04 | S480: 205317.54 | T480: 207830 | U480: 210472.53 | V480: 214443.47 | W480: 216405.97 | X480: 217278.92 | Y480: 220571.99 | Z480: 223902.04 | AA480: 227010.8 | AB480: 229486.49 | AC480: 231435.05 | AD480: 233966.7 | AE480: 237058.1 | AF480: 240112.27 | AG480: 243135.04 | AH480: 246131.96 | AI480: 249309.67 | AJ480: 252984.13 | AK480: 256548.89 | AL480: 260380.5 | AM480: 264014.14 | AN480: 268094.33 | AO480: 272343.01 | AP480: 276528.67 | AQ480: 280690.49 | AR480: 284669.08 | AS480: 288376.29 | AT480: 291968.71 | AU480: 295753.09 | AV480: 299663.32 | AW480: 303636.13
B481: EXP_13_H01_2 | C481: 87751.619 | D481: 89160.499 | E481: 90592 | F481: 94648.266 | G481: 95762.725 | H481: 91338.84 | I481: 92842.624 | J481: 93318.269 | K481: 92489.469 | L481: 90798.539 | M481: 90214.103 | N481: 89458.218 | O481: 89952.851 | P481: 90856.473 | Q481: 91823.24 | R481: 93114.18 | S481: 94355.417 | T481: 95632.437 | U481: 95327.243 | V481: 99149.942 | W481: 98082.54 | X481: 97536.777 | Y481: 96371.544 | Z481: 93950.747 | AA481: 90813.506 | AB481: 86803.179 | AC481: 82985.253 | AD481: 81943.098 | AE481: 80030.126 | AF481: 77739.654 | AG481: 75444.59 | AH481: 73484.737 | AI481: 70914.969 | AJ481: 68136.026 | AK481: 65759.283 | AL481: 63414.748 | AM481: 61492.837 | AN481: 60632.846 | AO481: 59215.668 | AP481: 57673.908 | AQ481: 56477.073 | AR481: 54974.718 | AS481: 53624.195 | AT481: 52777.337 | AU481: 51876.172 | AV481: 50991.942 | AW481: 51001.745
... B591: AUTO_1 | C591: 30998.43 | D591: 31496.12 | E591: 32001.8 | F591: 32688.379 | G591: 33314.795 | H591: 34142.845 | I591: 34863.837 | J591: 35489.149 | K591: 35731.314 | L591: 35839.916 | M591: 35948.064 | N591: 35911.307 | O591: 35978.501 | P591: 36321.204 | Q591: 36708.886 | R591: 37113.744 | S591: 37189.731 | T591: 37045.547 | U591: 36737.401 | V591: 36371.236 | W591: 36012.417 | X591: 35644.916 | Y591: 35503.942 | Z591: 35454.932 | AA591: 35464.857 | AB591: 35507.348 | AC591: 35565.6 | AD591: 35634.676 | AE591: 35606.128 | AF591: 35542.571 | AG591: 35466.84 | AH591: 35295.136 | AI591: 35183.574 | AJ591: 35103.126 | AK591: 35039.261 | AL591: 34986.172 | AM591: 34939.117 | AN591: 34869.918 | AO591: 34789.196 | AP591: 34703.993 | AQ591: 34616.287 | AR591: 34527.139 | AS591: 34427.191 | AT591: 34322.813 | AU591: 34216.317 | AV591: 34108.937 | AW591: 34002.514
B592: RF_NET_1 | E592: 279982.11 | F592: 265240.2 | G592: 276779.62 | H592: 229146.13 | I592: 234335.61 | J592: 270619.14 | K592: 294932.47 | L592: 284779.32 | M592: 66096.378 | N592: 290213 | O592: 296652.71 | P592: 300982.04 | Q592: 317318.37 | R592: 319527.16 | S592: 322790.29 | T592: 315557 | U592: 333777.6 | V592: 331130.36 | W592: 335108.31 | X592: 331708.06 | Y592: 326166.23 | Z592: 322426.01 | AA592: 325930.58 | AB592: 334565.59 | AC592: 316303.88 | AD592: 329310.68 | AE592: 329669.67 | AF592: 332405.53 | AG592: 335247.81 | AH592: 338120.05 | AI592: 342167.34 | AJ592: 346430.9 | AK592: 354368.55 | AL592: 351837.43 | AM592: 357123.92 | AN592: 361694.34 | AO592: 365121.3 | AP592: 369858.05 | AQ592: 374007.15 | AR592: 371799.43 | AS592: 386796.3 | AT592: 392262.32 | AU592: 396605.31 | AV592: 401069.58 | AW592: 405472.15
B593: RF_NET_01_1 | E593: 10118.546 | F593: 9656.0874 | G593: 9452.3618 | H593: 8419.282 | I593: 9305.1645 | J593: 10619.3 | K593: 9647.7768 | L593: 10285.614 | M593: 9363.93 | N593: 10935.046 | O593: 10561.533 | P593: 9360.2798 | Q593: 9906.703 | R593: 9563.2001 | S593: 9600.3251 | T593: 9723.2154 | U593: 10026.081 | V593: 10157.66 | W593: 10407.193 | X593: 10541.749 | Y593: 10594.544 | Z593: 10541.441 | AA593: 10547.647 | AB593: 10579.253 | AC593: 10607.267 | AD593: 10627.414 | AE593: 10707.037 | AF593: 10824.575 | AG593: 10935.287 | AH593: 11045.805 | AI593: 11190.287 | AJ593: 11316.29 | AK593: 11456.483 | AL593: 11615.541 | AM593: 11783.047 | AN593: 11952.888 | AO593: 12119.49 | AP593: 12298.552 | AQ593: 12479.479 | AR593: 12665.145 | AS593: 12845.461 | AT593: 13026.851 | AU593: 13205.756 | AV593: 13385.186 | AW593: 13565.152
B594: RF_NET_02_1 | E594: 5955.092 | F594: 5232.761 | G594: 5584.9951 | H594: 4388.2907 | I594: 5981.8216 | J594: 5883.1132 | K594: 6442.9196 | L594: 5670.4435 | M594: 6014.404 | N594: 6216.1801 | O594: 6784.9121 | P594: 6669.5641 | Q594: 6489.0761 | R594: 6479.8961 | S594: 5165.5709 | T594: 5283.1371 | U594: 5413.5905 | V594: 5422.4741 | W594: 5492.2725 | X594: 5406.1227 | Y594: 5250.2524 | Z594: 5013.5238 | AA594: 4771.5661 | AB594: 4499.009 | AC594: 4166.0745 | AD594: 3753.4341 | AE594: 3828.5807 | AF594: 3929.1028 | AG594: 4027.2375 | AH594: 4125.3483 | AI594: 4244.3964 | AJ594: 4352.3538 | AK594: 4469.1621 | AL594: 4598.5147 | AM594: 4736.488 | AN594: 4880.0818 | AO594: 5031.3086 | AP594: 5192.3052 | AQ594: 5358.7234 | AR594: 5532.0581 | AS594: 5708.1209 | AT594: 5890.092 | AU594: 6074.8042 | AV594: 6264.3659 | AW594: 6458.4946
B595: RF_NET_03_1 | E595: -1066.0862 | F595: -1369.9617 | G595: -2230.1179 | H595: -2391.5803 | I595: -2337.5863 | J595: -340.39926 | K595: -1622.1687 | L595: -1622.2828 | M595: -1998.1602 | N595: -2228.6118 | O595: -1885.2583 | P595: -1681.9204 | Q595: -1948.6707 | R595: -1839.8234 | S595: -2555.8656 | T595: -3236.5719 | U595: -2580.3934 | V595: -2851.8587 | W595: -2874.3258 | X595: -3398.5343 | Y595: -3975.2737 | Z595: -4635.4862 | AA595: -5256.2872 | AB595: -5886.8298 | AC595: -6453.73 | AD595: -6753.0857 | AE595: -6817.6138 | AF595: -6858.7761 | AG595: -6901.2606 | AH595: -6943.3454 | AI595: -6983.7874 | AJ595: -7024.3863 | AK595: -7066.282 | AL595: -7102.9553 | AM595: -7135.6909 | AN595: -7163.2408 | AO595: -7184.3968 | AP595: -7192.2948 | AQ595: -7191.6868 | AR595: -7177.2585 | AS595: -7149.6766 | AT595: -7105.2402 | AU595: -7045.077 | AV595: -6964.9012 | AW595: -6862.3555
B596: RF_NET_04_1 | E596: -362.61321 | F596: -403.32144 | G596: -437.12833 | H596: -518.61834 | I596: -483.16022 | J596: -266.87703 | K596: -99.051711 | L596: -458.51946 | M596: -462.49409 | N596: -357.59917 | O596: -369.95576 | P596: -296.26785 | Q596: -337.65263 | R596: -422.11597 | S596: -468.58861 | T596: -494.28192 | U596: -472.78437 | V596: -508.53177 | W596: -534.59512 | X596: -355.73304 | Y596: 17.237128 | Z596: 259.61257 | AA596: 523.72053 | AB596: 826.20167 | AC596: 1173.2865 | AD596: 1574.2302 | AE596: 1553.1053 | AF596: 1547.0716 | AG596: 1546.5898 | AH596: 1551.083 | AI596: 1562.4586 | AJ596: 1577.6379 | AK596: 1595.2912 | AL596: 1616.8087 | AM596: 1640.6077 | AN596: 1665.7005 | AO596: 1701.8463 | AP596: 1742.6158 | AQ596: 1784.1208 | AR596: 1827.8152 | AS596: 1871.4705 | AT596: 1909.5486 | AU596: 1947.5637 | AV596: 1986.5188 | AW596: 2026.2756
B597: RF_NET_05_1 | E597: 644.22626 | F597: 581.62577 | G597: 471.58599 | H597: 134.40774 | I597: -128.81664 | J597: 356.37389 | K597: 1050.1551 | L597: 193.30152 | M597: 86.649106 | N597: 290.50818 | O597: 177.79873 | P597: 425.29337 | Q597: 436.7872 | R597: 313.34831 | S597: 201.58773 | T597: 170.94409 | U597: 267.94593 | V597: 183.05207 | W597: 175.08566 | X597: 91.855748 | Y597: 530.29362 | Z597: 421.6535 | AA597: 379.55246 | AB597: 358.05918 | AC597: 347.24252 | AD597: 347.9239 | AE597: 311.61132 | AF597: 286.07804 | AG597: 259.31136 | AH597: 232.7382 | AI597: 214.49305 | AJ597: 191.3211 | AK597: 160.8442 | AL597: 138.81604 | AM597: 115.16318 | AN597: 88.021533 | AO597: 57.22883 | AP597: 35.23072 | AQ597: 12.857657 | AR597: -3.0684529 | AS597: -27.471721 | AT597: -50.824293 | AU597: -76.456112 | AV597: -105.71074 | AW597: -136.18445
B598: RF_NET_06_1 | E598: -461.92367 | F598: -547.776 | G598: -629.76414 | H598: -801.60104 | I598: -821.91776 | J598: -295.99638 | K598: -493.87477 | L598: -646.90889 | M598: -493.67961 | N598: -515.21738 | O598: -501.43722 | P598: -563.95807 | Q598: -632.85276 | R598: -554.09687 | S598: -622.72719 | T598: -639.51967 | U598: -605.29265 | V598: -645.97793 | W598: -674.43967 | X598: -914.00863 | Y598: -823.03255 | Z598: -872.91433 | AA598: -299.38467 | AB598: 4277.4532 | AC598: -18621.371 | AD598: -11332.141 | AE598: -11484.497 | AF598: -11642.249 | AG598: -11798.738 | AH598: -11964.845 | AI598: -12141.907 | AJ598: -12318.516 | AK598: -12506.803 | AL598: -12698.633 | AM598: -12896.568 | AN598: -13098.353 | AO598: -13116.543 | AP598: -13142.625 | AQ598: -13155.566 | AR598: -13155.972 | AS598: -13140.578 | AT598: -13245.707 | AU598: -13334.65 | AV598: -13420.523 | AW598: -13503.639
B599: RF_NET_07_1 | E599: -1156.8521 | F599: -1168.5924 | G599: -1145.0088 | H599: -1225.0761 | I599: -1145.5486 | J599: -1269.3481 | K599: -1340.8878 | L599: -1407.3482 | M599: -1384.5355 | N599: -1417.839 | O599: -1408.9044 | P599: -1462.9275 | Q599: -1674.9714 | R599: -1819.6029 | S599: -1817.4293 | T599: -1910.5762 | U599: -2008.1838 | V599: -2254.1233 | W599: -2577.6206 | X599: -3105.7711 | Y599: -3507.9432 | Z599: -3499.3937 | AA599: -3474.2408 | AB599: -3436.6262 | AC599: -3380.7966 | AD599: -3303.7022 | AE599: -3346.3581 | AF599: -3384.19 | AG599: -3428.2507 | AH599: -3468.3274 | AI599: -3510.3704 | AJ599: -3572.133 | AK599: -3637.6576 | AL599: -3705.4669 | AM599: -3776.0517 | AN599: -3849.3272 | AO599: -4281.8505 | AP599: -4806.4101 | AQ599: -5473.9774 | AR599: -6341.4982 | AS599: -7510.2468 | AT599: -8273.1067 | AU599: -9218.2761 | AV599: -10364.278 | AW599: -11773.749
B600: RF_NET_08_1 | E600: 242.50956 | F600: 205.03623 | G600: 87.555805 | H600: 22.777701 | I600: 311.52918 | J600: 111.16636 | K600: 29.106505 | L600: 111.32422 | M600: 487.95207 | N600: 494.68668 | O600: 602.05499 | P600: 565.83191 | Q600: 217.88748 | R600: 115.10499 | S600: 778.2787 | T600: 902.0848 | U600: 943.25182 | V600: 809.93019 | W600: 677.36294 | X600: 520.10778 | Y600: 433.27479 | Z600: 527.11472 | AA600: 648.45112 | AB600: 796.07385 | AC600: 958.30224 | AD600: 1142.5975 | AE600: 1176.819 | AF600: 1223.497 | AG600: 1268.4787 | AH600: 1313.9401 | AI600: 1361.3802 | AJ600: 1408.2562 | AK600: 1454.4437 | AL600: 1502.4355 | AM600: 1550.3562 | AN600: 1598.0903 | AO600: 1617.5756 | AP600: 1641.6573 | AQ600: 1665.645 | AR600: 1692.4695 | AS600: 1718.7718 | AT600: 1742.5672 | AU600: 1766.0267 | AV600: 1789.3348 | AW600: 1812.2399
B601: RF_NET_09_1 | E601: -74.602904 | F601: -177.75392 | G601: -92.695273 | H601: -428.58579 | I601: -853.87082 | J601: 15.170965 | K601: 218.34968 | L601: -351.33573 | M601: -504.38126 | N601: -402.90005 | O601: -135.01123 | P601: -234.4605 | Q601: -236.5709 | R601: -325.34022 | S601: -617.24915 | T601: -589.42192 | U601: -467.97798 | V601: -526.88436 | W601: -534.74088 | X601: -591.58833 | Y601: -618.21796 | Z601: -690.98151 | AA601: -709.9639 | AB601: -704.69315 | AC601: -682.75347 | AD601: -642.80638 | AE601: -666.48851 | AF601: -671.26359 | AG601: -674.8843 | AH601: -676.52691 | AI601: -672.77323 | AJ601: -668.76544 | AK601: -667.45541 | AL601: -661.76151 | AM601: -655.46706 | AN601: -649.6095 | AO601: -646.15258 | AP601: -634.69311 | AQ601: -623.05703 | AR601: -606.05115 | AS601: -590.24585 | AT601: -565.8384 | AU601: -542.72375 | AV601: -518.83256 | AW601: -493.8484
B602: RF_NET_10_1 | E602: 582.72534 | F602: 546.10902 | G602: 276.69175 | H602: 26.171852 | I602: -473.91282 | J602: 282.1759 | K602: 444.23787 | L602: -13.307186 | M602: 8.8536184 | N602: 19.374525 | O602: 37.010626 | P602: -225.09626 | Q602: 9.4038654 | R602: -99.775959 | S602: -375.86631 | T602: -398.98271 | U602: -357.67259 | V602: -392.69933 | W602: -410.92215 | X602: -410.76185 | Y602: 15.56498 | Z602: 24.141098 | AA602: 53.858439 | AB602: 87.759814 | AC602: 124.91074 | AD602: 166.0745 | AE602: 140.62513 | AF602: 123.60966 | AG602: 108.26284 | AH602: 94.675357 | AI602: 83.890155 | AJ602: 75.467259 | AK602: 66.50471 | AL602: 59.377876 | AM602: 52.69849 | AN602: 45.924348 | AO602: 59.290719 | AP602: 76.426112 | AQ602: 94.061105 | AR602: 113.85368 | AS602: 133.2265 | AT602: 140.22854 | AU602: 146.76828 | AV602: 153.49789 | AW602: 160.45796
B603: RF_NET_11_1 | E603: -41.939713 | F603: -77.995438 | G603: -229.94871 | H603: -199.95415 | I603: -293.51655 | J603: -12.086261 | K603: -47.027756 | L603: -205.1938 | M603: -224.01772 | N603: -157.87301 | O603: -189.22539 | P603: -242.03242 | Q603: -143.67634 | R603: -237.35879 | S603: -285.25912 | T603: -292.23428 | U603: -267.77982 | V603: -283.38774 | W603: -289.46916 | X603: -332.93095 | Y603: -374.03617 | Z603: -411.73845 | AA603: -430.96081 | AB603: -427.67765 | AC603: -383.62758 | AD603: -261.55377 | AE603: -281.08208 | AF603: -297.81298 | AG603: -311.2823 | AH603: -322.22007 | AI603: -331.16834 | AJ603: -338.55593 | AK603: -344.04324 | AL603: -348.79959 | AM603: -352.64666 | AN603: -355.69099 | AO603: -357.65751 | AP603: -359.70513 | AQ603: -361.38455 | AR603: -363.00054 | AS603: -364.06708 | AT603: -365.14569 | AU603: -365.54252 | AV603: -365.51428 | AW603: -365.1709
... B629: RF_NET_2406_1 | E629: 85.892181 | F629: 81.173232 | G629: 122.91178 | H629: 159.19665 | I629: 199.71452 | J629: 271.38395 | K629: 349.49748 | L629: 432.97984 | M629: 560.78622 | N629: 748.77849 | O629: 1016.1528 | P629: 775.63663 | Q629: 650.11156 | R629: 553.77304 | S629: 525.38791 | T629: 477.36919 | U629: 688.97119 | V629: 774.33782 | W629: 848.9768 | X629: 634.36639 | Y629: 571.42174 | Z629: 712.7654 | AA629: 780.18527 | AB629: 825.36082 | AC629: 866.74897 | AD629: 911.45124 | AE629: 935.42035 | AF629: 973.76546 | AG629: 1015.9345 | AH629: 1061.4482 | AI629: 1106.3748 | AJ629: 1126.4661 | AK629: 1153.998 | AL629: 1184.9453 | AM629: 1217.7824 | AN629: 1250.2213 | AO629: 1264.7637 | AP629: 1284.9276 | AQ629: 1306.548 | AR629: 1328.6758 | AS629: 1349.9631 | AT629: 1386.4076 | AU629: 1417.3002 | AV629: 1447.2083 | AW629: 1477.5677
B630: PRF_NET_1 | C630: 0.96116878 | D630: 0.98039216 | E630: 1 | F630: 0.99443806 | G630: 0.98058626 | H630: 1.0906952 | I630: 0.98698204 | J630: 0.97774798 | K630: 0.94044028 | L630: 0.94059509 | M630: 4.0231303 | N630: 0.94894331 | O630: 0.95300727 | P630: 0.96095941 | Q630: 0.94619192 | R630: 0.95151411 | S630: 0.98541102 | T630: 0.99636072 | U630: 1.0282431 | V630: 1.0252328 | W630: 1.0407602 | X630: 1.0615965 | Y630: 1.0955584 | Z630: 1.1034548 | AA630: 1.1154129 | AB630: 1.117874 | AC630: 1.2127953 | AD630: 1.1981283 | AE630: 1.2223273 | AF630: 1.2486157 | AG630: 1.2752887 | AH630: 1.3025224 | AI630: 1.3305404 | AJ630: 1.3581611 | AK630: 1.3699155 | AL630: 1.4267044 | AM630: 1.4540475 | AN630: 1.4841069 | AO630: 1.5139935 | AP630: 1.5453863 | AQ630: 1.5795076 | AR630: 1.6442994 | AS630: 1.6330497 | AT630: 1.6657879 | AU630: 1.7022941 | AV630: 1.7386699 | AW630: 1.7760387
B631: PRF_NET_01_1 | C631: 0.96116878 | D631: 0.98039216 | E631: 1 | F631: 0.97133661 | G631: 0.95946213 | H631: 0.98347217 | I631: 0.9774272 | J631: 0.91758917 | K631: 0.90619901 | L631: 0.895267 | M631: 0.91739033 | N631: 0.91526358 | O631: 0.91163816 | P631: 0.94715798 | Q631: 0.98343893 | R631: 1.0297891 | S631: 1.1000465 | T631: 1.1254171 | U631: 1.1517479 | V631: 1.1765985 | W631: 1.2020844 | X631: 1.2266078 | Y631: 1.250629 | Z631: 1.2784923 | AA631: 1.3070595 | AB631: 1.3359194 | AC631: 1.3648824 | AD631: 1.3940239 | AE631: 1.4237147 | AF631: 1.4542854 | AG631: 1.4853995 | AH631: 1.5172546 | AI631: 1.5500563 | AJ631: 1.5833 | AK631: 1.6173125 | AL631: 1.6519607 | AM631: 1.6871927 | AN631: 1.7229954 | AO631: 1.7582408 | AP631: 1.7939124 | AQ631: 1.8301199 | AR631: 1.8669531 | AS631: 1.9043754 | AT631: 1.9420435 | AU631: 1.9803486 | AV631: 2.0193633 | AW631: 2.0591009
B632: PRF_NET_02_1 | C632: 0.96116878 | D632: 0.98039216 | E632: 1 | F632: 1.058323 | G632: 1.0685784 | H632: 1.1201035 | I632: 1.0352117 | J632: 0.98512458 | K632: 0.91017879 | L632: 0.89336795 | M632: 0.88790424 | N632: 0.9223017 | O632: 0.91371662 | P632: 0.89185314 | Q632: 0.90418902 | R632: 0.9233589 | S632: 1.0508653 | T632: 1.0758689 | U632: 1.1012319 | V632: 1.1243764 | W632: 1.1488211 | X632: 1.1703213 | Y632: 1.1911504 | Z632: 1.211746 | AA632: 1.232403 | AB632: 1.2522237 | AC632: 1.2699605 | AD632: 1.2838078 | AE632: 1.3137024 | AF632: 1.345009 | AG632: 1.3765191 | AH632: 1.4085129 | AI632: 1.4415605 | AJ632: 1.4744116 | AK632: 1.5079242 | AL632: 1.5420654 | AM632: 1.5768106 | AN632: 1.6120907 | AO632: 1.647813 | AP632: 1.6840242 | AQ632: 1.7207174 | AR632: 1.7580398 | AS632: 1.7959128 | AT632: 1.8343299 | AU632: 1.8732993 | AV632: 1.9129213 | AW632: 1.9531996
B633: PRF_NET_03_1 | C633: 0.96116878 | D633: 0.98039216 | E633: 1 | F633: 1.0510404 | G633: 1.0250513 | H633: 1.0138326 | I633: 0.97518981 | J633: 0.23112867 | K633: 1.0372413 | L633: 1.1018046 | M633: 1.1192336 | N633: 1.0883988 | O633: 0.99098147 | P633: 0.93087609 | Q633: 0.9992248 | R633: 1.0463901 | S633: 1.15786 | T633: 1.269654 | U633: 1.1918608 | V633: 1.2531528 | W633: 1.2732388 | X633: 1.3650541 | Y633: 1.4550626 | Z633: 1.5511031 | AA633: 1.6510734 | AB633: 1.7726018 | AC633: 1.9389302 | AD633: 2.2170835 | AE633: 2.2856233 | AF633: 2.3576252 | AG633: 2.4339143 | AH633: 2.514995 | AI633: 2.601254 | AJ633: 2.6931584 | AK633: 2.7913916 | AL633: 2.8958778 | AM633: 3.0075402 | AN633: 3.1271466 | AO633: 3.2555934 | AP633: 3.3942452 | AQ633: 3.54374 | AR633: 3.7059618 | AS633: 3.8829112 | AT633: 4.0769396 | AU633: 4.291464 | AV633: 4.530676 | AW633: 4.7994746
B634: PRF_NET_04_1 | C634: 0.96116878 | D634: 0.98039216 | E634: 1 | F634: 1.0172031 | G634: 1.0396809 | H634: 1.0884225 | I634: 1.1815265 | J634: 1.0868523 | K634: 1.0108068 | L634: 1.1372099 | M634: 1.1731848 | N634: 1.177806 | O634: 1.2087543 | P634: 1.1936158 | Q634: 1.2107777 | R634: 1.2224839 | S634: 1.2523364 | T634: 1.2722084 | U634: 1.2911473 | V634: 1.3109648 | W634: 1.3302243 | X634: 1.3522369 | Y634: 0.011095029 | Z634: 1.2980463 | AA634: 1.3713376 | AB634: 1.4175099 | AC634: 1.4567426 | AD634: 1.4934684 | AE634: 1.5194809 | AF634: 1.5472998 | AG634: 1.5766018 | AH634: 1.6075382 | AI634: 1.6397453 | AJ634: 1.6725774 | AK634: 1.7064531 | AL634: 1.7410574 | AM634: 1.7763231 | AN634: 1.8122123 | AO634: 1.8378676 | AP634: 1.8639882 | AQ634: 1.8899627 | AR634: 1.9157963 | AS634: 1.9414818 | AT634: 1.9743484 | AU634: 2.0070126 | AV634: 2.0400191 | AW634: 2.0734499
B635: PRF_NET_05_1 | C635: 0.96116878 | D635: 0.98039216 | E635: 1 | F635: 0.98652899 | G635: 1.012059 | H635: 1.414089 | I635: -0.37957894 | J635: 1.920387 | K635: 1.1902772 | L635: 1.384479 | M635: 2.2573684 | N635: 1.6194228 | O635: 2.2618929 | P635: 1.604409 | Q635: 1.4366833 | R635: 1.4128302 | S635: 1.6916293 | T635: 1.7729754 | U635: 1.6312899 | V635: 1.7213393 | W635: 1.6936729 | X635: 1.7970922 | Y635: 1.2981857 | Z635: 1.314786 | AA635: 1.3367774 | AB635: 1.3630244 | AC635: 1.3922585 | AD635: 1.4251498 | AE635: 1.4434634 | AF635: 1.4629759 | AG635: 1.4799888 | AH635: 1.4951183 | AI635: 1.51232 | AJ635: 1.520301 | AK635: 1.5108488 | AL635: 1.4987357 | AM635: 1.4624548 | AN635: 1.3692368 | AO635: 0.89031435 | AP635: -0.06999349 | AQ635: -4.4569518 | AR635: 32.708647 | AS635: 5.8263266 | AT635: 4.2053106 | AU635: 3.5780337 | AV635: 3.236524 | AW635: 3.0449744
B636: PRF_NET_06_1 | C636: 0.96116878 | D636: 0.98039216 | E636: 1 | F636: 1.0219758 | G636: 1.0396787 | H636: 1.0665691 | I636: 1.118929 | J636: 0.8669936 | K636: 1.0493614 | L636: 1.1114712 | M636: 1.0678203 | N636: 1.0925348 | O636: 1.1010851 | P636: 1.1369386 | Q636: 1.1775599 | R636: 1.1144438 | S636: 1.1794043 | T636: 1.2128529 | U636: 1.1819117 | V636: 1.2437363 | W636: 1.2881189 | X636: 1.5441681 | Y636: 2.0814525 | Z636: 2.8962888 | AA636: 11.824738 | AB636: -0.9713164 | AC636: 0.35048594 | AD636: 0.76944838 | AE636: 0.78335993 | AF636: 0.79575446 | AG636: 0.8076711 | AH636: 0.81865153 | AI636: 0.82919424 | AJ636: 0.84013198 | AK636: 0.85070098 | AL636: 0.86121191 | AM636: 0.87155037 | AN636: 0.881781 | AO636: 0.90484673 | AP636: 0.92791141 | AQ636: 0.95222081 | AR636: 0.97784686 | AS636: 1.005083 | AT636: 1.0234079 | AU636: 1.0433011 | AV636: 1.0638056 | AW636: 1.0848943
B637: PRF_NET_07_1 | C637: 0.96116878 | D637: 0.98039216 | E637: 1 | F637: 1.0241932 | G637: 1.1052074 | H637: 1.0469227 | I637: 1.0565615 | J637: 0.97556094 | K637: 0.94416079 | L637: 0.9290861 | M637: 0.91507883 | N637: 0.91301505 | O637: 0.9244712 | P637: 0.90040381 | Q637: 0.84916945 | R637: 0.8206523 | S637: 0.8366497 | T637: 0.8301294 | U637: 0.81614973 | V637: 0.7792982 | W637: 0.73279106 | X637: 0.65928971 | Y637: 0.48435521 | Z637: 0.50001069 | AA637: 0.51433248 | AB637: 0.52905458 | AC637: 0.54491932 | AD637: 0.56211048 | AE637: 0.57317131 | AF637: 0.58431801 | AG637: 0.59513817 | AH637: 0.60698496 | AI637: 0.61907419 | AJ637: 0.62839277 | AK637: 0.63815962 | AL637: 0.6478207 | AM637: 0.65755035 | AN637: 0.66733158 | AO637: 0.62262494 | AP637: 0.57525764 | AQ637: 0.52401783 | AR637: 0.4691807 | AS637: 0.41107764 | AT637: 0.38663084 | AU637: 0.35969148 | AV637: 0.33163867 | AW637: 0.30262916
B638: PRF_NET_08_1 | C638: 0.96116878 | D638: 0.98039216 | E638: 1 | F638: 0.9493571 | G638: 1.0847958 | H638: -1.8864023 | I638: 1.0924653 | J638: -0.022100883 | K638: -4.7840989 | L638: -0.65414449 | M638: 0.62429683 | N638: 0.62511728 | O638: 0.65487441 | P638: 0.40625609 | Q638: -0.88487769 | R638: -2.7700236 | S638: 0.24811098 | T638: 0.30918522 | U638: 0.3116063 | V638: 0.20541461 | W638: 0.053212049 | X638: -0.2233979 | Y638: -0.37610101 | Z638: -0.17569671 | AA638: 0.0080530406 | AB638: 0.16607277 | AC638: 0.29332767 | AD638: 0.40329175 | AE638: 0.43252594 | AF638: 0.46854586 | AG638: 0.5046027 | AH638: 0.54177338 | AI638: 0.58006322 | AJ638: 0.61838685 | AK638: 0.65674237 | AL638: 0.69572156 | AM638: 0.7347433 | AN638: 0.77400684 | AO638: 0.79618775 | AP638: 0.81994981 | AQ638: 0.84384778 | AR638: 0.86884836 | AS638: 0.89391947 | AT638: 0.91464015 | AU638: 0.93544096 | AV638: 0.9563781 | AW638: 0.97736456
B639: PRF_NET_09_1 | C639: 0.96116878 | D639: 0.98039216 | E639: 1 | F639: 1.041298 | G639: 1.2787421 | H639: 1.082928 | I639: 1.0949375 | J639: 7.7024969 | K639: 1.3338665 | L639: 1.0658458 | M639: 1.0777845 | N639: 0.94475509 | O639: 0.01788256 | P639: 0.61276657 | Q639: 0.71852975 | R639: 0.97927967 | S639: 1.1511958 | T639: 1.1434869 | U639: 1.032003 | V639: 1.101966 | W639: 1.1151702 | X639: 1.1738951 | Y639: 1.2214133 | Z639: 1.2865572 | AA639: 1.3086699 | AB639: 1.3101273 | AC639: 1.2917362 | AD639: 1.2418678 | AE639: 1.2786354 | AF639: 1.2943709 | AG639: 1.31059 | AH639: 1.32587 | AI639: 1.3354738 | AJ639: 1.3458096 | AK639: 1.3609563 | AL639: 1.3709164 | AM639: 1.3808062 | AN639: 1.3921826 | AO639: 1.412084 | AP639: 1.4199899 | AQ639: 1.4284054 | AR639: 1.427268 | AS639: 1.4281636 | AT639: 1.4043144 | AU639: 1.379005 | AV639: 1.3468908 | AW639: 1.3055756
B640: PRF_NET_10_1 | C640: 0.96116878 | D640: 0.98039216 | E640: 1 | F640: 0.97647908 | G640: 1.2007899 | H640: 5.9648634 | I640: 0.31751119 | J640: 3.4799419 | K640: 2.0537385 | L640: -24.915555 | M640: 35.715019 | N640: 18.184089 | O640: 10.88365 | P640: -1.1605805 | Q640: 61.138199 | R640: -5.1790404 | S640: -0.64047823 | T640: -0.42863385 | U640: -0.86429842 | V640: -0.53398025 | W640: -0.38522318 | X640: -0.315469 | Y640: 40.199324 | Z640: 27.525305 | AA640: 14.011624 | AB640: 9.7521223 | AC640: 7.740989 | AD640: 6.5669531 | AE640: 7.4099193 | AF640: 8.1911125 | AG640: 9.0896547 | AH640: 10.116629 | AI640: 11.163278 | AJ640: 12.157938 | AK640: 13.446604 | AL640: 14.722756 | AM640: 16.19315 | AN640: 18.074452 | AO640: 13.471834 | AP640: 10.164044 | AQ640: 7.996982 | AR640: 6.4152539 | AS640: 5.2775045 | AT640: 4.8518741 | AU640: 4.4406282 | AV640: 4.0478272 | AW640: 3.6750881
B641: PRF_NET_11_1 | C641: 0.96116878 | D641: 0.98039216 | E641: 1 | F641: 1.0829261 | G641: 0.99285417 | H641: 0.90492873 | I641: 0.9635219 | J641: -10.749707 | K641: -0.42804755 | L641: 0.94031217 | M641: 0.91388795 | N641: 0.62440366 | O641: 0.70457012 | P641: 0.76609253 | Q641: 0.094036937 | R641: 0.74221722 | S641: 0.82406228 | T641: 0.87764957 | U641: 0.63242942 | V641: 0.72910561 | W641: 0.73361733 | X641: 0.97773058 | Y641: 1.2177454 | Z641: 1.5180217 | AA641: 1.827953 | AB641: 2.2733897 | AC641: 3.0859367 | AD641: 5.4626515 | AE641: 5.3464444 | AF641: 5.2614744 | AG641: 5.2334064 | AH641: 5.244552 | AI641: 5.2840092 | AJ641: 5.3465428 | AK641: 5.445542 | AL641: 5.5522951 | AM641: 5.6743633 | AN641: 5.8112229 | AO641: 5.9718451 | AP641: 6.1230085 | AQ641: 6.2820278 | AR641: 6.4391646 | AS641: 6.6106917 | AT641: 6.7781327 | AU641: 6.9662919 | AV641: 7.1670049 | AW641: 7.3781341
... B667: PRF_NET_2406_1 | C667: 0.96116878 | D667: 0.98039216 | E667: 1 | F667: 0.89149146 | G667: 0.95271399 | H667: 1.0490079 | I667: 1.1155707 | J667: 1.1177276 | K667: 1.0883758 | L667: 1.0495633 | M667: 1.0212637 | N667: 1.0064354 | O667: 0.99626904 | P667: 0.82458715 | Q667: 0.68771494 | R667: 0.62737394 | S667: 0.63610449 | T667: 0.67980573 | U667: 0.81194461 | V667: 0.82256233 | W667: 0.82619596 | X667: 0.79133656 | Y667: 0.77803741 | Z667: 0.8262999 | AA667: 0.88252739 | AB667: 0.91481529 | AC667: 0.93536148 | AD667: 0.9521194 | AE667: 0.96342571 | AF667: 0.98352582 | AG667: 1.0066168 | AH667: 1.0316253 | AI667: 1.0566538 | AJ667: 1.0767303 | AK667: 1.1007005 | AL667: 1.1260374 | AM667: 1.1521773 | AN667: 1.1781848 | AO667: 1.200859 | AP667: 1.2262622 | AQ667: 1.2524145 | AR667: 1.2791137 | AS667: 1.3059093 | AT667: 1.3359075 | AU667: 1.3638167 | AV667: 1.3915343 | AW667: 1.419557
B668: RF_NET_2 | E668: 279982.11 | F668: 265240.2 | G668: 276779.62 | H668: 229146.13 | I668: 234335.61 | J668: 270619.14 | K668: 294932.47 | L668: 284779.32 | M668: 66096.378 | N668: 290213 | O668: 296652.71 | P668: 300982.04 | Q668: 317318.37 | R668: 319527.16 | S668: 322790.29 | T668: 315557 | U668: 333777.6 | V668: 331130.36 | W668: 336355.25 | X668: 334478.02 | Y668: 334416.81 | Z668: 335059.99 | AA668: 339332.25 | AB668: 346335.6 | AC668: 323029.39 | AD668: 332549.98 | AE668: 335193.54 | AF668: 336463.88 | AG668: 337483.67 | AH668: 337220.55 | AI668: 338295.26 | AJ668: 342675.35 | AK668: 353104.68 | AL668: 347202.58 | AM668: 350699.46 | AN668: 353198.05 | AO668: 358674.99 | AP668: 362918.33 | AQ668: 366825.81 | AR668: 371117.63 | AS668: 373951.6 | AT668: 375199.32 | AU668: 372054.24 | AV668: 386275.21 | AW668: 389523.98
B669: RF_NET_01_2 | E669: 10118.546 | F669: 9656.0874 | G669: 9452.3618 | H669: 8419.282 | I669: 9305.1645 | J669: 10619.3 | K669: 9647.7768 | L669: 10285.614 | M669: 9363.93 | N669: 10935.046 | O669: 10561.533 | P669: 9360.2798 | Q669: 9906.703 | R669: 9563.2001 | S669: 9600.3251 | T669: 9723.2154 | U669: 10026.081 | V669: 10157.66 | W669: 10421.536 | X669: 10601.136 | Y669: 10726.341 | Z669: 10963.605 | AA669: 11143.23 | AB669: 11254.056 | AC669: 11291.386 | AD669: 11302.468 | AE669: 11489.319 | AF669: 11709.378 | AG669: 11907.863 | AH669: 12106.272 | AI669: 12319.545 | AJ669: 12568.845 | AK669: 12849.664 | AL669: 13116.941 | AM669: 13415.308 | AN669: 13691.289 | AO669: 14008.752 | AP669: 14328.793 | AQ669: 14639.494 | AR669: 14954.388 | AS669: 15252.011 | AT669: 15533.053 | AU669: 15825.647 | AV669: 16144.797 | AW669: 16474.496
B670: RF_NET_02_2 | E670: 5955.092 | F670: 5232.761 | G670: 5584.9951 | H670: 4388.2907 | I670: 5981.8216 | J670: 5883.1132 | K670: 6442.9196 | L670: 5670.4435 | M670: 6014.404 | N670: 6216.1801 | O670: 6784.9121 | P670: 6669.5641 | Q670: 6489.0761 | R670: 6479.8961 | S670: 5165.5709 | T670: 5283.1371 | U670: 5413.5905 | V670: 5422.4741 | W670: 5504.5177 | X670: 5400.431 | Y670: 5212.6736 | Z670: 5053.3046 | AA670: 4805.2633 | AB670: 4429.4345 | AC670: 3904.9774 | AD670: 3225.2691 | AE670: 3284.1766 | AF670: 3334.678 | AG670: 3370.5818 | AH670: 3403.2495 | AI670: 3446.1383 | AJ670: 3509.9869 | AK670: 3593.3589 | AL670: 3657.4392 | AM670: 3750.4822 | AN670: 3823.4919 | AO670: 3932.365 | AP670: 4032.1643 | AQ670: 4126.0189 | AR670: 4228.7888 | AS670: 4328.4985 | AT670: 4415.3008 | AU670: 4512.92 | AV670: 4631.8791 | AW670: 4761.4465
B671: RF_NET_03_2 | E671: -1066.0862 | F671: -1369.9617 | G671: -2230.1179 | H671: -2391.5803 | I671: -2337.5863 | J671: -340.39926 | K671: -1622.1687 | L671: -1622.2828 | M671: -1998.1602 | N671: -2228.6118 | O671: -1885.2583 | P671: -1681.9204 | Q671: -1948.6707 | R671: -1839.8234 | S671: -2555.8656 | T671: -3236.5719 | U671: -2580.3934 | V671: -2851.8587 | W671: -2869.0349 | X671: -3277.0452 | Y671: -3845.4343 | Z671: -4521.9783 | AA671: -5186.3135 | AB671: -5986.1212 | AC671: -6806.359 | AD671: -7537.1941 | AE671: -7739.0008 | AF671: -7866.1679 | AG671: -7947.2116 | AH671: -8007.8242 | AI671: -8057.308 | AJ671: -8100.9074 | AK671: -8149.7442 | AL671: -8213.3501 | AM671: -8241.0389 | AN671: -8302.0504 | AO671: -8334.7189 | AP671: -8399.8197 | AQ671: -8460.0701 | AR671: -8510.6761 | AS671: -8564.7186 | AT671: -8616.2718 | AU671: -8665.0755 | AV671: -8720.2815 | AW671: -8777.5529
B672: RF_NET_04_2 | E672: -362.61321 | F672: -403.32144 | G672: -437.12833 | H672: -518.61834 | I672: -483.16022 | J672: -266.87703 | K672: -99.051711 | L672: -458.51946 | M672: -462.49409 | N672: -357.59917 | O672: -369.95576 | P672: -296.26785 | Q672: -337.65263 | R672: -422.11597 | S672: -468.58861 | T672: -494.28192 | U672: -472.78437 | V672: -508.53177 | W672: -531.30444 | X672: -303.78154 | Y672: 59.88909 | Z672: 301.60631 | AA672: 580.12511 | AB672: 900.89849 | AC672: 1274.0516 | AD672: 1715.7993 | AE672: 1647.9771 | AF672: 1606.3462 | AG672: 1578.5125 | AH672: 1556.2461 | AI672: 1538.7318 | AJ672: 1527.8414 | AK672: 1518.9975 | AL672: 1511.0553 | AM672: 1512.7666 | AN672: 1512.1879 | AO672: 1515.1269 | AP672: 1515.1718 | AQ672: 1513.46 | AR672: 1511.4979 | AS672: 1504.4528 | AT672: 1508.5568 | AU672: 1515.3799 | AV672: 1523.855 | AW672: 1533.2981
B673: RF_NET_05_2 | E673: 644.22626 | F673: 581.62577 | G673: 471.58599 | H673: 134.40774 | I673: -128.81664 | J673: 356.37389 | K673: 1050.1551 | L673: 193.30152 | M673: 86.649106 | N673: 290.50818 | O673: 177.79873 | P673: 425.29337 | Q673: 436.7872 | R673: 313.34831 | S673: 201.58773 | T673: 170.94409 | U673: 267.94593 | V673: 183.05207 | W673: 181.46898 | X673: 121.56764 | Y673: 461.30923 | Z673: 360.31262 | AA673: 285.40686 | AB673: 233.93161 | AC673: 179.71686 | AD673: 147.32491 | AE673: 102.7599 | AF673: 38.297794 | AG673: -24.159284 | AH673: -80.82035 | AI673: -124.38117 | AJ673: -165.62045 | AK673: -222.3215 | AL673: -275.56204 | AM673: -322.49625 | AN673: -375.22509 | AO673: -420.18507 | AP673: -488.86004 | AQ673: -562.21232 | AR673: -630.98175 | AS673: -716.31943 | AT673: -781.42864 | AU673: -832.76993 | AV673: -889.15227 | AW673: -948.92096
B674: RF_NET_06_2 | E674: -461.92367 | F674: -547.776 | G674: -629.76414 | H674: -801.60104 | I674: -821.91776 | J674: -295.99638 | K674: -493.87477 | L674: -646.90889 | M674: -493.67961 | N674: -515.21738 | O674: -501.43722 | P674: -563.95807 | Q674: -632.85276 | R674: -554.09687 | S674: -622.72719 | T674: -639.51967 | U674: -605.29265 | V674: -645.97793 | W674: -670.2807 | X674: -900.79869 | Y674: -900.86283 | Z674: -993.36351 | AA674: -458.3994 | AB674: 4054.2477 | AC674: -19679.68 | AD674: -12094.168 | AE674: -12251.105 | AF674: -12411.807 | AG674: -12573.449 | AH674: -12721.141 | AI674: -12894.838 | AJ674: -13091.32 | AK674: -13287.539 | AL674: -13460.523 | AM674: -13652.077 | AN674: -13807.305 | AO674: -13979.956 | AP674: -14130.305 | AQ674: -14286.49 | AR674: -14460.732 | AS674: -14638.483 | AT674: -14779.304 | AU674: -14925.607 | AV674: -15074.913 | AW674: -15230.993
B675: RF_NET_07_2 | E675: -1156.8521 | F675: -1168.5924 | G675: -1145.0088 | H675: -1225.0761 | I675: -1145.5486 | J675: -1269.3481 | K675: -1340.8878 | L675: -1407.3482 | M675: -1384.5355 | N675: -1417.839 | O675: -1408.9044 | P675: -1462.9275 | Q675: -1674.9714 | R675: -1819.6029 | S675: -1817.4293 | T675: -1910.5762 | U675: -2008.1838 | V675: -2254.1233 | W675: -2526.5146 | X675: -2846.1545 | Y675: -2983.7267 | Z675: -2969.8204 | AA675: -2899.4112 | AB675: -2835.6927 | AC675: -2772.4178 | AD675: -2715.8222 | AE675: -2763.0815 | AF675: -2798.3213 | AG675: -2825.9521 | AH675: -2867.2455 | AI675: -2891.0866 | AJ675: -2914.8114 | AK675: -2954.5028 | AL675: -3006.7464 | AM675: -3078.2941 | AN675: -3167.4772 | AO675: -3311.8619 | AP675: -3504.6179 | AQ675: -3727.2972 | AR675: -3969.5836 | AS675: -4240.37 | AT675: -4538.0528 | AU675: -4845.932 | AV675: -5180.0803 | AW675: -5543.6132
B676: RF_NET_08_2 | E676: 242.50956 | F676: 205.03623 | G676: 87.555805 | H676: 22.777701 | I676: 311.52918 | J676: 111.16636 | K676: 29.106505 | L676: 111.32422 | M676: 487.95207 | N676: 494.68668 | O676: 602.05499 | P676: 565.83191 | Q676: 217.88748 | R676: 115.10499 | S676: 778.2787 | T676: 902.0848 | U676: 943.25182 | V676: 809.93019 | W676: 691.60351 | X676: 632.42114 | Y676: 591.25887 | Z676: 698.59108 | AA676: 842.79065 | AB676: 1009.5556 | AC676: 1180.1349 | AD676: 1351.6817 | AE676: 1419.2156 | AF676: 1446.0128 | AG676: 1472.8354 | AH676: 1498.5717 | AI676: 1530.0989 | AJ676: 1565.6882 | AK676: 1599.5348 | AL676: 1631.8454 | AM676: 1665.5666 | AN676: 1695.4966 | AO676: 1712.3783 | AP676: 1725.4001 | AQ676: 1739.6487 | AR676: 1756.2822 | AS676: 1770.7867 | AT676: 1777.3184 | AU676: 1787.6811 | AV676: 1801.4559 | AW676: 1816.0722
B677: RF_NET_09_2 | E677: -74.602904 | F677: -177.75392 | G677: -92.695273 | H677: -428.58579 | I677: -853.87082 | J677: 15.170965 | K677: 218.34968 | L677: -351.33573 | M677: -504.38126 | N677: -402.90005 | O677: -135.01123 | P677: -234.4605 | Q677: -236.5709 | R677: -325.34022 | S677: -617.24915 | T677: -589.42192 | U677: -467.97798 | V677: -526.88436 | W677: -532.08602 | X677: -578.10431 | Y677: -604.27714 | Z677: -662.25138 | AA677: -677.56132 | AB677: -677.4363 | AC677: -665.71632 | AD677: -635.82381 | AE677: -685.7807 | AF677: -718.04745 | AG677: -745.24504 | AH677: -768.9311 | AI677: -785.28765 | AJ677: -795.33295 | AK677: -810.1469 | AL677: -825.27821 | AM677: -833.84732 | AN677: -848.09592 | AO677: -855.95368 | AP677: -868.01694 | AQ677: -876.63582 | AR677: -879.43181 | AS677: -885.7802 | AT677: -889.20605 | AU677: -887.23611 | AV677: -883.77022 | AW677: -879.4678
B678: RF_NET_10_2 | E678: 582.72534 | F678: 546.10902 | G678: 276.69175 | H678: 26.171852 | I678: -473.91282 | J678: 282.1759 | K678: 444.23787 | L678: -13.307186 | M678: 8.8536184 | N678: 19.374525 | O678: 37.010626 | P678: -225.09626 | Q678: 9.4038654 | R678: -99.775959 | S678: -375.86631 | T678: -398.98271 | U678: -357.67259 | V678: -392.69933 | W678: -409.65823 | X678: -398.36279 | Y678: -58.349549 | Z678: -81.942279 | AA678: -79.953766 | AB678: -72.988054 | AC678: -62.684556 | AD678: -46.992747 | AE678: -82.811952 | AF678: -113.84438 | AG678: -142.68193 | AH678: -168.46628 | AI678: -190.61277 | AJ678: -209.51676 | AK678: -229.99595 | AL678: -250.51945 | AM678: -265.80739 | AN678: -283.0889 | AO678: -291.9272 | AP678: -302.3604 | AQ678: -312.93371 | AR678: -321.47501 | AS678: -331.52365 | AT678: -343.08242 | AU678: -353.13547 | AV678: -362.73991 | AW678: -371.73925
B679: RF_NET_11_2 | E679: -41.939713 | F679: -77.995438 | G679: -229.94871 | H679: -199.95415 | I679: -293.51655 | J679: -12.086261 | K679: -47.027756 | L679: -205.1938 | M679: -224.01772 | N679: -157.87301 | O679: -189.22539 | P679: -242.03242 | Q679: -143.67634 | R679: -237.35879 | S679: -285.25912 | T679: -292.23428 | U679: -267.77982 | V679: -283.38774 | W679: -289.1917 | X679: -330.82826 | Y679: -371.64557 | Z679: -410.95067 | AA679: -433.33977 | AB679: -433.81699 | AC679: -391.93216 | AD679: -265.37401 | AE679: -278.5976 | AF679: -288.22848 | AG679: -294.99476 | AH679: -299.32134 | AI679: -301.7071 | AJ679: -302.16853 | AK679: -300.03581 | AL679: -294.96048 | AM679: -290.6606 | AN679: -282.80705 | AO679: -274.67069 | AP679: -263.48774 | AQ679: -251.263 | AR679: -239.21444 | AS679: -226.17849 | AT679: -212.8025 | AU679: -197.97866 | AV679: -181.66242 | AW679: -164.33005
... B705: RF_NET_2406_2 | E705: 85.892181 | F705: 81.173232 | G705: 122.91178 | H705: 159.19665 | I705: 199.71452 | J705: 271.38395 | K705: 349.49748 | L705: 432.97984 | M705: 560.78622 | N705: 748.77849 | O705: 1016.1528 | P705: 775.63663 | Q705: 650.11156 | R705: 553.77304 | S705: 525.38791 | T705: 477.36919 | U705: 688.97119 | V705: 774.33782 | W705: 851.61499 | X705: 974.77307 | Y705: 1073.8054 | Z705: 1117.0701 | AA705: 1193.1378 | AB705: 1266.7375 | AC705: 1286.3569 | AD705: 1308.9981 | AE705: 1371.0149 | AF705: 1421.6742 | AG705: 1465.8053 | AH705: 1484.4116 | AI705: 1507.0768 | AJ705: 1531.4165 | AK705: 1561.5151 | AL705: 1590.3831 | AM705: 1540.9245 | AN705: 1502.6596 | AO705: 1549.5349 | AP705: 1591.9856 | AQ705: 1625.1408 | AR705: 1657.0479 | AS705: 1691.2441 | AT705: 1630.0687 | AU705: 1589.8497 | AV705: 1563.9039 | AW705: 1540.1813
B706: PRF_NET_2 | C706: 0.96116878 | D706: 0.98039216 | E706: 1 | F706: 0.99443806 | G706: 0.98058626 | H706: 1.0906952 | I706: 0.98698204 | J706: 0.97774798 | K706: 0.94044028 | L706: 0.94059509 | M706: 4.0231303 | N706: 0.94894331 | O706: 0.95300727 | P706: 0.96095941 | Q706: 0.94619192 | R706: 0.95151411 | S706: 0.98541102 | T706: 0.99636072 | U706: 1.0282431 | V706: 1.0267563 | W706: 1.0459193 | X706: 1.0676206 | Y706: 1.0904297 | Z706: 1.1098458 | AA706: 1.1295935 | AB706: 1.1367085 | AC706: 1.2359944 | AD706: 1.2233473 | AE706: 1.2524666 | AF706: 1.2814667 | AG706: 1.3103787 | AH706: 1.3389925 | AI706: 1.3682349 | AJ706: 1.3983694 | AK706: 1.3899999 | AL706: 1.4674745 | AM706: 1.4874446 | AN706: 1.5299899 | AO706: 1.5512393 | AP706: 1.5830608 | AQ706: 1.61636 | AR706: 1.6508122 | AS706: 1.684346 | AT706: 1.723137 | AU706: 1.7938048 | AV706: 1.7855296 | AW706: 1.8276755
B707: PRF_NET_01_2 | C707: 0.96116878 | D707: 0.98039216 | E707: 1 | F707: 0.97133661 | G707: 0.95946213 | H707: 0.98347217 | I707: 0.9774272 | J707: 0.91758917 | K707: 0.90619901 | L707: 0.895267 | M707: 0.91739033 | N707: 0.91526358 | O707: 0.91163816 | P707: 0.94715798 | Q707: 0.98343893 | R707: 1.0297891 | S707: 1.1000465 | T707: 1.1254171 | U707: 1.1517479 | V707: 1.1765985 | W707: 1.2024348 | X707: 1.2276622 | Y707: 1.2531365 | Z707: 1.2848731 | AA707: 1.3175227 | AB707: 1.3503221 | AC707: 1.3833733 | AD707: 1.4162308 | AE707: 1.4505974 | AF707: 1.4865701 | AG707: 1.5229769 | AH707: 1.5597909 | AI707: 1.5972285 | AJ707: 1.6354323 | AK707: 1.6745414 | AL707: 1.7139416 | AM707: 1.7543322 | AN707: 1.7947633 | AO707: 1.8357985 | AP707: 1.8776451 | AQ707: 1.9205449 | AR707: 1.9645631 | AS707: 2.0094122 | AT707: 2.0538368 | AU707: 2.0985816 | AV707: 2.1441189 | AW707: 2.1905389
B708: PRF_NET_02_2 | C708: 0.96116878 | D708: 0.98039216 | E708: 1 | F708: 1.058323 | G708: 1.0685784 | H708: 1.1201035 | I708: 1.0352117 | J708: 0.98512458 | K708: 0.91017879 | L708: 0.89336795 | M708: 0.88790424 | N708: 0.9223017 | O708: 0.91371662 | P708: 0.89185314 | Q708: 0.90418902 | R708: 0.9233589 | S708: 1.0508653 | T708: 1.0758689 | U708: 1.1012319 | V708: 1.1243764 | W708: 1.1594127 | X708: 1.1924648 | Y708: 1.2192728 | Z708: 1.2435776 | AA708: 1.2686579 | AB708: 1.2910867 | AC708: 1.3102349 | AD708: 1.2461786 | AE708: 1.2779115 | AF708: 1.3108428 | AG708: 1.3429105 | AH708: 1.3749078 | AI708: 1.4083969 | AJ708: 1.4438108 | AK708: 1.4808381 | AL708: 1.515524 | AM708: 1.5539381 | AN708: 1.5895468 | AO708: 1.6302983 | AP708: 1.669746 | AQ708: 1.7097318 | AR708: 1.7517428 | AS708: 1.7947776 | AT708: 1.8363742 | AU708: 1.8786203 | AV708: 1.9223199 | AW708: 1.9672668
B709: PRF_NET_03_2 | C709: 0.96116878 | D709: 0.98039216 | E709: 1 | F709: 1.0510404 | G709: 1.0250513 | H709: 1.0138326 | I709: 0.97518981 | J709: 0.23112867 | K709: 1.0372413 | L709: 1.1018046 | M709: 1.1192336 | N709: 1.0883988 | O709: 0.99098147 | P709: 0.93087609 | Q709: 0.9992248 | R709: 1.0463901 | S709: 1.15786 | T709: 1.269654 | U709: 1.1918608 | V709: 1.2531528 | W709: 1.2723008 | X709: 1.3490389 | Y709: 1.4393105 | Z709: 1.5320012 | AA709: 1.6189693 | AB709: 1.7115117 | AC709: 1.8178712 | AD709: 1.9670978 | AE709: 1.9751695 | AF709: 1.9955059 | AG709: 2.0268746 | AH709: 2.0653542 | AI709: 2.1083577 | AJ709: 2.1539453 | AK709: 2.2004845 | AL709: 2.2451245 | AM709: 2.2934276 | AN709: 2.3383792 | AO709: 2.3873486 | AP709: 2.4337991 | AQ709: 2.4816035 | AR709: 2.531007 | AS709: 2.581212 | AT709: 2.6312068 | AU709: 2.681779 | AV709: 2.7326947 | AW709: 2.7845357
B710: PRF_NET_04_2 | C710: 0.96116878 | D710: 0.98039216 | E710: 1 | F710: 1.0172031 | G710: 1.0396809 | H710: 1.0884225 | I710: 1.1815265 | J710: 1.0868523 | K710: 1.0108068 | L710: 1.1372099 | M710: 1.1731848 | N710: 1.177806 | O710: 1.2087543 | P710: 1.1936158 | Q710: 1.2107777 | R710: 1.2224839 | S710: 1.2523364 | T710: 1.2722084 | U710: 1.2911473 | V710: 1.3109648 | W710: 1.3309924 | X710: 1.3530761 | Y710: 1.1086469 | Z710: 1.4316976 | AA710: 1.4608854 | AB710: 1.4932171 | AC710: 1.5279643 | AD710: 1.5368333 | AE710: 1.5667331 | AF710: 1.5997467 | AG710: 1.6372708 | AH710: 1.6752587 | AI710: 1.7142606 | AJ710: 1.7543446 | AK710: 1.7953012 | AL710: 1.8368935 | AM710: 1.8783779 | AN710: 1.9195205 | AO710: 1.9569851 | AP710: 1.9939142 | AQ710: 2.0313203 | AR710: 2.0694201 | AS710: 2.1078739 | AT710: 2.1458863 | AU710: 2.1840354 | AV710: 2.2219363 | AW710: 2.2601784
B711: PRF_NET_05_2 | C711: 0.96116878 | D711: 0.98039216 | E711: 1 | F711: 0.98652899 | G711: 1.012059 | H711: 1.414089 | I711: -0.37957894 | J711: 1.920387 | K711: 1.1902772 | L711: 1.384479 | M711: 2.2573684 | N711: 1.6194228 | O711: 2.2618929 | P711: 1.604409 | Q711: 1.4366833 | R711: 1.4128302 | S711: 1.6916293 | T711: 1.7729754 | U711: 1.6312899 | V711: 1.7213393 | W711: 1.8254847 | X711: 2.1705616 | Y711: 1.4453186 | Z711: 1.5247681 | AA711: 1.4466306 | AB711: 1.5325349 | AC711: 1.6265471 | AD711: 1.741807 | AE711: 1.9124549 | AF711: 2.5581921 | AG711: 0.032727842 | AH711: 1.1576816 | AI711: 1.3394993 | AJ711: 1.4388199 | AK711: 1.5360156 | AL711: 1.6055023 | AM711: 1.6617714 | AN711: 1.7169882 | AO711: 1.7819417 | AP711: 1.8512202 | AQ711: 1.9121541 | AR711: 1.9657296 | AS711: 2.0163057 | AT711: 2.064614 | AU711: 2.1106527 | AV711: 2.1562435 | AW711: 2.2012571
B712: PRF_NET_06_2 | C712: 0.96116878 | D712: 0.98039216 | E712: 1 | F712: 1.0219758 | G712: 1.0396787 | H712: 1.0665691 | I712: 1.118929 | J712: 0.8669936 | K712: 1.0493614 | L712: 1.1114712 | M712: 1.0678203 | N712: 1.0925348 | O712: 1.1010851 | P712: 1.1369386 | Q712: 1.1775599 | R712: 1.1144438 | S712: 1.1794043 | T712: 1.2128529 | U712: 1.1819117 | V712: 1.2437363 | W712: 1.2832421 | X712: 1.5360597 | Y712: 1.9915134 | Z712: 2.6916702 | AA712: 8.2256404 | AB712: -1.0993996 | AC712: 0.35768714 | AD712: 0.77870104 | AE712: 0.80908331 | AF712: 0.83798419 | AG712: 0.86610507 | AH712: 0.8950502 | AI712: 0.92171045 | AJ712: 0.94756622 | AK712: 0.97489488 | AL712: 1.0057419 | AM712: 1.0344947 | AN712: 1.0680766 | AO712: 1.1011005 | AP712: 1.1387059 | AQ712: 1.1771056 | AR712: 1.2147009 | AS712: 1.2525573 | AT712: 1.292833 | AU712: 1.3333606 | AV712: 1.3748996 | AW712: 1.4170493
B713: PRF_NET_07_2 | C713: 0.96116878 | D713: 0.98039216 | E713: 1 | F713: 1.0241932 | G713: 1.1052074 | H713: 1.0469227 | I713: 1.0565615 | J713: 0.97556094 | K713: 0.94416079 | L713: 0.9290861 | M713: 0.91507883 | N713: 0.91301505 | O713: 0.9244712 | P713: 0.90040381 | Q713: 0.84916945 | R713: 0.8206523 | S713: 0.8366497 | T713: 0.8301294 | U713: 0.81614973 | V713: 0.7792982 | W713: 0.74299788 | X713: 0.6995292 | Y713: 0.58092228 | Z713: 0.61388133 | AA713: 0.65222897 | AB713: 0.6893508 | AC713: 0.72584365 | AD713: 0.76013772 | AE713: 0.78245222 | AF713: 0.80534571 | AG713: 0.82963794 | AH713: 0.84988555 | AI713: 0.87416324 | AJ713: 0.89943676 | AK713: 0.92296009 | AL713: 0.94477488 | AM713: 0.95692716 | AN713: 0.96613909 | AO713: 0.96650519 | AP713: 0.95969561 | AQ713: 0.95042687 | AR713: 0.94081774 | AS713: 0.93014596 | AT713: 0.90922114 | AU713: 0.88906227 | AV713: 0.86763388 | AW713: 0.8452209
B714: PRF_NET_08_2 | C714: 0.96116878 | D714: 0.98039216 | E714: 1 | F714: 0.9493571 | G714: 1.0847958 | H714: -1.8864023 | I714: 1.0924653 | J714: -0.022100883 | K714: -4.7840989 | L714: -0.65414449 | M714: 0.62429683 | N714: 0.62511728 | O714: 0.65487441 | P714: 0.40625609 | Q714: -0.88487769 | R714: -2.7700236 | S714: 0.24811098 | T714: 0.30918522 | U714: 0.3116063 | V714: 0.20541461 | W714: 0.13163617 | X714: 0.11368796 | Y714: 0.12869001 | Z714: 0.25447273 | AA714: 0.37595833 | AB714: 0.48046492 | AC714: 0.56918685 | AD714: 0.47429096 | AE714: 0.51241058 | AF714: 0.53915475 | AG714: 0.56425346 | AH714: 0.58894447 | AI714: 0.61705398 | AJ714: 0.64732807 | AK714: 0.67736466 | AL714: 0.70706223 | AM714: 0.73759318 | AN714: 0.76688953 | AO714: 0.78644831 | AP714: 0.80361429 | AQ714: 0.82105293 | AR714: 0.84012541 | AS714: 0.85850969 | AT714: 0.86898076 | AU714: 0.88055093 | AV714: 0.89341972 | AW714: 0.906647
...

Sheet taux de profit des secteurs
D1: =résultats!C1 -> 2004 | E1: =résultats!D1 -> 2005 | F1: =résultats!E1 -> 2006 | G1: =résultats!F1 -> 2007 | H1: =résultats!G1 -> 2008 | I1: =résultats!H1 -> 2009 | J1: =résultats!I1 -> 2010 | K1: =résultats!J1 -> 2011 | ... AX1: =résultats!AW1 -> 2050
A2: AME | B2: taux de profit du secteur 01 | D2: =résultats!C593*résultats!C631/(résultats!C745*résultats!C783) -> 0 | E2: =résultats!D593*résultats!D631/(résultats!D745*résultats!D783) -> 0 | F2: =résultats!E593*résultats!E631/(résultats!E745*résultats!E783) -> 0.3153017 | G2: =résultats!F593*résultats!F631/(résultats!F745*résultats!F783) -> 0.28794528 | H2: =résultats!G593*résultats!G631/(résultats!G745*résultats!G783) -> 0.28150983 | I2: =résultats!H593*résultats!H631/(résultats!H745*résultats!H783) -> 0.24702375 | J2: =résultats!I593*résultats!I631/(résultats!I745*résultats!I783) -> 0.26356396 | K2: =résultats!J593*résultats!J631/(résultats!J745*résultats!J783) -> 0.29120181 | ... AX2: =résultats!AW593*résultats!AW631/(résultats!AW745*résultats!AW783) -> 0.28808806
B3: taux de profit du secteur 02 | D3: =résultats!C594*résultats!C632/(résultats!C746*résultats!C784) -> 0 | E3: =résultats!D594*résultats!D632/(résultats!D746*résultats!D784) -> 0 | F3: =résultats!E594*résultats!E632/(résultats!E746*résultats!E784) -> 0.21442462 | G3: =résultats!F594*résultats!F632/(résultats!F746*résultats!F784) -> 0.19065248 | H3: =résultats!G594*résultats!G632/(résultats!G746*résultats!G784) -> 0.21115328 | I3: =résultats!H594*résultats!H632/(résultats!H746*résultats!H784) -> 0.16457804 | J3: =résultats!I594*résultats!I632/(résultats!I746*résultats!I784) -> 0.21094316 | K3: =résultats!J594*résultats!J632/(résultats!J746*résultats!J784) -> 0.19579752 | ... AX3: =résultats!AW594*résultats!AW632/(résultats!AW746*résultats!AW784) -> 0.14826013
B4: taux de profit du secteur 03 | D4: =résultats!C595*résultats!C633/(résultats!C747*résultats!C785) -> 0 | E4: =résultats!D595*résultats!D633/(résultats!D747*résultats!D785) -> 0 | F4: =résultats!E595*résultats!E633/(résultats!E747*résultats!E785) -> -0.081916677 | G4: =résultats!F595*résultats!F633/(résultats!F747*résultats!F785) -> -0.11514296 | H4: =résultats!G595*résultats!G633/(résultats!G747*résultats!G785) -> -0.18285581 | I4: =résultats!H595*résultats!H633/(résultats!H747*résultats!H785) -> -0.20427668 | J4: =résultats!I595*résultats!I633/(résultats!I747*résultats!I785) -> -0.16152618 | K4: =résultats!J595*résultats!J633/(résultats!J747*résultats!J785) -> -0.0061792214 | ... AX4: =résultats!AW595*résultats!AW633/(résultats!AW747*résultats!AW785) -> -2.3746086
B5: taux de profit du secteur 04 | D5: =résultats!C596*résultats!C634/(résultats!C748*résultats!C786) -> 0 | E5: =résultats!D596*résultats!D634/(résultats!D748*résultats!D786) -> 0 | F5: =résultats!E596*résultats!E634/(résultats!E748*résultats!E786) -> -0.14995298 | G5: =résultats!F596*résultats!F634/(résultats!F748*résultats!F786) -> -0.16699672 | H5: =résultats!G596*résultats!G634/(résultats!G748*résultats!G786) -> -0.19740779 | I5: =résultats!H596*résultats!H634/(résultats!H748*résultats!H786) -> -0.27798697 | J5: =résultats!I596*résultats!I634/(résultats!I748*résultats!I786) -> -0.25834634 | K5: =résultats!J596*résultats!J634/(résultats!J748*résultats!J786) -> -0.11385242 | ... AX5: =résultats!AW596*résultats!AW634/(résultats!AW748*résultats!AW786) -> 0.32536918
B6: taux de profit du secteur 05 | D6: =résultats!C597*résultats!C635/(résultats!C749*résultats!C787) -> 0 | E6: =résultats!D597*résultats!D635/(résultats!D749*résultats!D787) -> 0 | F6: =résultats!E597*résultats!E635/(résultats!E749*résultats!E787) -> 0.10198844 | G6: =résultats!F597*résultats!F635/(résultats!F749*résultats!F787) -> 0.090015104 | H6: =résultats!G597*résultats!G635/(résultats!G749*résultats!G787) -> 0.079883284 | I6: =résultats!H597*résultats!H635/(résultats!H749*résultats!H787) -> 0.035800349 | J6: =résultats!I597*résultats!I635/(résultats!I749*résultats!I787) -> 0.0083265154 | K6: =résultats!J597*résultats!J635/(résultats!J749*résultats!J787) -> 0.10021936 | ... AX6: =résultats!AW597*résultats!AW635/(résultats!AW749*résultats!AW787) -> -0.0319538
B7: taux de profit du secteur 06 | D7: =résultats!C598*résultats!C636/(résultats!C750*résultats!C788) -> 0 | E7: =résultats!D598*résultats!D636/(résultats!D750*résultats!D788) -> 0 | F7: =résultats!E598*résultats!E636/(résultats!E750*résultats!E788) -> -0.10362457 | G7: =résultats!F598*résultats!F636/(résultats!F750*résultats!F788) -> -0.12389702 | H7: =résultats!G598*résultats!G636/(résultats!G750*résultats!G788) -> -0.15058704 | I7: =résultats!H598*résultats!H636/(résultats!H750*résultats!H788) -> -0.2138281 | J7: =résultats!I598*résultats!I636/(résultats!I750*résultats!I788) -> -0.19849119 | K7: =résultats!J598*résultats!J636/(résultats!J750*résultats!J788) -> -0.059264449 | ... AX7: =résultats!AW598*résultats!AW636/(résultats!AW750*résultats!AW788) -> 7.0093775
B8: taux de profit du secteur 07 | D8: =résultats!C599*résultats!C637/(résultats!C751*résultats!C789) -> 0 | E8: =résultats!D599*résultats!D637/(résultats!D751*résultats!D789) -> 0 | F8: =résultats!E599*résultats!E637/(résultats!E751*résultats!E789) -> -1.4048059 | G8: =résultats!F599*résultats!F637/(résultats!F751*résultats!F789) -> -1.4753344 | H8: =résultats!G599*résultats!G637/(résultats!G751*résultats!G789) -> -1.4857453 | I8: =résultats!H599*résultats!H637/(résultats!H751*résultats!H789) -> -1.4956492 | J8: =résultats!I599*résultats!I637/(résultats!I751*résultats!I789) -> -1.4663933 | K8: =résultats!J599*résultats!J637/(résultats!J751*résultats!J789) -> -1.4975985 | ... AX8: =résultats!AW599*résultats!AW637/(résultats!AW751*résultats!AW789) -> -3.0431729
B9: taux de profit du secteur 08 | D9: =résultats!C600*résultats!C638/(résultats!C752*résultats!C790) -> 0 | E9: =résultats!D600*résultats!D638/(résultats!D752*résultats!D790) -> 0 | F9: =résultats!E600*résultats!E638/(résultats!E752*résultats!E790) -> 0.064171195 | G9: =résultats!F600*résultats!F638/(résultats!F752*résultats!F790) -> 0.051653249 | H9: =résultats!G600*résultats!G638/(résultats!G752*résultats!G790) -> 0.025443432 | I9: =résultats!H600*résultats!H638/(résultats!H752*résultats!H790) -> -0.010540966 | J9: =résultats!I600*résultats!I638/(résultats!I752*résultats!I790) -> 0.091809914 | K9: =résultats!J600*résultats!J638/(résultats!J752*résultats!J790) -> -0.00067427171 | ... AX9: =résultats!AW600*résultats!AW638/(résultats!AW752*résultats!AW790) -> 0.11788208
B10: taux de profit du secteur 09 | D10: =résultats!C601*résultats!C639/(résultats!C753*résultats!C791) -> 0 | E10: =résultats!D601*résultats!D639/(résultats!D753*résultats!D791) -> 0 | F10: =résultats!E601*résultats!E639/(résultats!E753*résultats!E791) -> -0.010110392 | G10: =résultats!F601*résultats!F639/(résultats!F753*résultats!F791) -> -0.023743679 | H10: =résultats!G601*résultats!G639/(résultats!G753*résultats!G791) -> -0.01557274 | I10: =résultats!H601*résultats!H639/(résultats!H753*résultats!H791) -> -0.071286632 | J10: =résultats!I601*résultats!I639/(résultats!I753*résultats!I791) -> -0.12586034 | K10: =résultats!J601*résultats!J639/(résultats!J753*résultats!J791) -> 0.015003135 | ... AX10: =résultats!AW601*résultats!AW639/(résultats!AW753*résultats!AW791) -> -0.03069986
B11: taux de profit du secteur 10 | D11: =résultats!C602*résultats!C640/(résultats!C754*résultats!C792) -> 0 | E11: =résultats!D602*résultats!D640/(résultats!D754*résultats!D792) -> 0 | F11: =résultats!E602*résultats!E640/(résultats!E754*résultats!E792) -> 0.12768421 | G11: =résultats!F602*résultats!F640/(résultats!F754*résultats!F792) -> 0.12026196 | H11: =résultats!G602*résultats!G640/(résultats!G754*résultats!G792) -> 0.079612809 | I11: =résultats!H602*résultats!H640/(résultats!H754*résultats!H792) -> 0.045782567 | J11: =résultats!I602*résultats!I640/(résultats!I754*résultats!I792) -> -0.032459835 | K11: =résultats!J602*résultats!J640/(résultats!J754*résultats!J792) -> 0.21172632 | ... AX11: =résultats!AW602*résultats!AW640/(résultats!AW754*résultats!AW792) -> 0.06683275
B12: taux de profit du secteur 11 | D12: =résultats!C603*résultats!C641/(résultats!C755*résultats!C793) -> 0 | E12: =résultats!D603*résultats!D641/(résultats!D755*résultats!D793) -> 0 | F12: =résultats!E603*résultats!E641/(résultats!E755*résultats!E793) -> -0.021298662 | G12: =résultats!F603*résultats!F641/(résultats!F755*résultats!F793) -> -0.045168717 | H12: =résultats!G603*résultats!G641/(résultats!G755*résultats!G793) -> -0.12078134 | I12: =résultats!H603*résultats!H641/(résultats!H755*résultats!H793) -> -0.11387767 | J12: =résultats!I603*résultats!I641/(résultats!I755*résultats!I793) -> -0.14367054 | K12: =résultats!J603*résultats!J641/(résultats!J755*résultats!J793) -> 0.069157491 | ... AX12: =résultats!AW603*résultats!AW641/(résultats!AW755*résultats!AW793) -> -0.91476189
B13: taux de profit du secteur 12 | D13: =résultats!C604*résultats!C642/(résultats!C756*résultats!C794) -> 0 | E13: =résultats!D604*résultats!D642/(résultats!D756*résultats!D794) -> 0 | F13: =résultats!E604*résultats!E642/(résultats!E756*résultats!E794) -> 0.14022959 | G13: =résultats!F604*résultats!F642/(résultats!F756*résultats!F794) -> 0.12651204 | H13: =résultats!G604*résultats!G642/(résultats!G756*résultats!G794) -> 0.13835781 | I13: =résultats!H604*résultats!H642/(résultats!H756*résultats!H794) -> 0.1236868 | J13: =résultats!I604*résultats!I642/(résultats!I756*résultats!I794) -> 0.089280171 | K13: =résultats!J604*résultats!J642/(résultats!J756*résultats!J794) -> 0.13037538 | ... AX13: =résultats!AW604*résultats!AW642/(résultats!AW756*résultats!AW794) -> 0.12976674
B14: taux de profit du secteur 13 | D14: =résultats!C605*résultats!C643/(résultats!C757*résultats!C795) -> 0 | E14: =résultats!D605*résultats!D643/(résultats!D757*résultats!D795) -> 0 | F14: =résultats!E605*résultats!E643/(résultats!E757*résultats!E795) -> 0.26684707 | G14: =résultats!F605*résultats!F643/(résultats!F757*résultats!F795) -> 0.25223664 | H14: =résultats!G605*résultats!G643/(résultats!G757*résultats!G795) -> 0.27715862 | I14: =résultats!H605*résultats!H643/(résultats!H757*résultats!H795) -> 0.29416068 | J14: =résultats!I605*résultats!I643/(résultats!I757*résultats!I795) -> 0.23413574 | K14: =résultats!J605*résultats!J643/(résultats!J757*résultats!J795) -> 0.24100925 | ... AX14: =résultats!AW605*résultats!AW643/(résultats!AW757*résultats!AW795) -> 0.17800244
... B21: taux de profit du secteur 20 | D21: =résultats!C612*résultats!C650/(résultats!C764*résultats!C802) -> 0 | E21: =résultats!D612*résultats!D650/(résultats!D764*résultats!D802) -> 0 | F21: =résultats!E612*résultats!E650/(résultats!E764*résultats!E802) -> -0.02847956 | G21: =résultats!F612*résultats!F650/(résultats!F764*résultats!F802) -> -0.053414286 | H21: =résultats!G612*résultats!G650/(résultats!G764*résultats!G802) -> -0.066716291 | I21: =résultats!H612*résultats!H650/(résultats!H764*résultats!H802) -> -0.069259825 | J21: =résultats!I612*résultats!I650/(résultats!I764*résultats!I802) -> -0.056551516 | K21: =résultats!J612*résultats!J650/(résultats!J764*résultats!J802) -> -0.058119802 | ... AX21: =résultats!AW612*résultats!AW650/(résultats!AW764*résultats!AW802) -> -0.020858651
A22: AMS | B22: taux de profit du secteur 01 | D22: =résultats!C669*résultats!C707/(résultats!C745*résultats!C783) -> 0 | E22: =résultats!D669*résultats!D707/(résultats!D745*résultats!D783) -> 0 | F22: =résultats!E669*résultats!E707/(résultats!E745*résultats!E783) -> 0.3153017 | G22: =résultats!F669*résultats!F707/(résultats!F745*résultats!F783) -> 0.28794528 | H22: =résultats!G669*résultats!G707/(résultats!G745*résultats!G783) -> 0.28150983 | I22: =résultats!H669*résultats!H707/(résultats!H745*résultats!H783) -> 0.24702375 | J22: =résultats!I669*résultats!I707/(résultats!I745*résultats!I783) -> 0.26356396 | K22: =résultats!J669*résultats!J707/(résultats!J745*résultats!J783) -> 0.29120181 | ... AX22: =résultats!AW669*résultats!AW707/(résultats!AW745*résultats!AW783) -> 0.37220832
B23: taux de profit du secteur 02 | D23: =résultats!C670*résultats!C708/(résultats!C746*résultats!C784) -> 0 | E23: =résultats!D670*résultats!D708/(résultats!D746*résultats!D784) -> 0 | F23: =résultats!E670*résultats!E708/(résultats!E746*résultats!E784) -> 0.21442462 | G23: =résultats!F670*résultats!F708/(résultats!F746*résultats!F784) -> 0.19065248 | H23: =résultats!G670*résultats!G708/(résultats!G746*résultats!G784) -> 0.21115328 | I23: =résultats!H670*résultats!H708/(résultats!H746*résultats!H784) -> 0.16457804 | J23: =résultats!I670*résultats!I708/(résultats!I746*résultats!I784) -> 0.21094316 | K23: =résultats!J670*résultats!J708/(résultats!J746*résultats!J784) -> 0.19579752 | ... AX23: =résultats!AW670*résultats!AW708/(résultats!AW746*résultats!AW784) -> 0.11009019
B24: taux de profit du secteur 03 | D24: =résultats!C671*résultats!C709/(résultats!C747*résultats!C785) -> 0 | E24: =résultats!D671*résultats!D709/(résultats!D747*résultats!D785) -> 0 | F24: =résultats!E671*résultats!E709/(résultats!E747*résultats!E785) -> -0.081916677 | G24: =résultats!F671*résultats!F709/(résultats!F747*résultats!F785) -> -0.11514296 | H24: =résultats!G671*résultats!G709/(résultats!G747*résultats!G785) -> -0.18285581 | I24: =résultats!H671*résultats!H709/(résultats!H747*résultats!H785) -> -0.20427668 | J24: =résultats!I671*résultats!I709/(résultats!I747*résultats!I785) -> -0.16152618 | K24: =résultats!J671*résultats!J709/(résultats!J747*résultats!J785) -> -0.0061792214 | ... AX24: =résultats!AW671*résultats!AW709/(résultats!AW747*résultats!AW785) -> -1.7621845
B25: taux de profit du secteur 04 | D25: =résultats!C672*résultats!C710/(résultats!C748*résultats!C786) -> 0 | E25: =résultats!D672*résultats!D710/(résultats!D748*résultats!D786) -> 0 | F25: =résultats!E672*résultats!E710/(résultats!E748*résultats!E786) -> -0.14995298 | G25: =résultats!F672*résultats!F710/(résultats!F748*résultats!F786) -> -0.16699672 | H25: =résultats!G672*résultats!G710/(résultats!G748*résultats!G786) -> -0.19740779 | I25: =résultats!H672*résultats!H710/(résultats!H748*résultats!H786) -> -0.27798697 | J25: =résultats!I672*résultats!I710/(résultats!I748*résultats!I786) -> -0.25834634 | K25: =résultats!J672*résultats!J710/(résultats!J748*résultats!J786) -> -0.11385242 | ... AX25: =résultats!AW672*résultats!AW710/(résultats!AW748*résultats!AW786) -> 0.26838219
B26: taux de profit du secteur 05 | D26: =résultats!C673*résultats!C711/(résultats!C749*résultats!C787) -> 0 | E26: =résultats!D673*résultats!D711/(résultats!D749*résultats!D787) -> 0 | F26: =résultats!E673*résultats!E711/(résultats!E749*résultats!E787) -> 0.10198844 | G26: =résultats!F673*résultats!F711/(résultats!F749*résultats!F787) -> 0.090015104 | H26: =résultats!G673*résultats!G711/(résultats!G749*résultats!G787) -> 0.079883284 | I26: =résultats!H673*résultats!H711/(résultats!H749*résultats!H787) -> 0.035800349 | J26: =résultats!I673*résultats!I711/(résultats!I749*résultats!I787) -> 0.0083265154 | K26: =résultats!J673*résultats!J711/(résultats!J749*résultats!J787) -> 0.10021936 | ... AX26: =résultats!AW673*résultats!AW711/(résultats!AW749*résultats!AW787) -> -0.16095784
B27: taux de profit du secteur 06 | D27: =résultats!C674*résultats!C712/(résultats!C750*résultats!C788) -> 0 | E27: =résultats!D674*résultats!D712/(résultats!D750*résultats!D788) -> 0 | F27: =résultats!E674*résultats!E712/(résultats!E750*résultats!E788) -> -0.10362457 | G27: =résultats!F674*résultats!F712/(résultats!F750*résultats!F788) -> -0.12389702 | H27: =résultats!G674*résultats!G712/(résultats!G750*résultats!G788) -> -0.15058704 | I27: =résultats!H674*résultats!H712/(résultats!H750*résultats!H788) -> -0.2138281 | J27: =résultats!I674*résultats!I712/(résultats!I750*résultats!I788) -> -0.19849119 | K27: =résultats!J674*résultats!J712/(résultats!J750*résultats!J788) -> -0.059264449 | ... AX27: =résultats!AW674*résultats!AW712/(résultats!AW750*résultats!AW788) -> 10.326529
B28: taux de profit du secteur 07 | D28: =résultats!C675*résultats!C713/(résultats!C751*résultats!C789) -> 0 | E28: =résultats!D675*résultats!D713/(résultats!D751*résultats!D789) -> 0 | F28: =résultats!E675*résultats!E713/(résultats!E751*résultats!E789) -> -1.4048059 | G28: =résultats!F675*résultats!F713/(résultats!F751*résultats!F789) -> -1.4753344 | H28: =résultats!G675*résultats!G713/(résultats!G751*résultats!G789) -> -1.4857453 | I28: =résultats!H675*résultats!H713/(résultats!H751*résultats!H789) -> -1.4956492 | J28: =résultats!I675*résultats!I713/(résultats!I751*résultats!I789) -> -1.4663933 | K28: =résultats!J675*résultats!J713/(résultats!J751*résultats!J789) -> -1.4975985 | ... AX28: =résultats!AW675*résultats!AW713/(résultats!AW751*résultats!AW789) -> -4.0018815
B29: taux de profit du secteur 08 | D29: =résultats!C676*résultats!C714/(résultats!C752*résultats!C790) -> 0 | E29: =résultats!D676*résultats!D714/(résultats!D752*résultats!D790) -> 0 | F29: =résultats!E676*résultats!E714/(résultats!E752*résultats!E790) -> 0.064171195 | G29: =résultats!F676*résultats!F714/(résultats!F752*résultats!F790) -> 0.051653249 | H29: =résultats!G676*résultats!G714/(résultats!G752*résultats!G790) -> 0.025443432 | I29: =résultats!H676*résultats!H714/(résultats!H752*résultats!H790) -> -0.010540966 | J29: =résultats!I676*résultats!I714/(résultats!I752*résultats!I790) -> 0.091809914 | K29: =résultats!J676*résultats!J714/(résultats!J752*résultats!J790) -> -0.00067427171 | ... AX29: =résultats!AW676*résultats!AW714/(résultats!AW752*résultats!AW790) -> 0.10958392
B30: taux de profit du secteur 09 | D30: =résultats!C677*résultats!C715/(résultats!C753*résultats!C791) -> 0 | E30: =résultats!D677*résultats!D715/(résultats!D753*résultats!D791) -> 0 | F30: =résultats!E677*résultats!E715/(résultats!E753*résultats!E791) -> -0.010110392 | G30: =résultats!F677*résultats!F715/(résultats!F753*résultats!F791) -> -0.023743679 | H30: =résultats!G677*résultats!G715/(résultats!G753*résultats!G791) -> -0.01557274 | I30: =résultats!H677*résultats!H715/(résultats!H753*résultats!H791) -> -0.071286632 | J30: =résultats!I677*résultats!I715/(résultats!I753*résultats!I791) -> -0.12586034 | K30: =résultats!J677*résultats!J715/(résultats!J753*résultats!J791) -> 0.015003135 | ... AX30: =résultats!AW677*résultats!AW715/(résultats!AW753*résultats!AW791) -> -0.079175424
B31: taux de profit du secteur 10 | D31: =résultats!C678*résultats!C716/(résultats!C754*résultats!C792) -> 0 | E31: =résultats!D678*résultats!D716/(résultats!D754*résultats!D792) -> 0 | F31: =résultats!E678*résultats!E716/(résultats!E754*résultats!E792) -> 0.12768421 | G31: =résultats!F678*résultats!F716/(résultats!F754*résultats!F792) -> 0.12026196 | H31: =résultats!G678*résultats!G716/(résultats!G754*résultats!G792) -> 0.079612809 | I31: =résultats!H678*résultats!H716/(résultats!H754*résultats!H792) -> 0.045782567 | J31: =résultats!I678*résultats!I716/(résultats!I754*résultats!I792) -> -0.032459835 | K31: =résultats!J678*résultats!J716/(résultats!J754*résultats!J792) -> 0.21172632 | ... AX31: =résultats!AW678*résultats!AW716/(résultats!AW754*résultats!AW792) -> -0.076762043
B32: taux de profit du secteur 11 | D32: =résultats!C679*résultats!C717/(résultats!C755*résultats!C793) -> 0 | E32: =résultats!D679*résultats!D717/(résultats!D755*résultats!D793) -> 0 | F32: =résultats!E679*résultats!E717/(résultats!E755*résultats!E793) -> -0.021298662 | G32: =résultats!F679*résultats!F717/(résultats!F755*résultats!F793) -> -0.045168717 | H32: =résultats!G679*résultats!G717/(résultats!G755*résultats!G793) -> -0.12078134 | I32: =résultats!H679*résultats!H717/(résultats!H755*résultats!H793) -> -0.11387767 | J32: =résultats!I679*résultats!I717/(résultats!I755*résultats!I793) -> -0.14367054 | K32: =résultats!J679*résultats!J717/(résultats!J755*résultats!J793) -> 0.069157491 | ... AX32: =résultats!AW679*résultats!AW717/(résultats!AW755*résultats!AW793) -> -1.1507501
B33: taux de profit du secteur 12 | D33: =résultats!C680*résultats!C718/(résultats!C756*résultats!C794) -> 0 | E33: =résultats!D680*résultats!D718/(résultats!D756*résultats!D794) -> 0 | F33: =résultats!E680*résultats!E718/(résultats!E756*résultats!E794) -> 0.14022959 | G33: =résultats!F680*résultats!F718/(résultats!F756*résultats!F794) -> 0.12651204 | H33: =résultats!G680*résultats!G718/(résultats!G756*résultats!G794) -> 0.13835781 | I33: =résultats!H680*résultats!H718/(résultats!H756*résultats!H794) -> 0.1236868 | J33: =résultats!I680*résultats!I718/(résultats!I756*résultats!I794) -> 0.089280171 | K33: =résultats!J680*résultats!J718/(résultats!J756*résultats!J794) -> 0.13037538 | ... AX33: =résultats!AW680*résultats!AW718/(résultats!AW756*résultats!AW794) -> 0.1082689
B34: taux de profit du secteur 13 | D34: =résultats!C681*résultats!C719/(résultats!C757*résultats!C795) -> 0 | E34: =résultats!D681*résultats!D719/(résultats!D757*résultats!D795) -> 0 | F34: =résultats!E681*résultats!E719/(résultats!E757*résultats!E795) -> 0.26684707 | G34: =résultats!F681*résultats!F719/(résultats!F757*résultats!F795) -> 0.25223664 | H34: =résultats!G681*résultats!G719/(résultats!G757*résultats!G795) -> 0.27715862 | I34: =résultats!H681*résultats!H719/(résultats!H757*résultats!H795) -> 0.29416068 | J34: =résultats!I681*résultats!I719/(résultats!I757*résultats!I795) -> 0.23413574 | K34: =résultats!J681*résultats!J719/(résultats!J757*résultats!J795) -> 0.24100925 | ... AX34: =résultats!AW681*résultats!AW719/(résultats!AW757*résultats!AW795) -> 0.15326636
... B41: taux de profit du secteur 20 | D41: =résultats!C688*résultats!C726/(résultats!C764*résultats!C802) -> 0 | E41: =résultats!D688*résultats!D726/(résultats!D764*résultats!D802) -> 0 | F41: =résultats!E688*résultats!E726/(résultats!E764*résultats!E802) -> -0.02847956 | G41: =résultats!F688*résultats!F726/(résultats!F764*résultats!F802) -> -0.053414286 | H41: =résultats!G688*résultats!G726/(résultats!G764*résultats!G802) -> -0.066716291 | I41: =résultats!H688*résultats!H726/(résultats!H764*résultats!H802) -> -0.069259825 | J41: =résultats!I688*résultats!I726/(résultats!I764*résultats!I802) -> -0.056551516 | K41: =résultats!J688*résultats!J726/(résultats!J764*résultats!J802) -> -0.058119802 | ... AX41: =résultats!AW688*résultats!AW726/(résultats!AW764*résultats!AW802) -> -0.039025664

Sheet Parts VE
B1: 2004 | C1: 2005 | D1: 2006 | E1: 2007 | F1: 2008 | G1: 2009 | H1: 2010 | I1: 2011 | J1: 2012 | K1: 2013 | L1: 2014 | M1: 2015 | N1: 2016 | O1: 2017 | P1: 2018 | Q1: 2019 | R1: 2020 | S1: 2021 | T1: 2022 | U1: 2023 | V1: 2024 | W1: 2025 | X1: 2026 | Y1: 2027 | Z1: 2028 | AA1: 2029 | AB1: 2030 | AC1: 2031 | AD1: 2032 | AE1: 2033 | AF1: 2034 | AG1: 2035 | AH1: 2036 | AI1: 2037 | AJ1: 2038 | AK1: 2039 | AL1: 2040 | AM1: 2041 | AN1: 2042 | AO1: 2043 | AP1: 2044 | AQ1: 2045 | AR1: 2046 | AS1: 2047 | AT1: 2048 | AU1: 2049 | AV1: 2050
A2: =résultats!B584 -> NEWAUTO_ELEC_H01_2 | B2: =résultats!C584 -> 1.149299 | C2: =résultats!D584 -> 1.1677514 | D2: =résultats!E584 -> 2.1795284 | E2: =résultats!F584 -> 3.54705 | F2: =résultats!G584 -> 5.7124314 | G2: =résultats!H584 -> 9.1534476 | H2: =résultats!I584 -> 12.615368 | ... AV2: =résultats!AW584 -> 1464.903
A3: =résultats!B585 -> NEWAUTO_2 | B3: =résultats!C585 -> 2298.598 | C3: =résultats!D585 -> 2335.5027 | D3: =résultats!E585 -> 2373 | E3: =résultats!F585 -> 2446.6776 | F3: =résultats!G585 -> 2424.2766 | G3: =résultats!H585 -> 2660.3639 | H3: =résultats!I585 -> 2598.849 | ... AV3: =résultats!AW585 -> 1464.904
A4: =résultats!B586 -> AUTO_ELEC_2 | B4: =résultats!C586 -> 2.3360541 | C4: =résultats!D586 -> 2.3735602 | D4: =résultats!E586 -> 2.4116685 | E4: =résultats!F586 -> 5.8260767 | F4: =résultats!G586 -> 11.218074 | G4: =résultats!H586 -> 19.754527 | H4: =résultats!I586 -> 31.283396 | ... AV4: =résultats!AW586 -> 18313.318
A5: =résultats!B587 -> AUTO_2 | B5: =résultats!C587 -> 30998.43 | C5: =résultats!D587 -> 31496.12 | D5: =résultats!E587 -> 32001.8 | E5: =résultats!F587 -> 32688.379 | F5: =résultats!G587 -> 33314.795 | G5: =résultats!H587 -> 34142.845 | H5: =résultats!I587 -> 34863.837 | ... AV5: =résultats!AW587 -> 26760.313
A6: =résultats!B588 -> NEWAUTO_ELEC_H01_1 | B6: =résultats!C588 -> 1.149299 | C6: =résultats!D588 -> 1.1677514 | D6: =résultats!E588 -> 2.1795284 | E6: =résultats!F588 -> 3.54705 | F6: =résultats!G588 -> 5.7124314 | G6: =résultats!H588 -> 9.1534476 | H6: =résultats!I588 -> 12.615368 | ... AV6: =résultats!AW588 -> 1359.6054
A7: =résultats!B589 -> NEWAUTO_1 | B7: =résultats!C589 -> 2298.598 | C7: =résultats!D589 -> 2335.5027 | D7: =résultats!E589 -> 2373 | E7: =résultats!F589 -> 2446.6776 | F7: =résultats!G589 -> 2424.2766 | G7: =résultats!H589 -> 2660.3639 | H7: =résultats!I589 -> 2598.849 | ... AV7: =résultats!AW589 -> 2025.3853
A8: =résultats!B590 -> AUTO_ELEC_1 | B8: =résultats!C590 -> 2.3360541 | C8: =résultats!D590 -> 2.3735602 | D8: =résultats!E590 -> 2.4116685 | E8: =résultats!F590 -> 5.8260767 | F8: =résultats!G590 -> 11.218074 | G8: =résultats!H590 -> 19.754527 | H8: =résultats!I590 -> 31.283396 | ... AV8: =résultats!AW590 -> 14941.693
A9: =résultats!B591 -> AUTO_1 | B9: =résultats!C591 -> 30998.43 | C9: =résultats!D591 -> 31496.12 | D9: =résultats!E591 -> 32001.8 | E9: =résultats!F591 -> 32688.379 | F9: =résultats!G591 -> 33314.795 | G9: =résultats!H591 -> 34142.845 | H9: =résultats!I591 -> 34863.837 | ... AV9: =résultats!AW591 -> 34002.514
A11: part des ventes_2 | B11: =B2/B3 -> 0.0005 | C11: =C2/C3 -> 0.0005 | D11: =D2/D3 -> 0.00091846962 | E11: =E2/E3 -> 0.0014497415 | F11: =F2/F3 -> 0.0023563448 | G11: =G2/G3 -> 0.003440675 | H11: =H2/H3 -> 0.0048542135 | I11: =I2/I3 -> 0.0067431775 | ... AV11: =AV2/AV3 -> 0.99999931
A12: part des ventes_0 | B12: =B6/B7 -> 0.0005 | C12: =C6/C7 -> 0.0005 | D12: =D6/D7 -> 0.00091846962 | E12: =E6/E7 -> 0.0014497415 | F12: =F6/F7 -> 0.0023563448 | G12: =G6/G7 -> 0.003440675 | H12: =H6/H7 -> 0.0048542135 | I12: =I6/I7 -> 0.0067431775 | ... AV12: =AV6/AV7 -> 0.67128235
A13: réel observé | M13: 0.009006777 | N13: 0.010770076 | O13: 0.011801509 | P13: 0.014290296 | Q13: 0.019312885 | R13: 0.067217052 | S13: 0.097712903 | T13: 0.13271639
A15: part du parc_2 | B15: =B4/B5 -> 7.5360401e-05 | C15: =C4/C5 -> 7.5360401e-05 | D15: =D4/D5 -> 7.5360401e-05 | E15: =E4/E5 -> 0.00017823082 | F15: =F4/F5 -> 0.00033672949 | G15: =G4/G5 -> 0.00057858469 | H15: =H4/H5 -> 0.00089730215 | I15: =I4/I5 -> 0.0013161632 | ... AV15: =AV4/AV5 -> 0.68434617
A16: part du parc_0 | B16: =B8/B9 -> 7.5360401e-05 | C16: =C8/C9 -> 7.5360401e-05 | D16: =D8/D9 -> 7.5360401e-05 | E16: =E8/E9 -> 0.00017823082 | F16: =F8/F9 -> 0.00033672949 | G16: =G8/G9 -> 0.00057858469 | H16: =H8/H9 -> 0.00089730215 | I16: =I8/I9 -> 0.0013161632 | ... AV16: =AV8/AV9 -> 0.43942908

Sheet Rev_Dep_2
B1: 2004 | C1: 2005 | D1: 2006 | E1: 2007 | F1: 2008 | G1: 2009 | H1: 2010 | I1: 2011 | J1: 2012 | K1: 2013 | L1: 2014 | M1: 2015 | N1: 2016 | O1: 2017 | P1: 2018 | Q1: 2019 | R1: 2020 | S1: 2021 | T1: 2022 | U1: 2023 | V1: 2024 | W1: 2025 | X1: 2026 | Y1: 2027 | Z1: 2028 | AA1: 2029 | AB1: 2030 | AC1: 2031 | AD1: 2032 | AE1: 2033 | AF1: 2034 | AG1: 2035 | AH1: 2036 | AI1: 2037 | AJ1: 2038 | AK1: 2039 | AL1: 2040 | AM1: 2041 | AN1: 2042 | AO1: 2043 | AP1: 2044 | AQ1: 2045 | AR1: 2046 | AS1: 2047 | AT1: 2048 | AU1: 2049 | AV1: 2050
A2: =résultats!B470 -> TS_2 | B2: =résultats!C470 -> 0.043327542 | C2: =résultats!D470 -> 0.043327542 | D2: =résultats!E470 -> 0.059872177 | E2: =résultats!F470 -> 0.071907338 | F2: =résultats!G470 -> 0.080391001 | G2: =résultats!H470 -> 0.061875943 | H2: =résultats!I470 -> 0.034763886 | ... AV2: =résultats!AW470 -> 0.11299548
A3: =résultats!B471 -> TS_H01_2 | B3: =résultats!C471 -> 0.043327542 | C3: =résultats!D471 -> 0.043327542 | D3: =résultats!E471 -> 0.059872177 | E3: =résultats!F471 -> 0.071907338 | F3: =résultats!G471 -> 0.080391001 | G3: =résultats!H471 -> 0.061875943 | H3: =résultats!I471 -> 0.034763886 | ... AV3: =résultats!AW471 -> 0.11299548
A4: =résultats!B472 -> DISPINC_VAL_H01_2 | B4: =résultats!C472 -> 1079422.7 | C4: =résultats!D472 -> 1118688.3 | D4: =résultats!E472 -> 1148029.4 | E4: =résultats!F472 -> 1164739.4 | F4: =résultats!G472 -> 1195330.4 | G4: =résultats!H472 -> 1175909.3 | H4: =résultats!I472 -> 1164857.4 | ... AV4: =résultats!AW472 -> 3995963.3
A5: =résultats!B473 -> DISPINC_AI_VAL_H01_2 | B5: =résultats!C473 -> 1226094.8 | C5: =résultats!D473 -> 1270695.8 | D5: =résultats!E473 -> 1304023.8 | E5: =résultats!F473 -> 1328960 | F5: =résultats!G473 -> 1369991.9 | G5: =résultats!H473 -> 1353956.9 | H5: =résultats!I473 -> 1347772.3 | ... AV5: =résultats!AW473 -> 4680122.5
A6: =résultats!B474 -> IR_VAL_H01_2 | B6: =résultats!C474 -> 130354.82 | C6: =résultats!D474 -> 135096.67 | D6: =résultats!E474 -> 138640 | E6: =résultats!F474 -> 147514.56 | F6: =résultats!G474 -> 157549.07 | G6: =résultats!H474 -> 161120.87 | H6: =résultats!I474 -> 165776 | ... AV6: =résultats!AW474 -> 631816.53
A7: =résultats!B475 -> AIC_VAL_H01_2 | B7: =résultats!C475 -> 16317.279 | C7: =résultats!D475 -> 16910.844 | D7: =résultats!E475 -> 17354.384 | E7: =résultats!F475 -> 17686.243 | F7: =résultats!G475 -> 18232.309 | G7: =résultats!H475 -> 18018.91 | H7: =résultats!I475 -> 17936.604 | ... AV7: =résultats!AW475 -> 62284.632
A8: =résultats!B476 -> SUB_AUTO_VAL_2 | B8: =résultats!C476 -> 0 | C8: =résultats!D476 -> 0 | D8: =résultats!E476 -> 0 | E8: =résultats!F476 -> 0 | F8: =résultats!G476 -> -146.2765 | G8: =résultats!H476 -> -138.78175 | H8: =résultats!I476 -> -122.74094 | ... AV8: =résultats!AW476 -> 1946.0858
A9: =résultats!B477 -> SUB_RENOV_VAL_2 | B9: =résultats!C477 -> 0 | C9: =résultats!D477 -> 0 | D9: =résultats!E477 -> 0 | E9: =résultats!F477 -> 980.22799 | F9: =résultats!G477 -> 1266.1941 | G9: =résultats!H477 -> 1230.9552 | H9: =résultats!I477 -> 920.36014 | ... AV9: =résultats!AW477 -> 7995.9634
A10: =résultats!B478 -> EXP_H01_2 | B10: =résultats!C478 -> 1074373.2 | C10: =résultats!D478 -> 1091622.6 | D10: =résultats!E478 -> 1093371.1 | E10: =résultats!F478 -> 1120073.4 | F10: =résultats!G478 -> 1121282.5 | G10: =résultats!H478 -> 1118384.9 | H10: =résultats!I478 -> 1132035.4 | ... AV10: =résultats!AW478 -> 1696198.5
A11: =résultats!B479 -> EXP_11_H01_2 | B11: =résultats!C479 -> 158.85802 | C11: =résultats!D479 -> 161.40853 | D11: =résultats!E479 -> 160.90834 | E11: =résultats!F479 -> 153.09755 | F11: =résultats!G479 -> 144.51275 | G11: =résultats!H479 -> 149.96616 | H11: =résultats!I479 -> 145.83813 | ... AV11: =résultats!AW479 -> 191.00438
A12: =résultats!B480 -> EXP_12_H01_2 | B12: =résultats!C480 -> 173659.52 | C12: =résultats!D480 -> 176447.68 | D12: =résultats!E480 -> 175900.88 | E12: =résultats!F480 -> 183029.1 | F12: =résultats!G480 -> 182209.1 | G12: =résultats!H480 -> 179009.91 | H12: =résultats!I480 -> 181991.78 | ... AV12: =résultats!AW480 -> 303636.13
A13: =résultats!B481 -> EXP_13_H01_2 | B13: =résultats!C481 -> 87751.619 | C13: =résultats!D481 -> 89160.499 | D13: =résultats!E481 -> 90592 | E13: =résultats!F481 -> 94648.266 | F13: =résultats!G481 -> 95762.725 | G13: =résultats!H481 -> 91338.84 | H13: =résultats!I481 -> 92842.624 | ... AV13: =résultats!AW481 -> 51001.745
... A43: =résultats!B511 -> PEXP_19_H01_2 | B43: =résultats!C511 -> 0.96116878 | C43: =résultats!D511 -> 0.98039216 | D43: =résultats!E511 -> 0.9837325 | E43: =résultats!F511 -> 0.98436697 | F43: =résultats!G511 -> 0.99089004 | G43: =résultats!H511 -> 0.99624618 | H43: =résultats!I511 -> 0.99889057 | ... AV43: =résultats!AW511 -> 2.0228154
A44: =résultats!B513 -> PEXP_11_H01_2 | B44: =résultats!C513 -> 0.96116878 | C44: =résultats!D513 -> 0.98039216 | D44: =résultats!E513 -> 0.99593316 | E44: =résultats!F513 -> 1.0162647 | F44: =résultats!G513 -> 1.0379344 | G44: =résultats!H513 -> 1.0734794 | H44: =résultats!I513 -> 1.0827334 | ... AV44: =résultats!AW513 -> 2.3953736
A45: =résultats!B514 -> PEXP_12_H01_2 | B45: =résultats!C514 -> 0.96116878 | C45: =résultats!D514 -> 0.98039216 | D45: =résultats!E514 -> 0.99383755 | E45: =résultats!F514 -> 1.0033421 | F45: =résultats!G514 -> 1.0182408 | G45: =résultats!H514 -> 1.0330775 | H45: =résultats!I514 -> 1.046881 | ... AV45: =résultats!AW514 -> 2.2493911
A46: =résultats!B515 -> PEXP_13_H01_2 | B46: =résultats!C515 -> 0.96116878 | C46: =résultats!D515 -> 0.98039216 | D46: =résultats!E515 -> 0.99122367 | E46: =résultats!F515 -> 0.68991245 | F46: =résultats!G515 -> 0.70621589 | G46: =résultats!H515 -> 0.76095095 | H46: =résultats!I515 -> 0.75905853 | ... AV46: =résultats!AW515 -> 1.5679265
A47: =résultats!B516 -> PEXP_14_H01_2 | B47: =résultats!C516 -> 0.96116878 | C47: =résultats!D516 -> 0.98039216 | D47: =résultats!E516 -> 0.95102807 | E47: =résultats!F516 -> 0.93439337 | F47: =résultats!G516 -> 0.93660241 | G47: =résultats!H516 -> 0.94439681 | H47: =résultats!I516 -> 0.95028717 | ... AV47: =résultats!AW516 -> 2.0318636
A48: =résultats!B517 -> PEXP_15_H01_2 | B48: =résultats!C517 -> 0.96116878 | C48: =résultats!D517 -> 0.98039216 | D48: =résultats!E517 -> 0.97104877 | E48: =résultats!F517 -> 0.96078678 | F48: =résultats!G517 -> 0.97739248 | G48: =résultats!H517 -> 0.9891453 | H48: =résultats!I517 -> 0.99115291 | ... AV48: =résultats!AW517 -> 2.0101107
A49: =résultats!B518 -> PEXP_16_H01_2 | B49: =résultats!C518 -> 0.96116878 | C49: =résultats!D518 -> 0.98039216 | D49: =résultats!E518 -> 0.97816509 | E49: =résultats!F518 -> 0.97484316 | F49: =résultats!G518 -> 0.99531664 | G49: =résultats!H518 -> 1.0064764 | H49: =résultats!I518 -> 1.0162634 | ... AV49: =résultats!AW518 -> 2.1636959
A50: =résultats!B519 -> PEXP_17_H01_2 | B50: =résultats!C519 -> 0.96116878 | C50: =résultats!D519 -> 0.98039216 | D50: =résultats!E519 -> 0.99002992 | E50: =résultats!F519 -> 0.9577938 | F50: =résultats!G519 -> 0.97260678 | G50: =résultats!H519 -> 0.99354736 | H50: =résultats!I519 -> 0.96188911 | ... AV50: =résultats!AW519 -> 2.3412028
A51: =résultats!B520 -> PEXP_18_H01_2 | B51: =résultats!C520 -> 0.96116878 | C51: =résultats!D520 -> 0.98039216 | D51: =résultats!E520 -> 0.98820501 | E51: =résultats!F520 -> 0.98720138 | F51: =résultats!G520 -> 0.99154775 | G51: =résultats!H520 -> 1.0066915 | H51: =résultats!I520 -> 1.0279191 | ... AV51: =résultats!AW520 -> 2.1090912
A52: =résultats!B521 -> PEXP_19_H01_2 | B52: =résultats!C521 -> 0.96116878 | C52: =résultats!D521 -> 0.98039216 | D52: =résultats!E521 -> 0.9837325 | E52: =résultats!F521 -> 0.98436697 | F52: =résultats!G521 -> 0.99089004 | G52: =résultats!H521 -> 0.99624618 | H52: =résultats!I521 -> 0.99889057 | ... AV52: =résultats!AW521 -> 2.0228154
A53: =résultats!B522 -> PEXP_20_H01_2 | B53: =résultats!C522 -> 0.96116878 | C53: =résultats!D522 -> 0.98039216 | D53: =résultats!E522 -> 0.97820262 | E53: =résultats!F522 -> 0.9849402 | F53: =résultats!G522 -> 0.9981813 | G53: =résultats!H522 -> 0.99948864 | H53: =résultats!I522 -> 0.99957712 | ... AV53: =résultats!AW522 -> 1.9999019
A54: =résultats!B523 -> PEXP_21_H01_2 | B54: =résultats!C523 -> 0.96116878 | C54: =résultats!D523 -> 0.98039216 | D54: =résultats!E523 -> 0.98363517 | E54: =résultats!F523 -> 0.97216457 | F54: =résultats!G523 -> 1.4123615 | G54: =résultats!H523 -> 1.1671459 | H54: =résultats!I523 -> 1.3903599 | ... AV54: =résultats!AW523 -> 4.900069
A55: =résultats!B524 -> PEXP_22_H01_2 | B55: =résultats!C524 -> 0.96116878 | C55: =résultats!D524 -> 0.98039216 | D55: =résultats!E524 -> 0.98801922 | E55: =résultats!F524 -> 0.98669514 | F55: =résultats!G524 -> 1.0865794 | G55: =résultats!H524 -> 0.92639211 | H55: =résultats!I524 -> 1.0063821 | ... AV55: =résultats!AW524 -> 2.2105834
... A57: =résultats!B526 -> PEXP_24_H01_2 | B57: =résultats!C526 -> 0.96116878 | C57: =résultats!D526 -> 0.98039216 | D57: =résultats!E526 -> 0.96898725 | E57: =résultats!F526 -> 0.95296796 | F57: =résultats!G526 -> 1.0053635 | G57: =résultats!H526 -> 0.94205991 | H57: =résultats!I526 -> 0.9414914 | ... AV57: =résultats!AW526 -> 2.074484
A58: pexp*exp | B58: =B34*B10 -> 1032654 | C58: =C34*C10 -> 1070218.3 | D58: =D34*D10 -> 1079294.4 | E58: =E34*E10 -> 1080986.1 | F58: =F34*F10 -> 1099236.6 | G58: =G34*G10 -> 1103148.8 | H58: =H34*H10 -> 1124362.4 | I58: =I34*I10 -> 1142132.6 | ... AV58: =AV34*AV10 -> 3544437.6
A59: pexp*exp_1 | B59: =B35*B11 -> 152.68937 | C59: =C35*C11 -> 158.24366 | D59: =D35*D11 -> 160.25396 | E59: =E35*E11 -> 155.58764 | F59: =F35*F11 -> 149.99476 | G59: =G35*G11 -> 160.98558 | H59: =H35*H11 -> 157.90381 | I59: =I35*I11 -> 154.6657 | ... AV59: =AV35*AV11 -> 457.52685
A60: pexp*exp_2 | B60: =B36*B12 -> 166916.11 | C60: =C36*C12 -> 172987.92 | D60: =D36*D12 -> 174816.9 | E60: =E36*E12 -> 183640.81 | F60: =F36*F12 -> 185532.73 | G60: =G36*G12 -> 184931.11 | H60: =H36*H12 -> 190523.75 | I60: =I36*I12 -> 194568.7 | ... AV60: =AV36*AV12 -> 682996.43
A61: pexp*exp_3 | B61: =B37*B13 -> 84344.116 | C61: =C37*C13 -> 87412.254 | D61: =D37*D13 -> 89796.935 | E61: =E37*E13 -> 65299.018 | F61: =F37*F13 -> 67629.158 | G61: =G37*G13 -> 69504.376 | H61: =H37*H13 -> 70472.986 | I61: =I37*I13 -> 72475.426 | ... AV61: =AV37*AV13 -> 79966.986
A62: pexp*exp_4 | B62: =B38*B14 -> 3891.4423 | C62: =C38*C14 -> 4032.9991 | D62: =D38*D14 -> 3975.017 | E62: =E38*E14 -> 3991.0348 | F62: =F38*F14 -> 4214.9865 | G62: =G38*G14 -> 4234.4797 | H62: =H38*H14 -> 4356.2334 | I62: =I38*I14 -> 4405.1963 | ... AV62: =AV38*AV14 -> 17409.699
A63: pexp*exp_5 | B63: =B39*B15 -> 8600.8803 | C63: =C39*C15 -> 8913.7496 | D63: =D39*D15 -> 8970.5485 | E63: =E39*E15 -> 9070.1629 | F63: =F39*F15 -> 9721.6999 | G63: =G39*G15 -> 9802.5246 | H63: =H39*H15 -> 10042.209 | I63: =I39*I15 -> 10302.586 | ... AV63: =AV39*AV15 -> 27873.611
A64: pexp*exp_6 | B64: =B40*B16 -> 631.35728 | C64: =C40*C16 -> 654.3238 | D64: =D40*D16 -> 650.81435 | E64: =E40*E16 -> 662.81118 | F64: =F40*F16 -> 713.01963 | G64: =G40*G16 -> 718.37041 | H64: =H40*H16 -> 741.58661 | I64: =I40*I16 -> 760.74691 | ... AV64: =AV40*AV16 -> 2773.4513
A65: pexp*exp_7 | B65: =B41*B17 -> 334.35307 | C65: =C41*C17 -> 346.51564 | D65: =D41*D17 -> 348.83769 | E65: =E41*E17 -> 349.08318 | F65: =F41*F17 -> 356.41897 | G65: =G41*G17 -> 360.15684 | H65: =H41*H17 -> 361.5604 | I65: =I41*I17 -> 372.25486 | ... AV65: =AV41*AV17 -> 1511.2944
A66: pexp*exp_8 | B66: =B42*B18 -> 6830.1011 | C66: =C42*C18 -> 7078.5558 | D66: =D42*D18 -> 7249.5196 | E66: =E42*E18 -> 7586.036 | F66: =F42*F18 -> 7832.0573 | G66: =G42*G18 -> 7662.4063 | H66: =H42*H18 -> 7911.8183 | I66: =I42*I18 -> 8361.1681 | ... AV66: =AV42*AV18 -> 10607.22
A67: pexp*exp_9 | B67: =B43*B19 -> 454127.97 | C67: =C43*C19 -> 470647.52 | D67: =D43*D19 -> 470787.63 | E67: =E43*E19 -> 481577.97 | F67: =F43*F19 -> 487316.13 | G67: =G43*G19 -> 488991.51 | H67: =H43*H19 -> 496716.41 | I67: =I43*I19 -> 500170.62 | ... AV67: =AV43*AV19 -> 1820329.3
A68: pexp*exp_11 | B68: =B44*B20 -> 152.68937 | C68: =C44*C20 -> 158.24366 | D68: =D44*D20 -> 160.25396 | E68: =E44*E20 -> 155.58764 | F68: =F44*F20 -> 149.99476 | G68: =G44*G20 -> 160.98558 | H68: =H44*H20 -> 157.90381 | I68: =I44*I20 -> 154.6657 | ... AV68: =AV44*AV20 -> 457.52685
A69: pexp*exp_12 | B69: =B45*B21 -> 166916.11 | C69: =C45*C21 -> 172987.92 | D69: =D45*D21 -> 174816.9 | E69: =E45*E21 -> 183640.81 | F69: =F45*F21 -> 185532.73 | G69: =G45*G21 -> 184931.11 | H69: =H45*H21 -> 190523.75 | I69: =I45*I21 -> 194568.7 | ... AV69: =AV45*AV21 -> 682996.43
... A81: pexp*exp_24 | B81: =B57*B33 -> 9745.1207 | C81: =C57*C33 -> 10099.613 | D81: =D57*D33 -> 10142.391 | E81: =E57*E33 -> 10018.905 | F81: =F57*F33 -> 10460.97 | G81: =G57*G33 -> 9763.0498 | H81: =H57*H33 -> 9927.0214 | I81: =I57*I33 -> 10354.01 | ... AV81: =AV57*AV33 -> 9677.5899

Sheet Rev_Dep_0
B1: 2004 | C1: 2005 | D1: 2006 | E1: 2007 | F1: 2008 | G1: 2009 | H1: 2010 | I1: 2011 | J1: 2012 | K1: 2013 | L1: 2014 | M1: 2015 | N1: 2016 | O1: 2017 | P1: 2018 | Q1: 2019 | R1: 2020 | S1: 2021 | T1: 2022 | U1: 2023 | V1: 2024 | W1: 2025 | X1: 2026 | Y1: 2027 | Z1: 2028 | AA1: 2029 | AB1: 2030 | AC1: 2031 | AD1: 2032 | AE1: 2033 | AF1: 2034 | AG1: 2035 | AH1: 2036 | AI1: 2037 | AJ1: 2038 | AK1: 2039 | AL1: 2040 | AM1: 2041 | AN1: 2042 | AO1: 2043 | AP1: 2044 | AQ1: 2045 | AR1: 2046 | AS1: 2047 | AT1: 2048 | AU1: 2049 | AV1: 2050
A2: =résultats!B527 -> TS_1 | B2: =résultats!C527 -> 0.043327542 | C2: =résultats!D527 -> 0.043327542 | D2: =résultats!E527 -> 0.059872177 | E2: =résultats!F527 -> 0.071907338 | F2: =résultats!G527 -> 0.080391001 | G2: =résultats!H527 -> 0.061875943 | H2: =résultats!I527 -> 0.034763886 | ... AV2: =résultats!AW527 -> 0.10889261
A3: =résultats!B528 -> TS_H01_1 | B3: =résultats!C528 -> 0.043327542 | C3: =résultats!D528 -> 0.043327542 | D3: =résultats!E528 -> 0.059872177 | E3: =résultats!F528 -> 0.071907338 | F3: =résultats!G528 -> 0.080391001 | G3: =résultats!H528 -> 0.061875943 | H3: =résultats!I528 -> 0.034763886 | ... AV3: =résultats!AW528 -> 0.10889261
A4: =résultats!B529 -> DISPINC_VAL_H01_1 | B4: =résultats!C529 -> 1079422.7 | C4: =résultats!D529 -> 1118688.3 | D4: =résultats!E529 -> 1148029.4 | E4: =résultats!F529 -> 1164739.4 | F4: =résultats!G529 -> 1195330.4 | G4: =résultats!H529 -> 1175909.3 | H4: =résultats!I529 -> 1164857.4 | ... AV4: =résultats!AW529 -> 3819890.9
A5: =résultats!B530 -> DISPINC_AI_VAL_H01_1 | B5: =résultats!C530 -> 1226094.8 | C5: =résultats!D530 -> 1270695.8 | D5: =résultats!E530 -> 1304023.8 | E5: =résultats!F530 -> 1328960 | F5: =résultats!G530 -> 1369991.9 | G5: =résultats!H530 -> 1353956.9 | H5: =résultats!I530 -> 1347772.3 | ... AV5: =résultats!AW530 -> 4480933.7
A6: =résultats!B531 -> IR_VAL_H01_1 | B6: =résultats!C531 -> 130354.82 | C6: =résultats!D531 -> 135096.67 | D6: =résultats!E531 -> 138640 | E6: =résultats!F531 -> 147514.56 | F6: =résultats!G531 -> 157549.07 | G6: =résultats!H531 -> 161120.87 | H6: =résultats!I531 -> 165776 | ... AV6: =résultats!AW531 -> 604926.05
A7: =résultats!B532 -> AIC_VAL_H01_1 | B7: =résultats!C532 -> 16317.279 | C7: =résultats!D532 -> 16910.844 | D7: =résultats!E532 -> 17354.384 | E7: =résultats!F532 -> 17686.243 | F7: =résultats!G532 -> 18232.309 | G7: =résultats!H532 -> 18018.91 | H7: =résultats!I532 -> 17936.604 | ... AV7: =résultats!AW532 -> 59633.762
A8: =résultats!B533 -> SUB_AUTO_VAL_1 | B8: =résultats!C533 -> 0 | C8: =résultats!D533 -> 0 | D8: =résultats!E533 -> 0 | E8: =résultats!F533 -> 0 | F8: =résultats!G533 -> -146.2765 | G8: =résultats!H533 -> -138.78175 | H8: =résultats!I533 -> -122.74094 | ... AV8: =résultats!AW533 -> 3516.9996
A9: =résultats!B534 -> SUB_RENOV_VAL_1 | B9: =résultats!C534 -> 0 | C9: =résultats!D534 -> 0 | D9: =résultats!E534 -> 0 | E9: =résultats!F534 -> 980.22799 | F9: =résultats!G534 -> 1266.1941 | G9: =résultats!H534 -> 1230.9552 | H9: =résultats!I534 -> 920.36014 | ... AV9: =résultats!AW534 -> 0
A10: =résultats!B535 -> EXP_H01_1 | B10: =résultats!C535 -> 1074373.2 | C10: =résultats!D535 -> 1091622.6 | D10: =résultats!E535 -> 1093371.1 | E10: =résultats!F535 -> 1120073.4 | F10: =résultats!G535 -> 1121282.5 | G10: =résultats!H535 -> 1118384.9 | H10: =résultats!I535 -> 1132035.4 | ... AV10: =résultats!AW535 -> 1674953.4
A11: =résultats!B536 -> EXP_11_H01_1 | B11: =résultats!C536 -> 158.85802 | C11: =résultats!D536 -> 161.40853 | D11: =résultats!E536 -> 160.90834 | E11: =résultats!F536 -> 153.09755 | F11: =résultats!G536 -> 144.51275 | G11: =résultats!H536 -> 149.96616 | H11: =résultats!I536 -> 145.83813 | ... AV11: =résultats!AW536 -> 180.59642
A12: =résultats!B537 -> EXP_12_H01_1 | B12: =résultats!C537 -> 173659.52 | C12: =résultats!D537 -> 176447.68 | D12: =résultats!E537 -> 175900.88 | E12: =résultats!F537 -> 183029.1 | F12: =résultats!G537 -> 182209.1 | G12: =résultats!H537 -> 179009.91 | H12: =résultats!I537 -> 181991.78 | ... AV12: =résultats!AW537 -> 297610.87
A13: =résultats!B538 -> EXP_13_H01_1 | B13: =résultats!C538 -> 87751.619 | C13: =résultats!D538 -> 89160.499 | D13: =résultats!E538 -> 90592 | E13: =résultats!F538 -> 94648.266 | F13: =résultats!G538 -> 95762.725 | G13: =résultats!H538 -> 91338.84 | H13: =résultats!I538 -> 92842.624 | ... AV13: =résultats!AW538 -> 63184.743
... A43: =résultats!B568 -> PEXP_19_H01_1 | B43: =résultats!C568 -> 0.96116878 | C43: =résultats!D568 -> 0.98039216 | D43: =résultats!E568 -> 0.9837325 | E43: =résultats!F568 -> 0.98436697 | F43: =résultats!G568 -> 0.99089004 | G43: =résultats!H568 -> 0.99624618 | H43: =résultats!I568 -> 0.99889057 | ... AV43: =résultats!AW568 -> 1.9521126
A44: =résultats!B570 -> PEXP_11_H01_1 | B44: =résultats!C570 -> 0.96116878 | C44: =résultats!D570 -> 0.98039216 | D44: =résultats!E570 -> 0.99593316 | E44: =résultats!F570 -> 1.0162647 | F44: =résultats!G570 -> 1.0379344 | G44: =résultats!H570 -> 1.0734794 | H44: =résultats!I570 -> 1.0827334 | ... AV44: =résultats!AW570 -> 2.3387009
A45: =résultats!B571 -> PEXP_12_H01_1 | B45: =résultats!C571 -> 0.96116878 | C45: =résultats!D571 -> 0.98039216 | D45: =résultats!E571 -> 0.99383755 | E45: =résultats!F571 -> 1.0033421 | F45: =résultats!G571 -> 1.0182408 | G45: =résultats!H571 -> 1.0330775 | H45: =résultats!I571 -> 1.046881 | ... AV45: =résultats!AW571 -> 2.1860853
A46: =résultats!B572 -> PEXP_13_H01_1 | B46: =résultats!C572 -> 0.96116878 | C46: =résultats!D572 -> 0.98039216 | D46: =résultats!E572 -> 0.99122367 | E46: =résultats!F572 -> 0.68991245 | F46: =résultats!G572 -> 0.70621589 | G46: =résultats!H572 -> 0.76095095 | H46: =résultats!I572 -> 0.75905853 | ... AV46: =résultats!AW572 -> 1.8180373
A47: =résultats!B573 -> PEXP_14_H01_1 | B47: =résultats!C573 -> 0.96116878 | C47: =résultats!D573 -> 0.98039216 | D47: =résultats!E573 -> 0.95102807 | E47: =résultats!F573 -> 0.93439337 | F47: =résultats!G573 -> 0.93660241 | G47: =résultats!H573 -> 0.94439681 | H47: =résultats!I573 -> 0.95028717 | ... AV47: =résultats!AW573 -> 1.8945288
A48: =résultats!B574 -> PEXP_15_H01_1 | B48: =résultats!C574 -> 0.96116878 | C48: =résultats!D574 -> 0.98039216 | D48: =résultats!E574 -> 0.97104877 | E48: =résultats!F574 -> 0.96078678 | F48: =résultats!G574 -> 0.97739248 | G48: =résultats!H574 -> 0.9891453 | H48: =résultats!I574 -> 0.99115291 | ... AV48: =résultats!AW574 -> 1.9128987
A49: =résultats!B575 -> PEXP_16_H01_1 | B49: =résultats!C575 -> 0.96116878 | C49: =résultats!D575 -> 0.98039216 | D49: =résultats!E575 -> 0.97816509 | E49: =résultats!F575 -> 0.97484316 | F49: =résultats!G575 -> 0.99531664 | G49: =résultats!H575 -> 1.0064764 | H49: =résultats!I575 -> 1.0162634 | ... AV49: =résultats!AW575 -> 2.0801868
A50: =résultats!B576 -> PEXP_17_H01_1 | B50: =résultats!C576 -> 0.96116878 | C50: =résultats!D576 -> 0.98039216 | D50: =résultats!E576 -> 0.99002992 | E50: =résultats!F576 -> 0.9577938 | F50: =résultats!G576 -> 0.97260678 | G50: =résultats!H576 -> 0.99354736 | H50: =résultats!I576 -> 0.96188911 | ... AV50: =résultats!AW576 -> 2.2648694
A51: =résultats!B577 -> PEXP_18_H01_1 | B51: =résultats!C577 -> 0.96116878 | C51: =résultats!D577 -> 0.98039216 | D51: =résultats!E577 -> 0.98820501 | E51: =résultats!F577 -> 0.98720138 | F51: =résultats!G577 -> 0.99154775 | G51: =résultats!H577 -> 1.0066915 | H51: =résultats!I577 -> 1.0279191 | ... AV51: =résultats!AW577 -> 2.0566419
A52: =résultats!B578 -> PEXP_19_H01_1 | B52: =résultats!C578 -> 0.96116878 | C52: =résultats!D578 -> 0.98039216 | D52: =résultats!E578 -> 0.9837325 | E52: =résultats!F578 -> 0.98436697 | F52: =résultats!G578 -> 0.99089004 | G52: =résultats!H578 -> 0.99624618 | H52: =résultats!I578 -> 0.99889057 | ... AV52: =résultats!AW578 -> 1.9521126
A53: =résultats!B579 -> PEXP_20_H01_1 | B53: =résultats!C579 -> 0.96116878 | C53: =résultats!D579 -> 0.98039216 | D53: =résultats!E579 -> 0.97820262 | E53: =résultats!F579 -> 0.9849402 | F53: =résultats!G579 -> 0.9981813 | G53: =résultats!H579 -> 0.99948864 | H53: =résultats!I579 -> 0.99957712 | ... AV53: =résultats!AW579 -> 1.936858
A54: =résultats!B580 -> PEXP_21_H01_1 | B54: =résultats!C580 -> 0.96116878 | C54: =résultats!D580 -> 0.98039216 | D54: =résultats!E580 -> 0.98363517 | E54: =résultats!F580 -> 0.97216457 | F54: =résultats!G580 -> 1.4123615 | G54: =résultats!H580 -> 1.1671459 | H54: =résultats!I580 -> 1.3903599 | ... AV54: =résultats!AW580 -> 5.9268088
A55: =résultats!B581 -> PEXP_22_H01_1 | B55: =résultats!C581 -> 0.96116878 | C55: =résultats!D581 -> 0.98039216 | D55: =résultats!E581 -> 0.98801922 | E55: =résultats!F581 -> 0.98669514 | F55: =résultats!G581 -> 1.0865794 | G55: =résultats!H581 -> 0.92639211 | H55: =résultats!I581 -> 1.0063821 | ... AV55: =résultats!AW581 -> 2.1234273
... A57: =résultats!B583 -> PEXP_24_H01_1 | B57: =résultats!C583 -> 0.96116878 | C57: =résultats!D583 -> 0.98039216 | D57: =résultats!E583 -> 0.96898725 | E57: =résultats!F583 -> 0.95296796 | F57: =résultats!G583 -> 1.0053635 | G57: =résultats!H583 -> 0.94205991 | H57: =résultats!I583 -> 0.9414914 | ... AV57: =résultats!AW583 -> 2.0520996
A58: pexp*exp | B58: =B34*B10 -> 1032654 | C58: =C34*C10 -> 1070218.3 | D58: =D34*D10 -> 1079294.4 | E58: =E34*E10 -> 1080986.1 | F58: =F34*F10 -> 1099236.6 | G58: =G34*G10 -> 1103148.8 | H58: =H34*H10 -> 1124362.4 | I58: =I34*I10 -> 1142132.6 | ... AV58: =AV34*AV10 -> 3403933
A59: pexp*exp_1 | B59: =B35*B11 -> 152.68937 | C59: =C35*C11 -> 158.24366 | D59: =D35*D11 -> 160.25396 | E59: =E35*E11 -> 155.58764 | F59: =F35*F11 -> 149.99476 | G59: =G35*G11 -> 160.98558 | H59: =H35*H11 -> 157.90381 | I59: =I35*I11 -> 154.6657 | ... AV59: =AV35*AV11 -> 422.36102
A60: pexp*exp_2 | B60: =B36*B12 -> 166916.11 | C60: =C36*C12 -> 172987.92 | D60: =D36*D12 -> 174816.9 | E60: =E36*E12 -> 183640.81 | F60: =F36*F12 -> 185532.73 | G60: =G36*G12 -> 184931.11 | H60: =H36*H12 -> 190523.75 | I60: =I36*I12 -> 194568.7 | ... AV60: =AV36*AV12 -> 650602.75
A61: pexp*exp_3 | B61: =B37*B13 -> 84344.116 | C61: =C37*C13 -> 87412.254 | D61: =D37*D13 -> 89796.935 | E61: =E37*E13 -> 65299.018 | F61: =F37*F13 -> 67629.158 | G61: =G37*G13 -> 69504.376 | H61: =H37*H13 -> 70472.986 | I61: =I37*I13 -> 72475.426 | ... AV61: =AV37*AV13 -> 114872.22
A62: pexp*exp_4 | B62: =B38*B14 -> 3891.4423 | C62: =C38*C14 -> 4032.9991 | D62: =D38*D14 -> 3975.017 | E62: =E38*E14 -> 3991.0348 | F62: =F38*F14 -> 4214.9865 | G62: =G38*G14 -> 4234.4797 | H62: =H38*H14 -> 4356.2334 | I62: =I38*I14 -> 4405.1963 | ... AV62: =AV38*AV14 -> 9738.2354
A63: pexp*exp_5 | B63: =B39*B15 -> 8600.8803 | C63: =C39*C15 -> 8913.7496 | D63: =D39*D15 -> 8970.5485 | E63: =E39*E15 -> 9070.1629 | F63: =F39*F15 -> 9721.6999 | G63: =G39*G15 -> 9802.5246 | H63: =H39*H15 -> 10042.209 | I63: =I39*I15 -> 10302.586 | ... AV63: =AV39*AV15 -> 22122.261
A64: pexp*exp_6 | B64: =B40*B16 -> 631.35728 | C64: =C40*C16 -> 654.3238 | D64: =D40*D16 -> 650.81435 | E64: =E40*E16 -> 662.81118 | F64: =F40*F16 -> 713.01963 | G64: =G40*G16 -> 718.37041 | H64: =H40*H16 -> 741.58661 | I64: =I40*I16 -> 760.74691 | ... AV64: =AV40*AV16 -> 2538.5601
A65: pexp*exp_7 | B65: =B41*B17 -> 334.35307 | C65: =C41*C17 -> 346.51564 | D65: =D41*D17 -> 348.83769 | E65: =E41*E17 -> 349.08318 | F65: =F41*F17 -> 356.41897 | G65: =G41*G17 -> 360.15684 | H65: =H41*H17 -> 361.5604 | I65: =I41*I17 -> 372.25486 | ... AV65: =AV41*AV17 -> 1388.642
A66: pexp*exp_8 | B66: =B42*B18 -> 6830.1011 | C66: =C42*C18 -> 7078.5558 | D66: =D42*D18 -> 7249.5196 | E66: =E42*E18 -> 7586.036 | F66: =F42*F18 -> 7832.0573 | G66: =G42*G18 -> 7662.4063 | H66: =H42*H18 -> 7911.8183 | I66: =I42*I18 -> 8361.1681 | ... AV66: =AV42*AV18 -> 33821.344
A67: pexp*exp_9 | B67: =B43*B19 -> 454127.97 | C67: =C43*C19 -> 470647.52 | D67: =D43*D19 -> 470787.63 | E67: =E43*E19 -> 481577.97 | F67: =F43*F19 -> 487316.13 | G67: =G43*G19 -> 488991.51 | H67: =H43*H19 -> 496716.41 | I67: =I43*I19 -> 500170.62 | ... AV67: =AV43*AV19 -> 1669089.9
A68: pexp*exp_11 | B68: =B44*B20 -> 152.68937 | C68: =C44*C20 -> 158.24366 | D68: =D44*D20 -> 160.25396 | E68: =E44*E20 -> 155.58764 | F68: =F44*F20 -> 149.99476 | G68: =G44*G20 -> 160.98558 | H68: =H44*H20 -> 157.90381 | I68: =I44*I20 -> 154.6657 | ... AV68: =AV44*AV20 -> 422.36102
A69: pexp*exp_12 | B69: =B45*B21 -> 166916.11 | C69: =C45*C21 -> 172987.92 | D69: =D45*D21 -> 174816.9 | E69: =E45*E21 -> 183640.81 | F69: =F45*F21 -> 185532.73 | G69: =G45*G21 -> 184931.11 | H69: =H45*H21 -> 190523.75 | I69: =I45*I21 -> 194568.7 | ... AV69: =AV45*AV21 -> 650602.75
... A81: pexp*exp_24 | B81: =B57*B33 -> 9745.1207 | C81: =C57*C33 -> 10099.613 | D81: =D57*D33 -> 10142.391 | E81: =E57*E33 -> 10018.905 | F81: =F57*F33 -> 10460.97 | G81: =G57*G33 -> 9763.0498 | H81: =H57*H33 -> 9927.0214 | I81: =I57*I33 -> 10354.01 | ... AV81: =AV57*AV33 -> 13553.005

Sheet Rev_Dep_diff
B1: 2004 | C1: 2005 | D1: 2006 | E1: 2007 | F1: 2008 | G1: 2009 | H1: 2010 | I1: 2011 | J1: 2012 | K1: 2013 | L1: 2014 | M1: 2015 | N1: 2016 | O1: 2017 | P1: 2018 | Q1: 2019 | R1: 2020 | S1: 2021 | T1: 2022 | U1: 2023 | V1: 2024 | W1: 2025 | X1: 2026 | Y1: 2027 | Z1: 2028 | AA1: 2029 | AB1: 2030 | AC1: 2031 | AD1: 2032 | AE1: 2033 | AF1: 2034 | AG1: 2035 | AH1: 2036 | AI1: 2037 | AJ1: 2038 | AK1: 2039 | AL1: 2040 | AM1: 2041 | AN1: 2042 | AO1: 2043 | AP1: 2044 | AQ1: 2045 | AR1: 2046 | AS1: 2047 | AT1: 2048 | AU1: 2049 | AV1: 2050
A2: =résultats!B527 -> TS_1 | B2: =Rev_Dep_2!B2-Rev_Dep_0!B2 -> 0 | C2: =Rev_Dep_2!C2-Rev_Dep_0!C2 -> 0 | D2: =Rev_Dep_2!D2-Rev_Dep_0!D2 -> 0 | E2: =Rev_Dep_2!E2-Rev_Dep_0!E2 -> 0 | F2: =Rev_Dep_2!F2-Rev_Dep_0!F2 -> 0 | G2: =Rev_Dep_2!G2-Rev_Dep_0!G2 -> 0 | H2: =Rev_Dep_2!H2-Rev_Dep_0!H2 -> 0 | I2: =Rev_Dep_2!I2-Rev_Dep_0!I2 -> 0 | ... AV2: =Rev_Dep_2!AV2-Rev_Dep_0!AV2 -> 0.004102868
A3: =résultats!B528 -> TS_H01_1 | B3: =Rev_Dep_2!B3-Rev_Dep_0!B3 -> 0 | C3: =Rev_Dep_2!C3-Rev_Dep_0!C3 -> 0 | D3: =Rev_Dep_2!D3-Rev_Dep_0!D3 -> 0 | E3: =Rev_Dep_2!E3-Rev_Dep_0!E3 -> 0 | F3: =Rev_Dep_2!F3-Rev_Dep_0!F3 -> 0 | G3: =Rev_Dep_2!G3-Rev_Dep_0!G3 -> 0 | H3: =Rev_Dep_2!H3-Rev_Dep_0!H3 -> 0 | I3: =Rev_Dep_2!I3-Rev_Dep_0!I3 -> 0 | ... AV3: =Rev_Dep_2!AV3-Rev_Dep_0!AV3 -> 0.004102868
A4: =résultats!B529 -> DISPINC_VAL_H01_1 | B4: =Rev_Dep_2!B4-Rev_Dep_0!B4 -> 0 | C4: =Rev_Dep_2!C4-Rev_Dep_0!C4 -> 0 | D4: =Rev_Dep_2!D4-Rev_Dep_0!D4 -> 0 | E4: =Rev_Dep_2!E4-Rev_Dep_0!E4 -> 0 | F4: =Rev_Dep_2!F4-Rev_Dep_0!F4 -> 0 | G4: =Rev_Dep_2!G4-Rev_Dep_0!G4 -> 0 | H4: =Rev_Dep_2!H4-Rev_Dep_0!H4 -> 0 | I4: =Rev_Dep_2!I4-Rev_Dep_0!I4 -> 0 | ... AV4: =Rev_Dep_2!AV4-Rev_Dep_0!AV4 -> 176072.43
A5: =résultats!B530 -> DISPINC_AI_VAL_H01_1 | B5: =Rev_Dep_2!B5-Rev_Dep_0!B5 -> 0 | C5: =Rev_Dep_2!C5-Rev_Dep_0!C5 -> 0 | D5: =Rev_Dep_2!D5-Rev_Dep_0!D5 -> 0 | E5: =Rev_Dep_2!E5-Rev_Dep_0!E5 -> 0 | F5: =Rev_Dep_2!F5-Rev_Dep_0!F5 -> 0 | G5: =Rev_Dep_2!G5-Rev_Dep_0!G5 -> 0 | H5: =Rev_Dep_2!H5-Rev_Dep_0!H5 -> 0 | I5: =Rev_Dep_2!I5-Rev_Dep_0!I5 -> 0 | ... AV5: =Rev_Dep_2!AV5-Rev_Dep_0!AV5 -> 199188.73
A6: =résultats!B531 -> IR_VAL_H01_1 | B6: =Rev_Dep_2!B6-Rev_Dep_0!B6 -> 0 | C6: =Rev_Dep_2!C6-Rev_Dep_0!C6 -> 0 | D6: =Rev_Dep_2!D6-Rev_Dep_0!D6 -> 0 | E6: =Rev_Dep_2!E6-Rev_Dep_0!E6 -> 0 | F6: =Rev_Dep_2!F6-Rev_Dep_0!F6 -> 0 | G6: =Rev_Dep_2!G6-Rev_Dep_0!G6 -> 0 | H6: =Rev_Dep_2!H6-Rev_Dep_0!H6 -> 0 | I6: =Rev_Dep_2!I6-Rev_Dep_0!I6 -> 0 | ... AV6: =Rev_Dep_2!AV6-Rev_Dep_0!AV6 -> 26890.479
A7: =résultats!B532 -> AIC_VAL_H01_1 | B7: =Rev_Dep_2!B7-Rev_Dep_0!B7 -> 0 | C7: =Rev_Dep_2!C7-Rev_Dep_0!C7 -> 0 | D7: =Rev_Dep_2!D7-Rev_Dep_0!D7 -> 0 | E7: =Rev_Dep_2!E7-Rev_Dep_0!E7 -> 0 | F7: =Rev_Dep_2!F7-Rev_Dep_0!F7 -> 0 | G7: =Rev_Dep_2!G7-Rev_Dep_0!G7 -> 0 | H7: =Rev_Dep_2!H7-Rev_Dep_0!H7 -> 0 | I7: =Rev_Dep_2!I7-Rev_Dep_0!I7 -> 0 | ... AV7: =Rev_Dep_2!AV7-Rev_Dep_0!AV7 -> 2650.8701
A8: =résultats!B533 -> SUB_AUTO_VAL_1 | B8: =Rev_Dep_2!B8-Rev_Dep_0!B8 -> 0 | C8: =Rev_Dep_2!C8-Rev_Dep_0!C8 -> 0 | D8: =Rev_Dep_2!D8-Rev_Dep_0!D8 -> 0 | E8: =Rev_Dep_2!E8-Rev_Dep_0!E8 -> 0 | F8: =Rev_Dep_2!F8-Rev_Dep_0!F8 -> 0 | G8: =Rev_Dep_2!G8-Rev_Dep_0!G8 -> 0 | H8: =Rev_Dep_2!H8-Rev_Dep_0!H8 -> 0 | I8: =Rev_Dep_2!I8-Rev_Dep_0!I8 -> 0 | ... AV8: =Rev_Dep_2!AV8-Rev_Dep_0!AV8 -> -1570.9138
A9: =résultats!B534 -> SUB_RENOV_VAL_1 | B9: =Rev_Dep_2!B9-Rev_Dep_0!B9 -> 0 | C9: =Rev_Dep_2!C9-Rev_Dep_0!C9 -> 0 | D9: =Rev_Dep_2!D9-Rev_Dep_0!D9 -> 0 | E9: =Rev_Dep_2!E9-Rev_Dep_0!E9 -> 0 | F9: =Rev_Dep_2!F9-Rev_Dep_0!F9 -> 0 | G9: =Rev_Dep_2!G9-Rev_Dep_0!G9 -> 0 | H9: =Rev_Dep_2!H9-Rev_Dep_0!H9 -> 0 | I9: =Rev_Dep_2!I9-Rev_Dep_0!I9 -> 0 | ... AV9: =Rev_Dep_2!AV9-Rev_Dep_0!AV9 -> 7995.9634
A10: =résultats!B535 -> EXP_H01_1 | B10: =Rev_Dep_2!B10-Rev_Dep_0!B10 -> 0 | C10: =Rev_Dep_2!C10-Rev_Dep_0!C10 -> 0 | D10: =Rev_Dep_2!D10-Rev_Dep_0!D10 -> 0 | E10: =Rev_Dep_2!E10-Rev_Dep_0!E10 -> 0 | F10: =Rev_Dep_2!F10-Rev_Dep_0!F10 -> 0 | G10: =Rev_Dep_2!G10-Rev_Dep_0!G10 -> 0 | H10: =Rev_Dep_2!H10-Rev_Dep_0!H10 -> 0 | I10: =Rev_Dep_2!I10-Rev_Dep_0!I10 -> 0 | ... AV10: =Rev_Dep_2!AV10-Rev_Dep_0!AV10 -> 21245.089
A11: =résultats!B536 -> EXP_11_H01_1 | B11: =Rev_Dep_2!B11-Rev_Dep_0!B11 -> 0 | C11: =Rev_Dep_2!C11-Rev_Dep_0!C11 -> 0 | D11: =Rev_Dep_2!D11-Rev_Dep_0!D11 -> 0 | E11: =Rev_Dep_2!E11-Rev_Dep_0!E11 -> 0 | F11: =Rev_Dep_2!F11-Rev_Dep_0!F11 -> 0 | G11: =Rev_Dep_2!G11-Rev_Dep_0!G11 -> 0 | H11: =Rev_Dep_2!H11-Rev_Dep_0!H11 -> 0 | I11: =Rev_Dep_2!I11-Rev_Dep_0!I11 -> 0 | ... AV11: =Rev_Dep_2!AV11-Rev_Dep_0!AV11 -> 10.407959
A12: =résultats!B537 -> EXP_12_H01_1 | B12: =Rev_Dep_2!B12-Rev_Dep_0!B12 -> 0 | C12: =Rev_Dep_2!C12-Rev_Dep_0!C12 -> 0 | D12: =Rev_Dep_2!D12-Rev_Dep_0!D12 -> 0 | E12: =Rev_Dep_2!E12-Rev_Dep_0!E12 -> 0 | F12: =Rev_Dep_2!F12-Rev_Dep_0!F12 -> 0 | G12: =Rev_Dep_2!G12-Rev_Dep_0!G12 -> 0 | H12: =Rev_Dep_2!H12-Rev_Dep_0!H12 -> 0 | I12: =Rev_Dep_2!I12-Rev_Dep_0!I12 -> 0 | ... AV12: =Rev_Dep_2!AV12-Rev_Dep_0!AV12 -> 6025.2682
A13: =résultats!B538 -> EXP_13_H01_1 | B13: =Rev_Dep_2!B13-Rev_Dep_0!B13 -> 0 | C13: =Rev_Dep_2!C13-Rev_Dep_0!C13 -> 0 | D13: =Rev_Dep_2!D13-Rev_Dep_0!D13 -> 0 | E13: =Rev_Dep_2!E13-Rev_Dep_0!E13 -> 0 | F13: =Rev_Dep_2!F13-Rev_Dep_0!F13 -> 0 | G13: =Rev_Dep_2!G13-Rev_Dep_0!G13 -> 0 | H13: =Rev_Dep_2!H13-Rev_Dep_0!H13 -> 0 | I13: =Rev_Dep_2!I13-Rev_Dep_0!I13 -> 0 | ... AV13: =Rev_Dep_2!AV13-Rev_Dep_0!AV13 -> -12182.998
... A43: =résultats!B568 -> PEXP_19_H01_1 | B43: =Rev_Dep_2!B43-Rev_Dep_0!B43 -> 0 | C43: =Rev_Dep_2!C43-Rev_Dep_0!C43 -> 0 | D43: =Rev_Dep_2!D43-Rev_Dep_0!D43 -> 0 | E43: =Rev_Dep_2!E43-Rev_Dep_0!E43 -> 0 | F43: =Rev_Dep_2!F43-Rev_Dep_0!F43 -> 0 | G43: =Rev_Dep_2!G43-Rev_Dep_0!G43 -> 0 | H43: =Rev_Dep_2!H43-Rev_Dep_0!H43 -> 0 | I43: =Rev_Dep_2!I43-Rev_Dep_0!I43 -> 0 | ... AV43: =Rev_Dep_2!AV43-Rev_Dep_0!AV43 -> 0.070702896
A44: =résultats!B570 -> PEXP_11_H01_1 | B44: =Rev_Dep_2!B44-Rev_Dep_0!B44 -> 0 | C44: =Rev_Dep_2!C44-Rev_Dep_0!C44 -> 0 | D44: =Rev_Dep_2!D44-Rev_Dep_0!D44 -> 0 | E44: =Rev_Dep_2!E44-Rev_Dep_0!E44 -> 0 | F44: =Rev_Dep_2!F44-Rev_Dep_0!F44 -> 0 | G44: =Rev_Dep_2!G44-Rev_Dep_0!G44 -> 0 | H44: =Rev_Dep_2!H44-Rev_Dep_0!H44 -> 0 | I44: =Rev_Dep_2!I44-Rev_Dep_0!I44 -> 0 | ... AV44: =Rev_Dep_2!AV44-Rev_Dep_0!AV44 -> 0.056672666
A45: =résultats!B571 -> PEXP_12_H01_1 | B45: =Rev_Dep_2!B45-Rev_Dep_0!B45 -> 0 | C45: =Rev_Dep_2!C45-Rev_Dep_0!C45 -> 0 | D45: =Rev_Dep_2!D45-Rev_Dep_0!D45 -> 0 | E45: =Rev_Dep_2!E45-Rev_Dep_0!E45 -> 0 | F45: =Rev_Dep_2!F45-Rev_Dep_0!F45 -> 0 | G45: =Rev_Dep_2!G45-Rev_Dep_0!G45 -> 0 | H45: =Rev_Dep_2!H45-Rev_Dep_0!H45 -> 0 | I45: =Rev_Dep_2!I45-Rev_Dep_0!I45 -> 0 | ... AV45: =Rev_Dep_2!AV45-Rev_Dep_0!AV45 -> 0.063305794
A46: =résultats!B572 -> PEXP_13_H01_1 | B46: =Rev_Dep_2!B46-Rev_Dep_0!B46 -> 0 | C46: =Rev_Dep_2!C46-Rev_Dep_0!C46 -> 0 | D46: =Rev_Dep_2!D46-Rev_Dep_0!D46 -> 0 | E46: =Rev_Dep_2!E46-Rev_Dep_0!E46 -> 0 | F46: =Rev_Dep_2!F46-Rev_Dep_0!F46 -> 0 | G46: =Rev_Dep_2!G46-Rev_Dep_0!G46 -> 0 | H46: =Rev_Dep_2!H46-Rev_Dep_0!H46 -> 0 | I46: =Rev_Dep_2!I46-Rev_Dep_0!I46 -> 0 | ... AV46: =Rev_Dep_2!AV46-Rev_Dep_0!AV46 -> -0.25011085
A47: =résultats!B573 -> PEXP_14_H01_1 | B47: =Rev_Dep_2!B47-Rev_Dep_0!B47 -> 0 | C47: =Rev_Dep_2!C47-Rev_Dep_0!C47 -> 0 | D47: =Rev_Dep_2!D47-Rev_Dep_0!D47 -> 0 | E47: =Rev_Dep_2!E47-Rev_Dep_0!E47 -> 0 | F47: =Rev_Dep_2!F47-Rev_Dep_0!F47 -> 0 | G47: =Rev_Dep_2!G47-Rev_Dep_0!G47 -> 0 | H47: =Rev_Dep_2!H47-Rev_Dep_0!H47 -> 0 | I47: =Rev_Dep_2!I47-Rev_Dep_0!I47 -> 0 | ... AV47: =Rev_Dep_2!AV47-Rev_Dep_0!AV47 -> 0.13733483
A48: =résultats!B574 -> PEXP_15_H01_1 | B48: =Rev_Dep_2!B48-Rev_Dep_0!B48 -> 0 | C48: =Rev_Dep_2!C48-Rev_Dep_0!C48 -> 0 | D48: =Rev_Dep_2!D48-Rev_Dep_0!D48 -> 0 | E48: =Rev_Dep_2!E48-Rev_Dep_0!E48 -> 0 | F48: =Rev_Dep_2!F48-Rev_Dep_0!F48 -> 0 | G48: =Rev_Dep_2!G48-Rev_Dep_0!G48 -> 0 | H48: =Rev_Dep_2!H48-Rev_Dep_0!H48 -> 0 | I48: =Rev_Dep_2!I48-Rev_Dep_0!I48 -> 0 | ... AV48: =Rev_Dep_2!AV48-Rev_Dep_0!AV48 -> 0.097211923
A49: =résultats!B575 -> PEXP_16_H01_1 | B49: =Rev_Dep_2!B49-Rev_Dep_0!B49 -> 0 | C49: =Rev_Dep_2!C49-Rev_Dep_0!C49 -> 0 | D49: =Rev_Dep_2!D49-Rev_Dep_0!D49 -> 0 | E49: =Rev_Dep_2!E49-Rev_Dep_0!E49 -> 0 | F49: =Rev_Dep_2!F49-Rev_Dep_0!F49 -> 0 | G49: =Rev_Dep_2!G49-Rev_Dep_0!G49 -> 0 | H49: =Rev_Dep_2!H49-Rev_Dep_0!H49 -> 0 | I49: =Rev_Dep_2!I49-Rev_Dep_0!I49 -> 0 | ... AV49: =Rev_Dep_2!AV49-Rev_Dep_0!AV49 -> 0.083509115
A50: =résultats!B576 -> PEXP_17_H01_1 | B50: =Rev_Dep_2!B50-Rev_Dep_0!B50 -> 0 | C50: =Rev_Dep_2!C50-Rev_Dep_0!C50 -> 0 | D50: =Rev_Dep_2!D50-Rev_Dep_0!D50 -> 0 | E50: =Rev_Dep_2!E50-Rev_Dep_0!E50 -> 0 | F50: =Rev_Dep_2!F50-Rev_Dep_0!F50 -> 0 | G50: =Rev_Dep_2!G50-Rev_Dep_0!G50 -> 0 | H50: =Rev_Dep_2!H50-Rev_Dep_0!H50 -> 0 | I50: =Rev_Dep_2!I50-Rev_Dep_0!I50 -> 0 | ... AV50: =Rev_Dep_2!AV50-Rev_Dep_0!AV50 -> 0.076333373
A51: =résultats!B577 -> PEXP_18_H01_1 | B51: =Rev_Dep_2!B51-Rev_Dep_0!B51 -> 0 | C51: =Rev_Dep_2!C51-Rev_Dep_0!C51 -> 0 | D51: =Rev_Dep_2!D51-Rev_Dep_0!D51 -> 0 | E51: =Rev_Dep_2!E51-Rev_Dep_0!E51 -> 0 | F51: =Rev_Dep_2!F51-Rev_Dep_0!F51 -> 0 | G51: =Rev_Dep_2!G51-Rev_Dep_0!G51 -> 0 | H51: =Rev_Dep_2!H51-Rev_Dep_0!H51 -> 0 | I51: =Rev_Dep_2!I51-Rev_Dep_0!I51 -> 0 | ... AV51: =Rev_Dep_2!AV51-Rev_Dep_0!AV51 -> 0.052449354
A52: =résultats!B578 -> PEXP_19_H01_1 | B52: =Rev_Dep_2!B52-Rev_Dep_0!B52 -> 0 | C52: =Rev_Dep_2!C52-Rev_Dep_0!C52 -> 0 | D52: =Rev_Dep_2!D52-Rev_Dep_0!D52 -> 0 | E52: =Rev_Dep_2!E52-Rev_Dep_0!E52 -> 0 | F52: =Rev_Dep_2!F52-Rev_Dep_0!F52 -> 0 | G52: =Rev_Dep_2!G52-Rev_Dep_0!G52 -> 0 | H52: =Rev_Dep_2!H52-Rev_Dep_0!H52 -> 0 | I52: =Rev_Dep_2!I52-Rev_Dep_0!I52 -> 0 | ... AV52: =Rev_Dep_2!AV52-Rev_Dep_0!AV52 -> 0.070702896
A53: =résultats!B579 -> PEXP_20_H01_1 | B53: =Rev_Dep_2!B53-Rev_Dep_0!B53 -> 0 | C53: =Rev_Dep_2!C53-Rev_Dep_0!C53 -> 0 | D53: =Rev_Dep_2!D53-Rev_Dep_0!D53 -> 0 | E53: =Rev_Dep_2!E53-Rev_Dep_0!E53 -> 0 | F53: =Rev_Dep_2!F53-Rev_Dep_0!F53 -> 0 | G53: =Rev_Dep_2!G53-Rev_Dep_0!G53 -> 0 | H53: =Rev_Dep_2!H53-Rev_Dep_0!H53 -> 0 | I53: =Rev_Dep_2!I53-Rev_Dep_0!I53 -> 0 | ... AV53: =Rev_Dep_2!AV53-Rev_Dep_0!AV53 -> 0.06304392
A54: =résultats!B580 -> PEXP_21_H01_1 | B54: =Rev_Dep_2!B54-Rev_Dep_0!B54 -> 0 | C54: =Rev_Dep_2!C54-Rev_Dep_0!C54 -> 0 | D54: =Rev_Dep_2!D54-Rev_Dep_0!D54 -> 0 | E54: =Rev_Dep_2!E54-Rev_Dep_0!E54 -> 0 | F54: =Rev_Dep_2!F54-Rev_Dep_0!F54 -> 0 | G54: =Rev_Dep_2!G54-Rev_Dep_0!G54 -> 0 | H54: =Rev_Dep_2!H54-Rev_Dep_0!H54 -> 0 | I54: =Rev_Dep_2!I54-Rev_Dep_0!I54 -> 0 | ... AV54: =Rev_Dep_2!AV54-Rev_Dep_0!AV54 -> -1.0267399
A55: =résultats!B581 -> PEXP_22_H01_1 | B55: =Rev_Dep_2!B55-Rev_Dep_0!B55 -> 0 | C55: =Rev_Dep_2!C55-Rev_Dep_0!C55 -> 0 | D55: =Rev_Dep_2!D55-Rev_Dep_0!D55 -> 0 | E55: =Rev_Dep_2!E55-Rev_Dep_0!E55 -> 0 | F55: =Rev_Dep_2!F55-Rev_Dep_0!F55 -> 0 | G55: =Rev_Dep_2!G55-Rev_Dep_0!G55 -> 0 | H55: =Rev_Dep_2!H55-Rev_Dep_0!H55 -> 0 | I55: =Rev_Dep_2!I55-Rev_Dep_0!I55 -> 0 | ... AV55: =Rev_Dep_2!AV55-Rev_Dep_0!AV55 -> 0.087156094
... A57: =résultats!B583 -> PEXP_24_H01_1 | B57: =Rev_Dep_2!B57-Rev_Dep_0!B57 -> 0 | C57: =Rev_Dep_2!C57-Rev_Dep_0!C57 -> 0 | D57: =Rev_Dep_2!D57-Rev_Dep_0!D57 -> 0 | E57: =Rev_Dep_2!E57-Rev_Dep_0!E57 -> 0 | F57: =Rev_Dep_2!F57-Rev_Dep_0!F57 -> 0 | G57: =Rev_Dep_2!G57-Rev_Dep_0!G57 -> 0 | H57: =Rev_Dep_2!H57-Rev_Dep_0!H57 -> 0 | I57: =Rev_Dep_2!I57-Rev_Dep_0!I57 -> 0 | ... AV57: =Rev_Dep_2!AV57-Rev_Dep_0!AV57 -> 0.022384338
A58: pexp*exp | U58: =Rev_Dep_2!U58-Rev_Dep_0!U58 -> 527.8531 | V58: =Rev_Dep_2!V58-Rev_Dep_0!V58 -> 5404.4028 | W58: =Rev_Dep_2!W58-Rev_Dep_0!W58 -> 5104.2331 | X58: =Rev_Dep_2!X58-Rev_Dep_0!X58 -> -1384.9498 | Y58: =Rev_Dep_2!Y58-Rev_Dep_0!Y58 -> 4602.3659 | Z58: =Rev_Dep_2!Z58-Rev_Dep_0!Z58 -> 10002.535 | AA58: =Rev_Dep_2!AA58-Rev_Dep_0!AA58 -> 14015.114 | AB58: =Rev_Dep_2!AB58-Rev_Dep_0!AB58 -> 14958.701 | ... AV58: =Rev_Dep_2!AV58-Rev_Dep_0!AV58 -> 140504.54
A59: pexp*exp_1 | U59: =Rev_Dep_2!U59-Rev_Dep_0!U59 -> 0.10351949 | V59: =Rev_Dep_2!V59-Rev_Dep_0!V59 -> -0.79039425 | W59: =Rev_Dep_2!W59-Rev_Dep_0!W59 -> -1.6252093 | X59: =Rev_Dep_2!X59-Rev_Dep_0!X59 -> 0.36304477 | Y59: =Rev_Dep_2!Y59-Rev_Dep_0!Y59 -> 2.4446307 | Z59: =Rev_Dep_2!Z59-Rev_Dep_0!Z59 -> 4.2221363 | AA59: =Rev_Dep_2!AA59-Rev_Dep_0!AA59 -> 5.463835 | AB59: =Rev_Dep_2!AB59-Rev_Dep_0!AB59 -> 6.2054752 | ... AV59: =Rev_Dep_2!AV59-Rev_Dep_0!AV59 -> 35.165831
A60: pexp*exp_2 | U60: =Rev_Dep_2!U60-Rev_Dep_0!U60 -> 200.72437 | V60: =Rev_Dep_2!V60-Rev_Dep_0!V60 -> -1188.9394 | W60: =Rev_Dep_2!W60-Rev_Dep_0!W60 -> -2661.4267 | X60: =Rev_Dep_2!X60-Rev_Dep_0!X60 -> 236.4243 | Y60: =Rev_Dep_2!Y60-Rev_Dep_0!Y60 -> 3292.044 | Z60: =Rev_Dep_2!Z60-Rev_Dep_0!Z60 -> 5858.9055 | AA60: =Rev_Dep_2!AA60-Rev_Dep_0!AA60 -> 7590.0227 | AB60: =Rev_Dep_2!AB60-Rev_Dep_0!AB60 -> 8552.3796 | ... AV60: =Rev_Dep_2!AV60-Rev_Dep_0!AV60 -> 32393.677
A61: pexp*exp_3 | U61: =Rev_Dep_2!U61-Rev_Dep_0!U61 -> -63.493296 | V61: =Rev_Dep_2!V61-Rev_Dep_0!V61 -> -4392.0375 | W61: =Rev_Dep_2!W61-Rev_Dep_0!W61 -> -6906.8502 | X61: =Rev_Dep_2!X61-Rev_Dep_0!X61 -> -9714.8601 | Y61: =Rev_Dep_2!Y61-Rev_Dep_0!Y61 -> -9918.474 | Z61: =Rev_Dep_2!Z61-Rev_Dep_0!Z61 -> -12342.254 | AA61: =Rev_Dep_2!AA61-Rev_Dep_0!AA61 -> -15031.365 | AB61: =Rev_Dep_2!AB61-Rev_Dep_0!AB61 -> -18388.42 | ... AV61: =Rev_Dep_2!AV61-Rev_Dep_0!AV61 -> -34905.235
A62: pexp*exp_4 | U62: =Rev_Dep_2!U62-Rev_Dep_0!U62 -> 0.58989226 | V62: =Rev_Dep_2!V62-Rev_Dep_0!V62 -> 480.80127 | W62: =Rev_Dep_2!W62-Rev_Dep_0!W62 -> 931.38318 | X62: =Rev_Dep_2!X62-Rev_Dep_0!X62 -> 973.14899 | Y62: =Rev_Dep_2!Y62-Rev_Dep_0!Y62 -> 1088.9914 | Z62: =Rev_Dep_2!Z62-Rev_Dep_0!Z62 -> 1245.3055 | AA62: =Rev_Dep_2!AA62-Rev_Dep_0!AA62 -> 1433.0093 | AB62: =Rev_Dep_2!AB62-Rev_Dep_0!AB62 -> 1639.5399 | ... AV62: =Rev_Dep_2!AV62-Rev_Dep_0!AV62 -> 7671.4641
A63: pexp*exp_5 | U63: =Rev_Dep_2!U63-Rev_Dep_0!U63 -> 0.19549428 | V63: =Rev_Dep_2!V63-Rev_Dep_0!V63 -> 681.98061 | W63: =Rev_Dep_2!W63-Rev_Dep_0!W63 -> 1291.7705 | X63: =Rev_Dep_2!X63-Rev_Dep_0!X63 -> 1183.4817 | Y63: =Rev_Dep_2!Y63-Rev_Dep_0!Y63 -> 1258.714 | Z63: =Rev_Dep_2!Z63-Rev_Dep_0!Z63 -> 1435.6437 | AA63: =Rev_Dep_2!AA63-Rev_Dep_0!AA63 -> 1685.9501 | AB63: =Rev_Dep_2!AB63-Rev_Dep_0!AB63 -> 1968.7474 | ... AV63: =Rev_Dep_2!AV63-Rev_Dep_0!AV63 -> 5751.3509
A64: pexp*exp_6 | U64: =Rev_Dep_2!U64-Rev_Dep_0!U64 -> 0.51916264 | V64: =Rev_Dep_2!V64-Rev_Dep_0!V64 -> -11.388493 | W64: =Rev_Dep_2!W64-Rev_Dep_0!W64 -> -18.052033 | X64: =Rev_Dep_2!X64-Rev_Dep_0!X64 -> -8.9371158 | Y64: =Rev_Dep_2!Y64-Rev_Dep_0!Y64 -> 4.0747041 | Z64: =Rev_Dep_2!Z64-Rev_Dep_0!Z64 -> 17.820183 | AA64: =Rev_Dep_2!AA64-Rev_Dep_0!AA64 -> 36.216186 | AB64: =Rev_Dep_2!AB64-Rev_Dep_0!AB64 -> 54.010281 | ... AV64: =Rev_Dep_2!AV64-Rev_Dep_0!AV64 -> 234.89119
A65: pexp*exp_7 | U65: =Rev_Dep_2!U65-Rev_Dep_0!U65 -> 0.25723992 | V65: =Rev_Dep_2!V65-Rev_Dep_0!V65 -> -1.7729661 | W65: =Rev_Dep_2!W65-Rev_Dep_0!W65 -> -4.3469635 | X65: =Rev_Dep_2!X65-Rev_Dep_0!X65 -> -0.8068727 | Y65: =Rev_Dep_2!Y65-Rev_Dep_0!Y65 -> 4.6773966 | Z65: =Rev_Dep_2!Z65-Rev_Dep_0!Z65 -> 10.762521 | AA65: =Rev_Dep_2!AA65-Rev_Dep_0!AA65 -> 17.280101 | AB65: =Rev_Dep_2!AB65-Rev_Dep_0!AB65 -> 23.788728 | ... AV65: =Rev_Dep_2!AV65-Rev_Dep_0!AV65 -> 122.65235
A66: pexp*exp_8 | U66: =Rev_Dep_2!U66-Rev_Dep_0!U66 -> 7.1880415 | V66: =Rev_Dep_2!V66-Rev_Dep_0!V66 -> -308.9858 | W66: =Rev_Dep_2!W66-Rev_Dep_0!W66 -> -678.35589 | X66: =Rev_Dep_2!X66-Rev_Dep_0!X66 -> -1016.64 | Y66: =Rev_Dep_2!Y66-Rev_Dep_0!Y66 -> -1320.1589 | Z66: =Rev_Dep_2!Z66-Rev_Dep_0!Z66 -> -1660.8401 | AA66: =Rev_Dep_2!AA66-Rev_Dep_0!AA66 -> -2050.4652 | AB66: =Rev_Dep_2!AB66-Rev_Dep_0!AB66 -> -2495.5126 | ... AV66: =Rev_Dep_2!AV66-Rev_Dep_0!AV66 -> -23214.124
A67: pexp*exp_9 | U67: =Rev_Dep_2!U67-Rev_Dep_0!U67 -> 455.3349 | V67: =Rev_Dep_2!V67-Rev_Dep_0!V67 -> -2948.4226 | W67: =Rev_Dep_2!W67-Rev_Dep_0!W67 -> -6236.1076 | X67: =Rev_Dep_2!X67-Rev_Dep_0!X67 -> 1899.1171 | Y67: =Rev_Dep_2!Y67-Rev_Dep_0!Y67 -> 10552.114 | Z67: =Rev_Dep_2!Z67-Rev_Dep_0!Z67 -> 17982.061 | AA67: =Rev_Dep_2!AA67-Rev_Dep_0!AA67 -> 23318.251 | AB67: =Rev_Dep_2!AB67-Rev_Dep_0!AB67 -> 26649.282 | ... AV67: =Rev_Dep_2!AV67-Rev_Dep_0!AV67 -> 151239.36
A68: pexp*exp_11 | U68: =Rev_Dep_2!U68-Rev_Dep_0!U68 -> 0.10351949 | V68: =Rev_Dep_2!V68-Rev_Dep_0!V68 -> -0.79039425 | W68: =Rev_Dep_2!W68-Rev_Dep_0!W68 -> -1.6252093 | X68: =Rev_Dep_2!X68-Rev_Dep_0!X68 -> 0.36304477 | Y68: =Rev_Dep_2!Y68-Rev_Dep_0!Y68 -> 2.4446307 | Z68: =Rev_Dep_2!Z68-Rev_Dep_0!Z68 -> 4.2221363 | AA68: =Rev_Dep_2!AA68-Rev_Dep_0!AA68 -> 5.463835 | AB68: =Rev_Dep_2!AB68-Rev_Dep_0!AB68 -> 6.2054752 | ... AV68: =Rev_Dep_2!AV68-Rev_Dep_0!AV68 -> 35.165831
A69: pexp*exp_12 | U69: =Rev_Dep_2!U69-Rev_Dep_0!U69 -> 200.72437 | V69: =Rev_Dep_2!V69-Rev_Dep_0!V69 -> -1188.9394 | W69: =Rev_Dep_2!W69-Rev_Dep_0!W69 -> -2661.4267 | X69: =Rev_Dep_2!X69-Rev_Dep_0!X69 -> 236.4243 | Y69: =Rev_Dep_2!Y69-Rev_Dep_0!Y69 -> 3292.044 | Z69: =Rev_Dep_2!Z69-Rev_Dep_0!Z69 -> 5858.9055 | AA69: =Rev_Dep_2!AA69-Rev_Dep_0!AA69 -> 7590.0227 | AB69: =Rev_Dep_2!AB69-Rev_Dep_0!AB69 -> 8552.3796 | ... AV69: =Rev_Dep_2!AV69-Rev_Dep_0!AV69 -> 32393.677
... A81: pexp*exp_24 | U81: =Rev_Dep_2!U81-Rev_Dep_0!U81 -> -120.40026 | V81: =Rev_Dep_2!V81-Rev_Dep_0!V81 -> -204.73546 | W81: =Rev_Dep_2!W81-Rev_Dep_0!W81 -> -197.59708 | X81: =Rev_Dep_2!X81-Rev_Dep_0!X81 -> -192.28635 | Y81: =Rev_Dep_2!Y81-Rev_Dep_0!Y81 -> -379.28921 | Z81: =Rev_Dep_2!Z81-Rev_Dep_0!Z81 -> -573.53527 | AA81: =Rev_Dep_2!AA81-Rev_Dep_0!AA81 -> -610.50551 | AB81: =Rev_Dep_2!AB81-Rev_Dep_0!AB81 -> -653.97375 | ... AV81: =Rev_Dep_2!AV81-Rev_Dep_0!AV81 -> -3875.4149

Sheet Rev_Dep_taux
B1: 2004 | C1: 2005 | D1: 2006 | E1: 2007 | F1: 2008 | G1: 2009 | H1: 2010 | I1: 2011 | J1: 2012 | K1: 2013 | L1: 2014 | M1: 2015 | N1: 2016 | O1: 2017 | P1: 2018 | Q1: 2019 | R1: 2020 | S1: 2021 | T1: 2022 | U1: 2023 | V1: 2024 | W1: 2025 | X1: 2026 | Y1: 2027 | Z1: 2028 | AA1: 2029 | AB1: 2030 | AC1: 2031 | AD1: 2032 | AE1: 2033 | AF1: 2034 | AG1: 2035 | AH1: 2036 | AI1: 2037 | AJ1: 2038 | AK1: 2039 | AL1: 2040 | AM1: 2041 | AN1: 2042 | AO1: 2043 | AP1: 2044 | AQ1: 2045 | AR1: 2046 | AS1: 2047 | AT1: 2048 | AU1: 2049 | AV1: 2050
A2: =résultats!B527 -> TS_1 | B2: =Rev_Dep_2!B2-Rev_Dep_0!B2 -> 0 | C2: =Rev_Dep_2!C2-Rev_Dep_0!C2 -> 0 | D2: =Rev_Dep_2!D2-Rev_Dep_0!D2 -> 0 | E2: =Rev_Dep_2!E2-Rev_Dep_0!E2 -> 0 | F2: =Rev_Dep_2!F2-Rev_Dep_0!F2 -> 0 | G2: =Rev_Dep_2!G2-Rev_Dep_0!G2 -> 0 | H2: =Rev_Dep_2!H2-Rev_Dep_0!H2 -> 0 | I2: =Rev_Dep_2!I2-Rev_Dep_0!I2 -> 0 | ... T2: =Rev_Dep_2!T2-Rev_Dep_0!T2 -> 0 | U2: =Rev_Dep_diff!U2/Rev_Dep_0!U2 -> -0.00083468768 | V2: =Rev_Dep_diff!V2/Rev_Dep_0!V2 -> 0.0027778781 | W2: =Rev_Dep_diff!W2/Rev_Dep_0!W2 -> 0.023934204 | X2: =Rev_Dep_diff!X2/Rev_Dep_0!X2 -> 0.13415625 | Y2: =Rev_Dep_diff!Y2/Rev_Dep_0!Y2 -> 0.16220032 | Z2: =Rev_Dep_diff!Z2/Rev_Dep_0!Z2 -> 0.17933933 | AA2: =Rev_Dep_diff!AA2/Rev_Dep_0!AA2 -> 0.18894612 | AB2: =Rev_Dep_diff!AB2/Rev_Dep_0!AB2 -> 0.19477198 | ... AV2: =Rev_Dep_diff!AV2/Rev_Dep_0!AV2 -> 0.037678113
A3: =résultats!B528 -> TS_H01_1 | B3: =Rev_Dep_2!B3-Rev_Dep_0!B3 -> 0 | C3: =Rev_Dep_2!C3-Rev_Dep_0!C3 -> 0 | D3: =Rev_Dep_2!D3-Rev_Dep_0!D3 -> 0 | E3: =Rev_Dep_2!E3-Rev_Dep_0!E3 -> 0 | F3: =Rev_Dep_2!F3-Rev_Dep_0!F3 -> 0 | G3: =Rev_Dep_2!G3-Rev_Dep_0!G3 -> 0 | H3: =Rev_Dep_2!H3-Rev_Dep_0!H3 -> 0 | I3: =Rev_Dep_2!I3-Rev_Dep_0!I3 -> 0 | ... T3: =Rev_Dep_2!T3-Rev_Dep_0!T3 -> 0 | U3: =Rev_Dep_diff!U3/Rev_Dep_0!U3 -> -0.00083468768 | V3: =Rev_Dep_diff!V3/Rev_Dep_0!V3 -> 0.0027778781 | W3: =Rev_Dep_diff!W3/Rev_Dep_0!W3 -> 0.023934204 | X3: =Rev_Dep_diff!X3/Rev_Dep_0!X3 -> 0.13415625 | Y3: =Rev_Dep_diff!Y3/Rev_Dep_0!Y3 -> 0.16220032 | Z3: =Rev_Dep_diff!Z3/Rev_Dep_0!Z3 -> 0.17933933 | AA3: =Rev_Dep_diff!AA3/Rev_Dep_0!AA3 -> 0.18894612 | AB3: =Rev_Dep_diff!AB3/Rev_Dep_0!AB3 -> 0.19477198 | ... AV3: =Rev_Dep_diff!AV3/Rev_Dep_0!AV3 -> 0.037678113
A4: =résultats!B529 -> DISPINC_VAL_H01_1 | B4: =Rev_Dep_2!B4-Rev_Dep_0!B4 -> 0 | C4: =Rev_Dep_2!C4-Rev_Dep_0!C4 -> 0 | D4: =Rev_Dep_2!D4-Rev_Dep_0!D4 -> 0 | E4: =Rev_Dep_2!E4-Rev_Dep_0!E4 -> 0 | F4: =Rev_Dep_2!F4-Rev_Dep_0!F4 -> 0 | G4: =Rev_Dep_2!G4-Rev_Dep_0!G4 -> 0 | H4: =Rev_Dep_2!H4-Rev_Dep_0!H4 -> 0 | I4: =Rev_Dep_2!I4-Rev_Dep_0!I4 -> 0 | ... T4: =Rev_Dep_2!T4-Rev_Dep_0!T4 -> 0 | U4: =Rev_Dep_diff!U4/Rev_Dep_0!U4*100 -> 0.02902337 | V4: =Rev_Dep_diff!V4/Rev_Dep_0!V4*100 -> 0.36040414 | W4: =Rev_Dep_diff!W4/Rev_Dep_0!W4*100 -> 0.47007534 | X4: =Rev_Dep_diff!X4/Rev_Dep_0!X4*100 -> 0.75437913 | Y4: =Rev_Dep_diff!Y4/Rev_Dep_0!Y4*100 -> 1.2815563 | Z4: =Rev_Dep_diff!Z4/Rev_Dep_0!Z4*100 -> 1.7219207 | AA4: =Rev_Dep_diff!AA4/Rev_Dep_0!AA4*100 -> 2.0486009 | AB4: =Rev_Dep_diff!AB4/Rev_Dep_0!AB4*100 -> 2.173456 | ... AV4: =Rev_Dep_diff!AV4/Rev_Dep_0!AV4*100 -> 4.6093576
A5: =résultats!B530 -> DISPINC_AI_VAL_H01_1 | B5: =Rev_Dep_2!B5-Rev_Dep_0!B5 -> 0 | C5: =Rev_Dep_2!C5-Rev_Dep_0!C5 -> 0 | D5: =Rev_Dep_2!D5-Rev_Dep_0!D5 -> 0 | E5: =Rev_Dep_2!E5-Rev_Dep_0!E5 -> 0 | F5: =Rev_Dep_2!F5-Rev_Dep_0!F5 -> 0 | G5: =Rev_Dep_2!G5-Rev_Dep_0!G5 -> 0 | H5: =Rev_Dep_2!H5-Rev_Dep_0!H5 -> 0 | I5: =Rev_Dep_2!I5-Rev_Dep_0!I5 -> 0 | ... T5: =Rev_Dep_2!T5-Rev_Dep_0!T5 -> 0 | U5: =Rev_Dep_diff!U5/Rev_Dep_0!U5*100 -> 0.029809439 | V5: =Rev_Dep_diff!V5/Rev_Dep_0!V5*100 -> 0.17159472 | W5: =Rev_Dep_diff!W5/Rev_Dep_0!W5*100 -> 0.24682396 | X5: =Rev_Dep_diff!X5/Rev_Dep_0!X5*100 -> 0.41642475 | Y5: =Rev_Dep_diff!Y5/Rev_Dep_0!Y5*100 -> 0.92757393 | Z5: =Rev_Dep_diff!Z5/Rev_Dep_0!Z5*100 -> 1.3680413 | AA5: =Rev_Dep_diff!AA5/Rev_Dep_0!AA5*100 -> 1.7006132 | AB5: =Rev_Dep_diff!AB5/Rev_Dep_0!AB5*100 -> 1.8298396 | ... AV5: =Rev_Dep_diff!AV5/Rev_Dep_0!AV5*100 -> 4.4452506
A6: =résultats!B531 -> IR_VAL_H01_1 | B6: =Rev_Dep_2!B6-Rev_Dep_0!B6 -> 0 | C6: =Rev_Dep_2!C6-Rev_Dep_0!C6 -> 0 | D6: =Rev_Dep_2!D6-Rev_Dep_0!D6 -> 0 | E6: =Rev_Dep_2!E6-Rev_Dep_0!E6 -> 0 | F6: =Rev_Dep_2!F6-Rev_Dep_0!F6 -> 0 | G6: =Rev_Dep_2!G6-Rev_Dep_0!G6 -> 0 | H6: =Rev_Dep_2!H6-Rev_Dep_0!H6 -> 0 | I6: =Rev_Dep_2!I6-Rev_Dep_0!I6 -> 0 | ... T6: =Rev_Dep_2!T6-Rev_Dep_0!T6 -> 0 | U6: =Rev_Dep_diff!U6/Rev_Dep_0!U6*100 -> 0.029809429 | V6: =Rev_Dep_diff!V6/Rev_Dep_0!V6*100 -> 0.1715947 | W6: =Rev_Dep_diff!W6/Rev_Dep_0!W6*100 -> 0.24682395 | X6: =Rev_Dep_diff!X6/Rev_Dep_0!X6*100 -> 0.41642476 | Y6: =Rev_Dep_diff!Y6/Rev_Dep_0!Y6*100 -> 0.92757392 | Z6: =Rev_Dep_diff!Z6/Rev_Dep_0!Z6*100 -> 1.3680413 | AA6: =Rev_Dep_diff!AA6/Rev_Dep_0!AA6*100 -> 1.7006132 | AB6: =Rev_Dep_diff!AB6/Rev_Dep_0!AB6*100 -> 1.8298396 | ... AV6: =Rev_Dep_diff!AV6/Rev_Dep_0!AV6*100 -> 4.4452506
A7: =résultats!B532 -> AIC_VAL_H01_1 | B7: =Rev_Dep_2!B7-Rev_Dep_0!B7 -> 0 | C7: =Rev_Dep_2!C7-Rev_Dep_0!C7 -> 0 | D7: =Rev_Dep_2!D7-Rev_Dep_0!D7 -> 0 | E7: =Rev_Dep_2!E7-Rev_Dep_0!E7 -> 0 | F7: =Rev_Dep_2!F7-Rev_Dep_0!F7 -> 0 | G7: =Rev_Dep_2!G7-Rev_Dep_0!G7 -> 0 | H7: =Rev_Dep_2!H7-Rev_Dep_0!H7 -> 0 | I7: =Rev_Dep_2!I7-Rev_Dep_0!I7 -> 0 | ... T7: =Rev_Dep_2!T7-Rev_Dep_0!T7 -> 0 | U7: =Rev_Dep_diff!U7/Rev_Dep_0!U7*100 -> 0.029809426 | V7: =Rev_Dep_diff!V7/Rev_Dep_0!V7*100 -> 0.17159472 | W7: =Rev_Dep_diff!W7/Rev_Dep_0!W7*100 -> 0.24682396 | X7: =Rev_Dep_diff!X7/Rev_Dep_0!X7*100 -> 0.41642478 | Y7: =Rev_Dep_diff!Y7/Rev_Dep_0!Y7*100 -> 0.92757392 | Z7: =Rev_Dep_diff!Z7/Rev_Dep_0!Z7*100 -> 1.3680413 | AA7: =Rev_Dep_diff!AA7/Rev_Dep_0!AA7*100 -> 1.7006132 | AB7: =Rev_Dep_diff!AB7/Rev_Dep_0!AB7*100 -> 1.8298396 | ... AV7: =Rev_Dep_diff!AV7/Rev_Dep_0!AV7*100 -> 4.4452506
A8: =résultats!B533 -> SUB_AUTO_VAL_1 | B8: =Rev_Dep_2!B8-Rev_Dep_0!B8 -> 0 | C8: =Rev_Dep_2!C8-Rev_Dep_0!C8 -> 0 | D8: =Rev_Dep_2!D8-Rev_Dep_0!D8 -> 0 | E8: =Rev_Dep_2!E8-Rev_Dep_0!E8 -> 0 | F8: =Rev_Dep_2!F8-Rev_Dep_0!F8 -> 0 | G8: =Rev_Dep_2!G8-Rev_Dep_0!G8 -> 0 | H8: =Rev_Dep_2!H8-Rev_Dep_0!H8 -> 0 | I8: =Rev_Dep_2!I8-Rev_Dep_0!I8 -> 0 | ... T8: =Rev_Dep_2!T8-Rev_Dep_0!T8 -> 0 | U8: =Rev_Dep_diff!U8/Rev_Dep_0!U8*100 -> 0.13171736 | V8: =Rev_Dep_diff!V8/Rev_Dep_0!V8*100 -> 23.987022 | W8: =Rev_Dep_diff!W8/Rev_Dep_0!W8*100 -> 70.391968 | X8: =Rev_Dep_diff!X8/Rev_Dep_0!X8*100 -> 28.844016 | Y8: =Rev_Dep_diff!Y8/Rev_Dep_0!Y8*100 -> 13.305442 | Z8: =Rev_Dep_diff!Z8/Rev_Dep_0!Z8*100 -> -44.607316 | AA8: =Rev_Dep_diff!AA8/Rev_Dep_0!AA8*100 -> 50.774915 | AB8: =Rev_Dep_diff!AB8/Rev_Dep_0!AB8*100 -> 29.165529 | ... AV8: =Rev_Dep_diff!AV8/Rev_Dep_0!AV8*100 -> -44.666306
A9: =résultats!B534 -> SUB_RENOV_VAL_1 | B9: =Rev_Dep_2!B9-Rev_Dep_0!B9 -> 0 | C9: =Rev_Dep_2!C9-Rev_Dep_0!C9 -> 0 | D9: =Rev_Dep_2!D9-Rev_Dep_0!D9 -> 0 | E9: =Rev_Dep_2!E9-Rev_Dep_0!E9 -> 0 | F9: =Rev_Dep_2!F9-Rev_Dep_0!F9 -> 0 | G9: =Rev_Dep_2!G9-Rev_Dep_0!G9 -> 0 | H9: =Rev_Dep_2!H9-Rev_Dep_0!H9 -> 0 | I9: =Rev_Dep_2!I9-Rev_Dep_0!I9 -> 0 | ... T9: =Rev_Dep_2!T9-Rev_Dep_0!T9 -> 0 | U9: =Rev_Dep_diff!U9/Rev_Dep_0!U9*100 -> -0.37358998 | V9: =Rev_Dep_diff!V9/Rev_Dep_0!V9*100 -> #DIV/0! | W9: =Rev_Dep_diff!W9/Rev_Dep_0!W9*100 -> #DIV/0! | X9: =Rev_Dep_diff!X9/Rev_Dep_0!X9*100 -> #DIV/0! | Y9: =Rev_Dep_diff!Y9/Rev_Dep_0!Y9*100 -> #DIV/0! | Z9: =Rev_Dep_diff!Z9/Rev_Dep_0!Z9*100 -> #DIV/0! | AA9: =Rev_Dep_diff!AA9/Rev_Dep_0!AA9*100 -> #DIV/0! | AB9: =Rev_Dep_diff!AB9/Rev_Dep_0!AB9*100 -> #DIV/0! | ... AV9: =Rev_Dep_diff!AV9/Rev_Dep_0!AV9*100 -> #DIV/0!
A10: =résultats!B535 -> EXP_H01_1 | B10: =Rev_Dep_2!B10-Rev_Dep_0!B10 -> 0 | C10: =Rev_Dep_2!C10-Rev_Dep_0!C10 -> 0 | D10: =Rev_Dep_2!D10-Rev_Dep_0!D10 -> 0 | E10: =Rev_Dep_2!E10-Rev_Dep_0!E10 -> 0 | F10: =Rev_Dep_2!F10-Rev_Dep_0!F10 -> 0 | G10: =Rev_Dep_2!G10-Rev_Dep_0!G10 -> 0 | H10: =Rev_Dep_2!H10-Rev_Dep_0!H10 -> 0 | I10: =Rev_Dep_2!I10-Rev_Dep_0!I10 -> 0 | ... T10: =Rev_Dep_2!T10-Rev_Dep_0!T10 -> 0 | U10: =Rev_Dep_diff!U10/Rev_Dep_0!U10*100 -> 0.051652218 | V10: =Rev_Dep_diff!V10/Rev_Dep_0!V10*100 -> 0.56229791 | W10: =Rev_Dep_diff!W10/Rev_Dep_0!W10*100 -> 0.686389 | X10: =Rev_Dep_diff!X10/Rev_Dep_0!X10*100 -> 0.64375878 | Y10: =Rev_Dep_diff!Y10/Rev_Dep_0!Y10*100 -> 1.0062201 | Z10: =Rev_Dep_diff!Z10/Rev_Dep_0!Z10*100 -> 1.2836381 | AA10: =Rev_Dep_diff!AA10/Rev_Dep_0!AA10*100 -> 1.2786803 | AB10: =Rev_Dep_diff!AB10/Rev_Dep_0!AB10*100 -> 1.1032778 | ... AV10: =Rev_Dep_diff!AV10/Rev_Dep_0!AV10*100 -> 1.2683988
A11: =résultats!B536 -> EXP_11_H01_1 | B11: =Rev_Dep_2!B11-Rev_Dep_0!B11 -> 0 | C11: =Rev_Dep_2!C11-Rev_Dep_0!C11 -> 0 | D11: =Rev_Dep_2!D11-Rev_Dep_0!D11 -> 0 | E11: =Rev_Dep_2!E11-Rev_Dep_0!E11 -> 0 | F11: =Rev_Dep_2!F11-Rev_Dep_0!F11 -> 0 | G11: =Rev_Dep_2!G11-Rev_Dep_0!G11 -> 0 | H11: =Rev_Dep_2!H11-Rev_Dep_0!H11 -> 0 | I11: =Rev_Dep_2!I11-Rev_Dep_0!I11 -> 0 | ... T11: =Rev_Dep_2!T11-Rev_Dep_0!T11 -> 0 | U11: =Rev_Dep_diff!U11/Rev_Dep_0!U11*100 -> 0.063414852 | V11: =Rev_Dep_diff!V11/Rev_Dep_0!V11*100 -> -0.40993469 | W11: =Rev_Dep_diff!W11/Rev_Dep_0!W11*100 -> -0.8387869 | X11: =Rev_Dep_diff!X11/Rev_Dep_0!X11*100 -> 0.19765914 | Y11: =Rev_Dep_diff!Y11/Rev_Dep_0!Y11*100 -> 1.2158678 | Z11: =Rev_Dep_diff!Z11/Rev_Dep_0!Z11*100 -> 2.0025048 | AA11: =Rev_Dep_diff!AA11/Rev_Dep_0!AA11*100 -> 2.444554 | AB11: =Rev_Dep_diff!AB11/Rev_Dep_0!AB11*100 -> 2.5936883 | ... AV11: =Rev_Dep_diff!AV11/Rev_Dep_0!AV11*100 -> 5.7631037
A12: =résultats!B537 -> EXP_12_H01_1 | B12: =Rev_Dep_2!B12-Rev_Dep_0!B12 -> 0 | C12: =Rev_Dep_2!C12-Rev_Dep_0!C12 -> 0 | D12: =Rev_Dep_2!D12-Rev_Dep_0!D12 -> 0 | E12: =Rev_Dep_2!E12-Rev_Dep_0!E12 -> 0 | F12: =Rev_Dep_2!F12-Rev_Dep_0!F12 -> 0 | G12: =Rev_Dep_2!G12-Rev_Dep_0!G12 -> 0 | H12: =Rev_Dep_2!H12-Rev_Dep_0!H12 -> 0 | I12: =Rev_Dep_2!I12-Rev_Dep_0!I12 -> 0 | ... T12: =Rev_Dep_2!T12-Rev_Dep_0!T12 -> 0 | U12: =Rev_Dep_diff!U12/Rev_Dep_0!U12*100 -> 0.063414886 | V12: =Rev_Dep_diff!V12/Rev_Dep_0!V12*100 -> -0.41196428 | W12: =Rev_Dep_diff!W12/Rev_Dep_0!W12*100 -> -0.87719125 | X12: =Rev_Dep_diff!X12/Rev_Dep_0!X12*100 -> 0.10336908 | Y12: =Rev_Dep_diff!Y12/Rev_Dep_0!Y12*100 -> 1.0573603 | Z12: =Rev_Dep_diff!Z12/Rev_Dep_0!Z12*100 -> 1.7707336 | AA12: =Rev_Dep_diff!AA12/Rev_Dep_0!AA12*100 -> 2.1310108 | AB12: =Rev_Dep_diff!AB12/Rev_Dep_0!AB12*100 -> 2.1895492 | ... AV12: =Rev_Dep_diff!AV12/Rev_Dep_0!AV12*100 -> 2.0245458
A13: =résultats!B538 -> EXP_13_H01_1 | B13: =Rev_Dep_2!B13-Rev_Dep_0!B13 -> 0 | C13: =Rev_Dep_2!C13-Rev_Dep_0!C13 -> 0 | D13: =Rev_Dep_2!D13-Rev_Dep_0!D13 -> 0 | E13: =Rev_Dep_2!E13-Rev_Dep_0!E13 -> 0 | F13: =Rev_Dep_2!F13-Rev_Dep_0!F13 -> 0 | G13: =Rev_Dep_2!G13-Rev_Dep_0!G13 -> 0 | H13: =Rev_Dep_2!H13-Rev_Dep_0!H13 -> 0 | I13: =Rev_Dep_2!I13-Rev_Dep_0!I13 -> 0 | ... T13: =Rev_Dep_2!T13-Rev_Dep_0!T13 -> 0 | U13: =Rev_Dep_diff!U13/Rev_Dep_0!U13*100 -> -0.077042348 | V13: =Rev_Dep_diff!V13/Rev_Dep_0!V13*100 -> -0.085697654 | W13: =Rev_Dep_diff!W13/Rev_Dep_0!W13*100 -> 0.87046607 | X13: =Rev_Dep_diff!X13/Rev_Dep_0!X13*100 -> 3.063811 | Y13: =Rev_Dep_diff!Y13/Rev_Dep_0!Y13*100 -> 3.3395015 | Z13: =Rev_Dep_diff!Z13/Rev_Dep_0!Z13*100 -> 2.0271195 | AA13: =Rev_Dep_diff!AA13/Rev_Dep_0!AA13*100 -> -0.41252687 | AB13: =Rev_Dep_diff!AB13/Rev_Dep_0!AB13*100 -> -2.7860167 | ... AV13: =Rev_Dep_diff!AV13/Rev_Dep_0!AV13*100 -> -19.28155
A14: =résultats!B539 -> EXP_14_H01_1 | B14: =Rev_Dep_2!B14-Rev_Dep_0!B14 -> 0 | C14: =Rev_Dep_2!C14-Rev_Dep_0!C14 -> 0 | D14: =Rev_Dep_2!D14-Rev_Dep_0!D14 -> 0 | E14: =Rev_Dep_2!E14-Rev_Dep_0!E14 -> 0 | F14: =Rev_Dep_2!F14-Rev_Dep_0!F14 -> 0 | G14: =Rev_Dep_2!G14-Rev_Dep_0!G14 -> 0 | H14: =Rev_Dep_2!H14-Rev_Dep_0!H14 -> 0 | I14: =Rev_Dep_2!I14-Rev_Dep_0!I14 -> 0 | ... T14: =Rev_Dep_2!T14-Rev_Dep_0!T14 -> 0 | U14: =Rev_Dep_diff!U14/Rev_Dep_0!U14*100 -> 0.0082182829 | V14: =Rev_Dep_diff!V14/Rev_Dep_0!V14*100 -> 8.226467 | W14: =Rev_Dep_diff!W14/Rev_Dep_0!W14*100 -> 15.503219 | X14: =Rev_Dep_diff!X14/Rev_Dep_0!X14*100 -> 15.687247 | Y14: =Rev_Dep_diff!Y14/Rev_Dep_0!Y14*100 -> 17.092234 | Z14: =Rev_Dep_diff!Z14/Rev_Dep_0!Z14*100 -> 18.878018 | AA14: =Rev_Dep_diff!AA14/Rev_Dep_0!AA14*100 -> 20.968332 | AB14: =Rev_Dep_diff!AB14/Rev_Dep_0!AB14*100 -> 23.208666 | ... AV14: =Rev_Dep_diff!AV14/Rev_Dep_0!AV14*100 -> 66.693115
A15: =résultats!B540 -> EXP_15_H01_1 | B15: =Rev_Dep_2!B15-Rev_Dep_0!B15 -> 0 | C15: =Rev_Dep_2!C15-Rev_Dep_0!C15 -> 0 | D15: =Rev_Dep_2!D15-Rev_Dep_0!D15 -> 0 | E15: =Rev_Dep_2!E15-Rev_Dep_0!E15 -> 0 | F15: =Rev_Dep_2!F15-Rev_Dep_0!F15 -> 0 | G15: =Rev_Dep_2!G15-Rev_Dep_0!G15 -> 0 | H15: =Rev_Dep_2!H15-Rev_Dep_0!H15 -> 0 | I15: =Rev_Dep_2!I15-Rev_Dep_0!I15 -> 0 | ... T15: =Rev_Dep_2!T15-Rev_Dep_0!T15 -> 0 | U15: =Rev_Dep_diff!U15/Rev_Dep_0!U15*100 -> 0.019274545 | V15: =Rev_Dep_diff!V15/Rev_Dep_0!V15*100 -> 5.8339433 | W15: =Rev_Dep_diff!W15/Rev_Dep_0!W15*100 -> 10.688257 | X15: =Rev_Dep_diff!X15/Rev_Dep_0!X15*100 -> 9.880738 | Y15: =Rev_Dep_diff!Y15/Rev_Dep_0!Y15*100 -> 10.22713 | Z15: =Rev_Dep_diff!Z15/Rev_Dep_0!Z15*100 -> 10.898111 | AA15: =Rev_Dep_diff!AA15/Rev_Dep_0!AA15*100 -> 11.792563 | AB15: =Rev_Dep_diff!AB15/Rev_Dep_0!AB15*100 -> 12.817749 | ... AV15: =Rev_Dep_diff!AV15/Rev_Dep_0!AV15*100 -> 19.904575
... A43: =résultats!B568 -> PEXP_19_H01_1 | B43: =Rev_Dep_2!B43-Rev_Dep_0!B43 -> 0 | C43: =Rev_Dep_2!C43-Rev_Dep_0!C43 -> 0 | D43: =Rev_Dep_2!D43-Rev_Dep_0!D43 -> 0 | E43: =Rev_Dep_2!E43-Rev_Dep_0!E43 -> 0 | F43: =Rev_Dep_2!F43-Rev_Dep_0!F43 -> 0 | G43: =Rev_Dep_2!G43-Rev_Dep_0!G43 -> 0 | H43: =Rev_Dep_2!H43-Rev_Dep_0!H43 -> 0 | I43: =Rev_Dep_2!I43-Rev_Dep_0!I43 -> 0 | ... T43: =Rev_Dep_2!T43-Rev_Dep_0!T43 -> 0 | U43: =Rev_Dep_diff!U43/Rev_Dep_0!U43*100 -> 0.0025206077 | V43: =Rev_Dep_diff!V43/Rev_Dep_0!V43*100 -> -0.0019070059 | W43: =Rev_Dep_diff!W43/Rev_Dep_0!W43*100 -> -0.0034906864 | X43: =Rev_Dep_diff!X43/Rev_Dep_0!X43*100 -> 0.064930758 | Y43: =Rev_Dep_diff!Y43/Rev_Dep_0!Y43*100 -> 0.16285968 | Z43: =Rev_Dep_diff!Z43/Rev_Dep_0!Z43*100 -> 0.28124487 | AA43: =Rev_Dep_diff!AA43/Rev_Dep_0!AA43*100 -> 0.43972558 | AB43: =Rev_Dep_diff!AB43/Rev_Dep_0!AB43*100 -> 0.62080936 | ... AV43: =Rev_Dep_diff!AV43/Rev_Dep_0!AV43*100 -> 3.6218658
A44: =résultats!B570 -> PEXP_11_H01_1 | B44: =Rev_Dep_2!B44-Rev_Dep_0!B44 -> 0 | C44: =Rev_Dep_2!C44-Rev_Dep_0!C44 -> 0 | D44: =Rev_Dep_2!D44-Rev_Dep_0!D44 -> 0 | E44: =Rev_Dep_2!E44-Rev_Dep_0!E44 -> 0 | F44: =Rev_Dep_2!F44-Rev_Dep_0!F44 -> 0 | G44: =Rev_Dep_2!G44-Rev_Dep_0!G44 -> 0 | H44: =Rev_Dep_2!H44-Rev_Dep_0!H44 -> 0 | I44: =Rev_Dep_2!I44-Rev_Dep_0!I44 -> 0 | ... T44: =Rev_Dep_2!T44-Rev_Dep_0!T44 -> 0 | U44: =Rev_Dep_diff!U44/Rev_Dep_0!U44*100 -> -0.0041180101 | V44: =Rev_Dep_diff!V44/Rev_Dep_0!V44*100 -> -0.027894334 | W44: =Rev_Dep_diff!W44/Rev_Dep_0!W44*100 -> -0.035765946 | X44: =Rev_Dep_diff!X44/Rev_Dep_0!X44*100 -> -0.0073302988 | Y44: =Rev_Dep_diff!Y44/Rev_Dep_0!Y44*100 -> 0.031962466 | Z44: =Rev_Dep_diff!Z44/Rev_Dep_0!Z44*100 -> 0.092629577 | AA44: =Rev_Dep_diff!AA44/Rev_Dep_0!AA44*100 -> 0.18896527 | AB44: =Rev_Dep_diff!AB44/Rev_Dep_0!AB44*100 -> 0.30947011 | ... AV44: =Rev_Dep_diff!AV44/Rev_Dep_0!AV44*100 -> 2.4232541
A45: =résultats!B571 -> PEXP_12_H01_1 | B45: =Rev_Dep_2!B45-Rev_Dep_0!B45 -> 0 | C45: =Rev_Dep_2!C45-Rev_Dep_0!C45 -> 0 | D45: =Rev_Dep_2!D45-Rev_Dep_0!D45 -> 0 | E45: =Rev_Dep_2!E45-Rev_Dep_0!E45 -> 0 | F45: =Rev_Dep_2!F45-Rev_Dep_0!F45 -> 0 | G45: =Rev_Dep_2!G45-Rev_Dep_0!G45 -> 0 | H45: =Rev_Dep_2!H45-Rev_Dep_0!H45 -> 0 | I45: =Rev_Dep_2!I45-Rev_Dep_0!I45 -> 0 | ... T45: =Rev_Dep_2!T45-Rev_Dep_0!T45 -> 0 | U45: =Rev_Dep_diff!U45/Rev_Dep_0!U45*100 -> 0.0090764326 | V45: =Rev_Dep_diff!V45/Rev_Dep_0!V45*100 -> -0.0032558509 | W45: =Rev_Dep_diff!W45/Rev_Dep_0!W45*100 -> -0.026282506 | X45: =Rev_Dep_diff!X45/Rev_Dep_0!X45*100 -> -0.025089368 | Y45: =Rev_Dep_diff!Y45/Rev_Dep_0!Y45*100 -> 0.0051041725 | Z45: =Rev_Dep_diff!Z45/Rev_Dep_0!Z45*100 -> 0.069948633 | AA45: =Rev_Dep_diff!AA45/Rev_Dep_0!AA45*100 -> 0.18822698 | AB45: =Rev_Dep_diff!AB45/Rev_Dep_0!AB45*100 -> 0.35038082 | ... AV45: =Rev_Dep_diff!AV45/Rev_Dep_0!AV45*100 -> 2.8958519
A46: =résultats!B572 -> PEXP_13_H01_1 | B46: =Rev_Dep_2!B46-Rev_Dep_0!B46 -> 0 | C46: =Rev_Dep_2!C46-Rev_Dep_0!C46 -> 0 | D46: =Rev_Dep_2!D46-Rev_Dep_0!D46 -> 0 | E46: =Rev_Dep_2!E46-Rev_Dep_0!E46 -> 0 | F46: =Rev_Dep_2!F46-Rev_Dep_0!F46 -> 0 | G46: =Rev_Dep_2!G46-Rev_Dep_0!G46 -> 0 | H46: =Rev_Dep_2!H46-Rev_Dep_0!H46 -> 0 | I46: =Rev_Dep_2!I46-Rev_Dep_0!I46 -> 0 | ... T46: =Rev_Dep_2!T46-Rev_Dep_0!T46 -> 0 | U46: =Rev_Dep_diff!U46/Rev_Dep_0!U46*100 -> 0.019446085 | V46: =Rev_Dep_diff!V46/Rev_Dep_0!V46*100 -> -3.767449 | W46: =Rev_Dep_diff!W46/Rev_Dep_0!W46*100 -> -6.9100185 | X46: =Rev_Dep_diff!X46/Rev_Dep_0!X46*100 -> -11.14349 | Y46: =Rev_Dep_diff!Y46/Rev_Dep_0!Y46*100 -> -11.671458 | Z46: =Rev_Dep_diff!Z46/Rev_Dep_0!Z46*100 -> -12.655377 | AA46: =Rev_Dep_diff!AA46/Rev_Dep_0!AA46*100 -> -12.949292 | AB46: =Rev_Dep_diff!AB46/Rev_Dep_0!AB46*100 -> -13.954766 | ... AV46: =Rev_Dep_diff!AV46/Rev_Dep_0!AV46*100 -> -13.75719
A47: =résultats!B573 -> PEXP_14_H01_1 | B47: =Rev_Dep_2!B47-Rev_Dep_0!B47 -> 0 | C47: =Rev_Dep_2!C47-Rev_Dep_0!C47 -> 0 | D47: =Rev_Dep_2!D47-Rev_Dep_0!D47 -> 0 | E47: =Rev_Dep_2!E47-Rev_Dep_0!E47 -> 0 | F47: =Rev_Dep_2!F47-Rev_Dep_0!F47 -> 0 | G47: =Rev_Dep_2!G47-Rev_Dep_0!G47 -> 0 | H47: =Rev_Dep_2!H47-Rev_Dep_0!H47 -> 0 | I47: =Rev_Dep_2!I47-Rev_Dep_0!I47 -> 0 | ... T47: =Rev_Dep_2!T47-Rev_Dep_0!T47 -> 0 | U47: =Rev_Dep_diff!U47/Rev_Dep_0!U47*100 -> 0.0025794474 | V47: =Rev_Dep_diff!V47/Rev_Dep_0!V47*100 -> 0.36060879 | W47: =Rev_Dep_diff!W47/Rev_Dep_0!W47*100 -> 0.74337866 | X47: =Rev_Dep_diff!X47/Rev_Dep_0!X47*100 -> 0.77942767 | Y47: =Rev_Dep_diff!Y47/Rev_Dep_0!Y47*100 -> 0.88241568 | Z47: =Rev_Dep_diff!Z47/Rev_Dep_0!Z47*100 -> 1.156606 | AA47: =Rev_Dep_diff!AA47/Rev_Dep_0!AA47*100 -> 1.5072956 | AB47: =Rev_Dep_diff!AB47/Rev_Dep_0!AB47*100 -> 1.876511 | ... AV47: =Rev_Dep_diff!AV47/Rev_Dep_0!AV47*100 -> 7.2490233
A48: =résultats!B574 -> PEXP_15_H01_1 | B48: =Rev_Dep_2!B48-Rev_Dep_0!B48 -> 0 | C48: =Rev_Dep_2!C48-Rev_Dep_0!C48 -> 0 | D48: =Rev_Dep_2!D48-Rev_Dep_0!D48 -> 0 | E48: =Rev_Dep_2!E48-Rev_Dep_0!E48 -> 0 | F48: =Rev_Dep_2!F48-Rev_Dep_0!F48 -> 0 | G48: =Rev_Dep_2!G48-Rev_Dep_0!G48 -> 0 | H48: =Rev_Dep_2!H48-Rev_Dep_0!H48 -> 0 | I48: =Rev_Dep_2!I48-Rev_Dep_0!I48 -> 0 | ... T48: =Rev_Dep_2!T48-Rev_Dep_0!T48 -> 0 | U48: =Rev_Dep_diff!U48/Rev_Dep_0!U48*100 -> -0.017702435 | V48: =Rev_Dep_diff!V48/Rev_Dep_0!V48*100 -> -0.44876347 | W48: =Rev_Dep_diff!W48/Rev_Dep_0!W48*100 -> -0.66553501 | X48: =Rev_Dep_diff!X48/Rev_Dep_0!X48*100 -> -0.93145079 | Y48: =Rev_Dep_diff!Y48/Rev_Dep_0!Y48*100 -> -0.92777474 | Z48: =Rev_Dep_diff!Z48/Rev_Dep_0!Z48*100 -> -0.57098302 | AA48: =Rev_Dep_diff!AA48/Rev_Dep_0!AA48*100 -> 0.0021267718 | AB48: =Rev_Dep_diff!AB48/Rev_Dep_0!AB48*100 -> 0.59135561 | ... AV48: =Rev_Dep_diff!AV48/Rev_Dep_0!AV48*100 -> 5.0819168
A49: =résultats!B575 -> PEXP_16_H01_1 | B49: =Rev_Dep_2!B49-Rev_Dep_0!B49 -> 0 | C49: =Rev_Dep_2!C49-Rev_Dep_0!C49 -> 0 | D49: =Rev_Dep_2!D49-Rev_Dep_0!D49 -> 0 | E49: =Rev_Dep_2!E49-Rev_Dep_0!E49 -> 0 | F49: =Rev_Dep_2!F49-Rev_Dep_0!F49 -> 0 | G49: =Rev_Dep_2!G49-Rev_Dep_0!G49 -> 0 | H49: =Rev_Dep_2!H49-Rev_Dep_0!H49 -> 0 | I49: =Rev_Dep_2!I49-Rev_Dep_0!I49 -> 0 | ... T49: =Rev_Dep_2!T49-Rev_Dep_0!T49 -> 0 | U49: =Rev_Dep_diff!U49/Rev_Dep_0!U49*100 -> -0.014551263 | V49: =Rev_Dep_diff!V49/Rev_Dep_0!V49*100 -> -0.6307968 | W49: =Rev_Dep_diff!W49/Rev_Dep_0!W49*100 -> -0.86277031 | X49: =Rev_Dep_diff!X49/Rev_Dep_0!X49*100 -> -1.1649897 | Y49: =Rev_Dep_diff!Y49/Rev_Dep_0!Y49*100 -> -1.1836445 | Z49: =Rev_Dep_diff!Z49/Rev_Dep_0!Z49*100 -> -0.94721485 | AA49: =Rev_Dep_diff!AA49/Rev_Dep_0!AA49*100 -> -0.021008152 | AB49: =Rev_Dep_diff!AB49/Rev_Dep_0!AB49*100 -> 1.210721 | ... AV49: =Rev_Dep_diff!AV49/Rev_Dep_0!AV49*100 -> 4.0145008
A50: =résultats!B576 -> PEXP_17_H01_1 | B50: =Rev_Dep_2!B50-Rev_Dep_0!B50 -> 0 | C50: =Rev_Dep_2!C50-Rev_Dep_0!C50 -> 0 | D50: =Rev_Dep_2!D50-Rev_Dep_0!D50 -> 0 | E50: =Rev_Dep_2!E50-Rev_Dep_0!E50 -> 0 | F50: =Rev_Dep_2!F50-Rev_Dep_0!F50 -> 0 | G50: =Rev_Dep_2!G50-Rev_Dep_0!G50 -> 0 | H50: =Rev_Dep_2!H50-Rev_Dep_0!H50 -> 0 | I50: =Rev_Dep_2!I50-Rev_Dep_0!I50 -> 0 | ... T50: =Rev_Dep_2!T50-Rev_Dep_0!T50 -> 0 | U50: =Rev_Dep_diff!U50/Rev_Dep_0!U50*100 -> -0.018536687 | V50: =Rev_Dep_diff!V50/Rev_Dep_0!V50*100 -> 0.10892333 | W50: =Rev_Dep_diff!W50/Rev_Dep_0!W50*100 -> 0.14949525 | X50: =Rev_Dep_diff!X50/Rev_Dep_0!X50*100 -> -0.27932616 | Y50: =Rev_Dep_diff!Y50/Rev_Dep_0!Y50*100 -> -0.49810142 | Z50: =Rev_Dep_diff!Z50/Rev_Dep_0!Z50*100 -> -0.46854112 | AA50: =Rev_Dep_diff!AA50/Rev_Dep_0!AA50*100 -> -0.071365482 | AB50: =Rev_Dep_diff!AB50/Rev_Dep_0!AB50*100 -> 0.62430348 | ... AV50: =Rev_Dep_diff!AV50/Rev_Dep_0!AV50*100 -> 3.3703211
A51: =résultats!B577 -> PEXP_18_H01_1 | B51: =Rev_Dep_2!B51-Rev_Dep_0!B51 -> 0 | C51: =Rev_Dep_2!C51-Rev_Dep_0!C51 -> 0 | D51: =Rev_Dep_2!D51-Rev_Dep_0!D51 -> 0 | E51: =Rev_Dep_2!E51-Rev_Dep_0!E51 -> 0 | F51: =Rev_Dep_2!F51-Rev_Dep_0!F51 -> 0 | G51: =Rev_Dep_2!G51-Rev_Dep_0!G51 -> 0 | H51: =Rev_Dep_2!H51-Rev_Dep_0!H51 -> 0 | I51: =Rev_Dep_2!I51-Rev_Dep_0!I51 -> 0 | ... T51: =Rev_Dep_2!T51-Rev_Dep_0!T51 -> 0 | U51: =Rev_Dep_diff!U51/Rev_Dep_0!U51*100 -> 5.8574939e-05 | V51: =Rev_Dep_diff!V51/Rev_Dep_0!V51*100 -> 0.072922858 | W51: =Rev_Dep_diff!W51/Rev_Dep_0!W51*100 -> 0.10913627 | X51: =Rev_Dep_diff!X51/Rev_Dep_0!X51*100 -> 0.15358743 | Y51: =Rev_Dep_diff!Y51/Rev_Dep_0!Y51*100 -> 0.20232371 | Z51: =Rev_Dep_diff!Z51/Rev_Dep_0!Z51*100 -> 0.28087083 | AA51: =Rev_Dep_diff!AA51/Rev_Dep_0!AA51*100 -> 0.40176951 | AB51: =Rev_Dep_diff!AB51/Rev_Dep_0!AB51*100 -> 0.56662594 | ... AV51: =Rev_Dep_diff!AV51/Rev_Dep_0!AV51*100 -> 2.5502425
A52: =résultats!B578 -> PEXP_19_H01_1 | B52: =Rev_Dep_2!B52-Rev_Dep_0!B52 -> 0 | C52: =Rev_Dep_2!C52-Rev_Dep_0!C52 -> 0 | D52: =Rev_Dep_2!D52-Rev_Dep_0!D52 -> 0 | E52: =Rev_Dep_2!E52-Rev_Dep_0!E52 -> 0 | F52: =Rev_Dep_2!F52-Rev_Dep_0!F52 -> 0 | G52: =Rev_Dep_2!G52-Rev_Dep_0!G52 -> 0 | H52: =Rev_Dep_2!H52-Rev_Dep_0!H52 -> 0 | I52: =Rev_Dep_2!I52-Rev_Dep_0!I52 -> 0 | ... T52: =Rev_Dep_2!T52-Rev_Dep_0!T52 -> 0 | U52: =Rev_Dep_diff!U52/Rev_Dep_0!U52*100 -> 0.0025206077 | V52: =Rev_Dep_diff!V52/Rev_Dep_0!V52*100 -> -0.0019070059 | W52: =Rev_Dep_diff!W52/Rev_Dep_0!W52*100 -> -0.0034906864 | X52: =Rev_Dep_diff!X52/Rev_Dep_0!X52*100 -> 0.064930758 | Y52: =Rev_Dep_diff!Y52/Rev_Dep_0!Y52*100 -> 0.16285968 | Z52: =Rev_Dep_diff!Z52/Rev_Dep_0!Z52*100 -> 0.28124487 | AA52: =Rev_Dep_diff!AA52/Rev_Dep_0!AA52*100 -> 0.43972558 | AB52: =Rev_Dep_diff!AB52/Rev_Dep_0!AB52*100 -> 0.62080936 | ... AV52: =Rev_Dep_diff!AV52/Rev_Dep_0!AV52*100 -> 3.6218658
A53: =résultats!B579 -> PEXP_20_H01_1 | B53: =Rev_Dep_2!B53-Rev_Dep_0!B53 -> 0 | C53: =Rev_Dep_2!C53-Rev_Dep_0!C53 -> 0 | D53: =Rev_Dep_2!D53-Rev_Dep_0!D53 -> 0 | E53: =Rev_Dep_2!E53-Rev_Dep_0!E53 -> 0 | F53: =Rev_Dep_2!F53-Rev_Dep_0!F53 -> 0 | G53: =Rev_Dep_2!G53-Rev_Dep_0!G53 -> 0 | H53: =Rev_Dep_2!H53-Rev_Dep_0!H53 -> 0 | I53: =Rev_Dep_2!I53-Rev_Dep_0!I53 -> 0 | ... T53: =Rev_Dep_2!T53-Rev_Dep_0!T53 -> 0 | U53: =Rev_Dep_diff!U53/Rev_Dep_0!U53*100 -> -0.00076923337 | V53: =Rev_Dep_diff!V53/Rev_Dep_0!V53*100 -> 0.00013582495 | W53: =Rev_Dep_diff!W53/Rev_Dep_0!W53*100 -> 0.0051842596 | X53: =Rev_Dep_diff!X53/Rev_Dep_0!X53*100 -> 0.018020098 | Y53: =Rev_Dep_diff!Y53/Rev_Dep_0!Y53*100 -> 0.044866952 | Z53: =Rev_Dep_diff!Z53/Rev_Dep_0!Z53*100 -> 0.095314043 | AA53: =Rev_Dep_diff!AA53/Rev_Dep_0!AA53*100 -> 0.17326617 | AB53: =Rev_Dep_diff!AB53/Rev_Dep_0!AB53*100 -> 0.27170742 | ... AV53: =Rev_Dep_diff!AV53/Rev_Dep_0!AV53*100 -> 3.2549583
A54: =résultats!B580 -> PEXP_21_H01_1 | B54: =Rev_Dep_2!B54-Rev_Dep_0!B54 -> 0 | C54: =Rev_Dep_2!C54-Rev_Dep_0!C54 -> 0 | D54: =Rev_Dep_2!D54-Rev_Dep_0!D54 -> 0 | E54: =Rev_Dep_2!E54-Rev_Dep_0!E54 -> 0 | F54: =Rev_Dep_2!F54-Rev_Dep_0!F54 -> 0 | G54: =Rev_Dep_2!G54-Rev_Dep_0!G54 -> 0 | H54: =Rev_Dep_2!H54-Rev_Dep_0!H54 -> 0 | I54: =Rev_Dep_2!I54-Rev_Dep_0!I54 -> 0 | ... T54: =Rev_Dep_2!T54-Rev_Dep_0!T54 -> 0 | U54: =Rev_Dep_diff!U54/Rev_Dep_0!U54*100 -> 0.043096281 | V54: =Rev_Dep_diff!V54/Rev_Dep_0!V54*100 -> -3.8158341 | W54: =Rev_Dep_diff!W54/Rev_Dep_0!W54*100 -> -8.8902234 | X54: =Rev_Dep_diff!X54/Rev_Dep_0!X54*100 -> -12.262043 | Y54: =Rev_Dep_diff!Y54/Rev_Dep_0!Y54*100 -> -15.266472 | Z54: =Rev_Dep_diff!Z54/Rev_Dep_0!Z54*100 -> -17.910506 | AA54: =Rev_Dep_diff!AA54/Rev_Dep_0!AA54*100 -> -19.708598 | AB54: =Rev_Dep_diff!AB54/Rev_Dep_0!AB54*100 -> -21.128456 | ... AV54: =Rev_Dep_diff!AV54/Rev_Dep_0!AV54*100 -> -17.323655
A55: =résultats!B581 -> PEXP_22_H01_1 | B55: =Rev_Dep_2!B55-Rev_Dep_0!B55 -> 0 | C55: =Rev_Dep_2!C55-Rev_Dep_0!C55 -> 0 | D55: =Rev_Dep_2!D55-Rev_Dep_0!D55 -> 0 | E55: =Rev_Dep_2!E55-Rev_Dep_0!E55 -> 0 | F55: =Rev_Dep_2!F55-Rev_Dep_0!F55 -> 0 | G55: =Rev_Dep_2!G55-Rev_Dep_0!G55 -> 0 | H55: =Rev_Dep_2!H55-Rev_Dep_0!H55 -> 0 | I55: =Rev_Dep_2!I55-Rev_Dep_0!I55 -> 0 | ... T55: =Rev_Dep_2!T55-Rev_Dep_0!T55 -> 0 | U55: =Rev_Dep_diff!U55/Rev_Dep_0!U55*100 -> -0.056145507 | V55: =Rev_Dep_diff!V55/Rev_Dep_0!V55*100 -> -0.38635128 | W55: =Rev_Dep_diff!W55/Rev_Dep_0!W55*100 -> -0.48907105 | X55: =Rev_Dep_diff!X55/Rev_Dep_0!X55*100 -> -0.31089273 | Y55: =Rev_Dep_diff!Y55/Rev_Dep_0!Y55*100 -> -0.3325317 | Z55: =Rev_Dep_diff!Z55/Rev_Dep_0!Z55*100 -> -0.37694334 | AA55: =Rev_Dep_diff!AA55/Rev_Dep_0!AA55*100 -> 1.9475761 | AB55: =Rev_Dep_diff!AB55/Rev_Dep_0!AB55*100 -> 4.3511194 | ... AV55: =Rev_Dep_diff!AV55/Rev_Dep_0!AV55*100 -> 4.1045009
... A57: =résultats!B583 -> PEXP_24_H01_1 | B57: =Rev_Dep_2!B57-Rev_Dep_0!B57 -> 0 | C57: =Rev_Dep_2!C57-Rev_Dep_0!C57 -> 0 | D57: =Rev_Dep_2!D57-Rev_Dep_0!D57 -> 0 | E57: =Rev_Dep_2!E57-Rev_Dep_0!E57 -> 0 | F57: =Rev_Dep_2!F57-Rev_Dep_0!F57 -> 0 | G57: =Rev_Dep_2!G57-Rev_Dep_0!G57 -> 0 | H57: =Rev_Dep_2!H57-Rev_Dep_0!H57 -> 0 | I57: =Rev_Dep_2!I57-Rev_Dep_0!I57 -> 0 | ... T57: =Rev_Dep_2!T57-Rev_Dep_0!T57 -> 0 | U57: =Rev_Dep_diff!U57/Rev_Dep_0!U57*100 -> -2.4942996 | V57: =Rev_Dep_diff!V57/Rev_Dep_0!V57*100 -> -3.7177621 | W57: =Rev_Dep_diff!W57/Rev_Dep_0!W57*100 -> -3.4729693 | X57: =Rev_Dep_diff!X57/Rev_Dep_0!X57*100 -> -2.6163187 | Y57: =Rev_Dep_diff!Y57/Rev_Dep_0!Y57*100 -> -3.1839091 | Z57: =Rev_Dep_diff!Z57/Rev_Dep_0!Z57*100 -> -3.5764895 | AA57: =Rev_Dep_diff!AA57/Rev_Dep_0!AA57*100 -> -0.88982676 | AB57: =Rev_Dep_diff!AB57/Rev_Dep_0!AB57*100 -> 1.7797097 | ... AV57: =Rev_Dep_diff!AV57/Rev_Dep_0!AV57*100 -> 1.0908017
A58: pexp*exp | U58: =Rev_Dep_diff!U58/Rev_Dep_0!U58*100 -> 0.034587968 | V58: =Rev_Dep_diff!V58/Rev_Dep_0!V58*100 -> 0.34280383 | W58: =Rev_Dep_diff!W58/Rev_Dep_0!W58*100 -> 0.31569017 | X58: =Rev_Dep_diff!X58/Rev_Dep_0!X58*100 -> -0.083260222 | Y58: =Rev_Dep_diff!Y58/Rev_Dep_0!Y58*100 -> 0.27008379 | Z58: =Rev_Dep_diff!Z58/Rev_Dep_0!Z58*100 -> 0.57216171 | AA58: =Rev_Dep_diff!AA58/Rev_Dep_0!AA58*100 -> 0.78145353 | AB58: =Rev_Dep_diff!AB58/Rev_Dep_0!AB58*100 -> 0.81290082 | ... AV58: =Rev_Dep_diff!AV58/Rev_Dep_0!AV58*100 -> 4.1277116
A59: pexp*exp_1 | U59: =Rev_Dep_diff!U59/Rev_Dep_0!U59*100 -> 0.059294231 | V59: =Rev_Dep_diff!V59/Rev_Dep_0!V59*100 -> -0.43771468 | W59: =Rev_Dep_diff!W59/Rev_Dep_0!W59*100 -> -0.87425284 | X59: =Rev_Dep_diff!X59/Rev_Dep_0!X59*100 -> 0.19031435 | Y59: =Rev_Dep_diff!Y59/Rev_Dep_0!Y59*100 -> 1.2482189 | Z59: =Rev_Dep_diff!Z59/Rev_Dep_0!Z59*100 -> 2.0969893 | AA59: =Rev_Dep_diff!AA59/Rev_Dep_0!AA59*100 -> 2.6381386 | AB59: =Rev_Dep_diff!AB59/Rev_Dep_0!AB59*100 -> 2.9111851 | ... AV59: =Rev_Dep_diff!AV59/Rev_Dep_0!AV59*100 -> 8.3260125
A60: pexp*exp_2 | U60: =Rev_Dep_diff!U60/Rev_Dep_0!U60*100 -> 0.072497075 | V60: =Rev_Dep_diff!V60/Rev_Dep_0!V60*100 -> -0.41520672 | W60: =Rev_Dep_diff!W60/Rev_Dep_0!W60*100 -> -0.90324321 | X60: =Rev_Dep_diff!X60/Rev_Dep_0!X60*100 -> 0.078253778 | Y60: =Rev_Dep_diff!Y60/Rev_Dep_0!Y60*100 -> 1.0625185 | Z60: =Rev_Dep_diff!Z60/Rev_Dep_0!Z60*100 -> 1.8419209 | AA60: =Rev_Dep_diff!AA60/Rev_Dep_0!AA60*100 -> 2.3232489 | AB60: =Rev_Dep_diff!AB60/Rev_Dep_0!AB60*100 -> 2.5476018 | ... AV60: =Rev_Dep_diff!AV60/Rev_Dep_0!AV60*100 -> 4.9790255
A61: pexp*exp_3 | U61: =Rev_Dep_diff!U61/Rev_Dep_0!U61*100 -> -0.057611245 | V61: =Rev_Dep_diff!V61/Rev_Dep_0!V61*100 -> -3.849918 | W61: =Rev_Dep_diff!W61/Rev_Dep_0!W61*100 -> -6.0997018 | X61: =Rev_Dep_diff!X61/Rev_Dep_0!X61*100 -> -8.4210948 | Y61: =Rev_Dep_diff!Y61/Rev_Dep_0!Y61*100 -> -8.7217246 | Z61: =Rev_Dep_diff!Z61/Rev_Dep_0!Z61*100 -> -10.884797 | AA61: =Rev_Dep_diff!AA61/Rev_Dep_0!AA61*100 -> -13.308399 | AB61: =Rev_Dep_diff!AB61/Rev_Dep_0!AB61*100 -> -16.352001 | ... AV61: =Rev_Dep_diff!AV61/Rev_Dep_0!AV61*100 -> -30.386141
A62: pexp*exp_4 | U62: =Rev_Dep_diff!U62/Rev_Dep_0!U62*100 -> 0.010797942 | V62: =Rev_Dep_diff!V62/Rev_Dep_0!V62*100 -> 8.6167412 | W62: =Rev_Dep_diff!W62/Rev_Dep_0!W62*100 -> 16.361845 | X62: =Rev_Dep_diff!X62/Rev_Dep_0!X62*100 -> 16.588946 | Y62: =Rev_Dep_diff!Y62/Rev_Dep_0!Y62*100 -> 18.125475 | Z62: =Rev_Dep_diff!Z62/Rev_Dep_0!Z62*100 -> 20.252968 | AA62: =Rev_Dep_diff!AA62/Rev_Dep_0!AA62*100 -> 22.791683 | AB62: =Rev_Dep_diff!AB62/Rev_Dep_0!AB62*100 -> 25.52069 | ... AV62: =Rev_Dep_diff!AV62/Rev_Dep_0!AV62*100 -> 78.776738
A63: pexp*exp_5 | U63: =Rev_Dep_diff!U63/Rev_Dep_0!U63*100 -> 0.0015686983 | V63: =Rev_Dep_diff!V63/Rev_Dep_0!V63*100 -> 5.3589992 | W63: =Rev_Dep_diff!W63/Rev_Dep_0!W63*100 -> 9.9515876 | X63: =Rev_Dep_diff!X63/Rev_Dep_0!X63*100 -> 8.857253 | Y63: =Rev_Dep_diff!Y63/Rev_Dep_0!Y63*100 -> 9.2044707 | Z63: =Rev_Dep_diff!Z63/Rev_Dep_0!Z63*100 -> 10.264902 | AA63: =Rev_Dep_diff!AA63/Rev_Dep_0!AA63*100 -> 11.79494 | AB63: =Rev_Dep_diff!AB63/Rev_Dep_0!AB63*100 -> 13.484903 | ... AV63: =Rev_Dep_diff!AV63/Rev_Dep_0!AV63*100 -> 25.998025
A64: pexp*exp_6 | U64: =Rev_Dep_diff!U64/Rev_Dep_0!U64*100 -> 0.048854364 | V64: =Rev_Dep_diff!V64/Rev_Dep_0!V64*100 -> -1.0363361 | W64: =Rev_Dep_diff!W64/Rev_Dep_0!W64*100 -> -1.597056 | X64: =Rev_Dep_diff!X64/Rev_Dep_0!X64*100 -> -0.77152155 | Y64: =Rev_Dep_diff!Y64/Rev_Dep_0!Y64*100 -> 0.34312946 | Z64: =Rev_Dep_diff!Z64/Rev_Dep_0!Z64*100 -> 1.461804 | AA64: =Rev_Dep_diff!AA64/Rev_Dep_0!AA64*100 -> 2.8919726 | AB64: =Rev_Dep_diff!AB64/Rev_Dep_0!AB64*100 -> 4.1954916 | ... AV64: =Rev_Dep_diff!AV64/Rev_Dep_0!AV64*100 -> 9.2529302
A65: pexp*exp_7 | U65: =Rev_Dep_diff!U65/Rev_Dep_0!U65*100 -> 0.0448664 | V65: =Rev_Dep_diff!V65/Rev_Dep_0!V65*100 -> -0.29899535 | W65: =Rev_Dep_diff!W65/Rev_Dep_0!W65*100 -> -0.71197642 | X65: =Rev_Dep_diff!X65/Rev_Dep_0!X65*100 -> -0.12862342 | Y65: =Rev_Dep_diff!Y65/Rev_Dep_0!Y65*100 -> 0.72593923 | Z65: =Rev_Dep_diff!Z65/Rev_Dep_0!Z65*100 -> 1.6253137 | AA65: =Rev_Dep_diff!AA65/Rev_Dep_0!AA65*100 -> 2.5381923 | AB65: =Rev_Dep_diff!AB65/Rev_Dep_0!AB65*100 -> 3.396278 | ... AV65: =Rev_Dep_diff!AV65/Rev_Dep_0!AV65*100 -> 8.8325392
A66: pexp*exp_8 | U66: =Rev_Dep_diff!U66/Rev_Dep_0!U66*100 -> 0.058836102 | V66: =Rev_Dep_diff!V66/Rev_Dep_0!V66*100 -> -2.4459805 | W66: =Rev_Dep_diff!W66/Rev_Dep_0!W66*100 -> -5.2162357 | X66: =Rev_Dep_diff!X66/Rev_Dep_0!X66*100 -> -7.5902812 | Y66: =Rev_Dep_diff!Y66/Rev_Dep_0!Y66*100 -> -9.6030969 | Z66: =Rev_Dep_diff!Z66/Rev_Dep_0!Z66*100 -> -11.714806 | AA66: =Rev_Dep_diff!AA66/Rev_Dep_0!AA66*100 -> -13.999359 | AB66: =Rev_Dep_diff!AB66/Rev_Dep_0!AB66*100 -> -16.487894 | ... AV66: =Rev_Dep_diff!AV66/Rev_Dep_0!AV66*100 -> -68.637497
A67: pexp*exp_9 | U67: =Rev_Dep_diff!U67/Rev_Dep_0!U67*100 -> 0.065937071 | V67: =Rev_Dep_diff!V67/Rev_Dep_0!V67*100 -> -0.41279258 | W67: =Rev_Dep_diff!W67/Rev_Dep_0!W67*100 -> -0.84803182 | X67: =Rev_Dep_diff!X67/Rev_Dep_0!X67*100 -> 0.25167312 | Y67: =Rev_Dep_diff!Y67/Rev_Dep_0!Y67*100 -> 1.3621511 | Z67: =Rev_Dep_diff!Z67/Rev_Dep_0!Z67*100 -> 2.2582364 | AA67: =Rev_Dep_diff!AA67/Rev_Dep_0!AA67*100 -> 2.847333 | AB67: =Rev_Dep_diff!AB67/Rev_Dep_0!AB67*100 -> 3.1622965 | ... AV67: =Rev_Dep_diff!AV67/Rev_Dep_0!AV67*100 -> 9.0611869
A68: pexp*exp_11 | U68: =Rev_Dep_diff!U68/Rev_Dep_0!U68*100 -> 0.059294231 | V68: =Rev_Dep_diff!V68/Rev_Dep_0!V68*100 -> -0.43771468 | W68: =Rev_Dep_diff!W68/Rev_Dep_0!W68*100 -> -0.87425284 | X68: =Rev_Dep_diff!X68/Rev_Dep_0!X68*100 -> 0.19031435 | Y68: =Rev_Dep_diff!Y68/Rev_Dep_0!Y68*100 -> 1.2482189 | Z68: =Rev_Dep_diff!Z68/Rev_Dep_0!Z68*100 -> 2.0969893 | AA68: =Rev_Dep_diff!AA68/Rev_Dep_0!AA68*100 -> 2.6381386 | AB68: =Rev_Dep_diff!AB68/Rev_Dep_0!AB68*100 -> 2.9111851 | ... AV68: =Rev_Dep_diff!AV68/Rev_Dep_0!AV68*100 -> 8.3260125
A69: pexp*exp_12 | U69: =Rev_Dep_diff!U69/Rev_Dep_0!U69*100 -> 0.072497075 | V69: =Rev_Dep_diff!V69/Rev_Dep_0!V69*100 -> -0.41520672 | W69: =Rev_Dep_diff!W69/Rev_Dep_0!W69*100 -> -0.90324321 | X69: =Rev_Dep_diff!X69/Rev_Dep_0!X69*100 -> 0.078253778 | Y69: =Rev_Dep_diff!Y69/Rev_Dep_0!Y69*100 -> 1.0625185 | Z69: =Rev_Dep_diff!Z69/Rev_Dep_0!Z69*100 -> 1.8419209 | AA69: =Rev_Dep_diff!AA69/Rev_Dep_0!AA69*100 -> 2.3232489 | AB69: =Rev_Dep_diff!AB69/Rev_Dep_0!AB69*100 -> 2.5476018 | ... AV69: =Rev_Dep_diff!AV69/Rev_Dep_0!AV69*100 -> 4.9790255
... A81: pexp*exp_24 | U81: =Rev_Dep_diff!U81/Rev_Dep_0!U81*100 -> -1.1245988 | V81: =Rev_Dep_diff!V81/Rev_Dep_0!V81*100 -> -1.8973192 | W81: =Rev_Dep_diff!W81/Rev_Dep_0!W81*100 -> -1.8202299 | X81: =Rev_Dep_diff!X81/Rev_Dep_0!X81*100 -> -1.769145 | Y81: =Rev_Dep_diff!Y81/Rev_Dep_0!Y81*100 -> -3.4743755 | Z81: =Rev_Dep_diff!Z81/Rev_Dep_0!Z81*100 -> -5.2253798 | AA81: =Rev_Dep_diff!AA81/Rev_Dep_0!AA81*100 -> -5.5280118 | AB81: =Rev_Dep_diff!AB81/Rev_Dep_0!AB81*100 -> -5.8822272 | ... AV81: =Rev_Dep_diff!AV81/Rev_Dep_0!AV81*100 -> -28.594507

Sheet Dette rénovation
B1: =C1-1 -> 1979 | C1: =D1-1 -> 1980 | D1: =E1-1 -> 1981 | E1: =F1-1 -> 1982 | F1: =G1-1 -> 1983 | G1: =H1-1 -> 1984 | H1: =I1-1 -> 1985 | I1: =J1-1 -> 1986 | ... Y1: =Z1-1 -> 2002 | Z1: =AB1-1 -> 2003 | AB1: 2004 | AC1: 2005 | AD1: 2006 | AE1: 2007 | AF1: 2008 | AG1: 2009 | AH1: 2010 | AI1: 2011 | AJ1: 2012 | AK1: 2013 | AL1: 2014 | AM1: 2015 | AN1: 2016 | AO1: 2017 | AP1: 2018 | AQ1: 2019 | AR1: 2020 | AS1: 2021 | AT1: 2022 | AU1: 2023 | AV1: 2024 | AW1: 2025 | AX1: 2026 | AY1: 2027 | AZ1: 2028 | BA1: 2029 | BB1: 2030 | BC1: 2031 | BD1: 2032 | BE1: 2033 | BF1: 2034 | BG1: 2035 | BH1: 2036 | BI1: 2037 | BJ1: 2038 | BK1: 2039 | BL1: 2040 | BM1: 2041 | BN1: 2042 | BO1: 2043 | BP1: 2044 | BQ1: 2045 | BR1: 2046 | BS1: 2047 | BT1: 2048 | BU1: 2049 | BV1: 2050
A2: Rénovation (M€ courants) | B2: =C2/(1+0.04) -> 1769.7007 | C2: =D2/(1+0.04) -> 1840.4887 | D2: =E2/(1+0.04) -> 1914.1082 | E2: =F2/(1+0.04) -> 1990.6726 | F2: =G2/(1+0.04) -> 2070.2995 | G2: =H2/(1+0.04) -> 2153.1115 | H2: =I2/(1+0.04) -> 2239.2359 | I2: =J2/(1+0.04) -> 2328.8053 | ... Y2: =Z2/(1+0.04) -> 4361.8087 | Z2: =AB2/(1+Z4) -> 4536.2811 | AA2: REHAB_VAL_1 | AB2: =résultats!C2 -> 4655.932 | AC2: =résultats!D2 -> 4825.2982 | AD2: =résultats!E2 -> 4958.9472 | AE2: =résultats!F2 -> 4601.6258 | AF2: =résultats!G2 -> 5944.0779 | AG2: =résultats!H2 -> 6462.5149 | AH2: =résultats!I2 -> 5653.6409 | AI2: =résultats!J2 -> 5784.6682 | ... BV2: =résultats!AW2 -> 25982.98
A3: Taux d'emprunt | B3: 0.5 | C3: 0.5 | D3: 0.5 | E3: 0.5 | F3: 0.5 | G3: 0.5 | H3: 0.5 | I3: 0.5 | J3: 0.5 | K3: 0.5 | L3: 0.5 | M3: 0.5 | N3: 0.5 | O3: 0.5 | P3: 0.5 | Q3: 0.5 | R3: 0.5 | S3: 0.5 | T3: 0.5 | U3: 0.5 | V3: 0.5 | W3: 0.5 | X3: 0.5 | Y3: 0.5 | Z3: 0.5 | AA3: R_LOAN_REHAB_H01_CG_1 | AB3: =résultats!C3 -> 0.3 | AC3: =résultats!D3 -> 0.3 | AD3: =résultats!E3 -> 0.3 | AE3: =résultats!F3 -> 0.3 | AF3: =résultats!G3 -> 0.3 | AG3: =résultats!H3 -> 0.3 | AH3: =résultats!I3 -> 0.3 | AI3: =résultats!J3 -> 0.3 | ... BV3: =résultats!AW3 -> 0.3
A4: Taux d'intérêt | B4: 0.02637643 | C4: 0.02637643 | D4: 0.02637643 | E4: 0.02637643 | F4: 0.02637643 | G4: 0.02637643 | H4: 0.02637643 | I4: 0.02637643 | J4: 0.02637643 | K4: 0.02637643 | L4: 0.02637643 | M4: 0.02637643 | N4: 0.02637643 | O4: 0.02637643 | P4: 0.02637643 | Q4: 0.02637643 | R4: 0.02637643 | S4: 0.02637643 | T4: 0.02637643 | U4: 0.02637643 | V4: 0.02637643 | W4: 0.02637643 | X4: 0.02637643 | Y4: 0.02637643 | Z4: 0.02637643 | AA4: R_1 | AB4: =résultats!C4 -> 0.02637643 | AC4: =résultats!D4 -> 0.02637643 | AD4: =résultats!E4 -> 0.013276695 | AE4: =résultats!F4 -> 0.0096219735 | AF4: =résultats!G4 -> 0.020462196 | AG4: =résultats!H4 -> 0.0078342748 | AH4: =résultats!I4 -> 0.015112648 | AI4: =résultats!J4 -> 0.014958585 | ... BV4: =résultats!AW4 -> 0.025899267
A5: Durée de vie (an) | B5: 25 | C5: 25 | D5: 25 | E5: 25 | F5: 25 | G5: 25 | H5: 25 | I5: 25 | J5: 25 | K5: 25 | L5: 25 | M5: 25 | N5: 25 | O5: 25 | P5: 25 | Q5: 25 | R5: 25 | S5: 25 | T5: 25 | U5: 25 | V5: 25 | W5: 25 | X5: 25 | Y5: 25 | Z5: 25 | AA5: LD_REHAB_H01_CG | AB5: =résultats!C5 -> 25 | AC5: =résultats!D5 -> 25 | AD5: =résultats!E5 -> 25 | AE5: =résultats!F5 -> 25 | AF5: =résultats!G5 -> 25 | AG5: =résultats!H5 -> 25 | AH5: =résultats!I5 -> 25 | AI5: =résultats!J5 -> 25 | ... BV5: =résultats!AW5 -> 10
A6: Revenu (M€ courants) | B6: 1226094.8 | C6: 1226094.8 | D6: 1226094.8 | E6: 1226094.8 | F6: 1226094.8 | G6: 1226094.8 | H6: 1226094.8 | I6: 1226094.8 | J6: 1226094.8 | K6: 1226094.8 | L6: 1226094.8 | M6: 1226094.8 | N6: 1226094.8 | O6: 1226094.8 | P6: 1226094.8 | Q6: 1226094.8 | R6: 1226094.8 | S6: 1226094.8 | T6: 1226094.8 | U6: 1226094.8 | V6: 1226094.8 | W6: 1226094.8 | X6: 1226094.8 | Y6: 1226094.8 | Z6: 1226094.8 | AA6: DISPINC_AI_VAL_1 | AB6: =résultats!C6 -> 1226094.8 | AC6: =résultats!D6 -> 1270695.8 | AD6: =résultats!E6 -> 1304023.8 | AE6: =résultats!F6 -> 1328960 | AF6: =résultats!G6 -> 1369991.9 | AG6: =résultats!H6 -> 1353956.9 | AH6: =résultats!I6 -> 1347772.3 | AI6: =résultats!J6 -> 1381927.6 | ... BV6: =résultats!AW6 -> 4480933.7
A7: Nouvelles annuités (M€ courants) | B7: =-PMT(B4,B5,B3*B2) -> 48.785407 | C7: =-PMT(C4,C5,C3*C2) -> 50.736823 | D7: =-PMT(D4,D5,D3*D2) -> 52.766296 | E7: =-PMT(E4,E5,E3*E2) -> 54.876948 | F7: =-PMT(F4,F5,F3*F2) -> 57.072026 | G7: =-PMT(G4,G5,G3*G2) -> 59.354907 | H7: =-PMT(H4,H5,H3*H2) -> 61.729103 | I7: =-PMT(I4,I5,I3*I2) -> 64.198267 | ... Z7: =-PMT(Z4,Z5,Z3*Z2) -> 125.05184 | AB7: =-PMT(AB4,AB5,AB3*AB2) -> 77.010155 | AC7: =-PMT(AC4,AC5,AC3*AC2) -> 79.811509 | AD7: =-PMT(AD4,AD5,AD3*AD2) -> 70.31904 | AE7: =-PMT(AE4,AE5,AE3*AE2) -> 62.390997 | AF7: =-PMT(AF4,AF5,AF3*AF2) -> 91.833832 | AG7: =-PMT(AG4,AG5,AG3*AG2) -> 85.694705 | AH7: =-PMT(AH4,AH5,AH3*AH2) -> 81.970401 | AI7: =-PMT(AI4,AI5,AI3*AI2) -> 83.714638 | ... BV7: =-PMT(BV4,BV5,BV3*BV2) -> 894.77853
A8: Dette (M€ courants) | AB8: =AB2*AB3+SUM(B13:Z13) -> 1396.7796 | AC8: =AC2*AC3+AB8*(1-1/AC5) -> 2788.4979 | AD8: =AD2*AD3+AC8*(1-1/AD5) -> 4164.6421 | AE8: =AE2*AE3+AD8*(1-1/AE5) -> 5378.5442 | AF8: =AF2*AF3+AE8*(1-1/AF5) -> 6946.6258 | AG8: =AG2*AG3+AF8*(1-1/AG5) -> 8607.5152 | AH8: =AH2*AH3+AG8*(1-1/AH5) -> 9959.3069 | AI8: =AI2*AI3+AH8*(1-1/AI5) -> 11296.335 | AJ8: =AJ2*AJ3+AI8*(1-1/AJ5) -> 13007.272 | ... BV8: =BV2*BV3+BU8*(1-1/BV5) -> 63088.918
A9: Dette sur revenu | B9: =B8/B6 -> 0 | C9: =C8/C6 -> 0 | D9: =D8/D6 -> 0 | E9: =E8/E6 -> 0 | F9: =F8/F6 -> 0 | G9: =G8/G6 -> 0 | H9: =H8/H6 -> 0 | I9: =I8/I6 -> 0 | ... Z9: =Z8/Z6 -> 0 | AB9: =AB8/AB6 -> 0.0011392101 | AC9: =AC8/AC6 -> 0.0021944653 | AD9: =AD8/AD6 -> 0.0031936858 | AE9: =AE8/AE6 -> 0.004047183 | AF9: =AF8/AF6 -> 0.0050705597 | AG9: =AG8/AG6 -> 0.0063573037 | AH9: =AH8/AH6 -> 0.0073894579 | AI9: =AI8/AI6 -> 0.0081743321 | ... BV9: =BV8/BV6 -> 0.014079413
