Workbook

Sheet output
A1: Annuities heater (Billion euro/year) | C1: 1.027 | D1: 0.959 | E1: 0.884 | F1: 0.912 | G1: 0.854 | H1: 0.789 | I1: 0.728 | J1: 0.815 | K1: 0.75 | L1: 0.77 | M1: 0.795 | N1: 0.816 | O1: 0.708 | P1: 0.744 | Q1: 0.762 | R1: 0.693 | S1: 0.787 | T1: 0.709 | U1: 0.704 | V1: 0.653 | W1: 0.846 | X1: 0.727 | Y1: 0.771 | Z1: 0.75 | AA1: 0.748 | AB1: 0.747 | AC1: 0.745
A2: Annuities heater households (Billion euro/year) | C2: 1.561 | D2: 1.814 | E2: 1.673 | F2: 1.726 | G2: 1.615 | H2: 1.492 | I2: 1.378 | J2: 1.542 | K2: 1.418 | L2: 1.456 | M2: 1.503 | N2: 1.544 | O2: 1.34 | P2: 1.408 | Q2: 1.441 | R2: 1.311 | S2: 1.489 | T2: 1.341 | U2: 1.331 | V2: 1.234 | W2: 1.6 | X2: 1.375 | Y2: 1.458 | Z2: 1.418 | AA2: 1.415 | AB2: 1.414 | AC2: 1.409
A3: Annuities insulation (Billion euro/year) | C3: 0.386 | D3: 0.216 | E3: 0.329 | F3: 0.357 | G3: 0.333 | H3: 0.304 | I3: 0.379 | J3: 0.448 | K3: 0.43 | L3: 0.401 | M3: 0.384 | N3: 0.352 | O3: 0.355 | P3: 0.473 | Q3: 0.443 | R3: 0.424 | S3: 0.632 | T3: 0.461 | U3: 0.438 | V3: 0.386 | W3: 0.382 | X3: 0.366 | Y3: 0.349 | Z3: 0.334 | AA3: 0.32 | AB3: 0.307 | AC3: 0.296
A4: Annuities insulation households (Billion euro/year) | C4: 0.554 | D4: 0.425 | E4: 0.648 | F4: 0.708 | G4: 0.658 | H4: 0.598 | I4: 0.756 | J4: 0.886 | K4: 0.851 | L4: 0.791 | M4: 0.756 | N4: 0.69 | O4: 0.698 | P4: 0.922 | Q4: 0.863 | R4: 0.825 | S4: 1.238 | T4: 0.895 | U4: 0.849 | V4: 0.749 | W4: 0.742 | X4: 0.709 | Y4: 0.677 | Z4: 0.648 | AA4: 0.621 | AB4: 0.595 | AC4: 0.573
A5: Annuities insulation Owner-occupied - C1 (euro/year,household) | C5: 315.146 | D5: 192.269 | E5: 657.039 | F5: 1150.535 | G5: 1102.32 | H5: 1054.903 | I5: 1738.001 | J5: 1686.557 | K5: 1629.919 | L5: 1575.449 | M5: 1519.245 | N5: 1461.274 | O5: 1319 | P5: 1280.992 | Q5: 1244.559 | R5: 1208.35 | S5: 1011.993 | T5: 980.385 | U5: 958.416 | V5: 937.116 | W5: 922.093 | X5: 905.902 | Y5: 890.526 | Z5: 875.098 | AA5: 860.133 | AB5: 845.543 | AC5: 829.331
A6: Annuities insulation Owner-occupied - C2 (euro/year,household) | C6: 439.593 | D6: 706.915 | E6: 706.811 | F6: 1102.271 | G6: 1056.133 | H6: 1011.344 | I6: 1578.806 | J6: 1520.42 | K6: 1455.072 | L6: 1395.478 | M6: 1335.212 | N6: 1274.442 | O6: 1204.806 | P6: 1169.087 | Q6: 1133.628 | R6: 1099.919 | S6: 1001.562 | T6: 961.781 | U6: 945.26 | V6: 929.852 | W6: 920.051 | X6: 909.516 | Y6: 899.24 | Z6: 889.377 | AA6: 879.858 | AB6: 870.6 | AC6: 882.95
A7: Annuities insulation Owner-occupied - C3 (euro/year,household) | C7: 964.912 | D7: 888.48 | E7: 890.1 | F7: 1105.174 | G7: 1077.536 | H7: 1051.473 | I7: 1423.073 | J7: 1374.62 | K7: 1344.66 | L7: 1297.103 | M7: 1248.914 | N7: 1200.15 | O7: 1170.102 | P7: 1145.097 | Q7: 1120.354 | R7: 1097.945 | S7: 1292.586 | T7: 991.758 | U7: 984.566 | V7: 978.578 | W7: 976.919 | X7: 974.955 | Y7: 972.262 | Z7: 970.391 | AA7: 969.15 | AB7: 967.728 | AC7: 965.998
A8: Annuities insulation Owner-occupied - C4 (euro/year,household) | C8: 931 | D8: 933.078 | E8: 932.872 | F8: 1119.797 | G8: 1094.433 | H8: 1070.88 | I8: 1418.202 | J8: 1373.147 | K8: 1363.822 | L8: 1316.266 | M8: 1267.938 | N8: 1219.583 | O8: 1174.862 | P8: 1151.841 | Q8: 1131.279 | R8: 1110.723 | S8: 1329.547 | T8: 989.588 | U8: 983.478 | V8: 978.53 | W8: 981.982 | X8: 980.712 | Y8: 978.553 | Z8: 977.336 | AA8: 976.397 | AB8: 975.657 | AC8: 974.592
A9: Annuities insulation Owner-occupied - C5 (euro/year,household) | C9: 1179.05 | D9: 1140.559 | E9: 1116.542 | F9: 1248.897 | G9: 1211.632 | H9: 1180.796 | I9: 1391.221 | J9: 1350.955 | K9: 1430.168 | L9: 1369.132 | M9: 1310.163 | N9: 1253.901 | O9: 1186.868 | P9: 1155.482 | Q9: 1120.878 | R9: 1088.413 | S9: 1332.839 | T9: 1010.196 | U9: 1009.614 | V9: 1010.536 | W9: 1014.769 | X9: 1019.405 | Y9: 1021.857 | Z9: 1025.829 | AA9: 1029.726 | AB9: 1033.435 | AC9: 1036.771
A10: Annuities insulation Privately rented - C1 (euro/year,household) | C10: 815.738 | D10: 1540.522 | E10: 1820.005 | F10: 1779.634 | G10: 1732.705 | H10: 1678.654 | I10: 1616.611 | J10: 961.85 | K10: 939.018 | L10: 910.057 | M10: 877.935 | N10: 842.874 | O10: 822.215 | P10: 570.492 | Q10: 567.466 | R10: 564.842 | S10: 575.248 | T10: 561.309 | U10: 560.833 | V10: 560.657 | W10: 560.926 | X10: 561.184 | Y10: 562.071 | Z10: 562.825 | AA10: 563.89 | AB10: 565.177 | AC10: 566.335
A11: Annuities insulation Privately rented - C2 (euro/year,household) | C11: 947.655 | D11: 1587.525 | E11: 1867.167 | F11: 1814.372 | G11: 1753.16 | H11: 1682.841 | I11: 1603.139 | J11: 1023.619 | K11: 995.438 | L11: 957.412 | M11: 915.236 | N11: 869.395 | O11: 843.469 | P11: 619.28 | Q11: 618.165 | R11: 617.787 | S11: 645.994 | T11: 617.607 | U11: 618.131 | V11: 619.23 | W11: 621.444 | X11: 623.45 | Y11: 625.451 | Z11: 627.489 | AA11: 629.622 | AB11: 631.735 | AC11: 636.623
A12: Annuities insulation Privately rented - C3 (euro/year,household) | C12: 1133.728 | D12: 1524.941 | E12: 1871.543 | F12: 1803.428 | G12: 1725.665 | H12: 1638.016 | I12: 1541.514 | J12: 1084.447 | K12: 1051.917 | L12: 1002.633 | M12: 949.051 | N12: 892.083 | O12: 862.034 | P12: 648.797 | Q12: 651.566 | R12: 654.725 | S12: 720.745 | T12: 659.554 | U12: 663.077 | V12: 667.135 | W12: 671.616 | X12: 676.901 | Y12: 680.63 | Z12: 684.69 | AA12: 688.473 | AB12: 691.822 | AC12: 694.605
... A55: Annuities Single-family - Social-housing - C5 (euro) | C55: 1194125.7 | D55: 2496026.2 | E55: 3943721 | F55: 5503217.3 | G55: 7126046.8 | H55: 8730383.6 | I55: 10415463 | J55: 12226319 | K55: 14215771 | L55: 16439221 | M55: 17745981 | N55: 18811107 | O55: 19786449 | P55: 20512757 | Q55: 21111120 | R55: 21588875 | S55: 22250017 | T55: 22357010 | U55: 22229142 | V55: 21155042 | W55: 20002628 | X55: 18870165 | Y55: 17714210 | Z55: 16655009 | AA55: 15635982 | AB55: 14731175 | AC55: 13534095
A56: Average cost Cee (euro) | C56: 8806.903
A57: Average cost Cee heater (euro) | C57: 7868.634
A58: Average cost Cee insulation (euro) | C58: 11629.844
A59: Average cost Mpr (euro) | C59: 9620.599
A60: Average cost Mpr heater (euro) | C60: 8732.055
A61: Average cost Mpr insulation (euro) | C61: 12349.084
A62: Average cost Mpr multifamily (euro) | C62: 7499.803
A63: Average cost Mpr multifamily insulation (euro) | C63: 7499.803
A64: Average cost Mpr serenite (euro) | C64: 9775.139
A65: Average cost Mpr serenite insulation (euro) | C65: 9775.139
A66: Average cost Over cap (euro) | C66: 4618.255
A67: Average cost Over cap heater (euro) | C67: 0
A68: Average cost Over cap insulation (euro) | C68: 4618.255
A69: Average cost Reduced vat (euro) | C69: 8806.903 | D69: 7677.401 | E69: 7506.398 | F69: 7735.568 | G69: 7205.668 | H69: 6694.883 | I69: 6794.113 | J69: 7138.466 | K69: 6825.823 | L69: 6807.68 | M69: 6793.601 | N69: 6779.028 | O69: 6895.299 | P69: 6794.657 | Q69: 6842.101 | R69: 6872.593 | S69: 7662.126 | T69: 6957.697 | U69: 6931.202 | V69: 6921.447 | W69: 7045.471 | X69: 7157.463 | Y69: 6730.661 | Z69: 6919.962 | AA69: 6601.565 | AB69: 6261.544 | AC69: 5975.502
A70: Average cost Reduced vat heater (euro) | C70: 7868.634 | D70: 7358.448 | E70: 6801.633 | F70: 7031.051 | G70: 6593.528 | H70: 6103.443 | I70: 5649.509 | J70: 6334.08 | K70: 5830.9 | L70: 5993.882 | M70: 6195.346 | N70: 6367.262 | O70: 6419.697 | P70: 6750.127 | Q70: 6912.978 | R70: 7113.349 | S70: 7248.111 | T70: 7163.348 | U70: 7158.301 | V70: 7183.832 | W70: 7389.336 | X70: 7613.66 | Y70: 6826.861 | Z70: 7125.224 | AA70: 6595.948 | AB70: 6081.444 | AC70: 5673.832
A71: Average cost Reduced vat insulation (euro) | C71: 11629.844 | D71: 8999.472 | E71: 9538.858 | F71: 9615.634 | G71: 8806.393 | H71: 8287.986 | I71: 9669.751 | J71: 8672.34 | K71: 8837.077 | L71: 8504.921 | M71: 8019.404 | N71: 7658.191 | O71: 7772.706 | P71: 6849.041 | Q71: 6751.034 | R71: 6593.741 | S71: 8103.268 | T71: 6730.629 | U71: 6671.021 | V71: 6609.428 | W71: 6531.355 | X71: 6560.069 | Y71: 6574.339 | Z71: 6594.194 | AA71: 6611.622 | AB71: 6627.05 | AC71: 6657.512
A72: Average cost Zero interest loan (euro) | C72: 11629.844 | D72: 8999.472 | E72: 9538.858 | F72: 9615.634 | G72: 8806.393 | H72: 8287.986 | I72: 9669.751 | J72: 8672.34 | K72: 8837.077 | L72: 8504.921 | M72: 8019.404 | N72: 7658.191 | O72: 7772.706 | P72: 6849.041 | Q72: 6751.034 | R72: 6593.741 | S72: 8103.268 | T72: 6730.629 | U72: 6671.021 | V72: 6609.428 | W72: 6531.355 | X72: 6560.069 | Y72: 6574.339 | Z72: 6594.194 | AA72: 6611.622 | AB72: 6627.05 | AC72: 6657.512
A73: Average cost Zero interest loan insulation (euro) | C73: 11629.844 | D73: 8999.472 | E73: 9538.858 | F73: 9615.634 | G73: 8806.393 | H73: 8287.986 | I73: 9669.751 | J73: 8672.34 | K73: 8837.077 | L73: 8504.921 | M73: 8019.404 | N73: 7658.191 | O73: 7772.706 | P73: 6849.041 | Q73: 6751.034 | R73: 6593.741 | S73: 8103.268 | T73: 6730.629 | U73: 6671.021 | V73: 6609.428 | W73: 6531.355 | X73: 6560.069 | Y73: 6574.339 | Z73: 6594.194 | AA73: 6611.622 | AB73: 6627.05 | AC73: 6657.512
A74: Average energy std saved Cee insulation (MWh) | C74: 5.689
A75: Average energy std saved Mpr insulation (MWh) | C75: 5.304
A76: Average energy std saved Mpr multifamily insulation (MWh) | C76: 4.772
A77: Average energy std saved Mpr serenite insulation (MWh) | C77: 4.4
A78: Average energy std saved Over cap insulation (MWh) | C78: 0.615
A79: Average energy std saved Reduced vat insulation (MWh) | C79: 5.689 | D79: 4.149 | E79: 4.104 | F79: 4.399 | G79: 3.789 | H79: 3.354 | I79: 3.999 | J79: 3.8 | K79: 3.834 | L79: 3.457 | M79: 2.944 | N79: 2.627 | O79: 2.691 | P79: 2.088 | Q79: 1.953 | R79: 1.803 | S79: 2.563 | T79: 1.454 | U79: 1.383 | V79: 1.313 | W79: 1.237 | X79: 1.196 | Y79: 1.15 | Z79: 1.109 | AA79: 1.068 | AB79: 1.027 | AC79: 0.985
A80: Average energy std saved Zero interest loan insulation (MWh) | C80: 5.689 | D80: 4.149 | E80: 4.104 | F80: 4.399 | G80: 3.789 | H80: 3.354 | I80: 3.999 | J80: 3.8 | K80: 3.834 | L80: 3.457 | M80: 2.944 | N80: 2.627 | O80: 2.691 | P80: 2.088 | Q80: 1.953 | R80: 1.803 | S80: 2.563 | T80: 1.454 | U80: 1.383 | V80: 1.313 | W80: 1.237 | X80: 1.196 | Y80: 1.15 | Z80: 1.109 | AA80: 1.068 | AB80: 1.027 | AC80: 0.985
A81: Balance Owner-occupied - C1 (euro/year,household) | C81: -232.115 | D81: -79.296 | E81: -575.989 | F81: -809.676 | G81: -780.899 | H81: -753.656 | I81: -1243.452 | J81: -1204.973 | K81: -1164.351 | L81: -1127.672 | M81: -1091.724 | N81: -1056.254 | O81: -933.243 | P81: -908.18 | Q81: -884.772 | R81: -861.367 | S81: -746.186 | T81: -780.75 | U81: -769.903 | V81: -759.466 | W81: -753.159 | X81: -746.201 | Y81: -740.691 | Z81: -735.091 | AA81: -730.099 | AB81: -725.65 | AC81: -720.999
A82: Balance Owner-occupied - C2 (euro/year,household) | C82: -333.051 | D82: -607.225 | E82: -607.09 | F82: -764.576 | G82: -741.157 | H82: -719.5 | I82: -1100.351 | J82: -1062.369 | K82: -1020.165 | L82: -985.993 | M82: -953.594 | N82: -922.703 | O82: -849.726 | P82: -829.087 | Q82: -809.631 | R82: -790.737 | S82: -734.203 | T82: -773.655 | U82: -766.935 | V82: -760.693 | W82: -757.842 | X82: -754.515 | Y82: -752.197 | Z82: -749.893 | AA82: -748 | AB82: -746.449 | AC82: -765.55
A83: Balance Owner-occupied - C3 (euro/year,household) | C83: -520.74 | D83: -717.924 | E83: -718.385 | F83: -784.378 | G83: -773.157 | H83: -763.125 | I83: -987.483 | J83: -959.348 | K83: -927.896 | L83: -905.032 | M83: -884.314 | N83: -865.459 | O83: -815.904 | P83: -803.522 | Q83: -792.307 | R83: -781.417 | S83: -593.108 | T83: -796.931 | U83: -795.455 | V83: -794.366 | W83: -795.677 | X83: -796.851 | Y83: -798.748 | Z83: -800.709 | AA83: -803.223 | AB83: -805.693 | AC83: -808.365
A84: Balance Owner-occupied - C4 (euro/year,household) | C84: -545.663 | D84: -714.01 | E84: -715.599 | F84: -762.922 | G84: -755.702 | H84: -749.248 | I84: -943.971 | J84: -920.198 | K84: -896.528 | L84: -877.873 | M84: -860.803 | N84: -844.971 | O84: -780.646 | P84: -770.92 | Q84: -763.594 | R84: -755.21 | S84: -566.743 | T84: -774.922 | U84: -774.456 | V84: -774.327 | W84: -779.512 | X84: -781.516 | Y84: -784.242 | Z84: -786.995 | AA84: -790.043 | AB84: -793.266 | AC84: -796.77
A85: Balance Owner-occupied - C5 (euro/year,household) | C85: -544.291 | D85: -692.274 | E85: -692.585 | F85: -709.552 | G85: -704.537 | H85: -700.11 | I85: -800.275 | J85: -783.309 | K85: -779.137 | L85: -762.677 | M85: -747.065 | N85: -732.732 | O85: -653.445 | P85: -648.791 | Q85: -646.031 | R85: -644.351 | S85: -434.31 | T85: -725.005 | U85: -728.055 | V85: -731.375 | W85: -736.141 | X85: -741.18 | Y85: -746.821 | Z85: -752.478 | AA85: -758.281 | AB85: -764.049 | AC85: -770.144
A86: Balance standard Owner-occupied - C1 (euro/year,household) | C86: -100.774 | D86: 55.327 | E86: -450.173 | F86: -251.877 | G86: -252.466 | H86: -256.18 | I86: -472.76 | J86: -450.117 | K86: -430.867 | L86: -419.719 | M86: -414.38 | N86: -414.075 | O86: -338.853 | P86: -332.294 | Q86: -328.138 | R86: -323.723 | S86: -288.059 | T86: -481.545 | U86: -488.23 | V86: -494.816 | W86: -501.856 | X86: -509.022 | Y86: -519.167 | Z86: -529.068 | AA86: -539.886 | AB86: -551.598 | AC86: -565.478
A87: Balance standard Owner-occupied - C2 (euro/year,household) | C87: -201.116 | D87: -486.38 | E87: -486.457 | F87: -325.775 | G87: -330.791 | H87: -338.557 | I87: -504.773 | J87: -489.886 | K87: -475.381 | L87: -473.151 | M87: -477.011 | N87: -485.979 | O87: -423.204 | P87: -420.802 | Q87: -421.341 | R87: -420.917 | S87: -374.935 | T87: -558.853 | U87: -564.797 | V87: -570.293 | W87: -576.019 | X87: -581.517 | Y87: -589.323 | Z87: -596.526 | AA87: -604.243 | AB87: -612.434 | AC87: -640.825
A88: Balance standard Owner-occupied - C3 (euro/year,household) | C88: -34.998 | D88: -545.499 | E88: -545.669 | F88: -443.813 | G88: -451.355 | H88: -459.876 | I88: -533.389 | J88: -525.675 | K88: -490.391 | L88: -495.433 | M88: -506.687 | N88: -523.426 | O88: -467.513 | P88: -468.107 | Q88: -471.261 | R88: -472.51 | S88: 324.991 | T88: -626.305 | U88: -631.394 | V88: -635.927 | W88: -640.437 | X88: -644.929 | Y88: -651.924 | Z88: -658.143 | AA88: -664.84 | AB88: -671.629 | AC88: -679.103
A89: Balance standard Owner-occupied - C4 (euro/year,household) | C89: -185.816 | D89: -520.358 | E89: -526.041 | F89: -439.022 | G89: -450.966 | H89: -462.613 | I89: -527.2 | J89: -522.021 | K89: -482.215 | L89: -492.493 | M89: -507.23 | N89: -524.849 | O89: -458.169 | P89: -459.924 | Q89: -464.357 | R89: -466.766 | S89: 283.069 | T89: -620.971 | U89: -625.995 | V89: -630.546 | W89: -637.371 | X89: -642.248 | Y89: -649.486 | Z89: -655.876 | AA89: -662.525 | AB89: -669.292 | AC89: -676.781
A90: Balance standard Owner-occupied - C5 (euro/year,household) | C90: -135.137 | D90: -409.984 | E90: -433.735 | F90: -376.108 | G90: -397.97 | H90: -415.634 | I90: -454.273 | J90: -452.077 | K90: -393.641 | L90: -409.442 | M90: -424.672 | N90: -440.179 | O90: -372.536 | P90: -385.025 | Q90: -403.706 | R90: -423.516 | S90: 151.586 | T90: -603.277 | U90: -608.931 | V90: -614.063 | W90: -619.091 | X90: -624.17 | Y90: -631.672 | Z90: -638.254 | AA90: -645.075 | AB90: -651.961 | AC90: -659.537
... A138: Carbon footprint Windows (MtCO2) | C138: 0.069 | D138: 0.047 | E138: 0.064 | F138: 0.069 | G138: 0.07 | H138: 0.067 | I138: 0.071 | J138: 0.094 | K138: 0.091 | L138: 0.088 | M138: 0.089 | N138: 0.085 | O138: 0.087 | P138: 0.13 | Q138: 0.123 | R138: 0.12 | S138: 0.162 | T138: 0.133 | U138: 0.127 | V138: 0.113 | W138: 0.113 | X138: 0.108 | Y138: 0.103 | Z138: 0.098 | AA138: 0.094 | AB138: 0.09 | AC138: 0.088
A139: Carbon tax (Billion euro) | F139: 0.864 | G139: 0.852 | H139: 0.842 | I139: 0.804 | J139: 0.871 | K139: 0.897 | L139: 0.886 | M139: 0.846 | N139: 0.799 | O139: 0.759 | P139: 0.714 | Q139: 0.664 | R139: 0.618 | S139: 4.82 | T139: 0.487 | U139: 0.422 | V139: 0.373 | W139: 0.327 | X139: 0.291 | Y139: 0.22 | Z139: 0.157 | AA139: 0.1 | AB139: 0.047 | AC139: 0
A140: Carbon value (Billion euro) | B140: 5.103 | C140: 5.483 | D140: 5.905 | E140: 6.253 | F140: 6.415 | G140: 6.619 | H140: 6.815 | I140: 6.929 | J140: 7.183 | K140: 7.356 | L140: 7.476 | M140: 7.528 | N140: 7.536 | O140: 7.665 | P140: 7.721 | Q140: 7.764 | R140: 7.829 | S140: 7.242 | T140: 7.676 | U140: 7.613 | V140: 7.612 | W140: 7.643 | X140: 7.687 | Y140: 7.718 | Z140: 7.777 | AA140: 7.811 | AB140: 7.853 | AC140: 7.84
A141: Carbon value indirect (Billion euro) | C141: 2.183 | D141: 2.621 | E141: 3.026 | F141: 3.327 | G141: 3.574 | H141: 3.817 | I141: 3.073 | J141: 3.559 | K141: 3.838 | L141: 4.101 | M141: 4.395 | N141: 4.639 | O141: 4.961 | P141: 5.709 | Q141: 5.947 | R141: 6.226 | S141: 4.585 | T141: 4.243 | U141: 4.335 | V141: 4.305 | W141: 4.488 | X141: 4.6 | Y141: 4.717 | Z141: 4.838 | AA141: 4.974 | AB141: 5.114 | AC141: 5.086
A142: Carbon value indirect renovation (Billion euro) | C142: 0.399 | D142: 0.267 | E142: 0.434 | F142: 0.511 | G142: 0.534 | H142: 0.538 | I142: 0.666 | J142: 0.912 | K142: 0.95 | L142: 0.972 | M142: 1.025 | N142: 1.028 | O142: 1.109 | P142: 1.616 | Q142: 1.614 | R142: 1.653 | S142: 2.402 | T142: 1.96 | U142: 1.951 | V142: 1.812 | W142: 1.886 | X142: 1.88 | Y142: 1.874 | Z142: 1.869 | AA142: 1.869 | AB142: 1.87 | AC142: 1.872
A143: CBA Annuities heater (Billion euro) | C143: -1.027 | D143: -0.959 | E143: -0.884 | F143: -0.912 | G143: -0.854 | H143: -0.789 | I143: -0.728 | J143: -0.815 | K143: -0.75 | L143: -0.77 | M143: -0.795 | N143: -0.816 | O143: -0.708 | P143: -0.744 | Q143: -0.762 | R143: -0.693 | S143: -0.787 | T143: -0.709 | U143: -0.704 | V143: -0.653 | W143: -0.846 | X143: -0.727 | Y143: -0.771 | Z143: -0.75 | AA143: -0.748 | AB143: -0.747 | AC143: -0.745
A144: CBA Annuities insulation (Billion euro) | C144: -0.386 | D144: -0.216 | E144: -0.329 | F144: -0.357 | G144: -0.333 | H144: -0.304 | I144: -0.379 | J144: -0.448 | K144: -0.43 | L144: -0.401 | M144: -0.384 | N144: -0.352 | O144: -0.355 | P144: -0.473 | Q144: -0.443 | R144: -0.424 | S144: -0.632 | T144: -0.461 | U144: -0.438 | V144: -0.386 | W144: -0.382 | X144: -0.366 | Y144: -0.349 | Z144: -0.334 | AA144: -0.32 | AB144: -0.307 | AC144: -0.296
A145: CBA benefits (Billion euro) | C145: 2.298 | D145: 1.482 | E145: 2.003 | F145: 2.517 | G145: 2.084 | H145: 2.058 | I145: 2.228 | J145: 2.42 | K145: 2.45 | L145: 2.357 | M145: 2.303 | N145: 2.222 | O145: 1.738 | P145: 1.84 | Q145: 1.735 | R145: 1.526 | S145: 3.352 | T145: 0.048 | U145: 1.396 | V145: 1.231 | W145: 0.909 | X145: 0.871 | Y145: 0.884 | Z145: 0.784 | AA145: 0.795 | AB145: 0.758 | AC145: 0.772
A146: CBA Carbon Emission indirect (Billion euro) | C146: -0.021 | D146: -0.014 | E146: -0.023 | F146: -0.027 | G146: -0.028 | H146: -0.028 | I146: -0.035 | J146: -0.048 | K146: -0.05 | L146: -0.051 | M146: -0.054 | N146: -0.054 | O146: -0.058 | P146: -0.085 | Q146: -0.084 | R146: -0.087 | S146: -0.126 | T146: -0.103 | U146: -0.102 | V146: -0.095 | W146: -0.099 | X146: -0.098 | Y146: -0.098 | Z146: -0.098 | AA146: -0.098 | AB146: -0.098 | AC146: -0.098
A147: CBA COFP (Billion euro) | C147: 0 | D147: 0 | E147: 0 | F147: 0 | G147: 0 | H147: 0 | I147: 0 | J147: 0 | K147: 0 | L147: 0 | M147: 0 | N147: 0 | O147: 0 | P147: 0 | Q147: 0 | R147: 0 | S147: 0 | T147: 0 | U147: 0 | V147: 0 | W147: 0 | X147: 0 | Y147: 0 | Z147: 0 | AA147: 0 | AB147: 0 | AC147: 0
A148: CBA Consumption saving (TWh) | C148: 7.181 | D148: 4.482 | E148: 6.092 | F148: 8.846 | G148: 6.102 | H148: 5.482 | I148: 5.353 | J148: 6.663 | K148: 6.023 | L148: 5.815 | M148: 5.685 | N148: 5.591 | O148: 4.486 | P148: 4.988 | Q148: 4.811 | R148: 4.271 | S148: 10.698 | T148: -1.149 | U148: 3.727 | V148: 3.285 | W148: 2.443 | X148: 2.228 | Y148: 2.299 | Z148: 2.013 | AA148: 1.954 | AB148: 1.909 | AC148: 1.857
A149: CBA Consumption saving EE (Billion euro) | C149: 0.805 | D149: 0.58 | E149: 0.683 | F149: 0.737 | G149: 0.734 | H149: 0.734 | I149: 0.819 | J149: 0.889 | K149: 0.906 | L149: 0.876 | M149: 0.846 | N149: 0.818 | O149: 0.704 | P149: 0.75 | Q149: 0.717 | R149: 0.63 | S149: 0.75 | T149: 0.587 | U149: 0.562 | V149: 0.497 | W149: 0.316 | X149: 0.296 | Y149: 0.311 | Z149: 0.27 | AA149: 0.258 | AB149: 0.249 | AC149: 0.238
A150: CBA Consumption saving EE (TWh) | C150: 5.981 | D150: 4.502 | E150: 4.578 | F150: 5.199 | G150: 4.658 | H150: 4.067 | I150: 4.033 | J150: 5.166 | K150: 4.647 | L150: 4.568 | M150: 4.547 | N150: 4.515 | O150: 3.528 | P150: 4.04 | Q150: 3.951 | R150: 3.461 | S150: 4.33 | T150: 3.223 | U150: 3.052 | V150: 2.621 | W150: 1.803 | X150: 1.599 | Y150: 1.726 | Z150: 1.45 | AA150: 1.4 | AB150: 1.364 | AC150: 1.322
A151: CBA Consumption saving insulation (TWh) | C151: 1.921 | D151: 1.039 | E151: 1.49 | F151: 1.678 | G151: 1.484 | H151: 1.283 | I151: 1.614 | J151: 2.094 | K151: 1.996 | L151: 1.747 | M151: 1.523 | N151: 1.315 | O151: 1.353 | P151: 1.627 | Q151: 1.452 | R151: 1.322 | S151: 2.058 | T151: 1.157 | U151: 1.059 | V151: 0.901 | W151: 0.855 | X151: 0.789 | Y151: 0.726 | Z151: 0.671 | AA151: 0.62 | AB151: 0.573 | AC151: 0.529
A152: CBA Consumption saving prices (Billion euro) | C152: 0.209 | D152: 0.045 | E152: 0.142 | F152: 0.329 | G152: 0.144 | H152: 0.146 | I152: 0.141 | J152: 0.162 | K152: 0.154 | L152: 0.145 | M152: 0.137 | N152: 0.134 | O152: 0.124 | P152: 0.13 | Q152: 0.118 | R152: 0.115 | S152: 0.879 | T152: -0.616 | U152: 0.105 | V152: 0.106 | W152: 0.104 | X152: 0.106 | Y152: 0.099 | Z152: 0.099 | AA152: 0.1 | AB152: 0.101 | AC152: 0.102
... A160: CBA Thermal loss prices (Billion euro) | C160: -0.274 | D160: -0.056 | E160: -0.187 | F160: -0.457 | G160: -0.196 | H160: -0.196 | I160: -0.188 | J160: -0.218 | K160: -0.207 | L160: -0.194 | M160: -0.182 | N160: -0.177 | O160: -0.162 | P160: -0.17 | Q160: -0.153 | R160: -0.148 | S160: -1.86 | T160: 0.834 | U160: -0.132 | V160: -0.133 | W160: -0.131 | X160: -0.132 | Y160: -0.122 | Z160: -0.122 | AA160: -0.123 | AB160: -0.123 | AC160: -0.123
A161: Cee (Billion euro) | C161: 3.097
A162: Cee (Thousand households) | C162: 2408.639
A163: Cee heater (Billion euro) | C163: 2.045
A164: Cee heater (Thousand households) | C164: 1807.781
A165: Cee heater C1 (Thousand households) | C165: 136.897
A166: Cee heater C2 (Thousand households) | C166: 199.019
A167: Cee heater C3 (Thousand households) | C167: 266.392
A168: Cee heater C4 (Thousand households) | C168: 345.865
A169: Cee heater C5 (Thousand households) | C169: 859.608
A170: Cee heater Multi-family (Thousand households) | C170: 813.561
A171: Cee heater Single-family (Thousand households) | C171: 994.22
A172: Cee insulation (Billion euro) | C172: 1.051
... A182: Cee Single-family (Thousand households) | C182: 1437.236
A183: Cee tax (Billion euro) | B183: 1.015 | C183: 0.979
A184: COFP (Billion euro) | C184: 0 | D184: 0 | E184: 0 | F184: 0 | G184: 0 | H184: 0 | I184: 0 | J184: 0 | K184: 0 | L184: 0 | M184: 0 | N184: 0 | O184: 0 | P184: 0 | Q184: 0 | R184: 0 | S184: 0 | T184: 0 | U184: 0 | V184: 0 | W184: 0 | X184: 0 | Y184: 0 | Z184: 0 | AA184: 0 | AB184: 0 | AC184: 0
A185: Consumption (kWh/m2) | B185: 100.415 | C185: 97.086 | D185: 94.679 | E185: 91.71 | F185: 87.767 | G185: 84.904 | H185: 82.317 | I185: 80.018 | J185: 77.271 | K185: 74.781 | L185: 72.39 | M185: 70.067 | N185: 67.8 | O185: 65.942 | P185: 63.925 | Q185: 61.989 | R185: 60.257 | S185: 56.433 | T185: 56.696 | U185: 55.276 | V185: 54.005 | W185: 53.021 | X185: 52.11 | Y185: 51.175 | Z185: 50.337 | AA185: 49.52 | AB185: 48.717 | AC185: 47.92
A186: Consumption (TWh) | B186: 260.458 | C186: 253.846 | D186: 249.952 | E186: 244.435 | F186: 236.148 | G186: 230.592 | H186: 225.643 | I186: 220.662 | J186: 214.361 | K186: 208.682 | L186: 203.197 | M186: 197.826 | N186: 192.536 | O186: 188.338 | P186: 183.623 | Q186: 179.072 | R186: 175.048 | S186: 164.18 | T186: 165.186 | U186: 161.28 | V186: 157.8 | W186: 155.147 | X186: 152.7 | Y186: 150.173 | Z186: 147.924 | AA186: 145.726 | AB186: 143.566 | AC186: 141.363
A187: Consumption A (TWh) | B187: 0.617 | C187: 0.814 | D187: 1.119 | E187: 1.426 | F187: 1.735 | G187: 2.043 | H187: 2.349 | I187: 2.572 | J187: 2.8 | K187: 3.027 | L187: 3.257 | M187: 3.491 | N187: 3.729 | O187: 3.965 | P187: 4.204 | Q187: 4.449 | R187: 4.695 | S187: 4.81 | T187: 4.925 | U187: 5.043 | V187: 5.16 | W187: 5.231 | X187: 5.327 | Y187: 5.425 | Z187: 5.521 | AA187: 5.616 | AB187: 5.711 | AC187: 5.805
A188: Consumption B (TWh) | B188: 6.216 | C188: 6.788 | D188: 7.277 | E188: 7.856 | F188: 8.455 | G188: 9.134 | H188: 9.909 | I188: 10.723 | J188: 11.516 | K188: 12.441 | L188: 13.41 | M188: 14.419 | N188: 15.46 | O188: 16.387 | P188: 17.309 | Q188: 18.26 | R188: 19.17 | S188: 20.071 | T188: 20.971 | U188: 21.877 | V188: 22.731 | W188: 23.273 | X188: 23.842 | Y188: 24.428 | Z188: 24.967 | AA188: 25.49 | AB188: 26 | AC188: 26.491
A189: Consumption C (TWh) | B189: 35.497 | C189: 37.264 | D189: 38.407 | E189: 40.202 | F189: 41.752 | G189: 43.817 | H189: 46.184 | I189: 48.985 | J189: 51.322 | K189: 54.005 | L189: 56.434 | M189: 58.622 | N189: 60.516 | O189: 61.831 | P189: 63.343 | Q189: 64.442 | R189: 65.148 | S189: 64.604 | T189: 66.745 | U189: 67.011 | V189: 67.064 | W189: 67.065 | X189: 66.999 | Y189: 66.865 | Z189: 66.731 | AA189: 66.55 | AB189: 66.318 | AC189: 66.04
A190: Consumption D (TWh) | B190: 102.743 | C190: 101.978 | D190: 102.1 | E190: 101.233 | F190: 99.17 | G190: 97.6 | H190: 95.645 | I190: 93.645 | J190: 92.439 | K190: 90.583 | L190: 88.276 | M190: 85.372 | N190: 82.108 | O190: 79.172 | P190: 75.154 | Q190: 71.31 | R190: 67.999 | S190: 60.628 | T190: 60.033 | U190: 56.633 | V190: 53.726 | W190: 51.722 | X190: 49.85 | Y190: 47.857 | Z190: 46.101 | AA190: 44.379 | AB190: 42.687 | AC190: 41.033
A191: Consumption Direct electric (TWh) | B191: 43.913 | C191: 40.822 | D191: 38.813 | E191: 36.839 | F191: 34.963 | G191: 33.127 | H191: 31.307 | I191: 29.36 | J191: 27.512 | K191: 25.66 | L191: 23.901 | M191: 22.231 | N191: 20.646 | O191: 19.052 | P191: 17.454 | Q191: 15.96 | R191: 14.523 | S191: 13.138 | T191: 11.787 | U191: 10.502 | V191: 9.276 | W191: 8.877 | X191: 8.345 | Y191: 7.916 | Z191: 7.464 | AA191: 7.077 | AB191: 6.759 | AC191: 6.488
A192: Consumption District heating (TWh) | B192: 11.458 | C192: 12.433 | D192: 12.517 | E192: 14.035 | F192: 15.012 | G192: 17.038 | H192: 20.233 | I192: 24.458 | J192: 26.764 | K192: 30.185 | L192: 33.074 | M192: 35.36 | N192: 37.128 | O192: 38.414 | P192: 38.958 | Q192: 39.179 | R192: 39.085 | S192: 38.535 | T192: 38.152 | U192: 37.768 | V192: 37.422 | W192: 37.068 | X192: 36.724 | Y192: 36.39 | Z192: 36.062 | AA192: 35.742 | AB192: 35.43 | AC192: 35.089
A193: Consumption E (TWh) | B193: 52.265 | C193: 50.145 | D193: 48.184 | E193: 45.806 | F193: 42.733 | G193: 40.216 | H193: 37.776 | I193: 35.45 | J193: 31.056 | K193: 27.212 | L193: 23.748 | M193: 20.768 | N193: 18.106 | O193: 16.067 | P193: 14.196 | Q193: 12.504 | R193: 11.024 | S193: 8.802 | T193: 7.874 | U193: 6.766 | V193: 5.777 | W193: 4.963 | X193: 4.215 | Y193: 3.525 | Z193: 2.895 | AA193: 2.317 | AB193: 1.784 | AC193: 1.245
A194: Consumption Electricity (TWh) | B194: 50.897 | C194: 49.849 | D194: 49.664 | E194: 49.474 | F194: 49.552 | G194: 49.589 | H194: 49.554 | I194: 49.233 | J194: 49.176 | K194: 49.022 | L194: 49.005 | M194: 49.126 | N194: 49.378 | O194: 49.128 | P194: 48.891 | Q194: 48.791 | R194: 48.568 | S194: 48.451 | T194: 48.145 | U194: 47.868 | V194: 47.525 | W194: 47.539 | X194: 47.38 | Y194: 47.398 | Z194: 47.299 | AA194: 47.257 | AB194: 47.282 | AC194: 47.336
A195: Consumption Electricity saving (TWh/year) | C195: 1.293 | D195: 0.493 | E195: 0.497 | F195: 0.227 | G195: 0.267 | H195: 0.337 | I195: 0.519 | J195: 0.254 | K195: 0.348 | L195: 0.207 | M195: 0.065 | N195: -0.069 | O195: 0.429 | P195: 0.412 | Q195: 0.277 | R195: 0.4 | S195: 0.156 | T195: 0.341 | U195: 0.315 | V195: 0.384 | W195: 0.034 | X195: 0.204 | Y195: 0.029 | Z195: 0.146 | AA195: 0.088 | AB195: 0.022 | AC195: -0.032
A196: Consumption Electricity-Heat pump air (TWh) | B196: 1.397 | C196: 2.376 | D196: 3.727 | E196: 5.024 | F196: 6.437 | G196: 7.787 | H196: 9.07 | I196: 10.276 | J196: 11.594 | K196: 12.841 | L196: 14.115 | M196: 15.419 | N196: 16.749 | O196: 17.746 | P196: 18.757 | Q196: 19.788 | R196: 20.696 | S196: 21.667 | T196: 22.484 | U196: 23.275 | V196: 23.979 | W196: 24.597 | X196: 24.884 | Y196: 25.225 | Z196: 25.507 | AA196: 25.786 | AB196: 26.066 | AC196: 26.337
A197: Consumption Electricity-Heat pump water (TWh) | B197: 5.587 | C197: 6.651 | D197: 7.124 | E197: 7.611 | F197: 8.152 | G197: 8.674 | H197: 9.176 | I197: 9.598 | J197: 10.07 | K197: 10.521 | L197: 10.989 | M197: 11.477 | N197: 11.982 | O197: 12.33 | P197: 12.68 | Q197: 13.043 | R197: 13.349 | S197: 13.646 | T197: 13.874 | U197: 14.091 | V197: 14.271 | W197: 14.065 | X197: 14.151 | Y197: 14.258 | Z197: 14.328 | AA197: 14.394 | AB197: 14.457 | AC197: 14.512
A198: Consumption Electricity-Performance boiler (TWh) | B198: 43.913 | C198: 40.822 | D198: 38.813 | E198: 36.839 | F198: 34.963 | G198: 33.127 | H198: 31.307 | I198: 29.36 | J198: 27.512 | K198: 25.66 | L198: 23.901 | M198: 22.231 | N198: 20.646 | O198: 19.052 | P198: 17.454 | Q198: 15.96 | R198: 14.523 | S198: 13.138 | T198: 11.787 | U198: 10.502 | V198: 9.276 | W198: 8.877 | X198: 8.345 | Y198: 7.916 | Z198: 7.464 | AA198: 7.077 | AB198: 6.759 | AC198: 6.488
A199: Consumption existing (kWh/m2) | B199: 100.415 | C199: 97.798 | D199: 96.214 | E199: 94 | F199: 90.711 | G199: 88.475 | H199: 86.47 | I199: 84.507 | J199: 82.028 | K199: 79.787 | L199: 77.617 | M199: 75.489 | N199: 73.387 | O199: 71.709 | P199: 69.827 | Q199: 68.004 | R199: 66.386 | S199: 62.192 | T199: 62.649 | U199: 61.176 | V199: 59.866 | W199: 58.88 | X199: 57.972 | Y199: 57.029 | Z199: 56.194 | AA199: 55.377 | AB199: 54.573 | AC199: 53.764
A200: Consumption existing (TWh) | B200: 260.458 | C200: 253.41 | D200: 249.049 | E200: 243.066 | F200: 234.315 | G200: 228.295 | H200: 222.884 | I200: 217.591 | J200: 210.978 | K200: 204.99 | L200: 199.195 | M200: 193.516 | N200: 187.918 | O200: 183.413 | P200: 178.394 | Q200: 173.538 | R200: 169.21 | S200: 158.242 | T200: 159.124 | U200: 155.106 | V200: 151.514 | W200: 148.75 | X200: 146.193 | Y200: 143.556 | Z200: 141.197 | AA200: 138.889 | AB200: 136.619 | AC200: 134.312
A201: Consumption Existing (TWh) | B201: 260.458 | C201: 253.41 | D201: 249.049 | E201: 243.066 | F201: 234.315 | G201: 228.295 | H201: 222.884 | I201: 217.591 | J201: 210.978 | K201: 204.99 | L201: 199.195 | M201: 193.516 | N201: 187.918 | O201: 183.413 | P201: 178.394 | Q201: 173.538 | R201: 169.21 | S201: 158.242 | T201: 159.124 | U201: 155.106 | V201: 151.514 | W201: 148.75 | X201: 146.193 | Y201: 143.556 | Z201: 141.197 | AA201: 138.889 | AB201: 136.619 | AC201: 134.312
A202: Consumption F (TWh) | B202: 38.957 | C202: 36.622 | D202: 35.081 | E202: 32.424 | F202: 29.594 | G202: 27.303 | H202: 25.241 | I202: 22.428 | J202: 19.838 | K202: 17.38 | L202: 15.15 | M202: 13.139 | N202: 11.333 | O202: 9.836 | P202: 8.508 | Q202: 7.344 | R202: 6.369 | S202: 4.754 | T202: 4.209 | U202: 3.6 | V202: 3.058 | W202: 2.655 | X202: 2.272 | Y202: 1.915 | Z202: 1.585 | AA202: 1.278 | AB202: 0.993 | AC202: 0.7
A203: Consumption G (TWh) | B203: 24.164 | C203: 20.235 | D203: 17.784 | E203: 15.488 | F203: 12.709 | G203: 10.478 | H203: 8.539 | I203: 6.858 | J203: 5.389 | K203: 4.035 | L203: 2.922 | M203: 2.015 | N203: 1.283 | O203: 1.081 | P203: 0.909 | Q203: 0.764 | R203: 0.643 | S203: 0.511 | T203: 0.429 | U203: 0.351 | V203: 0.284 | W203: 0.237 | X203: 0.195 | Y203: 0.158 | Z203: 0.125 | AA203: 0.097 | AB203: 0.072 | AC203: 0.049
A204: Consumption Heat pump (TWh) | B204: 6.984 | C204: 9.027 | D204: 10.851 | E204: 12.635 | F204: 14.589 | G204: 16.461 | H204: 18.247 | I204: 19.873 | J204: 21.664 | K204: 23.362 | L204: 25.104 | M204: 26.896 | N204: 28.732 | O204: 30.076 | P204: 31.437 | Q204: 32.831 | R204: 34.045 | S204: 35.313 | T204: 36.358 | U204: 37.366 | V204: 38.249 | W204: 38.662 | X204: 39.035 | Y204: 39.483 | Z204: 39.835 | AA204: 40.18 | AB204: 40.523 | AC204: 40.849
A205: Consumption Heating (TWh) | B205: 11.458 | C205: 12.433 | D205: 12.517 | E205: 14.035 | F205: 15.012 | G205: 17.038 | H205: 20.233 | I205: 24.458 | J205: 26.764 | K205: 30.185 | L205: 33.074 | M205: 35.36 | N205: 37.128 | O205: 38.414 | P205: 38.958 | Q205: 39.179 | R205: 39.085 | S205: 38.535 | T205: 38.152 | U205: 37.768 | V205: 37.422 | W205: 37.068 | X205: 36.724 | Y205: 36.39 | Z205: 36.062 | AA205: 35.742 | AB205: 35.43 | AC205: 35.089
...

Sheet figures 2030
J1: 2018 | K1: 2019 | L1: 2020 | M1: 2021 | N1: 2022 | O1: 2023 | P1: 2024 | Q1: 2025 | R1: 2026 | S1: 2027 | T1: 2028 | U1: 2029 | V1: 2030
H3: Emission Natural gas (MtCO2) | I3: Emissions du gaz (MtCO2) | J3: =VLOOKUP($H3,output!$A$10:$N$2201,J$1-$J$1+2) -> 20.02 | K3: =VLOOKUP($H3,output!$A$10:$N$2201,K$1-$J$1+2) -> 19.601 | L3: =VLOOKUP($H3,output!$A$10:$N$2201,L$1-$J$1+2) -> 19.575 | M3: =VLOOKUP($H3,output!$A$10:$N$2201,M$1-$J$1+2) -> 19.088 | N3: =VLOOKUP($H3,output!$A$10:$N$2201,N$1-$J$1+2) -> 18.257 | O3: =VLOOKUP($H3,output!$A$10:$N$2201,O$1-$J$1+2) -> 17.594 | P3: =VLOOKUP($H3,output!$A$10:$N$2201,P$1-$J$1+2) -> 16.811 | Q3: =VLOOKUP($H3,output!$A$10:$N$2201,Q$1-$J$1+2) -> 15.886 | ... V3: =VLOOKUP($H3,output!$A$10:$N$2201,V$1-$J$1+2) -> 11.457
H4: Emission Oil fuel (MtCO2) | I4: Emissions du fioul (MtCO2) | J4: =VLOOKUP($H4,output!$A$10:$N$2201,J$1-$J$1+2) -> 10.044 | K4: =VLOOKUP($H4,output!$A$10:$N$2201,K$1-$J$1+2) -> 9.04 | L4: =VLOOKUP($H4,output!$A$10:$N$2201,L$1-$J$1+2) -> 8.182 | M4: =VLOOKUP($H4,output!$A$10:$N$2201,M$1-$J$1+2) -> 7.23 | N4: =VLOOKUP($H4,output!$A$10:$N$2201,N$1-$J$1+2) -> 6.14 | O4: =VLOOKUP($H4,output!$A$10:$N$2201,O$1-$J$1+2) -> 5.237 | P4: =VLOOKUP($H4,output!$A$10:$N$2201,P$1-$J$1+2) -> 4.379 | Q4: =VLOOKUP($H4,output!$A$10:$N$2201,Q$1-$J$1+2) -> 3.559 | ... V4: =VLOOKUP($H4,output!$A$10:$N$2201,V$1-$J$1+2) -> 0
H5: Emission Electricity (MtCO2) | I5: Emissions de l'électricité (MtCO2) | J5: =VLOOKUP($H5,output!$A$10:$N$2201,J$1-$J$1+2) -> 4.021 | K5: =VLOOKUP($H5,output!$A$10:$N$2201,K$1-$J$1+2) -> 3.938 | L5: =VLOOKUP($H5,output!$A$10:$N$2201,L$1-$J$1+2) -> 3.923 | M5: =VLOOKUP($H5,output!$A$10:$N$2201,M$1-$J$1+2) -> 3.908 | N5: =VLOOKUP($H5,output!$A$10:$N$2201,N$1-$J$1+2) -> 3.915 | O5: =VLOOKUP($H5,output!$A$10:$N$2201,O$1-$J$1+2) -> 3.917 | P5: =VLOOKUP($H5,output!$A$10:$N$2201,P$1-$J$1+2) -> 3.915 | Q5: =VLOOKUP($H5,output!$A$10:$N$2201,Q$1-$J$1+2) -> 3.889 | ... V5: =VLOOKUP($H5,output!$A$10:$N$2201,V$1-$J$1+2) -> 3.901
I7: Directes | J7: =J3+J4 -> 30.064 | K7: =K3+K4 -> 28.641 | L7: =L3+L4 -> 27.757 | M7: =M3+M4 -> 26.318 | N7: =N3+N4 -> 24.397 | O7: =O3+O4 -> 22.831 | P7: =P3+P4 -> 21.19 | Q7: =Q3+Q4 -> 19.445 | ... V7: =V3+V4 -> 11.457 | W7: =V7/L7-1 -> -0.58723925
I8: Gain annuel | K8: =J7-K7 -> 1.423 | L8: =K7-L7 -> 0.884 | M8: =L7-M7 -> 1.439 | N8: =M7-N7 -> 1.921 | O8: =N7-O7 -> 1.566 | P8: =O7-P7 -> 1.641 | Q8: =P7-Q7 -> 1.745 | R8: =Q7-R7 -> 1.682 | ... V8: =U7-V7 -> 1.425
H13: Stock A (Million) | I13: A | J13: =VLOOKUP($H13,output!$A$10:$N$2201,J$1-$J$1+2) -> 0.397 | K13: =VLOOKUP($H13,output!$A$10:$N$2201,K$1-$J$1+2) -> 0.545 | L13: =VLOOKUP($H13,output!$A$10:$N$2201,L$1-$J$1+2) -> 0.757 | M13: =VLOOKUP($H13,output!$A$10:$N$2201,M$1-$J$1+2) -> 0.969 | N13: =VLOOKUP($H13,output!$A$10:$N$2201,N$1-$J$1+2) -> 1.182 | O13: =VLOOKUP($H13,output!$A$10:$N$2201,O$1-$J$1+2) -> 1.395 | P13: =VLOOKUP($H13,output!$A$10:$N$2201,P$1-$J$1+2) -> 1.606 | Q13: =VLOOKUP($H13,output!$A$10:$N$2201,Q$1-$J$1+2) -> 1.757 | ... V13: =VLOOKUP($H13,output!$A$10:$N$2201,V$1-$J$1+2) -> 2.549
H14: Stock B (Million) | I14: B | J14: =VLOOKUP($H14,output!$A$10:$N$2201,J$1-$J$1+2) -> 2.156 | K14: =VLOOKUP($H14,output!$A$10:$N$2201,K$1-$J$1+2) -> 2.435 | L14: =VLOOKUP($H14,output!$A$10:$N$2201,L$1-$J$1+2) -> 2.686 | M14: =VLOOKUP($H14,output!$A$10:$N$2201,M$1-$J$1+2) -> 2.947 | N14: =VLOOKUP($H14,output!$A$10:$N$2201,N$1-$J$1+2) -> 3.224 | O14: =VLOOKUP($H14,output!$A$10:$N$2201,O$1-$J$1+2) -> 3.519 | P14: =VLOOKUP($H14,output!$A$10:$N$2201,P$1-$J$1+2) -> 3.834 | Q14: =VLOOKUP($H14,output!$A$10:$N$2201,Q$1-$J$1+2) -> 4.141 | ... V14: =VLOOKUP($H14,output!$A$10:$N$2201,V$1-$J$1+2) -> 6.018
H15: Stock C (Million) | I15: C | J15: =VLOOKUP($H15,output!$A$10:$N$2201,J$1-$J$1+2) -> 5.55 | K15: =VLOOKUP($H15,output!$A$10:$N$2201,K$1-$J$1+2) -> 6.018 | L15: =VLOOKUP($H15,output!$A$10:$N$2201,L$1-$J$1+2) -> 6.359 | M15: =VLOOKUP($H15,output!$A$10:$N$2201,M$1-$J$1+2) -> 6.835 | N15: =VLOOKUP($H15,output!$A$10:$N$2201,N$1-$J$1+2) -> 7.326 | O15: =VLOOKUP($H15,output!$A$10:$N$2201,O$1-$J$1+2) -> 7.843 | P15: =VLOOKUP($H15,output!$A$10:$N$2201,P$1-$J$1+2) -> 8.377 | Q15: =VLOOKUP($H15,output!$A$10:$N$2201,Q$1-$J$1+2) -> 8.945 | ... V15: =VLOOKUP($H15,output!$A$10:$N$2201,V$1-$J$1+2) -> 11.615
H16: Stock D (Million) | I16: D | J16: =VLOOKUP($H16,output!$A$10:$N$2201,J$1-$J$1+2) -> 12.774 | K16: =VLOOKUP($H16,output!$A$10:$N$2201,K$1-$J$1+2) -> 12.688 | L16: =VLOOKUP($H16,output!$A$10:$N$2201,L$1-$J$1+2) -> 12.639 | M16: =VLOOKUP($H16,output!$A$10:$N$2201,M$1-$J$1+2) -> 12.527 | N16: =VLOOKUP($H16,output!$A$10:$N$2201,N$1-$J$1+2) -> 12.387 | O16: =VLOOKUP($H16,output!$A$10:$N$2201,O$1-$J$1+2) -> 12.168 | P16: =VLOOKUP($H16,output!$A$10:$N$2201,P$1-$J$1+2) -> 11.876 | Q16: =VLOOKUP($H16,output!$A$10:$N$2201,Q$1-$J$1+2) -> 11.562 | ... V16: =VLOOKUP($H16,output!$A$10:$N$2201,V$1-$J$1+2) -> 10.039
H17: Stock E (Million) | I17: E | J17: =VLOOKUP($H17,output!$A$10:$N$2201,J$1-$J$1+2) -> 5.024 | K17: =VLOOKUP($H17,output!$A$10:$N$2201,K$1-$J$1+2) -> 4.841 | L17: =VLOOKUP($H17,output!$A$10:$N$2201,L$1-$J$1+2) -> 4.647 | M17: =VLOOKUP($H17,output!$A$10:$N$2201,M$1-$J$1+2) -> 4.446 | N17: =VLOOKUP($H17,output!$A$10:$N$2201,N$1-$J$1+2) -> 4.229 | O17: =VLOOKUP($H17,output!$A$10:$N$2201,O$1-$J$1+2) -> 4.001 | P17: =VLOOKUP($H17,output!$A$10:$N$2201,P$1-$J$1+2) -> 3.77 | Q17: =VLOOKUP($H17,output!$A$10:$N$2201,Q$1-$J$1+2) -> 3.54 | ... V17: =VLOOKUP($H17,output!$A$10:$N$2201,V$1-$J$1+2) -> 1.723
H18: Stock F (Million) | I18: F | J18: =VLOOKUP($H18,output!$A$10:$N$2201,J$1-$J$1+2) -> 2.927 | K18: =VLOOKUP($H18,output!$A$10:$N$2201,K$1-$J$1+2) -> 2.755 | L18: =VLOOKUP($H18,output!$A$10:$N$2201,L$1-$J$1+2) -> 2.62 | M18: =VLOOKUP($H18,output!$A$10:$N$2201,M$1-$J$1+2) -> 2.385 | N18: =VLOOKUP($H18,output!$A$10:$N$2201,N$1-$J$1+2) -> 2.17 | O18: =VLOOKUP($H18,output!$A$10:$N$2201,O$1-$J$1+2) -> 1.984 | P18: =VLOOKUP($H18,output!$A$10:$N$2201,P$1-$J$1+2) -> 1.823 | Q18: =VLOOKUP($H18,output!$A$10:$N$2201,Q$1-$J$1+2) -> 1.613 | ... V18: =VLOOKUP($H18,output!$A$10:$N$2201,V$1-$J$1+2) -> 0.816
H19: Stock G (Million) | I19: G | J19: =VLOOKUP($H19,output!$A$10:$N$2201,J$1-$J$1+2) -> 1.398 | K19: =VLOOKUP($H19,output!$A$10:$N$2201,K$1-$J$1+2) -> 1.162 | L19: =VLOOKUP($H19,output!$A$10:$N$2201,L$1-$J$1+2) -> 1.006 | M19: =VLOOKUP($H19,output!$A$10:$N$2201,M$1-$J$1+2) -> 0.872 | N19: =VLOOKUP($H19,output!$A$10:$N$2201,N$1-$J$1+2) -> 0.729 | O19: =VLOOKUP($H19,output!$A$10:$N$2201,O$1-$J$1+2) -> 0.605 | P19: =VLOOKUP($H19,output!$A$10:$N$2201,P$1-$J$1+2) -> 0.497 | Q19: =VLOOKUP($H19,output!$A$10:$N$2201,Q$1-$J$1+2) -> 0.403 | ... V19: =VLOOKUP($H19,output!$A$10:$N$2201,V$1-$J$1+2) -> 0.089
I21: Passoires | J21: =J18+J19 -> 4.325 | K21: =K18+K19 -> 3.917 | L21: =L18+L19 -> 3.626 | M21: =M18+M19 -> 3.257 | N21: =N18+N19 -> 2.899 | O21: =O18+O19 -> 2.589 | P21: =P18+P19 -> 2.32 | Q21: =Q18+Q19 -> 2.016 | ... V21: =V18+V19 -> 0.905 | W21: =V21/N21-1 -> -0.68782339
H26: Consumption Heating (TWh) | I26: Chauffage urbain | J26: =VLOOKUP($H26,output!$A$10:$N$2201,J$1-$J$1+2) -> 11.458 | K26: =VLOOKUP($H26,output!$A$10:$N$2201,K$1-$J$1+2) -> 12.433 | L26: =VLOOKUP($H26,output!$A$10:$N$2201,L$1-$J$1+2) -> 12.517 | M26: =VLOOKUP($H26,output!$A$10:$N$2201,M$1-$J$1+2) -> 14.035 | N26: =VLOOKUP($H26,output!$A$10:$N$2201,N$1-$J$1+2) -> 15.012 | O26: =VLOOKUP($H26,output!$A$10:$N$2201,O$1-$J$1+2) -> 17.038 | P26: =VLOOKUP($H26,output!$A$10:$N$2201,P$1-$J$1+2) -> 20.233 | Q26: =VLOOKUP($H26,output!$A$10:$N$2201,Q$1-$J$1+2) -> 24.458 | ... V26: =VLOOKUP($H26,output!$A$10:$N$2201,V$1-$J$1+2) -> 37.128
H27: Consumption Natural gas (TWh) | I27: Gaz naturel | J27: =VLOOKUP($H27,output!$A$10:$N$2201,J$1-$J$1+2) -> 91 | K27: =VLOOKUP($H27,output!$A$10:$N$2201,K$1-$J$1+2) -> 89.097 | L27: =VLOOKUP($H27,output!$A$10:$N$2201,L$1-$J$1+2) -> 88.979 | M27: =VLOOKUP($H27,output!$A$10:$N$2201,M$1-$J$1+2) -> 86.764 | N27: =VLOOKUP($H27,output!$A$10:$N$2201,N$1-$J$1+2) -> 82.988 | O27: =VLOOKUP($H27,output!$A$10:$N$2201,O$1-$J$1+2) -> 79.972 | P27: =VLOOKUP($H27,output!$A$10:$N$2201,P$1-$J$1+2) -> 76.412 | Q27: =VLOOKUP($H27,output!$A$10:$N$2201,Q$1-$J$1+2) -> 72.209 | ... V27: =VLOOKUP($H27,output!$A$10:$N$2201,V$1-$J$1+2) -> 52.078
H28: Consumption Oil fuel (TWh) | I28: Fioul | J28: =VLOOKUP($H28,output!$A$10:$N$2201,J$1-$J$1+2) -> 31 | K28: =VLOOKUP($H28,output!$A$10:$N$2201,K$1-$J$1+2) -> 27.903 | L28: =VLOOKUP($H28,output!$A$10:$N$2201,L$1-$J$1+2) -> 25.252 | M28: =VLOOKUP($H28,output!$A$10:$N$2201,M$1-$J$1+2) -> 22.315 | N28: =VLOOKUP($H28,output!$A$10:$N$2201,N$1-$J$1+2) -> 18.951 | O28: =VLOOKUP($H28,output!$A$10:$N$2201,O$1-$J$1+2) -> 16.163 | P28: =VLOOKUP($H28,output!$A$10:$N$2201,P$1-$J$1+2) -> 13.514 | Q28: =VLOOKUP($H28,output!$A$10:$N$2201,Q$1-$J$1+2) -> 10.984 | ... V28: =VLOOKUP($H28,output!$A$10:$N$2201,V$1-$J$1+2) -> 0
H29: Consumption Wood fuel (TWh) | I29: Bois | J29: =VLOOKUP($H29,output!$A$10:$N$2201,J$1-$J$1+2) -> 76.103 | K29: =VLOOKUP($H29,output!$A$10:$N$2201,K$1-$J$1+2) -> 74.564 | L29: =VLOOKUP($H29,output!$A$10:$N$2201,L$1-$J$1+2) -> 73.541 | M29: =VLOOKUP($H29,output!$A$10:$N$2201,M$1-$J$1+2) -> 71.848 | N29: =VLOOKUP($H29,output!$A$10:$N$2201,N$1-$J$1+2) -> 69.645 | O29: =VLOOKUP($H29,output!$A$10:$N$2201,O$1-$J$1+2) -> 67.831 | P29: =VLOOKUP($H29,output!$A$10:$N$2201,P$1-$J$1+2) -> 65.93 | Q29: =VLOOKUP($H29,output!$A$10:$N$2201,Q$1-$J$1+2) -> 63.778 | ... V29: =VLOOKUP($H29,output!$A$10:$N$2201,V$1-$J$1+2) -> 53.952
H30: Consumption Heat pump (TWh) | I30: Electricité (pompe à chaleur) | J30: =VLOOKUP($H30,output!$A$10:$N$2201,J$1-$J$1+2) -> 6.984 | K30: =VLOOKUP($H30,output!$A$10:$N$2201,K$1-$J$1+2) -> 9.027 | L30: =VLOOKUP($H30,output!$A$10:$N$2201,L$1-$J$1+2) -> 10.851 | M30: =VLOOKUP($H30,output!$A$10:$N$2201,M$1-$J$1+2) -> 12.635 | N30: =VLOOKUP($H30,output!$A$10:$N$2201,N$1-$J$1+2) -> 14.589 | O30: =VLOOKUP($H30,output!$A$10:$N$2201,O$1-$J$1+2) -> 16.461 | P30: =VLOOKUP($H30,output!$A$10:$N$2201,P$1-$J$1+2) -> 18.247 | Q30: =VLOOKUP($H30,output!$A$10:$N$2201,Q$1-$J$1+2) -> 19.873 | ... V30: =VLOOKUP($H30,output!$A$10:$N$2201,V$1-$J$1+2) -> 28.732
H31: Consumption Direct electric (TWh) | I31: Electricité (joule) | J31: =VLOOKUP($H31,output!$A$10:$N$2201,J$1-$J$1+2) -> 43.913 | K31: =VLOOKUP($H31,output!$A$10:$N$2201,K$1-$J$1+2) -> 40.822 | L31: =VLOOKUP($H31,output!$A$10:$N$2201,L$1-$J$1+2) -> 38.813 | M31: =VLOOKUP($H31,output!$A$10:$N$2201,M$1-$J$1+2) -> 36.839 | N31: =VLOOKUP($H31,output!$A$10:$N$2201,N$1-$J$1+2) -> 34.963 | O31: =VLOOKUP($H31,output!$A$10:$N$2201,O$1-$J$1+2) -> 33.127 | P31: =VLOOKUP($H31,output!$A$10:$N$2201,P$1-$J$1+2) -> 31.307 | Q31: =VLOOKUP($H31,output!$A$10:$N$2201,Q$1-$J$1+2) -> 29.36 | ... V31: =VLOOKUP($H31,output!$A$10:$N$2201,V$1-$J$1+2) -> 20.646
I33: total | J33: =SUM(J26:J31) -> 260.458 | K33: =SUM(K26:K31) -> 253.846 | L33: =SUM(L26:L31) -> 249.953 | M33: =SUM(M26:M31) -> 244.436 | N33: =SUM(N26:N31) -> 236.148 | O33: =SUM(O26:O31) -> 230.592 | P33: =SUM(P26:P31) -> 225.643 | Q33: =SUM(Q26:Q31) -> 220.662 | ... V33: =SUM(V26:V31) -> 192.536
H37: Stock Direct electric (Million) | I37: Electricité (joule) | J37: =VLOOKUP($H37,output!$A$10:$N$2201,J$1-$J$1+2) -> 8.317 | K37: =VLOOKUP($H37,output!$A$10:$N$2201,K$1-$J$1+2) -> 8.012 | L37: =VLOOKUP($H37,output!$A$10:$N$2201,L$1-$J$1+2) -> 7.768 | M37: =VLOOKUP($H37,output!$A$10:$N$2201,M$1-$J$1+2) -> 7.499 | N37: =VLOOKUP($H37,output!$A$10:$N$2201,N$1-$J$1+2) -> 7.241 | O37: =VLOOKUP($H37,output!$A$10:$N$2201,O$1-$J$1+2) -> 6.964 | P37: =VLOOKUP($H37,output!$A$10:$N$2201,P$1-$J$1+2) -> 6.666 | Q37: =VLOOKUP($H37,output!$A$10:$N$2201,Q$1-$J$1+2) -> 6.332 | ... V37: =VLOOKUP($H37,output!$A$10:$N$2201,V$1-$J$1+2) -> 4.795
H38: Stock Heat pump (Million) | I38: Electricité (pompe à chaleur) | J38: =VLOOKUP($H38,output!$A$10:$N$2201,J$1-$J$1+2) -> 2.896 | K38: =VLOOKUP($H38,output!$A$10:$N$2201,K$1-$J$1+2) -> 3.642 | L38: =VLOOKUP($H38,output!$A$10:$N$2201,L$1-$J$1+2) -> 4.368 | M38: =VLOOKUP($H38,output!$A$10:$N$2201,M$1-$J$1+2) -> 5.054 | N38: =VLOOKUP($H38,output!$A$10:$N$2201,N$1-$J$1+2) -> 5.799 | O38: =VLOOKUP($H38,output!$A$10:$N$2201,O$1-$J$1+2) -> 6.511 | P38: =VLOOKUP($H38,output!$A$10:$N$2201,P$1-$J$1+2) -> 7.184 | Q38: =VLOOKUP($H38,output!$A$10:$N$2201,Q$1-$J$1+2) -> 7.756 | ... V38: =VLOOKUP($H38,output!$A$10:$N$2201,V$1-$J$1+2) -> 11.107
H39: Stock Oil fuel (Million) | I39: Fioul | J39: =VLOOKUP($H39,output!$A$10:$N$2201,J$1-$J$1+2) -> 3.049 | K39: =VLOOKUP($H39,output!$A$10:$N$2201,K$1-$J$1+2) -> 2.788 | L39: =VLOOKUP($H39,output!$A$10:$N$2201,L$1-$J$1+2) -> 2.528 | M39: =VLOOKUP($H39,output!$A$10:$N$2201,M$1-$J$1+2) -> 2.27 | N39: =VLOOKUP($H39,output!$A$10:$N$2201,N$1-$J$1+2) -> 2.013 | O39: =VLOOKUP($H39,output!$A$10:$N$2201,O$1-$J$1+2) -> 1.758 | P39: =VLOOKUP($H39,output!$A$10:$N$2201,P$1-$J$1+2) -> 1.504 | Q39: =VLOOKUP($H39,output!$A$10:$N$2201,Q$1-$J$1+2) -> 1.251 | ... V39: =VLOOKUP($H39,output!$A$10:$N$2201,V$1-$J$1+2) -> 0
H40: Stock Wood fuel (Million) | I40: Bois | J40: =VLOOKUP($H40,output!$A$10:$N$2201,J$1-$J$1+2) -> 2.733 | K40: =VLOOKUP($H40,output!$A$10:$N$2201,K$1-$J$1+2) -> 2.763 | L40: =VLOOKUP($H40,output!$A$10:$N$2201,L$1-$J$1+2) -> 2.782 | M40: =VLOOKUP($H40,output!$A$10:$N$2201,M$1-$J$1+2) -> 2.8 | N40: =VLOOKUP($H40,output!$A$10:$N$2201,N$1-$J$1+2) -> 2.82 | O40: =VLOOKUP($H40,output!$A$10:$N$2201,O$1-$J$1+2) -> 2.84 | P40: =VLOOKUP($H40,output!$A$10:$N$2201,P$1-$J$1+2) -> 2.86 | Q40: =VLOOKUP($H40,output!$A$10:$N$2201,Q$1-$J$1+2) -> 2.876 | ... V40: =VLOOKUP($H40,output!$A$10:$N$2201,V$1-$J$1+2) -> 2.962
H41: Stock Natural gas (Million) | I41: Gaz naturel | J41: =VLOOKUP($H41,output!$A$10:$N$2201,J$1-$J$1+2) -> 11.809 | K41: =VLOOKUP($H41,output!$A$10:$N$2201,K$1-$J$1+2) -> 11.674 | L41: =VLOOKUP($H41,output!$A$10:$N$2201,L$1-$J$1+2) -> 11.648 | M41: =VLOOKUP($H41,output!$A$10:$N$2201,M$1-$J$1+2) -> 11.49 | N41: =VLOOKUP($H41,output!$A$10:$N$2201,N$1-$J$1+2) -> 11.328 | O41: =VLOOKUP($H41,output!$A$10:$N$2201,O$1-$J$1+2) -> 11.067 | P41: =VLOOKUP($H41,output!$A$10:$N$2201,P$1-$J$1+2) -> 10.695 | Q41: =VLOOKUP($H41,output!$A$10:$N$2201,Q$1-$J$1+2) -> 10.223 | ... V41: =VLOOKUP($H41,output!$A$10:$N$2201,V$1-$J$1+2) -> 8.208
H42: Stock District heating (Million) | I42: Chauffage urbain | J42: =VLOOKUP($H42,output!$A$10:$N$2201,J$1-$J$1+2) -> 1.421 | K42: =VLOOKUP($H42,output!$A$10:$N$2201,K$1-$J$1+2) -> 1.565 | L42: =VLOOKUP($H42,output!$A$10:$N$2201,L$1-$J$1+2) -> 1.619 | M42: =VLOOKUP($H42,output!$A$10:$N$2201,M$1-$J$1+2) -> 1.868 | N42: =VLOOKUP($H42,output!$A$10:$N$2201,N$1-$J$1+2) -> 2.047 | O42: =VLOOKUP($H42,output!$A$10:$N$2201,O$1-$J$1+2) -> 2.375 | P42: =VLOOKUP($H42,output!$A$10:$N$2201,P$1-$J$1+2) -> 2.874 | Q42: =VLOOKUP($H42,output!$A$10:$N$2201,Q$1-$J$1+2) -> 3.522 | ... V42: =VLOOKUP($H42,output!$A$10:$N$2201,V$1-$J$1+2) -> 5.777
H48: Retrofit 6 EPC (Thousand households) | I48: 6 classes | J48: =VLOOKUP($H48,output!$A$10:$N$2201,J$1-$J$1+2) -> 0 | K48: =VLOOKUP($H48,output!$A$10:$N$2201,K$1-$J$1+2) -> 0.059 | L48: =VLOOKUP($H48,output!$A$10:$N$2201,L$1-$J$1+2) -> 0.014 | M48: =VLOOKUP($H48,output!$A$10:$N$2201,M$1-$J$1+2) -> 0.006 | N48: =VLOOKUP($H48,output!$A$10:$N$2201,N$1-$J$1+2) -> 0.003 | O48: =VLOOKUP($H48,output!$A$10:$N$2201,O$1-$J$1+2) -> 0.002 | P48: =VLOOKUP($H48,output!$A$10:$N$2201,P$1-$J$1+2) -> 0.002 | Q48: =VLOOKUP($H48,output!$A$10:$N$2201,Q$1-$J$1+2) -> 0.001 | ... V48: =VLOOKUP($H48,output!$A$10:$N$2201,V$1-$J$1+2) -> 0.001
H49: Retrofit 5 EPC (Thousand households) | I49: 5 classes | J49: =VLOOKUP($H49,output!$A$10:$N$2201,J$1-$J$1+2) -> 0 | K49: =VLOOKUP($H49,output!$A$10:$N$2201,K$1-$J$1+2) -> 0.773 | L49: =VLOOKUP($H49,output!$A$10:$N$2201,L$1-$J$1+2) -> 0.31 | M49: =VLOOKUP($H49,output!$A$10:$N$2201,M$1-$J$1+2) -> 0.241 | N49: =VLOOKUP($H49,output!$A$10:$N$2201,N$1-$J$1+2) -> 0.279 | O49: =VLOOKUP($H49,output!$A$10:$N$2201,O$1-$J$1+2) -> 0.23 | P49: =VLOOKUP($H49,output!$A$10:$N$2201,P$1-$J$1+2) -> 0.182 | Q49: =VLOOKUP($H49,output!$A$10:$N$2201,Q$1-$J$1+2) -> 0.16 | ... V49: =VLOOKUP($H49,output!$A$10:$N$2201,V$1-$J$1+2) -> 0.097
H50: Retrofit 4 EPC (Thousand households) | I50: 4 classes | J50: =VLOOKUP($H50,output!$A$10:$N$2201,J$1-$J$1+2) -> 0 | K50: =VLOOKUP($H50,output!$A$10:$N$2201,K$1-$J$1+2) -> 61.33 | L50: =VLOOKUP($H50,output!$A$10:$N$2201,L$1-$J$1+2) -> 40.121 | M50: =VLOOKUP($H50,output!$A$10:$N$2201,M$1-$J$1+2) -> 29.405 | N50: =VLOOKUP($H50,output!$A$10:$N$2201,N$1-$J$1+2) -> 29.237 | O50: =VLOOKUP($H50,output!$A$10:$N$2201,O$1-$J$1+2) -> 22.59 | P50: =VLOOKUP($H50,output!$A$10:$N$2201,P$1-$J$1+2) -> 17.083 | Q50: =VLOOKUP($H50,output!$A$10:$N$2201,Q$1-$J$1+2) -> 13.109 | ... V50: =VLOOKUP($H50,output!$A$10:$N$2201,V$1-$J$1+2) -> 6.189
H51: Retrofit 3 EPC (Thousand households) | I51: 3 classes | J51: =VLOOKUP($H51,output!$A$10:$N$2201,J$1-$J$1+2) -> 0 | K51: =VLOOKUP($H51,output!$A$10:$N$2201,K$1-$J$1+2) -> 251.615 | L51: =VLOOKUP($H51,output!$A$10:$N$2201,L$1-$J$1+2) -> 184.159 | M51: =VLOOKUP($H51,output!$A$10:$N$2201,M$1-$J$1+2) -> 210.072 | N51: =VLOOKUP($H51,output!$A$10:$N$2201,N$1-$J$1+2) -> 221.142 | O51: =VLOOKUP($H51,output!$A$10:$N$2201,O$1-$J$1+2) -> 192.734 | P51: =VLOOKUP($H51,output!$A$10:$N$2201,P$1-$J$1+2) -> 166.147 | Q51: =VLOOKUP($H51,output!$A$10:$N$2201,Q$1-$J$1+2) -> 168.647 | ... V51: =VLOOKUP($H51,output!$A$10:$N$2201,V$1-$J$1+2) -> 122.339
H52: Retrofit 2 EPC (Thousand households) | I52: 2 classes | J52: =VLOOKUP($H52,output!$A$10:$N$2201,J$1-$J$1+2) -> 0 | K52: =VLOOKUP($H52,output!$A$10:$N$2201,K$1-$J$1+2) -> 354.066 | L52: =VLOOKUP($H52,output!$A$10:$N$2201,L$1-$J$1+2) -> 275.016 | M52: =VLOOKUP($H52,output!$A$10:$N$2201,M$1-$J$1+2) -> 332.511 | N52: =VLOOKUP($H52,output!$A$10:$N$2201,N$1-$J$1+2) -> 348.665 | O52: =VLOOKUP($H52,output!$A$10:$N$2201,O$1-$J$1+2) -> 341.088 | P52: =VLOOKUP($H52,output!$A$10:$N$2201,P$1-$J$1+2) -> 331.271 | Q52: =VLOOKUP($H52,output!$A$10:$N$2201,Q$1-$J$1+2) -> 362.798 | ... V52: =VLOOKUP($H52,output!$A$10:$N$2201,V$1-$J$1+2) -> 408.51
H53: Retrofit 1 EPC (Thousand households) | I53: 1 classe | J53: =VLOOKUP($H53,output!$A$10:$N$2201,J$1-$J$1+2) -> 0 | K53: =VLOOKUP($H53,output!$A$10:$N$2201,K$1-$J$1+2) -> 385.953 | L53: =VLOOKUP($H53,output!$A$10:$N$2201,L$1-$J$1+2) -> 333.736 | M53: =VLOOKUP($H53,output!$A$10:$N$2201,M$1-$J$1+2) -> 470.83 | N53: =VLOOKUP($H53,output!$A$10:$N$2201,N$1-$J$1+2) -> 468.452 | O53: =VLOOKUP($H53,output!$A$10:$N$2201,O$1-$J$1+2) -> 549.61 | P53: =VLOOKUP($H53,output!$A$10:$N$2201,P$1-$J$1+2) -> 624.923 | Q53: =VLOOKUP($H53,output!$A$10:$N$2201,Q$1-$J$1+2) -> 694.254 | ... V53: =VLOOKUP($H53,output!$A$10:$N$2201,V$1-$J$1+2) -> 668.203
I55: Part réno 2+ | K55: =SUM(K48:K52)/SUM(K48:K53) -> 0.6337498 | L55: =SUM(L48:L52)/SUM(L48:L53) -> 0.59952769 | M55: =SUM(M48:M52)/SUM(M48:M53) -> 0.54860915 | N55: =SUM(N48:N52)/SUM(N48:N53) -> 0.56128334 | O55: =SUM(O48:O52)/SUM(O48:O53) -> 0.5031792 | P55: =SUM(P48:P52)/SUM(P48:P53) -> 0.45163337 | Q55: =SUM(Q48:Q52)/SUM(Q48:Q53) -> 0.43965184 | R55: =SUM(R48:R52)/SUM(R48:R53) -> 0.45119005 | ... V55: =SUM(V48:V52)/SUM(V48:V53) -> 0.44563065
I56: Part réno 3+ | K56: =SUM(K48:K51)/SUM(K48:K53) -> 0.29775877 | L56: =SUM(L48:L51)/SUM(L48:L53) -> 0.26951747 | M56: =SUM(M48:M51)/SUM(M48:M53) -> 0.22982652 | N56: =SUM(N48:N51)/SUM(N48:N53) -> 0.23475011 | O56: =SUM(O48:O51)/SUM(O48:O53) -> 0.19485218 | P56: =SUM(P48:P51)/SUM(P48:P53) -> 0.16094482 | Q56: =SUM(Q48:Q51)/SUM(Q48:Q53) -> 0.14682934 | R56: =SUM(R48:R51)/SUM(R48:R53) -> 0.13158012 | ... V56: =SUM(V48:V51)/SUM(V48:V53) -> 0.10671355
H60: Renovation Multi-family - Owner-occupied (Thousand households) | I60: PO en copropriété | J60: =VLOOKUP($H60,output!$A$10:$N$2201,J$1-$J$1+2) -> 0 | K60: =VLOOKUP($H60,output!$A$10:$N$2201,K$1-$J$1+2) -> 66.859 | L60: =VLOOKUP($H60,output!$A$10:$N$2201,L$1-$J$1+2) -> 51 | M60: =VLOOKUP($H60,output!$A$10:$N$2201,M$1-$J$1+2) -> 50.872 | N60: =VLOOKUP($H60,output!$A$10:$N$2201,N$1-$J$1+2) -> 55.295 | O60: =VLOOKUP($H60,output!$A$10:$N$2201,O$1-$J$1+2) -> 54.615 | P60: =VLOOKUP($H60,output!$A$10:$N$2201,P$1-$J$1+2) -> 53.884 | Q60: =VLOOKUP($H60,output!$A$10:$N$2201,Q$1-$J$1+2) -> 57.446 | ... V60: =VLOOKUP($H60,output!$A$10:$N$2201,V$1-$J$1+2) -> 54.485
H61: Renovation Multi-family - Privately rented (Thousand households) | I61: PB en copropriété | J61: =VLOOKUP($H61,output!$A$10:$N$2201,J$1-$J$1+2) -> 0 | K61: =VLOOKUP($H61,output!$A$10:$N$2201,K$1-$J$1+2) -> 75.746 | L61: =VLOOKUP($H61,output!$A$10:$N$2201,L$1-$J$1+2) -> 60.488 | M61: =VLOOKUP($H61,output!$A$10:$N$2201,M$1-$J$1+2) -> 89.875 | N61: =VLOOKUP($H61,output!$A$10:$N$2201,N$1-$J$1+2) -> 75.798 | O61: =VLOOKUP($H61,output!$A$10:$N$2201,O$1-$J$1+2) -> 64.472 | P61: =VLOOKUP($H61,output!$A$10:$N$2201,P$1-$J$1+2) -> 55.584 | Q61: =VLOOKUP($H61,output!$A$10:$N$2201,Q$1-$J$1+2) -> 48.606 | ... V61: =VLOOKUP($H61,output!$A$10:$N$2201,V$1-$J$1+2) -> 104.876
H62: Renovation Multi-family - Social-housing (Thousand households) | I62: PB social en copropriété | J62: =VLOOKUP($H62,output!$A$10:$N$2201,J$1-$J$1+2) -> 0 | K62: =VLOOKUP($H62,output!$A$10:$N$2201,K$1-$J$1+2) -> 15.24 | L62: =VLOOKUP($H62,output!$A$10:$N$2201,L$1-$J$1+2) -> 61.818 | M62: =VLOOKUP($H62,output!$A$10:$N$2201,M$1-$J$1+2) -> 139.633 | N62: =VLOOKUP($H62,output!$A$10:$N$2201,N$1-$J$1+2) -> 181.31 | O62: =VLOOKUP($H62,output!$A$10:$N$2201,O$1-$J$1+2) -> 224.567 | P62: =VLOOKUP($H62,output!$A$10:$N$2201,P$1-$J$1+2) -> 234.966 | Q62: =VLOOKUP($H62,output!$A$10:$N$2201,Q$1-$J$1+2) -> 238.434 | ... V62: =VLOOKUP($H62,output!$A$10:$N$2201,V$1-$J$1+2) -> 325.795
H63: Renovation Single-family - Owner-occupied (Thousand households) | I63: PO en maison | J63: =VLOOKUP($H63,output!$A$10:$N$2201,J$1-$J$1+2) -> 0 | K63: =VLOOKUP($H63,output!$A$10:$N$2201,K$1-$J$1+2) -> 373.908 | L63: =VLOOKUP($H63,output!$A$10:$N$2201,L$1-$J$1+2) -> 194.506 | M63: =VLOOKUP($H63,output!$A$10:$N$2201,M$1-$J$1+2) -> 207.952 | N63: =VLOOKUP($H63,output!$A$10:$N$2201,N$1-$J$1+2) -> 230.087 | O63: =VLOOKUP($H63,output!$A$10:$N$2201,O$1-$J$1+2) -> 222.751 | P63: =VLOOKUP($H63,output!$A$10:$N$2201,P$1-$J$1+2) -> 216.001 | Q63: =VLOOKUP($H63,output!$A$10:$N$2201,Q$1-$J$1+2) -> 266.178 | ... V63: =VLOOKUP($H63,output!$A$10:$N$2201,V$1-$J$1+2) -> 218.739
H64: Renovation Single-family - Privately rented (Thousand households) | I64: PB en maison | J64: =VLOOKUP($H64,output!$A$10:$N$2201,J$1-$J$1+2) -> 0 | K64: =VLOOKUP($H64,output!$A$10:$N$2201,K$1-$J$1+2) -> 54.747 | L64: =VLOOKUP($H64,output!$A$10:$N$2201,L$1-$J$1+2) -> 37.575 | M64: =VLOOKUP($H64,output!$A$10:$N$2201,M$1-$J$1+2) -> 88.86 | N64: =VLOOKUP($H64,output!$A$10:$N$2201,N$1-$J$1+2) -> 71.556 | O64: =VLOOKUP($H64,output!$A$10:$N$2201,O$1-$J$1+2) -> 57.828 | P64: =VLOOKUP($H64,output!$A$10:$N$2201,P$1-$J$1+2) -> 47.111 | Q64: =VLOOKUP($H64,output!$A$10:$N$2201,Q$1-$J$1+2) -> 38.75 | ... V64: =VLOOKUP($H64,output!$A$10:$N$2201,V$1-$J$1+2) -> 26.642
H65: Renovation Single-family - Social-housing (Thousand households) | I65: PB social en maison | J65: =VLOOKUP($H65,output!$A$10:$N$2201,J$1-$J$1+2) -> 0 | K65: =VLOOKUP($H65,output!$A$10:$N$2201,K$1-$J$1+2) -> 14.484 | L65: =VLOOKUP($H65,output!$A$10:$N$2201,L$1-$J$1+2) -> 29.828 | M65: =VLOOKUP($H65,output!$A$10:$N$2201,M$1-$J$1+2) -> 47.03 | N65: =VLOOKUP($H65,output!$A$10:$N$2201,N$1-$J$1+2) -> 59.106 | O65: =VLOOKUP($H65,output!$A$10:$N$2201,O$1-$J$1+2) -> 61.26 | P65: =VLOOKUP($H65,output!$A$10:$N$2201,P$1-$J$1+2) -> 56.507 | Q65: =VLOOKUP($H65,output!$A$10:$N$2201,Q$1-$J$1+2) -> 61.023 | ... V65: =VLOOKUP($H65,output!$A$10:$N$2201,V$1-$J$1+2) -> 100.738
H72: Investment heater (Billion euro) | J72: =VLOOKUP($H72,output!$A$10:$N$2201,J$1-$J$1+2) -> 0 | K72: =VLOOKUP($H72,output!$A$10:$N$2201,K$1-$J$1+2) -> 15.007 | L72: =VLOOKUP($H72,output!$A$10:$N$2201,L$1-$J$1+2) -> 14.005 | M72: =VLOOKUP($H72,output!$A$10:$N$2201,M$1-$J$1+2) -> 12.918 | N72: =VLOOKUP($H72,output!$A$10:$N$2201,N$1-$J$1+2) -> 13.325 | O72: =VLOOKUP($H72,output!$A$10:$N$2201,O$1-$J$1+2) -> 12.469 | P72: =VLOOKUP($H72,output!$A$10:$N$2201,P$1-$J$1+2) -> 11.518 | Q72: =VLOOKUP($H72,output!$A$10:$N$2201,Q$1-$J$1+2) -> 10.638 | ... V72: =VLOOKUP($H72,output!$A$10:$N$2201,V$1-$J$1+2) -> 11.923
H73: Investment insulation (Billion euro) | J73: =VLOOKUP($H73,output!$A$10:$N$2201,J$1-$J$1+2) -> 0 | K73: =VLOOKUP($H73,output!$A$10:$N$2201,K$1-$J$1+2) -> 7.376 | L73: =VLOOKUP($H73,output!$A$10:$N$2201,L$1-$J$1+2) -> 4.132 | M73: =VLOOKUP($H73,output!$A$10:$N$2201,M$1-$J$1+2) -> 6.282 | N73: =VLOOKUP($H73,output!$A$10:$N$2201,N$1-$J$1+2) -> 6.829 | O73: =VLOOKUP($H73,output!$A$10:$N$2201,O$1-$J$1+2) -> 6.369 | P73: =VLOOKUP($H73,output!$A$10:$N$2201,P$1-$J$1+2) -> 5.806 | Q73: =VLOOKUP($H73,output!$A$10:$N$2201,Q$1-$J$1+2) -> 7.248 | ... V73: =VLOOKUP($H73,output!$A$10:$N$2201,V$1-$J$1+2) -> 6.716
H79: Investment total (Billion euro) | I79: Investissement total (milliards) | J79: =VLOOKUP($H79,output!$A$10:$N$2201,J$1-$J$1+2) -> 0 | K79: =VLOOKUP($H79,output!$A$10:$N$2201,K$1-$J$1+2) -> 22.383 | L79: =VLOOKUP($H79,output!$A$10:$N$2201,L$1-$J$1+2) -> 18.137 | M79: =VLOOKUP($H79,output!$A$10:$N$2201,M$1-$J$1+2) -> 19.199 | N79: =VLOOKUP($H79,output!$A$10:$N$2201,N$1-$J$1+2) -> 20.154 | O79: =VLOOKUP($H79,output!$A$10:$N$2201,O$1-$J$1+2) -> 18.838 | P79: =VLOOKUP($H79,output!$A$10:$N$2201,P$1-$J$1+2) -> 17.324 | Q79: =VLOOKUP($H79,output!$A$10:$N$2201,Q$1-$J$1+2) -> 17.886 | ... V79: =VLOOKUP($H79,output!$A$10:$N$2201,V$1-$J$1+2) -> 18.639
H80: Financing total (Billion euro) | J80: =VLOOKUP($H80,output!$A$10:$N$2201,J$1-$J$1+2) -> 0 | K80: =VLOOKUP($H80,output!$A$10:$N$2201,K$1-$J$1+2) -> 5.188 | L80: =VLOOKUP($H80,output!$A$10:$N$2201,L$1-$J$1+2) -> 6.106 | M80: =VLOOKUP($H80,output!$A$10:$N$2201,M$1-$J$1+2) -> 5.907 | N80: =VLOOKUP($H80,output!$A$10:$N$2201,N$1-$J$1+2) -> 6.208 | O80: =VLOOKUP($H80,output!$A$10:$N$2201,O$1-$J$1+2) -> 5.757 | P80: =VLOOKUP($H80,output!$A$10:$N$2201,P$1-$J$1+2) -> 5.282 | Q80: =VLOOKUP($H80,output!$A$10:$N$2201,Q$1-$J$1+2) -> 5.303 | ... V80: =VLOOKUP($H80,output!$A$10:$N$2201,V$1-$J$1+2) -> 5.466
H81: Debt total (Billion euro) | J81: =VLOOKUP($H81,output!$A$10:$N$2201,J$1-$J$1+2) -> 0 | K81: =VLOOKUP($H81,output!$A$10:$N$2201,K$1-$J$1+2) -> 5.71 | L81: =VLOOKUP($H81,output!$A$10:$N$2201,L$1-$J$1+2) -> 6.289 | M81: =VLOOKUP($H81,output!$A$10:$N$2201,M$1-$J$1+2) -> 7.949 | N81: =VLOOKUP($H81,output!$A$10:$N$2201,N$1-$J$1+2) -> 8.49 | O81: =VLOOKUP($H81,output!$A$10:$N$2201,O$1-$J$1+2) -> 8.065 | P81: =VLOOKUP($H81,output!$A$10:$N$2201,P$1-$J$1+2) -> 7.52 | Q81: =VLOOKUP($H81,output!$A$10:$N$2201,Q$1-$J$1+2) -> 8.539 | ... V81: =VLOOKUP($H81,output!$A$10:$N$2201,V$1-$J$1+2) -> 8.436
H82: Soutien total (milliards) | I82: Soutien total (milliards) | J82: =SUM(J106:J109) -> 0 | K82: =SUM(K106:K109) -> 0 | L82: =SUM(L106:L109) -> 0 | M82: =SUM(M106:M109) -> 4.55 | N82: =SUM(N106:N109) -> 4.9 | O82: =SUM(O106:O109) -> 5.7 | P82: =SUM(P106:P109) -> 0 | Q82: =SUM(Q106:Q109) -> 0 | ... V82: =SUM(V106:V109) -> 0
I83: Part soutien | M83: =M82/M79 -> 0.23699151 | N83: =N82/N79 -> 0.24312792 | O83: =O82/O79 -> 0.30257989 | P83: =P82/P79 -> 0 | Q83: =Q82/Q79 -> 0 | R83: =R82/R79 -> 0 | S83: =S82/S79 -> 0 | T83: =T82/T79 -> 0 | ... V83: =V82/V79 -> 0
I84: RAC | M84: =1-M83 -> 0.76300849 | N84: =1-N83 -> 0.75687208 | O84: =1-O83 -> 0.69742011 | P84: =1-P83 -> 1 | Q84: =1-Q83 -> 1 | R84: =1-R83 -> 1 | S84: =1-S83 -> 1 | T84: =1-T83 -> 1 | ... V84: =1-V83 -> 1
H86: Correction années historiques (I4CE) | I86: Investissement total (milliards) | M86: 15 | N86: 17 | O86: 19 | P86: =P79 -> 17.324 | Q86: =Q79 -> 17.886 | R86: =R79 -> 20.459 | S86: =S79 -> 19.163 | T86: =T79 -> 18.897 | U86: =U79 -> 18.944 | V86: =V79 -> 18.639
I87: Soutien total (milliards) | M87: 4.8 | N87: 5.5 | O87: 6 | P87: =P82 -> 0 | Q87: =Q82 -> 0 | R87: =R82 -> 0 | S87: =S82 -> 0 | T87: =T82 -> 0 | U87: =U82 -> 0 | V87: =V82 -> 0
H90: Carbon footprint renovation (MtCO2) | J90: =VLOOKUP($H90,output!$A$10:$N$2201,J$1-$J$1+2) -> 0 | K90: =VLOOKUP($H90,output!$A$10:$N$2201,K$1-$J$1+2) -> 2.623 | L90: =VLOOKUP($H90,output!$A$10:$N$2201,L$1-$J$1+2) -> 1.589 | M90: =VLOOKUP($H90,output!$A$10:$N$2201,M$1-$J$1+2) -> 2.347 | N90: =VLOOKUP($H90,output!$A$10:$N$2201,N$1-$J$1+2) -> 2.543 | O90: =VLOOKUP($H90,output!$A$10:$N$2201,O$1-$J$1+2) -> 2.459 | P90: =VLOOKUP($H90,output!$A$10:$N$2201,P$1-$J$1+2) -> 2.301 | Q90: =VLOOKUP($H90,output!$A$10:$N$2201,Q$1-$J$1+2) -> 2.664 | ... V90: =VLOOKUP($H90,output!$A$10:$N$2201,V$1-$J$1+2) -> 2.741
H91: Carbon footprint construction (MtCO2) | J91: =VLOOKUP($H91,output!$A$10:$N$2201,J$1-$J$1+2) -> 0 | K91: =VLOOKUP($H91,output!$A$10:$N$2201,K$1-$J$1+2) -> 11.736 | L91: =VLOOKUP($H91,output!$A$10:$N$2201,L$1-$J$1+2) -> 14.01 | M91: =VLOOKUP($H91,output!$A$10:$N$2201,M$1-$J$1+2) -> 14.01 | N91: =VLOOKUP($H91,output!$A$10:$N$2201,N$1-$J$1+2) -> 14.01 | O91: =VLOOKUP($H91,output!$A$10:$N$2201,O$1-$J$1+2) -> 14.01 | P91: =VLOOKUP($H91,output!$A$10:$N$2201,P$1-$J$1+2) -> 14.01 | Q91: =VLOOKUP($H91,output!$A$10:$N$2201,Q$1-$J$1+2) -> 9.629 | ... V91: =VLOOKUP($H91,output!$A$10:$N$2201,V$1-$J$1+2) -> 9.629
H92: Emission Natural gas (MtCO2) | J92: =VLOOKUP($H92,output!$A$10:$N$2201,J$1-$J$1+2) -> 20.02 | K92: =VLOOKUP($H92,output!$A$10:$N$2201,K$1-$J$1+2) -> 19.601 | L92: =VLOOKUP($H92,output!$A$10:$N$2201,L$1-$J$1+2) -> 19.575 | M92: =VLOOKUP($H92,output!$A$10:$N$2201,M$1-$J$1+2) -> 19.088 | N92: =VLOOKUP($H92,output!$A$10:$N$2201,N$1-$J$1+2) -> 18.257 | O92: =VLOOKUP($H92,output!$A$10:$N$2201,O$1-$J$1+2) -> 17.594 | P92: =VLOOKUP($H92,output!$A$10:$N$2201,P$1-$J$1+2) -> 16.811 | Q92: =VLOOKUP($H92,output!$A$10:$N$2201,Q$1-$J$1+2) -> 15.886 | ... V92: =VLOOKUP($H92,output!$A$10:$N$2201,V$1-$J$1+2) -> 11.457
H93: Emission Oil fuel (MtCO2) | J93: =VLOOKUP($H93,output!$A$10:$N$2201,J$1-$J$1+2) -> 10.044 | K93: =VLOOKUP($H93,output!$A$10:$N$2201,K$1-$J$1+2) -> 9.04 | L93: =VLOOKUP($H93,output!$A$10:$N$2201,L$1-$J$1+2) -> 8.182 | M93: =VLOOKUP($H93,output!$A$10:$N$2201,M$1-$J$1+2) -> 7.23 | N93: =VLOOKUP($H93,output!$A$10:$N$2201,N$1-$J$1+2) -> 6.14 | O93: =VLOOKUP($H93,output!$A$10:$N$2201,O$1-$J$1+2) -> 5.237 | P93: =VLOOKUP($H93,output!$A$10:$N$2201,P$1-$J$1+2) -> 4.379 | Q93: =VLOOKUP($H93,output!$A$10:$N$2201,Q$1-$J$1+2) -> 3.559 | ... V93: =VLOOKUP($H93,output!$A$10:$N$2201,V$1-$J$1+2) -> 0
H94: Emission Electricity (MtCO2) | J94: =VLOOKUP($H94,output!$A$10:$N$2201,J$1-$J$1+2) -> 4.021 | K94: =VLOOKUP($H94,output!$A$10:$N$2201,K$1-$J$1+2) -> 3.938 | L94: =VLOOKUP($H94,output!$A$10:$N$2201,L$1-$J$1+2) -> 3.923 | M94: =VLOOKUP($H94,output!$A$10:$N$2201,M$1-$J$1+2) -> 3.908 | N94: =VLOOKUP($H94,output!$A$10:$N$2201,N$1-$J$1+2) -> 3.915 | O94: =VLOOKUP($H94,output!$A$10:$N$2201,O$1-$J$1+2) -> 3.917 | P94: =VLOOKUP($H94,output!$A$10:$N$2201,P$1-$J$1+2) -> 3.915 | Q94: =VLOOKUP($H94,output!$A$10:$N$2201,Q$1-$J$1+2) -> 3.889 | ... V94: =VLOOKUP($H94,output!$A$10:$N$2201,V$1-$J$1+2) -> 3.901
H99: Cee (Billion euro) | J99: =VLOOKUP($H99,output!$A$10:$N$2201,J$1-$J$1+2) -> 0 | K99: =VLOOKUP($H99,output!$A$10:$N$2201,K$1-$J$1+2) -> 3.097 | L99: =VLOOKUP($H99,output!$A$10:$N$2201,L$1-$J$1+2) -> 0 | M99: =VLOOKUP($H99,output!$A$10:$N$2201,M$1-$J$1+2) -> 0 | N99: =VLOOKUP($H99,output!$A$10:$N$2201,N$1-$J$1+2) -> 0 | O99: =VLOOKUP($H99,output!$A$10:$N$2201,O$1-$J$1+2) -> 0 | P99: =VLOOKUP($H99,output!$A$10:$N$2201,P$1-$J$1+2) -> 0 | Q99: =VLOOKUP($H99,output!$A$10:$N$2201,Q$1-$J$1+2) -> 0 | ... V99: =VLOOKUP($H99,output!$A$10:$N$2201,V$1-$J$1+2) -> 0
H100: Mpr (Billion euro) | J100: =VLOOKUP($H100,output!$A$10:$N$2201,J$1-$J$1+2) -> 0 | K100: =VLOOKUP($H100,output!$A$10:$N$2201,K$1-$J$1+2) -> 1.607 | L100: =VLOOKUP($H100,output!$A$10:$N$2201,L$1-$J$1+2) -> 0 | M100: =VLOOKUP($H100,output!$A$10:$N$2201,M$1-$J$1+2) -> 0 | N100: =VLOOKUP($H100,output!$A$10:$N$2201,N$1-$J$1+2) -> 0 | O100: =VLOOKUP($H100,output!$A$10:$N$2201,O$1-$J$1+2) -> 0 | P100: =VLOOKUP($H100,output!$A$10:$N$2201,P$1-$J$1+2) -> 0 | Q100: =VLOOKUP($H100,output!$A$10:$N$2201,Q$1-$J$1+2) -> 0 | ... V100: =VLOOKUP($H100,output!$A$10:$N$2201,V$1-$J$1+2) -> 0
H101: Mpr multifamily (Billion euro) | J101: =VLOOKUP($H101,output!$A$10:$N$2201,J$1-$J$1+2) -> 0 | K101: =VLOOKUP($H101,output!$A$10:$N$2201,K$1-$J$1+2) -> 0.238 | L101: =VLOOKUP($H101,output!$A$10:$N$2201,L$1-$J$1+2) -> 0 | M101: =VLOOKUP($H101,output!$A$10:$N$2201,M$1-$J$1+2) -> 0 | N101: =VLOOKUP($H101,output!$A$10:$N$2201,N$1-$J$1+2) -> 0 | O101: =VLOOKUP($H101,output!$A$10:$N$2201,O$1-$J$1+2) -> 0 | P101: =VLOOKUP($H101,output!$A$10:$N$2201,P$1-$J$1+2) -> 0 | Q101: =VLOOKUP($H101,output!$A$10:$N$2201,Q$1-$J$1+2) -> 0 | ... V101: =VLOOKUP($H101,output!$A$10:$N$2201,V$1-$J$1+2) -> 0
H102: Mpr serenite low income (Billion euro) | J102: =VLOOKUP($H102,output!$A$10:$N$2201,J$1-$J$1+2) -> 0 | K102: =VLOOKUP($H102,output!$A$10:$N$2201,K$1-$J$1+2) -> 53.749 | L102: =VLOOKUP($H102,output!$A$10:$N$2201,L$1-$J$1+2) -> 0 | M102: =VLOOKUP($H102,output!$A$10:$N$2201,M$1-$J$1+2) -> 0 | N102: =VLOOKUP($H102,output!$A$10:$N$2201,N$1-$J$1+2) -> 0 | O102: =VLOOKUP($H102,output!$A$10:$N$2201,O$1-$J$1+2) -> 0 | P102: =VLOOKUP($H102,output!$A$10:$N$2201,P$1-$J$1+2) -> 0 | Q102: =VLOOKUP($H102,output!$A$10:$N$2201,Q$1-$J$1+2) -> 0 | ... V102: =VLOOKUP($H102,output!$A$10:$N$2201,V$1-$J$1+2) -> 0
H103: Mpr serenite high income (Billion euro) | J103: =VLOOKUP($H103,output!$A$10:$N$2201,J$1-$J$1+2) -> 0 | K103: =VLOOKUP($H103,output!$A$10:$N$2201,K$1-$J$1+2) -> 53.749 | L103: =VLOOKUP($H103,output!$A$10:$N$2201,L$1-$J$1+2) -> 0 | M103: =VLOOKUP($H103,output!$A$10:$N$2201,M$1-$J$1+2) -> 0 | N103: =VLOOKUP($H103,output!$A$10:$N$2201,N$1-$J$1+2) -> 0 | O103: =VLOOKUP($H103,output!$A$10:$N$2201,O$1-$J$1+2) -> 0 | P103: =VLOOKUP($H103,output!$A$10:$N$2201,P$1-$J$1+2) -> 0 | Q103: =VLOOKUP($H103,output!$A$10:$N$2201,Q$1-$J$1+2) -> 0 | ... V103: =VLOOKUP($H103,output!$A$10:$N$2201,V$1-$J$1+2) -> 0
H104: Over cap (Billion euro) | J104: =VLOOKUP($H104,output!$A$10:$N$2201,J$1-$J$1+2) -> 0 | K104: =VLOOKUP($H104,output!$A$10:$N$2201,K$1-$J$1+2) -> 0 | L104: =VLOOKUP($H104,output!$A$10:$N$2201,L$1-$J$1+2) -> 0 | M104: =VLOOKUP($H104,output!$A$10:$N$2201,M$1-$J$1+2) -> 0 | N104: =VLOOKUP($H104,output!$A$10:$N$2201,N$1-$J$1+2) -> 0 | O104: =VLOOKUP($H104,output!$A$10:$N$2201,O$1-$J$1+2) -> 0 | P104: =VLOOKUP($H104,output!$A$10:$N$2201,P$1-$J$1+2) -> 0 | Q104: =VLOOKUP($H104,output!$A$10:$N$2201,Q$1-$J$1+2) -> 0 | ... V104: =VLOOKUP($H104,output!$A$10:$N$2201,V$1-$J$1+2) -> 0
H106: Correction années historiques (I4CE) | I106: CEE | M106: 2 | N106: 2.2 | O106: 2.4 | P106: =P99 -> 0 | Q106: =Q99 -> 0 | R106: =R99 -> 0 | S106: =S99 -> 0 | T106: =T99 -> 0 | U106: =U99 -> 0 | V106: =V99 -> 0 | X106: =AVERAGE(O106:V106) -> 0.3
I107: MPR Efficacité | M107: 2 | N107: 2 | O107: 2.45 | P107: =P100 -> 0 | Q107: =Q100 -> 0 | R107: =R100 -> 0 | S107: =S100 -> 0 | T107: =T100 -> 0 | U107: =U100 -> 0 | V107: =V100 -> 0 | X107: =AVERAGE(O107:V107) -> 0.30625
I108: MPR Copro | M108: 0.15 | N108: 0.2 | O108: 0.25 | P108: =P101 -> 0 | Q108: =Q101 -> 0 | R108: =R101 -> 0 | S108: =S101 -> 0 | T108: =T101 -> 0 | U108: =U101 -> 0 | V108: =V101 -> 0 | X108: =AVERAGE(O108:V108) -> 0.03125
I109: MPR Performance | M109: 0.4 | N109: 0.5 | O109: 0.6 | P109: =P102+P103 -> 0 | Q109: =Q102+Q103 -> 0 | R109: =R102+R103 -> 0 | S109: =S102+S103 -> 0 | T109: =T102+T103 -> 0 | U109: =U102+U103 -> 0 | V109: =V102+V103 -> 0 | X109: =AVERAGE(O109:V109) -> 0.075
I110: Montant écrêté | M110: =M104 -> 0 | N110: =N104 -> 0 | O110: =O104 -> 0 | P110: =P104 -> 0 | Q110: =Q104 -> 0 | R110: =R104 -> 0 | S110: =S104 -> 0 | T110: =T104 -> 0 | ... V110: =V104 -> 0 | X110: =AVERAGE(O110:V110) -> 0
H112: MPR total | K112: =K107+K108+K109 -> 0 | L112: =L107+L108+L109 -> 0 | M112: =M107+M108+M109 -> 2.55 | N112: =N107+N108+N109 -> 2.7 | O112: =O107+O108+O109 -> 3.3 | P112: =P107+P108+P109 -> 0 | Q112: =Q107+Q108+Q109 -> 0 | R112: =R107+R108+R109 -> 0 | ... V112: =V107+V108+V109 -> 0 | X112: =AVERAGE(P112:V112) -> 0
H113: CEE | K113: =K106 -> 0 | L113: =L106 -> 0 | M113: =M106 -> 2 | N113: =N106 -> 2.2 | O113: =O106 -> 2.4 | P113: =P106 -> 0 | Q113: =Q106 -> 0 | R113: =R106 -> 0 | ... V113: =V106 -> 0 | X113: =AVERAGE(P113:V113) -> 0
H114: Soutien total | K114: =SUM(K106:K109) -> 0 | L114: =SUM(L106:L109) -> 0 | M114: =SUM(M106:M109) -> 4.55 | N114: =SUM(N106:N109) -> 4.9 | O114: =SUM(O106:O109) -> 5.7 | P114: =SUM(P106:P109) -> 0 | Q114: =SUM(Q106:Q109) -> 0 | R114: =SUM(R106:R109) -> 0 | ... V114: =SUM(V106:V109) -> 0 | X114: =AVERAGE(P114:V114) -> 0
H121: Replacement Floor (Thousand households) | J121: =VLOOKUP($H121,output!$A$10:$N$2201,J$1-$J$1+2) -> 0 | K121: =VLOOKUP($H121,output!$A$10:$N$2201,K$1-$J$1+2) -> 113.528 | L121: =VLOOKUP($H121,output!$A$10:$N$2201,L$1-$J$1+2) -> 70.798 | M121: =VLOOKUP($H121,output!$A$10:$N$2201,M$1-$J$1+2) -> 109.062 | N121: =VLOOKUP($H121,output!$A$10:$N$2201,N$1-$J$1+2) -> 116.565 | O121: =VLOOKUP($H121,output!$A$10:$N$2201,O$1-$J$1+2) -> 114.671 | P121: =VLOOKUP($H121,output!$A$10:$N$2201,P$1-$J$1+2) -> 107.732 | Q121: =VLOOKUP($H121,output!$A$10:$N$2201,Q$1-$J$1+2) -> 113.806 | ... V121: =VLOOKUP($H121,output!$A$10:$N$2201,V$1-$J$1+2) -> 140.471
H122: Replacement Roof (Thousand households) | J122: =VLOOKUP($H122,output!$A$10:$N$2201,J$1-$J$1+2) -> 0 | K122: =VLOOKUP($H122,output!$A$10:$N$2201,K$1-$J$1+2) -> 495.415 | L122: =VLOOKUP($H122,output!$A$10:$N$2201,L$1-$J$1+2) -> 352.848 | M122: =VLOOKUP($H122,output!$A$10:$N$2201,M$1-$J$1+2) -> 484.406 | N122: =VLOOKUP($H122,output!$A$10:$N$2201,N$1-$J$1+2) -> 523.278 | O122: =VLOOKUP($H122,output!$A$10:$N$2201,O$1-$J$1+2) -> 540.444 | P122: =VLOOKUP($H122,output!$A$10:$N$2201,P$1-$J$1+2) -> 529.286 | Q122: =VLOOKUP($H122,output!$A$10:$N$2201,Q$1-$J$1+2) -> 544.101 | ... V122: =VLOOKUP($H122,output!$A$10:$N$2201,V$1-$J$1+2) -> 654.734
H123: Replacement Wall (Thousand households) | J123: =VLOOKUP($H123,output!$A$10:$N$2201,J$1-$J$1+2) -> 0 | K123: =VLOOKUP($H123,output!$A$10:$N$2201,K$1-$J$1+2) -> 189.634 | L123: =VLOOKUP($H123,output!$A$10:$N$2201,L$1-$J$1+2) -> 112.911 | M123: =VLOOKUP($H123,output!$A$10:$N$2201,M$1-$J$1+2) -> 207.964 | N123: =VLOOKUP($H123,output!$A$10:$N$2201,N$1-$J$1+2) -> 216.444 | O123: =VLOOKUP($H123,output!$A$10:$N$2201,O$1-$J$1+2) -> 193.788 | P123: =VLOOKUP($H123,output!$A$10:$N$2201,P$1-$J$1+2) -> 168.732 | Q123: =VLOOKUP($H123,output!$A$10:$N$2201,Q$1-$J$1+2) -> 213.649 | ... V123: =VLOOKUP($H123,output!$A$10:$N$2201,V$1-$J$1+2) -> 205.539
H124: Replacement Windows (Thousand households) | J124: =VLOOKUP($H124,output!$A$10:$N$2201,J$1-$J$1+2) -> 0 | K124: =VLOOKUP($H124,output!$A$10:$N$2201,K$1-$J$1+2) -> 113.514 | L124: =VLOOKUP($H124,output!$A$10:$N$2201,L$1-$J$1+2) -> 81.351 | M124: =VLOOKUP($H124,output!$A$10:$N$2201,M$1-$J$1+2) -> 118.464 | N124: =VLOOKUP($H124,output!$A$10:$N$2201,N$1-$J$1+2) -> 127.539 | O124: =VLOOKUP($H124,output!$A$10:$N$2201,O$1-$J$1+2) -> 129.526 | P124: =VLOOKUP($H124,output!$A$10:$N$2201,P$1-$J$1+2) -> 124.749 | Q124: =VLOOKUP($H124,output!$A$10:$N$2201,Q$1-$J$1+2) -> 129.072 | ... V124: =VLOOKUP($H124,output!$A$10:$N$2201,V$1-$J$1+2) -> 165.654
H128: Cee heater Multi-family (Thousand households) | J128: =VLOOKUP($H128,output!$A$10:$N$2201,J$1-$J$1+2) -> 0 | K128: =VLOOKUP($H128,output!$A$10:$N$2201,K$1-$J$1+2) -> 813.561 | L128: =VLOOKUP($H128,output!$A$10:$N$2201,L$1-$J$1+2) -> 0 | M128: =VLOOKUP($H128,output!$A$10:$N$2201,M$1-$J$1+2) -> 0 | N128: =VLOOKUP($H128,output!$A$10:$N$2201,N$1-$J$1+2) -> 0 | O128: =VLOOKUP($H128,output!$A$10:$N$2201,O$1-$J$1+2) -> 0 | P128: =VLOOKUP($H128,output!$A$10:$N$2201,P$1-$J$1+2) -> 0 | Q128: =VLOOKUP($H128,output!$A$10:$N$2201,Q$1-$J$1+2) -> 0 | ... V128: =VLOOKUP($H128,output!$A$10:$N$2201,V$1-$J$1+2) -> 0
H129: Cee heater Single-family (Thousand households) | J129: =VLOOKUP($H129,output!$A$10:$N$2201,J$1-$J$1+2) -> 0 | K129: =VLOOKUP($H129,output!$A$10:$N$2201,K$1-$J$1+2) -> 994.22 | L129: =VLOOKUP($H129,output!$A$10:$N$2201,L$1-$J$1+2) -> 0 | M129: =VLOOKUP($H129,output!$A$10:$N$2201,M$1-$J$1+2) -> 0 | N129: =VLOOKUP($H129,output!$A$10:$N$2201,N$1-$J$1+2) -> 0 | O129: =VLOOKUP($H129,output!$A$10:$N$2201,O$1-$J$1+2) -> 0 | P129: =VLOOKUP($H129,output!$A$10:$N$2201,P$1-$J$1+2) -> 0 | Q129: =VLOOKUP($H129,output!$A$10:$N$2201,Q$1-$J$1+2) -> 0 | ... V129: =VLOOKUP($H129,output!$A$10:$N$2201,V$1-$J$1+2) -> 0
H130: Cee insulation Multi-family (Thousand households) | J130: =VLOOKUP($H130,output!$A$10:$N$2201,J$1-$J$1+2) -> 0 | K130: =VLOOKUP($H130,output!$A$10:$N$2201,K$1-$J$1+2) -> 157.842 | L130: =VLOOKUP($H130,output!$A$10:$N$2201,L$1-$J$1+2) -> 0 | M130: =VLOOKUP($H130,output!$A$10:$N$2201,M$1-$J$1+2) -> 0 | N130: =VLOOKUP($H130,output!$A$10:$N$2201,N$1-$J$1+2) -> 0 | O130: =VLOOKUP($H130,output!$A$10:$N$2201,O$1-$J$1+2) -> 0 | P130: =VLOOKUP($H130,output!$A$10:$N$2201,P$1-$J$1+2) -> 0 | Q130: =VLOOKUP($H130,output!$A$10:$N$2201,Q$1-$J$1+2) -> 0 | ... V130: =VLOOKUP($H130,output!$A$10:$N$2201,V$1-$J$1+2) -> 0
H131: Cee insulation Single-family (Thousand households) | J131: =VLOOKUP($H131,output!$A$10:$N$2201,J$1-$J$1+2) -> 0 | K131: =VLOOKUP($H131,output!$A$10:$N$2201,K$1-$J$1+2) -> 443.016 | L131: =VLOOKUP($H131,output!$A$10:$N$2201,L$1-$J$1+2) -> 0 | M131: =VLOOKUP($H131,output!$A$10:$N$2201,M$1-$J$1+2) -> 0 | N131: =VLOOKUP($H131,output!$A$10:$N$2201,N$1-$J$1+2) -> 0 | O131: =VLOOKUP($H131,output!$A$10:$N$2201,O$1-$J$1+2) -> 0 | P131: =VLOOKUP($H131,output!$A$10:$N$2201,P$1-$J$1+2) -> 0 | Q131: =VLOOKUP($H131,output!$A$10:$N$2201,Q$1-$J$1+2) -> 0 | ... V131: =VLOOKUP($H131,output!$A$10:$N$2201,V$1-$J$1+2) -> 0
H132: Mpr heater Multi-family (Thousand households) | J132: =VLOOKUP($H132,output!$A$10:$N$2201,J$1-$J$1+2) -> 0 | K132: =VLOOKUP($H132,output!$A$10:$N$2201,K$1-$J$1+2) -> 273.221 | L132: =VLOOKUP($H132,output!$A$10:$N$2201,L$1-$J$1+2) -> 0 | M132: =VLOOKUP($H132,output!$A$10:$N$2201,M$1-$J$1+2) -> 0 | N132: =VLOOKUP($H132,output!$A$10:$N$2201,N$1-$J$1+2) -> 0 | O132: =VLOOKUP($H132,output!$A$10:$N$2201,O$1-$J$1+2) -> 0 | P132: =VLOOKUP($H132,output!$A$10:$N$2201,P$1-$J$1+2) -> 0 | Q132: =VLOOKUP($H132,output!$A$10:$N$2201,Q$1-$J$1+2) -> 0 | ... V132: =VLOOKUP($H132,output!$A$10:$N$2201,V$1-$J$1+2) -> 0
H133: Mpr heater Single-family (Thousand households) | J133: =VLOOKUP($H133,output!$A$10:$N$2201,J$1-$J$1+2) -> 0 | K133: =VLOOKUP($H133,output!$A$10:$N$2201,K$1-$J$1+2) -> 674.952 | L133: =VLOOKUP($H133,output!$A$10:$N$2201,L$1-$J$1+2) -> 0 | M133: =VLOOKUP($H133,output!$A$10:$N$2201,M$1-$J$1+2) -> 0 | N133: =VLOOKUP($H133,output!$A$10:$N$2201,N$1-$J$1+2) -> 0 | O133: =VLOOKUP($H133,output!$A$10:$N$2201,O$1-$J$1+2) -> 0 | P133: =VLOOKUP($H133,output!$A$10:$N$2201,P$1-$J$1+2) -> 0 | Q133: =VLOOKUP($H133,output!$A$10:$N$2201,Q$1-$J$1+2) -> 0 | ... V133: =VLOOKUP($H133,output!$A$10:$N$2201,V$1-$J$1+2) -> 0
H134: Mpr insulation Single-family (Thousand households) | J134: =VLOOKUP($H134,output!$A$10:$N$2201,J$1-$J$1+2) -> 0 | K134: =VLOOKUP($H134,output!$A$10:$N$2201,K$1-$J$1+2) -> 308.777 | L134: =VLOOKUP($H134,output!$A$10:$N$2201,L$1-$J$1+2) -> 0 | M134: =VLOOKUP($H134,output!$A$10:$N$2201,M$1-$J$1+2) -> 0 | N134: =VLOOKUP($H134,output!$A$10:$N$2201,N$1-$J$1+2) -> 0 | O134: =VLOOKUP($H134,output!$A$10:$N$2201,O$1-$J$1+2) -> 0 | P134: =VLOOKUP($H134,output!$A$10:$N$2201,P$1-$J$1+2) -> 0 | Q134: =VLOOKUP($H134,output!$A$10:$N$2201,Q$1-$J$1+2) -> 0 | ... V134: =VLOOKUP($H134,output!$A$10:$N$2201,V$1-$J$1+2) -> 0
H135: Mpr multifamily (Thousand households) | J135: =VLOOKUP($H135,output!$A$10:$N$2201,J$1-$J$1+2) -> 0 | K135: =VLOOKUP($H135,output!$A$10:$N$2201,K$1-$J$1+2) -> 149.137 | L135: =VLOOKUP($H135,output!$A$10:$N$2201,L$1-$J$1+2) -> 0 | M135: =VLOOKUP($H135,output!$A$10:$N$2201,M$1-$J$1+2) -> 0 | N135: =VLOOKUP($H135,output!$A$10:$N$2201,N$1-$J$1+2) -> 0 | O135: =VLOOKUP($H135,output!$A$10:$N$2201,O$1-$J$1+2) -> 0 | P135: =VLOOKUP($H135,output!$A$10:$N$2201,P$1-$J$1+2) -> 0 | Q135: =VLOOKUP($H135,output!$A$10:$N$2201,Q$1-$J$1+2) -> 0 | ... V135: =VLOOKUP($H135,output!$A$10:$N$2201,V$1-$J$1+2) -> 0
... H137: Mpr serenite low income (Thousand households) | J137: =VLOOKUP($H137,output!$A$10:$N$2201,J$1-$J$1+2) -> 0 | K137: =VLOOKUP($H137,output!$A$10:$N$2201,K$1-$J$1+2) -> 53.749 | L137: =VLOOKUP($H137,output!$A$10:$N$2201,L$1-$J$1+2) -> 0 | M137: =VLOOKUP($H137,output!$A$10:$N$2201,M$1-$J$1+2) -> 0 | N137: =VLOOKUP($H137,output!$A$10:$N$2201,N$1-$J$1+2) -> 0 | O137: =VLOOKUP($H137,output!$A$10:$N$2201,O$1-$J$1+2) -> 0 | P137: =VLOOKUP($H137,output!$A$10:$N$2201,P$1-$J$1+2) -> 0 | Q137: =VLOOKUP($H137,output!$A$10:$N$2201,Q$1-$J$1+2) -> 0 | ... V137: =VLOOKUP($H137,output!$A$10:$N$2201,V$1-$J$1+2) -> 0
H139: CEE chauffage | J139: =J128+J129 -> 0 | K139: =K128+K129 -> 1807.781 | L139: =L128+L129 -> 0 | M139: =M128+M129 -> 0 | N139: =N128+N129 -> 0 | O139: =O128+O129 -> 0 | P139: =P128+P129 -> 0 | Q139: =Q128+Q129 -> 0 | ... V139: =V128+V129 -> 0
H140: CEE isolation | J140: =J130+J131 -> 0 | K140: =K130+K131 -> 600.858 | L140: =L130+L131 -> 0 | M140: =M130+M131 -> 0 | N140: =N130+N131 -> 0 | O140: =O130+O131 -> 0 | P140: =P130+P131 -> 0 | Q140: =Q130+Q131 -> 0 | ... V140: =V130+V131 -> 0
H141: MPR Efficacité chauffage | J141: =J132+J133 -> 0 | K141: =K132+K133 -> 948.173 | L141: =L132+L133 -> 0 | M141: =M132+M133 -> 0 | N141: =N132+N133 -> 0 | O141: =O132+O133 -> 0 | P141: =P132+P133 -> 0 | Q141: =Q132+Q133 -> 0 | ... V141: =V132+V133 -> 0
H142: MPR Efficacité isolation | J142: =J134 -> 0 | K142: =K134 -> 308.777 | L142: =L134 -> 0 | M142: =M134 -> 0 | N142: =N134 -> 0 | O142: =O134 -> 0 | P142: =P134 -> 0 | Q142: =Q134 -> 0 | ... V142: =V134 -> 0
H143: MPR Performance | J143: =J136+J137 -> 0 | K143: =K136+K137 -> 107.498 | L143: =L136+L137 -> 0 | M143: =M136+M137 -> 0 | N143: =N136+N137 -> 0 | O143: =O136+O137 -> 0 | P143: =P136+P137 -> 0 | Q143: =Q136+Q137 -> 0 | ... V143: =V136+V137 -> 0
H144: MPR Copro | J144: =J135 -> 0 | K144: =K135 -> 149.137 | L144: =L135 -> 0 | M144: =M135 -> 0 | N144: =N135 -> 0 | O144: =O135 -> 0 | P144: =P135 -> 0 | Q144: =Q135 -> 0 | ... V144: =V135 -> 0

Sheet figures 2050
J1: 2018 | K1: 2019 | L1: 2020 | M1: 2021 | N1: 2022 | O1: 2023 | P1: 2024 | Q1: 2025 | R1: 2026 | S1: 2027 | T1: 2028 | U1: 2029 | V1: 2030 | W1: 2031 | X1: 2032 | Y1: 2033 | Z1: 2034 | AA1: 2035 | AB1: 2036 | AC1: 2037 | AD1: 2038 | AE1: 2039 | AF1: 2040 | AG1: 2041 | AH1: 2042 | AI1: 2043 | AJ1: 2044 | AK1: 2045 | AL1: 2046 | AM1: 2047 | AN1: 2048 | AO1: 2049 | AP1: 2050
H2: Emissions (calculées par le modèle)
H3: Emission Natural gas (MtCO2) | I3: Emissions du gaz (MtCO2) | J3: =VLOOKUP($H3,output!$A$10:$AH$2201,J$1-$J$1+2) -> 20.02 | K3: =VLOOKUP($H3,output!$A$10:$AH$2201,K$1-$J$1+2) -> 19.601 | L3: =VLOOKUP($H3,output!$A$10:$AH$2201,L$1-$J$1+2) -> 19.575 | M3: =VLOOKUP($H3,output!$A$10:$AH$2201,M$1-$J$1+2) -> 19.088 | N3: =VLOOKUP($H3,output!$A$10:$AH$2201,N$1-$J$1+2) -> 18.257 | O3: =VLOOKUP($H3,output!$A$10:$AH$2201,O$1-$J$1+2) -> 17.594 | P3: =VLOOKUP($H3,output!$A$10:$AH$2201,P$1-$J$1+2) -> 16.811 | Q3: =VLOOKUP($H3,output!$A$10:$AH$2201,Q$1-$J$1+2) -> 15.886 | ... AP3: =VLOOKUP($H3,output!$A$10:$AH$2201,AP$1-$J$1+2) -> 0
H4: Emission Oil fuel (MtCO2) | I4: Emissions du fioul (MtCO2) | J4: =VLOOKUP($H4,output!$A$10:$AH$2201,J$1-$J$1+2) -> 10.044 | K4: =VLOOKUP($H4,output!$A$10:$AH$2201,K$1-$J$1+2) -> 9.04 | L4: =VLOOKUP($H4,output!$A$10:$AH$2201,L$1-$J$1+2) -> 8.182 | M4: =VLOOKUP($H4,output!$A$10:$AH$2201,M$1-$J$1+2) -> 7.23 | N4: =VLOOKUP($H4,output!$A$10:$AH$2201,N$1-$J$1+2) -> 6.14 | O4: =VLOOKUP($H4,output!$A$10:$AH$2201,O$1-$J$1+2) -> 5.237 | P4: =VLOOKUP($H4,output!$A$10:$AH$2201,P$1-$J$1+2) -> 4.379 | Q4: =VLOOKUP($H4,output!$A$10:$AH$2201,Q$1-$J$1+2) -> 3.559 | ... AP4: =VLOOKUP($H4,output!$A$10:$AH$2201,AP$1-$J$1+2) -> 0
H5: Emission Electricity (MtCO2) | I5: Emissions de l'électricité (MtCO2) | J5: =VLOOKUP($H5,output!$A$10:$AH$2201,J$1-$J$1+2) -> 4.021 | K5: =VLOOKUP($H5,output!$A$10:$AH$2201,K$1-$J$1+2) -> 3.938 | L5: =VLOOKUP($H5,output!$A$10:$AH$2201,L$1-$J$1+2) -> 3.923 | M5: =VLOOKUP($H5,output!$A$10:$AH$2201,M$1-$J$1+2) -> 3.908 | N5: =VLOOKUP($H5,output!$A$10:$AH$2201,N$1-$J$1+2) -> 3.915 | O5: =VLOOKUP($H5,output!$A$10:$AH$2201,O$1-$J$1+2) -> 3.917 | P5: =VLOOKUP($H5,output!$A$10:$AH$2201,P$1-$J$1+2) -> 3.915 | Q5: =VLOOKUP($H5,output!$A$10:$AH$2201,Q$1-$J$1+2) -> 3.889 | ... AP5: =VLOOKUP($H5,output!$A$10:$AH$2201,AP$1-$J$1+2) -> 0
I7: Directes | J7: =J3+J4 -> 30.064 | K7: =K3+K4 -> 28.641 | L7: =L3+L4 -> 27.757 | M7: =M3+M4 -> 26.318 | N7: =N3+N4 -> 24.397 | O7: =O3+O4 -> 22.831 | P7: =P3+P4 -> 21.19 | Q7: =Q3+Q4 -> 19.445 | ... AP7: =AP3+AP4 -> 0
I8: Gain annuel | K8: =J7-K7 -> 1.423 | L8: =K7-L7 -> 0.884 | M8: =L7-M7 -> 1.439 | N8: =M7-N7 -> 1.921 | O8: =N7-O7 -> 1.566 | P8: =O7-P7 -> 1.641 | Q8: =P7-Q7 -> 1.745 | R8: =Q7-R7 -> 1.682 | ... AP8: =AO7-AP7 -> 0
H10: Hypothèse de sobriété (baisse température de consigne & individualisation frais en collectif) | J10: 1 | K10: 1 | L10: 1 | M10: 1 | N10: 1 | O10: 1 | P10: 0.99 | Q10: 0.98 | R10: 0.97 | S10: 0.96 | T10: 0.95 | U10: 0.94 | V10: 0.93 | W10: =$V10-0.03*(W1-$V1)/20 -> 0.9285 | X10: =$V10-0.03*(X1-$V1)/20 -> 0.927 | Y10: =$V10-0.03*(Y1-$V1)/20 -> 0.9255 | Z10: =$V10-0.03*(Z1-$V1)/20 -> 0.924 | AA10: =$V10-0.03*(AA1-$V1)/20 -> 0.9225 | AB10: =$V10-0.03*(AB1-$V1)/20 -> 0.921 | AC10: =$V10-0.03*(AC1-$V1)/20 -> 0.9195 | AD10: =$V10-0.03*(AD1-$V1)/20 -> 0.918 | ... AO10: =$V10-0.03*(AO1-$V1)/20 -> 0.9015 | AP10: 0.9
H11: Impact du changement climatique (RCP2.6) | J11: 1 | K11: 1 | L11: 1 | M11: 0.99 | N11: 0.98 | O11: 0.97 | P11: 0.96 | Q11: 0.95 | R11: 0.94 | S11: 0.93 | T11: 0.92 | U11: 0.915 | V11: 0.91 | W11: 0.9 | X11: 0.9 | Y11: 0.89 | Z11: 0.89 | AA11: 0.88 | AB11: 0.88 | AC11: 0.88 | AD11: 0.87 | AE11: 0.87 | AF11: 0.87 | AG11: 0.87 | AH11: 0.87 | AI11: 0.87 | AJ11: 0.865 | AK11: 0.865 | AL11: 0.865 | AM11: 0.865 | AN11: 0.86 | AO11: 0.86 | AP11: 0.86
H12: Variation de la demande induite | J12: =J10*J11 -> 1 | K12: =K10*K11 -> 1 | L12: =L10*L11 -> 1 | M12: =M10*M11 -> 0.99 | N12: =N10*N11 -> 0.98 | O12: =O10*O11 -> 0.97 | P12: =P10*P11 -> 0.9504 | Q12: =Q10*Q11 -> 0.931 | ... AP12: =AP10*AP11 -> 0.774
H14: Emissions (incluant sobriété et CC)
H15: Emissions du gaz (MtCO2) | J15: =J3*J$12 -> 20.02 | K15: =K3*K$12 -> 19.601 | L15: =L3*L$12 -> 19.575 | M15: =M3*M$12 -> 18.89712 | N15: =N3*N$12 -> 17.89186 | O15: =O3*O$12 -> 17.06618 | P15: =P3*P$12 -> 15.977174 | Q15: =Q3*Q$12 -> 14.789866 | ... AP15: =AP3*AP$12 -> 0
H16: Emissions du fioul (MtCO2) | J16: =J4*J$12 -> 10.044 | K16: =K4*K$12 -> 9.04 | L16: =L4*L$12 -> 8.182 | M16: =M4*M$12 -> 7.1577 | N16: =N4*N$12 -> 6.0172 | O16: =O4*O$12 -> 5.07989 | P16: =P4*P$12 -> 4.1618016 | Q16: =Q4*Q$12 -> 3.313429 | ... AP16: =AP4*AP$12 -> 0
H17: Emissions de l'électricité (MtCO2) | J17: =J5*J$12 -> 4.021 | K17: =K5*K$12 -> 3.938 | L17: =L5*L$12 -> 3.923 | M17: =M5*M$12 -> 3.86892 | N17: =N5*N$12 -> 3.8367 | O17: =O5*O$12 -> 3.79949 | P17: =P5*P$12 -> 3.720816 | Q17: =Q5*Q$12 -> 3.620659 | ... AP17: =AP5*AP$12 -> 0
I19: Directes | J19: =SUM(J15:J16) -> 30.064 | K19: =SUM(K15:K16) -> 28.641 | L19: =SUM(L15:L16) -> 27.757 | M19: =SUM(M15:M16) -> 26.05482 | N19: =SUM(N15:N16) -> 23.90906 | O19: =SUM(O15:O16) -> 22.14607 | P19: =SUM(P15:P16) -> 20.138976 | Q19: =SUM(Q15:Q16) -> 18.103295 | ... AP19: =SUM(AP15:AP16) -> 0
I20: Gain annuel | K20: =K19-J19 -> -1.423 | L20: =L19-K19 -> -0.884 | M20: =M19-L19 -> -1.70218 | N20: =N19-M19 -> -2.14576 | O20: =O19-N19 -> -1.76299 | P20: =P19-O19 -> -2.007094 | Q20: =Q19-P19 -> -2.035681 | R20: =R19-Q19 -> -1.9069916 | ... AP20: =AP19-AO19 -> 0
I21: Réduction vs 2019 | L21: =L19/$K19-1 -> -0.030864844 | M21: =M19/$K19-1 -> -0.090296428 | N21: =N19/$K19-1 -> -0.1652156 | O21: =O19/$K19-1 -> -0.22677036 | P21: =P19/$K19-1 -> -0.29684802 | Q21: =Q19/$K19-1 -> -0.36792378 | R21: =R19/$K19-1 -> -0.43450636 | S21: =S19/$K19-1 -> -0.50052951 | ... AP21: =AP19/$K19-1 -> -1
H23: Stock A (Million) | I23: A | J23: =VLOOKUP($H23,output!$A$10:$AH$2201,J$1-$J$1+2) -> 0.397 | K23: =VLOOKUP($H23,output!$A$10:$AH$2201,K$1-$J$1+2) -> 0.545 | L23: =VLOOKUP($H23,output!$A$10:$AH$2201,L$1-$J$1+2) -> 0.757 | M23: =VLOOKUP($H23,output!$A$10:$AH$2201,M$1-$J$1+2) -> 0.969 | N23: =VLOOKUP($H23,output!$A$10:$AH$2201,N$1-$J$1+2) -> 1.182 | O23: =VLOOKUP($H23,output!$A$10:$AH$2201,O$1-$J$1+2) -> 1.395 | P23: =VLOOKUP($H23,output!$A$10:$AH$2201,P$1-$J$1+2) -> 1.606 | Q23: =VLOOKUP($H23,output!$A$10:$AH$2201,Q$1-$J$1+2) -> 1.757 | ... AP23: =VLOOKUP($H23,output!$A$10:$AH$2201,AP$1-$J$1+2) -> 0
H24: Stock B (Million) | I24: B | J24: =VLOOKUP($H24,output!$A$10:$AH$2201,J$1-$J$1+2) -> 2.156 | K24: =VLOOKUP($H24,output!$A$10:$AH$2201,K$1-$J$1+2) -> 2.435 | L24: =VLOOKUP($H24,output!$A$10:$AH$2201,L$1-$J$1+2) -> 2.686 | M24: =VLOOKUP($H24,output!$A$10:$AH$2201,M$1-$J$1+2) -> 2.947 | N24: =VLOOKUP($H24,output!$A$10:$AH$2201,N$1-$J$1+2) -> 3.224 | O24: =VLOOKUP($H24,output!$A$10:$AH$2201,O$1-$J$1+2) -> 3.519 | P24: =VLOOKUP($H24,output!$A$10:$AH$2201,P$1-$J$1+2) -> 3.834 | Q24: =VLOOKUP($H24,output!$A$10:$AH$2201,Q$1-$J$1+2) -> 4.141 | ... AP24: =VLOOKUP($H24,output!$A$10:$AH$2201,AP$1-$J$1+2) -> 0
H25: Stock C (Million) | I25: C | J25: =VLOOKUP($H25,output!$A$10:$AH$2201,J$1-$J$1+2) -> 5.55 | K25: =VLOOKUP($H25,output!$A$10:$AH$2201,K$1-$J$1+2) -> 6.018 | L25: =VLOOKUP($H25,output!$A$10:$AH$2201,L$1-$J$1+2) -> 6.359 | M25: =VLOOKUP($H25,output!$A$10:$AH$2201,M$1-$J$1+2) -> 6.835 | N25: =VLOOKUP($H25,output!$A$10:$AH$2201,N$1-$J$1+2) -> 7.326 | O25: =VLOOKUP($H25,output!$A$10:$AH$2201,O$1-$J$1+2) -> 7.843 | P25: =VLOOKUP($H25,output!$A$10:$AH$2201,P$1-$J$1+2) -> 8.377 | Q25: =VLOOKUP($H25,output!$A$10:$AH$2201,Q$1-$J$1+2) -> 8.945 | ... AP25: =VLOOKUP($H25,output!$A$10:$AH$2201,AP$1-$J$1+2) -> 0
H26: Stock D (Million) | I26: D | J26: =VLOOKUP($H26,output!$A$10:$AH$2201,J$1-$J$1+2) -> 12.774 | K26: =VLOOKUP($H26,output!$A$10:$AH$2201,K$1-$J$1+2) -> 12.688 | L26: =VLOOKUP($H26,output!$A$10:$AH$2201,L$1-$J$1+2) -> 12.639 | M26: =VLOOKUP($H26,output!$A$10:$AH$2201,M$1-$J$1+2) -> 12.527 | N26: =VLOOKUP($H26,output!$A$10:$AH$2201,N$1-$J$1+2) -> 12.387 | O26: =VLOOKUP($H26,output!$A$10:$AH$2201,O$1-$J$1+2) -> 12.168 | P26: =VLOOKUP($H26,output!$A$10:$AH$2201,P$1-$J$1+2) -> 11.876 | Q26: =VLOOKUP($H26,output!$A$10:$AH$2201,Q$1-$J$1+2) -> 11.562 | ... AP26: =VLOOKUP($H26,output!$A$10:$AH$2201,AP$1-$J$1+2) -> 0
H27: Stock E (Million) | I27: E | J27: =VLOOKUP($H27,output!$A$10:$AH$2201,J$1-$J$1+2) -> 5.024 | K27: =VLOOKUP($H27,output!$A$10:$AH$2201,K$1-$J$1+2) -> 4.841 | L27: =VLOOKUP($H27,output!$A$10:$AH$2201,L$1-$J$1+2) -> 4.647 | M27: =VLOOKUP($H27,output!$A$10:$AH$2201,M$1-$J$1+2) -> 4.446 | N27: =VLOOKUP($H27,output!$A$10:$AH$2201,N$1-$J$1+2) -> 4.229 | O27: =VLOOKUP($H27,output!$A$10:$AH$2201,O$1-$J$1+2) -> 4.001 | P27: =VLOOKUP($H27,output!$A$10:$AH$2201,P$1-$J$1+2) -> 3.77 | Q27: =VLOOKUP($H27,output!$A$10:$AH$2201,Q$1-$J$1+2) -> 3.54 | ... AP27: =VLOOKUP($H27,output!$A$10:$AH$2201,AP$1-$J$1+2) -> 0
H28: Stock F (Million) | I28: F | J28: =VLOOKUP($H28,output!$A$10:$AH$2201,J$1-$J$1+2) -> 2.927 | K28: =VLOOKUP($H28,output!$A$10:$AH$2201,K$1-$J$1+2) -> 2.755 | L28: =VLOOKUP($H28,output!$A$10:$AH$2201,L$1-$J$1+2) -> 2.62 | M28: =VLOOKUP($H28,output!$A$10:$AH$2201,M$1-$J$1+2) -> 2.385 | N28: =VLOOKUP($H28,output!$A$10:$AH$2201,N$1-$J$1+2) -> 2.17 | O28: =VLOOKUP($H28,output!$A$10:$AH$2201,O$1-$J$1+2) -> 1.984 | P28: =VLOOKUP($H28,output!$A$10:$AH$2201,P$1-$J$1+2) -> 1.823 | Q28: =VLOOKUP($H28,output!$A$10:$AH$2201,Q$1-$J$1+2) -> 1.613 | ... AP28: =VLOOKUP($H28,output!$A$10:$AH$2201,AP$1-$J$1+2) -> 0
H29: Stock G (Million) | I29: G | J29: =VLOOKUP($H29,output!$A$10:$AH$2201,J$1-$J$1+2) -> 1.398 | K29: =VLOOKUP($H29,output!$A$10:$AH$2201,K$1-$J$1+2) -> 1.162 | L29: =VLOOKUP($H29,output!$A$10:$AH$2201,L$1-$J$1+2) -> 1.006 | M29: =VLOOKUP($H29,output!$A$10:$AH$2201,M$1-$J$1+2) -> 0.872 | N29: =VLOOKUP($H29,output!$A$10:$AH$2201,N$1-$J$1+2) -> 0.729 | O29: =VLOOKUP($H29,output!$A$10:$AH$2201,O$1-$J$1+2) -> 0.605 | P29: =VLOOKUP($H29,output!$A$10:$AH$2201,P$1-$J$1+2) -> 0.497 | Q29: =VLOOKUP($H29,output!$A$10:$AH$2201,Q$1-$J$1+2) -> 0.403 | ... AP29: =VLOOKUP($H29,output!$A$10:$AH$2201,AP$1-$J$1+2) -> 0
I31: Passoires | J31: =J28+J29 -> 4.325 | K31: =K28+K29 -> 3.917 | L31: =L28+L29 -> 3.626 | M31: =M28+M29 -> 3.257 | N31: =N28+N29 -> 2.899 | O31: =O28+O29 -> 2.589 | P31: =P28+P29 -> 2.32 | Q31: =Q28+Q29 -> 2.016 | ... V31: =V28+V29 -> 0.905 | W31: =V31/K31-1 -> -0.76895583
AA34: Fioul pour correction | AC34: =AC38*AC$12 -> 0 | AD34: =AD38*AD$12 -> 0 | AE34: =AE38*AE$12 -> 0 | AF34: =AF38*AF$12 -> 0 | AG34: =AG38*AG$12 -> 0 | AH34: =AH38*AH$12 -> 0 | AI34: =AI38*AI$12 -> 0 | AJ34: =AJ38*AJ$12 -> 0 | ... AP34: =AP38*AP$12 -> 0
H35: Consommation (calculée par le modèle)
H36: Consumption Heating (TWh) | I36: Chauffage urbain | J36: =VLOOKUP($H36,output!$A$10:$AH$2201,J$1-$J$1+2) -> 11.458 | K36: =VLOOKUP($H36,output!$A$10:$AH$2201,K$1-$J$1+2) -> 12.433 | L36: =VLOOKUP($H36,output!$A$10:$AH$2201,L$1-$J$1+2) -> 12.517 | M36: =VLOOKUP($H36,output!$A$10:$AH$2201,M$1-$J$1+2) -> 14.035 | N36: =VLOOKUP($H36,output!$A$10:$AH$2201,N$1-$J$1+2) -> 15.012 | O36: =VLOOKUP($H36,output!$A$10:$AH$2201,O$1-$J$1+2) -> 17.038 | P36: =VLOOKUP($H36,output!$A$10:$AH$2201,P$1-$J$1+2) -> 20.233 | Q36: =VLOOKUP($H36,output!$A$10:$AH$2201,Q$1-$J$1+2) -> 24.458 | ... AP36: =VLOOKUP($H36,output!$A$10:$AH$2201,AP$1-$J$1+2) -> 0 | AQ36: Chauffage urbain
H37: Consumption Natural gas (TWh) | I37: Gaz | J37: =VLOOKUP($H37,output!$A$10:$AH$2201,J$1-$J$1+2) -> 91 | K37: =VLOOKUP($H37,output!$A$10:$AH$2201,K$1-$J$1+2) -> 89.097 | L37: =VLOOKUP($H37,output!$A$10:$AH$2201,L$1-$J$1+2) -> 88.979 | M37: =VLOOKUP($H37,output!$A$10:$AH$2201,M$1-$J$1+2) -> 86.764 | N37: =VLOOKUP($H37,output!$A$10:$AH$2201,N$1-$J$1+2) -> 82.988 | O37: =VLOOKUP($H37,output!$A$10:$AH$2201,O$1-$J$1+2) -> 79.972 | P37: =VLOOKUP($H37,output!$A$10:$AH$2201,P$1-$J$1+2) -> 76.412 | Q37: =VLOOKUP($H37,output!$A$10:$AH$2201,Q$1-$J$1+2) -> 72.209 | ... AP37: =VLOOKUP($H37,output!$A$10:$AH$2201,AP$1-$J$1+2) -> 0 | AQ37: Gaz
H38: Consumption Oil fuel (TWh) | I38: Fioul | J38: =VLOOKUP($H38,output!$A$10:$AH$2201,J$1-$J$1+2) -> 31 | K38: =VLOOKUP($H38,output!$A$10:$AH$2201,K$1-$J$1+2) -> 27.903 | L38: =VLOOKUP($H38,output!$A$10:$AH$2201,L$1-$J$1+2) -> 25.252 | M38: =VLOOKUP($H38,output!$A$10:$AH$2201,M$1-$J$1+2) -> 22.315 | N38: =VLOOKUP($H38,output!$A$10:$AH$2201,N$1-$J$1+2) -> 18.951 | O38: =VLOOKUP($H38,output!$A$10:$AH$2201,O$1-$J$1+2) -> 16.163 | P38: =VLOOKUP($H38,output!$A$10:$AH$2201,P$1-$J$1+2) -> 13.514 | Q38: =VLOOKUP($H38,output!$A$10:$AH$2201,Q$1-$J$1+2) -> 10.984 | ... AP38: =VLOOKUP($H38,output!$A$10:$AH$2201,AP$1-$J$1+2) -> 0 | AQ38: Fioul
H39: Consumption Wood fuel (TWh) | I39: Bois | J39: =VLOOKUP($H39,output!$A$10:$AH$2201,J$1-$J$1+2) -> 76.103 | K39: =VLOOKUP($H39,output!$A$10:$AH$2201,K$1-$J$1+2) -> 74.564 | L39: =VLOOKUP($H39,output!$A$10:$AH$2201,L$1-$J$1+2) -> 73.541 | M39: =VLOOKUP($H39,output!$A$10:$AH$2201,M$1-$J$1+2) -> 71.848 | N39: =VLOOKUP($H39,output!$A$10:$AH$2201,N$1-$J$1+2) -> 69.645 | O39: =VLOOKUP($H39,output!$A$10:$AH$2201,O$1-$J$1+2) -> 67.831 | P39: =VLOOKUP($H39,output!$A$10:$AH$2201,P$1-$J$1+2) -> 65.93 | Q39: =VLOOKUP($H39,output!$A$10:$AH$2201,Q$1-$J$1+2) -> 63.778 | ... AP39: =VLOOKUP($H39,output!$A$10:$AH$2201,AP$1-$J$1+2) -> 0 | AQ39: Bois
H40: Consumption Heat pump (TWh) | I40: Electricité (pompe à chaleur) | J40: =VLOOKUP($H40,output!$A$10:$AH$2201,J$1-$J$1+2) -> 6.984 | K40: =VLOOKUP($H40,output!$A$10:$AH$2201,K$1-$J$1+2) -> 9.027 | L40: =VLOOKUP($H40,output!$A$10:$AH$2201,L$1-$J$1+2) -> 10.851 | M40: =VLOOKUP($H40,output!$A$10:$AH$2201,M$1-$J$1+2) -> 12.635 | N40: =VLOOKUP($H40,output!$A$10:$AH$2201,N$1-$J$1+2) -> 14.589 | O40: =VLOOKUP($H40,output!$A$10:$AH$2201,O$1-$J$1+2) -> 16.461 | P40: =VLOOKUP($H40,output!$A$10:$AH$2201,P$1-$J$1+2) -> 18.247 | Q40: =VLOOKUP($H40,output!$A$10:$AH$2201,Q$1-$J$1+2) -> 19.873 | ... AP40: =VLOOKUP($H40,output!$A$10:$AH$2201,AP$1-$J$1+2) -> 0 | AQ40: Electricité (pompe à chaleur)
H41: Consumption Direct electric (TWh) | I41: Electricité (joule) | J41: =VLOOKUP($H41,output!$A$10:$AH$2201,J$1-$J$1+2) -> 43.913 | K41: =VLOOKUP($H41,output!$A$10:$AH$2201,K$1-$J$1+2) -> 40.822 | L41: =VLOOKUP($H41,output!$A$10:$AH$2201,L$1-$J$1+2) -> 38.813 | M41: =VLOOKUP($H41,output!$A$10:$AH$2201,M$1-$J$1+2) -> 36.839 | N41: =VLOOKUP($H41,output!$A$10:$AH$2201,N$1-$J$1+2) -> 34.963 | O41: =VLOOKUP($H41,output!$A$10:$AH$2201,O$1-$J$1+2) -> 33.127 | P41: =VLOOKUP($H41,output!$A$10:$AH$2201,P$1-$J$1+2) -> 31.307 | Q41: =VLOOKUP($H41,output!$A$10:$AH$2201,Q$1-$J$1+2) -> 29.36 | ... AP41: =VLOOKUP($H41,output!$A$10:$AH$2201,AP$1-$J$1+2) -> 0 | AQ41: Electricité (joule)
I43: total | J43: =SUM(J36:J41) -> 260.458 | K43: =SUM(K36:K41) -> 253.846 | L43: =SUM(L36:L41) -> 249.953 | M43: =SUM(M36:M41) -> 244.436 | N43: =SUM(N36:N41) -> 236.148 | O43: =SUM(O36:O41) -> 230.592 | P43: =SUM(P36:P41) -> 225.643 | Q43: =SUM(Q36:Q41) -> 220.662 | ... AP43: =SUM(AP36:AP41) -> 0
H44: Consommation (incluant sobriété et CC)
H45: Chauffage urbain | J45: =J36*J$12 -> 11.458 | K45: =K36*K$12 -> 12.433 | L45: =L36*L$12 -> 12.517 | M45: =M36*M$12 -> 13.89465 | N45: =N36*N$12 -> 14.71176 | O45: =O36*O$12 -> 16.52686 | P45: =P36*P$12 -> 19.229443 | Q45: =Q36*Q$12 -> 22.770398 | ... AP45: =AP36*AP$12 -> 0 | AQ45: Chauffage urbain
H46: Gaz | J46: =J37*J$12 -> 91 | K46: =K37*K$12 -> 89.097 | L46: =L37*L$12 -> 88.979 | M46: =M37*M$12 -> 85.89636 | N46: =N37*N$12 -> 81.32824 | O46: =O37*O$12 -> 77.57284 | P46: =P37*P$12 -> 72.621965 | Q46: =Q37*Q$12 -> 67.226579 | ... AP46: =AP37*AP$12 -> 0 | AQ46: Gaz
H47: Fioul | J47: =J38*J$12 -> 31 | K47: =K38*K$12 -> 27.903 | L47: =L38*L$12 -> 25.252 | M47: =M38*M$12 -> 22.09185 | N47: =N38*N$12 -> 18.57198 | O47: =O38*O$12 -> 15.67811 | P47: =P38*P$12 -> 12.843706 | Q47: =Q38*Q$12 -> 10.226104 | ... AC47: =AC38*AC$12 -> 0 | AD47: 1 | AE47: 0.5 | AF47: 0 | AG47: 0 | AH47: 0 | AI47: 0 | AJ47: 0 | AK47: 0 | AL47: 0 | AM47: 0 | AN47: 0 | AO47: 0 | AP47: 0 | AQ47: Fioul
H48: Bois | J48: =J39*J$12 -> 76.103 | K48: =K39*K$12 -> 74.564 | L48: =L39*L$12 -> 73.541 | M48: =M39*M$12 -> 71.12952 | N48: =N39*N$12 -> 68.2521 | O48: =O39*O$12 -> 65.79607 | P48: =P39*P$12 -> 62.659872 | Q48: =Q39*Q$12 -> 59.377318 | ... AP48: =AP39*AP$12 -> 0 | AQ48: Bois
H49: Electricité (pompe à chaleur) | J49: =J40*J$12 -> 6.984 | K49: =K40*K$12 -> 9.027 | L49: =L40*L$12 -> 10.851 | M49: =M40*M$12 -> 12.50865 | N49: =N40*N$12 -> 14.29722 | O49: =O40*O$12 -> 15.96717 | P49: =P40*P$12 -> 17.341949 | Q49: =Q40*Q$12 -> 18.501763 | ... AC49: =AC40*AC$12 -> 30.235073 | AD49: =AD40*AD$12+(AD34-AD47)/3 -> 30.214613 | AE49: =AE40*AE$12+(AE34-AE47)/3 -> 30.660672 | AF49: =AF40*AF$12+(AF34-AF47)/3 -> 31.073812 | AG49: =AG40*AG$12+(AG34-AG47)/3 -> 31.378917 | AH49: =AH40*AH$12+(AH34-AH47)/3 -> 31.606682 | AI49: =AI40*AI$12+(AI34-AI47)/3 -> 31.827984 | AJ49: =AJ40*AJ$12+(AJ34-AJ47)/3 -> 31.862627 | AK49: =AK40*AK$12+(AK34-AK47)/3 -> 32.065954 | ... AP49: =AP40*AP$12+(AP34-AP47)/3 -> 0 | AQ49: Electricité (pompe à chaleur)
H50: Electricité (joule) | J50: =J41*J$12 -> 43.913 | K50: =K41*K$12 -> 40.822 | L50: =L41*L$12 -> 38.813 | M50: =M41*M$12 -> 36.47061 | N50: =N41*N$12 -> 34.26374 | O50: =O41*O$12 -> 32.13319 | P50: =P41*P$12 -> 29.754173 | Q50: =Q41*Q$12 -> 27.33416 | ... AP50: =AP41*AP$12 -> 0 | AQ50: Electricité (joule)
H51: Chaleur environnement (COP ->) | I51: 3.2 | J51: =J49*($I51-1) -> 15.3648 | K51: =K49*($I51-1) -> 19.8594 | L51: =L49*($I51-1) -> 23.8722 | M51: =M49*($I51-1) -> 27.51903 | N51: =N49*($I51-1) -> 31.453884 | O51: =O49*($I51-1) -> 35.127774 | P51: =P49*($I51-1) -> 38.152287 | Q51: =Q49*($I51-1) -> 40.703879 | ... AP51: =AP49*($I51-1) -> 0 | AQ51: Chaleur environnement
I53: Total sans chaleur envi | J53: =SUM(J45:J50) -> 260.458 | K53: =SUM(K45:K50) -> 253.846 | L53: =SUM(L45:L50) -> 249.953 | M53: =SUM(M45:M50) -> 241.99164 | N53: =SUM(N45:N50) -> 231.42504 | O53: =SUM(O45:O50) -> 223.67424 | P53: =SUM(P45:P50) -> 214.45111 | Q53: =SUM(Q45:Q50) -> 205.43632 | ... AP53: =SUM(AP45:AP50) -> 0
I54: Total avec chaleur envi | J54: =SUM(J45:J51) -> 275.8228 | K54: =SUM(K45:K51) -> 273.7054 | L54: =SUM(L45:L51) -> 273.8252 | M54: =SUM(M45:M51) -> 269.51067 | N54: =SUM(N45:N51) -> 262.87892 | O54: =SUM(O45:O51) -> 258.80201 | P54: =SUM(P45:P51) -> 252.60339 | Q54: =SUM(Q45:Q51) -> 246.1402 | ... AP54: =SUM(AP45:AP51) -> 0
H56: Parc de logements par énergie | N56: =N59/M59-1 -> -0.11321586 | O56: =O59/N59-1 -> -0.1266766 | P56: =P59/O59-1 -> -0.14448237 | Q56: =Q59/P59-1 -> -0.16821809 | R56: =R59/Q59-1 -> -0.20143885 | S56: =S59/R59-1 -> -0.25125125 | T56: =T59/S59-1 -> -0.3355615 | U56: =U59/T59-1 -> -0.50100604 | ... AF56: =AF59/AE59-1 -> -1
H57: Stock Direct electric (Million) | I57: Electricité (joule) | J57: =VLOOKUP($H57,output!$A$10:$AH$2201,J$1-$J$1+2) -> 8.317 | K57: =VLOOKUP($H57,output!$A$10:$AH$2201,K$1-$J$1+2) -> 8.012 | L57: =VLOOKUP($H57,output!$A$10:$AH$2201,L$1-$J$1+2) -> 7.768 | M57: =VLOOKUP($H57,output!$A$10:$AH$2201,M$1-$J$1+2) -> 7.499 | N57: =VLOOKUP($H57,output!$A$10:$AH$2201,N$1-$J$1+2) -> 7.241 | O57: =VLOOKUP($H57,output!$A$10:$AH$2201,O$1-$J$1+2) -> 6.964 | P57: =VLOOKUP($H57,output!$A$10:$AH$2201,P$1-$J$1+2) -> 6.666 | Q57: =VLOOKUP($H57,output!$A$10:$AH$2201,Q$1-$J$1+2) -> 6.332 | ... AP57: =VLOOKUP($H57,output!$A$10:$AH$2201,AP$1-$J$1+2) -> 0 | AQ57: Electricité (joule)
H58: Stock Heat pump (Million) | I58: Electricité (pompe à chaleur) | J58: =VLOOKUP($H58,output!$A$10:$AH$2201,J$1-$J$1+2) -> 2.896 | K58: =VLOOKUP($H58,output!$A$10:$AH$2201,K$1-$J$1+2) -> 3.642 | L58: =VLOOKUP($H58,output!$A$10:$AH$2201,L$1-$J$1+2) -> 4.368 | M58: =VLOOKUP($H58,output!$A$10:$AH$2201,M$1-$J$1+2) -> 5.054 | N58: =VLOOKUP($H58,output!$A$10:$AH$2201,N$1-$J$1+2) -> 5.799 | O58: =VLOOKUP($H58,output!$A$10:$AH$2201,O$1-$J$1+2) -> 6.511 | P58: =VLOOKUP($H58,output!$A$10:$AH$2201,P$1-$J$1+2) -> 7.184 | Q58: =VLOOKUP($H58,output!$A$10:$AH$2201,Q$1-$J$1+2) -> 7.756 | ... AC58: =VLOOKUP($H58,output!$A$10:$AH$2201,AC$1-$J$1+2) -> 15.373 | AD58: =VLOOKUP($H58,output!$A$10:$AH$2201,AD$1-$J$1+2)+AD66-AD59 -> 15.783 | AE58: =VLOOKUP($H58,output!$A$10:$AH$2201,AE$1-$J$1+2)+AE66-AE59 -> 16.064 | AF58: =VLOOKUP($H58,output!$A$10:$AH$2201,AF$1-$J$1+2)+AF66-AF59 -> 16.441 | AG58: =VLOOKUP($H58,output!$A$10:$AH$2201,AG$1-$J$1+2)+AG66-AG59 -> 16.747 | AH58: =VLOOKUP($H58,output!$A$10:$AH$2201,AH$1-$J$1+2)+AH66-AH59 -> 17.018 | AI58: =VLOOKUP($H58,output!$A$10:$AH$2201,AI$1-$J$1+2)+AI66-AI59 -> 17.287 | AJ58: =VLOOKUP($H58,output!$A$10:$AH$2201,AJ$1-$J$1+2)+AJ66-AJ59 -> 17.554 | AK58: =VLOOKUP($H58,output!$A$10:$AH$2201,AK$1-$J$1+2)+AK66-AK59 -> 17.817 | ... AP58: =VLOOKUP($H58,output!$A$10:$AH$2201,AP$1-$J$1+2)+AP66-AP59 -> 0 | AQ58: Electricité (pompe à chaleur)
H59: Stock Oil fuel (Million) | I59: Fioul | J59: =VLOOKUP($H59,output!$A$10:$AH$2201,J$1-$J$1+2) -> 3.049 | K59: =VLOOKUP($H59,output!$A$10:$AH$2201,K$1-$J$1+2) -> 2.788 | L59: =VLOOKUP($H59,output!$A$10:$AH$2201,L$1-$J$1+2) -> 2.528 | M59: =VLOOKUP($H59,output!$A$10:$AH$2201,M$1-$J$1+2) -> 2.27 | N59: =VLOOKUP($H59,output!$A$10:$AH$2201,N$1-$J$1+2) -> 2.013 | O59: =VLOOKUP($H59,output!$A$10:$AH$2201,O$1-$J$1+2) -> 1.758 | P59: =VLOOKUP($H59,output!$A$10:$AH$2201,P$1-$J$1+2) -> 1.504 | Q59: =VLOOKUP($H59,output!$A$10:$AH$2201,Q$1-$J$1+2) -> 1.251 | ... AC59: =VLOOKUP($H59,output!$A$10:$AH$2201,AC$1-$J$1+2) -> 0 | AD59: 0.1 | AE59: 0.1 | AF59: 0 | AG59: 0 | AH59: 0 | AI59: 0 | AJ59: 0 | AK59: 0 | AL59: 0 | AM59: 0 | AN59: 0 | AO59: 0 | AP59: 0 | AQ59: Fioul
H60: Stock Wood fuel (Million) | I60: Bois | J60: =VLOOKUP($H60,output!$A$10:$AH$2201,J$1-$J$1+2) -> 2.733 | K60: =VLOOKUP($H60,output!$A$10:$AH$2201,K$1-$J$1+2) -> 2.763 | L60: =VLOOKUP($H60,output!$A$10:$AH$2201,L$1-$J$1+2) -> 2.782 | M60: =VLOOKUP($H60,output!$A$10:$AH$2201,M$1-$J$1+2) -> 2.8 | N60: =VLOOKUP($H60,output!$A$10:$AH$2201,N$1-$J$1+2) -> 2.82 | O60: =VLOOKUP($H60,output!$A$10:$AH$2201,O$1-$J$1+2) -> 2.84 | P60: =VLOOKUP($H60,output!$A$10:$AH$2201,P$1-$J$1+2) -> 2.86 | Q60: =VLOOKUP($H60,output!$A$10:$AH$2201,Q$1-$J$1+2) -> 2.876 | ... AP60: =VLOOKUP($H60,output!$A$10:$AH$2201,AP$1-$J$1+2) -> 0 | AQ60: Bois
H61: Stock Natural gas (Million) | I61: Gaz naturel | J61: =VLOOKUP($H61,output!$A$10:$AH$2201,J$1-$J$1+2) -> 11.809 | K61: =VLOOKUP($H61,output!$A$10:$AH$2201,K$1-$J$1+2) -> 11.674 | L61: =VLOOKUP($H61,output!$A$10:$AH$2201,L$1-$J$1+2) -> 11.648 | M61: =VLOOKUP($H61,output!$A$10:$AH$2201,M$1-$J$1+2) -> 11.49 | N61: =VLOOKUP($H61,output!$A$10:$AH$2201,N$1-$J$1+2) -> 11.328 | O61: =VLOOKUP($H61,output!$A$10:$AH$2201,O$1-$J$1+2) -> 11.067 | P61: =VLOOKUP($H61,output!$A$10:$AH$2201,P$1-$J$1+2) -> 10.695 | Q61: =VLOOKUP($H61,output!$A$10:$AH$2201,Q$1-$J$1+2) -> 10.223 | ... AP61: =VLOOKUP($H61,output!$A$10:$AH$2201,AP$1-$J$1+2) -> 0 | AQ61: Gaz naturel
H62: Stock District heating (Million) | I62: Chauffage urbain | J62: =VLOOKUP($H62,output!$A$10:$AH$2201,J$1-$J$1+2) -> 1.421 | K62: =VLOOKUP($H62,output!$A$10:$AH$2201,K$1-$J$1+2) -> 1.565 | L62: =VLOOKUP($H62,output!$A$10:$AH$2201,L$1-$J$1+2) -> 1.619 | M62: =VLOOKUP($H62,output!$A$10:$AH$2201,M$1-$J$1+2) -> 1.868 | N62: =VLOOKUP($H62,output!$A$10:$AH$2201,N$1-$J$1+2) -> 2.047 | O62: =VLOOKUP($H62,output!$A$10:$AH$2201,O$1-$J$1+2) -> 2.375 | P62: =VLOOKUP($H62,output!$A$10:$AH$2201,P$1-$J$1+2) -> 2.874 | Q62: =VLOOKUP($H62,output!$A$10:$AH$2201,Q$1-$J$1+2) -> 3.522 | ... AP62: =VLOOKUP($H62,output!$A$10:$AH$2201,AP$1-$J$1+2) -> 0 | AQ62: Chauffage urbain
K63: =K62-J62 -> 0.144 | L63: =L62-K62 -> 0.054 | M63: =M62-L62 -> 0.249 | N63: =N62-M62 -> 0.179 | O63: =O62-N62 -> 0.328 | P63: =P62-O62 -> 0.499 | Q63: =Q62-P62 -> 0.648 | R63: =R62-Q62 -> 0.397 | ... AP63: =AP62-AO62 -> 0
I64: raccordement RCU/an | K64: =(K62-J62)*1000 -> 144 | L64: =(L62-K62)*1000 -> 54 | M64: =(M62-L62)*1000 -> 249 | N64: =(N62-M62)*1000 -> 179 | O64: =(O62-N62)*1000 -> 328 | P64: =(P62-O62)*1000 -> 499 | Q64: =(Q62-P62)*1000 -> 648 | R64: =(R62-Q62)*1000 -> 397 | ... AP64: =(AP62-AO62)*1000 -> 0
AA66: Fioul pour correction | AD66: =VLOOKUP($H59,output!$A$10:$AH$2201,AD$1-$J$1+2) -> 0 | AE66: =VLOOKUP($H59,output!$A$10:$AH$2201,AE$1-$J$1+2) -> 0 | AF66: =VLOOKUP($H59,output!$A$10:$AH$2201,AF$1-$J$1+2) -> 0 | AG66: =VLOOKUP($H59,output!$A$10:$AH$2201,AG$1-$J$1+2) -> 0 | AH66: =VLOOKUP($H59,output!$A$10:$AH$2201,AH$1-$J$1+2) -> 0 | AI66: =VLOOKUP($H59,output!$A$10:$AH$2201,AI$1-$J$1+2) -> 0 | AJ66: =VLOOKUP($H59,output!$A$10:$AH$2201,AJ$1-$J$1+2) -> 0 | AK66: =VLOOKUP($H59,output!$A$10:$AH$2201,AK$1-$J$1+2) -> 0 | ... AP66: =VLOOKUP($H59,output!$A$10:$AH$2201,AP$1-$J$1+2) -> 0
H67: Rénovations (isolation ou chauffage) par saut de classe
H68: Retrofit 6 EPC (Thousand households) | I68: 6 classes | J68: =VLOOKUP($H68,output!$A$10:$AH$2201,J$1-$J$1+2) -> 0 | K68: =VLOOKUP($H68,output!$A$10:$AH$2201,K$1-$J$1+2) -> 0.059 | L68: =VLOOKUP($H68,output!$A$10:$AH$2201,L$1-$J$1+2) -> 0.014 | M68: =VLOOKUP($H68,output!$A$10:$AH$2201,M$1-$J$1+2) -> 0.006 | N68: =VLOOKUP($H68,output!$A$10:$AH$2201,N$1-$J$1+2) -> 0.003 | O68: =VLOOKUP($H68,output!$A$10:$AH$2201,O$1-$J$1+2) -> 0.002 | P68: =VLOOKUP($H68,output!$A$10:$AH$2201,P$1-$J$1+2) -> 0.002 | Q68: =VLOOKUP($H68,output!$A$10:$AH$2201,Q$1-$J$1+2) -> 0.001 | ... AP68: =VLOOKUP($H68,output!$A$10:$AH$2201,AP$1-$J$1+2) -> 0
H69: Retrofit 5 EPC (Thousand households) | I69: 5 classes | J69: =VLOOKUP($H69,output!$A$10:$AH$2201,J$1-$J$1+2) -> 0 | K69: =VLOOKUP($H69,output!$A$10:$AH$2201,K$1-$J$1+2) -> 0.773 | L69: =VLOOKUP($H69,output!$A$10:$AH$2201,L$1-$J$1+2) -> 0.31 | M69: =VLOOKUP($H69,output!$A$10:$AH$2201,M$1-$J$1+2) -> 0.241 | N69: =VLOOKUP($H69,output!$A$10:$AH$2201,N$1-$J$1+2) -> 0.279 | O69: =VLOOKUP($H69,output!$A$10:$AH$2201,O$1-$J$1+2) -> 0.23 | P69: =VLOOKUP($H69,output!$A$10:$AH$2201,P$1-$J$1+2) -> 0.182 | Q69: =VLOOKUP($H69,output!$A$10:$AH$2201,Q$1-$J$1+2) -> 0.16 | ... AP69: =VLOOKUP($H69,output!$A$10:$AH$2201,AP$1-$J$1+2) -> 0
H70: Retrofit 4 EPC (Thousand households) | I70: 4 classes | J70: =VLOOKUP($H70,output!$A$10:$AH$2201,J$1-$J$1+2) -> 0 | K70: =VLOOKUP($H70,output!$A$10:$AH$2201,K$1-$J$1+2) -> 61.33 | L70: =VLOOKUP($H70,output!$A$10:$AH$2201,L$1-$J$1+2) -> 40.121 | M70: =VLOOKUP($H70,output!$A$10:$AH$2201,M$1-$J$1+2) -> 29.405 | N70: =VLOOKUP($H70,output!$A$10:$AH$2201,N$1-$J$1+2) -> 29.237 | O70: =VLOOKUP($H70,output!$A$10:$AH$2201,O$1-$J$1+2) -> 22.59 | P70: =VLOOKUP($H70,output!$A$10:$AH$2201,P$1-$J$1+2) -> 17.083 | Q70: =VLOOKUP($H70,output!$A$10:$AH$2201,Q$1-$J$1+2) -> 13.109 | ... AP70: =VLOOKUP($H70,output!$A$10:$AH$2201,AP$1-$J$1+2) -> 0
H71: Retrofit 3 EPC (Thousand households) | I71: 3 classes | J71: =VLOOKUP($H71,output!$A$10:$AH$2201,J$1-$J$1+2) -> 0 | K71: =VLOOKUP($H71,output!$A$10:$AH$2201,K$1-$J$1+2) -> 251.615 | L71: =VLOOKUP($H71,output!$A$10:$AH$2201,L$1-$J$1+2) -> 184.159 | M71: =VLOOKUP($H71,output!$A$10:$AH$2201,M$1-$J$1+2) -> 210.072 | N71: =VLOOKUP($H71,output!$A$10:$AH$2201,N$1-$J$1+2) -> 221.142 | O71: =VLOOKUP($H71,output!$A$10:$AH$2201,O$1-$J$1+2) -> 192.734 | P71: =VLOOKUP($H71,output!$A$10:$AH$2201,P$1-$J$1+2) -> 166.147 | Q71: =VLOOKUP($H71,output!$A$10:$AH$2201,Q$1-$J$1+2) -> 168.647 | ... AP71: =VLOOKUP($H71,output!$A$10:$AH$2201,AP$1-$J$1+2) -> 0
H72: Retrofit 2 EPC (Thousand households) | I72: 2 classes | J72: =VLOOKUP($H72,output!$A$10:$AH$2201,J$1-$J$1+2) -> 0 | K72: =VLOOKUP($H72,output!$A$10:$AH$2201,K$1-$J$1+2) -> 354.066 | L72: =VLOOKUP($H72,output!$A$10:$AH$2201,L$1-$J$1+2) -> 275.016 | M72: =VLOOKUP($H72,output!$A$10:$AH$2201,M$1-$J$1+2) -> 332.511 | N72: =VLOOKUP($H72,output!$A$10:$AH$2201,N$1-$J$1+2) -> 348.665 | O72: =VLOOKUP($H72,output!$A$10:$AH$2201,O$1-$J$1+2) -> 341.088 | P72: =VLOOKUP($H72,output!$A$10:$AH$2201,P$1-$J$1+2) -> 331.271 | Q72: =VLOOKUP($H72,output!$A$10:$AH$2201,Q$1-$J$1+2) -> 362.798 | ... AP72: =VLOOKUP($H72,output!$A$10:$AH$2201,AP$1-$J$1+2) -> 0
H73: Retrofit 1 EPC (Thousand households) | I73: 1 classe | J73: =VLOOKUP($H73,output!$A$10:$AH$2201,J$1-$J$1+2) -> 0 | K73: =VLOOKUP($H73,output!$A$10:$AH$2201,K$1-$J$1+2) -> 385.953 | L73: =VLOOKUP($H73,output!$A$10:$AH$2201,L$1-$J$1+2) -> 333.736 | M73: =VLOOKUP($H73,output!$A$10:$AH$2201,M$1-$J$1+2) -> 470.83 | N73: =VLOOKUP($H73,output!$A$10:$AH$2201,N$1-$J$1+2) -> 468.452 | O73: =VLOOKUP($H73,output!$A$10:$AH$2201,O$1-$J$1+2) -> 549.61 | P73: =VLOOKUP($H73,output!$A$10:$AH$2201,P$1-$J$1+2) -> 624.923 | Q73: =VLOOKUP($H73,output!$A$10:$AH$2201,Q$1-$J$1+2) -> 694.254 | ... AP73: =VLOOKUP($H73,output!$A$10:$AH$2201,AP$1-$J$1+2) -> 0
H74: Retrofit (Thousand households) | I74: tout | J74: =VLOOKUP($H74,output!$A$10:$AH$2201,J$1-$J$1+2) -> 0 | K74: =VLOOKUP($H74,output!$A$10:$AH$2201,K$1-$J$1+2) -> 2381.487 | L74: =VLOOKUP($H74,output!$A$10:$AH$2201,L$1-$J$1+2) -> 2217.358 | M74: =VLOOKUP($H74,output!$A$10:$AH$2201,M$1-$J$1+2) -> 2395.354 | N74: =VLOOKUP($H74,output!$A$10:$AH$2201,N$1-$J$1+2) -> 2436.677 | O74: =VLOOKUP($H74,output!$A$10:$AH$2201,O$1-$J$1+2) -> 2442.248 | P74: =VLOOKUP($H74,output!$A$10:$AH$2201,P$1-$J$1+2) -> 2416.545 | Q74: =VLOOKUP($H74,output!$A$10:$AH$2201,Q$1-$J$1+2) -> 2458.227 | ... AP74: =VLOOKUP($H74,output!$A$10:$AH$2201,AP$1-$J$1+2) -> 0
I76: 2 ou plus | J76: =SUM(J68:J72) -> 0 | K76: =SUM(K68:K72) -> 667.843 | L76: =SUM(L68:L72) -> 499.62 | M76: =SUM(M68:M72) -> 572.235 | N76: =SUM(N68:N72) -> 599.326 | O76: =SUM(O68:O72) -> 556.644 | P76: =SUM(P68:P72) -> 514.685 | Q76: =SUM(Q68:Q72) -> 544.715 | ... AP76: =SUM(AP68:AP72) -> 0
I77: 1 ou plus | J77: =SUM(J68:J73) -> 0 | K77: =SUM(K68:K73) -> 1053.796 | L77: =SUM(L68:L73) -> 833.356 | M77: =SUM(M68:M73) -> 1043.065 | N77: =SUM(N68:N73) -> 1067.778 | O77: =SUM(O68:O73) -> 1106.254 | P77: =SUM(P68:P73) -> 1139.608 | Q77: =SUM(Q68:Q73) -> 1238.969 | ... AK77: =SUM(AK68:AK73) -> 388.617
H80: Rénovation (isolation) par type d'occupant
H81: Renovation Multi-family - Owner-occupied (Thousand households) | I81: PO en copropriété | J81: =VLOOKUP($H81,output!$A$10:$AH$2201,J$1-$J$1+2) -> 0 | K81: =VLOOKUP($H81,output!$A$10:$AH$2201,K$1-$J$1+2) -> 66.859 | L81: =VLOOKUP($H81,output!$A$10:$AH$2201,L$1-$J$1+2) -> 51 | M81: =VLOOKUP($H81,output!$A$10:$AH$2201,M$1-$J$1+2) -> 50.872 | N81: =VLOOKUP($H81,output!$A$10:$AH$2201,N$1-$J$1+2) -> 55.295 | O81: =VLOOKUP($H81,output!$A$10:$AH$2201,O$1-$J$1+2) -> 54.615 | P81: =VLOOKUP($H81,output!$A$10:$AH$2201,P$1-$J$1+2) -> 53.884 | Q81: =VLOOKUP($H81,output!$A$10:$AH$2201,Q$1-$J$1+2) -> 57.446 | ... AP81: =VLOOKUP($H81,output!$A$10:$AH$2201,AP$1-$J$1+2) -> 0
H82: Renovation Multi-family - Privately rented (Thousand households) | I82: PB en copropriété | J82: =VLOOKUP($H82,output!$A$10:$AH$2201,J$1-$J$1+2) -> 0 | K82: =VLOOKUP($H82,output!$A$10:$AH$2201,K$1-$J$1+2) -> 75.746 | L82: =VLOOKUP($H82,output!$A$10:$AH$2201,L$1-$J$1+2) -> 60.488 | M82: =VLOOKUP($H82,output!$A$10:$AH$2201,M$1-$J$1+2) -> 89.875 | N82: =VLOOKUP($H82,output!$A$10:$AH$2201,N$1-$J$1+2) -> 75.798 | O82: =VLOOKUP($H82,output!$A$10:$AH$2201,O$1-$J$1+2) -> 64.472 | P82: =VLOOKUP($H82,output!$A$10:$AH$2201,P$1-$J$1+2) -> 55.584 | Q82: =VLOOKUP($H82,output!$A$10:$AH$2201,Q$1-$J$1+2) -> 48.606 | ... AP82: =VLOOKUP($H82,output!$A$10:$AH$2201,AP$1-$J$1+2) -> 0
H83: Renovation Multi-family - Social-housing (Thousand households) | I83: PB social en copropriété | J83: =VLOOKUP($H83,output!$A$10:$AH$2201,J$1-$J$1+2) -> 0 | K83: =VLOOKUP($H83,output!$A$10:$AH$2201,K$1-$J$1+2) -> 15.24 | L83: =VLOOKUP($H83,output!$A$10:$AH$2201,L$1-$J$1+2) -> 61.818 | M83: =VLOOKUP($H83,output!$A$10:$AH$2201,M$1-$J$1+2) -> 139.633 | N83: =VLOOKUP($H83,output!$A$10:$AH$2201,N$1-$J$1+2) -> 181.31 | O83: =VLOOKUP($H83,output!$A$10:$AH$2201,O$1-$J$1+2) -> 224.567 | P83: =VLOOKUP($H83,output!$A$10:$AH$2201,P$1-$J$1+2) -> 234.966 | Q83: =VLOOKUP($H83,output!$A$10:$AH$2201,Q$1-$J$1+2) -> 238.434 | ... AP83: =VLOOKUP($H83,output!$A$10:$AH$2201,AP$1-$J$1+2) -> 0
H84: Renovation Single-family - Owner-occupied (Thousand households) | I84: PO en maison | J84: =VLOOKUP($H84,output!$A$10:$AH$2201,J$1-$J$1+2) -> 0 | K84: =VLOOKUP($H84,output!$A$10:$AH$2201,K$1-$J$1+2) -> 373.908 | L84: =VLOOKUP($H84,output!$A$10:$AH$2201,L$1-$J$1+2) -> 194.506 | M84: =VLOOKUP($H84,output!$A$10:$AH$2201,M$1-$J$1+2) -> 207.952 | N84: =VLOOKUP($H84,output!$A$10:$AH$2201,N$1-$J$1+2) -> 230.087 | O84: =VLOOKUP($H84,output!$A$10:$AH$2201,O$1-$J$1+2) -> 222.751 | P84: =VLOOKUP($H84,output!$A$10:$AH$2201,P$1-$J$1+2) -> 216.001 | Q84: =VLOOKUP($H84,output!$A$10:$AH$2201,Q$1-$J$1+2) -> 266.178 | ... AP84: =VLOOKUP($H84,output!$A$10:$AH$2201,AP$1-$J$1+2) -> 0
H85: Renovation Single-family - Privately rented (Thousand households) | I85: PB en maison | J85: =VLOOKUP($H85,output!$A$10:$AH$2201,J$1-$J$1+2) -> 0 | K85: =VLOOKUP($H85,output!$A$10:$AH$2201,K$1-$J$1+2) -> 54.747 | L85: =VLOOKUP($H85,output!$A$10:$AH$2201,L$1-$J$1+2) -> 37.575 | M85: =VLOOKUP($H85,output!$A$10:$AH$2201,M$1-$J$1+2) -> 88.86 | N85: =VLOOKUP($H85,output!$A$10:$AH$2201,N$1-$J$1+2) -> 71.556 | O85: =VLOOKUP($H85,output!$A$10:$AH$2201,O$1-$J$1+2) -> 57.828 | P85: =VLOOKUP($H85,output!$A$10:$AH$2201,P$1-$J$1+2) -> 47.111 | Q85: =VLOOKUP($H85,output!$A$10:$AH$2201,Q$1-$J$1+2) -> 38.75 | ... AP85: =VLOOKUP($H85,output!$A$10:$AH$2201,AP$1-$J$1+2) -> 0
H86: Renovation Single-family - Social-housing (Thousand households) | I86: PB social en maison | J86: =VLOOKUP($H86,output!$A$10:$AH$2201,J$1-$J$1+2) -> 0 | K86: =VLOOKUP($H86,output!$A$10:$AH$2201,K$1-$J$1+2) -> 14.484 | L86: =VLOOKUP($H86,output!$A$10:$AH$2201,L$1-$J$1+2) -> 29.828 | M86: =VLOOKUP($H86,output!$A$10:$AH$2201,M$1-$J$1+2) -> 47.03 | N86: =VLOOKUP($H86,output!$A$10:$AH$2201,N$1-$J$1+2) -> 59.106 | O86: =VLOOKUP($H86,output!$A$10:$AH$2201,O$1-$J$1+2) -> 61.26 | P86: =VLOOKUP($H86,output!$A$10:$AH$2201,P$1-$J$1+2) -> 56.507 | Q86: =VLOOKUP($H86,output!$A$10:$AH$2201,Q$1-$J$1+2) -> 61.023 | ... AP86: =VLOOKUP($H86,output!$A$10:$AH$2201,AP$1-$J$1+2) -> 0
H88: Total | J88: =SUM(J81:J86) -> 0 | K88: =SUM(K81:K86) -> 600.984 | L88: =SUM(L81:L86) -> 435.215 | M88: =SUM(M81:M86) -> 624.222 | N88: =SUM(N81:N86) -> 673.152 | O88: =SUM(O81:O86) -> 685.493 | P88: =SUM(P81:P86) -> 664.053 | Q88: =SUM(Q81:Q86) -> 710.437 | ... AP88: =SUM(AP81:AP86) -> 0
H89: dont maison | K89: =(K84+K85)/K88 -> 0.71325526 | L89: =(L84+L85)/L88 -> 0.53325598 | M89: =(M84+M85)/M88 -> 0.47549109 | N89: =(N84+N85)/N88 -> 0.44810533 | O89: =(O84+O85)/O88 -> 0.4093098 | P89: =(P84+P85)/P88 -> 0.39622139 | Q89: =(Q84+Q85)/Q88 -> 0.42921188 | R89: =(R84+R85)/R88 -> 0.34324383 | ... V89: =(V84+V85)/V88 -> 0.29518631
H90: dont logements collectifs | K90: =(K81+K82)/K88 -> 0.23728585 | L90: =(L81+L82)/L88 -> 0.25616764 | M90: =(M81+M82)/M88 -> 0.22547587 | N90: =(N81+N82)/N88 -> 0.19474502 | O90: =(O81+O82)/O88 -> 0.1737246 | P90: =(P81+P82)/P88 -> 0.16484829 | Q90: =(Q81+Q82)/Q88 -> 0.14927714 | R90: =(R81+R82)/R88 -> 0.31247225 | ... V90: =(V81+V82)/V88 -> 0.19170672
H91: dont logements sociaux | K91: =(K83+K86)/K88 -> 0.049458887 | L91: =(L83+L86)/L88 -> 0.21057638 | M91: =(M83+M86)/M88 -> 0.29903304 | N91: =(N83+N86)/N88 -> 0.35714965 | O91: =(O83+O86)/O88 -> 0.4169656 | P91: =(P83+P86)/P88 -> 0.43893033 | Q91: =(Q83+Q86)/Q88 -> 0.42151099 | R91: =(R83+R86)/R88 -> 0.34428392 | ... V91: =(V83+V86)/V88 -> 0.51310697
H93: Investment heater (Billion euro) | J93: =VLOOKUP($H93,output!$A$10:$AH$2201,J$1-$J$1+2) -> 0 | K93: =VLOOKUP($H93,output!$A$10:$AH$2201,K$1-$J$1+2) -> 15.007 | L93: =VLOOKUP($H93,output!$A$10:$AH$2201,L$1-$J$1+2) -> 14.005 | M93: =VLOOKUP($H93,output!$A$10:$AH$2201,M$1-$J$1+2) -> 12.918 | N93: =VLOOKUP($H93,output!$A$10:$AH$2201,N$1-$J$1+2) -> 13.325 | O93: =VLOOKUP($H93,output!$A$10:$AH$2201,O$1-$J$1+2) -> 12.469 | P93: =VLOOKUP($H93,output!$A$10:$AH$2201,P$1-$J$1+2) -> 11.518 | Q93: =VLOOKUP($H93,output!$A$10:$AH$2201,Q$1-$J$1+2) -> 10.638 | ... AP93: =VLOOKUP($H93,output!$A$10:$AH$2201,AP$1-$J$1+2) -> 0
H94: Investment insulation (Billion euro) | J94: =VLOOKUP($H94,output!$A$10:$AH$2201,J$1-$J$1+2) -> 0 | K94: =VLOOKUP($H94,output!$A$10:$AH$2201,K$1-$J$1+2) -> 7.376 | L94: =VLOOKUP($H94,output!$A$10:$AH$2201,L$1-$J$1+2) -> 4.132 | M94: =VLOOKUP($H94,output!$A$10:$AH$2201,M$1-$J$1+2) -> 6.282 | N94: =VLOOKUP($H94,output!$A$10:$AH$2201,N$1-$J$1+2) -> 6.829 | O94: =VLOOKUP($H94,output!$A$10:$AH$2201,O$1-$J$1+2) -> 6.369 | P94: =VLOOKUP($H94,output!$A$10:$AH$2201,P$1-$J$1+2) -> 5.806 | Q94: =VLOOKUP($H94,output!$A$10:$AH$2201,Q$1-$J$1+2) -> 7.248 | ... AP94: =VLOOKUP($H94,output!$A$10:$AH$2201,AP$1-$J$1+2) -> 0
H100: Investment total (Billion euro) | I100: Investissement total (milliards) | J100: =VLOOKUP($H100,output!$A$10:$AH$2201,J$1-$J$1+2) -> 0 | K100: =VLOOKUP($H100,output!$A$10:$AH$2201,K$1-$J$1+2) -> 22.383 | L100: =VLOOKUP($H100,output!$A$10:$AH$2201,L$1-$J$1+2) -> 18.137 | M100: =VLOOKUP($H100,output!$A$10:$AH$2201,M$1-$J$1+2) -> 19.199 | N100: =VLOOKUP($H100,output!$A$10:$AH$2201,N$1-$J$1+2) -> 20.154 | O100: =VLOOKUP($H100,output!$A$10:$AH$2201,O$1-$J$1+2) -> 18.838 | P100: =VLOOKUP($H100,output!$A$10:$AH$2201,P$1-$J$1+2) -> 17.324 | Q100: =VLOOKUP($H100,output!$A$10:$AH$2201,Q$1-$J$1+2) -> 17.886 | ... AP100: =VLOOKUP($H100,output!$A$10:$AH$2201,AP$1-$J$1+2) -> 0
H101: Financing total (Billion euro) | J101: =VLOOKUP($H101,output!$A$10:$AH$2201,J$1-$J$1+2) -> 0 | K101: =VLOOKUP($H101,output!$A$10:$AH$2201,K$1-$J$1+2) -> 5.188 | L101: =VLOOKUP($H101,output!$A$10:$AH$2201,L$1-$J$1+2) -> 6.106 | M101: =VLOOKUP($H101,output!$A$10:$AH$2201,M$1-$J$1+2) -> 5.907 | N101: =VLOOKUP($H101,output!$A$10:$AH$2201,N$1-$J$1+2) -> 6.208 | O101: =VLOOKUP($H101,output!$A$10:$AH$2201,O$1-$J$1+2) -> 5.757 | P101: =VLOOKUP($H101,output!$A$10:$AH$2201,P$1-$J$1+2) -> 5.282 | Q101: =VLOOKUP($H101,output!$A$10:$AH$2201,Q$1-$J$1+2) -> 5.303 | ... AP101: =VLOOKUP($H101,output!$A$10:$AH$2201,AP$1-$J$1+2) -> 0
H102: Debt total (Billion euro) | J102: =VLOOKUP($H102,output!$A$10:$AH$2201,J$1-$J$1+2) -> 0 | K102: =VLOOKUP($H102,output!$A$10:$AH$2201,K$1-$J$1+2) -> 5.71 | L102: =VLOOKUP($H102,output!$A$10:$AH$2201,L$1-$J$1+2) -> 6.289 | M102: =VLOOKUP($H102,output!$A$10:$AH$2201,M$1-$J$1+2) -> 7.949 | N102: =VLOOKUP($H102,output!$A$10:$AH$2201,N$1-$J$1+2) -> 8.49 | O102: =VLOOKUP($H102,output!$A$10:$AH$2201,O$1-$J$1+2) -> 8.065 | P102: =VLOOKUP($H102,output!$A$10:$AH$2201,P$1-$J$1+2) -> 7.52 | Q102: =VLOOKUP($H102,output!$A$10:$AH$2201,Q$1-$J$1+2) -> 8.539 | ... AP102: =VLOOKUP($H102,output!$A$10:$AH$2201,AP$1-$J$1+2) -> 0
H103: Soutien total (milliards) | I103: Soutien total (milliards) | J103: =SUM(J141:J144) -> 0 | K103: =SUM(K141:K144) -> 0 | L103: =SUM(L141:L144) -> 0 | M103: =SUM(M141:M144) -> 5.2 | N103: =SUM(N141:N144) -> 4.25 | O103: =SUM(O141:O144) -> 3.3968 | P103: =SUM(P141:P144) -> 0.2994 | Q103: =SUM(Q141:Q144) -> 0.3888 | ... AP103: =SUM(AP141:AP144) -> 0
I104: Part soutien | M104: =M103/M100 -> 0.27084744 | N104: =N103/N100 -> 0.21087625 | O104: =O103/O100 -> 0.18031638 | P104: =P103/P100 -> 0.017282383 | Q104: =Q103/Q100 -> 0.021737672 | R104: =R103/R100 -> 0.011642798 | S104: =S103/S100 -> 0.017909513 | T104: =T103/T100 -> 0.016066042 | ... V104: =V103/V100 -> 0.011427652
I105: RAC | M105: =1-M104 -> 0.72915256 | N105: =1-N104 -> 0.78912375 | O105: =1-O104 -> 0.81968362 | P105: =1-P104 -> 0.98271762 | Q105: =1-Q104 -> 0.97826233 | R105: =1-R104 -> 0.9883572 | S105: =1-S104 -> 0.98209049 | T105: =1-T104 -> 0.98393396 | ... V105: =1-V104 -> 0.98857235
H107: Correction années historiques (I4CE) | I107: Investissement total (milliards) | M107: 15 | N107: 17 | O107: 19 | P107: =P100 -> 17.324 | Q107: =Q100 -> 17.886 | R107: =R100 -> 20.459 | S107: =S100 -> 19.163 | T107: =T100 -> 18.897 | U107: =U100 -> 18.944 | V107: =V100 -> 18.639 | W107: =W100 -> 17.137 | ... AP107: =AP100 -> 0
I108: Soutien total (milliards) | M108: 4.8 | N108: 5.5 | O108: 6 | P108: =P103 -> 0.2994 | Q108: =Q103 -> 0.3888 | R108: =R103 -> 0.2382 | S108: =S103 -> 0.3432 | T108: =T103 -> 0.3036 | U108: =U103 -> 0.255 | V108: =V103 -> 0.213 | W108: =W103 -> 0.1758 | ... AP108: =AP103 -> 0
M109: =M108/M107 -> 0.32 | N109: =N108/N107 -> 0.32352941 | O109: =O108/O107 -> 0.31578947 | P109: =P108/P107 -> 0.017282383 | Q109: =Q108/Q107 -> 0.021737672 | R109: =R108/R107 -> 0.011642798 | S109: =S108/S107 -> 0.017909513 | T109: =T108/T107 -> 0.016066042 | ... AP109: =AP108/AP107 -> #DIV/0!
H111: Carbon footprint renovation (MtCO2) | J111: =VLOOKUP($H111,output!$A$10:$AH$2201,J$1-$J$1+2) -> 0 | K111: =VLOOKUP($H111,output!$A$10:$AH$2201,K$1-$J$1+2) -> 2.623 | L111: =VLOOKUP($H111,output!$A$10:$AH$2201,L$1-$J$1+2) -> 1.589 | M111: =VLOOKUP($H111,output!$A$10:$AH$2201,M$1-$J$1+2) -> 2.347 | N111: =VLOOKUP($H111,output!$A$10:$AH$2201,N$1-$J$1+2) -> 2.543 | O111: =VLOOKUP($H111,output!$A$10:$AH$2201,O$1-$J$1+2) -> 2.459 | P111: =VLOOKUP($H111,output!$A$10:$AH$2201,P$1-$J$1+2) -> 2.301 | Q111: =VLOOKUP($H111,output!$A$10:$AH$2201,Q$1-$J$1+2) -> 2.664 | ... AP111: =VLOOKUP($H111,output!$A$10:$AH$2201,AP$1-$J$1+2) -> 0
H112: Carbon footprint construction (MtCO2) | J112: =VLOOKUP($H112,output!$A$10:$AH$2201,J$1-$J$1+2) -> 0 | K112: =VLOOKUP($H112,output!$A$10:$AH$2201,K$1-$J$1+2) -> 11.736 | L112: =VLOOKUP($H112,output!$A$10:$AH$2201,L$1-$J$1+2) -> 14.01 | M112: =VLOOKUP($H112,output!$A$10:$AH$2201,M$1-$J$1+2) -> 14.01 | N112: =VLOOKUP($H112,output!$A$10:$AH$2201,N$1-$J$1+2) -> 14.01 | O112: =VLOOKUP($H112,output!$A$10:$AH$2201,O$1-$J$1+2) -> 14.01 | P112: =VLOOKUP($H112,output!$A$10:$AH$2201,P$1-$J$1+2) -> 14.01 | Q112: =VLOOKUP($H112,output!$A$10:$AH$2201,Q$1-$J$1+2) -> 9.629 | ... AP112: =VLOOKUP($H112,output!$A$10:$AH$2201,AP$1-$J$1+2) -> 0
H113: Emission Natural gas (MtCO2) | J113: =VLOOKUP($H113,output!$A$10:$AH$2201,J$1-$J$1+2) -> 20.02 | K113: =VLOOKUP($H113,output!$A$10:$AH$2201,K$1-$J$1+2) -> 19.601 | L113: =VLOOKUP($H113,output!$A$10:$AH$2201,L$1-$J$1+2) -> 19.575 | M113: =VLOOKUP($H113,output!$A$10:$AH$2201,M$1-$J$1+2) -> 19.088 | N113: =VLOOKUP($H113,output!$A$10:$AH$2201,N$1-$J$1+2) -> 18.257 | O113: =VLOOKUP($H113,output!$A$10:$AH$2201,O$1-$J$1+2) -> 17.594 | P113: =VLOOKUP($H113,output!$A$10:$AH$2201,P$1-$J$1+2) -> 16.811 | Q113: =VLOOKUP($H113,output!$A$10:$AH$2201,Q$1-$J$1+2) -> 15.886 | ... AP113: =VLOOKUP($H113,output!$A$10:$AH$2201,AP$1-$J$1+2) -> 0
H114: Emission Oil fuel (MtCO2) | J114: =VLOOKUP($H114,output!$A$10:$AH$2201,J$1-$J$1+2) -> 10.044 | K114: =VLOOKUP($H114,output!$A$10:$AH$2201,K$1-$J$1+2) -> 9.04 | L114: =VLOOKUP($H114,output!$A$10:$AH$2201,L$1-$J$1+2) -> 8.182 | M114: =VLOOKUP($H114,output!$A$10:$AH$2201,M$1-$J$1+2) -> 7.23 | N114: =VLOOKUP($H114,output!$A$10:$AH$2201,N$1-$J$1+2) -> 6.14 | O114: =VLOOKUP($H114,output!$A$10:$AH$2201,O$1-$J$1+2) -> 5.237 | P114: =VLOOKUP($H114,output!$A$10:$AH$2201,P$1-$J$1+2) -> 4.379 | Q114: =VLOOKUP($H114,output!$A$10:$AH$2201,Q$1-$J$1+2) -> 3.559 | ... AP114: =VLOOKUP($H114,output!$A$10:$AH$2201,AP$1-$J$1+2) -> 0
H115: Emission Electricity (MtCO2) | J115: =VLOOKUP($H115,output!$A$10:$AH$2201,J$1-$J$1+2) -> 4.021 | K115: =VLOOKUP($H115,output!$A$10:$AH$2201,K$1-$J$1+2) -> 3.938 | L115: =VLOOKUP($H115,output!$A$10:$AH$2201,L$1-$J$1+2) -> 3.923 | M115: =VLOOKUP($H115,output!$A$10:$AH$2201,M$1-$J$1+2) -> 3.908 | N115: =VLOOKUP($H115,output!$A$10:$AH$2201,N$1-$J$1+2) -> 3.915 | O115: =VLOOKUP($H115,output!$A$10:$AH$2201,O$1-$J$1+2) -> 3.917 | P115: =VLOOKUP($H115,output!$A$10:$AH$2201,P$1-$J$1+2) -> 3.915 | Q115: =VLOOKUP($H115,output!$A$10:$AH$2201,Q$1-$J$1+2) -> 3.889 | ... AP115: =VLOOKUP($H115,output!$A$10:$AH$2201,AP$1-$J$1+2) -> 0
H119: Montant des aides (au sens du modèle)
H120: Cee (Billion euro) | J120: =VLOOKUP($H120,output!$A$10:$AH$2201,J$1-$J$1+2) -> 0 | K120: =VLOOKUP($H120,output!$A$10:$AH$2201,K$1-$J$1+2) -> 3.097 | L120: =VLOOKUP($H120,output!$A$10:$AH$2201,L$1-$J$1+2) -> 0 | M120: =VLOOKUP($H120,output!$A$10:$AH$2201,M$1-$J$1+2) -> 0 | N120: =VLOOKUP($H120,output!$A$10:$AH$2201,N$1-$J$1+2) -> 0 | O120: =VLOOKUP($H120,output!$A$10:$AH$2201,O$1-$J$1+2) -> 0 | P120: =VLOOKUP($H120,output!$A$10:$AH$2201,P$1-$J$1+2) -> 0 | Q120: =VLOOKUP($H120,output!$A$10:$AH$2201,Q$1-$J$1+2) -> 0 | ... AP120: =VLOOKUP($H120,output!$A$10:$AH$2201,AP$1-$J$1+2) -> 0
H121: Mpr (Billion euro) | J121: =VLOOKUP($H121,output!$A$10:$AH$2201,J$1-$J$1+2) -> 0 | K121: =VLOOKUP($H121,output!$A$10:$AH$2201,K$1-$J$1+2) -> 1.607 | L121: =VLOOKUP($H121,output!$A$10:$AH$2201,L$1-$J$1+2) -> 0 | M121: =VLOOKUP($H121,output!$A$10:$AH$2201,M$1-$J$1+2) -> 0 | N121: =VLOOKUP($H121,output!$A$10:$AH$2201,N$1-$J$1+2) -> 0 | O121: =VLOOKUP($H121,output!$A$10:$AH$2201,O$1-$J$1+2) -> 0 | P121: =VLOOKUP($H121,output!$A$10:$AH$2201,P$1-$J$1+2) -> 0 | Q121: =VLOOKUP($H121,output!$A$10:$AH$2201,Q$1-$J$1+2) -> 0 | ... AP121: =VLOOKUP($H121,output!$A$10:$AH$2201,AP$1-$J$1+2) -> 0
H122: Mpr multifamily (Billion euro) | J122: =VLOOKUP($H122,output!$A$10:$AH$2201,J$1-$J$1+2) -> 0 | K122: =VLOOKUP($H122,output!$A$10:$AH$2201,K$1-$J$1+2) -> 0.238 | L122: =VLOOKUP($H122,output!$A$10:$AH$2201,L$1-$J$1+2) -> 0 | M122: =VLOOKUP($H122,output!$A$10:$AH$2201,M$1-$J$1+2) -> 0 | N122: =VLOOKUP($H122,output!$A$10:$AH$2201,N$1-$J$1+2) -> 0 | O122: =VLOOKUP($H122,output!$A$10:$AH$2201,O$1-$J$1+2) -> 0 | P122: =VLOOKUP($H122,output!$A$10:$AH$2201,P$1-$J$1+2) -> 0 | Q122: =VLOOKUP($H122,output!$A$10:$AH$2201,Q$1-$J$1+2) -> 0 | ... AP122: =VLOOKUP($H122,output!$A$10:$AH$2201,AP$1-$J$1+2) -> 0
H123: Mpr serenite (Billion euro) | J123: =VLOOKUP($H123,output!$A$10:$AH$2201,J$1-$J$1+2) -> 0 | K123: =VLOOKUP($H123,output!$A$10:$AH$2201,K$1-$J$1+2) -> 0.007 | L123: =VLOOKUP($H123,output!$A$10:$AH$2201,L$1-$J$1+2) -> 0 | M123: =VLOOKUP($H123,output!$A$10:$AH$2201,M$1-$J$1+2) -> 0 | N123: =VLOOKUP($H123,output!$A$10:$AH$2201,N$1-$J$1+2) -> 0 | O123: =VLOOKUP($H123,output!$A$10:$AH$2201,O$1-$J$1+2) -> 0 | P123: =VLOOKUP($H123,output!$A$10:$AH$2201,P$1-$J$1+2) -> 0 | Q123: =VLOOKUP($H123,output!$A$10:$AH$2201,Q$1-$J$1+2) -> 0 | ... AP123: =VLOOKUP($H123,output!$A$10:$AH$2201,AP$1-$J$1+2) -> 0
H124: Mpr performance (Billion euro) | J124: =VLOOKUP($H124,output!$A$10:$AH$2201,J$1-$J$1+2) -> 0 | K124: =VLOOKUP($H124,output!$A$10:$AH$2201,K$1-$J$1+2) -> 0 | L124: =VLOOKUP($H124,output!$A$10:$AH$2201,L$1-$J$1+2) -> 0 | M124: =VLOOKUP($H124,output!$A$10:$AH$2201,M$1-$J$1+2) -> 0 | N124: =VLOOKUP($H124,output!$A$10:$AH$2201,N$1-$J$1+2) -> 0 | O124: =VLOOKUP($H124,output!$A$10:$AH$2201,O$1-$J$1+2) -> 0 | P124: =VLOOKUP($H124,output!$A$10:$AH$2201,P$1-$J$1+2) -> 0 | Q124: =VLOOKUP($H124,output!$A$10:$AH$2201,Q$1-$J$1+2) -> 0 | ... AP124: =VLOOKUP($H124,output!$A$10:$AH$2201,AP$1-$J$1+2) -> 0
H125: Over cap (Billion euro) | J125: =VLOOKUP($H125,output!$A$10:$AH$2201,J$1-$J$1+2) -> 0 | K125: =VLOOKUP($H125,output!$A$10:$AH$2201,K$1-$J$1+2) -> 0 | L125: =VLOOKUP($H125,output!$A$10:$AH$2201,L$1-$J$1+2) -> 0 | M125: =VLOOKUP($H125,output!$A$10:$AH$2201,M$1-$J$1+2) -> 0 | N125: =VLOOKUP($H125,output!$A$10:$AH$2201,N$1-$J$1+2) -> 0 | O125: =VLOOKUP($H125,output!$A$10:$AH$2201,O$1-$J$1+2) -> 0 | P125: =VLOOKUP($H125,output!$A$10:$AH$2201,P$1-$J$1+2) -> 0 | Q125: =VLOOKUP($H125,output!$A$10:$AH$2201,Q$1-$J$1+2) -> 0 | ... AP125: =VLOOKUP($H125,output!$A$10:$AH$2201,AP$1-$J$1+2) -> 0
H126: Part CEE de MPR copro | J126: =J122/4 -> 0 | K126: =K122/4 -> 0.0595 | L126: =L122/4 -> 0 | M126: =M122/4 -> 0 | N126: =N122/4 -> 0 | O126: =O122/4 -> 0 | P126: =P122/4 -> 0 | Q126: =Q122/4 -> 0 | ... AP126: =AP122/4 -> 0
H127: Part CEE de MPR Performance | J127: =J124/4 -> 0 | K127: =K124/4 -> 0 | L127: =L124/4 -> 0 | M127: =M124/4 -> 0 | N127: =N124/4 -> 0 | O127: =O124/4 -> 0 | P127: =P124/4 -> 0 | Q127: =Q124/4 -> 0 | ... AP127: =AP124/4 -> 0
...

Sheet Post traitement FE
A1: Taux de biogaz
B3: 2023 | C3: 2024 | D3: 2025 | E3: 2026 | F3: 2027 | G3: 2028 | H3: 2029 | I3: 2030 | J3: 2031 | K3: 2032 | L3: 2033 | M3: 2034 | N3: 2035 | O3: 2036 | P3: 2037 | Q3: 2038 | R3: 2039 | S3: 2040 | T3: 2041 | U3: 2042 | V3: 2043 | W3: 2044 | X3: 2045 | Y3: 2046 | Z3: 2047 | AA3: 2048 | AB3: 2049 | AC3: 2050 | AD3: 2045 | AE3: 2046 | AF3: 2047 | AG3: 2048 | AH3: 2049 | AI3: 2050
A4: Emission content Natural gas (gCO2/kWh) | B4: =VLOOKUP($A4,output!$A$9:$AI$2200,B$3-$B$3+2) -> 220 | C4: =VLOOKUP($A4,output!$A$9:$AI$2200,C$3-$B$3+2) -> 220 | D4: =VLOOKUP($A4,output!$A$9:$AI$2200,D$3-$B$3+2) -> 220 | E4: =VLOOKUP($A4,output!$A$9:$AI$2200,E$3-$B$3+2) -> 220 | F4: =VLOOKUP($A4,output!$A$9:$AI$2200,F$3-$B$3+2) -> 220 | G4: =VLOOKUP($A4,output!$A$9:$AI$2200,G$3-$B$3+2) -> 220 | H4: =VLOOKUP($A4,output!$A$9:$AI$2200,H$3-$B$3+2) -> 220 | I4: =VLOOKUP($A4,output!$A$9:$AI$2200,I$3-$B$3+2) -> 220 | ... AI4: =VLOOKUP($A4,output!$A$9:$AI$2200,AI$3-$B$3+2) -> 220
A5: Consumption Natural gas (TWh) | B5: =VLOOKUP($A5,output!$A$9:$AI$2200,B$3-$B$3+2) -> 91 | C5: =VLOOKUP($A5,output!$A$9:$AI$2200,C$3-$B$3+2) -> 89.097 | D5: =VLOOKUP($A5,output!$A$9:$AI$2200,D$3-$B$3+2) -> 88.979 | E5: =VLOOKUP($A5,output!$A$9:$AI$2200,E$3-$B$3+2) -> 86.764 | F5: =VLOOKUP($A5,output!$A$9:$AI$2200,F$3-$B$3+2) -> 82.988 | G5: =VLOOKUP($A5,output!$A$9:$AI$2200,G$3-$B$3+2) -> 79.972 | H5: =VLOOKUP($A5,output!$A$9:$AI$2200,H$3-$B$3+2) -> 76.412 | I5: =VLOOKUP($A5,output!$A$9:$AI$2200,I$3-$B$3+2) -> 72.209 | ... AI5: =VLOOKUP($A5,output!$A$9:$AI$2200,AI$3-$B$3+2) -> 18.159
A7: Recalcul FE Gaz | B7: 220.0992 | C7: 217.8746 | D7: 215.65 | E7: 211.11 | F7: 206.57 | G7: 202.03 | H7: 197.49 | I7: 192.95 | J7: 187.502 | K7: 182.054 | L7: 176.606 | M7: 171.158 | N7: 165.71 | O7: 157.538 | P7: 149.366 | Q7: 141.194 | R7: 133.022 | S7: 124.85 | T7: 117.586 | U7: 110.322 | V7: 103.058 | W7: 95.794 | X7: 88.53 | Y7: 70.824 | Z7: 53.118 | AA7: 35.412 | AB7: 17.706 | AC7: 0 | AD7: 88.53 | AE7: 70.824 | AF7: 53.118 | AG7: 35.412 | AH7: 17.706 | AI7: 0
A9: Emissions Gaz | B9: =B5*B7/1000 -> 20.029027 | C9: =C5*C7/1000 -> 19.411973 | D9: =D5*D7/1000 -> 19.188321 | E9: =E5*E7/1000 -> 18.316748 | F9: =F5*F7/1000 -> 17.142831 | G9: =G5*G7/1000 -> 16.156743 | H9: =H5*H7/1000 -> 15.090606 | I9: =I5*I7/1000 -> 13.932727 | ... AI9: =AI5*AI7/1000 -> 0

Sheet Parc et émission
J1: 2023 | K1: 2024 | L1: 2025 | M1: 2026 | N1: 2027 | O1: 2028 | P1: 2029 | Q1: 2030 | R1: 2031 | S1: 2032 | T1: 2033 | U1: 2034 | V1: 2035 | W1: 2036 | X1: 2037 | Y1: 2038 | Z1: 2039 | AA1: 2040 | AB1: 2041 | AC1: 2042 | AD1: 2043 | AE1: 2044 | AF1: 2045 | AG1: 2046 | AH1: 2047 | AI1: 2048 | AJ1: 2049 | AK1: 2050
H2: Emissions (calculées par le modèle)
H3: Emission Natural gas (MtCO2) | I3: Emissions du gaz (MtCO2) | J3: ='Post traitement FE'!B9 -> 20.029027 | K3: ='Post traitement FE'!C9 -> 19.411973 | L3: ='Post traitement FE'!D9 -> 19.188321 | M3: ='Post traitement FE'!E9 -> 18.316748 | N3: ='Post traitement FE'!F9 -> 17.142831 | O3: ='Post traitement FE'!G9 -> 16.156743 | P3: ='Post traitement FE'!H9 -> 15.090606 | Q3: ='Post traitement FE'!I9 -> 13.932727 | ... AK3: ='Post traitement FE'!AC9 -> 0
H4: Emission Oil fuel (MtCO2) | I4: Emissions du fioul (MtCO2) | J4: =VLOOKUP($H4,output!$A$9:$AI$2200,J$1-$J$1+2) -> 10.044 | K4: =VLOOKUP($H4,output!$A$9:$AI$2200,K$1-$J$1+2) -> 9.04 | L4: =VLOOKUP($H4,output!$A$9:$AI$2200,L$1-$J$1+2) -> 8.182 | M4: =VLOOKUP($H4,output!$A$9:$AI$2200,M$1-$J$1+2) -> 7.23 | N4: =VLOOKUP($H4,output!$A$9:$AI$2200,N$1-$J$1+2) -> 6.14 | O4: =VLOOKUP($H4,output!$A$9:$AI$2200,O$1-$J$1+2) -> 5.237 | P4: =VLOOKUP($H4,output!$A$9:$AI$2200,P$1-$J$1+2) -> 4.379 | Q4: =VLOOKUP($H4,output!$A$9:$AI$2200,Q$1-$J$1+2) -> 3.559 | ... AK4: =VLOOKUP($H4,output!$A$9:$AI$2200,AK$1-$J$1+2) -> 0
H5: Emission Electricity (MtCO2) | I5: Emissions de l'électricité (MtCO2) | J5: =VLOOKUP($H5,output!$A$9:$AI$2200,J$1-$J$1+2) -> 4.021 | K5: =VLOOKUP($H5,output!$A$9:$AI$2200,K$1-$J$1+2) -> 3.938 | L5: =VLOOKUP($H5,output!$A$9:$AI$2200,L$1-$J$1+2) -> 3.923 | M5: =VLOOKUP($H5,output!$A$9:$AI$2200,M$1-$J$1+2) -> 3.908 | N5: =VLOOKUP($H5,output!$A$9:$AI$2200,N$1-$J$1+2) -> 3.915 | O5: =VLOOKUP($H5,output!$A$9:$AI$2200,O$1-$J$1+2) -> 3.917 | P5: =VLOOKUP($H5,output!$A$9:$AI$2200,P$1-$J$1+2) -> 3.915 | Q5: =VLOOKUP($H5,output!$A$9:$AI$2200,Q$1-$J$1+2) -> 3.889 | ... AK5: =VLOOKUP($H5,output!$A$9:$AI$2200,AK$1-$J$1+2) -> 3.74
I7: Directes | J7: =J3+J4 -> 30.073027 | K7: =K3+K4 -> 28.451973 | L7: =L3+L4 -> 27.370321 | M7: =M3+M4 -> 25.546748 | N7: =N3+N4 -> 23.282831 | O7: =O3+O4 -> 21.393743 | P7: =P3+P4 -> 19.469606 | Q7: =Q3+Q4 -> 17.491727 | ... AK7: =AK3+AK4 -> 0
I8: Gain annuel | K8: =K7-L7 -> 1.0816519 | L8: =L7-M7 -> 1.8235733 | M8: =M7-N7 -> 2.2639169 | N8: =N7-O7 -> 1.889088 | O8: =O7-P7 -> 1.9241373 | P8: =P7-Q7 -> 1.9778793 | Q8: =Q7-R7 -> 1.9455901 | R8: =R7-S7 -> 1.9423734 | ... AJ8: =AJ7-AK7 -> 0.34462958 | AK8: =AK7-#REF! -> #REF!
H10: Année historique de sobriété : on estime que 2/3 du chemin est fait entre 2020 et 2023
H11: Hyp sobriété | I11: Economie d'énergie (2030/2020) | L11: 0.07
I12: Economie d'énergie (2050/2030) | L12: 0.03
I13: Chemin parcouru en 2023 | L13: =2/3 -> 0.66666667 | P13: Par rapport à 2023
H14: Hypothèse de sobriété (baisse température de consigne & individualisation frais en collectif) | J14: 1 | K14: =J14-(1-$L$13)*$L$11*1/7 -> 0.99666667 | L14: =K14-(1-$L$13)*$L$11*1/7 -> 0.99333333 | M14: =L14-(1-$L$13)*$L$11*1/7 -> 0.99 | N14: =M14-(1-$L$13)*$L$11*1/7 -> 0.98666667 | O14: =N14-(1-$L$13)*$L$11*1/7 -> 0.98333333 | P14: =O14-(1-$L$13)*$L$11*1/7 -> 0.98 | Q14: =P14-(1-$L$13)*$L$11*1/7 -> 0.97666667 | R14: =Q14+($AK$14-$Q$14)/20 -> 0.97516667 | S14: =R14+($AK$14-$Q$14)/20 -> 0.97366667 | T14: =S14+($AK$14-$Q$14)/20 -> 0.97216667 | U14: =T14+($AK$14-$Q$14)/20 -> 0.97066667 | V14: =U14+($AK$14-$Q$14)/20 -> 0.96916667 | W14: =V14+($AK$14-$Q$14)/20 -> 0.96766667 | X14: =W14+($AK$14-$Q$14)/20 -> 0.96616667 | Y14: =X14+($AK$14-$Q$14)/20 -> 0.96466667 | ... AJ14: =AI14+($AK$14-$Q$14)/20 -> 0.94816667 | AK14: =Q14-L12 -> 0.94666667
H15: Impact du changement climatique (RCP2.6) | J15: 0.97 | K15: 0.96 | L15: 0.95 | M15: 0.94 | N15: 0.93 | O15: 0.92 | P15: 0.91 | Q15: =100%-10% -> 0.9 | R15: =Q15+($AK$15-$Q$15)/20 -> 0.8975 | S15: =R15+($AK$15-$Q$15)/20 -> 0.895 | T15: =S15+($AK$15-$Q$15)/20 -> 0.8925 | U15: =T15+($AK$15-$Q$15)/20 -> 0.89 | V15: =U15+($AK$15-$Q$15)/20 -> 0.8875 | W15: =V15+($AK$15-$Q$15)/20 -> 0.885 | X15: =W15+($AK$15-$Q$15)/20 -> 0.8825 | Y15: =X15+($AK$15-$Q$15)/20 -> 0.88 | ... AJ15: =AI15+($AK$15-$Q$15)/20 -> 0.8525 | AK15: =100%-15% -> 0.85
H16: Variation de la demande induite | J16: =J14*J15 -> 0.97 | K16: =K14*K15 -> 0.9568 | L16: =L14*L15 -> 0.94366667 | M16: =M14*M15 -> 0.9306 | N16: =N14*N15 -> 0.9176 | O16: =O14*O15 -> 0.90466667 | P16: =P14*P15 -> 0.8918 | Q16: =Q14*Q15 -> 0.879 | ... AK16: =AK14*AK15 -> 0.80466667
H18: Emissions (incluant CC)
H19: Emissions du gaz (MtCO2) | J19: =J3*J$16 -> 19.428156 | K19: =K3*K$16 -> 18.573376 | L19: =L3*L$16 -> 18.107379 | M19: =M3*M$16 -> 17.045566 | N19: =N3*N$16 -> 15.730262 | O19: =O3*O$16 -> 14.616467 | P19: =P3*P$16 -> 13.457802 | Q19: =Q3*Q$16 -> 12.246867 | ... AK19: =AK3*AK$16 -> 0
H20: Emissions du fioul (MtCO2) | J20: =J4*J$16 -> 9.74268 | K20: =K4*K$16 -> 8.649472 | L20: =L4*L$16 -> 7.7210807 | M20: =M4*M$16 -> 6.728238 | N20: =N4*N$16 -> 5.634064 | O20: =O4*O$16 -> 4.7377393 | P20: =P4*P$16 -> 3.9051922 | Q20: =Q4*Q$16 -> 3.128361 | ... AK20: =AK4*AK$16 -> 0
H21: Emissions de l'électricité (MtCO2) | J21: =J5*J$16 -> 3.90037 | K21: =K5*K$16 -> 3.7678784 | L21: =L5*L$16 -> 3.7020043 | M21: =M5*M$16 -> 3.6367848 | N21: =N5*N$16 -> 3.592404 | O21: =O5*O$16 -> 3.5435793 | P21: =P5*P$16 -> 3.491397 | Q21: =Q5*Q$16 -> 3.418431 | ... AK21: =AK5*AK$16 -> 3.0094533
H23: Directes | J23: =SUM(J19:J20) -> 29.170836 | K23: =SUM(K19:K20) -> 27.222848 | L23: =SUM(L19:L20) -> 25.82846 | M23: =SUM(M19:M20) -> 23.773804 | N23: =SUM(N19:N20) -> 21.364326 | O23: =SUM(O19:O20) -> 19.354206 | P23: =SUM(P19:P20) -> 17.362995 | Q23: =SUM(Q19:Q20) -> 15.375228 | ... AK23: =SUM(AK19:AK20) -> 0
H24: Gain annuel | K24: =K23-J23 -> -1.9479884 | L24: =L23-K23 -> -1.3943881 | M24: =M23-L23 -> -2.0546562 | N24: =N23-M23 -> -2.4094779 | O24: =O23-N23 -> -2.0101196 | P24: =P23-O23 -> -1.9912118 | Q24: =Q23-P23 -> -1.9877669 | R24: =R23-Q23 -> -1.7690612 | ... AK24: =AK23-AJ23 -> -0.27856826
H25: Réduction vs 2019 | L25: =L23/$K23-1 -> -0.051221242 | M25: =M23/$K23-1 -> -0.12669667 | N25: =N23/$K23-1 -> -0.21520607 | O25: =O23/$K23-1 -> -0.2890455 | P25: =P23/$K23-1 -> -0.36219037 | Q25: =Q23/$K23-1 -> -0.4352087 | R25: =R23/$K23-1 -> -0.50019313 | S25: =S23/$K23-1 -> -0.5645294 | ... AK25: =AK23/$K23-1 -> -1
H27: Parc DPE
H29: Stock A (Million) | I29: A | J29: =VLOOKUP($H29,output!$A$9:$AJ$2200,J$1-$J$1+2) -> 0.397 | K29: =VLOOKUP($H29,output!$A$9:$AJ$2200,K$1-$J$1+2) -> 0.545 | L29: =VLOOKUP($H29,output!$A$9:$AJ$2200,L$1-$J$1+2) -> 0.757 | M29: =VLOOKUP($H29,output!$A$9:$AJ$2200,M$1-$J$1+2) -> 0.969 | N29: =VLOOKUP($H29,output!$A$9:$AJ$2200,N$1-$J$1+2) -> 1.182 | O29: =VLOOKUP($H29,output!$A$9:$AJ$2200,O$1-$J$1+2) -> 1.395 | P29: =VLOOKUP($H29,output!$A$9:$AJ$2200,P$1-$J$1+2) -> 1.606 | Q29: =VLOOKUP($H29,output!$A$9:$AJ$2200,Q$1-$J$1+2) -> 1.757 | ... AK29: =VLOOKUP($H29,output!$A$9:$AJ$2200,AK$1-$J$1+2) -> 4.232 | AL29: =(AK29+AK30)/SUM(AK29:AK35) -> 0.44809481
H30: Stock B (Million) | I30: B | J30: =VLOOKUP($H30,output!$A$9:$AJ$2200,J$1-$J$1+2) -> 2.156 | K30: =VLOOKUP($H30,output!$A$9:$AJ$2200,K$1-$J$1+2) -> 2.435 | L30: =VLOOKUP($H30,output!$A$9:$AJ$2200,L$1-$J$1+2) -> 2.686 | M30: =VLOOKUP($H30,output!$A$9:$AJ$2200,M$1-$J$1+2) -> 2.947 | N30: =VLOOKUP($H30,output!$A$9:$AJ$2200,N$1-$J$1+2) -> 3.224 | O30: =VLOOKUP($H30,output!$A$9:$AJ$2200,O$1-$J$1+2) -> 3.519 | P30: =VLOOKUP($H30,output!$A$9:$AJ$2200,P$1-$J$1+2) -> 3.834 | Q30: =VLOOKUP($H30,output!$A$9:$AJ$2200,Q$1-$J$1+2) -> 4.141 | ... AK30: =VLOOKUP($H30,output!$A$9:$AJ$2200,AK$1-$J$1+2) -> 11.044
H31: Stock C (Million) | I31: C | J31: =VLOOKUP($H31,output!$A$9:$AJ$2200,J$1-$J$1+2) -> 5.55 | K31: =VLOOKUP($H31,output!$A$9:$AJ$2200,K$1-$J$1+2) -> 6.018 | L31: =VLOOKUP($H31,output!$A$9:$AJ$2200,L$1-$J$1+2) -> 6.359 | M31: =VLOOKUP($H31,output!$A$9:$AJ$2200,M$1-$J$1+2) -> 6.835 | N31: =VLOOKUP($H31,output!$A$9:$AJ$2200,N$1-$J$1+2) -> 7.326 | O31: =VLOOKUP($H31,output!$A$9:$AJ$2200,O$1-$J$1+2) -> 7.843 | P31: =VLOOKUP($H31,output!$A$9:$AJ$2200,P$1-$J$1+2) -> 8.377 | Q31: =VLOOKUP($H31,output!$A$9:$AJ$2200,Q$1-$J$1+2) -> 8.945 | ... AK31: =VLOOKUP($H31,output!$A$9:$AJ$2200,AK$1-$J$1+2) -> 13.908
H32: Stock D (Million) | I32: D | J32: =VLOOKUP($H32,output!$A$9:$AJ$2200,J$1-$J$1+2) -> 12.774 | K32: =VLOOKUP($H32,output!$A$9:$AJ$2200,K$1-$J$1+2) -> 12.688 | L32: =VLOOKUP($H32,output!$A$9:$AJ$2200,L$1-$J$1+2) -> 12.639 | M32: =VLOOKUP($H32,output!$A$9:$AJ$2200,M$1-$J$1+2) -> 12.527 | N32: =VLOOKUP($H32,output!$A$9:$AJ$2200,N$1-$J$1+2) -> 12.387 | O32: =VLOOKUP($H32,output!$A$9:$AJ$2200,O$1-$J$1+2) -> 12.168 | P32: =VLOOKUP($H32,output!$A$9:$AJ$2200,P$1-$J$1+2) -> 11.876 | Q32: =VLOOKUP($H32,output!$A$9:$AJ$2200,Q$1-$J$1+2) -> 11.562 | ... AK32: =VLOOKUP($H32,output!$A$9:$AJ$2200,AK$1-$J$1+2) -> 4.746
H33: Stock E (Million) | I33: E | J33: =VLOOKUP($H33,output!$A$9:$AJ$2200,J$1-$J$1+2) -> 5.024 | K33: =VLOOKUP($H33,output!$A$9:$AJ$2200,K$1-$J$1+2) -> 4.841 | L33: =VLOOKUP($H33,output!$A$9:$AJ$2200,L$1-$J$1+2) -> 4.647 | M33: =VLOOKUP($H33,output!$A$9:$AJ$2200,M$1-$J$1+2) -> 4.446 | N33: =VLOOKUP($H33,output!$A$9:$AJ$2200,N$1-$J$1+2) -> 4.229 | O33: =VLOOKUP($H33,output!$A$9:$AJ$2200,O$1-$J$1+2) -> 4.001 | P33: =VLOOKUP($H33,output!$A$9:$AJ$2200,P$1-$J$1+2) -> 3.77 | Q33: =VLOOKUP($H33,output!$A$9:$AJ$2200,Q$1-$J$1+2) -> 3.54 | ... AK33: =VLOOKUP($H33,output!$A$9:$AJ$2200,AK$1-$J$1+2) -> 0.111
H34: Stock F (Million) | I34: F | J34: =VLOOKUP($H34,output!$A$9:$AJ$2200,J$1-$J$1+2) -> 2.927 | K34: =VLOOKUP($H34,output!$A$9:$AJ$2200,K$1-$J$1+2) -> 2.755 | L34: =VLOOKUP($H34,output!$A$9:$AJ$2200,L$1-$J$1+2) -> 2.62 | M34: =VLOOKUP($H34,output!$A$9:$AJ$2200,M$1-$J$1+2) -> 2.385 | N34: =VLOOKUP($H34,output!$A$9:$AJ$2200,N$1-$J$1+2) -> 2.17 | O34: =VLOOKUP($H34,output!$A$9:$AJ$2200,O$1-$J$1+2) -> 1.984 | P34: =VLOOKUP($H34,output!$A$9:$AJ$2200,P$1-$J$1+2) -> 1.823 | Q34: =VLOOKUP($H34,output!$A$9:$AJ$2200,Q$1-$J$1+2) -> 1.613 | ... AK34: =VLOOKUP($H34,output!$A$9:$AJ$2200,AK$1-$J$1+2) -> 0.047
H35: Stock G (Million) | I35: G | J35: =VLOOKUP($H35,output!$A$9:$AJ$2200,J$1-$J$1+2) -> 1.398 | K35: =VLOOKUP($H35,output!$A$9:$AJ$2200,K$1-$J$1+2) -> 1.162 | L35: =VLOOKUP($H35,output!$A$9:$AJ$2200,L$1-$J$1+2) -> 1.006 | M35: =VLOOKUP($H35,output!$A$9:$AJ$2200,M$1-$J$1+2) -> 0.872 | N35: =VLOOKUP($H35,output!$A$9:$AJ$2200,N$1-$J$1+2) -> 0.729 | O35: =VLOOKUP($H35,output!$A$9:$AJ$2200,O$1-$J$1+2) -> 0.605 | P35: =VLOOKUP($H35,output!$A$9:$AJ$2200,P$1-$J$1+2) -> 0.497 | Q35: =VLOOKUP($H35,output!$A$9:$AJ$2200,Q$1-$J$1+2) -> 0.403 | ... AK35: =VLOOKUP($H35,output!$A$9:$AJ$2200,AK$1-$J$1+2) -> 0.003
I37: Passoires | J37: =J34+J35 -> 4.325 | K37: =K34+K35 -> 3.917 | L37: =L34+L35 -> 3.626 | M37: =M34+M35 -> 3.257 | N37: =N34+N35 -> 2.899 | O37: =O34+O35 -> 2.589 | P37: =P34+P35 -> 2.32 | Q37: =Q34+Q35 -> 2.016 | ... AK37: =AK34+AK35 -> 0.05
H41: Parc de logements
H42: Stock new (Million) | I42: Neuf | J42: =VLOOKUP($H42,output!$A$9:$AJ$2200,J$1-$J$1+2) -> 0 | K42: =VLOOKUP($H42,output!$A$9:$AJ$2200,K$1-$J$1+2) -> 0.25 | L42: =VLOOKUP($H42,output!$A$9:$AJ$2200,L$1-$J$1+2) -> 0.548 | M42: =VLOOKUP($H42,output!$A$9:$AJ$2200,M$1-$J$1+2) -> 0.847 | N42: =VLOOKUP($H42,output!$A$9:$AJ$2200,N$1-$J$1+2) -> 1.145 | O42: =VLOOKUP($H42,output!$A$9:$AJ$2200,O$1-$J$1+2) -> 1.444 | P42: =VLOOKUP($H42,output!$A$9:$AJ$2200,P$1-$J$1+2) -> 1.742 | Q42: =VLOOKUP($H42,output!$A$9:$AJ$2200,Q$1-$J$1+2) -> 1.952 | ... AK42: =VLOOKUP($H42,output!$A$9:$AJ$2200,AK$1-$J$1+2) -> 4.942
H43: Stock existing (Million) | I43: Existant | J43: =VLOOKUP($H43,output!$A$9:$AJ$2200,J$1-$J$1+2) -> 30.225 | K43: =VLOOKUP($H43,output!$A$9:$AJ$2200,K$1-$J$1+2) -> 30.195 | L43: =VLOOKUP($H43,output!$A$9:$AJ$2200,L$1-$J$1+2) -> 30.165 | M43: =VLOOKUP($H43,output!$A$9:$AJ$2200,M$1-$J$1+2) -> 30.134 | N43: =VLOOKUP($H43,output!$A$9:$AJ$2200,N$1-$J$1+2) -> 30.103 | O43: =VLOOKUP($H43,output!$A$9:$AJ$2200,O$1-$J$1+2) -> 30.072 | P43: =VLOOKUP($H43,output!$A$9:$AJ$2200,P$1-$J$1+2) -> 30.04 | Q43: =VLOOKUP($H43,output!$A$9:$AJ$2200,Q$1-$J$1+2) -> 30.008 | ... AK43: =VLOOKUP($H43,output!$A$9:$AJ$2200,AK$1-$J$1+2) -> 29.15
H45: Stock (Million) | J45: =VLOOKUP($H45,output!$A$9:$AJ$2200,J$1-$J$1+2) -> 30.225 | K45: =VLOOKUP($H45,output!$A$9:$AJ$2200,K$1-$J$1+2) -> 30.445 | L45: =VLOOKUP($H45,output!$A$9:$AJ$2200,L$1-$J$1+2) -> 30.713 | M45: =VLOOKUP($H45,output!$A$9:$AJ$2200,M$1-$J$1+2) -> 30.981 | N45: =VLOOKUP($H45,output!$A$9:$AJ$2200,N$1-$J$1+2) -> 31.248 | O45: =VLOOKUP($H45,output!$A$9:$AJ$2200,O$1-$J$1+2) -> 31.515 | P45: =VLOOKUP($H45,output!$A$9:$AJ$2200,P$1-$J$1+2) -> 31.782 | Q45: =VLOOKUP($H45,output!$A$9:$AJ$2200,Q$1-$J$1+2) -> 31.961 | ... AK45: =VLOOKUP($H45,output!$A$9:$AJ$2200,AK$1-$J$1+2) -> 34.092

Sheet Consommation
L1: 2023 | M1: 2024 | N1: 2025 | O1: 2026 | P1: 2027 | Q1: 2028 | R1: 2029 | S1: 2030 | T1: 2031 | U1: 2032 | V1: 2033 | W1: 2034 | X1: 2035 | Y1: 2036 | Z1: 2037 | AA1: 2038 | AB1: 2039 | AC1: 2040 | AD1: 2041 | AE1: 2042 | AF1: 2043 | AG1: 2044 | AH1: 2045 | AI1: 2046 | AJ1: 2047 | AK1: 2048 | AL1: 2049 | AM1: 2050
J2: Consommation (calculée par le modèle)
J3: Consumption Heating (TWh) | K3: Chauffage urbain | L3: =VLOOKUP($J3,output!$A$9:$AI$2200,L$1-$L$1+2) -> 11.458 | M3: =VLOOKUP($J3,output!$A$9:$AI$2200,M$1-$L$1+2) -> 12.433 | N3: =VLOOKUP($J3,output!$A$9:$AI$2200,N$1-$L$1+2) -> 12.517 | O3: =VLOOKUP($J3,output!$A$9:$AI$2200,O$1-$L$1+2) -> 14.035 | P3: =VLOOKUP($J3,output!$A$9:$AI$2200,P$1-$L$1+2) -> 15.012 | Q3: =VLOOKUP($J3,output!$A$9:$AI$2200,Q$1-$L$1+2) -> 17.038 | R3: =VLOOKUP($J3,output!$A$9:$AI$2200,R$1-$L$1+2) -> 20.233 | S3: =VLOOKUP($J3,output!$A$9:$AI$2200,S$1-$L$1+2) -> 24.458 | ... AM3: =VLOOKUP($J3,output!$A$9:$AI$2200,AM$1-$L$1+2) -> 35.089 | AN3: Chauffage urbain
J4: Consumption Natural gas (TWh) | K4: Gaz | L4: =VLOOKUP($J4,output!$A$9:$AI$2200,L$1-$L$1+2) -> 91 | M4: =VLOOKUP($J4,output!$A$9:$AI$2200,M$1-$L$1+2) -> 89.097 | N4: =VLOOKUP($J4,output!$A$9:$AI$2200,N$1-$L$1+2) -> 88.979 | O4: =VLOOKUP($J4,output!$A$9:$AI$2200,O$1-$L$1+2) -> 86.764 | P4: =VLOOKUP($J4,output!$A$9:$AI$2200,P$1-$L$1+2) -> 82.988 | Q4: =VLOOKUP($J4,output!$A$9:$AI$2200,Q$1-$L$1+2) -> 79.972 | R4: =VLOOKUP($J4,output!$A$9:$AI$2200,R$1-$L$1+2) -> 76.412 | S4: =VLOOKUP($J4,output!$A$9:$AI$2200,S$1-$L$1+2) -> 72.209 | ... AM4: =VLOOKUP($J4,output!$A$9:$AI$2200,AM$1-$L$1+2) -> 18.159 | AN4: Gaz
J5: Consumption Oil fuel (TWh) | K5: Fioul | L5: =VLOOKUP($J5,output!$A$9:$AI$2200,L$1-$L$1+2) -> 31 | M5: =VLOOKUP($J5,output!$A$9:$AI$2200,M$1-$L$1+2) -> 27.903 | N5: =VLOOKUP($J5,output!$A$9:$AI$2200,N$1-$L$1+2) -> 25.252 | O5: =VLOOKUP($J5,output!$A$9:$AI$2200,O$1-$L$1+2) -> 22.315 | P5: =VLOOKUP($J5,output!$A$9:$AI$2200,P$1-$L$1+2) -> 18.951 | Q5: =VLOOKUP($J5,output!$A$9:$AI$2200,Q$1-$L$1+2) -> 16.163 | R5: =VLOOKUP($J5,output!$A$9:$AI$2200,R$1-$L$1+2) -> 13.514 | S5: =VLOOKUP($J5,output!$A$9:$AI$2200,S$1-$L$1+2) -> 10.984 | ... AM5: =VLOOKUP($J5,output!$A$9:$AI$2200,AM$1-$L$1+2) -> 0 | AN5: Fioul
J6: Consumption Wood fuel (TWh) | K6: Bois | L6: =VLOOKUP($J6,output!$A$9:$AI$2200,L$1-$L$1+2) -> 76.103 | M6: =VLOOKUP($J6,output!$A$9:$AI$2200,M$1-$L$1+2) -> 74.564 | N6: =VLOOKUP($J6,output!$A$9:$AI$2200,N$1-$L$1+2) -> 73.541 | O6: =VLOOKUP($J6,output!$A$9:$AI$2200,O$1-$L$1+2) -> 71.848 | P6: =VLOOKUP($J6,output!$A$9:$AI$2200,P$1-$L$1+2) -> 69.645 | Q6: =VLOOKUP($J6,output!$A$9:$AI$2200,Q$1-$L$1+2) -> 67.831 | R6: =VLOOKUP($J6,output!$A$9:$AI$2200,R$1-$L$1+2) -> 65.93 | S6: =VLOOKUP($J6,output!$A$9:$AI$2200,S$1-$L$1+2) -> 63.778 | ... AM6: =VLOOKUP($J6,output!$A$9:$AI$2200,AM$1-$L$1+2) -> 40.778 | AN6: Bois
J7: Consumption Heat pump (TWh) | K7: Electricité (pompe à chaleur) | L7: =VLOOKUP($J7,output!$A$9:$AI$2200,L$1-$L$1+2) -> 6.984 | M7: =VLOOKUP($J7,output!$A$9:$AI$2200,M$1-$L$1+2) -> 9.027 | N7: =VLOOKUP($J7,output!$A$9:$AI$2200,N$1-$L$1+2) -> 10.851 | O7: =VLOOKUP($J7,output!$A$9:$AI$2200,O$1-$L$1+2) -> 12.635 | P7: =VLOOKUP($J7,output!$A$9:$AI$2200,P$1-$L$1+2) -> 14.589 | Q7: =VLOOKUP($J7,output!$A$9:$AI$2200,Q$1-$L$1+2) -> 16.461 | R7: =VLOOKUP($J7,output!$A$9:$AI$2200,R$1-$L$1+2) -> 18.247 | S7: =VLOOKUP($J7,output!$A$9:$AI$2200,S$1-$L$1+2) -> 19.873 | ... AM7: =VLOOKUP($J7,output!$A$9:$AI$2200,AM$1-$L$1+2) -> 40.849 | AN7: Electricité (pompe à chaleur)
J8: Consumption Electricity-Heat pump air (TWh) | K8: dont PAC air/air | L8: =VLOOKUP($J8,output!$A$9:$AI$2200,L$1-$L$1+2) -> 1.397 | M8: =VLOOKUP($J8,output!$A$9:$AI$2200,M$1-$L$1+2) -> 2.376 | N8: =VLOOKUP($J8,output!$A$9:$AI$2200,N$1-$L$1+2) -> 3.727 | O8: =VLOOKUP($J8,output!$A$9:$AI$2200,O$1-$L$1+2) -> 5.024 | P8: =VLOOKUP($J8,output!$A$9:$AI$2200,P$1-$L$1+2) -> 6.437 | Q8: =VLOOKUP($J8,output!$A$9:$AI$2200,Q$1-$L$1+2) -> 7.787 | R8: =VLOOKUP($J8,output!$A$9:$AI$2200,R$1-$L$1+2) -> 9.07 | S8: =VLOOKUP($J8,output!$A$9:$AI$2200,S$1-$L$1+2) -> 10.276 | ... AM8: =VLOOKUP($J8,output!$A$9:$AI$2200,AM$1-$L$1+2) -> 26.337 | AN8: dont PAC air/air
J9: Consumption Electricity-Heat pump water (TWh) | K9: dont PAC air/eau | L9: =VLOOKUP($J9,output!$A$9:$AI$2200,L$1-$L$1+2) -> 5.587 | M9: =VLOOKUP($J9,output!$A$9:$AI$2200,M$1-$L$1+2) -> 6.651 | N9: =VLOOKUP($J9,output!$A$9:$AI$2200,N$1-$L$1+2) -> 7.124 | O9: =VLOOKUP($J9,output!$A$9:$AI$2200,O$1-$L$1+2) -> 7.611 | P9: =VLOOKUP($J9,output!$A$9:$AI$2200,P$1-$L$1+2) -> 8.152 | Q9: =VLOOKUP($J9,output!$A$9:$AI$2200,Q$1-$L$1+2) -> 8.674 | R9: =VLOOKUP($J9,output!$A$9:$AI$2200,R$1-$L$1+2) -> 9.176 | S9: =VLOOKUP($J9,output!$A$9:$AI$2200,S$1-$L$1+2) -> 9.598 | ... AM9: =VLOOKUP($J9,output!$A$9:$AI$2200,AM$1-$L$1+2) -> 14.512 | AN9: dont PAC air/eau
J10: Consumption Direct electric (TWh) | K10: Electricité (joule) | L10: =VLOOKUP($J10,output!$A$9:$AI$2200,L$1-$L$1+2) -> 43.913 | M10: =VLOOKUP($J10,output!$A$9:$AI$2200,M$1-$L$1+2) -> 40.822 | N10: =VLOOKUP($J10,output!$A$9:$AI$2200,N$1-$L$1+2) -> 38.813 | O10: =VLOOKUP($J10,output!$A$9:$AI$2200,O$1-$L$1+2) -> 36.839 | P10: =VLOOKUP($J10,output!$A$9:$AI$2200,P$1-$L$1+2) -> 34.963 | Q10: =VLOOKUP($J10,output!$A$9:$AI$2200,Q$1-$L$1+2) -> 33.127 | R10: =VLOOKUP($J10,output!$A$9:$AI$2200,R$1-$L$1+2) -> 31.307 | S10: =VLOOKUP($J10,output!$A$9:$AI$2200,S$1-$L$1+2) -> 29.36 | ... AM10: =VLOOKUP($J10,output!$A$9:$AI$2200,AM$1-$L$1+2) -> 6.488 | AN10: Electricité (joule)
K12: total | L12: =SUM(L3:L7,L10) -> 260.458 | M12: =SUM(M3:M7,M10) -> 253.846 | N12: =SUM(N3:N7,N10) -> 249.953 | O12: =SUM(O3:O7,O10) -> 244.436 | P12: =SUM(P3:P7,P10) -> 236.148 | Q12: =SUM(Q3:Q7,Q10) -> 230.592 | R12: =SUM(R3:R7,R10) -> 225.643 | S12: =SUM(S3:S7,S10) -> 220.662 | ... AM12: =SUM(AM3:AM7,AM10) -> 141.363
J14: Consommation (incluant CC)
J15: Chauffage urbain | K15: Voir post traitement dans l'onglet "géothermie et PAC hybride" | L15: =L3*'Parc et émission'!J$16 -> 11.11426 | M15: =M3*'Parc et émission'!K$16 -> 11.895894 | N15: =N3*'Parc et émission'!L$16 -> 11.811876 | O15: =O3*'Parc et émission'!M$16 -> 13.060971 | P15: =P3*'Parc et émission'!N$16 -> 13.775011 | Q15: =Q3*'Parc et émission'!O$16 -> 15.413711 | R15: =R3*'Parc et émission'!P$16 -> 18.043789 | S15: =S3*'Parc et émission'!Q$16 -> 21.498582 | ... AM15: =AM3*'Parc et émission'!AK$16 -> 28.234949
J16: Gaz | L16: =L4*'Parc et émission'!J$16 -> 88.27 | M16: =M4*'Parc et émission'!K$16 -> 85.24801 | N16: =N4*'Parc et émission'!L$16 -> 83.966516 | O16: =O4*'Parc et émission'!M$16 -> 80.742578 | P16: =P4*'Parc et émission'!N$16 -> 76.149789 | Q16: =Q4*'Parc et émission'!O$16 -> 72.348003 | R16: =R4*'Parc et émission'!P$16 -> 68.144222 | S16: =S4*'Parc et émission'!Q$16 -> 63.471711 | ... AM16: =AM4*'Parc et émission'!AK$16 -> 14.611942
J17: Fioul | L17: =L5*'Parc et émission'!J$16 -> 30.07 | M17: =M5*'Parc et émission'!K$16 -> 26.69759 | N17: =N5*'Parc et émission'!L$16 -> 23.829471 | O17: =O5*'Parc et émission'!M$16 -> 20.766339 | P17: =P5*'Parc et émission'!N$16 -> 17.389438 | Q17: =Q5*'Parc et émission'!O$16 -> 14.622127 | R17: =R5*'Parc et émission'!P$16 -> 12.051785 | S17: =S5*'Parc et émission'!Q$16 -> 9.654936 | ... AM17: =AM5*'Parc et émission'!AK$16 -> 0
J18: Bois | L18: =L6*'Parc et émission'!J$16 -> 73.81991 | M18: =M6*'Parc et émission'!K$16 -> 71.342835 | N18: =N6*'Parc et émission'!L$16 -> 69.39819 | O18: =O6*'Parc et émission'!M$16 -> 66.861749 | P18: =P6*'Parc et émission'!N$16 -> 63.906252 | Q18: =Q6*'Parc et émission'!O$16 -> 61.364445 | R18: =R6*'Parc et émission'!P$16 -> 58.796374 | S18: =S6*'Parc et émission'!Q$16 -> 56.060862 | ... AM18: =AM6*'Parc et émission'!AK$16 -> 32.812697
J19: Electricité (pompe à chaleur) | L19: =L7*'Parc et émission'!J$16 -> 6.77448 | M19: =M7*'Parc et émission'!K$16 -> 8.6370336 | N19: =N7*'Parc et émission'!L$16 -> 10.239727 | O19: =O7*'Parc et émission'!M$16 -> 11.758131 | P19: =P7*'Parc et émission'!N$16 -> 13.386866 | Q19: =Q7*'Parc et émission'!O$16 -> 14.891718 | R19: =R7*'Parc et émission'!P$16 -> 16.272675 | S19: =S7*'Parc et émission'!Q$16 -> 17.468367 | ... AM19: =AM7*'Parc et émission'!AK$16 -> 32.869829
J20: dont PAC air/air | L20: =L8*'Parc et émission'!J$16 -> 1.35509 | M20: =M8*'Parc et émission'!K$16 -> 2.2733568 | N20: =N8*'Parc et émission'!L$16 -> 3.5170457 | O20: =O8*'Parc et émission'!M$16 -> 4.6753344 | P20: =P8*'Parc et émission'!N$16 -> 5.9065912 | Q20: =Q8*'Parc et émission'!O$16 -> 7.0446393 | R20: =R8*'Parc et émission'!P$16 -> 8.088626 | S20: =S8*'Parc et émission'!Q$16 -> 9.032604 | ... AM20: =AM8*'Parc et émission'!AK$16 -> 21.192506
J21: dont PAC air/eau | L21: =L9*'Parc et émission'!J$16 -> 5.41939 | M21: =M9*'Parc et émission'!K$16 -> 6.3636768 | N21: =N9*'Parc et émission'!L$16 -> 6.7226813 | O21: =O9*'Parc et émission'!M$16 -> 7.0827966 | P21: =P9*'Parc et émission'!N$16 -> 7.4802752 | Q21: =Q9*'Parc et émission'!O$16 -> 7.8470787 | R21: =R9*'Parc et émission'!P$16 -> 8.1831568 | S21: =S9*'Parc et émission'!Q$16 -> 8.436642 | ... AM21: =AM9*'Parc et émission'!AK$16 -> 11.677323
J22: Electricité (joule) | L22: =L10*'Parc et émission'!J$16 -> 42.59561 | M22: =M10*'Parc et émission'!K$16 -> 39.05849 | N22: =N10*'Parc et émission'!L$16 -> 36.626534 | O22: =O10*'Parc et émission'!M$16 -> 34.282373 | P22: =P10*'Parc et émission'!N$16 -> 32.082049 | Q22: =Q10*'Parc et émission'!O$16 -> 29.968893 | R22: =R10*'Parc et émission'!P$16 -> 27.919583 | S22: =S10*'Parc et émission'!Q$16 -> 25.80744 | ... AM22: =AM10*'Parc et émission'!AK$16 -> 5.2206773
J23: Chaleur environnement (COP ->) | K23: 3.2 | L23: =L19*($K$23-1) -> 14.903856 | M23: =M19*($K$23-1) -> 19.001474 | N23: =N19*($K$23-1) -> 22.527399 | O23: =O19*($K$23-1) -> 25.867888 | P23: =P19*($K$23-1) -> 29.451106 | Q23: =Q19*($K$23-1) -> 32.76178 | R23: =R19*($K$23-1) -> 35.799884 | S23: =S19*($K$23-1) -> 38.430407 | ... AM23: =AM19*($K$23-1) -> 72.313623
K25: total sans chaleur envi | L25: =SUM(L15:L19,L22) -> 252.64426 | M25: =SUM(M15:M19,M22) -> 242.87985 | N25: =SUM(N15:N19,N22) -> 235.87231 | O25: =SUM(O15:O19,O22) -> 227.47214 | P25: =SUM(P15:P19,P22) -> 216.6894 | Q25: =SUM(Q15:Q19,Q22) -> 208.6089 | R25: =SUM(R15:R19,R22) -> 201.22843 | S25: =SUM(S15:S19,S22) -> 193.9619 | ... AM25: =SUM(AM15:AM19,AM22) -> 113.75009
K26: total avec chaleur envi | L26: =SUM(L15:L19,L22:L23) -> 267.54812 | M26: =SUM(M15:M19,M22:M23) -> 261.88133 | N26: =SUM(N15:N19,N22:N23) -> 258.39971 | O26: =SUM(O15:O19,O22:O23) -> 253.34003 | P26: =SUM(P15:P19,P22:P23) -> 246.14051 | Q26: =SUM(Q15:Q19,Q22:Q23) -> 241.37068 | R26: =SUM(R15:R19,R22:R23) -> 237.02831 | S26: =SUM(S15:S19,S22:S23) -> 232.39231 | ... AM26: =SUM(AM15:AM19,AM22:AM23) -> 186.06372
L27: =L16/L35 -> 7.4748074 | M27: =M16/M35 -> 7.3023822 | N27: =N16/N35 -> 7.2086638 | O27: =O16/O35 -> 7.0272044 | P27: =P16/P35 -> 6.7222624 | Q27: =Q16/Q35 -> 6.5372732 | R27: =R16/R35 -> 6.3715962 | S27: =S16/S35 -> 6.2087167
J28: Parc de logements par énergie
J29: Stock Direct electric (Million) | K29: Voir post traitement dans l'onglet "géothermie et PAC hybride" | L29: =VLOOKUP($J29,output!$A$9:$AI$2200,L$1-$L$1+2) -> 8.317 | M29: =VLOOKUP($J29,output!$A$9:$AI$2200,M$1-$L$1+2) -> 8.012 | N29: =VLOOKUP($J29,output!$A$9:$AI$2200,N$1-$L$1+2) -> 7.768 | O29: =VLOOKUP($J29,output!$A$9:$AI$2200,O$1-$L$1+2) -> 7.499 | P29: =VLOOKUP($J29,output!$A$9:$AI$2200,P$1-$L$1+2) -> 7.241 | Q29: =VLOOKUP($J29,output!$A$9:$AI$2200,Q$1-$L$1+2) -> 6.964 | R29: =VLOOKUP($J29,output!$A$9:$AI$2200,R$1-$L$1+2) -> 6.666 | S29: =VLOOKUP($J29,output!$A$9:$AI$2200,S$1-$L$1+2) -> 6.332 | ... AM29: =VLOOKUP($J29,output!$A$9:$AI$2200,AM$1-$L$1+2) -> 2.09 | AN29: Electricité (joule)
J30: Stock Heat pump (Million) | L30: =VLOOKUP($J30,output!$A$9:$AI$2200,L$1-$L$1+2) -> 2.896 | M30: =VLOOKUP($J30,output!$A$9:$AI$2200,M$1-$L$1+2) -> 3.642 | N30: =VLOOKUP($J30,output!$A$9:$AI$2200,N$1-$L$1+2) -> 4.368 | O30: =VLOOKUP($J30,output!$A$9:$AI$2200,O$1-$L$1+2) -> 5.054 | P30: =VLOOKUP($J30,output!$A$9:$AI$2200,P$1-$L$1+2) -> 5.799 | Q30: =VLOOKUP($J30,output!$A$9:$AI$2200,Q$1-$L$1+2) -> 6.511 | R30: =VLOOKUP($J30,output!$A$9:$AI$2200,R$1-$L$1+2) -> 7.184 | S30: =VLOOKUP($J30,output!$A$9:$AI$2200,S$1-$L$1+2) -> 7.756 | ... AM30: =VLOOKUP($J30,output!$A$9:$AI$2200,AM$1-$L$1+2) -> 17.817 | AN30: Electricité (pompe à chaleur)
J31: Stock Electricity-Heat pump air (Million) | L31: =VLOOKUP($J31,output!$A$9:$AI$2200,L$1-$L$1+2) -> 0.579 | M31: =VLOOKUP($J31,output!$A$9:$AI$2200,M$1-$L$1+2) -> 0.913 | N31: =VLOOKUP($J31,output!$A$9:$AI$2200,N$1-$L$1+2) -> 1.39 | O31: =VLOOKUP($J31,output!$A$9:$AI$2200,O$1-$L$1+2) -> 1.836 | P31: =VLOOKUP($J31,output!$A$9:$AI$2200,P$1-$L$1+2) -> 2.322 | Q31: =VLOOKUP($J31,output!$A$9:$AI$2200,Q$1-$L$1+2) -> 2.782 | R31: =VLOOKUP($J31,output!$A$9:$AI$2200,R$1-$L$1+2) -> 3.212 | S31: =VLOOKUP($J31,output!$A$9:$AI$2200,S$1-$L$1+2) -> 3.601 | ... AM31: =VLOOKUP($J31,output!$A$9:$AI$2200,AM$1-$L$1+2) -> 10.601 | AN31: dont PAC air/air
J32: Stock Electricity-Heat pump water (Million) | L32: =VLOOKUP($J32,output!$A$9:$AI$2200,L$1-$L$1+2) -> 2.317 | M32: =VLOOKUP($J32,output!$A$9:$AI$2200,M$1-$L$1+2) -> 2.729 | N32: =VLOOKUP($J32,output!$A$9:$AI$2200,N$1-$L$1+2) -> 2.978 | O32: =VLOOKUP($J32,output!$A$9:$AI$2200,O$1-$L$1+2) -> 3.218 | P32: =VLOOKUP($J32,output!$A$9:$AI$2200,P$1-$L$1+2) -> 3.477 | Q32: =VLOOKUP($J32,output!$A$9:$AI$2200,Q$1-$L$1+2) -> 3.729 | R32: =VLOOKUP($J32,output!$A$9:$AI$2200,R$1-$L$1+2) -> 3.972 | S32: =VLOOKUP($J32,output!$A$9:$AI$2200,S$1-$L$1+2) -> 4.155 | ... AM32: =VLOOKUP($J32,output!$A$9:$AI$2200,AM$1-$L$1+2) -> 7.216 | AN32: dont PAC air/eau
J33: Stock Oil fuel (Million) | L33: =VLOOKUP($J33,output!$A$9:$AI$2200,L$1-$L$1+2) -> 3.049 | M33: =VLOOKUP($J33,output!$A$9:$AI$2200,M$1-$L$1+2) -> 2.788 | N33: =VLOOKUP($J33,output!$A$9:$AI$2200,N$1-$L$1+2) -> 2.528 | O33: =VLOOKUP($J33,output!$A$9:$AI$2200,O$1-$L$1+2) -> 2.27 | P33: =VLOOKUP($J33,output!$A$9:$AI$2200,P$1-$L$1+2) -> 2.013 | Q33: =VLOOKUP($J33,output!$A$9:$AI$2200,Q$1-$L$1+2) -> 1.758 | R33: =VLOOKUP($J33,output!$A$9:$AI$2200,R$1-$L$1+2) -> 1.504 | S33: =VLOOKUP($J33,output!$A$9:$AI$2200,S$1-$L$1+2) -> 1.251 | ... AM33: =VLOOKUP($J33,output!$A$9:$AI$2200,AM$1-$L$1+2) -> 0 | AN33: Fioul
J34: Stock Wood fuel (Million) | L34: =VLOOKUP($J34,output!$A$9:$AI$2200,L$1-$L$1+2) -> 2.733 | M34: =VLOOKUP($J34,output!$A$9:$AI$2200,M$1-$L$1+2) -> 2.763 | N34: =VLOOKUP($J34,output!$A$9:$AI$2200,N$1-$L$1+2) -> 2.782 | O34: =VLOOKUP($J34,output!$A$9:$AI$2200,O$1-$L$1+2) -> 2.8 | P34: =VLOOKUP($J34,output!$A$9:$AI$2200,P$1-$L$1+2) -> 2.82 | Q34: =VLOOKUP($J34,output!$A$9:$AI$2200,Q$1-$L$1+2) -> 2.84 | R34: =VLOOKUP($J34,output!$A$9:$AI$2200,R$1-$L$1+2) -> 2.86 | S34: =VLOOKUP($J34,output!$A$9:$AI$2200,S$1-$L$1+2) -> 2.876 | ... AM34: =VLOOKUP($J34,output!$A$9:$AI$2200,AM$1-$L$1+2) -> 3.039 | AN34: Bois
B35: à tracer | C35: consumption wood fuel performance | J35: Stock Natural gas (Million) | L35: =VLOOKUP($J35,output!$A$9:$AI$2200,L$1-$L$1+2) -> 11.809 | M35: =VLOOKUP($J35,output!$A$9:$AI$2200,M$1-$L$1+2) -> 11.674 | N35: =VLOOKUP($J35,output!$A$9:$AI$2200,N$1-$L$1+2) -> 11.648 | O35: =VLOOKUP($J35,output!$A$9:$AI$2200,O$1-$L$1+2) -> 11.49 | P35: =VLOOKUP($J35,output!$A$9:$AI$2200,P$1-$L$1+2) -> 11.328 | Q35: =VLOOKUP($J35,output!$A$9:$AI$2200,Q$1-$L$1+2) -> 11.067 | R35: =VLOOKUP($J35,output!$A$9:$AI$2200,R$1-$L$1+2) -> 10.695 | S35: =VLOOKUP($J35,output!$A$9:$AI$2200,S$1-$L$1+2) -> 10.223 | ... AM35: =VLOOKUP($J35,output!$A$9:$AI$2200,AM$1-$L$1+2) -> 4.362 | AN35: Gaz naturel
J36: Stock District heating (Million) | L36: =VLOOKUP($J36,output!$A$9:$AI$2200,L$1-$L$1+2) -> 1.421 | M36: =VLOOKUP($J36,output!$A$9:$AI$2200,M$1-$L$1+2) -> 1.565 | N36: =VLOOKUP($J36,output!$A$9:$AI$2200,N$1-$L$1+2) -> 1.619 | O36: =VLOOKUP($J36,output!$A$9:$AI$2200,O$1-$L$1+2) -> 1.868 | P36: =VLOOKUP($J36,output!$A$9:$AI$2200,P$1-$L$1+2) -> 2.047 | Q36: =VLOOKUP($J36,output!$A$9:$AI$2200,Q$1-$L$1+2) -> 2.375 | R36: =VLOOKUP($J36,output!$A$9:$AI$2200,R$1-$L$1+2) -> 2.874 | S36: =VLOOKUP($J36,output!$A$9:$AI$2200,S$1-$L$1+2) -> 3.522 | ... AM36: =VLOOKUP($J36,output!$A$9:$AI$2200,AM$1-$L$1+2) -> 6.784 | AN36: Chauffage urbain
AM37: =AM35/L35-1 -> -0.63062071
K38: raccordement RCU/an | M38: =(M36-L36)*1000 -> 144 | N38: =(N36-M36)*1000 -> 54 | O38: =(O36-N36)*1000 -> 249 | P38: =(P36-O36)*1000 -> 179 | Q38: =(Q36-P36)*1000 -> 328 | R38: =(R36-Q36)*1000 -> 499 | S38: =(S36-R36)*1000 -> 648 | U38: =(U36-T36)*1000 -> 572 | V38: =(V36-U36)*1000 -> 506 | W38: =(W36-V36)*1000 -> 425 | X38: =(X36-W36)*1000 -> 355 | Y38: =(Y36-X36)*1000 -> 293 | Z38: =(Z36-Y36)*1000 -> 193 | AA38: =(AA36-Z36)*1000 -> 143 | AB38: =(AB36-AA36)*1000 -> 92 | ... AM38: =(AM36-AL36)*1000 -> 25
K39: Suppression gaz | M39: =(M35-L35)*1000 -> -135 | N39: =(N35-M35)*1000 -> -26 | O39: =(O35-N35)*1000 -> -158 | P39: =(P35-O35)*1000 -> -162 | Q39: =(Q35-P35)*1000 -> -261 | R39: =(R35-Q35)*1000 -> -372 | S39: =(S35-R35)*1000 -> -472 | U39: =(U35-T35)*1000 -> -456 | V39: =(V35-U35)*1000 -> -434 | W39: =(W35-V35)*1000 -> -402 | X39: =(X35-W35)*1000 -> -378 | Y39: =(Y35-X35)*1000 -> -436 | Z39: =(Z35-Y35)*1000 -> -391 | AA39: =(AA35-Z35)*1000 -> -371 | AB39: =(AB35-AA35)*1000 -> -275 | ... AM39: =(AM35-AL35)*1000 -> -197
X40: =1-X35/N35 -> 0.29532967
K41: Suppression fioul | M41: =(M33-L33)*1000 -> -261 | N41: =(N33-M33)*1000 -> -260 | O41: =(O33-N33)*1000 -> -258 | P41: =(P33-O33)*1000 -> -257 | Q41: =(Q33-P33)*1000 -> -255 | R41: =(R33-Q33)*1000 -> -254 | S41: =(S33-R33)*1000 -> -253 | T41: =(T33-S33)*1000 -> -252 | ... AM41: =(AM33-AL33)*1000 -> 0
J44: Logements existants/neufs conso
J46: Consumption (kWh/m2) | L46: =VLOOKUP($J46,output!$A$9:$AI$2200,L$1-$L$1+2) -> 100.415 | M46: =VLOOKUP($J46,output!$A$9:$AI$2200,M$1-$L$1+2) -> 97.086 | N46: =VLOOKUP($J46,output!$A$9:$AI$2200,N$1-$L$1+2) -> 94.679 | O46: =VLOOKUP($J46,output!$A$9:$AI$2200,O$1-$L$1+2) -> 91.71 | P46: =VLOOKUP($J46,output!$A$9:$AI$2200,P$1-$L$1+2) -> 87.767 | Q46: =VLOOKUP($J46,output!$A$9:$AI$2200,Q$1-$L$1+2) -> 84.904 | R46: =VLOOKUP($J46,output!$A$9:$AI$2200,R$1-$L$1+2) -> 82.317 | S46: =VLOOKUP($J46,output!$A$9:$AI$2200,S$1-$L$1+2) -> 80.018 | ... AM46: =VLOOKUP($J46,output!$A$9:$AI$2200,AM$1-$L$1+2) -> 47.92
J47: Consumption existing (KWh/m2) | L47: =VLOOKUP($J47,output!$A$9:$AI$2200,L$1-$L$1+2) -> 100.415 | M47: =VLOOKUP($J47,output!$A$9:$AI$2200,M$1-$L$1+2) -> 97.798 | N47: =VLOOKUP($J47,output!$A$9:$AI$2200,N$1-$L$1+2) -> 96.214 | O47: =VLOOKUP($J47,output!$A$9:$AI$2200,O$1-$L$1+2) -> 94 | P47: =VLOOKUP($J47,output!$A$9:$AI$2200,P$1-$L$1+2) -> 90.711 | Q47: =VLOOKUP($J47,output!$A$9:$AI$2200,Q$1-$L$1+2) -> 88.475 | R47: =VLOOKUP($J47,output!$A$9:$AI$2200,R$1-$L$1+2) -> 86.47 | S47: =VLOOKUP($J47,output!$A$9:$AI$2200,S$1-$L$1+2) -> 84.507 | ... AM47: =VLOOKUP($J47,output!$A$9:$AI$2200,AM$1-$L$1+2) -> 53.764
J48: Consumption new (KWh/m2) | L48: =VLOOKUP($J48,output!$A$9:$AI$2200,L$1-$L$1+2) -> 0 | M48: =VLOOKUP($J48,output!$A$9:$AI$2200,M$1-$L$1+2) -> 18.538 | N48: =VLOOKUP($J48,output!$A$9:$AI$2200,N$1-$L$1+2) -> 17.538 | O48: =VLOOKUP($J48,output!$A$9:$AI$2200,O$1-$L$1+2) -> 17.222 | P48: =VLOOKUP($J48,output!$A$9:$AI$2200,P$1-$L$1+2) -> 17.044 | Q48: =VLOOKUP($J48,output!$A$9:$AI$2200,Q$1-$L$1+2) -> 16.942 | R48: =VLOOKUP($J48,output!$A$9:$AI$2200,R$1-$L$1+2) -> 16.868 | S48: =VLOOKUP($J48,output!$A$9:$AI$2200,S$1-$L$1+2) -> 16.798 | ... AM48: =VLOOKUP($J48,output!$A$9:$AI$2200,AM$1-$L$1+2) -> 15.607
J53: Parc de logements par énergie
J54: Stock Multi-family Electricity-Heat pump air (Million) | L54: =VLOOKUP($J54,output!$A$9:$AI$2200,L$1-$L$1+2) -> 0.196 | M54: =VLOOKUP($J54,output!$A$9:$AI$2200,M$1-$L$1+2) -> 0.302 | N54: =VLOOKUP($J54,output!$A$9:$AI$2200,N$1-$L$1+2) -> 0.468 | O54: =VLOOKUP($J54,output!$A$9:$AI$2200,O$1-$L$1+2) -> 0.6 | P54: =VLOOKUP($J54,output!$A$9:$AI$2200,P$1-$L$1+2) -> 0.75 | Q54: =VLOOKUP($J54,output!$A$9:$AI$2200,Q$1-$L$1+2) -> 0.87 | R54: =VLOOKUP($J54,output!$A$9:$AI$2200,R$1-$L$1+2) -> 0.955 | S54: =VLOOKUP($J54,output!$A$9:$AI$2200,S$1-$L$1+2) -> 1.003 | ... AM54: =VLOOKUP($J54,output!$A$9:$AI$2200,AM$1-$L$1+2) -> 3.053
J55: Stock Single-family Electricity-Heat pump air (Million) | L55: =VLOOKUP($J55,output!$A$9:$AI$2200,L$1-$L$1+2) -> 0.383 | M55: =VLOOKUP($J55,output!$A$9:$AI$2200,M$1-$L$1+2) -> 0.611 | N55: =VLOOKUP($J55,output!$A$9:$AI$2200,N$1-$L$1+2) -> 0.922 | O55: =VLOOKUP($J55,output!$A$9:$AI$2200,O$1-$L$1+2) -> 1.236 | P55: =VLOOKUP($J55,output!$A$9:$AI$2200,P$1-$L$1+2) -> 1.572 | Q55: =VLOOKUP($J55,output!$A$9:$AI$2200,Q$1-$L$1+2) -> 1.912 | R55: =VLOOKUP($J55,output!$A$9:$AI$2200,R$1-$L$1+2) -> 2.257 | S55: =VLOOKUP($J55,output!$A$9:$AI$2200,S$1-$L$1+2) -> 2.598 | ... AM55: =VLOOKUP($J55,output!$A$9:$AI$2200,AM$1-$L$1+2) -> 7.548
J56: Stock Multi-family Electricity-Heat pump water (Million) | L56: =VLOOKUP($J56,output!$A$9:$AI$2200,L$1-$L$1+2) -> 0.783 | M56: =VLOOKUP($J56,output!$A$9:$AI$2200,M$1-$L$1+2) -> 0.903 | N56: =VLOOKUP($J56,output!$A$9:$AI$2200,N$1-$L$1+2) -> 1.006 | O56: =VLOOKUP($J56,output!$A$9:$AI$2200,O$1-$L$1+2) -> 1.097 | P56: =VLOOKUP($J56,output!$A$9:$AI$2200,P$1-$L$1+2) -> 1.196 | Q56: =VLOOKUP($J56,output!$A$9:$AI$2200,Q$1-$L$1+2) -> 1.285 | R56: =VLOOKUP($J56,output!$A$9:$AI$2200,R$1-$L$1+2) -> 1.361 | S56: =VLOOKUP($J56,output!$A$9:$AI$2200,S$1-$L$1+2) -> 1.406 | ... AM56: =VLOOKUP($J56,output!$A$9:$AI$2200,AM$1-$L$1+2) -> 2.679
J57: Stock Single-family Electricity-Heat pump water (Million) | L57: =VLOOKUP($J57,output!$A$9:$AI$2200,L$1-$L$1+2) -> 1.533 | M57: =VLOOKUP($J57,output!$A$9:$AI$2200,M$1-$L$1+2) -> 1.826 | N57: =VLOOKUP($J57,output!$A$9:$AI$2200,N$1-$L$1+2) -> 1.972 | O57: =VLOOKUP($J57,output!$A$9:$AI$2200,O$1-$L$1+2) -> 2.121 | P57: =VLOOKUP($J57,output!$A$9:$AI$2200,P$1-$L$1+2) -> 2.281 | Q57: =VLOOKUP($J57,output!$A$9:$AI$2200,Q$1-$L$1+2) -> 2.444 | R57: =VLOOKUP($J57,output!$A$9:$AI$2200,R$1-$L$1+2) -> 2.611 | S57: =VLOOKUP($J57,output!$A$9:$AI$2200,S$1-$L$1+2) -> 2.749 | ... AM57: =VLOOKUP($J57,output!$A$9:$AI$2200,AM$1-$L$1+2) -> 4.538
J58: Stock Multi-family Electricity-Performance boiler (Million) | L58: =VLOOKUP($J58,output!$A$9:$AI$2200,L$1-$L$1+2) -> 3.933 | M58: =VLOOKUP($J58,output!$A$9:$AI$2200,M$1-$L$1+2) -> 3.806 | N58: =VLOOKUP($J58,output!$A$9:$AI$2200,N$1-$L$1+2) -> 3.714 | O58: =VLOOKUP($J58,output!$A$9:$AI$2200,O$1-$L$1+2) -> 3.597 | P58: =VLOOKUP($J58,output!$A$9:$AI$2200,P$1-$L$1+2) -> 3.489 | Q58: =VLOOKUP($J58,output!$A$9:$AI$2200,Q$1-$L$1+2) -> 3.362 | R58: =VLOOKUP($J58,output!$A$9:$AI$2200,R$1-$L$1+2) -> 3.214 | S58: =VLOOKUP($J58,output!$A$9:$AI$2200,S$1-$L$1+2) -> 3.033 | ... AM58: =VLOOKUP($J58,output!$A$9:$AI$2200,AM$1-$L$1+2) -> 1.169
J59: Stock Single-family Electricity-Performance boiler (Million) | L59: =VLOOKUP($J59,output!$A$9:$AI$2200,L$1-$L$1+2) -> 4.384 | M59: =VLOOKUP($J59,output!$A$9:$AI$2200,M$1-$L$1+2) -> 4.206 | N59: =VLOOKUP($J59,output!$A$9:$AI$2200,N$1-$L$1+2) -> 4.054 | O59: =VLOOKUP($J59,output!$A$9:$AI$2200,O$1-$L$1+2) -> 3.902 | P59: =VLOOKUP($J59,output!$A$9:$AI$2200,P$1-$L$1+2) -> 3.752 | Q59: =VLOOKUP($J59,output!$A$9:$AI$2200,Q$1-$L$1+2) -> 3.602 | R59: =VLOOKUP($J59,output!$A$9:$AI$2200,R$1-$L$1+2) -> 3.451 | S59: =VLOOKUP($J59,output!$A$9:$AI$2200,S$1-$L$1+2) -> 3.299 | ... AM59: =VLOOKUP($J59,output!$A$9:$AI$2200,AM$1-$L$1+2) -> 0.922
J60: Stock Multi-family Heating-District heating (Million) | L60: =VLOOKUP($J60,output!$A$9:$AI$2200,L$1-$L$1+2) -> 1.156 | M60: =VLOOKUP($J60,output!$A$9:$AI$2200,M$1-$L$1+2) -> 1.3 | N60: =VLOOKUP($J60,output!$A$9:$AI$2200,N$1-$L$1+2) -> 1.353 | O60: =VLOOKUP($J60,output!$A$9:$AI$2200,O$1-$L$1+2) -> 1.602 | P60: =VLOOKUP($J60,output!$A$9:$AI$2200,P$1-$L$1+2) -> 1.781 | Q60: =VLOOKUP($J60,output!$A$9:$AI$2200,Q$1-$L$1+2) -> 2.11 | R60: =VLOOKUP($J60,output!$A$9:$AI$2200,R$1-$L$1+2) -> 2.608 | S60: =VLOOKUP($J60,output!$A$9:$AI$2200,S$1-$L$1+2) -> 3.256 | ... AM60: =VLOOKUP($J60,output!$A$9:$AI$2200,AM$1-$L$1+2) -> 6.519
J61: Stock Single-family Natural gas-Performance boiler (Million) | L61: =VLOOKUP($J61,output!$A$9:$AI$2200,L$1-$L$1+2) -> 4.883 | M61: =VLOOKUP($J61,output!$A$9:$AI$2200,M$1-$L$1+2) -> 4.815 | N61: =VLOOKUP($J61,output!$A$9:$AI$2200,N$1-$L$1+2) -> 4.818 | O61: =VLOOKUP($J61,output!$A$9:$AI$2200,O$1-$L$1+2) -> 4.814 | P61: =VLOOKUP($J61,output!$A$9:$AI$2200,P$1-$L$1+2) -> 4.772 | Q61: =VLOOKUP($J61,output!$A$9:$AI$2200,Q$1-$L$1+2) -> 4.723 | R61: =VLOOKUP($J61,output!$A$9:$AI$2200,R$1-$L$1+2) -> 4.663 | S61: =VLOOKUP($J61,output!$A$9:$AI$2200,S$1-$L$1+2) -> 4.593 | ... AM61: =VLOOKUP($J61,output!$A$9:$AI$2200,AM$1-$L$1+2) -> 1.783
J62: Stock Multi-family Natural gas-Performance boiler (Million) | L62: =VLOOKUP($J62,output!$A$9:$AI$2200,L$1-$L$1+2) -> 6.927 | M62: =VLOOKUP($J62,output!$A$9:$AI$2200,M$1-$L$1+2) -> 6.858 | N62: =VLOOKUP($J62,output!$A$9:$AI$2200,N$1-$L$1+2) -> 6.829 | O62: =VLOOKUP($J62,output!$A$9:$AI$2200,O$1-$L$1+2) -> 6.676 | P62: =VLOOKUP($J62,output!$A$9:$AI$2200,P$1-$L$1+2) -> 6.556 | Q62: =VLOOKUP($J62,output!$A$9:$AI$2200,Q$1-$L$1+2) -> 6.345 | R62: =VLOOKUP($J62,output!$A$9:$AI$2200,R$1-$L$1+2) -> 6.032 | S62: =VLOOKUP($J62,output!$A$9:$AI$2200,S$1-$L$1+2) -> 5.631 | ... AM62: =VLOOKUP($J62,output!$A$9:$AI$2200,AM$1-$L$1+2) -> 2.579
J63: Stock Single-family Natural gas-Standard boiler (Million) | L63: =VLOOKUP($J63,output!$A$9:$AI$2200,L$1-$L$1+2) -> 4.883 | M63: =VLOOKUP($J63,output!$A$9:$AI$2200,M$1-$L$1+2) -> 4.815 | N63: =VLOOKUP($J63,output!$A$9:$AI$2200,N$1-$L$1+2) -> 4.818 | O63: =VLOOKUP($J63,output!$A$9:$AI$2200,O$1-$L$1+2) -> 4.814 | P63: =VLOOKUP($J63,output!$A$9:$AI$2200,P$1-$L$1+2) -> 4.772 | Q63: =VLOOKUP($J63,output!$A$9:$AI$2200,Q$1-$L$1+2) -> 4.723 | R63: =VLOOKUP($J63,output!$A$9:$AI$2200,R$1-$L$1+2) -> 4.663 | S63: =VLOOKUP($J63,output!$A$9:$AI$2200,S$1-$L$1+2) -> 4.593 | ... AM63: =VLOOKUP($J63,output!$A$9:$AI$2200,AM$1-$L$1+2) -> 1.783
J64: Stock Multi-family Natural gas-Standard boiler (Million) | L64: =VLOOKUP($J64,output!$A$9:$AI$2200,L$1-$L$1+2) -> 6.927 | M64: =VLOOKUP($J64,output!$A$9:$AI$2200,M$1-$L$1+2) -> 6.858 | N64: =VLOOKUP($J64,output!$A$9:$AI$2200,N$1-$L$1+2) -> 6.829 | O64: =VLOOKUP($J64,output!$A$9:$AI$2200,O$1-$L$1+2) -> 6.676 | P64: =VLOOKUP($J64,output!$A$9:$AI$2200,P$1-$L$1+2) -> 6.556 | Q64: =VLOOKUP($J64,output!$A$9:$AI$2200,Q$1-$L$1+2) -> 6.345 | R64: =VLOOKUP($J64,output!$A$9:$AI$2200,R$1-$L$1+2) -> 6.032 | S64: =VLOOKUP($J64,output!$A$9:$AI$2200,S$1-$L$1+2) -> 5.631 | ... AM64: =VLOOKUP($J64,output!$A$9:$AI$2200,AM$1-$L$1+2) -> 2.579
J65: Stock Single-family Oil fuel-Performance boiler (Million) | L65: =VLOOKUP($J65,output!$A$9:$AI$2200,L$1-$L$1+2) -> 2.459 | M65: =VLOOKUP($J65,output!$A$9:$AI$2200,M$1-$L$1+2) -> 2.248 | N65: =VLOOKUP($J65,output!$A$9:$AI$2200,N$1-$L$1+2) -> 2.038 | O65: =VLOOKUP($J65,output!$A$9:$AI$2200,O$1-$L$1+2) -> 1.83 | P65: =VLOOKUP($J65,output!$A$9:$AI$2200,P$1-$L$1+2) -> 1.622 | Q65: =VLOOKUP($J65,output!$A$9:$AI$2200,Q$1-$L$1+2) -> 1.416 | R65: =VLOOKUP($J65,output!$A$9:$AI$2200,R$1-$L$1+2) -> 1.211 | S65: =VLOOKUP($J65,output!$A$9:$AI$2200,S$1-$L$1+2) -> 1.008 | ... AM65: =VLOOKUP($J65,output!$A$9:$AI$2200,AM$1-$L$1+2) -> 0
... J72: Stock Multi-family Wood fuel-Performance boiler (Million) | L72: =VLOOKUP($J72,output!$A$9:$AI$2200,L$1-$L$1+2) -> 0.59 | M72: =VLOOKUP($J72,output!$A$9:$AI$2200,M$1-$L$1+2) -> 0.54 | N72: =VLOOKUP($J72,output!$A$9:$AI$2200,N$1-$L$1+2) -> 0.49 | O72: =VLOOKUP($J72,output!$A$9:$AI$2200,O$1-$L$1+2) -> 0.44 | P72: =VLOOKUP($J72,output!$A$9:$AI$2200,P$1-$L$1+2) -> 0.391 | Q72: =VLOOKUP($J72,output!$A$9:$AI$2200,Q$1-$L$1+2) -> 0.341 | R72: =VLOOKUP($J72,output!$A$9:$AI$2200,R$1-$L$1+2) -> 0.292 | S72: =VLOOKUP($J72,output!$A$9:$AI$2200,S$1-$L$1+2) -> 0.244 | ... AM72: =VLOOKUP($J72,output!$A$9:$AI$2200,AM$1-$L$1+2) -> 0
J75: PAC air/air - LC | L75: =L54 -> 0.196 | M75: =M54 -> 0.302 | N75: =N54 -> 0.468 | O75: =O54 -> 0.6 | P75: =P54 -> 0.75 | Q75: =Q54 -> 0.87 | R75: =R54 -> 0.955 | S75: =S54 -> 1.003 | ... AM75: =AM54 -> 3.053
J76: PAC air/air - MI | L76: =L55 -> 0.383 | M76: =M55 -> 0.611 | N76: =N55 -> 0.922 | O76: =O55 -> 1.236 | P76: =P55 -> 1.572 | Q76: =Q55 -> 1.912 | R76: =R55 -> 2.257 | S76: =S55 -> 2.598 | ... AM76: =AM55 -> 7.548
J77: PAC air/eau - LC | L77: =L56 -> 0.783 | M77: =M56 -> 0.903 | N77: =N56 -> 1.006 | O77: =O56 -> 1.097 | P77: =P56 -> 1.196 | Q77: =Q56 -> 1.285 | R77: =R56 -> 1.361 | S77: =S56 -> 1.406 | ... AM77: =AM56 -> 2.679
J78: PAC air/eau - MI | L78: =L57 -> 1.533 | M78: =M57 -> 1.826 | N78: =N57 -> 1.972 | O78: =O57 -> 2.121 | P78: =P57 -> 2.281 | Q78: =Q57 -> 2.444 | R78: =R57 -> 2.611 | S78: =S57 -> 2.749 | ... AM78: =AM57 -> 4.538
J79: Joule - LC | L79: =L58 -> 3.933 | M79: =M58 -> 3.806 | N79: =N58 -> 3.714 | O79: =O58 -> 3.597 | P79: =P58 -> 3.489 | Q79: =Q58 -> 3.362 | R79: =R58 -> 3.214 | S79: =S58 -> 3.033 | ... AM79: =AM58 -> 1.169
J80: Joule - MI | L80: =L59 -> 4.384 | M80: =M59 -> 4.206 | N80: =N59 -> 4.054 | O80: =O59 -> 3.902 | P80: =P59 -> 3.752 | Q80: =Q59 -> 3.602 | R80: =R59 -> 3.451 | S80: =S59 -> 3.299 | ... AM80: =AM59 -> 0.922
J81: RCU - LC | L81: =L60 -> 1.156 | M81: =M60 -> 1.3 | N81: =N60 -> 1.353 | O81: =O60 -> 1.602 | P81: =P60 -> 1.781 | Q81: =Q60 -> 2.11 | R81: =R60 -> 2.608 | S81: =S60 -> 3.256 | ... AM81: =AM60 -> 6.519
J82: Gaz - LC | L82: =L62 -> 6.927 | M82: =M62 -> 6.858 | N82: =N62 -> 6.829 | O82: =O62 -> 6.676 | P82: =P62 -> 6.556 | Q82: =Q62 -> 6.345 | R82: =R62 -> 6.032 | S82: =S62 -> 5.631 | ... AM82: =AM62 -> 2.579
J83: Gaz - MI | L83: =L63 -> 4.883 | M83: =M63 -> 4.815 | N83: =N63 -> 4.818 | O83: =O63 -> 4.814 | P83: =P63 -> 4.772 | Q83: =Q63 -> 4.723 | R83: =R63 -> 4.663 | S83: =S63 -> 4.593 | ... AM83: =AM63 -> 1.783
J84: Fioul - LC | L84: =L68 -> 0.59 | M84: =M68 -> 0.54 | N84: =N68 -> 0.49 | O84: =O68 -> 0.44 | P84: =P68 -> 0.391 | Q84: =Q68 -> 0.341 | R84: =R68 -> 0.292 | S84: =S68 -> 0.244 | ... AM84: =AM68 -> 0
J85: Fioul - MI | L85: =L65 -> 2.459 | M85: =M65 -> 2.248 | N85: =N65 -> 2.038 | O85: =O65 -> 1.83 | P85: =P65 -> 1.622 | Q85: =Q65 -> 1.416 | R85: =R65 -> 1.211 | S85: =S65 -> 1.008 | ... AM85: =AM65 -> 0
J86: Bois - LC | L86: =L72 -> 0.59 | M86: =M72 -> 0.54 | N86: =N72 -> 0.49 | O86: =O72 -> 0.44 | P86: =P72 -> 0.391 | Q86: =Q72 -> 0.341 | R86: =R72 -> 0.292 | S86: =S72 -> 0.244 | ... AM86: =AM72 -> 0
J87: Bois - Mi | L87: =L70 -> 2.733 | M87: =M70 -> 2.763 | N87: =N70 -> 2.782 | O87: =O70 -> 2.8 | P87: =P70 -> 2.82 | Q87: =Q70 -> 2.84 | R87: =R70 -> 2.86 | S87: =S70 -> 2.876 | ... AM87: =AM70 -> 3.039
J91: Intensité conso logement avec CC et sobriété
L92: MWh/log/an
J93: Electricité (joule) | L93: =L22/L29 -> 5.1215114 | M93: =M22/M29 -> 4.8749987 | N93: =N22/N29 -> 4.7150533 | O93: =O22/O29 -> 4.5715927 | P93: =P22/P29 -> 4.4306102 | Q93: =Q22/Q29 -> 4.3034022 | R93: =R22/R29 -> 4.1883562 | S93: =S22/S29 -> 4.075717 | ... AM93: =AM22/AM29 -> 2.4979317
J94: Electricité (pompe à chaleur) | L94: =L19/L30 -> 2.3392541 | M94: =M19/M30 -> 2.3715084 | N94: =N19/N30 -> 2.3442598 | O94: =O19/O30 -> 2.3265 | P94: =P19/P30 -> 2.3084784 | Q94: =Q19/Q30 -> 2.287163 | R94: =R19/R30 -> 2.2651273 | S94: =S19/S30 -> 2.2522392 | ... AM94: =AM19/AM30 -> 1.8448576
J95: Fioul | L95: =L17/L33 -> 9.8622499 | M95: =M17/M33 -> 9.5758933 | N95: =N17/N33 -> 9.4262147 | O95: =O17/O33 -> 9.148167 | P95: =P17/P33 -> 8.6385681 | Q95: =Q17/Q33 -> 8.3174786 | R95: =R17/R33 -> 8.0131551 | S95: =S17/S33 -> 7.7177746 | ... AC95: =AC17/AC33 -> #DIV/0!
J96: Bois (ppl + secondaire) | L96: =L18/L34 -> 27.010578 | M96: =M18/M34 -> 25.820787 | N96: =N18/N34 -> 24.945431 | O96: =O18/O34 -> 23.879196 | P96: =P18/P34 -> 22.661791 | Q96: =Q18/Q34 -> 21.607199 | R96: =R18/R34 -> 20.558173 | S96: =S18/S34 -> 19.49265 | ... AM96: =AM18/AM34 -> 10.797202
J97: Gaz naturel | L97: =L16/L35 -> 7.4748074 | M97: =M16/M35 -> 7.3023822 | N97: =N16/N35 -> 7.2086638 | O97: =O16/O35 -> 7.0272044 | P97: =P16/P35 -> 6.7222624 | Q97: =Q16/Q35 -> 6.5372732 | R97: =R16/R35 -> 6.3715962 | S97: =S16/S35 -> 6.2087167 | ... AM97: =AM16/AM35 -> 3.3498262
J98: Chauffage urbain | L98: =L15/L36 -> 7.8214356 | M98: =M15/M36 -> 7.6012105 | N98: =N15/N36 -> 7.2957848 | O98: =O15/O36 -> 6.9919545 | P98: =P15/P36 -> 6.7293655 | Q98: =Q15/Q36 -> 6.4899834 | R98: =R15/R36 -> 6.2782844 | S98: =S15/S36 -> 6.1040835 | ... AM98: =AM15/AM36 -> 4.1619913

Sheet Consommation - post traitement
D1: 2022 | E1: 2023 | F1: 2024 | G1: 2025 | H1: 2026 | I1: 2027 | J1: 2028 | K1: 2029 | L1: 2030 | M1: 2031 | N1: 2032 | O1: 2033 | P1: 2034 | Q1: 2035 | R1: 2036 | S1: 2037 | T1: 2038 | U1: 2039 | V1: 2040 | W1: 2041 | X1: 2042 | Y1: 2043 | Z1: 2044 | AA1: 2045 | AB1: 2046 | AC1: 2047 | AD1: 2048 | AE1: 2049 | AF1: 2050
A2: 1. Géothermique de surface
A3: Hypothèses
A4: Objectifs PPE | D4: 3.2 | E4: =D4+($L$4-$D$4)/8 -> 4.05 | F4: =E4+($L$4-$D$4)/8 -> 4.9 | G4: =F4+($L$4-$D$4)/8 -> 5.75 | H4: =G4+($L$4-$D$4)/8 -> 6.6 | I4: =H4+($L$4-$D$4)/8 -> 7.45 | J4: =I4+($L$4-$D$4)/8 -> 8.3 | K4: =J4+($L$4-$D$4)/8 -> 9.15 | L4: 10 | M4: =L4+($Q$4-$L$4)/5 -> 11.2 | N4: =M4+($Q$4-$L$4)/5 -> 12.4 | O4: =N4+($Q$4-$L$4)/5 -> 13.6 | P4: =O4+($Q$4-$L$4)/5 -> 14.8 | Q4: 16 | R4: =Q4+($AF$4-$Q$4)/15 -> 17.266667 | S4: =R4+($AF$4-$Q$4)/15 -> 18.533333 | T4: =S4+($AF$4-$Q$4)/15 -> 19.8 | U4: =T4+($AF$4-$Q$4)/15 -> 21.066667 | V4: =U4+($AF$4-$Q$4)/15 -> 22.333333 | W4: =V4+($AF$4-$Q$4)/15 -> 23.6 | X4: =W4+($AF$4-$Q$4)/15 -> 24.866667 | Y4: =X4+($AF$4-$Q$4)/15 -> 26.133333 | ... AE4: =AD4+($AF$4-$Q$4)/15 -> 33.733333 | AF4: 35
A5: Hypothèse de répartition | B5: Résidentiel | C5: Tertiaire | AF5: A faire valider
B6: 0.65 | C6: 0.35
A7: COP PAC air/eau | B7: 3.2
A8: COP géothermique | B8: 4.2
A9: %MI | B9: % | C9: à compléter
A10: %LC | B10: %
A12: Input (sorties du modèle res irf)
A13: Consommation élec PAC air/eau (TWh) | E13: =Consommation!L21 -> 5.41939 | F13: =Consommation!M21 -> 6.3636768 | G13: =Consommation!N21 -> 6.7226813 | H13: =Consommation!O21 -> 7.0827966 | I13: =Consommation!P21 -> 7.4802752 | J13: =Consommation!Q21 -> 7.8470787 | K13: =Consommation!R21 -> 8.1831568 | L13: =Consommation!S21 -> 8.436642 | ... AF13: =Consommation!AM21 -> 11.677323
A14: Nombre de PAC air/eau (Millions) | E14: =Consommation!L32 -> 2.317 | F14: =Consommation!M32 -> 2.729 | G14: =Consommation!N32 -> 2.978 | H14: =Consommation!O32 -> 3.218 | I14: =Consommation!P32 -> 3.477 | J14: =Consommation!Q32 -> 3.729 | K14: =Consommation!R32 -> 3.972 | L14: =Consommation!S32 -> 4.155 | ... AF14: =Consommation!AM32 -> 7.216
A16: Calculs
A17: Trajectoire géothermie résidentiel (TWh thermique) | E17: =E4*$B$6 -> 2.6325 | F17: =F4*$B$6 -> 3.185 | G17: =G4*$B$6 -> 3.7375 | H17: =H4*$B$6 -> 4.29 | I17: =I4*$B$6 -> 4.8425 | J17: =J4*$B$6 -> 5.395 | K17: =K4*$B$6 -> 5.9475 | L17: =L4*$B$6 -> 6.5 | ... AF17: =AF4*$B$6 -> 22.75
A18: Trajectoire géothermique tertiaire (TWh thermique) | E18: =E4*$C$6 -> 1.4175 | F18: =F4*$C$6 -> 1.715 | G18: =G4*$C$6 -> 2.0125 | H18: =H4*$C$6 -> 2.31 | I18: =I4*$C$6 -> 2.6075 | J18: =J4*$C$6 -> 2.905 | K18: =K4*$C$6 -> 3.2025 | L18: =L4*$C$6 -> 3.5 | ... AF18: =AF4*$C$6 -> 12.25
A19: Attention, cette trajectoire ne repose sur aucune optimisation économique
A20: Besoin thermique PAC air/eau (TWh thermique) | E20: =E13*$B$7 -> 17.342048 | F20: =F13*$B$7 -> 20.363766 | G20: =G13*$B$7 -> 21.51258 | H20: =H13*$B$7 -> 22.664949 | I20: =I13*$B$7 -> 23.936881 | J20: =J13*$B$7 -> 25.110652 | K20: =K13*$B$7 -> 26.186102 | L20: =L13*$B$7 -> 26.997254 | ... AF20: =AF13*$B$7 -> 37.367433
A22: Après ajout des PAC géothermiques
A23: Besoin thermique PAC air/eau (TWh thermique) | E23: =E20-E17 -> 14.709548 | F23: =F20-F17 -> 17.178766 | G23: =G20-G17 -> 17.77508 | H23: =H20-H17 -> 18.374949 | I23: =I20-I17 -> 19.094381 | J23: =J20-J17 -> 19.715652 | K23: =K20-K17 -> 20.238602 | L23: =L20-L17 -> 20.497254 | ... AF23: =AF20-AF17 -> 14.617433
A24: Besoin thermique PAC géothermique (Millions) | E24: =E17 -> 2.6325 | F24: =F17 -> 3.185 | G24: =G17 -> 3.7375 | H24: =H17 -> 4.29 | I24: =I17 -> 4.8425 | J24: =J17 -> 5.395 | K24: =K17 -> 5.9475 | L24: =L17 -> 6.5 | ... AF24: =AF17 -> 22.75
A26: Consommation électrique PAC air/eau (TWh) | E26: =E23/$B$7 -> 4.5967338 | F26: =F23/$B$7 -> 5.3683643 | G26: =G23/$B$7 -> 5.5547126 | H26: =H23/$B$7 -> 5.7421716 | I26: =I23/$B$7 -> 5.966994 | J26: =J23/$B$7 -> 6.1611412 | K26: =K23/$B$7 -> 6.3245631 | L26: =L23/$B$7 -> 6.405392 | ... AF26: =AF23/$B$7 -> 4.5679477
A27: Consommation électrique PAC géothermique (TWh) | E27: =E24/$B$8 -> 0.62678571 | F27: =F24/$B$8 -> 0.75833333 | G27: =G24/$B$8 -> 0.88988095 | H27: =H24/$B$8 -> 1.0214286 | I27: =I24/$B$8 -> 1.1529762 | J27: =J24/$B$8 -> 1.2845238 | K27: =K24/$B$8 -> 1.4160714 | L27: =L24/$B$8 -> 1.547619 | ... AF27: =AF24/$B$8 -> 5.4166667
A28: Nombre de PAC géothermique (Millions) | E28: =E14*E24/E20 -> 0.35171754 | F28: =F14*F24/F20 -> 0.42682994 | G28: =G14*G24/G20 -> 0.51738447 | H28: =H14*H24/H20 -> 0.60909998 | I28: =I14*I24/I20 -> 0.70340713 | J28: =J14*J24/J20 -> 0.80117216 | K28: =K14*K24/K20 -> 0.90213771 | L28: =L14*L24/L20 -> 1.0003795 | ... AF28: =AF14*AF24/AF20 -> 4.3932373
A29: Nombre de PAC air/eau (Millions) | E29: =E14-E28 -> 1.9652825 | F29: =F14-F28 -> 2.3021701 | G29: =G14-G28 -> 2.4606155 | H29: =H14-H28 -> 2.6089 | I29: =I14-I28 -> 2.7735929 | J29: =J14-J28 -> 2.9278278 | K29: =K14-K28 -> 3.0698623 | L29: =L14-L28 -> 3.1546205 | ... AF29: =AF14-AF28 -> 2.8227627
A32: 2. PAC hybrides
A34: Hypothèses
A35: Trajectoire PAC hybrides (Millions) | D35: 0.02 | E35: =D35+($L$35-$D$35)/8 -> 0.03 | F35: =E35+($L$35-$D$35)/8 -> 0.04 | G35: =F35+($L$35-$D$35)/8 -> 0.05 | H35: =G35+($L$35-$D$35)/8 -> 0.06 | I35: =H35+($L$35-$D$35)/8 -> 0.07 | J35: =I35+($L$35-$D$35)/8 -> 0.08 | K35: =J35+($L$35-$D$35)/8 -> 0.09 | L35: 0.1 | M35: =L35+($Q$35-$L$35)/5 -> 0.16 | N35: =M35+($Q$35-$L$35)/5 -> 0.22 | O35: =N35+($Q$35-$L$35)/5 -> 0.28 | P35: =O35+($Q$35-$L$35)/5 -> 0.34 | Q35: 0.4 | R35: =Q35+($AF$35-$Q$35)/15 -> 0.46666667 | S35: =R35+($AF$35-$Q$35)/15 -> 0.53333333 | T35: =S35+($AF$35-$Q$35)/15 -> 0.6 | U35: =T35+($AF$35-$Q$35)/15 -> 0.66666667 | V35: =U35+($AF$35-$Q$35)/15 -> 0.73333333 | W35: =V35+($AF$35-$Q$35)/15 -> 0.8 | X35: =W35+($AF$35-$Q$35)/15 -> 0.86666667 | Y35: =X35+($AF$35-$Q$35)/15 -> 0.93333333 | ... AE35: =AD35+($AF$35-$Q$35)/15 -> 1.3333333 | AF35: 1.4
A36: Explications : RTE jusqu'à 2035 (scénario de référence) Post 2035 : rythme 2030-2035 prolongé Packagée et non packagée (appoint) | C36: %PAC hybride/PAC total | D36: =D35/Consommation!P30 -> 0.0034488705 | E36: =E35/Consommation!Q30 -> 0.0046075872 | F36: =F35/Consommation!R30 -> 0.0055679287 | G36: =G35/Consommation!S30 -> 0.006446622 | H36: =H35/Consommation!T30 -> 0.0071267371 | I36: =I35/Consommation!U30 -> 0.0077442195 | J36: =J35/Consommation!V30 -> 0.0082542303 | K36: =K35/Consommation!W30 -> 0.0086688499 | ... AA36: =AA35/Consommation!AM30 -> 0.059867916 | AB36: =AB35/Consommation!#REF! -> #REF! | AC36: =AC35/Consommation!#REF! -> #REF! | AD36: =AD35/Consommation!#REF! -> #REF! | AE36: =AE35/Consommation!#REF! -> #REF! | AF36: =AF35/Consommation!#REF! -> #REF!
A37: Hypothèse de répartition
A39: %MI | B39: 0.1
A40: %LC | B40: 0.9
A41: Ratio fonctionnement élec de la PAC hybride | B41: 0.7
A42: Ratio fonctionnement gaz de la PAC hybride | B42: 0.3
A43: COP PAC | B43: 3.2
A44: Rendement chaudière gaz | B44: 0.95
A46: Input (sorties du modèle res irf et post traitement pac géothermiques)
A48: Consommation électrique PAC air/eau - hors pac géo (TWh) | D48: =D26 -> 0 | E48: =E26 -> 4.5967338 | F48: =F26 -> 5.3683643 | G48: =G26 -> 5.5547126 | H48: =H26 -> 5.7421716 | I48: =I26 -> 5.966994 | J48: =J26 -> 6.1611412 | K48: =K26 -> 6.3245631 | ... AF48: =AF26 -> 4.5679477
A49: Nombre de PAC air/eau - hors pac géo (Millions) | D49: =D29 -> 0 | E49: =E29 -> 1.9652825 | F49: =F29 -> 2.3021701 | G49: =G29 -> 2.4606155 | H49: =H29 -> 2.6089 | I49: =I29 -> 2.7735929 | J49: =J29 -> 2.9278278 | K49: =K29 -> 3.0698623 | ... AF49: =AF29 -> 2.8227627
A50: Consommation électrique PAC air/eau - hors pac géo hors pac hybride (TWh) | E50: =E48*(1-E35/E49) -> 4.5265647 | F50: =F48*(1-F35/F49) -> 5.2750894 | G50: =G48*(1-G35/G49) -> 5.4418402 | H50: =H48*(1-H35/H49) -> 5.610112 | I50: =I48*(1-I35/I49) -> 5.8163988 | J50: =J48*(1-J35/J49) -> 5.9927941 | K50: =K48*(1-K35/K49) -> 6.1391441 | L50: =L48*(1-L35/L49) -> 6.2023441 | ... AF50: =AF48*(1-AF35/AF49) -> 2.3023917
A51: Consommation électrique PAC hybride | E51: =E48*E35/E49*$B$41 -> 0.049118338 | F51: =F48*F35/F49*$B$41 -> 0.065292397 | G51: =G48*G35/G49*$B$41 -> 0.079010694 | H51: =H48*H35/H49*$B$41 -> 0.092441721 | I51: =I48*I35/I49*$B$41 -> 0.10541659 | J51: =J48*J35/J49*$B$41 -> 0.11784296 | K51: =K48*K35/K49*$B$41 -> 0.12979327 | L51: =L48*L35/L49*$B$41 -> 0.14213356 | ... AF51: =AF48*AF35/AF49*$B$41 -> 1.5858892
A52: Consommation gaz PAC hybride | E52: =E48*E35/E49*$B$42*$B$43/$B$44 -> 0.070907676 | F52: =F48*F35/F49*$B$42*$B$43/$B$44 -> 0.094256693 | G52: =G48*G35/G49*$B$42*$B$43/$B$44 -> 0.11406055 | H52: =H48*H35/H49*$B$42*$B$43/$B$44 -> 0.1334497 | I52: =I48*I35/I49*$B$42*$B$43/$B$44 -> 0.15218034 | J52: =J48*J35/J49*$B$42*$B$43/$B$44 -> 0.17011916 | K52: =K48*K35/K49*$B$42*$B$43/$B$44 -> 0.18737074 | L52: =L48*L35/L49*$B$42*$B$43/$B$44 -> 0.20518529 | ... AF52: =AF48*AF35/AF49*$B$42*$B$43/$B$44 -> 2.2894039
A53: Nombre de PAC air/eau - hors pac géo hors PAC hybrides (Millions) | E53: =E49-E35 -> 1.9352825 | F53: =F49-F35 -> 2.2621701 | G53: =G49-G35 -> 2.4106155 | H53: =H49-H35 -> 2.5489 | I53: =I49-I35 -> 2.7035929 | J53: =J49-J35 -> 2.8478278 | K53: =K49-K35 -> 2.9798623 | L53: =L49-L35 -> 3.0546205 | ... AF53: =AF49-AF35 -> 1.4227627
A55: 4. Bois principal et secondaire | B55: Source : fichier du CIRED "calibration_consommation_2023_bois
A57: TWh | B57: coeff correctif
A58: Chauffage urbain | B58: 1 | E58: =Consommation!L15 -> 11.11426 | F58: =Consommation!M15 -> 11.895894 | G58: =Consommation!N15 -> 11.811876 | H58: =Consommation!O15 -> 13.060971 | I58: =Consommation!P15 -> 13.775011 | J58: =Consommation!Q15 -> 15.413711 | K58: =Consommation!R15 -> 18.043789 | L58: =Consommation!S15 -> 21.498582 | ... AF58: =Consommation!AM15 -> 28.234949
A59: Gaz | B59: 0.79478162 | E59: =Consommation!L16 -> 88.27 | F59: =Consommation!M16 -> 85.24801 | G59: =Consommation!N16 -> 83.966516 | H59: =Consommation!O16 -> 80.742578 | I59: =Consommation!P16 -> 76.149789 | J59: =Consommation!Q16 -> 72.348003 | K59: =Consommation!R16 -> 68.144222 | L59: =Consommation!S16 -> 63.471711 | ... AF59: =Consommation!AM16 -> 14.611942
A60: Fioul | B60: 0.77269007 | E60: =Consommation!L17 -> 30.07 | F60: =Consommation!M17 -> 26.69759 | G60: =Consommation!N17 -> 23.829471 | H60: =Consommation!O17 -> 20.766339 | I60: =Consommation!P17 -> 17.389438 | J60: =Consommation!Q17 -> 14.622127 | K60: =Consommation!R17 -> 12.051785 | L60: =Consommation!S17 -> 9.654936 | ... AF60: =Consommation!AM17 -> 0
A61: Bois | B61: 1 | E61: =Consommation!L18 -> 73.81991 | F61: =Consommation!M18 -> 71.342835 | G61: =Consommation!N18 -> 69.39819 | H61: =Consommation!O18 -> 66.861749 | I61: =Consommation!P18 -> 63.906252 | J61: =Consommation!Q18 -> 61.364445 | K61: =Consommation!R18 -> 58.796374 | L61: =Consommation!S18 -> 56.060862 | ... AF61: =Consommation!AM18 -> 32.812697
A62: Electricité (pompe à chaleur) | B62: 1 | E62: =Consommation!L19 -> 6.77448 | F62: =Consommation!M19 -> 8.6370336 | G62: =Consommation!N19 -> 10.239727 | H62: =Consommation!O19 -> 11.758131 | I62: =Consommation!P19 -> 13.386866 | J62: =Consommation!Q19 -> 14.891718 | K62: =Consommation!R19 -> 16.272675 | L62: =Consommation!S19 -> 17.468367 | ... AF62: =Consommation!AM19 -> 32.869829
A63: Electricité (joule) | B63: 0.83609383 | E63: =Consommation!L20 -> 1.35509 | F63: =Consommation!M20 -> 2.2733568 | G63: =Consommation!N20 -> 3.5170457 | H63: =Consommation!O20 -> 4.6753344 | I63: =Consommation!P20 -> 5.9065912 | J63: =Consommation!Q20 -> 7.0446393 | K63: =Consommation!R20 -> 8.088626 | L63: =Consommation!S20 -> 9.032604 | ... AF63: =Consommation!AM20 -> 21.192506
A65: total | E65: =SUM(E58:E63) -> 211.40374 | F65: =SUM(F58:F63) -> 206.09472 | G65: =SUM(G58:G63) -> 202.76283 | H65: =SUM(H58:H63) -> 197.8651 | I65: =SUM(I58:I63) -> 190.51395 | J65: =SUM(J58:J63) -> 185.68464 | K65: =SUM(K58:K63) -> 181.39747 | L65: =SUM(L58:L63) -> 177.18706 | ... AF65: =SUM(AF58:AF63) -> 129.72192
A68: Calcul intermédiaire
A69: =A59 -> Gaz | E69: =E59*(1/$B59-1) -> 22.791954 | F69: =F59*(1/$B59-1) -> 22.011654 | G69: =G59*(1/$B59-1) -> 21.680763 | H69: =H59*(1/$B59-1) -> 20.848319 | I69: =I59*(1/$B59-1) -> 19.662427 | J69: =J59*(1/$B59-1) -> 18.680779 | K69: =K59*(1/$B59-1) -> 17.595332 | L69: =L59*(1/$B59-1) -> 16.388856 | ... AF69: =AF59*(1/$B59-1) -> 3.7729093
A70: =A60 -> Fioul | E70: =E60*(1/$B60-1) -> 8.8459915 | F70: =F60*(1/$B60-1) -> 7.8538961 | G70: =G60*(1/$B60-1) -> 7.0101528 | H70: =H60*(1/$B60-1) -> 6.1090408 | I70: =I60*(1/$B60-1) -> 5.1156241 | J70: =J60*(1/$B60-1) -> 4.3015369 | K70: =K60*(1/$B60-1) -> 3.5453937 | L70: =L60*(1/$B60-1) -> 2.8402887 | ... AF70: =AF60*(1/$B60-1) -> 0
A71: =A61 -> Bois | E71: =E61*(1/$B61-1) -> 0 | F71: =F61*(1/$B61-1) -> 0 | G71: =G61*(1/$B61-1) -> 0 | H71: =H61*(1/$B61-1) -> 0 | I71: =I61*(1/$B61-1) -> 0 | J71: =J61*(1/$B61-1) -> 0 | K71: =K61*(1/$B61-1) -> 0 | L71: =L61*(1/$B61-1) -> 0 | ... AF71: =AF61*(1/$B61-1) -> 0
A72: =A62 -> Electricité (pompe à chaleur) | E72: =E62*(1/$B62-1) -> 0 | F72: =F62*(1/$B62-1) -> 0 | G72: =G62*(1/$B62-1) -> 0 | H72: =H62*(1/$B62-1) -> 0 | I72: =I62*(1/$B62-1) -> 0 | J72: =J62*(1/$B62-1) -> 0 | K72: =K62*(1/$B62-1) -> 0 | L72: =L62*(1/$B62-1) -> 0 | ... AF72: =AF62*(1/$B62-1) -> 0
A73: =A63 -> Electricité (joule) | E73: =E63*(1/$B63-1) -> 0.26564914 | F73: =F63*(1/$B63-1) -> 0.44566434 | G73: =G63*(1/$B63-1) -> 0.68947463 | H73: =H63*(1/$B63-1) -> 0.91654324 | I73: =I63*(1/$B63-1) -> 1.1579164 | J73: =J63*(1/$B63-1) -> 1.3810171 | K73: =K63*(1/$B63-1) -> 1.5856781 | L73: =L63*(1/$B63-1) -> 1.7707337 | ... AF73: =AF63*(1/$B63-1) -> 4.1545367
A75: Consommation bois - chauffage secondaire (TWh) | E75: =SUM(E69:E73) -> 31.903595 | F75: =SUM(F69:F73) -> 30.311215 | G75: =SUM(G69:G73) -> 29.380391 | H75: =SUM(H69:H73) -> 27.873903 | I75: =SUM(I69:I73) -> 25.935968 | J75: =SUM(J69:J73) -> 24.363333 | K75: =SUM(K69:K73) -> 22.726404 | L75: =SUM(L69:L73) -> 20.999878 | ... AF75: =SUM(AF69:AF73) -> 7.927446
A76: Consommation bois - chauffage principal (TWh) | E76: =E61-E75 -> 41.916315 | F76: =F61-F75 -> 41.031621 | G76: =G61-G75 -> 40.0178 | H76: =H61-H75 -> 38.987846 | I76: =I61-I75 -> 37.970284 | J76: =J61-J75 -> 37.001112 | K76: =K61-K75 -> 36.06997 | L76: =L61-L75 -> 35.060984 | ... AF76: =AF61-AF75 -> 24.885251
A78: 4. Bilan
A80: =Consommation!J14 -> Consommation (incluant CC)
A81: =Consommation!J15 -> Chauffage urbain | E81: =Consommation!L15 -> 11.11426 | F81: =Consommation!M15 -> 11.895894 | G81: =Consommation!N15 -> 11.811876 | H81: =Consommation!O15 -> 13.060971 | I81: =Consommation!P15 -> 13.775011 | J81: =Consommation!Q15 -> 15.413711 | K81: =Consommation!R15 -> 18.043789 | L81: =Consommation!S15 -> 21.498582 | ... AF81: =Consommation!AM15 -> 28.234949
A82: =Consommation!J16 -> Gaz | E82: =Consommation!L16+E52 -> 88.340908 | F82: =Consommation!M16+F52 -> 85.342266 | G82: =Consommation!N16+G52 -> 84.080577 | H82: =Consommation!O16+H52 -> 80.876028 | I82: =Consommation!P16+I52 -> 76.301969 | J82: =Consommation!Q16+J52 -> 72.518122 | K82: =Consommation!R16+K52 -> 68.331592 | L82: =Consommation!S16+L52 -> 63.676896 | ... AF82: =Consommation!AM16+AF52 -> 16.901346
A83: dont gaz - chaudière | E83: =Consommation!L16 -> 88.27 | F83: =Consommation!M16 -> 85.24801 | G83: =Consommation!N16 -> 83.966516 | H83: =Consommation!O16 -> 80.742578 | I83: =Consommation!P16 -> 76.149789 | J83: =Consommation!Q16 -> 72.348003 | K83: =Consommation!R16 -> 68.144222 | L83: =Consommation!S16 -> 63.471711 | ... AF83: =Consommation!AM16 -> 14.611942
A84: dont gaz - PAC hybride | E84: =E52 -> 0.070907676 | F84: =F52 -> 0.094256693 | G84: =G52 -> 0.11406055 | H84: =H52 -> 0.1334497 | I84: =I52 -> 0.15218034 | J84: =J52 -> 0.17011916 | K84: =K52 -> 0.18737074 | L84: =L52 -> 0.20518529 | ... AF84: =AF52 -> 2.2894039
A85: =Consommation!J17 -> Fioul | E85: =Consommation!L17 -> 30.07 | F85: =Consommation!M17 -> 26.69759 | G85: =Consommation!N17 -> 23.829471 | H85: =Consommation!O17 -> 20.766339 | I85: =Consommation!P17 -> 17.389438 | J85: =Consommation!Q17 -> 14.622127 | K85: =Consommation!R17 -> 12.051785 | L85: =Consommation!S17 -> 9.654936 | ... AF85: =Consommation!AM17 -> 0
A86: =Consommation!J18 -> Bois | E86: =Consommation!L18 -> 73.81991 | F86: =Consommation!M18 -> 71.342835 | G86: =Consommation!N18 -> 69.39819 | H86: =Consommation!O18 -> 66.861749 | I86: =Consommation!P18 -> 63.906252 | J86: =Consommation!Q18 -> 61.364445 | K86: =Consommation!R18 -> 58.796374 | L86: =Consommation!S18 -> 56.060862 | ... AF86: =Consommation!AM18 -> 32.812697
A87: dont chauffage principal | E87: =E76 -> 41.916315 | F87: =F76 -> 41.031621 | G87: =G76 -> 40.0178 | H87: =H76 -> 38.987846 | I87: =I76 -> 37.970284 | J87: =J76 -> 37.001112 | K87: =K76 -> 36.06997 | L87: =L76 -> 35.060984 | ... AF87: =AF76 -> 24.885251
A88: dont chauffage secondaire | E88: =E75 -> 31.903595 | F88: =F75 -> 30.311215 | G88: =G75 -> 29.380391 | H88: =H75 -> 27.873903 | I88: =I75 -> 25.935968 | J88: =J75 -> 24.363333 | K88: =K75 -> 22.726404 | L88: =L75 -> 20.999878 | ... AF88: =AF75 -> 7.927446
A89: =Consommation!J19 -> Electricité (pompe à chaleur) | E89: =E50+E51+E27+Consommation!L20 -> 6.5575587 | F89: =F50+F51+F27+Consommation!M20 -> 8.372072 | G89: =G50+G51+G27+Consommation!N20 -> 9.9277775 | H89: =H50+H51+H27+Consommation!O20 -> 11.399317 | I89: =I50+I51+I27+Consommation!P20 -> 12.981383 | J89: =J50+J51+J27+Consommation!Q20 -> 14.4398 | K89: =K50+K51+K27+Consommation!R20 -> 15.773635 | L89: =L50+L51+L27+Consommation!S20 -> 16.924701 | ... AF89: =AF50+AF51+AF27+Consommation!AM20 -> 30.497454
A90: =Consommation!J20 -> dont PAC air/air | E90: =Consommation!L20 -> 1.35509 | F90: =Consommation!M20 -> 2.2733568 | G90: =Consommation!N20 -> 3.5170457 | H90: =Consommation!O20 -> 4.6753344 | I90: =Consommation!P20 -> 5.9065912 | J90: =Consommation!Q20 -> 7.0446393 | K90: =Consommation!R20 -> 8.088626 | L90: =Consommation!S20 -> 9.032604 | ... AF90: =Consommation!AM20 -> 21.192506
A91: =Consommation!J21 -> dont PAC air/eau | E91: =E50 -> 4.5265647 | F91: =F50 -> 5.2750894 | G91: =G50 -> 5.4418402 | H91: =H50 -> 5.610112 | I91: =I50 -> 5.8163988 | J91: =J50 -> 5.9927941 | K91: =K50 -> 6.1391441 | L91: =L50 -> 6.2023441 | ... AF91: =AF50 -> 2.3023917
A92: dont PAC géothermique | E92: =E27 -> 0.62678571 | F92: =F27 -> 0.75833333 | G92: =G27 -> 0.88988095 | H92: =H27 -> 1.0214286 | I92: =I27 -> 1.1529762 | J92: =J27 -> 1.2845238 | K92: =K27 -> 1.4160714 | L92: =L27 -> 1.547619 | ... AF92: =AF27 -> 5.4166667
A93: dont PAC hybride | E93: =E51 -> 0.049118338 | F93: =F51 -> 0.065292397 | G93: =G51 -> 0.079010694 | H93: =H51 -> 0.092441721 | I93: =I51 -> 0.10541659 | J93: =J51 -> 0.11784296 | K93: =K51 -> 0.12979327 | L93: =L51 -> 0.14213356 | ... AF93: =AF51 -> 1.5858892
A94: =Consommation!J22 -> Electricité (joule) | E94: =Consommation!L22 -> 42.59561 | F94: =Consommation!M22 -> 39.05849 | G94: =Consommation!N22 -> 36.626534 | H94: =Consommation!O22 -> 34.282373 | I94: =Consommation!P22 -> 32.082049 | J94: =Consommation!Q22 -> 29.968893 | K94: =Consommation!R22 -> 27.919583 | L94: =Consommation!S22 -> 25.80744 | ... AF94: =Consommation!AM22 -> 5.2206773
A96: =Consommation!J28 -> Parc de logements par énergie
A97: =Consommation!J29 -> Stock Direct electric (Million) | E97: =Consommation!L29 -> 8.317 | F97: =Consommation!M29 -> 8.012 | G97: =Consommation!N29 -> 7.768 | H97: =Consommation!O29 -> 7.499 | I97: =Consommation!P29 -> 7.241 | J97: =Consommation!Q29 -> 6.964 | K97: =Consommation!R29 -> 6.666 | L97: =Consommation!S29 -> 6.332 | ... AF97: =Consommation!AM29 -> 2.09
A98: =Consommation!J30 -> Stock Heat pump (Million) | E98: =Consommation!L30 -> 2.896 | F98: =Consommation!M30 -> 3.642 | G98: =Consommation!N30 -> 4.368 | H98: =Consommation!O30 -> 5.054 | I98: =Consommation!P30 -> 5.799 | J98: =Consommation!Q30 -> 6.511 | K98: =Consommation!R30 -> 7.184 | L98: =Consommation!S30 -> 7.756 | ... AF98: =Consommation!AM30 -> 17.817
A99: PAC air/air | E99: =Consommation!L31 -> 0.579 | F99: =Consommation!M31 -> 0.913 | G99: =Consommation!N31 -> 1.39 | H99: =Consommation!O31 -> 1.836 | I99: =Consommation!P31 -> 2.322 | J99: =Consommation!Q31 -> 2.782 | K99: =Consommation!R31 -> 3.212 | L99: =Consommation!S31 -> 3.601 | ... AF99: =Consommation!AM31 -> 10.601 | AG99: Ca divise presque par 2 le nombre de PAC air/eau
A100: PAC air/eau | E100: =E53 -> 1.9352825 | F100: =F53 -> 2.2621701 | G100: =G53 -> 2.4106155 | H100: =H53 -> 2.5489 | I100: =I53 -> 2.7035929 | J100: =J53 -> 2.8478278 | K100: =K53 -> 2.9798623 | L100: =L53 -> 3.0546205 | ... AF100: =AF53 -> 1.4227627
A101: PAC géothermique | E101: =E28 -> 0.35171754 | F101: =F28 -> 0.42682994 | G101: =G28 -> 0.51738447 | H101: =H28 -> 0.60909998 | I101: =I28 -> 0.70340713 | J101: =J28 -> 0.80117216 | K101: =K28 -> 0.90213771 | L101: =L28 -> 1.0003795 | ... AF101: =AF28 -> 4.3932373
A102: PAC hybride | E102: =E35 -> 0.03 | F102: =F35 -> 0.04 | G102: =G35 -> 0.05 | H102: =H35 -> 0.06 | I102: =I35 -> 0.07 | J102: =J35 -> 0.08 | K102: =K35 -> 0.09 | L102: =L35 -> 0.1 | ... AF102: =AF35 -> 1.4
A103: =Consommation!J33 -> Stock Oil fuel (Million) | E103: =Consommation!L33 -> 3.049 | F103: =Consommation!M33 -> 2.788 | G103: =Consommation!N33 -> 2.528 | H103: =Consommation!O33 -> 2.27 | I103: =Consommation!P33 -> 2.013 | J103: =Consommation!Q33 -> 1.758 | K103: =Consommation!R33 -> 1.504 | L103: =Consommation!S33 -> 1.251 | ... AF103: =Consommation!AM33 -> 0
A104: =Consommation!J34 -> Stock Wood fuel (Million) | E104: =Consommation!L34 -> 2.733 | F104: =Consommation!M34 -> 2.763 | G104: =Consommation!N34 -> 2.782 | H104: =Consommation!O34 -> 2.8 | I104: =Consommation!P34 -> 2.82 | J104: =Consommation!Q34 -> 2.84 | K104: =Consommation!R34 -> 2.86 | L104: =Consommation!S34 -> 2.876 | ... AF104: =Consommation!AM34 -> 3.039
A105: =Consommation!J35 -> Stock Natural gas (Million) | E105: =Consommation!L35 -> 11.809 | F105: =Consommation!M35 -> 11.674 | G105: =Consommation!N35 -> 11.648 | H105: =Consommation!O35 -> 11.49 | I105: =Consommation!P35 -> 11.328 | J105: =Consommation!Q35 -> 11.067 | K105: =Consommation!R35 -> 10.695 | L105: =Consommation!S35 -> 10.223 | ... AF105: =Consommation!AM35 -> 4.362
A106: =Consommation!J36 -> Stock District heating (Million) | E106: =Consommation!L36 -> 1.421 | F106: =Consommation!M36 -> 1.565 | G106: =Consommation!N36 -> 1.619 | H106: =Consommation!O36 -> 1.868 | I106: =Consommation!P36 -> 2.047 | J106: =Consommation!Q36 -> 2.375 | K106: =Consommation!R36 -> 2.874 | L106: =Consommation!S36 -> 3.522 | ... AF106: =Consommation!AM36 -> 6.784
F107: =AF105/11.8-1 -> -0.63033898
A108: Intensité de consommation
A109: Chauffage urbain | E109: =E81/E106 -> 7.8214356 | F109: =F81/F106 -> 7.6012105 | G109: =G81/G106 -> 7.2957848 | H109: =H81/H106 -> 6.9919545 | I109: =I81/I106 -> 6.7293655 | J109: =J81/J106 -> 6.4899834 | K109: =K81/K106 -> 6.2782844 | L109: =L81/L106 -> 6.1040835 | ... AF109: =AF81/AF106 -> 4.1619913
A110: Gaz | E110: =E82/E105 -> 7.4808119 | F110: =F82/F105 -> 7.3104563 | G110: =G82/G105 -> 7.2184561 | H110: =H82/H105 -> 7.0388188 | I110: =I82/I105 -> 6.7356964 | J110: =J82/J105 -> 6.552645 | K110: =K82/K105 -> 6.3891157 | L110: =L82/L105 -> 6.2287877 | ... AF110: =AF82/AF105 -> 3.8746781
A111: Fioul | E111: =E85/E103 -> 9.8622499 | F111: =F85/F103 -> 9.5758933 | G111: =G85/G103 -> 9.4262147 | H111: =H85/H103 -> 9.148167 | I111: =I85/I103 -> 8.6385681 | J111: =J85/J103 -> 8.3174786 | K111: =K85/K103 -> 8.0131551 | L111: =L85/L103 -> 7.7177746 | ... AF111: =AF85/AF103 -> #DIV/0!
A112: Bois - principal | E112: =E87/E104 -> 15.337108 | F112: =F87/F104 -> 14.850387 | G112: =G87/G104 -> 14.384543 | H112: =H87/H104 -> 13.924231 | I112: =I87/I104 -> 13.46464 | J112: =J87/J104 -> 13.028561 | K112: =K87/K104 -> 12.611878 | L112: =L87/L104 -> 12.190884 | ... AF112: =AF87/AF104 -> 8.1886316
A113: Electricité (pompe à chaleur) | E113: =E89/E98 -> 2.2643504 | F113: =F89/F98 -> 2.2987567 | G113: =G89/G98 -> 2.2728428 | H113: =H89/H98 -> 2.2555039 | I113: =I89/I98 -> 2.2385554 | J113: =J89/J98 -> 2.2177546 | K113: =K89/K98 -> 2.1956619 | L113: =L89/L98 -> 2.1821429 | ... AF113: =AF89/AF98 -> 1.7117053
A114: Electricité (joule) | E114: =E94/E97 -> 5.1215114 | F114: =F94/F97 -> 4.8749987 | G114: =G94/G97 -> 4.7150533 | H114: =H94/H97 -> 4.5715927 | I114: =I94/I97 -> 4.4306102 | J114: =J94/J97 -> 4.3034022 | K114: =K94/K97 -> 4.1883562 | L114: =L94/L97 -> 4.075717 | ... AF114: =AF94/AF97 -> 2.4979317
A118: AMS run 2
A119: Chauffage urbain | E119: 11.370166 | F119: 11.300984 | G119: 13.966396 | H119: 16.234916 | I119: 18.146171 | J119: 19.720467 | K119: 21.11978 | L119: 22.313798 | M119: 22.993013 | N119: 23.856023 | O119: 24.210558 | P119: 24.640224 | Q119: 24.63425 | R119: 24.889297 | S119: 24.909105 | T119: 24.644421 | U119: 24.645654 | V119: 24.543325 | W119: 24.44206 | X119: 24.33814 | Y119: 24.292402 | Z119: 24.080938 | AA119: 24.008958 | AB119: 23.938488 | AC119: 23.871394 | AD119: 23.670887 | AE119: 23.613442 | AF119: 23.561155
A120: Gaz | E120: 119.28153 | F120: 115.49607 | G120: 109.19725 | H120: 103.24344 | I120: 97.274098 | J120: 91.566441 | K120: 86.40449 | L120: 80.44102 | M120: 75.492235 | N120: 71.934706 | O120: 67.819966 | P120: 64.743917 | Q120: 61.159311 | R120: 58.63387 | S120: 56.176377 | T120: 53.336604 | U120: 51.319227 | V120: 49.221094 | W120: 47.296536 | X120: 45.522867 | Y120: 43.91776 | Z120: 42.173879 | AA120: 40.789397 | AB120: 39.501563 | AC120: 38.301491 | AD120: 36.966337 | AE120: 35.924913 | AF120: 34.949515
A121: Fioul | E121: 26.281911 | F121: 20.706412 | G121: 16.4177 | H121: 13.072827 | I121: 10.425547 | J121: 8.4624328 | K121: 6.9787474 | L121: 5.1804699 | M121: 3.9900364 | N121: 2.7815288 | O121: 2.174826 | P121: 1.7965499 | Q121: 1.66689 | R121: 1.6230528 | S121: 1.6202102 | T121: 1 | U121: 0.5 | V121: 0 | W121: 0 | X121: 0 | Y121: 0 | Z121: 0 | AA121: 0 | AB121: 0 | AC121: 0 | AD121: 0 | AE121: 0 | AF121: 0
A122: Bois - principal (source calibration_consommation.xlsx | E122: 30.42196 | F122: 33.0734 | G122: 34.643942 | H122: 35.175498 | I122: 35.269442 | J122: 35.044012 | K122: 34.579142 | L122: 34.124047 | M122: 33.47878 | N122: 32.490042 | O122: 31.990666 | P122: 30.992195 | Q122: 30.252884 | R122: 29.087377 | S122: 28.362755 | T122: 27.663259 | U122: 26.897154 | V122: 26.434728 | W122: 25.86693 | X122: 25.150545 | Y122: 24.452569 | Z122: 23.777239 | AA122: 22.982266 | AB122: 22.337824 | AC122: 21.706439 | AD122: 21.087141 | AE122: 20.361234 | AF122: 19.768083 | AG122: 19.185563
...

Sheet Gestes de rénovation
