Workbook

Sheet Feuil1
A1: Interdiction de gaz en 2027, avec compensation RCU et PAC mais pas à 50/50 en 2040 car trop de RCU
A2: Le reste sur du joule

Sheet Tableau de bord
B2: 1. Conformité au décret tertiaire
E4: Bureaux | F4: Café Hôtels Restaurants | G4: Commerce | H4: Enseignement | I4: Habitat communautaire | J4: Santé social | K4: Sport Loisir Culture | L4: Transport | M4: Total | O4: Commentaire (AME 24)
C6: Surface du parc (milliers de m²) | E6: 261321 | F6: 76051 | G6: 247482 | H6: 224459 | I6: 72135 | J6: 138496 | K6: 73203 | L6: 31290 | M6: =SUM(E6:L6) -> 1124437 | O6: Màj à partir de l'étude d'impact DHUP (2023) pour l'AME 24
C8: Part Etat | E8: 0.1 | F8: 0 | G8: 0 | H8: 0.07 | I8: 0 | J8: 0.6 | K8: 0.06 | L8: 0.5 | M8: =SUMPRODUCT(E$6:L$6,E8:L8)/M$6 -> 0.12893476 | O8: Etude d'impact DHUP (avant 2023) utilisée pour l'AMS run 2 (voir onglet source)
C9: Part collectivités | E9: 0.1 | F9: 0 | G9: 0 | H9: 0.72 | I9: 0.1 | J9: 0.08 | K9: 0.85 | L9: 0 | M9: =SUMPRODUCT(E$6:L$6,E9:L9)/M$6 -> 0.23857122
C10: Part Privé | E10: 0.8 | F10: 1 | G10: 1 | H10: 0.21 | I10: 0.9 | J10: 0.32 | K10: 0.09 | L10: 0.5 | M10: =SUMPRODUCT(E$6:L$6,E10:L10)/M$6 -> 0.63249402 | Q10: Proportion du parc qui applique la trajectoire décret tertiaire
C12: Surfaces > 1000m² | E12: 0.76 | F12: 0.61 | G12: 0.74 | H12: 0.92 | I12: 0.85 | J12: 0.83 | K12: 0.77 | L12: 0.86 | M12: =SUMPRODUCT(E$6:L$6,E12:L12)/M$6 -> 0.79522123 | O12: Màj à partir de l'étude d'impact DHUP (2023) pour l'AME 24 (voir onglet source) | Q12: Ademe | R12: S2 | S12: S3 | T12: S4
C13: Surfaces > 500m² | E13: =MIN(100%, E12+0.175) -> 0.935 | F13: =MIN(100%, F12+0.175) -> 0.785 | G13: =MIN(100%, G12+0.175) -> 0.915 | H13: =MIN(100%, H12+0.175) -> 1 | I13: 0.9 | J13: =MIN(100%, J12+0.175) -> 1 | K13: =MIN(100%, K12+0.175) -> 0.945 | L13: =MIN(100%, L12+0.175) -> 1 | M13: =SUMPRODUCT(E$6:L$6,E13:L13)/M$6 -> 0.94164861 | O13: Hyp AMS run 2 : +17,5% pour les surfaces > 500m²
Q14: Bureaux | R14: 0.65 | S14: 0.65 | T14: 0.55
B15: AME | C15: Part de la surface assujettie qui applique les objectifs du décret tertiaire | D15: Etat | E15: 0.6 | F15: 0.6 | G15: 0.6 | H15: 0.6 | I15: 0.6 | J15: 0.6 | K15: 0.6 | L15: 0.6 | M15: =SUMPRODUCT(E$6:L$6,E15:L15)/M$6 -> 0.6 | O15: L'Analyse du taux de complétion d'Operat au 04/01/2024 de la DHUP estime un taux de complétion de 53% pour les branches. Si on considère qu'en AME, ce taux peut monter à 60% (sans relance de la DHUP pour inciter les inscriptions sur Operat), que 10% utilisent des dérogations type bâtiments historiques, on tombe à 50%. Sachant qu'une part des bâtiments hors Operat pourrait respecter la trajectoire DEET (proportion probablement faible) et qu'une part inscrite sur Operat ne respectera pas le DEET en AME. | Q15: Cafés-hôtels-restaurants | R15: 0.66 | S15: 0.66 | T15: 0.55
D16: Collectivités | E16: 0.5 | F16: 0.5 | G16: 0.5 | H16: 0.5 | I16: 0.5 | J16: 0.5 | K16: 0.5 | L16: 0.5 | M16: =SUMPRODUCT(E$6:L$6,E16:L16)/M$6 -> 0.5 | Q16: Commerce | R16: 0.52 | S16: 0.52 | T16: 0.42
D17: Privé | E17: 0.45 | F17: 0.45 | G17: 0.45 | H17: 0.45 | I17: 0.45 | J17: 0.45 | K17: 0.45 | L17: 0.45 | M17: =SUMPRODUCT(E$6:L$6,E17:L17)/M$6 -> 0.45 | Q17: Enseignement-recherche | R17: 0.85 | S17: 0.85 | T17: 0.75
Q18: Habitat communautaire | R18: 0.78 | S18: 0.78 | T18: 0.68
B19: AMS | C19: Part de la surface assujettie qui applique les objectifs du décret tertiaire | D19: Etat | E19: 1 | F19: 1 | G19: 1 | H19: 1 | I19: 1 | J19: 1 | K19: 1 | L19: 1 | M19: =SUMPRODUCT(E$6:L$6,E19:L19)/M$6 -> 1 | Q19: Santé | R19: 0.99 | S19: 0.99 | T19: 0.89
D20: Collectivités | E20: 0.95 | F20: 0.95 | G20: 0.95 | H20: 0.95 | I20: 0.95 | J20: 0.95 | K20: 0.95 | L20: 0.95 | M20: =SUMPRODUCT(E$6:L$6,E20:L20)/M$6 -> 0.95 | Q20: Sport, Loisirs, Culture | R20: 0.59 | S20: 0.59 | T20: 0.49
D21: Privé | E21: 0.9 | F21: 0.9 | G21: 0.9 | H21: 0.9 | I21: 0.9 | J21: 0.9 | K21: 0.9 | L21: 0.9 | M21: =SUMPRODUCT(E$6:L$6,E21:L21)/M$6 -> 0.9 | Q21: Transport | R21: 0.78 | S21: 0.58 | T21: 0.58
Q22: TOTAL | R22: 0.7085533 | S22: 0.71522963 | T22: 0.61947514
B24: AME | C24: Proportion du parc assujetti qui applique la trajectoire décret tertiaire | D24: Total | E24: =E8*E15+E9*E16+E10*E17 -> 0.47 | F24: =F8*F15+F9*F16+F10*F17 -> 0.45 | G24: =G8*G15+G9*G16+G10*G17 -> 0.45 | H24: =H8*H15+H9*H16+H10*H17 -> 0.4965 | I24: =I8*I15+I9*I16+I10*I17 -> 0.455 | J24: =J8*J15+J9*J16+J10*J17 -> 0.544 | K24: =K8*K15+K9*K16+K10*K17 -> 0.5015 | L24: =L8*L15+L9*L16+L10*L17 -> 0.525 | M24: =SUMPRODUCT(E$6:L$6,E24:L24)/M$6 -> 0.48126877
B25: AMS | D25: Total | E25: =E8*E19+E9*E20+E10*E21 -> 0.915 | F25: =F8*F19+F9*F20+F10*F21 -> 0.9 | G25: =G8*G19+G9*G20+G10*G21 -> 0.9 | H25: =H8*H19+H9*H20+H10*H21 -> 0.943 | I25: =I8*I19+I9*I20+I10*I21 -> 0.905 | J25: =J8*J19+J9*J20+J10*J21 -> 0.964 | K25: =K8*K19+K9*K20+K10*K21 -> 0.9485 | L25: =L8*L19+L9*L20+L10*L21 -> 0.95 | M25: =SUMPRODUCT(E$6:L$6,E25:L25)/M$6 -> 0.92482204
B27: AME | C27: Proportion du parc qui applique la trajectoire décret tertiaire | D27: Total | E27: =E12*E24 -> 0.3572 | F27: =F12*F24 -> 0.2745 | G27: =G12*G24 -> 0.333 | H27: =H12*H24 -> 0.45678 | I27: =I12*I24 -> 0.38675 | J27: =J12*J24 -> 0.45152 | K27: =K12*K24 -> 0.386155 | L27: =L12*L24 -> 0.4515 | M27: =SUMPRODUCT(E$6:L$6,E27:L27)/M$6 -> 0.38418054
B28: AMS | D28: Total | E28: =E13*E25 -> 0.855525 | F28: =F13*F25 -> 0.7065 | G28: =G13*G25 -> 0.8235 | H28: =H13*H25 -> 0.943 | I28: =I13*I25 -> 0.8145 | J28: =J13*J25 -> 0.964 | K28: =K13*K25 -> 0.8963325 | L28: =L13*L25 -> 0.95 | M28: =SUMPRODUCT(E$6:L$6,E28:L28)/M$6 -> 0.87187346
B31: 2. Gain énergétique en 2030 pour le parc qui respecte le décret tertiaire
A32: 2030 | P32: 2040 | AE32: 2050
B33: AMS run 3 | E33: Part du parc | F33: Gain en terme de consommation énergétique par m² en 2030 | G33: Commentaire | P33: 0.5 | AE33: 0.6
A34: BUREAUX | B34: Parc assujetti atteignant les valeurs absolues aujourd'hui | E34: 0.5 | F34: 0.2 | G34: Basé sur les VA publiées, au vu des données déclarées sur OPERAT. La diminution de conso vient de la tendance observée 2010-2020 au vu des données CEREN et OPERAT ; on suppose qu'ils ne font plus rien ensuite car ils ont déjà atteint les objectifs
B35: Parc visant la valeur absolue | E35: 0.25 | F35: 0.33 | G35: Basé sur les VA publiées, au vu des données déclarées sur OPERAT. On suppose qu'ils ont déjà fait 20% entre 2010 et 2020, et refont 10% sur la décennie suivante. Ceux-là choisissent la VA car au global c'est plus facile que la VR (40%)
B36: Parc visant la valeur relative | E36: 0.25 | F36: 0.45 | G36: Le reste
B37: Total | E37: =SUM(E34:E36) -> 1 | F37: {=MMULT(TRANSPOSE(E34:E36),F34:F36)} -> 0.295 | G37: Gain énergétique de plus en 2030 par rapport à 2010 pour les bureaux
A38: AUTRES BRANCHES | B38: Parc assujetti atteignant les valeurs absolues aujourd'hui | E38: 0.25 | F38: 0.2 | G38: Basé sur les VA publiées, au vu des données déclarées sur OPERAT. La diminution de conso vient de la tendance observée 2010-2020 au vu des données CEREN et OPERAT ; on suppose qu'ils ne font plus rien ensuite car ils ont déjà atteint les objectifs
B39: Parc visant la valeur absolue | E39: 0.25 | F39: 0.33 | G39: Basé sur les VA publiées, au vu des données déclarées sur OPERAT. On suppose qu'ils ont déjà fait 20% entre 2010 et 2020, et refont 10% sur la décennie suivante. Ceux-là choisissent la VA car au global c'est plus facile que la VR (40%)
B40: Parc visant la valeur relative | E40: 0.5 | F40: 0.45 | G40: Le reste
B41: Total | E41: =SUM(E38:E40) -> 1 | F41: {=MMULT(TRANSPOSE(E38:E40),F38:F40)} -> 0.3575 | G41: Gain énergétique de plus en 2030 par rapport à 2010 pour les autres branches
B44: Remarque 1 : L'année de référence est à choisir après 2010 pour respecter le décret tertiaire. La baisse relative affichée s'entend ici par rapport à 2020. On considère donc qu'une partie du parc a déjà fait les travaux (ligne "parc assujetti atteignant les valeurs absolues aujourd'hui")
B45: Remarque 2 : Pour 2040 et 2050, on applique directement les valeurs relatives de -50% en -60% en prévision de valeurs absolues ambitieuses et en absence de données pertinentes.
A47: 2030 | P47: 2040 | AE47: 2050
B48: AME 24 | E48: Part du parc | F48: Gain en termes de consommation énergétique par m² en 2030/2010 | G48: Commentaire | Q48: AME 24 | T48: Part du parc | U48: Gain en termes de consommation énergétique par m² en 2040/2010 | V48: Commentaire | AF48: AME 24 | AI48: Part du parc | AJ48: Gain en termes de consommation énergétique par m² en 2050/2010 | AK48: Commentaire
A49: BUREAUX | B49: Parc assujetti atteignant les valeurs absolues aujourd'hui | E49: 0.5 | F49: 0.2 | G49: Basé sur les VA publiées, au vu des données déclarées sur OPERAT. La diminution de conso vient de la tendance observée 2010-2020 au vu des données CEREN et OPERAT ; on suppose qu'ils ne font plus rien ensuite car ils ont déjà atteint les objectifs | P49: BUREAUX | Q49: Parc assujetti atteignant les valeurs absolues aujourd'hui | T49: 0.25 | U49: 0.3 | V49: On suppose que les VA sont réhaussées pour être ajustées sur les 25% les plus performants. Les valeurs devraient diminuer de l'ordre de 10% supplémentaire | AE49: BUREAUX | AF49: Parc assujetti atteignant les valeurs absolues aujourd'hui | AI49: 0.25 | AJ49: 0.4 | AK49: On suppose que les VA sont réhaussées pour être ajustées sur les 25% les plus performants. Les valeurs devraient diminuer de l'ordre de 10% supplémentaire
B50: Parc visant la valeur absolue | E50: 0.25 | F50: 0.3 | G50: Basé sur les VA publiées, au vu des données déclarées sur OPERAT. On suppose qu'ils ont déjà fait 20% entre 2010 et 2020, et refont 10% sur la décennie suivante. Ceux-là choisissent la VA car au global c'est plus facile que la VR (40%) | Q50: Parc visant la valeur absolue | T50: 0.25 | U50: 0.4 | AF50: Parc visant la valeur absolue | AI50: 0.25 | AJ50: 0.5
B51: Parc visant la valeur relative | E51: 0.25 | F51: 0.4 | G51: Le reste | Q51: Parc visant la valeur relative | T51: 0.5 | U51: 0.5 | AF51: Parc visant la valeur relative | AI51: 0.5 | AJ51: 0.6
B52: Total | E52: =SUM(E49:E51) -> 1 | F52: {=MMULT(TRANSPOSE(E49:E51),F49:F51)} -> 0.275 | G52: Gain énergétique de plus en 2030 par rapport à 2010 pour les bureaux | Q52: Total | T52: =SUM(T49:T51) -> 1 | U52: {=MMULT(TRANSPOSE(T49:T51),U49:U51)} -> 0.425 | V52: Gain énergétique de plus en 2040 par rapport à 2010 pour les bureaux | AF52: Total | AI52: =SUM(AI49:AI51) -> 1 | AJ52: {=MMULT(TRANSPOSE(AI49:AI51),AJ49:AJ51)} -> 0.525 | AK52: Gain énergétique de plus en 2050 par rapport à 2010 pour les bureaux
A53: AUTRES BRANCHES | B53: Parc assujetti atteignant les valeurs absolues aujourd'hui | E53: 0.25 | F53: 0.2 | G53: Basé sur les VA publiées, au vu des données déclarées sur OPERAT. La diminution de conso vient de la tendance observée 2010-2020 au vu des données CEREN et OPERAT ; on suppose qu'ils ne font plus rien ensuite car ils ont déjà atteint les objectifs | P53: AUTRES BRANCHES | Q53: Parc assujetti atteignant les valeurs absolues aujourd'hui | T53: 0.25 | U53: 0.3 | V53: On suppose que les VA sont réhaussées pour être ajustées sur les 25% les plus performants. Les valeurs devraient diminuer de l'ordre de 10% supplémentaire | AE53: AUTRES BRANCHES | AF53: Parc assujetti atteignant les valeurs absolues aujourd'hui | AI53: 0.25 | AJ53: 0.4 | AK53: On suppose que les VA sont réhaussées pour être ajustées sur les 25% les plus performants. Les valeurs devraient diminuer de l'ordre de 10% supplémentaire
B54: Parc visant la valeur absolue | E54: 0.25 | F54: 0.3 | G54: Basé sur les VA publiées, au vu des données déclarées sur OPERAT. On suppose qu'ils ont déjà fait 20% entre 2010 et 2020, et refont 10% sur la décennie suivante. Ceux-là choisissent la VA car au global c'est plus facile que la VR (40%) | Q54: Parc visant la valeur absolue | T54: 0.25 | U54: 0.4 | AF54: Parc visant la valeur absolue | AI54: 0.25 | AJ54: 0.5
B55: Parc visant la valeur relative | E55: 0.5 | F55: 0.4 | G55: Le reste | Q55: Parc visant la valeur relative | T55: 0.5 | U55: 0.5 | AF55: Parc visant la valeur relative | AI55: 0.5 | AJ55: 0.6
B56: Total | E56: =SUM(E53:E55) -> 1 | F56: {=MMULT(TRANSPOSE(E53:E55),F53:F55)} -> 0.325 | G56: Gain énergétique de plus en 2030 par rapport à 2010 pour les autres branches | Q56: Total | T56: =SUM(T53:T55) -> 1 | U56: {=MMULT(TRANSPOSE(T53:T55),U53:U55)} -> 0.425 | V56: Gain énergétique de plus en 2040 par rapport à 2010 pour les autres branches | AF56: Total | AI56: =SUM(AI53:AI55) -> 1 | AJ56: {=MMULT(TRANSPOSE(AI53:AI55),AJ53:AJ55)} -> 0.525 | AK56: Gain énergétique de plus en 2050 par rapport à 2010 pour les autres branches
B58: Remarque 1 : L'année de référence est à choisir après 2010 pour respecter le décret tertiaire. La baisse relative affichée s'entend ici par rapport à 2020. On considère donc qu'une partie du parc a déjà fait les travaux (ligne "parc assujetti atteignant les valeurs absolues aujourd'hui") | P58: Remarque 1 : Plus de distinction entre bureaux et reste pour les autres échéances, l'idée étant qu'on aura recalibré le niveau d'ambition d'ici-là. J'ai donc mis la même chose partout

Sheet Résultats
A1: Scénario AME | P1: Scénario AMS
A3: Consommation totale | P3: Consommation totale
B7: Surface chauffée - Scénario AME [thousand sq m] | Y7: Surface chauffée - Scénario AMS [thousand sq m]
A8: Catégorie | C8: 2020 | D8: 2030 | E8: 2040 | F8: 2050 | X8: Catégorie | Z8: 2020 | AA8: 2030 | AB8: 2040 | AC8: 2050
A9: Bureaux | B9: Neuf post 2020 | C9: ='Bureaux - AME'!H8 -> 0 | D9: ='Bureaux - AME'!I8 -> 6206.4099 | E9: ='Bureaux - AME'!J8 -> 6411.8445 | F9: ='Bureaux - AME'!K8 -> 5961.6497 | X9: Bureaux | Y9: Neuf post 2020 | Z9: ='Bureaux - AMS'!H8 -> 0 | AA9: ='Bureaux - AMS'!I8 -> 6206.4099 | AB9: ='Bureaux - AMS'!J8 -> 5920.8739 | AC9: ='Bureaux - AMS'!K8 -> 5623.8459
B10: Existant 2020 | C10: ='Bureaux - AME'!H9 -> 287333.79 | D10: ='Bureaux - AME'!I9 -> 269335.76 | E10: ='Bureaux - AME'!J9 -> 269590.46 | F10: ='Bureaux - AME'!K9 -> 263785.02 | Y10: Existant 2020 | Z10: ='Bureaux - AMS'!H9 -> 287333.79 | AA10: ='Bureaux - AMS'!I9 -> 267908.12 | AB10: ='Bureaux - AMS'!J9 -> 254442.36 | AC10: ='Bureaux - AMS'!K9 -> 233249.46
A11: Café Hôtels Restaurants | B11: Neuf post 2020 | C11: ='CaHoREs - AME'!H8 -> 0 | D11: ='CaHoREs - AME'!I8 -> 4554.2951 | E11: ='CaHoREs - AME'!J8 -> 3048.0727 | F11: ='CaHoREs - AME'!K8 -> 2041.8509 | X11: Café Hôtels Restaurants | Y11: Neuf post 2020 | Z11: ='CaHoREs - AMS'!H8 -> 0 | AA11: ='CaHoREs - AMS'!I8 -> 4192.3289 | AB11: ='CaHoREs - AMS'!J8 -> 2902.3742 | AC11: ='CaHoREs - AMS'!K8 -> 2027.5304
B12: Existant 2020 | C12: ='CaHoREs - AME'!H9 -> 67243.869 | D12: ='CaHoREs - AME'!I9 -> 65307.246 | E12: ='CaHoREs - AME'!J9 -> 67849.529 | F12: ='CaHoREs - AME'!K9 -> 68171.331 | Y12: Existant 2020 | Z12: ='CaHoREs - AMS'!H9 -> 67243.869 | AA12: ='CaHoREs - AMS'!I9 -> 65307.246 | AB12: ='CaHoREs - AMS'!J9 -> 67497.987 | AC12: ='CaHoREs - AMS'!K9 -> 66866.719
A13: Commerce | B13: Neuf post 2020 | C13: ='Commerce - AME'!H8 -> 0 | D13: ='Commerce - AME'!I8 -> 13164.331 | E13: ='Commerce - AME'!J8 -> 8969.5375 | F13: ='Commerce - AME'!K8 -> 8772.0507 | X13: Commerce | Y13: Neuf post 2020 | Z13: ='Commerce - AMS'!H8 -> 0 | AA13: ='Commerce - AMS'!I8 -> 12185.885 | AB13: ='Commerce - AMS'!J8 -> 8717.0415 | AC13: ='Commerce - AMS'!K8 -> 8710.528
B14: Existant 2020 | C14: ='Commerce - AME'!H9 -> 184229.65 | D14: ='Commerce - AME'!I9 -> 175681.39 | E14: ='Commerce - AME'!J9 -> 180083.28 | F14: ='Commerce - AME'!K9 -> 175887.23 | Y14: Existant 2020 | Z14: ='Commerce - AMS'!H9 -> 184229.65 | AA14: ='Commerce - AMS'!I9 -> 175681.39 | AB14: ='Commerce - AMS'!J9 -> 179009.85 | AC14: ='Commerce - AMS'!K9 -> 172479.99
A15: Enseignement | B15: Neuf post 2020 | C15: ='Enseignement - AME'!H8 -> 0 | D15: ='Enseignement - AME'!I8 -> 5840.7077 | E15: ='Enseignement - AME'!J8 -> 3412.3997 | F15: ='Enseignement - AME'!K8 -> 3380.7737 | X15: Enseignement | Y15: Neuf post 2020 | Z15: ='Enseignement - AMS'!H8 -> 0 | AA15: ='Enseignement - AMS'!I8 -> 4962.0556 | AB15: ='Enseignement - AMS'!J8 -> 3394.7194 | AC15: ='Enseignement - AMS'!K8 -> 3357.0627
B16: Existant 2020 | C16: ='Enseignement - AME'!H9 -> 167106.71 | D16: ='Enseignement - AME'!I9 -> 163744.18 | E16: ='Enseignement - AME'!J9 -> 164600.78 | F16: ='Enseignement - AME'!K9 -> 158963.24 | Y16: Existant 2020 | Z16: ='Enseignement - AMS'!H9 -> 167106.71 | AA16: ='Enseignement - AMS'!I9 -> 163744.18 | AB16: ='Enseignement - AMS'!J9 -> 163440.1 | AC16: ='Enseignement - AMS'!K9 -> 155937.37
A17: Santé social | B17: Neuf post 2020 | C17: ='Santé social - AME'!H8 -> 0 | D17: ='Santé social - AME'!I8 -> 22460.451 | E17: ='Santé social - AME'!J8 -> 19028.378 | F17: ='Santé social - AME'!K8 -> 14323.903 | X17: Santé social | Y17: Neuf post 2020 | Z17: ='Santé social - AMS'!H8 -> 0 | AA17: ='Santé social - AMS'!I8 -> 21439.618 | AB17: ='Santé social - AMS'!J8 -> 18543.246 | AC17: ='Santé social - AMS'!K8 -> 11635.794
B18: Existant 2020 | C18: ='Santé social - AME'!H9 -> 179200 | D18: ='Santé social - AME'!I9 -> 174566.15 | E18: ='Santé social - AME'!J9 -> 191931.78 | F18: ='Santé social - AME'!K9 -> 205505.03 | Y18: Existant 2020 | Z18: ='Santé social - AMS'!H9 -> 179200 | AA18: ='Santé social - AMS'!I9 -> 174566.15 | AB18: ='Santé social - AMS'!J9 -> 190937.34 | AC18: ='Santé social - AMS'!K9 -> 204063.73
A19: Sport Loisir Culture | B19: Neuf post 2020 | C19: ='Sport Loisir Culture - AME'!H8 -> 0 | D19: ='Sport Loisir Culture - AME'!I8 -> 3336.8292 | E19: ='Sport Loisir Culture - AME'!J8 -> 2051.9847 | F19: ='Sport Loisir Culture - AME'!K8 -> 1198.8501 | X19: Sport Loisir Culture | Y19: Neuf post 2020 | Z19: ='Sport Loisir Culture - AMS'!H8 -> 0 | AA19: ='Sport Loisir Culture - AMS'!I8 -> 3032.6507 | AB19: ='Sport Loisir Culture - AMS'!J8 -> 1932.1865 | AC19: ='Sport Loisir Culture - AMS'!K8 -> 1190.4419
B20: Existant 2020 | C20: ='Sport Loisir Culture - AME'!H9 -> 56508.434 | D20: ='Sport Loisir Culture - AME'!I9 -> 55371.367 | E20: ='Sport Loisir Culture - AME'!J9 -> 57526.866 | F20: ='Sport Loisir Culture - AME'!K9 -> 57804.848 | Y20: Existant 2020 | Z20: ='Sport Loisir Culture - AMS'!H9 -> 56508.434 | AA20: ='Sport Loisir Culture - AMS'!I9 -> 55371.367 | AB20: ='Sport Loisir Culture - AMS'!J9 -> 57228.808 | AC20: ='Sport Loisir Culture - AMS'!K9 -> 56704.89
A21: Transport | B21: Neuf post 2020 | C21: ='Transport - AME'!H8 -> 0 | D21: ='Transport - AME'!I8 -> 2714.9401 | E21: ='Transport - AME'!J8 -> 1773.7602 | F21: ='Transport - AME'!K8 -> 1146.2522 | X21: Transport | Y21: Neuf post 2020 | Z21: ='Transport - AMS'!H8 -> 0 | AA21: ='Transport - AMS'!I8 -> 2489.8568 | AB21: ='Transport - AMS'!J8 -> 1683.79 | AC21: ='Transport - AMS'!K8 -> 1138.213
B22: Existant 2020 | C22: ='Transport - AME'!H9 -> 41814.604 | D22: ='Transport - AME'!I9 -> 40727.425 | E22: ='Transport - AME'!J9 -> 42312.863 | F22: ='Transport - AME'!K9 -> 42514.775 | Y22: Existant 2020 | Z22: ='Transport - AMS'!H9 -> 41814.604 | AA22: ='Transport - AMS'!I9 -> 40727.425 | AB22: ='Transport - AMS'!J9 -> 42093.632 | AC22: ='Transport - AMS'!K9 -> 41702.656
A23: Total | B23: Neuf post 2020 | C23: =C9+C11+C13+C15+C17+C19+C21 -> 0 | D23: =D9+D11+D13+D15+D17+D19+D21 -> 58277.964 | E23: =E9+E11+E13+E15+E17+E19+E21 -> 44695.977 | F23: =F9+F11+F13+F15+F17+F19+F21 -> 36825.33 | X23: Total | Y23: Neuf post 2020 | Z23: =Z9+Z11+Z13+Z15+Z17+Z19+Z21 -> 0 | AA23: =AA9+AA11+AA13+AA15+AA17+AA19+AA21 -> 54508.805 | AB23: =AB9+AB11+AB13+AB15+AB17+AB19+AB21 -> 43094.231 | AC23: =AC9+AC11+AC13+AC15+AC17+AC19+AC21 -> 33683.416
B24: Existant 2020 | C24: =C10+C12+C14+C16+C18+C20+C22 -> 983437.06 | D24: =D10+D12+D14+D16+D18+D20+D22 -> 944733.51 | E24: =E10+E12+E14+E16+E18+E20+E22 -> 973895.55 | F24: =F10+F12+F14+F16+F18+F20+F22 -> 972631.48 | Y24: Existant 2020 | Z24: =Z10+Z12+Z14+Z16+Z18+Z20+Z22 -> 983437.06 | AA24: =AA10+AA12+AA14+AA16+AA18+AA20+AA22 -> 943305.87 | AB24: =AB10+AB12+AB14+AB16+AB18+AB20+AB22 -> 954650.08 | AC24: =AC10+AC12+AC14+AC16+AC18+AC20+AC22 -> 931004.81
AA25: =AA24*0.4/7 -> 53903.193 | AC25: =AC24*0.3/10 -> 27930.144
A27: Consommation totale en GWh AME | X27: Consommation totale en GWh AMS
A28: Usage | B28: 2020 | C28: 2030 | D28: 2040 | E28: 2050 | X28: Usage | Y28: 2020 | Z28: 2030 | AA28: 2040 | AB28: 2050
A29: Chauffage | B29: =B64 -> 100997.67 | C29: =C64 -> 82779.177 | D29: =D64 -> 75656.355 | E29: =E64 -> 66876.448 | X29: Chauffage | Y29: =Y64 -> 100997.67 | Z29: =Z64 -> 81335.173 | AA29: =AA64 -> 62532.978 | AB29: =AB64 -> 48822.166
A30: Hors chauffage | B30: =B120 -> 158828.24 | C30: =C120 -> 163798.85 | D30: =D120 -> 185016.6 | E30: =E120 -> 213980.17 | X30: Hors chauffage | Y30: =Y120 -> 151855.24 | Z30: =Z120 -> 130305.87 | AA30: =AA120 -> 123681.67 | AB30: =AB120 -> 120626.2
A31: Total | B31: =SUM(B29:B30) -> 259825.91 | C31: =SUM(C29:C30) -> 246578.03 | D31: =SUM(D29:D30) -> 260672.96 | E31: =SUM(E29:E30) -> 280856.62 | X31: Total | Y31: =SUM(Y29:Y30) -> 252852.91 | Z31: =SUM(Z29:Z30) -> 211641.04 | AA31: =SUM(AA29:AA30) -> 186214.65 | AB31: =SUM(AB29:AB30) -> 169448.37
A33: Consommation totale en GWh AME | X33: Consommation totale en GWh AMS
A34: Energie | B34: 2020 | C34: 2030 | D34: 2040 | E34: 2050 | X34: Energie | Y34: 2020 | Z34: 2030 | AA34: 2040 | AB34: 2050
A35: Fuel domestique | B35: =B57+B116 -> 22595.211 | C35: =C57+C116 -> 16467.226 | D35: =D57+D116 -> 13527.856 | E35: =E57+E116 -> 10756.59 | X35: Fuel domestique | Y35: =Y57+Y116 -> 22595.211 | Z35: =Z57+Z116 -> 1657.2553 | AA35: =AA57+AA116 -> 0 | AB35: =AB57+AB116 -> 0 | AC35: =Z35/Y35-1 -> -0.92665458 | AD35: J'aimerais bien que le tertiaire fasse plus d'effort que le résidentiel sur le gaz mais en comparent l'évolution du nombre de chaudière (res) à l'évolution du nombre de m², ce n'est pas équivalent
A36: Gaz naturel | B36: =B58+B115 -> 72724.002 | C36: =C58+C115 -> 59107.144 | D36: =D58+D115 -> 54381.501 | E36: =E58+E115 -> 48964.706 | X36: Gaz naturel | Y36: =Y58+Y115 -> 72856.921 | Z36: =Z58+Z115 -> 50935.799 | AA36: =AA58+AA115 -> 21647.97 | AB36: =AB58+AB115 -> 2830.2408 | AC36: =Z36/Y36-1 -> -0.30087906 | AD36: Le gaz est plus haut en 2030 malgré l'interdiction des chaudières à gaz du fait de la baisse des objectifs DEET dans les bureaux notamment et changement du parc
A37: Réseau de chaleur | B37: =B59+B118 -> 8956.0755 | C37: =C59+C118 -> 8753.9663 | D37: =D59+D118 -> 8305.5385 | E37: =E59+E118 -> 7473.4208 | X37: Réseau de chaleur | Y37: =Y59+Y118 -> 8956.0755 | Z37: =Z59+Z118 -> 18541.841 | AA37: =AA59+AA118 -> 20367.21 | AB37: =AB59+AB118 -> 19367.231 | AC37: =Z37/Y37-1 -> 1.0703087 | AD37: Ne pas faire une extrapolation linéaire entre 2030 et 2040 mais un pic en 2035 et une stabilisation
A38: GPL | B38: =B60 -> 1272.5787 | C38: =C60 -> 1096.1877 | D38: =D60 -> 1044.2803 | E38: =E60 -> 969.07551 | X38: GPL | Y38: =Y60 -> 1272.5787 | Z38: =Z60 -> 767.39292 | AA38: =AA60 -> 433.51045 | AB38: =AB60 -> 44.699236 | AC38: =Z38/Y38-1 -> -0.39697802
A39: ENR | B39: =B61+B117+B119 -> 1509.289 | C39: =C61+C117+C119 -> 1539.1785 | D39: =D61+D117+D119 -> 1625.3271 | E39: =E61+E117+E119 -> 1663.1942 | X39: ENR | Y39: =Y61+Y117+Y119 -> 1509.289 | Z39: =Z61+Z117+Z119 -> 2468.9607 | AA39: =AA61+AA117+AA119 -> 2907.1975 | AB39: =AB61+AB117+AB119 -> 3632.0252 | AC39: =Z39/Y39-1 -> 0.63584357
A40: Electricité (PAC incluses) | B40: =B62+B63+B114 -> 152768.75 | C40: =C62+C63+C114 -> 159614.33 | D40: =D62+D63+D114 -> 181788.45 | E40: =E62+E63+E114 -> 211029.63 | X40: Electricité (PAC incluses) | Y40: =Y62+Y63+Y114 -> 145662.83 | Z40: =Z62+Z63+Z114 -> 137167.52 | AA40: =AA62+AA63+AA114 -> 140681.46 | AB40: =AB62+AB63+AB114 -> 143344.62 | AC40: =Z40/Y40-1 -> -0.058321743
A41: Total | B41: =SUM(B35:B40) -> 259825.91 | C41: =SUM(C35:C40) -> 246578.03 | D41: =SUM(D35:D40) -> 260672.96 | E41: =SUM(E35:E40) -> 280856.62 | X41: Total | Y41: =Y64+Y120 -> 252852.91 | Z41: =Z64+Z120 -> 211641.04 | AA41: =AA64+AA120 -> 186214.65 | AB41: =AB64+AB120 -> 169448.37
A42: Gain énergétique | B42: =B41/$B41-1 -> 0 | C42: =C41/$B41-1 -> -0.050987518 | D42: =D41/$B41-1 -> 0.0032600586 | E42: =E41/$B41-1 -> 0.080941534 | X42: Gain énergétique | Y42: =Y41/$Y41-1 -> 0 | Z42: =Z41/$Y41-1 -> -0.16298752 | AA42: =AA41/$Y41-1 -> -0.26354555 | AB42: =AB41/$Y41-1 -> -0.32985399
B44: =SUM(B35:B40) -> 259825.91 | C44: =SUM(C35:C40) -> 246578.03 | D44: =SUM(D35:D40) -> 260672.96 | E44: =SUM(E35:E40) -> 280856.62
A49: Chauffage | P49: Chauffage
A55: Consommation totale de chauffage en GWh AME (hors chaleur environnement des PAC) | X55: Consommation totale de chauffage en GWh AMS (hors chaleur environnement des PAC)
A56: Energie | B56: 2020 | C56: 2030 | D56: 2040 | E56: 2050 | X56: Energie | Y56: 2020 | Z56: 2030 | AA56: 2040 | AB56: 2050
A57: Fuel domestique | B57: ='Bureaux - AME'!H13+'CaHoREs - AME'!H13+'Commerce - AME'!H13+'Enseignement - AME'!H13+'Santé social - AME'!H13+'Sport Loisir Culture - AME'!H13+'Transport - AME'!H13 -> 17636.415 | C57: ='Bureaux - AME'!I13+'CaHoREs - AME'!I13+'Commerce - AME'!I13+'Enseignement - AME'!I13+'Santé social - AME'!I13+'Sport Loisir Culture - AME'!I13+'Transport - AME'!I13 -> 12584.183 | D57: ='Bureaux - AME'!J13+'CaHoREs - AME'!J13+'Commerce - AME'!J13+'Enseignement - AME'!J13+'Santé social - AME'!J13+'Sport Loisir Culture - AME'!J13+'Transport - AME'!J13 -> 10229.373 | E57: ='Bureaux - AME'!K13+'CaHoREs - AME'!K13+'Commerce - AME'!K13+'Enseignement - AME'!K13+'Santé social - AME'!K13+'Sport Loisir Culture - AME'!K13+'Transport - AME'!K13 -> 7821.9678 | X57: Fuel domestique | Y57: ='Bureaux - AMS'!H13+'CaHoREs - AMS'!H13+'Commerce - AMS'!H13+'Enseignement - AMS'!H13+'Santé social - AMS'!H13+'Sport Loisir Culture - AMS'!H13+'Transport - AMS'!H13 -> 17636.415 | Z57: ='Bureaux - AMS'!I13+'CaHoREs - AMS'!I13+'Commerce - AMS'!I13+'Enseignement - AMS'!I13+'Santé social - AMS'!I13+'Sport Loisir Culture - AMS'!I13+'Transport - AMS'!I13 -> 1412.7353 | AA57: ='Bureaux - AMS'!J13+'CaHoREs - AMS'!J13+'Commerce - AMS'!J13+'Enseignement - AMS'!J13+'Santé social - AMS'!J13+'Sport Loisir Culture - AMS'!J13+'Transport - AMS'!J13 -> 0 | AB57: ='Bureaux - AMS'!K13+'CaHoREs - AMS'!K13+'Commerce - AMS'!K13+'Enseignement - AMS'!K13+'Santé social - AMS'!K13+'Sport Loisir Culture - AMS'!K13+'Transport - AMS'!K13 -> 0
A58: Gaz naturel | B58: ='Bureaux - AME'!H14+'CaHoREs - AME'!H14+'Commerce - AME'!H14+'Enseignement - AME'!H14+'Santé social - AME'!H14+'Sport Loisir Culture - AME'!H14+'Transport - AME'!H14 -> 55805.57 | C58: ='Bureaux - AME'!I14+'CaHoREs - AME'!I14+'Commerce - AME'!I14+'Enseignement - AME'!I14+'Santé social - AME'!I14+'Sport Loisir Culture - AME'!I14+'Transport - AME'!I14 -> 44705.077 | D58: ='Bureaux - AME'!J14+'CaHoREs - AME'!J14+'Commerce - AME'!J14+'Enseignement - AME'!J14+'Santé social - AME'!J14+'Sport Loisir Culture - AME'!J14+'Transport - AME'!J14 -> 40854.269 | E58: ='Bureaux - AME'!K14+'CaHoREs - AME'!K14+'Commerce - AME'!K14+'Enseignement - AME'!K14+'Santé social - AME'!K14+'Sport Loisir Culture - AME'!K14+'Transport - AME'!K14 -> 36337.095 | X58: Gaz naturel | Y58: ='Bureaux - AMS'!H14+'CaHoREs - AMS'!H14+'Commerce - AMS'!H14+'Enseignement - AMS'!H14+'Santé social - AMS'!H14+'Sport Loisir Culture - AMS'!H14+'Transport - AMS'!H14 -> 55805.57 | Z58: ='Bureaux - AMS'!I14+'CaHoREs - AMS'!I14+'Commerce - AMS'!I14+'Enseignement - AMS'!I14+'Santé social - AMS'!I14+'Sport Loisir Culture - AMS'!I14+'Transport - AMS'!I14 -> 41192.518 | AA58: ='Bureaux - AMS'!J14+'CaHoREs - AMS'!J14+'Commerce - AMS'!J14+'Enseignement - AMS'!J14+'Santé social - AMS'!J14+'Sport Loisir Culture - AMS'!J14+'Transport - AMS'!J14 -> 17539.893 | AB58: ='Bureaux - AMS'!K14+'CaHoREs - AMS'!K14+'Commerce - AMS'!K14+'Enseignement - AMS'!K14+'Santé social - AMS'!K14+'Sport Loisir Culture - AMS'!K14+'Transport - AMS'!K14 -> 1994.3656
A59: Réseau de chaleur | B59: ='Bureaux - AME'!H15+'CaHoREs - AME'!H15+'Commerce - AME'!H15+'Enseignement - AME'!H15+'Santé social - AME'!H15+'Sport Loisir Culture - AME'!H15+'Transport - AME'!H15 -> 7405.5823 | C59: ='Bureaux - AME'!I15+'CaHoREs - AME'!I15+'Commerce - AME'!I15+'Enseignement - AME'!I15+'Santé social - AME'!I15+'Sport Loisir Culture - AME'!I15+'Transport - AME'!I15 -> 7048.953 | D59: ='Bureaux - AME'!J15+'CaHoREs - AME'!J15+'Commerce - AME'!J15+'Enseignement - AME'!J15+'Santé social - AME'!J15+'Sport Loisir Culture - AME'!J15+'Transport - AME'!J15 -> 6658.4542 | E59: ='Bureaux - AME'!K15+'CaHoREs - AME'!K15+'Commerce - AME'!K15+'Enseignement - AME'!K15+'Santé social - AME'!K15+'Sport Loisir Culture - AME'!K15+'Transport - AME'!K15 -> 5916.0549 | X59: Réseau de chaleur | Y59: ='Bureaux - AMS'!H15+'CaHoREs - AMS'!H15+'Commerce - AMS'!H15+'Enseignement - AMS'!H15+'Santé social - AMS'!H15+'Sport Loisir Culture - AMS'!H15+'Transport - AMS'!H15 -> 7405.5823 | Z59: ='Bureaux - AMS'!I15+'CaHoREs - AMS'!I15+'Commerce - AMS'!I15+'Enseignement - AMS'!I15+'Santé social - AMS'!I15+'Sport Loisir Culture - AMS'!I15+'Transport - AMS'!I15 -> 15030.614 | AA59: ='Bureaux - AMS'!J15+'CaHoREs - AMS'!J15+'Commerce - AMS'!J15+'Enseignement - AMS'!J15+'Santé social - AMS'!J15+'Sport Loisir Culture - AMS'!J15+'Transport - AMS'!J15 -> 16931.093 | AB59: ='Bureaux - AMS'!K15+'CaHoREs - AMS'!K15+'Commerce - AMS'!K15+'Enseignement - AMS'!K15+'Santé social - AMS'!K15+'Sport Loisir Culture - AMS'!K15+'Transport - AMS'!K15 -> 16308.183
A60: GPL | B60: ='Bureaux - AME'!H16+'CaHoREs - AME'!H16+'Commerce - AME'!H16+'Enseignement - AME'!H16+'Santé social - AME'!H16+'Sport Loisir Culture - AME'!H16+'Transport - AME'!H16 -> 1272.5787 | C60: ='Bureaux - AME'!I16+'CaHoREs - AME'!I16+'Commerce - AME'!I16+'Enseignement - AME'!I16+'Santé social - AME'!I16+'Sport Loisir Culture - AME'!I16+'Transport - AME'!I16 -> 1096.1877 | D60: ='Bureaux - AME'!J16+'CaHoREs - AME'!J16+'Commerce - AME'!J16+'Enseignement - AME'!J16+'Santé social - AME'!J16+'Sport Loisir Culture - AME'!J16+'Transport - AME'!J16 -> 1044.2803 | E60: ='Bureaux - AME'!K16+'CaHoREs - AME'!K16+'Commerce - AME'!K16+'Enseignement - AME'!K16+'Santé social - AME'!K16+'Sport Loisir Culture - AME'!K16+'Transport - AME'!K16 -> 969.07551 | X60: GPL | Y60: ='Bureaux - AMS'!H16+'CaHoREs - AMS'!H16+'Commerce - AMS'!H16+'Enseignement - AMS'!H16+'Santé social - AMS'!H16+'Sport Loisir Culture - AMS'!H16+'Transport - AMS'!H16 -> 1272.5787 | Z60: ='Bureaux - AMS'!I16+'CaHoREs - AMS'!I16+'Commerce - AMS'!I16+'Enseignement - AMS'!I16+'Santé social - AMS'!I16+'Sport Loisir Culture - AMS'!I16+'Transport - AMS'!I16 -> 767.39292 | AA60: ='Bureaux - AMS'!J16+'CaHoREs - AMS'!J16+'Commerce - AMS'!J16+'Enseignement - AMS'!J16+'Santé social - AMS'!J16+'Sport Loisir Culture - AMS'!J16+'Transport - AMS'!J16 -> 433.51045 | AB60: ='Bureaux - AMS'!K16+'CaHoREs - AMS'!K16+'Commerce - AMS'!K16+'Enseignement - AMS'!K16+'Santé social - AMS'!K16+'Sport Loisir Culture - AMS'!K16+'Transport - AMS'!K16 -> 44.699236
A61: ENR | B61: ='Bureaux - AME'!H17+'CaHoREs - AME'!H17+'Commerce - AME'!H17+'Enseignement - AME'!H17+'Santé social - AME'!H17+'Sport Loisir Culture - AME'!H17+'Transport - AME'!H17 -> 1294.6737 | C61: ='Bureaux - AME'!I17+'CaHoREs - AME'!I17+'Commerce - AME'!I17+'Enseignement - AME'!I17+'Santé social - AME'!I17+'Sport Loisir Culture - AME'!I17+'Transport - AME'!I17 -> 1301.9333 | D61: ='Bureaux - AME'!J17+'CaHoREs - AME'!J17+'Commerce - AME'!J17+'Enseignement - AME'!J17+'Santé social - AME'!J17+'Sport Loisir Culture - AME'!J17+'Transport - AME'!J17 -> 1378.0056 | E61: ='Bureaux - AME'!K17+'CaHoREs - AME'!K17+'Commerce - AME'!K17+'Enseignement - AME'!K17+'Santé social - AME'!K17+'Sport Loisir Culture - AME'!K17+'Transport - AME'!K17 -> 1409.2486 | X61: ENR | Y61: ='Bureaux - AMS'!H17+'CaHoREs - AMS'!H17+'Commerce - AMS'!H17+'Enseignement - AMS'!H17+'Santé social - AMS'!H17+'Sport Loisir Culture - AMS'!H17+'Transport - AMS'!H17 -> 1294.6737 | Z61: ='Bureaux - AMS'!I17+'CaHoREs - AMS'!I17+'Commerce - AMS'!I17+'Enseignement - AMS'!I17+'Santé social - AMS'!I17+'Sport Loisir Culture - AMS'!I17+'Transport - AMS'!I17 -> 1805.8393 | AA61: ='Bureaux - AMS'!J17+'CaHoREs - AMS'!J17+'Commerce - AMS'!J17+'Enseignement - AMS'!J17+'Santé social - AMS'!J17+'Sport Loisir Culture - AMS'!J17+'Transport - AMS'!J17 -> 2373.5326 | AB61: ='Bureaux - AMS'!K17+'CaHoREs - AMS'!K17+'Commerce - AMS'!K17+'Enseignement - AMS'!K17+'Santé social - AMS'!K17+'Sport Loisir Culture - AMS'!K17+'Transport - AMS'!K17 -> 3195.7121
A62: Electricité Joule | B62: ='Bureaux - AME'!H18+'CaHoREs - AME'!H18+'Commerce - AME'!H18+'Enseignement - AME'!H18+'Santé social - AME'!H18+'Sport Loisir Culture - AME'!H18+'Transport - AME'!H18 -> 14607.453 | C62: ='Bureaux - AME'!I18+'CaHoREs - AME'!I18+'Commerce - AME'!I18+'Enseignement - AME'!I18+'Santé social - AME'!I18+'Sport Loisir Culture - AME'!I18+'Transport - AME'!I18 -> 10422.471 | D62: ='Bureaux - AME'!J18+'CaHoREs - AME'!J18+'Commerce - AME'!J18+'Enseignement - AME'!J18+'Santé social - AME'!J18+'Sport Loisir Culture - AME'!J18+'Transport - AME'!J18 -> 8187.5359 | E62: ='Bureaux - AME'!K18+'CaHoREs - AME'!K18+'Commerce - AME'!K18+'Enseignement - AME'!K18+'Santé social - AME'!K18+'Sport Loisir Culture - AME'!K18+'Transport - AME'!K18 -> 5993.7367 | X62: Electricité Joule | Y62: ='Bureaux - AMS'!H18+'CaHoREs - AMS'!H18+'Commerce - AMS'!H18+'Enseignement - AMS'!H18+'Santé social - AMS'!H18+'Sport Loisir Culture - AMS'!H18+'Transport - AMS'!H18 -> 14607.453 | Z62: ='Bureaux - AMS'!I18+'CaHoREs - AMS'!I18+'Commerce - AMS'!I18+'Enseignement - AMS'!I18+'Santé social - AMS'!I18+'Sport Loisir Culture - AMS'!I18+'Transport - AMS'!I18 -> 9642.0183 | AA62: ='Bureaux - AMS'!J18+'CaHoREs - AMS'!J18+'Commerce - AMS'!J18+'Enseignement - AMS'!J18+'Santé social - AMS'!J18+'Sport Loisir Culture - AMS'!J18+'Transport - AMS'!J18 -> 5751.6397 | AB62: ='Bureaux - AMS'!K18+'CaHoREs - AMS'!K18+'Commerce - AMS'!K18+'Enseignement - AMS'!K18+'Santé social - AMS'!K18+'Sport Loisir Culture - AMS'!K18+'Transport - AMS'!K18 -> 5000.8677
A63: Electricité PAC | B63: ='Bureaux - AME'!H19+'CaHoREs - AME'!H19+'Commerce - AME'!H19+'Enseignement - AME'!H19+'Santé social - AME'!H19+'Sport Loisir Culture - AME'!H19+'Transport - AME'!H19 -> 2975.3948 | C63: ='Bureaux - AME'!I19+'CaHoREs - AME'!I19+'Commerce - AME'!I19+'Enseignement - AME'!I19+'Santé social - AME'!I19+'Sport Loisir Culture - AME'!I19+'Transport - AME'!I19 -> 5620.3727 | D63: ='Bureaux - AME'!J19+'CaHoREs - AME'!J19+'Commerce - AME'!J19+'Enseignement - AME'!J19+'Santé social - AME'!J19+'Sport Loisir Culture - AME'!J19+'Transport - AME'!J19 -> 7304.4367 | E63: ='Bureaux - AME'!K19+'CaHoREs - AME'!K19+'Commerce - AME'!K19+'Enseignement - AME'!K19+'Santé social - AME'!K19+'Sport Loisir Culture - AME'!K19+'Transport - AME'!K19 -> 8429.2693 | X63: Electricité PAC | Y63: ='Bureaux - AMS'!H19+'CaHoREs - AMS'!H19+'Commerce - AMS'!H19+'Enseignement - AMS'!H19+'Santé social - AMS'!H19+'Sport Loisir Culture - AMS'!H19+'Transport - AMS'!H19 -> 2975.3948 | Z63: ='Bureaux - AMS'!I19+'CaHoREs - AMS'!I19+'Commerce - AMS'!I19+'Enseignement - AMS'!I19+'Santé social - AMS'!I19+'Sport Loisir Culture - AMS'!I19+'Transport - AMS'!I19 -> 11484.055 | AA63: ='Bureaux - AMS'!J19+'CaHoREs - AMS'!J19+'Commerce - AMS'!J19+'Enseignement - AMS'!J19+'Santé social - AMS'!J19+'Sport Loisir Culture - AMS'!J19+'Transport - AMS'!J19 -> 19503.309 | AB63: ='Bureaux - AMS'!K19+'CaHoREs - AMS'!K19+'Commerce - AMS'!K19+'Enseignement - AMS'!K19+'Santé social - AMS'!K19+'Sport Loisir Culture - AMS'!K19+'Transport - AMS'!K19 -> 22278.339
A64: Total | B64: =SUM(B57:B63) -> 100997.67 | C64: =SUM(C57:C63) -> 82779.177 | D64: =SUM(D57:D63) -> 75656.355 | E64: =SUM(E57:E63) -> 66876.448 | X64: Total | Y64: =SUM(Y57:Y63) -> 100997.67 | Z64: =SUM(Z57:Z63) -> 81335.173 | AA64: =SUM(AA57:AA63) -> 62532.978 | AB64: =SUM(AB57:AB63) -> 48822.166
A65: Gain énergétique | B65: =B64/$B64-1 -> 0 | C65: =C64/$B64-1 -> -0.18038526 | D65: =D64/$B64-1 -> -0.25090988 | E65: =E64/$B64-1 -> -0.33784166 | X65: Gain énergétique vs 2020 | Y65: =Y64/$Y64-1 -> 0 | Z65: =Z64/$Y64-1 -> -0.19468266 | AA65: =AA64/$Y64-1 -> -0.38084731 | AB65: =AB64/$Y64-1 -> -0.51660105
X67: REBASAGE Consommation totale de chauffage en GWh AMS
X68: Energie | Y68: 2020 | Z68: 2030 | AA68: 2040 | AB68: 2050
X69: Fuel domestique | Y69: =Y57*$B$76/$B$64 -> 0 | Z69: =Z57*$B$76/$B$64 -> 0 | AA69: =AA57*$B$76/$B$64 -> 0 | AB69: =AB57*$B$76/$B$64 -> 0
X70: Gaz naturel | Y70: =Y58*$B$76/$B$64 -> 0 | Z70: =Z58*$B$76/$B$64 -> 0 | AA70: =AA58*$B$76/$B$64 -> 0 | AB70: =AB58*$B$76/$B$64 -> 0
X71: Réseau de chaleur | Y71: =Y59*$B$76/$B$64 -> 0 | Z71: =Z59*$B$76/$B$64 -> 0 | AA71: =AA59*$B$76/$B$64 -> 0 | AB71: =AB59*$B$76/$B$64 -> 0
X72: GPL | Y72: =Y60*$B$76/$B$64 -> 0 | Z72: =Z60*$B$76/$B$64 -> 0 | AA72: =AA60*$B$76/$B$64 -> 0 | AB72: =AB60*$B$76/$B$64 -> 0
X73: ENR | Y73: =Y61*$B$76/$B$64 -> 0 | Z73: =Z61*$B$76/$B$64 -> 0 | AA73: =AA61*$B$76/$B$64 -> 0 | AB73: =AB61*$B$76/$B$64 -> 0
X74: Electricité Joule | Y74: =Y62*$B$76/$B$64 -> 0 | Z74: =Z62*$B$76/$B$64 -> 0 | AA74: =AA62*$B$76/$B$64 -> 0 | AB74: =AB62*$B$76/$B$64 -> 0
X75: Electricité PAC | Y75: =Y63*$B$76/$B$64 -> 0 | Z75: =Z63*$B$76/$B$64 -> 0 | AA75: =AA63*$B$76/$B$64 -> 0 | AB75: =AB63*$B$76/$B$64 -> 0
X76: Total | Y76: 112000 | Z76: =Z64*$B$76/$B$64 -> 0 | AA76: =AA64*$B$76/$B$64 -> 0 | AB76: =AB64*$B$76/$B$64 -> 0
X77: Gain énergétique | Y77: =Y76/$Y76-1 -> 0 | Z77: =Z76/$Y76-1 -> -1 | AA77: =AA76/$Y76-1 -> -1 | AB77: =AB76/$Y76-1 -> -1
A79: Consommation parc suivant le décret en GWh AME | X79: Consommation parc suivant le décret en GWh AMS
A80: Energie | B80: 2020 | C80: 2030 | D80: 2040 | E80: 2050 | X80: Energie | Y80: 2020 | Z80: 2030 | AA80: 2040 | AB80: 2050
A81: Fuel domestique | B81: ='Bureaux - AME'!H111+'CaHoREs - AME'!H111+'Commerce - AME'!H111+'Enseignement - AME'!H111+'Santé social - AME'!H111+'Sport Loisir Culture - AME'!H111+'Transport - AME'!H111 -> 6972.2798 | C81: ='Bureaux - AME'!I111+'CaHoREs - AME'!I111+'Commerce - AME'!I111+'Enseignement - AME'!I111+'Santé social - AME'!I111+'Sport Loisir Culture - AME'!I111+'Transport - AME'!I111 -> 4111.1754 | D81: ='Bureaux - AME'!J111+'CaHoREs - AME'!J111+'Commerce - AME'!J111+'Enseignement - AME'!J111+'Santé social - AME'!J111+'Sport Loisir Culture - AME'!J111+'Transport - AME'!J111 -> 3116.8322 | E81: ='Bureaux - AME'!K111+'CaHoREs - AME'!K111+'Commerce - AME'!K111+'Enseignement - AME'!K111+'Santé social - AME'!K111+'Sport Loisir Culture - AME'!K111+'Transport - AME'!K111 -> 2159.2824 | X81: Fuel domestique | Y81: ='Bureaux - AMS'!H111+'CaHoREs - AMS'!H111+'Commerce - AMS'!H111+'Enseignement - AMS'!H111+'Santé social - AMS'!H111+'Sport Loisir Culture - AMS'!H111+'Transport - AMS'!H111 -> 15677.951 | Z81: ='Bureaux - AMS'!I111+'CaHoREs - AMS'!I111+'Commerce - AMS'!I111+'Enseignement - AMS'!I111+'Santé social - AMS'!I111+'Sport Loisir Culture - AMS'!I111+'Transport - AMS'!I111 -> 1264.1057 | AA81: ='Bureaux - AMS'!J111+'CaHoREs - AMS'!J111+'Commerce - AMS'!J111+'Enseignement - AMS'!J111+'Santé social - AMS'!J111+'Sport Loisir Culture - AMS'!J111+'Transport - AMS'!J111 -> 0 | AB81: ='Bureaux - AMS'!K111+'CaHoREs - AMS'!K111+'Commerce - AMS'!K111+'Enseignement - AMS'!K111+'Santé social - AMS'!K111+'Sport Loisir Culture - AMS'!K111+'Transport - AMS'!K111 -> 0
A82: Gaz naturel | B82: ='Bureaux - AME'!H112+'CaHoREs - AME'!H112+'Commerce - AME'!H112+'Enseignement - AME'!H112+'Santé social - AME'!H112+'Sport Loisir Culture - AME'!H112+'Transport - AME'!H112 -> 21704.94 | C82: ='Bureaux - AME'!I112+'CaHoREs - AME'!I112+'Commerce - AME'!I112+'Enseignement - AME'!I112+'Santé social - AME'!I112+'Sport Loisir Culture - AME'!I112+'Transport - AME'!I112 -> 14287.535 | D82: ='Bureaux - AME'!J112+'CaHoREs - AME'!J112+'Commerce - AME'!J112+'Enseignement - AME'!J112+'Santé social - AME'!J112+'Sport Loisir Culture - AME'!J112+'Transport - AME'!J112 -> 12077.574 | E82: ='Bureaux - AME'!K112+'CaHoREs - AME'!K112+'Commerce - AME'!K112+'Enseignement - AME'!K112+'Santé social - AME'!K112+'Sport Loisir Culture - AME'!K112+'Transport - AME'!K112 -> 9839.8145 | X82: Gaz naturel | Y82: ='Bureaux - AMS'!H112+'CaHoREs - AMS'!H112+'Commerce - AMS'!H112+'Enseignement - AMS'!H112+'Santé social - AMS'!H112+'Sport Loisir Culture - AMS'!H112+'Transport - AMS'!H112 -> 49305.068 | Z82: ='Bureaux - AMS'!I112+'CaHoREs - AMS'!I112+'Commerce - AMS'!I112+'Enseignement - AMS'!I112+'Santé social - AMS'!I112+'Sport Loisir Culture - AMS'!I112+'Transport - AMS'!I112 -> 36178.937 | AA82: ='Bureaux - AMS'!J112+'CaHoREs - AMS'!J112+'Commerce - AMS'!J112+'Enseignement - AMS'!J112+'Santé social - AMS'!J112+'Sport Loisir Culture - AMS'!J112+'Transport - AMS'!J112 -> 15335.266 | AB82: ='Bureaux - AMS'!K112+'CaHoREs - AMS'!K112+'Commerce - AMS'!K112+'Enseignement - AMS'!K112+'Santé social - AMS'!K112+'Sport Loisir Culture - AMS'!K112+'Transport - AMS'!K112 -> 1736.2961
A83: Réseau de chaleur | B83: ='Bureaux - AME'!H113+'CaHoREs - AME'!H113+'Commerce - AME'!H113+'Enseignement - AME'!H113+'Santé social - AME'!H113+'Sport Loisir Culture - AME'!H113+'Transport - AME'!H113 -> 2920.2151 | C83: ='Bureaux - AME'!I113+'CaHoREs - AME'!I113+'Commerce - AME'!I113+'Enseignement - AME'!I113+'Santé social - AME'!I113+'Sport Loisir Culture - AME'!I113+'Transport - AME'!I113 -> 2518.4436 | D83: ='Bureaux - AME'!J113+'CaHoREs - AME'!J113+'Commerce - AME'!J113+'Enseignement - AME'!J113+'Santé social - AME'!J113+'Sport Loisir Culture - AME'!J113+'Transport - AME'!J113 -> 2207.7839 | E83: ='Bureaux - AME'!K113+'CaHoREs - AME'!K113+'Commerce - AME'!K113+'Enseignement - AME'!K113+'Santé social - AME'!K113+'Sport Loisir Culture - AME'!K113+'Transport - AME'!K113 -> 1779.3643 | X83: Réseau de chaleur | Y83: ='Bureaux - AMS'!H113+'CaHoREs - AMS'!H113+'Commerce - AMS'!H113+'Enseignement - AMS'!H113+'Santé social - AMS'!H113+'Sport Loisir Culture - AMS'!H113+'Transport - AMS'!H113 -> 6576.8119 | Z83: ='Bureaux - AMS'!I113+'CaHoREs - AMS'!I113+'Commerce - AMS'!I113+'Enseignement - AMS'!I113+'Santé social - AMS'!I113+'Sport Loisir Culture - AMS'!I113+'Transport - AMS'!I113 -> 12224.423 | AA83: ='Bureaux - AMS'!J113+'CaHoREs - AMS'!J113+'Commerce - AMS'!J113+'Enseignement - AMS'!J113+'Santé social - AMS'!J113+'Sport Loisir Culture - AMS'!J113+'Transport - AMS'!J113 -> 13882.247 | AB83: ='Bureaux - AMS'!K113+'CaHoREs - AMS'!K113+'Commerce - AMS'!K113+'Enseignement - AMS'!K113+'Santé social - AMS'!K113+'Sport Loisir Culture - AMS'!K113+'Transport - AMS'!K113 -> 13420.577
A84: GPL | B84: ='Bureaux - AME'!H114+'CaHoREs - AME'!H114+'Commerce - AME'!H114+'Enseignement - AME'!H114+'Santé social - AME'!H114+'Sport Loisir Culture - AME'!H114+'Transport - AME'!H114 -> 495.96141 | C84: ='Bureaux - AME'!I114+'CaHoREs - AME'!I114+'Commerce - AME'!I114+'Enseignement - AME'!I114+'Santé social - AME'!I114+'Sport Loisir Culture - AME'!I114+'Transport - AME'!I114 -> 341.84977 | D84: ='Bureaux - AME'!J114+'CaHoREs - AME'!J114+'Commerce - AME'!J114+'Enseignement - AME'!J114+'Santé social - AME'!J114+'Sport Loisir Culture - AME'!J114+'Transport - AME'!J114 -> 307.33844 | E84: ='Bureaux - AME'!K114+'CaHoREs - AME'!K114+'Commerce - AME'!K114+'Enseignement - AME'!K114+'Santé social - AME'!K114+'Sport Loisir Culture - AME'!K114+'Transport - AME'!K114 -> 269.30056 | X84: GPL | Y84: ='Bureaux - AMS'!H114+'CaHoREs - AMS'!H114+'Commerce - AMS'!H114+'Enseignement - AMS'!H114+'Santé social - AMS'!H114+'Sport Loisir Culture - AMS'!H114+'Transport - AMS'!H114 -> 1122.0414 | Z84: ='Bureaux - AMS'!I114+'CaHoREs - AMS'!I114+'Commerce - AMS'!I114+'Enseignement - AMS'!I114+'Santé social - AMS'!I114+'Sport Loisir Culture - AMS'!I114+'Transport - AMS'!I114 -> 596.48222 | AA84: ='Bureaux - AMS'!J114+'CaHoREs - AMS'!J114+'Commerce - AMS'!J114+'Enseignement - AMS'!J114+'Santé social - AMS'!J114+'Sport Loisir Culture - AMS'!J114+'Transport - AMS'!J114 -> 321.73629 | AB84: ='Bureaux - AMS'!K114+'CaHoREs - AMS'!K114+'Commerce - AMS'!K114+'Enseignement - AMS'!K114+'Santé social - AMS'!K114+'Sport Loisir Culture - AMS'!K114+'Transport - AMS'!K114 -> 0
A85: ENR | B85: ='Bureaux - AME'!H115+'CaHoREs - AME'!H115+'Commerce - AME'!H115+'Enseignement - AME'!H115+'Santé social - AME'!H115+'Sport Loisir Culture - AME'!H115+'Transport - AME'!H115 -> 490.36176 | C85: ='Bureaux - AME'!I115+'CaHoREs - AME'!I115+'Commerce - AME'!I115+'Enseignement - AME'!I115+'Santé social - AME'!I115+'Sport Loisir Culture - AME'!I115+'Transport - AME'!I115 -> 355.28733 | D85: ='Bureaux - AME'!J115+'CaHoREs - AME'!J115+'Commerce - AME'!J115+'Enseignement - AME'!J115+'Santé social - AME'!J115+'Sport Loisir Culture - AME'!J115+'Transport - AME'!J115 -> 328.35296 | E85: ='Bureaux - AME'!K115+'CaHoREs - AME'!K115+'Commerce - AME'!K115+'Enseignement - AME'!K115+'Santé social - AME'!K115+'Sport Loisir Culture - AME'!K115+'Transport - AME'!K115 -> 294.00984 | X85: ENR | Y85: ='Bureaux - AMS'!H115+'CaHoREs - AMS'!H115+'Commerce - AMS'!H115+'Enseignement - AMS'!H115+'Santé social - AMS'!H115+'Sport Loisir Culture - AMS'!H115+'Transport - AMS'!H115 -> 1122.8654 | Z85: ='Bureaux - AMS'!I115+'CaHoREs - AMS'!I115+'Commerce - AMS'!I115+'Enseignement - AMS'!I115+'Santé social - AMS'!I115+'Sport Loisir Culture - AMS'!I115+'Transport - AMS'!I115 -> 1455.4779 | AA85: ='Bureaux - AMS'!J115+'CaHoREs - AMS'!J115+'Commerce - AMS'!J115+'Enseignement - AMS'!J115+'Santé social - AMS'!J115+'Sport Loisir Culture - AMS'!J115+'Transport - AMS'!J115 -> 1933.5812 | AB85: ='Bureaux - AMS'!K115+'CaHoREs - AMS'!K115+'Commerce - AMS'!K115+'Enseignement - AMS'!K115+'Santé social - AMS'!K115+'Sport Loisir Culture - AMS'!K115+'Transport - AMS'!K115 -> 2587.3303
A86: Electricité Joule | B86: ='Bureaux - AME'!H116+'CaHoREs - AME'!H116+'Commerce - AME'!H116+'Enseignement - AME'!H116+'Santé social - AME'!H116+'Sport Loisir Culture - AME'!H116+'Transport - AME'!H116 -> 5412.3542 | C86: ='Bureaux - AME'!I116+'CaHoREs - AME'!I116+'Commerce - AME'!I116+'Enseignement - AME'!I116+'Santé social - AME'!I116+'Sport Loisir Culture - AME'!I116+'Transport - AME'!I116 -> 3196.4902 | D86: ='Bureaux - AME'!J116+'CaHoREs - AME'!J116+'Commerce - AME'!J116+'Enseignement - AME'!J116+'Santé social - AME'!J116+'Sport Loisir Culture - AME'!J116+'Transport - AME'!J116 -> 2492.2801 | E86: ='Bureaux - AME'!K116+'CaHoREs - AME'!K116+'Commerce - AME'!K116+'Enseignement - AME'!K116+'Santé social - AME'!K116+'Sport Loisir Culture - AME'!K116+'Transport - AME'!K116 -> 1740.3837 | X86: Electricité Joule | Y86: ='Bureaux - AMS'!H116+'CaHoREs - AMS'!H116+'Commerce - AMS'!H116+'Enseignement - AMS'!H116+'Santé social - AMS'!H116+'Sport Loisir Culture - AMS'!H116+'Transport - AMS'!H116 -> 12624.856 | Z86: ='Bureaux - AMS'!I116+'CaHoREs - AMS'!I116+'Commerce - AMS'!I116+'Enseignement - AMS'!I116+'Santé social - AMS'!I116+'Sport Loisir Culture - AMS'!I116+'Transport - AMS'!I116 -> 8151.8233 | AA86: ='Bureaux - AMS'!J116+'CaHoREs - AMS'!J116+'Commerce - AMS'!J116+'Enseignement - AMS'!J116+'Santé social - AMS'!J116+'Sport Loisir Culture - AMS'!J116+'Transport - AMS'!J116 -> 4952.0376 | AB86: ='Bureaux - AMS'!K116+'CaHoREs - AMS'!K116+'Commerce - AMS'!K116+'Enseignement - AMS'!K116+'Santé social - AMS'!K116+'Sport Loisir Culture - AMS'!K116+'Transport - AMS'!K116 -> 4384.8516
A87: Electricité PAC | B87: ='Bureaux - AME'!H117+'CaHoREs - AME'!H117+'Commerce - AME'!H117+'Enseignement - AME'!H117+'Santé social - AME'!H117+'Sport Loisir Culture - AME'!H117+'Transport - AME'!H117 -> 1068.6057 | C87: ='Bureaux - AME'!I117+'CaHoREs - AME'!I117+'Commerce - AME'!I117+'Enseignement - AME'!I117+'Santé social - AME'!I117+'Sport Loisir Culture - AME'!I117+'Transport - AME'!I117 -> 1615.9999 | D87: ='Bureaux - AME'!J117+'CaHoREs - AME'!J117+'Commerce - AME'!J117+'Enseignement - AME'!J117+'Santé social - AME'!J117+'Sport Loisir Culture - AME'!J117+'Transport - AME'!J117 -> 2249.9941 | E87: ='Bureaux - AME'!K117+'CaHoREs - AME'!K117+'Commerce - AME'!K117+'Enseignement - AME'!K117+'Santé social - AME'!K117+'Sport Loisir Culture - AME'!K117+'Transport - AME'!K117 -> 2784.0591 | X87: Electricité PAC | Y87: ='Bureaux - AMS'!H117+'CaHoREs - AMS'!H117+'Commerce - AMS'!H117+'Enseignement - AMS'!H117+'Santé social - AMS'!H117+'Sport Loisir Culture - AMS'!H117+'Transport - AMS'!H117 -> 2527.1486 | Z87: ='Bureaux - AMS'!I117+'CaHoREs - AMS'!I117+'Commerce - AMS'!I117+'Enseignement - AMS'!I117+'Santé social - AMS'!I117+'Sport Loisir Culture - AMS'!I117+'Transport - AMS'!I117 -> 9089.5883 | AA87: ='Bureaux - AMS'!J117+'CaHoREs - AMS'!J117+'Commerce - AMS'!J117+'Enseignement - AMS'!J117+'Santé social - AMS'!J117+'Sport Loisir Culture - AMS'!J117+'Transport - AMS'!J117 -> 16364.513 | AB87: ='Bureaux - AMS'!K117+'CaHoREs - AMS'!K117+'Commerce - AMS'!K117+'Enseignement - AMS'!K117+'Santé social - AMS'!K117+'Sport Loisir Culture - AMS'!K117+'Transport - AMS'!K117 -> 19145.296
A88: Total | B88: =SUM(B81:B87) -> 39064.718 | C88: =SUM(C81:C87) -> 26426.781 | D88: =SUM(D81:D87) -> 22780.155 | E88: =SUM(E81:E87) -> 18866.214 | X88: Total | Y88: =SUM(Y81:Y87) -> 88956.743 | Z88: =SUM(Z81:Z87) -> 68960.838 | AA88: =SUM(AA81:AA87) -> 52789.382 | AB88: =SUM(AB81:AB87) -> 41274.351
A89: Gain énergétique | B89: =B88/$B88-1 -> 0 | C89: =C88/$B88-1 -> -0.32351282 | D89: =D88/$B88-1 -> -0.41686113 | E89: =E88/$B88-1 -> -0.51705234 | X89: Gain énergétique vs 2020 | Y89: =Y88/$Y88-1 -> 0 | Z89: =Z88/$Y88-1 -> -0.22478234 | AA89: =AA88/$Y88-1 -> -0.40657245 | AB89: =AB88/$Y88-1 -> -0.53601774
A91: Consommation parc hors décret en GWh AME | X91: Consommation parc hors décret en GWh AMS
A92: Energie | B92: 2020 | C92: 2030 | D92: 2040 | E92: 2050 | X92: Energie | Y92: 2020 | Z92: 2030 | AA92: 2040 | AB92: 2050
A93: Fuel domestique | B93: ='Bureaux - AME'!H122+'CaHoREs - AME'!H122+'Commerce - AME'!H122+'Enseignement - AME'!H122+'Santé social - AME'!H122+'Sport Loisir Culture - AME'!H122+'Transport - AME'!H122 -> 10664.135 | C93: ='Bureaux - AME'!I122+'CaHoREs - AME'!I122+'Commerce - AME'!I122+'Enseignement - AME'!I122+'Santé social - AME'!I122+'Sport Loisir Culture - AME'!I122+'Transport - AME'!I122 -> 8469.3394 | D93: ='Bureaux - AME'!J122+'CaHoREs - AME'!J122+'Commerce - AME'!J122+'Enseignement - AME'!J122+'Santé social - AME'!J122+'Sport Loisir Culture - AME'!J122+'Transport - AME'!J122 -> 7111.1063 | E93: ='Bureaux - AME'!K122+'CaHoREs - AME'!K122+'Commerce - AME'!K122+'Enseignement - AME'!K122+'Santé social - AME'!K122+'Sport Loisir Culture - AME'!K122+'Transport - AME'!K122 -> 5661.3849 | X93: Fuel domestique | Y93: ='Bureaux - AMS'!H122+'CaHoREs - AMS'!H122+'Commerce - AMS'!H122+'Enseignement - AMS'!H122+'Santé social - AMS'!H122+'Sport Loisir Culture - AMS'!H122+'Transport - AMS'!H122 -> 1958.4638 | Z93: ='Bureaux - AMS'!I122+'CaHoREs - AMS'!I122+'Commerce - AMS'!I122+'Enseignement - AMS'!I122+'Santé social - AMS'!I122+'Sport Loisir Culture - AMS'!I122+'Transport - AMS'!I122 -> 148.62958 | AA93: ='Bureaux - AMS'!J122+'CaHoREs - AMS'!J122+'Commerce - AMS'!J122+'Enseignement - AMS'!J122+'Santé social - AMS'!J122+'Sport Loisir Culture - AMS'!J122+'Transport - AMS'!J122 -> 0 | AB93: ='Bureaux - AMS'!K122+'CaHoREs - AMS'!K122+'Commerce - AMS'!K122+'Enseignement - AMS'!K122+'Santé social - AMS'!K122+'Sport Loisir Culture - AMS'!K122+'Transport - AMS'!K122 -> 0
A94: Gaz naturel | B94: ='Bureaux - AME'!H123+'CaHoREs - AME'!H123+'Commerce - AME'!H123+'Enseignement - AME'!H123+'Santé social - AME'!H123+'Sport Loisir Culture - AME'!H123+'Transport - AME'!H123 -> 34100.63 | C94: ='Bureaux - AME'!I123+'CaHoREs - AME'!I123+'Commerce - AME'!I123+'Enseignement - AME'!I123+'Santé social - AME'!I123+'Sport Loisir Culture - AME'!I123+'Transport - AME'!I123 -> 30417.543 | D94: ='Bureaux - AME'!J123+'CaHoREs - AME'!J123+'Commerce - AME'!J123+'Enseignement - AME'!J123+'Santé social - AME'!J123+'Sport Loisir Culture - AME'!J123+'Transport - AME'!J123 -> 28776.695 | E94: ='Bureaux - AME'!K123+'CaHoREs - AME'!K123+'Commerce - AME'!K123+'Enseignement - AME'!K123+'Santé social - AME'!K123+'Sport Loisir Culture - AME'!K123+'Transport - AME'!K123 -> 26497.28 | X94: Gaz naturel | Y94: ='Bureaux - AMS'!H123+'CaHoREs - AMS'!H123+'Commerce - AMS'!H123+'Enseignement - AMS'!H123+'Santé social - AMS'!H123+'Sport Loisir Culture - AMS'!H123+'Transport - AMS'!H123 -> 6500.5014 | Z94: ='Bureaux - AMS'!I123+'CaHoREs - AMS'!I123+'Commerce - AMS'!I123+'Enseignement - AMS'!I123+'Santé social - AMS'!I123+'Sport Loisir Culture - AMS'!I123+'Transport - AMS'!I123 -> 4982.025 | AA94: ='Bureaux - AMS'!J123+'CaHoREs - AMS'!J123+'Commerce - AMS'!J123+'Enseignement - AMS'!J123+'Santé social - AMS'!J123+'Sport Loisir Culture - AMS'!J123+'Transport - AMS'!J123 -> 2185.227 | AB94: ='Bureaux - AMS'!K123+'CaHoREs - AMS'!K123+'Commerce - AMS'!K123+'Enseignement - AMS'!K123+'Santé social - AMS'!K123+'Sport Loisir Culture - AMS'!K123+'Transport - AMS'!K123 -> 246.2669
A95: Réseau de chaleur | B95: ='Bureaux - AME'!H124+'CaHoREs - AME'!H124+'Commerce - AME'!H124+'Enseignement - AME'!H124+'Santé social - AME'!H124+'Sport Loisir Culture - AME'!H124+'Transport - AME'!H124 -> 4485.3672 | C95: ='Bureaux - AME'!I124+'CaHoREs - AME'!I124+'Commerce - AME'!I124+'Enseignement - AME'!I124+'Santé social - AME'!I124+'Sport Loisir Culture - AME'!I124+'Transport - AME'!I124 -> 4107.7016 | D95: ='Bureaux - AME'!J124+'CaHoREs - AME'!J124+'Commerce - AME'!J124+'Enseignement - AME'!J124+'Santé social - AME'!J124+'Sport Loisir Culture - AME'!J124+'Transport - AME'!J124 -> 4101.063 | E95: ='Bureaux - AME'!K124+'CaHoREs - AME'!K124+'Commerce - AME'!K124+'Enseignement - AME'!K124+'Santé social - AME'!K124+'Sport Loisir Culture - AME'!K124+'Transport - AME'!K124 -> 3861.5949 | X95: Réseau de chaleur | Y95: ='Bureaux - AMS'!H124+'CaHoREs - AMS'!H124+'Commerce - AMS'!H124+'Enseignement - AMS'!H124+'Santé social - AMS'!H124+'Sport Loisir Culture - AMS'!H124+'Transport - AMS'!H124 -> 828.77043 | Z95: ='Bureaux - AMS'!I124+'CaHoREs - AMS'!I124+'Commerce - AMS'!I124+'Enseignement - AMS'!I124+'Santé social - AMS'!I124+'Sport Loisir Culture - AMS'!I124+'Transport - AMS'!I124 -> 1729.5924 | AA95: ='Bureaux - AMS'!J124+'CaHoREs - AMS'!J124+'Commerce - AMS'!J124+'Enseignement - AMS'!J124+'Santé social - AMS'!J124+'Sport Loisir Culture - AMS'!J124+'Transport - AMS'!J124 -> 2166.5328 | AB95: ='Bureaux - AMS'!K124+'CaHoREs - AMS'!K124+'Commerce - AMS'!K124+'Enseignement - AMS'!K124+'Santé social - AMS'!K124+'Sport Loisir Culture - AMS'!K124+'Transport - AMS'!K124 -> 2268.5551
A96: GPL | B96: ='Bureaux - AME'!H125+'CaHoREs - AME'!H125+'Commerce - AME'!H125+'Enseignement - AME'!H125+'Santé social - AME'!H125+'Sport Loisir Culture - AME'!H125+'Transport - AME'!H125 -> 776.61727 | C96: ='Bureaux - AME'!I125+'CaHoREs - AME'!I125+'Commerce - AME'!I125+'Enseignement - AME'!I125+'Santé social - AME'!I125+'Sport Loisir Culture - AME'!I125+'Transport - AME'!I125 -> 708.74036 | D96: ='Bureaux - AME'!J125+'CaHoREs - AME'!J125+'Commerce - AME'!J125+'Enseignement - AME'!J125+'Santé social - AME'!J125+'Sport Loisir Culture - AME'!J125+'Transport - AME'!J125 -> 698.31185 | E96: ='Bureaux - AME'!K125+'CaHoREs - AME'!K125+'Commerce - AME'!K125+'Enseignement - AME'!K125+'Santé social - AME'!K125+'Sport Loisir Culture - AME'!K125+'Transport - AME'!K125 -> 670.69558 | X96: GPL | Y96: ='Bureaux - AMS'!H125+'CaHoREs - AMS'!H125+'Commerce - AMS'!H125+'Enseignement - AMS'!H125+'Santé social - AMS'!H125+'Sport Loisir Culture - AMS'!H125+'Transport - AMS'!H125 -> 150.53733 | Z96: ='Bureaux - AMS'!I125+'CaHoREs - AMS'!I125+'Commerce - AMS'!I125+'Enseignement - AMS'!I125+'Santé social - AMS'!I125+'Sport Loisir Culture - AMS'!I125+'Transport - AMS'!I125 -> 91.961003 | AA96: ='Bureaux - AMS'!J125+'CaHoREs - AMS'!J125+'Commerce - AMS'!J125+'Enseignement - AMS'!J125+'Santé social - AMS'!J125+'Sport Loisir Culture - AMS'!J125+'Transport - AMS'!J125 -> 47.619276 | AB96: ='Bureaux - AMS'!K125+'CaHoREs - AMS'!K125+'Commerce - AMS'!K125+'Enseignement - AMS'!K125+'Santé social - AMS'!K125+'Sport Loisir Culture - AMS'!K125+'Transport - AMS'!K125 -> 0
A97: ENR | B97: ='Bureaux - AME'!H126+'CaHoREs - AME'!H126+'Commerce - AME'!H126+'Enseignement - AME'!H126+'Santé social - AME'!H126+'Sport Loisir Culture - AME'!H126+'Transport - AME'!H126 -> 804.31191 | C97: ='Bureaux - AME'!I126+'CaHoREs - AME'!I126+'Commerce - AME'!I126+'Enseignement - AME'!I126+'Santé social - AME'!I126+'Sport Loisir Culture - AME'!I126+'Transport - AME'!I126 -> 869.15983 | D97: ='Bureaux - AME'!J126+'CaHoREs - AME'!J126+'Commerce - AME'!J126+'Enseignement - AME'!J126+'Santé social - AME'!J126+'Sport Loisir Culture - AME'!J126+'Transport - AME'!J126 -> 986.02449 | E97: ='Bureaux - AME'!K126+'CaHoREs - AME'!K126+'Commerce - AME'!K126+'Enseignement - AME'!K126+'Santé social - AME'!K126+'Sport Loisir Culture - AME'!K126+'Transport - AME'!K126 -> 1065.4071 | X97: ENR | Y97: ='Bureaux - AMS'!H126+'CaHoREs - AMS'!H126+'Commerce - AMS'!H126+'Enseignement - AMS'!H126+'Santé social - AMS'!H126+'Sport Loisir Culture - AMS'!H126+'Transport - AMS'!H126 -> 171.80825 | Z97: ='Bureaux - AMS'!I126+'CaHoREs - AMS'!I126+'Commerce - AMS'!I126+'Enseignement - AMS'!I126+'Santé social - AMS'!I126+'Sport Loisir Culture - AMS'!I126+'Transport - AMS'!I126 -> 222.78345 | AA97: ='Bureaux - AMS'!J126+'CaHoREs - AMS'!J126+'Commerce - AMS'!J126+'Enseignement - AMS'!J126+'Santé social - AMS'!J126+'Sport Loisir Culture - AMS'!J126+'Transport - AMS'!J126 -> 291.11526 | AB97: ='Bureaux - AMS'!K126+'CaHoREs - AMS'!K126+'Commerce - AMS'!K126+'Enseignement - AMS'!K126+'Santé social - AMS'!K126+'Sport Loisir Culture - AMS'!K126+'Transport - AMS'!K126 -> 430.90689
A98: Electricité Joule | B98: ='Bureaux - AME'!H127+'CaHoREs - AME'!H127+'Commerce - AME'!H127+'Enseignement - AME'!H127+'Santé social - AME'!H127+'Sport Loisir Culture - AME'!H127+'Transport - AME'!H127 -> 9195.0988 | C98: ='Bureaux - AME'!I127+'CaHoREs - AME'!I127+'Commerce - AME'!I127+'Enseignement - AME'!I127+'Santé social - AME'!I127+'Sport Loisir Culture - AME'!I127+'Transport - AME'!I127 -> 6909.9241 | D98: ='Bureaux - AME'!J127+'CaHoREs - AME'!J127+'Commerce - AME'!J127+'Enseignement - AME'!J127+'Santé social - AME'!J127+'Sport Loisir Culture - AME'!J127+'Transport - AME'!J127 -> 5455.2333 | E98: ='Bureaux - AME'!K127+'CaHoREs - AME'!K127+'Commerce - AME'!K127+'Enseignement - AME'!K127+'Santé social - AME'!K127+'Sport Loisir Culture - AME'!K127+'Transport - AME'!K127 -> 4046.2273 | X98: Electricité Joule | Y98: ='Bureaux - AMS'!H127+'CaHoREs - AMS'!H127+'Commerce - AMS'!H127+'Enseignement - AMS'!H127+'Santé social - AMS'!H127+'Sport Loisir Culture - AMS'!H127+'Transport - AMS'!H127 -> 1982.5971 | Z98: ='Bureaux - AMS'!I127+'CaHoREs - AMS'!I127+'Commerce - AMS'!I127+'Enseignement - AMS'!I127+'Santé social - AMS'!I127+'Sport Loisir Culture - AMS'!I127+'Transport - AMS'!I127 -> 1060.0354 | AA98: ='Bureaux - AMS'!J127+'CaHoREs - AMS'!J127+'Commerce - AMS'!J127+'Enseignement - AMS'!J127+'Santé social - AMS'!J127+'Sport Loisir Culture - AMS'!J127+'Transport - AMS'!J127 -> 693.61102 | AB98: ='Bureaux - AMS'!K127+'CaHoREs - AMS'!K127+'Commerce - AMS'!K127+'Enseignement - AMS'!K127+'Santé social - AMS'!K127+'Sport Loisir Culture - AMS'!K127+'Transport - AMS'!K127 -> 586.61882
A99: Electricité PAC | B99: ='Bureaux - AME'!H128+'CaHoREs - AME'!H128+'Commerce - AME'!H128+'Enseignement - AME'!H128+'Santé social - AME'!H128+'Sport Loisir Culture - AME'!H128+'Transport - AME'!H128 -> 1906.7891 | C99: ='Bureaux - AME'!I128+'CaHoREs - AME'!I128+'Commerce - AME'!I128+'Enseignement - AME'!I128+'Santé social - AME'!I128+'Sport Loisir Culture - AME'!I128+'Transport - AME'!I128 -> 2967.0522 | D99: ='Bureaux - AME'!J128+'CaHoREs - AME'!J128+'Commerce - AME'!J128+'Enseignement - AME'!J128+'Santé social - AME'!J128+'Sport Loisir Culture - AME'!J128+'Transport - AME'!J128 -> 4262.1098 | E99: ='Bureaux - AME'!K128+'CaHoREs - AME'!K128+'Commerce - AME'!K128+'Enseignement - AME'!K128+'Santé social - AME'!K128+'Sport Loisir Culture - AME'!K128+'Transport - AME'!K128 -> 4989.1781 | X99: Electricité PAC | Y99: ='Bureaux - AMS'!H128+'CaHoREs - AMS'!H128+'Commerce - AMS'!H128+'Enseignement - AMS'!H128+'Santé social - AMS'!H128+'Sport Loisir Culture - AMS'!H128+'Transport - AMS'!H128 -> 448.24616 | Z99: ='Bureaux - AMS'!I128+'CaHoREs - AMS'!I128+'Commerce - AMS'!I128+'Enseignement - AMS'!I128+'Santé social - AMS'!I128+'Sport Loisir Culture - AMS'!I128+'Transport - AMS'!I128 -> 1291.3951 | AA99: ='Bureaux - AMS'!J128+'CaHoREs - AMS'!J128+'Commerce - AMS'!J128+'Enseignement - AMS'!J128+'Santé social - AMS'!J128+'Sport Loisir Culture - AMS'!J128+'Transport - AMS'!J128 -> 2113.6986 | AB99: ='Bureaux - AMS'!K128+'CaHoREs - AMS'!K128+'Commerce - AMS'!K128+'Enseignement - AMS'!K128+'Santé social - AMS'!K128+'Sport Loisir Culture - AMS'!K128+'Transport - AMS'!K128 -> 2304.071
A100: Total | B100: =SUM(B93:B99) -> 61932.949 | C100: =SUM(C93:C99) -> 54449.46 | D100: =SUM(D93:D99) -> 51390.544 | E100: =SUM(E93:E99) -> 46791.768 | X100: Total | Y100: =SUM(Y93:Y99) -> 12040.924 | Z100: =SUM(Z93:Z99) -> 9526.4219 | AA100: =SUM(AA93:AA99) -> 7497.804 | AB100: =SUM(AB93:AB99) -> 5836.4187
A101: Gain énergétique | B101: =B100/$B100-1 -> 0 | C101: =C100/$B100-1 -> -0.12083211 | D101: =D100/$B100-1 -> -0.17022289 | E101: =E100/$B100-1 -> -0.24447699 | X101: Gain énergétique vs 2020 | Y101: =Y100/$Y100-1 -> 0 | Z101: =Z100/$Y100-1 -> -0.20882969 | AA101: =AA100/$Y100-1 -> -0.37730662 | AB101: =AB100/$Y100-1 -> -0.51528484
A106: Hors Chauffage | P106: Hors Chauffage
A112: Consommation par source énergie - Scénario AME [GWh LHV] | X112: Consommation par source énergie - Scénario AMS [GWh LHV]
A113: Energie | B113: 2020 | C113: 2030 | D113: 2040 | E113: 2050 | X113: Energie | Y113: 2020 | Z113: 2021 | AA113: 2022 | AB113: 2023
A114: Electricité | B114: ='Hors chauffage - AME'!E6*1000 -> 135185.9 | C114: ='Hors chauffage - AME'!F6*1000 -> 143571.48 | D114: ='Hors chauffage - AME'!G6*1000 -> 166296.48 | E114: ='Hors chauffage - AME'!H6*1000 -> 196606.62 | X114: Electricité | Y114: ='Hors chauffage - AMS'!E6*1000 -> 128079.98 | Z114: ='Hors chauffage - AMS'!F6*1000 -> 116041.45 | AA114: ='Hors chauffage - AMS'!G6*1000 -> 115426.51 | AB114: ='Hors chauffage - AMS'!H6*1000 -> 116065.41
A115: Gaz | B115: ='Hors chauffage - AME'!E7*1000 -> 16918.432 | C115: ='Hors chauffage - AME'!F7*1000 -> 14402.066 | D115: ='Hors chauffage - AME'!G7*1000 -> 13527.232 | E115: ='Hors chauffage - AME'!H7*1000 -> 12627.612 | X115: Gaz | Y115: ='Hors chauffage - AMS'!E7*1000 -> 17051.351 | Z115: ='Hors chauffage - AMS'!F7*1000 -> 9743.2811 | AA115: ='Hors chauffage - AMS'!G7*1000 -> 4108.0765 | AB115: ='Hors chauffage - AMS'!H7*1000 -> 835.8752
A116: Pétrole | B116: ='Hors chauffage - AME'!E8*1000 -> 4958.796 | C116: ='Hors chauffage - AME'!F8*1000 -> 3883.0439 | D116: ='Hors chauffage - AME'!G8*1000 -> 3298.4831 | E116: ='Hors chauffage - AME'!H8*1000 -> 2934.6221 | X116: Pétrole | Y116: ='Hors chauffage - AMS'!E8*1000 -> 4958.796 | Z116: ='Hors chauffage - AMS'!F8*1000 -> 244.52002 | AA116: ='Hors chauffage - AMS'!G8*1000 -> 0 | AB116: ='Hors chauffage - AMS'!H8*1000 -> 0
A117: Bois | B117: ='Hors chauffage - AME'!E9*1000 -> 214.61535 | C117: ='Hors chauffage - AME'!F9*1000 -> 237.24517 | D117: ='Hors chauffage - AME'!G9*1000 -> 247.32152 | E117: ='Hors chauffage - AME'!H9*1000 -> 253.94561 | X117: Bois | Y117: ='Hors chauffage - AMS'!E9*1000 -> 214.61535 | Z117: ='Hors chauffage - AMS'!F9*1000 -> 663.01905 | AA117: ='Hors chauffage - AMS'!G9*1000 -> 533.48745 | AB117: ='Hors chauffage - AMS'!H9*1000 -> 436.08335
A118: Chaleur | B118: ='Hors chauffage - AME'!E10*1000 -> 1550.4931 | C118: ='Hors chauffage - AME'!F10*1000 -> 1705.0133 | D118: ='Hors chauffage - AME'!G10*1000 -> 1647.0843 | E118: ='Hors chauffage - AME'!H10*1000 -> 1557.3658 | X118: Chaleur | Y118: ='Hors chauffage - AMS'!E10*1000 -> 1550.4931 | Z118: ='Hors chauffage - AMS'!F10*1000 -> 3511.227 | AA118: ='Hors chauffage - AMS'!G10*1000 -> 3436.1167 | AB118: ='Hors chauffage - AMS'!H10*1000 -> 3059.0485
A119: EnR thermique | B119: 0 | C119: 0 | D119: 0 | E119: 0 | X119: EnR thermique | Y119: ='Hors chauffage - AMS'!E11 -> 0 | Z119: ='Hors chauffage - AMS'!F11 -> 0.10237102 | AA119: ='Hors chauffage - AMS'!G11 -> 0.17748115 | AB119: ='Hors chauffage - AMS'!H11 -> 0.22978422
A120: Total | B120: ='Hors chauffage - AME'!E5*1000 -> 158828.24 | C120: ='Hors chauffage - AME'!F5*1000 -> 163798.85 | D120: ='Hors chauffage - AME'!G5*1000 -> 185016.6 | E120: ='Hors chauffage - AME'!H5*1000 -> 213980.17 | X120: Total | Y120: ='Hors chauffage - AMS'!E5*1000 -> 151855.24 | Z120: ='Hors chauffage - AMS'!F5*1000 -> 130305.87 | AA120: ='Hors chauffage - AMS'!G5*1000 -> 123681.67 | AB120: ='Hors chauffage - AMS'!H5*1000 -> 120626.2
A122: Réalisation des objectifs | X122: Réalisation des objectifs
A123: Baisse de consommation | B123: =B120/$B120-1 -> 0 | C123: =C120/$B120-1 -> 0.031295519 | D123: =D120/$B120-1 -> 0.16488478 | E123: =E120/$B120-1 -> 0.34724257 | F123: Augmentation presque 100% lié au data center | X123: Baisse de consommation | Y123: =Y120/$B120-1 -> -0.043902785 | Z123: =Z120/$B120-1 -> -0.17958 | AA123: =AA120/$B120-1 -> -0.22128666 | AB123: =AB120/$Y120-1 -> -0.20565006
AI126: SDES | AJ126: 2019 | AK126: Mtep | AL126: TWh
A127: Estimation GES (FE constant) | P127: Estimation GES | AK127: 22.4 | AL127: =AK127/86000*1000000 -> 260.46512
AI128: chauffage | AJ128: 0.43 | AK128: =AK$127*AJ128 -> 9.632 | AL128: =AK128/86000*1000000 -> 112
A130: Emissions totales (Mt) AME | X130: Emissions totales (Mt) AMS | AI130: elec spé | AJ130: 0.3 | AK130: =AK$127*AJ130 -> 6.72 | AL130: =AK130/86000*1000000 -> 78.139535
A131: Energie | B131: 2020 | C131: 2030 | D131: 2040 | E131: 2050 | X131: Energie | Y131: 2020 | Z131: 2030 | AA131: 2040 | AB131: 2050 | AI131: ecs | AJ131: 0.1 | AK131: =AK$127*AJ131 -> 2.24 | AL131: =AK131/86000*1000000 -> 26.046512
A132: Fuel domestique | B132: =B35*'Init. énergie'!$M4*10^-6 -> 6.1222742 | C132: =C35*'Init. énergie'!$M4*10^-6 -> 4.4618692 | D132: =D35*'Init. énergie'!$M4*10^-6 -> 3.6654336 | E132: =E35*'Init. énergie'!$M4*10^-6 -> 2.9145465 | X132: Fuel domestique | Y132: =Y35*'Init. énergie'!M4*10^-6 -> 6.1222742 | Z132: =Z35*'Init. énergie'!N4*10^-6 -> 0.44904078 | AA132: =AA35*'Init. énergie'!O4*10^-6 -> 0 | AB132: =AB35*'Init. énergie'!P4*10^-6 -> 0 | AI132: clim | AJ132: 0.09 | AK132: =AK$127*AJ132 -> 2.016 | AL132: =AK132/86000*1000000 -> 23.44186
...

Sheet Résultats - post traitement
A1: Scénario AME | P1: Scénario AMS
A3: Consommation totale | P3: Consommation totale
B7: Surface chauffée - Scénario AME [thousand sq m] | Y7: Surface chauffée - Scénario AMS [thousand sq m]
A8: Catégorie | C8: 2020 | D8: 2030 | E8: 2040 | F8: 2050 | X8: Catégorie | Z8: 2020 | AA8: 2030 | AB8: 2040 | AC8: 2050
A9: Bureaux | B9: Neuf post 2020 | C9: ='Bureaux - AME'!H8 -> 0 | D9: ='Bureaux - AME'!I8 -> 6206.4099 | E9: ='Bureaux - AME'!J8 -> 6411.8445 | F9: ='Bureaux - AME'!K8 -> 5961.6497 | X9: Bureaux | Y9: Neuf post 2020 | Z9: ='Bureaux - AMS'!H8 -> 0 | AA9: ='Bureaux - AMS'!I8 -> 6206.4099 | AB9: ='Bureaux - AMS'!J8 -> 5920.8739 | AC9: ='Bureaux - AMS'!K8 -> 5623.8459
B10: Existant 2020 | C10: ='Bureaux - AME'!H9 -> 287333.79 | D10: ='Bureaux - AME'!I9 -> 269335.76 | E10: ='Bureaux - AME'!J9 -> 269590.46 | F10: ='Bureaux - AME'!K9 -> 263785.02 | Y10: Existant 2020 | Z10: ='Bureaux - AMS'!H9 -> 287333.79 | AA10: ='Bureaux - AMS'!I9 -> 267908.12 | AB10: ='Bureaux - AMS'!J9 -> 254442.36 | AC10: ='Bureaux - AMS'!K9 -> 233249.46
A11: Café Hôtels Restaurants | B11: Neuf post 2020 | C11: ='CaHoREs - AME'!H8 -> 0 | D11: ='CaHoREs - AME'!I8 -> 4554.2951 | E11: ='CaHoREs - AME'!J8 -> 3048.0727 | F11: ='CaHoREs - AME'!K8 -> 2041.8509 | X11: Café Hôtels Restaurants | Y11: Neuf post 2020 | Z11: ='CaHoREs - AMS'!H8 -> 0 | AA11: ='CaHoREs - AMS'!I8 -> 4192.3289 | AB11: ='CaHoREs - AMS'!J8 -> 2902.3742 | AC11: ='CaHoREs - AMS'!K8 -> 2027.5304
B12: Existant 2020 | C12: ='CaHoREs - AME'!H9 -> 67243.869 | D12: ='CaHoREs - AME'!I9 -> 65307.246 | E12: ='CaHoREs - AME'!J9 -> 67849.529 | F12: ='CaHoREs - AME'!K9 -> 68171.331 | Y12: Existant 2020 | Z12: ='CaHoREs - AMS'!H9 -> 67243.869 | AA12: ='CaHoREs - AMS'!I9 -> 65307.246 | AB12: ='CaHoREs - AMS'!J9 -> 67497.987 | AC12: ='CaHoREs - AMS'!K9 -> 66866.719
A13: Commerce | B13: Neuf post 2020 | C13: ='Commerce - AME'!H8 -> 0 | D13: ='Commerce - AME'!I8 -> 13164.331 | E13: ='Commerce - AME'!J8 -> 8969.5375 | F13: ='Commerce - AME'!K8 -> 8772.0507 | X13: Commerce | Y13: Neuf post 2020 | Z13: ='Commerce - AMS'!H8 -> 0 | AA13: ='Commerce - AMS'!I8 -> 12185.885 | AB13: ='Commerce - AMS'!J8 -> 8717.0415 | AC13: ='Commerce - AMS'!K8 -> 8710.528
B14: Existant 2020 | C14: ='Commerce - AME'!H9 -> 184229.65 | D14: ='Commerce - AME'!I9 -> 175681.39 | E14: ='Commerce - AME'!J9 -> 180083.28 | F14: ='Commerce - AME'!K9 -> 175887.23 | Y14: Existant 2020 | Z14: ='Commerce - AMS'!H9 -> 184229.65 | AA14: ='Commerce - AMS'!I9 -> 175681.39 | AB14: ='Commerce - AMS'!J9 -> 179009.85 | AC14: ='Commerce - AMS'!K9 -> 172479.99
A15: Enseignement | B15: Neuf post 2020 | C15: ='Enseignement - AME'!H8 -> 0 | D15: ='Enseignement - AME'!I8 -> 5840.7077 | E15: ='Enseignement - AME'!J8 -> 3412.3997 | F15: ='Enseignement - AME'!K8 -> 3380.7737 | X15: Enseignement | Y15: Neuf post 2020 | Z15: ='Enseignement - AMS'!H8 -> 0 | AA15: ='Enseignement - AMS'!I8 -> 4962.0556 | AB15: ='Enseignement - AMS'!J8 -> 3394.7194 | AC15: ='Enseignement - AMS'!K8 -> 3357.0627
B16: Existant 2020 | C16: ='Enseignement - AME'!H9 -> 167106.71 | D16: ='Enseignement - AME'!I9 -> 163744.18 | E16: ='Enseignement - AME'!J9 -> 164600.78 | F16: ='Enseignement - AME'!K9 -> 158963.24 | Y16: Existant 2020 | Z16: ='Enseignement - AMS'!H9 -> 167106.71 | AA16: ='Enseignement - AMS'!I9 -> 163744.18 | AB16: ='Enseignement - AMS'!J9 -> 163440.1 | AC16: ='Enseignement - AMS'!K9 -> 155937.37
A17: Santé social | B17: Neuf post 2020 | C17: ='Santé social - AME'!H8 -> 0 | D17: ='Santé social - AME'!I8 -> 22460.451 | E17: ='Santé social - AME'!J8 -> 19028.378 | F17: ='Santé social - AME'!K8 -> 14323.903 | X17: Santé social | Y17: Neuf post 2020 | Z17: ='Santé social - AMS'!H8 -> 0 | AA17: ='Santé social - AMS'!I8 -> 21439.618 | AB17: ='Santé social - AMS'!J8 -> 18543.246 | AC17: ='Santé social - AMS'!K8 -> 11635.794
B18: Existant 2020 | C18: ='Santé social - AME'!H9 -> 179200 | D18: ='Santé social - AME'!I9 -> 174566.15 | E18: ='Santé social - AME'!J9 -> 191931.78 | F18: ='Santé social - AME'!K9 -> 205505.03 | Y18: Existant 2020 | Z18: ='Santé social - AMS'!H9 -> 179200 | AA18: ='Santé social - AMS'!I9 -> 174566.15 | AB18: ='Santé social - AMS'!J9 -> 190937.34 | AC18: ='Santé social - AMS'!K9 -> 204063.73
A19: Sport Loisir Culture | B19: Neuf post 2020 | C19: ='Sport Loisir Culture - AME'!H8 -> 0 | D19: ='Sport Loisir Culture - AME'!I8 -> 3336.8292 | E19: ='Sport Loisir Culture - AME'!J8 -> 2051.9847 | F19: ='Sport Loisir Culture - AME'!K8 -> 1198.8501 | X19: Sport Loisir Culture | Y19: Neuf post 2020 | Z19: ='Sport Loisir Culture - AMS'!H8 -> 0 | AA19: ='Sport Loisir Culture - AMS'!I8 -> 3032.6507 | AB19: ='Sport Loisir Culture - AMS'!J8 -> 1932.1865 | AC19: ='Sport Loisir Culture - AMS'!K8 -> 1190.4419
B20: Existant 2020 | C20: ='Sport Loisir Culture - AME'!H9 -> 56508.434 | D20: ='Sport Loisir Culture - AME'!I9 -> 55371.367 | E20: ='Sport Loisir Culture - AME'!J9 -> 57526.866 | F20: ='Sport Loisir Culture - AME'!K9 -> 57804.848 | Y20: Existant 2020 | Z20: ='Sport Loisir Culture - AMS'!H9 -> 56508.434 | AA20: ='Sport Loisir Culture - AMS'!I9 -> 55371.367 | AB20: ='Sport Loisir Culture - AMS'!J9 -> 57228.808 | AC20: ='Sport Loisir Culture - AMS'!K9 -> 56704.89
A21: Transport | B21: Neuf post 2020 | C21: ='Transport - AME'!H8 -> 0 | D21: ='Transport - AME'!I8 -> 2714.9401 | E21: ='Transport - AME'!J8 -> 1773.7602 | F21: ='Transport - AME'!K8 -> 1146.2522 | X21: Transport | Y21: Neuf post 2020 | Z21: ='Transport - AMS'!H8 -> 0 | AA21: ='Transport - AMS'!I8 -> 2489.8568 | AB21: ='Transport - AMS'!J8 -> 1683.79 | AC21: ='Transport - AMS'!K8 -> 1138.213
B22: Existant 2020 | C22: ='Transport - AME'!H9 -> 41814.604 | D22: ='Transport - AME'!I9 -> 40727.425 | E22: ='Transport - AME'!J9 -> 42312.863 | F22: ='Transport - AME'!K9 -> 42514.775 | Y22: Existant 2020 | Z22: ='Transport - AMS'!H9 -> 41814.604 | AA22: ='Transport - AMS'!I9 -> 40727.425 | AB22: ='Transport - AMS'!J9 -> 42093.632 | AC22: ='Transport - AMS'!K9 -> 41702.656
A23: Total | B23: Neuf post 2020 | C23: =C9+C11+C13+C15+C17+C19+C21 -> 0 | D23: =D9+D11+D13+D15+D17+D19+D21 -> 58277.964 | E23: =E9+E11+E13+E15+E17+E19+E21 -> 44695.977 | F23: =F9+F11+F13+F15+F17+F19+F21 -> 36825.33 | X23: Total | Y23: Neuf post 2020 | Z23: =Z9+Z11+Z13+Z15+Z17+Z19+Z21 -> 0 | AA23: =AA9+AA11+AA13+AA15+AA17+AA19+AA21 -> 54508.805 | AB23: =AB9+AB11+AB13+AB15+AB17+AB19+AB21 -> 43094.231 | AC23: =AC9+AC11+AC13+AC15+AC17+AC19+AC21 -> 33683.416
B24: Existant 2020 | C24: =C10+C12+C14+C16+C18+C20+C22 -> 983437.06 | D24: =D10+D12+D14+D16+D18+D20+D22 -> 944733.51 | E24: =E10+E12+E14+E16+E18+E20+E22 -> 973895.55 | F24: =F10+F12+F14+F16+F18+F20+F22 -> 972631.48 | Y24: Existant 2020 | Z24: =Z10+Z12+Z14+Z16+Z18+Z20+Z22 -> 983437.06 | AA24: =AA10+AA12+AA14+AA16+AA18+AA20+AA22 -> 943305.87 | AB24: =AB10+AB12+AB14+AB16+AB18+AB20+AB22 -> 954650.08 | AC24: =AC10+AC12+AC14+AC16+AC18+AC20+AC22 -> 931004.81
AA25: =AA24*0.4/7 -> 53903.193 | AC25: =AC24*0.3/10 -> 27930.144
A27: Consommation totale en GWh AME | X27: Consommation totale en GWh AMS
A28: Usage | B28: 2020 | C28: 2030 | D28: 2040 | E28: 2050 | X28: Usage | Y28: 2020 | Z28: 2030 | AA28: 2040 | AB28: 2050
A29: Chauffage | B29: =B64 -> 100997.67 | C29: =C64 -> 82779.177 | D29: =D64 -> 75656.355 | E29: =E64 -> 66876.448 | X29: Chauffage | Y29: =Y69 -> 100997.67 | Z29: =Z69 -> 81145.038 | AA29: =AA69 -> 62549.422 | AB29: =AB69 -> 48997.735
A30: Hors chauffage | B30: =B120 -> 158828.24 | C30: =C120 -> 163798.85 | D30: =D120 -> 185016.6 | E30: =E120 -> 213980.17 | X30: Hors chauffage | Y30: =Y120 -> 151855.24 | Z30: =Z120 -> 130305.87 | AA30: =AA120 -> 123681.67 | AB30: =AB120 -> 120626.2
A31: Total | B31: =SUM(B29:B30) -> 259825.91 | C31: =SUM(C29:C30) -> 246578.03 | D31: =SUM(D29:D30) -> 260672.96 | E31: =SUM(E29:E30) -> 280856.62 | X31: Total | Y31: =SUM(Y29:Y30) -> 252852.91 | Z31: =SUM(Z29:Z30) -> 211450.9 | AA31: =SUM(AA29:AA30) -> 186231.09 | AB31: =SUM(AB29:AB30) -> 169623.94
A33: Consommation totale en GWh AME | X33: Consommation totale en GWh AMS
A34: Energie | B34: 2020 | C34: 2030 | D34: 2040 | E34: 2050 | X34: Energie | Y34: 2020 | Z34: 2030 | AA34: 2040 | AB34: 2050
A35: Fuel domestique | B35: =B57+B116 -> 22595.211 | C35: =C57+C116 -> 16467.226 | D35: =D57+D116 -> 13527.856 | E35: =E57+E116 -> 10756.59 | X35: Fuel domestique | Y35: =Y57+Y116 -> 22595.211 | Z35: =Z57+Z116 -> 1657.2553 | AA35: =AA57+AA116 -> 0 | AB35: =AB57+AB116 -> 0 | AC35: =Z35/Y35-1 -> -0.92665458 | AD35: J'aimerais bien que le tertiaire fasse plus d'effort que le résidentiel sur le gaz mais en comparent l'évolution du nombre de chaudière (res) à l'évolution du nombre de m², ce n'est pas équivalent
A36: Gaz naturel | B36: =B58+B115 -> 72724.002 | C36: =C58+C115 -> 59107.144 | D36: =D58+D115 -> 54381.501 | E36: =E58+E115 -> 48964.706 | X36: Gaz naturel | Y36: =Y58+Y115 -> 72856.921 | Z36: =Z58+Z115 -> 51040.534 | AA36: =AA58+AA115 -> 22537.321 | AB36: =AB58+AB115 -> 4455.6684 | AC36: =Z36/Y36-1 -> -0.29944152 | AD36: Le gaz est plus haut en 2030 malgré l'interdiction des chaudières à gaz du fait de la baisse des objectifs DEET dans les bureaux notamment et changement du parc
A37: Réseau de chaleur | B37: =B59+B118 -> 8956.0755 | C37: =C59+C118 -> 8753.9663 | D37: =D59+D118 -> 8305.5385 | E37: =E59+E118 -> 7473.4208 | X37: Réseau de chaleur | Y37: =Y61+Y118 -> 8956.0755 | Z37: =Z61+Z118 -> 18541.841 | AA37: =AA61+AA118 -> 20367.21 | AB37: =AB61+AB118 -> 19367.231 | AC37: =Z37/Y37-1 -> 1.0703087 | AD37: Ne pas faire une extrapolation linéaire entre 2030 et 2040 mais un pic en 2035 et une stabilisation
A38: GPL | B38: =B60 -> 1272.5787 | C38: =C60 -> 1096.1877 | D38: =D60 -> 1044.2803 | E38: =E60 -> 969.07551 | X38: GPL | Y38: =Y62 -> 1272.5787 | Z38: =Z62 -> 767.39292 | AA38: =AA62 -> 433.51045 | AB38: =AB62 -> 44.699236 | AC38: =Z38/Y38-1 -> -0.39697802
A39: ENR | B39: =B61+B117+B119 -> 1509.289 | C39: =C61+C117+C119 -> 1539.1785 | D39: =D61+D117+D119 -> 1625.3271 | E39: =E61+E117+E119 -> 1663.1942 | X39: ENR | Y39: =Y63+Y117+Y119 -> 1509.289 | Z39: =Z63+Z117+Z119 -> 2468.9607 | AA39: =AA63+AA117+AA119 -> 2907.1975 | AB39: =AB63+AB117+AB119 -> 3632.0252 | AC39: =Z39/Y39-1 -> 0.63584357
A40: Electricité (PAC incluses) | B40: =B62+B63+B114 -> 152768.75 | C40: =C62+C63+C114 -> 159614.33 | D40: =D62+D63+D114 -> 181788.45 | E40: =E62+E63+E114 -> 211029.63 | X40: Electricité (PAC incluses) | Y40: =Y64+Y65+Y114 -> 145662.83 | Z40: =Z64+Z65+Z114 -> 136872.65 | AA40: =AA64+AA65+AA114 -> 139808.55 | AB40: =AB64+AB65+AB114 -> 141894.76 | AC40: =Z40/Y40-1 -> -0.060346068
A41: Total | B41: =SUM(B35:B40) -> 259825.91 | C41: =SUM(C35:C40) -> 246578.03 | D41: =SUM(D35:D40) -> 260672.96 | E41: =SUM(E35:E40) -> 280856.62 | X41: Total | Y41: =Y69+Y120 -> 252852.91 | Z41: =Z69+Z120 -> 211450.9 | AA41: =AA69+AA120 -> 186231.09 | AB41: =AB69+AB120 -> 169623.94
A42: Gain énergétique | B42: =B41/$B41-1 -> 0 | C42: =C41/$B41-1 -> -0.050987518 | D42: =D41/$B41-1 -> 0.0032600586 | E42: =E41/$B41-1 -> 0.080941534 | X42: Gain énergétique | Y42: =Y41/$Y41-1 -> 0 | Z42: =Z41/$Y41-1 -> -0.16373947 | AA42: =AA41/$Y41-1 -> -0.26348052 | AB42: =AB41/$Y41-1 -> -0.32915964
B44: =SUM(B35:B40) -> 259825.91 | C44: =SUM(C35:C40) -> 246578.03 | D44: =SUM(D35:D40) -> 260672.96 | E44: =SUM(E35:E40) -> 280856.62
A49: Chauffage | P49: Chauffage
AE52: Trajectoire de PAC hybride (même proposition par rapport aux PAC que dans le résidentiel)
A55: Consommation totale de chauffage en GWh AME (hors chaleur environnement des PAC) | X55: Consommation totale de chauffage en GWh AMS (hors chaleur environnement des PAC) | AF55: 0 | AG55: 0.01 | AH55: 0.05 | AI55: 0.08
A56: Energie | B56: 2020 | C56: 2030 | D56: 2040 | E56: 2050 | X56: Energie | Y56: 2020 | Z56: 2030 | AA56: 2040 | AB56: 2050
A57: Fuel domestique | B57: ='Bureaux - AME'!H13+'CaHoREs - AME'!H13+'Commerce - AME'!H13+'Enseignement - AME'!H13+'Santé social - AME'!H13+'Sport Loisir Culture - AME'!H13+'Transport - AME'!H13 -> 17636.415 | C57: ='Bureaux - AME'!I13+'CaHoREs - AME'!I13+'Commerce - AME'!I13+'Enseignement - AME'!I13+'Santé social - AME'!I13+'Sport Loisir Culture - AME'!I13+'Transport - AME'!I13 -> 12584.183 | D57: ='Bureaux - AME'!J13+'CaHoREs - AME'!J13+'Commerce - AME'!J13+'Enseignement - AME'!J13+'Santé social - AME'!J13+'Sport Loisir Culture - AME'!J13+'Transport - AME'!J13 -> 10229.373 | E57: ='Bureaux - AME'!K13+'CaHoREs - AME'!K13+'Commerce - AME'!K13+'Enseignement - AME'!K13+'Santé social - AME'!K13+'Sport Loisir Culture - AME'!K13+'Transport - AME'!K13 -> 7821.9678 | X57: Fuel domestique | Y57: ='Bureaux - AMS'!H13+'CaHoREs - AMS'!H13+'Commerce - AMS'!H13+'Enseignement - AMS'!H13+'Santé social - AMS'!H13+'Sport Loisir Culture - AMS'!H13+'Transport - AMS'!H13 -> 17636.415 | Z57: ='Bureaux - AMS'!I13+'CaHoREs - AMS'!I13+'Commerce - AMS'!I13+'Enseignement - AMS'!I13+'Santé social - AMS'!I13+'Sport Loisir Culture - AMS'!I13+'Transport - AMS'!I13 -> 1412.7353 | AA57: ='Bureaux - AMS'!J13+'CaHoREs - AMS'!J13+'Commerce - AMS'!J13+'Enseignement - AMS'!J13+'Santé social - AMS'!J13+'Sport Loisir Culture - AMS'!J13+'Transport - AMS'!J13 -> 0 | AB57: ='Bureaux - AMS'!K13+'CaHoREs - AMS'!K13+'Commerce - AMS'!K13+'Enseignement - AMS'!K13+'Santé social - AMS'!K13+'Sport Loisir Culture - AMS'!K13+'Transport - AMS'!K13 -> 0 | AE57: COP PAC | AF57: 3.2
A58: Gaz naturel | B58: ='Bureaux - AME'!H14+'CaHoREs - AME'!H14+'Commerce - AME'!H14+'Enseignement - AME'!H14+'Santé social - AME'!H14+'Sport Loisir Culture - AME'!H14+'Transport - AME'!H14 -> 55805.57 | C58: ='Bureaux - AME'!I14+'CaHoREs - AME'!I14+'Commerce - AME'!I14+'Enseignement - AME'!I14+'Santé social - AME'!I14+'Sport Loisir Culture - AME'!I14+'Transport - AME'!I14 -> 44705.077 | D58: ='Bureaux - AME'!J14+'CaHoREs - AME'!J14+'Commerce - AME'!J14+'Enseignement - AME'!J14+'Santé social - AME'!J14+'Sport Loisir Culture - AME'!J14+'Transport - AME'!J14 -> 40854.269 | E58: ='Bureaux - AME'!K14+'CaHoREs - AME'!K14+'Commerce - AME'!K14+'Enseignement - AME'!K14+'Santé social - AME'!K14+'Sport Loisir Culture - AME'!K14+'Transport - AME'!K14 -> 36337.095 | X58: Gaz naturel | Y58: ='Bureaux - AMS'!H14+'CaHoREs - AMS'!H14+'Commerce - AMS'!H14+'Enseignement - AMS'!H14+'Santé social - AMS'!H14+'Sport Loisir Culture - AMS'!H14+'Transport - AMS'!H14 -> 55805.57 | Z58: =Résultats!Z58+Z60 -> 41297.253 | AA58: =Résultats!AA58+AA60 -> 18429.244 | AB58: =Résultats!AB58+AB60 -> 3619.7932 | AE58: Fonction élec | AF58: 0.7
A59: Réseau de chaleur | B59: ='Bureaux - AME'!H15+'CaHoREs - AME'!H15+'Commerce - AME'!H15+'Enseignement - AME'!H15+'Santé social - AME'!H15+'Sport Loisir Culture - AME'!H15+'Transport - AME'!H15 -> 7405.5823 | C59: ='Bureaux - AME'!I15+'CaHoREs - AME'!I15+'Commerce - AME'!I15+'Enseignement - AME'!I15+'Santé social - AME'!I15+'Sport Loisir Culture - AME'!I15+'Transport - AME'!I15 -> 7048.953 | D59: ='Bureaux - AME'!J15+'CaHoREs - AME'!J15+'Commerce - AME'!J15+'Enseignement - AME'!J15+'Santé social - AME'!J15+'Sport Loisir Culture - AME'!J15+'Transport - AME'!J15 -> 6658.4542 | E59: ='Bureaux - AME'!K15+'CaHoREs - AME'!K15+'Commerce - AME'!K15+'Enseignement - AME'!K15+'Santé social - AME'!K15+'Sport Loisir Culture - AME'!K15+'Transport - AME'!K15 -> 5916.0549 | X59: dont chaudière gaz | Z59: =Z58-Z60 -> 41192.518 | AA59: =AA58-AA60 -> 17539.893 | AB59: =AB58-AB60 -> 1994.3656 | AE59: Fonctionnement gaz | AF59: 0.3
A60: GPL | B60: ='Bureaux - AME'!H16+'CaHoREs - AME'!H16+'Commerce - AME'!H16+'Enseignement - AME'!H16+'Santé social - AME'!H16+'Sport Loisir Culture - AME'!H16+'Transport - AME'!H16 -> 1272.5787 | C60: ='Bureaux - AME'!I16+'CaHoREs - AME'!I16+'Commerce - AME'!I16+'Enseignement - AME'!I16+'Santé social - AME'!I16+'Sport Loisir Culture - AME'!I16+'Transport - AME'!I16 -> 1096.1877 | D60: ='Bureaux - AME'!J16+'CaHoREs - AME'!J16+'Commerce - AME'!J16+'Enseignement - AME'!J16+'Santé social - AME'!J16+'Sport Loisir Culture - AME'!J16+'Transport - AME'!J16 -> 1044.2803 | E60: ='Bureaux - AME'!K16+'CaHoREs - AME'!K16+'Commerce - AME'!K16+'Enseignement - AME'!K16+'Santé social - AME'!K16+'Sport Loisir Culture - AME'!K16+'Transport - AME'!K16 -> 969.07551 | X60: dont PAC hybride | Z60: =Résultats!Z63*AG55*$AF$59*$AF$57*$AF$60 -> 104.73458 | AA60: =Résultats!AA63*AH55*$AF$59*$AF$57*$AF$60 -> 889.35089 | AB60: =Résultats!AB63*AI55*$AF$59*$AF$57*$AF$60 -> 1625.4276 | AE60: Rendement chaudière gaz | AF60: 0.95
A61: ENR | B61: ='Bureaux - AME'!H17+'CaHoREs - AME'!H17+'Commerce - AME'!H17+'Enseignement - AME'!H17+'Santé social - AME'!H17+'Sport Loisir Culture - AME'!H17+'Transport - AME'!H17 -> 1294.6737 | C61: ='Bureaux - AME'!I17+'CaHoREs - AME'!I17+'Commerce - AME'!I17+'Enseignement - AME'!I17+'Santé social - AME'!I17+'Sport Loisir Culture - AME'!I17+'Transport - AME'!I17 -> 1301.9333 | D61: ='Bureaux - AME'!J17+'CaHoREs - AME'!J17+'Commerce - AME'!J17+'Enseignement - AME'!J17+'Santé social - AME'!J17+'Sport Loisir Culture - AME'!J17+'Transport - AME'!J17 -> 1378.0056 | E61: ='Bureaux - AME'!K17+'CaHoREs - AME'!K17+'Commerce - AME'!K17+'Enseignement - AME'!K17+'Santé social - AME'!K17+'Sport Loisir Culture - AME'!K17+'Transport - AME'!K17 -> 1409.2486 | X61: Réseau de chaleur | Y61: ='Bureaux - AMS'!H15+'CaHoREs - AMS'!H15+'Commerce - AMS'!H15+'Enseignement - AMS'!H15+'Santé social - AMS'!H15+'Sport Loisir Culture - AMS'!H15+'Transport - AMS'!H15 -> 7405.5823 | Z61: ='Bureaux - AMS'!I15+'CaHoREs - AMS'!I15+'Commerce - AMS'!I15+'Enseignement - AMS'!I15+'Santé social - AMS'!I15+'Sport Loisir Culture - AMS'!I15+'Transport - AMS'!I15 -> 15030.614 | AA61: ='Bureaux - AMS'!J15+'CaHoREs - AMS'!J15+'Commerce - AMS'!J15+'Enseignement - AMS'!J15+'Santé social - AMS'!J15+'Sport Loisir Culture - AMS'!J15+'Transport - AMS'!J15 -> 16931.093 | AB61: ='Bureaux - AMS'!K15+'CaHoREs - AMS'!K15+'Commerce - AMS'!K15+'Enseignement - AMS'!K15+'Santé social - AMS'!K15+'Sport Loisir Culture - AMS'!K15+'Transport - AMS'!K15 -> 16308.183
A62: Electricité Joule | B62: ='Bureaux - AME'!H18+'CaHoREs - AME'!H18+'Commerce - AME'!H18+'Enseignement - AME'!H18+'Santé social - AME'!H18+'Sport Loisir Culture - AME'!H18+'Transport - AME'!H18 -> 14607.453 | C62: ='Bureaux - AME'!I18+'CaHoREs - AME'!I18+'Commerce - AME'!I18+'Enseignement - AME'!I18+'Santé social - AME'!I18+'Sport Loisir Culture - AME'!I18+'Transport - AME'!I18 -> 10422.471 | D62: ='Bureaux - AME'!J18+'CaHoREs - AME'!J18+'Commerce - AME'!J18+'Enseignement - AME'!J18+'Santé social - AME'!J18+'Sport Loisir Culture - AME'!J18+'Transport - AME'!J18 -> 8187.5359 | E62: ='Bureaux - AME'!K18+'CaHoREs - AME'!K18+'Commerce - AME'!K18+'Enseignement - AME'!K18+'Santé social - AME'!K18+'Sport Loisir Culture - AME'!K18+'Transport - AME'!K18 -> 5993.7367 | X62: GPL | Y62: ='Bureaux - AMS'!H16+'CaHoREs - AMS'!H16+'Commerce - AMS'!H16+'Enseignement - AMS'!H16+'Santé social - AMS'!H16+'Sport Loisir Culture - AMS'!H16+'Transport - AMS'!H16 -> 1272.5787 | Z62: ='Bureaux - AMS'!I16+'CaHoREs - AMS'!I16+'Commerce - AMS'!I16+'Enseignement - AMS'!I16+'Santé social - AMS'!I16+'Sport Loisir Culture - AMS'!I16+'Transport - AMS'!I16 -> 767.39292 | AA62: ='Bureaux - AMS'!J16+'CaHoREs - AMS'!J16+'Commerce - AMS'!J16+'Enseignement - AMS'!J16+'Santé social - AMS'!J16+'Sport Loisir Culture - AMS'!J16+'Transport - AMS'!J16 -> 433.51045 | AB62: ='Bureaux - AMS'!K16+'CaHoREs - AMS'!K16+'Commerce - AMS'!K16+'Enseignement - AMS'!K16+'Santé social - AMS'!K16+'Sport Loisir Culture - AMS'!K16+'Transport - AMS'!K16 -> 44.699236 | AE62: Trajectoire de PAC géothermique (besoins thermiques) : 35% des besoins thermiques de la trajectoire géothermie (cf résidentiel)
A63: Electricité PAC | B63: ='Bureaux - AME'!H19+'CaHoREs - AME'!H19+'Commerce - AME'!H19+'Enseignement - AME'!H19+'Santé social - AME'!H19+'Sport Loisir Culture - AME'!H19+'Transport - AME'!H19 -> 2975.3948 | C63: ='Bureaux - AME'!I19+'CaHoREs - AME'!I19+'Commerce - AME'!I19+'Enseignement - AME'!I19+'Santé social - AME'!I19+'Sport Loisir Culture - AME'!I19+'Transport - AME'!I19 -> 5620.3727 | D63: ='Bureaux - AME'!J19+'CaHoREs - AME'!J19+'Commerce - AME'!J19+'Enseignement - AME'!J19+'Santé social - AME'!J19+'Sport Loisir Culture - AME'!J19+'Transport - AME'!J19 -> 7304.4367 | E63: ='Bureaux - AME'!K19+'CaHoREs - AME'!K19+'Commerce - AME'!K19+'Enseignement - AME'!K19+'Santé social - AME'!K19+'Sport Loisir Culture - AME'!K19+'Transport - AME'!K19 -> 8429.2693 | X63: ENR | Y63: ='Bureaux - AMS'!H17+'CaHoREs - AMS'!H17+'Commerce - AMS'!H17+'Enseignement - AMS'!H17+'Santé social - AMS'!H17+'Sport Loisir Culture - AMS'!H17+'Transport - AMS'!H17 -> 1294.6737 | Z63: ='Bureaux - AMS'!I17+'CaHoREs - AMS'!I17+'Commerce - AMS'!I17+'Enseignement - AMS'!I17+'Santé social - AMS'!I17+'Sport Loisir Culture - AMS'!I17+'Transport - AMS'!I17 -> 1805.8393 | AA63: ='Bureaux - AMS'!J17+'CaHoREs - AMS'!J17+'Commerce - AMS'!J17+'Enseignement - AMS'!J17+'Santé social - AMS'!J17+'Sport Loisir Culture - AMS'!J17+'Transport - AMS'!J17 -> 2373.5326 | AB63: ='Bureaux - AMS'!K17+'CaHoREs - AMS'!K17+'Commerce - AMS'!K17+'Enseignement - AMS'!K17+'Santé social - AMS'!K17+'Sport Loisir Culture - AMS'!K17+'Transport - AMS'!K17 -> 3195.7121
A64: Total | B64: =SUM(B57:B63) -> 100997.67 | C64: =SUM(C57:C63) -> 82779.177 | D64: =SUM(D57:D63) -> 75656.355 | E64: =SUM(E57:E63) -> 66876.448 | X64: Electricité Joule | Y64: ='Bureaux - AMS'!H18+'CaHoREs - AMS'!H18+'Commerce - AMS'!H18+'Enseignement - AMS'!H18+'Santé social - AMS'!H18+'Sport Loisir Culture - AMS'!H18+'Transport - AMS'!H18 -> 14607.453 | Z64: ='Bureaux - AMS'!I18+'CaHoREs - AMS'!I18+'Commerce - AMS'!I18+'Enseignement - AMS'!I18+'Santé social - AMS'!I18+'Sport Loisir Culture - AMS'!I18+'Transport - AMS'!I18 -> 9642.0183 | AA64: ='Bureaux - AMS'!J18+'CaHoREs - AMS'!J18+'Commerce - AMS'!J18+'Enseignement - AMS'!J18+'Santé social - AMS'!J18+'Sport Loisir Culture - AMS'!J18+'Transport - AMS'!J18 -> 5751.6397 | AB64: ='Bureaux - AMS'!K18+'CaHoREs - AMS'!K18+'Commerce - AMS'!K18+'Enseignement - AMS'!K18+'Santé social - AMS'!K18+'Sport Loisir Culture - AMS'!K18+'Transport - AMS'!K18 -> 5000.8677 | AF64: 2022 | AG64: 2030 | AH64: 2040 | AI64: 2050
A65: Gain énergétique | B65: =B64/$B64-1 -> 0 | C65: =C64/$B64-1 -> -0.18038526 | D65: =D64/$B64-1 -> -0.25090988 | E65: =E64/$B64-1 -> -0.33784166 | X65: Electricité PAC | Y65: ='Bureaux - AMS'!H19+'CaHoREs - AMS'!H19+'Commerce - AMS'!H19+'Enseignement - AMS'!H19+'Santé social - AMS'!H19+'Sport Loisir Culture - AMS'!H19+'Transport - AMS'!H19 -> 2975.3948 | Z65: =Résultats!Z63-AG55*Résultats!Z63-AG65*1000/$AF$57+Z67+Z68 -> 11189.186 | AA65: =Résultats!AA63-AH55*Résultats!AA63-AH65*1000/$AF$57+AA67+AA68 -> 18630.402 | AB65: =Résultats!AB63-AI55*Résultats!AB63-AI65*1000/$AF$57+AB67+AB68 -> 20828.481 | AE65: Besoins en TWh thermique | AF65: 1.1 | AG65: 3.5 | AH65: 7.8 | AI65: 12.3
X66: dont PAC air/eau et air/air | Z66: =Z65-Z67-Z68 -> 10275.464 | AA66: =AA65-AA67-AA68 -> 16090.643 | AB66: =AB65-AB67-AB68 -> 16652.322 | AE66: COP PAC géo | AF66: 4.2
X67: dont PAC géothermique | Z67: =AG65/$AF$66*1000 -> 833.33333 | AA67: =AH65/$AF$66*1000 -> 1857.1429 | AB67: =AI65/$AF$66*1000 -> 2928.5714
X68: dont PAC hybride | Z68: =AG55*Résultats!Z63*$AF$58 -> 80.388382 | AA68: =AH55*Résultats!AA63*$AF$58 -> 682.61581 | AB68: =AI55*Résultats!AB63*$AF$58 -> 1247.587
X69: Total | Y69: =SUM(Y57:Y65) -> 100997.67 | Z69: =SUM(Z57:Z58,Z61:Z65) -> 81145.038 | AA69: =SUM(AA57:AA58,AA61:AA65) -> 62549.422 | AB69: =SUM(AB57:AB58,AB61:AB65) -> 48997.735
X70: Gain énergétique vs 2020 | Y70: =Y69/$Y69-1 -> 0 | Z70: =Z69/$Y69-1 -> -0.19656522 | AA70: =AA69/$Y69-1 -> -0.38068449 | AB70: =AB69/$Y69-1 -> -0.5148627
A79: Consommation parc suivant le décret en GWh AME | X79: Consommation parc suivant le décret en GWh AMS
A80: Energie | B80: 2020 | C80: 2030 | D80: 2040 | E80: 2050 | X80: Energie | Y80: 2020 | Z80: 2030 | AA80: 2040 | AB80: 2050
A81: Fuel domestique | B81: ='Bureaux - AME'!H111+'CaHoREs - AME'!H111+'Commerce - AME'!H111+'Enseignement - AME'!H111+'Santé social - AME'!H111+'Sport Loisir Culture - AME'!H111+'Transport - AME'!H111 -> 6972.2798 | C81: ='Bureaux - AME'!I111+'CaHoREs - AME'!I111+'Commerce - AME'!I111+'Enseignement - AME'!I111+'Santé social - AME'!I111+'Sport Loisir Culture - AME'!I111+'Transport - AME'!I111 -> 4111.1754 | D81: ='Bureaux - AME'!J111+'CaHoREs - AME'!J111+'Commerce - AME'!J111+'Enseignement - AME'!J111+'Santé social - AME'!J111+'Sport Loisir Culture - AME'!J111+'Transport - AME'!J111 -> 3116.8322 | E81: ='Bureaux - AME'!K111+'CaHoREs - AME'!K111+'Commerce - AME'!K111+'Enseignement - AME'!K111+'Santé social - AME'!K111+'Sport Loisir Culture - AME'!K111+'Transport - AME'!K111 -> 2159.2824 | X81: Fuel domestique | Y81: ='Bureaux - AMS'!H111+'CaHoREs - AMS'!H111+'Commerce - AMS'!H111+'Enseignement - AMS'!H111+'Santé social - AMS'!H111+'Sport Loisir Culture - AMS'!H111+'Transport - AMS'!H111 -> 15677.951 | Z81: ='Bureaux - AMS'!I111+'CaHoREs - AMS'!I111+'Commerce - AMS'!I111+'Enseignement - AMS'!I111+'Santé social - AMS'!I111+'Sport Loisir Culture - AMS'!I111+'Transport - AMS'!I111 -> 1264.1057 | AA81: ='Bureaux - AMS'!J111+'CaHoREs - AMS'!J111+'Commerce - AMS'!J111+'Enseignement - AMS'!J111+'Santé social - AMS'!J111+'Sport Loisir Culture - AMS'!J111+'Transport - AMS'!J111 -> 0 | AB81: ='Bureaux - AMS'!K111+'CaHoREs - AMS'!K111+'Commerce - AMS'!K111+'Enseignement - AMS'!K111+'Santé social - AMS'!K111+'Sport Loisir Culture - AMS'!K111+'Transport - AMS'!K111 -> 0
A82: Gaz naturel | B82: ='Bureaux - AME'!H112+'CaHoREs - AME'!H112+'Commerce - AME'!H112+'Enseignement - AME'!H112+'Santé social - AME'!H112+'Sport Loisir Culture - AME'!H112+'Transport - AME'!H112 -> 21704.94 | C82: ='Bureaux - AME'!I112+'CaHoREs - AME'!I112+'Commerce - AME'!I112+'Enseignement - AME'!I112+'Santé social - AME'!I112+'Sport Loisir Culture - AME'!I112+'Transport - AME'!I112 -> 14287.535 | D82: ='Bureaux - AME'!J112+'CaHoREs - AME'!J112+'Commerce - AME'!J112+'Enseignement - AME'!J112+'Santé social - AME'!J112+'Sport Loisir Culture - AME'!J112+'Transport - AME'!J112 -> 12077.574 | E82: ='Bureaux - AME'!K112+'CaHoREs - AME'!K112+'Commerce - AME'!K112+'Enseignement - AME'!K112+'Santé social - AME'!K112+'Sport Loisir Culture - AME'!K112+'Transport - AME'!K112 -> 9839.8145 | X82: Gaz naturel | Y82: ='Bureaux - AMS'!H112+'CaHoREs - AMS'!H112+'Commerce - AMS'!H112+'Enseignement - AMS'!H112+'Santé social - AMS'!H112+'Sport Loisir Culture - AMS'!H112+'Transport - AMS'!H112 -> 49305.068 | Z82: ='Bureaux - AMS'!I112+'CaHoREs - AMS'!I112+'Commerce - AMS'!I112+'Enseignement - AMS'!I112+'Santé social - AMS'!I112+'Sport Loisir Culture - AMS'!I112+'Transport - AMS'!I112 -> 36178.937 | AA82: ='Bureaux - AMS'!J112+'CaHoREs - AMS'!J112+'Commerce - AMS'!J112+'Enseignement - AMS'!J112+'Santé social - AMS'!J112+'Sport Loisir Culture - AMS'!J112+'Transport - AMS'!J112 -> 15335.266 | AB82: ='Bureaux - AMS'!K112+'CaHoREs - AMS'!K112+'Commerce - AMS'!K112+'Enseignement - AMS'!K112+'Santé social - AMS'!K112+'Sport Loisir Culture - AMS'!K112+'Transport - AMS'!K112 -> 1736.2961
A83: Réseau de chaleur | B83: ='Bureaux - AME'!H113+'CaHoREs - AME'!H113+'Commerce - AME'!H113+'Enseignement - AME'!H113+'Santé social - AME'!H113+'Sport Loisir Culture - AME'!H113+'Transport - AME'!H113 -> 2920.2151 | C83: ='Bureaux - AME'!I113+'CaHoREs - AME'!I113+'Commerce - AME'!I113+'Enseignement - AME'!I113+'Santé social - AME'!I113+'Sport Loisir Culture - AME'!I113+'Transport - AME'!I113 -> 2518.4436 | D83: ='Bureaux - AME'!J113+'CaHoREs - AME'!J113+'Commerce - AME'!J113+'Enseignement - AME'!J113+'Santé social - AME'!J113+'Sport Loisir Culture - AME'!J113+'Transport - AME'!J113 -> 2207.7839 | E83: ='Bureaux - AME'!K113+'CaHoREs - AME'!K113+'Commerce - AME'!K113+'Enseignement - AME'!K113+'Santé social - AME'!K113+'Sport Loisir Culture - AME'!K113+'Transport - AME'!K113 -> 1779.3643 | X83: Réseau de chaleur | Y83: ='Bureaux - AMS'!H113+'CaHoREs - AMS'!H113+'Commerce - AMS'!H113+'Enseignement - AMS'!H113+'Santé social - AMS'!H113+'Sport Loisir Culture - AMS'!H113+'Transport - AMS'!H113 -> 6576.8119 | Z83: ='Bureaux - AMS'!I113+'CaHoREs - AMS'!I113+'Commerce - AMS'!I113+'Enseignement - AMS'!I113+'Santé social - AMS'!I113+'Sport Loisir Culture - AMS'!I113+'Transport - AMS'!I113 -> 12224.423 | AA83: ='Bureaux - AMS'!J113+'CaHoREs - AMS'!J113+'Commerce - AMS'!J113+'Enseignement - AMS'!J113+'Santé social - AMS'!J113+'Sport Loisir Culture - AMS'!J113+'Transport - AMS'!J113 -> 13882.247 | AB83: ='Bureaux - AMS'!K113+'CaHoREs - AMS'!K113+'Commerce - AMS'!K113+'Enseignement - AMS'!K113+'Santé social - AMS'!K113+'Sport Loisir Culture - AMS'!K113+'Transport - AMS'!K113 -> 13420.577
A84: GPL | B84: ='Bureaux - AME'!H114+'CaHoREs - AME'!H114+'Commerce - AME'!H114+'Enseignement - AME'!H114+'Santé social - AME'!H114+'Sport Loisir Culture - AME'!H114+'Transport - AME'!H114 -> 495.96141 | C84: ='Bureaux - AME'!I114+'CaHoREs - AME'!I114+'Commerce - AME'!I114+'Enseignement - AME'!I114+'Santé social - AME'!I114+'Sport Loisir Culture - AME'!I114+'Transport - AME'!I114 -> 341.84977 | D84: ='Bureaux - AME'!J114+'CaHoREs - AME'!J114+'Commerce - AME'!J114+'Enseignement - AME'!J114+'Santé social - AME'!J114+'Sport Loisir Culture - AME'!J114+'Transport - AME'!J114 -> 307.33844 | E84: ='Bureaux - AME'!K114+'CaHoREs - AME'!K114+'Commerce - AME'!K114+'Enseignement - AME'!K114+'Santé social - AME'!K114+'Sport Loisir Culture - AME'!K114+'Transport - AME'!K114 -> 269.30056 | X84: GPL | Y84: ='Bureaux - AMS'!H114+'CaHoREs - AMS'!H114+'Commerce - AMS'!H114+'Enseignement - AMS'!H114+'Santé social - AMS'!H114+'Sport Loisir Culture - AMS'!H114+'Transport - AMS'!H114 -> 1122.0414 | Z84: ='Bureaux - AMS'!I114+'CaHoREs - AMS'!I114+'Commerce - AMS'!I114+'Enseignement - AMS'!I114+'Santé social - AMS'!I114+'Sport Loisir Culture - AMS'!I114+'Transport - AMS'!I114 -> 596.48222 | AA84: ='Bureaux - AMS'!J114+'CaHoREs - AMS'!J114+'Commerce - AMS'!J114+'Enseignement - AMS'!J114+'Santé social - AMS'!J114+'Sport Loisir Culture - AMS'!J114+'Transport - AMS'!J114 -> 321.73629 | AB84: ='Bureaux - AMS'!K114+'CaHoREs - AMS'!K114+'Commerce - AMS'!K114+'Enseignement - AMS'!K114+'Santé social - AMS'!K114+'Sport Loisir Culture - AMS'!K114+'Transport - AMS'!K114 -> 0
A85: ENR | B85: ='Bureaux - AME'!H115+'CaHoREs - AME'!H115+'Commerce - AME'!H115+'Enseignement - AME'!H115+'Santé social - AME'!H115+'Sport Loisir Culture - AME'!H115+'Transport - AME'!H115 -> 490.36176 | C85: ='Bureaux - AME'!I115+'CaHoREs - AME'!I115+'Commerce - AME'!I115+'Enseignement - AME'!I115+'Santé social - AME'!I115+'Sport Loisir Culture - AME'!I115+'Transport - AME'!I115 -> 355.28733 | D85: ='Bureaux - AME'!J115+'CaHoREs - AME'!J115+'Commerce - AME'!J115+'Enseignement - AME'!J115+'Santé social - AME'!J115+'Sport Loisir Culture - AME'!J115+'Transport - AME'!J115 -> 328.35296 | E85: ='Bureaux - AME'!K115+'CaHoREs - AME'!K115+'Commerce - AME'!K115+'Enseignement - AME'!K115+'Santé social - AME'!K115+'Sport Loisir Culture - AME'!K115+'Transport - AME'!K115 -> 294.00984 | X85: ENR | Y85: ='Bureaux - AMS'!H115+'CaHoREs - AMS'!H115+'Commerce - AMS'!H115+'Enseignement - AMS'!H115+'Santé social - AMS'!H115+'Sport Loisir Culture - AMS'!H115+'Transport - AMS'!H115 -> 1122.8654 | Z85: ='Bureaux - AMS'!I115+'CaHoREs - AMS'!I115+'Commerce - AMS'!I115+'Enseignement - AMS'!I115+'Santé social - AMS'!I115+'Sport Loisir Culture - AMS'!I115+'Transport - AMS'!I115 -> 1455.4779 | AA85: ='Bureaux - AMS'!J115+'CaHoREs - AMS'!J115+'Commerce - AMS'!J115+'Enseignement - AMS'!J115+'Santé social - AMS'!J115+'Sport Loisir Culture - AMS'!J115+'Transport - AMS'!J115 -> 1933.5812 | AB85: ='Bureaux - AMS'!K115+'CaHoREs - AMS'!K115+'Commerce - AMS'!K115+'Enseignement - AMS'!K115+'Santé social - AMS'!K115+'Sport Loisir Culture - AMS'!K115+'Transport - AMS'!K115 -> 2587.3303
A86: Electricité Joule | B86: ='Bureaux - AME'!H116+'CaHoREs - AME'!H116+'Commerce - AME'!H116+'Enseignement - AME'!H116+'Santé social - AME'!H116+'Sport Loisir Culture - AME'!H116+'Transport - AME'!H116 -> 5412.3542 | C86: ='Bureaux - AME'!I116+'CaHoREs - AME'!I116+'Commerce - AME'!I116+'Enseignement - AME'!I116+'Santé social - AME'!I116+'Sport Loisir Culture - AME'!I116+'Transport - AME'!I116 -> 3196.4902 | D86: ='Bureaux - AME'!J116+'CaHoREs - AME'!J116+'Commerce - AME'!J116+'Enseignement - AME'!J116+'Santé social - AME'!J116+'Sport Loisir Culture - AME'!J116+'Transport - AME'!J116 -> 2492.2801 | E86: ='Bureaux - AME'!K116+'CaHoREs - AME'!K116+'Commerce - AME'!K116+'Enseignement - AME'!K116+'Santé social - AME'!K116+'Sport Loisir Culture - AME'!K116+'Transport - AME'!K116 -> 1740.3837 | X86: Electricité Joule | Y86: ='Bureaux - AMS'!H116+'CaHoREs - AMS'!H116+'Commerce - AMS'!H116+'Enseignement - AMS'!H116+'Santé social - AMS'!H116+'Sport Loisir Culture - AMS'!H116+'Transport - AMS'!H116 -> 12624.856 | Z86: ='Bureaux - AMS'!I116+'CaHoREs - AMS'!I116+'Commerce - AMS'!I116+'Enseignement - AMS'!I116+'Santé social - AMS'!I116+'Sport Loisir Culture - AMS'!I116+'Transport - AMS'!I116 -> 8151.8233 | AA86: ='Bureaux - AMS'!J116+'CaHoREs - AMS'!J116+'Commerce - AMS'!J116+'Enseignement - AMS'!J116+'Santé social - AMS'!J116+'Sport Loisir Culture - AMS'!J116+'Transport - AMS'!J116 -> 4952.0376 | AB86: ='Bureaux - AMS'!K116+'CaHoREs - AMS'!K116+'Commerce - AMS'!K116+'Enseignement - AMS'!K116+'Santé social - AMS'!K116+'Sport Loisir Culture - AMS'!K116+'Transport - AMS'!K116 -> 4384.8516
A87: Electricité PAC | B87: ='Bureaux - AME'!H117+'CaHoREs - AME'!H117+'Commerce - AME'!H117+'Enseignement - AME'!H117+'Santé social - AME'!H117+'Sport Loisir Culture - AME'!H117+'Transport - AME'!H117 -> 1068.6057 | C87: ='Bureaux - AME'!I117+'CaHoREs - AME'!I117+'Commerce - AME'!I117+'Enseignement - AME'!I117+'Santé social - AME'!I117+'Sport Loisir Culture - AME'!I117+'Transport - AME'!I117 -> 1615.9999 | D87: ='Bureaux - AME'!J117+'CaHoREs - AME'!J117+'Commerce - AME'!J117+'Enseignement - AME'!J117+'Santé social - AME'!J117+'Sport Loisir Culture - AME'!J117+'Transport - AME'!J117 -> 2249.9941 | E87: ='Bureaux - AME'!K117+'CaHoREs - AME'!K117+'Commerce - AME'!K117+'Enseignement - AME'!K117+'Santé social - AME'!K117+'Sport Loisir Culture - AME'!K117+'Transport - AME'!K117 -> 2784.0591 | X87: Electricité PAC | Y87: ='Bureaux - AMS'!H117+'CaHoREs - AMS'!H117+'Commerce - AMS'!H117+'Enseignement - AMS'!H117+'Santé social - AMS'!H117+'Sport Loisir Culture - AMS'!H117+'Transport - AMS'!H117 -> 2527.1486 | Z87: ='Bureaux - AMS'!I117+'CaHoREs - AMS'!I117+'Commerce - AMS'!I117+'Enseignement - AMS'!I117+'Santé social - AMS'!I117+'Sport Loisir Culture - AMS'!I117+'Transport - AMS'!I117 -> 9089.5883 | AA87: ='Bureaux - AMS'!J117+'CaHoREs - AMS'!J117+'Commerce - AMS'!J117+'Enseignement - AMS'!J117+'Santé social - AMS'!J117+'Sport Loisir Culture - AMS'!J117+'Transport - AMS'!J117 -> 16364.513 | AB87: ='Bureaux - AMS'!K117+'CaHoREs - AMS'!K117+'Commerce - AMS'!K117+'Enseignement - AMS'!K117+'Santé social - AMS'!K117+'Sport Loisir Culture - AMS'!K117+'Transport - AMS'!K117 -> 19145.296
A88: Total | B88: =SUM(B81:B87) -> 39064.718 | C88: =SUM(C81:C87) -> 26426.781 | D88: =SUM(D81:D87) -> 22780.155 | E88: =SUM(E81:E87) -> 18866.214 | X88: Total | Y88: =SUM(Y81:Y87) -> 88956.743 | Z88: =SUM(Z81:Z87) -> 68960.838 | AA88: =SUM(AA81:AA87) -> 52789.382 | AB88: =SUM(AB81:AB87) -> 41274.351
A89: Gain énergétique | B89: =B88/$B88-1 -> 0 | C89: =C88/$B88-1 -> -0.32351282 | D89: =D88/$B88-1 -> -0.41686113 | E89: =E88/$B88-1 -> -0.51705234 | X89: Gain énergétique vs 2020 | Y89: =Y88/$Y88-1 -> 0 | Z89: =Z88/$Y88-1 -> -0.22478234 | AA89: =AA88/$Y88-1 -> -0.40657245 | AB89: =AB88/$Y88-1 -> -0.53601774
A91: Consommation parc hors décret en GWh AME | X91: Consommation parc hors décret en GWh AMS
A92: Energie | B92: 2020 | C92: 2030 | D92: 2040 | E92: 2050 | X92: Energie | Y92: 2020 | Z92: 2030 | AA92: 2040 | AB92: 2050
A93: Fuel domestique | B93: ='Bureaux - AME'!H122+'CaHoREs - AME'!H122+'Commerce - AME'!H122+'Enseignement - AME'!H122+'Santé social - AME'!H122+'Sport Loisir Culture - AME'!H122+'Transport - AME'!H122 -> 10664.135 | C93: ='Bureaux - AME'!I122+'CaHoREs - AME'!I122+'Commerce - AME'!I122+'Enseignement - AME'!I122+'Santé social - AME'!I122+'Sport Loisir Culture - AME'!I122+'Transport - AME'!I122 -> 8469.3394 | D93: ='Bureaux - AME'!J122+'CaHoREs - AME'!J122+'Commerce - AME'!J122+'Enseignement - AME'!J122+'Santé social - AME'!J122+'Sport Loisir Culture - AME'!J122+'Transport - AME'!J122 -> 7111.1063 | E93: ='Bureaux - AME'!K122+'CaHoREs - AME'!K122+'Commerce - AME'!K122+'Enseignement - AME'!K122+'Santé social - AME'!K122+'Sport Loisir Culture - AME'!K122+'Transport - AME'!K122 -> 5661.3849 | X93: Fuel domestique | Y93: ='Bureaux - AMS'!H122+'CaHoREs - AMS'!H122+'Commerce - AMS'!H122+'Enseignement - AMS'!H122+'Santé social - AMS'!H122+'Sport Loisir Culture - AMS'!H122+'Transport - AMS'!H122 -> 1958.4638 | Z93: ='Bureaux - AMS'!I122+'CaHoREs - AMS'!I122+'Commerce - AMS'!I122+'Enseignement - AMS'!I122+'Santé social - AMS'!I122+'Sport Loisir Culture - AMS'!I122+'Transport - AMS'!I122 -> 148.62958 | AA93: ='Bureaux - AMS'!J122+'CaHoREs - AMS'!J122+'Commerce - AMS'!J122+'Enseignement - AMS'!J122+'Santé social - AMS'!J122+'Sport Loisir Culture - AMS'!J122+'Transport - AMS'!J122 -> 0 | AB93: ='Bureaux - AMS'!K122+'CaHoREs - AMS'!K122+'Commerce - AMS'!K122+'Enseignement - AMS'!K122+'Santé social - AMS'!K122+'Sport Loisir Culture - AMS'!K122+'Transport - AMS'!K122 -> 0
A94: Gaz naturel | B94: ='Bureaux - AME'!H123+'CaHoREs - AME'!H123+'Commerce - AME'!H123+'Enseignement - AME'!H123+'Santé social - AME'!H123+'Sport Loisir Culture - AME'!H123+'Transport - AME'!H123 -> 34100.63 | C94: ='Bureaux - AME'!I123+'CaHoREs - AME'!I123+'Commerce - AME'!I123+'Enseignement - AME'!I123+'Santé social - AME'!I123+'Sport Loisir Culture - AME'!I123+'Transport - AME'!I123 -> 30417.543 | D94: ='Bureaux - AME'!J123+'CaHoREs - AME'!J123+'Commerce - AME'!J123+'Enseignement - AME'!J123+'Santé social - AME'!J123+'Sport Loisir Culture - AME'!J123+'Transport - AME'!J123 -> 28776.695 | E94: ='Bureaux - AME'!K123+'CaHoREs - AME'!K123+'Commerce - AME'!K123+'Enseignement - AME'!K123+'Santé social - AME'!K123+'Sport Loisir Culture - AME'!K123+'Transport - AME'!K123 -> 26497.28 | X94: Gaz naturel | Y94: ='Bureaux - AMS'!H123+'CaHoREs - AMS'!H123+'Commerce - AMS'!H123+'Enseignement - AMS'!H123+'Santé social - AMS'!H123+'Sport Loisir Culture - AMS'!H123+'Transport - AMS'!H123 -> 6500.5014 | Z94: ='Bureaux - AMS'!I123+'CaHoREs - AMS'!I123+'Commerce - AMS'!I123+'Enseignement - AMS'!I123+'Santé social - AMS'!I123+'Sport Loisir Culture - AMS'!I123+'Transport - AMS'!I123 -> 4982.025 | AA94: ='Bureaux - AMS'!J123+'CaHoREs - AMS'!J123+'Commerce - AMS'!J123+'Enseignement - AMS'!J123+'Santé social - AMS'!J123+'Sport Loisir Culture - AMS'!J123+'Transport - AMS'!J123 -> 2185.227 | AB94: ='Bureaux - AMS'!K123+'CaHoREs - AMS'!K123+'Commerce - AMS'!K123+'Enseignement - AMS'!K123+'Santé social - AMS'!K123+'Sport Loisir Culture - AMS'!K123+'Transport - AMS'!K123 -> 246.2669
A95: Réseau de chaleur | B95: ='Bureaux - AME'!H124+'CaHoREs - AME'!H124+'Commerce - AME'!H124+'Enseignement - AME'!H124+'Santé social - AME'!H124+'Sport Loisir Culture - AME'!H124+'Transport - AME'!H124 -> 4485.3672 | C95: ='Bureaux - AME'!I124+'CaHoREs - AME'!I124+'Commerce - AME'!I124+'Enseignement - AME'!I124+'Santé social - AME'!I124+'Sport Loisir Culture - AME'!I124+'Transport - AME'!I124 -> 4107.7016 | D95: ='Bureaux - AME'!J124+'CaHoREs - AME'!J124+'Commerce - AME'!J124+'Enseignement - AME'!J124+'Santé social - AME'!J124+'Sport Loisir Culture - AME'!J124+'Transport - AME'!J124 -> 4101.063 | E95: ='Bureaux - AME'!K124+'CaHoREs - AME'!K124+'Commerce - AME'!K124+'Enseignement - AME'!K124+'Santé social - AME'!K124+'Sport Loisir Culture - AME'!K124+'Transport - AME'!K124 -> 3861.5949 | X95: Réseau de chaleur | Y95: ='Bureaux - AMS'!H124+'CaHoREs - AMS'!H124+'Commerce - AMS'!H124+'Enseignement - AMS'!H124+'Santé social - AMS'!H124+'Sport Loisir Culture - AMS'!H124+'Transport - AMS'!H124 -> 828.77043 | Z95: ='Bureaux - AMS'!I124+'CaHoREs - AMS'!I124+'Commerce - AMS'!I124+'Enseignement - AMS'!I124+'Santé social - AMS'!I124+'Sport Loisir Culture - AMS'!I124+'Transport - AMS'!I124 -> 1729.5924 | AA95: ='Bureaux - AMS'!J124+'CaHoREs - AMS'!J124+'Commerce - AMS'!J124+'Enseignement - AMS'!J124+'Santé social - AMS'!J124+'Sport Loisir Culture - AMS'!J124+'Transport - AMS'!J124 -> 2166.5328 | AB95: ='Bureaux - AMS'!K124+'CaHoREs - AMS'!K124+'Commerce - AMS'!K124+'Enseignement - AMS'!K124+'Santé social - AMS'!K124+'Sport Loisir Culture - AMS'!K124+'Transport - AMS'!K124 -> 2268.5551
A96: GPL | B96: ='Bureaux - AME'!H125+'CaHoREs - AME'!H125+'Commerce - AME'!H125+'Enseignement - AME'!H125+'Santé social - AME'!H125+'Sport Loisir Culture - AME'!H125+'Transport - AME'!H125 -> 776.61727 | C96: ='Bureaux - AME'!I125+'CaHoREs - AME'!I125+'Commerce - AME'!I125+'Enseignement - AME'!I125+'Santé social - AME'!I125+'Sport Loisir Culture - AME'!I125+'Transport - AME'!I125 -> 708.74036 | D96: ='Bureaux - AME'!J125+'CaHoREs - AME'!J125+'Commerce - AME'!J125+'Enseignement - AME'!J125+'Santé social - AME'!J125+'Sport Loisir Culture - AME'!J125+'Transport - AME'!J125 -> 698.31185 | E96: ='Bureaux - AME'!K125+'CaHoREs - AME'!K125+'Commerce - AME'!K125+'Enseignement - AME'!K125+'Santé social - AME'!K125+'Sport Loisir Culture - AME'!K125+'Transport - AME'!K125 -> 670.69558 | X96: GPL | Y96: ='Bureaux - AMS'!H125+'CaHoREs - AMS'!H125+'Commerce - AMS'!H125+'Enseignement - AMS'!H125+'Santé social - AMS'!H125+'Sport Loisir Culture - AMS'!H125+'Transport - AMS'!H125 -> 150.53733 | Z96: ='Bureaux - AMS'!I125+'CaHoREs - AMS'!I125+'Commerce - AMS'!I125+'Enseignement - AMS'!I125+'Santé social - AMS'!I125+'Sport Loisir Culture - AMS'!I125+'Transport - AMS'!I125 -> 91.961003 | AA96: ='Bureaux - AMS'!J125+'CaHoREs - AMS'!J125+'Commerce - AMS'!J125+'Enseignement - AMS'!J125+'Santé social - AMS'!J125+'Sport Loisir Culture - AMS'!J125+'Transport - AMS'!J125 -> 47.619276 | AB96: ='Bureaux - AMS'!K125+'CaHoREs - AMS'!K125+'Commerce - AMS'!K125+'Enseignement - AMS'!K125+'Santé social - AMS'!K125+'Sport Loisir Culture - AMS'!K125+'Transport - AMS'!K125 -> 0
A97: ENR | B97: ='Bureaux - AME'!H126+'CaHoREs - AME'!H126+'Commerce - AME'!H126+'Enseignement - AME'!H126+'Santé social - AME'!H126+'Sport Loisir Culture - AME'!H126+'Transport - AME'!H126 -> 804.31191 | C97: ='Bureaux - AME'!I126+'CaHoREs - AME'!I126+'Commerce - AME'!I126+'Enseignement - AME'!I126+'Santé social - AME'!I126+'Sport Loisir Culture - AME'!I126+'Transport - AME'!I126 -> 869.15983 | D97: ='Bureaux - AME'!J126+'CaHoREs - AME'!J126+'Commerce - AME'!J126+'Enseignement - AME'!J126+'Santé social - AME'!J126+'Sport Loisir Culture - AME'!J126+'Transport - AME'!J126 -> 986.02449 | E97: ='Bureaux - AME'!K126+'CaHoREs - AME'!K126+'Commerce - AME'!K126+'Enseignement - AME'!K126+'Santé social - AME'!K126+'Sport Loisir Culture - AME'!K126+'Transport - AME'!K126 -> 1065.4071 | X97: ENR | Y97: ='Bureaux - AMS'!H126+'CaHoREs - AMS'!H126+'Commerce - AMS'!H126+'Enseignement - AMS'!H126+'Santé social - AMS'!H126+'Sport Loisir Culture - AMS'!H126+'Transport - AMS'!H126 -> 171.80825 | Z97: ='Bureaux - AMS'!I126+'CaHoREs - AMS'!I126+'Commerce - AMS'!I126+'Enseignement - AMS'!I126+'Santé social - AMS'!I126+'Sport Loisir Culture - AMS'!I126+'Transport - AMS'!I126 -> 222.78345 | AA97: ='Bureaux - AMS'!J126+'CaHoREs - AMS'!J126+'Commerce - AMS'!J126+'Enseignement - AMS'!J126+'Santé social - AMS'!J126+'Sport Loisir Culture - AMS'!J126+'Transport - AMS'!J126 -> 291.11526 | AB97: ='Bureaux - AMS'!K126+'CaHoREs - AMS'!K126+'Commerce - AMS'!K126+'Enseignement - AMS'!K126+'Santé social - AMS'!K126+'Sport Loisir Culture - AMS'!K126+'Transport - AMS'!K126 -> 430.90689
A98: Electricité Joule | B98: ='Bureaux - AME'!H127+'CaHoREs - AME'!H127+'Commerce - AME'!H127+'Enseignement - AME'!H127+'Santé social - AME'!H127+'Sport Loisir Culture - AME'!H127+'Transport - AME'!H127 -> 9195.0988 | C98: ='Bureaux - AME'!I127+'CaHoREs - AME'!I127+'Commerce - AME'!I127+'Enseignement - AME'!I127+'Santé social - AME'!I127+'Sport Loisir Culture - AME'!I127+'Transport - AME'!I127 -> 6909.9241 | D98: ='Bureaux - AME'!J127+'CaHoREs - AME'!J127+'Commerce - AME'!J127+'Enseignement - AME'!J127+'Santé social - AME'!J127+'Sport Loisir Culture - AME'!J127+'Transport - AME'!J127 -> 5455.2333 | E98: ='Bureaux - AME'!K127+'CaHoREs - AME'!K127+'Commerce - AME'!K127+'Enseignement - AME'!K127+'Santé social - AME'!K127+'Sport Loisir Culture - AME'!K127+'Transport - AME'!K127 -> 4046.2273 | X98: Electricité Joule | Y98: ='Bureaux - AMS'!H127+'CaHoREs - AMS'!H127+'Commerce - AMS'!H127+'Enseignement - AMS'!H127+'Santé social - AMS'!H127+'Sport Loisir Culture - AMS'!H127+'Transport - AMS'!H127 -> 1982.5971 | Z98: ='Bureaux - AMS'!I127+'CaHoREs - AMS'!I127+'Commerce - AMS'!I127+'Enseignement - AMS'!I127+'Santé social - AMS'!I127+'Sport Loisir Culture - AMS'!I127+'Transport - AMS'!I127 -> 1060.0354 | AA98: ='Bureaux - AMS'!J127+'CaHoREs - AMS'!J127+'Commerce - AMS'!J127+'Enseignement - AMS'!J127+'Santé social - AMS'!J127+'Sport Loisir Culture - AMS'!J127+'Transport - AMS'!J127 -> 693.61102 | AB98: ='Bureaux - AMS'!K127+'CaHoREs - AMS'!K127+'Commerce - AMS'!K127+'Enseignement - AMS'!K127+'Santé social - AMS'!K127+'Sport Loisir Culture - AMS'!K127+'Transport - AMS'!K127 -> 586.61882
A99: Electricité PAC | B99: ='Bureaux - AME'!H128+'CaHoREs - AME'!H128+'Commerce - AME'!H128+'Enseignement - AME'!H128+'Santé social - AME'!H128+'Sport Loisir Culture - AME'!H128+'Transport - AME'!H128 -> 1906.7891 | C99: ='Bureaux - AME'!I128+'CaHoREs - AME'!I128+'Commerce - AME'!I128+'Enseignement - AME'!I128+'Santé social - AME'!I128+'Sport Loisir Culture - AME'!I128+'Transport - AME'!I128 -> 2967.0522 | D99: ='Bureaux - AME'!J128+'CaHoREs - AME'!J128+'Commerce - AME'!J128+'Enseignement - AME'!J128+'Santé social - AME'!J128+'Sport Loisir Culture - AME'!J128+'Transport - AME'!J128 -> 4262.1098 | E99: ='Bureaux - AME'!K128+'CaHoREs - AME'!K128+'Commerce - AME'!K128+'Enseignement - AME'!K128+'Santé social - AME'!K128+'Sport Loisir Culture - AME'!K128+'Transport - AME'!K128 -> 4989.1781 | X99: Electricité PAC | Y99: ='Bureaux - AMS'!H128+'CaHoREs - AMS'!H128+'Commerce - AMS'!H128+'Enseignement - AMS'!H128+'Santé social - AMS'!H128+'Sport Loisir Culture - AMS'!H128+'Transport - AMS'!H128 -> 448.24616 | Z99: ='Bureaux - AMS'!I128+'CaHoREs - AMS'!I128+'Commerce - AMS'!I128+'Enseignement - AMS'!I128+'Santé social - AMS'!I128+'Sport Loisir Culture - AMS'!I128+'Transport - AMS'!I128 -> 1291.3951 | AA99: ='Bureaux - AMS'!J128+'CaHoREs - AMS'!J128+'Commerce - AMS'!J128+'Enseignement - AMS'!J128+'Santé social - AMS'!J128+'Sport Loisir Culture - AMS'!J128+'Transport - AMS'!J128 -> 2113.6986 | AB99: ='Bureaux - AMS'!K128+'CaHoREs - AMS'!K128+'Commerce - AMS'!K128+'Enseignement - AMS'!K128+'Santé social - AMS'!K128+'Sport Loisir Culture - AMS'!K128+'Transport - AMS'!K128 -> 2304.071
A100: Total | B100: =SUM(B93:B99) -> 61932.949 | C100: =SUM(C93:C99) -> 54449.46 | D100: =SUM(D93:D99) -> 51390.544 | E100: =SUM(E93:E99) -> 46791.768 | X100: Total | Y100: =SUM(Y93:Y99) -> 12040.924 | Z100: =SUM(Z93:Z99) -> 9526.4219 | AA100: =SUM(AA93:AA99) -> 7497.804 | AB100: =SUM(AB93:AB99) -> 5836.4187
A101: Gain énergétique | B101: =B100/$B100-1 -> 0 | C101: =C100/$B100-1 -> -0.12083211 | D101: =D100/$B100-1 -> -0.17022289 | E101: =E100/$B100-1 -> -0.24447699 | X101: Gain énergétique vs 2020 | Y101: =Y100/$Y100-1 -> 0 | Z101: =Z100/$Y100-1 -> -0.20882969 | AA101: =AA100/$Y100-1 -> -0.37730662 | AB101: =AB100/$Y100-1 -> -0.51528484
A106: Hors Chauffage | P106: Hors Chauffage
A112: Consommation par source énergie - Scénario AME [GWh LHV] | X112: Consommation par source énergie - Scénario AMS [GWh LHV]
A113: Energie | B113: 2020 | C113: 2030 | D113: 2040 | E113: 2050 | X113: Energie | Y113: 2020 | Z113: 2021 | AA113: 2022 | AB113: 2023
A114: Electricité | B114: ='Hors chauffage - AME'!E6*1000 -> 135185.9 | C114: ='Hors chauffage - AME'!F6*1000 -> 143571.48 | D114: ='Hors chauffage - AME'!G6*1000 -> 166296.48 | E114: ='Hors chauffage - AME'!H6*1000 -> 196606.62 | X114: Electricité | Y114: ='Hors chauffage - AMS'!E6*1000 -> 128079.98 | Z114: ='Hors chauffage - AMS'!F6*1000 -> 116041.45 | AA114: ='Hors chauffage - AMS'!G6*1000 -> 115426.51 | AB114: ='Hors chauffage - AMS'!H6*1000 -> 116065.41
A115: Gaz | B115: ='Hors chauffage - AME'!E7*1000 -> 16918.432 | C115: ='Hors chauffage - AME'!F7*1000 -> 14402.066 | D115: ='Hors chauffage - AME'!G7*1000 -> 13527.232 | E115: ='Hors chauffage - AME'!H7*1000 -> 12627.612 | X115: Gaz | Y115: ='Hors chauffage - AMS'!E7*1000 -> 17051.351 | Z115: ='Hors chauffage - AMS'!F7*1000 -> 9743.2811 | AA115: ='Hors chauffage - AMS'!G7*1000 -> 4108.0765 | AB115: ='Hors chauffage - AMS'!H7*1000 -> 835.8752
A116: Pétrole | B116: ='Hors chauffage - AME'!E8*1000 -> 4958.796 | C116: ='Hors chauffage - AME'!F8*1000 -> 3883.0439 | D116: ='Hors chauffage - AME'!G8*1000 -> 3298.4831 | E116: ='Hors chauffage - AME'!H8*1000 -> 2934.6221 | X116: Pétrole | Y116: ='Hors chauffage - AMS'!E8*1000 -> 4958.796 | Z116: ='Hors chauffage - AMS'!F8*1000 -> 244.52002 | AA116: ='Hors chauffage - AMS'!G8*1000 -> 0 | AB116: ='Hors chauffage - AMS'!H8*1000 -> 0
A117: Bois | B117: ='Hors chauffage - AME'!E9*1000 -> 214.61535 | C117: ='Hors chauffage - AME'!F9*1000 -> 237.24517 | D117: ='Hors chauffage - AME'!G9*1000 -> 247.32152 | E117: ='Hors chauffage - AME'!H9*1000 -> 253.94561 | X117: Bois | Y117: ='Hors chauffage - AMS'!E9*1000 -> 214.61535 | Z117: ='Hors chauffage - AMS'!F9*1000 -> 663.01905 | AA117: ='Hors chauffage - AMS'!G9*1000 -> 533.48745 | AB117: ='Hors chauffage - AMS'!H9*1000 -> 436.08335
A118: Chaleur | B118: ='Hors chauffage - AME'!E10*1000 -> 1550.4931 | C118: ='Hors chauffage - AME'!F10*1000 -> 1705.0133 | D118: ='Hors chauffage - AME'!G10*1000 -> 1647.0843 | E118: ='Hors chauffage - AME'!H10*1000 -> 1557.3658 | X118: Chaleur | Y118: ='Hors chauffage - AMS'!E10*1000 -> 1550.4931 | Z118: ='Hors chauffage - AMS'!F10*1000 -> 3511.227 | AA118: ='Hors chauffage - AMS'!G10*1000 -> 3436.1167 | AB118: ='Hors chauffage - AMS'!H10*1000 -> 3059.0485
A119: EnR thermique | B119: 0 | C119: 0 | D119: 0 | E119: 0 | X119: EnR thermique | Y119: ='Hors chauffage - AMS'!E11 -> 0 | Z119: ='Hors chauffage - AMS'!F11 -> 0.10237102 | AA119: ='Hors chauffage - AMS'!G11 -> 0.17748115 | AB119: ='Hors chauffage - AMS'!H11 -> 0.22978422
A120: Total | B120: ='Hors chauffage - AME'!E5*1000 -> 158828.24 | C120: ='Hors chauffage - AME'!F5*1000 -> 163798.85 | D120: ='Hors chauffage - AME'!G5*1000 -> 185016.6 | E120: ='Hors chauffage - AME'!H5*1000 -> 213980.17 | X120: Total | Y120: ='Hors chauffage - AMS'!E5*1000 -> 151855.24 | Z120: ='Hors chauffage - AMS'!F5*1000 -> 130305.87 | AA120: ='Hors chauffage - AMS'!G5*1000 -> 123681.67 | AB120: ='Hors chauffage - AMS'!H5*1000 -> 120626.2
A122: Réalisation des objectifs | X122: Réalisation des objectifs
A123: Baisse de consommation | B123: =B120/$B120-1 -> 0 | C123: =C120/$B120-1 -> 0.031295519 | D123: =D120/$B120-1 -> 0.16488478 | E123: =E120/$B120-1 -> 0.34724257 | F123: Augmentation presque 100% lié au data center | X123: Baisse de consommation | Y123: =Y120/$B120-1 -> -0.043902785 | Z123: =Z120/$B120-1 -> -0.17958 | AA123: =AA120/$B120-1 -> -0.22128666 | AB123: =AB120/$Y120-1 -> -0.20565006
AI126: SDES | AJ126: 2019 | AK126: Mtep | AL126: TWh
A127: Estimation GES (FE constant) | P127: Estimation GES | AK127: 22.4 | AL127: =AK127/86000*1000000 -> 260.46512
AI128: chauffage | AJ128: 0.43 | AK128: =AK$127*AJ128 -> 9.632 | AL128: =AK128/86000*1000000 -> 112
A130: Emissions totales (Mt) AME | X130: Emissions totales (Mt) AMS | AI130: elec spé | AJ130: 0.3 | AK130: =AK$127*AJ130 -> 6.72 | AL130: =AK130/86000*1000000 -> 78.139535
A131: Energie | B131: 2020 | C131: 2030 | D131: 2040 | E131: 2050 | X131: Energie | Y131: 2020 | Z131: 2030 | AA131: 2040 | AB131: 2050 | AI131: ecs | AJ131: 0.1 | AK131: =AK$127*AJ131 -> 2.24 | AL131: =AK131/86000*1000000 -> 26.046512
A132: Fuel domestique | B132: =B35*'Init. énergie'!$M4*10^-6 -> 6.1222742 | C132: =C35*'Init. énergie'!$M4*10^-6 -> 4.4618692 | D132: =D35*'Init. énergie'!$M4*10^-6 -> 3.6654336 | E132: =E35*'Init. énergie'!$M4*10^-6 -> 2.9145465 | X132: Fuel domestique | Y132: =Y35*'Init. énergie'!M4*10^-6 -> 6.1222742 | Z132: =Z35*'Init. énergie'!N4*10^-6 -> 0.44904078 | AA132: =AA35*'Init. énergie'!O4*10^-6 -> 0 | AB132: =AB35*'Init. énergie'!P4*10^-6 -> 0 | AI132: clim | AJ132: 0.09 | AK132: =AK$127*AJ132 -> 2.016 | AL132: =AK132/86000*1000000 -> 23.44186
A133: Gaz naturel | B133: =B36*'Init. énergie'!$M5*10^-6 -> 14.924105 | C133: =C36*'Init. énergie'!$M5*10^-6 -> 12.129712 | D133: =D36*'Init. énergie'!$M5*10^-6 -> 11.159937 | E133: =E36*'Init. énergie'!$M5*10^-6 -> 10.048325 | X133: Gaz naturel | Y133: =Y36*'Init. énergie'!M5*10^-6 -> 14.951382 | Z133: =Z36*'Init. énergie'!N5*10^-6 -> 10.474318 | AA133: =AA36*'Init. énergie'!O5*10^-6 -> 4.6250115 | AB133: =AB36*'Init. énergie'!P5*10^-6 -> 0.914373 | AI133: cuisson | AJ133: 0.05 | AK133: =AK$127*AJ133 -> 1.12 | AL133: =AK133/86000*1000000 -> 13.023256
A134: Réseau de chaleur | B134: =B37*'Init. énergie'!$M6*10^-6 -> 1.3434113 | C134: =C37*'Init. énergie'!$M6*10^-6 -> 1.3130949 | D134: =D37*'Init. énergie'!$M6*10^-6 -> 1.2458308 | E134: =E37*'Init. énergie'!$M6*10^-6 -> 1.1210131 | X134: Réseau de chaleur | Y134: =Y37*'Init. énergie'!M6*10^-6 -> 1.3434113 | Z134: =Z37*'Init. énergie'!N6*10^-6 -> 2.1632148 | AA134: =AA37*'Init. énergie'!O6*10^-6 -> 1.5841163 | AB134: =AB37*'Init. énergie'!P6*10^-6 -> 0.96836155 | AI134: autre | AJ134: 0.04 | AK134: =AK$127*AJ134 -> 0.896 | AL134: =AK134/86000*1000000 -> 10.418605
A135: GPL | B135: =B38*'Init. énergie'!$M7*10^-6 -> 0.34481092 | C135: =C38*'Init. énergie'!$M7*10^-6 -> 0.297017 | D135: =D38*'Init. énergie'!$M7*10^-6 -> 0.28295246 | E135: =E38*'Init. énergie'!$M7*10^-6 -> 0.26257537 | X135: GPL | Y135: =Y38*'Init. énergie'!M7*10^-6 -> 0.34481092 | Z135: =Z38*'Init. énergie'!N7*10^-6 -> 0.20792857 | AA135: =AA38*'Init. énergie'!O7*10^-6 -> 0.11746161 | AB135: =AB38*'Init. énergie'!P7*10^-6 -> 0.012111459
A136: ENR | B136: =B39*'Init. énergie'!$M8*10^-6 -> 0 | C136: =C39*'Init. énergie'!$M8*10^-6 -> 0 | D136: =D39*'Init. énergie'!$M8*10^-6 -> 0 | E136: =E39*'Init. énergie'!$M8*10^-6 -> 0 | X136: ENR | Y136: =Y39*'Init. énergie'!M8*10^-6 -> 0 | Z136: =Z39*'Init. énergie'!N8*10^-6 -> 0 | AA136: =AA39*'Init. énergie'!O8*10^-6 -> 0 | AB136: =AB39*'Init. énergie'!P8*10^-6 -> 0 | AI136: total HC | AJ136: =SUM(AJ130:AJ134) -> 0.58 | AK136: =SUM(AK130:AK134) -> 12.992 | AL136: =SUM(AL130:AL134) -> 151.06977
A137: Electricité (PAC incluses) | B137: =B40*'Init. énergie'!$M9*10^-6 -> 12.068731 | C137: =C40*'Init. énergie'!$M9*10^-6 -> 12.609532 | D137: =D40*'Init. énergie'!$M9*10^-6 -> 14.361288 | E137: =E40*'Init. énergie'!$M9*10^-6 -> 16.671341 | X137: Electricité (PAC incluses) | Y137: =Y40*'Init. énergie'!M9*10^-6 -> 11.507364 | Z137: =Z40*'Init. énergie'!N9*10^-6 -> 9.4898372 | AA137: =AA40*'Init. énergie'!O9*10^-6 -> 6.4622619 | AB137: =AB40*'Init. énergie'!P9*10^-6 -> 7.0947378
...

Sheet Init. parc
B2: Projection surface tertiaire AME 24 | H2: Renouvellement du parc (destruction reconstruction) | M2: Parc post-2020 (besoins suppl. + destruction/reconstruction)
C3: Etat initial (2020) | D3: 2030 | E3: 2040 | F3: 2050 | I3: 2020-2030 | J3: 2030-2040 | K3: 2040-2050 | M3: Etat initial (2020) | N3: 2030 | O3: 2040 | P3: 2050
B4: Bureaux Administration | C4: 287333.79 | D4: 275542.17 | E4: 276002.3 | F4: 269746.67 | H4: Bureaux Administration | I4: 0.00216 | J4: 0.00216 | K4: 0.00216 | M4: Bureaux Administration | N4: =IF(D4>C4,D4-C4,0)+C4*I4*10 -> 6206.4099 | O4: =IF(E4>D4,E4-D4,0)+D4*J4*10 -> 6411.8445 | P4: =IF(F4>E4,F4-E4,0)+E4*K4*10 -> 5961.6497
B5: Café Hôtel Restaurant | C5: 67243.869 | D5: 69861.541 | E5: 70897.601 | F5: 70213.182 | H5: Café Hôtel Restaurant | I5: 0.00288 | J5: 0.00288 | K5: 0.00288 | M5: Café Hôtel Restaurant | N5: =IF(D5>C5,D5-C5,0)+C5*I5*10 -> 4554.2951 | O5: =IF(E5>D5,E5-D5,0)+D5*J5*10 -> 3048.0727 | P5: =IF(F5>E5,F5-E5,0)+E5*K5*10 -> 2041.8509
B6: Commerce | C6: 184229.65 | D6: 188845.72 | E6: 189052.82 | F6: 184659.28 | H6: Commerce | I6: 0.00464 | J6: 0.00464 | K6: 0.00464 | M6: Commerce | N6: =IF(D6>C6,D6-C6,0)+C6*I6*10 -> 13164.331 | O6: =IF(E6>D6,E6-D6,0)+D6*J6*10 -> 8969.5375 | P6: =IF(F6>E6,F6-E6,0)+E6*K6*10 -> 8772.0507
B7: Enseignement Recherche | C7: 167106.71 | D7: 169584.88 | E7: 168013.18 | F7: 162344.01 | H7: Enseignement Recherche | I7: 0.0020122075 | J7: 0.0020122075 | K7: 0.0020122075 | M7: Enseignement Recherche | N7: =IF(D7>C7,D7-C7,0)+C7*I7*10 -> 5840.7077 | O7: =IF(E7>D7,E7-D7,0)+D7*J7*10 -> 3412.3997 | P7: =IF(F7>E7,F7-E7,0)+E7*K7*10 -> 3380.7737
C8: 0 | D8: 0 | E8: 0 | F8: 0 | I8: 0.002 | J8: 0.002 | K8: 0.002 | M8: Habitat communautaire | N8: =IF(D8>C8,D8-C8,0)+C8*I8*10 -> 0 | O8: =IF(E8>D8,E8-D8,0)+D8*J8*10 -> 0 | P8: =IF(F8>E8,F8-E8,0)+E8*K8*10 -> 0
B9: Santé Action Sociale | C9: 179200 | D9: 197026.6 | E9: 210960.16 | F9: 219828.94 | H9: Santé Action Sociale | I9: 0.0025858545 | J9: 0.0025858545 | K9: 0.0025858545 | M9: Santé Action Sociale | N9: =IF(D9>C9,D9-C9,0)+C9*I9*10 -> 22460.451 | O9: =IF(E9>D9,E9-D9,0)+D9*J9*10 -> 19028.378 | P9: =IF(F9>E9,F9-E9,0)+E9*K9*10 -> 14323.903
B10: Sport Loisir Culture | C10: 56508.434 | D10: 58708.196 | E10: 59578.85 | F10: 59003.698 | H10: Sport Loisir Culture | I10: 0.0020122075 | J10: 0.0020122075 | K10: 0.0020122075 | M10: Sport Loisir Culture | N10: =IF(D10>C10,D10-C10,0)+C10*I10*10 -> 3336.8292 | O10: =IF(E10>D10,E10-D10,0)+D10*J10*10 -> 2051.9847 | P10: =IF(F10>E10,F10-E10,0)+E10*K10*10 -> 1198.8501
B11: Transport | C11: 41814.604 | D11: 43442.365 | E11: 44086.623 | F11: 43661.027 | H11: Transport | I11: 0.0026 | J11: 0.0026 | K11: 0.0026 | M11: Transport | N11: =IF(D11>C11,D11-C11,0)+C11*I11*10 -> 2714.9401 | O11: =IF(E11>D11,E11-D11,0)+D11*J11*10 -> 1773.7602 | P11: =IF(F11>E11,F11-E11,0)+E11*K11*10 -> 1146.2522
B12: total | C12: =SUM(C4:C11) -> 983437.06 | D12: =SUM(D4:D11) -> 1003011.5 | E12: =SUM(E4:E11) -> 1018591.5 | F12: =SUM(F4:F11) -> 1009456.8 | H12: Flux de renouvellement annuel | I12: =SUMPRODUCT(C4:C11,I4:I11) -> 2691.192 | J12: =SUMPRODUCT(D4:D11,J4:J11) -> 2754.4218 | K12: =SUMPRODUCT(E4:E11,K4:K11) -> 2795.655 | M12: total | N12: =SUM(N4:N11) -> 58277.964 | O12: =SUM(O4:O11) -> 44695.977 | P12: =SUM(P4:P11) -> 36825.33
D13: =(D12-C12)/10 -> 1957.4421 | E13: =(E12-D12)/10 -> 1558.0054 | F13: =(F12-E12)/10 -> -913.47178 | M13: par an | N13: =N12/10 -> 5827.7964 | O13: =O12/10 -> 4469.5977 | P13: =P12/10 -> 3682.533
N14: =N13/D12 -> 0.0058102988 | O14: =O13/E12 -> 0.0043880178 | P14: =P13/F12 -> 0.0036480342
B17: milliers de m²
B18: Projection surface tertiaire nette AMS run 3 | H18: Renouvellement du parc (destruction reconstruction) | M18: Parc post-2020
C19: Etat initial (2020) | D19: 2030 | E19: 2040 | F19: 2050 | I19: 2020-2030 | J19: 2030-2040 | K19: 2040-2050 | M19: Etat initial (2020) | N19: 2030 | O19: 2040 | P19: 2050
B20: Bureaux Administration | C20: 287333.79 | D20: 274114.53 | E20: 260363.23 | F20: 238873.31 | H20: Bureaux Administration | I20: 0.00216 | J20: 0.00216 | K20: 0.00216 | M20: Bureaux Administration | N20: =IF(D20>C20,D20-C20,0)+C20*I20*10 -> 6206.4099 | O20: =IF(E20>D20,E20-D20,0)+D20*J20*10 -> 5920.8739 | P20: =IF(F20>E20,F20-E20,0)+E20*K20*10 -> 5623.8459
B21: Café Hôtel Restaurant | C21: 67243.869 | D21: 69499.575 | E21: 70400.361 | F21: 68894.25 | H21: Café Hôtel Restaurant | I21: 0.00288 | J21: 0.00288 | K21: 0.00288 | M21: Café Hôtel Restaurant | N21: =IF(D21>C21,D21-C21,0)+C21*I21*10 -> 4192.3289 | O21: =IF(E21>D21,E21-D21,0)+D21*J21*10 -> 2902.3742 | P21: =IF(F21>E21,F21-E21,0)+E21*K21*10 -> 2027.5304
B22: Commerce | C22: 184229.65 | D22: 187867.27 | E22: 187726.9 | F22: 181190.52 | H22: Commerce | I22: 0.00464 | J22: 0.00464 | K22: 0.00464 | M22: Commerce | N22: =IF(D22>C22,D22-C22,0)+C22*I22*10 -> 12185.885 | O22: =IF(E22>D22,E22-D22,0)+D22*J22*10 -> 8717.0415 | P22: =IF(F22>E22,F22-E22,0)+E22*K22*10 -> 8710.528
B23: Enseignement Recherche | C23: 167106.71 | D23: 168706.23 | E23: 166834.82 | F23: 159294.43 | H23: Enseignement Recherche | I23: 0.0020122075 | J23: 0.0020122075 | K23: 0.0020122075 | M23: Enseignement Recherche | N23: =IF(D23>C23,D23-C23,0)+C23*I23*10 -> 4962.0556 | O23: =IF(E23>D23,E23-D23,0)+D23*J23*10 -> 3394.7194 | P23: =IF(F23>E23,F23-E23,0)+E23*K23*10 -> 3357.0627
C24: 0 | D24: 0 | E24: 0 | F24: 0 | I24: 0.002 | J24: 0.002 | K24: 0.002 | M24: Habitat communautaire | N24: =IF(D24>C24,D24-C24,0)+C24*I24*10 -> 0 | O24: =IF(E24>D24,E24-D24,0)+D24*J24*10 -> 0 | P24: =IF(F24>E24,F24-E24,0)+E24*K24*10 -> 0
B25: Santé Action Sociale | C25: 179200 | D25: 196005.77 | E25: 209480.59 | F25: 215699.52 | H25: Santé Action Sociale | I25: 0.0025858545 | J25: 0.0025858545 | K25: 0.0025858545 | M25: Santé Action Sociale | N25: =IF(D25>C25,D25-C25,0)+C25*I25*10 -> 21439.618 | O25: =IF(E25>D25,E25-D25,0)+D25*J25*10 -> 18543.246 | P25: =IF(F25>E25,F25-E25,0)+E25*K25*10 -> 11635.794
B26: Sport Loisir Culture | C26: 56508.434 | D26: 58404.018 | E26: 59160.994 | F26: 57895.332 | H26: Sport Loisir Culture | I26: 0.0020122075 | J26: 0.0020122075 | K26: 0.0020122075 | M26: Sport Loisir Culture | N26: =IF(D26>C26,D26-C26,0)+C26*I26*10 -> 3032.6507 | O26: =IF(E26>D26,E26-D26,0)+D26*J26*10 -> 1932.1865 | P26: =IF(F26>E26,F26-E26,0)+E26*K26*10 -> 1190.4419
B27: Transport | C27: 41814.604 | D27: 43217.281 | E27: 43777.422 | F27: 42840.869 | H27: Transport | I27: 0.0026 | J27: 0.0026 | K27: 0.0026 | M27: Transport | N27: =IF(D27>C27,D27-C27,0)+C27*I27*10 -> 2489.8568 | O27: =IF(E27>D27,E27-D27,0)+D27*J27*10 -> 1683.79 | P27: =IF(F27>E27,F27-E27,0)+E27*K27*10 -> 1138.213
B28: total | C28: 983437.06 | D28: 997814.68 | E28: 997744.31 | F28: 964688.23 | H28: Flux de renouvellement annuel | I28: 2691.192 | J28: 2754.4218 | K28: 2795.655 | M28: total | N28: =SUM(N20:N27) -> 54508.805 | O28: =SUM(O20:O27) -> 43094.231 | P28: =SUM(P20:P27) -> 33683.416
M29: par an | N29: =N28/10 -> 5450.8805 | O29: =O28/10 -> 4309.4231 | P29: =P28/10 -> 3368.3416
N30: =N29/D28 -> 0.0054628185 | O30: =O29/E28 -> 0.0043191658 | P30: =P29/F28 -> 0.0034916375
B34: https://www.ecologie.gouv.fr/sites/default/files/CGDD_scenarios_renovation_batiments_tertiaires_publication_20201203.pdf
B35: p. 54
B41: Parc Ademe | C41: 2020
B42: Bureaux Administration | C42: 239113.67
B43: Café Hôtel Restaurant | C43: 67389.902
B44: Commerce | C44: 215959
B45: Enseignement Recherche | C45: 190850
B46: Hab com | C46: 72592
B47: Santé Action Sociale | C47: 118445.14
B48: Sport Loisir Culture | C48: 74481
B49: Transport | C49: 25839.303
C50: =SUM(C42:C49) -> 1004670

Sheet Bureaux - AME
C1: Bureaux - Scénario AME
C3: Résultats - Scénario AME
F5: Surface chauffée - Scénario AME [thousand sq m]
E6: Catégorie | G6: 2010 | H6: 2020 | I6: 2030 | J6: 2040 | K6: 2050
E7: Tous bureaux | H7: =H34 -> 287333.79 | I7: =I34 -> 275542.17 | J7: =J34 -> 276002.3 | K7: =K34 -> 269746.67
E8: Dont surfaces construites après 2015 | H8: =H35 -> 0 | I8: =I35 -> 6206.4099 | J8: =J35 -> 6411.8445 | K8: =K35 -> 5961.6497
E9: Dont surfaces existantes en 2015 | H9: =H36 -> 287333.79 | I9: =I36 -> 269335.76 | J9: =J36 -> 269590.46 | K9: =K36 -> 263785.02
F11: Consommation par source énergie - Scénario AME [GWh LHV]
E12: Energie | G12: 2010 | H12: 2020 | I12: 2030 | J12: 2040 | K12: 2050
E13: Fuel domestique | H13: =H133+H167 -> 3705.1685 | I13: =I133+I167 -> 2535.2489 | J13: =J133+J167 -> 1849.638 | K13: =K133+K167 -> 1270.1721
E14: Gaz naturel | H14: =H134+H168 -> 17519.297 | I14: =I134+I168 -> 14064.469 | J14: =J134+J168 -> 12178.541 | K14: =K134+K168 -> 10558.977
E15: Réseau de chaleur | H15: =H135+H169 -> 2766.1151 | I15: =I135+I169 -> 2535.3244 | J15: =J135+J169 -> 2323.5714 | K15: =K135+K169 -> 2055.4152
E16: GPL | H16: =H136+H170 -> 394.01187 | I16: =I136+I170 -> 302.77798 | J16: =J136+J170 -> 255.44488 | K16: =K136+K170 -> 212.4528
E17: ENR | H17: =H137+H171 -> 411.65001 | I17: =I137+I171 -> 427.87867 | J17: =J137+J171 -> 464.91367 | K17: =K137+K171 -> 489.59612
E18: Electricité Joule | H18: =H138+H172 -> 6418.4622 | I18: =I138+I172 -> 4703.0268 | J18: =J138+J172 -> 3735.1157 | K18: =K138+K172 -> 2905.3549
E19: Electricité PAC | H19: =H139+H173 -> 1152.0826 | I19: =I139+I173 -> 1595.5655 | J19: =J139+J173 -> 2205.5392 | K19: =K139+K173 -> 2444.3127
E20: Total | H20: =SUM(H13:H19) -> 32366.788 | I20: =SUM(I13:I19) -> 26164.291 | J20: =SUM(J13:J19) -> 23012.764 | K20: =SUM(K13:K19) -> 19936.28
F22: Réalisation des objectifs
E23: Baisse de la consommation du parc suivant le décret | I23: =I118/$G118-1 -> -0.3204126 | J23: =J118/$G118-1 -> -0.46050719 | K23: =K118/$G118-1 -> -0.56392917
E24: Baisse de la consommation du parc hors décret | I24: =I129/$G129-1 -> -0.15599987 | J24: =J129/$G129-1 -> -0.22698864 | K24: =K129/$G129-1 -> -0.31365817
C27: Calculs - Scénario AME
D29: SURFACES CHAUFFEES
F32: Surfaces chauffées - Scénario AME [thousand sq m]
E33: Surface | G33: 2010 | H33: 2020 | I33: 2030 | J33: 2040 | K33: 2050
E34: Surface [thousand sq m] | G34: =H34 -> 287333.79 | H34: ='Init. parc'!C4 -> 287333.79 | I34: ='Init. parc'!D4 -> 275542.17 | J34: ='Init. parc'!E4 -> 276002.3 | K34: ='Init. parc'!F4 -> 269746.67
E35: Dont surfaces construites après 2020 | H35: 0 | I35: ='Init. parc'!N4 -> 6206.4099 | J35: ='Init. parc'!O4 -> 6411.8445 | K35: ='Init. parc'!P4 -> 5961.6497
E36: Dont surfaces existantes en 2020 | G36: =G34-G35 -> 287333.79 | H36: =H34-H35 -> 287333.79 | I36: =I34-I35 -> 269335.76 | J36: =J34-J35 -> 269590.46 | K36: =K34-K35 -> 263785.02
D39: CHAUFFAGE
E41: Parc existant en 2020
F43: Parc existant en 2015 - Répartition des surfaces chauffées par type d'énergie de chauffage - Scénario Tendanciel - surfaces suivant la traj décret
E44: Energie | G44: 2010 | H44: 2020 | I44: 2030 | J44: 2040 | K44: 2050 | M44: Justification hypothèses
E45: Fuel domestique | G45: =H45 -> 0.09 | H45: ='Init. énergie'!B3 -> 0.09 | I45: =H45+((K45-H45)/3) -> 0.073333333 | J45: =H45+((K45-H45)/3*2) -> 0.056666667 | K45: 0.04 | M45: Bâtiments qui suivent le décret : baisse du gaz et du joule au profit de RCU et surtout PAC qui sont favorisés dans le DEET. Pour le gaz : baisse supplémentaire liée au cadrage macro-éco. Pic RCU en 2030/2040 car plus de fonds chaleur et juste coup de pouce CEE + classement des fonds chaleur mais après ça s'arrête
E46: Gaz naturel | G46: =H46 -> 0.425 | H46: ='Init. énergie'!B4 -> 0.425 | I46: =H46+((K46-H46)/3) -> 0.39666667 | J46: =H46+((K46-H46)/3*2) -> 0.36833333 | K46: 0.34
E47: Réseaux de chaleur | G47: =H47 -> 0.08 | H47: ='Init. énergie'!B5 -> 0.08 | I47: 0.1 | J47: 0.1 | K47: 0.09
E48: GPL | G48: =H48 -> 0.013 | H48: ='Init. énergie'!B6 -> 0.013 | I48: =H48+((K48-H48)/3) -> 0.012 | J48: =H48+((K48-H48)/3*2) -> 0.011 | K48: 0.01
E49: ENR | G49: =H49 -> 0.012 | H49: ='Init. énergie'!B7 -> 0.012 | I49: =H49+((K49-H49)/3) -> 0.014666667 | J49: =H49+((K49-H49)/3*2) -> 0.017333333 | K49: 0.02
E50: Joule | G50: =H50 -> 0.306 | H50: ='Init. énergie'!B8 -> 0.306 | I50: =H50+((K50-H50)/3) -> 0.27733333 | J50: =H50+((K50-H50)/3*2) -> 0.24866667 | K50: =1-K45-K46-K47-K48-K49-K51 -> 0.22
E51: PAC | G51: =H51 -> 0.073 | H51: ='Init. énergie'!B9 -> 0.073 | I51: 0.13 | J51: 0.2 | K51: 0.28
E52: Total | G52: =SUM(G45:G51) -> 0.999 | H52: =SUM(H45:H51) -> 0.999 | I52: =SUM(I45:I51) -> 1.004 | J52: =SUM(J45:J51) -> 1.002 | K52: =SUM(K45:K51) -> 1
F54: Baisses de consommation induites par les changements de système de chauffage
H55: =(G$81*(H45-G45)+G$82*(H46-G46)+G$83*(H47-G47)+G$84*(H48-G48)+G$85*(H49-G49)+G$86*(H50-G50)+G$87*(H51-G51))/(G$81*G45+G$82*G46+G$83*G47+G$84*G48+G$85*G49+G$86*G50+G$87*G51) -> 0 | I55: =(H$81*(I45-H45)+H$82*(I46-H46)+H$83*(I47-H47)+H$84*(I48-H48)+H$85*(I49-H49)+H$86*(I50-H50)+H$87*(I51-H51))/(H$81*H45+H$82*H46+H$83*H47+H$84*H48+H$85*H49+H$86*H50+H$87*H51) -> -0.024813089 | J55: =(I$81*(J45-I45)+I$82*(J46-I46)+I$83*(J47-I47)+I$84*(J48-I48)+I$85*(J49-I49)+I$86*(J50-I50)+I$87*(J51-I51))/(I$81*I45+I$82*I46+I$83*I47+I$84*I48+I$85*I49+I$86*I50+I$87*I51) -> -0.040853407 | K55: =(J$81*(K45-J45)+J$82*(K46-J46)+J$83*(K47-J47)+J$84*(K48-J48)+J$85*(K49-J49)+J$86*(K50-J50)+J$87*(K51-J51))/(J$81*J45+J$82*J46+J$83*J47+J$84*J48+J$85*J49+J$86*J50+J$87*J51) -> -0.048801586
F57: Parc existant en 2015 - Répartition des surfaces chauffées par type d'énergie de chauffage - Scénario Tendanciel - surfaces hors décret
E58: Energie | G58: 2010 | H58: 2020 | I58: 2030 | J58: 2040 | K58: 2050 | M58: Justification hypothèses
E59: Fuel domestique | G59: =H59 -> 0.09 | H59: =H45 -> 0.09 | I59: =H59+((K59-H59)/3) -> 0.076666667 | J59: =H59+((K59-H59)/3*2) -> 0.063333333 | K59: 0.05 | M59: Bâtiments qui ne suivent pas le décret : légère baisse du gaz en faveur des PAC lié au cadrage macro-éco (ratio prix de l'élec/gaz de 1,5 en 2040/2050 qui oriente naturellement vers les PAC), pas de raccordement RCU car plus de fonds chaleur.
E60: Gaz naturel | G60: =H60 -> 0.425 | H60: =H46 -> 0.425 | I60: =H60 -> 0.425 | J60: 0.41 | K60: 0.4
E61: Réseaux de chaleur | G61: =H61 -> 0.08 | H61: =H47 -> 0.08 | I61: 0.08 | J61: 0.08 | K61: 0.08
E62: GPL | G62: =H62 -> 0.013 | H62: =H48 -> 0.013 | I62: =H62+((K62-H62)/3) -> 0.012 | J62: =H62+((K62-H62)/3*2) -> 0.011 | K62: 0.01
E63: ENR | G63: =H63 -> 0.012 | H63: =H49 -> 0.012 | I63: =H63+((K63-H63)/3) -> 0.014666667 | J63: =H63+((K63-H63)/3*2) -> 0.017333333 | K63: 0.02
E64: Joule | G64: =H64 -> 0.306 | H64: =H50 -> 0.306 | I64: =H64+((K64-H64)/3) -> 0.27733333 | J64: =H64+((K64-H64)/3*2) -> 0.24866667 | K64: =1-K59-K60-K61-K62-K63-K65 -> 0.22
E65: PAC | G65: =H65 -> 0.073 | H65: =H51 -> 0.073 | I65: 0.11 | J65: 0.18 | K65: 0.22
E66: Total | G66: =SUM(G59:G65) -> 0.999 | H66: 1 | I66: =SUM(I59:I65) -> 0.99566667 | J66: =SUM(J59:J65) -> 1.0103333 | K66: =SUM(K59:K65) -> 1
F68: Baisses de consommation induites par les changements de système de chauffage
H69: =(G101*(H59-G59)+G102*(H60-G60)+G103*(H61-H61)+G104*(H62-G62)+G105*(H63-G63)+G106*(H64-G64)+G107*(H65-G65))/(G101*G59+G102*G60+G103*G61+G104*G62+G105*G63+G106*G64+G107*G65) -> 0 | I69: =(H$101*(I59-H59)+H$102*(I60-H60)+H$103*(I61-H61)+H$104*(I62-H62)+H$105*(I63-H63)+H$106*(I64-H64)+H$107*(I65-H65))/(H$101*H59+H$102*H60+H$103*H61+H$104*H62+H$105*H63+H$106*H64+H$107*H65) -> -0.015605695 | J69: =(I$101*(J59-I59)+I$102*(J60-I60)+I$103*(J61-I61)+I$104*(J62-I62)+I$105*(J63-I63)+I$106*(J64-I64)+I$107*(J65-I65))/(I$101*I59+I$102*I60+I$103*I61+I$104*I62+I$105*I63+I$106*I64+I$107*I65) -> -0.01932827 | K69: =(J$101*(K59-J59)+J$102*(K60-J60)+J$103*(K61-J61)+J$104*(K62-J62)+J$105*(K63-J63)+J$106*(K64-J64)+J$107*(K65-J65))/(J$101*J59+J$102*J60+J$103*J61+J$104*J62+J$105*J63+J$106*J64+J$107*J65) -> -0.027801021
M71: Justification hypothèses
H72: Proportion du parc assujeti (>1000m²) | I72: Proportion du parc assujetti suivant la trajectoire du décret tertiaire | J72: Proportion du parc suivant la trajectoire décret tertiaire | M72: Part du parc assujettie (>1000m²) x part du parc asujetti respectant la trajectoire du décret
G73: Proportion | H73: ='Tableau de bord'!E12 -> 0.76 | I73: ='Tableau de bord'!E24 -> 0.47 | J73: ='Tableau de bord'!E27 -> 0.3572
H75: 2030 | I75: 2040 | J75: 2050 | M75: Justification hypothèses
H76: Gain énergétique en 2030/2010 pour le parc suivant le décret | I76: Gain énergétique en 2040/2010 pour le parc suivant le décret | J76: Gain énergétique en 2050/2010 pour le parc suivant le décret | M76: Trajectoire spécifique pour les bureaux en raison de VA moins ambitieuses que les VR. La même pour les autres branches
H77: ='Tableau de bord'!F52 -> 0.275 | I77: ='Tableau de bord'!U52 -> 0.425 | J77: ='Tableau de bord'!AJ52 -> 0.525
F79: Trajectoire décret tertiaire [kWh/sq m]
E80: Energie | G80: 2010 | H80: 2020 | I80: 2030 | J80: 2040 | K80: 2050 | M80: Justification hypothèses
E81: Fuel domestique | G81: =H81/0.998^10 -> 146.17508 | H81: ='Init. énergie'!D3 -> 143.27775 | I81: =G81*(1-H$77)/(1+I$55) -> 108.67346 | J81: =G81*(1-I$77)/(1+I$55)/(1+J$55) -> 89.860395 | K81: =G81*(1-J$77)/(1+I$55)/(1+J$55)/(1+K$55) -> 78.041026 | M81: Réduction de consommation liée aux hypothèses du tableau de bord sur le respect du DEET
E82: Gaz naturel | G82: =H82/0.998^10 -> 146.36446 | H82: ='Init. énergie'!D4 -> 143.46338 | I82: =G82*(1-H$77)/(1+I$55) -> 108.81425 | J82: =G82*(1-I$77)/(1+I$55)/(1+J$55) -> 89.976817 | K82: =G82*(1-J$77)/(1+I$55)/(1+J$55)/(1+K$55) -> 78.142135
E83: Réseaux de chaleur | G83: =H83/0.998^10 -> 122.76884 | H83: ='Init. énergie'!D5 -> 120.33544 | I83: =G83*(1-H$77)/(1+I$55) -> 91.272151 | J83: =G83*(1-I$77)/(1+I$55)/(1+J$55) -> 75.471526 | K83: =G83*(1-J$77)/(1+I$55)/(1+J$55)/(1+K$55) -> 65.54473
E84: GPL | G84: =H84/0.998^10 -> 107.61525 | H84: ='Init. énergie'!D6 -> 105.48222 | I84: =G84*(1-H$77)/(1+I$55) -> 80.006262 | J84: =G84*(1-I$77)/(1+I$55)/(1+J$55) -> 66.155938 | K84: =G84*(1-J$77)/(1+I$55)/(1+J$55)/(1+K$55) -> 57.454424
E85: ENR | G85: =H85/0.998^10 -> 121.8021 | H85: ='Init. énergie'!D7 -> 119.38786 | I85: =G85*(1-H$77)/(1+I$55) -> 90.553431 | J85: =G85*(1-I$77)/(1+I$55)/(1+J$55) -> 74.877228 | K85: =G85*(1-J$77)/(1+I$55)/(1+J$55)/(1+K$55) -> 65.028601
E86: Joule | G86: =H86/0.998^10 -> 74.476189 | H86: ='Init. énergie'!D8 -> 73 | I86: =G86*(1-H$77)/(1+I$55) -> 55.369116 | J86: =G86*(1-I$77)/(1+I$55)/(1+J$55) -> 45.783864 | K86: =G86*(1-J$77)/(1+I$55)/(1+J$55)/(1+K$55) -> 39.761896
E87: PAC | G87: =H87/0.998^10 -> 56.036197 | H87: ='Init. énergie'!D9 -> 54.925506 | I87: =G87*(1-H$77)/(1+I$55) -> 41.659955 | J87: =G87*(1-I$77)/(1+I$55)/(1+J$55) -> 34.447971 | K87: =G87*(1-J$77)/(1+I$55)/(1+J$55)/(1+K$55) -> 29.917017
G88: Hyp de décroissance de la conso de 0,2%/an (SDES)
F89: Parc existant en 2015 hors décret tertiaire - Hypothèses de consommation unitaire de chauffage par type d'énergie - Scénario AME
E90: Energie | F90: TCAM 2010-2020 toutes branches | G90: Hypothèse TCAM 2020-2050 | M90: Justification hypothèses
E91: Fuel domestique | F91: ='Init. énergie'!L78 -> -0.0219191 | G91: =F91/3 -> -0.0073063666 | M91: Les segments du parc non concernés par le décret tertiaire sont rénovés plus lentement que le rythme tendanciel, car il s'agit de surfaces plus difficiles à rénover (nature du propriétaire…).
E92: Gaz naturel | F92: ='Init. énergie'!L77 -> -0.018828545 | G92: =F92/3 -> -0.0062761816
E93: Réseaux de chaleur | F93: ='Init. énergie'!L79 -> -0.012173839 | G93: =F93/3 -> -0.0040579464
E94: GPL | F94: ='Init. énergie'!L79 -> -0.012173839 | G94: =F94/3 -> -0.0040579464
E95: ENR | F95: ='Init. énergie'!L79 -> -0.012173839 | G95: =F95/3 -> -0.0040579464
E96: Joule | F96: ='Init. énergie'!L80 -> -0.028705469 | G96: =F96/3 -> -0.0095684898
E97: PAC | F97: =F96 -> -0.028705469 | G97: =F97/3 -> -0.0095684898
F99: Parc existant en 2020 hors décret tertiaire - Consommation unitaire de chauffage par type d'énergie [kWh/sq m] - Scénario AME
E100: Energie | G100: 2010 | H100: 2020 | I100: 2030 | J100: 2040 | K100: 2050 | M100: [Aide au calage] Evolution 2010-2050
E101: Fuel domestique | G101: =G81 -> 146.17508 | H101: =H81 -> 143.27775 | I101: =$H101*(1+$G91)^(I$100-$H$100) -> 133.14692 | J101: =$H101*(1+$G91)^(J$100-$H$100) -> 123.73241 | K101: =$H101*(1+$G91)^(K$100-$H$100) -> 114.98358 | M101: =(K101-G101)/H101 -> -0.21769949
E102: Gaz naturel | G102: =G82 -> 146.36446 | H102: =H82 -> 143.46338 | I102: =$H102*(1+$G92)^(I$100-$H$100) -> 134.70944 | J102: =$H102*(1+$G92)^(J$100-$H$100) -> 126.48966 | K102: =$H102*(1+$G92)^(K$100-$H$100) -> 118.77144 | M102: =(K102-G102)/H102 -> -0.19233492
E103: Réseaux de chaleur | G103: =G83 -> 122.76884 | H103: =H83 -> 120.33544 | I103: =$H103*(1+$G93)^(I$100-$H$100) -> 115.54051 | J103: =$H103*(1+$G93)^(J$100-$H$100) -> 110.93663 | K103: =$H103*(1+$G93)^(K$100-$H$100) -> 106.5162 | M103: =(K103-G103)/H103 -> -0.13506107
E104: GPL | G104: =G84 -> 107.61525 | H104: =H84 -> 105.48222 | I104: =$H104*(1+$G94)^(I$100-$H$100) -> 101.27913 | J104: =$H104*(1+$G94)^(J$100-$H$100) -> 97.243519 | K104: =$H104*(1+$G94)^(K$100-$H$100) -> 93.368714 | M104: =(K104-G104)/H104 -> -0.13506107
E105: ENR | G105: =G85 -> 121.8021 | H105: =H85 -> 119.38786 | I105: =$H105*(1+$G95)^(I$100-$H$100) -> 114.63069 | J105: =$H105*(1+$G95)^(J$100-$H$100) -> 110.06306 | K105: =$H105*(1+$G95)^(K$100-$H$100) -> 105.67745 | M105: =(K105-G105)/H105 -> -0.13506107
E106: Joule | G106: =G86 -> 74.476189 | H106: =H86 -> 73 | I106: =$H106*(1+$G96)^(I$100-$H$100) -> 66.308217 | J106: =$H106*(1+$G96)^(J$100-$H$100) -> 60.229858 | K106: =$H106*(1+$G96)^(K$100-$H$100) -> 54.708691 | M106: =(K106-G106)/H106 -> -0.27078765
E107: PAC | G107: =G87 -> 56.036197 | H107: =H87 -> 54.925506 | I107: =$H107*(1+$G97)^(I$100-$H$100) -> 49.89058 | J107: =$H107*(1+$G97)^(J$100-$H$100) -> 45.317197 | K107: =$H107*(1+$G97)^(K$100-$H$100) -> 41.163049 | M107: =(K107-G107)/H107 -> -0.27078765
F109: Parc existant en 2015 suivant le décret tertiaire - Consommation de chauffage par type d'énergie - Scénario AME [GWh LHV]
E110: Energie | G110: 2010 | H110: 2020 | I110: 2030 | J110: 2040 | K110: 2050
E111: Fuel domestique | G111: =G$36*G45*$J$73*G81/1000 -> 1350.2494 | H111: =H$36*H45*$J$73*H81/1000 -> 1323.4862 | I111: =I$36*I45*$J$73*I81/1000 -> 766.70866 | J111: =J$36*J45*$J$73*J81/1000 -> 490.35653 | K111: =K$36*K45*$J$73*K81/1000 -> 294.13354 | M111: =(K111-G111)/H111 -> -0.79798028
E112: Gaz naturel | G112: =G$36*G46*$J$73*G82/1000 -> 6384.4386 | H112: =H$36*H46*$J$73*H82/1000 -> 6257.893 | I112: =I$36*I46*$J$73*I82/1000 -> 4152.5699 | J112: =J$36*J46*$J$73*J82/1000 -> 3191.4468 | K112: =K$36*K46*$J$73*K82/1000 -> 2503.3742 | M112: =(K112-G112)/H112 -> -0.62018709
E113: Réseaux de chaleur | G113: =G$36*G47*$J$73*G83/1000 -> 1008.0366 | H113: =H$36*H47*$J$73*H83/1000 -> 988.05631 | I113: =I$36*I47*$J$73*I83/1000 -> 878.09955 | J113: =J$36*J47*$J$73*J83/1000 -> 726.77353 | K113: =K$36*K47*$J$73*K83/1000 -> 555.82986 | M113: =(K113-G113)/H113 -> -0.457673
E114: GPL | G114: =G$36*G48*$J$73*G84/1000 -> 143.58707 | H114: =H$36*H48*$J$73*H84/1000 -> 140.74104 | I114: =I$36*I48*$J$73*I84/1000 -> 92.365694 | J114: =J$36*J48*$J$73*J84/1000 -> 70.07732 | K114: =K$36*K48*$J$73*K84/1000 -> 54.135863 | M114: =(K114-G114)/H114 -> -0.63557304
E115: ENR | G115: =G$36*G49*$J$73*G85/1000 -> 150.01482 | H115: =H$36*H49*$J$73*H85/1000 -> 147.04138 | I115: =I$36*I49*$J$73*I85/1000 -> 127.7738 | J115: =J$36*J49*$J$73*J85/1000 -> 124.9821 | K115: =K$36*K49*$J$73*K85/1000 -> 122.54511 | M115: =(K115-G115)/H115 -> -0.18681618
E116: Joule | G116: =G$36*G50*$J$73*G86/1000 -> 2339.0367 | H116: =H$36*H50*$J$73*H86/1000 -> 2292.6747 | I116: =I$36*I50*$J$73*I86/1000 -> 1477.3219 | J116: =J$36*J50*$J$73*J86/1000 -> 1096.3418 | K116: =K$36*K50*$J$73*K86/1000 -> 824.23557 | M116: =(K116-G116)/H116 -> -0.66071348
E117: PAC | G117: =G$36*G51*$J$73*G87/1000 -> 419.84566 | H117: =H$36*H51*$J$73*H87/1000 -> 411.52392 | I117: =I$36*I51*$J$73*I87/1000 -> 521.03586 | J117: =J$36*J51*$J$73*J87/1000 -> 663.45216 | K117: =K$36*K51*$J$73*K87/1000 -> 789.29238 | M117: =(K117-G117)/H117 -> 0.89775273
E118: Total | G118: =SUM(G111:G117) -> 11795.209 | H118: =SUM(H111:H117) -> 11561.416 | I118: =SUM(I111:I117) -> 8015.8753 | J118: =SUM(J111:J117) -> 6363.4303 | K118: =SUM(K111:K117) -> 5143.5465 | M118: =(K118-G118)/H118 -> -0.57533281
F120: Parc existant en 2015 hors décret tertiaire - Consommation de chauffage par type d'énergie - Scénario AME [GWh LHV]
E121: Energie | G121: 2010 | H121: 2020 | I121: 2030 | J121: 2040 | K121: 2050
E122: Fuel domestique | G122: =G$36*G45*(1-$J$73)*G101/1000 -> 2429.8441 | H122: =H$36*H45*(1-$J$73)*H101/1000 -> 2381.6823 | I122: =I$36*I59*(1-$J$73)*I101/1000 -> 1767.289 | J122: =J$36*J59*(1-$J$73)*J101/1000 -> 1357.9889 | K122: =K$36*K59*(1-$J$73)*K101/1000 -> 974.83665 | M122: =(K122-G122)/H122 -> -0.61091585
...

Sheet CaHoREs - AME
C1: Bureaux - Scénario AME
C3: Résultats - Scénario AME
F5: Surface chauffée - Scénario AME [thousand sq m]
E6: Catégorie | G6: 2010 | H6: 2020 | I6: 2030 | J6: 2040 | K6: 2050
E7: Tous bureaux | H7: =H34 -> 67243.869 | I7: =I34 -> 69861.541 | J7: =J34 -> 70897.601 | K7: =K34 -> 70213.182
E8: Dont surfaces construites après 2015 | H8: =H35 -> 0 | I8: =I35 -> 4554.2951 | J8: =J35 -> 3048.0727 | K8: =K35 -> 2041.8509
E9: Dont surfaces existantes en 2015 | H9: =H36 -> 67243.869 | I9: =I36 -> 65307.246 | J9: =J36 -> 67849.529 | K9: =K36 -> 68171.331
F11: Consommation par source énergie - Scénario AME [GWh LHV]
E12: Energie | G12: 2010 | H12: 2020 | I12: 2030 | J12: 2040 | K12: 2050
E13: Fuel domestique | H13: =H133+H167 -> 1146.8356 | I13: =I133+I167 -> 835.17619 | J13: =J133+J167 -> 675.50311 | K13: =K133+K167 -> 510.20016
E14: Gaz naturel | H14: =H134+H168 -> 3676.1473 | I14: =I134+I168 -> 3015.5264 | J14: =J134+J168 -> 2811.9835 | K14: =K134+K168 -> 2529.5397
E15: Réseau de chaleur | H15: =H135+H169 -> 623.71893 | I15: =I135+I169 -> 712.056 | J15: =J135+J169 -> 753.20931 | K15: =K135+K169 -> 632.38683
E16: GPL | H16: =H136+H170 -> 125.59756 | I16: =I136+I170 -> 98.056256 | J16: =J136+J170 -> 86.136962 | K16: =K136+K170 -> 72.03639
E17: ENR | H17: =H137+H171 -> 213.99844 | I17: =I137+I171 -> 288.40871 | J17: =J137+J171 -> 378.06855 | K17: =K137+K171 -> 452.31176
E18: Electricité Joule | H18: =H138+H172 -> 1168.4295 | I18: =I138+I172 -> 836.424 | J18: =J138+J172 -> 682.92741 | K18: =K138+K172 -> 544.06695
E19: Electricité PAC | H19: =H139+H173 -> 330.97384 | I19: =I139+I173 -> 472.41985 | J19: =J139+J173 -> 531.33973 | K19: =K139+K173 -> 567.53441
E20: Total | H20: =SUM(H13:H19) -> 7285.7012 | I20: =SUM(I13:I19) -> 6258.0674 | J20: =SUM(J13:J19) -> 5919.1686 | K20: =SUM(K13:K19) -> 5308.0762
F22: Réalisation des objectifs
E23: Baisse de la consommation du parc suivant le décret | I23: =I118/$G118-1 -> -0.34444 | J23: =J118/$G118-1 -> -0.41982103 | K23: =K118/$G118-1 -> -0.51844856
E24: Baisse de la consommation du parc hors décret | I24: =I129/$G129-1 -> -0.11265686 | J24: =J129/$G129-1 -> -0.13867983 | K24: =K129/$G129-1 -> -0.20913738
C27: Calculs - Scénario AME
D29: SURFACES CHAUFFEES
F32: Surfaces chauffées - Scénario AME [thousand sq m]
E33: Surface | G33: 2010 | H33: 2020 | I33: 2030 | J33: 2040 | K33: 2050
E34: Surface [thousand sq m] | G34: =H34 -> 67243.869 | H34: ='Init. parc'!C5 -> 67243.869 | I34: ='Init. parc'!D5 -> 69861.541 | J34: ='Init. parc'!E5 -> 70897.601 | K34: ='Init. parc'!F5 -> 70213.182
E35: Dont surfaces construites après 2015 | H35: 0 | I35: ='Init. parc'!N5 -> 4554.2951 | J35: ='Init. parc'!O5 -> 3048.0727 | K35: ='Init. parc'!P5 -> 2041.8509
E36: Dont surfaces existantes en 2015 | G36: =G34-G35 -> 67243.869 | H36: =H34-H35 -> 67243.869 | I36: =I34-I35 -> 65307.246 | J36: =J34-J35 -> 67849.529 | K36: =K34-K35 -> 68171.331
D39: CHAUFFAGE
E41: Parc existant en 2020
F43: Parc existant en 2015 - Répartition des surfaces chauffées par type d'énergie de chauffage - Scénario Tendanciel - surfaces suivant la traj décret
E44: Energie | G44: 2010 | H44: 2020 | I44: 2030 | J44: 2040 | K44: 2050 | M44: Justification hypothèses
E45: Fuel domestique | G45: =H45 -> 0.08 | H45: ='Init. énergie'!B12 -> 0.08 | I45: =H45+((K45-H45)/3) -> 0.066666667 | J45: =H45+((K45-H45)/3*2) -> 0.053333333 | K45: 0.04 | M45: Bâtiments qui suivent le décret : baisse du gaz et du joule au profit de RCU et surtout PAC qui sont favorisés dans le DEET. Pour le gaz : baisse supplémentaire liée au cadrage macro-éco. Pic RCU en 2030/2040 car plus de fonds chaleur et juste coup de pouce CEE + classement des fonds chaleur mais après ça s'arrête
E46: Gaz naturel | G46: =H46 -> 0.345 | H46: ='Init. énergie'!B13 -> 0.345 | I46: =H46+((K46-H46)/3) -> 0.32333333 | J46: =H46+((K46-H46)/3*2) -> 0.30166667 | K46: 0.28
E47: Réseaux de chaleur | G47: =H47 -> 0.066 | H47: ='Init. énergie'!B14 -> 0.066 | I47: 0.1 | J47: 0.1 | K47: 0.09
E48: GPL | G48: =H48 -> 0.014 | H48: ='Init. énergie'!B15 -> 0.014 | I48: =H48+((K48-H48)/3) -> 0.012666667 | J48: =H48+((K48-H48)/3*2) -> 0.011333333 | K48: 0.01
E49: ENR | G49: =H49 -> 0.027 | H49: ='Init. énergie'!B16 -> 0.027 | I49: =H49+((K49-H49)/3) -> 0.028 | J49: =H49+((K49-H49)/3*2) -> 0.029 | K49: 0.03
E50: Joule | G50: =H50 -> 0.362 | H50: ='Init. énergie'!B17 -> 0.362 | I50: 0.31 | J50: 0.27 | K50: =1-K45-K46-K47-K48-K49-K51 -> 0.23
E51: PAC | G51: =H51 -> 0.107 | H51: ='Init. énergie'!B18 -> 0.107 | I51: 0.16 | J51: 0.24 | K51: 0.32
E52: Total | G52: =SUM(G45:G51) -> 1.001 | H52: =SUM(H45:H51) -> 1.001 | I52: =SUM(I45:I51) -> 1.0006667 | J52: =SUM(J45:J51) -> 1.0053333 | K52: =SUM(K45:K51) -> 1
F54: Baisses de consommation induites par les changements de système de chauffage
H55: =(G$81*(H45-G45)+G$82*(H46-G46)+G$83*(H47-G47)+G$84*(H48-G48)+G$85*(H49-G49)+G$86*(H50-G50)+G$87*(H51-G51))/(G$81*G45+G$82*G46+G$83*G47+G$84*G48+G$85*G49+G$86*G50+G$87*G51) -> 0 | I55: =(H$81*(I45-H45)+H$82*(I46-H46)+H$83*(I47-H47)+H$84*(I48-H48)+H$85*(I49-H49)+H$86*(I50-H50)+H$87*(I51-H51))/(H$81*H45+H$82*H46+H$83*H47+H$84*H48+H$85*H49+H$86*H50+H$87*H51) -> -0.014910693 | J55: =(I$81*(J45-I45)+I$82*(J46-I46)+I$83*(J47-I47)+I$84*(J48-I48)+I$85*(J49-I49)+I$86*(J50-I50)+I$87*(J51-I51))/(I$81*I45+I$82*I46+I$83*I47+I$84*I48+I$85*I49+I$86*I50+I$87*I51) -> -0.042872026 | K55: =(J$81*(K45-J45)+J$82*(K46-J46)+J$83*(K47-J47)+J$84*(K48-J48)+J$85*(K49-J49)+J$86*(K50-J50)+J$87*(K51-J51))/(J$81*J45+J$82*J46+J$83*J47+J$84*J48+J$85*J49+J$86*J50+J$87*J51) -> -0.058549501
F57: Parc existant en 2015 - Répartition des surfaces chauffées par type d'énergie de chauffage - Scénario Tendanciel - surfaces hors décret
E58: Energie | F58: 2006 | G58: 2015 | H58: 2020 | I58: 2030 | J58: 2040 | K58: 2050
E59: Fuel domestique | G59: =H59 -> 0.08 | H59: =H45 -> 0.08 | I59: =H59+((K59-H59)/3) -> 0.07 | J59: =H59+((K59-H59)/3*2) -> 0.06 | K59: 0.05 | M59: Bâtiments qui ne suivent pas le décret : légère baisse du gaz en faveur des PAC lié au cadrage macro-éco (ratio prix de l'élec/gaz de 1,5 en 2040/2050 qui oriente naturellement vers les PAC), pas de raccordement RCU car plus de fonds chaleur.
E60: Gaz naturel | G60: =H60 -> 0.345 | H60: =H46 -> 0.345 | I60: =H60+((K60-H60)/3) -> 0.33666667 | J60: =H60+((K60-H60)/3*2) -> 0.32833333 | K60: 0.32
E61: Réseaux de chaleur | G61: =H61 -> 0.066 | H61: =H47 -> 0.066 | I61: 0.08 | J61: 0.09 | K61: 0.08
E62: GPL | G62: =H62 -> 0.014 | H62: =H48 -> 0.014 | I62: =H62+((K62-H62)/3) -> 0.012666667 | J62: =H62+((K62-H62)/3*2) -> 0.011333333 | K62: 0.01
E63: ENR | G63: =H63 -> 0.027 | H63: =H49 -> 0.027 | I63: =H63+((K63-H63)/3) -> 0.044666667 | J63: =H63+((K63-H63)/3*2) -> 0.062333333 | K63: 0.08
E64: Joule | G64: =H64 -> 0.362 | H64: =H50 -> 0.362 | I64: 0.31 | J64: 0.27 | K64: =1-K59-K60-K61-K62-K63-K65 -> 0.24
E65: PAC | G65: =H65 -> 0.107 | H65: =H51 -> 0.107 | I65: =H65+((K65-H65)/3) -> 0.14466667 | J65: =H65+((K65-H65)/3*2) -> 0.18233333 | K65: 0.22
E66: Total | G66: =SUM(G59:G65) -> 1.001 | H66: 1 | I66: =SUM(I59:I65) -> 0.99866667 | J66: =SUM(J59:J65) -> 1.0043333 | K66: =SUM(K59:K65) -> 1
F68: Baisses de consommation induites par les changements de système de chauffage
H69: =(G101*(H59-G59)+G102*(H60-G60)+G103*(H61-H61)+G104*(H62-G62)+G105*(H63-G63)+G106*(H64-G64)+G107*(H65-G65))/(G101*G59+G102*G60+G103*G61+G104*G62+G105*G63+G106*G64+G107*G65) -> 0 | I69: =(H$101*(I59-H59)+H$102*(I60-H60)+H$103*(I61-H61)+H$104*(I62-H62)+H$105*(I63-H63)+H$106*(I64-H64)+H$107*(I65-H65))/(H$101*H59+H$102*H60+H$103*H61+H$104*H62+H$105*H63+H$106*H64+H$107*H65) -> -0.003172504 | J69: =(I$101*(J59-I59)+I$102*(J60-I60)+I$103*(J61-I61)+I$104*(J62-I62)+I$105*(J63-I63)+I$106*(J64-I64)+I$107*(J65-I65))/(I$101*I59+I$102*I60+I$103*I61+I$104*I62+I$105*I63+I$106*I64+I$107*I65) -> -0.0021118087 | K69: =(J$101*(K59-J59)+J$102*(K60-J60)+J$103*(K61-J61)+J$104*(K62-J62)+J$105*(K63-J63)+J$106*(K64-J64)+J$107*(K65-J65))/(J$101*J59+J$102*J60+J$103*J61+J$104*J62+J$105*J63+J$106*J64+J$107*J65) -> -0.024414782
M71: Justification hypothèses
H72: Proportion du parc assujeti (>1000m²) | I72: Proportion du parc assujetti suivant la trajectoire du décret tertiaire | J72: Proportion du parc suivant la trajectoire décret tertiaire | M72: Part du parc assujettie (>1000m²) x part du parc asujetti respectant la trajectoire du décret
G73: Proportion | H73: ='Tableau de bord'!F12 -> 0.61 | I73: ='Tableau de bord'!F24 -> 0.45 | J73: ='Tableau de bord'!F27 -> 0.2745
H75: 2030 | I75: 2040 | J75: 2050 | M75: Justification hypothèses
H76: Gain énergétique en 2030/2010 pour le parc suivant le décret | I76: Gain énergétique en 2040/2010 pour le parc suivant le décret | J76: Gain énergétique en 2050/2010 pour le parc suivant le décret | M76: Trajectoire spécifique pour les bureaux en raison de VA moins ambitieuses que les VR. La même pour les autres branches
H77: ='Tableau de bord'!F56 -> 0.325 | I77: ='Tableau de bord'!U56 -> 0.425 | J77: ='Tableau de bord'!AJ56 -> 0.525
F79: Trajectoire décret tertiaire [kWh/sq m]
E80: Energie | G80: 2010 | H80: 2020 | I80: 2030 | J80: 2040 | K80: 2050 | M80: Justification hypothèses
E81: Fuel domestique | G81: =H81/0.998^10 -> 217.49689 | H81: ='Init. énergie'!D12 -> 213.1859 | I81: =G81*(1-H$77)/(1+I$55) -> 149.03258 | J81: =G81*(1-I$77)/(1+I$55)/(1+J$55) -> 132.64024 | K81: =G81*(1-J$77)/(1+I$55)/(1+J$55)/(1+K$55) -> 116.38676 | M81: Réduction de consommation liée aux hypothèses du tableau de bord sur le respect du DEET
E82: Gaz naturel | G82: =H82/0.998^10 -> 161.66489 | H82: ='Init. énergie'!D13 -> 158.46054 | I82: =G82*(1-H$77)/(1+I$55) -> 110.77554 | J82: =G82*(1-I$77)/(1+I$55)/(1+J$55) -> 98.591151 | K82: =G82*(1-J$77)/(1+I$55)/(1+J$55)/(1+K$55) -> 86.50998
E83: Réseaux de chaleur | G83: =H83/0.998^10 -> 143.37944 | H83: ='Init. énergie'!D14 -> 140.53752 | I83: =G83*(1-H$77)/(1+I$55) -> 98.246039 | J83: =G83*(1-I$77)/(1+I$55)/(1+J$55) -> 87.439791 | K83: =G83*(1-J$77)/(1+I$55)/(1+J$55)/(1+K$55) -> 76.725086
E84: GPL | G84: =H84/0.998^10 -> 136.11158 | H84: ='Init. énergie'!D15 -> 133.41372 | I84: =G84*(1-H$77)/(1+I$55) -> 93.265976 | J84: =G84*(1-I$77)/(1+I$55)/(1+J$55) -> 83.007494 | K84: =G84*(1-J$77)/(1+I$55)/(1+J$55)/(1+K$55) -> 72.835915
E85: ENR | G85: =H85/0.998^10 -> 120.25101 | H85: ='Init. énergie'!D16 -> 117.86752 | I85: =G85*(1-H$77)/(1+I$55) -> 82.398046 | J85: =G85*(1-I$77)/(1+I$55)/(1+J$55) -> 73.334945 | K85: =G85*(1-J$77)/(1+I$55)/(1+J$55)/(1+K$55) -> 64.348622
E86: Joule | G86: =H86/0.998^10 -> 48.970645 | H86: ='Init. énergie'!D17 -> 48 | I86: =G86*(1-H$77)/(1+I$55) -> 33.555521 | J86: =G86*(1-I$77)/(1+I$55)/(1+J$55) -> 29.864693 | K86: =G86*(1-J$77)/(1+I$55)/(1+J$55)/(1+K$55) -> 26.205131
E87: PAC | G87: =H87/0.998^10 -> 46.930133 | H87: ='Init. énergie'!D18 -> 45.999933 | I87: =G87*(1-H$77)/(1+I$55) -> 32.157328 | J87: =G87*(1-I$77)/(1+I$55)/(1+J$55) -> 28.620289 | K87: =G87*(1-J$77)/(1+I$55)/(1+J$55)/(1+K$55) -> 25.113214
G88: Hyp de décroissance de la conso de 0,2%/an (SDES)
F89: Parc existant en 2015 hors décret tertiaire - Hypothèses de consommation unitaire de chauffage par type d'énergie - Scénario AME
E90: Energie | F90: TCAM 2010-2020 toutes branches | G90: Hypothèse TCAM 2020-2050 | M90: Justification hypothèses
E91: Fuel domestique | F91: ='Init. énergie'!L78 -> -0.0219191 | G91: =F91/3 -> -0.0073063666 | M91: Les segments du parc non concernés par le décret tertiaire sont rénovés plus lentement que le rythme tendanciel, car il s'agit de surfaces plus difficiles à rénover (nature du propriétaire…).
E92: Gaz naturel | F92: ='Init. énergie'!L77 -> -0.018828545 | G92: =F92/3 -> -0.0062761816
E93: Réseaux de chaleur | F93: ='Init. énergie'!L79 -> -0.012173839 | G93: =F93/3 -> -0.0040579464
E94: GPL | F94: ='Init. énergie'!L79 -> -0.012173839 | G94: =F94/3 -> -0.0040579464
E95: ENR | F95: ='Init. énergie'!L79 -> -0.012173839 | G95: =F95/3 -> -0.0040579464
E96: Joule | F96: ='Init. énergie'!L80 -> -0.028705469 | G96: =F96/3 -> -0.0095684898
E97: PAC | F97: =F96 -> -0.028705469 | G97: =F97/3 -> -0.0095684898
F99: Parc existant en 2020 hors décret tertiaire - Consommation unitaire de chauffage par type d'énergie [kWh/sq m] - Scénario AME
E100: Energie | G100: 2010 | H100: 2020 | I100: 2030 | J100: 2040 | K100: 2050 | M100: [Aide au calage] Evolution 2010-2050
E101: Fuel domestique | G101: =G81 -> 217.49689 | H101: =H81 -> 213.1859 | I101: =$H101*(1+$G91)^(I$100-$H$100) -> 198.11202 | J101: =$H101*(1+$G91)^(J$100-$H$100) -> 184.10399 | K101: =$H101*(1+$G91)^(K$100-$H$100) -> 171.08643 | M101: =(K101-G101)/H101 -> -0.21769949
E102: Gaz naturel | G102: =G82 -> 161.66489 | H102: =H82 -> 158.46054 | I102: =$H102*(1+$G92)^(I$100-$H$100) -> 148.7915 | J102: =$H102*(1+$G92)^(J$100-$H$100) -> 139.71245 | K102: =$H102*(1+$G92)^(K$100-$H$100) -> 131.18739 | M102: =(K102-G102)/H102 -> -0.19233492
E103: Réseaux de chaleur | G103: =G83 -> 143.37944 | H103: =H83 -> 140.53752 | I103: =$H103*(1+$G93)^(I$100-$H$100) -> 134.93761 | J103: =$H103*(1+$G93)^(J$100-$H$100) -> 129.56083 | K103: =$H103*(1+$G93)^(K$100-$H$100) -> 124.39829 | M103: =(K103-G103)/H103 -> -0.13506107
E104: GPL | G104: =G84 -> 136.11158 | H104: =H84 -> 133.41372 | I104: =$H104*(1+$G94)^(I$100-$H$100) -> 128.09766 | J104: =$H104*(1+$G94)^(J$100-$H$100) -> 122.99343 | K104: =$H104*(1+$G94)^(K$100-$H$100) -> 118.09258 | M104: =(K104-G104)/H104 -> -0.13506107
E105: ENR | G105: =G85 -> 120.25101 | H105: =H85 -> 117.86752 | I105: =$H105*(1+$G95)^(I$100-$H$100) -> 113.17092 | J105: =$H105*(1+$G95)^(J$100-$H$100) -> 108.66147 | K105: =$H105*(1+$G95)^(K$100-$H$100) -> 104.3317 | M105: =(K105-G105)/H105 -> -0.13506107
E106: Joule | G106: =G86 -> 48.970645 | H106: =H86 -> 48 | I106: =$H106*(1+$G96)^(I$100-$H$100) -> 43.599923 | J106: =$H106*(1+$G96)^(J$100-$H$100) -> 39.603194 | K106: =$H106*(1+$G96)^(K$100-$H$100) -> 35.972838 | M106: =(K106-G106)/H106 -> -0.27078765
E107: PAC | G107: =G87 -> 46.930133 | H107: =H87 -> 45.999933 | I107: =$H107*(1+$G97)^(I$100-$H$100) -> 41.783199 | J107: =$H107*(1+$G97)^(J$100-$H$100) -> 37.953006 | K107: =$H107*(1+$G97)^(K$100-$H$100) -> 34.473919 | M107: =(K107-G107)/H107 -> -0.27078765
F109: Parc existant en 2015 suivant le décret tertiaire - Consommation de chauffage par type d'énergie - Scénario AME [GWh LHV]
E110: Energie | G110: 2010 | H110: 2020 | I110: 2030 | J110: 2040 | K110: 2050
E111: Fuel domestique | G111: =G$36*G45*$J$73*G81/1000 -> 321.17231 | H111: =H$36*H45*$J$73*H81/1000 -> 314.80636 | I111: =I$36*I45*$J$73*I81/1000 -> 178.11221 | J111: =J$36*J45*$J$73*J81/1000 -> 131.75381 | K111: =K$36*K45*$J$73*K81/1000 -> 87.117956 | M111: =(K111-G111)/H111 -> -0.74348672
E112: Gaz naturel | G112: =G$36*G46*$J$73*G82/1000 -> 1029.5083 | H112: =H$36*H46*$J$73*H82/1000 -> 1009.1024 | I112: =I$36*I46*$J$73*I82/1000 -> 642.0932 | J112: =J$36*J46*$J$73*J82/1000 -> 553.92944 | K112: =K$36*K46*$J$73*K82/1000 -> 453.28189 | M112: =(K112-G112)/H112 -> -0.57102864
E113: Réseaux de chaleur | G113: =G$36*G47*$J$73*G83/1000 -> 174.67303 | H113: =H$36*H47*$J$73*H83/1000 -> 171.21085 | I113: =I$36*I47*$J$73*I83/1000 -> 176.12409 | J113: =J$36*J47*$J$73*J83/1000 -> 162.85395 | K113: =K$36*K47*$J$73*K83/1000 -> 129.2183 | M113: =(K113-G113)/H113 -> -0.26548981
E114: GPL | G114: =G$36*G48*$J$73*G84/1000 -> 35.173708 | H114: =H$36*H48*$J$73*H84/1000 -> 34.476531 | I114: =I$36*I48*$J$73*I84/1000 -> 21.178212 | J114: =J$36*J48*$J$73*J84/1000 -> 17.521212 | K114: =K$36*K48*$J$73*K84/1000 -> 13.629807 | M114: =(K114-G114)/H114 -> -0.62488598
E115: ENR | G115: =G$36*G49*$J$73*G85/1000 -> 59.930452 | H115: =H$36*H49*$J$73*H85/1000 -> 58.742573 | I115: =I$36*I49*$J$73*I85/1000 -> 41.359822 | J115: =J$36*J49*$J$73*J85/1000 -> 39.60939 | K115: =K$36*K49*$J$73*K85/1000 -> 36.124731 | M115: =(K115-G115)/H115 -> -0.40525498
E116: Joule | G116: =G$36*G50*$J$73*G86/1000 -> 327.2197 | H116: =H$36*H50*$J$73*H86/1000 -> 320.73389 | I116: =I$36*I50*$J$73*I86/1000 -> 186.47877 | J116: =J$36*J50*$J$73*J86/1000 -> 150.17962 | K116: =K$36*K50*$J$73*K86/1000 -> 112.7868 | M116: =(K116-G116)/H116 -> -0.66856949
E117: PAC | G117: =G$36*G51*$J$73*G87/1000 -> 92.689515 | H117: =H$36*H51*$J$73*H87/1000 -> 90.85232 | I117: =I$36*I51*$J$73*I87/1000 -> 92.236678 | J117: =J$36*J51*$J$73*J87/1000 -> 127.9306 | K117: =K$36*K51*$J$73*K87/1000 -> 150.38219 | M117: =(K117-G117)/H117 -> 0.63501593
E118: Total | G118: =SUM(G111:G117) -> 2040.367 | H118: =SUM(H111:H117) -> 1999.925 | I118: =SUM(I111:I117) -> 1337.583 | J118: =SUM(J111:J117) -> 1183.778 | K118: =SUM(K111:K117) -> 982.54167 | M118: =(K118-G118)/H118 -> -0.52893251
F120: Parc existant en 2015 hors décret tertiaire - Consommation de chauffage par type d'énergie - Scénario AME [GWh LHV]
E121: Energie | G121: 2010 | H121: 2020 | I121: 2030 | J121: 2040 | K121: 2050
E122: Fuel domestique | G122: =G$36*G45*(1-$J$73)*G101/1000 -> 848.85431 | H122: =H$36*H45*(1-$J$73)*H101/1000 -> 832.0292 | I122: =I$36*I59*(1-$J$73)*I101/1000 -> 657.06398 | J122: =J$36*J59*(1-$J$73)*J101/1000 -> 543.74929 | K122: =K$36*K59*(1-$J$73)*K101/1000 -> 423.08221 | M122: =(K122-G122)/H122 -> -0.51172735
...

Sheet Commerce - AME
C1: Bureaux - Scénario AME
C3: Résultats - Scénario AME
F5: Surface chauffée - Scénario AME [thousand sq m]
E6: Catégorie | G6: 2010 | H6: 2020 | I6: 2030 | J6: 2040 | K6: 2050
E7: Tous bureaux | H7: =H34 -> 184229.65 | I7: =I34 -> 188845.72 | J7: =J34 -> 189052.82 | K7: =K34 -> 184659.28
E8: Dont surfaces construites après 2015 | H8: =H35 -> 0 | I8: =I35 -> 13164.331 | J8: =J35 -> 8969.5375 | K8: =K35 -> 8772.0507
E9: Dont surfaces existantes en 2015 | H9: =H36 -> 184229.65 | I9: =I36 -> 175681.39 | J9: =J36 -> 180083.28 | K9: =K36 -> 175887.23
F11: Consommation par source énergie - Scénario AME [GWh LHV]
E12: Energie | G12: 2010 | H12: 2020 | I12: 2030 | J12: 2040 | K12: 2050
E13: Fuel domestique | H13: =H133+H167 -> 3430.6718 | I13: =I133+I167 -> 2428.7885 | J13: =J133+J167 -> 1974.2603 | K13: =K133+K167 -> 1465.9959
E14: Gaz naturel | H14: =H134+H168 -> 7861.9618 | I14: =I134+I168 -> 6281.2396 | J14: =J134+J168 -> 5758.9276 | K14: =K134+K168 -> 5009.7399
E15: Réseau de chaleur | H15: =H135+H169 -> 392.69537 | I15: =I135+I169 -> 337.41146 | J15: =J135+J169 -> 296.77485 | K15: =K135+K169 -> 232.21019
E16: GPL | H16: =H136+H170 -> 159.09604 | I16: =I136+I170 -> 138.28346 | J16: =J136+J170 -> 137.83284 | K16: =K136+K170 -> 130.22436
E17: ENR | H17: =H137+H171 -> 142.21439 | I17: =I137+I171 -> 112.40533 | J17: =J137+J171 -> 95.9689 | K17: =K137+K171 -> 77.872305
E18: Electricité Joule | H18: =H138+H172 -> 2654.7492 | I18: =I138+I172 -> 1911.1201 | J18: =J138+J172 -> 1385.0424 | K18: =K138+K172 -> 921.23625
E19: Electricité PAC | H19: =H139+H173 -> 822.29267 | I19: =I139+I173 -> 1507.7136 | J19: =J139+J173 -> 1917.8681 | K19: =K139+K173 -> 2211.6673
E20: Total | H20: =SUM(H13:H19) -> 15463.681 | I20: =SUM(I13:I19) -> 12716.962 | J20: =SUM(J13:J19) -> 11566.675 | K20: =SUM(K13:K19) -> 10048.946
F22: Réalisation des objectifs
E23: Baisse de la consommation du parc suivant le décret | I23: =I118/$G118-1 -> -0.35632 | J23: =J118/$G118-1 -> -0.43794124 | K23: =K118/$G118-1 -> -0.54650927
E24: Baisse de la consommation du parc hors décret | I24: =I129/$G129-1 -> -0.14836324 | J24: =J129/$G129-1 -> -0.20572739 | K24: =K129/$G129-1 -> -0.29522114
C27: Calculs - Scénario AME
D29: SURFACES CHAUFFEES
F32: Surfaces chauffées - Scénario AME [thousand sq m]
E33: Surface | G33: 2010 | H33: 2020 | I33: 2030 | J33: 2040 | K33: 2050
E34: Surface [thousand sq m] | G34: =H34 -> 184229.65 | H34: ='Init. parc'!C6 -> 184229.65 | I34: ='Init. parc'!D6 -> 188845.72 | J34: ='Init. parc'!E6 -> 189052.82 | K34: ='Init. parc'!F6 -> 184659.28
E35: Dont surfaces construites après 2015 | H35: 0 | I35: ='Init. parc'!N6 -> 13164.331 | J35: ='Init. parc'!O6 -> 8969.5375 | K35: ='Init. parc'!P6 -> 8772.0507
E36: Dont surfaces existantes en 2015 | G36: =G34-G35 -> 184229.65 | H36: =H34-H35 -> 184229.65 | I36: =I34-I35 -> 175681.39 | J36: =J34-J35 -> 180083.28 | K36: =K34-K35 -> 175887.23
D39: CHAUFFAGE
E41: Parc existant en 2020
F43: Parc existant en 2015 - Répartition des surfaces chauffées par type d'énergie de chauffage - Scénario Tendanciel - surfaces suivant la traj décret
E44: Energie | G44: 2010 | H44: 2020 | I44: 2030 | J44: 2040 | K44: 2050 | M44: Justification hypothèses
E45: Fuel domestique | G45: =H45 -> 0.184 | H45: ='Init. énergie'!B21 -> 0.184 | I45: 0.15 | J45: =H45+((K45-H45)/3*2) -> 0.128 | K45: 0.1 | M45: Bâtiments qui suivent le décret : baisse du gaz et du joule au profit de RCU et surtout PAC qui sont favorisés dans le DEET. Pour le gaz : baisse supplémentaire liée au cadrage macro-éco. Pic RCU en 2030/2040 car plus de fonds chaleur et juste coup de pouce CEE + classement des fonds chaleur mais après ça s'arrête
E46: Gaz naturel | G46: =H46 -> 0.393 | H46: ='Init. énergie'!B22 -> 0.393 | I46: =H46+((K46-H46)/3) -> 0.36866667 | J46: =H46+((K46-H46)/3*2) -> 0.34433333 | K46: 0.32
E47: Réseaux de chaleur | G47: =H47 -> 0.042 | H47: ='Init. énergie'!B23 -> 0.042 | I47: 0.05 | J47: 0.05 | K47: 0.04
E48: GPL | G48: =H48 -> 0.018 | H48: ='Init. énergie'!B24 -> 0.018 | I48: =H48+((K48-H48)/3) -> 0.018666667 | J48: =H48+((K48-H48)/3*2) -> 0.019333333 | K48: 0.02
E49: ENR | G49: =H49 -> 0.014 | H49: ='Init. énergie'!B25 -> 0.014 | I49: =H49+((K49-H49)/3) -> 0.012666667 | J49: =H49+((K49-H49)/3*2) -> 0.011333333 | K49: 0.01
E50: Joule | G50: =H50 -> 0.262 | H50: ='Init. énergie'!B26 -> 0.262 | I50: =H50+((K50-H50)/3) -> 0.21133333 | J50: =H50+((K50-H50)/3*2) -> 0.16066667 | K50: =1-K45-K46-K47-K48-K49-K51 -> 0.11
E51: PAC | G51: =H51 -> 0.088 | H51: ='Init. énergie'!B27 -> 0.088 | I51: =H51+((K51-H51)/3) -> 0.192 | J51: 0.29 | K51: 0.4
E52: Total | G52: =SUM(G45:G51) -> 1.001 | H52: =SUM(H45:H51) -> 1.001 | I52: =SUM(I45:I51) -> 1.0033333 | J52: =SUM(J45:J51) -> 1.0036667 | K52: =SUM(K45:K51) -> 1
F54: Baisses de consommation induites par les changements de système de chauffage
H55: =(G$81*(H45-G45)+G$82*(H46-G46)+G$83*(H47-G47)+G$84*(H48-G48)+G$85*(H49-G49)+G$86*(H50-G50)+G$87*(H51-G51))/(G$81*G45+G$82*G46+G$83*G47+G$84*G48+G$85*G49+G$86*G50+G$87*G51) -> 0 | I55: =(H$81*(I45-H45)+H$82*(I46-H46)+H$83*(I47-H47)+H$84*(I48-H48)+H$85*(I49-H49)+H$86*(I50-H50)+H$87*(I51-H51))/(H$81*H45+H$82*H46+H$83*H47+H$84*H48+H$85*H49+H$86*H50+H$87*H51) -> -0.038487308 | J55: =(I$81*(J45-I45)+I$82*(J46-I46)+I$83*(J47-I47)+I$84*(J48-I48)+I$85*(J49-I49)+I$86*(J50-I50)+I$87*(J51-I51))/(I$81*I45+I$82*I46+I$83*I47+I$84*I48+I$85*I49+I$86*I50+I$87*I51) -> -0.033781461 | K55: =(J$81*(K45-J45)+J$82*(K46-J46)+J$83*(K47-J47)+J$84*(K48-J48)+J$85*(K49-J49)+J$86*(K50-J50)+J$87*(K51-J51))/(J$81*J45+J$82*J46+J$83*J47+J$84*J48+J$85*J49+J$86*J50+J$87*J51) -> -0.041452608
F57: Parc existant en 2015 - Répartition des surfaces chauffées par type d'énergie de chauffage - Scénario Tendanciel - surfaces hors décret
E58: Energie | F58: 2006 | G58: 2015 | H58: 2020 | I58: 2030 | J58: 2040 | K58: 2050
E59: Fuel domestique | G59: =H59 -> 0.184 | H59: =H45 -> 0.184 | I59: =H59+((K59-H59)/3) -> 0.16266667 | J59: =H59+((K59-H59)/3*2) -> 0.14133333 | K59: 0.12 | M59: Bâtiments qui ne suivent pas le décret : légère baisse du gaz en faveur des PAC lié au cadrage macro-éco (ratio prix de l'élec/gaz de 1,5 en 2040/2050 qui oriente naturellement vers les PAC), pas de raccordement RCU car plus de fonds chaleur.
E60: Gaz naturel | G60: =H60 -> 0.393 | H60: =H46 -> 0.393 | I60: =H60+((K60-H60)/3) -> 0.38533333 | J60: =H60+((K60-H60)/3*2) -> 0.37766667 | K60: 0.37
E61: Réseaux de chaleur | G61: =H61 -> 0.042 | H61: =H47 -> 0.042 | I61: =H61+((K61-H61)/3) -> 0.038 | J61: =H61+((K61-H61)/3*2) -> 0.034 | K61: 0.03
E62: GPL | G62: =H62 -> 0.018 | H62: =H48 -> 0.018 | I62: =H62+((K62-H62)/3) -> 0.018666667 | J62: =H62+((K62-H62)/3*2) -> 0.019333333 | K62: 0.02
E63: ENR | G63: =H63 -> 0.014 | H63: =H49 -> 0.014 | I63: =H63+((K63-H63)/3) -> 0.012666667 | J63: =H63+((K63-H63)/3*2) -> 0.011333333 | K63: 0.01
E64: Joule | G64: =H64 -> 0.262 | H64: =H50 -> 0.262 | I64: =H64+((K64-H64)/3) -> 0.218 | J64: =H64+((K64-H64)/3*2) -> 0.174 | K64: =1-K59-K60-K61-K62-K63-K65 -> 0.13
E65: PAC | G65: =H65 -> 0.088 | H65: =H51 -> 0.088 | I65: =H65+((K65-H65)/3) -> 0.16533333 | J65: =H65+((K65-H65)/3*2) -> 0.24266667 | K65: 0.32
E66: Total | G66: =SUM(G59:G65) -> 1.001 | H66: 1 | I66: =SUM(I59:I65) -> 1.0006667 | J66: =SUM(J59:J65) -> 1.0003333 | K66: =SUM(K59:K65) -> 1
F68: Baisses de consommation induites par les changements de système de chauffage
H69: =(G101*(H59-G59)+G102*(H60-G60)+G103*(H61-H61)+G104*(H62-G62)+G105*(H63-G63)+G106*(H64-G64)+G107*(H65-G65))/(G101*G59+G102*G60+G103*G61+G104*G62+G105*G63+G106*G64+G107*G65) -> 0 | I69: =(H$101*(I59-H59)+H$102*(I60-H60)+H$103*(I61-H61)+H$104*(I62-H62)+H$105*(I63-H63)+H$106*(I64-H64)+H$107*(I65-H65))/(H$101*H59+H$102*H60+H$103*H61+H$104*H62+H$105*H63+H$106*H64+H$107*H65) -> -0.020654648 | J69: =(I$101*(J59-I59)+I$102*(J60-I60)+I$103*(J61-I61)+I$104*(J62-I62)+I$105*(J63-I63)+I$106*(J64-I64)+I$107*(J65-I65))/(I$101*I59+I$102*I60+I$103*I61+I$104*I62+I$105*I63+I$106*I64+I$107*I65) -> -0.021682176 | K69: =(J$101*(K59-J59)+J$102*(K60-J60)+J$103*(K61-J61)+J$104*(K62-J62)+J$105*(K63-J63)+J$106*(K64-J64)+J$107*(K65-J65))/(J$101*J59+J$102*J60+J$103*J61+J$104*J62+J$105*J63+J$106*J64+J$107*J65) -> -0.022769676
M71: Justification hypothèses
H72: Proportion du parc assujeti (>1000m²) | I72: Proportion du parc assujetti suivant la trajectoire du décret tertiaire | J72: Proportion du parc suivant la trajectoire décret tertiaire | M72: Part du parc assujettie (>1000m²) x part du parc asujetti respectant la trajectoire du décret
G73: Proportion | H73: ='Tableau de bord'!G12 -> 0.74 | I73: ='Tableau de bord'!G24 -> 0.45 | J73: ='Tableau de bord'!G27 -> 0.333
H75: 2030 | I75: 2040 | J75: 2050 | M75: Justification hypothèses
H76: Gain énergétique en 2030/2010 pour le parc suivant le décret | I76: Gain énergétique en 2040/2010 pour le parc suivant le décret | J76: Gain énergétique en 2050/2010 pour le parc suivant le décret | M76: Trajectoire spécifique pour les bureaux en raison de VA moins ambitieuses que les VR. La même pour les autres branches
H77: ='Tableau de bord'!F56 -> 0.325 | I77: ='Tableau de bord'!U56 -> 0.425 | J77: ='Tableau de bord'!AJ56 -> 0.525
F79: Trajectoire décret tertiaire [kWh/sq m]
E80: Energie | G80: 2010 | H80: 2020 | I80: 2030 | J80: 2040 | K80: 2050 | M80: Justification hypothèses
E81: Fuel domestique | G81: =H81/0.998^10 -> 103.25151 | H81: ='Init. énergie'!D21 -> 101.20497 | I81: =G81*(1-H$77)/(1+I$55) -> 72.484503 | J81: =G81*(1-I$77)/(1+I$55)/(1+J$55) -> 63.904858 | K81: =G81*(1-J$77)/(1+I$55)/(1+J$55)/(1+K$55) -> 55.073927 | M81: Réduction de consommation liée aux hypothèses du tableau de bord sur le respect du DEET
E82: Gaz naturel | G82: =H82/0.998^10 -> 110.78308 | H82: ='Init. énergie'!D22 -> 108.58726 | I82: =G82*(1-H$77)/(1+I$55) -> 77.771809 | J82: =G82*(1-I$77)/(1+I$55)/(1+J$55) -> 68.566331 | K82: =G82*(1-J$77)/(1+I$55)/(1+J$55)/(1+K$55) -> 59.091237
E83: Réseaux de chaleur | G83: =H83/0.998^10 -> 51.777558 | H83: ='Init. énergie'!D23 -> 50.751278 | I83: =G83*(1-H$77)/(1+I$55) -> 36.34882 | J83: =G83*(1-I$77)/(1+I$55)/(1+J$55) -> 32.046383 | K83: =G83*(1-J$77)/(1+I$55)/(1+J$55)/(1+K$55) -> 27.617935
E84: GPL | G84: =H84/0.998^10 -> 48.946535 | H84: ='Init. énergie'!D24 -> 47.976367 | I84: =G84*(1-H$77)/(1+I$55) -> 34.361388 | J84: =G84*(1-I$77)/(1+I$55)/(1+J$55) -> 30.294194 | K84: =G84*(1-J$77)/(1+I$55)/(1+J$55)/(1+K$55) -> 26.107878
E85: ENR | G85: =H85/0.998^10 -> 56.253633 | H85: ='Init. énergie'!D25 -> 55.138632 | I85: =G85*(1-H$77)/(1+I$55) -> 39.491108 | J85: =G85*(1-I$77)/(1+I$55)/(1+J$55) -> 34.816734 | K85: =G85*(1-J$77)/(1+I$55)/(1+J$55)/(1+K$55) -> 30.005454
E86: Joule | G86: =H86/0.998^10 -> 56.112197 | H86: ='Init. énergie'!D26 -> 55 | I86: =G86*(1-H$77)/(1+I$55) -> 39.391818 | J86: =G86*(1-I$77)/(1+I$55)/(1+J$55) -> 34.729196 | K86: =G86*(1-J$77)/(1+I$55)/(1+J$55)/(1+K$55) -> 29.930013
E87: PAC | G87: =H87/0.998^10 -> 51.746242 | H87: ='Init. énergie'!D27 -> 50.720582 | I87: =G87*(1-H$77)/(1+I$55) -> 36.326836 | J87: =G87*(1-I$77)/(1+I$55)/(1+J$55) -> 32.027001 | K87: =G87*(1-J$77)/(1+I$55)/(1+J$55)/(1+K$55) -> 27.601231
G88: Hyp de décroissance de la conso de 0,2%/an (SDES)
F89: Parc existant en 2015 hors décret tertiaire - Hypothèses de consommation unitaire de chauffage par type d'énergie - Scénario AME
E90: Energie | F90: TCAM 2010-2020 toutes branches | G90: Hypothèse TCAM 2020-2050 | M90: Justification hypothèses
E91: Fuel domestique | F91: ='Init. énergie'!L78 -> -0.0219191 | G91: =F91/3 -> -0.0073063666 | M91: Les segments du parc non concernés par le décret tertiaire sont rénovés plus lentement que le rythme tendanciel, car il s'agit de surfaces plus difficiles à rénover (nature du propriétaire…).
E92: Gaz naturel | F92: ='Init. énergie'!L77 -> -0.018828545 | G92: =F92/3 -> -0.0062761816
E93: Réseaux de chaleur | F93: ='Init. énergie'!L79 -> -0.012173839 | G93: =F93/3 -> -0.0040579464
E94: GPL | F94: ='Init. énergie'!L79 -> -0.012173839 | G94: =F94/3 -> -0.0040579464
E95: ENR | F95: ='Init. énergie'!L79 -> -0.012173839 | G95: =F95/3 -> -0.0040579464
E96: Joule | F96: ='Init. énergie'!L80 -> -0.028705469 | G96: =F96/3 -> -0.0095684898
E97: PAC | F97: =F96 -> -0.028705469 | G97: =F97/3 -> -0.0095684898
F99: Parc existant en 2020 hors décret tertiaire - Consommation unitaire de chauffage par type d'énergie [kWh/sq m] - Scénario AME
E100: Energie | G100: 2010 | H100: 2020 | I100: 2030 | J100: 2040 | K100: 2050 | M100: [Aide au calage] Evolution 2010-2050
E101: Fuel domestique | G101: =G81 -> 103.25151 | H101: =H81 -> 101.20497 | I101: =$H101*(1+$G91)^(I$100-$H$100) -> 94.049002 | J101: =$H101*(1+$G91)^(J$100-$H$100) -> 87.399019 | K101: =$H101*(1+$G91)^(K$100-$H$100) -> 81.219241 | M101: =(K101-G101)/H101 -> -0.21769949
E102: Gaz naturel | G102: =G82 -> 110.78308 | H102: =H82 -> 108.58726 | I102: =$H102*(1+$G92)^(I$100-$H$100) -> 101.96142 | J102: =$H102*(1+$G92)^(J$100-$H$100) -> 95.739875 | K102: =$H102*(1+$G92)^(K$100-$H$100) -> 89.897963 | M102: =(K102-G102)/H102 -> -0.19233492
E103: Réseaux de chaleur | G103: =G83 -> 51.777558 | H103: =H83 -> 50.751278 | I103: =$H103*(1+$G93)^(I$100-$H$100) -> 48.729021 | J103: =$H103*(1+$G93)^(J$100-$H$100) -> 46.787344 | K103: =$H103*(1+$G93)^(K$100-$H$100) -> 44.923037 | M103: =(K103-G103)/H103 -> -0.13506107
E104: GPL | G104: =G84 -> 48.946535 | H104: =H84 -> 47.976367 | I104: =$H104*(1+$G94)^(I$100-$H$100) -> 46.064681 | J104: =$H104*(1+$G94)^(J$100-$H$100) -> 44.229169 | K104: =$H104*(1+$G94)^(K$100-$H$100) -> 42.466795 | M104: =(K104-G104)/H104 -> -0.13506107
E105: ENR | G105: =G85 -> 56.253633 | H105: =H85 -> 55.138632 | I105: =$H105*(1+$G95)^(I$100-$H$100) -> 52.941555 | J105: =$H105*(1+$G95)^(J$100-$H$100) -> 50.832024 | K105: =$H105*(1+$G95)^(K$100-$H$100) -> 48.80655 | M105: =(K105-G105)/H105 -> -0.13506107
E106: Joule | G106: =G86 -> 56.112197 | H106: =H86 -> 55 | I106: =$H106*(1+$G96)^(I$100-$H$100) -> 49.958245 | J106: =$H106*(1+$G96)^(J$100-$H$100) -> 45.37866 | K106: =$H106*(1+$G96)^(K$100-$H$100) -> 41.218877 | M106: =(K106-G106)/H106 -> -0.27078765
E107: PAC | G107: =G87 -> 51.746242 | H107: =H87 -> 50.720582 | I107: =$H107*(1+$G97)^(I$100-$H$100) -> 46.071115 | J107: =$H107*(1+$G97)^(J$100-$H$100) -> 41.847856 | K107: =$H107*(1+$G97)^(K$100-$H$100) -> 38.011735 | M107: =(K107-G107)/H107 -> -0.27078765
F109: Parc existant en 2015 suivant le décret tertiaire - Consommation de chauffage par type d'énergie - Scénario AME [GWh LHV]
E110: Energie | G110: 2010 | H110: 2020 | I110: 2030 | J110: 2040 | K110: 2050
E111: Fuel domestique | G111: =G$36*G45*$J$73*G81/1000 -> 1165.5153 | H111: =H$36*H45*$J$73*H81/1000 -> 1142.4137 | I111: =I$36*I45*$J$73*I81/1000 -> 636.0722 | J111: =J$36*J45*$J$73*J81/1000 -> 490.52536 | K111: =K$36*K45*$J$73*K81/1000 -> 322.57046 | M111: =(K111-G111)/H111 -> -0.73786305
E112: Gaz naturel | G112: =G$36*G46*$J$73*G82/1000 -> 2670.9746 | H112: =H$36*H46*$J$73*H82/1000 -> 2618.0333 | I112: =I$36*I46*$J$73*I82/1000 -> 1677.3592 | J112: =J$36*J46*$J$73*J82/1000 -> 1415.8186 | K112: =K$36*K46*$J$73*K82/1000 -> 1107.5201 | M112: =(K112-G112)/H112 -> -0.59718663
E113: Réseaux de chaleur | G113: =G$36*G47*$J$73*G83/1000 -> 133.41191 | H113: =H$36*H47*$J$73*H83/1000 -> 130.76756 | I113: =I$36*I47*$J$73*I83/1000 -> 106.32376 | J113: =J$36*J47*$J$73*J83/1000 -> 96.087446 | K113: =K$36*K47*$J$73*K83/1000 -> 64.703793 | M113: =(K113-G113)/H113 -> -0.52542173
E114: GPL | G114: =G$36*G48*$J$73*G84/1000 -> 54.050312 | H114: =H$36*H48*$J$73*H84/1000 -> 52.978983 | I114: =I$36*I48*$J$73*I84/1000 -> 37.523856 | J114: =J$36*J48*$J$73*J84/1000 -> 35.122366 | K114: =K$36*K48*$J$73*K84/1000 -> 30.583003 | M114: =(K114-G114)/H114 -> -0.44295506
E115: ENR | G115: =G$36*G49*$J$73*G85/1000 -> 48.315042 | H115: =H$36*H49*$J$73*H85/1000 -> 47.357391 | I115: =I$36*I49*$J$73*I85/1000 -> 29.263863 | J115: =J$36*J49*$J$73*J85/1000 -> 23.662646 | K115: =K$36*K49*$J$73*K85/1000 -> 17.574329 | M115: =(K115-G115)/H115 -> -0.64912174
E116: Joule | G116: =G$36*G50*$J$73*G86/1000 -> 901.90816 | H116: =H$36*H50*$J$73*H86/1000 -> 884.03148 | I116: =I$36*I50*$J$73*I86/1000 -> 487.01689 | J116: =J$36*J50*$J$73*J86/1000 -> 334.6094 | K116: =K$36*K50*$J$73*K86/1000 -> 192.83157 | M116: =(K116-G116)/H116 -> -0.80209427
E117: PAC | G117: =G$36*G51*$J$73*G87/1000 -> 279.36066 | H117: =H$36*H51*$J$73*H87/1000 -> 273.82346 | I117: =I$36*I51*$J$73*I87/1000 -> 408.03629 | J117: =J$36*J51*$J$73*J87/1000 -> 556.97012 | K117: =K$36*K51*$J$73*K87/1000 -> 646.64659 | M117: =(K117-G117)/H117 -> 1.3413239
E118: Total | G118: =SUM(G111:G117) -> 5253.536 | H118: =SUM(H111:H117) -> 5149.4059 | I118: =SUM(I111:I117) -> 3381.596 | J118: =SUM(J111:J117) -> 2952.7959 | K118: =SUM(K111:K117) -> 2382.4299 | M118: =(K118-G118)/H118 -> -0.55756066
F120: Parc existant en 2015 hors décret tertiaire - Consommation de chauffage par type d'énergie - Scénario AME [GWh LHV]
E121: Energie | G121: 2010 | H121: 2020 | I121: 2030 | J121: 2040 | K121: 2050
E122: Fuel domestique | G122: =G$36*G45*(1-$J$73)*G101/1000 -> 2334.5307 | H122: =H$36*H45*(1-$J$73)*H101/1000 -> 2288.2581 | I122: =I$36*I59*(1-$J$73)*I101/1000 -> 1792.6865 | J122: =J$36*J59*(1-$J$73)*J101/1000 -> 1483.7147 | K122: =K$36*K59*(1-$J$73)*K101/1000 -> 1143.4056 | M122: =(K122-G122)/H122 -> -0.52053791
...

Sheet Enseignement - AME
C1: Bureaux - Scénario AME
C3: Résultats - Scénario AME
F5: Surface chauffée - Scénario AME [thousand sq m]
E6: Catégorie | G6: 2010 | H6: 2020 | I6: 2030 | J6: 2040 | K6: 2050
E7: Tous bureaux | H7: =H34 -> 167106.71 | I7: =I34 -> 169584.88 | J7: =J34 -> 168013.18 | K7: =K34 -> 162344.01
E8: Dont surfaces construites après 2015 | H8: =H35 -> 0 | I8: =I35 -> 5840.7077 | J8: =J35 -> 3412.3997 | K8: =K35 -> 3380.7737
E9: Dont surfaces existantes en 2015 | H9: =H36 -> 167106.71 | I9: =I36 -> 163744.18 | J9: =J36 -> 164600.78 | K9: =K36 -> 158963.24
F11: Consommation par source énergie - Scénario AME [GWh LHV]
E12: Energie | G12: 2010 | H12: 2020 | I12: 2030 | J12: 2040 | K12: 2050
E13: Fuel domestique | H13: =H133+H167 -> 3584.895 | I13: =I133+I167 -> 2621.0025 | J13: =J133+J167 -> 2142.0011 | K13: =K133+K167 -> 1647.061
E14: Gaz naturel | H14: =H134+H168 -> 8977.6736 | I14: =I134+I168 -> 7154.85 | J14: =J134+J168 -> 6440.7193 | K14: =K134+K168 -> 5525.384
E15: Réseau de chaleur | H15: =H135+H169 -> 1357.2567 | I15: =I135+I169 -> 1185.3944 | J15: =J135+J169 -> 1130.7378 | K15: =K135+K169 -> 1028.2412
E16: GPL | H16: =H136+H170 -> 214.36381 | I16: =I136+I170 -> 162.61007 | J16: =J136+J170 -> 138.4419 | K16: =K136+K170 -> 111.46831
E17: ENR | H17: =H137+H171 -> 141.7556 | I17: =I137+I171 -> 123.32236 | J17: =J137+J171 -> 117.6789 | K17: =K137+K171 -> 107.92926
E18: Electricité Joule | H18: =H138+H172 -> 751.9802 | I18: =I138+I172 -> 499.37701 | J18: =J138+J172 -> 357.77721 | K18: =K138+K172 -> 232.4827
E19: Electricité PAC | H19: =H139+H173 -> 116.24971 | I19: =I139+I173 -> 522.61095 | J19: =J139+J173 -> 682.65368 | K19: =K139+K173 -> 809.31798
E20: Total | H20: =SUM(H13:H19) -> 15144.175 | I20: =SUM(I13:I19) -> 12269.167 | J20: =SUM(J13:J19) -> 11010.01 | K20: =SUM(K13:K19) -> 9461.8845
F22: Réalisation des objectifs
E23: Baisse de la consommation du parc suivant le décret | I23: =I118/$G118-1 -> -0.3385824 | J23: =J118/$G118-1 -> -0.4336227 | K23: =K118/$G118-1 -> -0.54814778
E24: Baisse de la consommation du parc hors décret | I24: =I129/$G129-1 -> -0.1143849 | J24: =J129/$G129-1 -> -0.17615584 | K24: =K129/$G129-1 -> -0.2642009
C27: Calculs - Scénario AME
D29: SURFACES CHAUFFEES
F32: Surfaces chauffées - Scénario AME [thousand sq m]
E33: Surface | G33: 2010 | H33: 2020 | I33: 2030 | J33: 2040 | K33: 2050
E34: Surface [thousand sq m] | G34: =H34 -> 167106.71 | H34: ='Init. parc'!C7 -> 167106.71 | I34: ='Init. parc'!D7 -> 169584.88 | J34: ='Init. parc'!E7 -> 168013.18 | K34: ='Init. parc'!F7 -> 162344.01
E35: Dont surfaces construites après 2015 | H35: 0 | I35: ='Init. parc'!N7 -> 5840.7077 | J35: ='Init. parc'!O7 -> 3412.3997 | K35: ='Init. parc'!P7 -> 3380.7737
E36: Dont surfaces existantes en 2015 | G36: =G34-G35 -> 167106.71 | H36: =H34-H35 -> 167106.71 | I36: =I34-I35 -> 163744.18 | J36: =J34-J35 -> 164600.78 | K36: =K34-K35 -> 158963.24
D39: CHAUFFAGE
E41: Parc existant en 2020
F43: Parc existant en 2015 - Répartition des surfaces chauffées par type d'énergie de chauffage - Scénario Tendanciel - surfaces suivant la traj décret
E44: Energie | G44: 2010 | H44: 2020 | I44: 2030 | J44: 2040 | K44: 2050 | M44: Justification hypothèses
E45: Fuel domestique | G45: =H45 -> 0.202 | H45: ='Init. énergie'!B30 -> 0.202 | I45: =H45+((K45-H45)/3) -> 0.18133333 | J45: =H45+((K45-H45)/3*2) -> 0.16066667 | K45: 0.14 | M45: Bâtiments qui suivent le décret : baisse du gaz et du joule au profit de RCU et surtout PAC qui sont favorisés dans le DEET. Pour le gaz : baisse supplémentaire liée au cadrage macro-éco. Pic RCU en 2030/2040 car plus de fonds chaleur et juste coup de pouce CEE + classement des fonds chaleur mais après ça s'arrête
E46: Gaz naturel | G46: =H46 -> 0.588 | H46: ='Init. énergie'!B31 -> 0.588 | I46: =H46+((K46-H46)/3) -> 0.572 | J46: =H46+((K46-H46)/3*2) -> 0.556 | K46: 0.54
E47: Réseaux de chaleur | G47: =H47 -> 0.084 | H47: ='Init. énergie'!B32 -> 0.084 | I47: 0.1 | J47: 0.11 | K47: 0.12
E48: GPL | G48: =H48 -> 0.013 | H48: ='Init. énergie'!B33 -> 0.013 | I48: =H48+((K48-H48)/3) -> 0.012 | J48: =H48+((K48-H48)/3*2) -> 0.011 | K48: 0.01
E49: ENR | G49: =H49 -> 0.009 | H49: ='Init. énergie'!B34 -> 0.009 | I49: =H49+((K49-H49)/3) -> 0.0093333333 | J49: =H49+((K49-H49)/3*2) -> 0.0096666667 | K49: 0.01
E50: Joule | G50: =H50 -> 0.09 | H50: ='Init. énergie'!B35 -> 0.09 | I50: =H50+((K50-H50)/3) -> 0.066666667 | J50: =H50+((K50-H50)/3*2) -> 0.043333333 | K50: =1-K45-K46-K47-K48-K49-K51 -> 0.02
E51: PAC | G51: =H51 -> 0.013 | H51: ='Init. énergie'!B36 -> 0.013 | I51: =H51+((K51-H51)/3) -> 0.062 | J51: =H51+((K51-H51)/3*2) -> 0.111 | K51: 0.16
E52: Total | G52: =SUM(G45:G51) -> 0.999 | H52: =SUM(H45:H51) -> 0.999 | I52: =SUM(I45:I51) -> 1.0033333 | J52: =SUM(J45:J51) -> 1.0016667 | K52: =SUM(K45:K51) -> 1
F54: Baisses de consommation induites par les changements de système de chauffage
H55: =(G$81*(H45-G45)+G$82*(H46-G46)+G$83*(H47-G47)+G$84*(H48-G48)+G$85*(H49-G49)+G$86*(H50-G50)+G$87*(H51-G51))/(G$81*G45+G$82*G46+G$83*G47+G$84*G48+G$85*G49+G$86*G50+G$87*G51) -> 0 | I55: =(H$81*(I45-H45)+H$82*(I46-H46)+H$83*(I47-H47)+H$84*(I48-H48)+H$85*(I49-H49)+H$86*(I50-H50)+H$87*(I51-H51))/(H$81*H45+H$82*H46+H$83*H47+H$84*H48+H$85*H49+H$86*H50+H$87*H51) -> -0.0079609467 | J55: =(I$81*(J45-I45)+I$82*(J46-I46)+I$83*(J47-I47)+I$84*(J48-I48)+I$85*(J49-I49)+I$86*(J50-I50)+I$87*(J51-I51))/(I$81*I45+I$82*I46+I$83*I47+I$84*I48+I$85*I49+I$86*I50+I$87*I51) -> -0.014477801 | K55: =(J$81*(K45-J45)+J$82*(K46-J46)+J$83*(K47-J47)+J$84*(K48-J48)+J$85*(K49-J49)+J$86*(K50-J50)+J$87*(K51-J51))/(J$81*J45+J$82*J46+J$83*J47+J$84*J48+J$85*J49+J$86*J50+J$87*J51) -> -0.014690487
F57: Parc existant en 2015 - Répartition des surfaces chauffées par type d'énergie de chauffage - Scénario Tendanciel - surfaces hors décret
E58: Energie | F58: 2006 | G58: 2015 | H58: 2020 | I58: 2030 | J58: 2040 | K58: 2050
E59: Fuel domestique | G59: =H59 -> 0.202 | H59: =H45 -> 0.202 | I59: =H59+((K59-H59)/3) -> 0.18466667 | J59: =H59+((K59-H59)/3*2) -> 0.16733333 | K59: 0.15 | M59: Bâtiments qui ne suivent pas le décret : légère baisse du gaz en faveur des PAC lié au cadrage macro-éco (ratio prix de l'élec/gaz de 1,5 en 2040/2050 qui oriente naturellement vers les PAC), pas de raccordement RCU car plus de fonds chaleur.
E60: Gaz naturel | G60: =H60 -> 0.588 | H60: =H46 -> 0.588 | I60: =H60+((K60-H60)/3) -> 0.582 | J60: =H60+((K60-H60)/3*2) -> 0.576 | K60: 0.57
E61: Réseaux de chaleur | G61: =H61 -> 0.084 | H61: =H47 -> 0.084 | I61: 0.08 | J61: 0.08 | K61: 0.08
E62: GPL | G62: =H62 -> 0.013 | H62: =H48 -> 0.013 | I62: =H62+((K62-H62)/3) -> 0.012 | J62: =H62+((K62-H62)/3*2) -> 0.011 | K62: 0.01
E63: ENR | G63: =H63 -> 0.009 | H63: =H49 -> 0.009 | I63: =H63+((K63-H63)/3) -> 0.0093333333 | J63: =H63+((K63-H63)/3*2) -> 0.0096666667 | K63: 0.01
E64: Joule | G64: =H64 -> 0.09 | H64: =H50 -> 0.09 | I64: =H64+((K64-H64)/3) -> 0.08 | J64: =H64+((K64-H64)/3*2) -> 0.07 | K64: =1-K59-K60-K61-K62-K63-K65 -> 0.06
E65: PAC | G65: =H65 -> 0.013 | H65: =H51 -> 0.013 | I65: =H65+((K65-H65)/3) -> 0.048666667 | J65: =H65+((K65-H65)/3*2) -> 0.084333333 | K65: 0.12
E66: Total | G66: =SUM(G59:G65) -> 0.999 | H66: 1 | I66: =SUM(I59:I65) -> 0.99666667 | J66: =SUM(J59:J65) -> 0.99833333 | K66: =SUM(K59:K65) -> 1
F68: Baisses de consommation induites par les changements de système de chauffage
H69: =(G101*(H59-G59)+G102*(H60-G60)+G103*(H61-H61)+G104*(H62-G62)+G105*(H63-G63)+G106*(H64-G64)+G107*(H65-G65))/(G101*G59+G102*G60+G103*G61+G104*G62+G105*G63+G106*G64+G107*G65) -> 0 | I69: =(H$101*(I59-H59)+H$102*(I60-H60)+H$103*(I61-H61)+H$104*(I62-H62)+H$105*(I63-H63)+H$106*(I64-H64)+H$107*(I65-H65))/(H$101*H59+H$102*H60+H$103*H61+H$104*H62+H$105*H63+H$106*H64+H$107*H65) -> -0.015828271 | J69: =(I$101*(J59-I59)+I$102*(J60-I60)+I$103*(J61-I61)+I$104*(J62-I62)+I$105*(J63-I63)+I$106*(J64-I64)+I$107*(J65-I65))/(I$101*I59+I$102*I60+I$103*I61+I$104*I62+I$105*I63+I$106*I64+I$107*I65) -> -0.012092719 | K69: =(J$101*(K59-J59)+J$102*(K60-J60)+J$103*(K61-J61)+J$104*(K62-J62)+J$105*(K63-J63)+J$106*(K64-J64)+J$107*(K65-J65))/(J$101*J59+J$102*J60+J$103*J61+J$104*J62+J$105*J63+J$106*J64+J$107*J65) -> -0.012580529
M71: Justification hypothèses
H72: Proportion du parc assujeti (>1000m²) | I72: Proportion du parc assujetti suivant la trajectoire du décret tertiaire | J72: Proportion du parc suivant la trajectoire décret tertiaire | M72: Part du parc assujettie (>1000m²) x part du parc asujetti respectant la trajectoire du décret
G73: Proportion | H73: ='Tableau de bord'!H12 -> 0.92 | I73: ='Tableau de bord'!H24 -> 0.4965 | J73: ='Tableau de bord'!H27 -> 0.45678
H75: 2030 | I75: 2040 | J75: 2050 | M75: Justification hypothèses
H76: Gain énergétique en 2030/2010 pour le parc suivant le décret | I76: Gain énergétique en 2040/2010 pour le parc suivant le décret | J76: Gain énergétique en 2050/2010 pour le parc suivant le décret | M76: Trajectoire spécifique pour les bureaux en raison de VA moins ambitieuses que les VR. La même pour les autres branches
H77: ='Tableau de bord'!F56 -> 0.325 | I77: ='Tableau de bord'!U56 -> 0.425 | J77: ='Tableau de bord'!AJ56 -> 0.525
F79: Trajectoire décret tertiaire [kWh/sq m]
E80: Energie | G80: 2010 | H80: 2020 | I80: 2030 | J80: 2040 | K80: 2050 | M80: Justification hypothèses
E81: Fuel domestique | G81: =H81/0.998^10 -> 108.34922 | H81: ='Init. énergie'!D30 -> 106.20163 | I81: =G81*(1-H$77)/(1+I$55) -> 73.722622 | J81: =G81*(1-I$77)/(1+I$55)/(1+J$55) -> 63.723326 | K81: =G81*(1-J$77)/(1+I$55)/(1+J$55)/(1+K$55) -> 53.42586 | M81: Réduction de consommation liée aux hypothèses du tableau de bord sur le respect du DEET
E82: Gaz naturel | G82: =H82/0.998^10 -> 93.215295 | H82: ='Init. énergie'!D31 -> 91.367679 | I82: =G82*(1-H$77)/(1+I$55) -> 63.425249 | J82: =G82*(1-I$77)/(1+I$55)/(1+J$55) -> 54.822627 | K82: =G82*(1-J$77)/(1+I$55)/(1+J$55)/(1+K$55) -> 45.963483
E83: Réseaux de chaleur | G83: =H83/0.998^10 -> 98.646889 | H83: ='Init. énergie'!D32 -> 96.691613 | I83: =G83*(1-H$77)/(1+I$55) -> 67.120997 | J83: =G83*(1-I$77)/(1+I$55)/(1+J$55) -> 58.017105 | K83: =G83*(1-J$77)/(1+I$55)/(1+J$55)/(1+K$55) -> 48.641745
E84: GPL | G84: =H84/0.998^10 -> 100.67203 | H84: ='Init. énergie'!D33 -> 98.67661 | I84: =G84*(1-H$77)/(1+I$55) -> 68.498934 | J84: =G84*(1-I$77)/(1+I$55)/(1+J$55) -> 59.208147 | K84: =G84*(1-J$77)/(1+I$55)/(1+J$55)/(1+K$55) -> 49.640319
E85: ENR | G85: =H85/0.998^10 -> 96.160875 | H85: ='Init. énergie'!D34 -> 94.254875 | I85: =G85*(1-H$77)/(1+I$55) -> 65.429471 | J85: =G85*(1-I$77)/(1+I$55)/(1+J$55) -> 56.555008 | K85: =G85*(1-J$77)/(1+I$55)/(1+J$55)/(1+K$55) -> 47.415918
E86: Joule | G86: =H86/0.998^10 -> 51.011089 | H86: ='Init. énergie'!D35 -> 50 | I86: =G86*(1-H$77)/(1+I$55) -> 34.7088 | J86: =G86*(1-I$77)/(1+I$55)/(1+J$55) -> 30.001105 | K86: =G86*(1-J$77)/(1+I$55)/(1+J$55)/(1+K$55) -> 25.153032
E87: PAC | G87: =H87/0.998^10 -> 54.59454 | H87: ='Init. énergie'!D36 -> 53.512424 | I87: =G87*(1-H$77)/(1+I$55) -> 37.14704 | J87: =G87*(1-I$77)/(1+I$55)/(1+J$55) -> 32.108638 | K87: =G87*(1-J$77)/(1+I$55)/(1+J$55)/(1+K$55) -> 26.919995
G88: Hyp de décroissance de la conso de 0,2%/an (SDES)
F89: Parc existant en 2015 hors décret tertiaire - Hypothèses de consommation unitaire de chauffage par type d'énergie - Scénario AME
E90: Energie | F90: TCAM 2010-2020 toutes branches | G90: Hypothèse TCAM 2020-2050 | M90: Justification hypothèses
E91: Fuel domestique | F91: ='Init. énergie'!L78 -> -0.0219191 | G91: =F91/3 -> -0.0073063666 | M91: Les segments du parc non concernés par le décret tertiaire sont rénovés plus lentement que le rythme tendanciel, car il s'agit de surfaces plus difficiles à rénover (nature du propriétaire…).
E92: Gaz naturel | F92: ='Init. énergie'!L77 -> -0.018828545 | G92: =F92/3 -> -0.0062761816
E93: Réseaux de chaleur | F93: ='Init. énergie'!L79 -> -0.012173839 | G93: =F93/3 -> -0.0040579464
E94: GPL | F94: ='Init. énergie'!L79 -> -0.012173839 | G94: =F94/3 -> -0.0040579464
E95: ENR | F95: ='Init. énergie'!L79 -> -0.012173839 | G95: =F95/3 -> -0.0040579464
E96: Joule | F96: ='Init. énergie'!L80 -> -0.028705469 | G96: =F96/3 -> -0.0095684898
E97: PAC | F97: =F96 -> -0.028705469 | G97: =F97/3 -> -0.0095684898
F99: Parc existant en 2020 hors décret tertiaire - Consommation unitaire de chauffage par type d'énergie [kWh/sq m] - Scénario AME
E100: Energie | G100: 2010 | H100: 2020 | I100: 2030 | J100: 2040 | K100: 2050 | M100: [Aide au calage] Evolution 2010-2050
E101: Fuel domestique | G101: =G81 -> 108.34922 | H101: =H81 -> 106.20163 | I101: =$H101*(1+$G91)^(I$100-$H$100) -> 98.692363 | J101: =$H101*(1+$G91)^(J$100-$H$100) -> 91.714059 | K101: =$H101*(1+$G91)^(K$100-$H$100) -> 85.229174 | M101: =(K101-G101)/H101 -> -0.21769949
E102: Gaz naturel | G102: =G82 -> 93.215295 | H102: =H82 -> 91.367679 | I102: =$H102*(1+$G92)^(I$100-$H$100) -> 85.792552 | J102: =$H102*(1+$G92)^(J$100-$H$100) -> 80.557612 | K102: =$H102*(1+$G92)^(K$100-$H$100) -> 75.6421 | M102: =(K102-G102)/H102 -> -0.19233492
E103: Réseaux de chaleur | G103: =G83 -> 98.646889 | H103: =H83 -> 96.691613 | I103: =$H103*(1+$G93)^(I$100-$H$100) -> 92.838799 | J103: =$H103*(1+$G93)^(J$100-$H$100) -> 89.139506 | K103: =$H103*(1+$G93)^(K$100-$H$100) -> 85.587616 | M103: =(K103-G103)/H103 -> -0.13506107
E104: GPL | G104: =G84 -> 100.67203 | H104: =H84 -> 98.67661 | I104: =$H104*(1+$G94)^(I$100-$H$100) -> 94.744701 | J104: =$H104*(1+$G94)^(J$100-$H$100) -> 90.969464 | K104: =$H104*(1+$G94)^(K$100-$H$100) -> 87.344658 | M104: =(K104-G104)/H104 -> -0.13506107
E105: ENR | G105: =G85 -> 96.160875 | H105: =H85 -> 94.254875 | I105: =$H105*(1+$G95)^(I$100-$H$100) -> 90.499156 | J105: =$H105*(1+$G95)^(J$100-$H$100) -> 86.893089 | K105: =$H105*(1+$G95)^(K$100-$H$100) -> 83.430711 | M105: =(K105-G105)/H105 -> -0.13506107
E106: Joule | G106: =G86 -> 51.011089 | H106: =H86 -> 50 | I106: =$H106*(1+$G96)^(I$100-$H$100) -> 45.416587 | J106: =$H106*(1+$G96)^(J$100-$H$100) -> 41.253327 | K106: =$H106*(1+$G96)^(K$100-$H$100) -> 37.471706 | M106: =(K106-G106)/H106 -> -0.27078765
E107: PAC | G107: =G87 -> 54.59454 | H107: =H87 -> 53.512424 | I107: =$H107*(1+$G97)^(I$100-$H$100) -> 48.607033 | J107: =$H107*(1+$G97)^(J$100-$H$100) -> 44.151311 | K107: =$H107*(1+$G97)^(K$100-$H$100) -> 40.104037 | M107: =(K107-G107)/H107 -> -0.27078765
F109: Parc existant en 2015 suivant le décret tertiaire - Consommation de chauffage par type d'énergie - Scénario AME [GWh LHV]
E110: Energie | G110: 2010 | H110: 2020 | I110: 2030 | J110: 2040 | K110: 2050
E111: Fuel domestique | G111: =G$36*G45*$J$73*G81/1000 -> 1670.6217 | H111: =H$36*H45*$J$73*H81/1000 -> 1637.5083 | I111: =I$36*I45*$J$73*I81/1000 -> 999.88801 | J111: =J$36*J45*$J$73*J81/1000 -> 769.7739 | K111: =K$36*K45*$J$73*K81/1000 -> 543.10442 | M111: =(K111-G111)/H111 -> -0.68855664
E112: Gaz naturel | G112: =G$36*G46*$J$73*G82/1000 -> 4183.7476 | H112: =H$36*H46*$J$73*H82/1000 -> 4100.8217 | I112: =I$36*I46*$J$73*I82/1000 -> 2713.5083 | J112: =J$36*J46*$J$73*J82/1000 -> 2291.7836 | K112: =K$36*K46*$J$73*K82/1000 -> 1802.2311 | M112: =(K112-G112)/H112 -> -0.5807413
E113: Réseaux de chaleur | G113: =G$36*G47*$J$73*G83/1000 -> 632.50454 | H113: =H$36*H47*$J$73*H83/1000 -> 619.9677 | I113: =I$36*I47*$J$73*I83/1000 -> 502.03193 | J113: =J$36*J47*$J$73*J83/1000 -> 479.83034 | K113: =K$36*K47*$J$73*K83/1000 -> 423.83242 | M113: =(K113-G113)/H113 -> -0.33658548
E114: GPL | G114: =G$36*G48*$J$73*G84/1000 -> 99.897158 | H114: =H$36*H48*$J$73*H84/1000 -> 97.9171 | I114: =I$36*I48*$J$73*I84/1000 -> 61.480587 | J114: =J$36*J48*$J$73*J84/1000 -> 48.968086 | K114: =K$36*K48*$J$73*K84/1000 -> 36.044445 | M114: =(K114-G114)/H114 -> -0.65210992
E115: ENR | G115: =G$36*G49*$J$73*G85/1000 -> 66.060505 | H115: =H$36*H49*$J$73*H85/1000 -> 64.751122 | I115: =I$36*I49*$J$73*I85/1000 -> 45.675481 | J115: =J$36*J49*$J$73*J85/1000 -> 41.104255 | K115: =K$36*K49*$J$73*K85/1000 -> 34.42928 | M115: =(K115-G115)/H115 -> -0.48850466
E116: Joule | G116: =G$36*G50*$J$73*G86/1000 -> 350.43548 | H116: =H$36*H50*$J$73*H86/1000 -> 343.48951 | I116: =I$36*I50*$J$73*I86/1000 -> 173.0698 | J116: =J$36*J50*$J$73*J86/1000 -> 97.745848 | K116: =K$36*K50*$J$73*K86/1000 -> 36.527851 | M116: =(K116-G116)/H116 -> -0.91387835
E117: PAC | G117: =G$36*G51*$J$73*G87/1000 -> 54.174329 | H117: =H$36*H51*$J$73*H87/1000 -> 53.100542 | I117: =I$36*I51*$J$73*I87/1000 -> 172.26175 | J117: =J$36*J51*$J$73*J87/1000 -> 267.96855 | K117: =K$36*K51*$J$73*K87/1000 -> 312.75101 | M117: =(K117-G117)/H117 -> 4.8695678
E118: Total | G118: =SUM(G111:G117) -> 7057.4413 | H118: =SUM(H111:H117) -> 6917.5561 | I118: =SUM(I111:I117) -> 4667.9159 | J118: =SUM(J111:J117) -> 3997.1746 | K118: =SUM(K111:K117) -> 3188.9205 | M118: =(K118-G118)/H118 -> -0.5592323
F120: Parc existant en 2015 hors décret tertiaire - Consommation de chauffage par type d'énergie - Scénario AME [GWh LHV]
E121: Energie | G121: 2010 | H121: 2020 | I121: 2030 | J121: 2040 | K121: 2050
E122: Fuel domestique | G122: =G$36*G45*(1-$J$73)*G101/1000 -> 1986.7663 | H122: =H$36*H45*(1-$J$73)*H101/1000 -> 1947.3867 | I122: =I$36*I59*(1-$J$73)*I101/1000 -> 1621.1144 | J122: =J$36*J59*(1-$J$73)*J101/1000 -> 1372.2272 | K122: =K$36*K59*(1-$J$73)*K101/1000 -> 1103.9566 | M122: =(K122-G122)/H122 -> -0.45333047
...

Sheet Santé social - AME
C1: Bureaux - Scénario AME
C3: Résultats - Scénario AME
F5: Surface chauffée - Scénario AME [thousand sq m]
E6: Catégorie | G6: 2010 | H6: 2020 | I6: 2030 | J6: 2040 | K6: 2050
E7: Tous bureaux | H7: =H34 -> 179200 | I7: =I34 -> 197026.6 | J7: =J34 -> 210960.16 | K7: =K34 -> 219828.94
E8: Dont surfaces construites après 2015 | H8: =H35 -> 0 | I8: =I35 -> 22460.451 | J8: =J35 -> 19028.378 | K8: =K35 -> 14323.903
E9: Dont surfaces existantes en 2015 | H9: =H36 -> 179200 | I9: =I36 -> 174566.15 | J9: =J36 -> 191931.78 | K9: =K36 -> 205505.03
F11: Consommation par source énergie - Scénario AME [GWh LHV]
E12: Energie | G12: 2010 | H12: 2020 | I12: 2030 | J12: 2040 | K12: 2050
E13: Fuel domestique | H13: =H133+H167 -> 3808.9479 | I13: =I133+I167 -> 2725.8265 | J13: =J133+J167 -> 2376.274 | K13: =K133+K167 -> 1962.3462
E14: Gaz naturel | H14: =H134+H168 -> 10537.023 | I14: =I134+I168 -> 8382.2348 | J14: =J134+J168 -> 8265.1476 | K14: =K134+K168 -> 7896.7378
E15: Réseau de chaleur | H15: =H135+H169 -> 1744.7347 | I15: =I135+I169 -> 1742.8526 | J15: =J135+J169 -> 1671.0646 | K15: =K135+K169 -> 1543.7966
E16: GPL | H16: =H136+H170 -> 268.71712 | I16: =I136+I170 -> 292.67648 | J16: =J136+J170 -> 317.50398 | K16: =K136+K170 -> 331.5677
E17: ENR | H17: =H137+H171 -> 289.13035 | I17: =I137+I171 -> 269.97939 | J17: =J137+J171 -> 249.34782 | K17: =K137+K171 -> 219.09565
E18: Electricité Joule | H18: =H138+H172 -> 2089.6512 | I18: =I138+I172 -> 1355.1752 | J18: =J138+J172 -> 1093.9871 | K18: =K138+K172 -> 658.2375
E19: Electricité PAC | H19: =H139+H173 -> 258.00165 | I19: =I139+I173 -> 988.70901 | J19: =J139+J173 -> 1320.5307 | K19: =K139+K173 -> 1671.3861
E20: Total | H20: =SUM(H13:H19) -> 18996.206 | I20: =SUM(I13:I19) -> 15757.454 | J20: =SUM(J13:J19) -> 15293.856 | K20: =SUM(K13:K19) -> 14283.168
F22: Réalisation des objectifs
E23: Baisse de la consommation du parc suivant le décret | I23: =I118/$G118-1 -> -0.34245452 | J23: =J118/$G118-1 -> -0.38414747 | K23: =K118/$G118-1 -> -0.45527405
