Workbook

Sheet Récap run 1bis
B1: Mesures | C1: Cibles | D1: Modélisation | E1: Résultat
A2: Tertiaire
B3: Obligation de rénovation | C3: 9Mtep/2020 | D3: Choc exogène d'investissement et de consommation énergétique (cf. I4CE) | E3: Cible atteinte
B4: Réduction du nombre de m2 par employé/tend | C4: Xm²vs Xm²/employé an 2050 | D4: Choc exogène d'investissement immobilier | E4: Cible atteinte
A5: Energie
B6: Modification de la part des combustibles fossiles dans les vecteurs carburant, chaleur et vapeur et électricité | C6: Cibles Enerdata : 60% de biocarb, Electricité totalement décarbonée 27% de nucléaire; 0.6% de gaz naturel dans le vecteur chaleur et vapeur. | D6: Modification exogène | E6: Cible atteinte
A7: Résidentiel
B8: Hausse des taux moyens pondérés de ma prime rénov de 11.5% à 16.6% en 2025 puis 20% en 2040, quel que soit le saut de classe énergie. | C8: Réduction de la consommation énergétique des ménages de 42Mtep en 2015 à 29 Mtep en 2050 | D8: Hausse des crédits d'impôts à l'efficacité énergétique | E8: Cible atteinte
B9: Réduction de la construction neuve | C9: nombre de m² par tête de 44m² dans AME à 42m² dans AMS | D9: Modification exogene du nombre de m² par tête | E9: Cible atteinte
B10: Doublement du budget CEE alloué au résidentiel en 2024 jusqu’en 2050. | D10: Modification exogene du nombre CEE | E10: Cible atteinte
A11: Transport de voyageur
B12: Interdiction de la vente des Vth à partir de 2035 (pas d’interdiction dans AME) | C12: Baisse des émissions du parc de 37% en 2030 | D12: Modification exogene des coefficients du modèle de Bass; baisse des taux d'aide à l'achat de VE; aide à l'installation de bornes électriques | E12: Cible atteinte
B13: Développement du covoiturage et du télétravail | C13: Nombre de Km parcourus; nombre de véhicule en circulation | D13: Choc exogene sur le nombre de KM courte distance parcourus; choc sur le nombre de passagers/véhicule | E13: cible atteinte
A14: Transport de marchandises
B15: Report modal du transport de marchandises | C15: Part du fret ferroviaire passe de 10 à 18% en 2030 ; Part du fluvial de 2 à 3% en 2030; La part du routier de 88 à 79% en 2030 | D15: Modification exogene des coefficients techniques | E15: Cible atteinte
B16: Evolution exogène de la consommation de transport aérien | C16: Limitation à 22% de la hausse du trafic d'ici 2050 | D16: Choc exogene sur la demande finale | E16: Cible atteinte
B17: Aide à l'électrification des poids lourds | C17: Le parc passe de 97% gazole 3% élec en 2019 à 78% gazole 16% élec 6% gaz en 2050. | D17: Introduction d'un crédit d'impôt à l'électrification (Hausse du crédit d’impôt de 0 en 2023 à 270M€ en 2030 puis à 860M€ en 2050 (13Mds€ sur toute la période). | E17: Cible atteinte
B18: Electrification des bus | D18: non réalisé
B19: Amélioration des rendements des moteurs | C19: (1.5%/An versus 0.3%/an) | D19: non réalisé
B20: Augmentation du taux de chargement | C20: baisse du trafic de 16% en veh.km (ce qui correspond à l’augmentation de 20% du taux de chargement) | D20: Choc négatif sur le ratio énergie/production | E20: Cible atteinte
A21: Industrie | B21: Crédit d'impôt à l'EE | C21: 12mds€ pour une baisse de 35MtCO2 | D21: Introduction d'un crédit d'impôt à l'efficacité énergéttique | E21: Cible atteinte
B22: Introduction des CEE | D22: non réalisé
B23: Réduction de la consommation de produits manufacturés | C23: Sucre (-31% dans AMS en 2050 ; Papier (baisse de 30% dans l’AME en 2050 et seulement 15% dans l’AMS); Textile (baisse de la consommation finale de 15% en 2050 dans AME et 30% dans l’AMS en 2050 | D23: Choc de demande négatif sur le sucre, le textile, le plastique. Insertion d’un choc sur la demande finale de l’agroalimentaire au prorata de la part du sucre dans la consommation qui est de 2,4%; Insertion d’un choc négatif sur la consommation finale du secteur autre industrie au prorata de la part de la consommation du textile 19,4% | E23: Cible atteinte
B24: Réduction de la demande de consommation intermédiaire de plastique | C24: La part de marché des menuiseries PVC passe de 61 à 48 et 27% dans l’AME et l’AMS en 2050. En revanche la part des tuyaux reste à 100%. Il est prévu que la part de marché du PVC dans les menuiseries soit réduite. Il est prévu que les films plastiques disparaissent dans l’AMS en 2050 ; que le nombre de bouteilles chute de 80% par rapport à 2014, que les emballages chutent de 60% etc… | D24: Faute d’avoir les quantités concernées par ses sous-produits, nous avons appliqué aux ratios CI/prod de plastiques consommés par les divers secteurs de production hors automobile et construction, le taux de croissance anticipé de la production de dichlore et d’éthylène consommé par le secteur de la fabrication de plastique entre aujourd’hui et 2050 | E24: Cible atteinte
B25: Réduction de la demanded'engrais azotés | C25: Il est prévu de réduire la consommation d’engrais de respectivement 29% et 59% en 2050 dans l’AME et l’AMS et de réduire la consommation de produits phytosanitaires de 31% et 44%. | D25: Modification des coefficients techniques | E25: Cible atteinte
B26: Augmentation de la construction bois | C26: La part des MI en bois passe de 10% aujourd’hui à 38% dans l’AMS en 2050, la part des LC passe de 3% à 38% ; respectivement 25 et 15% dans l’AME. | D26: On introduit un choc moyen pondéré (avec 44% de MI et 66% de LC) sur le ratio consommations intermédiaires/production de bois dans le bâtiment de la même ampleur. un choc inverse de même ampleur est appliqué à au ratio de consommations intermédiaires/production d’acier et de ciment par le BTP. | E26: Cible atteinte
B27: Modifiaction des taux d'import et d'export | C27: Cible de VA/PIB | D27: Non réalisé

Sheet Récap run 2
B1: Mesures | C1: Cibles | D1: Modélisation | E1: Résultat
A2: Tertiaire
B3: Obligation de rénovation
B4: Réduction du nombre de m2 par employé/tend
A5: Energie
B6: Modification de la part des combustibles fossiles dans les vecteurs carburant, chaleur et vapeur et électricité
A7: Résidentiel
B8: Hausse des taux moyens pondérés de ma prime rénov de 11.5% à 16.6% en 2025 puis 20% en 2040, quel que soit le saut de classe énergie.
B9: Réduction de la construction neuve
B10: Doublement du budget CEE alloué au résidentiel en 2024 jusqu’en 2050.
A11: Transport de voyageurs
B12: Interdiction de la vente des Vth à partir de 2035 (pas d’interdiction dans AME)
B13: Développement du covoiturage et du télétravail
A14: Transport de marchandises
B15: Report modal du transport de marchandises
B16: Evolution exogène de la consommation de transport aérien
B17: Aide à l'électrification des poids lourds
B18: Electrification des bus
B19: Amélioration des rendements des moteurs
B20: Augmentation du taux de chargement
A21: Industrie | B21: Crédit d'impôt à l'EE
B22: Introduction des CEE
B23: Réduction de la consommation de produits manufacturés
B24: Réduction de la demande de consommation intermédiaire de plastique
B25: Réduction de la demanded'engrais azotés
B26: Augmentation de la construction bois
B27: Modification des taux d'import et d'export | C27: Cible de VA/PIB | D27: Non réalisé

Sheet Variables AME
B1: 2004 | C1: 2005 | D1: 2006 | E1: 2007 | F1: 2008 | G1: 2009 | H1: 2010 | I1: 2011 | J1: 2012 | K1: 2013 | L1: 2014 | M1: 2015 | N1: 2016 | O1: 2017 | P1: 2018 | Q1: 2019 | R1: 2020 | S1: 2021 | T1: 2022 | U1: 2023 | V1: 2024 | W1: 2025 | X1: 2026 | Y1: 2027 | Z1: 2028 | AA1: 2029 | AB1: 2030 | AC1: 2031 | AD1: 2032 | AE1: 2033 | AF1: 2034 | AG1: 2035 | AH1: 2036 | AI1: 2037 | AJ1: 2038 | AK1: 2039 | AL1: 2040 | AM1: 2041 | AN1: 2042 | AO1: 2043 | AP1: 2044 | AQ1: 2045 | AR1: 2046 | AS1: 2047 | AT1: 2048 | AU1: 2049 | AV1: 2050
A2: NEWAUTO_ELEC_H01_1 | B2: 1.149299 | C2: 1.1677514 | D2: 2.1795284 | E2: 3.547016 | F2: 5.7123385 | G2: 9.1532957 | H2: 12.615338 | I2: 17.14676 | J2: 20.465819 | K2: 26.068457 | L2: 34.520713 | M2: 42.053287 | N2: 57.293884 | O2: 77.334793 | P2: 101.82701 | Q2: 131.38201 | R2: 142.42415 | S2: 157.17609 | T2: 197.20989 | U2: 245.22433 | V2: 291.13823 | W2: 336.90526 | X2: 436.40521 | Y2: 519.20602 | Z2: 600.30871 | AA2: 677.02292 | AB2: 748.55698 | AC2: 816.71218 | AD2: 838.45699 | AE2: 876.08867 | AF2: 917.71998 | AG2: 914.71055 | AH2: 979.21172 | AI2: 1029.4205 | AJ2: 1070.873 | AK2: 1107.4311 | AL2: 1139.4612 | AM2: 1160.2497 | AN2: 1184.2959 | AO2: 1210.3841 | AP2: 1236.0266 | AQ2: 1260.9109 | AR2: 1278.5939 | AS2: 1298.7024 | AT2: 1319.1199 | AU2: 1339.36 | AV2: 1360.017
A3: NEWAUTO_TH_H01_1 | B3: 2297.4487 | C3: 2334.335 | D3: 2370.8205 | E3: 2443.1306 | F3: 2418.5642 | G3: 2651.2106 | H3: 2586.2336 | I3: 2525.6757 | J3: 2173.6021 | K3: 2047.7565 | L3: 2044.8223 | M3: 1898.3337 | N3: 1985.0221 | O3: 2064.2932 | P3: 2101.915 | Q3: 2108.92 | R3: 1789.3354 | S3: 1557.3268 | T3: 1553.4291 | U3: 1549.745 | V3: 1491.1436 | W3: 1414.0827 | X3: 1519.1815 | Y3: 1517.8806 | Z3: 1492.6078 | AA3: 1449.66 | AB3: 1396.9915 | AC3: 1343.5623 | AD3: 1228.6922 | AE3: 1154.6411 | AF3: 1097.2699 | AG3: 999.95777 | AH3: 985.60912 | AI3: 959.98205 | AJ3: 930.40967 | AK3: 900.91807 | AL3: 871.84588 | AM3: 838.30036 | AN3: 810.91855 | AO3: 787.98095 | AP3: 767.30334 | AQ3: 748.38023 | AR3: 727.30298 | AS3: 709.56242 | AT3: 693.64079 | AU3: 679.07121 | AV3: 665.98317
A4: NEWAUTO_H01_1 | B4: 2298.598 | C4: 2335.5027 | D4: 2373 | E4: 2446.6776 | F4: 2424.2766 | G4: 2660.3639 | H4: 2598.849 | I4: 2542.8224 | J4: 2194.0679 | K4: 2073.825 | L4: 2079.343 | M4: 1940.387 | N4: 2042.316 | O4: 2141.628 | P4: 2203.742 | Q4: 2240.302 | R4: 1931.7595 | S4: 1714.5029 | T4: 1750.639 | U4: 1794.9694 | V4: 1782.2818 | W4: 1750.988 | X4: 1955.5868 | Y4: 2037.0867 | Z4: 2092.9165 | AA4: 2126.6829 | AB4: 2145.5485 | AC4: 2160.2745 | AD4: 2067.1492 | AE4: 2030.7298 | AF4: 2014.9898 | AG4: 1914.6683 | AH4: 1964.8208 | AI4: 1989.4025 | AJ4: 2001.2827 | AK4: 2008.3491 | AL4: 2011.3071 | AM4: 1998.55 | AN4: 1995.2145 | AO4: 1998.365 | AP4: 2003.33 | AQ4: 2009.2911 | AR4: 2005.8969 | AS4: 2008.2648 | AT4: 2012.7607 | AU4: 2018.4312 | AV4: 2026.0001
A5: PAUTO_ELEC_H01_1 | B5: 32.360331 | C5: 33.007538 | D5: 33.488809 | E5: 33.839494 | F5: 34.293416 | G5: 34.811247 | H5: 34.91417 | I5: 35.171003 | J5: 35.488543 | K5: 35.912137 | L5: 36.504035 | M5: 37.069763 | N5: 37.545288 | O5: 38.395762 | P5: 38.888451 | Q5: 39.418662 | R5: 40.067961 | S5: 40.604049 | T5: 40.697631 | U5: 41.005045 | V5: 41.561604 | W5: 42.127885 | X5: 42.702397 | Y5: 43.285092 | Z5: 43.876042 | AA5: 44.47524 | AB5: 45.083172 | AC5: 45.701113 | AD5: 46.329811 | AE5: 46.97022 | AF5: 47.623412 | AG5: 48.289918 | AH5: 48.969914 | AI5: 49.66366 | AJ5: 50.370978 | AK5: 51.091802 | AL5: 51.826328 | AM5: 52.544713 | AN5: 53.275889 | AO5: 54.019879 | AP5: 54.776991 | AQ5: 55.54754 | AR5: 56.332024 | AS5: 57.130734 | AT5: 57.943953 | AU5: 58.771982 | AV5: 59.616281
A6: PNEWAUTO_TH_H01_1 | B6: 21.704143 | C6: 22.138226 | D6: 22.417243 | E6: 22.83235 | F6: 22.906497 | G6: 23.386835 | H6: 23.514262 | I6: 23.605102 | J6: 23.817102 | K6: 24.147671 | L6: 24.706833 | M6: 25.200848 | N6: 25.668231 | O6: 26.364201 | P6: 26.547282 | Q6: 26.917385 | R6: 26.979834 | S6: 27.33753 | T6: 27.257914 | U6: 27.546627 | V6: 28.017065 | W6: 28.494237 | X6: 28.993492 | Y6: 29.503083 | Z6: 30.0186 | AA6: 30.540507 | AB6: 31.070022 | AC6: 31.608256 | AD6: 32.155336 | AE6: 32.714171 | AF6: 33.281408 | AG6: 33.860904 | AH6: 34.453812 | AI6: 35.0552 | AJ6: 35.671621 | AK6: 36.29989 | AL6: 36.940618 | AM6: 37.564976 | AN6: 38.199753 | AO6: 38.845735 | AP6: 39.502689 | AQ6: 40.170735 | AR6: 40.848734 | AS6: 41.538336 | AT6: 42.239856 | AU6: 42.953787 | AV6: 43.681095
A7: PNEWAUTO_H01_1 | B7: 21.709471 | C7: 22.143661 | D7: 22.427412 | E7: 22.848307 | F7: 22.933329 | G7: 23.426142 | H7: 23.5696 | I7: 23.683093 | J7: 23.92597 | K7: 24.295553 | L7: 24.902687 | M7: 25.458078 | N7: 26.001423 | O7: 26.798664 | P7: 27.117523 | Q7: 27.65052 | R7: 27.944791 | S7: 28.553731 | T7: 28.771901 | U7: 29.385283 | V7: 30.229585 | W7: 31.117469 | X7: 32.052747 | Y7: 33.015797 | Z7: 33.993313 | AA7: 34.976586 | AB7: 35.959047 | AC7: 36.936194 | AD7: 37.904649 | AE7: 38.864454 | AF7: 39.813423 | AG7: 40.754198 | AH7: 41.688231 | AI7: 42.614378 | AJ7: 43.537149 | AK7: 44.456352 | AL7: 45.373785 | AM7: 46.261398 | AN7: 47.148468 | AO7: 48.036519 | AP7: 48.92672 | AQ7: 49.820298 | AR7: 50.718055 | AS7: 51.62161 | AT7: 52.531982 | AU7: 53.450185 | AV7: 54.378095
A8: PCH_1 | B8: 0.96116878 | C8: 0.98039216 | D8: 0.98715712 | E8: 0.99036346 | F8: 1.0043122 | G8: 1.0057988 | H8: 1.0145862 | I8: 1.0232782 | J8: 1.032617 | K8: 1.0399768 | L8: 1.0501176 | M8: 1.0574685 | N8: 1.064722 | O8: 1.0798249 | P8: 1.1017374 | Q8: 1.1217746 | R8: 1.1440126 | S8: 1.1667712 | T8: 1.1905363 | U8: 1.2149769 | V8: 1.2399797 | W8: 1.2654671 | X8: 1.2907267 | Y8: 1.3160357 | Z8: 1.3415843 | AA8: 1.3673916 | AB8: 1.3935086 | AC8: 1.4200773 | AD8: 1.4467659 | AE8: 1.4742381 | AF8: 1.5023842 | AG8: 1.5308525 | AH8: 1.5605419 | AI8: 1.5907691 | AJ8: 1.6215977 | AK8: 1.6530092 | AL8: 1.6850182 | AM8: 1.7177333 | AN8: 1.7510721 | AO8: 1.78504 | AP8: 1.819655 | AQ8: 1.8549028 | AR8: 1.8908421 | AS8: 1.9275086 | AT8: 1.9648686 | AU8: 2.0029474 | AV8: 2.0420028
A9: AUTO_ELEC_H01_1 | B9: 2.3360541 | C9: 2.3735602 | D9: 2.4116685 | E9: 5.8260427 | F9: 11.217949 | G9: 19.754257 | H9: 31.283111 | I9: 46.7093 | J9: 64.606108 | K9: 87.121228 | L9: 116.85027 | M9: 152.4768 | N9: 201.38446 | O9: 268.65003 | P9: 357.04453 | Q9: 470.57431 | R9: 589.46975 | S9: 717.17235 | T9: 874.53933 | U9: 1068.3202 | V9: 1296.616 | W9: 1557.2498 | X9: 1902.052 | Y9: 2309.3727 | Z9: 2773.8359 | AA9: 3287.692 | AB9: 3842.8553 | AC9: 4433.5172 | AD9: 5011.1791 | AE9: 5592.4925 | AF9: 6181.2423 | AG9: 6732.3504 | AH9: 7315.5415 | AI9: 7914.636 | AJ9: 8519.9422 | AK9: 9126.2002 | AL9: 9728.8261 | AM9: 10313.406 | AN9: 10883.808 | AO9: 11442.467 | AP9: 11989.189 | AQ9: 12523.482 | AR9: 13038.449 | AS9: 13537.247 | AT9: 14020.734 | AU9: 14489.241 | AV9: 14943.68
A10: AUTO_TH_H01_1 | B10: 30996.094 | C10: 31493.746 | D10: 31999.389 | E10: 32682.553 | F10: 33303.577 | G10: 34123.091 | H10: 34832.554 | I10: 35442.44 | J10: 35666.707 | K10: 35752.795 | L10: 35831.214 | M10: 35758.831 | N10: 35777.117 | O10: 36052.554 | P10: 36351.842 | Q10: 36643.17 | R10: 36600.346 | S10: 36327.656 | T10: 35862.882 | U10: 35303.046 | V10: 34717.54 | W10: 34089.414 | X10: 33603.336 | Y10: 33144.55 | Z10: 32687.478 | AA10: 32214.345 | AB10: 31716.375 | AC10: 31194.269 | AD10: 30588.004 | AE10: 29943.351 | AF10: 29279.247 | AG10: 28556.896 | AH10: 27862.688 | AI10: 27183.688 | AJ10: 26515.057 | AK10: 25856.266 | AL10: 25207.155 | AM10: 24553.908 | AN10: 23903.284 | AO10: 23259.931 | AP10: 22626.034 | AQ10: 22003.139 | AR10: 21388.787 | AS10: 20786.154 | AT10: 20196.699 | AU10: 19621.317 | AV10: 19060.968
A11: AUTO_1 | B11: 30998.43 | C11: 31496.12 | D11: 32001.8 | E11: 32688.379 | F11: 33314.795 | G11: 34142.845 | H11: 34863.837 | I11: 35489.149 | J11: 35731.314 | K11: 35839.916 | L11: 35948.064 | M11: 35911.307 | N11: 35978.501 | O11: 36321.204 | P11: 36708.886 | Q11: 37113.744 | R11: 37189.816 | S11: 37044.828 | T11: 36737.421 | U11: 36371.366 | V11: 36014.156 | W11: 35646.664 | X11: 35505.388 | Y11: 35453.922 | Z11: 35461.314 | AA11: 35502.037 | AB11: 35559.231 | AC11: 35627.786 | AD11: 35599.183 | AE11: 35535.843 | AF11: 35460.489 | AG11: 35289.246 | AH11: 35178.229 | AI11: 35098.324 | AJ11: 35035 | AK11: 34982.466 | AL11: 34935.981 | AM11: 34867.313 | AN11: 34787.093 | AO11: 34702.398 | AP11: 34615.222 | AQ11: 34526.621 | AR11: 34427.236 | AS11: 34323.401 | AT11: 34217.433 | AU11: 34110.558 | AV11: 34004.648
A12: PENER_AUTOELEC_H01_CA_1 | B12: 0.25383749 | C12: 0.25891424 | D12: 0.25652822 | E12: 0.2632583 | F12: 0.26012564 | G12: 0.26053308 | H12: 0.26147498 | I12: 0.26226138 | J12: 0.26370216 | K12: 0.26522646 | L12: 0.26828614 | M12: 0.27155537 | N12: 0.27593021 | O12: 0.27923703 | P12: 0.28294175 | Q12: 0.28964151 | R12: 0.29904186 | S12: 0.3078615 | T12: 0.31713878 | U12: 0.32555112 | V12: 0.33650908 | W12: 0.34642302 | X12: 0.35276036 | Y12: 0.35910501 | Z12: 0.36546514 | AA12: 0.37201866 | AB12: 0.37859118 | AC12: 0.38504973 | AD12: 0.39391643 | AE12: 0.40306621 | AF12: 0.41202883 | AG12: 0.42361783 | AH12: 0.43285079 | AI12: 0.44221355 | AJ12: 0.45205593 | AK12: 0.46213309 | AL12: 0.47256152 | AM12: 0.48366692 | AN12: 0.49516768 | AO12: 0.50707924 | AP12: 0.51933954 | AQ12: 0.53195164 | AR12: 0.54516618 | AS12: 0.55887674 | AT12: 0.57277642 | AU12: 0.5869885 | AV12: 0.60153417
A13: PEXP_AUTO_H01_1 | B13: 0.96116878 | C13: 0.98039216 | D13: 0.98801884 | E13: 0.98669645 | F13: 1.0865767 | G13: 0.92641605 | H13: 1.006402 | I13: 1.1281116 | J13: 1.2272799 | K13: 1.2038813 | L13: 1.1516351 | M13: 1.0086765 | N13: 0.93008066 | O13: 1.0053342 | P13: 1.1682937 | Q13: 1.161239 | R13: 1.198542 | S13: 1.2390652 | T13: 1.2836593 | U13: 1.3335803 | V13: 1.3895946 | W13: 1.4519692 | X13: 1.4718601 | Y13: 1.4918798 | Z13: 1.5117038 | AA13: 1.531271 | AB13: 1.5505712 | AC13: 1.5692313 | AD13: 1.5876968 | AE13: 1.6059559 | AF13: 1.6239264 | AG13: 1.6416184 | AH13: 1.6590211 | AI13: 1.6759291 | AJ13: 1.6923399 | AK13: 1.7081466 | AL13: 1.723219 | AM13: 1.7530704 | AN13: 1.7834491 | AO13: 1.814317 | AP13: 1.8459358 | AQ13: 1.8784981 | AR13: 1.91551 | AS13: 1.9533956 | AT13: 1.9919377 | AU13: 2.0312262 | AV13: 2.0714168
... A44: BUIL_H01_CG_1 | B44: 1.8297097e+08 | C44: 1.8590863e+08 | D44: 188893454 | E44: 1.800399e+08 | F44: 1.7103185e+08 | G44: 1.6228071e+08 | H44: 154931207 | I44: 1.4786681e+08 | J44: 1.4048552e+08 | K44: 1.3272979e+08 | L44: 1.2536576e+08 | M44: 1.1900069e+08 | N44: 1.1407377e+08 | O44: 1.0969824e+08 | P44: 1.0510932e+08 | Q44: 99294803 | R44: 93330572 | S44: 87081895 | T44: 81129942 | U44: 75286529 | V44: 69986650 | W44: 64995939 | X44: 60709057 | Y44: 56928129 | Z44: 53527734 | AA44: 50429906 | AB44: 47582872 | AC44: 44950407 | AD44: 42505895 | AE44: 40223692 | AF44: 38084214 | AG44: 36074224 | AH44: 34181038 | AI44: 32393063 | AJ44: 30701659 | AK44: 29100207 | AL44: 27583327 | AM44: 26142497 | AN44: 24762422 | AO44: 23436976 | AP44: 22163575 | AQ44: 20941083 | AR44: 19768131 | AS44: 18642018 | AT44: 17561544 | AU44: 16526273 | AV44: 15536004
A45: BUIL_H01_DES_1 | C45: 2182612 | D45: 2217654.6 | E45: 2253259.7 | F45: 2197348 | G45: 2135517.6 | H45: 2073850.5 | I45: 2025887.2 | J45: 1978454.7 | K45: 1924316.5 | L45: 1863141.2 | M45: 1803611.1 | N45: 1753745.6 | O45: 1720550.5 | P45: 1692851.5 | Q45: 1659938.1 | R45: 1607861.2 | S45: 1600180.9 | T45: 1582221.9 | U45: 1561512.8 | V45: 1535440.8 | W45: 1511719.1 | X45: 1487546.1 | Y45: 1470747 | Z45: 1460304.2 | AA45: 1452832 | AB45: 1447319.2 | AC45: 1443131 | AD45: 1439867.2 | AE45: 1437276.5 | AF45: 1435067.5 | AG45: 1433032.4 | AH45: 1431077 | AI45: 1429083.9 | AJ45: 1426942.5 | AK45: 1424577.2 | AL45: 1421944.4 | AM45: 1419028.9 | AN45: 1415663.3 | AO45: 1411326.4 | AP45: 1405812 | AQ45: 1399061.6 | AR45: 1391084.8 | AS45: 1381880.2 | AT45: 1371366.7 | AU45: 1359546.5 | AV45: 1346479.4
A46: REHAB_H01_1 | B46: 27240235 | C46: 27677586 | D46: 28121958 | E46: 39354810 | F46: 45364406 | G46: 45516119 | H46: 35070344 | I46: 35012114 | J46: 39899401 | K46: 46533664 | L46: 46964548 | M46: 41281813 | N46: 28952518 | O46: 30282525 | P46: 37773608 | Q46: 62400636 | R46: 69799680 | S46: 83652349 | T46: 84518164 | U46: 92015110 | V46: 86066225 | W46: 86536359 | X46: 71165919 | Y46: 62420843 | Z46: 57576384 | AA46: 54921959 | AB46: 53550860 | AC46: 52854576 | AD46: 52471596 | AE46: 52426343 | AF46: 52572922 | AG46: 52697743 | AH46: 52897932 | AI46: 53137577 | AJ46: 53468504 | AK46: 53944496 | AL46: 54514948 | AM46: 55318467 | AN46: 56624760 | AO46: 58166785 | AP46: 59820487 | AQ46: 61506465 | AR46: 63217691 | AS46: 65025231 | AT46: 66858082 | AU46: 68601149 | AV46: 70221997
A47: PREHAB_H01_1 | B47: 0.00017092114 | C47: 0.00017433956 | D47: 0.00017633719 | E47: 0.00014003564 | F47: 0.00014683287 | G47: 0.00015141592 | H47: 0.00015511363 | I47: 0.00015050677 | J47: 0.00016363455 | K47: 0.00015928559 | L47: 0.00015397907 | M47: 0.00014433845 | N47: 0.00013845886 | O47: 0.00011055861 | P47: 0.00012352136 | Q47: 0.00011079756 | R47: 0.00013276872 | S47: 0.00011200677 | T47: 0.00013078063 | U47: 0.0001291518 | V47: 0.00015380977 | W47: 0.00014424135 | X47: 0.00018738453 | Y47: 0.00017601744 | Z47: 0.00017751826 | AA47: 0.00017875099 | AB47: 0.00017993094 | AC47: 0.00018126419 | AD47: 0.00018280753 | AE47: 0.00018462048 | AF47: 0.00018671268 | AG47: 0.00018906178 | AH47: 0.00019164298 | AI47: 0.00019446954 | AJ47: 0.00019749818 | AK47: 0.00020069703 | AL47: 0.00020406877 | AM47: 0.00020766518 | AN47: 0.00021169769 | AO47: 0.00021599659 | AP47: 0.00022047744 | AQ47: 0.00022511854 | AR47: 0.0002299376 | AS47: 0.00023497223 | AT47: 0.00024019504 | AU47: 0.00024559014 | AV47: 0.00025119817
A48: RENOV_VAL_1 | B48: 4655.932 | C48: 4825.2982 | D48: 4958.9473 | E48: 6685.0332 | F48: 8079.8942 | G48: 8204.6011 | H48: 6325.4515 | I48: 6303.711 | J48: 7395.6572 | K48: 8536.6752 | L48: 8693.9841 | M48: 7712.534 | N48: 5313.4787 | O48: 5170.6902 | P48: 6806.4049 | Q48: 11316.814 | R48: 13348.567 | S48: 15518.483 | T48: 16503.877 | U48: 17540.8 | V48: 16544.131 | W48: 15854.552 | X48: 13335.392 | Y48: 10987.157 | Z48: 10220.86 | AA48: 9817.3545 | AB48: 9635.4569 | AC48: 9580.6417 | AD48: 9592.2028 | AE48: 9678.9763 | AF48: 9816.0312 | AG48: 9963.1292 | AH48: 10137.517 | AI48: 10333.64 | AJ48: 10559.932 | AK48: 10826.5 | AL48: 11124.798 | AM48: 11487.719 | AN48: 11987.331 | AO48: 12563.827 | AP48: 13189.068 | AQ48: 13846.246 | AR48: 14536.124 | AS48: 15279.124 | AT48: 16058.979 | AU48: 16847.766 | AV48: 17639.637
A49: SUB_RENOV_VAL_1 | B49: 0 | C49: 0 | D49: 0 | E49: 1173.9571 | F49: 1418.9082 | G49: 1312.7362 | H49: 885.56321 | I49: 778.65691 | J49: 616.14297 | K49: 878.41651 | L49: 1198.0624 | M49: 1550.8859 | N49: 968.05518 | O49: 1025.6624 | P49: 872.60071 | Q49: 1541.5524 | R49: 1535.9671 | S49: 3033.2484 | T49: 2272.6217 | U49: 2415.4084 | V49: 0 | W49: 0 | X49: 0 | Y49: 0 | Z49: 0 | AA49: 0 | AB49: 0 | AC49: 0 | AD49: 0 | AE49: 0 | AF49: 0 | AG49: 0 | AH49: 0 | AI49: 0 | AJ49: 0 | AK49: 0 | AL49: 0 | AM49: 0 | AN49: 0 | AO49: 0 | AP49: 0 | AQ49: 0 | AR49: 0 | AS49: 0 | AT49: 0 | AU49: 0 | AV49: 0
A50: R_SUB_CEE_H01_CF_CA_1 | B50: 0 | C50: 0 | D50: 0 | E50: 0 | F50: 0 | G50: 0 | H50: 0 | I50: 0.040530719 | J50: 0.033883896 | K50: 0.028830481 | L50: 0.03040774 | M50: 0.02633315 | N50: 0.06336543 | O50: 0.15414461 | P50: 0.18628877 | Q50: 0.25284707 | R50: 0.19068605 | S50: 0.20076736 | T50: 0.19255578 | U50: 0.18479631 | V50: 0.19984759 | W50: 0.21271057 | X50: 0 | Y50: 0 | Z50: 0 | AA50: 0 | AB50: 0 | AC50: 0 | AD50: 0 | AE50: 0 | AF50: 0 | AG50: 0 | AH50: 0 | AI50: 0 | AJ50: 0 | AK50: 0 | AL50: 0 | AM50: 0 | AN50: 0 | AO50: 0 | AP50: 0 | AQ50: 0 | AR50: 0 | AS50: 0 | AT50: 0 | AU50: 0 | AV50: 0
A51: ER_TERTIARY_1 | B51: 21.072807 | C51: 21.411137 | D51: 21.7549 | E51: 23.111168 | F51: 23.885852 | G51: 23.444481 | H51: 24.603056 | I51: 25.441776 | J51: 25.783656 | K51: 26.232663 | L51: 27.090239 | M51: 28.31981 | N51: 27.949439 | O51: 27.547144 | P51: 26.801156 | Q51: 25.826825 | R51: 25.021981 | S51: 25.034436 | T51: 25.010957 | U51: 24.998994 | V51: 25.182672 | W51: 25.408836 | X51: 25.569184 | Y51: 25.682776 | Z51: 25.764489 | AA51: 25.819159 | AB51: 25.850019 | AC51: 25.861495 | AD51: 25.848674 | AE51: 25.8123 | AF51: 25.764021 | AG51: 25.701683 | AH51: 25.621796 | AI51: 25.529929 | AJ51: 25.42513 | AK51: 25.309382 | AL51: 25.183195 | AM51: 24.912207 | AN51: 24.615317 | AO51: 24.313775 | AP51: 24.0125 | AQ51: 23.712359 | AR51: 23.414926 | AS51: 23.119103 | AT51: 22.825638 | AU51: 22.534187 | AV51: 22.244617
A52: ER_TERTIARY_COAL_1 | B52: 0 | C52: 0 | D52: 0 | E52: 0 | F52: 0 | G52: 0 | H52: 0 | I52: 0 | J52: 0 | K52: 0 | L52: 0 | M52: 0 | N52: 0 | O52: 0 | P52: 0 | Q52: 0 | R52: 0 | S52: 0 | T52: 0 | U52: 0 | V52: 0 | W52: 0 | X52: 0 | Y52: 0 | Z52: 0 | AA52: 0 | AB52: 0 | AC52: 0 | AD52: 0 | AE52: 0 | AF52: 0 | AG52: 0 | AH52: 0 | AI52: 0 | AJ52: 0 | AK52: 0 | AL52: 0 | AM52: 0 | AN52: 0 | AO52: 0 | AP52: 0 | AQ52: 0 | AR52: 0 | AS52: 0 | AT52: 0 | AU52: 0 | AV52: 0
A53: ER_TERTIARY_OIL_1 | B53: 4.6065844 | C53: 4.6805446 | D53: 4.7556923 | E53: 4.8584285 | F53: 4.6740887 | G53: 4.613069 | H53: 4.5416749 | I53: 4.34262 | J53: 4.1268973 | K53: 4.0489182 | L53: 4.0627365 | M53: 4.1781675 | N53: 3.9170705 | O53: 3.6404446 | P53: 3.4042399 | Q53: 3.2198847 | R53: 3.0142307 | S53: 3.0092941 | T53: 3.0128964 | U53: 3.0144777 | V53: 2.9186239 | W53: 2.8147547 | X53: 2.7241297 | Y53: 2.6426243 | Z53: 2.5674745 | AA53: 2.4977719 | AB53: 2.4327476 | AC53: 2.3715018 | AD53: 2.3146738 | AE53: 2.2621251 | AF53: 2.2119048 | AG53: 2.1643703 | AH53: 2.1199207 | AI53: 2.0777417 | AJ53: 2.0380682 | AK53: 2.000482 | AL53: 1.9649022 | AM53: 1.9562959 | AN53: 1.9526402 | AO53: 1.9499118 | AP53: 1.9471789 | AQ53: 1.944281 | AR53: 1.9408812 | AS53: 1.9372527 | AT53: 1.9332059 | AU53: 1.9288109 | AV53: 1.9240909
A54: ER_TERTIARY_ELEC_1 | B54: 10.826676 | C54: 11.000502 | D54: 11.177119 | E54: 11.887835 | F54: 12.504639 | G54: 11.787154 | H54: 12.310258 | I54: 12.871045 | J54: 13.217653 | K54: 13.280641 | L54: 13.295465 | M54: 13.068313 | N54: 12.451329 | O54: 12.503449 | P54: 12.948172 | Q54: 12.810045 | R54: 12.634897 | S54: 12.736727 | T54: 12.766863 | U54: 12.803145 | V54: 13.078122 | W54: 13.396181 | X54: 13.614864 | Y54: 13.793156 | Z54: 13.941159 | AA54: 14.060246 | AB54: 14.15687 | AC54: 14.236272 | AD54: 14.302971 | AE54: 14.356875 | AF54: 14.400023 | AG54: 14.431494 | AH54: 14.456883 | AI54: 14.472666 | AJ54: 14.475275 | AK54: 14.468025 | AL54: 14.45054 | AM54: 14.31593 | AN54: 14.155715 | AO54: 13.989369 | AP54: 13.821598 | AQ54: 13.653065 | AR54: 13.486661 | AS54: 13.319006 | AT54: 13.152783 | AU54: 12.987435 | AV54: 12.822939
A55: ER_TERTIARY_GAS_1 | B55: 5.6395461 | C55: 5.7300908 | D55: 5.8220893 | E55: 6.3649049 | F55: 6.7071242 | G55: 7.0442581 | H55: 7.7511234 | I55: 8.2281112 | J55: 8.4391064 | K55: 8.9031038 | L55: 9.7320375 | M55: 11.07333 | N55: 11.581039 | O55: 11.403251 | P55: 10.448744 | Q55: 9.7968949 | R55: 9.3728535 | S55: 9.2884151 | T55: 9.2311979 | U55: 9.1813715 | V55: 9.1859254 | W55: 9.1979005 | X55: 9.23019 | Y55: 9.2469959 | Z55: 9.2558549 | AA55: 9.2611403 | AB55: 9.2604014 | AC55: 9.2537216 | AD55: 9.2310294 | AE55: 9.1932992 | AF55: 9.1520934 | AG55: 9.1058186 | AH55: 9.0449923 | AI55: 8.9795209 | AJ55: 8.9117866 | AK55: 8.8408747 | AL55: 8.7677531 | AM55: 8.6399813 | AN55: 8.5069617 | AO55: 8.3744945 | AP55: 8.243723 | AQ55: 8.1150126 | AR55: 7.9873832 | AS55: 7.8628446 | AT55: 7.7396486 | AU55: 7.6179417 | AV55: 7.4975879
A56: EMS_SEC_TOT_19_1 | B56: 20640521 | C56: 20971911 | D56: 21313933 | E56: 22206970 | F56: 21946561 | G56: 21680617 | H56: 22244065 | I56: 22089159 | J56: 21448171 | K56: 21467673 | L56: 22211890 | M56: 23793446 | N56: 23724535 | O56: 22820726 | P56: 21088588 | Q56: 19827775 | R56: 18787404 | S56: 18229321 | T56: 17715657 | U56: 17201328 | V56: 17463053 | W56: 17696752 | X56: 17435693 | Y56: 17173619 | Z56: 16913993 | AA56: 16657440 | AB56: 16402893 | AC56: 16164193 | AD56: 15917633 | AE56: 15664513 | AF56: 15411216 | AG56: 15159308 | AH56: 14950461 | AI56: 14742103 | AJ56: 14537324 | AK56: 14333466 | AL56: 14132316 | AM56: 13921122 | AN56: 13716845 | AO56: 13516877 | AP56: 13320356 | AQ56: 13127259 | AR56: 12934343 | AS56: 12745479 | AT56: 12558478 | AU56: 12373612 | AV56: 12190772
A57: EMS_SEC_TOT_20_1 | B57: 5733144.5 | C57: 5825191.9 | D57: 5919233.7 | E57: 6053525.2 | F57: 6003086.6 | G57: 6290808 | H57: 6414227.9 | I57: 6373952.7 | J57: 6246017.5 | K57: 6309819 | L57: 6515336.1 | M57: 6967670.1 | N57: 7036455.2 | O57: 6747901.3 | P57: 6121807.8 | Q57: 5688631.4 | R57: 5357163.9 | S57: 5121868.2 | T57: 4905286.8 | U57: 4687526.9 | V57: 4833942.8 | W57: 4962523.7 | X57: 4864708.3 | Y57: 4768675.8 | Z57: 4675395.5 | AA57: 4584687.6 | AB57: 4495960.4 | AC57: 4414549.3 | AD57: 4331124.2 | AE57: 4246093.9 | AF57: 4161693.2 | AG57: 4078459.1 | AH57: 4013103.9 | AI57: 3948242.1 | AJ57: 3884900.2 | AK57: 3822058.2 | AL57: 3760357.9 | AM57: 3694346.8 | AN57: 3630528.4 | AO57: 3568076 | AP57: 3506723.1 | AQ57: 3446479.2 | AR57: 3386205.8 | AS57: 3327271.8 | AT57: 3268927.7 | AU57: 3211270.8 | AV57: 3154268.5
... A562: I_MDE_14_1 | B562: 528.06275 | C562: 536.54097 | D562: 509.09232 | E562: 725.67716 | F562: 692.31355 | G562: 505.49928 | H562: 764.92789 | I562: 921.48445 | J562: 889.35546 | K562: 842.51177 | L562: 822.04169 | M562: 863.35214 | N562: 479.51703 | O562: 841.13881 | P562: 899.10766 | Q562: 753.75232 | R562: 852.06465 | S562: 6504.2346 | T562: 5016.7551 | U562: 5365.7591 | V562: 4493.54 | W562: 3994.514 | X562: 4689.3872 | Y562: 4755.3001 | Z562: 4826.4177 | AA562: 4782.2808 | AB562: 4830.0905 | AC562: 4829.267 | AD562: 4751.7322 | AE562: 4833.641 | AF562: 4916.221 | AG562: 4917.6575 | AH562: 5111.2441 | AI562: 5173.9206 | AJ562: 5125.9716 | AK562: 5153.3403 | AL562: 5157.9294 | AM562: 5196.7662 | AN562: 5247.5903 | AO562: 5224.3293 | AP562: 5239.3607 | AQ562: 5250.4846 | AR562: 5278.8864 | AS562: 5319.2347 | AT562: 5362.2643 | AU562: 5383.0866 | AV562: 5421.9021
A563: I_MDE_15_1 | C563: 25.563692 | D563: 27.174516 | E563: 59.014301 | F563: 62.266563 | G563: 66.091101 | H563: 70.100616 | I563: 75.499498 | J563: 75.503546 | K563: 76.823477 | L563: 85.080937 | M563: 75.917302 | N563: 53.370951 | O563: 87.446867 | P563: 94.174744 | Q563: 232.53303 | R563: 297.98834 | S563: 401.08835 | T563: 353.0158 | U563: 304.43347 | V563: 270.61017 | W563: 742.62923 | X563: 680.48022 | Y563: 697.19692 | Z563: 722.97782 | AA563: 747.34089 | AB563: 771.66041 | AC563: 826.85488 | AD563: 834.65145 | AE563: 871.7986 | AF563: 905.1375 | AG563: 914.57744 | AH563: 803.99839 | AI563: 824.32767 | AJ563: 846.44997 | AK563: 870.55733 | AL563: 893.6645 | AM563: 699.92397 | AN563: 714.94252 | AO563: 728.334 | AP563: 740.6741 | AQ563: 751.75805 | AR563: 611.47624 | AS563: 614.95113 | AT563: 617.72457 | AU563: 620.31598 | AV563: 624.90315
A564: I_MDE_16_1 | C564: 32.611451 | D564: 37.137185 | E564: 37.560493 | F564: 59.347566 | G564: 80.304664 | H564: 101.93379 | I564: 120.87487 | J564: 153.7942 | K564: 186.91817 | L564: 217.76751 | M564: 263.26599 | N564: 260.33005 | O564: 337.82378 | P564: 334.0845 | Q564: 416.89997 | R564: 452.97004 | S564: 1333.6678 | T564: 1193.0527 | U564: 1131.8637 | V564: 997.63448 | W564: 2781.0417 | X564: 3554.4028 | Y564: 3794.0071 | Z564: 4026.8878 | AA564: 4267.5324 | AB564: 4524.7079 | AC564: 5723.7094 | AD564: 6034.1034 | AE564: 6369.2728 | AF564: 6708.0625 | AG564: 7065.57 | AH564: 6684.5884 | AI564: 7021.4955 | AJ564: 7379.8842 | AK564: 7738.4065 | AL564: 8090.0374 | AM564: 6315.886 | AN564: 6573.007 | AO564: 6760.6486 | AP564: 6973.225 | AQ564: 7154.8571 | AR564: 5882.0359 | AS564: 5934.6851 | AT564: 6010.1736 | AU564: 6084.3229 | AV564: 6189.2132
A565: I_MDE_17_1 | B565: 534.35075 | C565: 542.92993 | D565: 546.81091 | E565: 569.83881 | F565: 606.47755 | G565: 368.21115 | H565: 525.58189 | I565: 605.3048 | J565: 589.55305 | K565: 581.06324 | L565: 586.84064 | M565: 640.91957 | N565: 605.51066 | O565: 716.90508 | P565: 776.56361 | Q565: 732.32542 | R565: 712.94488 | S565: 687.30827 | T565: 692.54602 | U565: 708.23915 | V565: 716.52052 | W565: 722.53176 | X565: 722.63608 | Y565: 729.38726 | Z565: 738.3557 | AA565: 747.77576 | AB565: 758.23405 | AC565: 766.70001 | AD565: 776.04097 | AE565: 786.47305 | AF565: 798.07382 | AG565: 811.04756 | AH565: 825.8568 | AI565: 842.1083 | AJ565: 858.86135 | AK565: 876.51073 | AL565: 894.3283 | AM565: 913.94677 | AN565: 933.79361 | AO565: 953.3311 | AP565: 972.94737 | AQ565: 992.51623 | AR565: 1012.8738 | AS565: 1033.1152 | AT565: 1053.8184 | AU565: 1074.8286 | AV565: 1096.5855
A566: I_MDE_18_1 | B566: 970.42802 | C566: 986.00856 | D566: 991.19398 | E566: 1069.1726 | F566: 1193.4499 | G566: 752.11733 | H566: 1072.1105 | I566: 1256.8962 | J566: 1230.0432 | K566: 1187.1796 | L566: 1113.3729 | M566: 1149.7972 | N566: 1051.2057 | O566: 1345.4529 | P566: 1484.6629 | Q566: 1386.3185 | R566: 1345.9331 | S566: 1313.5488 | T566: 1307.8935 | U566: 1312.1658 | V566: 1329.1598 | W566: 1341.4787 | X566: 1296.8359 | Y566: 1287.9037 | Z566: 1292.9133 | AA566: 1299.6553 | AB566: 1306.6876 | AC566: 1309.9035 | AD566: 1311.1313 | AE566: 1314.8671 | AF566: 1320.2512 | AG566: 1327.222 | AH566: 1337.537 | AI566: 1349.2907 | AJ566: 1359.5044 | AK566: 1370.5454 | AL566: 1380.5823 | AM566: 1405.1601 | AN566: 1419.0006 | AO566: 1430.2082 | AP566: 1441.1104 | AQ566: 1451.1328 | AR566: 1452.7581 | AS566: 1459.2587 | AT566: 1466.4956 | AU566: 1473.4788 | AV566: 1480.8595
A567: ER_COAL_1 | B567: 5.570579 | C567: 5.6600164 | D567: 5.7508898 | E567: 5.7929036 | F567: 4.8242806 | G567: 4.2185211 | H567: 4.084085 | I567: 3.8991141 | J567: 3.7615492 | K567: 4.0026494 | L567: 4.0988615 | M567: 4.1630921 | N567: 3.2553048 | O567: 2.7334405 | P567: 2.3991506 | Q567: 2.1834951 | R567: 1.9973772 | S567: 2.0030384 | T567: 1.9618528 | U567: 1.9451373 | V567: 1.91255 | W567: 1.8640023 | X567: 1.8554258 | Y567: 1.8721113 | Z567: 1.8944213 | AA567: 1.9199594 | AB567: 1.9494204 | AC567: 1.9504081 | AD567: 1.9567921 | AE567: 1.9647827 | AF567: 1.9740917 | AG567: 1.986342 | AH567: 2.0001071 | AI567: 2.0145604 | AJ567: 2.03095 | AK567: 2.0482868 | AL567: 2.065978 | AM567: 2.0579387 | AN567: 2.046346 | AO567: 2.0317768 | AP567: 2.0159639 | AQ567: 1.9975455 | AR567: 1.9951071 | AS567: 1.994435 | AT567: 1.993777 | AU567: 1.9927857 | AV567: 1.9924393
A568: ER_OIL_2201_1 | B568: 77.477679 | C568: 78.721608 | D568: 80.00373 | E568: 80.189475 | F568: 76.950267 | G568: 74.603074 | H568: 73.063966 | I568: 71.285518 | J568: 69.186514 | K568: 67.614613 | L568: 67.318829 | M568: 67.648774 | N568: 66.103925 | O568: 64.464309 | P568: 62.191245 | Q568: 60.914616 | R568: 59.282102 | S568: 58.819585 | T568: 57.857999 | U568: 57.140669 | V568: 56.29937 | W568: 55.173092 | X568: 54.512926 | Y568: 54.128834 | Z568: 53.856553 | AA568: 53.650891 | AB568: 53.520664 | AC568: 52.960715 | AD568: 52.421773 | AE568: 51.903042 | AF568: 51.398656 | AG568: 50.908673 | AH568: 50.535956 | AI568: 50.189798 | AJ568: 49.874339 | AK568: 49.581325 | AL568: 49.301862 | AM568: 49.002877 | AN568: 48.708631 | AO568: 48.40791 | AP568: 48.115104 | AQ568: 47.81666 | AR568: 47.695796 | AS568: 47.592621 | AT568: 47.501982 | AU568: 47.421731 | AV568: 47.369434
A569: ER_OIL_2202_1 | B569: 0.67805251 | C569: 0.68893886 | D569: 0.66746531 | E569: 1.0023107 | F569: 1.2829737 | G569: 1.5564776 | H569: 1.8318169 | I569: 2.0884318 | J569: 2.3204771 | K569: 2.555809 | L569: 2.832603 | M569: 3.1370651 | N569: 3.1170784 | O569: 3.0934185 | P569: 3.0395931 | Q569: 3.0350888 | R569: 3.0141586 | S569: 3.1567748 | T569: 3.2641188 | U569: 3.3763985 | V569: 3.4835503 | W569: 3.5749335 | X569: 3.53197 | Y569: 3.5068862 | Z569: 3.4890369 | AA569: 3.4766189 | AB569: 3.4691425 | AC569: 3.4297875 | AD569: 3.3916918 | AE569: 3.3547916 | AF569: 3.3191882 | AG569: 3.2843966 | AH569: 3.2618467 | AI569: 3.2410665 | AJ569: 3.2223303 | AK569: 3.2045297 | AL569: 3.1876547 | AM569: 3.1804792 | AN569: 3.1739363 | AO569: 3.1673155 | AP569: 3.1615781 | AQ569: 3.155859 | AR569: 3.1642321 | AS569: 3.1740729 | AT569: 3.1850647 | AU569: 3.1970877 | AV569: 3.2113558
A570: ER_ELEC_2301_1 | B570: 28.634797 | C570: 29.094538 | D570: 29.720948 | E570: 30.52551 | F570: 31.195934 | G570: 29.010321 | H570: 30.081874 | I570: 31.084929 | J570: 31.401742 | K570: 31.225922 | L570: 31.043343 | M570: 30.417636 | N570: 28.689727 | O570: 28.16767 | P570: 28.076537 | Q570: 27.095231 | R570: 26.128889 | S570: 26.107046 | T570: 25.987033 | U570: 25.997111 | V570: 26.913215 | W570: 27.877809 | X570: 27.952276 | Y570: 28.069737 | Z570: 28.203491 | AA570: 28.418866 | AB570: 28.658586 | AC570: 28.348215 | AD570: 28.057527 | AE570: 27.770024 | AF570: 27.456182 | AG570: 27.149444 | AH570: 26.764746 | AI570: 26.379998 | AJ570: 25.989665 | AK570: 25.565523 | AL570: 25.132998 | AM570: 24.670229 | AN570: 24.203396 | AO570: 23.728973 | AP570: 23.253397 | AQ570: 22.772367 | AR570: 22.171953 | AS570: 21.561739 | AT570: 20.949909 | AU570: 20.33612 | AV570: 19.727952
A571: ER_ELEC_2302_1 | B571: 0.3674935 | C571: 0.37339372 | D571: 0.38143295 | E571: 0.37117253 | F571: 0.35939186 | G571: 0.31665047 | H571: 0.31109271 | I571: 0.30457354 | J571: 0.29150996 | K571: 0.27464537 | L571: 0.25869191 | M571: 0.24015806 | N571: 0.20849842 | O571: 0.18561328 | P571: 0.16441312 | Q571: 0.13707606 | R571: 0.1094941 | S571: 0.14544881 | T571: 0.18182678 | U571: 0.22018257 | V571: 0.23134827 | W571: 0.2427947 | X571: 0.24194868 | Y571: 0.24145254 | Z571: 0.24107083 | AA571: 0.2413657 | AB571: 0.24183777 | AC571: 0.24700557 | AD571: 0.25232996 | AE571: 0.25767409 | AF571: 0.26319354 | AG571: 0.26877911 | AH571: 0.26840178 | AI571: 0.26803281 | AJ571: 0.26761562 | AK571: 0.26702013 | AL571: 0.26634458 | AM571: 0.27117357 | AN571: 0.27597204 | AO571: 0.28069402 | AP571: 0.28540923 | AQ571: 0.29006176 | AR571: 0.29179369 | AS571: 0.2933964 | AT571: 0.29497158 | AU571: 0.29651137 | AV571: 0.29812658
A572: ER_ELEC_2303_1 | B572: 1.4676116 | C572: 1.4911746 | D572: 1.5232798 | E572: 1.5667914 | F572: 1.6035313 | G572: 1.4933554 | H572: 1.5507677 | I572: 1.6048075 | J572: 1.6235214 | K572: 1.6167793 | L572: 1.6096637 | M572: 1.5795135 | N572: 1.6684922 | O572: 1.8274882 | P572: 2.0258946 | Q572: 2.1692357 | R572: 2.3169547 | S572: 2.2378991 | T572: 2.1483525 | U572: 2.0672767 | V572: 1.3717159 | W572: 0.70932612 | X572: 0.71216301 | Y572: 0.71610931 | Z572: 0.72048751 | AA572: 0.7269392 | AB572: 0.7340318 | AC572: 0.74108576 | AD572: 0.74862553 | AE572: 0.75623314 | AF572: 0.76393767 | AG572: 0.77183605 | AH572: 0.77970675 | AI572: 0.78762463 | AJ572: 0.79542249 | AK572: 0.80311017 | AL572: 0.81057558 | AM572: 0.81637412 | AN572: 0.82206829 | AO572: 0.82752611 | AP572: 0.83295831 | AQ572: 0.83820422 | AR572: 1.1515195 | AS572: 1.4643167 | AT572: 1.7768059 | AU572: 2.0888496 | AV572: 2.4012366
A573: ER_ELEC_2304_1 | B573: 1.4643634 | C573: 1.4878742 | D573: 1.5199084 | E573: 1.4374556 | F573: 1.3527148 | G573: 1.1583439 | H573: 1.1060293 | I573: 1.0524182 | J573: 0.97896903 | K573: 0.89641111 | L573: 0.82061072 | M573: 0.74040767 | N573: 0.62013914 | O573: 0.52598398 | P573: 0.43486356 | Q573: 0.32594416 | R573: 0.21581314 | S573: 0.2083253 | T573: 0.19985741 | U573: 0.19217359 | V573: 0.12628916 | W573: 0.063535037 | X573: 0.06376655 | Y573: 0.064097062 | Z573: 0.064465845 | AA573: 0.065019861 | AB573: 0.065630757 | AC573: 0.066244766 | AD573: 0.066902231 | AE573: 0.067565777 | AF573: 0.068236798 | AG573: 0.068925139 | AH573: 0.06962487 | AI573: 0.070328805 | AJ573: 0.071022017 | AK573: 0.071705229 | AL573: 0.072368589 | AM573: 0.072883283 | AN573: 0.073388656 | AO573: 0.073872926 | AP573: 0.074354907 | AQ573: 0.074820258 | AR573: 0.075005586 | AS573: 0.075157705 | AT573: 0.075302916 | AU573: 0.075439288 | AV573: 0.075595007
A574: ER_ELEC_2305_1 | B574: 0.29584764 | C574: 0.30059757 | D574: 0.30706949 | E574: 0.65474226 | F574: 0.98938789 | G574: 1.1913305 | H574: 1.4861652 | I574: 1.7591862 | J574: 1.9607947 | K574: 2.0825344 | L574: 2.1417785 | M574: 2.0949807 | N574: 2.2292512 | O574: 2.4570621 | P574: 2.7386938 | Q574: 2.946486 | R574: 3.1604122 | S574: 3.3567812 | T574: 3.5458839 | U574: 3.7586318 | V574: 4.1643559 | W574: 4.5666652 | X574: 4.9020657 | Y574: 5.249818 | Z574: 5.6061819 | AA574: 5.8748008 | AB574: 6.1527722 | AC574: 6.5163186 | AD574: 6.8835649 | AE574: 7.2511015 | AF574: 7.6348685 | AG574: 8.0205018 | AH574: 8.4223877 | AI574: 8.8255907 | AJ574: 9.2282065 | AK574: 9.6440123 | AL574: 10.057781 | AM574: 10.467129 | AN574: 10.875616 | AO574: 11.281307 | AP574: 11.686869 | AQ574: 12.089951 | AR574: 12.463137 | AS574: 12.830797 | AT574: 13.197085 | AU574: 13.561564 | AV574: 13.929308
A575: ER_ELEC_2306_1 | B575: 0.066565719 | C575: 0.067634453 | D575: 0.069090634 | E575: 0.094406599 | F575: 0.12835723 | G575: 0.15880266 | H575: 0.2190751 | I575: 0.30117639 | J575: 0.40476942 | K575: 0.53549095 | L575: 0.70825272 | M575: 0.92326874 | N575: 0.98244244 | O575: 1.0828398 | P575: 1.2069564 | Q575: 1.2985315 | R575: 1.3928099 | S575: 1.4590186 | T575: 1.5215543 | U575: 1.5937024 | V575: 1.729023 | W575: 1.8642962 | X575: 2.0139216 | Y575: 2.1687981 | Z575: 2.3274237 | AA575: 2.4942688 | AB575: 2.6661025 | AC575: 3.0100168 | AD575: 3.3553066 | AE575: 3.7005517 | AF575: 4.0619751 | AG575: 4.424355 | AH575: 4.8027681 | AI575: 5.1823126 | AJ575: 5.5618564 | AK575: 5.9555087 | AL575: 6.3481706 | AM575: 6.7445158 | AN575: 7.1404956 | AO575: 7.5347667 | AP575: 7.9290336 | AQ575: 8.3216652 | AR575: 8.5285861 | AS575: 8.7317261 | AT575: 8.9339597 | AU575: 9.1350029 | AV575: 9.3382736
A576: ER_ELEC_2307_1 | B576: 3.3276745 | C576: 3.3811014 | D576: 3.4538971 | E576: 3.422464 | F576: 3.3744515 | G576: 3.0275196 | H576: 3.0287857 | I576: 3.0195538 | J576: 2.9429024 | K576: 2.8233624 | L576: 2.7080026 | M576: 2.5599724 | N576: 2.724045 | O576: 3.0024196 | P576: 3.3465609 | Q576: 3.6004737 | R576: 3.8618819 | S576: 4.0825224 | T576: 4.2938366 | U576: 4.5332765 | V576: 4.4446352 | W576: 4.3739256 | X576: 4.38942 | Y576: 4.4117225 | Z576: 4.4366515 | AA576: 4.4751461 | AB576: 4.5175626 | AC576: 4.5578142 | AD576: 4.6010596 | AE576: 4.6447253 | AF576: 4.6891854 | AG576: 4.7348361 | AH576: 4.7814856 | AI576: 4.8284204 | AJ576: 4.8746155 | AK576: 4.9202875 | AL576: 4.964595 | AM576: 4.9988467 | AN576: 5.0324577 | AO576: 5.0646205 | AP576: 5.0966257 | AQ576: 5.1274907 | AR576: 5.1397733 | AS576: 5.1497803 | AT576: 5.1593142 | AU576: 5.1682428 | AV576: 5.1784972
... A583: ER_GAS_2406_1 | B583: 0.38745858 | C583: 0.39367935 | D583: 0.40215282 | E583: 0.52785941 | F583: 0.66903135 | G583: 0.83514647 | H583: 1.1121051 | I583: 1.4449534 | J583: 1.8084917 | K583: 2.3104359 | L583: 3.027959 | M583: 4.0451221 | N583: 3.8683427 | O583: 3.5934692 | P583: 3.159847 | Q583: 2.8020055 | R583: 2.4914822 | S583: 2.9844098 | T583: 3.4745633 | U583: 3.98735 | V583: 3.447689 | W583: 2.9427683 | X583: 3.1004591 | Y583: 3.2764051 | Z583: 3.4641104 | AA583: 3.6707588 | AB583: 3.8907546 | AC583: 4.0265617 | AD583: 4.1650648 | AE583: 4.3033466 | AF583: 4.450475 | AG583: 4.6019081 | AH583: 4.694793 | AI583: 4.7890942 | AJ583: 4.8861441 | AK583: 4.987523 | AL583: 5.0900604 | AM583: 5.1731211 | AN583: 5.257352 | AO583: 5.339647 | AP583: 5.4212945 | AQ583: 5.5007027 | AR583: 5.6247147 | AS583: 5.7489807 | AT583: 5.8727825 | AU583: 5.9960963 | AV583: 6.1213229
A584: CU_MWH_PGDP_21_1 | C584: 0.70669314 | D584: 0.71066547 | E584: 0.70761269 | F584: 0.78087648 | G584: 0.79873526 | H584: 0.78948766 | I584: 0.85369216 | J584: 0.86082471 | K584: 0.81643942 | L584: 0.77210169 | M584: 0.69788597 | N584: 0.71071358 | O584: 0.770476 | P584: 0.84912354 | Q584: 1.3316156 | R584: 1.2506507 | S584: 1.3466477 | T584: 1.3451529 | U584: 1.333578 | V584: 1.3223564 | W584: 1.3132803 | X584: 0.4637076 | Y584: 0.45814773 | Z584: 0.45776892 | AA584: 0.45897758 | AB584: 0.4601343 | AC584: 0.46519951 | AD584: 0.46856869 | AE584: 0.47172697 | AF584: 0.47471643 | AG584: 0.4774599 | AH584: 0.48043506 | AI584: 0.48345003 | AJ584: 0.48621236 | AK584: 0.48892945 | AL584: 0.49166153 | AM584: 0.50082997 | AN584: 0.51100006 | AO584: 0.52185712 | AP584: 0.53311016 | AQ584: 0.54505977 | AR584: 0.55246078 | AS584: 0.55938196 | AT584: 0.56639029 | AU584: 0.57357906 | AV584: 0.58074569
A585: CU_MWH_PGDP_22_1 | C585: 51.523121 | D585: 51.626149 | E585: 51.596122 | F585: 59.336701 | G585: 47.327293 | H585: 54.508285 | I585: 61.89053 | J585: 67.54747 | K585: 64.382134 | L585: 59.392643 | M585: 51.054452 | N585: 46.551465 | O585: 51.358778 | P585: 58.886407 | Q585: 55.655135 | R585: 56.738522 | S585: 58.516815 | T585: 60.730894 | U585: 62.980972 | V585: 65.325815 | W585: 68.141277 | X585: 66.221372 | Y585: 64.751069 | Z585: 63.323704 | AA585: 61.927756 | AB585: 60.543753 | AC585: 59.414529 | AD585: 58.275584 | AE585: 57.154689 | AF585: 56.054723 | AG585: 54.974981 | AH585: 53.84073 | AI585: 52.708844 | AJ585: 51.589753 | AK585: 50.489676 | AL585: 49.407622 | AM585: 48.849232 | AN585: 48.331056 | AO585: 47.914424 | AP585: 48.248057 | AQ585: 48.733869 | AR585: 49.181871 | AS585: 49.625707 | AT585: 50.062908 | AU585: 50.4952 | AV585: 50.934323
A586: CU_MWH_PGDP_23_1 | C586: 73.266064 | D586: 73.287457 | E586: 73.523895 | F586: 74.737482 | G586: 75.53518 | H586: 75.492773 | I586: 76.999871 | J586: 78.533378 | K586: 79.171262 | L586: 79.525782 | M586: 79.915427 | N586: 81.451333 | O586: 83.00474 | P586: 84.493242 | Q586: 87.018954 | R586: 87.870637 | S586: 90.961766 | T586: 94.553941 | U586: 98.260081 | V586: 96.461112 | W586: 94.566556 | X586: 91.924606 | Y586: 91.156237 | Z586: 90.409777 | AA586: 89.883575 | AB586: 89.367138 | AC586: 89.825398 | AD586: 90.186703 | AE586: 90.562061 | AF586: 90.900934 | AG586: 91.215015 | AH586: 91.501977 | AI586: 91.79942 | AJ586: 92.056576 | AK586: 92.288189 | AL586: 92.498 | AM586: 92.615498 | AN586: 92.706097 | AO586: 92.76589 | AP586: 92.806509 | AQ586: 92.837237 | AR586: 92.767549 | AS586: 92.753693 | AT586: 92.760484 | AU586: 92.776524 | AV586: 92.792618
A587: CU_MWH_PGDP_24_1 | C587: 47.351267 | D587: 47.174037 | E587: 46.127939 | F587: 50.150751 | G587: 42.222375 | H587: 44.063508 | I587: 47.233788 | J587: 50.160538 | K587: 47.460644 | L587: 43.549028 | M587: 38.68259 | N587: 35.696775 | O587: 37.739849 | P587: 41.325781 | Q587: 40.955972 | R587: 40.830206 | S587: 41.295639 | T587: 41.740396 | U587: 42.309431 | V587: 44.666532 | W587: 47.28152 | X587: 44.33748 | Y587: 43.961286 | Z587: 43.676614 | AA587: 43.386938 | AB587: 43.082507 | AC587: 43.000784 | AD587: 42.871274 | AE587: 42.75294 | AF587: 42.623907 | AG587: 42.498661 | AH587: 42.467946 | AI587: 42.403165 | AJ587: 42.303527 | AK587: 42.207964 | AL587: 42.112735 | AM587: 42.036605 | AN587: 41.882098 | AO587: 41.720644 | AP587: 41.570638 | AQ587: 41.437595 | AR587: 41.396806 | AS587: 41.350241 | AT587: 41.312266 | AU587: 41.276885 | AV587: 41.239912
A588: CU_MWH_PGDP_2201_1 | C588: 51.430588 | D588: 51.510911 | E588: 51.457245 | F588: 59.216846 | G588: 46.898524 | H588: 54.12867 | I588: 61.634867 | J588: 67.419762 | K588: 64.109193 | L588: 58.892801 | M588: 50.133656 | N588: 45.350583 | O588: 50.347655 | P588: 58.183525 | Q588: 54.757653 | R588: 55.916192 | S588: 57.783061 | T588: 60.069897 | U588: 62.421927 | V588: 64.904976 | W588: 67.892437 | X588: 65.900788 | Y588: 64.392018 | Z588: 62.924898 | AA588: 61.488092 | AB588: 60.06337 | AC588: 58.891035 | AD588: 57.713248 | AE588: 56.555294 | AF588: 55.42034 | AG588: 54.307533 | AH588: 53.142874 | AI588: 51.981726 | AJ588: 50.835861 | AK588: 49.711219 | AL588: 48.606626 | AM588: 48.051611 | AN588: 47.535738 | AO588: 47.121497 | AP588: 47.444605 | AQ588: 47.914039 | AR588: 48.352317 | AS588: 48.787232 | AT588: 49.21687 | AU588: 49.642716 | AV588: 50.075932
A589: CU_MWH_PGDP_2202_1 | C589: 62.329864 | D589: 65.743951 | E589: 62.954793 | F589: 66.694178 | G589: 68.346705 | H589: 70.005365 | I589: 70.838366 | J589: 71.453553 | K589: 71.794935 | L589: 71.59253 | M589: 71.466917 | N589: 72.747892 | O589: 73.049982 | P589: 73.700716 | Q589: 74.227499 | R589: 73.423756 | S589: 72.626929 | T589: 72.833013 | U589: 72.76333 | V589: 72.365482 | W589: 72.120645 | X589: 71.352765 | Y589: 70.503195 | Z589: 69.718983 | AA589: 68.983297 | AB589: 68.258709 | AC589: 67.835865 | AD589: 67.3378 | AE589: 66.832051 | AF589: 66.315443 | AG589: 65.791186 | AH589: 65.154923 | AI589: 64.50298 | AJ589: 63.823762 | AK589: 63.130203 | AL589: 62.42215 | AM589: 61.772614 | AN589: 61.179785 | AO589: 60.685794 | AP589: 61.148082 | AQ589: 61.853616 | AR589: 62.40166 | AS589: 62.930353 | AT589: 63.428751 | AU589: 63.902581 | AV589: 64.37253
A590: CU_MWH_PGDP_2301_1 | C590: 71.19287 | D590: 71.262191 | E590: 71.600931 | F590: 72.023889 | G590: 73.161614 | H590: 72.488175 | I590: 73.442578 | J590: 74.696516 | K590: 75.301714 | L590: 75.386446 | M590: 75.434222 | N590: 76.969093 | O590: 78.187941 | P590: 79.406407 | Q590: 81.846331 | R590: 82.499261 | S590: 85.979009 | T590: 90.30006 | U590: 94.797854 | V590: 93.408481 | W590: 92.297534 | X590: 90.085546 | Y590: 89.406368 | Z590: 88.787493 | AA590: 88.390415 | AB590: 88.096261 | AC590: 88.778069 | AD590: 89.206918 | AE590: 89.682731 | AF590: 90.210008 | AG590: 90.756266 | AH590: 91.306818 | AI590: 91.854864 | AJ590: 92.415566 | AK590: 93.02518 | AL590: 93.644673 | AM590: 94.087488 | AN590: 94.525596 | AO590: 94.975487 | AP590: 95.436209 | AQ590: 95.912657 | AR590: 96.105632 | AS590: 96.246723 | AT590: 96.406366 | AU590: 96.59867 | AV590: 96.817072
A591: CU_MWH_PGDP_2302_1 | C591: 223.60228 | D591: 224.26164 | E591: 226.83095 | F591: 237.27446 | G591: 228.70146 | H591: 240.10938 | I591: 253.90276 | J591: 268.04407 | K591: 269.05636 | L591: 264.10162 | M591: 252.04652 | N591: 252.63778 | O591: 266.111 | P591: 288.18067 | Q591: 303.17188 | R591: 325.14702 | S591: 295.34225 | T591: 292.69359 | U591: 297.73489 | V591: 298.97988 | W591: 299.86598 | X591: 296.85263 | Y591: 294.16019 | Z591: 291.60126 | AA591: 289.39319 | AB591: 287.33501 | AC591: 286.81222 | AD591: 286.84222 | AE591: 286.98408 | AF591: 287.14039 | AG591: 287.368 | AH591: 288.70683 | AI591: 289.35154 | AJ591: 289.91364 | AK591: 290.55473 | AL591: 291.18797 | AM591: 296.03715 | AN591: 302.11412 | AO591: 308.72062 | AP591: 315.9228 | AQ591: 323.80374 | AR591: 328.13233 | AS591: 332.48334 | AT591: 337.05309 | AU591: 341.83931 | AV591: 346.84091
A592: CU_MWH_PGDP_2303_1 | C592: 76.782812 | D592: 76.069556 | E592: 75.682599 | F592: 76.81299 | G592: 76.570663 | H592: 78.357733 | I592: 80.00255 | J592: 82.211024 | K592: 82.487925 | L592: 81.406417 | M592: 79.776156 | N592: 79.214901 | O592: 81.241437 | P592: 84.625438 | Q592: 89.000255 | R592: 90.761912 | S592: 94.586054 | T592: 97.403133 | U592: 100.27968 | V592: 108.72379 | W592: 121.40632 | X592: 109.61261 | Y592: 108.37195 | Z592: 108.44273 | AA592: 108.65822 | AB592: 108.60465 | AC592: 109.36155 | AD592: 109.91835 | AE592: 110.48729 | AF592: 111.03347 | AG592: 111.61631 | AH592: 112.31757 | AI592: 113.03662 | AJ592: 113.74406 | AK592: 114.45109 | AL592: 115.16528 | AM592: 117.4601 | AN592: 119.87777 | AO592: 122.42889 | AP592: 125.13348 | AQ592: 128.01519 | AR592: 123.14471 | AS592: 124.26689 | AT592: 125.79261 | AU592: 127.07958 | AV592: 128.18055
A593: CU_MWH_PGDP_2304_1 | C593: 108.14911 | D593: 107.91407 | E593: 108.8986 | F593: 125.40348 | G593: 117.63549 | H593: 126.62323 | I593: 137.30744 | J593: 136.02972 | K593: 126.00984 | L593: 124.34507 | M593: 122.71598 | N593: 128.92526 | O593: 145.7336 | P593: 155.3261 | Q593: 150.72944 | R593: 164.20778 | S593: 166.23601 | T593: 177.26515 | U593: 192.45235 | V593: 220.69091 | W593: 269.27172 | X593: 246.7288 | Y593: 242.87545 | Z593: 241.33331 | AA593: 239.93029 | AB593: 238.31153 | AC593: 238.62812 | AD593: 238.5221 | AE593: 238.49058 | AF593: 238.57837 | AG593: 238.77772 | AH593: 239.09042 | AI593: 239.49354 | AJ593: 239.70968 | AK593: 239.96654 | AL593: 240.22875 | AM593: 246.95062 | AN593: 254.29245 | AO593: 262.25115 | AP593: 270.97144 | AQ593: 280.54208 | AR593: 285.46853 | AS593: 290.73105 | AT593: 296.26542 | AU593: 302.05988 | AV593: 308.13294
A594: CU_MWH_PGDP_2305_1 | C594: 96.989308 | D594: 97.273808 | E594: 81.568498 | F594: 85.132922 | G594: 88.757148 | H594: 88.669425 | I594: 89.720553 | J594: 90.999895 | K594: 91.802699 | L594: 92.450859 | M594: 93.608878 | N594: 93.744886 | O594: 95.309502 | P594: 97.011933 | Q594: 99.960571 | R594: 101.00163 | S594: 101.25256 | T594: 101.2833 | U594: 101.41867 | V594: 94.716495 | W594: 89.093826 | X594: 85.585675 | Y594: 84.425163 | Z594: 83.231359 | AA594: 82.603329 | AB594: 81.774224 | AC594: 81.33768 | AD594: 81.016556 | AE594: 80.728148 | AF594: 80.371237 | AG594: 80.039578 | AH594: 79.550266 | AI594: 79.104901 | AJ594: 78.610526 | AK594: 78.077575 | AL594: 77.556046 | AM594: 76.986218 | AN594: 76.426239 | AO594: 75.840851 | AP594: 75.251015 | AQ594: 74.665073 | AR594: 74.134096 | AS594: 73.664454 | AT594: 73.199478 | AU594: 72.730723 | AV594: 72.253106
A595: CU_MWH_PGDP_2306_1 | C595: 189.25946 | D595: 190.48367 | E595: 176.81701 | F595: 174.66411 | G595: 177.28147 | H595: 175.18598 | I595: 176.65438 | J595: 178.70337 | K595: 179.49679 | L595: 178.96015 | M595: 178.40397 | N595: 188.94451 | O595: 190.77413 | P595: 190.95177 | Q595: 194.01032 | R595: 195.94893 | S595: 196.24896 | T595: 196.09808 | U595: 195.96327 | V595: 182.61405 | W595: 171.46764 | X595: 162.13357 | Y595: 155.32569 | Z595: 148.70865 | AA595: 142.41204 | AB595: 136.3193 | AC595: 131.20872 | AD595: 128.2148 | AE595: 125.68046 | AF595: 123.04261 | AG595: 120.56346 | AH595: 118.53416 | AI595: 116.89391 | AJ595: 115.36269 | AK595: 113.83217 | AL595: 112.43242 | AM595: 110.94559 | AN595: 109.58239 | AO595: 108.26306 | AP595: 106.98509 | AQ595: 105.7559 | AR595: 104.96196 | AS595: 103.95491 | AT595: 102.94679 | AU595: 101.97029 | AV595: 101.01478
... A603: CU_MWH_PGDP_2406_1 | C603: 31.074366 | D603: 31.375236 | E603: 30.799733 | F603: 31.874119 | G603: 32.862507 | H603: 33.001562 | I603: 33.581889 | J603: 33.730645 | K603: 33.288404 | L603: 32.692558 | M603: 32.057333 | N603: 34.137185 | O603: 34.547439 | P603: 34.546333 | Q603: 35.415748 | R603: 35.242041 | S603: 33.449033 | T603: 33.361258 | U603: 33.883138 | V603: 37.157676 | W603: 38.880103 | X603: 33.988023 | Y603: 33.30152 | Z603: 33.312053 | AA603: 33.442535 | AB603: 33.537236 | AC603: 33.86173 | AD603: 33.968365 | AE603: 34.056443 | AF603: 34.18104 | AG603: 34.370658 | AH603: 34.670475 | AI603: 34.885374 | AJ603: 35.011072 | AK603: 35.148236 | AL603: 35.297587 | AM603: 35.351831 | AN603: 35.334336 | AO603: 35.282029 | AP603: 35.242166 | AQ603: 35.226065 | AR603: 35.165968 | AS603: 35.173462 | AT603: 35.209835 | AU603: 35.242318 | AV603: 35.267974
A604: Q_MTEP_SEC_22_16_1 | B604: 15.957318 | C604: 16.213518 | D604: 16.487425 | E604: 16.453211 | F604: 16.193826 | G604: 15.671266 | H604: 15.603228 | I604: 15.565496 | J604: 15.430786 | K604: 15.202894 | L604: 15.103931 | M604: 14.983981 | N604: 14.975198 | O604: 15.039467 | P604: 14.841093 | Q604: 14.648582 | R604: 14.457892 | S604: 14.773869 | T604: 14.8087 | U604: 15.015113 | V604: 15.163934 | W604: 15.146107 | X604: 15.022742 | Y604: 14.976424 | Z604: 14.95257 | AA604: 14.940184 | AB604: 14.944156 | AC604: 14.778551 | AD604: 14.63148 | AE604: 14.492289 | AF604: 14.357561 | AG604: 14.230094 | AH604: 14.181521 | AI604: 14.132777 | AJ604: 14.086937 | AK604: 14.040762 | AL604: 13.990331 | AM604: 14.074012 | AN604: 14.171585 | AO604: 14.265957 | AP604: 14.36168 | AQ604: 14.451688 | AR604: 14.640187 | AS604: 14.826026 | AT604: 15.0138 | AU604: 15.203112 | AV604: 15.399807
A605: Q_MTEP_SEC_23_16_1 | B605: 0.080720537 | C605: 0.082016531 | D605: 0.083790529 | E605: 0.085099742 | F605: 0.082367787 | G605: 0.075980317 | H605: 0.078442484 | I605: 0.080053972 | J605: 0.078914693 | K605: 0.079833268 | L605: 0.082778036 | M605: 0.087080434 | N605: 0.090484994 | O605: 0.096701275 | P605: 0.098271923 | Q605: 0.10190553 | R605: 0.10612122 | S605: 0.12225904 | T605: 0.1337304 | U605: 0.14473279 | V605: 0.1535943 | W605: 0.18348266 | X605: 0.22470036 | Y605: 0.26772867 | Z605: 0.31213891 | AA605: 0.357913 | AB605: 0.40533809 | AC605: 0.46988564 | AD605: 0.53618046 | AE605: 0.60412131 | AF605: 0.67375041 | AG605: 0.74537754 | AH605: 0.80841984 | AI605: 0.87313265 | AJ605: 0.93980223 | AK605: 1.0083294 | AL605: 1.0785033 | AM605: 1.1157097 | AN605: 1.1548284 | AO605: 1.1945375 | AP605: 1.2352243 | AQ605: 1.2762915 | AR605: 1.2931658 | AS605: 1.309811 | AT605: 1.3266331 | AU605: 1.3435969 | AV605: 1.3612193
A606: Q_MTEP_SEC_24_16_1 | B606: 0.024451024 | C606: 0.024843593 | D606: 0.025304327 | E606: 0.029859256 | F606: 0.033925152 | G606: 0.037546112 | H606: 0.042385563 | I606: 0.04692052 | J606: 0.051061047 | K606: 0.055012941 | L606: 0.05820068 | M606: 0.060100175 | N606: 0.066267111 | O606: 0.073609366 | P606: 0.081460492 | Q606: 0.090625222 | R606: 0.10162568 | S606: 0.15709391 | T606: 0.20055639 | U606: 0.23856489 | V606: 0.26954802 | W606: 0.38509622 | X606: 0.51170841 | Y606: 0.64294442 | Z606: 0.77812289 | AA606: 0.91731393 | AB606: 1.0613342 | AC606: 1.2304248 | AD606: 1.4040919 | AE606: 1.5820706 | AF606: 1.7644715 | AG606: 1.9521062 | AH606: 2.0998959 | AI606: 2.2516172 | AJ606: 2.4079867 | AK606: 2.5687261 | AL606: 2.7332847 | AM606: 2.8150011 | AN606: 2.9012201 | AO606: 2.9885931 | AP606: 3.0780865 | AQ606: 3.1682084 | AR606: 3.2130669 | AS606: 3.257433 | AT606: 3.302316 | AU606: 3.3476296 | AV606: 3.3946633
A607: MAT_N_06_01_0/Y_01_1 | B607: 0.001691807 | C607: 0.001691807 | D607: 0.0016936265 | E607: 0.0016891316 | F607: 0.0016974486 | G607: 0.0016111186 | H607: 0.0015787209 | I607: 0.0015418109 | J607: 0.0014763243 | K607: 0.0015119494 | L607: 0.0014333149 | M607: 0.0014393917 | N607: 0.0014879815 | O607: 0.0015105384 | P607: 0.0015133731 | Q607: 0.0014749611 | R607: 0.0014757458 | S607: 0.0014765065 | T607: 0.0014766714 | U607: 0.0014765005 | V607: 0.0014859281 | W607: 0.0014953406 | X607: 0.0015078598 | Y607: 0.0015196566 | Z607: 0.0015303573 | AA607: 0.0015405105 | AB607: 0.0015504673 | AC607: 0.0015494257 | AD607: 0.0015470856 | AE607: 0.0015451624 | AF607: 0.0015437227 | AG607: 0.0015413939 | AH607: 0.0015407333 | AI607: 0.0015402791 | AJ607: 0.001539622 | AK607: 0.0015388553 | AL607: 0.0015380369 | AM607: 0.0015375732 | AN607: 0.0015372472 | AO607: 0.001536889 | AP607: 0.0015364445 | AQ607: 0.0015359419 | AR607: 0.0015353747 | AS607: 0.0015347835 | AT607: 0.0015341678 | AU607: 0.0015335252 | AV607: 0.0015326482
A608: MAT_N_06_02_0/Y_02_1 | B608: 0.016902639 | C608: 0.016902639 | D608: 0.017123012 | E608: 0.016935826 | F608: 0.016992686 | G608: 0.016117965 | H608: 0.01626116 | I608: 0.015392253 | J608: 0.014979803 | K608: 0.014990005 | L608: 0.014497458 | M608: 0.014504281 | N608: 0.014653392 | O608: 0.014803666 | P608: 0.014584166 | Q608: 0.014408818 | R608: 0.014417174 | S608: 0.014421626 | T608: 0.014420961 | U608: 0.014416297 | V608: 0.014520839 | W608: 0.014625377 | X608: 0.014761928 | Y608: 0.014897703 | Z608: 0.015025169 | AA608: 0.015146787 | AB608: 0.01526491 | AC608: 0.015266378 | AD608: 0.015252081 | AE608: 0.015238261 | AF608: 0.015227435 | AG608: 0.015205911 | AH608: 0.015199173 | AI608: 0.015195866 | AJ608: 0.015191877 | AK608: 0.01518735 | AL608: 0.01518249 | AM608: 0.015177056 | AN608: 0.015172952 | AO608: 0.015168587 | AP608: 0.015163299 | AQ608: 0.015157283 | AR608: 0.015149875 | AS608: 0.015141858 | AT608: 0.015133309 | AU608: 0.015124247 | AV608: 0.015114398
A609: MAT_N_06_03_0/Y_03_1 | B609: 0.001264969 | C609: 0.001264969 | D609: 0.0012649007 | E609: 0.0012935883 | F609: 0.0013025329 | G609: 0.0013811887 | H609: 0.0013012957 | I609: 0.0012396438 | J609: 0.0011961763 | K609: 0.0011921024 | L609: 0.0011515804 | M609: 0.0011262138 | N609: 0.0010954761 | O609: 0.001059274 | P609: 0.0010291484 | Q609: 0.00099080897 | R609: 0.0009910929 | S609: 0.00099108958 | T609: 0.00099118418 | U609: 0.00099089494 | V609: 0.00099116723 | W609: 0.00099088529 | X609: 0.00099192832 | Y609: 0.00099339168 | Z609: 0.00099395276 | AA609: 0.00099426614 | AB609: 0.00099443374 | AC609: 0.00099432817 | AD609: 0.00099372239 | AE609: 0.00099298821 | AF609: 0.00099254929 | AG609: 0.00099176303 | AH609: 0.00099140027 | AI609: 0.00099144863 | AJ609: 0.0009913003 | AK609: 0.0009911346 | AL609: 0.00099096156 | AM609: 0.00099112415 | AN609: 0.00099092053 | AO609: 0.00099075642 | AP609: 0.00099054456 | AQ609: 0.00099031501 | AR609: 0.00099004962 | AS609: 0.00098974689 | AT609: 0.00098943517 | AU609: 0.00098911662 | AV609: 0.00098851438
A610: MAT_N_06_04_0/Y_04_1 | B610: 0.030517138 | C610: 0.030517138 | D610: 0.030633897 | E610: 0.030858571 | F610: 0.032472135 | G610: 0.03563065 | H610: 0.03515049 | I610: 0.030238401 | J610: 0.031143005 | K610: 0.032083174 | L610: 0.031281623 | M610: 0.031750039 | N610: 0.030881761 | O610: 0.030464213 | P610: 0.029681382 | Q610: 0.028906081 | R610: 0.02891466 | S610: 0.02891637 | T610: 0.028915662 | U610: 0.028907991 | V610: 0.029325642 | W610: 0.029740924 | X610: 0.030199002 | Y610: 0.030663493 | Z610: 0.031122654 | AA610: 0.031580777 | AB610: 0.032040456 | AC610: 0.032041417 | AD610: 0.032024408 | AE610: 0.032006111 | AF610: 0.031992559 | AG610: 0.031967849 | AH610: 0.031959738 | AI610: 0.031958127 | AJ610: 0.031954675 | AK610: 0.031950691 | AL610: 0.03194645 | AM610: 0.031950309 | AN610: 0.031950596 | AO610: 0.031949949 | AP610: 0.03194732 | AQ610: 0.031943084 | AR610: 0.031937008 | AS610: 0.03192967 | AT610: 0.031921319 | AU610: 0.031912159 | AV610: 0.03189211
A611: MAT_N_06_05_0/Y_05_1 | B611: 0.0058610672 | C611: 0.0058610672 | D611: 0.0058672894 | E611: 0.0059126955 | F611: 0.0062179873 | G611: 0.0068308929 | H611: 0.0067306961 | I611: 0.0057633759 | J611: 0.0059708762 | K611: 0.0061652222 | L611: 0.0060170379 | M611: 0.0061310123 | N611: 0.0059550024 | O611: 0.0058718099 | P611: 0.0057308665 | Q611: 0.0055697069 | R611: 0.0055741689 | S611: 0.0055738882 | T611: 0.0055762032 | U611: 0.0055765482 | V611: 0.0056023961 | W611: 0.005622316 | X611: 0.0056541393 | Y611: 0.0056846545 | Z611: 0.0057129757 | AA611: 0.0057403091 | AB611: 0.0057672096 | AC611: 0.0057732752 | AD611: 0.0057770895 | AE611: 0.005779954 | AF611: 0.0057834771 | AG611: 0.0057859563 | AH611: 0.0057904824 | AI611: 0.0057962168 | AJ611: 0.0058010601 | AK611: 0.0058055136 | AL611: 0.0058097291 | AM611: 0.0058272324 | AN611: 0.0058427479 | AO611: 0.0058585051 | AP611: 0.0058739795 | AQ611: 0.0058894214 | AR611: 0.0059043407 | AS611: 0.0059187256 | AT611: 0.0059326598 | AU611: 0.005946426 | AV611: 0.0059385085
A612: MAT_N_06_06_0/Y_06_1 | B612: 0.33257167 | C612: 0.33257167 | D612: 0.33345627 | E612: 0.33497098 | F612: 0.34137627 | G612: 0.35834842 | H612: 0.34411874 | I612: 0.33972864 | J612: 0.34112953 | K612: 0.33794401 | L612: 0.33577603 | M612: 0.33266309 | N612: 0.33777228 | O612: 0.34719817 | P612: 0.34253747 | Q612: 0.34064416 | R612: 0.34074024 | S612: 0.3407707 | T612: 0.3407831 | U612: 0.34071972 | V612: 0.3655555 | W612: 0.39252803 | X612: 0.42224395 | Y612: 0.45434039 | Z612: 0.48880233 | AA612: 0.52584013 | AB612: 0.56564895 | AC612: 0.56636125 | AD612: 0.56669815 | AE612: 0.56692934 | AF612: 0.56717641 | AG612: 0.56724708 | AH612: 0.56752697 | AI612: 0.56788894 | AJ612: 0.56821961 | AK612: 0.56853432 | AL612: 0.56883853 | AM612: 0.56926288 | AN612: 0.56961142 | AO612: 0.56992191 | AP612: 0.57017564 | AQ612: 0.57037847 | AR612: 0.5705189 | AS612: 0.5706139 | AT612: 0.57066388 | AU612: 0.57067166 | AV612: 0.57051205
A613: MAT_N_06_07_0/Y_07_1 | B613: 0.0050209205 | C613: 0.0050209205 | D613: 0.005022034 | E613: 0.0050750325 | F613: 0.0049572047 | G613: 0.0050374943 | H613: 0.0049192489 | I613: 0.0046617729 | J613: 0.0045591107 | K613: 0.0045272425 | L613: 0.004470755 | M613: 0.0043702886 | N613: 0.0043093459 | O613: 0.0043355581 | P613: 0.0042528954 | Q613: 0.0040802123 | R613: 0.0040799713 | S613: 0.0040790398 | T613: 0.0040770982 | U613: 0.0040739314 | V613: 0.0040716642 | W613: 0.0040686748 | X613: 0.0040685566 | Y613: 0.0040680228 | Z613: 0.0040663642 | AA613: 0.0040642014 | AB613: 0.0040619404 | AC613: 0.0040591118 | AD613: 0.0040552736 | AE613: 0.0040516345 | AF613: 0.0040484672 | AG613: 0.0040447761 | AH613: 0.0040424655 | AI613: 0.0040405769 | AJ613: 0.0040385875 | AK613: 0.0040366008 | AL613: 0.0040346559 | AM613: 0.0040328655 | AN613: 0.0040305836 | AO613: 0.0040279493 | AP613: 0.0040249128 | AQ613: 0.004021482 | AR613: 0.0040180954 | AS613: 0.0040145834 | AT613: 0.0040109635 | AU613: 0.0040072504 | AV613: 0.0040029533
A614: MAT_N_06_08_0/Y_08_1 | B614: 0.0089822933 | C614: 0.0089822933 | D614: 0.0089823288 | E614: 0.0090608818 | F614: 0.0088371402 | G614: 0.0089097237 | H614: 0.0086863328 | I614: 0.0081982282 | J614: 0.0079237548 | K614: 0.0078206631 | L614: 0.0076578948 | M614: 0.0074227139 | N614: 0.0073103053 | O614: 0.0072868109 | P614: 0.0070849968 | Q614: 0.0066921618 | R614: 0.006693222 | S614: 0.0066926954 | T614: 0.0066926176 | U614: 0.0066920833 | V614: 0.0067972673 | W614: 0.0069032375 | X614: 0.0070117346 | Y614: 0.007123917 | Z614: 0.0072356527 | AA614: 0.0073484475 | AB614: 0.0074632601 | AC614: 0.0074607496 | AD614: 0.0074579369 | AE614: 0.0074552011 | AF614: 0.007452828 | AG614: 0.0074501463 | AH614: 0.0074483394 | AI614: 0.007446836 | AJ614: 0.0074452157 | AK614: 0.0074436156 | AL614: 0.0074420305 | AM614: 0.0074409854 | AN614: 0.0074395266 | AO614: 0.0074379569 | AP614: 0.0074361486 | AQ614: 0.007433434 | AR614: 0.0074312012 | AS614: 0.0074289671 | AT614: 0.007426646 | AU614: 0.0074242022 | AV614: 0.0074218072
A615: MAT_N_06_09_0/Y_09_1 | B615: 0.019547856 | C615: 0.019547856 | D615: 0.019604778 | E615: 0.019226133 | F615: 0.019324712 | G615: 0.021228606 | H615: 0.020369477 | I615: 0.018857375 | J615: 0.018833691 | K615: 0.019605999 | L615: 0.019740325 | M615: 0.019162929 | N615: 0.019227611 | O615: 0.019203221 | P615: 0.018876587 | Q615: 0.018819152 | R615: 0.018826603 | S615: 0.018828527 | T615: 0.018830807 | U615: 0.018829834 | V615: 0.020515433 | W615: 0.022344021 | X615: 0.024366261 | Y615: 0.026570257 | Z615: 0.028961605 | AA615: 0.031560893 | AB615: 0.034388859 | AC615: 0.034306125 | AD615: 0.034209201 | AE615: 0.034111432 | AF615: 0.034019223 | AG615: 0.033919318 | AH615: 0.033833492 | AI615: 0.033754276 | AJ615: 0.033672961 | AK615: 0.033591261 | AL615: 0.033509462 | AM615: 0.033441956 | AN615: 0.033369989 | AO615: 0.033298003 | AP615: 0.033224075 | AQ615: 0.033148757 | AR615: 0.033071798 | AS615: 0.032993553 | AT615: 0.032914249 | AU615: 0.032834221 | AV615: 0.032735408
... A767: PNEWBUIL_H01_1 | B767: 0.0012516089 | C767: 0.0012766411 | D767: 0.0012912692 | E767: 0.0013032028 | F767: 0.0013163943 | G767: 0.0013478795 | H767: 0.0013925213 | I767: 0.0014296137 | J767: 0.0014631521 | K767: 0.0014947025 | L767: 0.0015430482 | M767: 0.001610379 | N767: 0.001662071 | O767: 0.0016972231 | P767: 0.0017270109 | Q767: 0.0017570185 | R767: 0.0018129394 | S767: 0.0018705949 | T767: 0.0019072196 | U767: 0.0019445126 | V767: 0.0019822625 | W767: 0.0020208766 | X767: 0.0020600213 | Y767: 0.0020998182 | Z767: 0.0021401852 | AA767: 0.0021810558 | AB767: 0.002222424 | AC767: 0.0022644813 | AD767: 0.0023069919 | AE767: 0.0023499929 | AF767: 0.0023935583 | AG767: 0.0024377252 | AH767: 0.0024824731 | AI767: 0.0025278043 | AJ767: 0.0025737099 | AK767: 0.0026201364 | AL767: 0.0026670467 | AM767: 0.0027140997 | AN767: 0.0027617266 | AO767: 0.0028097664 | AP767: 0.0028580623 | AQ767: 0.0029065203 | AR767: 0.0029551097 | AS767: 0.0030037629 | AT767: 0.0030523873 | AU767: 0.003100882 | AV767: 0.0031647903
A768: NEW_TRUCKS_15_1 | C768: 5.4807907 | D768: 5.5687866 | E768: 4.2574992 | F768: 4.486056 | G768: 4.7564216 | H768: 5.0004223 | I768: 5.393404 | J768: 5.0119464 | K768: 4.8596928 | L768: 5.5442938 | M768: 4.1937125 | N768: 5.6893087 | O768: 5.5268256 | P768: 5.9497884 | Q768: 6.233129 | R768: 4.5631186 | S768: 4.5140781 | T768: 5.2573099 | U768: 5.4360857 | V768: 5.2526692 | W768: 5.1249451 | X768: 5.5931284 | Y768: 5.3464078 | Z768: 5.3936091 | AA768: 5.3979546 | AB768: 5.4004208 | AC768: 5.3596351 | AD768: 5.081713 | AE768: 5.2599839 | AF768: 5.353978 | AG768: 5.1352684 | AH768: 5.6446821 | AI768: 5.6444411 | AJ768: 5.666531 | AK768: 5.7097243 | AL768: 5.7402631 | AM768: 5.7427502 | AN768: 5.8194489 | AO768: 5.8776865 | AP768: 5.9240671 | AQ768: 5.9571883 | AR768: 5.9669045 | AS768: 6.0160499 | AT768: 6.0585659 | AU768: 6.0995089 | AV768: 6.1603358
A769: NEW_TRUCKS_16_1 | C769: 45.90819 | D769: 46.64526 | E769: 42.36853 | F769: 37.667917 | G769: 27.81915 | H769: 38.534588 | I769: 45.497517 | J769: 39.264363 | K769: 28.502252 | L769: 37.475078 | M769: 34.607495 | N769: 40.069704 | O769: 42.930682 | P769: 46.504883 | Q769: 43.699156 | R769: 40.410339 | S769: 54.999072 | T769: 43.94642 | U769: 50.852112 | V769: 48.802563 | W769: 47.463937 | X769: 45.035054 | Y769: 48.655055 | Z769: 50.249074 | AA769: 51.47943 | AB769: 53.007429 | AC769: 49.244075 | AD769: 50.635041 | AE769: 51.6503 | AF769: 52.576521 | AG769: 53.702861 | AH769: 55.226195 | AI769: 56.088993 | AJ769: 57.144197 | AK769: 58.080754 | AL769: 58.842093 | AM769: 59.029588 | AN769: 60.542427 | AO769: 61.192883 | AP769: 62.091979 | AQ769: 62.616355 | AR769: 63.498948 | AS769: 64.053489 | AT769: 64.85444 | AU769: 65.640585 | AV769: 66.758215
A770: NEW_LUV_16_1 | C770: 405.5254 | D770: 412.03624 | E770: 373.41874 | F770: 365.28754 | G770: 379.33932 | H770: 402.60878 | I770: 362.17209 | J770: 482.80088 | K770: 511.94586 | L770: 457.9653 | M770: 467.61275 | N770: 514.39681 | O770: 498.69779 | P770: 309.48518 | Q770: 316.35024 | R770: 400.40127 | S770: 544.95208 | T770: 435.43813 | U770: 503.86239 | V770: 483.55467 | W770: 470.29105 | X770: 446.22473 | Y770: 482.09311 | Z770: 497.88727 | AA770: 510.07811 | AB770: 525.21811 | AC770: 487.92934 | AD770: 501.71157 | AE770: 511.77115 | AF770: 520.94851 | AG770: 532.10872 | AH770: 547.2025 | AI770: 555.75145 | AJ770: 566.20681 | AK770: 575.48658 | AL770: 583.03022 | AM770: 584.88799 | AN770: 599.87779 | AO770: 606.32276 | AP770: 615.23135 | AQ770: 620.42707 | AR770: 629.17214 | AS770: 634.66675 | AT770: 642.60288 | AU770: 650.39231 | AV770: 661.46622
A771: TRUCKS_15_1 | B771: 80.756911 | C771: 82.053489 | D771: 83.370885 | E771: 83.308735 | F771: 83.478362 | G771: 83.909567 | H771: 84.56243 | I771: 85.574448 | J771: 86.152574 | K771: 86.548492 | L771: 87.608497 | M771: 87.263 | N771: 88.431 | O771: 89.376 | P771: 90.695 | Q771: 92.229 | R771: 92.013509 | S771: 91.760143 | T771: 92.263136 | U771: 92.918844 | V771: 93.357162 | W771: 93.645045 | X771: 94.386195 | Y771: 94.842224 | Z771: 95.321826 | AA771: 95.780925 | AB771: 96.218702 | AC771: 96.593012 | AD771: 96.670006 | AE771: 96.921281 | AF771: 97.253531 | AG771: 97.349857 | AH771: 97.950606 | AI771: 98.519987 | AJ771: 99.081958 | AK771: 99.658004 | AL771: 100.23474 | AM771: 100.78409 | AN771: 101.38167 | AO771: 102.00652 | AP771: 102.64538 | AQ771: 103.28426 | AR771: 103.89976 | AS771: 104.53251 | AT771: 105.17499 | AU771: 105.82513 | AV771: 106.5024
A772: TRUCKS_22_15_1 | B772: 79.434309 | C772: 80.709652 | D772: 82.005472 | E772: 81.778348 | F772: 81.778528 | G772: 82.033762 | H772: 82.50354 | I772: 83.320411 | J772: 83.71165 | K772: 83.923902 | L772: 84.777203 | M772: 84.269 | N772: 85.43 | O772: 86.222 | P772: 87.363 | Q772: 88.291 | R772: 87.119058 | S772: 85.657483 | T772: 85.144317 | U772: 84.95768 | V772: 84.722053 | W772: 82.4299 | X772: 80.971268 | Y772: 79.241263 | Z772: 77.510027 | AA772: 75.741124 | AB772: 73.935302 | AC772: 71.91545 | AD772: 69.663459 | AE772: 67.529219 | AF772: 65.437457 | AG772: 63.176716 | AH772: 62.006411 | AI772: 60.797611 | AJ772: 59.566217 | AK772: 58.325159 | AL772: 57.066145 | AM772: 56.719269 | AN772: 56.392031 | AO772: 56.071965 | AP772: 55.751326 | AQ772: 55.422336 | AR772: 55.75261 | AS772: 56.092144 | AT772: 56.4369 | AU772: 56.785763 | AV772: 57.14919
A773: TRUCKS_23_15_1 | B773: 0.35351914 | C773: 0.35919501 | D773: 0.36496199 | E773: 0.36468992 | F773: 0.36543248 | G773: 0.36732011 | H773: 0.37017806 | I773: 0.37460824 | J773: 0.37713903 | K773: 0.37887219 | L773: 0.38351244 | M773: 0.382 | N773: 0.426 | O773: 0.474 | P773: 0.519 | Q773: 0.773 | R773: 0.89287323 | S773: 1.3038669 | T773: 1.6435891 | U773: 1.9232208 | V773: 2.1476649 | W773: 3.0184315 | X773: 3.8469815 | Y773: 4.6741168 | Z773: 5.5103903 | AA773: 6.3534811 | AB773: 7.2028037 | AC773: 8.0859362 | AD773: 8.9481752 | AE773: 9.8294525 | AF773: 10.724108 | AG773: 11.596542 | AH773: 12.173797 | AI773: 12.753196 | AJ773: 13.337475 | AK773: 13.929525 | AL773: 14.527623 | AM773: 14.707301 | AN773: 14.895157 | AO773: 15.088233 | AP773: 15.284637 | AQ773: 15.482311 | AR773: 15.574574 | AS773: 15.669423 | AT773: 15.765731 | AU773: 15.863187 | AV773: 15.96471
A774: TRUCKS_24_15_1 | B774: 0.96908292 | C774: 0.98464186 | D774: 1.0004506 | E774: 1.1656975 | F774: 1.3344017 | G774: 1.5084843 | H774: 1.6887118 | I774: 1.879429 | J774: 2.0637851 | K774: 2.2457172 | L774: 2.4477816 | M774: 2.612 | N774: 2.575 | O774: 2.68 | P774: 2.813 | Q774: 3.165 | R774: 4.0015783 | S774: 4.7987935 | T774: 5.4752301 | U774: 6.0379436 | V774: 6.4874437 | W774: 8.1967136 | X774: 9.5679456 | Y774: 10.926844 | Z774: 12.301409 | AA774: 13.68632 | AB774: 15.080597 | AC774: 16.591626 | AD774: 18.058372 | AE774: 19.56261 | AF774: 21.091966 | AG774: 22.576599 | AH774: 23.770398 | AI774: 24.969181 | AJ774: 26.178265 | AK774: 27.40332 | AL774: 28.640975 | AM774: 29.357518 | AN774: 30.094479 | AO774: 30.846323 | AP774: 31.60942 | AQ774: 32.379617 | AR774: 32.572574 | AS774: 32.770941 | AT774: 32.97236 | AU774: 33.176177 | AV774: 33.388504
A775: NEW_TRUCKS_22_15_1 | C775: 5.3910287 | D775: 5.4775834 | E775: 4.0217791 | F775: 4.2373161 | G775: 4.4923788 | H775: 4.7201468 | I775: 5.0915806 | J775: 4.7082723 | K775: 4.5495573 | L775: 5.2016027 | M775: 3.8843103 | N775: 5.5271823 | O775: 5.2183365 | P775: 5.608372 | Q775: 5.45449 | R775: 3.4026297 | S775: 3.0522757 | T775: 3.9249575 | U775: 4.2248971 | V775: 4.1662377 | W775: 2.0975026 | X775: 2.8122623 | Y775: 2.4653135 | Z775: 2.3744473 | AA775: 2.2470805 | AB775: 2.11851 | AC775: 1.8109159 | AD775: 1.4741237 | AE775: 1.4751935 | AF775: 1.4070924 | AG775: 1.1297323 | AH775: 2.1030344 | AI775: 2.0039035 | AJ775: 1.9186788 | AK775: 1.8452131 | AL775: 1.7629545 | AM775: 2.6098594 | AN775: 2.6115264 | AO775: 2.6017422 | AP775: 2.5845864 | AQ775: 2.5596216 | AR775: 3.201841 | AS775: 3.2282124 | AT775: 3.2510264 | AU775: 3.2729965 | AV775: 3.3056362
A776: NEW_TRUCKS_23_15_1 | C776: 0.023992553 | D776: 0.024377748 | E776: 0.018637506 | F776: 0.01963803 | G776: 0.020821574 | H776: 0.021889705 | I776: 0.02361001 | J776: 0.021940152 | K776: 0.021273652 | L776: 0.024270541 | M776: 0.018358275 | N776: 0.063792351 | O776: 0.070072098 | P776: 0.069559095 | Q776: 0.28089065 | R776: 0.15992424 | S776: 0.45725562 | T776: 0.40727874 | U776: 0.36479005 | V776: 0.32409082 | W776: 0.98204233 | X776: 0.98494234 | Y776: 1.0264568 | Z776: 1.0784509 | AA776: 1.1285976 | AB776: 1.1785119 | AC776: 1.2563273 | AD776: 1.2811911 | AE776: 1.3449041 | AF776: 1.4039432 | AG776: 1.4280763 | AH776: 1.1781006 | AI776: 1.2101522 | AJ776: 1.2450537 | AK776: 1.2830968 | AL776: 1.3198206 | AM776: 0.93238968 | AN776: 0.94987691 | AO776: 0.96483117 | AP776: 0.97816116 | AQ776: 0.98960885 | AR776: 0.89443899 | AS776: 0.90180588 | AT776: 0.90817902 | AU776: 0.91431638 | AV776: 0.92343434
A777: NEW_TRUCKS_24_15_1 | C777: 0.065769488 | D777: 0.066825452 | E777: 0.21708267 | F777: 0.2291018 | G777: 0.24322124 | H777: 0.25838577 | I777: 0.2782134 | J777: 0.28173391 | K777: 0.28886185 | L777: 0.31842053 | M777: 0.29104389 | N777: 0.098334086 | O777: 0.23841703 | P777: 0.27185733 | Q777: 0.49774839 | R777: 1.0005647 | S777: 1.0045467 | T777: 0.92507371 | U777: 0.84639857 | V777: 0.76234069 | W777: 2.0454001 | X777: 1.7959238 | Y777: 1.8546375 | Z777: 1.9407109 | AA777: 2.0222766 | AB777: 2.1033989 | AC777: 2.2923919 | AD777: 2.3263983 | AE777: 2.4398863 | AF777: 2.5429424 | AG777: 2.5774597 | AH777: 2.363547 | AI777: 2.4303855 | AJ777: 2.5027985 | AK777: 2.5814144 | AL777: 2.657488 | AM777: 2.2005011 | AN777: 2.2580455 | AO777: 2.311113 | AP777: 2.3613195 | AQ777: 2.4079579 | AR777: 1.8706246 | AS777: 1.8860316 | AT777: 1.8993604 | AU777: 1.912196 | AV777: 1.9312653
A778: TRUCKS_16_1 | B778: 561.33716 | C778: 570.34961 | D778: 579.50675 | E778: 583.78529 | F778: 583.08199 | G778: 572.57615 | H778: 573.47627 | I778: 581.28017 | J778: 582.33797 | K778: 572.56413 | L778: 572.40554 | M778: 569.38979 | N778: 572.03447 | O778: 577.3663 | P778: 585.92187 | Q778: 591.10938 | R778: 592.6671 | S778: 608.71116 | T778: 612.64803 | U778: 623.23183 | V778: 631.07042 | W778: 637.05517 | X778: 640.21766 | Y778: 646.7923 | Z778: 654.52881 | AA778: 662.98717 | AB778: 672.41758 | AC778: 677.46478 | AD778: 683.57121 | AE778: 690.29153 | AF778: 697.49636 | AG778: 705.35397 | AH778: 714.21844 | AI778: 723.36307 | AJ778: 732.96184 | AK778: 742.86625 | AL778: 752.881 | AM778: 762.425 | AN778: 772.85452 | AO778: 783.24899 | AP778: 793.85934 | AQ778: 804.29667 | AR778: 814.93056 | AS778: 825.42004 | AT778: 836.02102 | AU778: 846.71136 | AV778: 857.81667
A779: TRUCKS_22_16_1 | B779: 559.39986 | C779: 568.38121 | D779: 577.50675 | E779: 581.89404 | F779: 581.22183 | G779: 570.68144 | H779: 571.48954 | I779: 579.14904 | J779: 580.01275 | K779: 569.99578 | L779: 569.54395 | M779: 566.18231 | N779: 568.42451 | O779: 573.29204 | P779: 581.31498 | Q779: 585.89365 | R779: 586.73413 | S779: 598.08306 | T779: 598.30011 | U779: 605.66471 | V779: 610.87539 | W779: 606.94949 | X779: 598.76169 | Y779: 593.59473 | Z779: 589.24371 | AA779: 585.2592 | AB779: 581.8198 | AC779: 571.21776 | AD779: 561.26237 | AE779: 551.52762 | AF779: 541.87229 | AG779: 532.39127 | AH779: 527.28517 | AI779: 522.08843 | AJ779: 516.90989 | AK779: 511.62476 | AL779: 506.08661 | AM779: 507.85129 | AN779: 510.08399 | AO779: 512.16651 | AP779: 514.26208 | AQ779: 516.11717 | AR779: 522.66386 | AS779: 529.11076 | AT779: 535.62195 | AU779: 542.18315 | AV779: 549.00267
A780: TRUCKS_23_16_1 | B780: 0.96864644 | C780: 0.98419838 | D780: 1 | E780: 0.7562145 | F780: 0.57186037 | G780: 0.4324491 | H780: 0.32702428 | I780: 0.2473005 | J780: 0.18701223 | K780: 0.14142136 | L780: 0.10694488 | M780: 0.080873269 | N780: 0.061157538 | O780: 0.046248217 | P780: 0.034973572 | Q780: 0.026447523 | R780: 0.020077737 | S780: 0.71602391 | T780: 1.280575 | U780: 1.758372 | V780: 2.1496121 | W780: 3.6604982 | X780: 6.0162844 | Y780: 8.4396882 | Z780: 10.930507 | AA780: 13.492512 | AB780: 16.139617 | AC780: 19.79961 | AD780: 23.548823 | AE780: 27.386187 | AF780: 31.315513 | AG780: 35.352828 | AH780: 38.851021 | AI780: 42.441458 | AJ780: 46.138684 | AK780: 49.938543 | AL780: 53.830992 | AM780: 55.80951 | AN780: 57.886804 | AO780: 59.996873 | AP780: 62.159186 | AQ780: 64.343733 | AR780: 65.194445 | AS780: 66.033603 | AT780: 66.881682 | AU780: 67.736909 | AV780: 68.625334
A781: TRUCKS_24_16_1 | B781: 0.96864644 | C781: 0.98419838 | D781: 1 | E781: 1.1350323 | F781: 1.2882984 | G781: 1.4622604 | H781: 1.6597128 | I781: 1.8838277 | J781: 2.1382054 | K781: 2.4269322 | L781: 2.7546466 | M781: 3.1266129 | N781: 3.5488068 | O781: 4.0280105 | P781: 4.5719221 | Q781: 5.1892795 | R781: 5.9128936 | S781: 9.9120834 | T781: 13.067352 | U781: 15.808747 | V781: 18.045411 | W781: 26.445176 | X781: 35.439684 | Y781: 44.757875 | Z781: 54.354592 | AA781: 64.235458 | AB781: 74.458156 | AC781: 86.447411 | AD781: 98.760013 | AE781: 111.37773 | AF781: 124.30856 | AG781: 137.60987 | AH781: 148.08226 | AI781: 158.83318 | AJ781: 169.91327 | AK781: 181.30295 | AL781: 192.9634 | AM781: 198.7642 | AN781: 204.88373 | AO781: 211.0856 | AP781: 217.43807 | AQ781: 223.83576 | AR781: 227.07225 | AS781: 230.27568 | AT781: 233.51739 | AU781: 236.7913 | AV781: 240.18867
A782: NEW_TRUCKS_22_16_1 | C782: 45.749751 | D782: 46.484278 | E782: 42.345827 | F782: 37.574697 | G782: 27.662334 | H782: 38.318025 | I782: 45.222541 | J782: 38.930198 | K782: 28.106283 | L782: 37.013027 | M782: 34.073513 | N782: 39.456404 | O782: 42.229111 | P782: 45.704452 | Q782: 42.787521 | R782: 39.350274 | S782: 49.913972 | T782: 39.528033 | U782: 46.689855 | V782: 45.020001 | W782: 36.225901 | X782: 31.705965 | Y782: 34.18863 | Z782: 34.664953 | AA782: 34.745481 | AB782: 35.028698 | AC782: 27.639989 | AD782: 27.589788 | AE782: 27.156071 | AF782: 26.595643 | AG782: 26.135327 | AH782: 29.887074 | AI782: 29.460826 | AJ782: 29.137444 | AK782: 28.690481 | AL782: 28.090082 | AM782: 35.028897 | AN782: 35.612898 | AO782: 35.609484 | AP782: 35.759403 | AQ782: 35.656665 | AR782: 40.470198 | AS782: 40.800703 | AT782: 41.288746 | AU782: 41.766728 | AV782: 42.456298
A783: NEW_TRUCKS_23_16_1 | C783: 0.079219421 | D783: 0.080491315 | E783: -0.1780572 | F783: -0.13464943 | G783: -0.10182385 | H783: -0.077000675 | I783: -0.058229026 | J783: -0.044033634 | K783: -0.033298872 | L783: -0.02518109 | M783: -0.019042305 | N783: -0.014400068 | O783: -0.01088954 | P783: -0.0082348279 | Q783: -0.0062272962 | R783: -0.0046314345 | S783: 0.69726585 | T783: 0.61161412 | U783: 0.56196703 | V783: 0.50681492 | W783: 1.6521765 | X783: 2.5963845 | Y783: 2.818844 | Z783: 3.0455451 | AA783: 3.2804491 | AB783: 3.5339445 | AC783: 4.7208227 | AD783: 5.0506076 | AE783: 5.3851881 | AF783: 5.7293738 | AG783: 6.0956306 | AH783: 5.8218745 | AI783: 6.1440485 | AJ783: 6.4868316 | AK783: 6.8324769 | AL783: 7.1748242 | AM783: 5.516738 | AN783: 5.7455584 | AO783: 5.9148702 | AP783: 6.1058065 | AQ783: 6.2701649 | AR783: 5.0799158 | AS783: 5.1242792 | AT783: 5.1883552 | AU783: 5.2512468 | AV783: 5.3406572
A784: NEW_TRUCKS_24_16_1 | C784: 0.079219421 | D784: 0.080491315 | E784: 0.20076064 | F784: 0.22786982 | G784: 0.25863962 | H784: 0.29356433 | I784: 0.33320501 | J784: 0.37819846 | K784: 0.42926748 | L784: 0.48723248 | M784: 0.55302462 | N784: 0.62770082 | O784: 0.71246073 | P784: 0.80866597 | Q784: 0.91786203 | R784: 1.0646967 | S784: 4.3878343 | T784: 3.8067727 | U784: 3.60029 | V784: 3.2757462 | W784: 9.5858598 | X784: 10.732705 | Y784: 11.647581 | Z784: 12.538576 | AA784: 13.453501 | AB784: 14.444786 | AC784: 16.883263 | AD784: 17.994645 | AE784: 19.109041 | AF784: 20.251505 | AG784: 21.471903 | AH784: 19.517246 | AI784: 20.484119 | AJ784: 21.519922 | AK784: 22.557796 | AL784: 23.577187 | AM784: 18.483953 | AN784: 19.183971 | AO784: 19.668529 | AP784: 20.226769 | AQ784: 20.689525 | AR784: 17.948834 | AS784: 18.128507 | AT784: 18.377339 | AU784: 18.62261 | AV784: 18.96126
A785: PNEW_TRUCKS_22_15_1 | B785: 205.41388 | C785: 209.52216 | D785: 219.23607 | E785: 223.0875 | F785: 228.0717 | G785: 233.32669 | H785: 234.72943 | I785: 237.24569 | J785: 239.73614 | K785: 243.47959 | L785: 248.57155 | M785: 253.86256 | N785: 254.41298 | O785: 258.16207 | P785: 260.9686 | Q785: 263.62048 | R785: 262.48584 | S785: 262.95786 | T785: 259.38977 | U785: 251.57069 | V785: 256.66258 | W785: 261.84171 | X785: 267.05401 | Y785: 272.38757 | Z785: 277.82163 | AA785: 283.33851 | AB785: 288.9438 | AC785: 294.66005 | AD785: 300.51702 | AE785: 306.47022 | AF785: 312.54297 | AG785: 318.78605 | AH785: 325.10881 | AI785: 331.58959 | AJ785: 338.22114 | AK785: 344.99333 | AL785: 351.90666 | AM785: 358.95193 | AN785: 366.13596 | AO785: 373.44718 | AP785: 380.89387 | AQ785: 388.48034 | AR785: 396.21672 | AS785: 404.10083 | AT785: 412.13831 | AU785: 420.33257 | AV785: 428.70458
A786: PNEW_TRUCKS_23_15_1 | B786: 378.07612 | C786: 385.63764 | D786: 479.64963 | E786: 488.07588 | F786: 498.98043 | G786: 510.47742 | H786: 513.54637 | I786: 519.0515 | J786: 524.50016 | K786: 532.69016 | L786: 543.83047 | M786: 555.40625 | N786: 537.28309 | O786: 497.27843 | P786: 479.35301 | Q786: 485.20845 | R786: 467.72976 | S786: 462.5959 | T786: 455.40393 | U786: 441.67617 | V786: 441.72766 | W786: 422.49579 | X786: 418.19493 | Y786: 414.87852 | Z786: 412.44403 | AA786: 410.80268 | AB786: 409.90621 | AC786: 409.73377 | AD786: 410.27635 | AE786: 413.70429 | AF786: 417.10919 | AG786: 420.55256 | AH786: 425.9025 | AI786: 431.34166 | AJ786: 436.8563 | AK786: 442.42928 | AL786: 448.05733 | AM786: 453.72495 | AN786: 459.43703 | AO786: 465.17536 | AP786: 470.94664 | AQ786: 476.75245 | AR786: 482.60123 | AS786: 488.48625 | AT786: 494.41016 | AU786: 500.37282 | AV786: 506.39464
A787: PNEW_TRUCKS_24_15_1 | B787: 235.67177 | C787: 240.38521 | D787: 228.64976 | E787: 232.66657 | F787: 237.86478 | G787: 243.34542 | H787: 244.80839 | I787: 247.4327 | J787: 250.03008 | K787: 253.93427 | L787: 259.24487 | M787: 264.76307 | N787: 285.92973 | O787: 289.59281 | P787: 295.75939 | Q787: 302.45237 | R787: 300.08994 | S787: 302.22106 | T787: 299.49623 | U787: 290.46817 | V787: 296.34736 | W787: 302.32729 | X787: 308.3455 | Y787: 314.50373 | Z787: 320.77799 | AA787: 327.14788 | AB787: 333.61986 | AC787: 340.21995 | AD787: 346.9825 | AE787: 353.85618 | AF787: 360.86789 | AG787: 368.07627 | AH787: 375.37664 | AI787: 382.85947 | AJ787: 390.51638 | AK787: 398.33568 | AL787: 406.31794 | AM787: 414.45254 | AN787: 422.74735 | AO787: 431.18902 | AP787: 439.7871 | AQ787: 448.54659 | AR787: 457.47915 | AS787: 466.58229 | AT787: 475.86251 | AU787: 485.32376 | AV787: 494.99024
A788: PNEW_TRUCKS_22_16_1 | B788: 69.326338 | C788: 70.712865 | D788: 72.446646 | E788: 73.719326 | F788: 75.364141 | G788: 77.098026 | H788: 77.567752 | I788: 78.403141 | J788: 79.229599 | K788: 80.468048 | L788: 82.148679 | M788: 83.896737 | N788: 86.217153 | O788: 88.441628 | P788: 89.83951 | Q788: 91.471536 | R788: 90.785431 | S788: 96.394038 | T788: 101.42422 | U788: 102.00367 | V788: 104.04685 | W788: 106.12821 | X788: 108.2485 | Y788: 112.20867 | Z788: 114.41797 | AA788: 116.6573 | AB788: 118.92816 | AC788: 121.2617 | AD788: 123.63822 | AE788: 126.06159 | AF788: 128.53568 | AG788: 131.06649 | AH788: 133.64794 | AI788: 136.28649 | AJ788: 138.98114 | AK788: 141.73048 | AL788: 144.53555 | AM788: 147.39427 | AN788: 150.30566 | AO788: 153.26943 | AP788: 156.28674 | AQ788: 159.36076 | AR788: 162.49253 | AS788: 165.68533 | AT788: 168.93935 | AU788: 172.25595 | AV788: 175.64286
A789: PNEW_TRUCKS_23_16_1 | B789: 266.12455 | C789: 271.44704 | D789: 274.82504 | E789: 279.65293 | F789: 285.8925 | G789: 292.46996 | H789: 294.25186 | I789: 297.42089 | J789: 300.55605 | K789: 305.25408 | L789: 311.62953 | M789: 318.26075 | N789: 323.71602 | O789: 328.98251 | P789: 334.47855 | Q789: 341.58661 | R789: 348.50005 | S789: 343.72335 | T789: 387.31025 | U789: 396.67446 | V789: 358.24801 | W789: 337.34847 | X789: 279.78317 | Y789: 262.61145 | Z789: 249.57227 | AA789: 241.05251 | AB789: 233.73316 | AC789: 228.8718 | AD789: 225.54823 | AE789: 223.91202 | AF789: 222.03735 | AG789: 219.92149 | AH789: 222.375 | AI789: 224.82379 | AJ789: 227.26229 | AK789: 229.68419 | AL789: 232.08717 | AM789: 237.0072 | AN789: 242.02484 | AO789: 247.13996 | AP789: 252.3548 | AQ789: 257.67482 | AR789: 263.10209 | AS789: 268.64234 | AT789: 274.29626 | AU789: 280.06648 | AV789: 285.96601
A790: PNEW_TRUCKS_24_16_1 | B790: 85.329538 | C790: 87.036129 | D790: 134.4017 | E790: 136.76276 | F790: 139.81419 | G790: 143.03086 | H790: 143.90229 | I790: 145.45209 | J790: 146.98532 | K790: 149.28286 | L790: 152.40074 | M790: 155.64371 | N790: 157.02305 | O790: 132.16775 | P790: 130.05602 | Q790: 133.88525 | R790: 111.74222 | S790: 113.93754 | T790: 116.23419 | U790: 117.43236 | V790: 118.63282 | W790: 119.83114 | X790: 121.02691 | Y790: 122.19684 | Z790: 123.35677 | AA790: 124.50063 | AB790: 125.62903 | AC790: 128.09404 | AD790: 130.60447 | AE790: 133.16438 | AF790: 135.77787 | AG790: 138.45127 | AH790: 141.17818 | AI790: 143.96538 | AJ790: 146.81187 | AK790: 149.71612 | AL790: 152.67923 | AM790: 155.69902 | AN790: 158.77445 | AO790: 161.90521 | AP790: 165.09253 | AQ790: 168.33976 | AR790: 171.64797 | AS790: 175.02067 | AT790: 178.45804 | AU790: 181.9615 | AV790: 185.53924
A791: LUV_16_1 | B791: 4958.5156 | C791: 5038.1262 | D791: 5119.0149 | E791: 5155.9695 | F791: 5182.3639 | G791: 5221.0752 | H791: 5280.5116 | I791: 5295.6046 | J791: 5430.3344 | K791: 5585.3535 | L791: 5676.203 | M791: 5770.7286 | N791: 5905.8252 | O791: 6016.3431 | P791: 5930.3842 | Q791: 5856.9404 | R791: 5872.3749 | S791: 6031.3457 | T791: 6070.3537 | U791: 6175.222 | V791: 6252.8898 | W791: 6312.189 | X791: 6343.5243 | Y791: 6408.6683 | Z791: 6485.3246 | AA791: 6569.1333 | AB791: 6662.5735 | AC791: 6712.5831 | AD791: 6773.088 | AE791: 6839.6755 | AF791: 6911.0638 | AG791: 6988.92 | AH791: 7076.7526 | AI791: 7167.3611 | AJ791: 7262.4694 | AK791: 7360.6062 | AL791: 7459.8362 | AM791: 7554.4018 | AN791: 7657.7416 | AO791: 7760.734 | AP791: 7865.8654 | AQ791: 7969.2825 | AR791: 8074.6472 | AS791: 8178.5811 | AT791: 8283.6197 | AU791: 8389.5437 | AV791: 8499.5794
A792: LUV_22_16_1 | B792: 4956.5783 | C792: 5036.1578 | D792: 5117.0149 | E792: 5151.1931 | F792: 5174.7884 | G792: 5210.6493 | H792: 5267.1428 | I792: 5279.3669 | J792: 5410.7824 | K792: 5562.261 | L792: 5649.7056 | M792: 5740.7118 | N792: 5871.1638 | O792: 5975.2452 | P792: 5883.4112 | Q792: 5802.5334 | R792: 5806.5018 | S792: 5938.525 | T792: 5956.6709 | U792: 6043.0859 | V792: 6105.7344 | W792: 6109.7016 | X792: 6063.6374 | Y792: 6048.7284 | Z792: 6042.9775 | AA792: 6041.9586 | AB792: 6047.6636 | AC792: 5976.5587 | AD792: 5912.8801 | AE792: 5852.3059 | AF792: 5793.4448 | AG792: 5737.4155 | AH792: 5707.8551 | AI792: 5677.97 | AJ792: 5648.9817 | AK792: 5619.5729 | AL792: 5588.1633 | AM792: 5614.2653 | AN792: 5645.7159 | AO792: 5675.6886 | AP792: 5705.9932 | AQ792: 5733.8191 | AR792: 5810.4515 | AS792: 5886.0757 | AT792: 5962.5163 | AU792: 6039.6157 | AV792: 6119.6972
A793: LUV_23_16_1 | B793: 0.96864644 | C793: 0.98419838 | D793: 1 | E793: 1.4103096 | F793: 1.9848265 | G793: 2.7999168 | H793: 3.9650776 | I793: 5.5677762 | J793: 7.9943529 | K793: 11.51325 | L793: 16.383086 | M793: 23.321633 | N793: 27.826681 | O793: 34.019323 | P793: 39.439141 | Q793: 46.312848 | R793: 56.733986 | S793: 83.348131 | T793: 104.07959 | U793: 122.3106 | V793: 137.16067 | W793: 192.21334 | X793: 266.38417 | Y793: 343.08829 | Z793: 422.04538 | AA793: 503.32001 | AB793: 587.37838 | AC793: 703.88454 | AD793: 823.33678 | AE793: 945.65082 | AF793: 1070.9327 | AG793: 1199.7092 | AH793: 1313.0702 | AI793: 1429.4244 | AJ793: 1549.2554 | AK793: 1672.4162 | AL793: 1798.5665 | AM793: 1865.0307 | AN793: 1934.805 | AO793: 2005.6841 | AP793: 2078.319 | AQ793: 2151.7063 | AR793: 2180.1547 | AS793: 2208.2169 | AT793: 2236.5773 | AU793: 2265.1768 | AV793: 2294.8864
A794: LUV_24_16_1 | B794: 0.96864644 | C794: 0.98419838 | D794: 1 | E794: 3.3661092 | F794: 5.5906758 | G794: 7.6260333 | H794: 9.4037116 | I794: 10.66993 | J794: 11.557638 | K794: 11.579277 | L794: 10.114331 | M794: 6.6951147 | N794: 6.8346567 | O794: 7.0785578 | P794: 7.533841 | Q794: 8.0941082 | R794: 9.1391078 | S794: 9.4726001 | T794: 9.6031802 | U794: 9.8254904 | V794: 9.9947649 | W794: 10.274068 | X794: 13.502666 | Y794: 16.851558 | Z794: 20.301752 | AA794: 23.854716 | AB794: 27.531442 | AC794: 32.139933 | AD794: 36.871146 | AE794: 41.718814 | AF794: 46.686243 | AG794: 51.795233 | AH794: 55.827367 | AI794: 59.966657 | AJ794: 64.232329 | AK794: 68.617116 | AL794: 73.106395 | AM794: 75.105863 | AN794: 77.220666 | AO794: 79.361266 | AP794: 81.553293 | AQ794: 83.757159 | AR794: 84.040928 | AS794: 84.288457 | AT794: 84.526055 | AU794: 84.751171 | AV794: 84.995794
A795: PNEW_LUV_22_16_1 | B795: 19.033911 | C795: 19.414589 | D795: 16.725575 | E795: 17.019396 | F795: 17.39913 | G795: 17.799428 | H795: 17.907872 | I795: 18.100736 | J795: 18.291539 | K795: 18.577456 | L795: 18.965459 | M795: 19.369029 | N795: 19.701032 | O795: 20.021545 | P795: 20.356028 | Q795: 21.830963 | R795: 24.925618 | S795: 25.415313 | T795: 25.927612 | U795: 26.446755 | V795: 26.976497 | W795: 27.516136 | X795: 28.065869 | Y795: 28.620545 | Z795: 29.184062 | AA795: 29.755238 | AB795: 30.334455 | AC795: 30.929658 | AD795: 31.535828 | AE795: 32.153945 | AF795: 32.785 | AG795: 33.430522 | AH795: 34.088962 | AI795: 34.761962 | AJ795: 35.449275 | AK795: 36.150537 | AL795: 36.866012 | AM795: 37.595172 | AN795: 38.337767 | AO795: 39.093722 | AP795: 39.863335 | AQ795: 40.647411 | AR795: 41.446216 | AS795: 42.26059 | AT795: 43.090578 | AU795: 43.936526 | AV795: 44.80041
A796: PNEW_LUV_23_16_1 | B796: 23.218583 | C796: 23.682954 | D796: 30.312868 | E796: 30.845378 | F796: 31.533596 | G796: 32.259082 | H796: 32.455623 | I796: 32.805164 | J796: 33.150967 | K796: 33.669155 | L796: 34.372358 | M796: 35.103775 | N796: 32.774547 | O796: 36.841792 | P796: 36.646354 | Q796: 38.900359 | R796: 30.405602 | S796: 31.171625 | T796: 32.855534 | U796: 33.542991 | V796: 33.403784 | W796: 33.242695 | X796: 33.307584 | Y796: 33.817259 | Z796: 34.292641 | AA796: 34.729922 | AB796: 35.127079 | AC796: 35.313397 | AD796: 35.492701 | AE796: 35.897236 | AF796: 36.304905 | AG796: 36.717035 | AH796: 37.33919 | AI796: 37.973348 | AJ796: 38.61911 | AK796: 39.275953 | AL796: 39.94404 | AM796: 40.73408 | AN796: 41.538675 | AO796: 42.357747 | AP796: 43.191617 | AQ796: 44.041157 | AR796: 44.906655 | AS796: 45.789023 | AT796: 46.688309 | AU796: 47.604887 | AV796: 48.540899
A797: PNEW_LUV_24_16_1 | B797: 21.001877 | C797: 21.421914 | D797: 18.424008 | E797: 18.747665 | F797: 19.16596 | G797: 19.606907 | H797: 19.726364 | I797: 19.938813 | J797: 20.148991 | K797: 20.463942 | L797: 20.891346 | M797: 21.335897 | N797: 21.701613 | O797: 22.054673 | P797: 22.391631 | Q797: 24.014059 | R797: 27.502743 | S797: 28.043069 | T797: 28.608336 | U797: 29.181154 | V797: 29.765668 | W797: 30.361102 | X797: 30.967672 | Y797: 31.579698 | Z797: 32.201478 | AA797: 32.831709 | AB797: 33.470813 | AC797: 34.127557 | AD797: 34.7964 | AE797: 35.478425 | AF797: 36.174727 | AG797: 36.886991 | AH797: 37.613509 | AI797: 38.356092 | AJ797: 39.114469 | AK797: 39.888236 | AL797: 40.677686 | AM797: 41.482236 | AN797: 42.301609 | AO797: 43.135724 | AP797: 43.98491 | AQ797: 44.850054 | AR797: 45.731448 | AS797: 46.630023 | AT797: 47.545825 | AU797: 48.479238 | AV797: 49.432441
A798: NEW_LUV_22_16_1 | C798: 405.36696 | D798: 411.87526 | E798: 370.51086 | F798: 362.17451 | G798: 375.99094 | H798: 398.98066 | I798: 358.42447 | J798: 478.41932 | K798: 507.1202 | L798: 453.04258 | M798: 462.35179 | N798: 507.77927 | O798: 489.98301 | P798: 300.90878 | Q798: 305.82881 | R798: 385.35906 | S798: 513.67472 | T798: 408.47515 | U798: 477.9369 | V798: 459.85024 | W798: 405.2868 | X798: 355.51615 | Y798: 383.64361 | Z798: 391.82174 | AA798: 396.1758 | AB798: 402.83271 | AC798: 326.39771 | AD798: 329.15048 | AE798: 328.06944 | AF798: 325.80104 | AG798: 324.76402 | AH798: 347.55014 | AI798: 345.2826 | AJ798: 344.21504 | AK798: 341.88915 | AL798: 337.95546 | AM798: 393.40243 | AN798: 400.46683 | AO798: 401.05602 | AP798: 403.35795 | AQ798: 402.87115 | AR798: 453.50668 | AS798: 457.53533 | AT798: 463.32237 | AU798: 469.00552 | AV798: 477.05517
...

Sheet Variables AMS
B1: 2004 | C1: 2005 | D1: 2006 | E1: 2007 | F1: 2008 | G1: 2009 | H1: 2010 | I1: 2011 | J1: 2012 | K1: 2013 | L1: 2014 | M1: 2015 | N1: 2016 | O1: 2017 | P1: 2018 | Q1: 2019 | R1: 2020 | S1: 2021 | T1: 2022 | U1: 2023 | V1: 2024 | W1: 2025 | X1: 2026 | Y1: 2027 | Z1: 2028 | AA1: 2029 | AB1: 2030 | AC1: 2031 | AD1: 2032 | AE1: 2033 | AF1: 2034 | AG1: 2035 | AH1: 2036 | AI1: 2037 | AJ1: 2038 | AK1: 2039 | AL1: 2040 | AM1: 2041 | AN1: 2042 | AO1: 2043 | AP1: 2044 | AQ1: 2045 | AR1: 2046 | AS1: 2047 | AT1: 2048 | AU1: 2049 | AV1: 2050
A2: NEWAUTO_ELEC_H01_2 | B2: 1.149299 | C2: 1.1677514 | D2: 2.1795284 | E2: 3.547016 | F2: 5.7123385 | G2: 9.1532957 | H2: 12.615338 | I2: 17.14676 | J2: 20.465819 | K2: 26.068457 | L2: 34.520713 | M2: 42.053287 | N2: 57.293884 | O2: 77.334793 | P2: 101.82701 | Q2: 131.38201 | R2: 142.42415 | S2: 157.17609 | T2: 197.20989 | U2: 245.53125 | V2: 369.10544 | W2: 467.08336 | X2: 484.44787 | Y2: 574.74716 | Z2: 729.25581 | AA2: 895.88404 | AB2: 1062.3645 | AC2: 1208.5317 | AD2: 1327.0612 | AE2: 1404.8546 | AF2: 1450.4285 | AG2: 1472.5615 | AH2: 1519.8902 | AI2: 1546.967 | AJ2: 1553.6848 | AK2: 1555.8917 | AL2: 1547.8555 | AM2: 1537.3043 | AN2: 1523.7276 | AO2: 1509.0834 | AP2: 1492.8133 | AQ2: 1522.8212 | AR2: 1523.8903 | AS2: 1517.1944 | AT2: 1508.3881 | AU2: 1495.812 | AV2: 1465.3582
A3: NEWAUTO_TH_H01_2 | B3: 2297.4487 | C3: 2334.335 | D3: 2370.8205 | E3: 2443.1306 | F3: 2418.5642 | G3: 2651.2106 | H3: 2586.2336 | I3: 2525.6757 | J3: 2173.6021 | K3: 2047.7565 | L3: 2044.8223 | M3: 1898.3337 | N3: 1985.0221 | O3: 2064.2932 | P3: 2101.915 | Q3: 2108.92 | R3: 1789.3354 | S3: 1557.3268 | T3: 1553.4291 | U3: 1551.6869 | V3: 1890.3118 | W3: 1960.3045 | X3: 1562.3305 | Y3: 1283.6743 | Z3: 1022.2938 | AA3: 769.07151 | AB3: 541.09297 | AC3: 351.9231 | AD3: 212.63415 | AE3: 119.7256 | AF3: 64.089205 | AG3: 33.18118 | AH3: 17.296614 | AI3: 8.8445897 | AJ3: 4.4505744 | AK3: 2.2298789 | AL3: 1.1091145 | AM3: 0.55054305 | AN3: 0.27267399 | AO3: 0.13493126 | AP3: 0.066687716 | AQ3: 0.033988446 | AR3: 0.016992987 | AS3: 0.0084524746 | AT3: 0.0041983458 | AU3: 0.0020799867 | AV3: 0.0010179867
A4: NEWAUTO_H01_2 | B4: 2298.598 | C4: 2335.5027 | D4: 2373 | E4: 2446.6776 | F4: 2424.2766 | G4: 2660.3639 | H4: 2598.849 | I4: 2542.8224 | J4: 2194.0679 | K4: 2073.825 | L4: 2079.343 | M4: 1940.387 | N4: 2042.316 | O4: 2141.628 | P4: 2203.742 | Q4: 2240.302 | R4: 1931.7595 | S4: 1714.5029 | T4: 1750.639 | U4: 1797.2181 | V4: 2259.4173 | W4: 2427.3879 | X4: 2046.7784 | Y4: 1858.4215 | Z4: 1751.5496 | AA4: 1664.9555 | AB4: 1603.4575 | AC4: 1560.4548 | AD4: 1539.6953 | AE4: 1524.5802 | AF4: 1514.5177 | AG4: 1505.7427 | AH4: 1537.1869 | AI4: 1555.8116 | AJ4: 1558.1354 | AK4: 1558.1216 | AL4: 1548.9646 | AM4: 1537.8549 | AN4: 1524.0003 | AO4: 1509.2183 | AP4: 1492.88 | AQ4: 1522.8552 | AR4: 1523.9073 | AS4: 1517.2028 | AT4: 1508.3923 | AU4: 1495.8141 | AV4: 1465.3592
A5: PAUTO_ELEC_H01_2 | B5: 32.360331 | C5: 33.007538 | D5: 33.488809 | E5: 33.839494 | F5: 34.293416 | G5: 34.811247 | H5: 34.91417 | I5: 35.171003 | J5: 35.488543 | K5: 35.912137 | L5: 36.504035 | M5: 37.069763 | N5: 37.545288 | O5: 38.395762 | P5: 38.888451 | Q5: 39.418662 | R5: 40.067961 | S5: 40.604049 | T5: 40.697631 | U5: 41.004937 | V5: 41.518786 | W5: 42.087872 | X5: 42.67351 | Y5: 43.233748 | Z5: 43.795672 | AA5: 44.374432 | AB5: 44.97027 | AC5: 45.578587 | AD5: 46.202397 | AE5: 46.846488 | AF5: 47.509486 | AG5: 48.18857 | AH5: 48.881177 | AI5: 49.587501 | AJ5: 50.321883 | AK5: 51.055704 | AL5: 51.816877 | AM5: 52.602307 | AN5: 53.415112 | AO5: 54.246389 | AP5: 55.089331 | AQ5: 55.630793 | AR5: 56.500995 | AS5: 57.387758 | AT5: 58.289707 | AU5: 59.20705 | AV5: 60.141451
A6: PNEWAUTO_TH_H01_2 | B6: 21.704143 | C6: 22.138226 | D6: 22.417243 | E6: 22.83235 | F6: 22.906497 | G6: 23.386835 | H6: 23.514262 | I6: 23.605102 | J6: 23.817102 | K6: 24.147671 | L6: 24.706833 | M6: 25.200848 | N6: 25.668231 | O6: 26.364201 | P6: 26.547282 | Q6: 26.917385 | R6: 26.979834 | S6: 27.33753 | T6: 27.257914 | U6: 27.546784 | V6: 27.982213 | W6: 28.457482 | X6: 28.967953 | Y6: 29.466058 | Z6: 29.957038 | AA6: 30.448734 | AB6: 30.950203 | AC6: 31.476986 | AD6: 32.022718 | AE6: 32.586218 | AF6: 33.165029 | AG6: 33.757751 | AH6: 34.366546 | AI6: 34.986817 | AJ6: 35.631356 | AK6: 36.27383 | AL6: 36.942317 | AM6: 37.618281 | AN6: 38.319985 | AO6: 39.036003 | AP6: 39.762793 | AQ6: 40.268768 | AR6: 41.016494 | AS6: 41.77755 | AT6: 42.552073 | AU6: 43.339953 | AV6: 44.142127
A7: PNEWAUTO_H01_2 | B7: 21.709471 | C7: 22.143661 | D7: 22.427412 | E7: 22.848307 | F7: 22.933329 | G7: 23.426142 | H7: 23.5696 | I7: 23.683093 | J7: 23.92597 | K7: 24.295553 | L7: 24.902687 | M7: 25.458078 | N7: 26.001423 | O7: 26.798664 | P7: 27.117523 | Q7: 27.65052 | R7: 27.944791 | S7: 28.553731 | T7: 28.771901 | U7: 29.385402 | V7: 30.19359 | W7: 31.080272 | X7: 32.211894 | Y7: 33.723941 | Z7: 35.718738 | AA7: 37.941913 | AB7: 40.239144 | AC7: 42.39831 | AD7: 44.244163 | AE7: 45.726626 | AF7: 46.902478 | AG7: 47.870567 | AH7: 48.717856 | AI7: 49.504498 | AJ7: 50.279922 | AK7: 51.034549 | AL7: 51.806226 | AM7: 52.596942 | AN7: 53.412412 | AO7: 54.245029 | AP7: 55.088646 | AQ7: 55.63045 | AR7: 56.500822 | AS7: 57.387671 | AT7: 58.289663 | AU7: 59.207028 | AV7: 60.14144
A8: PCH_2 | B8: 0.96116878 | C8: 0.98039216 | D8: 0.98715712 | E8: 0.99036346 | F8: 1.0043122 | G8: 1.0057988 | H8: 1.0145862 | I8: 1.0232782 | J8: 1.032617 | K8: 1.0399768 | L8: 1.0501176 | M8: 1.0574685 | N8: 1.064722 | O8: 1.0798249 | P8: 1.1017374 | Q8: 1.1217746 | R8: 1.1440126 | S8: 1.1667712 | T8: 1.1905363 | U8: 1.2147495 | V8: 1.240596 | W8: 1.2670456 | X8: 1.2920881 | Y8: 1.3176177 | Z8: 1.344049 | AA8: 1.3724534 | AB8: 1.4017752 | AC8: 1.4309954 | AD8: 1.4602649 | AE8: 1.4900211 | AF8: 1.5204956 | AG8: 1.5513668 | AH8: 1.5828024 | AI8: 1.6148732 | AJ8: 1.6480149 | AK8: 1.6817155 | AL8: 1.7165612 | AM8: 1.7519466 | AN8: 1.7883149 | AO8: 1.8256092 | AP8: 1.8636105 | AQ8: 1.9024049 | AR8: 1.9421462 | AS8: 1.9826509 | AT8: 2.0238124 | AU8: 2.0656553 | AV8: 2.1084356
A9: AUTO_ELEC_H01_2 | B9: 2.3360541 | C9: 2.3735602 | D9: 2.4116685 | E9: 5.8260427 | F9: 11.217949 | G9: 19.754257 | H9: 31.283111 | I9: 46.7093 | J9: 64.606108 | K9: 87.121228 | L9: 116.85027 | M9: 152.4768 | N9: 201.38446 | O9: 268.65003 | P9: 357.04453 | Q9: 470.57431 | R9: 589.46975 | S9: 717.17235 | T9: 874.53933 | U9: 1068.6271 | V9: 1374.8721 | W9: 1761.0806 | X9: 2141.5277 | Y9: 2589.3068 | Z9: 3164.4372 | AA9: 3871.2114 | AB9: 4701.3032 | AC9: 5626.6239 | AD9: 6613.3651 | AE9: 7616.5984 | AF9: 8602.6002 | AG9: 9548.4719 | AH9: 10481.366 | AI9: 11381.335 | AJ9: 12229.565 | AK9: 13024.281 | AL9: 13758.119 | AM9: 14435.54 | AN9: 15057.047 | AO9: 15625.065 | AP9: 16141.312 | AQ9: 16588.045 | AR9: 17006.066 | AS9: 17389.523 | AT9: 17738.609 | AU9: 18051.847 | AV9: 18313.749
A10: AUTO_TH_H01_2 | B10: 30996.094 | C10: 31493.746 | D10: 31999.389 | E10: 32682.553 | F10: 33303.577 | G10: 34123.091 | H10: 34832.554 | I10: 35442.44 | J10: 35666.707 | K10: 35752.795 | L10: 35831.214 | M10: 35758.831 | N10: 35777.117 | O10: 36052.554 | P10: 36351.842 | Q10: 36643.17 | R10: 36600.346 | S10: 36327.656 | T10: 35862.882 | U10: 35304.988 | V10: 35118.535 | W10: 35013.044 | X10: 34507.675 | Y10: 33745.44 | Z10: 32759.076 | AA10: 31570.434 | AB10: 30217.301 | AC10: 28748.905 | AD10: 27222.694 | AE10: 25689.219 | AF10: 24186.893 | AG10: 22739.244 | AH10: 21358.636 | AI10: 20049.046 | AJ10: 18810.787 | AK10: 17642.221 | AL10: 16540.692 | AM10: 15507.449 | AN10: 14538.506 | AO10: 13629.984 | AP10: 12778.177 | AQ10: 11926.333 | AR10: 11131.261 | AS10: 10389.185 | AT10: 9696.577 | AU10: 9050.1406 | AV10: 8446.7989
A11: AUTO_2 | B11: 30998.43 | C11: 31496.12 | D11: 32001.8 | E11: 32688.379 | F11: 33314.795 | G11: 34142.845 | H11: 34863.837 | I11: 35489.149 | J11: 35731.314 | K11: 35839.916 | L11: 35948.064 | M11: 35911.307 | N11: 35978.501 | O11: 36321.204 | P11: 36708.886 | Q11: 37113.744 | R11: 37189.816 | S11: 37044.828 | T11: 36737.421 | U11: 36373.615 | V11: 36493.407 | W11: 36774.124 | X11: 36649.202 | Y11: 36334.746 | Z11: 35923.513 | AA11: 35441.645 | AB11: 34918.604 | AC11: 34375.529 | AD11: 33836.059 | AE11: 33305.818 | AF11: 32789.493 | AG11: 32287.716 | AH11: 31840.002 | AI11: 31430.381 | AJ11: 31040.353 | AK11: 30666.502 | AL11: 30298.81 | AM11: 29942.989 | AN11: 29595.553 | AO11: 29255.049 | AP11: 28919.489 | AQ11: 28514.378 | AR11: 28137.327 | AS11: 27778.708 | AT11: 27435.186 | AU11: 27101.988 | AV11: 26760.548
A12: PENER_AUTOELEC_H01_CA_2 | B12: 0.25383749 | C12: 0.25891424 | D12: 0.25652822 | E12: 0.2632583 | F12: 0.26012564 | G12: 0.26053308 | H12: 0.26147498 | I12: 0.26226138 | J12: 0.26370216 | K12: 0.26522646 | L12: 0.26828614 | M12: 0.27155537 | N12: 0.27593021 | O12: 0.27923703 | P12: 0.28294175 | Q12: 0.28964151 | R12: 0.29904186 | S12: 0.3078615 | T12: 0.31713878 | U12: 0.32535004 | V12: 0.32235119 | W12: 0.3233734 | X12: 0.33727094 | Y12: 0.344107 | Z12: 0.35016654 | AA12: 0.35504499 | AB12: 0.36077188 | AC12: 0.36837437 | AD12: 0.37631434 | AE12: 0.38454192 | AF12: 0.3938538 | AG12: 0.40102935 | AH12: 0.40688144 | AI12: 0.41482027 | AJ12: 0.42288617 | AK12: 0.43119502 | AL12: 0.44099694 | AM12: 0.44933934 | AN12: 0.4578026 | AO12: 0.46640562 | AP12: 0.47511859 | AQ12: 0.48377188 | AR12: 0.49351313 | AS12: 0.50278232 | AT12: 0.51215393 | AU12: 0.52184736 | AV12: 0.5318839
A13: PEXP_AUTO_H01_2 | B13: 0.96116878 | C13: 0.98039216 | D13: 0.98801884 | E13: 0.98669645 | F13: 1.0865767 | G13: 0.92641605 | H13: 1.006402 | I13: 1.1281116 | J13: 1.2272799 | K13: 1.2038813 | L13: 1.1516351 | M13: 1.0086765 | N13: 0.93008066 | O13: 1.0053342 | P13: 1.1682937 | Q13: 1.161239 | R13: 1.198542 | S13: 1.2390652 | T13: 1.2836593 | U13: 1.3328283 | V13: 1.3842822 | W13: 1.4453659 | X13: 1.4687068 | Y13: 1.4889683 | Z13: 1.5086637 | AA13: 1.5627148 | AB13: 1.6179093 | AC13: 1.6455475 | AD13: 1.6701098 | AE13: 1.692461 | AF13: 1.7133838 | AG13: 1.7312629 | AH13: 1.7415335 | AI13: 1.7527316 | AJ13: 1.7645484 | AK13: 1.7765547 | AL13: 1.7903575 | AM13: 1.8221755 | AN13: 1.8547443 | AO13: 1.8871289 | AP13: 1.9183452 | AQ13: 1.9482991 | AR13: 1.9866191 | AS13: 2.0245731 | AT13: 2.062559 | AU13: 2.1008939 | AV13: 2.1397864
... A44: BUIL_H01_CG_2 | B44: 1.8297097e+08 | C44: 1.8590863e+08 | D44: 188893454 | E44: 1.800399e+08 | F44: 1.7103185e+08 | G44: 1.6228071e+08 | H44: 154931207 | I44: 1.4786681e+08 | J44: 1.4048552e+08 | K44: 1.3272979e+08 | L44: 1.2536576e+08 | M44: 1.1900069e+08 | N44: 1.1407377e+08 | O44: 1.0969824e+08 | P44: 1.0510932e+08 | Q44: 99294803 | R44: 93330572 | S44: 87081895 | T44: 81129942 | U44: 75317528 | V44: 69772300 | W44: 64145791 | X44: 58697289 | Y44: 53648745 | Z44: 49072799 | AA44: 44955491 | AB44: 41129231 | AC44: 37522011 | AD44: 34237101 | AE44: 31283742 | AF44: 28626476 | AG44: 26233092 | AH44: 24078571 | AI44: 22136964 | AJ44: 20388007 | AK44: 18798009 | AL44: 17299285 | AM44: 15898777 | AN44: 14618261 | AO44: 13455202 | AP44: 12401609 | AQ44: 11448581 | AR44: 10579145 | AS44: 9763681.3 | AT44: 8993692.7 | AU44: 8267101 | AV44: 7583904.4
A45: BUIL_H01_DES_2 | C45: 2182612 | D45: 2217654.6 | E45: 2253259.7 | F45: 2197348 | G45: 2135517.6 | H45: 2073850.5 | I45: 2025887.2 | J45: 1978454.7 | K45: 1924316.5 | L45: 1863141.2 | M45: 1803611.1 | N45: 1753745.6 | O45: 1720550.5 | P45: 1692851.5 | Q45: 1659938.1 | R45: 1607861.2 | S45: 1600180.9 | T45: 1582221.9 | U45: 1561512.8 | V45: 1535852.1 | W45: 1506701.1 | X45: 1467194 | Y45: 1421395.6 | Z45: 1374795.2 | AA45: 1329979.1 | AB45: 1287891.8 | AC45: 1245826.3 | AD45: 1202264.4 | AE45: 1160042.6 | AF45: 1120276.2 | AG45: 1082779.5 | AH45: 1047494.9 | AI45: 1014630 | AJ45: 983997.17 | AK45: 955475.43 | AL45: 928605.02 | AM45: 901399.43 | AN45: 874136.09 | AO45: 847912.79 | AP45: 822934.91 | AQ45: 799261.63 | AR45: 776929.88 | AS45: 755589.74 | AT45: 734173.89 | AU45: 712429.96 | AV45: 690388.21
A46: REHAB_H01_2 | B46: 27240235 | C46: 27677586 | D46: 28121958 | E46: 39354810 | F46: 45364406 | G46: 45516119 | H46: 35070344 | I46: 35012114 | J46: 39899401 | K46: 46533664 | L46: 46964548 | M46: 41281813 | N46: 28952518 | O46: 30282525 | P46: 37773608 | Q46: 62400636 | R46: 69799680 | S46: 83652349 | T46: 84518164 | U46: 91632163 | V46: 97274360 | W46: 1.1595549e+08 | X46: 1.2880736e+08 | Y46: 1.3565586e+08 | Z46: 137263444 | AA46: 1.3491452e+08 | AB46: 1.3439637e+08 | AC46: 1.3641965e+08 | AD46: 1.3439525e+08 | AE46: 1.3109101e+08 | AF46: 1.2844675e+08 | AG46: 1.2553121e+08 | AH46: 1.2183729e+08 | AI46: 1.1859032e+08 | AJ46: 115620910 | AK46: 1.1330334e+08 | AL46: 1.1467643e+08 | AM46: 1.1486883e+08 | AN46: 1.1328279e+08 | AO46: 111072346 | AP46: 1.086155e+08 | AQ46: 1.0604011e+08 | AR46: 1.0393592e+08 | AS46: 1.0343455e+08 | AT46: 1.0322588e+08 | AU46: 1.0302058e+08 | AV46: 1.0274601e+08
A47: PREHAB_H01_2 | B47: 0.00017092114 | C47: 0.00017433956 | D47: 0.00017633719 | E47: 0.00014003564 | F47: 0.00014683287 | G47: 0.00015141592 | H47: 0.00015511363 | I47: 0.00015050677 | J47: 0.00016363455 | K47: 0.00015928559 | L47: 0.00015397907 | M47: 0.00014433845 | N47: 0.00013845886 | O47: 0.00011055861 | P47: 0.00012352136 | Q47: 0.00011079756 | R47: 0.00013276872 | S47: 0.00011200677 | T47: 0.00013078063 | U47: 0.00012892418 | V47: 0.00012649794 | W47: 0.00010729722 | X47: 0.00011664318 | Y47: 0.0001208241 | Z47: 0.00012165578 | AA47: 0.00012657862 | AB47: 0.00012758377 | AC47: 0.00012573239 | AD47: 0.0001303423 | AE47: 0.00013238169 | AF47: 0.000133139 | AG47: 0.00013659325 | AH47: 0.0001390166 | AI47: 0.00013995737 | AJ47: 0.00014326831 | AK47: 0.00014640662 | AL47: 0.00014567904 | AM47: 0.00015178037 | AN47: 0.00015528484 | AO47: 0.00015900265 | AP47: 0.00016277008 | AQ47: 0.00016679302 | AR47: 0.00017118244 | AS47: 0.00017672661 | AT47: 0.00018248677 | AU47: 0.00018826636 | AV47: 0.00019412583
A48: RENOV_VAL_2 | B48: 4655.932 | C48: 4825.2982 | D48: 4958.9473 | E48: 6685.0332 | F48: 8079.8942 | G48: 8204.6011 | H48: 6325.4515 | I48: 6303.711 | J48: 7395.6572 | K48: 8536.6752 | L48: 8693.9841 | M48: 7712.534 | N48: 5313.4787 | O48: 5170.6902 | P48: 6806.4049 | Q48: 11316.814 | R48: 13348.567 | S48: 15518.483 | T48: 16503.877 | U48: 17459.256 | V48: 18547.27 | W48: 22244.757 | X48: 26036.538 | Y48: 27305.765 | Z48: 27525.502 | AA48: 27251.659 | AB48: 27297.173 | AC48: 28143.158 | AD48: 28368.514 | AE48: 27948.067 | AF48: 27728.363 | AG48: 27559.621 | AH48: 27093.875 | AI48: 26743.452 | AJ48: 26545.082 | AK48: 26411.146 | AL48: 27178.602 | AM48: 27926.444 | AN48: 27930.8 | AO48: 27838.396 | AP48: 27695.138 | AQ48: 27552.999 | AR48: 27553.339 | AS48: 28074.184 | AT48: 28700.476 | AU48: 29337.746 | AV48: 29971.538
A49: SUB_RENOV_VAL_2 | B49: 0 | C49: 0 | D49: 0 | E49: 1173.9571 | F49: 1418.9082 | G49: 1312.7362 | H49: 885.56321 | I49: 778.65691 | J49: 616.14297 | K49: 878.41651 | L49: 1198.0624 | M49: 1550.8859 | N49: 968.05518 | O49: 1025.6624 | P49: 872.60071 | Q49: 1541.5524 | R49: 1535.9671 | S49: 3033.2484 | T49: 2272.6217 | U49: 2404.1796 | V49: 2935.9589 | W49: 4004.0563 | X49: 5728.0383 | Y49: 6007.2684 | Z49: 6055.6104 | AA49: 5995.3651 | AB49: 6005.378 | AC49: 7035.7896 | AD49: 7092.1286 | AE49: 6987.0167 | AF49: 6932.0907 | AG49: 6889.9053 | AH49: 6773.4687 | AI49: 6685.863 | AJ49: 6636.2706 | AK49: 6602.7864 | AL49: 6794.6506 | AM49: 6981.6109 | AN49: 6982.6999 | AO49: 6959.5991 | AP49: 6923.7845 | AQ49: 6888.2498 | AR49: 6888.3348 | AS49: 7018.5461 | AT49: 7175.1191 | AU49: 7334.4365 | AV49: 7492.8846
A50: R_SUB_CEE_H01_CF_CA_2 | B50: 0 | C50: 0 | D50: 0 | E50: 0 | F50: 0 | G50: 0 | H50: 0 | I50: 0.040530719 | J50: 0.033883896 | K50: 0.028830481 | L50: 0.03040774 | M50: 0.02633315 | N50: 0.06336543 | O50: 0.15414461 | P50: 0.18628877 | Q50: 0.25284707 | R50: 0.19068605 | S50: 0.20076736 | T50: 0.19255578 | U50: 0.18565941 | V50: 0.17826369 | W50: 0.26069064 | X50: 0.20294557 | Y50: 0.17974226 | Z50: 0.17333017 | AA50: 0.15334846 | AB50: 0.15184723 | AC50: 0.14053149 | AD50: 0.13250606 | AE50: 0.12906081 | AF50: 0.13325706 | AG50: 0.12783195 | AH50: 0.12486217 | AI50: 0.12937746 | AJ50: 0.12597437 | AK50: 0.12191822 | AL50: 0.13532705 | AM50: 0.12568732 | AN50: 0.1201899 | AO50: 0.11559574 | AP50: 0.11164415 | AQ50: 0.10808261 | AR50: 0.10427048 | AS50: 0.098880879 | AT50: 0.093656982 | AU50: 0.088895718 | AV50: 0.084513513
A51: ER_TERTIARY_2 | B51: 21.072807 | C51: 21.411137 | D51: 21.7549 | E51: 23.111168 | F51: 23.885852 | G51: 23.444481 | H51: 24.603056 | I51: 25.441776 | J51: 25.783656 | K51: 26.232663 | L51: 27.090239 | M51: 28.31981 | N51: 27.949439 | O51: 27.547144 | P51: 26.801156 | Q51: 25.826825 | R51: 25.021981 | S51: 25.034436 | T51: 25.010957 | U51: 25.113654 | V51: 26.519548 | W51: 27.201105 | X51: 27.256033 | Y51: 27.037315 | Z51: 26.611801 | AA51: 25.903202 | AB51: 25.088331 | AC51: 24.859818 | AD51: 24.591356 | AE51: 24.320338 | AF51: 24.020209 | AG51: 23.726902 | AH51: 23.458023 | AI51: 23.189274 | AJ51: 22.92006 | AK51: 22.538032 | AL51: 22.148524 | AM51: 21.891927 | AN51: 21.650225 | AO51: 21.414706 | AP51: 21.186972 | AQ51: 20.966861 | AR51: 20.638076 | AS51: 20.304297 | AT51: 19.974269 | AU51: 19.648139 | AV51: 19.326158
A52: ER_TERTIARY_COAL_2 | B52: 0 | C52: 0 | D52: 0 | E52: 0 | F52: 0 | G52: 0 | H52: 0 | I52: 0 | J52: 0 | K52: 0 | L52: 0 | M52: 0 | N52: 0 | O52: 0 | P52: 0 | Q52: 0 | R52: 0 | S52: 0 | T52: 0 | U52: 0 | V52: 0 | W52: 0 | X52: 0 | Y52: 0 | Z52: 0 | AA52: 0 | AB52: 0 | AC52: 0 | AD52: 0 | AE52: 0 | AF52: 0 | AG52: 0 | AH52: 0 | AI52: 0 | AJ52: 0 | AK52: 0 | AL52: 0 | AM52: 0 | AN52: 0 | AO52: 0 | AP52: 0 | AQ52: 0 | AR52: 0 | AS52: 0 | AT52: 0 | AU52: 0 | AV52: 0
A53: ER_TERTIARY_OIL_2 | B53: 4.6065844 | C53: 4.6805446 | D53: 4.7556923 | E53: 4.8584285 | F53: 4.6740887 | G53: 4.613069 | H53: 4.5416749 | I53: 4.34262 | J53: 4.1268973 | K53: 4.0489182 | L53: 4.0627365 | M53: 4.1781675 | N53: 3.9170705 | O53: 3.6404446 | P53: 3.4042399 | Q53: 3.2198847 | R53: 3.0142307 | S53: 3.0092941 | T53: 3.0128964 | U53: 2.9978702 | V53: 2.5198912 | W53: 2.1738888 | X53: 1.936867 | Y53: 1.745639 | Z53: 1.5888209 | AA53: 1.4767656 | AB53: 1.3827105 | AC53: 1.3700012 | AD53: 1.3645723 | AE53: 1.3597624 | AF53: 1.3594807 | AG53: 1.3579402 | AH53: 1.3526566 | AI53: 1.3475424 | AJ53: 1.3425069 | AK53: 1.3542536 | AL53: 1.3672689 | AM53: 1.3603821 | AN53: 1.351248 | AO53: 1.3411901 | AP53: 1.3299812 | AQ53: 1.3176324 | AR53: 1.3213842 | AS53: 1.3257794 | AT53: 1.329558 | AU53: 1.3327233 | AV53: 1.3352486
A54: ER_TERTIARY_ELEC_2 | B54: 10.826676 | C54: 11.000502 | D54: 11.177119 | E54: 11.887835 | F54: 12.504639 | G54: 11.787154 | H54: 12.310258 | I54: 12.871045 | J54: 13.217653 | K54: 13.280641 | L54: 13.295465 | M54: 13.068313 | N54: 12.451329 | O54: 12.503449 | P54: 12.948172 | Q54: 12.810045 | R54: 12.634897 | S54: 12.736727 | T54: 12.766863 | U54: 12.742245 | V54: 12.828497 | W54: 12.393795 | X54: 11.740228 | Y54: 11.049657 | Z54: 10.375912 | AA54: 9.880389 | AB54: 9.423375 | AC54: 9.3467049 | AD54: 9.287598 | AE54: 9.225843 | AF54: 9.1878654 | AG54: 9.1516324 | AH54: 9.0925071 | AI54: 9.0249027 | AJ54: 8.9559184 | AK54: 8.9942901 | AL54: 9.0334262 | AM54: 8.9550656 | AN54: 8.8645256 | AO54: 8.7684864 | AP54: 8.6647257 | AQ54: 8.5542553 | AR54: 8.542791 | AS54: 8.5374617 | AT54: 8.5284833 | AU54: 8.5146733 | AV54: 8.4956784
A55: ER_TERTIARY_GAS_2 | B55: 5.6395461 | C55: 5.7300908 | D55: 5.8220893 | E55: 6.3649049 | F55: 6.7071242 | G55: 7.0442581 | H55: 7.7511234 | I55: 8.2281112 | J55: 8.4391064 | K55: 8.9031038 | L55: 9.7320375 | M55: 11.07333 | N55: 11.581039 | O55: 11.403251 | P55: 10.448744 | Q55: 9.7968949 | R55: 9.3728535 | S55: 9.2884151 | T55: 9.2311979 | U55: 9.3735384 | V55: 11.17116 | W55: 12.63342 | X55: 13.578938 | Y55: 14.242019 | Z55: 14.647067 | AA55: 14.546047 | AB55: 14.282246 | AC55: 14.143112 | AD55: 13.939186 | AE55: 13.734732 | AF55: 13.472863 | AG55: 13.217329 | AH55: 13.012859 | AI55: 12.816829 | AJ55: 12.621635 | AK55: 12.189488 | AL55: 11.747829 | AM55: 11.576479 | AN55: 11.434452 | AO55: 11.30503 | AP55: 11.192265 | AQ55: 11.094974 | AR55: 10.773901 | AS55: 10.441055 | AT55: 10.116228 | AU55: 9.8007422 | AV55: 9.4952308
A56: EMS_SEC_TOT_19_2 | B56: 20640521 | C56: 20971911 | D56: 21313933 | E56: 22206970 | F56: 21946561 | G56: 21680617 | H56: 22244065 | I56: 22089159 | J56: 21448171 | K56: 21467673 | L56: 22211890 | M56: 23793446 | N56: 23724535 | O56: 22820726 | P56: 21088588 | Q56: 19827775 | R56: 18787404 | S56: 18229321 | T56: 17715657 | U56: 17208680 | V56: 17907876 | W56: 18404028 | X56: 18280598 | Y56: 17913507 | Z56: 17328118 | AA56: 16367832 | AB56: 15311733 | AC56: 13867909 | AD56: 12435971 | AE56: 11057835 | AF56: 10177626 | AG56: 9325349.3 | AH56: 8480360.8 | AI56: 7659982.6 | AJ56: 6855590.1 | AK56: 7287008.6 | AL56: 7608164.6 | AM56: 6582462.8 | AN56: 5598218.1 | AO56: 4643474.9 | AP56: 3713633.4 | AQ56: 2800021.6 | AR56: 2994140.5 | AS56: 3159782.1 | AT56: 3300873.4 | AU56: 3419025.6 | AV56: 3515820.6
A57: EMS_SEC_TOT_20_2 | B57: 5733144.5 | C57: 5825191.9 | D57: 5919233.7 | E57: 6053525.2 | F57: 6003086.6 | G57: 6290808 | H57: 6414227.9 | I57: 6373952.7 | J57: 6246017.5 | K57: 6309819 | L57: 6515336.1 | M57: 6967670.1 | N57: 7036455.2 | O57: 6747901.3 | P57: 6121807.8 | Q57: 5688631.4 | R57: 5357163.9 | S57: 5121868.2 | T57: 4905286.8 | U57: 4704772 | V57: 5015786.9 | W57: 5189004 | X57: 5123541.5 | Y57: 4979584.4 | Z57: 4773546.8 | AA57: 4468832.6 | AB57: 4144683.4 | AC57: 3701758.8 | AD57: 3267600.8 | AE57: 2851903.1 | AF57: 2603735.7 | AG57: 2365895 | AH57: 2133728.2 | AI57: 1912070 | AJ57: 1698884.2 | AK57: 1910311.4 | AL57: 2095350.8 | AM57: 1784757.4 | AN57: 1489293.2 | AO57: 1205788 | AP57: 933343.45 | AQ57: 670211.78 | AR57: 754267.82 | AS57: 830073.04 | AT57: 898811.86 | AU57: 960946.53 | AV57: 1016963.1
... A562: I_MDE_14_2 | B562: 528.06275 | C562: 536.54097 | D562: 509.09232 | E562: 725.67716 | F562: 692.31355 | G562: 505.49928 | H562: 764.92789 | I562: 921.48445 | J562: 889.35546 | K562: 842.51177 | L562: 822.04169 | M562: 863.35214 | N562: 479.51703 | O562: 841.13881 | P562: 899.10766 | Q562: 753.75232 | R562: 852.06465 | S562: 6504.2346 | T562: 5016.7551 | U562: 5392.2901 | V562: 6102.718 | W562: 5569.1962 | X562: 5121.7568 | Y562: 5320.4735 | Z562: 5412.8895 | AA562: 5543.2657 | AB562: 5752.9629 | AC562: 5771.0457 | AD562: 5804.0213 | AE562: 5879.424 | AF562: 5986.8111 | AG562: 6110.6888 | AH562: 6257.7367 | AI562: 6365.1288 | AJ562: 6337.6763 | AK562: 6421.2484 | AL562: 6458.7382 | AM562: 6629.3111 | AN562: 6715.5924 | AO562: 6756.9618 | AP562: 6832.5934 | AQ562: 6904.3651 | AR562: 6991.76 | AS562: 7131.4865 | AT562: 7267.4192 | AU562: 7372.8218 | AV562: 7478.5703
A563: I_MDE_15_2 | C563: 25.563692 | D563: 27.174516 | E563: 59.014301 | F563: 62.266563 | G563: 66.091101 | H563: 70.100616 | I563: 75.499498 | J563: 75.503546 | K563: 76.823477 | L563: 85.080937 | M563: 75.917302 | N563: 53.370951 | O563: 87.446867 | P563: 94.174744 | Q563: 232.53303 | R563: 297.98834 | S563: 401.08835 | T563: 353.0158 | U563: 304.96954 | V563: 1161.3012 | W563: 1213.9456 | X563: 814.54693 | Y563: 850.968 | Z563: 884.30902 | AA563: 913.869 | AB563: 941.68948 | AC563: 1308.3323 | AD563: 1343.0046 | AE563: 1379.0191 | AF563: 1416.2126 | AG563: 1453.0819 | AH563: 1623.9422 | AI563: 1677.2766 | AJ563: 1721.0662 | AK563: 1776.9675 | AL563: 1818.7793 | AM563: 1725.5093 | AN563: 1765.2821 | AO563: 1809.3236 | AP563: 1850.2294 | AQ563: 1919.6468 | AR563: 1684.8342 | AS563: 1710.1926 | AT563: 1741.6405 | AU563: 1767.5071 | AV563: 1755.0256
A564: I_MDE_16_2 | C564: 32.611451 | D564: 37.137185 | E564: 37.560493 | F564: 59.347566 | G564: 80.304664 | H564: 101.93379 | I564: 120.87487 | J564: 153.7942 | K564: 186.91817 | L564: 217.76751 | M564: 263.26599 | N564: 260.33005 | O564: 337.82378 | P564: 334.0845 | Q564: 416.89997 | R564: 452.97004 | S564: 1333.6678 | T564: 1193.0527 | U564: 1138.4541 | V564: 2543.3475 | W564: 2529.288 | X564: 6546.7007 | Y564: 6839.6106 | Z564: 7120.2364 | AA564: 7353.3567 | AB564: 7639.8673 | AC564: 13026.634 | AD564: 13560.685 | AE564: 14187.043 | AF564: 14809.117 | AG564: 15501.696 | AH564: 19721.558 | AI564: 20859.186 | AJ564: 21720.941 | AK564: 23287.695 | AL564: 24032.799 | AM564: 21244.129 | AN564: 21689.201 | AO564: 22567.084 | AP564: 23653.043 | AQ564: 24394.387 | AR564: 19246.616 | AS564: 19865.791 | AT564: 20363.477 | AU564: 20830.066 | AV564: 21300.935
A565: I_MDE_17_2 | B565: 534.35075 | C565: 542.92993 | D565: 546.81091 | E565: 569.83881 | F565: 606.47755 | G565: 368.21115 | H565: 525.58189 | I565: 605.3048 | J565: 589.55305 | K565: 581.06324 | L565: 586.84064 | M565: 640.91957 | N565: 605.51066 | O565: 716.90508 | P565: 776.56361 | Q565: 732.32542 | R565: 712.94488 | S565: 687.30827 | T565: 692.54602 | U565: 708.2562 | V565: 713.04136 | W565: 716.08073 | X565: 715.50659 | Y565: 719.71887 | Z565: 725.39796 | AA565: 793.15793 | AB565: 809.15781 | AC565: 773.43679 | AD565: 770.96118 | AE565: 775.47299 | AF565: 782.19484 | AG565: 790.31066 | AH565: 783.18707 | AI565: 791.60448 | AJ565: 802.16977 | AK565: 815.12104 | AL565: 827.67209 | AM565: 874.10494 | AN565: 892.95552 | AO565: 903.43132 | AP565: 911.90041 | AQ565: 918.57733 | AR565: 952.74778 | AS565: 975.05222 | AT565: 994.86011 | AU565: 1013.652 | AV565: 1032.1358
A566: I_MDE_18_2 | B566: 970.42802 | C566: 986.00856 | D566: 991.19398 | E566: 1069.1726 | F566: 1193.4499 | G566: 752.11733 | H566: 1072.1105 | I566: 1256.8962 | J566: 1230.0432 | K566: 1187.1796 | L566: 1113.3729 | M566: 1149.7972 | N566: 1051.2057 | O566: 1345.4529 | P566: 1484.6629 | Q566: 1386.3185 | R566: 1345.9331 | S566: 1313.5488 | T566: 1307.8935 | U566: 1312.298 | V566: 1313.5134 | W566: 1308.095 | X566: 1250.3397 | Y566: 1227.5968 | Z566: 1219.7659 | AA566: 1215.6837 | AB566: 1219.9137 | AC566: 1210.5593 | AD566: 1194.1601 | AE566: 1180.3427 | AF566: 1168.2348 | AG566: 1157.3885 | AH566: 1149.3597 | AI566: 1142.2231 | AJ566: 1131.6665 | AK566: 1122.8944 | AL566: 1112.8178 | AM566: 1119.1533 | AN566: 1114.9185 | AO566: 1106.8728 | AP566: 1098.4953 | AQ566: 1088.9555 | AR566: 1086.2268 | AS566: 1080.6155 | AT566: 1075.064 | AU566: 1069.3317 | AV566: 1064.0712
A567: ER_COAL_2 | B567: 5.570579 | C567: 5.6600164 | D567: 5.7508898 | E567: 5.7929036 | F567: 4.8242806 | G567: 4.2185211 | H567: 4.084085 | I567: 3.8991141 | J567: 3.7615492 | K567: 4.0026494 | L567: 4.0988615 | M567: 4.1630921 | N567: 3.2553048 | O567: 2.7334405 | P567: 2.3991506 | Q567: 2.1834951 | R567: 1.9973772 | S567: 2.0030384 | T567: 1.9618528 | U567: 1.6610309 | V567: 1.2772449 | W567: 0.92575411 | X567: 0.69174807 | Y567: 0.53580483 | Z567: 0.4260706 | AA567: 0.34680263 | AB567: 0.28925689 | AC567: 0.25657292 | AD567: 0.23321539 | AE567: 0.21451149 | AF567: 0.19917428 | AG567: 0.18631372 | AH567: 0.1757918 | AI567: 0.16688974 | AJ567: 0.15927524 | AK567: 0.15269725 | AL567: 0.14683961 | AM567: 0.14099639 | AN567: 0.13541444 | AO567: 0.13015768 | AP567: 0.12531883 | AQ567: 0.12049284 | AR567: 0.11649806 | AS567: 0.11292355 | AT567: 0.10959598 | AU567: 0.10647685 | AV567: 0.10358393
A568: ER_OIL_2201_2 | B568: 77.477679 | C568: 78.721608 | D568: 80.00373 | E568: 80.189475 | F568: 76.950267 | G568: 74.603074 | H568: 73.063966 | I568: 71.285518 | J568: 69.186514 | K568: 67.614613 | L568: 67.318829 | M568: 67.648774 | N568: 66.103925 | O568: 64.464309 | P568: 62.191245 | Q568: 60.914616 | R568: 59.282102 | S568: 58.819585 | T568: 57.857999 | U568: 56.687406 | V568: 54.305864 | W568: 51.807127 | X568: 49.68164 | Y568: 47.68183 | Z568: 45.719261 | AA568: 43.669959 | AB568: 41.632447 | AC568: 38.989065 | AD568: 36.406034 | AE568: 33.849965 | AF568: 31.348666 | AG568: 28.877322 | AH568: 26.288081 | AI568: 23.727129 | AJ568: 21.146548 | AK568: 18.639534 | AL568: 16.06478 | AM568: 14.55891 | AN568: 13.026572 | AO568: 11.479191 | AP568: 9.9091311 | AQ568: 8.2726722 | AR568: 7.7678515 | AS568: 7.2746207 | AT568: 6.7903086 | AU568: 6.3113492 | AV568: 5.8348928
A569: ER_OIL_2202_2 | B569: 0.67805251 | C569: 0.68893886 | D569: 0.66746531 | E569: 1.0023107 | F569: 1.2829737 | G569: 1.5564776 | H569: 1.8318169 | I569: 2.0884318 | J569: 2.3204771 | K569: 2.555809 | L569: 2.832603 | M569: 3.1370651 | N569: 3.1170784 | O569: 3.0934185 | P569: 3.0395931 | Q569: 3.0350888 | R569: 3.0141586 | S569: 3.1567748 | T569: 3.2641188 | U569: 3.3496156 | V569: 3.5892509 | W569: 3.8160074 | X569: 3.8258444 | Y569: 3.8471291 | Z569: 3.8740971 | AA569: 3.8930668 | AB569: 3.9159795 | AC569: 4.5228862 | AD569: 5.1431892 | AE569: 5.7777127 | AF569: 6.4245159 | AG569: 7.0999697 | AH569: 7.8762626 | AI569: 8.7017406 | AJ569: 9.5785704 | AK569: 10.515148 | AL569: 11.542585 | AM569: 11.744039 | AN569: 11.976428 | AO569: 12.26697 | AP569: 12.639618 | AQ569: 13.084196 | AR569: 12.720393 | AS569: 12.388406 | AT569: 12.089509 | AU569: 11.824755 | AV569: 11.598483
A570: ER_ELEC_2301_2 | B570: 28.634797 | C570: 29.094538 | D570: 29.720948 | E570: 30.52551 | F570: 31.195934 | G570: 29.010321 | H570: 30.081874 | I570: 31.084929 | J570: 31.401742 | K570: 31.225922 | L570: 31.043343 | M570: 30.417636 | N570: 28.689727 | O570: 28.16767 | P570: 28.076537 | Q570: 27.095231 | R570: 26.128889 | S570: 26.107046 | T570: 25.987033 | U570: 25.617845 | V570: 26.527877 | W570: 26.932054 | X570: 26.574237 | Y570: 26.19228 | Z570: 25.803509 | AA570: 25.580586 | AB570: 25.401137 | AC570: 24.637125 | AD570: 23.888472 | AE570: 23.157393 | AF570: 22.345994 | AG570: 21.545536 | AH570: 21.260952 | AI570: 20.967053 | AJ570: 20.673978 | AK570: 20.488028 | AL570: 20.275691 | AM570: 19.506261 | AN570: 18.741035 | AO570: 17.984202 | AP570: 17.239916 | AQ570: 16.495768 | AR570: 15.782155 | AS570: 15.083867 | AT570: 14.393676 | AU570: 13.708427 | AV570: 13.029001
A571: ER_ELEC_2302_2 | B571: 0.3674935 | C571: 0.37339372 | D571: 0.38143295 | E571: 0.37117253 | F571: 0.35939186 | G571: 0.31665047 | H571: 0.31109271 | I571: 0.30457354 | J571: 0.29150996 | K571: 0.27464537 | L571: 0.25869191 | M571: 0.24015806 | N571: 0.20849842 | O571: 0.18561328 | P571: 0.16441312 | Q571: 0.13707606 | R571: 0.1094941 | S571: 0.14544881 | T571: 0.18182678 | U571: 0.21697037 | V571: 0.15387005 | W571: 0.091662563 | X571: 0.069698127 | Y571: 0.048217946 | Z571: 0.02729822 | AA571: 0.024312471 | AB571: 0.021405409 | AC571: 0.020914285 | AD571: 0.0204328 | AE571: 0.019962955 | AF571: 0.019406315 | AG571: 0.01885401 | AH571: 0.015171895 | AI571: 0.011547945 | AJ571: 0.0079914716 | AK571: 0.0085552944 | AL571: 0.0091004171 | AM571: 0.0087405753 | AN571: 0.0083828802 | AO571: 0.0080292172 | AP571: 0.0076814439 | AQ571: 0.0073340372 | AR571: 0.0072820379 | AS571: 0.0072333015 | AT571: 0.00718462 | AU571: 0.0071343593 | AV571: 0.0070827861
A572: ER_ELEC_2303_2 | B572: 1.4676116 | C572: 1.4911746 | D572: 1.5232798 | E572: 1.5667914 | F572: 1.6035313 | G572: 1.4933554 | H572: 1.5507677 | I572: 1.6048075 | J572: 1.6235214 | K572: 1.6167793 | L572: 1.6096637 | M572: 1.5795135 | N572: 1.6684922 | O572: 1.8274882 | P572: 2.0258946 | Q572: 2.1692357 | R572: 2.3169547 | S572: 2.2378991 | T572: 2.1483525 | U572: 2.0371177 | V572: 2.2378843 | W572: 2.3890374 | X572: 2.2974836 | Y572: 2.2054214 | Z572: 2.1144375 | AA572: 2.040131 | AB572: 1.9700533 | AC572: 1.8439418 | AD572: 1.7204685 | AE572: 1.5997456 | AF572: 1.4812359 | AG572: 1.3657105 | AH572: 1.108634 | AI572: 0.85558445 | AJ572: 0.60723516 | AK572: 0.37736421 | AL572: 0.14971904 | AM572: 0.15909857 | AN572: 0.1682392 | AO572: 0.17716623 | AP572: 0.18591805 | AQ572: 0.19435361 | AR572: 0.20065424 | AS572: 0.20693857 | AT572: 0.21312174 | AU572: 0.21915373 | AV572: 0.22503803
A573: ER_ELEC_2304_2 | B573: 1.4643634 | C573: 1.4878742 | D573: 1.5199084 | E573: 1.4374556 | F573: 1.3527148 | G573: 1.1583439 | H573: 1.1060293 | I573: 1.0524182 | J573: 0.97896903 | K573: 0.89641111 | L573: 0.82061072 | M573: 0.74040767 | N573: 0.62013914 | O573: 0.52598398 | P573: 0.43486356 | Q573: 0.32594416 | R573: 0.21581314 | S573: 0.2083253 | T573: 0.19985741 | U573: 0.18937001 | V573: 0.1209189 | W573: 0.054225167 | X573: 0.041645274 | Y573: 0.029340559 | Z573: 0.017355756 | AA573: 0.017224345 | AB573: 0.017121954 | AC573: 0.014112868 | AD573: 0.011168116 | AE573: 0.0082869669 | AF573: 0.0081429994 | AG573: 0.0079977237 | AH573: 0.0079252787 | AI573: 0.0078487354 | AJ573: 0.0077718521 | AK573: 0.0077304669 | AL573: 0.0076787813 | AM573: 0.0076130083 | AN573: 0.0075447836 | AO573: 0.0074756089 | AP573: 0.0074071737 | AQ573: 0.0073340372 | AR573: 0.0072820379 | AS573: 0.0072333015 | AT573: 0.00718462 | AU573: 0.0071343593 | AV573: 0.0070827861
A574: ER_ELEC_2305_2 | B574: 0.29584764 | C574: 0.30059757 | D574: 0.30706949 | E574: 0.65474226 | F574: 0.98938789 | G574: 1.1913305 | H574: 1.4861652 | I574: 1.7591862 | J574: 1.9607947 | K574: 2.0825344 | L574: 2.1417785 | M574: 2.0949807 | N574: 2.2292512 | O574: 2.4570621 | P574: 2.7386938 | Q574: 2.946486 | R574: 3.1604122 | S574: 3.3567812 | T574: 3.5458839 | U574: 3.7037979 | V574: 3.9240426 | W574: 4.0646679 | X574: 4.2944014 | Y574: 4.5127451 | Z574: 4.7220784 | AA574: 4.9468172 | AB574: 5.1763549 | AC574: 5.7600797 | AD574: 6.330931 | AE574: 6.8900189 | AF574: 7.3555062 | AG574: 7.7990257 | AH574: 8.3073389 | AI574: 8.8004722 | AJ574: 9.2820163 | AK574: 9.77144 | AL574: 10.241356 | AM574: 10.774443 | AN574: 11.293134 | AO574: 11.799198 | AP574: 12.295208 | AQ574: 12.771869 | AR574: 13.267435 | AS574: 13.760837 | AT574: 14.246503 | AU574: 14.721073 | AV574: 15.184739
A575: ER_ELEC_2306_2 | B575: 0.066565719 | C575: 0.067634453 | D575: 0.069090634 | E575: 0.094406599 | F575: 0.12835723 | G575: 0.15880266 | H575: 0.2190751 | I575: 0.30117639 | J575: 0.40476942 | K575: 0.53549095 | L575: 0.70825272 | M575: 0.92326874 | N575: 0.98244244 | O575: 1.0828398 | P575: 1.2069564 | Q575: 1.2985315 | R575: 1.3928099 | S575: 1.4590186 | T575: 1.5215543 | U575: 1.5704523 | V575: 1.7965841 | W575: 1.9792506 | X575: 2.3145396 | Y575: 2.6381827 | Z575: 2.9511529 | AA575: 3.2653661 | AB575: 3.5805127 | AC575: 3.907311 | AD575: 4.2268704 | AE575: 4.5398904 | AF575: 4.7922373 | AG575: 5.0320494 | AH575: 5.2363153 | AI575: 5.4331764 | AJ575: 5.6249654 | AK575: 5.8291198 | AL575: 6.0226887 | AM575: 6.2570844 | AN575: 6.4844315 | AO575: 6.7058006 | AP575: 6.9226638 | AQ575: 7.129815 | AR575: 7.2870747 | AS575: 7.4447248 | AT575: 7.5996513 | AU575: 7.7500838 | AV575: 7.8961845
A576: ER_ELEC_2307_2 | B576: 3.3276745 | C576: 3.3811014 | D576: 3.4538971 | E576: 3.422464 | F576: 3.3744515 | G576: 3.0275196 | H576: 3.0287857 | I576: 3.0195538 | J576: 2.9429024 | K576: 2.8233624 | L576: 2.7080026 | M576: 2.5599724 | N576: 2.724045 | O576: 3.0024196 | P576: 3.3465609 | Q576: 3.6004737 | R576: 3.8618819 | S576: 4.0825224 | T576: 4.2938366 | U576: 4.4671415 | V576: 4.438122 | W576: 4.3346178 | X576: 4.2861762 | Y576: 4.2335996 | Z576: 4.1796691 | AA576: 4.1503869 | AB576: 4.1280655 | AC576: 4.1282222 | AD576: 4.1281842 | AE576: 4.1284222 | AF576: 4.0786299 | AG576: 4.0274034 | AH576: 3.9612529 | AI576: 3.8936117 | AJ576: 3.8263763 | AK576: 3.7825542 | AL576: 3.7339743 | AM576: 3.7221096 | AN576: 3.7086922 | AO576: 3.6944447 | AP576: 3.6801989 | AQ576: 3.6632433 | AR576: 3.6286849 | AS576: 3.5958712 | AT576: 3.5631996 | AU576: 3.5298614 | AV576: 3.495994
... A583: ER_GAS_2406_2 | B583: 0.38745858 | C583: 0.39367935 | D583: 0.40215282 | E583: 0.52785941 | F583: 0.66903135 | G583: 0.83514647 | H583: 1.1121051 | I583: 1.4449534 | J583: 1.8084917 | K583: 2.3104359 | L583: 3.027959 | M583: 4.0451221 | N583: 3.8683427 | O583: 3.5934692 | P583: 3.159847 | Q583: 2.8020055 | R583: 2.4914822 | S583: 2.9844098 | T583: 3.4745633 | U583: 4.0470828 | V583: 4.5128517 | W583: 4.9013888 | X583: 5.1462877 | Y583: 5.397608 | Z583: 5.6297318 | AA583: 5.7602233 | AB583: 5.8649502 | AC583: 6.105598 | AD583: 6.3398663 | AE583: 6.5707781 | AF583: 6.7027472 | AG583: 6.8273144 | AH583: 6.9312694 | AI583: 7.0410509 | AJ583: 7.1489717 | AK583: 6.923486 | AL583: 6.7072082 | AM583: 6.8380352 | AN583: 6.9709075 | AO583: 7.1084502 | AP583: 7.2561113 | AQ583: 7.4099673 | AR583: 7.2187179 | AS583: 7.0333883 | AT583: 6.8563786 | AU583: 6.687604 | AV583: 6.5284264
A584: CU_MWH_PGDP_21_2 | C584: 0.70669314 | D584: 0.71066547 | E584: 0.70761269 | F584: 0.78087648 | G584: 0.79873526 | H584: 0.78948766 | I584: 0.85369216 | J584: 0.86082471 | K584: 0.81643942 | L584: 0.77210169 | M584: 0.69788597 | N584: 0.71071358 | O584: 0.770476 | P584: 0.84912354 | Q584: 1.3316156 | R584: 1.2506507 | S584: 1.3466477 | T584: 1.3451529 | U584: 1.4759566 | V584: 1.7118418 | W584: 2.9228686 | X584: 3.063084 | Y584: 3.1205626 | Z584: 3.1961248 | AA584: 2.9575155 | AB584: 2.9096157 | AC584: 2.7736221 | AD584: 2.6299724 | AE584: 2.5053965 | AF584: 2.4819187 | AG584: 2.3557898 | AH584: 2.2542346 | AI584: 2.2354244 | AJ584: 2.1533691 | AK584: 2.0864646 | AL584: 2.1965779 | AM584: 2.0954374 | AN584: 1.9978643 | AO584: 1.9097056 | AP584: 1.8312919 | AQ584: 1.764379 | AR584: 1.7170504 | AS584: 1.6779063 | AT584: 1.6449036 | AU584: 1.6166951 | AV584: 1.5918281
A585: CU_MWH_PGDP_22_2 | C585: 51.523121 | D585: 51.626149 | E585: 51.596122 | F585: 59.336701 | G585: 47.327293 | H585: 54.508285 | I585: 61.89053 | J585: 67.54747 | K585: 64.382134 | L585: 59.392643 | M585: 51.054452 | N585: 46.551465 | O585: 51.358778 | P585: 58.886407 | Q585: 55.655135 | R585: 56.738522 | S585: 58.516815 | T585: 60.730894 | U585: 63.411059 | V585: 65.970731 | W585: 69.489507 | X585: 68.787799 | Y585: 68.206549 | Z585: 67.808478 | AA585: 67.246073 | AB585: 67.000053 | AC585: 67.401277 | AD585: 68.100303 | AE585: 68.997818 | AF585: 70.119695 | AG585: 71.410856 | AH585: 73.207801 | AI585: 75.30992 | AJ585: 77.796926 | AK585: 80.635704 | AL585: 84.117394 | AM585: 87.093378 | AN585: 90.1274 | AO585: 94.26425 | AP585: 99.758995 | AQ585: 105.9887 | AR585: 110.63881 | AS585: 114.93822 | AT585: 119.37775 | AU585: 123.99717 | AV585: 128.79735
A586: CU_MWH_PGDP_23_2 | C586: 73.266064 | D586: 73.287457 | E586: 73.523895 | F586: 74.737482 | G586: 75.53518 | H586: 75.492773 | I586: 76.999871 | J586: 78.533378 | K586: 79.171262 | L586: 79.525782 | M586: 79.915427 | N586: 81.451333 | O586: 83.00474 | P586: 84.493242 | Q586: 87.018954 | R586: 87.870637 | S586: 90.961766 | T586: 94.553941 | U586: 98.876311 | V586: 93.877815 | W586: 91.606895 | X586: 91.756514 | Y586: 91.556688 | Z586: 91.432744 | AA586: 90.74956 | AB586: 90.421784 | AC586: 90.18131 | AD586: 89.958617 | AE586: 89.759314 | AF586: 95.277995 | AG586: 100.89927 | AH586: 101.27715 | AI586: 102.2795 | AJ586: 103.10169 | AK586: 103.79435 | AL586: 104.82132 | AM586: 105.65695 | AN586: 106.38678 | AO586: 107.07508 | AP586: 107.75054 | AQ586: 108.19998 | AR586: 107.93055 | AS586: 107.40816 | AT586: 106.84099 | AU586: 106.25435 | AV586: 105.63751
A587: CU_MWH_PGDP_24_2 | C587: 47.351267 | D587: 47.174037 | E587: 46.127939 | F587: 50.150751 | G587: 42.222375 | H587: 44.063508 | I587: 47.233788 | J587: 50.160538 | K587: 47.460644 | L587: 43.549028 | M587: 38.68259 | N587: 35.696775 | O587: 37.739849 | P587: 41.325781 | Q587: 40.955972 | R587: 40.830206 | S587: 41.295639 | T587: 41.740396 | U587: 41.796201 | V587: 44.658182 | W587: 49.2172 | X587: 48.878417 | Y587: 48.282826 | Z587: 47.851317 | AA587: 46.928275 | AB587: 46.303651 | AC587: 44.627806 | AD587: 43.254764 | AE587: 42.117919 | AF587: 41.849582 | AG587: 41.346481 | AH587: 40.849374 | AI587: 40.568871 | AJ587: 40.1896 | AK587: 41.87199 | AL587: 43.606594 | AM587: 42.219482 | AN587: 41.215444 | AO587: 40.453764 | AP587: 39.796933 | AQ587: 39.172207 | AR587: 40.302157 | AS587: 41.084259 | AT587: 41.730518 | AU587: 42.357089 | AV587: 42.993709
A588: CU_MWH_PGDP_2201_2 | C588: 51.430588 | D588: 51.510911 | E588: 51.457245 | F588: 59.216846 | G588: 46.898524 | H588: 54.12867 | I588: 61.634867 | J588: 67.419762 | K588: 64.109193 | L588: 58.892801 | M588: 50.133656 | N588: 45.350583 | O588: 50.347655 | P588: 58.183525 | Q588: 54.757653 | R588: 55.916192 | S588: 57.783061 | T588: 60.069897 | U588: 62.847923 | V588: 65.552423 | W588: 69.232261 | X588: 68.413524 | Y588: 67.762892 | Z588: 67.286882 | AA588: 66.638192 | AB588: 66.306179 | AC588: 66.626944 | AD588: 67.013635 | AE588: 67.547005 | AF588: 68.264092 | AG588: 69.099487 | AH588: 70.364953 | AI588: 71.794075 | AJ588: 73.472055 | AK588: 75.371884 | AL588: 77.747763 | AM588: 79.689507 | AN588: 82.309744 | AO588: 85.885403 | AP588: 90.553096 | AQ588: 95.803285 | AR588: 98.729557 | AS588: 102.49517 | AT588: 106.37486 | AU588: 110.3272 | AV588: 114.37301
A589: CU_MWH_PGDP_2202_2 | C589: 62.329864 | D589: 65.743951 | E589: 62.954793 | F589: 66.694178 | G589: 68.346705 | H589: 70.005365 | I589: 70.838366 | J589: 71.453553 | K589: 71.794935 | L589: 71.59253 | M589: 71.466917 | N589: 72.747892 | O589: 73.049982 | P589: 73.700716 | Q589: 74.227499 | R589: 73.423756 | S589: 72.626929 | T589: 72.833013 | U589: 73.267511 | V589: 72.529184 | W589: 73.115646 | X589: 73.843532 | Y589: 73.937916 | Z589: 74.239306 | AA589: 74.389206 | AB589: 74.751707 | AC589: 74.440569 | AD589: 76.24524 | AE589: 78.040727 | AF589: 79.804644 | AG589: 81.529926 | AH589: 83.501956 | AI589: 85.810195 | AJ589: 88.379293 | AK589: 91.129103 | AL589: 94.281598 | AM589: 97.776498 | AN589: 100.21098 | AO589: 103.78317 | AP589: 108.79232 | AQ589: 114.39862 | AR589: 120.31453 | AS589: 124.85944 | AT589: 129.52026 | AU589: 134.38793 | AV589: 139.42949
A590: CU_MWH_PGDP_2301_2 | C590: 71.19287 | D590: 71.262191 | E590: 71.600931 | F590: 72.023889 | G590: 73.161614 | H590: 72.488175 | I590: 73.442578 | J590: 74.696516 | K590: 75.301714 | L590: 75.386446 | M590: 75.434222 | N590: 76.969093 | O590: 78.187941 | P590: 79.406407 | Q590: 81.846331 | R590: 82.499261 | S590: 85.979009 | T590: 90.30006 | U590: 95.364188 | V590: 89.6186 | W590: 86.368222 | X590: 86.477964 | Y590: 86.377376 | Z590: 86.480974 | AA590: 86.102541 | AB590: 86.1881 | AC590: 86.351124 | AD590: 86.351301 | AE590: 86.441469 | AF590: 92.090475 | AG590: 98.015272 | AH590: 98.549973 | AI590: 99.803555 | AJ590: 100.95634 | AK590: 101.96218 | AL590: 103.2998 | AM590: 105.5482 | AN590: 107.54719 | AO590: 109.66605 | AP590: 111.97314 | AQ590: 113.91407 | AR590: 115.84754 | AS590: 117.87856 | AT590: 120.13097 | AU590: 122.64251 | AV590: 125.44443
A591: CU_MWH_PGDP_2302_2 | C591: 223.60228 | D591: 224.26164 | E591: 226.83095 | F591: 237.27446 | G591: 228.70146 | H591: 240.10938 | I591: 253.90276 | J591: 268.04407 | K591: 269.05636 | L591: 264.10162 | M591: 252.04652 | N591: 252.63778 | O591: 266.111 | P591: 288.18067 | Q591: 303.17188 | R591: 325.14702 | S591: 295.34225 | T591: 292.69359 | U591: 300.02573 | V591: 332.12593 | W591: 375.69572 | X591: 385.96279 | Y591: 427.97166 | Z591: 534.70297 | AA591: 534.47988 | AB591: 559.48467 | AC591: 550.99372 | AD591: 545.74017 | AE591: 540.82986 | AF591: 568.93487 | AG591: 598.99541 | AH591: 665.77843 | AI591: 765.82245 | AJ591: 947.41635 | AK591: 864.05641 | AL591: 808.3325 | AM591: 818.62379 | AN591: 824.33854 | AO591: 827.3585 | AP591: 829.70218 | AQ591: 831.89721 | AR591: 814.97225 | AS591: 800.4735 | AT591: 786.96428 | AU591: 773.69529 | AV591: 760.80012
A592: CU_MWH_PGDP_2303_2 | C592: 76.782812 | D592: 76.069556 | E592: 75.682599 | F592: 76.81299 | G592: 76.570663 | H592: 78.357733 | I592: 80.00255 | J592: 82.211024 | K592: 82.487925 | L592: 81.406417 | M592: 79.776156 | N592: 79.214901 | O592: 81.241437 | P592: 84.625438 | Q592: 89.000255 | R592: 90.761912 | S592: 94.586054 | T592: 97.403133 | U592: 100.66614 | V592: 99.008368 | W592: 103.14999 | X592: 104.99733 | Y592: 104.52983 | Z592: 104.02369 | AA592: 102.91741 | AB592: 102.35924 | AC592: 101.40311 | AD592: 100.41728 | AE592: 99.542118 | AF592: 104.0366 | AG592: 108.35727 | AH592: 110.79123 | AI592: 114.01029 | AJ592: 119.12983 | AK592: 131.34913 | AL592: 167.81724 | AM592: 145.64094 | AN592: 142.09446 | AO592: 142.38755 | AP592: 142.72745 | AQ592: 141.86704 | AR592: 142.12471 | AS592: 142.71538 | AT592: 143.75939 | AU592: 145.31183 | AV592: 147.2977
A593: CU_MWH_PGDP_2304_2 | C593: 108.14911 | D593: 107.91407 | E593: 108.8986 | F593: 125.40348 | G593: 117.63549 | H593: 126.62323 | I593: 137.30744 | J593: 136.02972 | K593: 126.00984 | L593: 124.34507 | M593: 122.71598 | N593: 128.92526 | O593: 145.7336 | P593: 155.3261 | Q593: 150.72944 | R593: 164.20778 | S593: 166.23601 | T593: 177.26515 | U593: 194.34144 | V593: 225.06036 | W593: 289.45629 | X593: 296.59772 | Y593: 330.64979 | Z593: 412.40051 | AA593: 394.68621 | AB593: 391.96881 | AC593: 432.25806 | AD593: 483.55586 | AE593: 564.86583 | AF593: 584.63091 | AG593: 617.10079 | AH593: 615.06873 | AI593: 615.39438 | AJ593: 612.8511 | AK593: 608.04375 | AL593: 603.81266 | AM593: 608.04561 | AN593: 613.21435 | AO593: 618.54804 | AP593: 625.07674 | AQ593: 633.1936 | AR593: 635.41576 | AS593: 638.28691 | AT593: 641.98565 | AU593: 646.29631 | AV593: 651.35106
A594: CU_MWH_PGDP_2305_2 | C594: 96.989308 | D594: 97.273808 | E594: 81.568498 | F594: 85.132922 | G594: 88.757148 | H594: 88.669425 | I594: 89.720553 | J594: 90.999895 | K594: 91.802699 | L594: 92.450859 | M594: 93.608878 | N594: 93.744886 | O594: 95.309502 | P594: 97.011933 | Q594: 99.960571 | R594: 101.00163 | S594: 101.25256 | T594: 101.2833 | U594: 102.11587 | V594: 99.481897 | W594: 100.00511 | X594: 99.267195 | Y594: 98.313018 | Z594: 97.496129 | AA594: 96.06085 | AB594: 95.01783 | AC594: 92.781455 | AD594: 91.020175 | AE594: 89.247774 | AF594: 93.253854 | AG594: 97.133224 | AH594: 97.014909 | AI594: 97.693676 | AJ594: 98.090327 | AK594: 98.341103 | AL594: 98.985337 | AM594: 98.610902 | AN594: 98.283987 | AO594: 97.910944 | AP594: 97.543899 | AQ594: 97.217428 | AR594: 97.396684 | AS594: 97.586002 | AT594: 97.783358 | AU594: 97.983718 | AV594: 98.192277
A595: CU_MWH_PGDP_2306_2 | C595: 189.25946 | D595: 190.48367 | E595: 176.81701 | F595: 174.66411 | G595: 177.28147 | H595: 175.18598 | I595: 176.65438 | J595: 178.70337 | K595: 179.49679 | L595: 178.96015 | M595: 178.40397 | N595: 188.94451 | O595: 190.77413 | P595: 190.95177 | Q595: 194.01032 | R595: 195.94893 | S595: 196.24896 | T595: 196.09808 | U595: 197.37153 | V595: 178.90137 | W595: 167.68362 | X595: 156.73943 | Y595: 148.52459 | Z595: 141.10173 | AA595: 133.26716 | AB595: 125.96765 | AC595: 121.84768 | AD595: 119.20812 | AE595: 117.01691 | AF595: 122.73024 | AG595: 128.50885 | AH595: 127.23061 | AI595: 126.4462 | AJ595: 125.53722 | AK595: 124.55781 | AL595: 124.14691 | AM595: 122.64064 | AN595: 121.33472 | AO595: 120.05509 | AP595: 118.80683 | AQ595: 117.62669 | AR595: 111.8006 | AS595: 105.01167 | AT595: 98.146077 | AU595: 91.319823 | AV595: 84.46717
... A603: CU_MWH_PGDP_2406_2 | C603: 31.074366 | D603: 31.375236 | E603: 30.799733 | F603: 31.874119 | G603: 32.862507 | H603: 33.001562 | I603: 33.581889 | J603: 33.730645 | K603: 33.288404 | L603: 32.692558 | M603: 32.057333 | N603: 34.137185 | O603: 34.547439 | P603: 34.546333 | Q603: 35.415748 | R603: 35.242041 | S603: 33.449033 | T603: 33.361258 | U603: 33.660805 | V603: 34.670954 | W603: 37.376452 | X603: 37.377741 | Y603: 36.976936 | Z603: 36.695018 | AA603: 35.944169 | AB603: 35.57356 | AC603: 34.848981 | AD603: 34.353793 | AE603: 34.014678 | AF603: 34.084629 | AG603: 33.864562 | AH603: 33.678796 | AI603: 33.642212 | AJ603: 33.431232 | AK603: 33.837098 | AL603: 34.210559 | AM603: 33.357747 | AN603: 32.970087 | AO603: 32.771676 | AP603: 32.648147 | AQ603: 32.54179 | AR603: 32.835695 | AS603: 32.689403 | AT603: 32.397418 | AU603: 32.096946 | AV603: 31.83645
A604: Q_MTEP_SEC_22_16_2 | B604: 15.957318 | C604: 16.213518 | D604: 16.487425 | E604: 16.453211 | F604: 16.193826 | G604: 15.671266 | H604: 15.603228 | I604: 15.565496 | J604: 15.430786 | K604: 15.202894 | L604: 15.103931 | M604: 14.983981 | N604: 14.975198 | O604: 15.039467 | P604: 14.841093 | Q604: 14.648582 | R604: 14.457892 | S604: 14.773869 | T604: 14.8087 | U604: 15.034147 | V604: 15.121689 | W604: 15.115771 | X604: 14.870782 | Y604: 14.702706 | Z604: 14.536614 | AA604: 14.332207 | AB604: 14.129853 | AC604: 13.633 | AD604: 13.125847 | AE604: 12.614997 | AF604: 12.101181 | AG604: 11.59478 | AH604: 10.98122 | AI604: 10.355524 | AJ604: 9.6946773 | AK604: 9.054817 | AL604: 8.3737368 | AM604: 7.9774248 | AN604: 7.5463275 | AO604: 7.1050928 | AP604: 6.6604983 | AQ604: 6.1994811 | AR604: 6.0209395 | AS604: 5.8441885 | AT604: 5.6649081 | AU604: 5.4819577 | AV604: 5.2952651
A605: Q_MTEP_SEC_23_16_2 | B605: 0.080720537 | C605: 0.082016531 | D605: 0.083790529 | E605: 0.085099742 | F605: 0.082367787 | G605: 0.075980317 | H605: 0.078442484 | I605: 0.080053972 | J605: 0.078914693 | K605: 0.079833268 | L605: 0.082778036 | M605: 0.087080434 | N605: 0.090484994 | O605: 0.096701275 | P605: 0.098271923 | Q605: 0.10190553 | R605: 0.10612122 | S605: 0.12225904 | T605: 0.1337304 | U605: 0.14491626 | V605: 0.1873222 | W605: 0.22920249 | X605: 0.34818613 | Y605: 0.47042166 | Z605: 0.59495078 | AA605: 0.71994202 | AB605: 0.84685095 | AC605: 1.0872413 | AD605: 1.3298775 | AE605: 1.5753096 | AF605: 1.8238313 | AG605: 2.0775863 | AH605: 2.3971871 | AI605: 2.7232857 | AJ605: 3.0489892 | AK605: 3.391636 | AL605: 3.7304361 | AM605: 3.9833868 | AN605: 4.2290539 | AO605: 4.478316 | AP605: 4.7358583 | AQ605: 4.9928993 | AR605: 5.1265099 | AS605: 5.2662705 | AT605: 5.4088947 | AU605: 5.5534521 | AV605: 5.699913
A606: Q_MTEP_SEC_24_16_2 | B606: 0.024451024 | C606: 0.024843593 | D606: 0.025304327 | E606: 0.029859256 | F606: 0.033925152 | G606: 0.037546112 | H606: 0.042385563 | I606: 0.04692052 | J606: 0.051061047 | K606: 0.055012941 | L606: 0.05820068 | M606: 0.060100175 | N606: 0.066267111 | O606: 0.073609366 | P606: 0.081460492 | Q606: 0.090625222 | R606: 0.10162568 | S606: 0.15709391 | T606: 0.20055639 | U606: 0.23886731 | V606: 0.23038759 | W606: 0.22033585 | X606: 0.25881218 | Y606: 0.29911261 | Z606: 0.34020556 | AA606: 0.38108525 | AB606: 0.42262883 | AC606: 0.48435279 | AD606: 0.54656781 | AE606: 0.60951488 | AF606: 0.67328648 | AG606: 0.7386241 | AH606: 0.81859143 | AI606: 0.90016798 | AJ606: 0.98111969 | AK606: 1.0670393 | AL606: 1.1512913 | AM606: 1.2215451 | AN606: 1.2893874 | AO606: 1.3581771 | AP606: 1.4293293 | AQ606: 1.5001875 | AR606: 1.5370906 | AS606: 1.5757836 | AT606: 1.6152768 | AU606: 1.6552906 | AV606: 1.6958157
A607: MAT_N_06_01_2/Y_01_2 | B607: 0.001691807 | C607: 0.001691807 | D607: 0.0016936265 | E607: 0.0016891316 | F607: 0.0016974486 | G607: 0.0016111186 | H607: 0.0015787209 | I607: 0.0015418109 | J607: 0.0014763243 | K607: 0.0015119494 | L607: 0.0014333149 | M607: 0.0014393917 | N607: 0.0014879815 | O607: 0.0015105384 | P607: 0.0015133731 | Q607: 0.0014749611 | R607: 0.0014749487 | S607: 0.0014750015 | T607: 0.0014750719 | U607: 0.001475148 | V607: 0.0014783886 | W607: 0.0014816362 | X607: 0.001484891 | Y607: 0.001488153 | Z607: 0.0014914221 | AA607: 0.0014946983 | AB607: 0.0014979818 | AC607: 0.0014976033 | AD607: 0.0014972248 | AE607: 0.0014968464 | AF607: 0.0014964681 | AG607: 0.0014960899 | AH607: 0.0014957118 | AI607: 0.0014953339 | AJ607: 0.0014949559 | AK607: 0.0014945781 | AL607: 0.0014942004 | AM607: 0.0014938228 | AN607: 0.0014934453 | AO607: 0.0014930679 | AP607: 0.0014926905 | AQ607: 0.0014923133 | AR607: 0.0014919362 | AS607: 0.0014915591 | AT607: 0.0014911822 | AU607: 0.0014908053 | AV607: 0.0014904286
A608: MAT_N_06_02_2/Y_02_2 | B608: 0.016902639 | C608: 0.016902639 | D608: 0.017123012 | E608: 0.016935826 | F608: 0.016992686 | G608: 0.016117965 | H608: 0.01626116 | I608: 0.015392253 | J608: 0.014979803 | K608: 0.014990005 | L608: 0.014497458 | M608: 0.014504281 | N608: 0.014653392 | O608: 0.014803666 | P608: 0.014584166 | Q608: 0.014408818 | R608: 0.014408453 | S608: 0.014408432 | T608: 0.014408465 | U608: 0.014408573 | V608: 0.01447896 | W608: 0.014549691 | X608: 0.014620767 | Y608: 0.014692191 | Z608: 0.014763964 | AA608: 0.014836087 | AB608: 0.014908562 | AC608: 0.01492075 | AD608: 0.014932947 | AE608: 0.014945155 | AF608: 0.014957372 | AG608: 0.0149696 | AH608: 0.014981837 | AI608: 0.014994085 | AJ608: 0.015006342 | AK608: 0.015018609 | AL608: 0.015030887 | AM608: 0.015043175 | AN608: 0.015055472 | AO608: 0.01506778 | AP608: 0.015080098 | AQ608: 0.015092425 | AR608: 0.015104763 | AS608: 0.015117111 | AT608: 0.015129469 | AU608: 0.015141837 | AV608: 0.015154216
A609: MAT_N_06_03_2/Y_03_2 | B609: 0.001264969 | C609: 0.001264969 | D609: 0.0012649007 | E609: 0.0012935883 | F609: 0.0013025329 | G609: 0.0013811887 | H609: 0.0013012957 | I609: 0.0012396438 | J609: 0.0011961763 | K609: 0.0011921024 | L609: 0.0011515804 | M609: 0.0011262138 | N609: 0.0010954761 | O609: 0.001059274 | P609: 0.0010291484 | Q609: 0.00099080897 | R609: 0.00099079377 | S609: 0.00099080538 | T609: 0.00099080375 | U609: 0.00099067288 | V609: 0.00099067288 | W609: 0.00099067288 | X609: 0.00099067288 | Y609: 0.00099067288 | Z609: 0.00099067288 | AA609: 0.00099067288 | AB609: 0.00099067288 | AC609: 0.00099067288 | AD609: 0.00099067288 | AE609: 0.00099067288 | AF609: 0.00099067288 | AG609: 0.00099067288 | AH609: 0.00099067288 | AI609: 0.00099067288 | AJ609: 0.00099067288 | AK609: 0.00099067288 | AL609: 0.00099067288 | AM609: 0.00099067288 | AN609: 0.00099067288 | AO609: 0.00099067288 | AP609: 0.00099067288 | AQ609: 0.00099067288 | AR609: 0.00099067288 | AS609: 0.00099067288 | AT609: 0.00099067288 | AU609: 0.00099067288 | AV609: 0.00099067288
A610: MAT_N_06_04_2/Y_04_2 | B610: 0.030517138 | C610: 0.030517138 | D610: 0.030633897 | E610: 0.030858571 | F610: 0.032472135 | G610: 0.03563065 | H610: 0.03515049 | I610: 0.030238401 | J610: 0.031143005 | K610: 0.032083174 | L610: 0.031281623 | M610: 0.031750039 | N610: 0.030881761 | O610: 0.030464213 | P610: 0.029681382 | Q610: 0.028906081 | R610: 0.028905862 | S610: 0.028906635 | T610: 0.028906871 | U610: 0.028907847 | V610: 0.029387835 | W610: 0.029875792 | X610: 0.030371851 | Y610: 0.030876147 | Z610: 0.031388817 | AA610: 0.031909998 | AB610: 0.032439834 | AC610: 0.032448362 | AD610: 0.032456892 | AE610: 0.032465425 | AF610: 0.03247396 | AG610: 0.032482497 | AH610: 0.032491037 | AI610: 0.032499578 | AJ610: 0.032508122 | AK610: 0.032516669 | AL610: 0.032525217 | AM610: 0.032533768 | AN610: 0.032542321 | AO610: 0.032550876 | AP610: 0.032559433 | AQ610: 0.032567993 | AR610: 0.032576555 | AS610: 0.032585119 | AT610: 0.032593686 | AU610: 0.032602254 | AV610: 0.032610825
A611: MAT_N_06_05_2/Y_05_2 | B611: 0.0058610672 | C611: 0.0058610672 | D611: 0.0058672894 | E611: 0.0059126955 | F611: 0.0062179873 | G611: 0.0068308929 | H611: 0.0067306961 | I611: 0.0057633759 | J611: 0.0059708762 | K611: 0.0061652222 | L611: 0.0060170379 | M611: 0.0061310123 | N611: 0.0059550024 | O611: 0.0058718099 | P611: 0.0057308665 | Q611: 0.0055697069 | R611: 0.0055696719 | S611: 0.005569807 | T611: 0.0055698049 | U611: 0.0055699623 | V611: 0.0055794691 | W611: 0.0055889921 | X611: 0.0055985314 | Y611: 0.0056080869 | Z611: 0.0056176587 | AA611: 0.0056272469 | AB611: 0.0056368515 | AC611: 0.0056389392 | AD611: 0.0056410277 | AE611: 0.005643117 | AF611: 0.0056452071 | AG611: 0.0056472979 | AH611: 0.0056493895 | AI611: 0.0056514819 | AJ611: 0.0056535751 | AK611: 0.005655669 | AL611: 0.0056577637 | AM611: 0.0056598592 | AN611: 0.0056619555 | AO611: 0.0056640525 | AP611: 0.0056661503 | AQ611: 0.0056682489 | AR611: 0.0056703483 | AS611: 0.0056724484 | AT611: 0.0056745494 | AU611: 0.0056766511 | AV611: 0.0056787535
A612: MAT_N_06_06_2/Y_06_2 | B612: 0.33257167 | C612: 0.33257167 | D612: 0.33345627 | E612: 0.33497098 | F612: 0.34137627 | G612: 0.35834842 | H612: 0.34411874 | I612: 0.33972864 | J612: 0.34112953 | K612: 0.33794401 | L612: 0.33577603 | M612: 0.33266309 | N612: 0.33777228 | O612: 0.34719817 | P612: 0.34253747 | Q612: 0.34064416 | R612: 0.34063992 | S612: 0.34064413 | T612: 0.34064548 | U612: 0.34065182 | V612: 0.36606998 | W612: 0.39338475 | X612: 0.42273764 | Y612: 0.45428073 | Z612: 0.48817745 | AA612: 0.52460341 | AB612: 0.56374734 | AC612: 0.56506584 | AD612: 0.56638742 | AE612: 0.56771209 | AF612: 0.56903986 | AG612: 0.57037073 | AH612: 0.57170472 | AI612: 0.57304183 | AJ612: 0.57438206 | AK612: 0.57572543 | AL612: 0.57707194 | AM612: 0.5784216 | AN612: 0.57977441 | AO612: 0.58113039 | AP612: 0.58248955 | AQ612: 0.58385188 | AR612: 0.58521739 | AS612: 0.5865861 | AT612: 0.58795801 | AU612: 0.58933313 | AV612: 0.59071147
A613: MAT_N_06_07_2/Y_07_2 | B613: 0.0050209205 | C613: 0.0050209205 | D613: 0.005022034 | E613: 0.0050750325 | F613: 0.0049572047 | G613: 0.0050374943 | H613: 0.0049192489 | I613: 0.0046617729 | J613: 0.0045591107 | K613: 0.0045272425 | L613: 0.004470755 | M613: 0.0043702886 | N613: 0.0043093459 | O613: 0.0043355581 | P613: 0.0042528954 | Q613: 0.0040802123 | R613: 0.0040801264 | S613: 0.0040803148 | T613: 0.0040803859 | U613: 0.0040806155 | V613: 0.0040836582 | W613: 0.0040867031 | X613: 0.0040897504 | Y613: 0.0040927999 | Z613: 0.0040958516 | AA613: 0.0040989057 | AB613: 0.004101962 | AC613: 0.0041037773 | AD613: 0.0041055935 | AE613: 0.0041074104 | AF613: 0.0041092282 | AG613: 0.0041110467 | AH613: 0.0041128661 | AI613: 0.0041146862 | AJ613: 0.0041165072 | AK613: 0.0041183289 | AL613: 0.0041201515 | AM613: 0.0041219749 | AN613: 0.0041237991 | AO613: 0.0041256241 | AP613: 0.0041274499 | AQ613: 0.0041292765 | AR613: 0.0041311039 | AS613: 0.0041329321 | AT613: 0.0041347612 | AU613: 0.004136591 | AV613: 0.0041384217
A614: MAT_N_06_08_2/Y_08_2 | B614: 0.0089822933 | C614: 0.0089822933 | D614: 0.0089823288 | E614: 0.0090608818 | F614: 0.0088371402 | G614: 0.0089097237 | H614: 0.0086863328 | I614: 0.0081982282 | J614: 0.0079237548 | K614: 0.0078206631 | L614: 0.0076578948 | M614: 0.0074227139 | N614: 0.0073103053 | O614: 0.0072868109 | P614: 0.0070849968 | Q614: 0.0066921618 | R614: 0.0066921246 | S614: 0.0066921375 | T614: 0.0066921403 | U614: 0.0066922204 | V614: 0.0067809332 | W614: 0.006870822 | X614: 0.0069619023 | Y614: 0.00705419 | Z614: 0.0071477011 | AA614: 0.0072424518 | AB614: 0.0073384585 | AC614: 0.0073459982 | AD614: 0.0073535455 | AE614: 0.0073611006 | AF614: 0.0073686635 | AG614: 0.0073762341 | AH614: 0.0073838126 | AI614: 0.0073913988 | AJ614: 0.0073989928 | AK614: 0.0074065946 | AL614: 0.0074142042 | AM614: 0.0074218216 | AN614: 0.0074294469 | AO614: 0.00743708 | AP614: 0.0074447209 | AQ614: 0.0074523697 | AR614: 0.0074600264 | AS614: 0.0074676909 | AT614: 0.0074753633 | AU614: 0.0074830435 | AV614: 0.0074907317
A615: MAT_N_06_09_2/Y_09_2 | B615: 0.019547856 | C615: 0.019547856 | D615: 0.019604778 | E615: 0.019226133 | F615: 0.019324712 | G615: 0.021228606 | H615: 0.020369477 | I615: 0.018857375 | J615: 0.018833691 | K615: 0.019605999 | L615: 0.019740325 | M615: 0.019162929 | N615: 0.019227611 | O615: 0.019203221 | P615: 0.018876587 | Q615: 0.018819152 | R615: 0.018819102 | S615: 0.018819303 | T615: 0.018819319 | U615: 0.018819594 | V615: 0.020428932 | W615: 0.022175892 | X615: 0.02407224 | Y615: 0.026130753 | Z615: 0.028365298 | AA615: 0.030790927 | AB615: 0.033423982 | AC615: 0.033467742 | AD615: 0.03351156 | AE615: 0.033555435 | AF615: 0.033599367 | AG615: 0.033643357 | AH615: 0.033687405 | AI615: 0.03373151 | AJ615: 0.033775673 | AK615: 0.033819894 | AL615: 0.033864172 | AM615: 0.033908509 | AN615: 0.033952904 | AO615: 0.033997357 | AP615: 0.034041868 | AQ615: 0.034086437 | AR615: 0.034131065 | AS615: 0.034175751 | AT615: 0.034220495 | AU615: 0.034265299 | AV615: 0.03431016
... A767: PNEWBUIL_H01_2 | B767: 0.0012516089 | C767: 0.0012766411 | D767: 0.0012912692 | E767: 0.0013032028 | F767: 0.0013163943 | G767: 0.0013478795 | H767: 0.0013925213 | I767: 0.0014296137 | J767: 0.0014631521 | K767: 0.0014947025 | L767: 0.0015430482 | M767: 0.001610379 | N767: 0.001662071 | O767: 0.0016972231 | P767: 0.0017270109 | Q767: 0.0017570185 | R767: 0.0018129394 | S767: 0.0018705949 | T767: 0.0019072196 | U767: 0.0019446008 | V767: 0.0019822764 | W767: 0.0020209805 | X767: 0.0020611287 | Y767: 0.0021011004 | Z767: 0.0021415918 | AA767: 0.0021831445 | AB767: 0.0022260623 | AC767: 0.0022709181 | AD767: 0.0023153376 | AE767: 0.0023603495 | AF767: 0.002406406 | AG767: 0.0024534193 | AH767: 0.0025013149 | AI767: 0.002549636 | AJ767: 0.0025986723 | AK767: 0.0026484586 | AL767: 0.0026990282 | AM767: 0.0027506615 | AN767: 0.0028021279 | AO767: 0.0028541724 | AP767: 0.0029069165 | AQ767: 0.0029599772 | AR767: 0.0030132029 | AS767: 0.0030672022 | AT767: 0.00312121 | AU767: 0.0031750022 | AV767: 0.0032443062
A768: NEW_TRUCKS_15_2 | C768: 5.4807907 | D768: 5.5687866 | E768: 4.2574992 | F768: 4.486056 | G768: 4.7564216 | H768: 5.0004223 | I768: 5.393404 | J768: 5.0119464 | K768: 4.8596928 | L768: 5.5442938 | M768: 4.1937125 | N768: 5.6893087 | O768: 5.5268256 | P768: 5.9497884 | Q768: 6.233129 | R768: 4.5631186 | S768: 4.5140781 | T768: 5.2573099 | U768: 5.4616642 | V768: 8.5542031 | W768: 7.9642063 | X768: 5.0740828 | Y768: 5.5298599 | Z768: 5.7937272 | AA768: 5.9266853 | AB768: 6.0024571 | AC768: 5.4343505 | AD768: 5.4820985 | AE768: 5.4559531 | AF768: 5.4601868 | AG768: 5.4712713 | AH768: 5.7157338 | AI768: 5.7478152 | AJ768: 5.7100672 | AK768: 5.7704427 | AL768: 5.7342764 | AM768: 5.8291235 | AN768: 5.8348065 | AO768: 5.8689974 | AP768: 5.8862325 | AQ768: 6.0581657 | AR768: 5.9273269 | AS768: 5.9347967 | AT768: 5.9747165 | AU768: 5.9870903 | AV768: 5.816726
A769: NEW_TRUCKS_16_2 | C769: 45.90819 | D769: 46.64526 | E769: 42.36853 | F769: 37.667917 | G769: 27.81915 | H769: 38.534588 | I769: 45.497517 | J769: 39.264363 | K769: 28.502252 | L769: 37.475078 | M769: 34.607495 | N769: 40.069704 | O769: 42.930682 | P769: 46.504883 | Q769: 43.699156 | R769: 40.410339 | S769: 54.999072 | T769: 43.94642 | U769: 51.642138 | V769: 47.648549 | W769: 44.231077 | X769: 43.511258 | Y769: 47.062431 | Z769: 47.716437 | AA769: 46.581062 | AB769: 47.121792 | AC769: 46.619171 | AD769: 46.657769 | AE769: 47.004545 | AF769: 47.417892 | AG769: 48.474087 | AH769: 50.860804 | AI769: 51.440172 | AJ769: 50.420218 | AK769: 53.280015 | AL769: 51.743958 | AM769: 55.217031 | AN769: 53.672746 | AO769: 54.055493 | AP769: 55.169207 | AQ769: 54.935356 | AR769: 54.366734 | AS769: 55.406012 | AT769: 55.991164 | AU769: 56.449991 | AV769: 56.905135
A770: NEW_LUV_16_2 | C770: 405.5254 | D770: 412.03624 | E770: 373.41874 | F770: 365.28754 | G770: 379.33932 | H770: 402.60878 | I770: 362.17209 | J770: 482.80088 | K770: 511.94586 | L770: 457.9653 | M770: 467.61275 | N770: 514.39681 | O770: 498.69779 | P770: 309.48518 | Q770: 316.35024 | R770: 400.40127 | S770: 544.95208 | T770: 435.43813 | U770: 511.69028 | V770: 474.13991 | W770: 440.42948 | X770: 433.44099 | Y770: 468.81862 | Z770: 475.47666 | AA770: 464.37558 | AB770: 469.90787 | AC770: 465.07982 | AD770: 465.62445 | AE770: 469.23223 | AF770: 473.50462 | AG770: 484.17461 | AH770: 508.09272 | AI770: 514.0434 | AJ770: 504.07461 | AK770: 532.73627 | AL770: 517.62821 | AM770: 552.4261 | AN770: 537.23565 | AO770: 541.2465 | AP770: 552.55174 | AQ770: 550.4188 | AR770: 544.94048 | AS770: 555.51128 | AT770: 561.55472 | AU770: 566.34028 | AV770: 571.09217
A771: TRUCKS_15_2 | B771: 80.756911 | C771: 82.053489 | D771: 83.370885 | E771: 83.308735 | F771: 83.478362 | G771: 83.909567 | H771: 84.56243 | I771: 85.574448 | J771: 86.152574 | K771: 86.548492 | L771: 87.608497 | M771: 87.263 | N771: 88.431 | O771: 89.376 | P771: 90.695 | Q771: 92.229 | R771: 92.013509 | S771: 91.760143 | T771: 92.263136 | U771: 92.944423 | V771: 96.682949 | W771: 99.637776 | X771: 99.549383 | Y771: 99.921346 | Z771: 100.53791 | AA771: 101.25548 | AB771: 102.01164 | AC771: 102.16052 | AD771: 102.34943 | AE771: 102.50241 | AF771: 102.6517 | AG771: 102.80434 | AH771: 103.19353 | AI771: 103.59463 | AJ771: 103.93721 | AK771: 104.32241 | AL771: 104.65149 | AM771: 105.05836 | AN771: 105.44984 | AO771: 105.85523 | AP771: 106.25684 | AQ771: 106.80958 | AR771: 107.20284 | AS771: 107.5832 | AT771: 107.98377 | AU771: 108.37596 | AV771: 108.57746
A772: TRUCKS_22_15_2 | B772: 79.434309 | C772: 80.709652 | D772: 82.005472 | E772: 81.778348 | F772: 81.778528 | G772: 82.033762 | H772: 82.50354 | I772: 83.320411 | J772: 83.71165 | K772: 83.923902 | L772: 84.777203 | M772: 84.269 | N772: 85.43 | O772: 86.222 | P772: 87.363 | Q772: 88.291 | R772: 87.119058 | S772: 85.657483 | T772: 85.144317 | U772: 84.981067 | V772: 84.806479 | W772: 83.695732 | X772: 81.431395 | Y772: 79.537392 | Z772: 77.816339 | AA772: 76.144118 | AB772: 74.468498 | AC772: 70.8994 | AD772: 67.345926 | AE772: 63.7565 | AF772: 60.153896 | AG772: 56.542384 | AH772: 52.628698 | AI772: 48.689478 | AJ772: 44.693 | AK772: 40.685741 | AL772: 36.628022 | AM772: 33.198443 | AN772: 29.736855 | AO772: 26.252096 | AP772: 22.738964 | AQ772: 19.225725 | AR772: 16.723644 | AS772: 14.200982 | AT772: 11.662247 | AU772: 9.1035803 | AV772: 6.5146476
A773: TRUCKS_23_15_2 | B773: 0.35351914 | C773: 0.35919501 | D773: 0.36496199 | E773: 0.36468992 | F773: 0.36543248 | G773: 0.36732011 | H773: 0.37017806 | I773: 0.37460824 | J773: 0.37713903 | K773: 0.37887219 | L773: 0.38351244 | M773: 0.382 | N773: 0.426 | O773: 0.474 | P773: 0.519 | Q773: 0.773 | R773: 0.89287323 | S773: 1.3038669 | T773: 1.6435891 | U773: 1.9237502 | V773: 3.9010533 | W773: 5.9782665 | X773: 7.7648518 | Y773: 9.5924492 | Z773: 11.461321 | AA773: 13.365723 | AB773: 15.301746 | AC773: 18.797536 | AD773: 22.312176 | AE773: 25.830608 | AF773: 29.358386 | AG773: 32.897387 | AH773: 36.943282 | AI773: 41.023475 | AJ773: 45.108749 | AK773: 49.240179 | AL773: 53.37226 | AM773: 56.731517 | AN773: 60.10641 | AO773: 63.513135 | AP773: 66.94181 | AQ773: 70.494323 | AR773: 72.683528 | AS773: 74.877907 | AT773: 77.10041 | AU773: 79.3312 | AV773: 81.433095
A774: TRUCKS_24_15_2 | B774: 0.96908292 | C774: 0.98464186 | D774: 1.0004506 | E774: 1.1656975 | F774: 1.3344017 | G774: 1.5084843 | H774: 1.6887118 | I774: 1.879429 | J774: 2.0637851 | K774: 2.2457172 | L774: 2.4477816 | M774: 2.612 | N774: 2.575 | O774: 2.68 | P774: 2.813 | Q774: 3.165 | R774: 4.0015783 | S774: 4.7987935 | T774: 5.4752301 | U774: 6.0396057 | V774: 7.9754166 | W774: 9.9637776 | X774: 10.353136 | Y774: 10.791505 | Z774: 11.260245 | AA774: 11.745635 | AB774: 12.241397 | AC774: 12.463583 | AD774: 12.69133 | AE774: 12.915304 | AF774: 13.139417 | AG774: 13.364564 | AH774: 13.621545 | AI774: 13.881681 | AJ774: 14.135461 | AK774: 14.396493 | AL774: 14.651209 | AM774: 15.128405 | AN774: 15.606577 | AO774: 16.089994 | AP774: 16.576067 | AQ774: 17.089533 | AR774: 17.795672 | AS774: 18.50431 | AT774: 19.221111 | AU774: 19.941176 | AV774: 20.629717
A775: NEW_TRUCKS_22_15_2 | C775: 5.3910287 | D775: 5.4775834 | E775: 4.0217791 | F775: 4.2373161 | G775: 4.4923788 | H775: 4.7201468 | I775: 5.0915806 | J775: 4.7082723 | K775: 4.5495573 | L775: 5.2016027 | M775: 3.8843103 | N775: 5.5271823 | O775: 5.2183365 | P775: 5.608372 | Q775: 5.45449 | R775: 3.4026297 | S775: 3.0522757 | T775: 3.9249575 | U775: 4.248284 | V775: 4.2284883 | W775: 3.2832832 | X775: 2.0721431 | Y775: 2.3251558 | Z775: 2.399973 | AA775: 2.3596339 | AB775: 2.2695916 | AC775: 0.28929716 | AD775: 0.11999677 | AE775: -0.10006969 | AF775: -0.29922496 | AG775: -0.49479111 | AH775: -0.98408747 | AI775: -1.2123996 | AJ775: -1.4737568 | AK775: -1.6916061 | AL775: -1.9496918 | AM775: -1.5317912 | AN775: -1.7414957 | AO775: -1.9440204 | AP775: -2.1529469 | AQ775: -2.3350783 | AR775: -1.5059494 | AS775: -1.6561685 | AT775: -1.8029478 | AU775: -1.9544172 | AV775: -2.117254
A776: NEW_TRUCKS_23_15_2 | C776: 0.023992553 | D776: 0.024377748 | E776: 0.018637506 | F776: 0.01963803 | G776: 0.020821574 | H776: 0.021889705 | I776: 0.02361001 | J776: 0.021940152 | K776: 0.021273652 | L776: 0.024270541 | M776: 0.018358275 | N776: 0.063792351 | O776: 0.070072098 | P776: 0.069559095 | Q776: 0.28089065 | R776: 0.15992424 | S776: 0.45725562 | T776: 0.40727874 | U776: 0.36531947 | V776: 2.0769773 | W776: 2.2793363 | X776: 2.0963339 | Y776: 2.2299133 | Z776: 2.3658801 | AA776: 2.4982407 | AB776: 2.6285339 | AC776: 4.2886102 | AD776: 4.4885868 | AE776: 4.6744798 | AF776: 4.8661248 | AG776: 5.060131 | AH776: 5.7503888 | AI776: 5.9943139 | AJ776: 6.2108006 | AK776: 6.4686238 | AL776: 6.6833351 | AM776: 6.1246039 | AN776: 6.3142908 | AO776: 6.5209853 | AP776: 6.7194447 | AQ776: 7.0209318 | AR776: 5.8416869 | AS776: 5.9602898 | AT776: 6.1021105 | AU776: 6.2255497 | AV776: 6.2122377
A777: NEW_TRUCKS_24_15_2 | C777: 0.065769488 | D777: 0.066825452 | E777: 0.21708267 | F777: 0.2291018 | G777: 0.24322124 | H777: 0.25838577 | I777: 0.2782134 | J777: 0.28173391 | K777: 0.28886185 | L777: 0.31842053 | M777: 0.29104389 | N777: 0.098334086 | O777: 0.23841703 | P777: 0.27185733 | Q777: 0.49774839 | R777: 1.0005647 | S777: 1.0045467 | T777: 0.92507371 | U777: 0.84806069 | V777: 2.2487375 | W777: 2.4015868 | X777: 0.90560581 | Y777: 0.97479082 | Z777: 1.0278742 | AA777: 1.0688107 | AB777: 1.1043316 | AC777: 0.8564431 | AD777: 0.87351488 | AE777: 0.88154301 | AF777: 0.89328694 | AG777: 0.90593139 | AH777: 0.94943244 | AI777: 0.96590088 | AJ777: 0.97302343 | AK777: 0.99342504 | AL777: 1.0006331 | AM777: 1.2363107 | AN777: 1.2620115 | AO777: 1.2920325 | AP777: 1.3197347 | AQ777: 1.3723122 | AR777: 1.5915894 | AS777: 1.6306754 | AT777: 1.6755538 | AU777: 1.7159578 | AV777: 1.7217423
A778: TRUCKS_16_2 | B778: 561.33716 | C778: 570.34961 | D778: 579.50675 | E778: 583.78529 | F778: 583.08199 | G778: 572.57615 | H778: 573.47627 | I778: 581.28017 | J778: 582.33797 | K778: 572.56413 | L778: 572.40554 | M778: 569.38979 | N778: 572.03447 | O778: 577.3663 | P778: 585.92187 | Q778: 591.10938 | R778: 592.6671 | S778: 608.71116 | T778: 612.64803 | U778: 624.02185 | V778: 630.6545 | W778: 633.43373 | X778: 635.31046 | Y778: 640.61501 | Z778: 646.22491 | AA778: 650.3307 | AB778: 654.70736 | AC778: 658.29373 | AD778: 661.68296 | AE778: 665.19621 | AF778: 668.89188 | AG778: 673.40084 | AH778: 680.00015 | AI778: 686.74506 | AJ778: 692.02669 | AK778: 699.82096 | AL778: 705.56688 | AM778: 714.40819 | AN778: 721.1241 | AO778: 727.78133 | AP778: 735.1147 | AQ778: 741.73221 | AR778: 747.34615 | AS778: 753.63036 | AT778: 760.08668 | AU778: 766.57746 | AV778: 773.09676
A779: TRUCKS_22_16_2 | B779: 559.39986 | C779: 568.38121 | D779: 577.50675 | E779: 581.89404 | F779: 581.22183 | G779: 570.68144 | H779: 571.48954 | I779: 579.14904 | J779: 580.01275 | K779: 569.99578 | L779: 569.54395 | M779: 566.18231 | N779: 568.42451 | O779: 573.29204 | P779: 581.31498 | Q779: 585.89365 | R779: 586.73413 | S779: 598.08306 | T779: 598.30011 | U779: 606.43247 | V779: 608.19027 | W779: 606.16194 | X779: 592.66867 | Y779: 582.20031 | Z779: 571.7468 | AA779: 559.72872 | AB779: 547.73962 | AC779: 522.97672 | AD779: 497.76302 | AE779: 472.35149 | AF779: 446.76547 | AG779: 421.37663 | AH779: 395.9041 | AI779: 369.93545 | AJ779: 342.65501 | AK779: 316.04947 | AL779: 287.92943 | AM779: 270.79622 | AN779: 252.40571 | AO779: 233.60641 | AP779: 214.61795 | AQ779: 195.01547 | AR779: 184.19038 | AS779: 173.33464 | AT779: 162.30879 | AU779: 151.07719 | AV779: 139.63706
A780: TRUCKS_23_16_2 | B780: 0.96864644 | C780: 0.98419838 | D780: 1 | E780: 0.7562145 | F780: 0.57186037 | G780: 0.4324491 | H780: 0.32702428 | I780: 0.2473005 | J780: 0.18701223 | K780: 0.14142136 | L780: 0.10694488 | M780: 0.080873269 | N780: 0.061157538 | O780: 0.046248217 | P780: 0.034973572 | Q780: 0.026447523 | R780: 0.020077737 | S780: 0.71602391 | T780: 1.280575 | U780: 1.760601 | V780: 7.2741931 | W780: 12.825344 | X780: 25.396807 | Y780: 38.246973 | Z780: 51.330689 | AA780: 64.486605 | AB780: 77.836721 | AC780: 102.41753 | AD780: 127.22362 | AE780: 152.30682 | AF780: 177.6963 | AG780: 203.60289 | AH780: 230.63305 | AI780: 258.20388 | AJ780: 285.66731 | AK780: 314.64935 | AL780: 343.20892 | AM780: 364.94818 | AN780: 385.98146 | AO780: 407.30976 | AP780: 429.35798 | AQ780: 451.32863 | AR780: 465.68135 | AS780: 480.62585 | AT780: 495.86655 | AU780: 511.3192 | AV780: 526.98127
A781: TRUCKS_24_16_2 | B781: 0.96864644 | C781: 0.98419838 | D781: 1 | E781: 1.1350323 | F781: 1.2882984 | G781: 1.4622604 | H781: 1.6597128 | I781: 1.8838277 | J781: 2.1382054 | K781: 2.4269322 | L781: 2.7546466 | M781: 3.1266129 | N781: 3.5488068 | O781: 4.0280105 | P781: 4.5719221 | Q781: 5.1892795 | R781: 5.9128936 | S781: 9.9120834 | T781: 13.067352 | U781: 15.828786 | V781: 15.190042 | W781: 14.44644 | X781: 17.244985 | Y781: 20.167724 | Z781: 23.14742 | AA781: 26.115382 | AB781: 29.131015 | AC781: 32.899478 | AD781: 36.69633 | AE781: 40.537901 | AF781: 44.430109 | AG781: 48.421318 | AH781: 53.462989 | AI781: 58.605732 | AJ781: 63.704376 | AK781: 69.122144 | AL781: 74.428533 | AM781: 78.663786 | AN781: 82.736927 | AO781: 86.865158 | AP781: 91.138767 | AQ781: 95.388118 | AR781: 97.474424 | AS781: 99.669874 | AT781: 101.91134 | AU781: 104.18107 | AV781: 106.47842
A782: NEW_TRUCKS_22_16_2 | C782: 45.749751 | D782: 46.484278 | E782: 42.345827 | F782: 37.574697 | G782: 27.662334 | H782: 38.318025 | I782: 45.222541 | J782: 38.930198 | K782: 28.106283 | L782: 37.013027 | M782: 34.073513 | N782: 39.456404 | O782: 42.229111 | P782: 45.704452 | Q782: 42.787521 | R782: 39.350274 | S782: 49.913972 | T782: 39.528033 | U782: 47.457612 | V782: 41.61758 | W782: 37.946992 | X782: 26.348722 | Y782: 28.486754 | Z782: 27.813526 | AA782: 25.561865 | AB782: 24.800927 | AC782: 11.239093 | AD782: 9.1606693 | AE782: 7.3055923 | AF782: 5.4608419 | AG782: 3.9762967 | AH782: 2.223848 | AI782: 0.053450639 | AJ782: -2.9652107 | AK782: -4.083404 | AL782: -7.346647 | AM782: 1.7919084 | AN782: -0.59153183 | AO782: -2.2091053 | AP782: -3.6339042 | AQ782: -5.496012 | AR782: 1.9929457 | AS782: 1.2507885 | AT782: 0.36713721 | AU782: -0.5633197 | AV782: -1.5100759
A783: NEW_TRUCKS_23_16_2 | C783: 0.079219421 | D783: 0.080491315 | E783: -0.1780572 | F783: -0.13464943 | G783: -0.10182385 | H783: -0.077000675 | I783: -0.058229026 | J783: -0.044033634 | K783: -0.033298872 | L783: -0.02518109 | M783: -0.019042305 | N783: -0.014400068 | O783: -0.01088954 | P783: -0.0082348279 | Q783: -0.0062272962 | R783: -0.0046314345 | S783: 0.69726585 | T783: 0.61161412 | U783: 0.56419599 | V783: 5.6293134 | W783: 6.0292712 | X783: 13.414452 | Y783: 14.519454 | Z783: 15.597625 | AA783: 16.529795 | AB783: 17.588712 | AC783: 29.696882 | AD783: 31.53782 | AE783: 33.445395 | AF783: 35.400354 | AG783: 37.586265 | AH783: 40.412634 | AI783: 42.729946 | AJ783: 44.434729 | AK783: 47.758471 | AL783: 49.240934 | AM783: 44.297809 | AN783: 45.020699 | AO783: 46.698209 | AP783: 48.820002 | AQ783: 50.191621 | AR783: 44.017783 | AS783: 45.552945 | AT783: 46.831425 | AU783: 48.045123 | AV783: 49.270212
A784: NEW_TRUCKS_24_16_2 | C784: 0.079219421 | D784: 0.080491315 | E784: 0.20076064 | F784: 0.22786982 | G784: 0.25863962 | H784: 0.29356433 | I784: 0.33320501 | J784: 0.37819846 | K784: 0.42926748 | L784: 0.48723248 | M784: 0.55302462 | N784: 0.62770082 | O784: 0.71246073 | P784: 0.80866597 | Q784: 0.91786203 | R784: 1.0646967 | S784: 4.3878343 | T784: 3.8067727 | U784: 3.6203296 | V784: 0.40165507 | W784: 0.25481385 | X784: 3.7480846 | Y784: 4.0562233 | Z784: 4.3052858 | AA784: 4.489403 | AB784: 4.7321529 | AC784: 5.6831949 | AD784: 5.9592793 | AE784: 6.253558 | AF784: 6.5566959 | AG784: 6.9115246 | AH784: 8.2243218 | AI784: 8.6567751 | AJ784: 8.9506993 | AK784: 9.6049483 | AL784: 9.8496711 | AM784: 9.1273135 | AN784: 9.2435785 | AO784: 9.5663888 | AP784: 9.9831091 | AQ784: 10.239747 | AR784: 8.3560051 | AS784: 8.602279 | AT784: 8.792602 | AU784: 8.9681869 | AV784: 9.1449987
A785: PNEW_TRUCKS_22_15_2 | B785: 205.41388 | C785: 209.52216 | D785: 219.23607 | E785: 223.0875 | F785: 228.0717 | G785: 233.32669 | H785: 234.72943 | I785: 237.24569 | J785: 239.73614 | K785: 243.47959 | L785: 248.57155 | M785: 253.86256 | N785: 254.41298 | O785: 258.16207 | P785: 260.9686 | Q785: 263.62048 | R785: 262.48584 | S785: 262.95786 | T785: 259.38977 | U785: 251.57682 | V785: 256.52139 | W785: 261.44625 | X785: 266.69826 | Y785: 272.02657 | Z785: 277.27339 | AA785: 282.67601 | AB785: 288.27554 | AC785: 294.14323 | AD785: 300.12453 | AE785: 306.34124 | AF785: 312.75731 | AG785: 319.34369 | AH785: 326.06253 | AI785: 332.91471 | AJ785: 340.04241 | AK785: 347.20663 | AL785: 354.60964 | AM785: 362.11507 | AN785: 369.82652 | AO785: 377.74643 | AP785: 385.78739 | AQ785: 393.93039 | AR785: 402.24766 | AS785: 410.76928 | AT785: 419.43397 | AU785: 428.2551 | AV785: 437.27731
A786: PNEW_TRUCKS_23_15_2 | B786: 378.07612 | C786: 385.63764 | D786: 479.64963 | E786: 488.07588 | F786: 498.98043 | G786: 510.47742 | H786: 513.54637 | I786: 519.0515 | J786: 524.50016 | K786: 532.69016 | L786: 543.83047 | M786: 555.40625 | N786: 537.28309 | O786: 497.27843 | P786: 479.35301 | Q786: 485.20845 | R786: 467.72976 | S786: 462.5959 | T786: 455.40393 | U786: 441.68693 | V786: 441.48467 | W786: 421.85768 | X786: 417.63785 | Y786: 414.32866 | Z786: 411.63014 | AA786: 409.84216 | AB786: 408.95819 | AC786: 409.0151 | AD786: 409.74052 | AE786: 413.53018 | AF786: 417.39524 | AG786: 421.28822 | AH786: 427.15191 | AI786: 433.06541 | AJ786: 439.20871 | AK786: 445.26766 | AL786: 451.49883 | AM786: 457.72323 | AN786: 464.06805 | AO786: 470.53062 | AP786: 476.99712 | AQ786: 483.44088 | AR786: 489.94706 | AS786: 496.54722 | AT786: 503.1622 | AU786: 509.80396 | AV786: 516.52093
A787: PNEW_TRUCKS_24_15_2 | B787: 235.67177 | C787: 240.38521 | D787: 228.64976 | E787: 232.66657 | F787: 237.86478 | G787: 243.34542 | H787: 244.80839 | I787: 247.4327 | J787: 250.03008 | K787: 253.93427 | L787: 259.24487 | M787: 264.76307 | N787: 285.92973 | O787: 289.59281 | P787: 295.75939 | Q787: 302.45237 | R787: 300.08994 | S787: 302.22106 | T787: 299.49623 | U787: 290.47525 | V787: 296.18434 | W787: 301.87067 | X787: 307.93475 | Y787: 314.0869 | Z787: 320.14499 | AA787: 326.38295 | AB787: 332.84827 | AC787: 339.62321 | AD787: 346.52934 | AE787: 353.70726 | AF787: 361.11537 | AG787: 368.72014 | AH787: 376.47783 | AI787: 384.38948 | AJ787: 392.61926 | AK787: 400.89119 | AL787: 409.43884 | AM787: 418.10475 | AN787: 427.00854 | AO787: 436.15302 | AP787: 445.43726 | AQ787: 454.83931 | AR787: 464.44258 | AS787: 474.28181 | AT787: 484.28621 | AU787: 494.47126 | AV787: 504.88847
A788: PNEW_TRUCKS_22_16_2 | B788: 69.326338 | C788: 70.712865 | D788: 72.446646 | E788: 73.719326 | F788: 75.364141 | G788: 77.098026 | H788: 77.567752 | I788: 78.403141 | J788: 79.229599 | K788: 80.468048 | L788: 82.148679 | M788: 83.896737 | N788: 86.217153 | O788: 88.441628 | P788: 89.83951 | Q788: 91.471536 | R788: 90.785431 | S788: 96.394038 | T788: 101.42422 | U788: 102.00353 | V788: 104.08622 | W788: 106.11403 | X788: 108.17701 | Y788: 112.10785 | Z788: 114.23231 | AA788: 116.43277 | AB788: 118.7104 | AC788: 121.07745 | AD788: 123.50733 | AE788: 126.03748 | AF788: 128.65231 | AG788: 131.33402 | AH788: 134.06873 | AI788: 136.85844 | AJ788: 139.76634 | AK788: 142.6735 | AL788: 145.68991 | AM788: 148.7297 | AN788: 151.87079 | AO788: 155.09458 | AP788: 158.362 | AQ788: 161.68233 | AR788: 165.0686 | AS788: 168.52903 | AT788: 172.04769 | AU788: 175.62926 | AV788: 179.28296
A789: PNEW_TRUCKS_23_16_2 | B789: 266.12455 | C789: 271.44704 | D789: 274.82504 | E789: 279.65293 | F789: 285.8925 | G789: 292.46996 | H789: 294.25186 | I789: 297.42089 | J789: 300.55605 | K789: 305.25408 | L789: 311.62953 | M789: 318.26075 | N789: 323.71602 | O789: 328.98251 | P789: 334.47855 | Q789: 341.58661 | R789: 348.50005 | S789: 343.72335 | T789: 387.31025 | U789: 396.67394 | V789: 358.38356 | W789: 337.3034 | X789: 279.5984 | Y789: 262.37549 | Z789: 249.16731 | AA789: 240.58855 | AB789: 233.30517 | AC789: 228.52406 | AD789: 225.30945 | AE789: 223.86921 | AF789: 222.23882 | AG789: 220.37039 | AH789: 223.07514 | AI789: 225.76731 | AJ789: 228.54625 | AK789: 231.21242 | AL789: 233.94078 | AM789: 239.15455 | AN789: 244.54504 | AO789: 250.08294 | AP789: 255.7057 | AQ789: 261.42862 | AR789: 267.27317 | AS789: 273.25311 | AT789: 279.34308 | AU789: 285.55105 | AV789: 291.89251
A790: PNEW_TRUCKS_24_16_2 | B790: 85.329538 | C790: 87.036129 | D790: 134.4017 | E790: 136.76276 | F790: 139.81419 | G790: 143.03086 | H790: 143.90229 | I790: 145.45209 | J790: 146.98532 | K790: 149.28286 | L790: 152.40074 | M790: 155.64371 | N790: 157.02305 | O790: 132.16775 | P790: 130.05602 | Q790: 133.88525 | R790: 111.74222 | S790: 113.93754 | T790: 116.23419 | U790: 117.43221 | V790: 118.67771 | W790: 119.81513 | X790: 120.94698 | Y790: 122.08704 | Z790: 123.15661 | AA790: 124.261 | AB790: 125.39899 | AC790: 127.89942 | AD790: 130.4662 | AE790: 133.13892 | AF790: 135.90107 | AG790: 138.73388 | AH790: 141.62267 | AI790: 144.56956 | AJ790: 147.64131 | AK790: 150.71227 | AL790: 153.89864 | AM790: 157.1097 | AN790: 160.42776 | AO790: 163.8332 | AP790: 167.28472 | AQ790: 170.79213 | AR790: 174.36919 | AS790: 178.0246 | AT790: 181.74152 | AU790: 185.52488 | AV790: 189.38445
A791: LUV_16_2 | B791: 4958.5156 | C791: 5038.1262 | D791: 5119.0149 | E791: 5155.9695 | F791: 5182.3639 | G791: 5221.0752 | H791: 5280.5116 | I791: 5295.6046 | J791: 5430.3344 | K791: 5585.3535 | L791: 5676.203 | M791: 5770.7286 | N791: 5905.8252 | O791: 6016.3431 | P791: 5930.3842 | Q791: 5856.9404 | R791: 5872.3749 | S791: 6031.3457 | T791: 6070.3537 | U791: 6183.0499 | V791: 6250.7884 | W791: 6280.3642 | X791: 6301.0075 | Y791: 6355.6716 | Z791: 6413.4007 | AA791: 6456.2343 | AB791: 6501.7848 | AC791: 6539.5134 | AD791: 6575.3067 | AE791: 6612.3552 | AF791: 6651.2409 | AG791: 6698.2407 | AH791: 6766.0694 | AI791: 6835.3905 | AJ791: 6890.1865 | AK791: 6970.0425 | AL791: 7029.5416 | AM791: 7119.9279 | AN791: 7189.1827 | AO791: 7257.8964 | AP791: 7333.3989 | AQ791: 7401.8058 | AR791: 7460.2382 | AS791: 7525.4006 | AT791: 7592.3235 | AU791: 7659.6332 | AV791: 7727.2707
A792: LUV_22_16_2 | B792: 4956.5783 | C792: 5036.1578 | D792: 5117.0149 | E792: 5151.1931 | F792: 5174.7884 | G792: 5210.6493 | H792: 5267.1428 | I792: 5279.3669 | J792: 5410.7824 | K792: 5562.261 | L792: 5649.7056 | M792: 5740.7118 | N792: 5871.1638 | O792: 5975.2452 | P792: 5883.4112 | Q792: 5802.5334 | R792: 5806.5018 | S792: 5938.525 | T792: 5956.6709 | U792: 6050.7463 | V792: 6085.1772 | W792: 6081.9605 | X792: 5963.3295 | Y792: 5875.2393 | Z792: 5787.5098 | AA792: 5684.1261 | AB792: 5581.1899 | AC792: 5316.0024 | AD792: 5045.8963 | AE792: 4773.4388 | AF792: 4498.8524 | AG792: 4225.846 | AH792: 3818.8586 | AI792: 3403.5964 | AJ792: 2972.8508 | AK792: 2543.9665 | AL792: 2098.3885 | AM792: 1815.7667 | AN792: 1520.8141 | AO792: 1219.7476 | AP792: 913.55084 | AQ792: 600.21244 | AR792: 498.88105 | AS792: 396.24245 | AT792: 291.81855 | AU792: 185.501 | AV792: 77.272707
A793: LUV_23_16_2 | B793: 0.96864644 | C793: 0.98419838 | D793: 1 | E793: 1.4103096 | F793: 1.9848265 | G793: 2.7999168 | H793: 3.9650776 | I793: 5.5677762 | J793: 7.9943529 | K793: 11.51325 | L793: 16.383086 | M793: 23.321633 | N793: 27.826681 | O793: 34.019323 | P793: 39.439141 | Q793: 46.312848 | R793: 56.733986 | S793: 83.348131 | T793: 104.07959 | U793: 122.46564 | V793: 155.66548 | W793: 188.41093 | X793: 327.65239 | Y793: 470.3197 | Z793: 615.68647 | AA793: 761.83565 | AB793: 910.24988 | AC793: 1203.2705 | AD793: 1499.1699 | AE793: 1798.5606 | AF793: 2101.7921 | AG793: 2411.3666 | AH793: 2875.566 | AI793: 3349.314 | AJ793: 3824.0122 | AK793: 4321.3706 | AL793: 4815.1657 | AM793: 5176.273 | AN793: 5528.7259 | AO793: 5886.5604 | AP793: 6255.9613 | AQ793: 6625.3564 | AR793: 6777.0296 | AS793: 6936.4628 | AT793: 7099.278 | AU793: 7264.243 | AV793: 7431.3162
A794: LUV_24_16_2 | B794: 0.96864644 | C794: 0.98419838 | D794: 1 | E794: 3.3661092 | F794: 5.5906758 | G794: 7.6260333 | H794: 9.4037116 | I794: 10.66993 | J794: 11.557638 | K794: 11.579277 | L794: 10.114331 | M794: 6.6951147 | N794: 6.8346567 | O794: 7.0785578 | P794: 7.533841 | Q794: 8.0941082 | R794: 9.1391078 | S794: 9.4726001 | T794: 9.6031802 | U794: 9.8379455 | V794: 9.9457253 | W794: 9.9927837 | X794: 10.02563 | Y794: 10.112606 | Z794: 10.20446 | AA794: 10.272613 | AB794: 10.34509 | AC794: 20.240462 | AD794: 30.240421 | AE794: 40.355705 | AF794: 50.596407 | AG794: 61.028003 | AH794: 71.644824 | AI794: 82.480127 | AJ794: 93.323579 | AK794: 104.70544 | AL794: 115.98744 | AM794: 127.88814 | AN794: 139.64269 | AO794: 151.58842 | AP794: 163.8868 | AQ794: 176.237 | AR794: 184.32756 | AS794: 192.69541 | AT794: 201.22694 | AU794: 209.88927 | AV794: 218.68176
A795: PNEW_LUV_22_16_2 | B795: 19.033911 | C795: 19.414589 | D795: 16.725575 | E795: 17.019396 | F795: 17.39913 | G795: 17.799428 | H795: 17.907872 | I795: 18.100736 | J795: 18.291539 | K795: 18.577456 | L795: 18.965459 | M795: 19.369029 | N795: 19.701032 | O795: 20.021545 | P795: 20.356028 | Q795: 21.830963 | R795: 24.925618 | S795: 25.415313 | T795: 25.927612 | U795: 26.446721 | V795: 26.986704 | W795: 27.51246 | X795: 28.047334 | Y795: 28.594829 | Z795: 29.136707 | AA795: 29.697967 | AB795: 30.27891 | AC795: 30.882665 | AD795: 31.502442 | AE795: 32.147797 | AF795: 32.814747 | AG795: 33.498761 | AH795: 34.196289 | AI795: 34.907848 | AJ795: 35.649552 | AK795: 36.391069 | AL795: 37.160451 | AM795: 37.935795 | AN795: 38.736978 | AO795: 39.559256 | AP795: 40.392661 | AQ795: 41.239562 | AR795: 42.103282 | AS795: 42.985918 | AT795: 43.883408 | AU795: 44.79694 | AV795: 45.728875
A796: PNEW_LUV_23_16_2 | B796: 23.218583 | C796: 23.682954 | D796: 30.312868 | E796: 30.845378 | F796: 31.533596 | G796: 32.259082 | H796: 32.455623 | I796: 32.805164 | J796: 33.150967 | K796: 33.669155 | L796: 34.372358 | M796: 35.103775 | N796: 32.774547 | O796: 36.841792 | P796: 36.646354 | Q796: 38.900359 | R796: 30.405602 | S796: 31.171625 | T796: 32.855534 | U796: 33.542948 | V796: 33.416422 | W796: 33.238253 | X796: 33.285588 | Y796: 33.786874 | Z796: 34.236997 | AA796: 34.663076 | AB796: 35.062759 | AC796: 35.259743 | AD796: 35.455127 | AE796: 35.890373 | AF796: 36.337846 | AG796: 36.791983 | AH796: 37.45675 | AI796: 38.132711 | AJ796: 38.837296 | AK796: 39.53728 | AL796: 40.263062 | AM796: 41.103141 | AN796: 41.971217 | AO796: 42.862149 | AP796: 43.765137 | AQ796: 44.682748 | AR796: 45.618582 | AS796: 46.574911 | AT796: 47.547334 | AU796: 48.537139 | AV796: 49.546883
A797: PNEW_LUV_24_16_2 | B797: 21.001877 | C797: 21.421914 | D797: 18.424008 | E797: 18.747665 | F797: 19.16596 | G797: 19.606907 | H797: 19.726364 | I797: 19.938813 | J797: 20.148991 | K797: 20.463942 | L797: 20.891346 | M797: 21.335897 | N797: 21.701613 | O797: 22.054673 | P797: 22.391631 | Q797: 24.014059 | R797: 27.502743 | S797: 28.043069 | T797: 28.608336 | U797: 29.181116 | V797: 29.77693 | W797: 30.357045 | X797: 30.947221 | Y797: 31.551323 | Z797: 32.149227 | AA797: 32.768517 | AB797: 33.409526 | AC797: 34.075705 | AD797: 34.759562 | AE797: 35.471642 | AF797: 36.20755 | AG797: 36.962286 | AH797: 37.731933 | AI797: 38.517061 | AJ797: 39.335453 | AK797: 40.153637 | AL797: 41.002567 | AM797: 41.858076 | AN797: 42.742095 | AO797: 43.649391 | AP797: 44.568964 | AQ797: 45.503429 | AR797: 46.456451 | AS797: 47.430345 | AT797: 48.420628 | AU797: 49.428613 | AV797: 50.456903
A798: NEW_LUV_22_16_2 | C798: 405.36696 | D798: 411.87526 | E798: 370.51086 | F798: 362.17451 | G798: 375.99094 | H798: 398.98066 | I798: 358.42447 | J798: 478.41932 | K798: 507.1202 | L798: 453.04258 | M798: 462.35179 | N798: 507.77927 | O798: 489.98301 | P798: 300.90878 | Q798: 305.82881 | R798: 385.35906 | S798: 513.67472 | T798: 408.47515 | U798: 485.59728 | V798: 432.1362 | W798: 396.75164 | X798: 281.12594 | Y798: 303.86933 | Z798: 298.44003 | AA798: 277.0195 | AB798: 270.6718 | AC798: 101.65472 | AD798: 79.305729 | AE798: 59.200721 | AF798: 39.163551 | AG798: 22.695627 | AH798: -129.22973 | AI798: -164.25513 | AJ798: -207.03301 | AK798: -233.48385 | AL798: -278.36739 | AM798: -144.69823 | AN798: -175.60536 | AO798: -201.106 | AP798: -226.02478 | AQ798: -253.29225 | AR798: -61.880443 | AS798: -69.847996 | AT798: -78.379554 | AU798: -87.136811 | AV798: -96.035625
...

Sheet Prix
C1: 2004 | D1: 2005 | E1: 2006 | F1: 2007 | G1: 2008 | H1: 2009 | I1: 2010 | J1: 2011 | K1: 2012 | L1: 2013 | M1: 2014 | N1: 2015 | O1: 2016 | P1: 2017 | Q1: 2018 | R1: 2019 | S1: 2020 | T1: 2021 | U1: 2022 | V1: 2023 | W1: 2024 | X1: 2025 | Y1: 2026 | Z1: 2027 | AA1: 2028 | AB1: 2029 | AC1: 2030 | AD1: 2031 | AE1: 2032 | AF1: 2033 | AG1: 2034 | AH1: 2035 | AI1: 2036 | AJ1: 2037 | AK1: 2038 | AL1: 2039 | AM1: 2040 | AN1: 2041 | AO1: 2042 | AP1: 2043 | AQ1: 2044 | AR1: 2045 | AS1: 2046 | AT1: 2047 | AU1: 2048 | AV1: 2049 | AW1: 2050 | AX1: commentaire
A2: ratios de prix AMS/AME
B3: PY_01_2 | C3: ='Variables AMS'!B213/'Variables AME'!B213-1 -> 0 | D3: ='Variables AMS'!C213/'Variables AME'!C213-1 -> 0 | E3: ='Variables AMS'!D213/'Variables AME'!D213-1 -> 0 | F3: ='Variables AMS'!E213/'Variables AME'!E213-1 -> 0 | G3: ='Variables AMS'!F213/'Variables AME'!F213-1 -> 0 | H3: ='Variables AMS'!G213/'Variables AME'!G213-1 -> 0 | I3: ='Variables AMS'!H213/'Variables AME'!H213-1 -> 0 | J3: ='Variables AMS'!I213/'Variables AME'!I213-1 -> 0 | ... AW3: ='Variables AMS'!AV213/'Variables AME'!AV213-1 -> 0.041372726
B4: PY_02_2 | C4: ='Variables AMS'!B214/'Variables AME'!B214-1 -> 0 | D4: ='Variables AMS'!C214/'Variables AME'!C214-1 -> 0 | E4: ='Variables AMS'!D214/'Variables AME'!D214-1 -> 0 | F4: ='Variables AMS'!E214/'Variables AME'!E214-1 -> 0 | G4: ='Variables AMS'!F214/'Variables AME'!F214-1 -> 0 | H4: ='Variables AMS'!G214/'Variables AME'!G214-1 -> 0 | I4: ='Variables AMS'!H214/'Variables AME'!H214-1 -> 0 | J4: ='Variables AMS'!I214/'Variables AME'!I214-1 -> 0 | ... AW4: ='Variables AMS'!AV214/'Variables AME'!AV214-1 -> 0.033376633
B5: PY_03_2 | C5: ='Variables AMS'!B215/'Variables AME'!B215-1 -> 0 | D5: ='Variables AMS'!C215/'Variables AME'!C215-1 -> 0 | E5: ='Variables AMS'!D215/'Variables AME'!D215-1 -> 0 | F5: ='Variables AMS'!E215/'Variables AME'!E215-1 -> 0 | G5: ='Variables AMS'!F215/'Variables AME'!F215-1 -> 0 | H5: ='Variables AMS'!G215/'Variables AME'!G215-1 -> 0 | I5: ='Variables AMS'!H215/'Variables AME'!H215-1 -> 0 | J5: ='Variables AMS'!I215/'Variables AME'!I215-1 -> 0 | ... AW5: ='Variables AMS'!AV215/'Variables AME'!AV215-1 -> 0.020822148
B6: PY_04_2 | C6: ='Variables AMS'!B216/'Variables AME'!B216-1 -> 0 | D6: ='Variables AMS'!C216/'Variables AME'!C216-1 -> 0 | E6: ='Variables AMS'!D216/'Variables AME'!D216-1 -> 0 | F6: ='Variables AMS'!E216/'Variables AME'!E216-1 -> 0 | G6: ='Variables AMS'!F216/'Variables AME'!F216-1 -> 0 | H6: ='Variables AMS'!G216/'Variables AME'!G216-1 -> 0 | I6: ='Variables AMS'!H216/'Variables AME'!H216-1 -> 0 | J6: ='Variables AMS'!I216/'Variables AME'!I216-1 -> 0 | ... AW6: ='Variables AMS'!AV216/'Variables AME'!AV216-1 -> 0.014601721
B7: PY_05_2 | C7: ='Variables AMS'!B217/'Variables AME'!B217-1 -> 0 | D7: ='Variables AMS'!C217/'Variables AME'!C217-1 -> 0 | E7: ='Variables AMS'!D217/'Variables AME'!D217-1 -> 0 | F7: ='Variables AMS'!E217/'Variables AME'!E217-1 -> 0 | G7: ='Variables AMS'!F217/'Variables AME'!F217-1 -> 0 | H7: ='Variables AMS'!G217/'Variables AME'!G217-1 -> 0 | I7: ='Variables AMS'!H217/'Variables AME'!H217-1 -> 0 | J7: ='Variables AMS'!I217/'Variables AME'!I217-1 -> 0 | ... AW7: ='Variables AMS'!AV217/'Variables AME'!AV217-1 -> 0.0024841167
B8: PY_06_2 | C8: ='Variables AMS'!B218/'Variables AME'!B218-1 -> 0 | D8: ='Variables AMS'!C218/'Variables AME'!C218-1 -> 0 | E8: ='Variables AMS'!D218/'Variables AME'!D218-1 -> 0 | F8: ='Variables AMS'!E218/'Variables AME'!E218-1 -> 0 | G8: ='Variables AMS'!F218/'Variables AME'!F218-1 -> 0 | H8: ='Variables AMS'!G218/'Variables AME'!G218-1 -> 0 | I8: ='Variables AMS'!H218/'Variables AME'!H218-1 -> 0 | J8: ='Variables AMS'!I218/'Variables AME'!I218-1 -> 0 | ... AW8: ='Variables AMS'!AV218/'Variables AME'!AV218-1 -> 0.018633367
B9: PY_07_2 | C9: ='Variables AMS'!B219/'Variables AME'!B219-1 -> 0 | D9: ='Variables AMS'!C219/'Variables AME'!C219-1 -> 0 | E9: ='Variables AMS'!D219/'Variables AME'!D219-1 -> 0 | F9: ='Variables AMS'!E219/'Variables AME'!E219-1 -> 0 | G9: ='Variables AMS'!F219/'Variables AME'!F219-1 -> 0 | H9: ='Variables AMS'!G219/'Variables AME'!G219-1 -> 0 | I9: ='Variables AMS'!H219/'Variables AME'!H219-1 -> 0 | J9: ='Variables AMS'!I219/'Variables AME'!I219-1 -> 0 | ... AW9: ='Variables AMS'!AV219/'Variables AME'!AV219-1 -> -0.021742341
B10: PY_08_2 | C10: ='Variables AMS'!B220/'Variables AME'!B220-1 -> 0 | D10: ='Variables AMS'!C220/'Variables AME'!C220-1 -> 0 | E10: ='Variables AMS'!D220/'Variables AME'!D220-1 -> 0 | F10: ='Variables AMS'!E220/'Variables AME'!E220-1 -> 0 | G10: ='Variables AMS'!F220/'Variables AME'!F220-1 -> 0 | H10: ='Variables AMS'!G220/'Variables AME'!G220-1 -> 0 | I10: ='Variables AMS'!H220/'Variables AME'!H220-1 -> 0 | J10: ='Variables AMS'!I220/'Variables AME'!I220-1 -> 0 | ... AW10: ='Variables AMS'!AV220/'Variables AME'!AV220-1 -> 0.038892969
B11: PY_09_2 | C11: ='Variables AMS'!B221/'Variables AME'!B221-1 -> 0 | D11: ='Variables AMS'!C221/'Variables AME'!C221-1 -> 0 | E11: ='Variables AMS'!D221/'Variables AME'!D221-1 -> 0 | F11: ='Variables AMS'!E221/'Variables AME'!E221-1 -> 0 | G11: ='Variables AMS'!F221/'Variables AME'!F221-1 -> 0 | H11: ='Variables AMS'!G221/'Variables AME'!G221-1 -> 0 | I11: ='Variables AMS'!H221/'Variables AME'!H221-1 -> 0 | J11: ='Variables AMS'!I221/'Variables AME'!I221-1 -> 0 | ... AW11: ='Variables AMS'!AV221/'Variables AME'!AV221-1 -> 0.032263855
B12: PY_10_2 | C12: ='Variables AMS'!B222/'Variables AME'!B222-1 -> 0 | D12: ='Variables AMS'!C222/'Variables AME'!C222-1 -> 0 | E12: ='Variables AMS'!D222/'Variables AME'!D222-1 -> 0 | F12: ='Variables AMS'!E222/'Variables AME'!E222-1 -> 0 | G12: ='Variables AMS'!F222/'Variables AME'!F222-1 -> 0 | H12: ='Variables AMS'!G222/'Variables AME'!G222-1 -> 0 | I12: ='Variables AMS'!H222/'Variables AME'!H222-1 -> 0 | J12: ='Variables AMS'!I222/'Variables AME'!I222-1 -> 0 | ... AW12: ='Variables AMS'!AV222/'Variables AME'!AV222-1 -> 0.015069998
B13: PY_11_2 | C13: ='Variables AMS'!B223/'Variables AME'!B223-1 -> 0 | D13: ='Variables AMS'!C223/'Variables AME'!C223-1 -> 0 | E13: ='Variables AMS'!D223/'Variables AME'!D223-1 -> 0 | F13: ='Variables AMS'!E223/'Variables AME'!E223-1 -> 0 | G13: ='Variables AMS'!F223/'Variables AME'!F223-1 -> 0 | H13: ='Variables AMS'!G223/'Variables AME'!G223-1 -> 0 | I13: ='Variables AMS'!H223/'Variables AME'!H223-1 -> 0 | J13: ='Variables AMS'!I223/'Variables AME'!I223-1 -> 0 | ... AW13: ='Variables AMS'!AV223/'Variables AME'!AV223-1 -> 0.030433302
B14: PY_12_2 | C14: ='Variables AMS'!B224/'Variables AME'!B224-1 -> 0 | D14: ='Variables AMS'!C224/'Variables AME'!C224-1 -> 0 | E14: ='Variables AMS'!D224/'Variables AME'!D224-1 -> 0 | F14: ='Variables AMS'!E224/'Variables AME'!E224-1 -> 0 | G14: ='Variables AMS'!F224/'Variables AME'!F224-1 -> 0 | H14: ='Variables AMS'!G224/'Variables AME'!G224-1 -> 0 | I14: ='Variables AMS'!H224/'Variables AME'!H224-1 -> 0 | J14: ='Variables AMS'!I224/'Variables AME'!I224-1 -> 0 | ... AW14: ='Variables AMS'!AV224/'Variables AME'!AV224-1 -> 0.033278066
... B39: PY_2406_2 | C39: ='Variables AMS'!B249/'Variables AME'!B249-1 -> 0 | D39: ='Variables AMS'!C249/'Variables AME'!C249-1 -> 0 | E39: ='Variables AMS'!D249/'Variables AME'!D249-1 -> 0 | F39: ='Variables AMS'!E249/'Variables AME'!E249-1 -> 0 | G39: ='Variables AMS'!F249/'Variables AME'!F249-1 -> 0 | H39: ='Variables AMS'!G249/'Variables AME'!G249-1 -> 0 | I39: ='Variables AMS'!H249/'Variables AME'!H249-1 -> 0 | J39: ='Variables AMS'!I249/'Variables AME'!I249-1 -> 0 | ... AW39: ='Variables AMS'!AV249/'Variables AME'!AV249-1 -> -0.029464787

Sheet Graphes comparatifs
B1: Transports | C1: 2021 | D1: 2030 | E1: 2030 AMS - 2021 constaté | F1: 2030 AMS - 2021 projeté
B2: VP électriques
A3: 2022 | B3: Historique I4CE | C3: 12.278311
A4: 2022 | B4: AMS I4CE run 2 | C4: 13.649158 | D4: 44.796895 | E4: =D4-C3 -> 32.518584
A5: 2021 | B5: AMS ThreeME | C5: =SUMIFS('Transport AMS'!$C$8:$AW$8,'Transport AMS'!$C$1:$AW$1,'Graphes comparatifs'!C1)/1000 -> 6.3819857 | D5: =SUMIFS('Transport AMS'!$C$8:$AW$8,'Transport AMS'!$C$1:$AW$1,'Graphes comparatifs'!D1)/1000 -> 39.765491 | E5: =D5-C3 -> 27.487179 | F5: =D5-C5 -> 33.383505
A6: 2022 | B6: AMS ThreeME | C6: =C5*$D$148/$C$148 -> 6.6554305 | D6: =D5*$D$148/$C$148 -> 41.469297 | E6: =E5*$D$148/$C$148 -> 28.664905 | F6: =F5*$D$148/$C$148 -> 34.813867
B7: AMS JPF-SM | D7: 40.025051 | E7: =D7-C3 -> 27.746739
B8: AMS Tresor | D8: 38.44125 | E8: =D8-C3 -> 26.162939
A9: 2022 | B9: AME I4CE run 2 | C9: 13.557894 | D9: 40.993024
A10: 2021 | B10: AME ThreeME | C10: =SUMIFS('Transport AME'!$C$8:$AW$8,'Transport AME'!$C$1:$AW$1,'Graphes comparatifs'!C1)/1000 -> 6.3819857 | D10: =SUMIFS('Transport AME'!$C$8:$AW$8,'Transport AME'!$C$1:$AW$1,'Graphes comparatifs'!D1)/1000 -> 28.256305
A11: 2022 | B11: AME ThreeME | C11: =C10*$D$148/$C$148 -> 6.6554305 | D11: =D10*$D$148/$C$148 -> 29.466985
B12: AME JPF-SM
B13: AME Tresor
B14: VP fossiles
A15: 2022 | B15: Historique I4CE | C15: 38.258636
A16: 2022 | B16: AMS I4CE run 2 | C16: 40.313332 | D16: 15.405819 | E16: =D16-C15 -> -22.852817
A17: 2021 | B17: AMS ThreeME | C17: =SUMIFS('Transport AMS'!$C$21:$AW$21,'Transport AMS'!$C$1:$AW$1,'Graphes comparatifs'!C1)/1000 -> 42.573469 | D17: =SUMIFS('Transport AMS'!$C$21:$AW$21,'Transport AMS'!$C$1:$AW$1,'Graphes comparatifs'!D1)/1000 -> 13.939356 | E17: =D17-C15 -> -24.31928
A18: 2022 | B18: AMS ThreeME | C18: =C17*$D$148/$C$148 -> 44.397587 | D18: =D17*$D$148/$C$148 -> 14.536606 | E18: =E17*$D$148/$C$148 -> -25.361273
B19: AMS JPF-SM | D19: 15.003995 | E19: =D19-C15 -> -23.254641
B20: AMS Tresor | D20: 16.438794 | E20: =D20-C15 -> -21.819842
A21: 2022 | B21: AME I4CE run 2 | C21: 41.942053 | D21: 34.508863
A22: 2021 | B22: AME ThreeME | C22: =SUMIFS('Transport AME'!$C$21:$AW$21,'Transport AME'!$C$1:$AW$1,'Graphes comparatifs'!C1)/1000 -> 42.573469 | D22: =SUMIFS('Transport AME'!$C$21:$AW$21,'Transport AME'!$C$1:$AW$1,'Graphes comparatifs'!D1)/1000 -> 36.342214
A23: 2022 | B23: AME ThreeME | C23: =C22*$D$148/$C$148 -> 44.397587 | D23: =D22*$D$148/$C$148 -> 37.899345
B24: AME JPF-SM
B25: AME Tresor
B26: Tresor AME
A27: 2022 | B27: I4CE constaté | C27: 0.99276703
A28: 2022 | B28: I4CE run 2 | D28: 11.245443 | E28: =D28-C27 -> 10.252676
B29: JPF-SM | D29: 12.794607 | E29: =D29-C27 -> 11.80184
B30: Tresor | D30: 8.4760842 | E30: =D30-C27 -> 7.4833172
A31: 2021 | B31: ThreeME | C31: 0 | D31: 0.47661165 | E31: =D31/1000-C27 -> -0.99229042 | F31: =(D31-C31)/1000 -> 0.00047661165
A32: 2022 | B32: ThreeME AMS | C32: =C31*$D$148/$C$148 -> 0 | D32: =D31*$D$148/$C$148 -> 0.49703272 | E32: =E31*$D$148/$C$148 -> -1.0348064 | F32: =F31*$D$148/$C$148 -> 0.00049703272
B33: VUL PL
A34: 2022 | B34: Historique I4CE | C34: 0.99276703
A35: 2022 | B35: AMS I4CE run 2 | D35: 11.245443
A36: 2021 | B36: AMS ThreeME | C36: =SUMIFS('Transp lourd AMS'!$C$11:$AW$11,'Transp lourd AMS'!$C$1:$AW$1,'Graphes comparatifs'!C1)/1000 -> 1.626491 | D36: =SUMIFS('Transp lourd AMS'!$C$11:$AW$11,'Transp lourd AMS'!$C$1:$AW$1,'Graphes comparatifs'!D1)/1000 -> 9.3172943 | E36: =D36-C36 -> 7.6908033
A37: 2022 | B37: AMS ThreeME | C37: =C36*$D$148/$C$148 -> 1.6961802 | D37: =D36*$D$148/$C$148 -> 9.7165064 | E37: =E36*$D$148/$C$148 -> 8.0203262 | F37: =F36*$D$148/$C$148 -> 0
B38: AMS JPF-SM | D38: 12.794607 | E38: =D38-C34 -> 11.80184
B39: AMS Tresor | D39: 8.4760842 | E39: =D39-C34 -> 7.4833172
A40: 2022 | B40: AME I4CE run 2 | C40: 0.24487205 | D40: 7.0051598
A41: 2021 | B41: AME ThreeME | C41: =SUMIFS('Transp lourd AME'!$C$11:$AW$11,'Transp lourd AME'!$C$1:$AW$1,'Graphes comparatifs'!C1)/1000 -> 1.626491 | D41: =SUMIFS('Transp lourd AME'!$C$11:$AW$11,'Transp lourd AME'!$C$1:$AW$1,'Graphes comparatifs'!D1)/1000 -> 5.5181632
A42: 2022 | B42: AME ThreeME | C42: =C41*$D$148/$C$148 -> 1.6961802 | D42: =D41*$D$148/$C$148 -> 5.7545964
B43: AME JPF-SM
B44: AME Tresor
B45: Ferroviaire
A46: 2022 | B46: Historique I4CE | C46: 9.6
A47: 2022 | B47: AMS I4CE run 2 | C47: 0 | D47: 13.003 | E47: =D47-C46 -> 3.403
A48: 2021 | B48: AMS ThreeME | C48: =SUMIFS('Transp lourd AMS'!$C$23:$AW$23,'Transp lourd AMS'!$C$1:$AW$1,'Graphes comparatifs'!C1)/1000 -> 15.311591 | D48: =SUMIFS('Transp lourd AMS'!$C$23:$AW$23,'Transp lourd AMS'!$C$1:$AW$1,'Graphes comparatifs'!D1)/1000 -> 12.838595 | E48: =D48-C48 -> -2.4729962
A49: 2022 | B49: AMS ThreeME | C49: =C48*$D$148/$C$148 -> 15.967637 | D49: =D48*$D$148/$C$148 -> 13.388682 | E49: =E48*$D$148/$C$148 -> -2.5789551 | F49: =F48*$D$148/$C$148 -> 0
A50: 2022 | B50: AME I4CE run 2 | C50: 0 | D50: 6.9630487
A51: 2021 | B51: AME ThreeME | C51: =SUMIFS('Transp lourd AME'!$C$23:$AW$23,'Transp lourd AME'!$C$1:$AW$1,'Graphes comparatifs'!C1)/1000 -> 15.311591 | D51: =SUMIFS('Transp lourd AME'!$C$23:$AW$23,'Transp lourd AME'!$C$1:$AW$1,'Graphes comparatifs'!D1)/1000 -> 11.298273
A52: 2022 | B52: AME ThreeME | C52: =C51*$D$148/$C$148 -> 15.967637 | D52: =D51*$D$148/$C$148 -> 11.782363
B54: Bâtiments | C54: 2021 | D54: 2030 AMS | E54: 2030 AMS - 2021 constaté | F54: 2030 AMS - 2021 projeté
B55: Résidentiel
A56: 2022 | B56: Historique I4CE | C56: 15.194628
A57: 2022 | B57: AMS I4CE run 2 | C57: 0 | D57: 31.21898 | E57: =D57-$C$56 -> 16.024352
A58: 2021 | B58: AMS ThreeME | C58: =SUMIFS('Résidentiel AMS'!$C$23:$AW$23,'Résidentiel AMS'!$C$1:$AW$1,'Graphes comparatifs'!C1)/1000 -> 15.518483 | D58: =SUMIFS('Résidentiel AMS'!$C$23:$AW$23,'Résidentiel AMS'!$C$1:$AW$1,'Graphes comparatifs'!D1)/1000 -> 22.720871 | E58: =D58-$C$56 -> 7.5262431 | F58: =(D58-C58) -> 7.2023885
A59: 2022 | B59: AMS ThreeME | C59: =C58*$D$148/$C$148 -> 16.183393 | D59: =D58*$D$148/$C$148 -> 23.694377 | E59: =E58*$D$148/$C$148 -> 7.8487152 | F59: =F58*$D$148/$C$148 -> 7.5109846
B60: AMS JPF-SM | D60: 26.6 | E60: =D60-$C$56 -> 11.405372
B61: AMS Tresor | D61: 36.564897 | E61: =D61-$C$56 -> 21.370269
A62: 2022 | B62: AME I4CE run 2 | C62: 0 | D62: 19.491121
A63: 2021 | B63: AME ThreeME | C63: =SUMIFS('Résidentiel AME'!$C$23:$AW$23,'Résidentiel AME'!$C$1:$AW$1,'Graphes comparatifs'!C1)/1000 -> 15.518483 | D63: =SUMIFS('Résidentiel AME'!$C$23:$AW$23,'Résidentiel AME'!$C$1:$AW$1,'Graphes comparatifs'!D1)/1000 -> 8.0676743
A64: 2022 | B64: AME ThreeME | C64: =C63*$D$148/$C$148 -> 16.183393 | D64: =D63*$D$148/$C$148 -> 8.4133447
B65: AME JPF-SM
B66: AME Tresor
B67: Tertiaire
B68: Historique I4CE | C68: 5.3661345 | W68: =8*3*6 -> 144
B69: AMS I4CE run 2 | D69: 22.25802 | E69: =D69-$C$68 -> 16.891885
A70: 2021 | B70: AMS ThreeME* | C70: =SUMIFS('Tertiaire AMS'!$C$14:$AW$14,'Tertiaire AMS'!$C$1:$AW$1,'Graphes comparatifs'!C1)/1000 -> 5.8268558 | D70: =SUMIFS('Tertiaire AMS'!$C$14:$AW$14,'Tertiaire AMS'!$C$1:$AW$1,'Graphes comparatifs'!D1)/1000 -> 22.262077 | E70: =D70-$C$68 -> 16.895943 | F70: =(D70-C70) -> 16.435221
A71: 2022 | B71: AMS ThreeME* | C71: =C70*$D$148/$C$148 -> 6.0765153 | D71: =D70*$D$148/$C$148 -> 23.215926 | E71: =E70*$D$148/$C$148 -> 17.619872 | F71: =F70*$D$148/$C$148 -> 17.139411
B72: AMS JPF-SM | D72: 27.167401 | E72: =D72-$C$68 -> 21.801267
A73: 2022 | B73: AME I4CE run 2 | C73: 0 | D73: 16.52
A74: 2021 | B74: AME ThreeME* | C74: =SUMIFS('Tertiaire AME'!$C$14:$AW$14,'Tertiaire AME'!$C$1:$AW$1,'Graphes comparatifs'!C1)/1000 -> 5.8268558 | D74: =SUMIFS('Tertiaire AME'!$C$14:$AW$14,'Tertiaire AME'!$C$1:$AW$1,'Graphes comparatifs'!D1)/1000 -> 6.2837161
A75: 2022 | B75: AME ThreeME* | C75: =C74*$D$148/$C$148 -> 6.0765153 | D75: =D74*$D$148/$C$148 -> 6.5529504
B76: AME JPF-SM
B77: Construction
B78: Historique I4CE | C78: 77.458135
A79: 2022 | B79: AMS I4CE run 2 | C79: 93.676125 | D79: 36.461162 | E79: =D79-$C$78 -> -40.996973
A80: 2021 | B80: AMS ThreeME* | C80: =SUMIFS('Résidentiel AMS'!$C$33:$AW$33,'Résidentiel AMS'!$C$1:$AW$1,'Graphes comparatifs'!C1)/1000 -> 57.386134 | D80: =SUMIFS('Résidentiel AMS'!$C$33:$AW$33,'Résidentiel AMS'!$C$1:$AW$1,'Graphes comparatifs'!D1)/1000 -> 33.194823 | E80: =D80-$C$78 -> -44.263312 | F80: =(D80-C80) -> -24.19131
A81: 2022 | B81: AMS ThreeME* | C81: =C80*$D$148/$C$148 -> 59.84492 | D81: =D80*$D$148/$C$148 -> 34.6171 | E81: =E80*$D$148/$C$148 -> -46.159833 | F81: =F80*$D$148/$C$148 -> -25.22782
A82: 2022 | B82: AME I4CE run 2 | C82: 94.479248 | D82: 75.709336
A83: 2021 | B83: AME ThreeME* | C83: =SUMIFS('Résidentiel AME'!$C$33:$AW$33,'Résidentiel AME'!$C$1:$AW$1,'Graphes comparatifs'!C1)/1000 -> 57.386134 | D83: =SUMIFS('Résidentiel AME'!$C$33:$AW$33,'Résidentiel AME'!$C$1:$AW$1,'Graphes comparatifs'!D1)/1000 -> 50.887319
A84: 2022 | B84: AME ThreeME* | C84: =C83*$D$148/$C$148 -> 59.84492 | D84: =D83*$D$148/$C$148 -> 53.067655
B86: Energie | C86: 2021 | D86: 2030 AMS | E86: 2030 AMS - 2021 constaté | F86: 2030 AMS - 2021 projeté
B87: Energie
B88: Historique I4CE | C88: 18.410935
B89: AMS I4CE run 2 | D89: 30.079508 | E89: =D89-$C$56 -> 14.88488
A90: 2021 | B90: AMS ThreeME* | C90: =SUM(C105:F105) -> 21.301653 | D90: =SUM(G105:J105) -> 16.894656 | E90: =D90-$C$88 -> -1.5162791 | F90: =(D90-C90)/1000 -> -0.004406997
A91: 2022 | B91: AMS ThreeME* | C91: =C90*$D$148/$C$148 -> 22.214351 | D91: =D90*$D$148/$C$148 -> 17.618531 | E91: =E90*$D$148/$C$148 -> -1.5812461 | F91: =F90*$D$148/$C$148 -> -0.0045958208
B92: AMS JPF-SM* | D92: =E92+$C$88 -> 27.410935 | E92: 9
B93: AMS Tresor* | D93: =E93+$C$88 -> 35.410935 | E93: 17
B94: AME I4CE run 2
A95: 2021 | B95: AME ThreeME* | C95: =SUM(C114:F114) -> 21.301653 | D95: =SUM(G114:J114) -> 15.26953
A96: 2022 | B96: AME ThreeME* | C96: =C95*$D$148/$C$148 -> 22.214351 | D96: =D95*$D$148/$C$148 -> 15.923774
B97: AME JPF-SM
B98: AME Tresor
B99: Energie par poste | C99: 2021 | G99: 2030
C100: EnR électriques | D100: Nucléaire électrique | E100: Biométhane, chaleur renouvelable, biocarbs | F100: Réseaux élec & flexibilités | G100: EnR électriques | H100: Nucléaire électrique | I100: Biométhane, chaleur renouvelable, biocarbs | J100: Réseaux élec & flexibilités
B101: Historique I4CE | C101: 6.1086707 | D101: 4.7182475 | E101: 1.4525001 | F101: 6.1315171
A102: 2022 | B102: AMS I4CE run 2 | G102: 10.394188 | H102: 5.7688343 | I102: 2.8771234 | J102: 11.039362
...

Sheet T surcroît d'I AMS
